Workbook
Name company: CaseData!$J$3
Name lstCountries: CaseData!$D$10:$D$17
Name lstCurrencies: CaseData!$B$47:$B$52
Name lstStoreCurrencies: CaseData!$E$10:$E$17
Name lstStores: CaseData!$C$10:$C$17
Name periods: CaseData!$J$5
Name start_date: CaseData!$J$4
Name topic: "CFM Topic: " & CaseData!$J$6

Sheet Cover
E15: =company -> Fashion Boutique
E16: {=topic} -> CFM Topic: Revenue

Sheet Notes
A1: =company -> Fashion Boutique
A2: {=topic} -> CFM Topic: Revenue
A3: NOTES
A5: GENERAL NOTES
E7: - keeping arrays of similar size throughout the model pays off
E8: - need more practice with da formulas for Time sheet
A10: COMPOUNDED INFLATION
E12: • bug in original Price!J8: IF(rate="n.a.",1, 1*(1+rate)) only applies the current year's rate once, so each year resets to 1 instead of compounding
E13: • correct logic (per CaseSolution): inflation index = product of (1 + rate) for every year from start through the current year
E14: • key insight: the column axis is SEQUENTIAL (year j depends on year j-1), not independent — so BYROW / BYCOL / MAP don't work, because they require scalar returns and treat elements in isolation
E15: • SCAN is the right primitive: SCAN(1, rates_row, LAMBDA(s,c, s*(1+c))) carries the accumulator forward along one dimension
E16: • to spill the full grid (currencies × years), wrap SCAN in MAKEARRAY: each (i,j) call re-runs SCAN over row i and picks element j
E17: • MAKEARRAY(rows, cols, LAMBDA(i,j, ...)): Excel calls the LAMBDA once per output cell, passing in row index i and column index j
E18: • final formula in CaseData!I86 spills 6×5 grid; lookup against currency/year happens at the consumer (e.g. Price!J8), not inside the grid formula
A21: PRICE FORMULA
E23: - unified operating flag. Very useful.
E26: - calculation of the unit price at each store
E35: - calculation of the discount, XLOOKUP
E41: - calculation of the compounded inflation
E43: - this is the most important formula

Sheet Revenue
A1: =company -> Fashion Boutique
A2: {=topic} -> CFM Topic: Revenue | J2: {=EDATE( start_date, _xlfn.SEQUENCE( 1, periods, 0, 1 ) )} -> 44562 | K2: 44593 | L2: 44621 | M2: 44652 | N2: 44682 | O2: 44713 | P2: 44743 | Q2: 44774 | R2: 44805 | S2: 44835 | T2: 44866 | U2: 44896 | V2: 44927 | W2: 44958 | X2: 44986 | Y2: 45017 | Z2: 45047 | AA2: 45078 | AB2: 45108 | AC2: 45139 | AD2: 45170 | AE2: 45200 | AF2: 45231 | AG2: 45261 | AH2: 45292 | AI2: 45323 | AJ2: 45352 | AK2: 45383 | AL2: 45413 | AM2: 45444 | AN2: 45474 | AO2: 45505 | AP2: 45536 | AQ2: 45566 | AR2: 45597 | AS2: 45627 | AT2: 45658 | AU2: 45689 | AV2: 45717 | AW2: 45748 | AX2: 45778 | AY2: 45809 | AZ2: 45839 | BA2: 45870 | BB2: 45901 | BC2: 45931 | BD2: 45962 | BE2: 45992 | BF2: 46023 | BG2: 46054 | BH2: 46082 | BI2: 46113 | BJ2: 46143 | BK2: 46174 | BL2: 46204 | BM2: 46235 | BN2: 46266 | BO2: 46296 | BP2: 46327 | BQ2: 46357
A3: REVENUE SCHEDULE | F3: Constant | G3: Unit | H3: Total | J3: {=EOMONTH( start_date, _xlfn.SEQUENCE( 1, periods, 0, 1 ) )} -> 44592 | K3: 44620 | L3: 44651 | M3: 44681 | N3: 44712 | O3: 44742 | P3: 44773 | Q3: 44804 | R3: 44834 | S3: 44865 | T3: 44895 | U3: 44926 | V3: 44957 | W3: 44985 | X3: 45016 | Y3: 45046 | Z3: 45077 | AA3: 45107 | AB3: 45138 | AC3: 45169 | AD3: 45199 | AE3: 45230 | AF3: 45260 | AG3: 45291 | AH3: 45322 | AI3: 45351 | AJ3: 45382 | AK3: 45412 | AL3: 45443 | AM3: 45473 | AN3: 45504 | AO3: 45535 | AP3: 45565 | AQ3: 45596 | AR3: 45626 | AS3: 45657 | AT3: 45688 | AU3: 45716 | AV3: 45747 | AW3: 45777 | AX3: 45808 | AY3: 45838 | AZ3: 45869 | BA3: 45900 | BB3: 45930 | BC3: 45961 | BD3: 45991 | BE3: 46022 | BF3: 46053 | BG3: 46081 | BH3: 46112 | BI3: 46142 | BJ3: 46173 | BK3: 46203 | BL3: 46234 | BM3: 46265 | BN3: 46295 | BO3: 46326 | BP3: 46356 | BQ3: 46387
A5: MONTHLY REVENUE
D7: i Total sales | G7: EUR | H7: {=_xlfn.LET( _xlpm.anchor,$J7, _xlpm.block, OFFSET( _xlpm.anchor, 0, 0, 1, periods ), _xlfn.BYROW( _xlpm.block, _xlfn.LAMBDA(_xlpm.row, SUM( _xlpm.row ) ) ) )} -> 83483876 | J7: {=_xlfn.LET( _xlpm.operating_flag,_xlfn.ANCHORARRAY( Time!$J18), _xlpm.w_units_anchor, Volume!$J8, _xlpm.w_units_sold, OFFSET( _xlpm.w_units_anchor, 0, 0, COUNTA( lstStores ), periods ), _xlpm.w_price_anchor, Price!$J40, _xlpm.w_price, OFFSET( _xlpm.w_price_anchor, 0, 0, COUNTA( lstStores ), periods ), _xlpm.w_revenue, _xlfn.BYCOL( _xlpm.w_units_sold * _xlpm.w_price, _xlfn.LAMBDA(_xlpm.column, SUM( _xlpm.column ) ) ), _xlpm.m_units_anchor, Volume!$J18, _xlpm.m_units_sold, OFFSET( _xlpm.m_units_anchor, 0, 0, COUNTA( lstStores ), periods ), _xlpm.m_price_anchor, Price!$J50, _xlpm.m_price, OFFSET( _xlpm.m_price_anchor, 0, 0, COUNTA( lstStores ), periods ), _xlpm.m_revenue, _xlfn.BYCOL( _xlpm.m_units_sold * _xlpm.m_price, _xlfn.LAMBDA(_xlpm.column, SUM( _xlpm.column ) ) ), _xlpm.a_units_anchor, Volume!$J45, _xlpm.a_units_sold, OFFSET( _xlpm.a_units_anchor, 0, 0, COUNTA( lstStores ), periods ), _xlpm.a_price_anchor, Price!$J60, _xlpm.a_price, OFFSET( _xlpm.a_price_anchor, 0, 0, COUNTA( lstStores ), periods ), _xlpm.a_revenue, _xlfn.BYCOL( _xlpm.a_units_sold * _xlpm.a_price, _xlfn.LAMBDA(_xlpm.column, SUM( _xlpm.column ) ) ), _xlfn.BYCOL( _xlfn.VSTACK(_xlpm.w_revenue, _xlpm.m_revenue, _xlpm.a_revenue ), _xlfn.LAMBDA(_xlpm.column, SUM( _xlpm.column ) ) ) )} -> 1003953.5 | K7: 669302.33 | L7: 669302.33 | M7: 726423.54 | N7: 730817.48 | O7: 735211.42 | P7: 1109408 | Q7: 743999.3 | R7: 748393.23 | S7: 851486.84 | T7: 863473.06 | U7: 1050551.1 | V7: 1344002.3 | W7: 908179.02 | X7: 920356.51 | Y7: 1107453.9 | Z7: 1128946.8 | AA7: 1150439.7 | AB7: 1755995.5 | AC7: 1193425.5 | AD7: 1214918.3 | AE7: 1322979.7 | AF7: 1344030.9 | AG7: 1638098.6 | AH7: 2054153.6 | AI7: 1411576.4 | AJ7: 1432543.1 | AK7: 1439768.8 | AL7: 1446994.5 | AM7: 1454220.2 | AN7: 2151120.7 | AO7: 1468671.7 | AP7: 1475897.4 | AQ7: 1475897.4 | AR7: 1475897.4 | AS7: 1771076.8 | AT7: 2197355.4 | AU7: 1494010.4 | AV7: 1494010.4 | AW7: 1494010.4 | AX7: 1494010.4 | AY7: 1494010.4 | AZ7: 2197355.4 | BA7: 1494010.4 | BB7: 1494010.4 | BC7: 1494010.4 | BD7: 1494010.4 | BE7: 1792812.5 | BF7: 2222814.3 | BG7: 1511339.6 | BH7: 1511339.6 | BI7: 1511339.6 | BJ7: 1511339.6 | BK7: 1511339.6 | BL7: 2222814.3 | BM7: 1511339.6 | BN7: 1511339.6 | BO7: 1511339.6 | BP7: 1511339.6 | BQ7: 1813607.5
D9: ii. Total sales split by category
E10: Women's | G10: EUR | H10: {=_xlfn.LET( _xlpm.anchor,$J10, _xlpm.block, OFFSET( _xlpm.anchor, 0, 0, COUNTA( $E$10:$E$12 ) + 1, periods ), _xlfn.BYROW( _xlpm.block, _xlfn.LAMBDA(_xlpm.row, SUM( _xlpm.row ) ) ) )} -> 44332304 | J10: {=_xlfn.LET( _xlpm.operating_flag,_xlfn.ANCHORARRAY( Time!$J18), _xlpm.w_units_anchor, Volume!$J8, _xlpm.w_units_sold, OFFSET( _xlpm.w_units_anchor, 0, 0, COUNTA( lstStores ), periods ), _xlpm.w_price_anchor, Price!$J40, _xlpm.w_price, OFFSET( _xlpm.w_price_anchor, 0, 0, COUNTA( lstStores ), periods ), _xlpm.w_revenue, _xlfn.BYCOL( _xlpm.w_units_sold * _xlpm.w_price, _xlfn.LAMBDA(_xlpm.column, SUM( _xlpm.column ) ) ), _xlpm.m_units_anchor, Volume!$J18, _xlpm.m_units_sold, OFFSET( _xlpm.m_units_anchor, 0, 0, COUNTA( lstStores ), periods ), _xlpm.m_price_anchor, Price!$J50, _xlpm.m_price, OFFSET( _xlpm.m_price_anchor, 0, 0, COUNTA( lstStores ), periods ), _xlpm.m_revenue, _xlfn.BYCOL( _xlpm.m_units_sold * _xlpm.m_price, _xlfn.LAMBDA(_xlpm.column, SUM( _xlpm.column ) ) ), _xlpm.a_units_anchor, Volume!$J45, _xlpm.a_units_sold, OFFSET( _xlpm.a_units_anchor, 0, 0, COUNTA( lstStores ), periods ), _xlpm.a_price_anchor, Price!$J60, _xlpm.a_price, OFFSET( _xlpm.a_price_anchor, 0, 0, COUNTA( lstStores ), periods ), _xlpm.a_revenue, _xlfn.BYCOL( _xlpm.a_units_sold * _xlpm.a_price, _xlfn.LAMBDA(_xlpm.column, SUM( _xlpm.column ) ) ), _xlfn.VSTACK(_xlpm.w_revenue, _xlpm.m_revenue, _xlpm.a_revenue ) )} -> 539040.7 | K10: 359360.47 | L10: 359360.47 | M10: 385089.63 | N10: 387068.8 | O10: 389047.97 | P10: 586540.7 | Q10: 393006.3 | R10: 394985.47 | S10: 442770 | T10: 448272.66 | U10: 544530.38 | V10: 695154.87 | W10: 469026.76 | X10: 474616.94 | Y10: 587153.06 | Z10: 599105.07 | AA10: 611057.08 | AB10: 934513.63 | AC10: 634961.09 | AD10: 646913.1 | AE10: 700022.87 | AF10: 711845.48 | AG10: 868401.7 | AH10: 1106429.6 | AI10: 749394.31 | AJ10: 761168.9 | AK10: 764597.57 | AL10: 768026.24 | AM10: 771454.9 | AN10: 1162325.4 | AO10: 778312.24 | AP10: 781740.91 | AQ10: 781740.91 | AR10: 781740.91 | AS10: 938089.1 | AT10: 1187410.8 | AU10: 791607.18 | AV10: 791607.18 | AW10: 791607.18 | AX10: 791607.18 | AY10: 791607.18 | AZ10: 1187410.8 | BA10: 791607.18 | BB10: 791607.18 | BC10: 791607.18 | BD10: 791607.18 | BE10: 949928.61 | BF10: 1201843.6 | BG10: 801229.06 | BH10: 801229.06 | BI10: 801229.06 | BJ10: 801229.06 | BK10: 801229.06 | BL10: 1201843.6 | BM10: 801229.06 | BN10: 801229.06 | BO10: 801229.06 | BP10: 801229.06 | BQ10: 961474.87
E11: Men's | G11: EUR | H11: 28625015 | J11: 337360.47 | K11: 224906.98 | L11: 224906.98 | M11: 248912.66 | N11: 250759.25 | O11: 252605.84 | P11: 381678.65 | Q11: 256299.02 | R11: 258145.61 | S11: 293982.7 | T11: 298443.94 | U11: 363486.22 | V11: 465871.89 | W11: 315115.28 | X11: 319649.3 | Y11: 375224.87 | Z11: 381945.3 | AA11: 388665.73 | AB11: 593079.23 | AC11: 402106.58 | AD11: 408827.01 | AE11: 451341.97 | AF11: 458370.44 | AG11: 558478.69 | AH11: 710995.96 | AI11: 480997.99 | AJ11: 487998.68 | AK11: 490945.64 | AL11: 493892.59 | AM11: 496839.55 | AN11: 749679.76 | AO11: 502733.46 | AP11: 505680.42 | AQ11: 505680.42 | AR11: 505680.42 | AS11: 606816.5 | AT11: 767387.98 | AU11: 511591.99 | AV11: 511591.99 | AW11: 511591.99 | AX11: 511591.99 | AY11: 511591.99 | AZ11: 767387.98 | BA11: 511591.99 | BB11: 511591.99 | BC11: 511591.99 | BD11: 511591.99 | BE11: 613910.39 | BF11: 775442.61 | BG11: 516961.74 | BH11: 516961.74 | BI11: 516961.74 | BJ11: 516961.74 | BK11: 516961.74 | BL11: 775442.61 | BM11: 516961.74 | BN11: 516961.74 | BO11: 516961.74 | BP11: 516961.74 | BQ11: 620354.09
E12: Accessories | G12: EUR | H12: 10526557 | J12: 127552.33 | K12: 85034.884 | L12: 85034.884 | M12: 92421.247 | N12: 92989.429 | O12: 93557.611 | P12: 141188.69 | Q12: 94693.975 | R12: 95262.156 | S12: 114734.14 | T12: 116756.46 | U12: 142534.54 | V12: 182975.54 | W12: 124036.98 | X12: 126090.27 | Y12: 145076.02 | Z12: 147896.46 | AA12: 150716.9 | AB12: 228402.66 | AC12: 156357.78 | AD12: 159178.23 | AE12: 171614.86 | AF12: 173815.01 | AG12: 211218.19 | AH12: 236728.11 | AI12: 181184.15 | AJ12: 183375.54 | AK12: 184225.62 | AL12: 185075.7 | AM12: 185925.79 | AN12: 239115.62 | AO12: 187625.95 | AP12: 188476.04 | AQ12: 188476.04 | AR12: 188476.04 | AS12: 226171.24 | AT12: 242556.67 | AU12: 190811.25 | AV12: 190811.25 | AW12: 190811.25 | AX12: 190811.25 | AY12: 190811.25 | AZ12: 242556.67 | BA12: 190811.25 | BB12: 190811.25 | BC12: 190811.25 | BD12: 190811.25 | BE12: 228973.5 | BF12: 245528.09 | BG12: 193148.76 | BH12: 193148.76 | BI12: 193148.76 | BJ12: 193148.76 | BK12: 193148.76 | BL12: 245528.09 | BM12: 193148.76 | BN12: 193148.76 | BO12: 193148.76 | BP12: 193148.76 | BQ12: 231778.51
E13: Total sales split by category | G13: EUR | H13: 83483876 | J13: {=_xlfn.LET( _xlpm.anchor, $J10, _xlpm.block, OFFSET( _xlpm.anchor, 0, 0, COUNTA( $E$10:$E$12 ), periods ), _xlfn.BYCOL( _xlpm.block, _xlfn.LAMBDA(_xlpm.column, SUM( _xlpm.column ) ) ) )} -> 1003953.5 | K13: 669302.33 | L13: 669302.33 | M13: 726423.54 | N13: 730817.48 | O13: 735211.42 | P13: 1109408 | Q13: 743999.3 | R13: 748393.23 | S13: 851486.84 | T13: 863473.06 | U13: 1050551.1 | V13: 1344002.3 | W13: 908179.02 | X13: 920356.51 | Y13: 1107453.9 | Z13: 1128946.8 | AA13: 1150439.7 | AB13: 1755995.5 | AC13: 1193425.5 | AD13: 1214918.3 | AE13: 1322979.7 | AF13: 1344030.9 | AG13: 1638098.6 | AH13: 2054153.6 | AI13: 1411576.4 | AJ13: 1432543.1 | AK13: 1439768.8 | AL13: 1446994.5 | AM13: 1454220.2 | AN13: 2151120.7 | AO13: 1468671.7 | AP13: 1475897.4 | AQ13: 1475897.4 | AR13: 1475897.4 | AS13: 1771076.8 | AT13: 2197355.4 | AU13: 1494010.4 | AV13: 1494010.4 | AW13: 1494010.4 | AX13: 1494010.4 | AY13: 1494010.4 | AZ13: 2197355.4 | BA13: 1494010.4 | BB13: 1494010.4 | BC13: 1494010.4 | BD13: 1494010.4 | BE13: 1792812.5 | BF13: 2222814.3 | BG13: 1511339.6 | BH13: 1511339.6 | BI13: 1511339.6 | BJ13: 1511339.6 | BK13: 1511339.6 | BL13: 2222814.3 | BM13: 1511339.6 | BN13: 1511339.6 | BO13: 1511339.6 | BP13: 1511339.6 | BQ13: 1813607.5
D15: iii. Total sales split by country
E16: {=lstCountries} -> France | G16: EUR | H16: {=_xlfn.LET( _xlpm.anchor,$J16, _xlpm.block, OFFSET( _xlpm.anchor, 0, 0, COUNTA( lstCountries ) + 1, periods ), _xlfn.BYROW( _xlpm.block, _xlfn.LAMBDA(_xlpm.row, SUM( _xlpm.row ) ) ) )} -> 13159056 | J16: {=_xlfn.LET( _xlpm.operating_flag,_xlfn.ANCHORARRAY( Time!$J18), _xlpm.w_units_anchor, Volume!$J8, _xlpm.w_units_sold, OFFSET( _xlpm.w_units_anchor, 0, 0, COUNTA( lstStores ), periods ), _xlpm.w_price_anchor, Price!$J40, _xlpm.w_price, OFFSET( _xlpm.w_price_anchor, 0, 0, COUNTA( lstStores ), periods ), _xlpm.m_units_anchor, Volume!$J18, _xlpm.m_units_sold, OFFSET( _xlpm.m_units_anchor, 0, 0, COUNTA( lstStores ), periods ), _xlpm.m_price_anchor, Price!$J50, _xlpm.m_price, OFFSET( _xlpm.m_price_anchor, 0, 0, COUNTA( lstStores ), periods ), _xlpm.a_units_anchor, Volume!$J45, _xlpm.a_units_sold, OFFSET( _xlpm.a_units_anchor, 0, 0, COUNTA( lstStores ), periods ), _xlpm.a_price_anchor, Price!$J60, _xlpm.a_price, OFFSET( _xlpm.a_price_anchor, 0, 0, COUNTA( lstStores ), periods ), _xlpm.operating_flag * ( (_xlpm.w_units_sold * _xlpm.w_price ) + (_xlpm.m_units_sold * _xlpm.m_price ) + (_xlpm.a_units_sold * _xlpm.a_price ) ) )} -> 295500 | K16: 197000 | L16: 197000 | M16: 197000 | N16: 197000 | O16: 197000 | P16: 295500 | Q16: 197000 | R16: 197000 | S16: 197000 | T16: 197000 | U16: 236400 | V16: 296977.5 | W16: 197985 | X16: 197985 | Y16: 197985 | Z16: 197985 | AA16: 197985 | AB16: 296491.61 | AC16: 197985 | AD16: 197985 | AE16: 197985 | AF16: 197985 | AG16: 237582 | AH16: 291472.73 | AI16: 198974.92 | AJ16: 198974.92 | AK16: 198974.92 | AL16: 198974.92 | AM16: 198974.92 | AN16: 289805.34 | AO16: 198974.92 | AP16: 198974.92 | AQ16: 198974.92 | AR16: 198974.92 | AS16: 238769.91 | AT16: 292343.69 | AU16: 200964.67 | AV16: 200964.67 | AW16: 200964.67 | AX16: 200964.67 | AY16: 200964.67 | AZ16: 292343.69 | BA16: 200964.67 | BB16: 200964.67 | BC16: 200964.67 | BD16: 200964.67 | BE16: 241157.61 | BF16: 299652.28 | BG16: 205988.79 | BH16: 205988.79 | BI16: 205988.79 | BJ16: 205988.79 | BK16: 205988.79 | BL16: 299652.28 | BM16: 205988.79 | BN16: 205988.79 | BO16: 205988.79 | BP16: 205988.79 | BQ16: 247186.55
E17: Italy | G17: EUR | H17: 15428200 | J17: 345750 | K17: 230500 | L17: 230500 | M17: 230500 | N17: 230500 | O17: 230500 | P17: 345750 | Q17: 230500 | R17: 230500 | S17: 230500 | T17: 230500 | U17: 276600 | V17: 347478.75 | W17: 231652.5 | X17: 231652.5 | Y17: 231652.5 | Z17: 231652.5 | AA17: 231652.5 | AB17: 347198.43 | AC17: 231652.5 | AD17: 231652.5 | AE17: 231652.5 | AF17: 231652.5 | AG17: 277983 | AH17: 345183.65 | AI17: 232810.76 | AJ17: 232810.76 | AK17: 232810.76 | AL17: 232810.76 | AM17: 232810.76 | AN17: 344221.69 | AO17: 232810.76 | AP17: 232810.76 | AQ17: 232810.76 | AR17: 232810.76 | AS17: 279372.91 | AT17: 347456.39 | AU17: 235138.87 | AV17: 235138.87 | AW17: 235138.87 | AX17: 235138.87 | AY17: 235138.87 | AZ17: 347456.39 | BA17: 235138.87 | BB17: 235138.87 | BC17: 235138.87 | BD17: 235138.87 | BE17: 282166.64 | BF17: 356142.8 | BG17: 241017.34 | BH17: 241017.34 | BI17: 241017.34 | BJ17: 241017.34 | BK17: 241017.34 | BL17: 356142.8 | BM17: 241017.34 | BN17: 241017.34 | BO17: 241017.34 | BP17: 241017.34 | BQ17: 289220.81
E18: Spain | G18: EUR | H18: 8035722.3 | J18: 180000 | K18: 120000 | L18: 120000 | M18: 120000 | N18: 120000 | O18: 120000 | P18: 180000 | Q18: 120000 | R18: 120000 | S18: 120000 | T18: 120000 | U18: 144000 | V18: 180900 | W18: 120600 | X18: 120600 | Y18: 120600 | Z18: 120600 | AA18: 120600 | AB18: 180787.87 | AC18: 120600 | AD18: 120600 | AE18: 120600 | AF18: 120600 | AG18: 144720 | AH18: 180191.5 | AI18: 121203 | AJ18: 121203 | AK18: 121203 | AL18: 121203 | AM18: 121203 | AN18: 179806.72 | AO18: 121203 | AP18: 121203 | AQ18: 121203 | AR18: 121203 | AS18: 145443.6 | AT18: 181521.78 | AU18: 122415.03 | AV18: 122415.03 | AW18: 122415.03 | AX18: 122415.03 | AY18: 122415.03 | AZ18: 181521.78 | BA18: 122415.03 | BB18: 122415.03 | BC18: 122415.03 | BD18: 122415.03 | BE18: 146898.04 | BF18: 186059.82 | BG18: 125475.41 | BH18: 125475.41 | BI18: 125475.41 | BJ18: 125475.41 | BK18: 125475.41 | BL18: 186059.82 | BM18: 125475.41 | BN18: 125475.41 | BO18: 125475.41 | BP18: 125475.41 | BQ18: 150570.49
E19: UK | G19: EUR | H19: 8122540.2 | J19: 182703.49 | K19: 121802.33 | L19: 121802.33 | M19: 121802.33 | N19: 121802.33 | O19: 121802.33 | P19: 182703.49 | Q19: 121802.33 | R19: 121802.33 | S19: 121802.33 | T19: 121802.33 | U19: 146162.79 | V19: 186021.55 | W19: 124014.37 | X19: 124014.37 | Y19: 124014.37 | Z19: 124014.37 | AA19: 124014.37 | AB19: 185838.09 | AC19: 124014.37 | AD19: 124014.37 | AE19: 124014.37 | AF19: 124014.37 | AG19: 148817.24 | AH19: 183124.67 | AI19: 123831.16 | AJ19: 123831.16 | AK19: 123831.16 | AL19: 123831.16 | AM19: 123831.16 | AN19: 182499.17 | AO19: 123831.16 | AP19: 123831.16 | AQ19: 123831.16 | AR19: 123831.16 | AS19: 148597.4 | AT19: 182119.69 | AU19: 123664.2 | AV19: 123664.2 | AW19: 123664.2 | AX19: 123664.2 | AY19: 123664.2 | AZ19: 182119.69 | BA19: 123664.2 | BB19: 123664.2 | BC19: 123664.2 | BD19: 123664.2 | BE19: 148397.04 | BF19: 181897.09 | BG19: 123513.06 | BH19: 123513.06 | BI19: 123513.06 | BJ19: 123513.06 | BK19: 123513.06 | BL19: 181897.09 | BM19: 123513.06 | BN19: 123513.06 | BO19: 123513.06 | BP19: 123513.06 | BQ19: 148215.67
E20: US | G20: EUR | H20: 6473259.2 | J20: 0 | K20: 0 | L20: 0 | M20: 57121.212 | N20: 61515.152 | O20: 65909.091 | P20: 105454.55 | Q20: 74696.97 | R20: 79090.909 | S20: 83484.848 | T20: 87878.788 | U20: 110727.27 | V20: 148004.5 | W20: 103154.65 | X20: 107639.64 | Y20: 107639.64 | Z20: 107639.64 | AA20: 107639.64 | AB20: 161286.91 | AC20: 107639.64 | AD20: 107639.64 | AE20: 107639.64 | AF20: 107639.64 | AG20: 129167.57 | AH20: 160721.5 | AI20: 108812.14 | AJ20: 108812.14 | AK20: 108812.14 | AL20: 108812.14 | AM20: 108812.14 | AN20: 160125.9 | AO20: 108812.14 | AP20: 108812.14 | AQ20: 108812.14 | AR20: 108812.14 | AS20: 130574.57 | AT20: 163340.25 | AU20: 111084.68 | AV20: 111084.68 | AW20: 111084.68 | AX20: 111084.68 | AY20: 111084.68 | AZ20: 163340.25 | BA20: 111084.68 | BB20: 111084.68 | BC20: 111084.68 | BD20: 111084.68 | BE20: 133301.62 | BF20: 162716.98 | BG20: 110660.8 | BH20: 110660.8 | BI20: 110660.8 | BJ20: 110660.8 | BK20: 110660.8 | BL20: 162716.98 | BM20: 110660.8 | BN20: 110660.8 | BO20: 110660.8 | BP20: 110660.8 | BQ20: 132792.96
E21: Canada | G21: EUR | H21: 9946468.4 | J21: 0 | K21: 0 | L21: 0 | M21: 0 | N21: 0 | O21: 0 | P21: 0 | Q21: 0 | R21: 0 | S21: 98699.664 | T21: 106291.95 | U21: 136661.07 | V21: 184620 | W21: 130772.5 | X21: 138465 | Y21: 146157.5 | Z21: 153850 | AA21: 161542.5 | AB21: 253450.68 | AC21: 176927.5 | AD21: 184620 | AE21: 184620 | AF21: 184620 | AG21: 221544 | AH21: 274240.46 | AI21: 187065.3 | AJ21: 187065.3 | AK21: 187065.3 | AL21: 187065.3 | AM21: 187065.3 | AN21: 272723.87 | AO21: 187065.3 | AP21: 187065.3 | AQ21: 187065.3 | AR21: 187065.3 | AS21: 224478.36 | AT21: 277373.03 | AU21: 190480.47 | AV21: 190480.47 | AW21: 190480.47 | AX21: 190480.47 | AY21: 190480.47 | AZ21: 277373.03 | BA21: 190480.47 | BB21: 190480.47 | BC21: 190480.47 | BD21: 190480.47 | BE21: 228576.56 | BF21: 281071.33 | BG21: 193020.21 | BH21: 193020.21 | BI21: 193020.21 | BJ21: 193020.21 | BK21: 193020.21 | BL21: 281071.33 | BM21: 193020.21 | BN21: 193020.21 | BO21: 193020.21 | BP21: 193020.21 | BQ21: 231624.25
E22: Switzerland | G22: EUR | H22: 15446099 | J22: 0 | K22: 0 | L22: 0 | M22: 0 | N22: 0 | O22: 0 | P22: 0 | Q22: 0 | R22: 0 | S22: 0 | T22: 0 | U22: 0 | V22: 0 | W22: 0 | X22: 0 | Y22: 179404.94 | Z22: 193205.32 | AA22: 207005.7 | AB22: 330941.92 | AC22: 234606.45 | AD22: 248406.83 | AE22: 262207.21 | AF22: 276007.59 | AG22: 347769.57 | AH22: 448215.6 | AI22: 316042.11 | AJ22: 329783.07 | AK22: 329783.07 | AL22: 329783.07 | AM22: 329783.07 | AN22: 487599.83 | AO22: 329783.07 | AP22: 329783.07 | AQ22: 329783.07 | AR22: 329783.07 | AS22: 395739.69 | AT22: 497323.2 | AU22: 336560.27 | AV22: 336560.27 | AW22: 336560.27 | AX22: 336560.27 | AY22: 336560.27 | AZ22: 497323.2 | BA22: 336560.27 | BB22: 336560.27 | BC22: 336560.27 | BD22: 336560.27 | BE22: 403872.32 | BF22: 500194.11 | BG22: 338503.14 | BH22: 338503.14 | BI22: 338503.14 | BJ22: 338503.14 | BK22: 338503.14 | BL22: 500194.11 | BM22: 338503.14 | BN22: 338503.14 | BO22: 338503.14 | BP22: 338503.14 | BQ22: 406203.76
E23: Russia | G23: EUR | H23: 6872532.3 | J23: 0 | K23: 0 | L23: 0 | M23: 0 | N23: 0 | O23: 0 | P23: 0 | Q23: 0 | R23: 0 | S23: 0 | T23: 0 | U23: 0 | V23: 0 | W23: 0 | X23: 0 | Y23: 0 | Z23: 0 | AA23: 0 | AB23: 0 | AC23: 0 | AD23: 0 | AE23: 94260.98 | AF23: 101511.82 | AG23: 130515.2 | AH23: 171003.54 | AI23: 122837.04 | AJ23: 130062.75 | AK23: 137288.46 | AL23: 144514.17 | AM23: 151739.88 | AN23: 234338.23 | AO23: 166191.29 | AP23: 173417 | AQ23: 173417 | AR23: 173417 | AS23: 208100.4 | AT23: 255877.41 | AU23: 173702.23 | AV23: 173702.23 | AW23: 173702.23 | AX23: 173702.23 | AY23: 173702.23 | AZ23: 255877.41 | BA23: 173702.23 | BB23: 173702.23 | BC23: 173702.23 | BD23: 173702.23 | BE23: 208442.67 | BF23: 255079.87 | BG23: 173160.82 | BH23: 173160.82 | BI23: 173160.82 | BJ23: 173160.82 | BK23: 173160.82 | BL23: 255079.87 | BM23: 173160.82 | BN23: 173160.82 | BO23: 173160.82 | BP23: 173160.82 | BQ23: 207792.98
E24: Total sales split by country | G24: EUR | H24: 83483876 | J24: {=_xlfn.LET( _xlpm.anchor, $J16, _xlpm.block, OFFSET( _xlpm.anchor, 0, 0, COUNTA( lstCountries ), periods ), _xlfn.BYCOL( _xlpm.block, _xlfn.LAMBDA(_xlpm.column, SUM( _xlpm.column ) ) ) )} -> 1003953.5 | K24: 669302.33 | L24: 669302.33 | M24: 726423.54 | N24: 730817.48 | O24: 735211.42 | P24: 1109408 | Q24: 743999.3 | R24: 748393.23 | S24: 851486.84 | T24: 863473.06 | U24: 1050551.1 | V24: 1344002.3 | W24: 908179.02 | X24: 920356.51 | Y24: 1107453.9 | Z24: 1128946.8 | AA24: 1150439.7 | AB24: 1755995.5 | AC24: 1193425.5 | AD24: 1214918.3 | AE24: 1322979.7 | AF24: 1344030.9 | AG24: 1638098.6 | AH24: 2054153.6 | AI24: 1411576.4 | AJ24: 1432543.1 | AK24: 1439768.8 | AL24: 1446994.5 | AM24: 1454220.2 | AN24: 2151120.7 | AO24: 1468671.7 | AP24: 1475897.4 | AQ24: 1475897.4 | AR24: 1475897.4 | AS24: 1771076.8 | AT24: 2197355.4 | AU24: 1494010.4 | AV24: 1494010.4 | AW24: 1494010.4 | AX24: 1494010.4 | AY24: 1494010.4 | AZ24: 2197355.4 | BA24: 1494010.4 | BB24: 1494010.4 | BC24: 1494010.4 | BD24: 1494010.4 | BE24: 1792812.5 | BF24: 2222814.3 | BG24: 1511339.6 | BH24: 1511339.6 | BI24: 1511339.6 | BJ24: 1511339.6 | BK24: 1511339.6 | BL24: 2222814.3 | BM24: 1511339.6 | BN24: 1511339.6 | BO24: 1511339.6 | BP24: 1511339.6 | BQ24: 1813607.5
A26: ANNUAL REVENUE
J28: {=_xlfn.ANCHORARRAY(Time!$J$13)} -> 2022 | K28: 2023 | L28: 2024 | M28: 2025 | N28: 2026
D30: i Total sales | G30: EUR | H30: {=_xlfn.LET( _xlpm.anchor,$J30, _xlpm.block, OFFSET( _xlpm.anchor, 0, 0, 1, periods ), _xlfn.BYROW( _xlpm.block, _xlfn.LAMBDA(_xlpm.row, SUM( _xlpm.row ) ) ) )} -> 83483876 | J30: {=MMULT(_xlfn.ANCHORARRAY( J7), --(TRANSPOSE(_xlfn.ANCHORARRAY( Time!J12) ) =_xlfn.ANCHORARRAY( Revenue!J28) ) )} -> 9902322.2 | K30: 15028827 | L30: 19057818 | M30: 19633617 | N30: 19861292
D32: ii. Total sales split by category
E33: Women's | G33: EUR | H33: {=_xlfn.LET( _xlpm.anchor,$J33, _xlpm.block, OFFSET( _xlpm.anchor, 0, 0, COUNTA( $E$10:$E$12 ) + 1, periods ), _xlfn.BYROW( _xlpm.block, _xlfn.LAMBDA(_xlpm.row, SUM( _xlpm.row ) ) ) )} -> 44332304 | J33: {=MMULT(_xlfn.ANCHORARRAY( J10), --( TRANSPOSE(_xlfn.ANCHORARRAY( Time!J12) ) =_xlfn.ANCHORARRAY( Revenue!J28) ) )} -> 5229073.5 | K33: 7932771.6 | L33: 10145021 | M33: 10449215 | N33: 10576224
E34: Men's | G34: EUR | H34: 28625015 | J34: 3391488.3 | K34: 5118676.3 | L34: 6537941.4 | M34: 6753014.2 | N34: 6823894.9
E35: Accessories | G35: EUR | H35: 10526557 | J35: 1281760.3 | K35: 1977378.9 | L35: 2374855.8 | M35: 2431388.1 | N35: 2461173.5
E36: Total sales split by category | G36: EUR | H36: 83483876 | J36: {=_xlfn.LET( _xlpm.anchor, $J33, _xlpm.block, OFFSET( _xlpm.anchor, 0, 0, COUNTA( $E$33:$E$35 ), COUNTA(_xlfn.ANCHORARRAY( J28) ) ), _xlfn.BYCOL( _xlpm.block, _xlfn.LAMBDA(_xlpm.column, SUM( _xlpm.column ) ) ) )} -> 9902322.2 | K36: 15028827 | L36: 19057818 | M36: 19633617 | N36: 19861292
D38: iii. Total sales split by country
E40: {=lstCountries} -> France | G40: EUR | H40: {=_xlfn.LET( _xlpm.anchor,$J40, _xlpm.block, OFFSET( _xlpm.anchor, 0, 0, COUNTA( lstCountries ) + 1, periods ), _xlfn.BYROW( _xlpm.block, _xlfn.LAMBDA(_xlpm.row, SUM( _xlpm.row ) ) ) )} -> 13159056 | J40: {=MMULT(_xlfn.ANCHORARRAY( J16), --(TRANSPOSE(_xlfn.ANCHORARRAY( Time!J12) ) =_xlfn.ANCHORARRAY( Revenue!J28) ) )} -> 2600400 | K40: 2612916.1 | L40: 2610822.3 | M40: 2634527.1 | N40: 2700390.2
E41: Italy | G41: EUR | H41: 15428200 | J41: 3042600 | K41: 3057532.7 | L41: 3064075.1 | M41: 3093329.3 | N41: 3170662.5
E42: Spain | G42: EUR | H42: 8035722.3 | J42: 1584000 | K42: 1591807.9 | L42: 1596268.8 | M42: 1611676.9 | N42: 1651968.8
E43: UK | G43: EUR | H43: 8122540.2 | J43: 1607790.7 | K43: 1636806.2 | L43: 1628701.7 | M43: 1625614.2 | N43: 1623627.4
E44: US | G44: EUR | H44: 6473259.2 | J44: 725878.79 | K44: 1402730.8 | L44: 1430731.3 | M44: 1459744.2 | N44: 1454174.2
E45: Canada | G45: EUR | H45: 9946468.4 | J45: 341652.68 | K45: 2121189.7 | L45: 2455030.4 | M45: 2497646.9 | N45: 2530948.8
E46: Switzerland | G46: EUR | H46: 15446099 | J46: 0 | K46: 2279555.5 | L46: 4285861.8 | M46: 4427561.1 | N46: 4453120.2
E47: Russia | G47: EUR | H47: 6872532.3 | J47: 0 | K47: 326288.01 | L47: 1986326.7 | M47: 2283517.5 | N47: 2276400.1
E48: Total sales split by country | G48: EUR | H48: 83483876 | J48: {=_xlfn.LET( _xlpm.anchor, $J40, _xlpm.block, OFFSET( _xlpm.anchor, 0, 0, COUNTA( lstCountries ), COUNTA(_xlfn.ANCHORARRAY( J28) ) ), _xlfn.BYCOL( _xlpm.block, _xlfn.LAMBDA(_xlpm.column, SUM( _xlpm.column ) ) ) )} -> 9902322.2 | K48: 15028827 | L48: 19057818 | M48: 19633617 | N48: 19861292
A50: End of schedule

Sheet Price
A1: =company -> Fashion Boutique
A2: {=topic} -> CFM Topic: Revenue | J2: {=EDATE( start_date, _xlfn.SEQUENCE( 1, periods, 0, 1 ) )} -> 44562 | K2: 44593 | L2: 44621 | M2: 44652 | N2: 44682 | O2: 44713 | P2: 44743 | Q2: 44774 | R2: 44805 | S2: 44835 | T2: 44866 | U2: 44896 | V2: 44927 | W2: 44958 | X2: 44986 | Y2: 45017 | Z2: 45047 | AA2: 45078 | AB2: 45108 | AC2: 45139 | AD2: 45170 | AE2: 45200 | AF2: 45231 | AG2: 45261 | AH2: 45292 | AI2: 45323 | AJ2: 45352 | AK2: 45383 | AL2: 45413 | AM2: 45444 | AN2: 45474 | AO2: 45505 | AP2: 45536 | AQ2: 45566 | AR2: 45597 | AS2: 45627 | AT2: 45658 | AU2: 45689 | AV2: 45717 | AW2: 45748 | AX2: 45778 | AY2: 45809 | AZ2: 45839 | BA2: 45870 | BB2: 45901 | BC2: 45931 | BD2: 45962 | BE2: 45992 | BF2: 46023 | BG2: 46054 | BH2: 46082 | BI2: 46113 | BJ2: 46143 | BK2: 46174 | BL2: 46204 | BM2: 46235 | BN2: 46266 | BO2: 46296 | BP2: 46327 | BQ2: 46357
A3: PRICE SCHEDULE | F3: Constant | G3: Unit | H3: Total | J3: {=EOMONTH( start_date, _xlfn.SEQUENCE( 1, periods, 0, 1 ) )} -> 44592 | K3: 44620 | L3: 44651 | M3: 44681 | N3: 44712 | O3: 44742 | P3: 44773 | Q3: 44804 | R3: 44834 | S3: 44865 | T3: 44895 | U3: 44926 | V3: 44957 | W3: 44985 | X3: 45016 | Y3: 45046 | Z3: 45077 | AA3: 45107 | AB3: 45138 | AC3: 45169 | AD3: 45199 | AE3: 45230 | AF3: 45260 | AG3: 45291 | AH3: 45322 | AI3: 45351 | AJ3: 45382 | AK3: 45412 | AL3: 45443 | AM3: 45473 | AN3: 45504 | AO3: 45535 | AP3: 45565 | AQ3: 45596 | AR3: 45626 | AS3: 45657 | AT3: 45688 | AU3: 45716 | AV3: 45747 | AW3: 45777 | AX3: 45808 | AY3: 45838 | AZ3: 45869 | BA3: 45900 | BB3: 45930 | BC3: 45961 | BD3: 45991 | BE3: 46022 | BF3: 46053 | BG3: 46081 | BH3: 46112 | BI3: 46142 | BJ3: 46173 | BK3: 46203 | BL3: 46234 | BM3: 46265 | BN3: 46295 | BO3: 46326 | BP3: 46356 | BQ3: 46387
A5: SECTION 4, 5 AND 7: AVERAGE LOCAL CURRENCY PRICE ADJUSTED FOR SEASONALITY AND INFLATION
D7: Women's
E8: {=lstStores} -> Paris | G8: {=INDEX( CaseData!$C$9:$E$17, MATCH(_xlfn.ANCHORARRAY( Price!E8), CaseData!$C$9:$C$17, 0 ), 3 )} -> EUR | J8: {=_xlfn.LET( _xlpm.operating_flag,_xlfn.ANCHORARRAY( Time!$J$18), _xlpm.unit_prices_table, CaseData!$B$46:$E$52, _xlpm.currency_row, CaseData!$B$46:$B$52, _xlpm.apparel_column, CaseData!$B$46:$E$46, _xlpm.current_apparel, Price!$D7, _xlpm.store_currency,_xlfn.ANCHORARRAY( Price!$G8), _xlpm.unit_price_at_store, INDEX( _xlpm.unit_prices_table, _xlfn.XMATCH( _xlpm.store_currency, _xlpm.currency_row, 0, 1 ), _xlfn.XMATCH( _xlpm.current_apparel, _xlpm.apparel_column, 0, 1 ) ), _xlpm.discount_month, CaseData!$C$58:$C$69, _xlpm.discount_percentage, CaseData!$E$58:$E$69, _xlpm.current_month,_xlfn.ANCHORARRAY( Time!J$11), _xlpm.discount, 1 - _xlfn.XLOOKUP( _xlpm.current_month, _xlpm.discount_month, _xlpm.discount_percentage, 0, 0, 1 ), _xlpm.current_year, YEAR(_xlfn.ANCHORARRAY( Time!J$9) ), _xlpm.clean_rates, IF( CaseData!$C$86:$G$91 = "n.a.", 0, CaseData!$C$86:$G$91), _xlpm.compounded_rates, _xlfn.MAKEARRAY( ROWS( _xlpm.clean_rates ), COLUMNS( _xlpm.clean_rates ), _xlfn.LAMBDA(_xlpm.i,_xlpm.j, INDEX( _xlfn.SCAN( 1, INDEX( _xlpm.clean_rates, _xlpm.i, 0 ), _xlfn.LAMBDA(_xlpm.s,_xlpm.c, _xlpm.s * ( 1 + _xlpm.c ) ) ), _xlpm.j ) ) ), _xlpm.inflation_rows, CaseData!$B$86:$B$91, _xlpm.inflation_columns, CaseData!$B$85:$G$85, _xlpm.inflation_table, _xlfn.VSTACK( _xlpm.inflation_columns, _xlfn.HSTACK( _xlpm.inflation_rows, _xlpm.compounded_rates ) ), _xlpm.inflation, INDEX( _xlpm.inflation_table, _xlfn.XMATCH( _xlpm.store_currency, _xlpm.inflation_rows, 0 ) + 1, _xlfn.XMATCH( _xlpm.current_year, _xlpm.inflation_columns, 0 ) ), _xlpm.operating_flag * _xlpm.unit_price_at_store * _xlpm.discount * _xlpm.inflation)} -> 300 | K8: 500 | L8: 500 | M8: 500 | N8: 500 | O8: 500 | P8: 300 | Q8: 500 | R8: 500 | S8: 500 | T8: 500 | U8: 400 | V8: 301.5 | W8: 502.5 | X8: 502.5 | Y8: 502.5 | Z8: 502.5 | AA8: 502.5 | AB8: 301.5 | AC8: 502.5 | AD8: 502.5 | AE8: 502.5 | AF8: 502.5 | AG8: 402 | AH8: 303.0075 | AI8: 505.0125 | AJ8: 505.0125 | AK8: 505.0125 | AL8: 505.0125 | AM8: 505.0125 | AN8: 303.0075 | AO8: 505.0125 | AP8: 505.0125 | AQ8: 505.0125 | AR8: 505.0125 | AS8: 404.01 | AT8: 306.03757 | AU8: 510.06262 | AV8: 510.06262 | AW8: 510.06262 | AX8: 510.06262 | AY8: 510.06262 | AZ8: 306.03757 | BA8: 510.06262 | BB8: 510.06262 | BC8: 510.06262 | BD8: 510.06262 | BE8: 408.0501 | BF8: 313.68851 | BG8: 522.81419 | BH8: 522.81419 | BI8: 522.81419 | BJ8: 522.81419 | BK8: 522.81419 | BL8: 313.68851 | BM8: 522.81419 | BN8: 522.81419 | BO8: 522.81419 | BP8: 522.81419 | BQ8: 418.25135
E9: Milano | G9: EUR | J9: 300 | K9: 500 | L9: 500 | M9: 500 | N9: 500 | O9: 500 | P9: 300 | Q9: 500 | R9: 500 | S9: 500 | T9: 500 | U9: 400 | V9: 301.5 | W9: 502.5 | X9: 502.5 | Y9: 502.5 | Z9: 502.5 | AA9: 502.5 | AB9: 301.5 | AC9: 502.5 | AD9: 502.5 | AE9: 502.5 | AF9: 502.5 | AG9: 402 | AH9: 303.0075 | AI9: 505.0125 | AJ9: 505.0125 | AK9: 505.0125 | AL9: 505.0125 | AM9: 505.0125 | AN9: 303.0075 | AO9: 505.0125 | AP9: 505.0125 | AQ9: 505.0125 | AR9: 505.0125 | AS9: 404.01 | AT9: 306.03757 | AU9: 510.06262 | AV9: 510.06262 | AW9: 510.06262 | AX9: 510.06262 | AY9: 510.06262 | AZ9: 306.03757 | BA9: 510.06262 | BB9: 510.06262 | BC9: 510.06262 | BD9: 510.06262 | BE9: 408.0501 | BF9: 313.68851 | BG9: 522.81419 | BH9: 522.81419 | BI9: 522.81419 | BJ9: 522.81419 | BK9: 522.81419 | BL9: 313.68851 | BM9: 522.81419 | BN9: 522.81419 | BO9: 522.81419 | BP9: 522.81419 | BQ9: 418.25135
E10: Madrid | G10: EUR | J10: 300 | K10: 500 | L10: 500 | M10: 500 | N10: 500 | O10: 500 | P10: 300 | Q10: 500 | R10: 500 | S10: 500 | T10: 500 | U10: 400 | V10: 301.5 | W10: 502.5 | X10: 502.5 | Y10: 502.5 | Z10: 502.5 | AA10: 502.5 | AB10: 301.5 | AC10: 502.5 | AD10: 502.5 | AE10: 502.5 | AF10: 502.5 | AG10: 402 | AH10: 303.0075 | AI10: 505.0125 | AJ10: 505.0125 | AK10: 505.0125 | AL10: 505.0125 | AM10: 505.0125 | AN10: 303.0075 | AO10: 505.0125 | AP10: 505.0125 | AQ10: 505.0125 | AR10: 505.0125 | AS10: 404.01 | AT10: 306.03757 | AU10: 510.06262 | AV10: 510.06262 | AW10: 510.06262 | AX10: 510.06262 | AY10: 510.06262 | AZ10: 306.03757 | BA10: 510.06262 | BB10: 510.06262 | BC10: 510.06262 | BD10: 510.06262 | BE10: 408.0501 | BF10: 313.68851 | BG10: 522.81419 | BH10: 522.81419 | BI10: 522.81419 | BJ10: 522.81419 | BK10: 522.81419 | BL10: 313.68851 | BM10: 522.81419 | BN10: 522.81419 | BO10: 522.81419 | BP10: 522.81419 | BQ10: 418.25135
E11: London | G11: GBP | J11: 255 | K11: 425 | L11: 425 | M11: 425 | N11: 425 | O11: 425 | P11: 255 | Q11: 425 | R11: 425 | S11: 425 | T11: 425 | U11: 340 | V11: 262.65 | W11: 437.75 | X11: 437.75 | Y11: 437.75 | Z11: 437.75 | AA11: 437.75 | AB11: 262.65 | AC11: 437.75 | AD11: 437.75 | AE11: 437.75 | AF11: 437.75 | AG11: 350.2 | AH11: 265.2765 | AI11: 442.1275 | AJ11: 442.1275 | AK11: 442.1275 | AL11: 442.1275 | AM11: 442.1275 | AN11: 265.2765 | AO11: 442.1275 | AP11: 442.1275 | AQ11: 442.1275 | AR11: 442.1275 | AS11: 353.702 | AT11: 267.92926 | AU11: 446.54877 | AV11: 446.54877 | AW11: 446.54877 | AX11: 446.54877 | AY11: 446.54877 | AZ11: 267.92926 | BA11: 446.54877 | BB11: 446.54877 | BC11: 446.54877 | BD11: 446.54877 | BE11: 357.23902 | BF11: 270.60856 | BG11: 451.01426 | BH11: 451.01426 | BI11: 451.01426 | BJ11: 451.01426 | BK11: 451.01426 | BL11: 270.60856 | BM11: 451.01426 | BN11: 451.01426 | BO11: 451.01426 | BP11: 451.01426 | BQ11: 360.81141
E12: New York | G12: USD | J12: 0 | K12: 0 | L12: 0 | M12: 475 | N12: 475 | O12: 475 | P12: 285 | Q12: 475 | R12: 475 | S12: 475 | T12: 475 | U12: 380 | V12: 293.55 | W12: 489.25 | X12: 489.25 | Y12: 489.25 | Z12: 489.25 | AA12: 489.25 | AB12: 293.55 | AC12: 489.25 | AD12: 489.25 | AE12: 489.25 | AF12: 489.25 | AG12: 391.4 | AH12: 299.421 | AI12: 499.035 | AJ12: 499.035 | AK12: 499.035 | AL12: 499.035 | AM12: 499.035 | AN12: 299.421 | AO12: 499.035 | AP12: 499.035 | AQ12: 499.035 | AR12: 499.035 | AS12: 399.228 | AT12: 308.40363 | AU12: 514.00605 | AV12: 514.00605 | AW12: 514.00605 | AX12: 514.00605 | AY12: 514.00605 | AZ12: 308.40363 | BA12: 514.00605 | BB12: 514.00605 | BC12: 514.00605 | BD12: 514.00605 | BE12: 411.20484 | BF12: 309.94565 | BG12: 516.57608 | BH12: 516.57608 | BI12: 516.57608 | BJ12: 516.57608 | BK12: 516.57608 | BL12: 309.94565 | BM12: 516.57608 | BN12: 516.57608 | BO12: 516.57608 | BP12: 516.57608 | BQ12: 413.26086
E13: Montreal | G13: CAD | J13: 0 | K13: 0 | L13: 0 | M13: 0 | N13: 0 | O13: 0 | P13: 0 | Q13: 0 | R13: 0 | S13: 700 | T13: 700 | U13: 560 | V13: 428.4 | W13: 714 | X13: 714 | Y13: 714 | Z13: 714 | AA13: 714 | AB13: 428.4 | AC13: 714 | AD13: 714 | AE13: 714 | AF13: 714 | AG13: 571.2 | AH13: 436.968 | AI13: 728.28 | AJ13: 728.28 | AK13: 728.28 | AL13: 728.28 | AM13: 728.28 | AN13: 436.968 | AO13: 728.28 | AP13: 728.28 | AQ13: 728.28 | AR13: 728.28 | AS13: 582.624 | AT13: 447.8922 | AU13: 746.487 | AV13: 746.487 | AW13: 746.487 | AX13: 746.487 | AY13: 746.487 | AZ13: 447.8922 | BA13: 746.487 | BB13: 746.487 | BC13: 746.487 | BD13: 746.487 | BE13: 597.1896 | BF13: 456.85004 | BG13: 761.41674 | BH13: 761.41674 | BI13: 761.41674 | BJ13: 761.41674 | BK13: 761.41674 | BL13: 456.85004 | BM13: 761.41674 | BN13: 761.41674 | BO13: 761.41674 | BP13: 761.41674 | BQ13: 609.13339
E14: Zurich | G14: CHF | J14: 0 | K14: 0 | L14: 0 | M14: 0 | N14: 0 | O14: 0 | P14: 0 | Q14: 0 | R14: 0 | S14: 0 | T14: 0 | U14: 0 | V14: 0 | W14: 0 | X14: 0 | Y14: 768.75 | Z14: 768.75 | AA14: 768.75 | AB14: 461.25 | AC14: 768.75 | AD14: 768.75 | AE14: 768.75 | AF14: 768.75 | AG14: 615 | AH14: 463.55625 | AI14: 772.59375 | AJ14: 772.59375 | AK14: 772.59375 | AL14: 772.59375 | AM14: 772.59375 | AN14: 463.55625 | AO14: 772.59375 | AP14: 772.59375 | AQ14: 772.59375 | AR14: 772.59375 | AS14: 618.075 | AT14: 477.46294 | AU14: 795.77156 | AV14: 795.77156 | AW14: 795.77156 | AX14: 795.77156 | AY14: 795.77156 | AZ14: 477.46294 | BA14: 795.77156 | BB14: 795.77156 | BC14: 795.77156 | BD14: 795.77156 | BE14: 636.61725 | BF14: 484.62488 | BG14: 807.70814 | BH14: 807.70814 | BI14: 807.70814 | BJ14: 807.70814 | BK14: 807.70814 | BL14: 484.62488 | BM14: 807.70814 | BN14: 807.70814 | BO14: 807.70814 | BP14: 807.70814 | BQ14: 646.16651
E15: Moscow | G15: RUB | J15: 0 | K15: 0 | L15: 0 | M15: 0 | N15: 0 | O15: 0 | P15: 0 | Q15: 0 | R15: 0 | S15: 0 | T15: 0 | U15: 0 | V15: 0 | W15: 0 | X15: 0 | Y15: 0 | Z15: 0 | AA15: 0 | AB15: 0 | AC15: 0 | AD15: 0 | AE15: 55550 | AF15: 55550 | AG15: 44440 | AH15: 33663.3 | AI15: 56105.5 | AJ15: 56105.5 | AK15: 56105.5 | AL15: 56105.5 | AM15: 56105.5 | AN15: 33663.3 | AO15: 56105.5 | AP15: 56105.5 | AQ15: 56105.5 | AR15: 56105.5 | AS15: 44884.4 | AT15: 34168.249 | AU15: 56947.082 | AV15: 56947.082 | AW15: 56947.082 | AX15: 56947.082 | AY15: 56947.082 | AZ15: 34168.249 | BA15: 56947.082 | BB15: 56947.082 | BC15: 56947.082 | BD15: 56947.082 | BE15: 45557.666 | BF15: 34509.932 | BG15: 57516.553 | BH15: 57516.553 | BI15: 57516.553 | BJ15: 57516.553 | BK15: 57516.553 | BL15: 34509.932 | BM15: 57516.553 | BN15: 57516.553 | BO15: 57516.553 | BP15: 57516.553 | BQ15: 46013.243
D17: Men's
E18: {=lstStores} -> Paris | G18: {=INDEX( CaseData!$C$9:$E$17, MATCH(_xlfn.ANCHORARRAY( Price!E18), CaseData!$C$9:$C$17, 0 ), 3 )} -> EUR | J18: {=_xlfn.LET( _xlpm.operating_flag,_xlfn.ANCHORARRAY( Time!$J$18), _xlpm.unit_prices_table, CaseData!$B$46:$E$52, _xlpm.currency_row, CaseData!$B$46:$B$52, _xlpm.apparel_column, CaseData!$B$46:$E$46, _xlpm.current_apparel, Price!$D17, _xlpm.store_currency,_xlfn.ANCHORARRAY( Price!$G18), _xlpm.unit_price_at_store, INDEX( _xlpm.unit_prices_table, _xlfn.XMATCH( _xlpm.store_currency, _xlpm.currency_row, 0, 1 ), _xlfn.XMATCH( _xlpm.current_apparel, _xlpm.apparel_column, 0, 1 ) ), _xlpm.discount_month, CaseData!$C$58:$C$69, _xlpm.discount_percentage, CaseData!$E$58:$E$69, _xlpm.current_month,_xlfn.ANCHORARRAY( Time!J$11), _xlpm.discount, 1 - _xlfn.XLOOKUP( _xlpm.current_month, _xlpm.discount_month, _xlpm.discount_percentage, 0, 0, 1 ), _xlpm.current_year, YEAR(_xlfn.ANCHORARRAY( Time!J$9) ), _xlpm.clean_rates, IF( CaseData!$C$86:$G$91 = "n.a.", 0, CaseData!$C$86:$G$91), _xlpm.compounded_rates, _xlfn.MAKEARRAY( ROWS( _xlpm.clean_rates ), COLUMNS( _xlpm.clean_rates ), _xlfn.LAMBDA(_xlpm.i,_xlpm.j, INDEX( _xlfn.SCAN( 1, INDEX( _xlpm.clean_rates, _xlpm.i, 0 ), _xlfn.LAMBDA(_xlpm.s,_xlpm.c, _xlpm.s * ( 1 + _xlpm.c ) ) ), _xlpm.j ) ) ), _xlpm.inflation_rows, CaseData!$B$86:$B$91, _xlpm.inflation_columns, CaseData!$B$85:$G$85, _xlpm.inflation_table, _xlfn.VSTACK( _xlpm.inflation_columns, _xlfn.HSTACK( _xlpm.inflation_rows, _xlpm.compounded_rates ) ), _xlpm.inflation, INDEX( _xlpm.inflation_table, _xlfn.XMATCH( _xlpm.store_currency, _xlpm.inflation_rows, 0 ) + 1, _xlfn.XMATCH( _xlpm.current_year, _xlpm.inflation_columns, 0 ) ), _xlpm.operating_flag * _xlpm.unit_price_at_store * _xlpm.discount * _xlpm.inflation)} -> 240 | K18: 400 | L18: 400 | M18: 400 | N18: 400 | O18: 400 | P18: 240 | Q18: 400 | R18: 400 | S18: 400 | T18: 400 | U18: 320 | V18: 241.2 | W18: 402 | X18: 402 | Y18: 402 | Z18: 402 | AA18: 402 | AB18: 241.2 | AC18: 402 | AD18: 402 | AE18: 402 | AF18: 402 | AG18: 321.6 | AH18: 242.406 | AI18: 404.01 | AJ18: 404.01 | AK18: 404.01 | AL18: 404.01 | AM18: 404.01 | AN18: 242.406 | AO18: 404.01 | AP18: 404.01 | AQ18: 404.01 | AR18: 404.01 | AS18: 323.208 | AT18: 244.83006 | AU18: 408.0501 | AV18: 408.0501 | AW18: 408.0501 | AX18: 408.0501 | AY18: 408.0501 | AZ18: 244.83006 | BA18: 408.0501 | BB18: 408.0501 | BC18: 408.0501 | BD18: 408.0501 | BE18: 326.44008 | BF18: 250.95081 | BG18: 418.25135 | BH18: 418.25135 | BI18: 418.25135 | BJ18: 418.25135 | BK18: 418.25135 | BL18: 250.95081 | BM18: 418.25135 | BN18: 418.25135 | BO18: 418.25135 | BP18: 418.25135 | BQ18: 334.60108
E19: Milano | G19: EUR | J19: 240 | K19: 400 | L19: 400 | M19: 400 | N19: 400 | O19: 400 | P19: 240 | Q19: 400 | R19: 400 | S19: 400 | T19: 400 | U19: 320 | V19: 241.2 | W19: 402 | X19: 402 | Y19: 402 | Z19: 402 | AA19: 402 | AB19: 241.2 | AC19: 402 | AD19: 402 | AE19: 402 | AF19: 402 | AG19: 321.6 | AH19: 242.406 | AI19: 404.01 | AJ19: 404.01 | AK19: 404.01 | AL19: 404.01 | AM19: 404.01 | AN19: 242.406 | AO19: 404.01 | AP19: 404.01 | AQ19: 404.01 | AR19: 404.01 | AS19: 323.208 | AT19: 244.83006 | AU19: 408.0501 | AV19: 408.0501 | AW19: 408.0501 | AX19: 408.0501 | AY19: 408.0501 | AZ19: 244.83006 | BA19: 408.0501 | BB19: 408.0501 | BC19: 408.0501 | BD19: 408.0501 | BE19: 326.44008 | BF19: 250.95081 | BG19: 418.25135 | BH19: 418.25135 | BI19: 418.25135 | BJ19: 418.25135 | BK19: 418.25135 | BL19: 250.95081 | BM19: 418.25135 | BN19: 418.25135 | BO19: 418.25135 | BP19: 418.25135 | BQ19: 334.60108
E20: Madrid | G20: EUR | J20: 240 | K20: 400 | L20: 400 | M20: 400 | N20: 400 | O20: 400 | P20: 240 | Q20: 400 | R20: 400 | S20: 400 | T20: 400 | U20: 320 | V20: 241.2 | W20: 402 | X20: 402 | Y20: 402 | Z20: 402 | AA20: 402 | AB20: 241.2 | AC20: 402 | AD20: 402 | AE20: 402 | AF20: 402 | AG20: 321.6 | AH20: 242.406 | AI20: 404.01 | AJ20: 404.01 | AK20: 404.01 | AL20: 404.01 | AM20: 404.01 | AN20: 242.406 | AO20: 404.01 | AP20: 404.01 | AQ20: 404.01 | AR20: 404.01 | AS20: 323.208 | AT20: 244.83006 | AU20: 408.0501 | AV20: 408.0501 | AW20: 408.0501 | AX20: 408.0501 | AY20: 408.0501 | AZ20: 244.83006 | BA20: 408.0501 | BB20: 408.0501 | BC20: 408.0501 | BD20: 408.0501 | BE20: 326.44008 | BF20: 250.95081 | BG20: 418.25135 | BH20: 418.25135 | BI20: 418.25135 | BJ20: 418.25135 | BK20: 418.25135 | BL20: 250.95081 | BM20: 418.25135 | BN20: 418.25135 | BO20: 418.25135 | BP20: 418.25135 | BQ20: 334.60108
E21: London | G21: GBP | J21: 210 | K21: 350 | L21: 350 | M21: 350 | N21: 350 | O21: 350 | P21: 210 | Q21: 350 | R21: 350 | S21: 350 | T21: 350 | U21: 280 | V21: 216.3 | W21: 360.5 | X21: 360.5 | Y21: 360.5 | Z21: 360.5 | AA21: 360.5 | AB21: 216.3 | AC21: 360.5 | AD21: 360.5 | AE21: 360.5 | AF21: 360.5 | AG21: 288.4 | AH21: 218.463 | AI21: 364.105 | AJ21: 364.105 | AK21: 364.105 | AL21: 364.105 | AM21: 364.105 | AN21: 218.463 | AO21: 364.105 | AP21: 364.105 | AQ21: 364.105 | AR21: 364.105 | AS21: 291.284 | AT21: 220.64763 | AU21: 367.74605 | AV21: 367.74605 | AW21: 367.74605 | AX21: 367.74605 | AY21: 367.74605 | AZ21: 220.64763 | BA21: 367.74605 | BB21: 367.74605 | BC21: 367.74605 | BD21: 367.74605 | BE21: 294.19684 | BF21: 222.85411 | BG21: 371.42351 | BH21: 371.42351 | BI21: 371.42351 | BJ21: 371.42351 | BK21: 371.42351 | BL21: 222.85411 | BM21: 371.42351 | BN21: 371.42351 | BO21: 371.42351 | BP21: 371.42351 | BQ21: 297.13881
E22: New York | G22: USD | J22: 0 | K22: 0 | L22: 0 | M22: 375 | N22: 375 | O22: 375 | P22: 225 | Q22: 375 | R22: 375 | S22: 375 | T22: 375 | U22: 300 | V22: 231.75 | W22: 386.25 | X22: 386.25 | Y22: 386.25 | Z22: 386.25 | AA22: 386.25 | AB22: 231.75 | AC22: 386.25 | AD22: 386.25 | AE22: 386.25 | AF22: 386.25 | AG22: 309 | AH22: 236.385 | AI22: 393.975 | AJ22: 393.975 | AK22: 393.975 | AL22: 393.975 | AM22: 393.975 | AN22: 236.385 | AO22: 393.975 | AP22: 393.975 | AQ22: 393.975 | AR22: 393.975 | AS22: 315.18 | AT22: 243.47655 | AU22: 405.79425 | AV22: 405.79425 | AW22: 405.79425 | AX22: 405.79425 | AY22: 405.79425 | AZ22: 243.47655 | BA22: 405.79425 | BB22: 405.79425 | BC22: 405.79425 | BD22: 405.79425 | BE22: 324.6354 | BF22: 244.69393 | BG22: 407.82322 | BH22: 407.82322 | BI22: 407.82322 | BJ22: 407.82322 | BK22: 407.82322 | BL22: 244.69393 | BM22: 407.82322 | BN22: 407.82322 | BO22: 407.82322 | BP22: 407.82322 | BQ22: 326.25858
E23: Montreal | G23: CAD | J23: 0 | K23: 0 | L23: 0 | M23: 0 | N23: 0 | O23: 0 | P23: 0 | Q23: 0 | R23: 0 | S23: 550 | T23: 550 | U23: 440 | V23: 336.6 | W23: 561 | X23: 561 | Y23: 561 | Z23: 561 | AA23: 561 | AB23: 336.6 | AC23: 561 | AD23: 561 | AE23: 561 | AF23: 561 | AG23: 448.8 | AH23: 343.332 | AI23: 572.22 | AJ23: 572.22 | AK23: 572.22 | AL23: 572.22 | AM23: 572.22 | AN23: 343.332 | AO23: 572.22 | AP23: 572.22 | AQ23: 572.22 | AR23: 572.22 | AS23: 457.776 | AT23: 351.9153 | AU23: 586.5255 | AV23: 586.5255 | AW23: 586.5255 | AX23: 586.5255 | AY23: 586.5255 | AZ23: 351.9153 | BA23: 586.5255 | BB23: 586.5255 | BC23: 586.5255 | BD23: 586.5255 | BE23: 469.2204 | BF23: 358.95361 | BG23: 598.25601 | BH23: 598.25601 | BI23: 598.25601 | BJ23: 598.25601 | BK23: 598.25601 | BL23: 358.95361 | BM23: 598.25601 | BN23: 598.25601 | BO23: 598.25601 | BP23: 598.25601 | BQ23: 478.60481
E24: Zurich | G24: CHF | J24: 0 | K24: 0 | L24: 0 | M24: 0 | N24: 0 | O24: 0 | P24: 0 | Q24: 0 | R24: 0 | S24: 0 | T24: 0 | U24: 0 | V24: 0 | W24: 0 | X24: 0 | Y24: 615 | Z24: 615 | AA24: 615 | AB24: 369 | AC24: 615 | AD24: 615 | AE24: 615 | AF24: 615 | AG24: 492 | AH24: 370.845 | AI24: 618.075 | AJ24: 618.075 | AK24: 618.075 | AL24: 618.075 | AM24: 618.075 | AN24: 370.845 | AO24: 618.075 | AP24: 618.075 | AQ24: 618.075 | AR24: 618.075 | AS24: 494.46 | AT24: 381.97035 | AU24: 636.61725 | AV24: 636.61725 | AW24: 636.61725 | AX24: 636.61725 | AY24: 636.61725 | AZ24: 381.97035 | BA24: 636.61725 | BB24: 636.61725 | BC24: 636.61725 | BD24: 636.61725 | BE24: 509.2938 | BF24: 387.69991 | BG24: 646.16651 | BH24: 646.16651 | BI24: 646.16651 | BJ24: 646.16651 | BK24: 646.16651 | BL24: 387.69991 | BM24: 646.16651 | BN24: 646.16651 | BO24: 646.16651 | BP24: 646.16651 | BQ24: 516.93321
E25: Moscow | G25: RUB | J25: 0 | K25: 0 | L25: 0 | M25: 0 | N25: 0 | O25: 0 | P25: 0 | Q25: 0 | R25: 0 | S25: 0 | T25: 0 | U25: 0 | V25: 0 | W25: 0 | X25: 0 | Y25: 0 | Z25: 0 | AA25: 0 | AB25: 0 | AC25: 0 | AD25: 0 | AE25: 40400 | AF25: 40400 | AG25: 32320 | AH25: 24482.4 | AI25: 40804 | AJ25: 40804 | AK25: 40804 | AL25: 40804 | AM25: 40804 | AN25: 24482.4 | AO25: 40804 | AP25: 40804 | AQ25: 40804 | AR25: 40804 | AS25: 32643.2 | AT25: 24849.636 | AU25: 41416.06 | AV25: 41416.06 | AW25: 41416.06 | AX25: 41416.06 | AY25: 41416.06 | AZ25: 24849.636 | BA25: 41416.06 | BB25: 41416.06 | BC25: 41416.06 | BD25: 41416.06 | BE25: 33132.848 | BF25: 25098.132 | BG25: 41830.221 | BH25: 41830.221 | BI25: 41830.221 | BJ25: 41830.221 | BK25: 41830.221 | BL25: 25098.132 | BM25: 41830.221 | BN25: 41830.221 | BO25: 41830.221 | BP25: 41830.221 | BQ25: 33464.176
D27: Accessories
E28: {=lstStores} -> Paris | G28: {=INDEX( CaseData!$C$9:$E$17, MATCH(_xlfn.ANCHORARRAY( Price!E28), CaseData!$C$9:$C$17, 0 ), 3 )} -> EUR | J28: {=_xlfn.LET( _xlpm.operating_flag,_xlfn.ANCHORARRAY( Time!$J$18), _xlpm.unit_prices_table, CaseData!$B$46:$E$52, _xlpm.currency_row, CaseData!$B$46:$B$52, _xlpm.apparel_column, CaseData!$B$46:$E$46, _xlpm.current_apparel, Price!$D27, _xlpm.store_currency,_xlfn.ANCHORARRAY( Price!$G28), _xlpm.unit_price_at_store, INDEX( _xlpm.unit_prices_table, _xlfn.XMATCH( _xlpm.store_currency, _xlpm.currency_row, 0, 1 ), _xlfn.XMATCH( _xlpm.current_apparel, _xlpm.apparel_column, 0, 1 ) ), _xlpm.discount_month, CaseData!$C$58:$C$69, _xlpm.discount_percentage, CaseData!$E$58:$E$69, _xlpm.current_month,_xlfn.ANCHORARRAY( Time!J$11), _xlpm.discount, 1 - _xlfn.XLOOKUP( _xlpm.current_month, _xlpm.discount_month, _xlpm.discount_percentage, 0, 0, 1 ), _xlpm.current_year, YEAR(_xlfn.ANCHORARRAY( Time!J$9) ), _xlpm.clean_rates, IF( CaseData!$C$86:$G$91 = "n.a.", 0, CaseData!$C$86:$G$91), _xlpm.compounded_rates, _xlfn.MAKEARRAY( ROWS( _xlpm.clean_rates ), COLUMNS( _xlpm.clean_rates ), _xlfn.LAMBDA(_xlpm.i,_xlpm.j, INDEX( _xlfn.SCAN( 1, INDEX( _xlpm.clean_rates, _xlpm.i, 0 ), _xlfn.LAMBDA(_xlpm.s,_xlpm.c, _xlpm.s * ( 1 + _xlpm.c ) ) ), _xlpm.j ) ) ), _xlpm.inflation_rows, CaseData!$B$86:$B$91, _xlpm.inflation_columns, CaseData!$B$85:$G$85, _xlpm.inflation_table, _xlfn.VSTACK( _xlpm.inflation_columns, _xlfn.HSTACK( _xlpm.inflation_rows, _xlpm.compounded_rates ) ), _xlpm.inflation, INDEX( _xlpm.inflation_table, _xlfn.XMATCH( _xlpm.store_currency, _xlpm.inflation_rows, 0 ) + 1, _xlfn.XMATCH( _xlpm.current_year, _xlpm.inflation_columns, 0 ) ), _xlpm.operating_flag * _xlpm.unit_price_at_store * _xlpm.discount * _xlpm.inflation)} -> 90 | K28: 150 | L28: 150 | M28: 150 | N28: 150 | O28: 150 | P28: 90 | Q28: 150 | R28: 150 | S28: 150 | T28: 150 | U28: 120 | V28: 90.45 | W28: 150.75 | X28: 150.75 | Y28: 150.75 | Z28: 150.75 | AA28: 150.75 | AB28: 90.45 | AC28: 150.75 | AD28: 150.75 | AE28: 150.75 | AF28: 150.75 | AG28: 120.6 | AH28: 90.90225 | AI28: 151.50375 | AJ28: 151.50375 | AK28: 151.50375 | AL28: 151.50375 | AM28: 151.50375 | AN28: 90.90225 | AO28: 151.50375 | AP28: 151.50375 | AQ28: 151.50375 | AR28: 151.50375 | AS28: 121.203 | AT28: 91.811272 | AU28: 153.01879 | AV28: 153.01879 | AW28: 153.01879 | AX28: 153.01879 | AY28: 153.01879 | AZ28: 91.811272 | BA28: 153.01879 | BB28: 153.01879 | BC28: 153.01879 | BD28: 153.01879 | BE28: 122.41503 | BF28: 94.106554 | BG28: 156.84426 | BH28: 156.84426 | BI28: 156.84426 | BJ28: 156.84426 | BK28: 156.84426 | BL28: 94.106554 | BM28: 156.84426 | BN28: 156.84426 | BO28: 156.84426 | BP28: 156.84426 | BQ28: 125.47541
E29: Milano | G29: EUR | J29: 90 | K29: 150 | L29: 150 | M29: 150 | N29: 150 | O29: 150 | P29: 90 | Q29: 150 | R29: 150 | S29: 150 | T29: 150 | U29: 120 | V29: 90.45 | W29: 150.75 | X29: 150.75 | Y29: 150.75 | Z29: 150.75 | AA29: 150.75 | AB29: 90.45 | AC29: 150.75 | AD29: 150.75 | AE29: 150.75 | AF29: 150.75 | AG29: 120.6 | AH29: 90.90225 | AI29: 151.50375 | AJ29: 151.50375 | AK29: 151.50375 | AL29: 151.50375 | AM29: 151.50375 | AN29: 90.90225 | AO29: 151.50375 | AP29: 151.50375 | AQ29: 151.50375 | AR29: 151.50375 | AS29: 121.203 | AT29: 91.811272 | AU29: 153.01879 | AV29: 153.01879 | AW29: 153.01879 | AX29: 153.01879 | AY29: 153.01879 | AZ29: 91.811272 | BA29: 153.01879 | BB29: 153.01879 | BC29: 153.01879 | BD29: 153.01879 | BE29: 122.41503 | BF29: 94.106554 | BG29: 156.84426 | BH29: 156.84426 | BI29: 156.84426 | BJ29: 156.84426 | BK29: 156.84426 | BL29: 94.106554 | BM29: 156.84426 | BN29: 156.84426 | BO29: 156.84426 | BP29: 156.84426 | BQ29: 125.47541
E30: Madrid | G30: EUR | J30: 90 | K30: 150 | L30: 150 | M30: 150 | N30: 150 | O30: 150 | P30: 90 | Q30: 150 | R30: 150 | S30: 150 | T30: 150 | U30: 120 | V30: 90.45 | W30: 150.75 | X30: 150.75 | Y30: 150.75 | Z30: 150.75 | AA30: 150.75 | AB30: 90.45 | AC30: 150.75 | AD30: 150.75 | AE30: 150.75 | AF30: 150.75 | AG30: 120.6 | AH30: 90.90225 | AI30: 151.50375 | AJ30: 151.50375 | AK30: 151.50375 | AL30: 151.50375 | AM30: 151.50375 | AN30: 90.90225 | AO30: 151.50375 | AP30: 151.50375 | AQ30: 151.50375 | AR30: 151.50375 | AS30: 121.203 | AT30: 91.811272 | AU30: 153.01879 | AV30: 153.01879 | AW30: 153.01879 | AX30: 153.01879 | AY30: 153.01879 | AZ30: 91.811272 | BA30: 153.01879 | BB30: 153.01879 | BC30: 153.01879 | BD30: 153.01879 | BE30: 122.41503 | BF30: 94.106554 | BG30: 156.84426 | BH30: 156.84426 | BI30: 156.84426 | BJ30: 156.84426 | BK30: 156.84426 | BL30: 94.106554 | BM30: 156.84426 | BN30: 156.84426 | BO30: 156.84426 | BP30: 156.84426 | BQ30: 125.47541
E31: London | G31: GBP | J31: 75 | K31: 125 | L31: 125 | M31: 125 | N31: 125 | O31: 125 | P31: 75 | Q31: 125 | R31: 125 | S31: 125 | T31: 125 | U31: 100 | V31: 77.25 | W31: 128.75 | X31: 128.75 | Y31: 128.75 | Z31: 128.75 | AA31: 128.75 | AB31: 77.25 | AC31: 128.75 | AD31: 128.75 | AE31: 128.75 | AF31: 128.75 | AG31: 103 | AH31: 78.0225 | AI31: 130.0375 | AJ31: 130.0375 | AK31: 130.0375 | AL31: 130.0375 | AM31: 130.0375 | AN31: 78.0225 | AO31: 130.0375 | AP31: 130.0375 | AQ31: 130.0375 | AR31: 130.0375 | AS31: 104.03 | AT31: 78.802725 | AU31: 131.33787 | AV31: 131.33787 | AW31: 131.33787 | AX31: 131.33787 | AY31: 131.33787 | AZ31: 78.802725 | BA31: 131.33787 | BB31: 131.33787 | BC31: 131.33787 | BD31: 131.33787 | BE31: 105.0703 | BF31: 79.590752 | BG31: 132.65125 | BH31: 132.65125 | BI31: 132.65125 | BJ31: 132.65125 | BK31: 132.65125 | BL31: 79.590752 | BM31: 132.65125 | BN31: 132.65125 | BO31: 132.65125 | BP31: 132.65125 | BQ31: 106.121
E32: New York | G32: USD | J32: 0 | K32: 0 | L32: 0 | M32: 150 | N32: 150 | O32: 150 | P32: 90 | Q32: 150 | R32: 150 | S32: 150 | T32: 150 | U32: 120 | V32: 92.7 | W32: 154.5 | X32: 154.5 | Y32: 154.5 | Z32: 154.5 | AA32: 154.5 | AB32: 92.7 | AC32: 154.5 | AD32: 154.5 | AE32: 154.5 | AF32: 154.5 | AG32: 123.6 | AH32: 94.554 | AI32: 157.59 | AJ32: 157.59 | AK32: 157.59 | AL32: 157.59 | AM32: 157.59 | AN32: 94.554 | AO32: 157.59 | AP32: 157.59 | AQ32: 157.59 | AR32: 157.59 | AS32: 126.072 | AT32: 97.39062 | AU32: 162.3177 | AV32: 162.3177 | AW32: 162.3177 | AX32: 162.3177 | AY32: 162.3177 | AZ32: 97.39062 | BA32: 162.3177 | BB32: 162.3177 | BC32: 162.3177 | BD32: 162.3177 | BE32: 129.85416 | BF32: 97.877573 | BG32: 163.12929 | BH32: 163.12929 | BI32: 163.12929 | BJ32: 163.12929 | BK32: 163.12929 | BL32: 97.877573 | BM32: 163.12929 | BN32: 163.12929 | BO32: 163.12929 | BP32: 163.12929 | BQ32: 130.50343
E33: Montreal | G33: CAD | J33: 0 | K33: 0 | L33: 0 | M33: 0 | N33: 0 | O33: 0 | P33: 0 | Q33: 0 | R33: 0 | S33: 200 | T33: 200 | U33: 160 | V33: 122.4 | W33: 204 | X33: 204 | Y33: 204 | Z33: 204 | AA33: 204 | AB33: 122.4 | AC33: 204 | AD33: 204 | AE33: 204 | AF33: 204 | AG33: 163.2 | AH33: 124.848 | AI33: 208.08 | AJ33: 208.08 | AK33: 208.08 | AL33: 208.08 | AM33: 208.08 | AN33: 124.848 | AO33: 208.08 | AP33: 208.08 | AQ33: 208.08 | AR33: 208.08 | AS33: 166.464 | AT33: 127.9692 | AU33: 213.282 | AV33: 213.282 | AW33: 213.282 | AX33: 213.282 | AY33: 213.282 | AZ33: 127.9692 | BA33: 213.282 | BB33: 213.282 | BC33: 213.282 | BD33: 213.282 | BE33: 170.6256 | BF33: 130.52858 | BG33: 217.54764 | BH33: 217.54764 | BI33: 217.54764 | BJ33: 217.54764 | BK33: 217.54764 | BL33: 130.52858 | BM33: 217.54764 | BN33: 217.54764 | BO33: 217.54764 | BP33: 217.54764 | BQ33: 174.03811
E34: Zurich | G34: CHF | J34: 0 | K34: 0 | L34: 0 | M34: 0 | N34: 0 | O34: 0 | P34: 0 | Q34: 0 | R34: 0 | S34: 0 | T34: 0 | U34: 0 | V34: 0 | W34: 0 | X34: 0 | Y34: 230.625 | Z34: 230.625 | AA34: 230.625 | AB34: 138.375 | AC34: 230.625 | AD34: 230.625 | AE34: 230.625 | AF34: 230.625 | AG34: 184.5 | AH34: 139.06687 | AI34: 231.77812 | AJ34: 231.77812 | AK34: 231.77812 | AL34: 231.77812 | AM34: 231.77812 | AN34: 139.06687 | AO34: 231.77812 | AP34: 231.77812 | AQ34: 231.77812 | AR34: 231.77812 | AS34: 185.4225 | AT34: 143.23888 | AU34: 238.73147 | AV34: 238.73147 | AW34: 238.73147 | AX34: 238.73147 | AY34: 238.73147 | AZ34: 143.23888 | BA34: 238.73147 | BB34: 238.73147 | BC34: 238.73147 | BD34: 238.73147 | BE34: 190.98517 | BF34: 145.38746 | BG34: 242.31244 | BH34: 242.31244 | BI34: 242.31244 | BJ34: 242.31244 | BK34: 242.31244 | BL34: 145.38746 | BM34: 242.31244 | BN34: 242.31244 | BO34: 242.31244 | BP34: 242.31244 | BQ34: 193.84995
E35: Moscow | G35: RUB | J35: 0 | K35: 0 | L35: 0 | M35: 0 | N35: 0 | O35: 0 | P35: 0 | Q35: 0 | R35: 0 | S35: 0 | T35: 0 | U35: 0 | V35: 0 | W35: 0 | X35: 0 | Y35: 0 | Z35: 0 | AA35: 0 | AB35: 0 | AC35: 0 | AD35: 0 | AE35: 15150 | AF35: 15150 | AG35: 12120 | AH35: 9180.9 | AI35: 15301.5 | AJ35: 15301.5 | AK35: 15301.5 | AL35: 15301.5 | AM35: 15301.5 | AN35: 9180.9 | AO35: 15301.5 | AP35: 15301.5 | AQ35: 15301.5 | AR35: 15301.5 | AS35: 12241.2 | AT35: 9318.6135 | AU35: 15531.022 | AV35: 15531.022 | AW35: 15531.022 | AX35: 15531.022 | AY35: 15531.022 | AZ35: 9318.6135 | BA35: 15531.022 | BB35: 15531.022 | BC35: 15531.022 | BD35: 15531.022 | BE35: 12424.818 | BF35: 9411.7996 | BG35: 15686.333 | BH35: 15686.333 | BI35: 15686.333 | BJ35: 15686.333 | BK35: 15686.333 | BL35: 9411.7996 | BM35: 15686.333 | BN35: 15686.333 | BO35: 15686.333 | BP35: 15686.333 | BQ35: 12549.066
A37: SECTION 6: AVERAGE PRICE IN CONSOLIDATION CURRENCY
D39: Women's
E40: {=lstStores} -> Paris | F40: {=INDEX( CaseData!$C$9:$E$17, MATCH(_xlfn.ANCHORARRAY( Price!E40), CaseData!$C$9:$C$17, 0 ), 3 )} -> EUR | G40: EUR | J40: {=_xlfn.LET( _xlpm.operating_flag,_xlfn.ANCHORARRAY( Time!J$18), _xlpm.fx_table, CaseData!$B$74:$G$80, _xlpm.fx_row, CaseData!$B$74:$B$80, _xlpm.fx_column, CaseData!$B$74:$G$74, _xlpm.store_currency,_xlfn.ANCHORARRAY( Price!$F40), _xlpm.current_year, YEAR(_xlfn.ANCHORARRAY( Time!J$9) ), _xlpm.fx_rate, INDEX( _xlpm.fx_table, _xlfn.XMATCH( _xlpm.store_currency, _xlpm.fx_row, 0, 1 ), _xlfn.XMATCH( _xlpm.current_year, _xlpm.fx_column, 0, 1 ) ), _xlpm.anchor,_xlfn.ANCHORARRAY( Price!$J8), _xlpm.block, OFFSET( _xlpm.anchor, 0, 0, COUNTA( _xlpm.store_currency ), periods ), _xlpm.block / _xlpm.fx_rate )} -> 300 | K40: 500 | L40: 500 | M40: 500 | N40: 500 | O40: 500 | P40: 300 | Q40: 500 | R40: 500 | S40: 500 | T40: 500 | U40: 400 | V40: 301.5 | W40: 502.5 | X40: 502.5 | Y40: 502.5 | Z40: 502.5 | AA40: 502.5 | AB40: 301.5 | AC40: 502.5 | AD40: 502.5 | AE40: 502.5 | AF40: 502.5 | AG40: 402 | AH40: 303.0075 | AI40: 505.0125 | AJ40: 505.0125 | AK40: 505.0125 | AL40: 505.0125 | AM40: 505.0125 | AN40: 303.0075 | AO40: 505.0125 | AP40: 505.0125 | AQ40: 505.0125 | AR40: 505.0125 | AS40: 404.01 | AT40: 306.03757 | AU40: 510.06262 | AV40: 510.06262 | AW40: 510.06262 | AX40: 510.06262 | AY40: 510.06262 | AZ40: 306.03757 | BA40: 510.06262 | BB40: 510.06262 | BC40: 510.06262 | BD40: 510.06262 | BE40: 408.0501 | BF40: 313.68851 | BG40: 522.81419 | BH40: 522.81419 | BI40: 522.81419 | BJ40: 522.81419 | BK40: 522.81419 | BL40: 313.68851 | BM40: 522.81419 | BN40: 522.81419 | BO40: 522.81419 | BP40: 522.81419 | BQ40: 418.25135
E41: Milano | F41: EUR | G41: EUR | J41: 300 | K41: 500 | L41: 500 | M41: 500 | N41: 500 | O41: 500 | P41: 300 | Q41: 500 | R41: 500 | S41: 500 | T41: 500 | U41: 400 | V41: 301.5 | W41: 502.5 | X41: 502.5 | Y41: 502.5 | Z41: 502.5 | AA41: 502.5 | AB41: 301.5 | AC41: 502.5 | AD41: 502.5 | AE41: 502.5 | AF41: 502.5 | AG41: 402 | AH41: 303.0075 | AI41: 505.0125 | AJ41: 505.0125 | AK41: 505.0125 | AL41: 505.0125 | AM41: 505.0125 | AN41: 303.0075 | AO41: 505.0125 | AP41: 505.0125 | AQ41: 505.0125 | AR41: 505.0125 | AS41: 404.01 | AT41: 306.03757 | AU41: 510.06262 | AV41: 510.06262 | AW41: 510.06262 | AX41: 510.06262 | AY41: 510.06262 | AZ41: 306.03757 | BA41: 510.06262 | BB41: 510.06262 | BC41: 510.06262 | BD41: 510.06262 | BE41: 408.0501 | BF41: 313.68851 | BG41: 522.81419 | BH41: 522.81419 | BI41: 522.81419 | BJ41: 522.81419 | BK41: 522.81419 | BL41: 313.68851 | BM41: 522.81419 | BN41: 522.81419 | BO41: 522.81419 | BP41: 522.81419 | BQ41: 418.25135
E42: Madrid | F42: EUR | G42: EUR | J42: 300 | K42: 500 | L42: 500 | M42: 500 | N42: 500 | O42: 500 | P42: 300 | Q42: 500 | R42: 500 | S42: 500 | T42: 500 | U42: 400 | V42: 301.5 | W42: 502.5 | X42: 502.5 | Y42: 502.5 | Z42: 502.5 | AA42: 502.5 | AB42: 301.5 | AC42: 502.5 | AD42: 502.5 | AE42: 502.5 | AF42: 502.5 | AG42: 402 | AH42: 303.0075 | AI42: 505.0125 | AJ42: 505.0125 | AK42: 505.0125 | AL42: 505.0125 | AM42: 505.0125 | AN42: 303.0075 | AO42: 505.0125 | AP42: 505.0125 | AQ42: 505.0125 | AR42: 505.0125 | AS42: 404.01 | AT42: 306.03757 | AU42: 510.06262 | AV42: 510.06262 | AW42: 510.06262 | AX42: 510.06262 | AY42: 510.06262 | AZ42: 306.03757 | BA42: 510.06262 | BB42: 510.06262 | BC42: 510.06262 | BD42: 510.06262 | BE42: 408.0501 | BF42: 313.68851 | BG42: 522.81419 | BH42: 522.81419 | BI42: 522.81419 | BJ42: 522.81419 | BK42: 522.81419 | BL42: 313.68851 | BM42: 522.81419 | BN42: 522.81419 | BO42: 522.81419 | BP42: 522.81419 | BQ42: 418.25135
E43: London | F43: GBP | G43: EUR | J43: 296.51163 | K43: 494.18605 | L43: 494.18605 | M43: 494.18605 | N43: 494.18605 | O43: 494.18605 | P43: 296.51163 | Q43: 494.18605 | R43: 494.18605 | S43: 494.18605 | T43: 494.18605 | U43: 395.34884 | V43: 301.89655 | W43: 503.16092 | X43: 503.16092 | Y43: 503.16092 | Z43: 503.16092 | AA43: 503.16092 | AB43: 301.89655 | AC43: 503.16092 | AD43: 503.16092 | AE43: 503.16092 | AF43: 503.16092 | AG43: 402.52874 | AH43: 301.45057 | AI43: 502.41761 | AJ43: 502.41761 | AK43: 502.41761 | AL43: 502.41761 | AM43: 502.41761 | AN43: 301.45057 | AO43: 502.41761 | AP43: 502.41761 | AQ43: 502.41761 | AR43: 502.41761 | AS43: 401.93409 | AT43: 301.04412 | AU43: 501.7402 | AV43: 501.7402 | AW43: 501.7402 | AX43: 501.7402 | AY43: 501.7402 | AZ43: 301.04412 | BA43: 501.7402 | BB43: 501.7402 | BC43: 501.7402 | BD43: 501.7402 | BE43: 401.39216 | BF43: 300.67618 | BG43: 501.12696 | BH43: 501.12696 | BI43: 501.12696 | BJ43: 501.12696 | BK43: 501.12696 | BL43: 300.67618 | BM43: 501.12696 | BN43: 501.12696 | BO43: 501.12696 | BP43: 501.12696 | BQ43: 400.90157
E44: New York | F44: USD | G44: EUR | J44: 0 | K44: 0 | L44: 0 | M44: 431.81818 | N44: 431.81818 | O44: 431.81818 | P44: 259.09091 | Q44: 431.81818 | R44: 431.81818 | S44: 431.81818 | T44: 431.81818 | U44: 345.45455 | V44: 264.45946 | W44: 440.76577 | X44: 440.76577 | Y44: 440.76577 | Z44: 440.76577 | AA44: 440.76577 | AB44: 264.45946 | AC44: 440.76577 | AD44: 440.76577 | AE44: 440.76577 | AF44: 440.76577 | AG44: 352.61261 | AH44: 267.34018 | AI44: 445.56696 | AJ44: 445.56696 | AK44: 445.56696 | AL44: 445.56696 | AM44: 445.56696 | AN44: 267.34018 | AO44: 445.56696 | AP44: 445.56696 | AQ44: 445.56696 | AR44: 445.56696 | AS44: 356.45357 | AT44: 272.92357 | AU44: 454.87261 | AV44: 454.87261 | AW44: 454.87261 | AX44: 454.87261 | AY44: 454.87261 | AZ44: 272.92357 | BA44: 454.87261 | BB44: 454.87261 | BC44: 454.87261 | BD44: 454.87261 | BE44: 363.89809 | BF44: 271.88215 | BG44: 453.13691 | BH44: 453.13691 | BI44: 453.13691 | BJ44: 453.13691 | BK44: 453.13691 | BL44: 271.88215 | BM44: 453.13691 | BN44: 453.13691 | BO44: 453.13691 | BP44: 453.13691 | BQ44: 362.50953
E45: Montreal | F45: CAD | G45: EUR | J45: 0 | K45: 0 | L45: 0 | M45: 0 | N45: 0 | O45: 0 | P45: 0 | Q45: 0 | R45: 0 | S45: 469.79866 | T45: 469.79866 | U45: 375.83893 | V45: 285.6 | W45: 476 | X45: 476 | Y45: 476 | Z45: 476 | AA45: 476 | AB45: 285.6 | AC45: 476 | AD45: 476 | AE45: 476 | AF45: 476 | AG45: 380.8 | AH45: 289.38278 | AI45: 482.30464 | AJ45: 482.30464 | AK45: 482.30464 | AL45: 482.30464 | AM45: 482.30464 | AN45: 289.38278 | AO45: 482.30464 | AP45: 482.30464 | AQ45: 482.30464 | AR45: 482.30464 | AS45: 385.84371 | AT45: 294.66592 | AU45: 491.10987 | AV45: 491.10987 | AW45: 491.10987 | AX45: 491.10987 | AY45: 491.10987 | AZ45: 294.66592 | BA45: 491.10987 | BB45: 491.10987 | BC45: 491.10987 | BD45: 491.10987 | BE45: 392.88789 | BF45: 298.5948 | BG45: 497.658 | BH45: 497.658 | BI45: 497.658 | BJ45: 497.658 | BK45: 497.658 | BL45: 298.5948 | BM45: 497.658 | BN45: 497.658 | BO45: 497.658 | BP45: 497.658 | BQ45: 398.1264
E46: Zurich | F46: CHF | G46: EUR | J46: 0 | K46: 0 | L46: 0 | M46: 0 | N46: 0 | O46: 0 | P46: 0 | Q46: 0 | R46: 0 | S46: 0 | T46: 0 | U46: 0 | V46: 0 | W46: 0 | X46: 0 | Y46: 718.45794 | Z46: 718.45794 | AA46: 718.45794 | AB46: 431.07477 | AC46: 718.45794 | AD46: 718.45794 | AE46: 718.45794 | AF46: 718.45794 | AG46: 574.76636 | AH46: 429.21875 | AI46: 715.36458 | AJ46: 715.36458 | AK46: 715.36458 | AL46: 715.36458 | AM46: 715.36458 | AN46: 429.21875 | AO46: 715.36458 | AP46: 715.36458 | AQ46: 715.36458 | AR46: 715.36458 | AS46: 572.29167 | AT46: 438.03939 | AU46: 730.06565 | AV46: 730.06565 | AW46: 730.06565 | AX46: 730.06565 | AY46: 730.06565 | AZ46: 438.03939 | BA46: 730.06565 | BB46: 730.06565 | BC46: 730.06565 | BD46: 730.06565 | BE46: 584.05252 | BF46: 440.56807 | BG46: 734.28012 | BH46: 734.28012 | BI46: 734.28012 | BJ46: 734.28012 | BK46: 734.28012 | BL46: 440.56807 | BM46: 734.28012 | BN46: 734.28012 | BO46: 734.28012 | BP46: 734.28012 | BQ46: 587.4241
E47: Moscow | F47: RUB | G47: EUR | J47: 0 | K47: 0 | L47: 0 | M47: 0 | N47: 0 | O47: 0 | P47: 0 | Q47: 0 | R47: 0 | S47: 0 | T47: 0 | U47: 0 | V47: 0 | W47: 0 | X47: 0 | Y47: 0 | Z47: 0 | AA47: 0 | AB47: 0 | AC47: 0 | AD47: 0 | AE47: 750.67568 | AF47: 750.67568 | AG47: 600.54054 | AH47: 448.844 | AI47: 748.07333 | AJ47: 748.07333 | AK47: 748.07333 | AL47: 748.07333 | AM47: 748.07333 | AN47: 448.844 | AO47: 748.07333 | AP47: 748.07333 | AQ47: 748.07333 | AR47: 748.07333 | AS47: 598.45867 | AT47: 449.58223 | AU47: 749.30372 | AV47: 749.30372 | AW47: 749.30372 | AX47: 749.30372 | AY47: 749.30372 | AZ47: 449.58223 | BA47: 749.30372 | BB47: 749.30372 | BC47: 749.30372 | BD47: 749.30372 | BE47: 599.44297 | BF47: 448.18093 | BG47: 746.96822 | BH47: 746.96822 | BI47: 746.96822 | BJ47: 746.96822 | BK47: 746.96822 | BL47: 448.18093 | BM47: 746.96822 | BN47: 746.96822 | BO47: 746.96822 | BP47: 746.96822 | BQ47: 597.57458
D49: Men's
E50: {=lstStores} -> Paris | F50: {=INDEX( CaseData!$C$9:$E$17, MATCH(_xlfn.ANCHORARRAY( Price!E50), CaseData!$C$9:$C$17, 0 ), 3 )} -> EUR | G50: EUR | J50: {=_xlfn.LET( _xlpm.operating_flag,_xlfn.ANCHORARRAY( Time!J$18), _xlpm.fx_table, CaseData!$B$74:$G$80, _xlpm.fx_row, CaseData!$B$74:$B$80, _xlpm.fx_column, CaseData!$B$74:$G$74, _xlpm.store_currency,_xlfn.ANCHORARRAY( Price!$F50), _xlpm.current_year, YEAR(_xlfn.ANCHORARRAY( Time!J$9) ), _xlpm.fx_rate, INDEX( _xlpm.fx_table, _xlfn.XMATCH( _xlpm.store_currency, _xlpm.fx_row, 0, 1 ), _xlfn.XMATCH( _xlpm.current_year, _xlpm.fx_column, 0, 1 ) ), _xlpm.anchor,_xlfn.ANCHORARRAY( Price!$J18), _xlpm.block, OFFSET( _xlpm.anchor, 0, 0, COUNTA( _xlpm.store_currency ), periods ), _xlpm.block / _xlpm.fx_rate )} -> 240 | K50: 400 | L50: 400 | M50: 400 | N50: 400 | O50: 400 | P50: 240 | Q50: 400 | R50: 400 | S50: 400 | T50: 400 | U50: 320 | V50: 241.2 | W50: 402 | X50: 402 | Y50: 402 | Z50: 402 | AA50: 402 | AB50: 241.2 | AC50: 402 | AD50: 402 | AE50: 402 | AF50: 402 | AG50: 321.6 | AH50: 242.406 | AI50: 404.01 | AJ50: 404.01 | AK50: 404.01 | AL50: 404.01 | AM50: 404.01 | AN50: 242.406 | AO50: 404.01 | AP50: 404.01 | AQ50: 404.01 | AR50: 404.01 | AS50: 323.208 | AT50: 244.83006 | AU50: 408.0501 | AV50: 408.0501 | AW50: 408.0501 | AX50: 408.0501 | AY50: 408.0501 | AZ50: 244.83006 | BA50: 408.0501 | BB50: 408.0501 | BC50: 408.0501 | BD50: 408.0501 | BE50: 326.44008 | BF50: 250.95081 | BG50: 418.25135 | BH50: 418.25135 | BI50: 418.25135 | BJ50: 418.25135 | BK50: 418.25135 | BL50: 250.95081 | BM50: 418.25135 | BN50: 418.25135 | BO50: 418.25135 | BP50: 418.25135 | BQ50: 334.60108
E51: Milano | F51: EUR | G51: EUR | J51: 240 | K51: 400 | L51: 400 | M51: 400 | N51: 400 | O51: 400 | P51: 240 | Q51: 400 | R51: 400 | S51: 400 | T51: 400 | U51: 320 | V51: 241.2 | W51: 402 | X51: 402 | Y51: 402 | Z51: 402 | AA51: 402 | AB51: 241.2 | AC51: 402 | AD51: 402 | AE51: 402 | AF51: 402 | AG51: 321.6 | AH51: 242.406 | AI51: 404.01 | AJ51: 404.01 | AK51: 404.01 | AL51: 404.01 | AM51: 404.01 | AN51: 242.406 | AO51: 404.01 | AP51: 404.01 | AQ51: 404.01 | AR51: 404.01 | AS51: 323.208 | AT51: 244.83006 | AU51: 408.0501 | AV51: 408.0501 | AW51: 408.0501 | AX51: 408.0501 | AY51: 408.0501 | AZ51: 244.83006 | BA51: 408.0501 | BB51: 408.0501 | BC51: 408.0501 | BD51: 408.0501 | BE51: 326.44008 | BF51: 250.95081 | BG51: 418.25135 | BH51: 418.25135 | BI51: 418.25135 | BJ51: 418.25135 | BK51: 418.25135 | BL51: 250.95081 | BM51: 418.25135 | BN51: 418.25135 | BO51: 418.25135 | BP51: 418.25135 | BQ51: 334.60108
E52: Madrid | F52: EUR | G52: EUR | J52: 240 | K52: 400 | L52: 400 | M52: 400 | N52: 400 | O52: 400 | P52: 240 | Q52: 400 | R52: 400 | S52: 400 | T52: 400 | U52: 320 | V52: 241.2 | W52: 402 | X52: 402 | Y52: 402 | Z52: 402 | AA52: 402 | AB52: 241.2 | AC52: 402 | AD52: 402 | AE52: 402 | AF52: 402 | AG52: 321.6 | AH52: 242.406 | AI52: 404.01 | AJ52: 404.01 | AK52: 404.01 | AL52: 404.01 | AM52: 404.01 | AN52: 242.406 | AO52: 404.01 | AP52: 404.01 | AQ52: 404.01 | AR52: 404.01 | AS52: 323.208 | AT52: 244.83006 | AU52: 408.0501 | AV52: 408.0501 | AW52: 408.0501 | AX52: 408.0501 | AY52: 408.0501 | AZ52: 244.83006 | BA52: 408.0501 | BB52: 408.0501 | BC52: 408.0501 | BD52: 408.0501 | BE52: 326.44008 | BF52: 250.95081 | BG52: 418.25135 | BH52: 418.25135 | BI52: 418.25135 | BJ52: 418.25135 | BK52: 418.25135 | BL52: 250.95081 | BM52: 418.25135 | BN52: 418.25135 | BO52: 418.25135 | BP52: 418.25135 | BQ52: 334.60108
E53: London | F53: GBP | G53: EUR | J53: 244.18605 | K53: 406.97674 | L53: 406.97674 | M53: 406.97674 | N53: 406.97674 | O53: 406.97674 | P53: 244.18605 | Q53: 406.97674 | R53: 406.97674 | S53: 406.97674 | T53: 406.97674 | U53: 325.5814 | V53: 248.62069 | W53: 414.36782 | X53: 414.36782 | Y53: 414.36782 | Z53: 414.36782 | AA53: 414.36782 | AB53: 248.62069 | AC53: 414.36782 | AD53: 414.36782 | AE53: 414.36782 | AF53: 414.36782 | AG53: 331.49425 | AH53: 248.25341 | AI53: 413.75568 | AJ53: 413.75568 | AK53: 413.75568 | AL53: 413.75568 | AM53: 413.75568 | AN53: 248.25341 | AO53: 413.75568 | AP53: 413.75568 | AQ53: 413.75568 | AR53: 413.75568 | AS53: 331.00455 | AT53: 247.91869 | AU53: 413.19781 | AV53: 413.19781 | AW53: 413.19781 | AX53: 413.19781 | AY53: 413.19781 | AZ53: 247.91869 | BA53: 413.19781 | BB53: 413.19781 | BC53: 413.19781 | BD53: 413.19781 | BE53: 330.55825 | BF53: 247.61567 | BG53: 412.69279 | BH53: 412.69279 | BI53: 412.69279 | BJ53: 412.69279 | BK53: 412.69279 | BL53: 247.61567 | BM53: 412.69279 | BN53: 412.69279 | BO53: 412.69279 | BP53: 412.69279 | BQ53: 330.15423
E54: New York | F54: USD | G54: EUR | J54: 0 | K54: 0 | L54: 0 | M54: 340.90909 | N54: 340.90909 | O54: 340.90909 | P54: 204.54545 | Q54: 340.90909 | R54: 340.90909 | S54: 340.90909 | T54: 340.90909 | U54: 272.72727 | V54: 208.78378 | W54: 347.97297 | X54: 347.97297 | Y54: 347.97297 | Z54: 347.97297 | AA54: 347.97297 | AB54: 208.78378 | AC54: 347.97297 | AD54: 347.97297 | AE54: 347.97297 | AF54: 347.97297 | AG54: 278.37838 | AH54: 211.05804 | AI54: 351.76339 | AJ54: 351.76339 | AK54: 351.76339 | AL54: 351.76339 | AM54: 351.76339 | AN54: 211.05804 | AO54: 351.76339 | AP54: 351.76339 | AQ54: 351.76339 | AR54: 351.76339 | AS54: 281.41071 | AT54: 215.46597 | AU54: 359.10996 | AV54: 359.10996 | AW54: 359.10996 | AX54: 359.10996 | AY54: 359.10996 | AZ54: 215.46597 | BA54: 359.10996 | BB54: 359.10996 | BC54: 359.10996 | BD54: 359.10996 | BE54: 287.28796 | BF54: 214.6438 | BG54: 357.73967 | BH54: 357.73967 | BI54: 357.73967 | BJ54: 357.73967 | BK54: 357.73967 | BL54: 214.6438 | BM54: 357.73967 | BN54: 357.73967 | BO54: 357.73967 | BP54: 357.73967 | BQ54: 286.19173
E55: Montreal | F55: CAD | G55: EUR | J55: 0 | K55: 0 | L55: 0 | M55: 0 | N55: 0 | O55: 0 | P55: 0 | Q55: 0 | R55: 0 | S55: 369.12752 | T55: 369.12752 | U55: 295.30201 | V55: 224.4 | W55: 374 | X55: 374 | Y55: 374 | Z55: 374 | AA55: 374 | AB55: 224.4 | AC55: 374 | AD55: 374 | AE55: 374 | AF55: 374 | AG55: 299.2 | AH55: 227.37219 | AI55: 378.95364 | AJ55: 378.95364 | AK55: 378.95364 | AL55: 378.95364 | AM55: 378.95364 | AN55: 227.37219 | AO55: 378.95364 | AP55: 378.95364 | AQ55: 378.95364 | AR55: 378.95364 | AS55: 303.16291 | AT55: 231.52322 | AU55: 385.87204 | AV55: 385.87204 | AW55: 385.87204 | AX55: 385.87204 | AY55: 385.87204 | AZ55: 231.52322 | BA55: 385.87204 | BB55: 385.87204 | BC55: 385.87204 | BD55: 385.87204 | BE55: 308.69763 | BF55: 234.6102 | BG55: 391.017 | BH55: 391.017 | BI55: 391.017 | BJ55: 391.017 | BK55: 391.017 | BL55: 234.6102 | BM55: 391.017 | BN55: 391.017 | BO55: 391.017 | BP55: 391.017 | BQ55: 312.8136
E56: Zurich | F56: CHF | G56: EUR | J56: 0 | K56: 0 | L56: 0 | M56: 0 | N56: 0 | O56: 0 | P56: 0 | Q56: 0 | R56: 0 | S56: 0 | T56: 0 | U56: 0 | V56: 0 | W56: 0 | X56: 0 | Y56: 574.76636 | Z56: 574.76636 | AA56: 574.76636 | AB56: 344.85981 | AC56: 574.76636 | AD56: 574.76636 | AE56: 574.76636 | AF56: 574.76636 | AG56: 459.81308 | AH56: 343.375 | AI56: 572.29167 | AJ56: 572.29167 | AK56: 572.29167 | AL56: 572.29167 | AM56: 572.29167 | AN56: 343.375 | AO56: 572.29167 | AP56: 572.29167 | AQ56: 572.29167 | AR56: 572.29167 | AS56: 457.83333 | AT56: 350.43151 | AU56: 584.05252 | AV56: 584.05252 | AW56: 584.05252 | AX56: 584.05252 | AY56: 584.05252 | AZ56: 350.43151 | BA56: 584.05252 | BB56: 584.05252 | BC56: 584.05252 | BD56: 584.05252 | BE56: 467.24202 | BF56: 352.45446 | BG56: 587.4241 | BH56: 587.4241 | BI56: 587.4241 | BJ56: 587.4241 | BK56: 587.4241 | BL56: 352.45446 | BM56: 587.4241 | BN56: 587.4241 | BO56: 587.4241 | BP56: 587.4241 | BQ56: 469.93928
E57: Moscow | F57: RUB | G57: EUR | J57: 0 | K57: 0 | L57: 0 | M57: 0 | N57: 0 | O57: 0 | P57: 0 | Q57: 0 | R57: 0 | S57: 0 | T57: 0 | U57: 0 | V57: 0 | W57: 0 | X57: 0 | Y57: 0 | Z57: 0 | AA57: 0 | AB57: 0 | AC57: 0 | AD57: 0 | AE57: 545.94595 | AF57: 545.94595 | AG57: 436.75676 | AH57: 326.432 | AI57: 544.05333 | AJ57: 544.05333 | AK57: 544.05333 | AL57: 544.05333 | AM57: 544.05333 | AN57: 326.432 | AO57: 544.05333 | AP57: 544.05333 | AQ57: 544.05333 | AR57: 544.05333 | AS57: 435.24267 | AT57: 326.96889 | AU57: 544.94816 | AV57: 544.94816 | AW57: 544.94816 | AX57: 544.94816 | AY57: 544.94816 | AZ57: 326.96889 | BA57: 544.94816 | BB57: 544.94816 | BC57: 544.94816 | BD57: 544.94816 | BE57: 435.95853 | BF57: 325.94977 | BG57: 543.24962 | BH57: 543.24962 | BI57: 543.24962 | BJ57: 543.24962 | BK57: 543.24962 | BL57: 325.94977 | BM57: 543.24962 | BN57: 543.24962 | BO57: 543.24962 | BP57: 543.24962 | BQ57: 434.59969
D59: Accessories
E60: {=lstStores} -> Paris | F60: {=INDEX( CaseData!$C$9:$E$17, MATCH(_xlfn.ANCHORARRAY( Price!E60), CaseData!$C$9:$C$17, 0 ), 3 )} -> EUR | G60: EUR | J60: {=_xlfn.LET( _xlpm.operating_flag,_xlfn.ANCHORARRAY( Time!J$18), _xlpm.fx_table, CaseData!$B$74:$G$80, _xlpm.fx_row, CaseData!$B$74:$B$80, _xlpm.fx_column, CaseData!$B$74:$G$74, _xlpm.store_currency,_xlfn.ANCHORARRAY( Price!$F60), _xlpm.current_year, YEAR(_xlfn.ANCHORARRAY( Time!J$9) ), _xlpm.fx_rate, INDEX( _xlpm.fx_table, _xlfn.XMATCH( _xlpm.store_currency, _xlpm.fx_row, 0, 1 ), _xlfn.XMATCH( _xlpm.current_year, _xlpm.fx_column, 0, 1 ) ), _xlpm.anchor,_xlfn.ANCHORARRAY( Price!$J28), _xlpm.block, OFFSET( _xlpm.anchor, 0, 0, COUNTA( _xlpm.store_currency ), periods ), _xlpm.block / _xlpm.fx_rate )} -> 90 | K60: 150 | L60: 150 | M60: 150 | N60: 150 | O60: 150 | P60: 90 | Q60: 150 | R60: 150 | S60: 150 | T60: 150 | U60: 120 | V60: 90.45 | W60: 150.75 | X60: 150.75 | Y60: 150.75 | Z60: 150.75 | AA60: 150.75 | AB60: 90.45 | AC60: 150.75 | AD60: 150.75 | AE60: 150.75 | AF60: 150.75 | AG60: 120.6 | AH60: 90.90225 | AI60: 151.50375 | AJ60: 151.50375 | AK60: 151.50375 | AL60: 151.50375 | AM60: 151.50375 | AN60: 90.90225 | AO60: 151.50375 | AP60: 151.50375 | AQ60: 151.50375 | AR60: 151.50375 | AS60: 121.203 | AT60: 91.811272 | AU60: 153.01879 | AV60: 153.01879 | AW60: 153.01879 | AX60: 153.01879 | AY60: 153.01879 | AZ60: 91.811272 | BA60: 153.01879 | BB60: 153.01879 | BC60: 153.01879 | BD60: 153.01879 | BE60: 122.41503 | BF60: 94.106554 | BG60: 156.84426 | BH60: 156.84426 | BI60: 156.84426 | BJ60: 156.84426 | BK60: 156.84426 | BL60: 94.106554 | BM60: 156.84426 | BN60: 156.84426 | BO60: 156.84426 | BP60: 156.84426 | BQ60: 125.47541
E61: Milano | F61: EUR | G61: EUR | J61: 90 | K61: 150 | L61: 150 | M61: 150 | N61: 150 | O61: 150 | P61: 90 | Q61: 150 | R61: 150 | S61: 150 | T61: 150 | U61: 120 | V61: 90.45 | W61: 150.75 | X61: 150.75 | Y61: 150.75 | Z61: 150.75 | AA61: 150.75 | AB61: 90.45 | AC61: 150.75 | AD61: 150.75 | AE61: 150.75 | AF61: 150.75 | AG61: 120.6 | AH61: 90.90225 | AI61: 151.50375 | AJ61: 151.50375 | AK61: 151.50375 | AL61: 151.50375 | AM61: 151.50375 | AN61: 90.90225 | AO61: 151.50375 | AP61: 151.50375 | AQ61: 151.50375 | AR61: 151.50375 | AS61: 121.203 | AT61: 91.811272 | AU61: 153.01879 | AV61: 153.01879 | AW61: 153.01879 | AX61: 153.01879 | AY61: 153.01879 | AZ61: 91.811272 | BA61: 153.01879 | BB61: 153.01879 | BC61: 153.01879 | BD61: 153.01879 | BE61: 122.41503 | BF61: 94.106554 | BG61: 156.84426 | BH61: 156.84426 | BI61: 156.84426 | BJ61: 156.84426 | BK61: 156.84426 | BL61: 94.106554 | BM61: 156.84426 | BN61: 156.84426 | BO61: 156.84426 | BP61: 156.84426 | BQ61: 125.47541
E62: Madrid | F62: EUR | G62: EUR | J62: 90 | K62: 150 | L62: 150 | M62: 150 | N62: 150 | O62: 150 | P62: 90 | Q62: 150 | R62: 150 | S62: 150 | T62: 150 | U62: 120 | V62: 90.45 | W62: 150.75 | X62: 150.75 | Y62: 150.75 | Z62: 150.75 | AA62: 150.75 | AB62: 90.45 | AC62: 150.75 | AD62: 150.75 | AE62: 150.75 | AF62: 150.75 | AG62: 120.6 | AH62: 90.90225 | AI62: 151.50375 | AJ62: 151.50375 | AK62: 151.50375 | AL62: 151.50375 | AM62: 151.50375 | AN62: 90.90225 | AO62: 151.50375 | AP62: 151.50375 | AQ62: 151.50375 | AR62: 151.50375 | AS62: 121.203 | AT62: 91.811272 | AU62: 153.01879 | AV62: 153.01879 | AW62: 153.01879 | AX62: 153.01879 | AY62: 153.01879 | AZ62: 91.811272 | BA62: 153.01879 | BB62: 153.01879 | BC62: 153.01879 | BD62: 153.01879 | BE62: 122.41503 | BF62: 94.106554 | BG62: 156.84426 | BH62: 156.84426 | BI62: 156.84426 | BJ62: 156.84426 | BK62: 156.84426 | BL62: 94.106554 | BM62: 156.84426 | BN62: 156.84426 | BO62: 156.84426 | BP62: 156.84426 | BQ62: 125.47541
E63: London | F63: GBP | G63: EUR | J63: 87.209302 | K63: 145.34884 | L63: 145.34884 | M63: 145.34884 | N63: 145.34884 | O63: 145.34884 | P63: 87.209302 | Q63: 145.34884 | R63: 145.34884 | S63: 145.34884 | T63: 145.34884 | U63: 116.27907 | V63: 88.793103 | W63: 147.98851 | X63: 147.98851 | Y63: 147.98851 | Z63: 147.98851 | AA63: 147.98851 | AB63: 88.793103 | AC63: 147.98851 | AD63: 147.98851 | AE63: 147.98851 | AF63: 147.98851 | AG63: 118.3908 | AH63: 88.661932 | AI63: 147.76989 | AJ63: 147.76989 | AK63: 147.76989 | AL63: 147.76989 | AM63: 147.76989 | AN63: 88.661932 | AO63: 147.76989 | AP63: 147.76989 | AQ63: 147.76989 | AR63: 147.76989 | AS63: 118.21591 | AT63: 88.542388 | AU63: 147.57065 | AV63: 147.57065 | AW63: 147.57065 | AX63: 147.57065 | AY63: 147.57065 | AZ63: 88.542388 | BA63: 147.57065 | BB63: 147.57065 | BC63: 147.57065 | BD63: 147.57065 | BE63: 118.05652 | BF63: 88.434169 | BG63: 147.39028 | BH63: 147.39028 | BI63: 147.39028 | BJ63: 147.39028 | BK63: 147.39028 | BL63: 88.434169 | BM63: 147.39028 | BN63: 147.39028 | BO63: 147.39028 | BP63: 147.39028 | BQ63: 117.91223
E64: New York | F64: USD | G64: EUR | J64: 0 | K64: 0 | L64: 0 | M64: 136.36364 | N64: 136.36364 | O64: 136.36364 | P64: 81.818182 | Q64: 136.36364 | R64: 136.36364 | S64: 136.36364 | T64: 136.36364 | U64: 109.09091 | V64: 83.513514 | W64: 139.18919 | X64: 139.18919 | Y64: 139.18919 | Z64: 139.18919 | AA64: 139.18919 | AB64: 83.513514 | AC64: 139.18919 | AD64: 139.18919 | AE64: 139.18919 | AF64: 139.18919 | AG64: 111.35135 | AH64: 84.423214 | AI64: 140.70536 | AJ64: 140.70536 | AK64: 140.70536 | AL64: 140.70536 | AM64: 140.70536 | AN64: 84.423214 | AO64: 140.70536 | AP64: 140.70536 | AQ64: 140.70536 | AR64: 140.70536 | AS64: 112.56429 | AT64: 86.186389 | AU64: 143.64398 | AV64: 143.64398 | AW64: 143.64398 | AX64: 143.64398 | AY64: 143.64398 | AZ64: 86.186389 | BA64: 143.64398 | BB64: 143.64398 | BC64: 143.64398 | BD64: 143.64398 | BE64: 114.91519 | BF64: 85.85752 | BG64: 143.09587 | BH64: 143.09587 | BI64: 143.09587 | BJ64: 143.09587 | BK64: 143.09587 | BL64: 85.85752 | BM64: 143.09587 | BN64: 143.09587 | BO64: 143.09587 | BP64: 143.09587 | BQ64: 114.47669
E65: Montreal | F65: CAD | G65: EUR | J65: 0 | K65: 0 | L65: 0 | M65: 0 | N65: 0 | O65: 0 | P65: 0 | Q65: 0 | R65: 0 | S65: 134.22819 | T65: 134.22819 | U65: 107.38255 | V65: 81.6 | W65: 136 | X65: 136 | Y65: 136 | Z65: 136 | AA65: 136 | AB65: 81.6 | AC65: 136 | AD65: 136 | AE65: 136 | AF65: 136 | AG65: 108.8 | AH65: 82.680795 | AI65: 137.80132 | AJ65: 137.80132 | AK65: 137.80132 | AL65: 137.80132 | AM65: 137.80132 | AN65: 82.680795 | AO65: 137.80132 | AP65: 137.80132 | AQ65: 137.80132 | AR65: 137.80132 | AS65: 110.24106 | AT65: 84.190263 | AU65: 140.31711 | AV65: 140.31711 | AW65: 140.31711 | AX65: 140.31711 | AY65: 140.31711 | AZ65: 84.190263 | BA65: 140.31711 | BB65: 140.31711 | BC65: 140.31711 | BD65: 140.31711 | BE65: 112.25368 | BF65: 85.3128 | BG65: 142.188 | BH65: 142.188 | BI65: 142.188 | BJ65: 142.188 | BK65: 142.188 | BL65: 85.3128 | BM65: 142.188 | BN65: 142.188 | BO65: 142.188 | BP65: 142.188 | BQ65: 113.7504
E66: Zurich | F66: CHF | G66: EUR | J66: 0 | K66: 0 | L66: 0 | M66: 0 | N66: 0 | O66: 0 | P66: 0 | Q66: 0 | R66: 0 | S66: 0 | T66: 0 | U66: 0 | V66: 0 | W66: 0 | X66: 0 | Y66: 215.53738 | Z66: 215.53738 | AA66: 215.53738 | AB66: 129.32243 | AC66: 215.53738 | AD66: 215.53738 | AE66: 215.53738 | AF66: 215.53738 | AG66: 172.42991 | AH66: 128.76562 | AI66: 214.60937 | AJ66: 214.60937 | AK66: 214.60937 | AL66: 214.60937 | AM66: 214.60937 | AN66: 128.76562 | AO66: 214.60937 | AP66: 214.60937 | AQ66: 214.60937 | AR66: 214.60937 | AS66: 171.6875 | AT66: 131.41182 | AU66: 219.0197 | AV66: 219.0197 | AW66: 219.0197 | AX66: 219.0197 | AY66: 219.0197 | AZ66: 131.41182 | BA66: 219.0197 | BB66: 219.0197 | BC66: 219.0197 | BD66: 219.0197 | BE66: 175.21576 | BF66: 132.17042 | BG66: 220.28404 | BH66: 220.28404 | BI66: 220.28404 | BJ66: 220.28404 | BK66: 220.28404 | BL66: 132.17042 | BM66: 220.28404 | BN66: 220.28404 | BO66: 220.28404 | BP66: 220.28404 | BQ66: 176.22723
E67: Moscow | F67: RUB | G67: EUR | J67: 0 | K67: 0 | L67: 0 | M67: 0 | N67: 0 | O67: 0 | P67: 0 | Q67: 0 | R67: 0 | S67: 0 | T67: 0 | U67: 0 | V67: 0 | W67: 0 | X67: 0 | Y67: 0 | Z67: 0 | AA67: 0 | AB67: 0 | AC67: 0 | AD67: 0 | AE67: 204.72973 | AF67: 204.72973 | AG67: 163.78378 | AH67: 122.412 | AI67: 204.02 | AJ67: 204.02 | AK67: 204.02 | AL67: 204.02 | AM67: 204.02 | AN67: 122.412 | AO67: 204.02 | AP67: 204.02 | AQ67: 204.02 | AR67: 204.02 | AS67: 163.216 | AT67: 122.61334 | AU67: 204.35556 | AV67: 204.35556 | AW67: 204.35556 | AX67: 204.35556 | AY67: 204.35556 | AZ67: 122.61334 | BA67: 204.35556 | BB67: 204.35556 | BC67: 204.35556 | BD67: 204.35556 | BE67: 163.48445 | BF67: 122.23116 | BG67: 203.71861 | BH67: 203.71861 | BI67: 203.71861 | BJ67: 203.71861 | BK67: 203.71861 | BL67: 122.23116 | BM67: 203.71861 | BN67: 203.71861 | BO67: 203.71861 | BP67: 203.71861 | BQ67: 162.97489
A69: End of schedule

Sheet Volume
A1: =company -> Fashion Boutique
A2: {=topic} -> CFM Topic: Revenue | J2: {=EDATE( start_date, _xlfn.SEQUENCE( 1, periods, 0, 1 ) )} -> 44562 | K2: 44593 | L2: 44621 | M2: 44652 | N2: 44682 | O2: 44713 | P2: 44743 | Q2: 44774 | R2: 44805 | S2: 44835 | T2: 44866 | U2: 44896 | V2: 44927 | W2: 44958 | X2: 44986 | Y2: 45017 | Z2: 45047 | AA2: 45078 | AB2: 45108 | AC2: 45139 | AD2: 45170 | AE2: 45200 | AF2: 45231 | AG2: 45261 | AH2: 45292 | AI2: 45323 | AJ2: 45352 | AK2: 45383 | AL2: 45413 | AM2: 45444 | AN2: 45474 | AO2: 45505 | AP2: 45536 | AQ2: 45566 | AR2: 45597 | AS2: 45627 | AT2: 45658 | AU2: 45689 | AV2: 45717 | AW2: 45748 | AX2: 45778 | AY2: 45809 | AZ2: 45839 | BA2: 45870 | BB2: 45901 | BC2: 45931 | BD2: 45962 | BE2: 45992 | BF2: 46023 | BG2: 46054 | BH2: 46082 | BI2: 46113 | BJ2: 46143 | BK2: 46174 | BL2: 46204 | BM2: 46235 | BN2: 46266 | BO2: 46296 | BP2: 46327 | BQ2: 46357
A3: VOLUME SCHEDULE | F3: Constant | G3: Unit | H3: Total | J3: {=EOMONTH( start_date, _xlfn.SEQUENCE( 1, periods, 0, 1 ) )} -> 44592 | K3: 44620 | L3: 44651 | M3: 44681 | N3: 44712 | O3: 44742 | P3: 44773 | Q3: 44804 | R3: 44834 | S3: 44865 | T3: 44895 | U3: 44926 | V3: 44957 | W3: 44985 | X3: 45016 | Y3: 45046 | Z3: 45077 | AA3: 45107 | AB3: 45138 | AC3: 45169 | AD3: 45199 | AE3: 45230 | AF3: 45260 | AG3: 45291 | AH3: 45322 | AI3: 45351 | AJ3: 45382 | AK3: 45412 | AL3: 45443 | AM3: 45473 | AN3: 45504 | AO3: 45535 | AP3: 45565 | AQ3: 45596 | AR3: 45626 | AS3: 45657 | AT3: 45688 | AU3: 45716 | AV3: 45747 | AW3: 45777 | AX3: 45808 | AY3: 45838 | AZ3: 45869 | BA3: 45900 | BB3: 45930 | BC3: 45961 | BD3: 45991 | BE3: 46022 | BF3: 46053 | BG3: 46081 | BH3: 46112 | BI3: 46142 | BJ3: 46173 | BK3: 46203 | BL3: 46234 | BM3: 46265 | BN3: 46295 | BO3: 46326 | BP3: 46356 | BQ3: 46387
A5: SECTION 2: UNIT SALES
D7: Women's
E8: {=lstStores} -> Paris | G8: units | J8: {=_xlfn.LET( _xlpm.operating_flag,_xlfn.ANCHORARRAY( Time!$J18), _xlpm.unit_sales_table, CaseData!$B$27:$E$35, _xlpm.store_row, CaseData!$B$27:$B$35, _xlpm.apparel_column, CaseData!$B$27:$E$27, _xlpm.current_apparel, Volume!$D7, _xlpm.current_store,_xlfn.ANCHORARRAY( Volume!$E8), _xlpm.women_unit_sales, INDEX( _xlpm.unit_sales_table, _xlfn.XMATCH( _xlpm.current_store, _xlpm.store_row, 0), _xlfn.XMATCH( _xlpm.current_apparel, _xlpm.apparel_column, 0) ), _xlpm.current_month,_xlfn.ANCHORARRAY( Time!J$11), _xlpm.seasonality_month, CaseData!$C$58:$C$69, _xlpm.seasonality_percentage, CaseData!$D$58:$D$69, _xlpm.seasonality, _xlfn.XLOOKUP( _xlpm.current_month, _xlpm.seasonality_month, _xlpm.seasonality_percentage, 1, 0, 1 ), _xlpm.current_capacity_month,_xlfn.ANCHORARRAY( Time!$J28), _xlpm.capacity_month, CaseData!$I$10:$I$22, _xlpm.capacity_percentage, CaseData!$J$10:$J$22, _xlpm.capacity, _xlfn.XLOOKUP( _xlpm.current_capacity_month, _xlpm.capacity_month, _xlpm.capacity_percentage, 1, 0, 1 ), _xlpm.operating_flag * _xlpm.women_unit_sales * _xlpm.seasonality * IF( _xlpm.capacity < 1, _xlpm.capacity, 1) )} -> 450 | K8: 180 | L8: 180 | M8: 180 | N8: 180 | O8: 180 | P8: 450 | Q8: 180 | R8: 180 | S8: 180 | T8: 180 | U8: 270 | V8: 450 | W8: 180 | X8: 180 | Y8: 180 | Z8: 180 | AA8: 180 | AB8: 450 | AC8: 180 | AD8: 180 | AE8: 180 | AF8: 180 | AG8: 270 | AH8: 450 | AI8: 180 | AJ8: 180 | AK8: 180 | AL8: 180 | AM8: 180 | AN8: 450 | AO8: 180 | AP8: 180 | AQ8: 180 | AR8: 180 | AS8: 270 | AT8: 450 | AU8: 180 | AV8: 180 | AW8: 180 | AX8: 180 | AY8: 180 | AZ8: 450 | BA8: 180 | BB8: 180 | BC8: 180 | BD8: 180 | BE8: 270 | BF8: 450 | BG8: 180 | BH8: 180 | BI8: 180 | BJ8: 180 | BK8: 180 | BL8: 450 | BM8: 180 | BN8: 180 | BO8: 180 | BP8: 180 | BQ8: 270
E9: Milano | G9: units | J9: 700 | K9: 280 | L9: 280 | M9: 280 | N9: 280 | O9: 280 | P9: 700 | Q9: 280 | R9: 280 | S9: 280 | T9: 280 | U9: 420 | V9: 700 | W9: 280 | X9: 280 | Y9: 280 | Z9: 280 | AA9: 280 | AB9: 700 | AC9: 280 | AD9: 280 | AE9: 280 | AF9: 280 | AG9: 420 | AH9: 700 | AI9: 280 | AJ9: 280 | AK9: 280 | AL9: 280 | AM9: 280 | AN9: 700 | AO9: 280 | AP9: 280 | AQ9: 280 | AR9: 280 | AS9: 420 | AT9: 700 | AU9: 280 | AV9: 280 | AW9: 280 | AX9: 280 | AY9: 280 | AZ9: 700 | BA9: 280 | BB9: 280 | BC9: 280 | BD9: 280 | BE9: 420 | BF9: 700 | BG9: 280 | BH9: 280 | BI9: 280 | BJ9: 280 | BK9: 280 | BL9: 700 | BM9: 280 | BN9: 280 | BO9: 280 | BP9: 280 | BQ9: 420
E10: Madrid | G10: units | J10: 375 | K10: 150 | L10: 150 | M10: 150 | N10: 150 | O10: 150 | P10: 375 | Q10: 150 | R10: 150 | S10: 150 | T10: 150 | U10: 225 | V10: 375 | W10: 150 | X10: 150 | Y10: 150 | Z10: 150 | AA10: 150 | AB10: 375 | AC10: 150 | AD10: 150 | AE10: 150 | AF10: 150 | AG10: 225 | AH10: 375 | AI10: 150 | AJ10: 150 | AK10: 150 | AL10: 150 | AM10: 150 | AN10: 375 | AO10: 150 | AP10: 150 | AQ10: 150 | AR10: 150 | AS10: 225 | AT10: 375 | AU10: 150 | AV10: 150 | AW10: 150 | AX10: 150 | AY10: 150 | AZ10: 375 | BA10: 150 | BB10: 150 | BC10: 150 | BD10: 150 | BE10: 225 | BF10: 375 | BG10: 150 | BH10: 150 | BI10: 150 | BJ10: 150 | BK10: 150 | BL10: 375 | BM10: 150 | BN10: 150 | BO10: 150 | BP10: 150 | BQ10: 225
E11: London | G11: units | J11: 275 | K11: 110 | L11: 110 | M11: 110 | N11: 110 | O11: 110 | P11: 275 | Q11: 110 | R11: 110 | S11: 110 | T11: 110 | U11: 165 | V11: 275 | W11: 110 | X11: 110 | Y11: 110 | Z11: 110 | AA11: 110 | AB11: 275 | AC11: 110 | AD11: 110 | AE11: 110 | AF11: 110 | AG11: 165 | AH11: 275 | AI11: 110 | AJ11: 110 | AK11: 110 | AL11: 110 | AM11: 110 | AN11: 275 | AO11: 110 | AP11: 110 | AQ11: 110 | AR11: 110 | AS11: 165 | AT11: 275 | AU11: 110 | AV11: 110 | AW11: 110 | AX11: 110 | AY11: 110 | AZ11: 275 | BA11: 110 | BB11: 110 | BC11: 110 | BD11: 110 | BE11: 165 | BF11: 275 | BG11: 110 | BH11: 110 | BI11: 110 | BJ11: 110 | BK11: 110 | BL11: 275 | BM11: 110 | BN11: 110 | BO11: 110 | BP11: 110 | BQ11: 165
E12: New York | G12: units | J12: 0 | K12: 0 | L12: 0 | M12: 59.583333 | N12: 64.166667 | O12: 68.75 | P12: 183.33333 | Q12: 77.916667 | R12: 82.5 | S12: 87.083333 | T12: 91.666667 | U12: 144.375 | V12: 252.08333 | W12: 105.41667 | X12: 110 | Y12: 110 | Z12: 110 | AA12: 110 | AB12: 275 | AC12: 110 | AD12: 110 | AE12: 110 | AF12: 110 | AG12: 165 | AH12: 275 | AI12: 110 | AJ12: 110 | AK12: 110 | AL12: 110 | AM12: 110 | AN12: 275 | AO12: 110 | AP12: 110 | AQ12: 110 | AR12: 110 | AS12: 165 | AT12: 275 | AU12: 110 | AV12: 110 | AW12: 110 | AX12: 110 | AY12: 110 | AZ12: 275 | BA12: 110 | BB12: 110 | BC12: 110 | BD12: 110 | BE12: 165 | BF12: 275 | BG12: 110 | BH12: 110 | BI12: 110 | BJ12: 110 | BK12: 110 | BL12: 275 | BM12: 110 | BN12: 110 | BO12: 110 | BP12: 110 | BQ12: 165
E13: Montreal | G13: units | J13: 0 | K13: 0 | L13: 0 | M13: 0 | N13: 0 | O13: 0 | P13: 0 | Q13: 0 | R13: 0 | S13: 97.5 | T13: 105 | U13: 168.75 | V13: 300 | W13: 127.5 | X13: 135 | Y13: 142.5 | Z13: 150 | AA13: 157.5 | AB13: 412.5 | AC13: 172.5 | AD13: 180 | AE13: 180 | AF13: 180 | AG13: 270 | AH13: 450 | AI13: 180 | AJ13: 180 | AK13: 180 | AL13: 180 | AM13: 180 | AN13: 450 | AO13: 180 | AP13: 180 | AQ13: 180 | AR13: 180 | AS13: 270 | AT13: 450 | AU13: 180 | AV13: 180 | AW13: 180 | AX13: 180 | AY13: 180 | AZ13: 450 | BA13: 180 | BB13: 180 | BC13: 180 | BD13: 180 | BE13: 270 | BF13: 450 | BG13: 180 | BH13: 180 | BI13: 180 | BJ13: 180 | BK13: 180 | BL13: 450 | BM13: 180 | BN13: 180 | BO13: 180 | BP13: 180 | BQ13: 270
E14: Zurich | G14: units | J14: 0 | K14: 0 | L14: 0 | M14: 0 | N14: 0 | O14: 0 | P14: 0 | Q14: 0 | R14: 0 | S14: 0 | T14: 0 | U14: 0 | V14: 0 | W14: 0 | X14: 0 | Y14: 151.66667 | Z14: 163.33333 | AA14: 175 | AB14: 466.66667 | AC14: 198.33333 | AD14: 210 | AE14: 221.66667 | AF14: 233.33333 | AG14: 367.5 | AH14: 641.66667 | AI14: 268.33333 | AJ14: 280 | AK14: 280 | AL14: 280 | AM14: 280 | AN14: 700 | AO14: 280 | AP14: 280 | AQ14: 280 | AR14: 280 | AS14: 420 | AT14: 700 | AU14: 280 | AV14: 280 | AW14: 280 | AX14: 280 | AY14: 280 | AZ14: 700 | BA14: 280 | BB14: 280 | BC14: 280 | BD14: 280 | BE14: 420 | BF14: 700 | BG14: 280 | BH14: 280 | BI14: 280 | BJ14: 280 | BK14: 280 | BL14: 700 | BM14: 280 | BN14: 280 | BO14: 280 | BP14: 280 | BQ14: 420
E15: Moscow | G15: units | J15: 0 | K15: 0 | L15: 0 | M15: 0 | N15: 0 | O15: 0 | P15: 0 | Q15: 0 | R15: 0 | S15: 0 | T15: 0 | U15: 0 | V15: 0 | W15: 0 | X15: 0 | Y15: 0 | Z15: 0 | AA15: 0 | AB15: 0 | AC15: 0 | AD15: 0 | AE15: 59.583333 | AF15: 64.166667 | AG15: 103.125 | AH15: 183.33333 | AI15: 77.916667 | AJ15: 82.5 | AK15: 87.083333 | AL15: 91.666667 | AM15: 96.25 | AN15: 252.08333 | AO15: 105.41667 | AP15: 110 | AQ15: 110 | AR15: 110 | AS15: 165 | AT15: 275 | AU15: 110 | AV15: 110 | AW15: 110 | AX15: 110 | AY15: 110 | AZ15: 275 | BA15: 110 | BB15: 110 | BC15: 110 | BD15: 110 | BE15: 165 | BF15: 275 | BG15: 110 | BH15: 110 | BI15: 110 | BJ15: 110 | BK15: 110 | BL15: 275 | BM15: 110 | BN15: 110 | BO15: 110 | BP15: 110 | BQ15: 165
D17: Men's
E18: {=lstStores} -> Paris | G18: units | J18: {=_xlfn.LET( _xlpm.operating_flag,_xlfn.ANCHORARRAY( Time!$J18), _xlpm.unit_sales_table, CaseData!$B$27:$E$35, _xlpm.store_row, CaseData!$B$27:$B$35, _xlpm.apparel_column, CaseData!$B$27:$E$27, _xlpm.current_apparel, Volume!$D17, _xlpm.current_store,_xlfn.ANCHORARRAY( Volume!$E18), _xlpm.men_unit_sales, INDEX( _xlpm.unit_sales_table, _xlfn.XMATCH( _xlpm.current_store, _xlpm.store_row, 0), _xlfn.XMATCH( _xlpm.current_apparel, _xlpm.apparel_column, 0) ), _xlpm.current_month,_xlfn.ANCHORARRAY( Time!J$11), _xlpm.seasonality_month, CaseData!$C$58:$C$69, _xlpm.seasonality_percentage, CaseData!$D$58:$D$69, _xlpm.seasonality, _xlfn.XLOOKUP( _xlpm.current_month, _xlpm.seasonality_month, _xlpm.seasonality_percentage, 1, 0, 1 ), _xlpm.current_capacity_month,_xlfn.ANCHORARRAY( Time!$J28), _xlpm.capacity_month, CaseData!$I$10:$I$22, _xlpm.capacity_percentage, CaseData!$J$10:$J$22, _xlpm.capacity, _xlfn.XLOOKUP( _xlpm.current_capacity_month, _xlpm.capacity_month, _xlpm.capacity_percentage, 1, 0, 1 ), _xlpm.operating_flag * _xlpm.men_unit_sales * _xlpm.seasonality * IF( _xlpm.capacity < 1, _xlpm.capacity, 1) )} -> 425 | K18: 170 | L18: 170 | M18: 170 | N18: 170 | O18: 170 | P18: 425 | Q18: 170 | R18: 170 | S18: 170 | T18: 170 | U18: 255 | V18: 425 | W18: 170 | X18: 170 | Y18: 170 | Z18: 170 | AA18: 170 | AB18: 425 | AC18: 170 | AD18: 170 | AE18: 170 | AF18: 170 | AG18: 255 | AH18: 425 | AI18: 170 | AJ18: 170 | AK18: 170 | AL18: 170 | AM18: 170 | AN18: 425 | AO18: 170 | AP18: 170 | AQ18: 170 | AR18: 170 | AS18: 255 | AT18: 425 | AU18: 170 | AV18: 170 | AW18: 170 | AX18: 170 | AY18: 170 | AZ18: 425 | BA18: 170 | BB18: 170 | BC18: 170 | BD18: 170 | BE18: 255 | BF18: 425 | BG18: 170 | BH18: 170 | BI18: 170 | BJ18: 170 | BK18: 170 | BL18: 425 | BM18: 170 | BN18: 170 | BO18: 170 | BP18: 170 | BQ18: 255
E19: Milano | G19: units | J19: 425 | K19: 170 | L19: 170 | M19: 170 | N19: 170 | O19: 170 | P19: 425 | Q19: 170 | R19: 170 | S19: 170 | T19: 170 | U19: 255 | V19: 425 | W19: 170 | X19: 170 | Y19: 170 | Z19: 170 | AA19: 170 | AB19: 425 | AC19: 170 | AD19: 170 | AE19: 170 | AF19: 170 | AG19: 255 | AH19: 425 | AI19: 170 | AJ19: 170 | AK19: 170 | AL19: 170 | AM19: 170 | AN19: 425 | AO19: 170 | AP19: 170 | AQ19: 170 | AR19: 170 | AS19: 255 | AT19: 425 | AU19: 170 | AV19: 170 | AW19: 170 | AX19: 170 | AY19: 170 | AZ19: 425 | BA19: 170 | BB19: 170 | BC19: 170 | BD19: 170 | BE19: 255 | BF19: 425 | BG19: 170 | BH19: 170 | BI19: 170 | BJ19: 170 | BK19: 170 | BL19: 425 | BM19: 170 | BN19: 170 | BO19: 170 | BP19: 170 | BQ19: 255
E20: Madrid | G20: units | J20: 225 | K20: 90 | L20: 90 | M20: 90 | N20: 90 | O20: 90 | P20: 225 | Q20: 90 | R20: 90 | S20: 90 | T20: 90 | U20: 135 | V20: 225 | W20: 90 | X20: 90 | Y20: 90 | Z20: 90 | AA20: 90 | AB20: 225 | AC20: 90 | AD20: 90 | AE20: 90 | AF20: 90 | AG20: 135 | AH20: 225 | AI20: 90 | AJ20: 90 | AK20: 90 | AL20: 90 | AM20: 90 | AN20: 225 | AO20: 90 | AP20: 90 | AQ20: 90 | AR20: 90 | AS20: 135 | AT20: 225 | AU20: 90 | AV20: 90 | AW20: 90 | AX20: 90 | AY20: 90 | AZ20: 225 | BA20: 90 | BB20: 90 | BC20: 90 | BD20: 90 | BE20: 135 | BF20: 225 | BG20: 90 | BH20: 90 | BI20: 90 | BJ20: 90 | BK20: 90 | BL20: 225 | BM20: 90 | BN20: 90 | BO20: 90 | BP20: 90 | BQ20: 135
E21: London | G21: units | J21: 325 | K21: 130 | L21: 130 | M21: 130 | N21: 130 | O21: 130 | P21: 325 | Q21: 130 | R21: 130 | S21: 130 | T21: 130 | U21: 195 | V21: 325 | W21: 130 | X21: 130 | Y21: 130 | Z21: 130 | AA21: 130 | AB21: 325 | AC21: 130 | AD21: 130 | AE21: 130 | AF21: 130 | AG21: 195 | AH21: 325 | AI21: 130 | AJ21: 130 | AK21: 130 | AL21: 130 | AM21: 130 | AN21: 325 | AO21: 130 | AP21: 130 | AQ21: 130 | AR21: 130 | AS21: 195 | AT21: 325 | AU21: 130 | AV21: 130 | AW21: 130 | AX21: 130 | AY21: 130 | AZ21: 325 | BA21: 130 | BB21: 130 | BC21: 130 | BD21: 130 | BE21: 195 | BF21: 325 | BG21: 130 | BH21: 130 | BI21: 130 | BJ21: 130 | BK21: 130 | BL21: 325 | BM21: 130 | BN21: 130 | BO21: 130 | BP21: 130 | BQ21: 195
E22: New York | G22: units | J22: 0 | K22: 0 | L22: 0 | M22: 70.416667 | N22: 75.833333 | O22: 81.25 | P22: 216.66667 | Q22: 92.083333 | R22: 97.5 | S22: 102.91667 | T22: 108.33333 | U22: 170.625 | V22: 297.91667 | W22: 124.58333 | X22: 130 | Y22: 130 | Z22: 130 | AA22: 130 | AB22: 325 | AC22: 130 | AD22: 130 | AE22: 130 | AF22: 130 | AG22: 195 | AH22: 325 | AI22: 130 | AJ22: 130 | AK22: 130 | AL22: 130 | AM22: 130 | AN22: 325 | AO22: 130 | AP22: 130 | AQ22: 130 | AR22: 130 | AS22: 195 | AT22: 325 | AU22: 130 | AV22: 130 | AW22: 130 | AX22: 130 | AY22: 130 | AZ22: 325 | BA22: 130 | BB22: 130 | BC22: 130 | BD22: 130 | BE22: 195 | BF22: 325 | BG22: 130 | BH22: 130 | BI22: 130 | BJ22: 130 | BK22: 130 | BL22: 325 | BM22: 130 | BN22: 130 | BO22: 130 | BP22: 130 | BQ22: 195
E23: Montreal | G23: units | J23: 0 | K23: 0 | L23: 0 | M23: 0 | N23: 0 | O23: 0 | P23: 0 | Q23: 0 | R23: 0 | S23: 92.083333 | T23: 99.166667 | U23: 159.375 | V23: 283.33333 | W23: 120.41667 | X23: 127.5 | Y23: 134.58333 | Z23: 141.66667 | AA23: 148.75 | AB23: 389.58333 | AC23: 162.91667 | AD23: 170 | AE23: 170 | AF23: 170 | AG23: 255 | AH23: 425 | AI23: 170 | AJ23: 170 | AK23: 170 | AL23: 170 | AM23: 170 | AN23: 425 | AO23: 170 | AP23: 170 | AQ23: 170 | AR23: 170 | AS23: 255 | AT23: 425 | AU23: 170 | AV23: 170 | AW23: 170 | AX23: 170 | AY23: 170 | AZ23: 425 | BA23: 170 | BB23: 170 | BC23: 170 | BD23: 170 | BE23: 255 | BF23: 425 | BG23: 170 | BH23: 170 | BI23: 170 | BJ23: 170 | BK23: 170 | BL23: 425 | BM23: 170 | BN23: 170 | BO23: 170 | BP23: 170 | BQ23: 255
E24: Zurich | G24: units | J24: 0 | K24: 0 | L24: 0 | M24: 0 | N24: 0 | O24: 0 | P24: 0 | Q24: 0 | R24: 0 | S24: 0 | T24: 0 | U24: 0 | V24: 0 | W24: 0 | X24: 0 | Y24: 92.083333 | Z24: 99.166667 | AA24: 106.25 | AB24: 283.33333 | AC24: 120.41667 | AD24: 127.5 | AE24: 134.58333 | AF24: 141.66667 | AG24: 223.125 | AH24: 389.58333 | AI24: 162.91667 | AJ24: 170 | AK24: 170 | AL24: 170 | AM24: 170 | AN24: 425 | AO24: 170 | AP24: 170 | AQ24: 170 | AR24: 170 | AS24: 255 | AT24: 425 | AU24: 170 | AV24: 170 | AW24: 170 | AX24: 170 | AY24: 170 | AZ24: 425 | BA24: 170 | BB24: 170 | BC24: 170 | BD24: 170 | BE24: 255 | BF24: 425 | BG24: 170 | BH24: 170 | BI24: 170 | BJ24: 170 | BK24: 170 | BL24: 425 | BM24: 170 | BN24: 170 | BO24: 170 | BP24: 170 | BQ24: 255
E25: Moscow | G25: units | J25: 0 | K25: 0 | L25: 0 | M25: 0 | N25: 0 | O25: 0 | P25: 0 | Q25: 0 | R25: 0 | S25: 0 | T25: 0 | U25: 0 | V25: 0 | W25: 0 | X25: 0 | Y25: 0 | Z25: 0 | AA25: 0 | AB25: 0 | AC25: 0 | AD25: 0 | AE25: 70.416667 | AF25: 75.833333 | AG25: 121.875 | AH25: 216.66667 | AI25: 92.083333 | AJ25: 97.5 | AK25: 102.91667 | AL25: 108.33333 | AM25: 113.75 | AN25: 297.91667 | AO25: 124.58333 | AP25: 130 | AQ25: 130 | AR25: 130 | AS25: 195 | AT25: 325 | AU25: 130 | AV25: 130 | AW25: 130 | AX25: 130 | AY25: 130 | AZ25: 325 | BA25: 130 | BB25: 130 | BC25: 130 | BD25: 130 | BE25: 195 | BF25: 325 | BG25: 130 | BH25: 130 | BI25: 130 | BJ25: 130 | BK25: 130 | BL25: 325 | BM25: 130 | BN25: 130 | BO25: 130 | BP25: 130 | BQ25: 195
A27: SECTION 3: MAXIMUM UNIT CAPACITY
D29: Accessories
E30: {=lstStores} -> Paris | G30: units | J30: {=_xlfn.LET( _xlpm.operating_flag,_xlfn.ANCHORARRAY( Time!$J18), _xlpm.unit_sales_table, CaseData!$B$27:$E$35, _xlpm.store_row, CaseData!$B$27:$B$35, _xlpm.apparel_column, CaseData!$B$27:$E$27, _xlpm.current_apparel, Volume!$D29, _xlpm.current_store,_xlfn.ANCHORARRAY( Volume!$E30), _xlpm.accessories_unit_sales, INDEX( _xlpm.unit_sales_table, _xlfn.XMATCH( _xlpm.current_store, _xlpm.store_row, 0), _xlfn.XMATCH( _xlpm.current_apparel, _xlpm.apparel_column, 0) ), _xlpm.current_month,_xlfn.ANCHORARRAY( Time!J$11), _xlpm.seasonality_month, CaseData!$C$58:$C$69, _xlpm.seasonality_percentage, CaseData!$D$58:$D$69, _xlpm.seasonality, _xlfn.XLOOKUP( _xlpm.current_month, _xlpm.seasonality_month, _xlpm.seasonality_percentage, 1, 0, 1 ), _xlpm.current_capacity_month,_xlfn.ANCHORARRAY( Time!$J28), _xlpm.capacity_month, CaseData!$I$10:$I$22, _xlpm.capacity_percentage, CaseData!$J$10:$J$22, _xlpm.capacity, _xlfn.XLOOKUP( _xlpm.current_capacity_month, _xlpm.capacity_month, _xlpm.capacity_percentage, 1, 0, 1 ), _xlpm.operating_flag * _xlpm.accessories_unit_sales * _xlpm.seasonality * IF( _xlpm.capacity < 1, _xlpm.capacity, 1) )} -> 650 | K30: 260 | L30: 260 | M30: 260 | N30: 260 | O30: 260 | P30: 650 | Q30: 260 | R30: 260 | S30: 260 | T30: 260 | U30: 390 | V30: 650 | W30: 260 | X30: 260 | Y30: 260 | Z30: 260 | AA30: 260 | AB30: 650 | AC30: 260 | AD30: 260 | AE30: 260 | AF30: 260 | AG30: 390 | AH30: 650 | AI30: 260 | AJ30: 260 | AK30: 260 | AL30: 260 | AM30: 260 | AN30: 650 | AO30: 260 | AP30: 260 | AQ30: 260 | AR30: 260 | AS30: 390 | AT30: 650 | AU30: 260 | AV30: 260 | AW30: 260 | AX30: 260 | AY30: 260 | AZ30: 650 | BA30: 260 | BB30: 260 | BC30: 260 | BD30: 260 | BE30: 390 | BF30: 650 | BG30: 260 | BH30: 260 | BI30: 260 | BJ30: 260 | BK30: 260 | BL30: 650 | BM30: 260 | BN30: 260 | BO30: 260 | BP30: 260 | BQ30: 390
E31: Milano | G31: units | J31: 375 | K31: 150 | L31: 150 | M31: 150 | N31: 150 | O31: 150 | P31: 375 | Q31: 150 | R31: 150 | S31: 150 | T31: 150 | U31: 225 | V31: 375 | W31: 150 | X31: 150 | Y31: 150 | Z31: 150 | AA31: 150 | AB31: 375 | AC31: 150 | AD31: 150 | AE31: 150 | AF31: 150 | AG31: 225 | AH31: 375 | AI31: 150 | AJ31: 150 | AK31: 150 | AL31: 150 | AM31: 150 | AN31: 375 | AO31: 150 | AP31: 150 | AQ31: 150 | AR31: 150 | AS31: 225 | AT31: 375 | AU31: 150 | AV31: 150 | AW31: 150 | AX31: 150 | AY31: 150 | AZ31: 375 | BA31: 150 | BB31: 150 | BC31: 150 | BD31: 150 | BE31: 225 | BF31: 375 | BG31: 150 | BH31: 150 | BI31: 150 | BJ31: 150 | BK31: 150 | BL31: 375 | BM31: 150 | BN31: 150 | BO31: 150 | BP31: 150 | BQ31: 225
E32: Madrid | G32: units | J32: 150 | K32: 60 | L32: 60 | M32: 60 | N32: 60 | O32: 60 | P32: 150 | Q32: 60 | R32: 60 | S32: 60 | T32: 60 | U32: 90 | V32: 150 | W32: 60 | X32: 60 | Y32: 60 | Z32: 60 | AA32: 60 | AB32: 150 | AC32: 60 | AD32: 60 | AE32: 60 | AF32: 60 | AG32: 90 | AH32: 150 | AI32: 60 | AJ32: 60 | AK32: 60 | AL32: 60 | AM32: 60 | AN32: 150 | AO32: 60 | AP32: 60 | AQ32: 60 | AR32: 60 | AS32: 90 | AT32: 150 | AU32: 60 | AV32: 60 | AW32: 60 | AX32: 60 | AY32: 60 | AZ32: 150 | BA32: 60 | BB32: 60 | BC32: 60 | BD32: 60 | BE32: 90 | BF32: 150 | BG32: 60 | BH32: 60 | BI32: 60 | BJ32: 60 | BK32: 60 | BL32: 150 | BM32: 60 | BN32: 60 | BO32: 60 | BP32: 60 | BQ32: 90
E33: London | G33: units | J33: 250 | K33: 100 | L33: 100 | M33: 100 | N33: 100 | O33: 100 | P33: 250 | Q33: 100 | R33: 100 | S33: 100 | T33: 100 | U33: 150 | V33: 250 | W33: 100 | X33: 100 | Y33: 100 | Z33: 100 | AA33: 100 | AB33: 250 | AC33: 100 | AD33: 100 | AE33: 100 | AF33: 100 | AG33: 150 | AH33: 250 | AI33: 100 | AJ33: 100 | AK33: 100 | AL33: 100 | AM33: 100 | AN33: 250 | AO33: 100 | AP33: 100 | AQ33: 100 | AR33: 100 | AS33: 150 | AT33: 250 | AU33: 100 | AV33: 100 | AW33: 100 | AX33: 100 | AY33: 100 | AZ33: 250 | BA33: 100 | BB33: 100 | BC33: 100 | BD33: 100 | BE33: 150 | BF33: 250 | BG33: 100 | BH33: 100 | BI33: 100 | BJ33: 100 | BK33: 100 | BL33: 250 | BM33: 100 | BN33: 100 | BO33: 100 | BP33: 100 | BQ33: 150
E34: New York | G34: units | J34: 0 | K34: 0 | L34: 0 | M34: 54.166667 | N34: 58.333333 | O34: 62.5 | P34: 166.66667 | Q34: 70.833333 | R34: 75 | S34: 79.166667 | T34: 83.333333 | U34: 131.25 | V34: 229.16667 | W34: 95.833333 | X34: 100 | Y34: 100 | Z34: 100 | AA34: 100 | AB34: 250 | AC34: 100 | AD34: 100 | AE34: 100 | AF34: 100 | AG34: 150 | AH34: 250 | AI34: 100 | AJ34: 100 | AK34: 100 | AL34: 100 | AM34: 100 | AN34: 250 | AO34: 100 | AP34: 100 | AQ34: 100 | AR34: 100 | AS34: 150 | AT34: 250 | AU34: 100 | AV34: 100 | AW34: 100 | AX34: 100 | AY34: 100 | AZ34: 250 | BA34: 100 | BB34: 100 | BC34: 100 | BD34: 100 | BE34: 150 | BF34: 250 | BG34: 100 | BH34: 100 | BI34: 100 | BJ34: 100 | BK34: 100 | BL34: 250 | BM34: 100 | BN34: 100 | BO34: 100 | BP34: 100 | BQ34: 150
E35: Montreal | G35: units | J35: 0 | K35: 0 | L35: 0 | M35: 0 | N35: 0 | O35: 0 | P35: 0 | Q35: 0 | R35: 0 | S35: 140.83333 | T35: 151.66667 | U35: 243.75 | V35: 433.33333 | W35: 184.16667 | X35: 195 | Y35: 205.83333 | Z35: 216.66667 | AA35: 227.5 | AB35: 595.83333 | AC35: 249.16667 | AD35: 260 | AE35: 260 | AF35: 260 | AG35: 390 | AH35: 650 | AI35: 260 | AJ35: 260 | AK35: 260 | AL35: 260 | AM35: 260 | AN35: 650 | AO35: 260 | AP35: 260 | AQ35: 260 | AR35: 260 | AS35: 390 | AT35: 650 | AU35: 260 | AV35: 260 | AW35: 260 | AX35: 260 | AY35: 260 | AZ35: 650 | BA35: 260 | BB35: 260 | BC35: 260 | BD35: 260 | BE35: 390 | BF35: 650 | BG35: 260 | BH35: 260 | BI35: 260 | BJ35: 260 | BK35: 260 | BL35: 650 | BM35: 260 | BN35: 260 | BO35: 260 | BP35: 260 | BQ35: 390
E36: Zurich | G36: units | J36: 0 | K36: 0 | L36: 0 | M36: 0 | N36: 0 | O36: 0 | P36: 0 | Q36: 0 | R36: 0 | S36: 0 | T36: 0 | U36: 0 | V36: 0 | W36: 0 | X36: 0 | Y36: 81.25 | Z36: 87.5 | AA36: 93.75 | AB36: 250 | AC36: 106.25 | AD36: 112.5 | AE36: 118.75 | AF36: 125 | AG36: 196.875 | AH36: 343.75 | AI36: 143.75 | AJ36: 150 | AK36: 150 | AL36: 150 | AM36: 150 | AN36: 375 | AO36: 150 | AP36: 150 | AQ36: 150 | AR36: 150 | AS36: 225 | AT36: 375 | AU36: 150 | AV36: 150 | AW36: 150 | AX36: 150 | AY36: 150 | AZ36: 375 | BA36: 150 | BB36: 150 | BC36: 150 | BD36: 150 | BE36: 225 | BF36: 375 | BG36: 150 | BH36: 150 | BI36: 150 | BJ36: 150 | BK36: 150 | BL36: 375 | BM36: 150 | BN36: 150 | BO36: 150 | BP36: 150 | BQ36: 225
E37: Moscow | G37: units | J37: 0 | K37: 0 | L37: 0 | M37: 0 | N37: 0 | O37: 0 | P37: 0 | Q37: 0 | R37: 0 | S37: 0 | T37: 0 | U37: 0 | V37: 0 | W37: 0 | X37: 0 | Y37: 0 | Z37: 0 | AA37: 0 | AB37: 0 | AC37: 0 | AD37: 0 | AE37: 54.166667 | AF37: 58.333333 | AG37: 93.75 | AH37: 166.66667 | AI37: 70.833333 | AJ37: 75 | AK37: 79.166667 | AL37: 83.333333 | AM37: 87.5 | AN37: 229.16667 | AO37: 95.833333 | AP37: 100 | AQ37: 100 | AR37: 100 | AS37: 150 | AT37: 250 | AU37: 100 | AV37: 100 | AW37: 100 | AX37: 100 | AY37: 100 | AZ37: 250 | BA37: 100 | BB37: 100 | BC37: 100 | BD37: 100 | BE37: 150 | BF37: 250 | BG37: 100 | BH37: 100 | BI37: 100 | BJ37: 100 | BK37: 100 | BL37: 250 | BM37: 100 | BN37: 100 | BO37: 100 | BP37: 100 | BQ37: 150
E39: Total maximum demand | G39: units | J39: {=_xlfn.LET( _xlpm.anchor, $J30, _xlpm.block, OFFSET( _xlpm.anchor, 0, 0, COUNTA( ( lstStores ) ), periods ), _xlfn.BYCOL( _xlpm.block, _xlfn.LAMBDA(_xlpm.column, SUM( _xlpm.column ) ) ) )} -> 1425 | K39: 570 | L39: 570 | M39: 624.16667 | N39: 628.33333 | O39: 632.5 | P39: 1591.6667 | Q39: 640.83333 | R39: 645 | S39: 790 | T39: 805 | U39: 1230 | V39: 2087.5 | W39: 850 | X39: 865 | Y39: 957.08333 | Z39: 974.16667 | AA39: 991.25 | AB39: 2520.8333 | AC39: 1025.4167 | AD39: 1042.5 | AE39: 1102.9167 | AF39: 1113.3333 | AG39: 1685.625 | AH39: 2835.4167 | AI39: 1144.5833 | AJ39: 1155 | AK39: 1159.1667 | AL39: 1163.3333 | AM39: 1167.5 | AN39: 2929.1667 | AO39: 1175.8333 | AP39: 1180 | AQ39: 1180 | AR39: 1180 | AS39: 1770 | AT39: 2950 | AU39: 1180 | AV39: 1180 | AW39: 1180 | AX39: 1180 | AY39: 1180 | AZ39: 2950 | BA39: 1180 | BB39: 1180 | BC39: 1180 | BD39: 1180 | BE39: 1770 | BF39: 2950 | BG39: 1180 | BH39: 1180 | BI39: 1180 | BJ39: 1180 | BK39: 1180 | BL39: 2950 | BM39: 1180 | BN39: 1180 | BO39: 1180 | BP39: 1180 | BQ39: 1770
E41: =CaseData!B$41 -> Max Capacity | F41: =CaseData!C$41 -> 2500 | G41: =CaseData!D$41 -> units
E42: Capacity constraint | G42: % | J42: {=_xlfn.LET( _xlpm.max_capacity, $F$41, _xlpm.max_demand,_xlfn.ANCHORARRAY( J39), _xlfn.BYCOL( _xlpm.max_demand, _xlfn.LAMBDA(_xlpm.d, MIN( 1, _xlpm.max_capacity / _xlpm.d ) ) ) )} -> 1 | K42: 1 | L42: 1 | M42: 1 | N42: 1 | O42: 1 | P42: 1 | Q42: 1 | R42: 1 | S42: 1 | T42: 1 | U42: 1 | V42: 1 | W42: 1 | X42: 1 | Y42: 1 | Z42: 1 | AA42: 1 | AB42: 0.99173554 | AC42: 1 | AD42: 1 | AE42: 1 | AF42: 1 | AG42: 1 | AH42: 0.88170463 | AI42: 1 | AJ42: 1 | AK42: 1 | AL42: 1 | AM42: 1 | AN42: 0.85348506 | AO42: 1 | AP42: 1 | AQ42: 1 | AR42: 1 | AS42: 1 | AT42: 0.84745763 | AU42: 1 | AV42: 1 | AW42: 1 | AX42: 1 | AY42: 1 | AZ42: 0.84745763 | BA42: 1 | BB42: 1 | BC42: 1 | BD42: 1 | BE42: 1 | BF42: 0.84745763 | BG42: 1 | BH42: 1 | BI42: 1 | BJ42: 1 | BK42: 1 | BL42: 0.84745763 | BM42: 1 | BN42: 1 | BO42: 1 | BP42: 1 | BQ42: 1
D44: Accessories (capacity constrained)
E45: {=lstStores} -> Paris | G45: units | J45: {=_xlfn.LET( _xlpm.accessories_max,_xlfn.ANCHORARRAY( J30), _xlpm.constraint,_xlfn.ANCHORARRAY( J42), _xlpm.accessories_max * _xlpm.constraint )} -> 650 | K45: 260 | L45: 260 | M45: 260 | N45: 260 | O45: 260 | P45: 650 | Q45: 260 | R45: 260 | S45: 260 | T45: 260 | U45: 390 | V45: 650 | W45: 260 | X45: 260 | Y45: 260 | Z45: 260 | AA45: 260 | AB45: 644.6281 | AC45: 260 | AD45: 260 | AE45: 260 | AF45: 260 | AG45: 390 | AH45: 573.10801 | AI45: 260 | AJ45: 260 | AK45: 260 | AL45: 260 | AM45: 260 | AN45: 554.76529 | AO45: 260 | AP45: 260 | AQ45: 260 | AR45: 260 | AS45: 390 | AT45: 550.84746 | AU45: 260 | AV45: 260 | AW45: 260 | AX45: 260 | AY45: 260 | AZ45: 550.84746 | BA45: 260 | BB45: 260 | BC45: 260 | BD45: 260 | BE45: 390 | BF45: 550.84746 | BG45: 260 | BH45: 260 | BI45: 260 | BJ45: 260 | BK45: 260 | BL45: 550.84746 | BM45: 260 | BN45: 260 | BO45: 260 | BP45: 260 | BQ45: 390
E46: Milano | G46: units | J46: 375 | K46: 150 | L46: 150 | M46: 150 | N46: 150 | O46: 150 | P46: 375 | Q46: 150 | R46: 150 | S46: 150 | T46: 150 | U46: 225 | V46: 375 | W46: 150 | X46: 150 | Y46: 150 | Z46: 150 | AA46: 150 | AB46: 371.90083 | AC46: 150 | AD46: 150 | AE46: 150 | AF46: 150 | AG46: 225 | AH46: 330.63924 | AI46: 150 | AJ46: 150 | AK46: 150 | AL46: 150 | AM46: 150 | AN46: 320.0569 | AO46: 150 | AP46: 150 | AQ46: 150 | AR46: 150 | AS46: 225 | AT46: 317.79661 | AU46: 150 | AV46: 150 | AW46: 150 | AX46: 150 | AY46: 150 | AZ46: 317.79661 | BA46: 150 | BB46: 150 | BC46: 150 | BD46: 150 | BE46: 225 | BF46: 317.79661 | BG46: 150 | BH46: 150 | BI46: 150 | BJ46: 150 | BK46: 150 | BL46: 317.79661 | BM46: 150 | BN46: 150 | BO46: 150 | BP46: 150 | BQ46: 225
E47: Madrid | G47: units | J47: 150 | K47: 60 | L47: 60 | M47: 60 | N47: 60 | O47: 60 | P47: 150 | Q47: 60 | R47: 60 | S47: 60 | T47: 60 | U47: 90 | V47: 150 | W47: 60 | X47: 60 | Y47: 60 | Z47: 60 | AA47: 60 | AB47: 148.76033 | AC47: 60 | AD47: 60 | AE47: 60 | AF47: 60 | AG47: 90 | AH47: 132.25569 | AI47: 60 | AJ47: 60 | AK47: 60 | AL47: 60 | AM47: 60 | AN47: 128.02276 | AO47: 60 | AP47: 60 | AQ47: 60 | AR47: 60 | AS47: 90 | AT47: 127.11864 | AU47: 60 | AV47: 60 | AW47: 60 | AX47: 60 | AY47: 60 | AZ47: 127.11864 | BA47: 60 | BB47: 60 | BC47: 60 | BD47: 60 | BE47: 90 | BF47: 127.11864 | BG47: 60 | BH47: 60 | BI47: 60 | BJ47: 60 | BK47: 60 | BL47: 127.11864 | BM47: 60 | BN47: 60 | BO47: 60 | BP47: 60 | BQ47: 90
E48: London | G48: units | J48: 250 | K48: 100 | L48: 100 | M48: 100 | N48: 100 | O48: 100 | P48: 250 | Q48: 100 | R48: 100 | S48: 100 | T48: 100 | U48: 150 | V48: 250 | W48: 100 | X48: 100 | Y48: 100 | Z48: 100 | AA48: 100 | AB48: 247.93388 | AC48: 100 | AD48: 100 | AE48: 100 | AF48: 100 | AG48: 150 | AH48: 220.42616 | AI48: 100 | AJ48: 100 | AK48: 100 | AL48: 100 | AM48: 100 | AN48: 213.37127 | AO48: 100 | AP48: 100 | AQ48: 100 | AR48: 100 | AS48: 150 | AT48: 211.86441 | AU48: 100 | AV48: 100 | AW48: 100 | AX48: 100 | AY48: 100 | AZ48: 211.86441 | BA48: 100 | BB48: 100 | BC48: 100 | BD48: 100 | BE48: 150 | BF48: 211.86441 | BG48: 100 | BH48: 100 | BI48: 100 | BJ48: 100 | BK48: 100 | BL48: 211.86441 | BM48: 100 | BN48: 100 | BO48: 100 | BP48: 100 | BQ48: 150
E49: New York | G49: units | J49: 0 | K49: 0 | L49: 0 | M49: 54.166667 | N49: 58.333333 | O49: 62.5 | P49: 166.66667 | Q49: 70.833333 | R49: 75 | S49: 79.166667 | T49: 83.333333 | U49: 131.25 | V49: 229.16667 | W49: 95.833333 | X49: 100 | Y49: 100 | Z49: 100 | AA49: 100 | AB49: 247.93388 | AC49: 100 | AD49: 100 | AE49: 100 | AF49: 100 | AG49: 150 | AH49: 220.42616 | AI49: 100 | AJ49: 100 | AK49: 100 | AL49: 100 | AM49: 100 | AN49: 213.37127 | AO49: 100 | AP49: 100 | AQ49: 100 | AR49: 100 | AS49: 150 | AT49: 211.86441 | AU49: 100 | AV49: 100 | AW49: 100 | AX49: 100 | AY49: 100 | AZ49: 211.86441 | BA49: 100 | BB49: 100 | BC49: 100 | BD49: 100 | BE49: 150 | BF49: 211.86441 | BG49: 100 | BH49: 100 | BI49: 100 | BJ49: 100 | BK49: 100 | BL49: 211.86441 | BM49: 100 | BN49: 100 | BO49: 100 | BP49: 100 | BQ49: 150
E50: Montreal | G50: units | J50: 0 | K50: 0 | L50: 0 | M50: 0 | N50: 0 | O50: 0 | P50: 0 | Q50: 0 | R50: 0 | S50: 140.83333 | T50: 151.66667 | U50: 243.75 | V50: 433.33333 | W50: 184.16667 | X50: 195 | Y50: 205.83333 | Z50: 216.66667 | AA50: 227.5 | AB50: 590.90909 | AC50: 249.16667 | AD50: 260 | AE50: 260 | AF50: 260 | AG50: 390 | AH50: 573.10801 | AI50: 260 | AJ50: 260 | AK50: 260 | AL50: 260 | AM50: 260 | AN50: 554.76529 | AO50: 260 | AP50: 260 | AQ50: 260 | AR50: 260 | AS50: 390 | AT50: 550.84746 | AU50: 260 | AV50: 260 | AW50: 260 | AX50: 260 | AY50: 260 | AZ50: 550.84746 | BA50: 260 | BB50: 260 | BC50: 260 | BD50: 260 | BE50: 390 | BF50: 550.84746 | BG50: 260 | BH50: 260 | BI50: 260 | BJ50: 260 | BK50: 260 | BL50: 550.84746 | BM50: 260 | BN50: 260 | BO50: 260 | BP50: 260 | BQ50: 390
E51: Zurich | G51: units | J51: 0 | K51: 0 | L51: 0 | M51: 0 | N51: 0 | O51: 0 | P51: 0 | Q51: 0 | R51: 0 | S51: 0 | T51: 0 | U51: 0 | V51: 0 | W51: 0 | X51: 0 | Y51: 81.25 | Z51: 87.5 | AA51: 93.75 | AB51: 247.93388 | AC51: 106.25 | AD51: 112.5 | AE51: 118.75 | AF51: 125 | AG51: 196.875 | AH51: 303.08597 | AI51: 143.75 | AJ51: 150 | AK51: 150 | AL51: 150 | AM51: 150 | AN51: 320.0569 | AO51: 150 | AP51: 150 | AQ51: 150 | AR51: 150 | AS51: 225 | AT51: 317.79661 | AU51: 150 | AV51: 150 | AW51: 150 | AX51: 150 | AY51: 150 | AZ51: 317.79661 | BA51: 150 | BB51: 150 | BC51: 150 | BD51: 150 | BE51: 225 | BF51: 317.79661 | BG51: 150 | BH51: 150 | BI51: 150 | BJ51: 150 | BK51: 150 | BL51: 317.79661 | BM51: 150 | BN51: 150 | BO51: 150 | BP51: 150 | BQ51: 225
E52: Moscow | G52: units | J52: 0 | K52: 0 | L52: 0 | M52: 0 | N52: 0 | O52: 0 | P52: 0 | Q52: 0 | R52: 0 | S52: 0 | T52: 0 | U52: 0 | V52: 0 | W52: 0 | X52: 0 | Y52: 0 | Z52: 0 | AA52: 0 | AB52: 0 | AC52: 0 | AD52: 0 | AE52: 54.166667 | AF52: 58.333333 | AG52: 93.75 | AH52: 146.95077 | AI52: 70.833333 | AJ52: 75 | AK52: 79.166667 | AL52: 83.333333 | AM52: 87.5 | AN52: 195.59033 | AO52: 95.833333 | AP52: 100 | AQ52: 100 | AR52: 100 | AS52: 150 | AT52: 211.86441 | AU52: 100 | AV52: 100 | AW52: 100 | AX52: 100 | AY52: 100 | AZ52: 211.86441 | BA52: 100 | BB52: 100 | BC52: 100 | BD52: 100 | BE52: 150 | BF52: 211.86441 | BG52: 100 | BH52: 100 | BI52: 100 | BJ52: 100 | BK52: 100 | BL52: 211.86441 | BM52: 100 | BN52: 100 | BO52: 100 | BP52: 100 | BQ52: 150
A54: End of schedule

Sheet Time
A1: =company -> Fashion Boutique
A2: {=topic} -> CFM Topic: Revenue | J2: {=EDATE( start_date, _xlfn.SEQUENCE( 1, periods, 0, 1 ) )} -> 44562 | K2: 44593 | L2: 44621 | M2: 44652 | N2: 44682 | O2: 44713 | P2: 44743 | Q2: 44774 | R2: 44805 | S2: 44835 | T2: 44866 | U2: 44896 | V2: 44927 | W2: 44958 | X2: 44986 | Y2: 45017 | Z2: 45047 | AA2: 45078 | AB2: 45108 | AC2: 45139 | AD2: 45170 | AE2: 45200 | AF2: 45231 | AG2: 45261 | AH2: 45292 | AI2: 45323 | AJ2: 45352 | AK2: 45383 | AL2: 45413 | AM2: 45444 | AN2: 45474 | AO2: 45505 | AP2: 45536 | AQ2: 45566 | AR2: 45597 | AS2: 45627 | AT2: 45658 | AU2: 45689 | AV2: 45717 | AW2: 45748 | AX2: 45778 | AY2: 45809 | AZ2: 45839 | BA2: 45870 | BB2: 45901 | BC2: 45931 | BD2: 45962 | BE2: 45992 | BF2: 46023 | BG2: 46054 | BH2: 46082 | BI2: 46113 | BJ2: 46143 | BK2: 46174 | BL2: 46204 | BM2: 46235 | BN2: 46266 | BO2: 46296 | BP2: 46327 | BQ2: 46357
A3: TIME SCHEDULE | F3: Constant | G3: Unit | H3: Total | J3: {=EOMONTH( start_date, _xlfn.SEQUENCE( 1, periods, 0, 1 ) )} -> 44592 | K3: 44620 | L3: 44651 | M3: 44681 | N3: 44712 | O3: 44742 | P3: 44773 | Q3: 44804 | R3: 44834 | S3: 44865 | T3: 44895 | U3: 44926 | V3: 44957 | W3: 44985 | X3: 45016 | Y3: 45046 | Z3: 45077 | AA3: 45107 | AB3: 45138 | AC3: 45169 | AD3: 45199 | AE3: 45230 | AF3: 45260 | AG3: 45291 | AH3: 45322 | AI3: 45351 | AJ3: 45382 | AK3: 45412 | AL3: 45443 | AM3: 45473 | AN3: 45504 | AO3: 45535 | AP3: 45565 | AQ3: 45596 | AR3: 45626 | AS3: 45657 | AT3: 45688 | AU3: 45716 | AV3: 45747 | AW3: 45777 | AX3: 45808 | AY3: 45838 | AZ3: 45869 | BA3: 45900 | BB3: 45930 | BC3: 45961 | BD3: 45991 | BE3: 46022 | BF3: 46053 | BG3: 46081 | BH3: 46112 | BI3: 46142 | BJ3: 46173 | BK3: 46203 | BL3: 46234 | BM3: 46265 | BN3: 46295 | BO3: 46326 | BP3: 46356 | BQ3: 46387
A5: TIME
E7: =CaseData!B$4 -> Model start date | F7: =start_date -> 44562
E8: Model period beginning | G8: date | J8: {=EDATE( start_date, _xlfn.SEQUENCE( 1, periods, 0, 1 ) )} -> 44562 | K8: 44593 | L8: 44621 | M8: 44652 | N8: 44682 | O8: 44713 | P8: 44743 | Q8: 44774 | R8: 44805 | S8: 44835 | T8: 44866 | U8: 44896 | V8: 44927 | W8: 44958 | X8: 44986 | Y8: 45017 | Z8: 45047 | AA8: 45078 | AB8: 45108 | AC8: 45139 | AD8: 45170 | AE8: 45200 | AF8: 45231 | AG8: 45261 | AH8: 45292 | AI8: 45323 | AJ8: 45352 | AK8: 45383 | AL8: 45413 | AM8: 45444 | AN8: 45474 | AO8: 45505 | AP8: 45536 | AQ8: 45566 | AR8: 45597 | AS8: 45627 | AT8: 45658 | AU8: 45689 | AV8: 45717 | AW8: 45748 | AX8: 45778 | AY8: 45809 | AZ8: 45839 | BA8: 45870 | BB8: 45901 | BC8: 45931 | BD8: 45962 | BE8: 45992 | BF8: 46023 | BG8: 46054 | BH8: 46082 | BI8: 46113 | BJ8: 46143 | BK8: 46174 | BL8: 46204 | BM8: 46235 | BN8: 46266 | BO8: 46296 | BP8: 46327 | BQ8: 46357
E9: Model period ending | G9: date | J9: {=EOMONTH( start_date, _xlfn.SEQUENCE( 1, periods, 0, 1 ) )} -> 44592 | K9: 44620 | L9: 44651 | M9: 44681 | N9: 44712 | O9: 44742 | P9: 44773 | Q9: 44804 | R9: 44834 | S9: 44865 | T9: 44895 | U9: 44926 | V9: 44957 | W9: 44985 | X9: 45016 | Y9: 45046 | Z9: 45077 | AA9: 45107 | AB9: 45138 | AC9: 45169 | AD9: 45199 | AE9: 45230 | AF9: 45260 | AG9: 45291 | AH9: 45322 | AI9: 45351 | AJ9: 45382 | AK9: 45412 | AL9: 45443 | AM9: 45473 | AN9: 45504 | AO9: 45535 | AP9: 45565 | AQ9: 45596 | AR9: 45626 | AS9: 45657 | AT9: 45688 | AU9: 45716 | AV9: 45747 | AW9: 45777 | AX9: 45808 | AY9: 45838 | AZ9: 45869 | BA9: 45900 | BB9: 45930 | BC9: 45961 | BD9: 45991 | BE9: 46022 | BF9: 46053 | BG9: 46081 | BH9: 46112 | BI9: 46142 | BJ9: 46173 | BK9: 46203 | BL9: 46234 | BM9: 46265 | BN9: 46295 | BO9: 46326 | BP9: 46356 | BQ9: 46387
E10: Model period counter | G10: counter | J10: {=_xlfn.SEQUENCE( 1, periods, 1, 1 )} -> 1 | K10: 2 | L10: 3 | M10: 4 | N10: 5 | O10: 6 | P10: 7 | Q10: 8 | R10: 9 | S10: 10 | T10: 11 | U10: 12 | V10: 13 | W10: 14 | X10: 15 | Y10: 16 | Z10: 17 | AA10: 18 | AB10: 19 | AC10: 20 | AD10: 21 | AE10: 22 | AF10: 23 | AG10: 24 | AH10: 25 | AI10: 26 | AJ10: 27 | AK10: 28 | AL10: 29 | AM10: 30 | AN10: 31 | AO10: 32 | AP10: 33 | AQ10: 34 | AR10: 35 | AS10: 36 | AT10: 37 | AU10: 38 | AV10: 39 | AW10: 40 | AX10: 41 | AY10: 42 | AZ10: 43 | BA10: 44 | BB10: 45 | BC10: 46 | BD10: 47 | BE10: 48 | BF10: 49 | BG10: 50 | BH10: 51 | BI10: 52 | BJ10: 53 | BK10: 54 | BL10: 55 | BM10: 56 | BN10: 57 | BO10: 58 | BP10: 59 | BQ10: 60
E11: Model periodic counter | G11: counter | J11: {=_xlfn.LET( _xlpm.model_operating_periods, _xlfn.SEQUENCE( 1, periods, 1, 0), _xlfn.SCAN( 0, _xlpm.model_operating_periods, _xlfn.LAMBDA(_xlpm.state,_xlpm.current, IF( _xlpm.state + _xlpm.current > 12, _xlpm.current, _xlpm.state + _xlpm.current ) ) ) )} -> 1 | K11: 2 | L11: 3 | M11: 4 | N11: 5 | O11: 6 | P11: 7 | Q11: 8 | R11: 9 | S11: 10 | T11: 11 | U11: 12 | V11: 1 | W11: 2 | X11: 3 | Y11: 4 | Z11: 5 | AA11: 6 | AB11: 7 | AC11: 8 | AD11: 9 | AE11: 10 | AF11: 11 | AG11: 12 | AH11: 1 | AI11: 2 | AJ11: 3 | AK11: 4 | AL11: 5 | AM11: 6 | AN11: 7 | AO11: 8 | AP11: 9 | AQ11: 10 | AR11: 11 | AS11: 12 | AT11: 1 | AU11: 2 | AV11: 3 | AW11: 4 | AX11: 5 | AY11: 6 | AZ11: 7 | BA11: 8 | BB11: 9 | BC11: 10 | BD11: 11 | BE11: 12 | BF11: 1 | BG11: 2 | BH11: 3 | BI11: 4 | BJ11: 5 | BK11: 6 | BL11: 7 | BM11: 8 | BN11: 9 | BO11: 10 | BP11: 11 | BQ11: 12
E12: Calendar year | G12: years | J12: {=YEAR(_xlfn.ANCHORARRAY( J9) )} -> 2022 | K12: 2022 | L12: 2022 | M12: 2022 | N12: 2022 | O12: 2022 | P12: 2022 | Q12: 2022 | R12: 2022 | S12: 2022 | T12: 2022 | U12: 2022 | V12: 2023 | W12: 2023 | X12: 2023 | Y12: 2023 | Z12: 2023 | AA12: 2023 | AB12: 2023 | AC12: 2023 | AD12: 2023 | AE12: 2023 | AF12: 2023 | AG12: 2023 | AH12: 2024 | AI12: 2024 | AJ12: 2024 | AK12: 2024 | AL12: 2024 | AM12: 2024 | AN12: 2024 | AO12: 2024 | AP12: 2024 | AQ12: 2024 | AR12: 2024 | AS12: 2024 | AT12: 2025 | AU12: 2025 | AV12: 2025 | AW12: 2025 | AX12: 2025 | AY12: 2025 | AZ12: 2025 | BA12: 2025 | BB12: 2025 | BC12: 2025 | BD12: 2025 | BE12: 2025 | BF12: 2026 | BG12: 2026 | BH12: 2026 | BI12: 2026 | BJ12: 2026 | BK12: 2026 | BL12: 2026 | BM12: 2026 | BN12: 2026 | BO12: 2026 | BP12: 2026 | BQ12: 2026
E13: Annual timeline | G13: years | J13: {=_xlfn.UNIQUE(_xlfn.ANCHORARRAY( J12), TRUE )} -> 2022 | K13: 2023 | L13: 2024 | M13: 2025 | N13: 2026
A15: SECTION 1: STORE DATA
B17: Operating flag
E18: {=lstStores} -> Paris | F18: {=_xlfn.XLOOKUP(_xlfn.ANCHORARRAY( Time!E18), lstStores, CaseData!$F$10:$F$17 )} -> 0 | G18: month | J18: {=IF(_xlfn.ANCHORARRAY( F18) = 0, 1, IF(_xlfn.ANCHORARRAY( F18) >=_xlfn.ANCHORARRAY( J10), 0, 1 ) )} -> 1 | K18: 1 | L18: 1 | M18: 1 | N18: 1 | O18: 1 | P18: 1 | Q18: 1 | R18: 1 | S18: 1 | T18: 1 | U18: 1 | V18: 1 | W18: 1 | X18: 1 | Y18: 1 | Z18: 1 | AA18: 1 | AB18: 1 | AC18: 1 | AD18: 1 | AE18: 1 | AF18: 1 | AG18: 1 | AH18: 1 | AI18: 1 | AJ18: 1 | AK18: 1 | AL18: 1 | AM18: 1 | AN18: 1 | AO18: 1 | AP18: 1 | AQ18: 1 | AR18: 1 | AS18: 1 | AT18: 1 | AU18: 1 | AV18: 1 | AW18: 1 | AX18: 1 | AY18: 1 | AZ18: 1 | BA18: 1 | BB18: 1 | BC18: 1 | BD18: 1 | BE18: 1 | BF18: 1 | BG18: 1 | BH18: 1 | BI18: 1 | BJ18: 1 | BK18: 1 | BL18: 1 | BM18: 1 | BN18: 1 | BO18: 1 | BP18: 1 | BQ18: 1
E19: Milano | F19: 0 | G19: month | J19: 1 | K19: 1 | L19: 1 | M19: 1 | N19: 1 | O19: 1 | P19: 1 | Q19: 1 | R19: 1 | S19: 1 | T19: 1 | U19: 1 | V19: 1 | W19: 1 | X19: 1 | Y19: 1 | Z19: 1 | AA19: 1 | AB19: 1 | AC19: 1 | AD19: 1 | AE19: 1 | AF19: 1 | AG19: 1 | AH19: 1 | AI19: 1 | AJ19: 1 | AK19: 1 | AL19: 1 | AM19: 1 | AN19: 1 | AO19: 1 | AP19: 1 | AQ19: 1 | AR19: 1 | AS19: 1 | AT19: 1 | AU19: 1 | AV19: 1 | AW19: 1 | AX19: 1 | AY19: 1 | AZ19: 1 | BA19: 1 | BB19: 1 | BC19: 1 | BD19: 1 | BE19: 1 | BF19: 1 | BG19: 1 | BH19: 1 | BI19: 1 | BJ19: 1 | BK19: 1 | BL19: 1 | BM19: 1 | BN19: 1 | BO19: 1 | BP19: 1 | BQ19: 1
E20: Madrid | F20: 0 | G20: month | J20: 1 | K20: 1 | L20: 1 | M20: 1 | N20: 1 | O20: 1 | P20: 1 | Q20: 1 | R20: 1 | S20: 1 | T20: 1 | U20: 1 | V20: 1 | W20: 1 | X20: 1 | Y20: 1 | Z20: 1 | AA20: 1 | AB20: 1 | AC20: 1 | AD20: 1 | AE20: 1 | AF20: 1 | AG20: 1 | AH20: 1 | AI20: 1 | AJ20: 1 | AK20: 1 | AL20: 1 | AM20: 1 | AN20: 1 | AO20: 1 | AP20: 1 | AQ20: 1 | AR20: 1 | AS20: 1 | AT20: 1 | AU20: 1 | AV20: 1 | AW20: 1 | AX20: 1 | AY20: 1 | AZ20: 1 | BA20: 1 | BB20: 1 | BC20: 1 | BD20: 1 | BE20: 1 | BF20: 1 | BG20: 1 | BH20: 1 | BI20: 1 | BJ20: 1 | BK20: 1 | BL20: 1 | BM20: 1 | BN20: 1 | BO20: 1 | BP20: 1 | BQ20: 1
E21: London | F21: 0 | G21: month | J21: 1 | K21: 1 | L21: 1 | M21: 1 | N21: 1 | O21: 1 | P21: 1 | Q21: 1 | R21: 1 | S21: 1 | T21: 1 | U21: 1 | V21: 1 | W21: 1 | X21: 1 | Y21: 1 | Z21: 1 | AA21: 1 | AB21: 1 | AC21: 1 | AD21: 1 | AE21: 1 | AF21: 1 | AG21: 1 | AH21: 1 | AI21: 1 | AJ21: 1 | AK21: 1 | AL21: 1 | AM21: 1 | AN21: 1 | AO21: 1 | AP21: 1 | AQ21: 1 | AR21: 1 | AS21: 1 | AT21: 1 | AU21: 1 | AV21: 1 | AW21: 1 | AX21: 1 | AY21: 1 | AZ21: 1 | BA21: 1 | BB21: 1 | BC21: 1 | BD21: 1 | BE21: 1 | BF21: 1 | BG21: 1 | BH21: 1 | BI21: 1 | BJ21: 1 | BK21: 1 | BL21: 1 | BM21: 1 | BN21: 1 | BO21: 1 | BP21: 1 | BQ21: 1
E22: New York | F22: 3 | G22: month | J22: 0 | K22: 0 | L22: 0 | M22: 1 | N22: 1 | O22: 1 | P22: 1 | Q22: 1 | R22: 1 | S22: 1 | T22: 1 | U22: 1 | V22: 1 | W22: 1 | X22: 1 | Y22: 1 | Z22: 1 | AA22: 1 | AB22: 1 | AC22: 1 | AD22: 1 | AE22: 1 | AF22: 1 | AG22: 1 | AH22: 1 | AI22: 1 | AJ22: 1 | AK22: 1 | AL22: 1 | AM22: 1 | AN22: 1 | AO22: 1 | AP22: 1 | AQ22: 1 | AR22: 1 | AS22: 1 | AT22: 1 | AU22: 1 | AV22: 1 | AW22: 1 | AX22: 1 | AY22: 1 | AZ22: 1 | BA22: 1 | BB22: 1 | BC22: 1 | BD22: 1 | BE22: 1 | BF22: 1 | BG22: 1 | BH22: 1 | BI22: 1 | BJ22: 1 | BK22: 1 | BL22: 1 | BM22: 1 | BN22: 1 | BO22: 1 | BP22: 1 | BQ22: 1
E23: Montreal | F23: 9 | G23: month | J23: 0 | K23: 0 | L23: 0 | M23: 0 | N23: 0 | O23: 0 | P23: 0 | Q23: 0 | R23: 0 | S23: 1 | T23: 1 | U23: 1 | V23: 1 | W23: 1 | X23: 1 | Y23: 1 | Z23: 1 | AA23: 1 | AB23: 1 | AC23: 1 | AD23: 1 | AE23: 1 | AF23: 1 | AG23: 1 | AH23: 1 | AI23: 1 | AJ23: 1 | AK23: 1 | AL23: 1 | AM23: 1 | AN23: 1 | AO23: 1 | AP23: 1 | AQ23: 1 | AR23: 1 | AS23: 1 | AT23: 1 | AU23: 1 | AV23: 1 | AW23: 1 | AX23: 1 | AY23: 1 | AZ23: 1 | BA23: 1 | BB23: 1 | BC23: 1 | BD23: 1 | BE23: 1 | BF23: 1 | BG23: 1 | BH23: 1 | BI23: 1 | BJ23: 1 | BK23: 1 | BL23: 1 | BM23: 1 | BN23: 1 | BO23: 1 | BP23: 1 | BQ23: 1
E24: Zurich | F24: 15 | G24: month | J24: 0 | K24: 0 | L24: 0 | M24: 0 | N24: 0 | O24: 0 | P24: 0 | Q24: 0 | R24: 0 | S24: 0 | T24: 0 | U24: 0 | V24: 0 | W24: 0 | X24: 0 | Y24: 1 | Z24: 1 | AA24: 1 | AB24: 1 | AC24: 1 | AD24: 1 | AE24: 1 | AF24: 1 | AG24: 1 | AH24: 1 | AI24: 1 | AJ24: 1 | AK24: 1 | AL24: 1 | AM24: 1 | AN24: 1 | AO24: 1 | AP24: 1 | AQ24: 1 | AR24: 1 | AS24: 1 | AT24: 1 | AU24: 1 | AV24: 1 | AW24: 1 | AX24: 1 | AY24: 1 | AZ24: 1 | BA24: 1 | BB24: 1 | BC24: 1 | BD24: 1 | BE24: 1 | BF24: 1 | BG24: 1 | BH24: 1 | BI24: 1 | BJ24: 1 | BK24: 1 | BL24: 1 | BM24: 1 | BN24: 1 | BO24: 1 | BP24: 1 | BQ24: 1
E25: Moscow | F25: 21 | G25: month | J25: 0 | K25: 0 | L25: 0 | M25: 0 | N25: 0 | O25: 0 | P25: 0 | Q25: 0 | R25: 0 | S25: 0 | T25: 0 | U25: 0 | V25: 0 | W25: 0 | X25: 0 | Y25: 0 | Z25: 0 | AA25: 0 | AB25: 0 | AC25: 0 | AD25: 0 | AE25: 1 | AF25: 1 | AG25: 1 | AH25: 1 | AI25: 1 | AJ25: 1 | AK25: 1 | AL25: 1 | AM25: 1 | AN25: 1 | AO25: 1 | AP25: 1 | AQ25: 1 | AR25: 1 | AS25: 1 | AT25: 1 | AU25: 1 | AV25: 1 | AW25: 1 | AX25: 1 | AY25: 1 | AZ25: 1 | BA25: 1 | BB25: 1 | BC25: 1 | BD25: 1 | BE25: 1 | BF25: 1 | BG25: 1 | BH25: 1 | BI25: 1 | BJ25: 1 | BK25: 1 | BL25: 1 | BM25: 1 | BN25: 1 | BO25: 1 | BP25: 1 | BQ25: 1
B27: Capacity flag
E28: {=lstStores} -> Paris | F28: {=_xlfn.XLOOKUP(_xlfn.ANCHORARRAY( Time!E28), lstStores, CaseData!$F$10:$F$17 )} -> 0 | G28: month | J28: {=IF(_xlfn.ANCHORARRAY( F28) = 0, 0, IF(_xlfn.ANCHORARRAY( J10) <_xlfn.ANCHORARRAY( F28), 0, IF(_xlfn.ANCHORARRAY( J10) -_xlfn.ANCHORARRAY( F28) + 1 <= 13,_xlfn.ANCHORARRAY( J10) -_xlfn.ANCHORARRAY( F28) + 1, 0 ) ) )} -> 0 | K28: 0 | L28: 0 | M28: 0 | N28: 0 | O28: 0 | P28: 0 | Q28: 0 | R28: 0 | S28: 0 | T28: 0 | U28: 0 | V28: 0 | W28: 0 | X28: 0 | Y28: 0 | Z28: 0 | AA28: 0 | AB28: 0 | AC28: 0 | AD28: 0 | AE28: 0 | AF28: 0 | AG28: 0 | AH28: 0 | AI28: 0 | AJ28: 0 | AK28: 0 | AL28: 0 | AM28: 0 | AN28: 0 | AO28: 0 | AP28: 0 | AQ28: 0 | AR28: 0 | AS28: 0 | AT28: 0 | AU28: 0 | AV28: 0 | AW28: 0 | AX28: 0 | AY28: 0 | AZ28: 0 | BA28: 0 | BB28: 0 | BC28: 0 | BD28: 0 | BE28: 0 | BF28: 0 | BG28: 0 | BH28: 0 | BI28: 0 | BJ28: 0 | BK28: 0 | BL28: 0 | BM28: 0 | BN28: 0 | BO28: 0 | BP28: 0 | BQ28: 0
E29: Milano | F29: 0 | G29: month | J29: 0 | K29: 0 | L29: 0 | M29: 0 | N29: 0 | O29: 0 | P29: 0 | Q29: 0 | R29: 0 | S29: 0 | T29: 0 | U29: 0 | V29: 0 | W29: 0 | X29: 0 | Y29: 0 | Z29: 0 | AA29: 0 | AB29: 0 | AC29: 0 | AD29: 0 | AE29: 0 | AF29: 0 | AG29: 0 | AH29: 0 | AI29: 0 | AJ29: 0 | AK29: 0 | AL29: 0 | AM29: 0 | AN29: 0 | AO29: 0 | AP29: 0 | AQ29: 0 | AR29: 0 | AS29: 0 | AT29: 0 | AU29: 0 | AV29: 0 | AW29: 0 | AX29: 0 | AY29: 0 | AZ29: 0 | BA29: 0 | BB29: 0 | BC29: 0 | BD29: 0 | BE29: 0 | BF29: 0 | BG29: 0 | BH29: 0 | BI29: 0 | BJ29: 0 | BK29: 0 | BL29: 0 | BM29: 0 | BN29: 0 | BO29: 0 | BP29: 0 | BQ29: 0
E30: Madrid | F30: 0 | G30: month | J30: 0 | K30: 0 | L30: 0 | M30: 0 | N30: 0 | O30: 0 | P30: 0 | Q30: 0 | R30: 0 | S30: 0 | T30: 0 | U30: 0 | V30: 0 | W30: 0 | X30: 0 | Y30: 0 | Z30: 0 | AA30: 0 | AB30: 0 | AC30: 0 | AD30: 0 | AE30: 0 | AF30: 0 | AG30: 0 | AH30: 0 | AI30: 0 | AJ30: 0 | AK30: 0 | AL30: 0 | AM30: 0 | AN30: 0 | AO30: 0 | AP30: 0 | AQ30: 0 | AR30: 0 | AS30: 0 | AT30: 0 | AU30: 0 | AV30: 0 | AW30: 0 | AX30: 0 | AY30: 0 | AZ30: 0 | BA30: 0 | BB30: 0 | BC30: 0 | BD30: 0 | BE30: 0 | BF30: 0 | BG30: 0 | BH30: 0 | BI30: 0 | BJ30: 0 | BK30: 0 | BL30: 0 | BM30: 0 | BN30: 0 | BO30: 0 | BP30: 0 | BQ30: 0
E31: London | F31: 0 | G31: month | J31: 0 | K31: 0 | L31: 0 | M31: 0 | N31: 0 | O31: 0 | P31: 0 | Q31: 0 | R31: 0 | S31: 0 | T31: 0 | U31: 0 | V31: 0 | W31: 0 | X31: 0 | Y31: 0 | Z31: 0 | AA31: 0 | AB31: 0 | AC31: 0 | AD31: 0 | AE31: 0 | AF31: 0 | AG31: 0 | AH31: 0 | AI31: 0 | AJ31: 0 | AK31: 0 | AL31: 0 | AM31: 0 | AN31: 0 | AO31: 0 | AP31: 0 | AQ31: 0 | AR31: 0 | AS31: 0 | AT31: 0 | AU31: 0 | AV31: 0 | AW31: 0 | AX31: 0 | AY31: 0 | AZ31: 0 | BA31: 0 | BB31: 0 | BC31: 0 | BD31: 0 | BE31: 0 | BF31: 0 | BG31: 0 | BH31: 0 | BI31: 0 | BJ31: 0 | BK31: 0 | BL31: 0 | BM31: 0 | BN31: 0 | BO31: 0 | BP31: 0 | BQ31: 0
E32: New York | F32: 3 | G32: month | J32: 0 | K32: 0 | L32: 1 | M32: 2 | N32: 3 | O32: 4 | P32: 5 | Q32: 6 | R32: 7 | S32: 8 | T32: 9 | U32: 10 | V32: 11 | W32: 12 | X32: 13 | Y32: 0 | Z32: 0 | AA32: 0 | AB32: 0 | AC32: 0 | AD32: 0 | AE32: 0 | AF32: 0 | AG32: 0 | AH32: 0 | AI32: 0 | AJ32: 0 | AK32: 0 | AL32: 0 | AM32: 0 | AN32: 0 | AO32: 0 | AP32: 0 | AQ32: 0 | AR32: 0 | AS32: 0 | AT32: 0 | AU32: 0 | AV32: 0 | AW32: 0 | AX32: 0 | AY32: 0 | AZ32: 0 | BA32: 0 | BB32: 0 | BC32: 0 | BD32: 0 | BE32: 0 | BF32: 0 | BG32: 0 | BH32: 0 | BI32: 0 | BJ32: 0 | BK32: 0 | BL32: 0 | BM32: 0 | BN32: 0 | BO32: 0 | BP32: 0 | BQ32: 0
E33: Montreal | F33: 9 | G33: month | J33: 0 | K33: 0 | L33: 0 | M33: 0 | N33: 0 | O33: 0 | P33: 0 | Q33: 0 | R33: 1 | S33: 2 | T33: 3 | U33: 4 | V33: 5 | W33: 6 | X33: 7 | Y33: 8 | Z33: 9 | AA33: 10 | AB33: 11 | AC33: 12 | AD33: 13 | AE33: 0 | AF33: 0 | AG33: 0 | AH33: 0 | AI33: 0 | AJ33: 0 | AK33: 0 | AL33: 0 | AM33: 0 | AN33: 0 | AO33: 0 | AP33: 0 | AQ33: 0 | AR33: 0 | AS33: 0 | AT33: 0 | AU33: 0 | AV33: 0 | AW33: 0 | AX33: 0 | AY33: 0 | AZ33: 0 | BA33: 0 | BB33: 0 | BC33: 0 | BD33: 0 | BE33: 0 | BF33: 0 | BG33: 0 | BH33: 0 | BI33: 0 | BJ33: 0 | BK33: 0 | BL33: 0 | BM33: 0 | BN33: 0 | BO33: 0 | BP33: 0 | BQ33: 0
E34: Zurich | F34: 15 | G34: month | J34: 0 | K34: 0 | L34: 0 | M34: 0 | N34: 0 | O34: 0 | P34: 0 | Q34: 0 | R34: 0 | S34: 0 | T34: 0 | U34: 0 | V34: 0 | W34: 0 | X34: 1 | Y34: 2 | Z34: 3 | AA34: 4 | AB34: 5 | AC34: 6 | AD34: 7 | AE34: 8 | AF34: 9 | AG34: 10 | AH34: 11 | AI34: 12 | AJ34: 13 | AK34: 0 | AL34: 0 | AM34: 0 | AN34: 0 | AO34: 0 | AP34: 0 | AQ34: 0 | AR34: 0 | AS34: 0 | AT34: 0 | AU34: 0 | AV34: 0 | AW34: 0 | AX34: 0 | AY34: 0 | AZ34: 0 | BA34: 0 | BB34: 0 | BC34: 0 | BD34: 0 | BE34: 0 | BF34: 0 | BG34: 0 | BH34: 0 | BI34: 0 | BJ34: 0 | BK34: 0 | BL34: 0 | BM34: 0 | BN34: 0 | BO34: 0 | BP34: 0 | BQ34: 0
E35: Moscow | F35: 21 | G35: month | J35: 0 | K35: 0 | L35: 0 | M35: 0 | N35: 0 | O35: 0 | P35: 0 | Q35: 0 | R35: 0 | S35: 0 | T35: 0 | U35: 0 | V35: 0 | W35: 0 | X35: 0 | Y35: 0 | Z35: 0 | AA35: 0 | AB35: 0 | AC35: 0 | AD35: 1 | AE35: 2 | AF35: 3 | AG35: 4 | AH35: 5 | AI35: 6 | AJ35: 7 | AK35: 8 | AL35: 9 | AM35: 10 | AN35: 11 | AO35: 12 | AP35: 13 | AQ35: 0 | AR35: 0 | AS35: 0 | AT35: 0 | AU35: 0 | AV35: 0 | AW35: 0 | AX35: 0 | AY35: 0 | AZ35: 0 | BA35: 0 | BB35: 0 | BC35: 0 | BD35: 0 | BE35: 0 | BF35: 0 | BG35: 0 | BH35: 0 | BI35: 0 | BJ35: 0 | BK35: 0 | BL35: 0 | BM35: 0 | BN35: 0 | BO35: 0 | BP35: 0 | BQ35: 0
A37: End of schedule

Sheet CaseData
A1: =$J$3&". Key Assumptions for the Financial Model" -> Fashion Boutique. Key Assumptions for the Financial Model
B3: Company Name: | J3: Fashion Boutique
B4: Model start date | J4: 44562
B5: Model periods: | J5: 60
B6: Model topic | J6: Revenue
A7: 1. Store Data
B9: # | C9: Store | D9: Country | E9: Currency | F9: Opening Month | I9: MOO | J9: Capacity | L9: MOO = Month of Operations (for a new store)
B10: 1 | C10: Paris | D10: France | E10: EUR | I10: 1 | J10: 0.5 | L10: 1 = first month of operations, 2 = second month of operations, …
B11: =B10+1 -> 2 | C11: Milano | D11: Italy | E11: EUR | I11: 2 | J11: 0.54166667
B12: =B11+1 -> 3 | C12: Madrid | D12: Spain | E12: EUR | I12: 3 | J12: 0.58333333
B13: =B12+1 -> 4 | C13: London | D13: UK | E13: GBP | I13: 4 | J13: 0.625
B14: =B13+1 -> 5 | C14: New York | D14: US | E14: USD | F14: 3 | G14: =EDATE($J$4,F14-1) -> 44621 | I14: 5 | J14: 0.66666667
B15: =B14+1 -> 6 | C15: Montreal | D15: Canada | E15: CAD | F15: 9 | G15: =EDATE($J$4,F15-1) -> 44805 | I15: 6 | J15: 0.70833333
B16: =B15+1 -> 7 | C16: Zurich | D16: Switzerland | E16: CHF | F16: 15 | G16: =EDATE($J$4,F16-1) -> 44986 | I16: 7 | J16: 0.75
B17: =B16+1 -> 8 | C17: Moscow | D17: Russia | E17: RUB | F17: 21 | G17: =EDATE($J$4,F17-1) -> 45170 | I17: 8 | J17: 0.79166667
I18: 9 | J18: 0.83333333
I19: 10 | J19: 0.875
I20: 11 | J20: 0.91666667
I21: 12 | J21: 0.95833333
I22: 13 | J22: 1
A25: 2. Unit Sales per Month - Base Case
B27: Store | C27: Women's | D27: Men's | E27: Accessories
B28: =C10 -> Paris | C28: 180 | D28: 170 | E28: 260
B29: =C11 -> Milano | C29: 280 | D29: 170 | E29: 150
B30: =C12 -> Madrid | C30: 150 | D30: 90 | E30: 60
B31: =C13 -> London | C31: 110 | D31: 130 | E31: 100 | F31: Same as
B32: =C14 -> New York | C32: =INDEX(C$28:C$31,MATCH($F32,$C$10:$C$13,0)) -> 110 | D32: =INDEX(D$28:D$31,MATCH($F32,$C$10:$C$13,0)) -> 130 | E32: =INDEX(E$28:E$31,MATCH($F32,$C$10:$C$13,0)) -> 100 | F32: London
B33: =C15 -> Montreal | C33: =INDEX(C$28:C$31,MATCH($F33,$C$10:$C$13,0)) -> 180 | D33: =INDEX(D$28:D$31,MATCH($F33,$C$10:$C$13,0)) -> 170 | E33: =INDEX(E$28:E$31,MATCH($F33,$C$10:$C$13,0)) -> 260 | F33: Paris
B34: =C16 -> Zurich | C34: =INDEX(C$28:C$31,MATCH($F34,$C$10:$C$13,0)) -> 280 | D34: =INDEX(D$28:D$31,MATCH($F34,$C$10:$C$13,0)) -> 170 | E34: =INDEX(E$28:E$31,MATCH($F34,$C$10:$C$13,0)) -> 150 | F34: Milano
B35: =C17 -> Moscow | C35: =INDEX(C$28:C$31,MATCH($F35,$C$10:$C$13,0)) -> 110 | D35: =INDEX(D$28:D$31,MATCH($F35,$C$10:$C$13,0)) -> 130 | E35: =INDEX(E$28:E$31,MATCH($F35,$C$10:$C$13,0)) -> 100 | F35: London
A38: 3. Maximum Unit Sales Capacity per Month
C40: Accessories
B41: Max Capacity | C41: 2500 | D41: units
A44: 4. Average Local Currency Prices - Base Case
B46: Currency | C46: Women's | D46: Men's | E46: Accessories
B47: EUR | C47: 500 | D47: 400 | E47: 150
B48: GBP | C48: 425 | D48: 350 | E48: 125
B49: USD | C49: 475 | D49: 375 | E49: 150
B50: CAD | C50: 700 | D50: 550 | E50: 200
B51: CHF | C51: 750 | D51: 600 | E51: 225
B52: RUB | C52: 55000 | D52: 40000 | E52: 15000
A55: 5. Sales Seasonality
B57: Month | C57: # | D57: Volume | E57: Discount
B58: =DATE($C$74,1,1) -> 44562 | C58: =MONTH(B58) -> 1 | D58: 2.5 | E58: 0.4
B59: =DATE($C$74,MONTH(B58)+1,1) -> 44593 | C59: =MONTH(B59) -> 2 | D59: 1 | E59: 0
B60: =DATE($C$74,MONTH(B59)+1,1) -> 44621 | C60: =MONTH(B60) -> 3 | D60: 1 | E60: 0
B61: =DATE($C$74,MONTH(B60)+1,1) -> 44652 | C61: =MONTH(B61) -> 4 | D61: 1 | E61: 0
B62: =DATE($C$74,MONTH(B61)+1,1) -> 44682 | C62: =MONTH(B62) -> 5 | D62: 1 | E62: 0
B63: =DATE($C$74,MONTH(B62)+1,1) -> 44713 | C63: =MONTH(B63) -> 6 | D63: 1 | E63: 0
B64: =DATE($C$74,MONTH(B63)+1,1) -> 44743 | C64: =MONTH(B64) -> 7 | D64: 2.5 | E64: 0.4
B65: =DATE($C$74,MONTH(B64)+1,1) -> 44774 | C65: =MONTH(B65) -> 8 | D65: 1 | E65: 0
B66: =DATE($C$74,MONTH(B65)+1,1) -> 44805 | C66: =MONTH(B66) -> 9 | D66: 1 | E66: 0
B67: =DATE($C$74,MONTH(B66)+1,1) -> 44835 | C67: =MONTH(B67) -> 10 | D67: 1 | E67: 0
B68: =DATE($C$74,MONTH(B67)+1,1) -> 44866 | C68: =MONTH(B68) -> 11 | D68: 1 | E68: 0
B69: =DATE($C$74,MONTH(B68)+1,1) -> 44896 | C69: =MONTH(B69) -> 12 | D69: 1.5 | E69: 0.2
A72: 6. FX Rates to EUR
B74: Currency | C74: =YEAR(J4) -> 2022 | D74: =C74+1 -> 2023 | E74: =D74+1 -> 2024 | F74: =E74+1 -> 2025 | G74: =F74+1 -> 2026
B75: =B47 -> EUR | C75: 1 | D75: =C75 -> 1 | E75: =D75 -> 1 | F75: =E75 -> 1 | G75: =F75 -> 1
B76: =B48 -> GBP | C76: 0.86 | D76: 0.87 | E76: 0.88 | F76: 0.89 | G76: 0.9
B77: =B49 -> USD | C77: 1.1 | D77: 1.11 | E77: 1.12 | F77: 1.13 | G77: 1.14
B78: =B50 -> CAD | C78: 1.49 | D78: 1.5 | E78: 1.51 | F78: 1.52 | G78: 1.53
B79: =B51 -> CHF | C79: 1.06 | D79: 1.07 | E79: 1.08 | F79: 1.09 | G79: 1.1
B80: =B52 -> RUB | C80: 73 | D80: 74 | E80: 75 | F80: 76 | G80: 77
A83: 7. Inflation Rates
B85: Currency | C85: =C74 -> 2022 | D85: =C85+1 -> 2023 | E85: =D85+1 -> 2024 | F85: =E85+1 -> 2025 | G85: =F85+1 -> 2026
B86: =B75 -> EUR | C86: n.a. | D86: 0.005 | E86: 0.005 | F86: 0.01 | G86: 0.025 | K86: 2022 | L86: 2023 | M86: 2024 | N86: 2025 | O86: 2026
B87: =B76 -> GBP | C87: n.a. | D87: 0.03 | E87: 0.01 | F87: 0.01 | G87: 0.01 | J87: {=lstStoreCurrencies} -> EUR | K87: {=_xlfn.LET( _xlpm.clean_rates, IF( $C$86:$G$91 = "n.a.", 0, $C$86:$G$91 ), _xlpm.compounded_rates, _xlfn.MAKEARRAY( ROWS( _xlpm.clean_rates ), COLUMNS( _xlpm.clean_rates ), _xlfn.LAMBDA(_xlpm.i,_xlpm.j, INDEX( _xlfn.SCAN( 1, INDEX( _xlpm.clean_rates, _xlpm.i, 0), _xlfn.LAMBDA(_xlpm.s,_xlpm.c, _xlpm.s * (1 + _xlpm.c ) ) ), _xlpm.j ) ) ), _xlpm.inflation_rows, $B$86:$B$91, _xlpm.inflation_column, $B$85:$G$85, _xlpm.inflation_table, _xlfn.VSTACK( _xlpm.inflation_column, _xlfn.HSTACK( _xlpm.inflation_rows, _xlpm.compounded_rates ) ), _xlpm.store_currency,_xlfn.ANCHORARRAY( J87), _xlpm.current_year, $K$86:$O$86, INDEX( _xlpm.inflation_table, _xlfn.XMATCH( _xlpm.store_currency, _xlpm.inflation_rows, 0 ) + 1, _xlfn.XMATCH( _xlpm.current_year, _xlpm.inflation_column, 0 ) ) )} -> 1 | L87: 1.005 | M87: 1.010025 | N87: 1.0201252 | O87: 1.0456284
B88: =B77 -> USD | C88: n.a. | D88: 0.03 | E88: 0.02 | F88: 0.03 | G88: 0.005 | J88: EUR | K88: 1 | L88: 1.005 | M88: 1.010025 | N88: 1.0201252 | O88: 1.0456284
B89: =B78 -> CAD | C89: n.a. | D89: 0.02 | E89: 0.02 | F89: 0.025 | G89: 0.02 | J89: EUR | K89: 1 | L89: 1.005 | M89: 1.010025 | N89: 1.0201252 | O89: 1.0456284
B90: =B79 -> CHF | C90: n.a. | D90: 0.025 | E90: 0.005 | F90: 0.03 | G90: 0.015 | J90: GBP | K90: 1 | L90: 1.03 | M90: 1.0403 | N90: 1.050703 | O90: 1.06121
B91: =B80 -> RUB | C91: n.a. | D91: 0.01 | E91: 0.01 | F91: 0.015 | G91: 0.01 | J91: USD | K91: 1 | L91: 1.03 | M91: 1.0506 | N91: 1.082118 | O91: 1.0875286
J92: CAD | K92: 1 | L92: 1.02 | M92: 1.0404 | N92: 1.06641 | O92: 1.0877382
J93: CHF | K93: 1 | L93: 1.025 | M93: 1.030125 | N93: 1.0610287 | O93: 1.0769442
J94: RUB | K94: 1 | L94: 1.01 | M94: 1.0201 | N94: 1.0354015 | O94: 1.0457555

Sheet CaseSolution
B2: =CaseData!$J$3&" 5-Year Sales Projections" -> Fashion Boutique 5-Year Sales Projections
G4: Monthly Data | BP4: Annual Summaries
B5: Start Date | G5: =CaseData!J4 -> 44562 | H5: =G6+1 -> 44593 | I5: =H6+1 -> 44621 | J5: =I6+1 -> 44652 | K5: =J6+1 -> 44682 | L5: =K6+1 -> 44713 | M5: =L6+1 -> 44743 | N5: =M6+1 -> 44774 | O5: =N6+1 -> 44805 | ... BN5: =BM6+1 -> 46357 | BP5: =G5 -> 44562 | BQ5: =BP6+1 -> 44927 | BR5: =BQ6+1 -> 45292 | BS5: =BR6+1 -> 45658 | BT5: =BS6+1 -> 46023
B6: End Date | G6: =EOMONTH(G5,0) -> 44592 | H6: =EOMONTH(H5,0) -> 44620 | I6: =EOMONTH(I5,0) -> 44651 | J6: =EOMONTH(J5,0) -> 44681 | K6: =EOMONTH(K5,0) -> 44712 | L6: =EOMONTH(L5,0) -> 44742 | M6: =EOMONTH(M5,0) -> 44773 | N6: =EOMONTH(N5,0) -> 44804 | ... BN6: =EOMONTH(BN5,0) -> 46387 | BP6: =EOMONTH(BP5,11) -> 44926 | BQ6: =EOMONTH(BQ5,11) -> 45291 | BR6: =EOMONTH(BR5,11) -> 45657 | BS6: =EOMONTH(BS5,11) -> 46022 | BT6: =EOMONTH(BT5,11) -> 46387
B7: Year | G7: =YEAR(G5) -> 2022 | H7: =YEAR(H5) -> 2022 | I7: =YEAR(I5) -> 2022 | J7: =YEAR(J5) -> 2022 | K7: =YEAR(K5) -> 2022 | L7: =YEAR(L5) -> 2022 | M7: =YEAR(M5) -> 2022 | N7: =YEAR(N5) -> 2022 | ... BN7: =YEAR(BN5) -> 2026 | BP7: =YEAR(BP5) -> 2022 | BQ7: =YEAR(BQ5) -> 2023 | BR7: =YEAR(BR5) -> 2024 | BS7: =YEAR(BS5) -> 2025 | BT7: =YEAR(BT5) -> 2026
B8: Period # | G8: 1 | H8: =G8+1 -> 2 | I8: =H8+1 -> 3 | J8: =I8+1 -> 4 | K8: =J8+1 -> 5 | L8: =K8+1 -> 6 | M8: =L8+1 -> 7 | N8: =M8+1 -> 8 | O8: =N8+1 -> 9 | ... BN8: =BM8+1 -> 60
B10: Total Sales by Store | G10: =SUM(G11:G18) -> 1003953.5 | H10: =SUM(H11:H18) -> 669302.33 | I10: =SUM(I11:I18) -> 722029.6 | J10: =SUM(J11:J18) -> 726423.54 | K10: =SUM(K11:K18) -> 730817.48 | L10: =SUM(L11:L18) -> 735211.42 | M10: =SUM(M11:M18) -> 1109408 | N10: =SUM(N11:N18) -> 743999.3 | ... BN10: =SUM(BN11:BN18) -> 1813607.5 | BP10: =SUM(BP11:BP18) -> 10046157 | BQ10: =SUM(BQ11:BQ18) -> 15281442 | BR10: =SUM(BR11:BR18) -> 19057818 | BS10: =SUM(BS11:BS18) -> 19633617 | BT10: =SUM(BT11:BT18) -> 19861292
B11: =CaseData!C10 -> Paris | G11: =SUMIFS(G$218:G$241,$B$218:$B$241,$B11) -> 295500 | H11: =SUMIFS(H$218:H$241,$B$218:$B$241,$B11) -> 197000 | I11: =SUMIFS(I$218:I$241,$B$218:$B$241,$B11) -> 197000 | J11: =SUMIFS(J$218:J$241,$B$218:$B$241,$B11) -> 197000 | K11: =SUMIFS(K$218:K$241,$B$218:$B$241,$B11) -> 197000 | L11: =SUMIFS(L$218:L$241,$B$218:$B$241,$B11) -> 197000 | M11: =SUMIFS(M$218:M$241,$B$218:$B$241,$B11) -> 295500 | N11: =SUMIFS(N$218:N$241,$B$218:$B$241,$B11) -> 197000 | ... BN11: =SUMIFS(BN$218:BN$241,$B$218:$B$241,$B11) -> 247186.55 | BP11: =SUMIFS($G11:$BN11,$G$7:$BN$7,BP$7) -> 2600400 | BQ11: =SUMIFS($G11:$BN11,$G$7:$BN$7,BQ$7) -> 2612916.1 | BR11: =SUMIFS($G11:$BN11,$G$7:$BN$7,BR$7) -> 2610822.3 | BS11: =SUMIFS($G11:$BN11,$G$7:$BN$7,BS$7) -> 2634527.1 | BT11: =SUMIFS($G11:$BN11,$G$7:$BN$7,BT$7) -> 2700390.2
B12: =CaseData!C11 -> Milano | G12: =SUMIFS(G$218:G$241,$B$218:$B$241,$B12) -> 345750 | H12: =SUMIFS(H$218:H$241,$B$218:$B$241,$B12) -> 230500 | I12: =SUMIFS(I$218:I$241,$B$218:$B$241,$B12) -> 230500 | J12: =SUMIFS(J$218:J$241,$B$218:$B$241,$B12) -> 230500 | K12: =SUMIFS(K$218:K$241,$B$218:$B$241,$B12) -> 230500 | L12: =SUMIFS(L$218:L$241,$B$218:$B$241,$B12) -> 230500 | M12: =SUMIFS(M$218:M$241,$B$218:$B$241,$B12) -> 345750 | N12: =SUMIFS(N$218:N$241,$B$218:$B$241,$B12) -> 230500 | ... BN12: =SUMIFS(BN$218:BN$241,$B$218:$B$241,$B12) -> 289220.81 | BP12: =SUMIFS($G12:$BN12,$G$7:$BN$7,BP$7) -> 3042600 | BQ12: =SUMIFS($G12:$BN12,$G$7:$BN$7,BQ$7) -> 3057532.7 | BR12: =SUMIFS($G12:$BN12,$G$7:$BN$7,BR$7) -> 3064075.1 | BS12: =SUMIFS($G12:$BN12,$G$7:$BN$7,BS$7) -> 3093329.3 | BT12: =SUMIFS($G12:$BN12,$G$7:$BN$7,BT$7) -> 3170662.5
B13: =CaseData!C12 -> Madrid | G13: =SUMIFS(G$218:G$241,$B$218:$B$241,$B13) -> 180000 | H13: =SUMIFS(H$218:H$241,$B$218:$B$241,$B13) -> 120000 | I13: =SUMIFS(I$218:I$241,$B$218:$B$241,$B13) -> 120000 | J13: =SUMIFS(J$218:J$241,$B$218:$B$241,$B13) -> 120000 | K13: =SUMIFS(K$218:K$241,$B$218:$B$241,$B13) -> 120000 | L13: =SUMIFS(L$218:L$241,$B$218:$B$241,$B13) -> 120000 | M13: =SUMIFS(M$218:M$241,$B$218:$B$241,$B13) -> 180000 | N13: =SUMIFS(N$218:N$241,$B$218:$B$241,$B13) -> 120000 | ... BN13: =SUMIFS(BN$218:BN$241,$B$218:$B$241,$B13) -> 150570.49 | BP13: =SUMIFS($G13:$BN13,$G$7:$BN$7,BP$7) -> 1584000 | BQ13: =SUMIFS($G13:$BN13,$G$7:$BN$7,BQ$7) -> 1591807.9 | BR13: =SUMIFS($G13:$BN13,$G$7:$BN$7,BR$7) -> 1596268.8 | BS13: =SUMIFS($G13:$BN13,$G$7:$BN$7,BS$7) -> 1611676.9 | BT13: =SUMIFS($G13:$BN13,$G$7:$BN$7,BT$7) -> 1651968.8
B14: =CaseData!C13 -> London | G14: =SUMIFS(G$218:G$241,$B$218:$B$241,$B14) -> 182703.49 | H14: =SUMIFS(H$218:H$241,$B$218:$B$241,$B14) -> 121802.33 | I14: =SUMIFS(I$218:I$241,$B$218:$B$241,$B14) -> 121802.33 | J14: =SUMIFS(J$218:J$241,$B$218:$B$241,$B14) -> 121802.33 | K14: =SUMIFS(K$218:K$241,$B$218:$B$241,$B14) -> 121802.33 | L14: =SUMIFS(L$218:L$241,$B$218:$B$241,$B14) -> 121802.33 | M14: =SUMIFS(M$218:M$241,$B$218:$B$241,$B14) -> 182703.49 | N14: =SUMIFS(N$218:N$241,$B$218:$B$241,$B14) -> 121802.33 | ... BN14: =SUMIFS(BN$218:BN$241,$B$218:$B$241,$B14) -> 148215.67 | BP14: =SUMIFS($G14:$BN14,$G$7:$BN$7,BP$7) -> 1607790.7 | BQ14: =SUMIFS($G14:$BN14,$G$7:$BN$7,BQ$7) -> 1636806.2 | BR14: =SUMIFS($G14:$BN14,$G$7:$BN$7,BR$7) -> 1628701.7 | BS14: =SUMIFS($G14:$BN14,$G$7:$BN$7,BS$7) -> 1625614.2 | BT14: =SUMIFS($G14:$BN14,$G$7:$BN$7,BT$7) -> 1623627.4
B15: =CaseData!C14 -> New York | G15: =SUMIFS(G$218:G$241,$B$218:$B$241,$B15) -> 0 | H15: =SUMIFS(H$218:H$241,$B$218:$B$241,$B15) -> 0 | I15: =SUMIFS(I$218:I$241,$B$218:$B$241,$B15) -> 52727.273 | J15: =SUMIFS(J$218:J$241,$B$218:$B$241,$B15) -> 57121.212 | K15: =SUMIFS(K$218:K$241,$B$218:$B$241,$B15) -> 61515.152 | L15: =SUMIFS(L$218:L$241,$B$218:$B$241,$B15) -> 65909.091 | M15: =SUMIFS(M$218:M$241,$B$218:$B$241,$B15) -> 105454.55 | N15: =SUMIFS(N$218:N$241,$B$218:$B$241,$B15) -> 74696.97 | ... BN15: =SUMIFS(BN$218:BN$241,$B$218:$B$241,$B15) -> 132792.96 | BP15: =SUMIFS($G15:$BN15,$G$7:$BN$7,BP$7) -> 778606.06 | BQ15: =SUMIFS($G15:$BN15,$G$7:$BN$7,BQ$7) -> 1402730.8 | BR15: =SUMIFS($G15:$BN15,$G$7:$BN$7,BR$7) -> 1430731.3 | BS15: =SUMIFS($G15:$BN15,$G$7:$BN$7,BS$7) -> 1459744.2 | BT15: =SUMIFS($G15:$BN15,$G$7:$BN$7,BT$7) -> 1454174.2
B16: =CaseData!C15 -> Montreal | G16: =SUMIFS(G$218:G$241,$B$218:$B$241,$B16) -> 0 | H16: =SUMIFS(H$218:H$241,$B$218:$B$241,$B16) -> 0 | I16: =SUMIFS(I$218:I$241,$B$218:$B$241,$B16) -> 0 | J16: =SUMIFS(J$218:J$241,$B$218:$B$241,$B16) -> 0 | K16: =SUMIFS(K$218:K$241,$B$218:$B$241,$B16) -> 0 | L16: =SUMIFS(L$218:L$241,$B$218:$B$241,$B16) -> 0 | M16: =SUMIFS(M$218:M$241,$B$218:$B$241,$B16) -> 0 | N16: =SUMIFS(N$218:N$241,$B$218:$B$241,$B16) -> 0 | ... BN16: =SUMIFS(BN$218:BN$241,$B$218:$B$241,$B16) -> 231624.25 | BP16: =SUMIFS($G16:$BN16,$G$7:$BN$7,BP$7) -> 432760.07 | BQ16: =SUMIFS($G16:$BN16,$G$7:$BN$7,BQ$7) -> 2121189.7 | BR16: =SUMIFS($G16:$BN16,$G$7:$BN$7,BR$7) -> 2455030.4 | BS16: =SUMIFS($G16:$BN16,$G$7:$BN$7,BS$7) -> 2497646.9 | BT16: =SUMIFS($G16:$BN16,$G$7:$BN$7,BT$7) -> 2530948.8
B17: =CaseData!C16 -> Zurich | G17: =SUMIFS(G$218:G$241,$B$218:$B$241,$B17) -> 0 | H17: =SUMIFS(H$218:H$241,$B$218:$B$241,$B17) -> 0 | I17: =SUMIFS(I$218:I$241,$B$218:$B$241,$B17) -> 0 | J17: =SUMIFS(J$218:J$241,$B$218:$B$241,$B17) -> 0 | K17: =SUMIFS(K$218:K$241,$B$218:$B$241,$B17) -> 0 | L17: =SUMIFS(L$218:L$241,$B$218:$B$241,$B17) -> 0 | M17: =SUMIFS(M$218:M$241,$B$218:$B$241,$B17) -> 0 | N17: =SUMIFS(N$218:N$241,$B$218:$B$241,$B17) -> 0 | ... BN17: =SUMIFS(BN$218:BN$241,$B$218:$B$241,$B17) -> 406203.76 | BP17: =SUMIFS($G17:$BN17,$G$7:$BN$7,BP$7) -> 0 | BQ17: =SUMIFS($G17:$BN17,$G$7:$BN$7,BQ$7) -> 2445160.1 | BR17: =SUMIFS($G17:$BN17,$G$7:$BN$7,BR$7) -> 4285861.8 | BS17: =SUMIFS($G17:$BN17,$G$7:$BN$7,BS$7) -> 4427561.1 | BT17: =SUMIFS($G17:$BN17,$G$7:$BN$7,BT$7) -> 4453120.2
B18: =CaseData!C17 -> Moscow | G18: =SUMIFS(G$218:G$241,$B$218:$B$241,$B18) -> 0 | H18: =SUMIFS(H$218:H$241,$B$218:$B$241,$B18) -> 0 | I18: =SUMIFS(I$218:I$241,$B$218:$B$241,$B18) -> 0 | J18: =SUMIFS(J$218:J$241,$B$218:$B$241,$B18) -> 0 | K18: =SUMIFS(K$218:K$241,$B$218:$B$241,$B18) -> 0 | L18: =SUMIFS(L$218:L$241,$B$218:$B$241,$B18) -> 0 | M18: =SUMIFS(M$218:M$241,$B$218:$B$241,$B18) -> 0 | N18: =SUMIFS(N$218:N$241,$B$218:$B$241,$B18) -> 0 | ... BN18: =SUMIFS(BN$218:BN$241,$B$218:$B$241,$B18) -> 207792.98 | BP18: =SUMIFS($G18:$BN18,$G$7:$BN$7,BP$7) -> 0 | BQ18: =SUMIFS($G18:$BN18,$G$7:$BN$7,BQ$7) -> 413298.14 | BR18: =SUMIFS($G18:$BN18,$G$7:$BN$7,BR$7) -> 1986326.7 | BS18: =SUMIFS($G18:$BN18,$G$7:$BN$7,BS$7) -> 2283517.5 | BT18: =SUMIFS($G18:$BN18,$G$7:$BN$7,BT$7) -> 2276400.1
B20: Total Sales by Category | G20: =SUM(G21:G23) -> 1003953.5 | H20: =SUM(H21:H23) -> 669302.33 | I20: =SUM(I21:I23) -> 722029.6 | J20: =SUM(J21:J23) -> 726423.54 | K20: =SUM(K21:K23) -> 730817.48 | L20: =SUM(L21:L23) -> 735211.42 | M20: =SUM(M21:M23) -> 1109408 | N20: =SUM(N21:N23) -> 743999.3 | ... BN20: =SUM(BN21:BN23) -> 1813607.5 | BP20: =SUM(BP21:BP23) -> 10046157 | BQ20: =SUM(BQ21:BQ23) -> 15281442 | BR20: =SUM(BR21:BR23) -> 19057818 | BS20: =SUM(BS21:BS23) -> 19633617 | BT20: =SUM(BT21:BT23) -> 19861292
B21: =CaseData!$C$27 -> Women's | G21: =SUMIFS(G$218:G$241,$C$218:$C$241,$B21) -> 539040.7 | H21: =SUMIFS(H$218:H$241,$C$218:$C$241,$B21) -> 359360.47 | I21: =SUMIFS(I$218:I$241,$C$218:$C$241,$B21) -> 383110.47 | J21: =SUMIFS(J$218:J$241,$C$218:$C$241,$B21) -> 385089.63 | K21: =SUMIFS(K$218:K$241,$C$218:$C$241,$B21) -> 387068.8 | L21: =SUMIFS(L$218:L$241,$C$218:$C$241,$B21) -> 389047.97 | M21: =SUMIFS(M$218:M$241,$C$218:$C$241,$B21) -> 586540.7 | N21: =SUMIFS(N$218:N$241,$C$218:$C$241,$B21) -> 393006.3 | ... BN21: =SUMIFS(BN$218:BN$241,$C$218:$C$241,$B21) -> 961474.87 | BP21: =SUMIFS($G21:$BN21,$G$7:$BN$7,BP$7) -> 5295105.4 | BQ21: =SUMIFS($G21:$BN21,$G$7:$BN$7,BQ$7) -> 8074642.9 | BR21: =SUMIFS($G21:$BN21,$G$7:$BN$7,BR$7) -> 10145021 | BS21: =SUMIFS($G21:$BN21,$G$7:$BN$7,BS$7) -> 10449215 | BT21: =SUMIFS($G21:$BN21,$G$7:$BN$7,BT$7) -> 10576224
B22: =CaseData!$D$27 -> Men's | G22: =SUMIFS(G$218:G$241,$C$218:$C$241,$B22) -> 337360.47 | H22: =SUMIFS(H$218:H$241,$C$218:$C$241,$B22) -> 224906.98 | I22: =SUMIFS(I$218:I$241,$C$218:$C$241,$B22) -> 247066.07 | J22: =SUMIFS(J$218:J$241,$C$218:$C$241,$B22) -> 248912.66 | K22: =SUMIFS(K$218:K$241,$C$218:$C$241,$B22) -> 250759.25 | L22: =SUMIFS(L$218:L$241,$C$218:$C$241,$B22) -> 252605.84 | M22: =SUMIFS(M$218:M$241,$C$218:$C$241,$B22) -> 381678.65 | N22: =SUMIFS(N$218:N$241,$C$218:$C$241,$B22) -> 256299.02 | ... BN22: =SUMIFS(BN$218:BN$241,$C$218:$C$241,$B22) -> 620354.09 | BP22: =SUMIFS($G22:$BN22,$G$7:$BN$7,BP$7) -> 3445023.2 | BQ22: =SUMIFS($G22:$BN22,$G$7:$BN$7,BQ$7) -> 5203017.9 | BR22: =SUMIFS($G22:$BN22,$G$7:$BN$7,BR$7) -> 6537941.4 | BS22: =SUMIFS($G22:$BN22,$G$7:$BN$7,BS$7) -> 6753014.2 | BT22: =SUMIFS($G22:$BN22,$G$7:$BN$7,BT$7) -> 6823894.9
B23: =CaseData!$E$27 -> Accessories | G23: =SUMIFS(G$218:G$241,$C$218:$C$241,$B23) -> 127552.33 | H23: =SUMIFS(H$218:H$241,$C$218:$C$241,$B23) -> 85034.884 | I23: =SUMIFS(I$218:I$241,$C$218:$C$241,$B23) -> 91853.066 | J23: =SUMIFS(J$218:J$241,$C$218:$C$241,$B23) -> 92421.247 | K23: =SUMIFS(K$218:K$241,$C$218:$C$241,$B23) -> 92989.429 | L23: =SUMIFS(L$218:L$241,$C$218:$C$241,$B23) -> 93557.611 | M23: =SUMIFS(M$218:M$241,$C$218:$C$241,$B23) -> 141188.69 | N23: =SUMIFS(N$218:N$241,$C$218:$C$241,$B23) -> 94693.975 | ... BN23: =SUMIFS(BN$218:BN$241,$C$218:$C$241,$B23) -> 231778.51 | BP23: =SUMIFS($G23:$BN23,$G$7:$BN$7,BP$7) -> 1306028.2 | BQ23: =SUMIFS($G23:$BN23,$G$7:$BN$7,BQ$7) -> 2003780.7 | BR23: =SUMIFS($G23:$BN23,$G$7:$BN$7,BR$7) -> 2374855.8 | BS23: =SUMIFS($G23:$BN23,$G$7:$BN$7,BS$7) -> 2431388.1 | BT23: =SUMIFS($G23:$BN23,$G$7:$BN$7,BT$7) -> 2461173.5
B25: Total Sales by Country | G25: =SUM(G26:G33) -> 1003953.5 | H25: =SUM(H26:H33) -> 669302.33 | I25: =SUM(I26:I33) -> 722029.6 | J25: =SUM(J26:J33) -> 726423.54 | K25: =SUM(K26:K33) -> 730817.48 | L25: =SUM(L26:L33) -> 735211.42 | M25: =SUM(M26:M33) -> 1109408 | N25: =SUM(N26:N33) -> 743999.3 | ... BN25: =SUM(BN26:BN33) -> 1813607.5 | BP25: =SUM(BP26:BP33) -> 10046157 | BQ25: =SUM(BQ26:BQ33) -> 15281442 | BR25: =SUM(BR26:BR33) -> 19057818 | BS25: =SUM(BS26:BS33) -> 19633617 | BT25: =SUM(BT26:BT33) -> 19861292
B26: =CaseData!D10 -> France | G26: =SUMIFS(G$218:G$241,$E$218:$E$241,$B26) -> 295500 | H26: =SUMIFS(H$218:H$241,$E$218:$E$241,$B26) -> 197000 | I26: =SUMIFS(I$218:I$241,$E$218:$E$241,$B26) -> 197000 | J26: =SUMIFS(J$218:J$241,$E$218:$E$241,$B26) -> 197000 | K26: =SUMIFS(K$218:K$241,$E$218:$E$241,$B26) -> 197000 | L26: =SUMIFS(L$218:L$241,$E$218:$E$241,$B26) -> 197000 | M26: =SUMIFS(M$218:M$241,$E$218:$E$241,$B26) -> 295500 | N26: =SUMIFS(N$218:N$241,$E$218:$E$241,$B26) -> 197000 | ... BN26: =SUMIFS(BN$218:BN$241,$E$218:$E$241,$B26) -> 247186.55 | BP26: =SUMIFS($G26:$BN26,$G$7:$BN$7,BP$7) -> 2600400 | BQ26: =SUMIFS($G26:$BN26,$G$7:$BN$7,BQ$7) -> 2612916.1 | BR26: =SUMIFS($G26:$BN26,$G$7:$BN$7,BR$7) -> 2610822.3 | BS26: =SUMIFS($G26:$BN26,$G$7:$BN$7,BS$7) -> 2634527.1 | BT26: =SUMIFS($G26:$BN26,$G$7:$BN$7,BT$7) -> 2700390.2
B27: =CaseData!D11 -> Italy | G27: =SUMIFS(G$218:G$241,$E$218:$E$241,$B27) -> 345750 | H27: =SUMIFS(H$218:H$241,$E$218:$E$241,$B27) -> 230500 | I27: =SUMIFS(I$218:I$241,$E$218:$E$241,$B27) -> 230500 | J27: =SUMIFS(J$218:J$241,$E$218:$E$241,$B27) -> 230500 | K27: =SUMIFS(K$218:K$241,$E$218:$E$241,$B27) -> 230500 | L27: =SUMIFS(L$218:L$241,$E$218:$E$241,$B27) -> 230500 | M27: =SUMIFS(M$218:M$241,$E$218:$E$241,$B27) -> 345750 | N27: =SUMIFS(N$218:N$241,$E$218:$E$241,$B27) -> 230500 | ... BN27: =SUMIFS(BN$218:BN$241,$E$218:$E$241,$B27) -> 289220.81 | BP27: =SUMIFS($G27:$BN27,$G$7:$BN$7,BP$7) -> 3042600 | BQ27: =SUMIFS($G27:$BN27,$G$7:$BN$7,BQ$7) -> 3057532.7 | BR27: =SUMIFS($G27:$BN27,$G$7:$BN$7,BR$7) -> 3064075.1 | BS27: =SUMIFS($G27:$BN27,$G$7:$BN$7,BS$7) -> 3093329.3 | BT27: =SUMIFS($G27:$BN27,$G$7:$BN$7,BT$7) -> 3170662.5
B28: =CaseData!D12 -> Spain | G28: =SUMIFS(G$218:G$241,$E$218:$E$241,$B28) -> 180000 | H28: =SUMIFS(H$218:H$241,$E$218:$E$241,$B28) -> 120000 | I28: =SUMIFS(I$218:I$241,$E$218:$E$241,$B28) -> 120000 | J28: =SUMIFS(J$218:J$241,$E$218:$E$241,$B28) -> 120000 | K28: =SUMIFS(K$218:K$241,$E$218:$E$241,$B28) -> 120000 | L28: =SUMIFS(L$218:L$241,$E$218:$E$241,$B28) -> 120000 | M28: =SUMIFS(M$218:M$241,$E$218:$E$241,$B28) -> 180000 | N28: =SUMIFS(N$218:N$241,$E$218:$E$241,$B28) -> 120000 | ... BN28: =SUMIFS(BN$218:BN$241,$E$218:$E$241,$B28) -> 150570.49 | BP28: =SUMIFS($G28:$BN28,$G$7:$BN$7,BP$7) -> 1584000 | BQ28: =SUMIFS($G28:$BN28,$G$7:$BN$7,BQ$7) -> 1591807.9 | BR28: =SUMIFS($G28:$BN28,$G$7:$BN$7,BR$7) -> 1596268.8 | BS28: =SUMIFS($G28:$BN28,$G$7:$BN$7,BS$7) -> 1611676.9 | BT28: =SUMIFS($G28:$BN28,$G$7:$BN$7,BT$7) -> 1651968.8
B29: =CaseData!D13 -> UK | G29: =SUMIFS(G$218:G$241,$E$218:$E$241,$B29) -> 182703.49 | H29: =SUMIFS(H$218:H$241,$E$218:$E$241,$B29) -> 121802.33 | I29: =SUMIFS(I$218:I$241,$E$218:$E$241,$B29) -> 121802.33 | J29: =SUMIFS(J$218:J$241,$E$218:$E$241,$B29) -> 121802.33 | K29: =SUMIFS(K$218:K$241,$E$218:$E$241,$B29) -> 121802.33 | L29: =SUMIFS(L$218:L$241,$E$218:$E$241,$B29) -> 121802.33 | M29: =SUMIFS(M$218:M$241,$E$218:$E$241,$B29) -> 182703.49 | N29: =SUMIFS(N$218:N$241,$E$218:$E$241,$B29) -> 121802.33 | ... BN29: =SUMIFS(BN$218:BN$241,$E$218:$E$241,$B29) -> 148215.67 | BP29: =SUMIFS($G29:$BN29,$G$7:$BN$7,BP$7) -> 1607790.7 | BQ29: =SUMIFS($G29:$BN29,$G$7:$BN$7,BQ$7) -> 1636806.2 | BR29: =SUMIFS($G29:$BN29,$G$7:$BN$7,BR$7) -> 1628701.7 | BS29: =SUMIFS($G29:$BN29,$G$7:$BN$7,BS$7) -> 1625614.2 | BT29: =SUMIFS($G29:$BN29,$G$7:$BN$7,BT$7) -> 1623627.4
B30: =CaseData!D14 -> US | G30: =SUMIFS(G$218:G$241,$E$218:$E$241,$B30) -> 0 | H30: =SUMIFS(H$218:H$241,$E$218:$E$241,$B30) -> 0 | I30: =SUMIFS(I$218:I$241,$E$218:$E$241,$B30) -> 52727.273 | J30: =SUMIFS(J$218:J$241,$E$218:$E$241,$B30) -> 57121.212 | K30: =SUMIFS(K$218:K$241,$E$218:$E$241,$B30) -> 61515.152 | L30: =SUMIFS(L$218:L$241,$E$218:$E$241,$B30) -> 65909.091 | M30: =SUMIFS(M$218:M$241,$E$218:$E$241,$B30) -> 105454.55 | N30: =SUMIFS(N$218:N$241,$E$218:$E$241,$B30) -> 74696.97 | ... BN30: =SUMIFS(BN$218:BN$241,$E$218:$E$241,$B30) -> 132792.96 | BP30: =SUMIFS($G30:$BN30,$G$7:$BN$7,BP$7) -> 778606.06 | BQ30: =SUMIFS($G30:$BN30,$G$7:$BN$7,BQ$7) -> 1402730.8 | BR30: =SUMIFS($G30:$BN30,$G$7:$BN$7,BR$7) -> 1430731.3 | BS30: =SUMIFS($G30:$BN30,$G$7:$BN$7,BS$7) -> 1459744.2 | BT30: =SUMIFS($G30:$BN30,$G$7:$BN$7,BT$7) -> 1454174.2
B31: =CaseData!D15 -> Canada | G31: =SUMIFS(G$218:G$241,$E$218:$E$241,$B31) -> 0 | H31: =SUMIFS(H$218:H$241,$E$218:$E$241,$B31) -> 0 | I31: =SUMIFS(I$218:I$241,$E$218:$E$241,$B31) -> 0 | J31: =SUMIFS(J$218:J$241,$E$218:$E$241,$B31) -> 0 | K31: =SUMIFS(K$218:K$241,$E$218:$E$241,$B31) -> 0 | L31: =SUMIFS(L$218:L$241,$E$218:$E$241,$B31) -> 0 | M31: =SUMIFS(M$218:M$241,$E$218:$E$241,$B31) -> 0 | N31: =SUMIFS(N$218:N$241,$E$218:$E$241,$B31) -> 0 | ... BN31: =SUMIFS(BN$218:BN$241,$E$218:$E$241,$B31) -> 231624.25 | BP31: =SUMIFS($G31:$BN31,$G$7:$BN$7,BP$7) -> 432760.07 | BQ31: =SUMIFS($G31:$BN31,$G$7:$BN$7,BQ$7) -> 2121189.7 | BR31: =SUMIFS($G31:$BN31,$G$7:$BN$7,BR$7) -> 2455030.4 | BS31: =SUMIFS($G31:$BN31,$G$7:$BN$7,BS$7) -> 2497646.9 | BT31: =SUMIFS($G31:$BN31,$G$7:$BN$7,BT$7) -> 2530948.8
B32: =CaseData!D16 -> Switzerland | G32: =SUMIFS(G$218:G$241,$E$218:$E$241,$B32) -> 0 | H32: =SUMIFS(H$218:H$241,$E$218:$E$241,$B32) -> 0 | I32: =SUMIFS(I$218:I$241,$E$218:$E$241,$B32) -> 0 | J32: =SUMIFS(J$218:J$241,$E$218:$E$241,$B32) -> 0 | K32: =SUMIFS(K$218:K$241,$E$218:$E$241,$B32) -> 0 | L32: =SUMIFS(L$218:L$241,$E$218:$E$241,$B32) -> 0 | M32: =SUMIFS(M$218:M$241,$E$218:$E$241,$B32) -> 0 | N32: =SUMIFS(N$218:N$241,$E$218:$E$241,$B32) -> 0 | ... BN32: =SUMIFS(BN$218:BN$241,$E$218:$E$241,$B32) -> 406203.76 | BP32: =SUMIFS($G32:$BN32,$G$7:$BN$7,BP$7) -> 0 | BQ32: =SUMIFS($G32:$BN32,$G$7:$BN$7,BQ$7) -> 2445160.1 | BR32: =SUMIFS($G32:$BN32,$G$7:$BN$7,BR$7) -> 4285861.8 | BS32: =SUMIFS($G32:$BN32,$G$7:$BN$7,BS$7) -> 4427561.1 | BT32: =SUMIFS($G32:$BN32,$G$7:$BN$7,BT$7) -> 4453120.2
B33: =CaseData!D17 -> Russia | G33: =SUMIFS(G$218:G$241,$E$218:$E$241,$B33) -> 0 | H33: =SUMIFS(H$218:H$241,$E$218:$E$241,$B33) -> 0 | I33: =SUMIFS(I$218:I$241,$E$218:$E$241,$B33) -> 0 | J33: =SUMIFS(J$218:J$241,$E$218:$E$241,$B33) -> 0 | K33: =SUMIFS(K$218:K$241,$E$218:$E$241,$B33) -> 0 | L33: =SUMIFS(L$218:L$241,$E$218:$E$241,$B33) -> 0 | M33: =SUMIFS(M$218:M$241,$E$218:$E$241,$B33) -> 0 | N33: =SUMIFS(N$218:N$241,$E$218:$E$241,$B33) -> 0 | ... BN33: =SUMIFS(BN$218:BN$241,$E$218:$E$241,$B33) -> 207792.98 | BP33: =SUMIFS($G33:$BN33,$G$7:$BN$7,BP$7) -> 0 | BQ33: =SUMIFS($G33:$BN33,$G$7:$BN$7,BQ$7) -> 413298.14 | BR33: =SUMIFS($G33:$BN33,$G$7:$BN$7,BR$7) -> 1986326.7 | BS33: =SUMIFS($G33:$BN33,$G$7:$BN$7,BS$7) -> 2283517.5 | BT33: =SUMIFS($G33:$BN33,$G$7:$BN$7,BT$7) -> 2276400.1
B35: A. Support Calculations. Unit Sales
B37: Unit Sales - Base Case (Before Seasonality and MOO Adjustments)
B38: Store | C38: Type
B39: =CaseData!$B$28 -> Paris | C39: =CaseData!C27 -> Women's | G39: =INDEX(CaseData!$B$27:$E$35,MATCH($B39,CaseData!$B$27:$B$35,0),MATCH($C39,CaseData!$B$27:$E$27,0)) -> 180 | H39: =INDEX(CaseData!$B$27:$E$35,MATCH($B39,CaseData!$B$27:$B$35,0),MATCH($C39,CaseData!$B$27:$E$27,0)) -> 180 | I39: =INDEX(CaseData!$B$27:$E$35,MATCH($B39,CaseData!$B$27:$B$35,0),MATCH($C39,CaseData!$B$27:$E$27,0)) -> 180 | J39: =INDEX(CaseData!$B$27:$E$35,MATCH($B39,CaseData!$B$27:$B$35,0),MATCH($C39,CaseData!$B$27:$E$27,0)) -> 180 | K39: =INDEX(CaseData!$B$27:$E$35,MATCH($B39,CaseData!$B$27:$B$35,0),MATCH($C39,CaseData!$B$27:$E$27,0)) -> 180 | L39: =INDEX(CaseData!$B$27:$E$35,MATCH($B39,CaseData!$B$27:$B$35,0),MATCH($C39,CaseData!$B$27:$E$27,0)) -> 180 | M39: =INDEX(CaseData!$B$27:$E$35,MATCH($B39,CaseData!$B$27:$B$35,0),MATCH($C39,CaseData!$B$27:$E$27,0)) -> 180 | N39: =INDEX(CaseData!$B$27:$E$35,MATCH($B39,CaseData!$B$27:$B$35,0),MATCH($C39,CaseData!$B$27:$E$27,0)) -> 180 | ... BN39: =INDEX(CaseData!$B$27:$E$35,MATCH($B39,CaseData!$B$27:$B$35,0),MATCH($C39,CaseData!$B$27:$E$27,0)) -> 180
B40: =B39 -> Paris | C40: =CaseData!D27 -> Men's | G40: =INDEX(CaseData!$B$27:$E$35,MATCH($B40,CaseData!$B$27:$B$35,0),MATCH($C40,CaseData!$B$27:$E$27,0)) -> 170 | H40: =INDEX(CaseData!$B$27:$E$35,MATCH($B40,CaseData!$B$27:$B$35,0),MATCH($C40,CaseData!$B$27:$E$27,0)) -> 170 | I40: =INDEX(CaseData!$B$27:$E$35,MATCH($B40,CaseData!$B$27:$B$35,0),MATCH($C40,CaseData!$B$27:$E$27,0)) -> 170 | J40: =INDEX(CaseData!$B$27:$E$35,MATCH($B40,CaseData!$B$27:$B$35,0),MATCH($C40,CaseData!$B$27:$E$27,0)) -> 170 | K40: =INDEX(CaseData!$B$27:$E$35,MATCH($B40,CaseData!$B$27:$B$35,0),MATCH($C40,CaseData!$B$27:$E$27,0)) -> 170 | L40: =INDEX(CaseData!$B$27:$E$35,MATCH($B40,CaseData!$B$27:$B$35,0),MATCH($C40,CaseData!$B$27:$E$27,0)) -> 170 | M40: =INDEX(CaseData!$B$27:$E$35,MATCH($B40,CaseData!$B$27:$B$35,0),MATCH($C40,CaseData!$B$27:$E$27,0)) -> 170 | N40: =INDEX(CaseData!$B$27:$E$35,MATCH($B40,CaseData!$B$27:$B$35,0),MATCH($C40,CaseData!$B$27:$E$27,0)) -> 170 | ... BN40: =INDEX(CaseData!$B$27:$E$35,MATCH($B40,CaseData!$B$27:$B$35,0),MATCH($C40,CaseData!$B$27:$E$27,0)) -> 170
B41: =B40 -> Paris | C41: =CaseData!E27 -> Accessories | G41: =INDEX(CaseData!$B$27:$E$35,MATCH($B41,CaseData!$B$27:$B$35,0),MATCH($C41,CaseData!$B$27:$E$27,0)) -> 260 | H41: =INDEX(CaseData!$B$27:$E$35,MATCH($B41,CaseData!$B$27:$B$35,0),MATCH($C41,CaseData!$B$27:$E$27,0)) -> 260 | I41: =INDEX(CaseData!$B$27:$E$35,MATCH($B41,CaseData!$B$27:$B$35,0),MATCH($C41,CaseData!$B$27:$E$27,0)) -> 260 | J41: =INDEX(CaseData!$B$27:$E$35,MATCH($B41,CaseData!$B$27:$B$35,0),MATCH($C41,CaseData!$B$27:$E$27,0)) -> 260 | K41: =INDEX(CaseData!$B$27:$E$35,MATCH($B41,CaseData!$B$27:$B$35,0),MATCH($C41,CaseData!$B$27:$E$27,0)) -> 260 | L41: =INDEX(CaseData!$B$27:$E$35,MATCH($B41,CaseData!$B$27:$B$35,0),MATCH($C41,CaseData!$B$27:$E$27,0)) -> 260 | M41: =INDEX(CaseData!$B$27:$E$35,MATCH($B41,CaseData!$B$27:$B$35,0),MATCH($C41,CaseData!$B$27:$E$27,0)) -> 260 | N41: =INDEX(CaseData!$B$27:$E$35,MATCH($B41,CaseData!$B$27:$B$35,0),MATCH($C41,CaseData!$B$27:$E$27,0)) -> 260 | ... BN41: =INDEX(CaseData!$B$27:$E$35,MATCH($B41,CaseData!$B$27:$B$35,0),MATCH($C41,CaseData!$B$27:$E$27,0)) -> 260
B42: =CaseData!$B$29 -> Milano | C42: =C39 -> Women's | G42: =INDEX(CaseData!$B$27:$E$35,MATCH($B42,CaseData!$B$27:$B$35,0),MATCH($C42,CaseData!$B$27:$E$27,0)) -> 280 | H42: =INDEX(CaseData!$B$27:$E$35,MATCH($B42,CaseData!$B$27:$B$35,0),MATCH($C42,CaseData!$B$27:$E$27,0)) -> 280 | I42: =INDEX(CaseData!$B$27:$E$35,MATCH($B42,CaseData!$B$27:$B$35,0),MATCH($C42,CaseData!$B$27:$E$27,0)) -> 280 | J42: =INDEX(CaseData!$B$27:$E$35,MATCH($B42,CaseData!$B$27:$B$35,0),MATCH($C42,CaseData!$B$27:$E$27,0)) -> 280 | K42: =INDEX(CaseData!$B$27:$E$35,MATCH($B42,CaseData!$B$27:$B$35,0),MATCH($C42,CaseData!$B$27:$E$27,0)) -> 280 | L42: =INDEX(CaseData!$B$27:$E$35,MATCH($B42,CaseData!$B$27:$B$35,0),MATCH($C42,CaseData!$B$27:$E$27,0)) -> 280 | M42: =INDEX(CaseData!$B$27:$E$35,MATCH($B42,CaseData!$B$27:$B$35,0),MATCH($C42,CaseData!$B$27:$E$27,0)) -> 280 | N42: =INDEX(CaseData!$B$27:$E$35,MATCH($B42,CaseData!$B$27:$B$35,0),MATCH($C42,CaseData!$B$27:$E$27,0)) -> 280 | ... BN42: =INDEX(CaseData!$B$27:$E$35,MATCH($B42,CaseData!$B$27:$B$35,0),MATCH($C42,CaseData!$B$27:$E$27,0)) -> 280
B43: =B42 -> Milano | C43: =C40 -> Men's | G43: =INDEX(CaseData!$B$27:$E$35,MATCH($B43,CaseData!$B$27:$B$35,0),MATCH($C43,CaseData!$B$27:$E$27,0)) -> 170 | H43: =INDEX(CaseData!$B$27:$E$35,MATCH($B43,CaseData!$B$27:$B$35,0),MATCH($C43,CaseData!$B$27:$E$27,0)) -> 170 | I43: =INDEX(CaseData!$B$27:$E$35,MATCH($B43,CaseData!$B$27:$B$35,0),MATCH($C43,CaseData!$B$27:$E$27,0)) -> 170 | J43: =INDEX(CaseData!$B$27:$E$35,MATCH($B43,CaseData!$B$27:$B$35,0),MATCH($C43,CaseData!$B$27:$E$27,0)) -> 170 | K43: =INDEX(CaseData!$B$27:$E$35,MATCH($B43,CaseData!$B$27:$B$35,0),MATCH($C43,CaseData!$B$27:$E$27,0)) -> 170 | L43: =INDEX(CaseData!$B$27:$E$35,MATCH($B43,CaseData!$B$27:$B$35,0),MATCH($C43,CaseData!$B$27:$E$27,0)) -> 170 | M43: =INDEX(CaseData!$B$27:$E$35,MATCH($B43,CaseData!$B$27:$B$35,0),MATCH($C43,CaseData!$B$27:$E$27,0)) -> 170 | N43: =INDEX(CaseData!$B$27:$E$35,MATCH($B43,CaseData!$B$27:$B$35,0),MATCH($C43,CaseData!$B$27:$E$27,0)) -> 170 | ... BN43: =INDEX(CaseData!$B$27:$E$35,MATCH($B43,CaseData!$B$27:$B$35,0),MATCH($C43,CaseData!$B$27:$E$27,0)) -> 170
B44: =B43 -> Milano | C44: =C41 -> Accessories | G44: =INDEX(CaseData!$B$27:$E$35,MATCH($B44,CaseData!$B$27:$B$35,0),MATCH($C44,CaseData!$B$27:$E$27,0)) -> 150 | H44: =INDEX(CaseData!$B$27:$E$35,MATCH($B44,CaseData!$B$27:$B$35,0),MATCH($C44,CaseData!$B$27:$E$27,0)) -> 150 | I44: =INDEX(CaseData!$B$27:$E$35,MATCH($B44,CaseData!$B$27:$B$35,0),MATCH($C44,CaseData!$B$27:$E$27,0)) -> 150 | J44: =INDEX(CaseData!$B$27:$E$35,MATCH($B44,CaseData!$B$27:$B$35,0),MATCH($C44,CaseData!$B$27:$E$27,0)) -> 150 | K44: =INDEX(CaseData!$B$27:$E$35,MATCH($B44,CaseData!$B$27:$B$35,0),MATCH($C44,CaseData!$B$27:$E$27,0)) -> 150 | L44: =INDEX(CaseData!$B$27:$E$35,MATCH($B44,CaseData!$B$27:$B$35,0),MATCH($C44,CaseData!$B$27:$E$27,0)) -> 150 | M44: =INDEX(CaseData!$B$27:$E$35,MATCH($B44,CaseData!$B$27:$B$35,0),MATCH($C44,CaseData!$B$27:$E$27,0)) -> 150 | N44: =INDEX(CaseData!$B$27:$E$35,MATCH($B44,CaseData!$B$27:$B$35,0),MATCH($C44,CaseData!$B$27:$E$27,0)) -> 150 | ... BN44: =INDEX(CaseData!$B$27:$E$35,MATCH($B44,CaseData!$B$27:$B$35,0),MATCH($C44,CaseData!$B$27:$E$27,0)) -> 150
B45: =CaseData!$B$30 -> Madrid | C45: =C42 -> Women's | G45: =INDEX(CaseData!$B$27:$E$35,MATCH($B45,CaseData!$B$27:$B$35,0),MATCH($C45,CaseData!$B$27:$E$27,0)) -> 150 | H45: =INDEX(CaseData!$B$27:$E$35,MATCH($B45,CaseData!$B$27:$B$35,0),MATCH($C45,CaseData!$B$27:$E$27,0)) -> 150 | I45: =INDEX(CaseData!$B$27:$E$35,MATCH($B45,CaseData!$B$27:$B$35,0),MATCH($C45,CaseData!$B$27:$E$27,0)) -> 150 | J45: =INDEX(CaseData!$B$27:$E$35,MATCH($B45,CaseData!$B$27:$B$35,0),MATCH($C45,CaseData!$B$27:$E$27,0)) -> 150 | K45: =INDEX(CaseData!$B$27:$E$35,MATCH($B45,CaseData!$B$27:$B$35,0),MATCH($C45,CaseData!$B$27:$E$27,0)) -> 150 | L45: =INDEX(CaseData!$B$27:$E$35,MATCH($B45,CaseData!$B$27:$B$35,0),MATCH($C45,CaseData!$B$27:$E$27,0)) -> 150 | M45: =INDEX(CaseData!$B$27:$E$35,MATCH($B45,CaseData!$B$27:$B$35,0),MATCH($C45,CaseData!$B$27:$E$27,0)) -> 150 | N45: =INDEX(CaseData!$B$27:$E$35,MATCH($B45,CaseData!$B$27:$B$35,0),MATCH($C45,CaseData!$B$27:$E$27,0)) -> 150 | ... BN45: =INDEX(CaseData!$B$27:$E$35,MATCH($B45,CaseData!$B$27:$B$35,0),MATCH($C45,CaseData!$B$27:$E$27,0)) -> 150
B46: =B45 -> Madrid | C46: =C43 -> Men's | G46: =INDEX(CaseData!$B$27:$E$35,MATCH($B46,CaseData!$B$27:$B$35,0),MATCH($C46,CaseData!$B$27:$E$27,0)) -> 90 | H46: =INDEX(CaseData!$B$27:$E$35,MATCH($B46,CaseData!$B$27:$B$35,0),MATCH($C46,CaseData!$B$27:$E$27,0)) -> 90 | I46: =INDEX(CaseData!$B$27:$E$35,MATCH($B46,CaseData!$B$27:$B$35,0),MATCH($C46,CaseData!$B$27:$E$27,0)) -> 90 | J46: =INDEX(CaseData!$B$27:$E$35,MATCH($B46,CaseData!$B$27:$B$35,0),MATCH($C46,CaseData!$B$27:$E$27,0)) -> 90 | K46: =INDEX(CaseData!$B$27:$E$35,MATCH($B46,CaseData!$B$27:$B$35,0),MATCH($C46,CaseData!$B$27:$E$27,0)) -> 90 | L46: =INDEX(CaseData!$B$27:$E$35,MATCH($B46,CaseData!$B$27:$B$35,0),MATCH($C46,CaseData!$B$27:$E$27,0)) -> 90 | M46: =INDEX(CaseData!$B$27:$E$35,MATCH($B46,CaseData!$B$27:$B$35,0),MATCH($C46,CaseData!$B$27:$E$27,0)) -> 90 | N46: =INDEX(CaseData!$B$27:$E$35,MATCH($B46,CaseData!$B$27:$B$35,0),MATCH($C46,CaseData!$B$27:$E$27,0)) -> 90 | ... BN46: =INDEX(CaseData!$B$27:$E$35,MATCH($B46,CaseData!$B$27:$B$35,0),MATCH($C46,CaseData!$B$27:$E$27,0)) -> 90
B47: =B46 -> Madrid | C47: =C44 -> Accessories | G47: =INDEX(CaseData!$B$27:$E$35,MATCH($B47,CaseData!$B$27:$B$35,0),MATCH($C47,CaseData!$B$27:$E$27,0)) -> 60 | H47: =INDEX(CaseData!$B$27:$E$35,MATCH($B47,CaseData!$B$27:$B$35,0),MATCH($C47,CaseData!$B$27:$E$27,0)) -> 60 | I47: =INDEX(CaseData!$B$27:$E$35,MATCH($B47,CaseData!$B$27:$B$35,0),MATCH($C47,CaseData!$B$27:$E$27,0)) -> 60 | J47: =INDEX(CaseData!$B$27:$E$35,MATCH($B47,CaseData!$B$27:$B$35,0),MATCH($C47,CaseData!$B$27:$E$27,0)) -> 60 | K47: =INDEX(CaseData!$B$27:$E$35,MATCH($B47,CaseData!$B$27:$B$35,0),MATCH($C47,CaseData!$B$27:$E$27,0)) -> 60 | L47: =INDEX(CaseData!$B$27:$E$35,MATCH($B47,CaseData!$B$27:$B$35,0),MATCH($C47,CaseData!$B$27:$E$27,0)) -> 60 | M47: =INDEX(CaseData!$B$27:$E$35,MATCH($B47,CaseData!$B$27:$B$35,0),MATCH($C47,CaseData!$B$27:$E$27,0)) -> 60 | N47: =INDEX(CaseData!$B$27:$E$35,MATCH($B47,CaseData!$B$27:$B$35,0),MATCH($C47,CaseData!$B$27:$E$27,0)) -> 60 | ... BN47: =INDEX(CaseData!$B$27:$E$35,MATCH($B47,CaseData!$B$27:$B$35,0),MATCH($C47,CaseData!$B$27:$E$27,0)) -> 60
B48: =CaseData!$B$31 -> London | C48: =C45 -> Women's | G48: =INDEX(CaseData!$B$27:$E$35,MATCH($B48,CaseData!$B$27:$B$35,0),MATCH($C48,CaseData!$B$27:$E$27,0)) -> 110 | H48: =INDEX(CaseData!$B$27:$E$35,MATCH($B48,CaseData!$B$27:$B$35,0),MATCH($C48,CaseData!$B$27:$E$27,0)) -> 110 | I48: =INDEX(CaseData!$B$27:$E$35,MATCH($B48,CaseData!$B$27:$B$35,0),MATCH($C48,CaseData!$B$27:$E$27,0)) -> 110 | J48: =INDEX(CaseData!$B$27:$E$35,MATCH($B48,CaseData!$B$27:$B$35,0),MATCH($C48,CaseData!$B$27:$E$27,0)) -> 110 | K48: =INDEX(CaseData!$B$27:$E$35,MATCH($B48,CaseData!$B$27:$B$35,0),MATCH($C48,CaseData!$B$27:$E$27,0)) -> 110 | L48: =INDEX(CaseData!$B$27:$E$35,MATCH($B48,CaseData!$B$27:$B$35,0),MATCH($C48,CaseData!$B$27:$E$27,0)) -> 110 | M48: =INDEX(CaseData!$B$27:$E$35,MATCH($B48,CaseData!$B$27:$B$35,0),MATCH($C48,CaseData!$B$27:$E$27,0)) -> 110 | N48: =INDEX(CaseData!$B$27:$E$35,MATCH($B48,CaseData!$B$27:$B$35,0),MATCH($C48,CaseData!$B$27:$E$27,0)) -> 110 | ... BN48: =INDEX(CaseData!$B$27:$E$35,MATCH($B48,CaseData!$B$27:$B$35,0),MATCH($C48,CaseData!$B$27:$E$27,0)) -> 110
B49: =B48 -> London | C49: =C46 -> Men's | G49: =INDEX(CaseData!$B$27:$E$35,MATCH($B49,CaseData!$B$27:$B$35,0),MATCH($C49,CaseData!$B$27:$E$27,0)) -> 130 | H49: =INDEX(CaseData!$B$27:$E$35,MATCH($B49,CaseData!$B$27:$B$35,0),MATCH($C49,CaseData!$B$27:$E$27,0)) -> 130 | I49: =INDEX(CaseData!$B$27:$E$35,MATCH($B49,CaseData!$B$27:$B$35,0),MATCH($C49,CaseData!$B$27:$E$27,0)) -> 130 | J49: =INDEX(CaseData!$B$27:$E$35,MATCH($B49,CaseData!$B$27:$B$35,0),MATCH($C49,CaseData!$B$27:$E$27,0)) -> 130 | K49: =INDEX(CaseData!$B$27:$E$35,MATCH($B49,CaseData!$B$27:$B$35,0),MATCH($C49,CaseData!$B$27:$E$27,0)) -> 130 | L49: =INDEX(CaseData!$B$27:$E$35,MATCH($B49,CaseData!$B$27:$B$35,0),MATCH($C49,CaseData!$B$27:$E$27,0)) -> 130 | M49: =INDEX(CaseData!$B$27:$E$35,MATCH($B49,CaseData!$B$27:$B$35,0),MATCH($C49,CaseData!$B$27:$E$27,0)) -> 130 | N49: =INDEX(CaseData!$B$27:$E$35,MATCH($B49,CaseData!$B$27:$B$35,0),MATCH($C49,CaseData!$B$27:$E$27,0)) -> 130 | ... BN49: =INDEX(CaseData!$B$27:$E$35,MATCH($B49,CaseData!$B$27:$B$35,0),MATCH($C49,CaseData!$B$27:$E$27,0)) -> 130
B50: =B49 -> London | C50: =C47 -> Accessories | G50: =INDEX(CaseData!$B$27:$E$35,MATCH($B50,CaseData!$B$27:$B$35,0),MATCH($C50,CaseData!$B$27:$E$27,0)) -> 100 | H50: =INDEX(CaseData!$B$27:$E$35,MATCH($B50,CaseData!$B$27:$B$35,0),MATCH($C50,CaseData!$B$27:$E$27,0)) -> 100 | I50: =INDEX(CaseData!$B$27:$E$35,MATCH($B50,CaseData!$B$27:$B$35,0),MATCH($C50,CaseData!$B$27:$E$27,0)) -> 100 | J50: =INDEX(CaseData!$B$27:$E$35,MATCH($B50,CaseData!$B$27:$B$35,0),MATCH($C50,CaseData!$B$27:$E$27,0)) -> 100 | K50: =INDEX(CaseData!$B$27:$E$35,MATCH($B50,CaseData!$B$27:$B$35,0),MATCH($C50,CaseData!$B$27:$E$27,0)) -> 100 | L50: =INDEX(CaseData!$B$27:$E$35,MATCH($B50,CaseData!$B$27:$B$35,0),MATCH($C50,CaseData!$B$27:$E$27,0)) -> 100 | M50: =INDEX(CaseData!$B$27:$E$35,MATCH($B50,CaseData!$B$27:$B$35,0),MATCH($C50,CaseData!$B$27:$E$27,0)) -> 100 | N50: =INDEX(CaseData!$B$27:$E$35,MATCH($B50,CaseData!$B$27:$B$35,0),MATCH($C50,CaseData!$B$27:$E$27,0)) -> 100 | ... BN50: =INDEX(CaseData!$B$27:$E$35,MATCH($B50,CaseData!$B$27:$B$35,0),MATCH($C50,CaseData!$B$27:$E$27,0)) -> 100
B51: =CaseData!$B$32 -> New York | C51: =C48 -> Women's | G51: =INDEX(CaseData!$B$27:$E$35,MATCH($B51,CaseData!$B$27:$B$35,0),MATCH($C51,CaseData!$B$27:$E$27,0)) -> 110 | H51: =INDEX(CaseData!$B$27:$E$35,MATCH($B51,CaseData!$B$27:$B$35,0),MATCH($C51,CaseData!$B$27:$E$27,0)) -> 110 | I51: =INDEX(CaseData!$B$27:$E$35,MATCH($B51,CaseData!$B$27:$B$35,0),MATCH($C51,CaseData!$B$27:$E$27,0)) -> 110 | J51: =INDEX(CaseData!$B$27:$E$35,MATCH($B51,CaseData!$B$27:$B$35,0),MATCH($C51,CaseData!$B$27:$E$27,0)) -> 110 | K51: =INDEX(CaseData!$B$27:$E$35,MATCH($B51,CaseData!$B$27:$B$35,0),MATCH($C51,CaseData!$B$27:$E$27,0)) -> 110 | L51: =INDEX(CaseData!$B$27:$E$35,MATCH($B51,CaseData!$B$27:$B$35,0),MATCH($C51,CaseData!$B$27:$E$27,0)) -> 110 | M51: =INDEX(CaseData!$B$27:$E$35,MATCH($B51,CaseData!$B$27:$B$35,0),MATCH($C51,CaseData!$B$27:$E$27,0)) -> 110 | N51: =INDEX(CaseData!$B$27:$E$35,MATCH($B51,CaseData!$B$27:$B$35,0),MATCH($C51,CaseData!$B$27:$E$27,0)) -> 110 | ... BN51: =INDEX(CaseData!$B$27:$E$35,MATCH($B51,CaseData!$B$27:$B$35,0),MATCH($C51,CaseData!$B$27:$E$27,0)) -> 110
B52: =B51 -> New York | C52: =C49 -> Men's | G52: =INDEX(CaseData!$B$27:$E$35,MATCH($B52,CaseData!$B$27:$B$35,0),MATCH($C52,CaseData!$B$27:$E$27,0)) -> 130 | H52: =INDEX(CaseData!$B$27:$E$35,MATCH($B52,CaseData!$B$27:$B$35,0),MATCH($C52,CaseData!$B$27:$E$27,0)) -> 130 | I52: =INDEX(CaseData!$B$27:$E$35,MATCH($B52,CaseData!$B$27:$B$35,0),MATCH($C52,CaseData!$B$27:$E$27,0)) -> 130 | J52: =INDEX(CaseData!$B$27:$E$35,MATCH($B52,CaseData!$B$27:$B$35,0),MATCH($C52,CaseData!$B$27:$E$27,0)) -> 130 | K52: =INDEX(CaseData!$B$27:$E$35,MATCH($B52,CaseData!$B$27:$B$35,0),MATCH($C52,CaseData!$B$27:$E$27,0)) -> 130 | L52: =INDEX(CaseData!$B$27:$E$35,MATCH($B52,CaseData!$B$27:$B$35,0),MATCH($C52,CaseData!$B$27:$E$27,0)) -> 130 | M52: =INDEX(CaseData!$B$27:$E$35,MATCH($B52,CaseData!$B$27:$B$35,0),MATCH($C52,CaseData!$B$27:$E$27,0)) -> 130 | N52: =INDEX(CaseData!$B$27:$E$35,MATCH($B52,CaseData!$B$27:$B$35,0),MATCH($C52,CaseData!$B$27:$E$27,0)) -> 130 | ... BN52: =INDEX(CaseData!$B$27:$E$35,MATCH($B52,CaseData!$B$27:$B$35,0),MATCH($C52,CaseData!$B$27:$E$27,0)) -> 130
B53: =B52 -> New York | C53: =C50 -> Accessories | G53: =INDEX(CaseData!$B$27:$E$35,MATCH($B53,CaseData!$B$27:$B$35,0),MATCH($C53,CaseData!$B$27:$E$27,0)) -> 100 | H53: =INDEX(CaseData!$B$27:$E$35,MATCH($B53,CaseData!$B$27:$B$35,0),MATCH($C53,CaseData!$B$27:$E$27,0)) -> 100 | I53: =INDEX(CaseData!$B$27:$E$35,MATCH($B53,CaseData!$B$27:$B$35,0),MATCH($C53,CaseData!$B$27:$E$27,0)) -> 100 | J53: =INDEX(CaseData!$B$27:$E$35,MATCH($B53,CaseData!$B$27:$B$35,0),MATCH($C53,CaseData!$B$27:$E$27,0)) -> 100 | K53: =INDEX(CaseData!$B$27:$E$35,MATCH($B53,CaseData!$B$27:$B$35,0),MATCH($C53,CaseData!$B$27:$E$27,0)) -> 100 | L53: =INDEX(CaseData!$B$27:$E$35,MATCH($B53,CaseData!$B$27:$B$35,0),MATCH($C53,CaseData!$B$27:$E$27,0)) -> 100 | M53: =INDEX(CaseData!$B$27:$E$35,MATCH($B53,CaseData!$B$27:$B$35,0),MATCH($C53,CaseData!$B$27:$E$27,0)) -> 100 | N53: =INDEX(CaseData!$B$27:$E$35,MATCH($B53,CaseData!$B$27:$B$35,0),MATCH($C53,CaseData!$B$27:$E$27,0)) -> 100 | ... BN53: =INDEX(CaseData!$B$27:$E$35,MATCH($B53,CaseData!$B$27:$B$35,0),MATCH($C53,CaseData!$B$27:$E$27,0)) -> 100
B54: =CaseData!$B$33 -> Montreal | C54: =C51 -> Women's | G54: =INDEX(CaseData!$B$27:$E$35,MATCH($B54,CaseData!$B$27:$B$35,0),MATCH($C54,CaseData!$B$27:$E$27,0)) -> 180 | H54: =INDEX(CaseData!$B$27:$E$35,MATCH($B54,CaseData!$B$27:$B$35,0),MATCH($C54,CaseData!$B$27:$E$27,0)) -> 180 | I54: =INDEX(CaseData!$B$27:$E$35,MATCH($B54,CaseData!$B$27:$B$35,0),MATCH($C54,CaseData!$B$27:$E$27,0)) -> 180 | J54: =INDEX(CaseData!$B$27:$E$35,MATCH($B54,CaseData!$B$27:$B$35,0),MATCH($C54,CaseData!$B$27:$E$27,0)) -> 180 | K54: =INDEX(CaseData!$B$27:$E$35,MATCH($B54,CaseData!$B$27:$B$35,0),MATCH($C54,CaseData!$B$27:$E$27,0)) -> 180 | L54: =INDEX(CaseData!$B$27:$E$35,MATCH($B54,CaseData!$B$27:$B$35,0),MATCH($C54,CaseData!$B$27:$E$27,0)) -> 180 | M54: =INDEX(CaseData!$B$27:$E$35,MATCH($B54,CaseData!$B$27:$B$35,0),MATCH($C54,CaseData!$B$27:$E$27,0)) -> 180 | N54: =INDEX(CaseData!$B$27:$E$35,MATCH($B54,CaseData!$B$27:$B$35,0),MATCH($C54,CaseData!$B$27:$E$27,0)) -> 180 | ... BN54: =INDEX(CaseData!$B$27:$E$35,MATCH($B54,CaseData!$B$27:$B$35,0),MATCH($C54,CaseData!$B$27:$E$27,0)) -> 180
B55: =B54 -> Montreal | C55: =C52 -> Men's | G55: =INDEX(CaseData!$B$27:$E$35,MATCH($B55,CaseData!$B$27:$B$35,0),MATCH($C55,CaseData!$B$27:$E$27,0)) -> 170 | H55: =INDEX(CaseData!$B$27:$E$35,MATCH($B55,CaseData!$B$27:$B$35,0),MATCH($C55,CaseData!$B$27:$E$27,0)) -> 170 | I55: =INDEX(CaseData!$B$27:$E$35,MATCH($B55,CaseData!$B$27:$B$35,0),MATCH($C55,CaseData!$B$27:$E$27,0)) -> 170 | J55: =INDEX(CaseData!$B$27:$E$35,MATCH($B55,CaseData!$B$27:$B$35,0),MATCH($C55,CaseData!$B$27:$E$27,0)) -> 170 | K55: =INDEX(CaseData!$B$27:$E$35,MATCH($B55,CaseData!$B$27:$B$35,0),MATCH($C55,CaseData!$B$27:$E$27,0)) -> 170 | L55: =INDEX(CaseData!$B$27:$E$35,MATCH($B55,CaseData!$B$27:$B$35,0),MATCH($C55,CaseData!$B$27:$E$27,0)) -> 170 | M55: =INDEX(CaseData!$B$27:$E$35,MATCH($B55,CaseData!$B$27:$B$35,0),MATCH($C55,CaseData!$B$27:$E$27,0)) -> 170 | N55: =INDEX(CaseData!$B$27:$E$35,MATCH($B55,CaseData!$B$27:$B$35,0),MATCH($C55,CaseData!$B$27:$E$27,0)) -> 170 | ... BN55: =INDEX(CaseData!$B$27:$E$35,MATCH($B55,CaseData!$B$27:$B$35,0),MATCH($C55,CaseData!$B$27:$E$27,0)) -> 170
B56: =B55 -> Montreal | C56: =C53 -> Accessories | G56: =INDEX(CaseData!$B$27:$E$35,MATCH($B56,CaseData!$B$27:$B$35,0),MATCH($C56,CaseData!$B$27:$E$27,0)) -> 260 | H56: =INDEX(CaseData!$B$27:$E$35,MATCH($B56,CaseData!$B$27:$B$35,0),MATCH($C56,CaseData!$B$27:$E$27,0)) -> 260 | I56: =INDEX(CaseData!$B$27:$E$35,MATCH($B56,CaseData!$B$27:$B$35,0),MATCH($C56,CaseData!$B$27:$E$27,0)) -> 260 | J56: =INDEX(CaseData!$B$27:$E$35,MATCH($B56,CaseData!$B$27:$B$35,0),MATCH($C56,CaseData!$B$27:$E$27,0)) -> 260 | K56: =INDEX(CaseData!$B$27:$E$35,MATCH($B56,CaseData!$B$27:$B$35,0),MATCH($C56,CaseData!$B$27:$E$27,0)) -> 260 | L56: =INDEX(CaseData!$B$27:$E$35,MATCH($B56,CaseData!$B$27:$B$35,0),MATCH($C56,CaseData!$B$27:$E$27,0)) -> 260 | M56: =INDEX(CaseData!$B$27:$E$35,MATCH($B56,CaseData!$B$27:$B$35,0),MATCH($C56,CaseData!$B$27:$E$27,0)) -> 260 | N56: =INDEX(CaseData!$B$27:$E$35,MATCH($B56,CaseData!$B$27:$B$35,0),MATCH($C56,CaseData!$B$27:$E$27,0)) -> 260 | ... BN56: =INDEX(CaseData!$B$27:$E$35,MATCH($B56,CaseData!$B$27:$B$35,0),MATCH($C56,CaseData!$B$27:$E$27,0)) -> 260
B57: =CaseData!$B$34 -> Zurich | C57: =C54 -> Women's | G57: =INDEX(CaseData!$B$27:$E$35,MATCH($B57,CaseData!$B$27:$B$35,0),MATCH($C57,CaseData!$B$27:$E$27,0)) -> 280 | H57: =INDEX(CaseData!$B$27:$E$35,MATCH($B57,CaseData!$B$27:$B$35,0),MATCH($C57,CaseData!$B$27:$E$27,0)) -> 280 | I57: =INDEX(CaseData!$B$27:$E$35,MATCH($B57,CaseData!$B$27:$B$35,0),MATCH($C57,CaseData!$B$27:$E$27,0)) -> 280 | J57: =INDEX(CaseData!$B$27:$E$35,MATCH($B57,CaseData!$B$27:$B$35,0),MATCH($C57,CaseData!$B$27:$E$27,0)) -> 280 | K57: =INDEX(CaseData!$B$27:$E$35,MATCH($B57,CaseData!$B$27:$B$35,0),MATCH($C57,CaseData!$B$27:$E$27,0)) -> 280 | L57: =INDEX(CaseData!$B$27:$E$35,MATCH($B57,CaseData!$B$27:$B$35,0),MATCH($C57,CaseData!$B$27:$E$27,0)) -> 280 | M57: =INDEX(CaseData!$B$27:$E$35,MATCH($B57,CaseData!$B$27:$B$35,0),MATCH($C57,CaseData!$B$27:$E$27,0)) -> 280 | N57: =INDEX(CaseData!$B$27:$E$35,MATCH($B57,CaseData!$B$27:$B$35,0),MATCH($C57,CaseData!$B$27:$E$27,0)) -> 280 | ... BN57: =INDEX(CaseData!$B$27:$E$35,MATCH($B57,CaseData!$B$27:$B$35,0),MATCH($C57,CaseData!$B$27:$E$27,0)) -> 280
B58: =B57 -> Zurich | C58: =C55 -> Men's | G58: =INDEX(CaseData!$B$27:$E$35,MATCH($B58,CaseData!$B$27:$B$35,0),MATCH($C58,CaseData!$B$27:$E$27,0)) -> 170 | H58: =INDEX(CaseData!$B$27:$E$35,MATCH($B58,CaseData!$B$27:$B$35,0),MATCH($C58,CaseData!$B$27:$E$27,0)) -> 170 | I58: =INDEX(CaseData!$B$27:$E$35,MATCH($B58,CaseData!$B$27:$B$35,0),MATCH($C58,CaseData!$B$27:$E$27,0)) -> 170 | J58: =INDEX(CaseData!$B$27:$E$35,MATCH($B58,CaseData!$B$27:$B$35,0),MATCH($C58,CaseData!$B$27:$E$27,0)) -> 170 | K58: =INDEX(CaseData!$B$27:$E$35,MATCH($B58,CaseData!$B$27:$B$35,0),MATCH($C58,CaseData!$B$27:$E$27,0)) -> 170 | L58: =INDEX(CaseData!$B$27:$E$35,MATCH($B58,CaseData!$B$27:$B$35,0),MATCH($C58,CaseData!$B$27:$E$27,0)) -> 170 | M58: =INDEX(CaseData!$B$27:$E$35,MATCH($B58,CaseData!$B$27:$B$35,0),MATCH($C58,CaseData!$B$27:$E$27,0)) -> 170 | N58: =INDEX(CaseData!$B$27:$E$35,MATCH($B58,CaseData!$B$27:$B$35,0),MATCH($C58,CaseData!$B$27:$E$27,0)) -> 170 | ... BN58: =INDEX(CaseData!$B$27:$E$35,MATCH($B58,CaseData!$B$27:$B$35,0),MATCH($C58,CaseData!$B$27:$E$27,0)) -> 170
B59: =B58 -> Zurich | C59: =C56 -> Accessories | G59: =INDEX(CaseData!$B$27:$E$35,MATCH($B59,CaseData!$B$27:$B$35,0),MATCH($C59,CaseData!$B$27:$E$27,0)) -> 150 | H59: =INDEX(CaseData!$B$27:$E$35,MATCH($B59,CaseData!$B$27:$B$35,0),MATCH($C59,CaseData!$B$27:$E$27,0)) -> 150 | I59: =INDEX(CaseData!$B$27:$E$35,MATCH($B59,CaseData!$B$27:$B$35,0),MATCH($C59,CaseData!$B$27:$E$27,0)) -> 150 | J59: =INDEX(CaseData!$B$27:$E$35,MATCH($B59,CaseData!$B$27:$B$35,0),MATCH($C59,CaseData!$B$27:$E$27,0)) -> 150 | K59: =INDEX(CaseData!$B$27:$E$35,MATCH($B59,CaseData!$B$27:$B$35,0),MATCH($C59,CaseData!$B$27:$E$27,0)) -> 150 | L59: =INDEX(CaseData!$B$27:$E$35,MATCH($B59,CaseData!$B$27:$B$35,0),MATCH($C59,CaseData!$B$27:$E$27,0)) -> 150 | M59: =INDEX(CaseData!$B$27:$E$35,MATCH($B59,CaseData!$B$27:$B$35,0),MATCH($C59,CaseData!$B$27:$E$27,0)) -> 150 | N59: =INDEX(CaseData!$B$27:$E$35,MATCH($B59,CaseData!$B$27:$B$35,0),MATCH($C59,CaseData!$B$27:$E$27,0)) -> 150 | ... BN59: =INDEX(CaseData!$B$27:$E$35,MATCH($B59,CaseData!$B$27:$B$35,0),MATCH($C59,CaseData!$B$27:$E$27,0)) -> 150
B60: =CaseData!$B$35 -> Moscow | C60: =C57 -> Women's | G60: =INDEX(CaseData!$B$27:$E$35,MATCH($B60,CaseData!$B$27:$B$35,0),MATCH($C60,CaseData!$B$27:$E$27,0)) -> 110 | H60: =INDEX(CaseData!$B$27:$E$35,MATCH($B60,CaseData!$B$27:$B$35,0),MATCH($C60,CaseData!$B$27:$E$27,0)) -> 110 | I60: =INDEX(CaseData!$B$27:$E$35,MATCH($B60,CaseData!$B$27:$B$35,0),MATCH($C60,CaseData!$B$27:$E$27,0)) -> 110 | J60: =INDEX(CaseData!$B$27:$E$35,MATCH($B60,CaseData!$B$27:$B$35,0),MATCH($C60,CaseData!$B$27:$E$27,0)) -> 110 | K60: =INDEX(CaseData!$B$27:$E$35,MATCH($B60,CaseData!$B$27:$B$35,0),MATCH($C60,CaseData!$B$27:$E$27,0)) -> 110 | L60: =INDEX(CaseData!$B$27:$E$35,MATCH($B60,CaseData!$B$27:$B$35,0),MATCH($C60,CaseData!$B$27:$E$27,0)) -> 110 | M60: =INDEX(CaseData!$B$27:$E$35,MATCH($B60,CaseData!$B$27:$B$35,0),MATCH($C60,CaseData!$B$27:$E$27,0)) -> 110 | N60: =INDEX(CaseData!$B$27:$E$35,MATCH($B60,CaseData!$B$27:$B$35,0),MATCH($C60,CaseData!$B$27:$E$27,0)) -> 110 | ... BN60: =INDEX(CaseData!$B$27:$E$35,MATCH($B60,CaseData!$B$27:$B$35,0),MATCH($C60,CaseData!$B$27:$E$27,0)) -> 110
B61: =B60 -> Moscow | C61: =C58 -> Men's | G61: =INDEX(CaseData!$B$27:$E$35,MATCH($B61,CaseData!$B$27:$B$35,0),MATCH($C61,CaseData!$B$27:$E$27,0)) -> 130 | H61: =INDEX(CaseData!$B$27:$E$35,MATCH($B61,CaseData!$B$27:$B$35,0),MATCH($C61,CaseData!$B$27:$E$27,0)) -> 130 | I61: =INDEX(CaseData!$B$27:$E$35,MATCH($B61,CaseData!$B$27:$B$35,0),MATCH($C61,CaseData!$B$27:$E$27,0)) -> 130 | J61: =INDEX(CaseData!$B$27:$E$35,MATCH($B61,CaseData!$B$27:$B$35,0),MATCH($C61,CaseData!$B$27:$E$27,0)) -> 130 | K61: =INDEX(CaseData!$B$27:$E$35,MATCH($B61,CaseData!$B$27:$B$35,0),MATCH($C61,CaseData!$B$27:$E$27,0)) -> 130 | L61: =INDEX(CaseData!$B$27:$E$35,MATCH($B61,CaseData!$B$27:$B$35,0),MATCH($C61,CaseData!$B$27:$E$27,0)) -> 130 | M61: =INDEX(CaseData!$B$27:$E$35,MATCH($B61,CaseData!$B$27:$B$35,0),MATCH($C61,CaseData!$B$27:$E$27,0)) -> 130 | N61: =INDEX(CaseData!$B$27:$E$35,MATCH($B61,CaseData!$B$27:$B$35,0),MATCH($C61,CaseData!$B$27:$E$27,0)) -> 130 | ... BN61: =INDEX(CaseData!$B$27:$E$35,MATCH($B61,CaseData!$B$27:$B$35,0),MATCH($C61,CaseData!$B$27:$E$27,0)) -> 130
B62: =B61 -> Moscow | C62: =C59 -> Accessories | G62: =INDEX(CaseData!$B$27:$E$35,MATCH($B62,CaseData!$B$27:$B$35,0),MATCH($C62,CaseData!$B$27:$E$27,0)) -> 100 | H62: =INDEX(CaseData!$B$27:$E$35,MATCH($B62,CaseData!$B$27:$B$35,0),MATCH($C62,CaseData!$B$27:$E$27,0)) -> 100 | I62: =INDEX(CaseData!$B$27:$E$35,MATCH($B62,CaseData!$B$27:$B$35,0),MATCH($C62,CaseData!$B$27:$E$27,0)) -> 100 | J62: =INDEX(CaseData!$B$27:$E$35,MATCH($B62,CaseData!$B$27:$B$35,0),MATCH($C62,CaseData!$B$27:$E$27,0)) -> 100 | K62: =INDEX(CaseData!$B$27:$E$35,MATCH($B62,CaseData!$B$27:$B$35,0),MATCH($C62,CaseData!$B$27:$E$27,0)) -> 100 | L62: =INDEX(CaseData!$B$27:$E$35,MATCH($B62,CaseData!$B$27:$B$35,0),MATCH($C62,CaseData!$B$27:$E$27,0)) -> 100 | M62: =INDEX(CaseData!$B$27:$E$35,MATCH($B62,CaseData!$B$27:$B$35,0),MATCH($C62,CaseData!$B$27:$E$27,0)) -> 100 | N62: =INDEX(CaseData!$B$27:$E$35,MATCH($B62,CaseData!$B$27:$B$35,0),MATCH($C62,CaseData!$B$27:$E$27,0)) -> 100 | ... BN62: =INDEX(CaseData!$B$27:$E$35,MATCH($B62,CaseData!$B$27:$B$35,0),MATCH($C62,CaseData!$B$27:$E$27,0)) -> 100
B64: New Store MOO | D64: Opening Month
B65: =CaseData!C14 -> New York | D65: =CaseData!F14 -> 3 | G65: =IF(G$8<$D65,0,F65+1) -> 0 | H65: =IF(H$8<$D65,0,G65+1) -> 0 | I65: =IF(I$8<$D65,0,H65+1) -> 1 | J65: =IF(J$8<$D65,0,I65+1) -> 2 | K65: =IF(K$8<$D65,0,J65+1) -> 3 | L65: =IF(L$8<$D65,0,K65+1) -> 4 | M65: =IF(M$8<$D65,0,L65+1) -> 5 | N65: =IF(N$8<$D65,0,M65+1) -> 6 | ... BN65: =IF(BN$8<$D65,0,BM65+1) -> 58
B66: =CaseData!C15 -> Montreal | D66: =CaseData!F15 -> 9 | G66: =IF(G$8<$D66,0,F66+1) -> 0 | H66: =IF(H$8<$D66,0,G66+1) -> 0 | I66: =IF(I$8<$D66,0,H66+1) -> 0 | J66: =IF(J$8<$D66,0,I66+1) -> 0 | K66: =IF(K$8<$D66,0,J66+1) -> 0 | L66: =IF(L$8<$D66,0,K66+1) -> 0 | M66: =IF(M$8<$D66,0,L66+1) -> 0 | N66: =IF(N$8<$D66,0,M66+1) -> 0 | ... BN66: =IF(BN$8<$D66,0,BM66+1) -> 52
B67: =CaseData!C16 -> Zurich | D67: =CaseData!F16 -> 15 | G67: =IF(G$8<$D67,0,F67+1) -> 0 | H67: =IF(H$8<$D67,0,G67+1) -> 0 | I67: =IF(I$8<$D67,0,H67+1) -> 0 | J67: =IF(J$8<$D67,0,I67+1) -> 0 | K67: =IF(K$8<$D67,0,J67+1) -> 0 | L67: =IF(L$8<$D67,0,K67+1) -> 0 | M67: =IF(M$8<$D67,0,L67+1) -> 0 | N67: =IF(N$8<$D67,0,M67+1) -> 0 | ... BN67: =IF(BN$8<$D67,0,BM67+1) -> 46
B68: =CaseData!C17 -> Moscow | D68: =CaseData!F17 -> 21 | G68: =IF(G$8<$D68,0,F68+1) -> 0 | H68: =IF(H$8<$D68,0,G68+1) -> 0 | I68: =IF(I$8<$D68,0,H68+1) -> 0 | J68: =IF(J$8<$D68,0,I68+1) -> 0 | K68: =IF(K$8<$D68,0,J68+1) -> 0 | L68: =IF(L$8<$D68,0,K68+1) -> 0 | M68: =IF(M$8<$D68,0,L68+1) -> 0 | N68: =IF(N$8<$D68,0,M68+1) -> 0 | ... BN68: =IF(BN$8<$D68,0,BM68+1) -> 40
B70: New Store Capacity
B71: =CaseData!C14 -> New York | G71: =IFERROR(VLOOKUP(G65,CaseData!$I$10:$J$22,2,1),0) -> 0 | H71: =IFERROR(VLOOKUP(H65,CaseData!$I$10:$J$22,2,1),0) -> 0 | I71: =IFERROR(VLOOKUP(I65,CaseData!$I$10:$J$22,2,1),0) -> 0.5 | J71: =IFERROR(VLOOKUP(J65,CaseData!$I$10:$J$22,2,1),0) -> 0.54166667 | K71: =IFERROR(VLOOKUP(K65,CaseData!$I$10:$J$22,2,1),0) -> 0.58333333 | L71: =IFERROR(VLOOKUP(L65,CaseData!$I$10:$J$22,2,1),0) -> 0.625 | M71: =IFERROR(VLOOKUP(M65,CaseData!$I$10:$J$22,2,1),0) -> 0.66666667 | N71: =IFERROR(VLOOKUP(N65,CaseData!$I$10:$J$22,2,1),0) -> 0.70833333 | ... BN71: =IFERROR(VLOOKUP(BN65,CaseData!$I$10:$J$22,2,1),0) -> 1
B72: =CaseData!C15 -> Montreal | G72: =IFERROR(VLOOKUP(G66,CaseData!$I$10:$J$22,2,1),0) -> 0 | H72: =IFERROR(VLOOKUP(H66,CaseData!$I$10:$J$22,2,1),0) -> 0 | I72: =IFERROR(VLOOKUP(I66,CaseData!$I$10:$J$22,2,1),0) -> 0 | J72: =IFERROR(VLOOKUP(J66,CaseData!$I$10:$J$22,2,1),0) -> 0 | K72: =IFERROR(VLOOKUP(K66,CaseData!$I$10:$J$22,2,1),0) -> 0 | L72: =IFERROR(VLOOKUP(L66,CaseData!$I$10:$J$22,2,1),0) -> 0 | M72: =IFERROR(VLOOKUP(M66,CaseData!$I$10:$J$22,2,1),0) -> 0 | N72: =IFERROR(VLOOKUP(N66,CaseData!$I$10:$J$22,2,1),0) -> 0 | ... BN72: =IFERROR(VLOOKUP(BN66,CaseData!$I$10:$J$22,2,1),0) -> 1
B73: =CaseData!C16 -> Zurich | G73: =IFERROR(VLOOKUP(G67,CaseData!$I$10:$J$22,2,1),0) -> 0 | H73: =IFERROR(VLOOKUP(H67,CaseData!$I$10:$J$22,2,1),0) -> 0 | I73: =IFERROR(VLOOKUP(I67,CaseData!$I$10:$J$22,2,1),0) -> 0 | J73: =IFERROR(VLOOKUP(J67,CaseData!$I$10:$J$22,2,1),0) -> 0 | K73: =IFERROR(VLOOKUP(K67,CaseData!$I$10:$J$22,2,1),0) -> 0 | L73: =IFERROR(VLOOKUP(L67,CaseData!$I$10:$J$22,2,1),0) -> 0 | M73: =IFERROR(VLOOKUP(M67,CaseData!$I$10:$J$22,2,1),0) -> 0 | N73: =IFERROR(VLOOKUP(N67,CaseData!$I$10:$J$22,2,1),0) -> 0 | ... BN73: =IFERROR(VLOOKUP(BN67,CaseData!$I$10:$J$22,2,1),0) -> 1
B74: =CaseData!C17 -> Moscow | G74: =IFERROR(VLOOKUP(G68,CaseData!$I$10:$J$22,2,1),0) -> 0 | H74: =IFERROR(VLOOKUP(H68,CaseData!$I$10:$J$22,2,1),0) -> 0 | I74: =IFERROR(VLOOKUP(I68,CaseData!$I$10:$J$22,2,1),0) -> 0 | J74: =IFERROR(VLOOKUP(J68,CaseData!$I$10:$J$22,2,1),0) -> 0 | K74: =IFERROR(VLOOKUP(K68,CaseData!$I$10:$J$22,2,1),0) -> 0 | L74: =IFERROR(VLOOKUP(L68,CaseData!$I$10:$J$22,2,1),0) -> 0 | M74: =IFERROR(VLOOKUP(M68,CaseData!$I$10:$J$22,2,1),0) -> 0 | N74: =IFERROR(VLOOKUP(N68,CaseData!$I$10:$J$22,2,1),0) -> 0 | ... BN74: =IFERROR(VLOOKUP(BN68,CaseData!$I$10:$J$22,2,1),0) -> 1
B76: Sales Seasonality | G76: =INDEX(CaseData!$D$58:$D$69,MATCH(MONTH(G$5),CaseData!$C$58:$C$69,0)) -> 2.5 | H76: =INDEX(CaseData!$D$58:$D$69,MATCH(MONTH(H$5),CaseData!$C$58:$C$69,0)) -> 1 | I76: =INDEX(CaseData!$D$58:$D$69,MATCH(MONTH(I$5),CaseData!$C$58:$C$69,0)) -> 1 | J76: =INDEX(CaseData!$D$58:$D$69,MATCH(MONTH(J$5),CaseData!$C$58:$C$69,0)) -> 1 | K76: =INDEX(CaseData!$D$58:$D$69,MATCH(MONTH(K$5),CaseData!$C$58:$C$69,0)) -> 1 | L76: =INDEX(CaseData!$D$58:$D$69,MATCH(MONTH(L$5),CaseData!$C$58:$C$69,0)) -> 1 | M76: =INDEX(CaseData!$D$58:$D$69,MATCH(MONTH(M$5),CaseData!$C$58:$C$69,0)) -> 2.5 | N76: =INDEX(CaseData!$D$58:$D$69,MATCH(MONTH(N$5),CaseData!$C$58:$C$69,0)) -> 1 | ... BN76: =INDEX(CaseData!$D$58:$D$69,MATCH(MONTH(BN$5),CaseData!$C$58:$C$69,0)) -> 1.5
B78: Unit Sales Before Capacity Adjustments
B79: Store | C79: Type | G79: =SUM(G80:G103) -> 4625 | H79: =SUM(H80:H103) -> 1850 | I79: =SUM(I80:I103) -> 2020 | J79: =SUM(J80:J103) -> 2034.1667 | K79: =SUM(K80:K103) -> 2048.3333 | L79: =SUM(L80:L103) -> 2062.5 | M79: =SUM(M80:M103) -> 5191.6667 | N79: =SUM(N80:N103) -> 2090.8333 | ... BN79: =SUM(BN80:BN103) -> 5610
B80: =CaseData!$B$28 -> Paris | C80: =CaseData!$C$27 -> Women's | G80: =G39*G$76*IFERROR(INDEX(G$71:G$74,MATCH($B80,$B$71:$B$74,0)),1) -> 450 | H80: =H39*H$76*IFERROR(INDEX(H$71:H$74,MATCH($B80,$B$71:$B$74,0)),1) -> 180 | I80: =I39*I$76*IFERROR(INDEX(I$71:I$74,MATCH($B80,$B$71:$B$74,0)),1) -> 180 | J80: =J39*J$76*IFERROR(INDEX(J$71:J$74,MATCH($B80,$B$71:$B$74,0)),1) -> 180 | K80: =K39*K$76*IFERROR(INDEX(K$71:K$74,MATCH($B80,$B$71:$B$74,0)),1) -> 180 | L80: =L39*L$76*IFERROR(INDEX(L$71:L$74,MATCH($B80,$B$71:$B$74,0)),1) -> 180 | M80: =M39*M$76*IFERROR(INDEX(M$71:M$74,MATCH($B80,$B$71:$B$74,0)),1) -> 450 | N80: =N39*N$76*IFERROR(INDEX(N$71:N$74,MATCH($B80,$B$71:$B$74,0)),1) -> 180 | ... BN80: =BN39*BN$76*IFERROR(INDEX(BN$71:BN$74,MATCH($B80,$B$71:$B$74,0)),1) -> 270
B81: =B80 -> Paris | C81: =CaseData!$D$27 -> Men's | G81: =G40*G$76*IFERROR(INDEX(G$71:G$74,MATCH($B81,$B$71:$B$74,0)),1) -> 425 | H81: =H40*H$76*IFERROR(INDEX(H$71:H$74,MATCH($B81,$B$71:$B$74,0)),1) -> 170 | I81: =I40*I$76*IFERROR(INDEX(I$71:I$74,MATCH($B81,$B$71:$B$74,0)),1) -> 170 | J81: =J40*J$76*IFERROR(INDEX(J$71:J$74,MATCH($B81,$B$71:$B$74,0)),1) -> 170 | K81: =K40*K$76*IFERROR(INDEX(K$71:K$74,MATCH($B81,$B$71:$B$74,0)),1) -> 170 | L81: =L40*L$76*IFERROR(INDEX(L$71:L$74,MATCH($B81,$B$71:$B$74,0)),1) -> 170 | M81: =M40*M$76*IFERROR(INDEX(M$71:M$74,MATCH($B81,$B$71:$B$74,0)),1) -> 425 | N81: =N40*N$76*IFERROR(INDEX(N$71:N$74,MATCH($B81,$B$71:$B$74,0)),1) -> 170 | ... BN81: =BN40*BN$76*IFERROR(INDEX(BN$71:BN$74,MATCH($B81,$B$71:$B$74,0)),1) -> 255
B82: =B81 -> Paris | C82: =CaseData!$E$27 -> Accessories | G82: =G41*G$76*IFERROR(INDEX(G$71:G$74,MATCH($B82,$B$71:$B$74,0)),1) -> 650 | H82: =H41*H$76*IFERROR(INDEX(H$71:H$74,MATCH($B82,$B$71:$B$74,0)),1) -> 260 | I82: =I41*I$76*IFERROR(INDEX(I$71:I$74,MATCH($B82,$B$71:$B$74,0)),1) -> 260 | J82: =J41*J$76*IFERROR(INDEX(J$71:J$74,MATCH($B82,$B$71:$B$74,0)),1) -> 260 | K82: =K41*K$76*IFERROR(INDEX(K$71:K$74,MATCH($B82,$B$71:$B$74,0)),1) -> 260 | L82: =L41*L$76*IFERROR(INDEX(L$71:L$74,MATCH($B82,$B$71:$B$74,0)),1) -> 260 | M82: =M41*M$76*IFERROR(INDEX(M$71:M$74,MATCH($B82,$B$71:$B$74,0)),1) -> 650 | N82: =N41*N$76*IFERROR(INDEX(N$71:N$74,MATCH($B82,$B$71:$B$74,0)),1) -> 260 | ... BN82: =BN41*BN$76*IFERROR(INDEX(BN$71:BN$74,MATCH($B82,$B$71:$B$74,0)),1) -> 390
B83: =CaseData!$B$29 -> Milano | C83: =C80 -> Women's | G83: =G42*G$76*IFERROR(INDEX(G$71:G$74,MATCH($B83,$B$71:$B$74,0)),1) -> 700 | H83: =H42*H$76*IFERROR(INDEX(H$71:H$74,MATCH($B83,$B$71:$B$74,0)),1) -> 280 | I83: =I42*I$76*IFERROR(INDEX(I$71:I$74,MATCH($B83,$B$71:$B$74,0)),1) -> 280 | J83: =J42*J$76*IFERROR(INDEX(J$71:J$74,MATCH($B83,$B$71:$B$74,0)),1) -> 280 | K83: =K42*K$76*IFERROR(INDEX(K$71:K$74,MATCH($B83,$B$71:$B$74,0)),1) -> 280 | L83: =L42*L$76*IFERROR(INDEX(L$71:L$74,MATCH($B83,$B$71:$B$74,0)),1) -> 280 | M83: =M42*M$76*IFERROR(INDEX(M$71:M$74,MATCH($B83,$B$71:$B$74,0)),1) -> 700 | N83: =N42*N$76*IFERROR(INDEX(N$71:N$74,MATCH($B83,$B$71:$B$74,0)),1) -> 280 | ... BN83: =BN42*BN$76*IFERROR(INDEX(BN$71:BN$74,MATCH($B83,$B$71:$B$74,0)),1) -> 420
B84: =B83 -> Milano | C84: =C81 -> Men's | G84: =G43*G$76*IFERROR(INDEX(G$71:G$74,MATCH($B84,$B$71:$B$74,0)),1) -> 425 | H84: =H43*H$76*IFERROR(INDEX(H$71:H$74,MATCH($B84,$B$71:$B$74,0)),1) -> 170 | I84: =I43*I$76*IFERROR(INDEX(I$71:I$74,MATCH($B84,$B$71:$B$74,0)),1) -> 170 | J84: =J43*J$76*IFERROR(INDEX(J$71:J$74,MATCH($B84,$B$71:$B$74,0)),1) -> 170 | K84: =K43*K$76*IFERROR(INDEX(K$71:K$74,MATCH($B84,$B$71:$B$74,0)),1) -> 170 | L84: =L43*L$76*IFERROR(INDEX(L$71:L$74,MATCH($B84,$B$71:$B$74,0)),1) -> 170 | M84: =M43*M$76*IFERROR(INDEX(M$71:M$74,MATCH($B84,$B$71:$B$74,0)),1) -> 425 | N84: =N43*N$76*IFERROR(INDEX(N$71:N$74,MATCH($B84,$B$71:$B$74,0)),1) -> 170 | ... BN84: =BN43*BN$76*IFERROR(INDEX(BN$71:BN$74,MATCH($B84,$B$71:$B$74,0)),1) -> 255
B85: =B84 -> Milano | C85: =C82 -> Accessories | G85: =G44*G$76*IFERROR(INDEX(G$71:G$74,MATCH($B85,$B$71:$B$74,0)),1) -> 375 | H85: =H44*H$76*IFERROR(INDEX(H$71:H$74,MATCH($B85,$B$71:$B$74,0)),1) -> 150 | I85: =I44*I$76*IFERROR(INDEX(I$71:I$74,MATCH($B85,$B$71:$B$74,0)),1) -> 150 | J85: =J44*J$76*IFERROR(INDEX(J$71:J$74,MATCH($B85,$B$71:$B$74,0)),1) -> 150 | K85: =K44*K$76*IFERROR(INDEX(K$71:K$74,MATCH($B85,$B$71:$B$74,0)),1) -> 150 | L85: =L44*L$76*IFERROR(INDEX(L$71:L$74,MATCH($B85,$B$71:$B$74,0)),1) -> 150 | M85: =M44*M$76*IFERROR(INDEX(M$71:M$74,MATCH($B85,$B$71:$B$74,0)),1) -> 375 | N85: =N44*N$76*IFERROR(INDEX(N$71:N$74,MATCH($B85,$B$71:$B$74,0)),1) -> 150 | ... BN85: =BN44*BN$76*IFERROR(INDEX(BN$71:BN$74,MATCH($B85,$B$71:$B$74,0)),1) -> 225
B86: =CaseData!$B$30 -> Madrid | C86: =C83 -> Women's | G86: =G45*G$76*IFERROR(INDEX(G$71:G$74,MATCH($B86,$B$71:$B$74,0)),1) -> 375 | H86: =H45*H$76*IFERROR(INDEX(H$71:H$74,MATCH($B86,$B$71:$B$74,0)),1) -> 150 | I86: =I45*I$76*IFERROR(INDEX(I$71:I$74,MATCH($B86,$B$71:$B$74,0)),1) -> 150 | J86: =J45*J$76*IFERROR(INDEX(J$71:J$74,MATCH($B86,$B$71:$B$74,0)),1) -> 150 | K86: =K45*K$76*IFERROR(INDEX(K$71:K$74,MATCH($B86,$B$71:$B$74,0)),1) -> 150 | L86: =L45*L$76*IFERROR(INDEX(L$71:L$74,MATCH($B86,$B$71:$B$74,0)),1) -> 150 | M86: =M45*M$76*IFERROR(INDEX(M$71:M$74,MATCH($B86,$B$71:$B$74,0)),1) -> 375 | N86: =N45*N$76*IFERROR(INDEX(N$71:N$74,MATCH($B86,$B$71:$B$74,0)),1) -> 150 | ... BN86: =BN45*BN$76*IFERROR(INDEX(BN$71:BN$74,MATCH($B86,$B$71:$B$74,0)),1) -> 225
B87: =B86 -> Madrid | C87: =C84 -> Men's | G87: =G46*G$76*IFERROR(INDEX(G$71:G$74,MATCH($B87,$B$71:$B$74,0)),1) -> 225 | H87: =H46*H$76*IFERROR(INDEX(H$71:H$74,MATCH($B87,$B$71:$B$74,0)),1) -> 90 | I87: =I46*I$76*IFERROR(INDEX(I$71:I$74,MATCH($B87,$B$71:$B$74,0)),1) -> 90 | J87: =J46*J$76*IFERROR(INDEX(J$71:J$74,MATCH($B87,$B$71:$B$74,0)),1) -> 90 | K87: =K46*K$76*IFERROR(INDEX(K$71:K$74,MATCH($B87,$B$71:$B$74,0)),1) -> 90 | L87: =L46*L$76*IFERROR(INDEX(L$71:L$74,MATCH($B87,$B$71:$B$74,0)),1) -> 90 | M87: =M46*M$76*IFERROR(INDEX(M$71:M$74,MATCH($B87,$B$71:$B$74,0)),1) -> 225 | N87: =N46*N$76*IFERROR(INDEX(N$71:N$74,MATCH($B87,$B$71:$B$74,0)),1) -> 90 | ... BN87: =BN46*BN$76*IFERROR(INDEX(BN$71:BN$74,MATCH($B87,$B$71:$B$74,0)),1) -> 135
B88: =B87 -> Madrid | C88: =C85 -> Accessories | G88: =G47*G$76*IFERROR(INDEX(G$71:G$74,MATCH($B88,$B$71:$B$74,0)),1) -> 150 | H88: =H47*H$76*IFERROR(INDEX(H$71:H$74,MATCH($B88,$B$71:$B$74,0)),1) -> 60 | I88: =I47*I$76*IFERROR(INDEX(I$71:I$74,MATCH($B88,$B$71:$B$74,0)),1) -> 60 | J88: =J47*J$76*IFERROR(INDEX(J$71:J$74,MATCH($B88,$B$71:$B$74,0)),1) -> 60 | K88: =K47*K$76*IFERROR(INDEX(K$71:K$74,MATCH($B88,$B$71:$B$74,0)),1) -> 60 | L88: =L47*L$76*IFERROR(INDEX(L$71:L$74,MATCH($B88,$B$71:$B$74,0)),1) -> 60 | M88: =M47*M$76*IFERROR(INDEX(M$71:M$74,MATCH($B88,$B$71:$B$74,0)),1) -> 150 | N88: =N47*N$76*IFERROR(INDEX(N$71:N$74,MATCH($B88,$B$71:$B$74,0)),1) -> 60 | ... BN88: =BN47*BN$76*IFERROR(INDEX(BN$71:BN$74,MATCH($B88,$B$71:$B$74,0)),1) -> 90
B89: =CaseData!$B$31 -> London | C89: =C86 -> Women's | G89: =G48*G$76*IFERROR(INDEX(G$71:G$74,MATCH($B89,$B$71:$B$74,0)),1) -> 275 | H89: =H48*H$76*IFERROR(INDEX(H$71:H$74,MATCH($B89,$B$71:$B$74,0)),1) -> 110 | I89: =I48*I$76*IFERROR(INDEX(I$71:I$74,MATCH($B89,$B$71:$B$74,0)),1) -> 110 | J89: =J48*J$76*IFERROR(INDEX(J$71:J$74,MATCH($B89,$B$71:$B$74,0)),1) -> 110 | K89: =K48*K$76*IFERROR(INDEX(K$71:K$74,MATCH($B89,$B$71:$B$74,0)),1) -> 110 | L89: =L48*L$76*IFERROR(INDEX(L$71:L$74,MATCH($B89,$B$71:$B$74,0)),1) -> 110 | M89: =M48*M$76*IFERROR(INDEX(M$71:M$74,MATCH($B89,$B$71:$B$74,0)),1) -> 275 | N89: =N48*N$76*IFERROR(INDEX(N$71:N$74,MATCH($B89,$B$71:$B$74,0)),1) -> 110 | ... BN89: =BN48*BN$76*IFERROR(INDEX(BN$71:BN$74,MATCH($B89,$B$71:$B$74,0)),1) -> 165
B90: =B89 -> London | C90: =C87 -> Men's | G90: =G49*G$76*IFERROR(INDEX(G$71:G$74,MATCH($B90,$B$71:$B$74,0)),1) -> 325 | H90: =H49*H$76*IFERROR(INDEX(H$71:H$74,MATCH($B90,$B$71:$B$74,0)),1) -> 130 | I90: =I49*I$76*IFERROR(INDEX(I$71:I$74,MATCH($B90,$B$71:$B$74,0)),1) -> 130 | J90: =J49*J$76*IFERROR(INDEX(J$71:J$74,MATCH($B90,$B$71:$B$74,0)),1) -> 130 | K90: =K49*K$76*IFERROR(INDEX(K$71:K$74,MATCH($B90,$B$71:$B$74,0)),1) -> 130 | L90: =L49*L$76*IFERROR(INDEX(L$71:L$74,MATCH($B90,$B$71:$B$74,0)),1) -> 130 | M90: =M49*M$76*IFERROR(INDEX(M$71:M$74,MATCH($B90,$B$71:$B$74,0)),1) -> 325 | N90: =N49*N$76*IFERROR(INDEX(N$71:N$74,MATCH($B90,$B$71:$B$74,0)),1) -> 130 | ... BN90: =BN49*BN$76*IFERROR(INDEX(BN$71:BN$74,MATCH($B90,$B$71:$B$74,0)),1) -> 195
B91: =B90 -> London | C91: =C88 -> Accessories | G91: =G50*G$76*IFERROR(INDEX(G$71:G$74,MATCH($B91,$B$71:$B$74,0)),1) -> 250 | H91: =H50*H$76*IFERROR(INDEX(H$71:H$74,MATCH($B91,$B$71:$B$74,0)),1) -> 100 | I91: =I50*I$76*IFERROR(INDEX(I$71:I$74,MATCH($B91,$B$71:$B$74,0)),1) -> 100 | J91: =J50*J$76*IFERROR(INDEX(J$71:J$74,MATCH($B91,$B$71:$B$74,0)),1) -> 100 | K91: =K50*K$76*IFERROR(INDEX(K$71:K$74,MATCH($B91,$B$71:$B$74,0)),1) -> 100 | L91: =L50*L$76*IFERROR(INDEX(L$71:L$74,MATCH($B91,$B$71:$B$74,0)),1) -> 100 | M91: =M50*M$76*IFERROR(INDEX(M$71:M$74,MATCH($B91,$B$71:$B$74,0)),1) -> 250 | N91: =N50*N$76*IFERROR(INDEX(N$71:N$74,MATCH($B91,$B$71:$B$74,0)),1) -> 100 | ... BN91: =BN50*BN$76*IFERROR(INDEX(BN$71:BN$74,MATCH($B91,$B$71:$B$74,0)),1) -> 150
B92: =CaseData!$B$32 -> New York | C92: =C89 -> Women's | G92: =G51*G$76*IFERROR(INDEX(G$71:G$74,MATCH($B92,$B$71:$B$74,0)),1) -> 0 | H92: =H51*H$76*IFERROR(INDEX(H$71:H$74,MATCH($B92,$B$71:$B$74,0)),1) -> 0 | I92: =I51*I$76*IFERROR(INDEX(I$71:I$74,MATCH($B92,$B$71:$B$74,0)),1) -> 55 | J92: =J51*J$76*IFERROR(INDEX(J$71:J$74,MATCH($B92,$B$71:$B$74,0)),1) -> 59.583333 | K92: =K51*K$76*IFERROR(INDEX(K$71:K$74,MATCH($B92,$B$71:$B$74,0)),1) -> 64.166667 | L92: =L51*L$76*IFERROR(INDEX(L$71:L$74,MATCH($B92,$B$71:$B$74,0)),1) -> 68.75 | M92: =M51*M$76*IFERROR(INDEX(M$71:M$74,MATCH($B92,$B$71:$B$74,0)),1) -> 183.33333 | N92: =N51*N$76*IFERROR(INDEX(N$71:N$74,MATCH($B92,$B$71:$B$74,0)),1) -> 77.916667 | ... BN92: =BN51*BN$76*IFERROR(INDEX(BN$71:BN$74,MATCH($B92,$B$71:$B$74,0)),1) -> 165
B93: =B92 -> New York | C93: =C90 -> Men's | G93: =G52*G$76*IFERROR(INDEX(G$71:G$74,MATCH($B93,$B$71:$B$74,0)),1) -> 0 | H93: =H52*H$76*IFERROR(INDEX(H$71:H$74,MATCH($B93,$B$71:$B$74,0)),1) -> 0 | I93: =I52*I$76*IFERROR(INDEX(I$71:I$74,MATCH($B93,$B$71:$B$74,0)),1) -> 65 | J93: =J52*J$76*IFERROR(INDEX(J$71:J$74,MATCH($B93,$B$71:$B$74,0)),1) -> 70.416667 | K93: =K52*K$76*IFERROR(INDEX(K$71:K$74,MATCH($B93,$B$71:$B$74,0)),1) -> 75.833333 | L93: =L52*L$76*IFERROR(INDEX(L$71:L$74,MATCH($B93,$B$71:$B$74,0)),1) -> 81.25 | M93: =M52*M$76*IFERROR(INDEX(M$71:M$74,MATCH($B93,$B$71:$B$74,0)),1) -> 216.66667 | N93: =N52*N$76*IFERROR(INDEX(N$71:N$74,MATCH($B93,$B$71:$B$74,0)),1) -> 92.083333 | ... BN93: =BN52*BN$76*IFERROR(INDEX(BN$71:BN$74,MATCH($B93,$B$71:$B$74,0)),1) -> 195
B94: =B93 -> New York | C94: =C91 -> Accessories | G94: =G53*G$76*IFERROR(INDEX(G$71:G$74,MATCH($B94,$B$71:$B$74,0)),1) -> 0 | H94: =H53*H$76*IFERROR(INDEX(H$71:H$74,MATCH($B94,$B$71:$B$74,0)),1) -> 0 | I94: =I53*I$76*IFERROR(INDEX(I$71:I$74,MATCH($B94,$B$71:$B$74,0)),1) -> 50 | J94: =J53*J$76*IFERROR(INDEX(J$71:J$74,MATCH($B94,$B$71:$B$74,0)),1) -> 54.166667 | K94: =K53*K$76*IFERROR(INDEX(K$71:K$74,MATCH($B94,$B$71:$B$74,0)),1) -> 58.333333 | L94: =L53*L$76*IFERROR(INDEX(L$71:L$74,MATCH($B94,$B$71:$B$74,0)),1) -> 62.5 | M94: =M53*M$76*IFERROR(INDEX(M$71:M$74,MATCH($B94,$B$71:$B$74,0)),1) -> 166.66667 | N94: =N53*N$76*IFERROR(INDEX(N$71:N$74,MATCH($B94,$B$71:$B$74,0)),1) -> 70.833333 | ... BN94: =BN53*BN$76*IFERROR(INDEX(BN$71:BN$74,MATCH($B94,$B$71:$B$74,0)),1) -> 150
B95: =CaseData!$B$33 -> Montreal | C95: =C92 -> Women's | G95: =G54*G$76*IFERROR(INDEX(G$71:G$74,MATCH($B95,$B$71:$B$74,0)),1) -> 0 | H95: =H54*H$76*IFERROR(INDEX(H$71:H$74,MATCH($B95,$B$71:$B$74,0)),1) -> 0 | I95: =I54*I$76*IFERROR(INDEX(I$71:I$74,MATCH($B95,$B$71:$B$74,0)),1) -> 0 | J95: =J54*J$76*IFERROR(INDEX(J$71:J$74,MATCH($B95,$B$71:$B$74,0)),1) -> 0 | K95: =K54*K$76*IFERROR(INDEX(K$71:K$74,MATCH($B95,$B$71:$B$74,0)),1) -> 0 | L95: =L54*L$76*IFERROR(INDEX(L$71:L$74,MATCH($B95,$B$71:$B$74,0)),1) -> 0 | M95: =M54*M$76*IFERROR(INDEX(M$71:M$74,MATCH($B95,$B$71:$B$74,0)),1) -> 0 | N95: =N54*N$76*IFERROR(INDEX(N$71:N$74,MATCH($B95,$B$71:$B$74,0)),1) -> 0 | ... BN95: =BN54*BN$76*IFERROR(INDEX(BN$71:BN$74,MATCH($B95,$B$71:$B$74,0)),1) -> 270
B96: =B95 -> Montreal | C96: =C93 -> Men's | G96: =G55*G$76*IFERROR(INDEX(G$71:G$74,MATCH($B96,$B$71:$B$74,0)),1) -> 0 | H96: =H55*H$76*IFERROR(INDEX(H$71:H$74,MATCH($B96,$B$71:$B$74,0)),1) -> 0 | I96: =I55*I$76*IFERROR(INDEX(I$71:I$74,MATCH($B96,$B$71:$B$74,0)),1) -> 0 | J96: =J55*J$76*IFERROR(INDEX(J$71:J$74,MATCH($B96,$B$71:$B$74,0)),1) -> 0 | K96: =K55*K$76*IFERROR(INDEX(K$71:K$74,MATCH($B96,$B$71:$B$74,0)),1) -> 0 | L96: =L55*L$76*IFERROR(INDEX(L$71:L$74,MATCH($B96,$B$71:$B$74,0)),1) -> 0 | M96: =M55*M$76*IFERROR(INDEX(M$71:M$74,MATCH($B96,$B$71:$B$74,0)),1) -> 0 | N96: =N55*N$76*IFERROR(INDEX(N$71:N$74,MATCH($B96,$B$71:$B$74,0)),1) -> 0 | ... BN96: =BN55*BN$76*IFERROR(INDEX(BN$71:BN$74,MATCH($B96,$B$71:$B$74,0)),1) -> 255
B97: =B96 -> Montreal | C97: =C94 -> Accessories | G97: =G56*G$76*IFERROR(INDEX(G$71:G$74,MATCH($B97,$B$71:$B$74,0)),1) -> 0 | H97: =H56*H$76*IFERROR(INDEX(H$71:H$74,MATCH($B97,$B$71:$B$74,0)),1) -> 0 | I97: =I56*I$76*IFERROR(INDEX(I$71:I$74,MATCH($B97,$B$71:$B$74,0)),1) -> 0 | J97: =J56*J$76*IFERROR(INDEX(J$71:J$74,MATCH($B97,$B$71:$B$74,0)),1) -> 0 | K97: =K56*K$76*IFERROR(INDEX(K$71:K$74,MATCH($B97,$B$71:$B$74,0)),1) -> 0 | L97: =L56*L$76*IFERROR(INDEX(L$71:L$74,MATCH($B97,$B$71:$B$74,0)),1) -> 0 | M97: =M56*M$76*IFERROR(INDEX(M$71:M$74,MATCH($B97,$B$71:$B$74,0)),1) -> 0 | N97: =N56*N$76*IFERROR(INDEX(N$71:N$74,MATCH($B97,$B$71:$B$74,0)),1) -> 0 | ... BN97: =BN56*BN$76*IFERROR(INDEX(BN$71:BN$74,MATCH($B97,$B$71:$B$74,0)),1) -> 390
