Workbook
Name company: CaseData!$E$84
Name expense_scenarios: CaseData!$L$10:$L$12
Name expense_selector: Calculations!$F$8
Name fx_rates: CaseData!$D$30:$D$32
Name fx_rates_selector: Calculations!$F$29
Name periods: CaseData!$H$36
Name pricing_scenarios: CaseData!$L$10:$L$12
Name pricing_selector: Calculations!$F$6
Name start_date: CaseData!$H$35
Name topic: "CFM Topic: " & CaseData!$E$85

Sheet Calculations
A1: {=company} -> Megabrick Inc.
A2: {=topic} -> CFM Topic: Costs | J2: {=EDATE( start_date, _xlfn.SEQUENCE( 1, periods, 0, 3 ))} -> 43831 | K2: 43922 | L2: 44013 | M2: 44105 | N2: 44197 | O2: 44287 | P2: 44378 | Q2: 44470 | R2: 44562 | S2: 44652 | T2: 44743 | U2: 44835 | V2: 44927 | W2: 45017 | X2: 45108 | Y2: 45200 | Z2: 45292 | AA2: 45383 | AB2: 45474 | AC2: 45566 | AD2: 45658 | AE2: 45748 | AF2: 45839 | AG2: 45931 | AH2: 46023 | AI2: 46113 | AJ2: 46204 | AK2: 46296 | AL2: 46388 | AM2: 46478 | AN2: 46569 | AO2: 46661 | AP2: 46753 | AQ2: 46844 | AR2: 46935 | AS2: 47027 | AT2: 47119 | AU2: 47209 | AV2: 47300 | AW2: 47392 | AX2: 47484 | AY2: 47574 | AZ2: 47665 | BA2: 47757 | BB2: 47849 | BC2: 47939 | BD2: 48030 | BE2: 48122 | BF2: 48214 | BG2: 48305 | BH2: 48396 | BI2: 48488 | BJ2: 48580 | BK2: 48670 | BL2: 48761 | BM2: 48853 | BN2: 48945 | BO2: 49035 | BP2: 49126 | BQ2: 49218
A3: CALCULATION SCHEDULE | F3: Constant | G3: Unit | H3: Total | J3: {=EOMONTH( start_date, _xlfn.SEQUENCE( 1, periods, 2, 3 ))} -> 43921 | K3: 44012 | L3: 44104 | M3: 44196 | N3: 44286 | O3: 44377 | P3: 44469 | Q3: 44561 | R3: 44651 | S3: 44742 | T3: 44834 | U3: 44926 | V3: 45016 | W3: 45107 | X3: 45199 | Y3: 45291 | Z3: 45382 | AA3: 45473 | AB3: 45565 | AC3: 45657 | AD3: 45747 | AE3: 45838 | AF3: 45930 | AG3: 46022 | AH3: 46112 | AI3: 46203 | AJ3: 46295 | AK3: 46387 | AL3: 46477 | AM3: 46568 | AN3: 46660 | AO3: 46752 | AP3: 46843 | AQ3: 46934 | AR3: 47026 | AS3: 47118 | AT3: 47208 | AU3: 47299 | AV3: 47391 | AW3: 47483 | AX3: 47573 | AY3: 47664 | AZ3: 47756 | BA3: 47848 | BB3: 47938 | BC3: 48029 | BD3: 48121 | BE3: 48213 | BF3: 48304 | BG3: 48395 | BH3: 48487 | BI3: 48579 | BJ3: 48669 | BK3: 48760 | BL3: 48852 | BM3: 48944 | BN3: 49034 | BO3: 49125 | BP3: 49217 | BQ3: 49309
B5: Scenarios
E6: Pricing scenario | F6: 1
E8: Expense scenario | F8: 1
A11: REVENUES
B13: Volume
E14: Forecasted unit sales | G14: slabs | H14: {=_xlfn.BYROW(_xlfn.ANCHORARRAY( J14), _xleta.SUM )} -> 1881523.8 | J14: {=_xlfn.LET( _xlpm.demand_constant, 1 + CaseData!$H$44, _xlpm.quarters_timeline,_xlfn.ANCHORARRAY( Time!J16), _xlpm.demand_base, INDEX( CaseData!$H$42:$K$42, 1, MOD( _xlfn.SEQUENCE( 1, periods ) - 1, 4) + 1 ), _xlpm.demand_factor, _xlpm.demand_constant ^ INT( _xlfn.SEQUENCE( 1, periods, 0 ) / 4 ), _xlpm.demand_base * _xlpm.demand_factor )} -> 26500 | K14: 28100 | L14: 29000 | M14: 25200 | N14: 27030 | O14: 28662 | P14: 29580 | Q14: 25704 | R14: 27570.6 | S14: 29235.24 | T14: 30171.6 | U14: 26218.08 | V14: 28122.012 | W14: 29819.945 | X14: 30775.032 | Y14: 26742.442 | Z14: 28684.452 | AA14: 30416.344 | AB14: 31390.533 | AC14: 27277.29 | AD14: 29258.141 | AE14: 31024.671 | AF14: 32018.343 | AG14: 27822.836 | AH14: 29843.304 | AI14: 31645.164 | AJ14: 32658.71 | AK14: 28379.293 | AL14: 30440.17 | AM14: 32278.067 | AN14: 33311.884 | AO14: 28946.879 | AP14: 31048.974 | AQ14: 32923.629 | AR14: 33978.122 | AS14: 29525.816 | AT14: 31669.953 | AU14: 33582.101 | AV14: 34657.684 | AW14: 30116.333 | AX14: 32303.352 | AY14: 34253.743 | AZ14: 35350.838 | BA14: 30718.659 | BB14: 32949.419 | BC14: 34938.818 | BD14: 36057.855 | BE14: 31333.033 | BF14: 33608.408 | BG14: 35637.594 | BH14: 36779.012 | BI14: 31959.693 | BJ14: 34280.576 | BK14: 36350.346 | BL14: 37514.592 | BM14: 32598.887 | BN14: 34966.187 | BO14: 37077.353 | BP14: 38264.884 | BQ14: 33250.865
B16: Sales Price
E17: Forecasted sales price | G17: USD / slab | J17: {=_xlfn.LET( _xlpm.indexation_table, CaseData!$H$12:$J$13, _xlpm.indexation_rows, CaseData!$D$12:$D$13, _xlpm.indexation_columns, CaseData!$H$10:$J$10, _xlpm.current_scenario, INDEX( pricing_scenarios, pricing_selector ), _xlpm.current_item, $B$16, _xlpm.index, INDEX( _xlpm.indexation_table, MATCH( _xlpm.current_item, _xlpm.indexation_rows, 0 ), MATCH( _xlpm.current_scenario, _xlpm.indexation_columns, 0 ) ), _xlpm.compound_frequency, CaseData!$E$12, _xlpm.quarterly_operating_flag,_xlfn.ANCHORARRAY( Time!$J$18), _xlpm.yearly_operating_flag,_xlfn.ANCHORARRAY( Time!$J$19), _xlpm.active_operating_flag, IF( _xlpm.compound_frequency = "Annual", _xlpm.yearly_operating_flag, _xlpm.quarterly_operating_flag ), _xlpm.periodic_rate, IF( _xlpm.compound_frequency = "Annual", 1 + _xlpm.index, (1 + _xlpm.index ) ^ (1 / 4 ) ), _xlpm.indexation_count, _xlfn.SCAN( 0, _xlpm.active_operating_flag, _xlfn.LAMBDA(_xlpm.s,_xlpm.c, _xlpm.s + _xlpm.c ) ), _xlpm.base_price, CaseData!$H$40, _xlpm.base_price * _xlpm.periodic_rate ^ _xlpm.indexation_count )} -> 280 | K17: 280 | L17: 280 | M17: 280 | N17: 287 | O17: 287 | P17: 287 | Q17: 287 | R17: 294.175 | S17: 294.175 | T17: 294.175 | U17: 294.175 | V17: 301.52937 | W17: 301.52937 | X17: 301.52937 | Y17: 301.52937 | Z17: 309.06761 | AA17: 309.06761 | AB17: 309.06761 | AC17: 309.06761 | AD17: 316.7943 | AE17: 316.7943 | AF17: 316.7943 | AG17: 316.7943 | AH17: 324.71416 | AI17: 324.71416 | AJ17: 324.71416 | AK17: 324.71416 | AL17: 332.83201 | AM17: 332.83201 | AN17: 332.83201 | AO17: 332.83201 | AP17: 341.15281 | AQ17: 341.15281 | AR17: 341.15281 | AS17: 341.15281 | AT17: 349.68163 | AU17: 349.68163 | AV17: 349.68163 | AW17: 349.68163 | AX17: 358.42367 | AY17: 358.42367 | AZ17: 358.42367 | BA17: 358.42367 | BB17: 367.38426 | BC17: 367.38426 | BD17: 367.38426 | BE17: 367.38426 | BF17: 376.56887 | BG17: 376.56887 | BH17: 376.56887 | BI17: 376.56887 | BJ17: 385.98309 | BK17: 385.98309 | BL17: 385.98309 | BM17: 385.98309 | BN17: 395.63267 | BO17: 395.63267 | BP17: 395.63267 | BQ17: 395.63267
B19: Revenue
E20: Forecasted revenue | G20: USD m | H20: {=_xlfn.BYROW(_xlfn.ANCHORARRAY( J20), _xleta.SUM )} -> 6.3553839e+08 | J20: {=_xlfn.ANCHORARRAY( J14) *_xlfn.ANCHORARRAY( J17)} -> 7420000 | K20: 7868000 | L20: 8120000 | M20: 7056000 | N20: 7757610 | O20: 8225994 | P20: 8489460 | Q20: 7377048 | R20: 8110581.3 | S20: 8600276.7 | T20: 8875730.4 | U20: 7712703.7 | V20: 8479612.7 | W20: 8991589.3 | X20: 9279576.2 | Y20: 8063631.7 | Z20: 8865435.1 | AA20: 9400706.6 | AB20: 9701796.9 | AC20: 8430526.9 | AD20: 9268812.4 | AE20: 9828438.8 | AF20: 10143229 | AG20: 8814115.9 | AH20: 9690543.3 | AI20: 10275633 | AJ20: 10604746 | AK20: 9215158.2 | AL20: 10131463 | AM20: 10743174 | AN20: 11087261 | AO20: 9634447.9 | AP20: 10592445 | AQ20: 11231988 | AR20: 11591732 | AS20: 10072815 | AT20: 11074401 | AU20: 11743044 | AV20: 12119156 | AW20: 10531128 | AX20: 11578286 | AY20: 12277352 | AZ20: 12670577 | BA20: 11010295 | BB20: 12105098 | BC20: 12835972 | BD20: 13247089 | BE20: 11511263 | BF20: 12655880 | BG20: 13420009 | BH20: 13849831 | BI20: 12035026 | BJ20: 13231723 | BK20: 14030619 | BL20: 14479998 | BM20: 12582619 | BN20: 13833766 | BO20: 14669012 | BP20: 15138838 | BQ20: 13155128
A23: RAW MATERIAL EXPENSES
B25: Demand
E26: Tonnes of raw material needed | G26: tonnes | H26: {=_xlfn.BYROW(_xlfn.ANCHORARRAY( J26), _xleta.SUM )} -> 5644571.3 | J26: {=_xlfn.LET( _xlpm.raw_material_per_slab, CaseData!$H$52, _xlpm.slabs,_xlfn.ANCHORARRAY( Calculations!J14), _xlpm.raw_material_per_slab * _xlpm.slabs)} -> 79500 | K26: 84300 | L26: 87000 | M26: 75600 | N26: 81090 | O26: 85986 | P26: 88740 | Q26: 77112 | R26: 82711.8 | S26: 87705.72 | T26: 90514.8 | U26: 78654.24 | V26: 84366.036 | W26: 89459.834 | X26: 92325.096 | Y26: 80227.325 | Z26: 86053.357 | AA26: 91249.031 | AB26: 94171.598 | AC26: 81831.871 | AD26: 87774.424 | AE26: 93074.012 | AF26: 96055.03 | AG26: 83468.509 | AH26: 89529.912 | AI26: 94935.492 | AJ26: 97976.13 | AK26: 85137.879 | AL26: 91320.511 | AM26: 96834.202 | AN26: 99935.653 | AO26: 86840.636 | AP26: 93146.921 | AQ26: 98770.886 | AR26: 101934.37 | AS26: 88577.449 | AT26: 95009.859 | AU26: 100746.3 | AV26: 103973.05 | AW26: 90348.998 | AX26: 96910.056 | AY26: 102761.23 | AZ26: 106052.51 | BA26: 92155.978 | BB26: 98848.258 | BC26: 104816.45 | BD26: 108173.56 | BE26: 93999.098 | BF26: 100825.22 | BG26: 106912.78 | BH26: 110337.04 | BI26: 95879.08 | BJ26: 102841.73 | BK26: 109051.04 | BL26: 112543.78 | BM26: 97796.661 | BN26: 104898.56 | BO26: 111232.06 | BP26: 114794.65 | BQ26: 99752.594
B28: Expense Indexations
E29: Exchange rate scenario | F29: 1 | G29: MXN / USD | J29: {=_xlfn.LET( _xlpm.fx_rates_table, CaseData!$H$30:$V$32, _xlpm.fx_columns, CaseData!$H$29:$V$29, _xlpm.fx_rate, INDEX( _xlpm.fx_rates_table, fx_rates_selector, MATCH(_xlfn.ANCHORARRAY( Time!J10), _xlpm.fx_columns, 0 ) ), _xlpm.fx_rate )} -> 19.5 | K29: 19.5 | L29: 19.5 | M29: 19.5 | N29: 20.09 | O29: 20.09 | P29: 20.09 | Q29: 20.09 | R29: 20.69 | S29: 20.69 | T29: 20.69 | U29: 20.69 | V29: 21.31 | W29: 21.31 | X29: 21.31 | Y29: 21.31 | Z29: 21.95 | AA29: 21.95 | AB29: 21.95 | AC29: 21.95 | AD29: 22.61 | AE29: 22.61 | AF29: 22.61 | AG29: 22.61 | AH29: 23.29 | AI29: 23.29 | AJ29: 23.29 | AK29: 23.29 | AL29: 23.99 | AM29: 23.99 | AN29: 23.99 | AO29: 23.99 | AP29: 24.71 | AQ29: 24.71 | AR29: 24.71 | AS29: 24.71 | AT29: 25.45 | AU29: 25.45 | AV29: 25.45 | AW29: 25.45 | AX29: 26.21 | AY29: 26.21 | AZ29: 26.21 | BA29: 26.21 | BB29: 27 | BC29: 27 | BD29: 27 | BE29: 27 | BF29: 27.81 | BG29: 27.81 | BH29: 27.81 | BI29: 27.81 | BJ29: 28.64 | BK29: 28.64 | BL29: 28.64 | BM29: 28.64 | BN29: 29.5 | BO29: 29.5 | BP29: 29.5 | BQ29: 29.5
E31: Supplier 1 - unit price adjusted for inflation | G31: USD | J31: {=_xlfn.LET( _xlpm.indexation_table, CaseData!$H$12:$J$13, _xlpm.indexation_rows, CaseData!$D$12:$D$13, _xlpm.indexation_columns, CaseData!$H$10:$J$10, _xlpm.current_scenario, INDEX( expense_scenarios, expense_selector ), _xlpm.current_item, $B$28, _xlpm.index, INDEX( _xlpm.indexation_table, MATCH( _xlpm.current_item, _xlpm.indexation_rows, 0 ), MATCH( _xlpm.current_scenario, _xlpm.indexation_columns, 0 ) ), _xlpm.compound_frequency, CaseData!$E$13, _xlpm.quarterly_operating_flag,_xlfn.ANCHORARRAY( Time!$J$18), _xlpm.yearly_operating_flag,_xlfn.ANCHORARRAY( Time!$J$19), _xlpm.active_operating_flag, IF( _xlpm.compound_frequency = "Annual", _xlpm.yearly_operating_flag, _xlpm.quarterly_operating_flag ), _xlpm.periodic_rate, IF( _xlpm.compound_frequency = "Annual", 1 + _xlpm.index, (1 + _xlpm.index ) ^ (1 / 4 ) ), _xlpm.indexation_count, _xlfn.SCAN( 0, _xlpm.active_operating_flag, _xlfn.LAMBDA(_xlpm.s,_xlpm.c, _xlpm.s + _xlpm.c ) ), _xlpm.base_price, CaseData!$H$55, _xlpm.base_price * _xlpm.periodic_rate ^ _xlpm.indexation_count )} -> 35 | K31: 35 | L31: 35 | M31: 35 | N31: 35.7 | O31: 35.7 | P31: 35.7 | Q31: 35.7 | R31: 36.414 | S31: 36.414 | T31: 36.414 | U31: 36.414 | V31: 37.14228 | W31: 37.14228 | X31: 37.14228 | Y31: 37.14228 | Z31: 37.885126 | AA31: 37.885126 | AB31: 37.885126 | AC31: 37.885126 | AD31: 38.642828 | AE31: 38.642828 | AF31: 38.642828 | AG31: 38.642828 | AH31: 39.415685 | AI31: 39.415685 | AJ31: 39.415685 | AK31: 39.415685 | AL31: 40.203998 | AM31: 40.203998 | AN31: 40.203998 | AO31: 40.203998 | AP31: 41.008078 | AQ31: 41.008078 | AR31: 41.008078 | AS31: 41.008078 | AT31: 41.82824 | AU31: 41.82824 | AV31: 41.82824 | AW31: 41.82824 | AX31: 42.664805 | AY31: 42.664805 | AZ31: 42.664805 | BA31: 42.664805 | BB31: 43.518101 | BC31: 43.518101 | BD31: 43.518101 | BE31: 43.518101 | BF31: 44.388463 | BG31: 44.388463 | BH31: 44.388463 | BI31: 44.388463 | BJ31: 45.276232 | BK31: 45.276232 | BL31: 45.276232 | BM31: 45.276232 | BN31: 46.181757 | BO31: 46.181757 | BP31: 46.181757 | BQ31: 46.181757
E32: Supplier 2 - unit price adjusted for inflation and for fx rate | G32: USD | J32: {=_xlfn.LET( _xlpm.indexation_table, CaseData!$H$12:$J$13, _xlpm.indexation_rows, CaseData!$D$12:$D$13, _xlpm.indexation_columns, CaseData!$H$10:$J$10, _xlpm.current_scenario, INDEX( expense_scenarios, expense_selector ), _xlpm.current_item, $B$28, _xlpm.index, INDEX( _xlpm.indexation_table, MATCH( _xlpm.current_item, _xlpm.indexation_rows, 0 ), MATCH( _xlpm.current_scenario, _xlpm.indexation_columns, 0 ) ), _xlpm.compound_frequency, CaseData!$E$13, _xlpm.quarterly_operating_flag,_xlfn.ANCHORARRAY( Time!$J$18), _xlpm.yearly_operating_flag,_xlfn.ANCHORARRAY( Time!$J$19), _xlpm.active_operating_flag, IF( _xlpm.compound_frequency = "Annual", _xlpm.yearly_operating_flag, _xlpm.quarterly_operating_flag ), _xlpm.periodic_rate, IF( _xlpm.compound_frequency = "Annual", 1 + _xlpm.index, (1 + _xlpm.index ) ^ (1 / 4 ) ), _xlpm.indexation_count, _xlfn.SCAN( 0, _xlpm.active_operating_flag, _xlfn.LAMBDA(_xlpm.s,_xlpm.c, _xlpm.s + _xlpm.c ) ), _xlpm.base_price, CaseData!$H$59, _xlpm.fx_rate,_xlfn.ANCHORARRAY( J29), ( _xlpm.base_price / _xlpm.fx_rate ) * _xlpm.periodic_rate ^ _xlpm.indexation_count )} -> 41.025641 | K32: 41.025641 | L32: 41.025641 | M32: 41.025641 | N32: 40.617222 | O32: 40.617222 | P32: 40.617222 | Q32: 40.617222 | R32: 40.22813 | S32: 40.22813 | T32: 40.22813 | U32: 40.22813 | V32: 39.838874 | W32: 39.838874 | X32: 39.838874 | Y32: 39.838874 | Z32: 39.45083 | AA32: 39.45083 | AB32: 39.45083 | AC32: 39.45083 | AD32: 39.065221 | AE32: 39.065221 | AF32: 39.065221 | AG32: 39.065221 | AH32: 38.683123 | AI32: 38.683123 | AJ32: 38.683123 | AK32: 38.683123 | AL32: 38.305483 | AM32: 38.305483 | AN32: 38.305483 | AO32: 38.305483 | AP32: 37.933124 | AQ32: 37.933124 | AR32: 37.933124 | AS32: 37.933124 | AT32: 37.566761 | AU32: 37.566761 | AV32: 37.566761 | AW32: 37.566761 | AX32: 37.207003 | AY32: 37.207003 | AZ32: 37.207003 | BA32: 37.207003 | BB32: 36.84072 | BC32: 36.84072 | BD32: 36.84072 | BE32: 36.84072 | BF32: 36.483043 | BG32: 36.483043 | BH32: 36.483043 | BI32: 36.483043 | BJ32: 36.134263 | BK32: 36.134263 | BL32: 36.134263 | BM32: 36.134263 | BN32: 35.782475 | BO32: 35.782475 | BP32: 35.782475 | BQ32: 35.782475
B34: Supply optimised by price and volume capacity
E35: Supplier 1 | G35: tonnes | J35: {=_xlfn.LET( _xlpm.demand,_xlfn.ANCHORARRAY( J26), _xlpm.supplier1_price,_xlfn.ANCHORARRAY( J31), _xlpm.supplier2_price,_xlfn.ANCHORARRAY( J32), _xlpm.supplier1_capacity, CaseData!$H$56, _xlpm.supplier2_capacity, CaseData!$H$60, _xlpm.supply, IF( _xlpm.supplier1_price <= _xlpm.supplier2_price, IF( _xlpm.demand <= _xlpm.supplier1_capacity, _xlpm.demand, _xlpm.supplier1_capacity ), _xlpm.demand - IF( _xlpm.demand <= _xlpm.supplier2_capacity, _xlpm.demand, _xlpm.supplier2_capacity ) ), _xlpm.overflow, _xlpm.demand - _xlpm.supply, _xlfn.VSTACK( _xlpm.supply, _xlpm.overflow ) )} -> 79500 | K35: 84300 | L35: 87000 | M35: 75600 | N35: 81090 | O35: 85986 | P35: 88740 | Q35: 77112 | R35: 82711.8 | S35: 87705.72 | T35: 90000 | U35: 78654.24 | V35: 84366.036 | W35: 89459.834 | X35: 90000 | Y35: 80227.325 | Z35: 86053.357 | AA35: 90000 | AB35: 90000 | AC35: 81831.871 | AD35: 87774.424 | AE35: 90000 | AF35: 90000 | AG35: 83468.509 | AH35: 19529.912 | AI35: 24935.492 | AJ35: 27976.13 | AK35: 15137.879 | AL35: 21320.511 | AM35: 26834.202 | AN35: 29935.653 | AO35: 16840.636 | AP35: 23146.921 | AQ35: 28770.886 | AR35: 31934.366 | AS35: 18577.449 | AT35: 25009.859 | AU35: 30746.304 | AV35: 33973.053 | AW35: 20348.998 | AX35: 26910.056 | AY35: 32761.23 | AZ35: 36052.515 | BA35: 22155.978 | BB35: 28848.258 | BC35: 34816.454 | BD35: 38173.565 | BE35: 23999.098 | BF35: 30825.223 | BG35: 36912.783 | BH35: 40337.036 | BI35: 25879.08 | BJ35: 32841.727 | BK35: 39051.039 | BL35: 42543.777 | BM35: 27796.661 | BN35: 34898.562 | BO35: 41232.06 | BP35: 44794.652 | BQ35: 29752.594
E36: Supplier 2 | G36: tonnes | J36: 0 | K36: 0 | L36: 0 | M36: 0 | N36: 0 | O36: 0 | P36: 0 | Q36: 0 | R36: 0 | S36: 0 | T36: 514.8 | U36: 0 | V36: 0 | W36: 0 | X36: 2325.096 | Y36: 0 | Z36: 0 | AA36: 1249.0311 | AB36: 4171.5979 | AC36: 0 | AD36: 0 | AE36: 3074.0117 | AF36: 6055.0299 | AG36: 0 | AH36: 70000 | AI36: 70000 | AJ36: 70000 | AK36: 70000 | AL36: 70000 | AM36: 70000 | AN36: 70000 | AO36: 70000 | AP36: 70000 | AQ36: 70000 | AR36: 70000 | AS36: 70000 | AT36: 70000 | AU36: 70000 | AV36: 70000 | AW36: 70000 | AX36: 70000 | AY36: 70000 | AZ36: 70000 | BA36: 70000 | BB36: 70000 | BC36: 70000 | BD36: 70000 | BE36: 70000 | BF36: 70000 | BG36: 70000 | BH36: 70000 | BI36: 70000 | BJ36: 70000 | BK36: 70000 | BL36: 70000 | BM36: 70000 | BN36: 70000 | BO36: 70000 | BP36: 70000 | BQ36: 70000
B38: Operating expenses | J38: .
E39: Supplier 1 | G39: USD | H39: {=_xlfn.BYROW(_xlfn.ANCHORARRAY( J39), _xleta.SUM )} -> 1.2111142e+08 | J39: {=_xlfn.LET( _xlpm.prices, _xlfn.VSTACK(_xlfn.ANCHORARRAY( J31),_xlfn.ANCHORARRAY( J32) ), _xlpm.supply,_xlfn.ANCHORARRAY( J35), _xlpm.prices * _xlpm.supply )} -> 2782500 | K39: 2950500 | L39: 3045000 | M39: 2646000 | N39: 2894913 | O39: 3069700.2 | P39: 3168018 | Q39: 2752898.4 | R39: 3011867.5 | S39: 3193716.1 | T39: 3277260 | U39: 2864115.5 | V39: 3133546.9 | W39: 3322742.2 | X39: 3342805.2 | Y39: 2979825.8 | Z39: 3260142.2 | AA39: 3409661.3 | AB39: 3409661.3 | AC39: 3100210.7 | AD39: 3391852 | AE39: 3477854.5 | AF39: 3477854.5 | AG39: 3225459.2 | AH39: 769784.87 | AI39: 982849.49 | AJ39: 1102698.3 | AK39: 596669.86 | AL39: 857169.77 | AM39: 1078842.2 | AN39: 1203532.9 | AO39: 677060.92 | AP39: 949210.74 | AQ39: 1179838.7 | AR39: 1309567 | AS39: 761825.49 | AT39: 1046118.4 | AU39: 1286063.8 | AV39: 1421033 | AW39: 851162.78 | AX39: 1148112.3 | AY39: 1397751.5 | AZ39: 1538173.5 | BA39: 945280.48 | BB39: 1255421.4 | BC39: 1515146 | BD39: 1661241 | BE39: 1044395.2 | BF39: 1368284.2 | BG39: 1638501.7 | BH39: 1790499 | BI39: 1148732.6 | BJ39: 1486949.7 | BK39: 1768083.9 | BL39: 1926221.9 | BM39: 1258528.1 | BN39: 1611676.9 | BO39: 1904169 | BP39: 2068695.7 | BQ39: 1374027.1
E40: Supplier 2 | G40: USD | H40: 94465894 | J40: 0 | K40: 0 | L40: 0 | M40: 0 | N40: 0 | O40: 0 | P40: 0 | Q40: 0 | R40: 0 | S40: 0 | T40: 20709.441 | U40: 0 | V40: 0 | W40: 0 | X40: 92629.206 | Y40: 0 | Z40: 0 | AA40: 49275.314 | AB40: 164573 | AC40: 0 | AD40: 0 | AE40: 120086.95 | AF40: 236541.08 | AG40: 0 | AH40: 2707818.6 | AI40: 2707818.6 | AJ40: 2707818.6 | AK40: 2707818.6 | AL40: 2681383.8 | AM40: 2681383.8 | AN40: 2681383.8 | AO40: 2681383.8 | AP40: 2655318.7 | AQ40: 2655318.7 | AR40: 2655318.7 | AS40: 2655318.7 | AT40: 2629673.2 | AU40: 2629673.2 | AV40: 2629673.2 | AW40: 2629673.2 | AX40: 2604490.2 | AY40: 2604490.2 | AZ40: 2604490.2 | BA40: 2604490.2 | BB40: 2578850.4 | BC40: 2578850.4 | BD40: 2578850.4 | BE40: 2578850.4 | BF40: 2553813 | BG40: 2553813 | BH40: 2553813 | BI40: 2553813 | BJ40: 2529398.4 | BK40: 2529398.4 | BL40: 2529398.4 | BM40: 2529398.4 | BN40: 2504773.2 | BO40: 2504773.2 | BP40: 2504773.2 | BQ40: 2504773.2
E41: Raw material expenses | G41: USD | H41: {=_xlfn.BYROW(_xlfn.ANCHORARRAY( J41), _xleta.SUM )} -> 2.1557732e+08 | J41: {=_xlfn.BYCOL(_xlfn.ANCHORARRAY( J39), _xleta.SUM )} -> 2782500 | K41: 2950500 | L41: 3045000 | M41: 2646000 | N41: 2894913 | O41: 3069700.2 | P41: 3168018 | Q41: 2752898.4 | R41: 3011867.5 | S41: 3193716.1 | T41: 3297969.4 | U41: 2864115.5 | V41: 3133546.9 | W41: 3322742.2 | X41: 3435434.4 | Y41: 2979825.8 | Z41: 3260142.2 | AA41: 3458936.6 | AB41: 3574234.3 | AC41: 3100210.7 | AD41: 3391852 | AE41: 3597941.5 | AF41: 3714395.6 | AG41: 3225459.2 | AH41: 3477603.5 | AI41: 3690668.1 | AJ41: 3810516.9 | AK41: 3304488.5 | AL41: 3538553.6 | AM41: 3760226 | AN41: 3884916.7 | AO41: 3358444.7 | AP41: 3604529.5 | AQ41: 3835157.4 | AR41: 3964885.7 | AS41: 3417144.2 | AT41: 3675791.6 | AU41: 3915737 | AV41: 4050706.3 | AW41: 3480836 | AX41: 3752602.5 | AY41: 4002241.6 | AZ41: 4142663.7 | BA41: 3549770.7 | BB41: 3834271.8 | BC41: 4093996.4 | BD41: 4240091.5 | BE41: 3623245.6 | BF41: 3922097.3 | BG41: 4192314.7 | BH41: 4344312.1 | BI41: 3702545.6 | BJ41: 4016348.1 | BK41: 4297482.3 | BL41: 4455620.4 | BM41: 3787926.5 | BN41: 4116450.1 | BO41: 4408942.2 | BP41: 4573469 | BQ41: 3878800.3
A44: MANUFACTORING COSTS
B46: Volume brackets
E47: Bracket 1 sales (0 – 25,000) | G47: slabs | H47: {=_xlfn.BYROW(_xlfn.ANCHORARRAY( J47), _xleta.SUM )} -> 1500000 | J47: {=_xlfn.LET( _xlpm.unit_sales,_xlfn.ANCHORARRAY( J14), _xlpm.upper, CaseData!$I$66:$I$69, _xlpm.lower, _xlfn.VSTACK( 0, CaseData!$I$66:$I$68 ), _xlpm.capped, IF( _xlpm.unit_sales < _xlpm.upper, _xlpm.unit_sales, _xlpm.upper ), _xlpm.width, _xlpm.capped - _xlpm.lower, IF( _xlpm.width > 0, _xlpm.width, 0 ) )} -> 25000 | K47: 25000 | L47: 25000 | M47: 25000 | N47: 25000 | O47: 25000 | P47: 25000 | Q47: 25000 | R47: 25000 | S47: 25000 | T47: 25000 | U47: 25000 | V47: 25000 | W47: 25000 | X47: 25000 | Y47: 25000 | Z47: 25000 | AA47: 25000 | AB47: 25000 | AC47: 25000 | AD47: 25000 | AE47: 25000 | AF47: 25000 | AG47: 25000 | AH47: 25000 | AI47: 25000 | AJ47: 25000 | AK47: 25000 | AL47: 25000 | AM47: 25000 | AN47: 25000 | AO47: 25000 | AP47: 25000 | AQ47: 25000 | AR47: 25000 | AS47: 25000 | AT47: 25000 | AU47: 25000 | AV47: 25000 | AW47: 25000 | AX47: 25000 | AY47: 25000 | AZ47: 25000 | BA47: 25000 | BB47: 25000 | BC47: 25000 | BD47: 25000 | BE47: 25000 | BF47: 25000 | BG47: 25000 | BH47: 25000 | BI47: 25000 | BJ47: 25000 | BK47: 25000 | BL47: 25000 | BM47: 25000 | BN47: 25000 | BO47: 25000 | BP47: 25000 | BQ47: 25000
E48: Bracket 2 sales (25,001 – 30,000) | G48: slabs | H48: 257222.33 | J48: 1500 | K48: 3100 | L48: 4000 | M48: 200 | N48: 2030 | O48: 3662 | P48: 4580 | Q48: 704 | R48: 2570.6 | S48: 4235.24 | T48: 5000 | U48: 1218.08 | V48: 3122.012 | W48: 4819.9448 | X48: 5000 | Y48: 1742.4416 | Z48: 3684.4522 | AA48: 5000 | AB48: 5000 | AC48: 2277.2904 | AD48: 4258.1413 | AE48: 5000 | AF48: 5000 | AG48: 2822.8362 | AH48: 4843.3041 | AI48: 5000 | AJ48: 5000 | AK48: 3379.293 | AL48: 5000 | AM48: 5000 | AN48: 5000 | AO48: 3946.8788 | AP48: 5000 | AQ48: 5000 | AR48: 5000 | AS48: 4525.8164 | AT48: 5000 | AU48: 5000 | AV48: 5000 | AW48: 5000 | AX48: 5000 | AY48: 5000 | AZ48: 5000 | BA48: 5000 | BB48: 5000 | BC48: 5000 | BD48: 5000 | BE48: 5000 | BF48: 5000 | BG48: 5000 | BH48: 5000 | BI48: 5000 | BJ48: 5000 | BK48: 5000 | BL48: 5000 | BM48: 5000 | BN48: 5000 | BO48: 5000 | BP48: 5000 | BQ48: 5000
E49: Bracket 3 sales (30,001 – 34,000) | G49: slabs | H49: 100171.95 | J49: 0 | K49: 0 | L49: 0 | M49: 0 | N49: 0 | O49: 0 | P49: 0 | Q49: 0 | R49: 0 | S49: 0 | T49: 171.6 | U49: 0 | V49: 0 | W49: 0 | X49: 775.032 | Y49: 0 | Z49: 0 | AA49: 416.3437 | AB49: 1390.5326 | AC49: 0 | AD49: 0 | AE49: 1024.6706 | AF49: 2018.3433 | AG49: 0 | AH49: 0 | AI49: 1645.164 | AJ49: 2658.7102 | AK49: 0 | AL49: 440.17019 | AM49: 2278.0673 | AN49: 3311.8844 | AO49: 0 | AP49: 1048.9736 | AQ49: 2923.6286 | AR49: 3978.122 | AS49: 0 | AT49: 1669.9531 | AU49: 3582.1012 | AV49: 4000 | AW49: 116.33273 | AX49: 2303.3521 | AY49: 4000 | AZ49: 4000 | BA49: 718.65938 | BB49: 2949.4192 | BC49: 4000 | BD49: 4000 | BE49: 1333.0326 | BF49: 3608.4076 | BG49: 4000 | BH49: 4000 | BI49: 1959.6932 | BJ49: 4000 | BK49: 4000 | BL49: 4000 | BM49: 2598.8871 | BN49: 4000 | BO49: 4000 | BP49: 4000 | BQ49: 3250.8648
E50: Bracket 4 sales (> 34,000) | G50: slabs | H50: 24129.484 | J50: 0 | K50: 0 | L50: 0 | M50: 0 | N50: 0 | O50: 0 | P50: 0 | Q50: 0 | R50: 0 | S50: 0 | T50: 0 | U50: 0 | V50: 0 | W50: 0 | X50: 0 | Y50: 0 | Z50: 0 | AA50: 0 | AB50: 0 | AC50: 0 | AD50: 0 | AE50: 0 | AF50: 0 | AG50: 0 | AH50: 0 | AI50: 0 | AJ50: 0 | AK50: 0 | AL50: 0 | AM50: 0 | AN50: 0 | AO50: 0 | AP50: 0 | AQ50: 0 | AR50: 0 | AS50: 0 | AT50: 0 | AU50: 0 | AV50: 657.68449 | AW50: 0 | AX50: 0 | AY50: 253.7432 | AZ50: 1350.8382 | BA50: 0 | BB50: 0 | BC50: 938.81807 | BD50: 2057.8549 | BE50: 0 | BF50: 0 | BG50: 1637.5944 | BH50: 2779.012 | BI50: 0 | BJ50: 280.57571 | BK50: 2350.3463 | BL50: 3514.5923 | BM50: 0 | BN50: 966.18722 | BO50: 3077.3532 | BP50: 4264.8841 | BQ50: 0
E51: Volume per quarter | G51: slabs | H51: {=_xlfn.BYROW(_xlfn.ANCHORARRAY( J51), _xleta.SUM )} -> 1881523.8 | J51: {=_xlfn.BYCOL(_xlfn.ANCHORARRAY( J47), _xleta.SUM )} -> 26500 | K51: 28100 | L51: 29000 | M51: 25200 | N51: 27030 | O51: 28662 | P51: 29580 | Q51: 25704 | R51: 27570.6 | S51: 29235.24 | T51: 30171.6 | U51: 26218.08 | V51: 28122.012 | W51: 29819.945 | X51: 30775.032 | Y51: 26742.442 | Z51: 28684.452 | AA51: 30416.344 | AB51: 31390.533 | AC51: 27277.29 | AD51: 29258.141 | AE51: 31024.671 | AF51: 32018.343 | AG51: 27822.836 | AH51: 29843.304 | AI51: 31645.164 | AJ51: 32658.71 | AK51: 28379.293 | AL51: 30440.17 | AM51: 32278.067 | AN51: 33311.884 | AO51: 28946.879 | AP51: 31048.974 | AQ51: 32923.629 | AR51: 33978.122 | AS51: 29525.816 | AT51: 31669.953 | AU51: 33582.101 | AV51: 34657.684 | AW51: 30116.333 | AX51: 32303.352 | AY51: 34253.743 | AZ51: 35350.838 | BA51: 30718.659 | BB51: 32949.419 | BC51: 34938.818 | BD51: 36057.855 | BE51: 31333.033 | BF51: 33608.408 | BG51: 35637.594 | BH51: 36779.012 | BI51: 31959.693 | BJ51: 34280.576 | BK51: 36350.346 | BL51: 37514.592 | BM51: 32598.887 | BN51: 34966.187 | BO51: 37077.353 | BP51: 38264.884 | BQ51: 33250.865
B53: Maginal costs
E54: Bracket 1 sales (0 – 25,000) | G54: USD | H54: {=_xlfn.BYROW(_xlfn.ANCHORARRAY( J54), _xleta.SUM )} -> 1.7293417e+08 | J54: {=_xlfn.LET( _xlpm.volume,_xlfn.ANCHORARRAY( J47), _xlpm.bracket_id, CaseData!$G$66:$G$69, _xlpm.price, _xlfn.XLOOKUP( _xlpm.bracket_id, CaseData!$G$66:$G$69, CaseData!$J$66:$J$69, 0 ), _xlpm.indexation_table, CaseData!$H$12:$J$13, _xlpm.indexation_rows, CaseData!$D$12:$D$13, _xlpm.indexation_columns, CaseData!$H$10:$J$10, _xlpm.current_scenario, INDEX( expense_scenarios, expense_selector ), _xlpm.current_item, $B$28, _xlpm.index, INDEX( _xlpm.indexation_table, MATCH( _xlpm.current_item, _xlpm.indexation_rows, 0 ), MATCH( _xlpm.current_scenario, _xlpm.indexation_columns, 0 ) ), _xlpm.compound_frequency, CaseData!$E$13, _xlpm.quarterly_operating_flag,_xlfn.ANCHORARRAY( Time!$J$18), _xlpm.yearly_operating_flag,_xlfn.ANCHORARRAY( Time!$J$19), _xlpm.active_operating_flag, IF( _xlpm.compound_frequency = "Annual", _xlpm.yearly_operating_flag, _xlpm.quarterly_operating_flag ), _xlpm.periodic_rate, IF( _xlpm.compound_frequency = "Annual", 1 + _xlpm.index, (1 + _xlpm.index ) ^ (1 / 4 ) ), _xlpm.indexation_count, _xlfn.SCAN( 0, _xlpm.active_operating_flag, _xlfn.LAMBDA(_xlpm.s,_xlpm.c, _xlpm.s + _xlpm.c ) ), _xlpm.volume * _xlpm.price * _xlpm.periodic_rate ^ _xlpm.indexation_count)} -> 2500000 | K54: 2500000 | L54: 2500000 | M54: 2500000 | N54: 2550000 | O54: 2550000 | P54: 2550000 | Q54: 2550000 | R54: 2601000 | S54: 2601000 | T54: 2601000 | U54: 2601000 | V54: 2653020 | W54: 2653020 | X54: 2653020 | Y54: 2653020 | Z54: 2706080.4 | AA54: 2706080.4 | AB54: 2706080.4 | AC54: 2706080.4 | AD54: 2760202 | AE54: 2760202 | AF54: 2760202 | AG54: 2760202 | AH54: 2815406 | AI54: 2815406 | AJ54: 2815406 | AK54: 2815406 | AL54: 2871714.2 | AM54: 2871714.2 | AN54: 2871714.2 | AO54: 2871714.2 | AP54: 2929148.5 | AQ54: 2929148.5 | AR54: 2929148.5 | AS54: 2929148.5 | AT54: 2987731.4 | AU54: 2987731.4 | AV54: 2987731.4 | AW54: 2987731.4 | AX54: 3047486 | AY54: 3047486 | AZ54: 3047486 | BA54: 3047486 | BB54: 3108435.8 | BC54: 3108435.8 | BD54: 3108435.8 | BE54: 3108435.8 | BF54: 3170604.5 | BG54: 3170604.5 | BH54: 3170604.5 | BI54: 3170604.5 | BJ54: 3234016.6 | BK54: 3234016.6 | BL54: 3234016.6 | BM54: 3234016.6 | BN54: 3298696.9 | BO54: 3298696.9 | BP54: 3298696.9 | BQ54: 3298696.9
E55: Bracket 2 sales (25,001 – 30,000) | G55: USD | H55: 27108367 | J55: 135000 | K55: 279000 | L55: 360000 | M55: 18000 | N55: 186354 | O55: 336171.6 | P55: 420444 | Q55: 64627.2 | R55: 240700.7 | S55: 396570.93 | T55: 468180 | U55: 114056.14 | V55: 298179.37 | W55: 460346.76 | X55: 477543.6 | Y55: 166418.37 | Z55: 358935.26 | AA55: 487094.47 | AB55: 487094.47 | AC55: 221851.12 | AD55: 423119.88 | AE55: 496836.36 | AF55: 496836.36 | AG55: 280497.54 | AH55: 490891.24 | AI55: 506773.09 | AJ55: 506773.09 | AK55: 342506.95 | AL55: 516908.55 | AM55: 516908.55 | AN55: 516908.55 | AO55: 408035.08 | AP55: 527246.72 | AQ55: 527246.72 | AR55: 527246.72 | AS55: 477244.37 | AT55: 537791.66 | AU55: 537791.66 | AV55: 537791.66 | AW55: 537791.66 | AX55: 548547.49 | AY55: 548547.49 | AZ55: 548547.49 | BA55: 548547.49 | BB55: 559518.44 | BC55: 559518.44 | BD55: 559518.44 | BE55: 559518.44 | BF55: 570708.81 | BG55: 570708.81 | BH55: 570708.81 | BI55: 570708.81 | BJ55: 582122.98 | BK55: 582122.98 | BL55: 582122.98 | BM55: 582122.98 | BN55: 593765.44 | BO55: 593765.44 | BP55: 593765.44 | BQ55: 593765.44
E56: Bracket 3 sales (30,001 – 34,000) | G56: USD | H56: 10499647 | J56: 0 | K56: 0 | L56: 0 | M56: 0 | N56: 0 | O56: 0 | P56: 0 | Q56: 0 | R56: 0 | S56: 0 | T56: 15175.274 | U56: 0 | V56: 0 | W56: 0 | X56: 69909.963 | Y56: 0 | Z56: 0 | AA56: 38306.424 | AB56: 127938.37 | AC56: 0 | AD56: 0 | AE56: 96162.124 | AF56: 189415.2 | AG56: 0 | AH56: 0 | AI56: 157481.36 | AJ56: 254501.85 | AK56: 0 | AL56: 42977.461 | AM56: 222426.57 | AN56: 323366.7 | AO56: 0 | AP56: 104468.38 | AQ56: 291167.24 | AR56: 396185.34 | AS56: 0 | AT56: 169638.62 | AU56: 363880.11 | AV56: 406331.47 | AW56: 11817.412 | AX56: 238660.74 | AY56: 414458.1 | AZ56: 414458.1 | BA56: 74463.551 | BB56: 311714.72 | BC56: 422747.26 | BD56: 422747.26 | BE56: 140883.97 | BF56: 388988.33 | BG56: 431202.21 | BH56: 431202.21 | BI56: 211256.01 | BJ56: 439826.25 | BK56: 439826.25 | BL56: 439826.25 | BM56: 285764.69 | BN56: 448622.78 | BO56: 448622.78 | BP56: 448622.78 | BQ56: 364603
E57: Bracket 4 sales (> 34,000) | G57: USD | H57: 2540519.8 | J57: 0 | K57: 0 | L57: 0 | M57: 0 | N57: 0 | O57: 0 | P57: 0 | Q57: 0 | R57: 0 | S57: 0 | T57: 0 | U57: 0 | V57: 0 | W57: 0 | X57: 0 | Y57: 0 | Z57: 0 | AA57: 0 | AB57: 0 | AC57: 0 | AD57: 0 | AE57: 0 | AF57: 0 | AG57: 0 | AH57: 0 | AI57: 0 | AJ57: 0 | AK57: 0 | AL57: 0 | AM57: 0 | AN57: 0 | AO57: 0 | AP57: 0 | AQ57: 0 | AR57: 0 | AS57: 0 | AT57: 0 | AU57: 0 | AV57: 64451.495 | AW57: 0 | AX57: 0 | AY57: 25363.547 | AZ57: 135026.46 | BA57: 0 | BB57: 0 | BC57: 95718.786 | BD57: 209812.09 | BE57: 0 | BF57: 0 | BG57: 170302.99 | BH57: 289005.66 | BI57: 0 | BJ57: 29762.277 | BK57: 249314.73 | BL57: 372812.99 | BM57: 0 | BN57: 104538.81 | BO57: 332961.18 | BP57: 461448.77 | BQ57: 0
E58: Manufactoring costs per quarter | G58: USD | H58: {=_xlfn.BYROW(_xlfn.ANCHORARRAY( J58), _xleta.SUM )} -> 2.130827e+08 | J58: {=_xlfn.BYCOL(_xlfn.ANCHORARRAY( J54), _xleta.SUM )} -> 2635000 | K58: 2779000 | L58: 2860000 | M58: 2518000 | N58: 2736354 | O58: 2886171.6 | P58: 2970444 | Q58: 2614627.2 | R58: 2841700.7 | S58: 2997570.9 | T58: 3084355.3 | U58: 2715056.1 | V58: 2951199.4 | W58: 3113366.8 | X58: 3200473.6 | Y58: 2819438.4 | Z58: 3065015.7 | AA58: 3231481.3 | AB58: 3321113.2 | AC58: 2927931.5 | AD58: 3183321.9 | AE58: 3353200.5 | AF58: 3446453.6 | AG58: 3040699.5 | AH58: 3306297.3 | AI58: 3479660.5 | AJ58: 3576681 | AK58: 3157913 | AL58: 3431600.2 | AM58: 3611049.3 | AN58: 3711989.4 | AO58: 3279749.3 | AP58: 3560863.6 | AQ58: 3747562.4 | AR58: 3852580.5 | AS58: 3406392.8 | AT58: 3695161.7 | AU58: 3889403.2 | AV58: 3996306 | AW58: 3537340.5 | AX58: 3834694.3 | AY58: 4035855.2 | AZ58: 4145518.1 | BA58: 3670497.1 | BB58: 3979668.9 | BC58: 4186420.3 | BD58: 4300513.6 | BE58: 3808838.2 | BF58: 4130301.6 | BG58: 4342818.5 | BH58: 4461521.2 | BI58: 3952569.3 | BJ58: 4285728.1 | BK58: 4505280.5 | BL58: 4628778.8 | BM58: 4101904.3 | BN58: 4445623.9 | BO58: 4674046.3 | BP58: 4802533.9 | BQ58: 4257065.4
A61: RENT AND STORAGE COSTS
B63: Rent and storage costs
E64: Fixed costs | G64: USD | H64: {=_xlfn.BYROW(_xlfn.ANCHORARRAY( J64), _xleta.SUM )} -> 41504201 | J64: {=_xlfn.LET( _xlpm.indexation_table, CaseData!$H$12:$J$13, _xlpm.indexation_rows, CaseData!$D$12:$D$13, _xlpm.indexation_columns, CaseData!$H$10:$J$10, _xlpm.current_scenario, INDEX( expense_scenarios, expense_selector ), _xlpm.current_item, $B$28, _xlpm.index, INDEX( _xlpm.indexation_table, MATCH( _xlpm.current_item, _xlpm.indexation_rows, 0 ), MATCH( _xlpm.current_scenario, _xlpm.indexation_columns, 0 ) ), _xlpm.compound_frequency, CaseData!$E$13, _xlpm.quarterly_operating_flag,_xlfn.ANCHORARRAY( Time!$J$18), _xlpm.yearly_operating_flag,_xlfn.ANCHORARRAY( Time!$J$19), _xlpm.active_operating_flag, IF( _xlpm.compound_frequency = "Annual", _xlpm.yearly_operating_flag, _xlpm.quarterly_operating_flag ), _xlpm.periodic_rate, IF( _xlpm.compound_frequency = "Annual", 1 + _xlpm.index, (1 + _xlpm.index ) ^ (1 / 4 ) ), _xlpm.indexation_count, _xlfn.SCAN( 0, _xlpm.active_operating_flag, _xlfn.LAMBDA(_xlpm.s,_xlpm.c, _xlpm.s + _xlpm.c ) ), _xlpm.initial_fixed_costs, _xlfn.SEQUENCE(1, periods, CaseData!$H$74, 0 ) * _xlpm.periodic_rate ^ _xlpm.indexation_count, _xlpm.initial_variable_costs, CaseData!$H$75 * _xlpm.periodic_rate ^ _xlpm.indexation_count, _xlpm.threshold, CaseData!$H$76, _xlpm.slabs_per_quarter,_xlfn.ANCHORARRAY( Calculations!J14), _xlpm.variable_costs_per_quarter, IF( _xlpm.slabs_per_quarter <= _xlpm.threshold, 0, _xlpm.initial_variable_costs * ( _xlpm.slabs_per_quarter - _xlpm.threshold ) ), _xlfn.VSTACK( _xlpm.initial_fixed_costs, _xlpm.variable_costs_per_quarter ) )} -> 600000 | K64: 600000 | L64: 600000 | M64: 600000 | N64: 612000 | O64: 612000 | P64: 612000 | Q64: 612000 | R64: 624240 | S64: 624240 | T64: 624240 | U64: 624240 | V64: 636724.8 | W64: 636724.8 | X64: 636724.8 | Y64: 636724.8 | Z64: 649459.3 | AA64: 649459.3 | AB64: 649459.3 | AC64: 649459.3 | AD64: 662448.48 | AE64: 662448.48 | AF64: 662448.48 | AG64: 662448.48 | AH64: 675697.45 | AI64: 675697.45 | AJ64: 675697.45 | AK64: 675697.45 | AL64: 689211.4 | AM64: 689211.4 | AN64: 689211.4 | AO64: 689211.4 | AP64: 702995.63 | AQ64: 702995.63 | AR64: 702995.63 | AS64: 702995.63 | AT64: 717055.54 | AU64: 717055.54 | AV64: 717055.54 | AW64: 717055.54 | AX64: 731396.65 | AY64: 731396.65 | AZ64: 731396.65 | BA64: 731396.65 | BB64: 746024.59 | BC64: 746024.59 | BD64: 746024.59 | BE64: 746024.59 | BF64: 760945.08 | BG64: 760945.08 | BH64: 760945.08 | BI64: 760945.08 | BJ64: 776163.98 | BK64: 776163.98 | BL64: 776163.98 | BM64: 776163.98 | BN64: 791687.26 | BO64: 791687.26 | BP64: 791687.26 | BQ64: 791687.26
E65: Variable costs above threshold | G65: USD | H65: 1946686.6 | J65: 0 | K65: 0 | L65: 0 | M65: 0 | N65: 0 | O65: 0 | P65: 0 | Q65: 0 | R65: 0 | S65: 0 | T65: 0 | U65: 0 | V65: 0 | W65: 0 | X65: 0 | Y65: 0 | Z65: 0 | AA65: 0 | AB65: 0 | AC65: 0 | AD65: 0 | AE65: 0 | AF65: 506.31194 | AG65: 0 | AH65: 0 | AI65: 0 | AJ65: 18545.366 | AK65: 0 | AL65: 0 | AM65: 7985.2969 | AN65: 37673.569 | AO65: 0 | AP65: 0 | AQ65: 27054.453 | AR65: 57942.131 | AS65: 0 | AT65: 0 | AU65: 47268.934 | AV65: 79404.475 | AW65: 0 | AX65: 9244.6138 | AY65: 68682.51 | AZ65: 102116.33 | BA65: 0 | BB65: 29512.085 | BC65: 91351.272 | BD65: 126135.81 | BE65: 0 | BF65: 50996.242 | BG65: 115333.73 | BH65: 151523.57 | BI65: 0 | BJ65: 73754.196 | BK65: 140690.92 | BL65: 178342.83 | BM65: 19368.108 | BN65: 97845.526 | BO65: 167486.49 | BP65: 206659.54 | BQ65: 41262.239
E66: Rent and storage costs | G66: USD | H66: {=_xlfn.BYROW(_xlfn.ANCHORARRAY( J66), _xleta.SUM )} -> 43450887 | J66: {=_xlfn.BYCOL(_xlfn.ANCHORARRAY( J64), _xleta.SUM )} -> 600000 | K66: 600000 | L66: 600000 | M66: 600000 | N66: 612000 | O66: 612000 | P66: 612000 | Q66: 612000 | R66: 624240 | S66: 624240 | T66: 624240 | U66: 624240 | V66: 636724.8 | W66: 636724.8 | X66: 636724.8 | Y66: 636724.8 | Z66: 649459.3 | AA66: 649459.3 | AB66: 649459.3 | AC66: 649459.3 | AD66: 662448.48 | AE66: 662448.48 | AF66: 662954.79 | AG66: 662448.48 | AH66: 675697.45 | AI66: 675697.45 | AJ66: 694242.82 | AK66: 675697.45 | AL66: 689211.4 | AM66: 697196.7 | AN66: 726884.97 | AO66: 689211.4 | AP66: 702995.63 | AQ66: 730050.08 | AR66: 760937.76 | AS66: 702995.63 | AT66: 717055.54 | AU66: 764324.48 | AV66: 796460.02 | AW66: 717055.54 | AX66: 740641.27 | AY66: 800079.16 | AZ66: 833512.98 | BA66: 731396.65 | BB66: 775536.67 | BC66: 837375.86 | BD66: 872160.4 | BE66: 746024.59 | BF66: 811941.32 | BG66: 876278.81 | BH66: 912468.65 | BI66: 760945.08 | BJ66: 849918.17 | BK66: 916854.9 | BL66: 954506.81 | BM66: 795532.09 | BN66: 889532.78 | BO66: 959173.75 | BP66: 998346.8 | BQ66: 832949.5
A69: STAFF AND OVERHEAD COSTS
B71: Staff and overhead costs
E72: Staff and overhead costs | G72: USD | H72: {=_xlfn.BYROW(_xlfn.ANCHORARRAY( J72), _xleta.SUM )} -> 31128150 | J72: {=_xlfn.LET( _xlpm.indexation_table, CaseData!$H$12:$J$13, _xlpm.indexation_rows, CaseData!$D$12:$D$13, _xlpm.indexation_columns, CaseData!$H$10:$J$10, _xlpm.current_scenario, INDEX( expense_scenarios, expense_selector ), _xlpm.current_item, $B$28, _xlpm.index, INDEX( _xlpm.indexation_table, MATCH( _xlpm.current_item, _xlpm.indexation_rows, 0 ), MATCH( _xlpm.current_scenario, _xlpm.indexation_columns, 0 ) ), _xlpm.compound_frequency, CaseData!$E$13, _xlpm.quarterly_operating_flag,_xlfn.ANCHORARRAY( Time!$J$18), _xlpm.yearly_operating_flag,_xlfn.ANCHORARRAY( Time!$J$19), _xlpm.active_operating_flag, IF( _xlpm.compound_frequency = "Annual", _xlpm.yearly_operating_flag, _xlpm.quarterly_operating_flag ), _xlpm.periodic_rate, IF( _xlpm.compound_frequency = "Annual", 1 + _xlpm.index, (1 + _xlpm.index ) ^ (1 / 4 ) ), _xlpm.indexation_count, _xlfn.SCAN( 0, _xlpm.active_operating_flag, _xlfn.LAMBDA(_xlpm.s,_xlpm.c, _xlpm.s + _xlpm.c ) ), _xlfn.SEQUENCE( 1, periods, CaseData!$H$79, 0 ) * _xlpm.periodic_rate ^ _xlpm.indexation_count )} -> 450000 | K72: 450000 | L72: 450000 | M72: 450000 | N72: 459000 | O72: 459000 | P72: 459000 | Q72: 459000 | R72: 468180 | S72: 468180 | T72: 468180 | U72: 468180 | V72: 477543.6 | W72: 477543.6 | X72: 477543.6 | Y72: 477543.6 | Z72: 487094.47 | AA72: 487094.47 | AB72: 487094.47 | AC72: 487094.47 | AD72: 496836.36 | AE72: 496836.36 | AF72: 496836.36 | AG72: 496836.36 | AH72: 506773.09 | AI72: 506773.09 | AJ72: 506773.09 | AK72: 506773.09 | AL72: 516908.55 | AM72: 516908.55 | AN72: 516908.55 | AO72: 516908.55 | AP72: 527246.72 | AQ72: 527246.72 | AR72: 527246.72 | AS72: 527246.72 | AT72: 537791.66 | AU72: 537791.66 | AV72: 537791.66 | AW72: 537791.66 | AX72: 548547.49 | AY72: 548547.49 | AZ72: 548547.49 | BA72: 548547.49 | BB72: 559518.44 | BC72: 559518.44 | BD72: 559518.44 | BE72: 559518.44 | BF72: 570708.81 | BG72: 570708.81 | BH72: 570708.81 | BI72: 570708.81 | BJ72: 582122.98 | BK72: 582122.98 | BL72: 582122.98 | BM72: 582122.98 | BN72: 593765.44 | BO72: 593765.44 | BP72: 593765.44 | BQ72: 593765.44
A75: ANNUAL SUMMARY
J77: {=_xlfn.ANCHORARRAY( Time!$J$11)} -> 2020 | K77: 2021 | L77: 2022 | M77: 2023 | N77: 2024 | O77: 2025 | P77: 2026 | Q77: 2027 | R77: 2028 | S77: 2029 | T77: 2030 | U77: 2031 | V77: 2032 | W77: 2033 | X77: 2034
E78: Revenue | G78: USD | H78: {=_xlfn.BYROW(_xlfn.ANCHORARRAY(J78), _xleta.SUM )} -> 6.3553839e+08 | J78: {=SUMIFS(_xlfn.ANCHORARRAY( Calculations!J20),_xlfn.ANCHORARRAY( Time!$J$10),_xlfn.ANCHORARRAY( J77) )} -> 30464000 | K78: 31850112 | L78: 33299292 | M78: 34814410 | N78: 36398466 | O78: 38054596 | P78: 39786080 | Q78: 41596346 | R78: 43488980 | S78: 45467729 | T78: 47536510 | U78: 49699422 | V78: 51960745 | W78: 54324959 | X78: 56796745
E80: Raw material expenses | G80: USD | H80: {=_xlfn.BYROW(_xlfn.ANCHORARRAY(J80), _xleta.SUM )} -> 2.1557732e+08 | J80: {=SUMIFS(_xlfn.ANCHORARRAY( Calculations!$J$41),_xlfn.ANCHORARRAY( Time!$J$10),_xlfn.ANCHORARRAY( $J$77) )} -> 11424000 | K80: 11885530 | L80: 12367669 | M80: 12871549 | N80: 13393524 | O80: 13929648 | P80: 14283277 | Q80: 14542141 | R80: 14821717 | S80: 15123071 | T80: 15447278 | U80: 15791605 | V80: 16161270 | W80: 16557377 | X80: 16977662
E81: Manufactoring expenses | G81: USD | H81: {=_xlfn.BYROW(_xlfn.ANCHORARRAY(J81), _xleta.SUM )} -> 2.130827e+08 | J81: {=SUMIFS(_xlfn.ANCHORARRAY( Calculations!$J$58),_xlfn.ANCHORARRAY( Time!$J$10),_xlfn.ANCHORARRAY( $J$77) )} -> 10792000 | K81: 11207597 | L81: 11638683 | M81: 12084478 | N81: 12545542 | O81: 13023675 | P81: 13520552 | Q81: 14034388 | R81: 14567399 | S81: 15118211 | T81: 15686565 | U81: 16275441 | V81: 16887211 | W81: 17521692 | X81: 18179270
E82: Rent and storage costs | G82: USD | H82: {=_xlfn.BYROW(_xlfn.ANCHORARRAY(J82), _xleta.SUM )} -> 43450887 | J82: {=SUMIFS(_xlfn.ANCHORARRAY( Calculations!$J$66),_xlfn.ANCHORARRAY( Time!$J$10),_xlfn.ANCHORARRAY( $J$77) )} -> 2400000 | K82: 2448000 | L82: 2496960 | M82: 2546899.2 | N82: 2597837.2 | O82: 2650300.2 | P82: 2721335.2 | Q82: 2802504.5 | R82: 2896979.1 | S82: 2994895.6 | T82: 3105630.1 | U82: 3231097.5 | V82: 3361633.9 | W82: 3516812 | X82: 3680002.8
E83: Staff and overhead costs | G83: USD | H83: {=_xlfn.BYROW(_xlfn.ANCHORARRAY(J83), _xleta.SUM )} -> 31128150 | J83: {=SUMIFS(_xlfn.ANCHORARRAY( Calculations!$J$72),_xlfn.ANCHORARRAY( Time!$J$10),_xlfn.ANCHORARRAY( $J$77) )} -> 1800000 | K83: 1836000 | L83: 1872720 | M83: 1910174.4 | N83: 1948377.9 | O83: 1987345.4 | P83: 2027092.4 | Q83: 2067634.2 | R83: 2108986.9 | S83: 2151166.6 | T83: 2194190 | U83: 2238073.8 | V83: 2282835.2 | W83: 2328491.9 | X83: 2375061.8
E84: Operating Costs | G84: USD | H84: {=_xlfn.BYROW(_xlfn.ANCHORARRAY(J84), _xleta.SUM )} -> 5.0323906e+08 | J84: {=_xlfn.LET( _xlpm.costs, _xlfn.VSTACK(_xlfn.ANCHORARRAY( J80),_xlfn.ANCHORARRAY( J81),_xlfn.ANCHORARRAY( J82),_xlfn.ANCHORARRAY( J83) ), _xlfn.BYCOL( _xlpm.costs, _xleta.SUM ) )} -> 26416000 | K84: 27377126 | L84: 28376032 | M84: 29413101 | N84: 30485281 | O84: 31590969 | P84: 32552256 | Q84: 33446668 | R84: 34395082 | S84: 35387345 | T84: 36433663 | U84: 37536217 | V84: 38692949 | W84: 39924373 | X84: 41211996
E86: Operating Profit | G86: USD | H86: {=_xlfn.BYROW(_xlfn.ANCHORARRAY(J86), _xleta.SUM )} -> 1.3229933e+08 | J86: {=_xlfn.ANCHORARRAY( J78) -_xlfn.ANCHORARRAY( J84)} -> 4048000 | K86: 4472985.6 | L86: 4923260.5 | M86: 5401308.9 | N86: 5913184.9 | O86: 6463626.2 | P86: 7233823.5 | Q86: 8149678.6 | R86: 9093898.1 | S86: 10080384 | T86: 11102847 | U86: 12163204 | V86: 13267796 | W86: 14400586 | X86: 15584749
K91: Sales Price / Expense Indexations
K92: {=INDEX( expense_scenarios, Calculations!$K$93:$M$93)} -> 1. Low | L92: 2. Medium | M92: 3. High
H93: Operating profit | J93: =Calculations!H86 -> 1.3229933e+08 | K93: 1 | L93: 2 | M93: 3
H94: =_xlfn.SINGLE(INDEX( fx_rates, Calculations!$J$94 )) -> FX Case 1 | J94: 1 | K94: 1.3229933e+08 | L94: 1.4387667e+08 | M94: 1.5497806e+08
H95: =_xlfn.SINGLE(INDEX( fx_rates, $J$95 )) -> FX Case 2 | J95: 2 | K95: 1.5710668e+08 | L95: 1.6868402e+08 | M95: 1.7978541e+08
H96: =_xlfn.SINGLE(INDEX( fx_rates, Calculations!$J$96 )) -> FX Case 3 | J96: 3 | K96: 1.6734427e+08 | L96: 1.7892161e+08 | M96: 1.90023e+08

Sheet Time
A1: {=company} -> Megabrick Inc.
A2: {=topic} -> CFM Topic: Costs | J2: {=EDATE( start_date, _xlfn.SEQUENCE( 1, periods, 0, 3 ) )} -> 43831 | K2: 43922 | L2: 44013 | M2: 44105 | N2: 44197 | O2: 44287 | P2: 44378 | Q2: 44470 | R2: 44562 | S2: 44652 | T2: 44743 | U2: 44835 | V2: 44927 | W2: 45017 | X2: 45108 | Y2: 45200 | Z2: 45292 | AA2: 45383 | AB2: 45474 | AC2: 45566 | AD2: 45658 | AE2: 45748 | AF2: 45839 | AG2: 45931 | AH2: 46023 | AI2: 46113 | AJ2: 46204 | AK2: 46296 | AL2: 46388 | AM2: 46478 | AN2: 46569 | AO2: 46661 | AP2: 46753 | AQ2: 46844 | AR2: 46935 | AS2: 47027 | AT2: 47119 | AU2: 47209 | AV2: 47300 | AW2: 47392 | AX2: 47484 | AY2: 47574 | AZ2: 47665 | BA2: 47757 | BB2: 47849 | BC2: 47939 | BD2: 48030 | BE2: 48122 | BF2: 48214 | BG2: 48305 | BH2: 48396 | BI2: 48488 | BJ2: 48580 | BK2: 48670 | BL2: 48761 | BM2: 48853 | BN2: 48945 | BO2: 49035 | BP2: 49126 | BQ2: 49218
A3: TMP SCHEDULE | J3: {=EOMONTH( start_date, _xlfn.SEQUENCE( 1, periods, 2, 3 ) )} -> 43921 | K3: 44012 | L3: 44104 | M3: 44196 | N3: 44286 | O3: 44377 | P3: 44469 | Q3: 44561 | R3: 44651 | S3: 44742 | T3: 44834 | U3: 44926 | V3: 45016 | W3: 45107 | X3: 45199 | Y3: 45291 | Z3: 45382 | AA3: 45473 | AB3: 45565 | AC3: 45657 | AD3: 45747 | AE3: 45838 | AF3: 45930 | AG3: 46022 | AH3: 46112 | AI3: 46203 | AJ3: 46295 | AK3: 46387 | AL3: 46477 | AM3: 46568 | AN3: 46660 | AO3: 46752 | AP3: 46843 | AQ3: 46934 | AR3: 47026 | AS3: 47118 | AT3: 47208 | AU3: 47299 | AV3: 47391 | AW3: 47483 | AX3: 47573 | AY3: 47664 | AZ3: 47756 | BA3: 47848 | BB3: 47938 | BC3: 48029 | BD3: 48121 | BE3: 48213 | BF3: 48304 | BG3: 48395 | BH3: 48487 | BI3: 48579 | BJ3: 48669 | BK3: 48760 | BL3: 48852 | BM3: 48944 | BN3: 49034 | BO3: 49125 | BP3: 49217 | BQ3: 49309
A5: Model timeline
E7: Model period beginning | G7: date | J7: {=EDATE( start_date, _xlfn.SEQUENCE( 1, periods, 0, 3 ) )} -> 43831 | K7: 43922 | L7: 44013 | M7: 44105 | N7: 44197 | O7: 44287 | P7: 44378 | Q7: 44470 | R7: 44562 | S7: 44652 | T7: 44743 | U7: 44835 | V7: 44927 | W7: 45017 | X7: 45108 | Y7: 45200 | Z7: 45292 | AA7: 45383 | AB7: 45474 | AC7: 45566 | AD7: 45658 | AE7: 45748 | AF7: 45839 | AG7: 45931 | AH7: 46023 | AI7: 46113 | AJ7: 46204 | AK7: 46296 | AL7: 46388 | AM7: 46478 | AN7: 46569 | AO7: 46661 | AP7: 46753 | AQ7: 46844 | AR7: 46935 | AS7: 47027 | AT7: 47119 | AU7: 47209 | AV7: 47300 | AW7: 47392 | AX7: 47484 | AY7: 47574 | AZ7: 47665 | BA7: 47757 | BB7: 47849 | BC7: 47939 | BD7: 48030 | BE7: 48122 | BF7: 48214 | BG7: 48305 | BH7: 48396 | BI7: 48488 | BJ7: 48580 | BK7: 48670 | BL7: 48761 | BM7: 48853 | BN7: 48945 | BO7: 49035 | BP7: 49126 | BQ7: 49218
E8: Model period ending | G8: date | J8: {=EOMONTH( start_date, _xlfn.SEQUENCE( 1, periods, 2, 3 ))} -> 43921 | K8: 44012 | L8: 44104 | M8: 44196 | N8: 44286 | O8: 44377 | P8: 44469 | Q8: 44561 | R8: 44651 | S8: 44742 | T8: 44834 | U8: 44926 | V8: 45016 | W8: 45107 | X8: 45199 | Y8: 45291 | Z8: 45382 | AA8: 45473 | AB8: 45565 | AC8: 45657 | AD8: 45747 | AE8: 45838 | AF8: 45930 | AG8: 46022 | AH8: 46112 | AI8: 46203 | AJ8: 46295 | AK8: 46387 | AL8: 46477 | AM8: 46568 | AN8: 46660 | AO8: 46752 | AP8: 46843 | AQ8: 46934 | AR8: 47026 | AS8: 47118 | AT8: 47208 | AU8: 47299 | AV8: 47391 | AW8: 47483 | AX8: 47573 | AY8: 47664 | AZ8: 47756 | BA8: 47848 | BB8: 47938 | BC8: 48029 | BD8: 48121 | BE8: 48213 | BF8: 48304 | BG8: 48395 | BH8: 48487 | BI8: 48579 | BJ8: 48669 | BK8: 48760 | BL8: 48852 | BM8: 48944 | BN8: 49034 | BO8: 49125 | BP8: 49217 | BQ8: 49309
E10: Model annual timeline | G10: year | J10: {=YEAR(_xlfn.ANCHORARRAY( J8) )} -> 2020 | K10: 2020 | L10: 2020 | M10: 2020 | N10: 2021 | O10: 2021 | P10: 2021 | Q10: 2021 | R10: 2022 | S10: 2022 | T10: 2022 | U10: 2022 | V10: 2023 | W10: 2023 | X10: 2023 | Y10: 2023 | Z10: 2024 | AA10: 2024 | AB10: 2024 | AC10: 2024 | AD10: 2025 | AE10: 2025 | AF10: 2025 | AG10: 2025 | AH10: 2026 | AI10: 2026 | AJ10: 2026 | AK10: 2026 | AL10: 2027 | AM10: 2027 | AN10: 2027 | AO10: 2027 | AP10: 2028 | AQ10: 2028 | AR10: 2028 | AS10: 2028 | AT10: 2029 | AU10: 2029 | AV10: 2029 | AW10: 2029 | AX10: 2030 | AY10: 2030 | AZ10: 2030 | BA10: 2030 | BB10: 2031 | BC10: 2031 | BD10: 2031 | BE10: 2031 | BF10: 2032 | BG10: 2032 | BH10: 2032 | BI10: 2032 | BJ10: 2033 | BK10: 2033 | BL10: 2033 | BM10: 2033 | BN10: 2034 | BO10: 2034 | BP10: 2034 | BQ10: 2034
E11: Model calendar timeline | G11: year | J11: {=_xlfn.UNIQUE(_xlfn.ANCHORARRAY( J10), TRUE )} -> 2020 | K11: 2021 | L11: 2022 | M11: 2023 | N11: 2024 | O11: 2025 | P11: 2026 | Q11: 2027 | R11: 2028 | S11: 2029 | T11: 2030 | U11: 2031 | V11: 2032 | W11: 2033 | X11: 2034
E12: Model year counter | G12: counter
E13: Number period counter | G13: counter | J13: =COUNTA(_xlfn.ANCHORARRAY( J11) ) -> 15
E14: Model operating flag | G14: flag | J14: {=_xlfn.SEQUENCE( 1, periods, 1, 0 )} -> 1 | K14: 1 | L14: 1 | M14: 1 | N14: 1 | O14: 1 | P14: 1 | Q14: 1 | R14: 1 | S14: 1 | T14: 1 | U14: 1 | V14: 1 | W14: 1 | X14: 1 | Y14: 1 | Z14: 1 | AA14: 1 | AB14: 1 | AC14: 1 | AD14: 1 | AE14: 1 | AF14: 1 | AG14: 1 | AH14: 1 | AI14: 1 | AJ14: 1 | AK14: 1 | AL14: 1 | AM14: 1 | AN14: 1 | AO14: 1 | AP14: 1 | AQ14: 1 | AR14: 1 | AS14: 1 | AT14: 1 | AU14: 1 | AV14: 1 | AW14: 1 | AX14: 1 | AY14: 1 | AZ14: 1 | BA14: 1 | BB14: 1 | BC14: 1 | BD14: 1 | BE14: 1 | BF14: 1 | BG14: 1 | BH14: 1 | BI14: 1 | BJ14: 1 | BK14: 1 | BL14: 1 | BM14: 1 | BN14: 1 | BO14: 1 | BP14: 1 | BQ14: 1
E15: Model period counter | G15: counter | J15: {=_xlfn.SEQUENCE( 1, periods, 1, 1 )} -> 1 | K15: 2 | L15: 3 | M15: 4 | N15: 5 | O15: 6 | P15: 7 | Q15: 8 | R15: 9 | S15: 10 | T15: 11 | U15: 12 | V15: 13 | W15: 14 | X15: 15 | Y15: 16 | Z15: 17 | AA15: 18 | AB15: 19 | AC15: 20 | AD15: 21 | AE15: 22 | AF15: 23 | AG15: 24 | AH15: 25 | AI15: 26 | AJ15: 27 | AK15: 28 | AL15: 29 | AM15: 30 | AN15: 31 | AO15: 32 | AP15: 33 | AQ15: 34 | AR15: 35 | AS15: 36 | AT15: 37 | AU15: 38 | AV15: 39 | AW15: 40 | AX15: 41 | AY15: 42 | AZ15: 43 | BA15: 44 | BB15: 45 | BC15: 46 | BD15: 47 | BE15: 48 | BF15: 49 | BG15: 50 | BH15: 51 | BI15: 52 | BJ15: 53 | BK15: 54 | BL15: 55 | BM15: 56 | BN15: 57 | BO15: 58 | BP15: 59 | BQ15: 60
E16: Model period label | G16: label | J16: {=IF( MOD(_xlfn.ANCHORARRAY( J15), 4 ) > 0, "Q"&MOD(_xlfn.ANCHORARRAY( J15), 4 ), "Q4" )} -> Q1 | K16: Q2 | L16: Q3 | M16: Q4 | N16: Q1 | O16: Q2 | P16: Q3 | Q16: Q4 | R16: Q1 | S16: Q2 | T16: Q3 | U16: Q4 | V16: Q1 | W16: Q2 | X16: Q3 | Y16: Q4 | Z16: Q1 | AA16: Q2 | AB16: Q3 | AC16: Q4 | AD16: Q1 | AE16: Q2 | AF16: Q3 | AG16: Q4 | AH16: Q1 | AI16: Q2 | AJ16: Q3 | AK16: Q4 | AL16: Q1 | AM16: Q2 | AN16: Q3 | AO16: Q4 | AP16: Q1 | AQ16: Q2 | AR16: Q3 | AS16: Q4 | AT16: Q1 | AU16: Q2 | AV16: Q3 | AW16: Q4 | AX16: Q1 | AY16: Q2 | AZ16: Q3 | BA16: Q4 | BB16: Q1 | BC16: Q2 | BD16: Q3 | BE16: Q4 | BF16: Q1 | BG16: Q2 | BH16: Q3 | BI16: Q4 | BJ16: Q1 | BK16: Q2 | BL16: Q3 | BM16: Q4 | BN16: Q1 | BO16: Q2 | BP16: Q3 | BQ16: Q4
E18: Quarterly operating flag | G18: flag | J18: {=IF(_xlfn.ANCHORARRAY( J15) <= 4, 0, _xlfn.SEQUENCE( 1, periods, 1,0 ) )} -> 0 | K18: 0 | L18: 0 | M18: 0 | N18: 1 | O18: 1 | P18: 1 | Q18: 1 | R18: 1 | S18: 1 | T18: 1 | U18: 1 | V18: 1 | W18: 1 | X18: 1 | Y18: 1 | Z18: 1 | AA18: 1 | AB18: 1 | AC18: 1 | AD18: 1 | AE18: 1 | AF18: 1 | AG18: 1 | AH18: 1 | AI18: 1 | AJ18: 1 | AK18: 1 | AL18: 1 | AM18: 1 | AN18: 1 | AO18: 1 | AP18: 1 | AQ18: 1 | AR18: 1 | AS18: 1 | AT18: 1 | AU18: 1 | AV18: 1 | AW18: 1 | AX18: 1 | AY18: 1 | AZ18: 1 | BA18: 1 | BB18: 1 | BC18: 1 | BD18: 1 | BE18: 1 | BF18: 1 | BG18: 1 | BH18: 1 | BI18: 1 | BJ18: 1 | BK18: 1 | BL18: 1 | BM18: 1 | BN18: 1 | BO18: 1 | BP18: 1 | BQ18: 1
E19: Yearly operating flag | G19: flag | J19: {=IF(_xlfn.ANCHORARRAY( J15) <= 4, 0, IF(_xlfn.ANCHORARRAY( J16) = "Q1", 1, 0 ) )} -> 0 | K19: 0 | L19: 0 | M19: 0 | N19: 1 | O19: 0 | P19: 0 | Q19: 0 | R19: 1 | S19: 0 | T19: 0 | U19: 0 | V19: 1 | W19: 0 | X19: 0 | Y19: 0 | Z19: 1 | AA19: 0 | AB19: 0 | AC19: 0 | AD19: 1 | AE19: 0 | AF19: 0 | AG19: 0 | AH19: 1 | AI19: 0 | AJ19: 0 | AK19: 0 | AL19: 1 | AM19: 0 | AN19: 0 | AO19: 0 | AP19: 1 | AQ19: 0 | AR19: 0 | AS19: 0 | AT19: 1 | AU19: 0 | AV19: 0 | AW19: 0 | AX19: 1 | AY19: 0 | AZ19: 0 | BA19: 0 | BB19: 1 | BC19: 0 | BD19: 0 | BE19: 0 | BF19: 1 | BG19: 0 | BH19: 0 | BI19: 0 | BJ19: 1 | BK19: 0 | BL19: 0 | BM19: 0 | BN19: 1 | BO19: 0 | BP19: 0 | BQ19: 0

Sheet CaseData
A1: Assumptions
B3: Indexation
D4: Each item is indexed either quarterly (start of each quarter) or annually (each 1 January).
D5: No indexation is applied on 1 January 2020. Use the initial prices for this quarter.
D6: Annual rates are provided. Quarterly indexation should be applied as (1+r)(1/4)-1 where r is the annual rate.
D7: Rates for 3 different cases are provided.
H9: Indexation Cases | L9: DROP DOWN - DO NOT DELETE
D10: Indexed Item | E10: Compound Frequency | H10: 1. Low | I10: 2. Medium | J10: 3. High | L10: =H10 -> 1. Low
D11: [text] | E11: [pick from list] | H11: [% p.a.] | I11: [% p.a.] | J11: [% p.a.] | L11: =I10 -> 2. Medium
D12: Sales Price | E12: Annual | H12: 0.025 | I12: 0.03 | J12: 0.032 | L12: =J10 -> 3. High
D13: Expense Indexations | E13: Annual | H13: 0.02 | I13: 0.025 | J13: 0.03
D15: Expenses that are indexed:
D16: Raw Materials - Supplier 1 (US)
D17: Raw Materials - Supplier 2 (Mexico) | E17: Note it is the Peso price that is indexed
D18: Manufacturing Costs | E18: Note that each bracket price is indexed at this rate
D19: Rent and Storage | E19: Note this applies to both the fixed and variable component.
D20: Staff and Other Overheads
D22: For example - in Q2 2020, if the indexation is quarterly and the low case of 2% is run for expenses, the manufacturing cost for the first bracket would be:
D23: $100 * (1+2%)^(1/4)-1 = $100.742
B25: Exchange Rates
D26: Exchange rate forecasts are given for each calendar year. 3 different cases are provided.
D27: The rate is in units of Mexican Pesos per United States Dollar.
D29: Case Name | H29: =YEAR(H35) -> 2020 | I29: =H29+1 -> 2021 | J29: =I29+1 -> 2022 | K29: =J29+1 -> 2023 | L29: =K29+1 -> 2024 | M29: =L29+1 -> 2025 | N29: =M29+1 -> 2026 | O29: =N29+1 -> 2027 | P29: =O29+1 -> 2028 | ... V29: =U29+1 -> 2034
D30: FX Case 1 | F30: [MXN per $] | H30: 19.5 | I30: =ROUND(H30*1.03,2) -> 20.09 | J30: =ROUND(I30*1.03,2) -> 20.69 | K30: =ROUND(J30*1.03,2) -> 21.31 | L30: =ROUND(K30*1.03,2) -> 21.95 | M30: =ROUND(L30*1.03,2) -> 22.61 | N30: =ROUND(M30*1.03,2) -> 23.29 | O30: =ROUND(N30*1.03,2) -> 23.99 | P30: =ROUND(O30*1.03,2) -> 24.71 | ... V30: =ROUND(U30*1.03,2) -> 29.5
D31: FX Case 2 | F31: [MXN per $] | H31: 20 | I31: =ROUND(H31*1.04,2) -> 20.8 | J31: =ROUND(I31*1.04,2) -> 21.63 | K31: =ROUND(J31*1.04,2) -> 22.5 | L31: =ROUND(K31*1.04,2) -> 23.4 | M31: =ROUND(L31*1.04,2) -> 24.34 | N31: =ROUND(M31*1.04,2) -> 25.31 | O31: =ROUND(N31*1.04,2) -> 26.32 | P31: =ROUND(O31*1.04,2) -> 27.37 | ... V31: =ROUND(U31*1.04,2) -> 34.62
D32: FX Case 3 | F32: [MXN per $] | H32: 20.5 | I32: =ROUND(H32*1.05,2) -> 21.53 | J32: =ROUND(I32*1.05,2) -> 22.61 | K32: =ROUND(J32*1.05,2) -> 23.74 | L32: =ROUND(K32*1.05,2) -> 24.93 | M32: =ROUND(L32*1.05,2) -> 26.18 | N32: =ROUND(M32*1.05,2) -> 27.49 | O32: =ROUND(N32*1.05,2) -> 28.86 | P32: =ROUND(O32*1.05,2) -> 30.3 | ... V32: =ROUND(U32*1.05,2) -> 40.6
B34: Model Timing
D35: Model start date (Forecast start date) | F35: [date] | H35: 43831 | I35: Must be a 1 January date
D36: Number of quarters to forecast | F36: [# qtrs] | H36: 60
D37: Final quarter end date (Forecast end date) | F37: [date] | H37: =EOMONTH(H35-1,H36*3) -> 49309
B39: Revenues
D40: Initial Sales price | F40: [$/slab] | H40: 280
H41: Q1 | I41: Q2 | J41: Q3 | K41: Q4
D42: Demand in 2020 (year 1) | F42: [slabs] | H42: 26500 | I42: 28100 | J42: 29000 | K42: 25200
D44: Demand growth Year on Year | F44: [% YoY] | H44: 0.02
D46: Example demand calculation for Q1 2021 and Q1 2022
D47: Q1 2021 | F47: [slabs] | H47: 26,500 * 1.02 = 27,030
D48: Q1 2022 | F48: [slabs] | H48: 27,030 * 1.02 = 27,571
B50: Expenses
C51: Raw Materials
D52: Tonnes of raw material needed per slab manufactured | F52: [tonnes/slab] | H52: 3
D54: Supplier 1 (US)
D55: Initial cost per quarter (dollars) | F55: [$ / tonne] | H55: 35
D56: Maximum amount they can supply each quarter | F56: [tonnes] | H56: 90000
D58: Supplier 2 (Mexico)
D59: Initial cost per quarter (pesos) | F59: [MXN / tonne] | H59: 800
D60: Maximum amount they can supply each quarter | F60: [tonnes] | H60: 70000
C62: Manufacturing Costs
D63: This table gives the marginal cost per quarter (in $ / slab) for each slab manufactured. | G63: Bracket | H63: From | I63: To | J63: Initial Cost
J64: Per Quarter
G65: [#] | H65: [# slabs / qtr] | I65: [# slabs / qtr] | J65: [$ / slab]
G66: 1 | H66: 0 | I66: 25000 | J66: 100
G67: 2 | H67: =I66+1 -> 25001 | I67: 30000 | J67: 90
G68: 3 | H68: =I67+1 -> 30001 | I68: 34000 | J68: 85
G69: 4 | H69: =I68+1 -> 34001 | I69: 999999 | J69: 82
D70: For example - in Q1 2020, the cost to manufacture 26,500 slabs is [25,000 * 100] + [1,500 * 90] = $2,635,000
C73: Rent and Storage
D74: Initial fixed cost | F74: [$/qtr] | H74: 600000
D75: Initial variable cost | F75: [$/slab/qtr] | H75: 25
D76: Variable cost applies to each slab sold per quarter above this amount: | F76: [# of slabs] | H76: 32000
C78: Staff and Other Overheads
D79: Initial fixed cost | F79: [$/qtr] | H79: 450000
C81: End Sheet
D84: Company name | E84: Megabrick Inc.
D85: CFM Topic | E85: Costs

Sheet CaseSolution
B2: Megabricks
B3: Operating Profit Model
B5: Period Start | I5: =CaseData!H35 -> 43831 | J5: =I6+1 -> 43922 | K5: =J6+1 -> 44013 | L5: =K6+1 -> 44105 | M5: =L6+1 -> 44197 | N5: =M6+1 -> 44287 | O5: =N6+1 -> 44378 | P5: =O6+1 -> 44470 | Q5: =P6+1 -> 44562 | ... BP5: =BO6+1 -> 49218
B6: Period End | F6: =MAX(I6:BP6) -> 49309 | G6: =CaseData!H37 -> 49309 | I6: =EOMONTH(I5,2) -> 43921 | J6: =EOMONTH(J5,2) -> 44012 | K6: =EOMONTH(K5,2) -> 44104 | L6: =EOMONTH(L5,2) -> 44196 | M6: =EOMONTH(M5,2) -> 44286 | N6: =EOMONTH(N5,2) -> 44377 | O6: =EOMONTH(O5,2) -> 44469 | P6: =EOMONTH(P5,2) -> 44561 | ... BP6: =EOMONTH(BP5,2) -> 49309
B7: Year | I7: =YEAR(I6) -> 2020 | J7: =YEAR(J6) -> 2020 | K7: =YEAR(K6) -> 2020 | L7: =YEAR(L6) -> 2020 | M7: =YEAR(M6) -> 2021 | N7: =YEAR(N6) -> 2021 | O7: =YEAR(O6) -> 2021 | P7: =YEAR(P6) -> 2021 | ... BP7: =YEAR(BP6) -> 2034
B8: Period Count | F8: =MAX(I8:BP8) -> 60 | G8: =CaseData!H36 -> 60 | I8: 1 | J8: =I8+1 -> 2 | K8: =J8+1 -> 3 | L8: =K8+1 -> 4 | M8: =L8+1 -> 5 | N8: =M8+1 -> 6 | O8: =N8+1 -> 7 | P8: =O8+1 -> 8 | Q8: =P8+1 -> 9 | ... BP8: =BO8+1 -> 60
B10: Scenarios
C12: =CaseData!D12 -> Sales Price | G12: 1
C14: =CaseData!D13 -> Expense Indexations | G14: =G12 -> 1
B16: Revenue
C18: Price | G18: =CaseData!H40 -> 280 | H18: =CaseData!F40 -> [$/slab] | I18: =G18 -> 280 | J18: =I18*(1+J19) -> 280 | K18: =J18*(1+K19) -> 280 | L18: =K18*(1+L19) -> 280 | M18: =L18*(1+M19) -> 287 | N18: =M18*(1+N19) -> 287 | O18: =N18*(1+O19) -> 287 | P18: =O18*(1+P19) -> 287 | Q18: =P18*(1+Q19) -> 294.175 | ... BP18: =BO18*(1+BP19) -> 395.63267
D19: Growth Rate | G19: =CaseData!E12 -> Annual | J19: =INDEX(J$20:J$21,MATCH($G19,$E$20:$E$21,0)) -> 0 | K19: =INDEX(K$20:K$21,MATCH($G19,$E$20:$E$21,0)) -> 0 | L19: =INDEX(L$20:L$21,MATCH($G19,$E$20:$E$21,0)) -> 0 | M19: =INDEX(M$20:M$21,MATCH($G19,$E$20:$E$21,0)) -> 0.025 | N19: =INDEX(N$20:N$21,MATCH($G19,$E$20:$E$21,0)) -> 0 | O19: =INDEX(O$20:O$21,MATCH($G19,$E$20:$E$21,0)) -> 0 | P19: =INDEX(P$20:P$21,MATCH($G19,$E$20:$E$21,0)) -> 0 | Q19: =INDEX(Q$20:Q$21,MATCH($G19,$E$20:$E$21,0)) -> 0.025 | ... BP19: =INDEX(BP$20:BP$21,MATCH($G19,$E$20:$E$21,0)) -> 0
E20: Annual | G20: =INDEX(CaseData!H12:J12,$G$12) -> 0.025 | J20: =IF(J$7<>I$7,$G20,0) -> 0 | K20: =IF(K$7<>J$7,$G20,0) -> 0 | L20: =IF(L$7<>K$7,$G20,0) -> 0 | M20: =IF(M$7<>L$7,$G20,0) -> 0.025 | N20: =IF(N$7<>M$7,$G20,0) -> 0 | O20: =IF(O$7<>N$7,$G20,0) -> 0 | P20: =IF(P$7<>O$7,$G20,0) -> 0 | Q20: =IF(Q$7<>P$7,$G20,0) -> 0.025 | ... BP20: =IF(BP$7<>BO$7,$G20,0) -> 0
E21: Quarterly | G21: =(1+G20)^(1/4)-1 -> 0.0061922463 | J21: =$G21 -> 0.0061922463 | K21: =$G21 -> 0.0061922463 | L21: =$G21 -> 0.0061922463 | M21: =$G21 -> 0.0061922463 | N21: =$G21 -> 0.0061922463 | O21: =$G21 -> 0.0061922463 | P21: =$G21 -> 0.0061922463 | Q21: =$G21 -> 0.0061922463 | ... BP21: =$G21 -> 0.0061922463
C24: Volume
D25: Demand | H25: =CaseData!F42 -> [slabs] | I25: =CaseData!H42 -> 26500 | J25: =CaseData!I42 -> 28100 | K25: =CaseData!J42 -> 29000 | L25: =CaseData!K42 -> 25200 | M25: =I28*(1+M26) -> 27030 | N25: =J28*(1+N26) -> 28662 | O25: =K28*(1+O26) -> 29580 | P25: =L28*(1+P26) -> 25704 | Q25: =M28*(1+Q26) -> 27570.6 | R25: =N28*(1+R26) -> 29235.24 | S25: =O28*(1+S26) -> 30171.6 | T25: =P28*(1+T26) -> 26218.08 | ... BP25: =BL28*(1+BP26) -> 33250.865
D26: YoY Growth Rate | G26: =CaseData!H44 -> 0.02 | H26: =CaseData!F44 -> [% YoY] | I26: n.a. | J26: n.a. | K26: n.a. | L26: n.a. | M26: =$G26 -> 0.02 | N26: =$G26 -> 0.02 | O26: =$G26 -> 0.02 | P26: =$G26 -> 0.02 | Q26: =$G26 -> 0.02 | R26: =$G26 -> 0.02 | S26: =$G26 -> 0.02 | T26: =$G26 -> 0.02 | ... BP26: =$G26 -> 0.02
D28: Volume | I28: =I25 -> 26500 | J28: =J25 -> 28100 | K28: =K25 -> 29000 | L28: =L25 -> 25200 | M28: =M25 -> 27030 | N28: =N25 -> 28662 | O28: =O25 -> 29580 | P28: =P25 -> 25704 | ... BP28: =BP25 -> 33250.865
C31: Revenue
D32: Price | H32: =$H$18 -> [$/slab] | I32: =I18 -> 280 | J32: =J18 -> 280 | K32: =K18 -> 280 | L32: =L18 -> 280 | M32: =M18 -> 287 | N32: =N18 -> 287 | O32: =O18 -> 287 | P32: =P18 -> 287 | ... BP32: =BP18 -> 395.63267
D33: Volume | H33: =$H$25 -> [slabs] | I33: =I28 -> 26500 | J33: =J28 -> 28100 | K33: =K28 -> 29000 | L33: =L28 -> 25200 | M33: =M28 -> 27030 | N33: =N28 -> 28662 | O33: =O28 -> 29580 | P33: =P28 -> 25704 | ... BP33: =BP28 -> 33250.865
D34: Total Revenue | H34: [$] | I34: =I32*I33 -> 7420000 | J34: =J32*J33 -> 7868000 | K34: =K32*K33 -> 8120000 | L34: =L32*L33 -> 7056000 | M34: =M32*M33 -> 7757610 | N34: =N32*N33 -> 8225994 | O34: =O32*O33 -> 8489460 | P34: =P32*P33 -> 7377048 | ... BP34: =BP32*BP33 -> 13155128
B36: Expenses
C38: Inflation | G38: =CaseData!E13 -> Annual | J38: =INDEX(J$39:J$40,MATCH($G38,$D$39:$D$40,0)) -> 0 | K38: =INDEX(K$39:K$40,MATCH($G38,$D$39:$D$40,0)) -> 0 | L38: =INDEX(L$39:L$40,MATCH($G38,$D$39:$D$40,0)) -> 0 | M38: =INDEX(M$39:M$40,MATCH($G38,$D$39:$D$40,0)) -> 0.02 | N38: =INDEX(N$39:N$40,MATCH($G38,$D$39:$D$40,0)) -> 0 | O38: =INDEX(O$39:O$40,MATCH($G38,$D$39:$D$40,0)) -> 0 | P38: =INDEX(P$39:P$40,MATCH($G38,$D$39:$D$40,0)) -> 0 | Q38: =INDEX(Q$39:Q$40,MATCH($G38,$D$39:$D$40,0)) -> 0.02 | ... BP38: =INDEX(BP$39:BP$40,MATCH($G38,$D$39:$D$40,0)) -> 0
D39: Annual | G39: =INDEX(CaseData!H13:J13,$G$14) -> 0.02 | J39: =IF(J$7<>I$7,$G39,0) -> 0 | K39: =IF(K$7<>J$7,$G39,0) -> 0 | L39: =IF(L$7<>K$7,$G39,0) -> 0 | M39: =IF(M$7<>L$7,$G39,0) -> 0.02 | N39: =IF(N$7<>M$7,$G39,0) -> 0 | O39: =IF(O$7<>N$7,$G39,0) -> 0 | P39: =IF(P$7<>O$7,$G39,0) -> 0 | Q39: =IF(Q$7<>P$7,$G39,0) -> 0.02 | ... BP39: =IF(BP$7<>BO$7,$G39,0) -> 0
D40: Quarterly | G40: =(1+G39)^(1/4)-1 -> 0.0049629316 | J40: =$G40 -> 0.0049629316 | K40: =$G40 -> 0.0049629316 | L40: =$G40 -> 0.0049629316 | M40: =$G40 -> 0.0049629316 | N40: =$G40 -> 0.0049629316 | O40: =$G40 -> 0.0049629316 | P40: =$G40 -> 0.0049629316 | Q40: =$G40 -> 0.0049629316 | ... BP40: =$G40 -> 0.0049629316
C43: Raw Materials
D44: Converstion | G44: =CaseData!H52 -> 3 | H44: =CaseData!F52 -> [tonnes/slab] | I44: =$G44 -> 3 | J44: =$G44 -> 3 | K44: =$G44 -> 3 | L44: =$G44 -> 3 | M44: =$G44 -> 3 | N44: =$G44 -> 3 | O44: =$G44 -> 3 | P44: =$G44 -> 3 | ... BP44: =$G44 -> 3
D45: Exchange Rate | G45: 1 | H45: =CaseData!F30 -> [MXN per $] | I45: =INDEX(CaseData!$H$30:$V$32,$G45,MATCH(I$7,CaseData!$H$29:$V$29,0)) -> 19.5 | J45: =INDEX(CaseData!$H$30:$V$32,$G45,MATCH(J$7,CaseData!$H$29:$V$29,0)) -> 19.5 | K45: =INDEX(CaseData!$H$30:$V$32,$G45,MATCH(K$7,CaseData!$H$29:$V$29,0)) -> 19.5 | L45: =INDEX(CaseData!$H$30:$V$32,$G45,MATCH(L$7,CaseData!$H$29:$V$29,0)) -> 19.5 | M45: =INDEX(CaseData!$H$30:$V$32,$G45,MATCH(M$7,CaseData!$H$29:$V$29,0)) -> 20.09 | N45: =INDEX(CaseData!$H$30:$V$32,$G45,MATCH(N$7,CaseData!$H$29:$V$29,0)) -> 20.09 | O45: =INDEX(CaseData!$H$30:$V$32,$G45,MATCH(O$7,CaseData!$H$29:$V$29,0)) -> 20.09 | P45: =INDEX(CaseData!$H$30:$V$32,$G45,MATCH(P$7,CaseData!$H$29:$V$29,0)) -> 20.09 | ... BP45: =INDEX(CaseData!$H$30:$V$32,$G45,MATCH(BP$7,CaseData!$H$29:$V$29,0)) -> 29.5
D47: Volume | H47: =H33 -> [slabs] | I47: =I33 -> 26500 | J47: =J33 -> 28100 | K47: =K33 -> 29000 | L47: =L33 -> 25200 | M47: =M33 -> 27030 | N47: =N33 -> 28662 | O47: =O33 -> 29580 | ... BP47: =BP33 -> 33250.865
D48: Volume | H48: [tonnes] | I48: =I44*I47 -> 79500 | J48: =J44*J47 -> 84300 | K48: =K44*K47 -> 87000 | L48: =L44*L47 -> 75600 | M48: =M44*M47 -> 81090 | N48: =N44*N47 -> 85986 | O48: =O44*O47 -> 88740 | P48: =P44*P47 -> 77112 | ... BP48: =BP44*BP47 -> 99752.594
C50: =CaseData!D54 -> Supplier 1 (US)
D51: Unit Cost | G51: =CaseData!H55 -> 35 | H51: =CaseData!F55 -> [$ / tonne] | I51: =G51 -> 35 | J51: =I51*(1+J52) -> 35 | K51: =J51*(1+K52) -> 35 | L51: =K51*(1+L52) -> 35 | M51: =L51*(1+M52) -> 35.7 | N51: =M51*(1+N52) -> 35.7 | O51: =N51*(1+O52) -> 35.7 | P51: =O51*(1+P52) -> 35.7 | Q51: =P51*(1+Q52) -> 36.414 | ... BP51: =BO51*(1+BP52) -> 46.181757
D52: Inflation | I52: =I$38 -> 0 | J52: =J$38 -> 0 | K52: =K$38 -> 0 | L52: =L$38 -> 0 | M52: =M$38 -> 0.02 | N52: =N$38 -> 0 | O52: =O$38 -> 0 | P52: =P$38 -> 0 | ... BP52: =BP$38 -> 0
D54: Max Capacity | G54: =CaseData!H56 -> 90000 | H54: =CaseData!F56 -> [tonnes] | I54: =$G54 -> 90000 | J54: =$G54 -> 90000 | K54: =$G54 -> 90000 | L54: =$G54 -> 90000 | M54: =$G54 -> 90000 | N54: =$G54 -> 90000 | O54: =$G54 -> 90000 | P54: =$G54 -> 90000 | ... BP54: =$G54 -> 90000
C56: =CaseData!D58 -> Supplier 2 (Mexico)
D57: Unit Cost | G57: =CaseData!H59 -> 800 | H57: =CaseData!F59 -> [MXN / tonne] | I57: =G57 -> 800 | J57: =I57*(1+J58) -> 800 | K57: =J57*(1+K58) -> 800 | L57: =K57*(1+L58) -> 800 | M57: =L57*(1+M58) -> 816 | N57: =M57*(1+N58) -> 816 | O57: =N57*(1+O58) -> 816 | P57: =O57*(1+P58) -> 816 | Q57: =P57*(1+Q58) -> 832.32 | ... BP57: =BO57*(1+BP58) -> 1055.583
D58: Inflation | I58: =I$38 -> 0 | J58: =J$38 -> 0 | K58: =K$38 -> 0 | L58: =L$38 -> 0 | M58: =M$38 -> 0.02 | N58: =N$38 -> 0 | O58: =O$38 -> 0 | P58: =P$38 -> 0 | ... BP58: =BP$38 -> 0
D60: Unit Cost | H60: [$ / tonne] | I60: =I57/I45 -> 41.025641 | J60: =J57/J45 -> 41.025641 | K60: =K57/K45 -> 41.025641 | L60: =L57/L45 -> 41.025641 | M60: =M57/M45 -> 40.617222 | N60: =N57/N45 -> 40.617222 | O60: =O57/O45 -> 40.617222 | P60: =P57/P45 -> 40.617222 | ... BP60: =BP57/BP45 -> 35.782475
D62: Max Capacity | G62: =CaseData!H60 -> 70000 | H62: =CaseData!F60 -> [tonnes] | I62: =$G62 -> 70000 | J62: =$G62 -> 70000 | K62: =$G62 -> 70000 | L62: =$G62 -> 70000 | M62: =$G62 -> 70000 | N62: =$G62 -> 70000 | O62: =$G62 -> 70000 | P62: =$G62 -> 70000 | ... BP62: =$G62 -> 70000
B64: Decision
C65: Low Price | H65: =CaseData!F55 -> [$ / tonne] | I65: =MIN(I51,I60) -> 35 | J65: =MIN(J51,J60) -> 35 | K65: =MIN(K51,K60) -> 35 | L65: =MIN(L51,L60) -> 35 | M65: =MIN(M51,M60) -> 35.7 | N65: =MIN(N51,N60) -> 35.7 | O65: =MIN(O51,O60) -> 35.7 | P65: =MIN(P51,P60) -> 35.7 | ... BP65: =MIN(BP51,BP60) -> 35.782475
C66: High Price | H66: =H65 -> [$ / tonne] | I66: =IF(I65=I51,I60,I51) -> 41.025641 | J66: =IF(J65=J51,J60,J51) -> 41.025641 | K66: =IF(K65=K51,K60,K51) -> 41.025641 | L66: =IF(L65=L51,L60,L51) -> 41.025641 | M66: =IF(M65=M51,M60,M51) -> 40.617222 | N66: =IF(N65=N51,N60,N51) -> 40.617222 | O66: =IF(O65=O51,O60,O51) -> 40.617222 | P66: =IF(P65=P51,P60,P51) -> 40.617222 | ... BP66: =IF(BP65=BP51,BP60,BP51) -> 46.181757
C68: Low Price Supplier | I68: =IF(I65=I51,$C50,$C56) -> Supplier 1 (US) | J68: =IF(J65=J51,$C50,$C56) -> Supplier 1 (US) | K68: =IF(K65=K51,$C50,$C56) -> Supplier 1 (US) | L68: =IF(L65=L51,$C50,$C56) -> Supplier 1 (US) | M68: =IF(M65=M51,$C50,$C56) -> Supplier 1 (US) | N68: =IF(N65=N51,$C50,$C56) -> Supplier 1 (US) | O68: =IF(O65=O51,$C50,$C56) -> Supplier 1 (US) | P68: =IF(P65=P51,$C50,$C56) -> Supplier 1 (US) | ... BP68: =IF(BP65=BP51,$C50,$C56) -> Supplier 2 (Mexico)
C70: Low Price Capacity | H70: =CaseData!F56 -> [tonnes] | I70: =IF(I65=I51,I54,I62) -> 90000 | J70: =IF(J65=J51,J54,J62) -> 90000 | K70: =IF(K65=K51,K54,K62) -> 90000 | L70: =IF(L65=L51,L54,L62) -> 90000 | M70: =IF(M65=M51,M54,M62) -> 90000 | N70: =IF(N65=N51,N54,N62) -> 90000 | O70: =IF(O65=O51,O54,O62) -> 90000 | P70: =IF(P65=P51,P54,P62) -> 90000 | ... BP70: =IF(BP65=BP51,BP54,BP62) -> 70000
C71: High Price Capacity | H71: =H70 -> [tonnes] | I71: =IF(I70=I54,I62,I54) -> 70000 | J71: =IF(J70=J54,J62,J54) -> 70000 | K71: =IF(K70=K54,K62,K54) -> 70000 | L71: =IF(L70=L54,L62,L54) -> 70000 | M71: =IF(M70=M54,M62,M54) -> 70000 | N71: =IF(N70=N54,N62,N54) -> 70000 | O71: =IF(O70=O54,O62,O54) -> 70000 | P71: =IF(P70=P54,P62,P54) -> 70000 | ... BP71: =IF(BP70=BP54,BP62,BP54) -> 90000
C73: Volume at Low Price | H73: =H71 -> [tonnes] | I73: =MIN(I48,I70) -> 79500 | J73: =MIN(J48,J70) -> 84300 | K73: =MIN(K48,K70) -> 87000 | L73: =MIN(L48,L70) -> 75600 | M73: =MIN(M48,M70) -> 81090 | N73: =MIN(N48,N70) -> 85986 | O73: =MIN(O48,O70) -> 88740 | P73: =MIN(P48,P70) -> 77112 | ... BP73: =MIN(BP48,BP70) -> 70000
C74: Volume at Higher Price | H74: =H73 -> [tonnes] | I74: =MIN(I48-I73,I71) -> 0 | J74: =MIN(J48-J73,J71) -> 0 | K74: =MIN(K48-K73,K71) -> 0 | L74: =MIN(L48-L73,L71) -> 0 | M74: =MIN(M48-M73,M71) -> 0 | N74: =MIN(N48-N73,N71) -> 0 | O74: =MIN(O48-O73,O71) -> 0 | P74: =MIN(P48-P73,P71) -> 0 | ... BP74: =MIN(BP48-BP73,BP71) -> 29752.594
C75: Total | H75: =H74 -> [tonnes] | I75: =SUM(I73:I74) -> 79500 | J75: =SUM(J73:J74) -> 84300 | K75: =SUM(K73:K74) -> 87000 | L75: =SUM(L73:L74) -> 75600 | M75: =SUM(M73:M74) -> 81090 | N75: =SUM(N73:N74) -> 85986 | O75: =SUM(O73:O74) -> 88740 | P75: =SUM(P73:P74) -> 77112 | ... BP75: =SUM(BP73:BP74) -> 99752.594
C76: CHECK | G76: =MAX(I76:BP76,ABS(MIN(I76:BP76))) -> 0 | I76: =I48-I75 -> 0 | J76: =J48-J75 -> 0 | K76: =K48-K75 -> 0 | L76: =L48-L75 -> 0 | M76: =M48-M75 -> 0 | N76: =N48-N75 -> 0 | O76: =O48-O75 -> 0 | P76: =P48-P75 -> 0 | ... BP76: =BP48-BP75 -> 0
C78: Expense | I78: =SUMPRODUCT(I73:I74,I65:I66) -> 2782500 | J78: =SUMPRODUCT(J73:J74,J65:J66) -> 2950500 | K78: =SUMPRODUCT(K73:K74,K65:K66) -> 3045000 | L78: =SUMPRODUCT(L73:L74,L65:L66) -> 2646000 | M78: =SUMPRODUCT(M73:M74,M65:M66) -> 2894913 | N78: =SUMPRODUCT(N73:N74,N65:N66) -> 3069700.2 | O78: =SUMPRODUCT(O73:O74,O65:O66) -> 3168018 | P78: =SUMPRODUCT(P73:P74,P65:P66) -> 2752898.4 | ... BP78: =SUMPRODUCT(BP73:BP74,BP65:BP66) -> 3878800.3
C81: Manufacturing Costs
D82: Volume | H82: =H33 -> [slabs] | I82: =I33 -> 26500 | J82: =J33 -> 28100 | K82: =K33 -> 29000 | L82: =L33 -> 25200 | M82: =M33 -> 27030 | N82: =N33 -> 28662 | O82: =O33 -> 29580 | ... BP82: =BP33 -> 33250.865
D84: Cost Brackets
E85: =CaseData!G66 -> 1 | G85: =CaseData!I66 -> 25000 | H85: =CaseData!I65 -> [# slabs / qtr] | I85: =MIN($G85-$G84,I$82-SUM(I$84:I84)) -> 25000 | J85: =MIN($G85-$G84,J$82-SUM(J$84:J84)) -> 25000 | K85: =MIN($G85-$G84,K$82-SUM(K$84:K84)) -> 25000 | L85: =MIN($G85-$G84,L$82-SUM(L$84:L84)) -> 25000 | M85: =MIN($G85-$G84,M$82-SUM(M$84:M84)) -> 25000 | N85: =MIN($G85-$G84,N$82-SUM(N$84:N84)) -> 25000 | O85: =MIN($G85-$G84,O$82-SUM(O$84:O84)) -> 25000 | P85: =MIN($G85-$G84,P$82-SUM(P$84:P84)) -> 25000 | ... BP85: =MIN($G85-$G84,BP$82-SUM(BP$84:BP84)) -> 25000
E86: =CaseData!G67 -> 2 | G86: =CaseData!I67 -> 30000 | H86: =H85 -> [# slabs / qtr] | I86: =MIN($G86-$G85,I$82-SUM(I$84:I85)) -> 1500 | J86: =MIN($G86-$G85,J$82-SUM(J$84:J85)) -> 3100 | K86: =MIN($G86-$G85,K$82-SUM(K$84:K85)) -> 4000 | L86: =MIN($G86-$G85,L$82-SUM(L$84:L85)) -> 200 | M86: =MIN($G86-$G85,M$82-SUM(M$84:M85)) -> 2030 | N86: =MIN($G86-$G85,N$82-SUM(N$84:N85)) -> 3662 | O86: =MIN($G86-$G85,O$82-SUM(O$84:O85)) -> 4580 | P86: =MIN($G86-$G85,P$82-SUM(P$84:P85)) -> 704 | ... BP86: =MIN($G86-$G85,BP$82-SUM(BP$84:BP85)) -> 5000
E87: =CaseData!G68 -> 3 | G87: =CaseData!I68 -> 34000 | H87: =H86 -> [# slabs / qtr] | I87: =MIN($G87-$G86,I$82-SUM(I$84:I86)) -> 0 | J87: =MIN($G87-$G86,J$82-SUM(J$84:J86)) -> 0 | K87: =MIN($G87-$G86,K$82-SUM(K$84:K86)) -> 0 | L87: =MIN($G87-$G86,L$82-SUM(L$84:L86)) -> 0 | M87: =MIN($G87-$G86,M$82-SUM(M$84:M86)) -> 0 | N87: =MIN($G87-$G86,N$82-SUM(N$84:N86)) -> 0 | O87: =MIN($G87-$G86,O$82-SUM(O$84:O86)) -> 0 | P87: =MIN($G87-$G86,P$82-SUM(P$84:P86)) -> 0 | ... BP87: =MIN($G87-$G86,BP$82-SUM(BP$84:BP86)) -> 3250.8648
E88: =CaseData!G69 -> 4 | G88: =CaseData!I69 -> 999999 | H88: =H87 -> [# slabs / qtr] | I88: =MIN($G88-$G87,I$82-SUM(I$84:I87)) -> 0 | J88: =MIN($G88-$G87,J$82-SUM(J$84:J87)) -> 0 | K88: =MIN($G88-$G87,K$82-SUM(K$84:K87)) -> 0 | L88: =MIN($G88-$G87,L$82-SUM(L$84:L87)) -> 0 | M88: =MIN($G88-$G87,M$82-SUM(M$84:M87)) -> 0 | N88: =MIN($G88-$G87,N$82-SUM(N$84:N87)) -> 0 | O88: =MIN($G88-$G87,O$82-SUM(O$84:O87)) -> 0 | P88: =MIN($G88-$G87,P$82-SUM(P$84:P87)) -> 0 | ... BP88: =MIN($G88-$G87,BP$82-SUM(BP$84:BP87)) -> 0
E89: Total | I89: =SUM(I85:I88) -> 26500 | J89: =SUM(J85:J88) -> 28100 | K89: =SUM(K85:K88) -> 29000 | L89: =SUM(L85:L88) -> 25200 | M89: =SUM(M85:M88) -> 27030 | N89: =SUM(N85:N88) -> 28662 | O89: =SUM(O85:O88) -> 29580 | P89: =SUM(P85:P88) -> 25704 | ... BP89: =SUM(BP85:BP88) -> 33250.865
E90: CHECK | G90: =MAX(I90:BP90,ABS(MIN(I90:BP90))) -> 0 | I90: =I82-I89 -> 0 | J90: =J82-J89 -> 0 | K90: =K82-K89 -> 0 | L90: =L82-L89 -> 0 | M90: =M82-M89 -> 0 | N90: =N82-N89 -> 0 | O90: =O82-O89 -> 0 | P90: =P82-P89 -> 0 | ... BP90: =BP82-BP89 -> 0
D92: Unit Costs
E93: Infaltion | I93: =I$38 -> 0 | J93: =J$38 -> 0 | K93: =K$38 -> 0 | L93: =L$38 -> 0 | M93: =M$38 -> 0.02 | N93: =N$38 -> 0 | O93: =O$38 -> 0 | P93: =P$38 -> 0 | ... BP93: =BP$38 -> 0
E95: =E85 -> 1 | G95: =CaseData!J66 -> 100 | H95: =CaseData!J65 -> [$ / slab] | I95: =G95 -> 100 | J95: =I95*(1+J$93) -> 100 | K95: =J95*(1+K$93) -> 100 | L95: =K95*(1+L$93) -> 100 | M95: =L95*(1+M$93) -> 102 | N95: =M95*(1+N$93) -> 102 | O95: =N95*(1+O$93) -> 102 | P95: =O95*(1+P$93) -> 102 | Q95: =P95*(1+Q$93) -> 104.04 | ... BP95: =BO95*(1+BP$93) -> 131.94788
E96: =E86 -> 2 | G96: =CaseData!J67 -> 90 | H96: =H95 -> [$ / slab] | I96: =G96 -> 90 | J96: =I96*(1+J$93) -> 90 | K96: =J96*(1+K$93) -> 90 | L96: =K96*(1+L$93) -> 90 | M96: =L96*(1+M$93) -> 91.8 | N96: =M96*(1+N$93) -> 91.8 | O96: =N96*(1+O$93) -> 91.8 | P96: =O96*(1+P$93) -> 91.8 | Q96: =P96*(1+Q$93) -> 93.636 | ... BP96: =BO96*(1+BP$93) -> 118.75309
E97: =E87 -> 3 | G97: =CaseData!J68 -> 85 | H97: =H96 -> [$ / slab] | I97: =G97 -> 85 | J97: =I97*(1+J$93) -> 85 | K97: =J97*(1+K$93) -> 85 | L97: =K97*(1+L$93) -> 85 | M97: =L97*(1+M$93) -> 86.7 | N97: =M97*(1+N$93) -> 86.7 | O97: =N97*(1+O$93) -> 86.7 | P97: =O97*(1+P$93) -> 86.7 | Q97: =P97*(1+Q$93) -> 88.434 | ... BP97: =BO97*(1+BP$93) -> 112.15569
E98: =E88 -> 4 | G98: =CaseData!J69 -> 82 | H98: =H97 -> [$ / slab] | I98: =G98 -> 82 | J98: =I98*(1+J$93) -> 82 | K98: =J98*(1+K$93) -> 82 | L98: =K98*(1+L$93) -> 82 | M98: =L98*(1+M$93) -> 83.64 | N98: =M98*(1+N$93) -> 83.64 | O98: =N98*(1+O$93) -> 83.64 | P98: =O98*(1+P$93) -> 83.64 | Q98: =P98*(1+Q$93) -> 85.3128 | ... BP98: =BO98*(1+BP$93) -> 108.19726
D100: Expense | I100: =SUMPRODUCT(I85:I88,I95:I98) -> 2635000 | J100: =SUMPRODUCT(J85:J88,J95:J98) -> 2779000 | K100: =SUMPRODUCT(K85:K88,K95:K98) -> 2860000 | L100: =SUMPRODUCT(L85:L88,L95:L98) -> 2518000 | M100: =SUMPRODUCT(M85:M88,M95:M98) -> 2736354 | N100: =SUMPRODUCT(N85:N88,N95:N98) -> 2886171.6 | O100: =SUMPRODUCT(O85:O88,O95:O98) -> 2970444 | P100: =SUMPRODUCT(P85:P88,P95:P98) -> 2614627.2 | ... BP100: =SUMPRODUCT(BP85:BP88,BP95:BP98) -> 4257065.4
C103: Rent and Storage
D104: Fixed Costs | I104: =I109 -> 600000 | J104: =J109 -> 600000 | K104: =K109 -> 600000 | L104: =L109 -> 600000 | M104: =M109 -> 612000 | N104: =N109 -> 612000 | O104: =O109 -> 612000 | P104: =P109 -> 612000 | ... BP104: =BP109 -> 791687.26
D105: Variable Costs | I105: =I120 -> 0 | J105: =J120 -> 0 | K105: =K120 -> 0 | L105: =L120 -> 0 | M105: =M120 -> 0 | N105: =N120 -> 0 | O105: =O120 -> 0 | P105: =P120 -> 0 | ... BP105: =BP120 -> 41262.239
D106: Total | I106: =SUM(I104:I105) -> 600000 | J106: =SUM(J104:J105) -> 600000 | K106: =SUM(K104:K105) -> 600000 | L106: =SUM(L104:L105) -> 600000 | M106: =SUM(M104:M105) -> 612000 | N106: =SUM(N104:N105) -> 612000 | O106: =SUM(O104:O105) -> 612000 | P106: =SUM(P104:P105) -> 612000 | ... BP106: =SUM(BP104:BP105) -> 832949.5
D108: Fixed Costs
E109: Expense | G109: =CaseData!H74 -> 600000 | H109: =CaseData!F74 -> [$/qtr] | I109: =G109 -> 600000 | J109: =I109*(1+J110) -> 600000 | K109: =J109*(1+K110) -> 600000 | L109: =K109*(1+L110) -> 600000 | M109: =L109*(1+M110) -> 612000 | N109: =M109*(1+N110) -> 612000 | O109: =N109*(1+O110) -> 612000 | P109: =O109*(1+P110) -> 612000 | Q109: =P109*(1+Q110) -> 624240 | ... BP109: =BO109*(1+BP110) -> 791687.26
E110: Inflation | I110: =I$38 -> 0 | J110: =J$38 -> 0 | K110: =K$38 -> 0 | L110: =L$38 -> 0 | M110: =M$38 -> 0.02 | N110: =N$38 -> 0 | O110: =O$38 -> 0 | P110: =P$38 -> 0 | ... BP110: =BP$38 -> 0
D112: Variable Costs
E113: Unit Cost | G113: =CaseData!H75 -> 25 | H113: =CaseData!F75 -> [$/slab/qtr] | I113: =G113 -> 25 | J113: =I113*(1+J114) -> 25 | K113: =J113*(1+K114) -> 25 | L113: =K113*(1+L114) -> 25 | M113: =L113*(1+M114) -> 25.5 | N113: =M113*(1+N114) -> 25.5 | O113: =N113*(1+O114) -> 25.5 | P113: =O113*(1+P114) -> 25.5 | Q113: =P113*(1+Q114) -> 26.01 | ... BP113: =BO113*(1+BP114) -> 32.986969
E114: Inflation | I114: =I$38 -> 0 | J114: =J$38 -> 0 | K114: =K$38 -> 0 | L114: =L$38 -> 0 | M114: =M$38 -> 0.02 | N114: =N$38 -> 0 | O114: =O$38 -> 0 | P114: =P$38 -> 0 | ... BP114: =BP$38 -> 0
E116: Volume | H116: =$H$33 -> [slabs] | I116: =I33 -> 26500 | J116: =J33 -> 28100 | K116: =K33 -> 29000 | L116: =L33 -> 25200 | M116: =M33 -> 27030 | N116: =N33 -> 28662 | O116: =O33 -> 29580 | P116: =P33 -> 25704 | ... BP116: =BP33 -> 33250.865
E117: Threshold | G117: =CaseData!H76 -> 32000 | H117: =$H$33 -> [slabs] | I117: =$G117 -> 32000 | J117: =$G117 -> 32000 | K117: =$G117 -> 32000 | L117: =$G117 -> 32000 | M117: =$G117 -> 32000 | N117: =$G117 -> 32000 | O117: =$G117 -> 32000 | P117: =$G117 -> 32000 | ... BP117: =$G117 -> 32000
E118: Subject to VC | H118: =$H$33 -> [slabs] | I118: =MAX(I116-I117,0) -> 0 | J118: =MAX(J116-J117,0) -> 0 | K118: =MAX(K116-K117,0) -> 0 | L118: =MAX(L116-L117,0) -> 0 | M118: =MAX(M116-M117,0) -> 0 | N118: =MAX(N116-N117,0) -> 0 | O118: =MAX(O116-O117,0) -> 0 | P118: =MAX(P116-P117,0) -> 0 | ... BP118: =MAX(BP116-BP117,0) -> 1250.8648
E120: Expense | I120: =I113*I118 -> 0 | J120: =J113*J118 -> 0 | K120: =K113*K118 -> 0 | L120: =L113*L118 -> 0 | M120: =M113*M118 -> 0 | N120: =N113*N118 -> 0 | O120: =O113*O118 -> 0 | P120: =P113*P118 -> 0 | ... BP120: =BP113*BP118 -> 41262.239
C123: Staff and Other Overheads
D124: Expense | G124: =CaseData!H79 -> 450000 | H124: =CaseData!F79 -> [$/qtr] | I124: =G124 -> 450000 | J124: =I124*(1+J125) -> 450000 | K124: =J124*(1+K125) -> 450000 | L124: =K124*(1+L125) -> 450000 | M124: =L124*(1+M125) -> 459000 | N124: =M124*(1+N125) -> 459000 | O124: =N124*(1+O125) -> 459000 | P124: =O124*(1+P125) -> 459000 | Q124: =P124*(1+Q125) -> 468180 | ... BP124: =BO124*(1+BP125) -> 593765.44
D125: Inflation | I125: =I$38 -> 0 | J125: =J$38 -> 0 | K125: =K$38 -> 0 | L125: =L$38 -> 0 | M125: =M$38 -> 0.02 | N125: =N$38 -> 0 | O125: =O$38 -> 0 | P125: =P$38 -> 0 | ... BP125: =BP$38 -> 0
B127: Operating Profit Schedule
C129: Revenue | I129: =I34 -> 7420000 | J129: =J34 -> 7868000 | K129: =K34 -> 8120000 | L129: =L34 -> 7056000 | M129: =M34 -> 7757610 | N129: =N34 -> 8225994 | O129: =O34 -> 8489460 | P129: =P34 -> 7377048 | ... BP129: =BP34 -> 13155128
C131: Raw Materials | I131: =I78 -> 2782500 | J131: =J78 -> 2950500 | K131: =K78 -> 3045000 | L131: =L78 -> 2646000 | M131: =M78 -> 2894913 | N131: =N78 -> 3069700.2 | O131: =O78 -> 3168018 | P131: =P78 -> 2752898.4 | ... BP131: =BP78 -> 3878800.3
C132: Manufacturing Costs | I132: =I100 -> 2635000 | J132: =J100 -> 2779000 | K132: =K100 -> 2860000 | L132: =L100 -> 2518000 | M132: =M100 -> 2736354 | N132: =N100 -> 2886171.6 | O132: =O100 -> 2970444 | P132: =P100 -> 2614627.2 | ... BP132: =BP100 -> 4257065.4
C133: Rent & Storage | I133: =I106 -> 600000 | J133: =J106 -> 600000 | K133: =K106 -> 600000 | L133: =L106 -> 600000 | M133: =M106 -> 612000 | N133: =N106 -> 612000 | O133: =O106 -> 612000 | P133: =P106 -> 612000 | ... BP133: =BP106 -> 832949.5
C134: Staff and Other Overheads | I134: =I124 -> 450000 | J134: =J124 -> 450000 | K134: =K124 -> 450000 | L134: =L124 -> 450000 | M134: =M124 -> 459000 | N134: =N124 -> 459000 | O134: =O124 -> 459000 | P134: =P124 -> 459000 | ... BP134: =BP124 -> 593765.44
C135: Total Expenses | I135: =SUM(I131:I134) -> 6467500 | J135: =SUM(J131:J134) -> 6779500 | K135: =SUM(K131:K134) -> 6955000 | L135: =SUM(L131:L134) -> 6214000 | M135: =SUM(M131:M134) -> 6702267 | N135: =SUM(N131:N134) -> 7026871.8 | O135: =SUM(O131:O134) -> 7209462 | P135: =SUM(P131:P134) -> 6438525.6 | ... BP135: =SUM(BP131:BP134) -> 9562580.6
C137: Operating Profit | I137: =I129-I135 -> 952500 | J137: =J129-J135 -> 1088500 | K137: =K129-K135 -> 1165000 | L137: =L129-L135 -> 842000 | M137: =M129-M135 -> 1055343 | N137: =N129-N135 -> 1199122.2 | O137: =O129-O135 -> 1279998 | P137: =P129-P135 -> 938522.4 | ... BP137: =BP129-BP135 -> 3592547.8
B139: Annual Summary
C141: Year | F141: =MAX(I141:BP141) -> 2034 | G141: =YEAR(G6) -> 2034 | I141: =MIN(I7:BP7) -> 2020 | J141: =I141+1 -> 2021 | K141: =J141+1 -> 2022 | L141: =K141+1 -> 2023 | M141: =L141+1 -> 2024 | N141: =M141+1 -> 2025 | O141: =N141+1 -> 2026 | P141: =O141+1 -> 2027 | Q141: =P141+1 -> 2028 | ... W141: =V141+1 -> 2034
C143: Revenue | I143: =SUMIF($I$7:$BP$7,I$141,$I129:$BP129) -> 30464000 | J143: =SUMIF($I$7:$BP$7,J$141,$I129:$BP129) -> 31850112 | K143: =SUMIF($I$7:$BP$7,K$141,$I129:$BP129) -> 33299292 | L143: =SUMIF($I$7:$BP$7,L$141,$I129:$BP129) -> 34814410 | M143: =SUMIF($I$7:$BP$7,M$141,$I129:$BP129) -> 36398466 | N143: =SUMIF($I$7:$BP$7,N$141,$I129:$BP129) -> 38054596 | O143: =SUMIF($I$7:$BP$7,O$141,$I129:$BP129) -> 39786080 | P143: =SUMIF($I$7:$BP$7,P$141,$I129:$BP129) -> 41596346 | ... W143: =SUMIF($I$7:$BP$7,W$141,$I129:$BP129) -> 56796745
C145: Raw Materials | I145: =SUMIF($I$7:$BP$7,I$141,$I131:$BP131) -> 11424000 | J145: =SUMIF($I$7:$BP$7,J$141,$I131:$BP131) -> 11885530 | K145: =SUMIF($I$7:$BP$7,K$141,$I131:$BP131) -> 12367669 | L145: =SUMIF($I$7:$BP$7,L$141,$I131:$BP131) -> 12871549 | M145: =SUMIF($I$7:$BP$7,M$141,$I131:$BP131) -> 13393524 | N145: =SUMIF($I$7:$BP$7,N$141,$I131:$BP131) -> 13929648 | O145: =SUMIF($I$7:$BP$7,O$141,$I131:$BP131) -> 14283277 | P145: =SUMIF($I$7:$BP$7,P$141,$I131:$BP131) -> 14542141 | ... W145: =SUMIF($I$7:$BP$7,W$141,$I131:$BP131) -> 16977662
C146: Manufacturing Costs | I146: =SUMIF($I$7:$BP$7,I$141,$I132:$BP132) -> 10792000 | J146: =SUMIF($I$7:$BP$7,J$141,$I132:$BP132) -> 11207597 | K146: =SUMIF($I$7:$BP$7,K$141,$I132:$BP132) -> 11638683 | L146: =SUMIF($I$7:$BP$7,L$141,$I132:$BP132) -> 12084478 | M146: =SUMIF($I$7:$BP$7,M$141,$I132:$BP132) -> 12545542 | N146: =SUMIF($I$7:$BP$7,N$141,$I132:$BP132) -> 13023675 | O146: =SUMIF($I$7:$BP$7,O$141,$I132:$BP132) -> 13520552 | P146: =SUMIF($I$7:$BP$7,P$141,$I132:$BP132) -> 14034388 | ... W146: =SUMIF($I$7:$BP$7,W$141,$I132:$BP132) -> 18179270
C147: Rent & Storage | I147: =SUMIF($I$7:$BP$7,I$141,$I133:$BP133) -> 2400000 | J147: =SUMIF($I$7:$BP$7,J$141,$I133:$BP133) -> 2448000 | K147: =SUMIF($I$7:$BP$7,K$141,$I133:$BP133) -> 2496960 | L147: =SUMIF($I$7:$BP$7,L$141,$I133:$BP133) -> 2546899.2 | M147: =SUMIF($I$7:$BP$7,M$141,$I133:$BP133) -> 2597837.2 | N147: =SUMIF($I$7:$BP$7,N$141,$I133:$BP133) -> 2650300.2 | O147: =SUMIF($I$7:$BP$7,O$141,$I133:$BP133) -> 2721335.2 | P147: =SUMIF($I$7:$BP$7,P$141,$I133:$BP133) -> 2802504.5 | ... W147: =SUMIF($I$7:$BP$7,W$141,$I133:$BP133) -> 3680002.8
C148: Staff and Other Overheads | I148: =SUMIF($I$7:$BP$7,I$141,$I134:$BP134) -> 1800000 | J148: =SUMIF($I$7:$BP$7,J$141,$I134:$BP134) -> 1836000 | K148: =SUMIF($I$7:$BP$7,K$141,$I134:$BP134) -> 1872720 | L148: =SUMIF($I$7:$BP$7,L$141,$I134:$BP134) -> 1910174.4 | M148: =SUMIF($I$7:$BP$7,M$141,$I134:$BP134) -> 1948377.9 | N148: =SUMIF($I$7:$BP$7,N$141,$I134:$BP134) -> 1987345.4 | O148: =SUMIF($I$7:$BP$7,O$141,$I134:$BP134) -> 2027092.4 | P148: =SUMIF($I$7:$BP$7,P$141,$I134:$BP134) -> 2067634.2 | ... W148: =SUMIF($I$7:$BP$7,W$141,$I134:$BP134) -> 2375061.8
C149: Total Expenses | I149: =SUM(I145:I148) -> 26416000 | J149: =SUM(J145:J148) -> 27377126 | K149: =SUM(K145:K148) -> 28376032 | L149: =SUM(L145:L148) -> 29413101 | M149: =SUM(M145:M148) -> 30485281 | N149: =SUM(N145:N148) -> 31590969 | O149: =SUM(O145:O148) -> 32552256 | P149: =SUM(P145:P148) -> 33446668 | ... W149: =SUM(W145:W148) -> 41211996
...

Sheet Tmp
A1: {=company} -> Megabrick Inc.
A2: {=topic} -> CFM Topic: Costs
A3: TMP SCHEDULE
