Workbook
Name company: CaseData!$K$17
Name periods: CaseData!$K$16
Name start_date: CaseData!$K$15
Name topic: "CFM Topic: Costs"

Sheet Summary
A1: =company -> Big Fish Co.
A2: {=topic} -> CFM Topic: Costs
A3: EXCUTIVE SUMMARY | F3: Constant | G3: Unit | H3: Total | J3: {=_xlfn.TAKE( EOMONTH( start_date, _xlfn.SEQUENCE( 1, periods, 1, 1 ) - 1 ),, -12 )} -> 43861 | K3: 43890 | L3: 43921 | M3: 43951 | N3: 43982 | O3: 44012 | P3: 44043 | Q3: 44074 | R3: 44104 | S3: 44135 | T3: 44165 | U3: 44196
A5: REVENUE BY CLIENT
E7: {=_xlfn.LET( _xlpm.revenue,_xlfn.ANCHORARRAY( Calculations!V197), _xlpm.revenue_rows, _xlfn.DROP( INDEX(_xlfn.ANCHORARRAY( Calculations!E196),, 1 ), 1 ), _xlpm.grouped, _xlfn.GROUPBY( _xlpm.revenue_rows, _xlpm.revenue, _xleta.SUM, 0, 0 ), _xlpm.labels, INDEX( _xlpm.grouped,, 1 ), _xlpm.rev_matrix, _xlfn.DROP( _xlpm.grouped,, 1 ), _xlpm.sort_order, MMULT( _xlpm.rev_matrix, _xlfn.SEQUENCE( COLUMNS(_xlpm.rev_matrix), 1, 1, 0 ) ), _xlfn.SORTBY( _xlpm.labels, _xlpm.sort_order, -1 ) )} -> Client 4 | G7: USD | H7: {=_xlfn.BYROW(_xlfn.ANCHORARRAY( J7), _xleta.SUM )} -> 28589247 | J7: {=_xlfn.LET( _xlpm.revenue,_xlfn.ANCHORARRAY( Calculations!V197), _xlpm.revenue_rows, _xlfn.DROP( INDEX(_xlfn.ANCHORARRAY( Calculations!E196),, 1 ), 1 ), _xlpm.grouped, _xlfn.GROUPBY( _xlpm.revenue_rows, _xlpm.revenue, _xleta.SUM, 0, 0 ), _xlpm.rev_matrix, _xlfn.DROP( _xlpm.grouped,, 1 ), _xlpm.sort_order, MMULT( _xlpm.rev_matrix, _xlfn.SEQUENCE( COLUMNS(_xlpm.rev_matrix), 1, 1, 0 ) ), _xlfn.SORTBY( _xlpm.rev_matrix, _xlpm.sort_order, -1 ) )} -> 2609106.4 | K7: 2016183.1 | L7: 2617854.2 | M7: 3339089.9 | N7: 1965966 | O7: 1920737 | P7: 1715634.6 | Q7: 2755115.8 | R7: 2434191.6 | S7: 3058445.4 | T7: 2377408.1 | U7: 1779514.4
E8: Client 3 | G8: USD | H8: 12009800 | J8: 1008120 | K8: 1166334.6 | L8: 1113695.8 | M8: 971973.94 | N8: 1094743.3 | O8: 947009.91 | P8: 884676.63 | Q8: 716452.51 | R8: 1137308.1 | S8: 1174666 | T8: 907736.94 | U8: 887082.2
E9: Client 1 | G9: USD | H9: 4738211.4 | J9: 465255.09 | K9: 239206.5 | L9: 237128.48 | M9: 278555.84 | N9: 353406.45 | O9: 455370.72 | P9: 445532.62 | Q9: 534480.41 | R9: 496536.8 | S9: 221558.57 | T9: 480971.25 | U9: 530208.67
E10: Client 2 | G10: USD | H10: 3057575.4 | J10: 196205.13 | K10: 205465.91 | L10: 88478.315 | M10: 0 | N10: 356951.62 | O10: 408808.04 | P10: 478364.3 | Q10: 379898.96 | R10: 166506.8 | S10: 26271.283 | T10: 261399.37 | U10: 489225.72
E11: Client 5 | G11: USD | H11: 2692257.9 | J11: 201000.68 | K11: 336551.94 | L11: 336551.94 | M11: 292156.74 | N11: 228994.11 | O11: 247682.68 | P11: 238377.82 | Q11: 140203.69 | R11: 254700.75 | S11: 116862.7 | T11: 142569.33 | U11: 156605.47
E12: Total revenue | G12: USD | H12: {=_xlfn.BYROW(_xlfn.ANCHORARRAY( J12), _xleta.SUM )} -> 51087091 | J12: {=_xlfn.BYCOL(_xlfn.ANCHORARRAY( J7), _xleta.SUM )} -> 4479687.3 | K12: 3963742 | L12: 4393708.7 | M12: 4881776.4 | N12: 4000061.4 | O12: 3979608.4 | P12: 3762586 | Q12: 4526151.4 | R12: 4489244 | S12: 4597803.9 | T12: 4170085 | U12: 3842636.4
A15: COSTS OF GOODS SOLD
E17: {=_xlfn.LET( _xlpm.COGS,_xlfn.ANCHORARRAY( Calculations!V229), _xlpm.cogs_rows, _xlfn.DROP( INDEX(_xlfn.ANCHORARRAY( Calculations!E228),, 2 ), 1 ), _xlpm.grouped, _xlfn.GROUPBY( _xlpm.cogs_rows, _xlpm.COGS, _xleta.SUM, 0, 0 ), _xlpm.labels, "Product " & INDEX( _xlpm.grouped,, 1 ), _xlpm.rev_matrix, _xlfn.DROP( _xlpm.grouped,, 1 ), _xlpm.sort_order, MMULT( _xlpm.rev_matrix, _xlfn.SEQUENCE( COLUMNS(_xlpm.rev_matrix), 1, 1, 0 ) ), _xlfn.SORTBY( _xlpm.labels, _xlpm.sort_order, -1 ) )} -> Product 1 | G17: USD | H17: {=_xlfn.BYROW(_xlfn.ANCHORARRAY( J17), _xleta.SUM )} -> 18606705 | J17: {=_xlfn.LET( _xlpm.COGS,_xlfn.ANCHORARRAY( Calculations!V229), _xlpm.cogs_rows, _xlfn.DROP( INDEX(_xlfn.ANCHORARRAY( Calculations!E228),, 2 ), 1 ), _xlpm.grouped, _xlfn.GROUPBY( _xlpm.cogs_rows, _xlpm.COGS, _xleta.SUM, 0, 0 ), _xlpm.rev_matrix, _xlfn.DROP( _xlpm.grouped,, 1 ), _xlpm.sort_order, MMULT( _xlpm.rev_matrix, _xlfn.SEQUENCE( COLUMNS(_xlpm.rev_matrix), 1, 1, 0 ) ), _xlfn.SORTBY( _xlpm.rev_matrix, _xlpm.sort_order, -1 ) )} -> 1723557.1 | K17: 1287513.9 | L17: 1632961.2 | M17: 2056926.3 | N17: 1320722.4 | O17: 1337494.6 | P17: 1189469.8 | Q17: 1805591.8 | R17: 1776040.6 | S17: 1785241.5 | T17: 1463691.5 | U17: 1227494.4
E18: Product 2 | G18: USD | H18: 4054788.6 | J18: 397972.22 | K18: 382305.26 | L18: 419266.12 | M18: 391174.49 | N18: 370246 | O18: 239220.26 | P18: 258980.18 | Q18: 269083.47 | R18: 287437.21 | S18: 367380.27 | T18: 340079.85 | U18: 331643.28
E19: Product 5 | G19: USD | H19: 2356945.8 | J19: 129141.31 | K19: 236479.71 | L19: 179464.99 | M19: 140639.06 | N19: 180953.38 | O19: 273769.92 | P19: 243733.94 | Q19: 140887.52 | R19: 218029.04 | S19: 219705.15 | T19: 214676.81 | U19: 179464.99
E20: Product 3 | G20: USD | H20: 1310248.8 | J20: 88328.614 | K20: 99038.011 | L20: 49943.126 | M20: 14461.452 | N20: 147254.35 | O20: 156634.32 | P20: 198788.12 | Q20: 150936.07 | R20: 79411.47 | S20: 20620.21 | T20: 110265.31 | U20: 194567.71
E21: Product 4 | G21: USD | H21: 0 | J21: 0 | K21: 0 | L21: 0 | M21: 0 | N21: 0 | O21: 0 | P21: 0 | Q21: 0 | R21: 0 | S21: 0 | T21: 0 | U21: 0
E22: Total Costs of Goods Sold | G22: USD | H22: {=_xlfn.BYROW(_xlfn.ANCHORARRAY( J22), _xleta.SUM )} -> 26328688 | J22: {=_xlfn.BYCOL(_xlfn.ANCHORARRAY( J17), _xleta.SUM )} -> 2338999.2 | K22: 2005336.9 | L22: 2281635.5 | M22: 2603201.3 | N22: 2019176.1 | O22: 2007119.2 | P22: 1890972 | Q22: 2366498.9 | R22: 2360918.3 | S22: 2392947.1 | T22: 2128713.5 | U22: 1933170.3
A25: MANUFACTORING PLAN
E27: {=_xlfn.LET( _xlpm.volume,_xlfn.ANCHORARRAY( Calculations!V166), _xlpm.volume_rows, _xlfn.DROP( INDEX(_xlfn.ANCHORARRAY( Calculations!E228),, 2 ), 1 ), _xlpm.grouped, _xlfn.GROUPBY( _xlpm.volume_rows, _xlpm.volume, _xleta.SUM, 0, 0 ), _xlpm.labels, "Product " & INDEX( _xlpm.grouped,, 1 ), _xlpm.rev_matrix, _xlfn.DROP( _xlpm.grouped,, 1 ), _xlpm.sort_order, MMULT( _xlpm.rev_matrix, _xlfn.SEQUENCE( COLUMNS(_xlpm.rev_matrix), 1, 1, 0 ) ), _xlfn.SORTBY( _xlpm.labels, _xlpm.sort_order, -1 ) )} -> Product 1 | G27: units | H27: {=_xlfn.BYROW(_xlfn.ANCHORARRAY( J27), _xleta.SUM )} -> 695577.76 | J27: {=_xlfn.LET( _xlpm.volume,_xlfn.ANCHORARRAY( Calculations!V166), _xlpm.volume_rows, _xlfn.DROP( INDEX(_xlfn.ANCHORARRAY( Calculations!E228),, 2 ), 1 ), _xlpm.grouped, _xlfn.GROUPBY( _xlpm.volume_rows, _xlpm.volume, _xleta.SUM, 0, 0 ), _xlpm.rev_matrix, _xlfn.DROP( _xlpm.grouped,, 1 ), _xlpm.sort_order, MMULT( _xlpm.rev_matrix, _xlfn.SEQUENCE( COLUMNS(_xlpm.rev_matrix), 1, 1, 0 ) ), _xlfn.SORTBY( _xlpm.rev_matrix, _xlpm.sort_order, -1 ) )} -> 64432.04 | K27: 48131.36 | L27: 61045.28 | M27: 76894.44 | N27: 49372.8 | O27: 49999.8 | P27: 44466.16 | Q27: 67498.76 | R27: 66394.04 | S27: 66738 | T27: 54717.44 | U27: 45887.64
E28: Product 2 | G28: units | H28: 508890.5 | J28: 49946.94 | K28: 47980.68 | L28: 52619.4 | M28: 49093.8 | N28: 46467.2 | O28: 30023 | P28: 32502.94 | Q28: 33770.94 | R28: 36074.4 | S28: 46107.54 | T28: 42681.24 | U28: 41622.42
E29: Product 5 | G29: units | H29: 358579.92 | J29: 19647.24 | K29: 35977.44 | L29: 27303.36 | M29: 21396.48 | N29: 27529.8 | O29: 41650.68 | P29: 37081.08 | Q29: 21434.28 | R29: 33170.4 | S29: 33425.4 | T29: 32660.4 | U29: 27303.36
E30: Product 3 | G30: units | H30: 236951.82 | J30: 15973.78 | K30: 17910.52 | L30: 9031.96 | M30: 2615.28 | N30: 26630.2 | O30: 28326.52 | P30: 35949.82 | Q30: 27296.02 | R30: 14361.16 | S30: 3729.06 | T30: 19940.92 | U30: 35186.58
E31: Product 4 | G31: units | H31: 0 | J31: 0 | K31: 0 | L31: 0 | M31: 0 | N31: 0 | O31: 0 | P31: 0 | Q31: 0 | R31: 0 | S31: 0 | T31: 0 | U31: 0
E32: Total Production | G32: units | H32: {=_xlfn.BYROW(_xlfn.ANCHORARRAY( J32), _xleta.SUM )} -> 1800000 | J32: {=_xlfn.BYCOL(_xlfn.ANCHORARRAY( J27), _xleta.SUM )} -> 150000 | K32: 150000 | L32: 150000 | M32: 150000 | N32: 150000 | O32: 150000 | P32: 150000 | Q32: 150000 | R32: 150000 | S32: 150000 | T32: 150000 | U32: 150000
A68: End of schedule

Sheet Calculations
A1: =company -> Big Fish Co.
A2: {=topic} -> CFM Topic: Costs
A3: CALCULATIONS SCHEDULE | G3: Unit | H3: Total | J3: {=EOMONTH( start_date, _xlfn.SEQUENCE( 1, periods, 1, 1 ) - 1 )} -> 43496 | K3: 43524 | L3: 43555 | M3: 43585 | N3: 43616 | O3: 43646 | P3: 43677 | Q3: 43708 | R3: 43738 | S3: 43769 | T3: 43799 | U3: 43830 | V3: 43861 | W3: 43890 | X3: 43921 | Y3: 43951 | Z3: 43982 | AA3: 44012 | AB3: 44043 | AC3: 44074 | AD3: 44104 | AE3: 44135 | AF3: 44165 | AG3: 44196
A6: PRICE (unranked by profitability)
E8: Client | F8: Product
E9: {=_xlfn.LET( _xlpm.historicals, CaseData!$B$8:$G$307, _xlpm.month, INDEX( _xlpm.historicals,, 1 ), _xlpm.client, "Client " & INDEX( _xlpm.historicals,, 2), _xlpm.product, INDEX( _xlpm.historicals,, 3), _xlpm.volume, INDEX( _xlpm.historicals,, 4 ), _xlpm.price, INDEX( _xlpm.historicals,, 5), _xlfn.TAKE( _xlfn.PIVOTBY( _xlfn.HSTACK( _xlpm.client, _xlpm.product ), _xlpm.month, _xlpm.volume, _xleta.SUM, ,0 ),, 2 ) )}
E10: Client 1 | F10: 1 | G10: USD / kg | J10: {=_xlfn.LET( _xlpm.historicals, CaseData!$B$8:$G$307, _xlpm.month, INDEX(_xlpm.historicals,,1), _xlpm.client, INDEX(_xlpm.historicals,,2), _xlpm.product, INDEX(_xlpm.historicals,,3), _xlpm.volume, INDEX(_xlpm.historicals,,4), _xlpm.price, INDEX(_xlpm.historicals,,5), _xlfn.DROP( _xlfn.DROP( _xlfn.DROP( _xlfn.PIVOTBY( _xlfn.HSTACK( _xlpm.client, _xlpm.product ), _xlpm.month, _xlpm.price, _xleta.SUM,,0 ),,2 ),, -1 ), 1) )} -> 40 | K10: 40 | L10: 40 | M10: 40 | N10: 40 | O10: 40 | P10: 40 | Q10: 40 | R10: 40 | S10: 40 | T10: 40 | U10: 40 | V10: {=_xlfn.LET( _xlpm.historicals, CaseData!$B$8:$G$307, _xlpm.month, INDEX(_xlpm.historicals,,1), _xlpm.client, "Client " & INDEX(_xlpm.historicals,,2), _xlpm.product, INDEX(_xlpm.historicals,,3), _xlpm.volume, INDEX(_xlpm.historicals,,4), _xlpm.price, INDEX(_xlpm.historicals,,5), _xlpm.last_actual, _xlfn.DROP( _xlfn.DROP( _xlfn.DROP( _xlfn.PIVOTBY( _xlfn.HSTACK( _xlpm.client, _xlpm.product ), _xlpm.month, _xlpm.price, _xleta.SUM,,0 ),,2 ),, -1 ), 1), _xlpm.current_client, _xlfn.DROP( INDEX(_xlfn.ANCHORARRAY( E9),, 1 ), 1 ), _xlpm.growth_table, CaseData!$I$8:$K$12, _xlpm.growth_rows, INDEX( _xlpm.growth_table,, 1 ), _xlpm.growth_rate, INDEX( _xlpm.growth_table, MATCH( _xlpm.current_client, _xlpm.growth_rows, 0 ), 3 ), _xlpm.last_actual * ( 1 + _xlpm.growth_rate ) )} -> 42.8 | W10: 42.8 | X10: 42.8 | Y10: 42.8 | Z10: 42.8 | AA10: 42.8 | AB10: 42.8 | AC10: 42.8 | AD10: 42.8 | AE10: 42.8 | AF10: 42.8 | AG10: 42.8
E11: Client 1 | F11: 2 | G11: USD / kg | J11: 17 | K11: 17 | L11: 17 | M11: 17 | N11: 17 | O11: 17 | P11: 17 | Q11: 17 | R11: 17 | S11: 17 | T11: 17 | U11: 17 | V11: 18.19 | W11: 18.19 | X11: 18.19 | Y11: 18.19 | Z11: 18.19 | AA11: 18.19 | AB11: 18.19 | AC11: 18.19 | AD11: 18.19 | AE11: 18.19 | AF11: 18.19 | AG11: 18.19
E12: Client 1 | F12: 3 | G12: USD / kg | J12: 12.8 | K12: 12.8 | L12: 12.8 | M12: 12.8 | N12: 12.8 | O12: 12.8 | P12: 12.8 | Q12: 12.8 | R12: 12.8 | S12: 12.8 | T12: 12.8 | U12: 12.8 | V12: 13.696 | W12: 13.696 | X12: 13.696 | Y12: 13.696 | Z12: 13.696 | AA12: 13.696 | AB12: 13.696 | AC12: 13.696 | AD12: 13.696 | AE12: 13.696 | AF12: 13.696 | AG12: 13.696
E13: Client 1 | F13: 4 | G13: USD / kg | J13: 10.8 | K13: 10.8 | L13: 10.8 | M13: 10.8 | N13: 10.8 | O13: 10.8 | P13: 10.8 | Q13: 10.8 | R13: 10.8 | S13: 10.8 | T13: 10.8 | U13: 10.8 | V13: 11.556 | W13: 11.556 | X13: 11.556 | Y13: 11.556 | Z13: 11.556 | AA13: 11.556 | AB13: 11.556 | AC13: 11.556 | AD13: 11.556 | AE13: 11.556 | AF13: 11.556 | AG13: 11.556
E14: Client 1 | F14: 5 | G14: USD / kg | J14: 14.9 | K14: 14.9 | L14: 14.9 | M14: 14.9 | N14: 14.9 | O14: 14.9 | P14: 14.9 | Q14: 14.9 | R14: 14.9 | S14: 14.9 | T14: 14.9 | U14: 14.9 | V14: 15.943 | W14: 15.943 | X14: 15.943 | Y14: 15.943 | Z14: 15.943 | AA14: 15.943 | AB14: 15.943 | AC14: 15.943 | AD14: 15.943 | AE14: 15.943 | AF14: 15.943 | AG14: 15.943
E15: Client 2 | F15: 1 | G15: USD / kg | J15: 34 | K15: 34 | L15: 34 | M15: 34 | N15: 34 | O15: 34 | P15: 34 | Q15: 34 | R15: 34 | S15: 34 | T15: 34 | U15: 34 | V15: 36.04 | W15: 36.04 | X15: 36.04 | Y15: 36.04 | Z15: 36.04 | AA15: 36.04 | AB15: 36.04 | AC15: 36.04 | AD15: 36.04 | AE15: 36.04 | AF15: 36.04 | AG15: 36.04
E16: Client 2 | F16: 2 | G16: USD / kg | J16: 16.32 | K16: 16.32 | L16: 16.32 | M16: 16.32 | N16: 16.32 | O16: 16.32 | P16: 16.32 | Q16: 16.32 | R16: 16.32 | S16: 16.32 | T16: 16.32 | U16: 16.32 | V16: 17.2992 | W16: 17.2992 | X16: 17.2992 | Y16: 17.2992 | Z16: 17.2992 | AA16: 17.2992 | AB16: 17.2992 | AC16: 17.2992 | AD16: 17.2992 | AE16: 17.2992 | AF16: 17.2992 | AG16: 17.2992
E17: Client 2 | F17: 3 | G17: USD / kg | J17: 14.21 | K17: 14.21 | L17: 14.21 | M17: 14.21 | N17: 14.21 | O17: 14.21 | P17: 14.21 | Q17: 14.21 | R17: 14.21 | S17: 14.21 | T17: 14.21 | U17: 14.21 | V17: 15.0626 | W17: 15.0626 | X17: 15.0626 | Y17: 15.0626 | Z17: 15.0626 | AA17: 15.0626 | AB17: 15.0626 | AC17: 15.0626 | AD17: 15.0626 | AE17: 15.0626 | AF17: 15.0626 | AG17: 15.0626
E18: Client 2 | F18: 4 | G18: USD / kg | J18: 9.83 | K18: 9.83 | L18: 9.83 | M18: 9.83 | N18: 9.83 | O18: 9.83 | P18: 9.83 | Q18: 9.83 | R18: 9.83 | S18: 9.83 | T18: 9.83 | U18: 9.83 | V18: 10.4198 | W18: 10.4198 | X18: 10.4198 | Y18: 10.4198 | Z18: 10.4198 | AA18: 10.4198 | AB18: 10.4198 | AC18: 10.4198 | AD18: 10.4198 | AE18: 10.4198 | AF18: 10.4198 | AG18: 10.4198
E19: Client 2 | F19: 5 | G19: USD / kg | J19: 14.16 | K19: 14.16 | L19: 14.16 | M19: 14.16 | N19: 14.16 | O19: 14.16 | P19: 14.16 | Q19: 14.16 | R19: 14.16 | S19: 14.16 | T19: 14.16 | U19: 14.16 | V19: 15.0096 | W19: 15.0096 | X19: 15.0096 | Y19: 15.0096 | Z19: 15.0096 | AA19: 15.0096 | AB19: 15.0096 | AC19: 15.0096 | AD19: 15.0096 | AE19: 15.0096 | AF19: 15.0096 | AG19: 15.0096
E20: Client 3 | F20: 1 | G20: USD / kg | J20: 39.6 | K20: 39.6 | L20: 39.6 | M20: 39.6 | N20: 39.6 | O20: 39.6 | P20: 39.6 | Q20: 39.6 | R20: 39.6 | S20: 39.6 | T20: 39.6 | U20: 39.6 | V20: 41.976 | W20: 41.976 | X20: 41.976 | Y20: 41.976 | Z20: 41.976 | AA20: 41.976 | AB20: 41.976 | AC20: 41.976 | AD20: 41.976 | AE20: 41.976 | AF20: 41.976 | AG20: 41.976
E21: Client 3 | F21: 2 | G21: USD / kg | J21: 17.85 | K21: 17.85 | L21: 17.85 | M21: 17.85 | N21: 17.85 | O21: 17.85 | P21: 17.85 | Q21: 17.85 | R21: 17.85 | S21: 17.85 | T21: 17.85 | U21: 17.85 | V21: 18.921 | W21: 18.921 | X21: 18.921 | Y21: 18.921 | Z21: 18.921 | AA21: 18.921 | AB21: 18.921 | AC21: 18.921 | AD21: 18.921 | AE21: 18.921 | AF21: 18.921 | AG21: 18.921
E22: Client 3 | F22: 3 | G22: USD / kg | J22: 14.72 | K22: 14.72 | L22: 14.72 | M22: 14.72 | N22: 14.72 | O22: 14.72 | P22: 14.72 | Q22: 14.72 | R22: 14.72 | S22: 14.72 | T22: 14.72 | U22: 14.72 | V22: 15.6032 | W22: 15.6032 | X22: 15.6032 | Y22: 15.6032 | Z22: 15.6032 | AA22: 15.6032 | AB22: 15.6032 | AC22: 15.6032 | AD22: 15.6032 | AE22: 15.6032 | AF22: 15.6032 | AG22: 15.6032
... E34: Client 5 | F34: 5 | G34: USD / kg | J34: 12.67 | K34: 12.67 | L34: 12.67 | M34: 12.67 | N34: 12.67 | O34: 12.67 | P34: 12.67 | Q34: 12.67 | R34: 12.67 | S34: 12.67 | T34: 12.67 | U34: 12.67 | V34: 13.5569 | W34: 13.5569 | X34: 13.5569 | Y34: 13.5569 | Z34: 13.5569 | AA34: 13.5569 | AB34: 13.5569 | AC34: 13.5569 | AD34: 13.5569 | AE34: 13.5569 | AF34: 13.5569 | AG34: 13.5569
A37: DIRECT COSTS
E39: Client | F39: Product
E40: {=_xlfn.LET( _xlpm.historicals, CaseData!$B$8:$G$307, _xlpm.month, INDEX( _xlpm.historicals,, 1 ), _xlpm.client, "Client " & INDEX( _xlpm.historicals,, 2), _xlpm.product, INDEX( _xlpm.historicals,, 3), _xlpm.volume, INDEX( _xlpm.historicals,, 4 ), _xlpm.price, INDEX( _xlpm.historicals,, 5), _xlfn.TAKE( _xlfn.PIVOTBY( _xlfn.HSTACK( _xlpm.client, _xlpm.product ), _xlpm.month, _xlpm.volume, _xleta.SUM, ,0 ),, 2 ) )}
E41: Client 1 | F41: 1 | G41: USD / kg | J41: {=_xlfn.LET( _xlpm.historicals, CaseData!$B$8:$G$307, _xlpm.month, INDEX(_xlpm.historicals,,1), _xlpm.client, INDEX(_xlpm.historicals,,2), _xlpm.product, INDEX(_xlpm.historicals,,3), _xlpm.volume, INDEX(_xlpm.historicals,,4), _xlpm.costs, INDEX(_xlpm.historicals,,6), _xlfn.DROP( _xlfn.DROP( _xlfn.DROP( _xlfn.PIVOTBY( _xlfn.HSTACK( _xlpm.client, _xlpm.product ), _xlpm.month, _xlpm.costs, _xleta.SUM,,0 ),,2 ),, -1 ), 1) )} -> 25 | K41: 25 | L41: 25 | M41: 25 | N41: 25 | O41: 25 | P41: 25 | Q41: 25 | R41: 25 | S41: 25 | T41: 25 | U41: 25 | V41: {=_xlfn.LET( _xlpm.historicals, CaseData!$B$8:$G$307, _xlpm.month, INDEX(_xlpm.historicals,,1), _xlpm.client, "Client " & INDEX(_xlpm.historicals,,2), _xlpm.product, INDEX(_xlpm.historicals,,3), _xlpm.volume, INDEX(_xlpm.historicals,,4), _xlpm.costs, INDEX(_xlpm.historicals,,6), _xlpm.last_actual, _xlfn.DROP( _xlfn.DROP( _xlfn.DROP( _xlfn.PIVOTBY( _xlfn.HSTACK( _xlpm.client, _xlpm.product ), _xlpm.month, _xlpm.costs, _xleta.SUM,,0 ),,2 ),, -1 ), 1), _xlpm.current_product, _xlfn.DROP( INDEX(_xlfn.ANCHORARRAY( E40),, 2 ), 1 ), _xlpm.growth_table, CaseData!$M$8:$N$12, _xlpm.growth_rows, INDEX( _xlpm.growth_table,, 1 ), _xlpm.growth_rate, INDEX( _xlpm.growth_table, MATCH( _xlpm.current_product, _xlpm.growth_rows, 0 ), 2 ), _xlpm.last_actual * ( 1 + _xlpm.growth_rate ) )} -> 26.75 | W41: 26.75 | X41: 26.75 | Y41: 26.75 | Z41: 26.75 | AA41: 26.75 | AB41: 26.75 | AC41: 26.75 | AD41: 26.75 | AE41: 26.75 | AF41: 26.75 | AG41: 26.75
E42: Client 1 | F42: 2 | G42: USD / kg | J42: 7.31 | K42: 7.31 | L42: 7.31 | M42: 7.31 | N42: 7.31 | O42: 7.31 | P42: 7.31 | Q42: 7.31 | R42: 7.31 | S42: 7.31 | T42: 7.31 | U42: 7.31 | V42: 7.9679 | W42: 7.9679 | X42: 7.9679 | Y42: 7.9679 | Z42: 7.9679 | AA42: 7.9679 | AB42: 7.9679 | AC42: 7.9679 | AD42: 7.9679 | AE42: 7.9679 | AF42: 7.9679 | AG42: 7.9679
E43: Client 1 | F43: 3 | G43: USD / kg | J43: 5.12 | K43: 5.12 | L43: 5.12 | M43: 5.12 | N43: 5.12 | O43: 5.12 | P43: 5.12 | Q43: 5.12 | R43: 5.12 | S43: 5.12 | T43: 5.12 | U43: 5.12 | V43: 5.5296 | W43: 5.5296 | X43: 5.5296 | Y43: 5.5296 | Z43: 5.5296 | AA43: 5.5296 | AB43: 5.5296 | AC43: 5.5296 | AD43: 5.5296 | AE43: 5.5296 | AF43: 5.5296 | AG43: 5.5296
E44: Client 1 | F44: 4 | G44: USD / kg | J44: 6.48 | K44: 6.48 | L44: 6.48 | M44: 6.48 | N44: 6.48 | O44: 6.48 | P44: 6.48 | Q44: 6.48 | R44: 6.48 | S44: 6.48 | T44: 6.48 | U44: 6.48 | V44: 6.9336 | W44: 6.9336 | X44: 6.9336 | Y44: 6.9336 | Z44: 6.9336 | AA44: 6.9336 | AB44: 6.9336 | AC44: 6.9336 | AD44: 6.9336 | AE44: 6.9336 | AF44: 6.9336 | AG44: 6.9336
E45: Client 1 | F45: 5 | G45: USD / kg | J45: 6.26 | K45: 6.26 | L45: 6.26 | M45: 6.26 | N45: 6.26 | O45: 6.26 | P45: 6.26 | Q45: 6.26 | R45: 6.26 | S45: 6.26 | T45: 6.26 | U45: 6.26 | V45: 6.573 | W45: 6.573 | X45: 6.573 | Y45: 6.573 | Z45: 6.573 | AA45: 6.573 | AB45: 6.573 | AC45: 6.573 | AD45: 6.573 | AE45: 6.573 | AF45: 6.573 | AG45: 6.573
E46: Client 2 | F46: 1 | G46: USD / kg | J46: 25 | K46: 25 | L46: 25 | M46: 25 | N46: 25 | O46: 25 | P46: 25 | Q46: 25 | R46: 25 | S46: 25 | T46: 25 | U46: 25 | V46: 26.75 | W46: 26.75 | X46: 26.75 | Y46: 26.75 | Z46: 26.75 | AA46: 26.75 | AB46: 26.75 | AC46: 26.75 | AD46: 26.75 | AE46: 26.75 | AF46: 26.75 | AG46: 26.75
E47: Client 2 | F47: 2 | G47: USD / kg | J47: 7.31 | K47: 7.31 | L47: 7.31 | M47: 7.31 | N47: 7.31 | O47: 7.31 | P47: 7.31 | Q47: 7.31 | R47: 7.31 | S47: 7.31 | T47: 7.31 | U47: 7.31 | V47: 7.9679 | W47: 7.9679 | X47: 7.9679 | Y47: 7.9679 | Z47: 7.9679 | AA47: 7.9679 | AB47: 7.9679 | AC47: 7.9679 | AD47: 7.9679 | AE47: 7.9679 | AF47: 7.9679 | AG47: 7.9679
E48: Client 2 | F48: 3 | G48: USD / kg | J48: 5.12 | K48: 5.12 | L48: 5.12 | M48: 5.12 | N48: 5.12 | O48: 5.12 | P48: 5.12 | Q48: 5.12 | R48: 5.12 | S48: 5.12 | T48: 5.12 | U48: 5.12 | V48: 5.5296 | W48: 5.5296 | X48: 5.5296 | Y48: 5.5296 | Z48: 5.5296 | AA48: 5.5296 | AB48: 5.5296 | AC48: 5.5296 | AD48: 5.5296 | AE48: 5.5296 | AF48: 5.5296 | AG48: 5.5296
E49: Client 2 | F49: 4 | G49: USD / kg | J49: 6.48 | K49: 6.48 | L49: 6.48 | M49: 6.48 | N49: 6.48 | O49: 6.48 | P49: 6.48 | Q49: 6.48 | R49: 6.48 | S49: 6.48 | T49: 6.48 | U49: 6.48 | V49: 6.9336 | W49: 6.9336 | X49: 6.9336 | Y49: 6.9336 | Z49: 6.9336 | AA49: 6.9336 | AB49: 6.9336 | AC49: 6.9336 | AD49: 6.9336 | AE49: 6.9336 | AF49: 6.9336 | AG49: 6.9336
E50: Client 2 | F50: 5 | G50: USD / kg | J50: 6.26 | K50: 6.26 | L50: 6.26 | M50: 6.26 | N50: 6.26 | O50: 6.26 | P50: 6.26 | Q50: 6.26 | R50: 6.26 | S50: 6.26 | T50: 6.26 | U50: 6.26 | V50: 6.573 | W50: 6.573 | X50: 6.573 | Y50: 6.573 | Z50: 6.573 | AA50: 6.573 | AB50: 6.573 | AC50: 6.573 | AD50: 6.573 | AE50: 6.573 | AF50: 6.573 | AG50: 6.573
E51: Client 3 | F51: 1 | G51: USD / kg | J51: 25 | K51: 25 | L51: 25 | M51: 25 | N51: 25 | O51: 25 | P51: 25 | Q51: 25 | R51: 25 | S51: 25 | T51: 25 | U51: 25 | V51: 26.75 | W51: 26.75 | X51: 26.75 | Y51: 26.75 | Z51: 26.75 | AA51: 26.75 | AB51: 26.75 | AC51: 26.75 | AD51: 26.75 | AE51: 26.75 | AF51: 26.75 | AG51: 26.75
E52: Client 3 | F52: 2 | G52: USD / kg | J52: 7.31 | K52: 7.31 | L52: 7.31 | M52: 7.31 | N52: 7.31 | O52: 7.31 | P52: 7.31 | Q52: 7.31 | R52: 7.31 | S52: 7.31 | T52: 7.31 | U52: 7.31 | V52: 7.9679 | W52: 7.9679 | X52: 7.9679 | Y52: 7.9679 | Z52: 7.9679 | AA52: 7.9679 | AB52: 7.9679 | AC52: 7.9679 | AD52: 7.9679 | AE52: 7.9679 | AF52: 7.9679 | AG52: 7.9679
E53: Client 3 | F53: 3 | G53: USD / kg | J53: 5.12 | K53: 5.12 | L53: 5.12 | M53: 5.12 | N53: 5.12 | O53: 5.12 | P53: 5.12 | Q53: 5.12 | R53: 5.12 | S53: 5.12 | T53: 5.12 | U53: 5.12 | V53: 5.5296 | W53: 5.5296 | X53: 5.5296 | Y53: 5.5296 | Z53: 5.5296 | AA53: 5.5296 | AB53: 5.5296 | AC53: 5.5296 | AD53: 5.5296 | AE53: 5.5296 | AF53: 5.5296 | AG53: 5.5296
... E65: Client 5 | F65: 5 | G65: USD / kg | J65: 6.26 | K65: 6.26 | L65: 6.26 | M65: 6.26 | N65: 6.26 | O65: 6.26 | P65: 6.26 | Q65: 6.26 | R65: 6.26 | S65: 6.26 | T65: 6.26 | U65: 6.26 | V65: 6.573 | W65: 6.573 | X65: 6.573 | Y65: 6.573 | Z65: 6.573 | AA65: 6.573 | AB65: 6.573 | AC65: 6.573 | AD65: 6.573 | AE65: 6.573 | AF65: 6.573 | AG65: 6.573
A68: GROSS PROFIT (per kg)
E70: Client | F70: Product
E71: {=_xlfn.LET( _xlpm.historicals, CaseData!$B$8:$G$307, _xlpm.month, INDEX( _xlpm.historicals,, 1 ), _xlpm.client, "Client " & INDEX( _xlpm.historicals,, 2), _xlpm.product, INDEX( _xlpm.historicals,, 3), _xlpm.volume, INDEX( _xlpm.historicals,, 4 ), _xlpm.price, INDEX( _xlpm.historicals,, 5), _xlfn.TAKE( _xlfn.PIVOTBY( _xlfn.HSTACK( _xlpm.client, _xlpm.product ), _xlpm.month, _xlpm.volume, _xleta.SUM, ,0 ),, 2 ) )}
E72: Client 1 | F72: 1 | G72: USD / kg | J72: {=_xlfn.LET( _xlpm.price, _xlfn.HSTACK(_xlfn.ANCHORARRAY( J10),_xlfn.ANCHORARRAY( V10) ), _xlpm.costs, _xlfn.HSTACK(_xlfn.ANCHORARRAY( J41),_xlfn.ANCHORARRAY( V41) ), _xlpm.price - _xlpm.costs )} -> 15 | K72: 15 | L72: 15 | M72: 15 | N72: 15 | O72: 15 | P72: 15 | Q72: 15 | R72: 15 | S72: 15 | T72: 15 | U72: 15 | V72: 16.05 | W72: 16.05 | X72: 16.05 | Y72: 16.05 | Z72: 16.05 | AA72: 16.05 | AB72: 16.05 | AC72: 16.05 | AD72: 16.05 | AE72: 16.05 | AF72: 16.05 | AG72: 16.05
E73: Client 1 | F73: 2 | G73: USD / kg | J73: 9.69 | K73: 9.69 | L73: 9.69 | M73: 9.69 | N73: 9.69 | O73: 9.69 | P73: 9.69 | Q73: 9.69 | R73: 9.69 | S73: 9.69 | T73: 9.69 | U73: 9.69 | V73: 10.2221 | W73: 10.2221 | X73: 10.2221 | Y73: 10.2221 | Z73: 10.2221 | AA73: 10.2221 | AB73: 10.2221 | AC73: 10.2221 | AD73: 10.2221 | AE73: 10.2221 | AF73: 10.2221 | AG73: 10.2221
E74: Client 1 | F74: 3 | G74: USD / kg | J74: 7.68 | K74: 7.68 | L74: 7.68 | M74: 7.68 | N74: 7.68 | O74: 7.68 | P74: 7.68 | Q74: 7.68 | R74: 7.68 | S74: 7.68 | T74: 7.68 | U74: 7.68 | V74: 8.1664 | W74: 8.1664 | X74: 8.1664 | Y74: 8.1664 | Z74: 8.1664 | AA74: 8.1664 | AB74: 8.1664 | AC74: 8.1664 | AD74: 8.1664 | AE74: 8.1664 | AF74: 8.1664 | AG74: 8.1664
E75: Client 1 | F75: 4 | G75: USD / kg | J75: 4.32 | K75: 4.32 | L75: 4.32 | M75: 4.32 | N75: 4.32 | O75: 4.32 | P75: 4.32 | Q75: 4.32 | R75: 4.32 | S75: 4.32 | T75: 4.32 | U75: 4.32 | V75: 4.6224 | W75: 4.6224 | X75: 4.6224 | Y75: 4.6224 | Z75: 4.6224 | AA75: 4.6224 | AB75: 4.6224 | AC75: 4.6224 | AD75: 4.6224 | AE75: 4.6224 | AF75: 4.6224 | AG75: 4.6224
E76: Client 1 | F76: 5 | G76: USD / kg | J76: 8.64 | K76: 8.64 | L76: 8.64 | M76: 8.64 | N76: 8.64 | O76: 8.64 | P76: 8.64 | Q76: 8.64 | R76: 8.64 | S76: 8.64 | T76: 8.64 | U76: 8.64 | V76: 9.37 | W76: 9.37 | X76: 9.37 | Y76: 9.37 | Z76: 9.37 | AA76: 9.37 | AB76: 9.37 | AC76: 9.37 | AD76: 9.37 | AE76: 9.37 | AF76: 9.37 | AG76: 9.37
E77: Client 2 | F77: 1 | G77: USD / kg | J77: 9 | K77: 9 | L77: 9 | M77: 9 | N77: 9 | O77: 9 | P77: 9 | Q77: 9 | R77: 9 | S77: 9 | T77: 9 | U77: 9 | V77: 9.29 | W77: 9.29 | X77: 9.29 | Y77: 9.29 | Z77: 9.29 | AA77: 9.29 | AB77: 9.29 | AC77: 9.29 | AD77: 9.29 | AE77: 9.29 | AF77: 9.29 | AG77: 9.29
E78: Client 2 | F78: 2 | G78: USD / kg | J78: 9.01 | K78: 9.01 | L78: 9.01 | M78: 9.01 | N78: 9.01 | O78: 9.01 | P78: 9.01 | Q78: 9.01 | R78: 9.01 | S78: 9.01 | T78: 9.01 | U78: 9.01 | V78: 9.3313 | W78: 9.3313 | X78: 9.3313 | Y78: 9.3313 | Z78: 9.3313 | AA78: 9.3313 | AB78: 9.3313 | AC78: 9.3313 | AD78: 9.3313 | AE78: 9.3313 | AF78: 9.3313 | AG78: 9.3313
E79: Client 2 | F79: 3 | G79: USD / kg | J79: 9.09 | K79: 9.09 | L79: 9.09 | M79: 9.09 | N79: 9.09 | O79: 9.09 | P79: 9.09 | Q79: 9.09 | R79: 9.09 | S79: 9.09 | T79: 9.09 | U79: 9.09 | V79: 9.533 | W79: 9.533 | X79: 9.533 | Y79: 9.533 | Z79: 9.533 | AA79: 9.533 | AB79: 9.533 | AC79: 9.533 | AD79: 9.533 | AE79: 9.533 | AF79: 9.533 | AG79: 9.533
E80: Client 2 | F80: 4 | G80: USD / kg | J80: 3.35 | K80: 3.35 | L80: 3.35 | M80: 3.35 | N80: 3.35 | O80: 3.35 | P80: 3.35 | Q80: 3.35 | R80: 3.35 | S80: 3.35 | T80: 3.35 | U80: 3.35 | V80: 3.4862 | W80: 3.4862 | X80: 3.4862 | Y80: 3.4862 | Z80: 3.4862 | AA80: 3.4862 | AB80: 3.4862 | AC80: 3.4862 | AD80: 3.4862 | AE80: 3.4862 | AF80: 3.4862 | AG80: 3.4862
E81: Client 2 | F81: 5 | G81: USD / kg | J81: 7.9 | K81: 7.9 | L81: 7.9 | M81: 7.9 | N81: 7.9 | O81: 7.9 | P81: 7.9 | Q81: 7.9 | R81: 7.9 | S81: 7.9 | T81: 7.9 | U81: 7.9 | V81: 8.4366 | W81: 8.4366 | X81: 8.4366 | Y81: 8.4366 | Z81: 8.4366 | AA81: 8.4366 | AB81: 8.4366 | AC81: 8.4366 | AD81: 8.4366 | AE81: 8.4366 | AF81: 8.4366 | AG81: 8.4366
E82: Client 3 | F82: 1 | G82: USD / kg | J82: 14.6 | K82: 14.6 | L82: 14.6 | M82: 14.6 | N82: 14.6 | O82: 14.6 | P82: 14.6 | Q82: 14.6 | R82: 14.6 | S82: 14.6 | T82: 14.6 | U82: 14.6 | V82: 15.226 | W82: 15.226 | X82: 15.226 | Y82: 15.226 | Z82: 15.226 | AA82: 15.226 | AB82: 15.226 | AC82: 15.226 | AD82: 15.226 | AE82: 15.226 | AF82: 15.226 | AG82: 15.226
E83: Client 3 | F83: 2 | G83: USD / kg | J83: 10.54 | K83: 10.54 | L83: 10.54 | M83: 10.54 | N83: 10.54 | O83: 10.54 | P83: 10.54 | Q83: 10.54 | R83: 10.54 | S83: 10.54 | T83: 10.54 | U83: 10.54 | V83: 10.9531 | W83: 10.9531 | X83: 10.9531 | Y83: 10.9531 | Z83: 10.9531 | AA83: 10.9531 | AB83: 10.9531 | AC83: 10.9531 | AD83: 10.9531 | AE83: 10.9531 | AF83: 10.9531 | AG83: 10.9531
E84: Client 3 | F84: 3 | G84: USD / kg | J84: 9.6 | K84: 9.6 | L84: 9.6 | M84: 9.6 | N84: 9.6 | O84: 9.6 | P84: 9.6 | Q84: 9.6 | R84: 9.6 | S84: 9.6 | T84: 9.6 | U84: 9.6 | V84: 10.0736 | W84: 10.0736 | X84: 10.0736 | Y84: 10.0736 | Z84: 10.0736 | AA84: 10.0736 | AB84: 10.0736 | AC84: 10.0736 | AD84: 10.0736 | AE84: 10.0736 | AF84: 10.0736 | AG84: 10.0736
... E96: Client 5 | F96: 5 | G96: USD / kg | J96: 6.41 | K96: 6.41 | L96: 6.41 | M96: 6.41 | N96: 6.41 | O96: 6.41 | P96: 6.41 | Q96: 6.41 | R96: 6.41 | S96: 6.41 | T96: 6.41 | U96: 6.41 | V96: 6.9839 | W96: 6.9839 | X96: 6.9839 | Y96: 6.9839 | Z96: 6.9839 | AA96: 6.9839 | AB96: 6.9839 | AC96: 6.9839 | AD96: 6.9839 | AE96: 6.9839 | AF96: 6.9839 | AG96: 6.9839
A99: RANKING BY GROSS PROFIT
E101: Client | F101: Product
E102: {=_xlfn.LET( _xlpm.historicals, CaseData!$B$8:$G$307, _xlpm.month, INDEX( _xlpm.historicals,, 1 ), _xlpm.client, "Client " & INDEX( _xlpm.historicals,, 2), _xlpm.product, INDEX( _xlpm.historicals,, 3), _xlpm.volume, INDEX( _xlpm.historicals,, 4 ), _xlpm.price, INDEX( _xlpm.historicals,, 5), _xlfn.TAKE( _xlfn.PIVOTBY( _xlfn.HSTACK( _xlpm.client, _xlpm.product ), _xlpm.month, _xlpm.volume, _xleta.SUM, ,0 ),, 2 ) )}
E103: Client 1 | F103: 1 | G103: rank | J103: {=_xlfn.LET( _xlpm.gross_profit,_xlfn.ANCHORARRAY( J72), _xlfn.MAKEARRAY( ROWS( _xlpm.gross_profit ), COLUMNS( _xlpm.gross_profit ), _xlfn.LAMBDA(_xlpm.i,_xlpm.j, _xlfn.RANK.EQ( INDEX( _xlpm.gross_profit, _xlpm.i, _xlpm.j ), INDEX( _xlpm.gross_profit, , _xlpm.j ) ) ) ) )} -> 2 | K103: 2 | L103: 2 | M103: 2 | N103: 2 | O103: 2 | P103: 2 | Q103: 2 | R103: 2 | S103: 2 | T103: 2 | U103: 2 | V103: 2 | W103: 2 | X103: 2 | Y103: 2 | Z103: 2 | AA103: 2 | AB103: 2 | AC103: 2 | AD103: 2 | AE103: 2 | AF103: 2 | AG103: 2
E104: Client 1 | F104: 2 | G104: rank | J104: 7 | K104: 7 | L104: 7 | M104: 7 | N104: 7 | O104: 7 | P104: 7 | Q104: 7 | R104: 7 | S104: 7 | T104: 7 | U104: 7 | V104: 7 | W104: 7 | X104: 7 | Y104: 7 | Z104: 7 | AA104: 7 | AB104: 7 | AC104: 7 | AD104: 7 | AE104: 7 | AF104: 7 | AG104: 7
E105: Client 1 | F105: 3 | G105: rank | J105: 19 | K105: 19 | L105: 19 | M105: 19 | N105: 19 | O105: 19 | P105: 19 | Q105: 19 | R105: 19 | S105: 19 | T105: 19 | U105: 19 | V105: 19 | W105: 19 | X105: 19 | Y105: 19 | Z105: 19 | AA105: 19 | AB105: 19 | AC105: 19 | AD105: 19 | AE105: 19 | AF105: 19 | AG105: 19
E106: Client 1 | F106: 4 | G106: rank | J106: 22 | K106: 22 | L106: 22 | M106: 22 | N106: 22 | O106: 22 | P106: 22 | Q106: 22 | R106: 22 | S106: 22 | T106: 22 | U106: 22 | V106: 22 | W106: 22 | X106: 22 | Y106: 22 | Z106: 22 | AA106: 22 | AB106: 22 | AC106: 22 | AD106: 22 | AE106: 22 | AF106: 22 | AG106: 22
E107: Client 1 | F107: 5 | G107: rank | J107: 13 | K107: 13 | L107: 13 | M107: 13 | N107: 13 | O107: 13 | P107: 13 | Q107: 13 | R107: 13 | S107: 13 | T107: 13 | U107: 13 | V107: 11 | W107: 11 | X107: 11 | Y107: 11 | Z107: 11 | AA107: 11 | AB107: 11 | AC107: 11 | AD107: 11 | AE107: 11 | AF107: 11 | AG107: 11
E108: Client 2 | F108: 1 | G108: rank | J108: 12 | K108: 12 | L108: 12 | M108: 12 | N108: 12 | O108: 12 | P108: 12 | Q108: 12 | R108: 12 | S108: 12 | T108: 12 | U108: 12 | V108: 13 | W108: 13 | X108: 13 | Y108: 13 | Z108: 13 | AA108: 13 | AB108: 13 | AC108: 13 | AD108: 13 | AE108: 13 | AF108: 13 | AG108: 13
E109: Client 2 | F109: 2 | G109: rank | J109: 11 | K109: 11 | L109: 11 | M109: 11 | N109: 11 | O109: 11 | P109: 11 | Q109: 11 | R109: 11 | S109: 11 | T109: 11 | U109: 11 | V109: 12 | W109: 12 | X109: 12 | Y109: 12 | Z109: 12 | AA109: 12 | AB109: 12 | AC109: 12 | AD109: 12 | AE109: 12 | AF109: 12 | AG109: 12
E110: Client 2 | F110: 3 | G110: rank | J110: 10 | K110: 10 | L110: 10 | M110: 10 | N110: 10 | O110: 10 | P110: 10 | Q110: 10 | R110: 10 | S110: 10 | T110: 10 | U110: 10 | V110: 10 | W110: 10 | X110: 10 | Y110: 10 | Z110: 10 | AA110: 10 | AB110: 10 | AC110: 10 | AD110: 10 | AE110: 10 | AF110: 10 | AG110: 10
E111: Client 2 | F111: 4 | G111: rank | J111: 24 | K111: 24 | L111: 24 | M111: 24 | N111: 24 | O111: 24 | P111: 24 | Q111: 24 | R111: 24 | S111: 24 | T111: 24 | U111: 24 | V111: 24 | W111: 24 | X111: 24 | Y111: 24 | Z111: 24 | AA111: 24 | AB111: 24 | AC111: 24 | AD111: 24 | AE111: 24 | AF111: 24 | AG111: 24
E112: Client 2 | F112: 5 | G112: rank | J112: 16 | K112: 16 | L112: 16 | M112: 16 | N112: 16 | O112: 16 | P112: 16 | Q112: 16 | R112: 16 | S112: 16 | T112: 16 | U112: 16 | V112: 17 | W112: 17 | X112: 17 | Y112: 17 | Z112: 17 | AA112: 17 | AB112: 17 | AC112: 17 | AD112: 17 | AE112: 17 | AF112: 17 | AG112: 17
E113: Client 3 | F113: 1 | G113: rank | J113: 3 | K113: 3 | L113: 3 | M113: 3 | N113: 3 | O113: 3 | P113: 3 | Q113: 3 | R113: 3 | S113: 3 | T113: 3 | U113: 3 | V113: 3 | W113: 3 | X113: 3 | Y113: 3 | Z113: 3 | AA113: 3 | AB113: 3 | AC113: 3 | AD113: 3 | AE113: 3 | AF113: 3 | AG113: 3
E114: Client 3 | F114: 2 | G114: rank | J114: 5 | K114: 5 | L114: 5 | M114: 5 | N114: 5 | O114: 5 | P114: 5 | Q114: 5 | R114: 5 | S114: 5 | T114: 5 | U114: 5 | V114: 5 | W114: 5 | X114: 5 | Y114: 5 | Z114: 5 | AA114: 5 | AB114: 5 | AC114: 5 | AD114: 5 | AE114: 5 | AF114: 5 | AG114: 5
E115: Client 3 | F115: 3 | G115: rank | J115: 8 | K115: 8 | L115: 8 | M115: 8 | N115: 8 | O115: 8 | P115: 8 | Q115: 8 | R115: 8 | S115: 8 | T115: 8 | U115: 8 | V115: 8 | W115: 8 | X115: 8 | Y115: 8 | Z115: 8 | AA115: 8 | AB115: 8 | AC115: 8 | AD115: 8 | AE115: 8 | AF115: 8 | AG115: 8
... E127: Client 5 | F127: 5 | G127: rank | J127: 20 | K127: 20 | L127: 20 | M127: 20 | N127: 20 | O127: 20 | P127: 20 | Q127: 20 | R127: 20 | S127: 20 | T127: 20 | U127: 20 | V127: 20 | W127: 20 | X127: 20 | Y127: 20 | Z127: 20 | AA127: 20 | AB127: 20 | AC127: 20 | AD127: 20 | AE127: 20 | AF127: 20 | AG127: 20
A130: VOLUME (unconstrained by factory capacity )
E132: Client | F132: Product
E133: {=_xlfn.LET( _xlpm.historicals, CaseData!$B$8:$G$307, _xlpm.month, INDEX( _xlpm.historicals,, 1 ), _xlpm.client, "Client " & INDEX( _xlpm.historicals,, 2), _xlpm.product, INDEX( _xlpm.historicals,, 3), _xlpm.volume, INDEX( _xlpm.historicals,, 4 ), _xlpm.price, INDEX( _xlpm.historicals,, 5), _xlfn.TAKE( _xlfn.PIVOTBY( _xlfn.HSTACK( _xlpm.client, _xlpm.product ), _xlpm.month, _xlpm.volume, _xleta.SUM, ,0 ),, 2 ) )}
E134: Client 1 | F134: 1 | G134: kg | H134: {=_xlfn.BYROW( _xlfn.HSTACK(_xlfn.ANCHORARRAY( J134),_xlfn.ANCHORARRAY( V134) ), _xleta.SUM )} -> 184300.76 | J134: {=_xlfn.LET( _xlpm.historicals, CaseData!$B$8:$G$307, _xlpm.month, INDEX(_xlpm.historicals,,1), _xlpm.client, INDEX(_xlpm.historicals,,2), _xlpm.product, INDEX(_xlpm.historicals,,3), _xlpm.volume, INDEX(_xlpm.historicals,,4), _xlpm.price, INDEX(_xlpm.historicals,,5), _xlfn.DROP( _xlfn.DROP( _xlfn.DROP( _xlfn.PIVOTBY( _xlfn.HSTACK( _xlpm.client, _xlpm.product ), _xlpm.month, _xlpm.volume, _xleta.SUM,,0 ),,2 ),, -1 ), 1) )} -> 10438 | K134: 4960 | L134: 4960 | M134: 5920 | N134: 4400 | O134: 5120 | P134: 5680 | Q134: 11920 | R134: 10880 | S134: 4560 | T134: 10560 | U134: 11840 | V134: {=_xlfn.LET( _xlpm.historicals, CaseData!$B$8:$G$307, _xlpm.month, INDEX(_xlpm.historicals,,1), _xlpm.client, "Client " & INDEX(_xlpm.historicals,,2), _xlpm.product, INDEX(_xlpm.historicals,,3), _xlpm.volume, INDEX(_xlpm.historicals,,4), _xlpm.price, INDEX(_xlpm.historicals,,5), _xlpm.last_actual, _xlfn.DROP( _xlfn.DROP( _xlfn.DROP( _xlfn.PIVOTBY( _xlfn.HSTACK( _xlpm.client, _xlpm.product ), _xlpm.month, _xlpm.volume, _xleta.SUM,,0 ),,2 ),, -1 ), 1), _xlpm.current_client, _xlfn.DROP( INDEX(_xlfn.ANCHORARRAY( E133),, 1 ), 1 ), _xlpm.growth_table, CaseData!$I$8:$K$12, _xlpm.growth_rows, INDEX( _xlpm.growth_table,, 1 ), _xlpm.growth_rate, INDEX( _xlpm.growth_table, MATCH( _xlpm.current_client, _xlpm.growth_rows, 0 ), 2 ), _xlpm.last_actual * ( 1 + _xlpm.growth_rate ) )} -> 10646.76 | W134: 5059.2 | X134: 5059.2 | Y134: 6038.4 | Z134: 4488 | AA134: 5222.4 | AB134: 5793.6 | AC134: 12158.4 | AD134: 11097.6 | AE134: 4651.2 | AF134: 10771.2 | AG134: 12076.8
E135: Client 1 | F135: 2 | G135: kg | H135: 23553.2 | J135: 516 | K135: 1222 | L135: 1110 | M135: 1084 | N135: 1264 | O135: 606 | P135: 930 | Q135: 760 | R135: 1162 | S135: 1212 | T135: 1076 | U135: 718 | V135: 526.32 | W135: 1246.44 | X135: 1132.2 | Y135: 1105.68 | Z135: 1289.28 | AA135: 618.12 | AB135: 948.6 | AC135: 775.2 | AD135: 1185.24 | AE135: 1236.24 | AF135: 1097.52 | AG135: 732.36
E136: Client 1 | F136: 3 | G136: kg | H136: 527862.36 | J136: 24860 | K136: 28698 | L136: 17784 | M136: 11722 | N136: 30112 | O136: 23444 | P136: 10712 | Q136: 19200 | R136: 24858 | S136: 26274 | T136: 27688 | U136: 15966 | V136: 25357.2 | W136: 29271.96 | X136: 18139.68 | Y136: 11956.44 | Z136: 30714.24 | AA136: 23912.88 | AB136: 10926.24 | AC136: 19584 | AD136: 25355.16 | AE136: 26799.48 | AF136: 28241.76 | AG136: 16285.32
E137: Client 1 | F137: 4 | G137: kg | H137: 624030.52 | J137: 17812 | K137: 28146 | L137: 37804 | M137: 15728 | N137: 25386 | O137: 21248 | P137: 32560 | Q137: 25662 | R137: 23178 | S137: 31734 | T137: 14900 | U137: 34768 | V137: 18168.24 | W137: 28708.92 | X137: 38560.08 | Y137: 16042.56 | Z137: 25893.72 | AA137: 21672.96 | AB137: 33211.2 | AC137: 26175.24 | AD137: 23641.56 | AE137: 32368.68 | AF137: 15198 | AG137: 35463.36
E138: Client 1 | F138: 5 | G138: kg | H138: 298398.44 | J138: 8018 | K138: 19306 | L138: 14088 | M138: 19436 | N138: 8478 | O138: 13566 | P138: 11088 | Q138: 9000 | R138: 10826 | S138: 6914 | T138: 12914 | U138: 14088 | V138: 8178.36 | W138: 19692.12 | X138: 14369.76 | Y138: 19824.72 | Z138: 8647.56 | AA138: 13837.32 | AB138: 11309.76 | AC138: 9180 | AD138: 11042.52 | AE138: 7052.28 | AF138: 13172.28 | AG138: 14369.76
E139: Client 2 | F139: 1 | G139: kg | H139: 70620.72 | J139: 1814 | K139: 2570 | L139: 3470 | M139: 3098 | N139: 4336 | O139: 3066 | P139: 1642 | Q139: 4368 | R139: 1580 | S139: 2540 | T139: 4306 | U139: 1828 | V139: 1886.56 | W139: 2672.8 | X139: 3608.8 | Y139: 3221.92 | Z139: 4509.44 | AA139: 3188.64 | AB139: 1707.68 | AC139: 4542.72 | AD139: 1643.2 | AE139: 2641.6 | AF139: 4478.24 | AG139: 1901.12
E140: Client 2 | F140: 2 | G140: kg | H140: 40950.96 | J140: 1994 | K140: 1480 | L140: 1080 | M140: 1376 | N140: 1080 | O140: 2544 | P140: 1550 | Q140: 2352 | R140: 1672 | S140: 2194 | T140: 1220 | U140: 1532 | V140: 2073.76 | W140: 1539.2 | X140: 1123.2 | Y140: 1431.04 | Z140: 1123.2 | AA140: 2645.76 | AB140: 1612 | AC140: 2446.08 | AD140: 1738.88 | AE140: 2281.76 | AF140: 1268.8 | AG140: 1593.28
E141: Client 2 | F141: 3 | G141: kg | H141: 767896.8 | J141: 32108 | K141: 37392 | L141: 20342 | M141: 42778 | N141: 22136 | O141: 24230 | P141: 24828 | Q141: 36496 | R141: 21838 | S141: 33204 | T141: 41282 | U141: 39786 | V141: 33392.32 | W141: 38887.68 | X141: 21155.68 | Y141: 44489.12 | Z141: 23021.44 | AA141: 25199.2 | AB141: 25821.12 | AC141: 37955.84 | AD141: 22711.52 | AE141: 34532.16 | AF141: 42933.28 | AG141: 41377.44
E142: Client 2 | F142: 4 | G142: kg | H142: 366408.48 | J142: 11892 | K142: 11464 | L142: 10050 | M142: 23556 | N142: 9266 | O142: 16804 | P142: 10050 | Q142: 19002 | R142: 10678 | S142: 17118 | T142: 18374 | U142: 21358 | V142: 12367.68 | W142: 11922.56 | X142: 10452 | Y142: 24498.24 | Z142: 9636.64 | AA142: 17476.16 | AB142: 10452 | AC142: 19762.08 | AD142: 11105.12 | AE142: 17802.72 | AF142: 19108.96 | AG142: 22212.32
E143: Client 2 | F143: 5 | G143: kg | H143: 350178.24 | J143: 16336 | K143: 7382 | L143: 14616 | M143: 14322 | N143: 15354 | O143: 17126 | P143: 16388 | Q143: 15798 | R143: 8564 | S143: 12698 | T143: 11812 | U143: 21260 | V143: 16989.44 | W143: 7677.28 | X143: 15200.64 | Y143: 14894.88 | Z143: 15968.16 | AA143: 17811.04 | AB143: 17043.52 | AC143: 16429.92 | AD143: 8906.56 | AE143: 13205.92 | AF143: 12284.48 | AG143: 22110.4
E144: Client 3 | F144: 1 | G144: kg | H144: 90799 | J144: 3362 | K144: 3144 | L144: 3040 | M144: 5112 | N144: 4248 | O144: 2452 | P144: 4490 | Q144: 3074 | R144: 5182 | S144: 4904 | T144: 1728 | U144: 4214 | V144: 3429.24 | W144: 3206.88 | X144: 3100.8 | Y144: 5214.24 | Z144: 4332.96 | AA144: 2501.04 | AB144: 4579.8 | AC144: 3135.48 | AD144: 5285.64 | AE144: 5002.08 | AF144: 1762.56 | AG144: 4298.28
E145: Client 3 | F145: 2 | G145: kg | H145: 431645.72 | J145: 25506 | K145: 19082 | L145: 24940 | M145: 18516 | N145: 28152 | O145: 17194 | P145: 10202 | Q145: 10202 | R145: 16248 | S145: 19650 | T145: 13036 | U145: 10958 | V145: 26016.12 | W145: 19463.64 | X145: 25438.8 | Y145: 18886.32 | Z145: 28715.04 | AA145: 17537.88 | AB145: 10406.04 | AC145: 10406.04 | AD145: 16572.96 | AE145: 20043 | AF145: 13296.72 | AG145: 11177.16
E146: Client 3 | F146: 3 | G146: kg | H146: 72772.52 | J146: 2890 | K146: 4186 | L146: 3096 | M146: 2564 | N146: 3538 | O146: 3066 | P146: 4274 | Q146: 2034 | R146: 3242 | S146: 1946 | T146: 2536 | U146: 2654 | V146: 2947.8 | W146: 4269.72 | X146: 3157.92 | Y146: 2615.28 | Z146: 3608.76 | AA146: 3127.32 | AB146: 4359.48 | AC146: 2074.68 | AD146: 3306.84 | AE146: 1984.92 | AF146: 2586.72 | AG146: 2707.08
... E158: Client 5 | F158: 5 | G158: kg | H158: 312990.48 | J158: 16734 | K158: 18670 | L158: 10096 | M158: 16458 | N158: 13138 | O158: 15628 | P158: 9404 | Q158: 8022 | R158: 6916 | S158: 8436 | T158: 18532 | U158: 16042 | V158: 16399.32 | W158: 18296.6 | X158: 9894.08 | Y158: 16128.84 | Z158: 12875.24 | AA158: 15315.44 | AB158: 9215.92 | AC158: 7861.56 | AD158: 6777.68 | AE158: 8267.28 | AF158: 18161.36 | AG158: 15721.16
E159: Total volume (unconstrained) | G159: kg | J159: {=_xlfn.BYCOL(_xlfn.ANCHORARRAY( J134), _xleta.SUM )} -> 391222 | K159: 393616 | L159: 377520 | M159: 421306 | N159: 363036 | O159: 335262 | P159: 324318 | Q159: 370798 | R159: 364778 | S159: 419816 | T159: 392906 | U159: 374294 | V159: {=_xlfn.BYCOL(_xlfn.ANCHORARRAY( V134), _xleta.SUM )} -> 399689.42 | W159: 402138.26 | X159: 386370.48 | Y159: 432040.24 | Z159: 371515.7 | AA159: 342723.72 | AB159: 331321.5 | AC159: 380220.86 | AD159: 373488.2 | AE159: 430130.58 | AF159: 401996.66 | AG159: 383765.58
A162: VOLUME (constrained by factory capacity )
E164: Client | F164: Product
E165: {=_xlfn.LET( _xlpm.historicals, CaseData!$B$8:$G$307, _xlpm.month, INDEX( _xlpm.historicals,, 1 ), _xlpm.client, "Client " & INDEX( _xlpm.historicals,, 2), _xlpm.product, INDEX( _xlpm.historicals,, 3), _xlpm.volume, INDEX( _xlpm.historicals,, 4 ), _xlpm.price, INDEX( _xlpm.historicals,, 5), _xlfn.TAKE( _xlfn.PIVOTBY( _xlfn.HSTACK( _xlpm.client, _xlpm.product ), _xlpm.month, _xlpm.volume, _xleta.SUM, ,0 ),, 2 ) )}
E166: Client 1 | F166: 1 | G166: kg | J166: {=_xlfn.LET( _xlpm.historicals, CaseData!$B$8:$G$307, _xlpm.month, INDEX(_xlpm.historicals,,1), _xlpm.client, INDEX(_xlpm.historicals,,2), _xlpm.product, INDEX(_xlpm.historicals,,3), _xlpm.volume, INDEX(_xlpm.historicals,,4), _xlpm.price, INDEX(_xlpm.historicals,,5), _xlfn.DROP( _xlfn.DROP( _xlfn.DROP( _xlfn.PIVOTBY( _xlfn.HSTACK( _xlpm.client, _xlpm.product ), _xlpm.month, _xlpm.volume, _xleta.SUM,,0 ),,2 ),, -1 ), 1) )} -> 10438 | K166: 4960 | L166: 4960 | M166: 5920 | N166: 4400 | O166: 5120 | P166: 5680 | Q166: 11920 | R166: 10880 | S166: 4560 | T166: 10560 | U166: 11840 | V166: {=_xlfn.LET( _xlpm.rank, _xlfn.TAKE(_xlfn.ANCHORARRAY( J103),, -12 ), _xlpm.demand,_xlfn.ANCHORARRAY( V134), _xlpm.capacity, CaseData!$P$7, _xlfn.MAKEARRAY( ROWS(_xlpm.demand), COLUMNS(_xlpm.demand), _xlfn.LAMBDA(_xlpm.i,_xlpm.j, _xlfn.LET( _xlpm.r, INDEX(_xlpm.rank, _xlpm.i, _xlpm.j), _xlpm.rank_column, INDEX(_xlpm.rank, , _xlpm.j), _xlpm.demand_column, INDEX(_xlpm.demand, , _xlpm.j), _xlpm.higher, SUMPRODUCT( (_xlpm.rank_column < _xlpm.r) * _xlpm.demand_column ), MIN( INDEX(_xlpm.demand, _xlpm.i, _xlpm.j), MAX( _xlpm.capacity - _xlpm.higher, 0 ) ) ) ) ) )} -> 10646.76 | W166: 5059.2 | X166: 5059.2 | Y166: 6038.4 | Z166: 4488 | AA166: 5222.4 | AB166: 5793.6 | AC166: 12158.4 | AD166: 11097.6 | AE166: 4651.2 | AF166: 10771.2 | AG166: 12076.8
E167: Client 1 | F167: 2 | G167: kg | J167: 516 | K167: 1222 | L167: 1110 | M167: 1084 | N167: 1264 | O167: 606 | P167: 930 | Q167: 760 | R167: 1162 | S167: 1212 | T167: 1076 | U167: 718 | V167: 526.32 | W167: 1246.44 | X167: 1132.2 | Y167: 1105.68 | Z167: 1289.28 | AA167: 618.12 | AB167: 948.6 | AC167: 775.2 | AD167: 1185.24 | AE167: 1236.24 | AF167: 1097.52 | AG167: 732.36
E168: Client 1 | F168: 3 | G168: kg | J168: 24860 | K168: 28698 | L168: 17784 | M168: 11722 | N168: 30112 | O168: 23444 | P168: 10712 | Q168: 19200 | R168: 24858 | S168: 26274 | T168: 27688 | U168: 15966 | V168: 0 | W168: 0 | X168: 0 | Y168: 0 | Z168: 0 | AA168: 0 | AB168: 0 | AC168: 0 | AD168: 0 | AE168: 0 | AF168: 0 | AG168: 0
E169: Client 1 | F169: 4 | G169: kg | J169: 17812 | K169: 28146 | L169: 37804 | M169: 15728 | N169: 25386 | O169: 21248 | P169: 32560 | Q169: 25662 | R169: 23178 | S169: 31734 | T169: 14900 | U169: 34768 | V169: 0 | W169: 0 | X169: 0 | Y169: 0 | Z169: 0 | AA169: 0 | AB169: 0 | AC169: 0 | AD169: 0 | AE169: 0 | AF169: 0 | AG169: 0
E170: Client 1 | F170: 5 | G170: kg | J170: 8018 | K170: 19306 | L170: 14088 | M170: 19436 | N170: 8478 | O170: 13566 | P170: 11088 | Q170: 9000 | R170: 10826 | S170: 6914 | T170: 12914 | U170: 14088 | V170: 0 | W170: 0 | X170: 0 | Y170: 0 | Z170: 8647.56 | AA170: 13837.32 | AB170: 11309.76 | AC170: 0 | AD170: 0 | AE170: 0 | AF170: 0 | AG170: 0
E171: Client 2 | F171: 1 | G171: kg | J171: 1814 | K171: 2570 | L171: 3470 | M171: 3098 | N171: 4336 | O171: 3066 | P171: 1642 | Q171: 4368 | R171: 1580 | S171: 2540 | T171: 4306 | U171: 1828 | V171: 0 | W171: 0 | X171: 0 | Y171: 0 | Z171: 0 | AA171: 0 | AB171: 1707.68 | AC171: 0 | AD171: 0 | AE171: 0 | AF171: 0 | AG171: 0
E172: Client 2 | F172: 2 | G172: kg | J172: 1994 | K172: 1480 | L172: 1080 | M172: 1376 | N172: 1080 | O172: 2544 | P172: 1550 | Q172: 2352 | R172: 1672 | S172: 2194 | T172: 1220 | U172: 1532 | V172: 0 | W172: 0 | X172: 0 | Y172: 0 | Z172: 588.98 | AA172: 1690.4 | AB172: 1612 | AC172: 0 | AD172: 0 | AE172: 0 | AF172: 0 | AG172: 0
E173: Client 2 | F173: 3 | G173: kg | J173: 32108 | K173: 37392 | L173: 20342 | M173: 42778 | N173: 22136 | O173: 24230 | P173: 24828 | Q173: 36496 | R173: 21838 | S173: 33204 | T173: 41282 | U173: 39786 | V173: 13025.98 | W173: 13640.8 | X173: 5874.04 | Y173: 0 | Z173: 23021.44 | AA173: 25199.2 | AB173: 25821.12 | AC173: 25221.34 | AD173: 11054.32 | AE173: 1744.14 | AF173: 17354.2 | AG173: 32479.5
...

Sheet CaseData
B2: Big Fish Co.
B3: Inputs and Assumptions
B5: Previous Year's Sales Report | I5: Projected Change of Prices and Volumes by Client (y/y) | M5: Projected Direct Cost Increase by Product (y/y) | P5: Maximum Factory Capacity
B6: Month | C6: Client | D6: Product | E6: Volume (Kg) | F6: Sales Price | G6: Direct Costs | I6: Client | J6: Volume | K6: Price | M6: Product | N6: Cost Increase | P6: kg/Month
E7: kg | F7: $/kg | G7: $/kg | J7: % | K7: % | N7: % | P7: 150000
B8: 43496 | C8: 1 | D8: 1 | E8: 10438 | F8: 40 | G8: 25 | I8: Client 1 | J8: 0.02 | K8: 0.07 | M8: 1 | N8: 0.07
B9: 43496 | C9: 1 | D9: 2 | E9: 516 | F9: 17 | G9: 7.31 | I9: Client 2 | J9: 0.04 | K9: 0.06 | M9: 2 | N9: 0.09
B10: 43496 | C10: 1 | D10: 3 | E10: 24860 | F10: 12.8 | G10: 5.12 | I10: Client 3 | J10: 0.02 | K10: 0.06 | M10: 3 | N10: 0.08
B11: 43496 | C11: 1 | D11: 4 | E11: 17812 | F11: 10.8 | G11: 6.48 | I11: Client 4 | J11: 0.05 | K11: 0.08 | M11: 4 | N11: 0.07
B12: 43496 | C12: 1 | D12: 5 | E12: 8018 | F12: 14.9 | G12: 6.26 | I12: Client 5 | J12: -0.02 | K12: 0.07 | M12: 5 | N12: 0.05
B13: 43496 | C13: 2 | D13: 1 | E13: 1814 | F13: 34 | G13: 25
B14: 43496 | C14: 2 | D14: 2 | E14: 1994 | F14: 16.32 | G14: 7.31
B15: 43496 | C15: 2 | D15: 3 | E15: 32108 | F15: 14.21 | G15: 5.12 | I15: Model period start | K15: 43466
B16: 43496 | C16: 2 | D16: 4 | E16: 11892 | F16: 9.83 | G16: 6.48 | I16: Number of periods | K16: 24
B17: 43496 | C17: 2 | D17: 5 | E17: 16336 | F17: 14.16 | G17: 6.26 | I17: Company name | K17: Big Fish Co.
B18: 43496 | C18: 3 | D18: 1 | E18: 3362 | F18: 39.6 | G18: 25
B19: 43496 | C19: 3 | D19: 2 | E19: 25506 | F19: 17.85 | G19: 7.31
B20: 43496 | C20: 3 | D20: 3 | E20: 2890 | F20: 14.72 | G20: 5.12
B21: 43496 | C21: 3 | D21: 4 | E21: 20270 | F21: 10.8 | G21: 6.48
B22: 43496 | C22: 3 | D22: 5 | E22: 19262 | F22: 15.65 | G22: 6.26
B23: 43496 | C23: 4 | D23: 1 | E23: 43200 | F23: 44.4 | G23: 25
B24: 43496 | C24: 4 | D24: 2 | E24: 22290 | F24: 17.17 | G24: 7.31
B25: 43496 | C25: 4 | D25: 3 | E25: 24338 | F25: 13.57 | G25: 5.12
B26: 43496 | C26: 4 | D26: 4 | E26: 552 | F26: 12.42 | G26: 6.48
B27: 43496 | C27: 4 | D27: 5 | E27: 11418 | F27: 14.16 | G27: 6.26
B28: 43496 | C28: 5 | D28: 1 | E28: 5098 | F28: 37.6 | G28: 25
B29: 43496 | C29: 5 | D29: 2 | E29: 36672 | F29: 15.13 | G29: 7.31
... B307: 43830 | C307: 5 | D307: 5 | E307: 16042 | F307: 12.67 | G307: 6.26

Sheet CaseSolution - Calculations
B2: =CaseData!B2 -> Big Fish Co.
B3: Operating Model
D5: Client | E5: Product | G5: Growth | I5: =CaseData!B8 -> 43496 | J5: =EOMONTH(I5,1) -> 43524 | K5: =EOMONTH(J5,1) -> 43555 | L5: =EOMONTH(K5,1) -> 43585 | M5: =EOMONTH(L5,1) -> 43616 | N5: =EOMONTH(M5,1) -> 43646 | O5: =EOMONTH(N5,1) -> 43677 | P5: =EOMONTH(O5,1) -> 43708 | Q5: =EOMONTH(P5,1) -> 43738 | ... AF5: =EOMONTH(AE5,1) -> 44196
B7: Sales Price
D8: =CaseData!C8 -> 1 | E8: =CaseData!D8 -> 1 | G8: =INDEX(CaseData!$K$8:$K$12,MATCH("Client "&$D8,CaseData!$I$8:$I$12,0)) -> 0.07 | I8: =SUMIFS(CaseData!$F$8:$F$307,CaseData!$B$8:$B$307,I$5,CaseData!$C$8:$C$307,$D8,CaseData!$D$8:$D$307,$E8) -> 40 | J8: =SUMIFS(CaseData!$F$8:$F$307,CaseData!$B$8:$B$307,J$5,CaseData!$C$8:$C$307,$D8,CaseData!$D$8:$D$307,$E8) -> 40 | K8: =SUMIFS(CaseData!$F$8:$F$307,CaseData!$B$8:$B$307,K$5,CaseData!$C$8:$C$307,$D8,CaseData!$D$8:$D$307,$E8) -> 40 | L8: =SUMIFS(CaseData!$F$8:$F$307,CaseData!$B$8:$B$307,L$5,CaseData!$C$8:$C$307,$D8,CaseData!$D$8:$D$307,$E8) -> 40 | M8: =SUMIFS(CaseData!$F$8:$F$307,CaseData!$B$8:$B$307,M$5,CaseData!$C$8:$C$307,$D8,CaseData!$D$8:$D$307,$E8) -> 40 | N8: =SUMIFS(CaseData!$F$8:$F$307,CaseData!$B$8:$B$307,N$5,CaseData!$C$8:$C$307,$D8,CaseData!$D$8:$D$307,$E8) -> 40 | O8: =SUMIFS(CaseData!$F$8:$F$307,CaseData!$B$8:$B$307,O$5,CaseData!$C$8:$C$307,$D8,CaseData!$D$8:$D$307,$E8) -> 40 | P8: =SUMIFS(CaseData!$F$8:$F$307,CaseData!$B$8:$B$307,P$5,CaseData!$C$8:$C$307,$D8,CaseData!$D$8:$D$307,$E8) -> 40 | ... T8: =SUMIFS(CaseData!$F$8:$F$307,CaseData!$B$8:$B$307,T$5,CaseData!$C$8:$C$307,$D8,CaseData!$D$8:$D$307,$E8) -> 40 | U8: =I8*(1+$G8) -> 42.8 | V8: =J8*(1+$G8) -> 42.8 | W8: =K8*(1+$G8) -> 42.8 | X8: =L8*(1+$G8) -> 42.8 | Y8: =M8*(1+$G8) -> 42.8 | Z8: =N8*(1+$G8) -> 42.8 | AA8: =O8*(1+$G8) -> 42.8 | AB8: =P8*(1+$G8) -> 42.8 | ... AF8: =T8*(1+$G8) -> 42.8
D9: =CaseData!C9 -> 1 | E9: =CaseData!D9 -> 2 | G9: =INDEX(CaseData!$K$8:$K$12,MATCH("Client "&$D9,CaseData!$I$8:$I$12,0)) -> 0.07 | I9: =SUMIFS(CaseData!$F$8:$F$307,CaseData!$B$8:$B$307,I$5,CaseData!$C$8:$C$307,$D9,CaseData!$D$8:$D$307,$E9) -> 17 | J9: =SUMIFS(CaseData!$F$8:$F$307,CaseData!$B$8:$B$307,J$5,CaseData!$C$8:$C$307,$D9,CaseData!$D$8:$D$307,$E9) -> 17 | K9: =SUMIFS(CaseData!$F$8:$F$307,CaseData!$B$8:$B$307,K$5,CaseData!$C$8:$C$307,$D9,CaseData!$D$8:$D$307,$E9) -> 17 | L9: =SUMIFS(CaseData!$F$8:$F$307,CaseData!$B$8:$B$307,L$5,CaseData!$C$8:$C$307,$D9,CaseData!$D$8:$D$307,$E9) -> 17 | M9: =SUMIFS(CaseData!$F$8:$F$307,CaseData!$B$8:$B$307,M$5,CaseData!$C$8:$C$307,$D9,CaseData!$D$8:$D$307,$E9) -> 17 | N9: =SUMIFS(CaseData!$F$8:$F$307,CaseData!$B$8:$B$307,N$5,CaseData!$C$8:$C$307,$D9,CaseData!$D$8:$D$307,$E9) -> 17 | O9: =SUMIFS(CaseData!$F$8:$F$307,CaseData!$B$8:$B$307,O$5,CaseData!$C$8:$C$307,$D9,CaseData!$D$8:$D$307,$E9) -> 17 | P9: =SUMIFS(CaseData!$F$8:$F$307,CaseData!$B$8:$B$307,P$5,CaseData!$C$8:$C$307,$D9,CaseData!$D$8:$D$307,$E9) -> 17 | ... T9: =SUMIFS(CaseData!$F$8:$F$307,CaseData!$B$8:$B$307,T$5,CaseData!$C$8:$C$307,$D9,CaseData!$D$8:$D$307,$E9) -> 17 | U9: =I9*(1+$G9) -> 18.19 | V9: =J9*(1+$G9) -> 18.19 | W9: =K9*(1+$G9) -> 18.19 | X9: =L9*(1+$G9) -> 18.19 | Y9: =M9*(1+$G9) -> 18.19 | Z9: =N9*(1+$G9) -> 18.19 | AA9: =O9*(1+$G9) -> 18.19 | AB9: =P9*(1+$G9) -> 18.19 | ... AF9: =T9*(1+$G9) -> 18.19
D10: =CaseData!C10 -> 1 | E10: =CaseData!D10 -> 3 | G10: =INDEX(CaseData!$K$8:$K$12,MATCH("Client "&$D10,CaseData!$I$8:$I$12,0)) -> 0.07 | I10: =SUMIFS(CaseData!$F$8:$F$307,CaseData!$B$8:$B$307,I$5,CaseData!$C$8:$C$307,$D10,CaseData!$D$8:$D$307,$E10) -> 12.8 | J10: =SUMIFS(CaseData!$F$8:$F$307,CaseData!$B$8:$B$307,J$5,CaseData!$C$8:$C$307,$D10,CaseData!$D$8:$D$307,$E10) -> 12.8 | K10: =SUMIFS(CaseData!$F$8:$F$307,CaseData!$B$8:$B$307,K$5,CaseData!$C$8:$C$307,$D10,CaseData!$D$8:$D$307,$E10) -> 12.8 | L10: =SUMIFS(CaseData!$F$8:$F$307,CaseData!$B$8:$B$307,L$5,CaseData!$C$8:$C$307,$D10,CaseData!$D$8:$D$307,$E10) -> 12.8 | M10: =SUMIFS(CaseData!$F$8:$F$307,CaseData!$B$8:$B$307,M$5,CaseData!$C$8:$C$307,$D10,CaseData!$D$8:$D$307,$E10) -> 12.8 | N10: =SUMIFS(CaseData!$F$8:$F$307,CaseData!$B$8:$B$307,N$5,CaseData!$C$8:$C$307,$D10,CaseData!$D$8:$D$307,$E10) -> 12.8 | O10: =SUMIFS(CaseData!$F$8:$F$307,CaseData!$B$8:$B$307,O$5,CaseData!$C$8:$C$307,$D10,CaseData!$D$8:$D$307,$E10) -> 12.8 | P10: =SUMIFS(CaseData!$F$8:$F$307,CaseData!$B$8:$B$307,P$5,CaseData!$C$8:$C$307,$D10,CaseData!$D$8:$D$307,$E10) -> 12.8 | ... T10: =SUMIFS(CaseData!$F$8:$F$307,CaseData!$B$8:$B$307,T$5,CaseData!$C$8:$C$307,$D10,CaseData!$D$8:$D$307,$E10) -> 12.8 | U10: =I10*(1+$G10) -> 13.696 | V10: =J10*(1+$G10) -> 13.696 | W10: =K10*(1+$G10) -> 13.696 | X10: =L10*(1+$G10) -> 13.696 | Y10: =M10*(1+$G10) -> 13.696 | Z10: =N10*(1+$G10) -> 13.696 | AA10: =O10*(1+$G10) -> 13.696 | AB10: =P10*(1+$G10) -> 13.696 | ... AF10: =T10*(1+$G10) -> 13.696
D11: =CaseData!C11 -> 1 | E11: =CaseData!D11 -> 4 | G11: =INDEX(CaseData!$K$8:$K$12,MATCH("Client "&$D11,CaseData!$I$8:$I$12,0)) -> 0.07 | I11: =SUMIFS(CaseData!$F$8:$F$307,CaseData!$B$8:$B$307,I$5,CaseData!$C$8:$C$307,$D11,CaseData!$D$8:$D$307,$E11) -> 10.8 | J11: =SUMIFS(CaseData!$F$8:$F$307,CaseData!$B$8:$B$307,J$5,CaseData!$C$8:$C$307,$D11,CaseData!$D$8:$D$307,$E11) -> 10.8 | K11: =SUMIFS(CaseData!$F$8:$F$307,CaseData!$B$8:$B$307,K$5,CaseData!$C$8:$C$307,$D11,CaseData!$D$8:$D$307,$E11) -> 10.8 | L11: =SUMIFS(CaseData!$F$8:$F$307,CaseData!$B$8:$B$307,L$5,CaseData!$C$8:$C$307,$D11,CaseData!$D$8:$D$307,$E11) -> 10.8 | M11: =SUMIFS(CaseData!$F$8:$F$307,CaseData!$B$8:$B$307,M$5,CaseData!$C$8:$C$307,$D11,CaseData!$D$8:$D$307,$E11) -> 10.8 | N11: =SUMIFS(CaseData!$F$8:$F$307,CaseData!$B$8:$B$307,N$5,CaseData!$C$8:$C$307,$D11,CaseData!$D$8:$D$307,$E11) -> 10.8 | O11: =SUMIFS(CaseData!$F$8:$F$307,CaseData!$B$8:$B$307,O$5,CaseData!$C$8:$C$307,$D11,CaseData!$D$8:$D$307,$E11) -> 10.8 | P11: =SUMIFS(CaseData!$F$8:$F$307,CaseData!$B$8:$B$307,P$5,CaseData!$C$8:$C$307,$D11,CaseData!$D$8:$D$307,$E11) -> 10.8 | ... T11: =SUMIFS(CaseData!$F$8:$F$307,CaseData!$B$8:$B$307,T$5,CaseData!$C$8:$C$307,$D11,CaseData!$D$8:$D$307,$E11) -> 10.8 | U11: =I11*(1+$G11) -> 11.556 | V11: =J11*(1+$G11) -> 11.556 | W11: =K11*(1+$G11) -> 11.556 | X11: =L11*(1+$G11) -> 11.556 | Y11: =M11*(1+$G11) -> 11.556 | Z11: =N11*(1+$G11) -> 11.556 | AA11: =O11*(1+$G11) -> 11.556 | AB11: =P11*(1+$G11) -> 11.556 | ... AF11: =T11*(1+$G11) -> 11.556
D12: =CaseData!C12 -> 1 | E12: =CaseData!D12 -> 5 | G12: =INDEX(CaseData!$K$8:$K$12,MATCH("Client "&$D12,CaseData!$I$8:$I$12,0)) -> 0.07 | I12: =SUMIFS(CaseData!$F$8:$F$307,CaseData!$B$8:$B$307,I$5,CaseData!$C$8:$C$307,$D12,CaseData!$D$8:$D$307,$E12) -> 14.9 | J12: =SUMIFS(CaseData!$F$8:$F$307,CaseData!$B$8:$B$307,J$5,CaseData!$C$8:$C$307,$D12,CaseData!$D$8:$D$307,$E12) -> 14.9 | K12: =SUMIFS(CaseData!$F$8:$F$307,CaseData!$B$8:$B$307,K$5,CaseData!$C$8:$C$307,$D12,CaseData!$D$8:$D$307,$E12) -> 14.9 | L12: =SUMIFS(CaseData!$F$8:$F$307,CaseData!$B$8:$B$307,L$5,CaseData!$C$8:$C$307,$D12,CaseData!$D$8:$D$307,$E12) -> 14.9 | M12: =SUMIFS(CaseData!$F$8:$F$307,CaseData!$B$8:$B$307,M$5,CaseData!$C$8:$C$307,$D12,CaseData!$D$8:$D$307,$E12) -> 14.9 | N12: =SUMIFS(CaseData!$F$8:$F$307,CaseData!$B$8:$B$307,N$5,CaseData!$C$8:$C$307,$D12,CaseData!$D$8:$D$307,$E12) -> 14.9 | O12: =SUMIFS(CaseData!$F$8:$F$307,CaseData!$B$8:$B$307,O$5,CaseData!$C$8:$C$307,$D12,CaseData!$D$8:$D$307,$E12) -> 14.9 | P12: =SUMIFS(CaseData!$F$8:$F$307,CaseData!$B$8:$B$307,P$5,CaseData!$C$8:$C$307,$D12,CaseData!$D$8:$D$307,$E12) -> 14.9 | ... T12: =SUMIFS(CaseData!$F$8:$F$307,CaseData!$B$8:$B$307,T$5,CaseData!$C$8:$C$307,$D12,CaseData!$D$8:$D$307,$E12) -> 14.9 | U12: =I12*(1+$G12) -> 15.943 | V12: =J12*(1+$G12) -> 15.943 | W12: =K12*(1+$G12) -> 15.943 | X12: =L12*(1+$G12) -> 15.943 | Y12: =M12*(1+$G12) -> 15.943 | Z12: =N12*(1+$G12) -> 15.943 | AA12: =O12*(1+$G12) -> 15.943 | AB12: =P12*(1+$G12) -> 15.943 | ... AF12: =T12*(1+$G12) -> 15.943
D13: =CaseData!C13 -> 2 | E13: =CaseData!D13 -> 1 | G13: =INDEX(CaseData!$K$8:$K$12,MATCH("Client "&$D13,CaseData!$I$8:$I$12,0)) -> 0.06 | I13: =SUMIFS(CaseData!$F$8:$F$307,CaseData!$B$8:$B$307,I$5,CaseData!$C$8:$C$307,$D13,CaseData!$D$8:$D$307,$E13) -> 34 | J13: =SUMIFS(CaseData!$F$8:$F$307,CaseData!$B$8:$B$307,J$5,CaseData!$C$8:$C$307,$D13,CaseData!$D$8:$D$307,$E13) -> 34 | K13: =SUMIFS(CaseData!$F$8:$F$307,CaseData!$B$8:$B$307,K$5,CaseData!$C$8:$C$307,$D13,CaseData!$D$8:$D$307,$E13) -> 34 | L13: =SUMIFS(CaseData!$F$8:$F$307,CaseData!$B$8:$B$307,L$5,CaseData!$C$8:$C$307,$D13,CaseData!$D$8:$D$307,$E13) -> 34 | M13: =SUMIFS(CaseData!$F$8:$F$307,CaseData!$B$8:$B$307,M$5,CaseData!$C$8:$C$307,$D13,CaseData!$D$8:$D$307,$E13) -> 34 | N13: =SUMIFS(CaseData!$F$8:$F$307,CaseData!$B$8:$B$307,N$5,CaseData!$C$8:$C$307,$D13,CaseData!$D$8:$D$307,$E13) -> 34 | O13: =SUMIFS(CaseData!$F$8:$F$307,CaseData!$B$8:$B$307,O$5,CaseData!$C$8:$C$307,$D13,CaseData!$D$8:$D$307,$E13) -> 34 | P13: =SUMIFS(CaseData!$F$8:$F$307,CaseData!$B$8:$B$307,P$5,CaseData!$C$8:$C$307,$D13,CaseData!$D$8:$D$307,$E13) -> 34 | ... T13: =SUMIFS(CaseData!$F$8:$F$307,CaseData!$B$8:$B$307,T$5,CaseData!$C$8:$C$307,$D13,CaseData!$D$8:$D$307,$E13) -> 34 | U13: =I13*(1+$G13) -> 36.04 | V13: =J13*(1+$G13) -> 36.04 | W13: =K13*(1+$G13) -> 36.04 | X13: =L13*(1+$G13) -> 36.04 | Y13: =M13*(1+$G13) -> 36.04 | Z13: =N13*(1+$G13) -> 36.04 | AA13: =O13*(1+$G13) -> 36.04 | AB13: =P13*(1+$G13) -> 36.04 | ... AF13: =T13*(1+$G13) -> 36.04
D14: =CaseData!C14 -> 2 | E14: =CaseData!D14 -> 2 | G14: =INDEX(CaseData!$K$8:$K$12,MATCH("Client "&$D14,CaseData!$I$8:$I$12,0)) -> 0.06 | I14: =SUMIFS(CaseData!$F$8:$F$307,CaseData!$B$8:$B$307,I$5,CaseData!$C$8:$C$307,$D14,CaseData!$D$8:$D$307,$E14) -> 16.32 | J14: =SUMIFS(CaseData!$F$8:$F$307,CaseData!$B$8:$B$307,J$5,CaseData!$C$8:$C$307,$D14,CaseData!$D$8:$D$307,$E14) -> 16.32 | K14: =SUMIFS(CaseData!$F$8:$F$307,CaseData!$B$8:$B$307,K$5,CaseData!$C$8:$C$307,$D14,CaseData!$D$8:$D$307,$E14) -> 16.32 | L14: =SUMIFS(CaseData!$F$8:$F$307,CaseData!$B$8:$B$307,L$5,CaseData!$C$8:$C$307,$D14,CaseData!$D$8:$D$307,$E14) -> 16.32 | M14: =SUMIFS(CaseData!$F$8:$F$307,CaseData!$B$8:$B$307,M$5,CaseData!$C$8:$C$307,$D14,CaseData!$D$8:$D$307,$E14) -> 16.32 | N14: =SUMIFS(CaseData!$F$8:$F$307,CaseData!$B$8:$B$307,N$5,CaseData!$C$8:$C$307,$D14,CaseData!$D$8:$D$307,$E14) -> 16.32 | O14: =SUMIFS(CaseData!$F$8:$F$307,CaseData!$B$8:$B$307,O$5,CaseData!$C$8:$C$307,$D14,CaseData!$D$8:$D$307,$E14) -> 16.32 | P14: =SUMIFS(CaseData!$F$8:$F$307,CaseData!$B$8:$B$307,P$5,CaseData!$C$8:$C$307,$D14,CaseData!$D$8:$D$307,$E14) -> 16.32 | ... T14: =SUMIFS(CaseData!$F$8:$F$307,CaseData!$B$8:$B$307,T$5,CaseData!$C$8:$C$307,$D14,CaseData!$D$8:$D$307,$E14) -> 16.32 | U14: =I14*(1+$G14) -> 17.2992 | V14: =J14*(1+$G14) -> 17.2992 | W14: =K14*(1+$G14) -> 17.2992 | X14: =L14*(1+$G14) -> 17.2992 | Y14: =M14*(1+$G14) -> 17.2992 | Z14: =N14*(1+$G14) -> 17.2992 | AA14: =O14*(1+$G14) -> 17.2992 | AB14: =P14*(1+$G14) -> 17.2992 | ... AF14: =T14*(1+$G14) -> 17.2992
D15: =CaseData!C15 -> 2 | E15: =CaseData!D15 -> 3 | G15: =INDEX(CaseData!$K$8:$K$12,MATCH("Client "&$D15,CaseData!$I$8:$I$12,0)) -> 0.06 | I15: =SUMIFS(CaseData!$F$8:$F$307,CaseData!$B$8:$B$307,I$5,CaseData!$C$8:$C$307,$D15,CaseData!$D$8:$D$307,$E15) -> 14.21 | J15: =SUMIFS(CaseData!$F$8:$F$307,CaseData!$B$8:$B$307,J$5,CaseData!$C$8:$C$307,$D15,CaseData!$D$8:$D$307,$E15) -> 14.21 | K15: =SUMIFS(CaseData!$F$8:$F$307,CaseData!$B$8:$B$307,K$5,CaseData!$C$8:$C$307,$D15,CaseData!$D$8:$D$307,$E15) -> 14.21 | L15: =SUMIFS(CaseData!$F$8:$F$307,CaseData!$B$8:$B$307,L$5,CaseData!$C$8:$C$307,$D15,CaseData!$D$8:$D$307,$E15) -> 14.21 | M15: =SUMIFS(CaseData!$F$8:$F$307,CaseData!$B$8:$B$307,M$5,CaseData!$C$8:$C$307,$D15,CaseData!$D$8:$D$307,$E15) -> 14.21 | N15: =SUMIFS(CaseData!$F$8:$F$307,CaseData!$B$8:$B$307,N$5,CaseData!$C$8:$C$307,$D15,CaseData!$D$8:$D$307,$E15) -> 14.21 | O15: =SUMIFS(CaseData!$F$8:$F$307,CaseData!$B$8:$B$307,O$5,CaseData!$C$8:$C$307,$D15,CaseData!$D$8:$D$307,$E15) -> 14.21 | P15: =SUMIFS(CaseData!$F$8:$F$307,CaseData!$B$8:$B$307,P$5,CaseData!$C$8:$C$307,$D15,CaseData!$D$8:$D$307,$E15) -> 14.21 | ... T15: =SUMIFS(CaseData!$F$8:$F$307,CaseData!$B$8:$B$307,T$5,CaseData!$C$8:$C$307,$D15,CaseData!$D$8:$D$307,$E15) -> 14.21 | U15: =I15*(1+$G15) -> 15.0626 | V15: =J15*(1+$G15) -> 15.0626 | W15: =K15*(1+$G15) -> 15.0626 | X15: =L15*(1+$G15) -> 15.0626 | Y15: =M15*(1+$G15) -> 15.0626 | Z15: =N15*(1+$G15) -> 15.0626 | AA15: =O15*(1+$G15) -> 15.0626 | AB15: =P15*(1+$G15) -> 15.0626 | ... AF15: =T15*(1+$G15) -> 15.0626
D16: =CaseData!C16 -> 2 | E16: =CaseData!D16 -> 4 | G16: =INDEX(CaseData!$K$8:$K$12,MATCH("Client "&$D16,CaseData!$I$8:$I$12,0)) -> 0.06 | I16: =SUMIFS(CaseData!$F$8:$F$307,CaseData!$B$8:$B$307,I$5,CaseData!$C$8:$C$307,$D16,CaseData!$D$8:$D$307,$E16) -> 9.83 | J16: =SUMIFS(CaseData!$F$8:$F$307,CaseData!$B$8:$B$307,J$5,CaseData!$C$8:$C$307,$D16,CaseData!$D$8:$D$307,$E16) -> 9.83 | K16: =SUMIFS(CaseData!$F$8:$F$307,CaseData!$B$8:$B$307,K$5,CaseData!$C$8:$C$307,$D16,CaseData!$D$8:$D$307,$E16) -> 9.83 | L16: =SUMIFS(CaseData!$F$8:$F$307,CaseData!$B$8:$B$307,L$5,CaseData!$C$8:$C$307,$D16,CaseData!$D$8:$D$307,$E16) -> 9.83 | M16: =SUMIFS(CaseData!$F$8:$F$307,CaseData!$B$8:$B$307,M$5,CaseData!$C$8:$C$307,$D16,CaseData!$D$8:$D$307,$E16) -> 9.83 | N16: =SUMIFS(CaseData!$F$8:$F$307,CaseData!$B$8:$B$307,N$5,CaseData!$C$8:$C$307,$D16,CaseData!$D$8:$D$307,$E16) -> 9.83 | O16: =SUMIFS(CaseData!$F$8:$F$307,CaseData!$B$8:$B$307,O$5,CaseData!$C$8:$C$307,$D16,CaseData!$D$8:$D$307,$E16) -> 9.83 | P16: =SUMIFS(CaseData!$F$8:$F$307,CaseData!$B$8:$B$307,P$5,CaseData!$C$8:$C$307,$D16,CaseData!$D$8:$D$307,$E16) -> 9.83 | ... T16: =SUMIFS(CaseData!$F$8:$F$307,CaseData!$B$8:$B$307,T$5,CaseData!$C$8:$C$307,$D16,CaseData!$D$8:$D$307,$E16) -> 9.83 | U16: =I16*(1+$G16) -> 10.4198 | V16: =J16*(1+$G16) -> 10.4198 | W16: =K16*(1+$G16) -> 10.4198 | X16: =L16*(1+$G16) -> 10.4198 | Y16: =M16*(1+$G16) -> 10.4198 | Z16: =N16*(1+$G16) -> 10.4198 | AA16: =O16*(1+$G16) -> 10.4198 | AB16: =P16*(1+$G16) -> 10.4198 | ... AF16: =T16*(1+$G16) -> 10.4198
D17: =CaseData!C17 -> 2 | E17: =CaseData!D17 -> 5 | G17: =INDEX(CaseData!$K$8:$K$12,MATCH("Client "&$D17,CaseData!$I$8:$I$12,0)) -> 0.06 | I17: =SUMIFS(CaseData!$F$8:$F$307,CaseData!$B$8:$B$307,I$5,CaseData!$C$8:$C$307,$D17,CaseData!$D$8:$D$307,$E17) -> 14.16 | J17: =SUMIFS(CaseData!$F$8:$F$307,CaseData!$B$8:$B$307,J$5,CaseData!$C$8:$C$307,$D17,CaseData!$D$8:$D$307,$E17) -> 14.16 | K17: =SUMIFS(CaseData!$F$8:$F$307,CaseData!$B$8:$B$307,K$5,CaseData!$C$8:$C$307,$D17,CaseData!$D$8:$D$307,$E17) -> 14.16 | L17: =SUMIFS(CaseData!$F$8:$F$307,CaseData!$B$8:$B$307,L$5,CaseData!$C$8:$C$307,$D17,CaseData!$D$8:$D$307,$E17) -> 14.16 | M17: =SUMIFS(CaseData!$F$8:$F$307,CaseData!$B$8:$B$307,M$5,CaseData!$C$8:$C$307,$D17,CaseData!$D$8:$D$307,$E17) -> 14.16 | N17: =SUMIFS(CaseData!$F$8:$F$307,CaseData!$B$8:$B$307,N$5,CaseData!$C$8:$C$307,$D17,CaseData!$D$8:$D$307,$E17) -> 14.16 | O17: =SUMIFS(CaseData!$F$8:$F$307,CaseData!$B$8:$B$307,O$5,CaseData!$C$8:$C$307,$D17,CaseData!$D$8:$D$307,$E17) -> 14.16 | P17: =SUMIFS(CaseData!$F$8:$F$307,CaseData!$B$8:$B$307,P$5,CaseData!$C$8:$C$307,$D17,CaseData!$D$8:$D$307,$E17) -> 14.16 | ... T17: =SUMIFS(CaseData!$F$8:$F$307,CaseData!$B$8:$B$307,T$5,CaseData!$C$8:$C$307,$D17,CaseData!$D$8:$D$307,$E17) -> 14.16 | U17: =I17*(1+$G17) -> 15.0096 | V17: =J17*(1+$G17) -> 15.0096 | W17: =K17*(1+$G17) -> 15.0096 | X17: =L17*(1+$G17) -> 15.0096 | Y17: =M17*(1+$G17) -> 15.0096 | Z17: =N17*(1+$G17) -> 15.0096 | AA17: =O17*(1+$G17) -> 15.0096 | AB17: =P17*(1+$G17) -> 15.0096 | ... AF17: =T17*(1+$G17) -> 15.0096
D18: =CaseData!C18 -> 3 | E18: =CaseData!D18 -> 1 | G18: =INDEX(CaseData!$K$8:$K$12,MATCH("Client "&$D18,CaseData!$I$8:$I$12,0)) -> 0.06 | I18: =SUMIFS(CaseData!$F$8:$F$307,CaseData!$B$8:$B$307,I$5,CaseData!$C$8:$C$307,$D18,CaseData!$D$8:$D$307,$E18) -> 39.6 | J18: =SUMIFS(CaseData!$F$8:$F$307,CaseData!$B$8:$B$307,J$5,CaseData!$C$8:$C$307,$D18,CaseData!$D$8:$D$307,$E18) -> 39.6 | K18: =SUMIFS(CaseData!$F$8:$F$307,CaseData!$B$8:$B$307,K$5,CaseData!$C$8:$C$307,$D18,CaseData!$D$8:$D$307,$E18) -> 39.6 | L18: =SUMIFS(CaseData!$F$8:$F$307,CaseData!$B$8:$B$307,L$5,CaseData!$C$8:$C$307,$D18,CaseData!$D$8:$D$307,$E18) -> 39.6 | M18: =SUMIFS(CaseData!$F$8:$F$307,CaseData!$B$8:$B$307,M$5,CaseData!$C$8:$C$307,$D18,CaseData!$D$8:$D$307,$E18) -> 39.6 | N18: =SUMIFS(CaseData!$F$8:$F$307,CaseData!$B$8:$B$307,N$5,CaseData!$C$8:$C$307,$D18,CaseData!$D$8:$D$307,$E18) -> 39.6 | O18: =SUMIFS(CaseData!$F$8:$F$307,CaseData!$B$8:$B$307,O$5,CaseData!$C$8:$C$307,$D18,CaseData!$D$8:$D$307,$E18) -> 39.6 | P18: =SUMIFS(CaseData!$F$8:$F$307,CaseData!$B$8:$B$307,P$5,CaseData!$C$8:$C$307,$D18,CaseData!$D$8:$D$307,$E18) -> 39.6 | ... T18: =SUMIFS(CaseData!$F$8:$F$307,CaseData!$B$8:$B$307,T$5,CaseData!$C$8:$C$307,$D18,CaseData!$D$8:$D$307,$E18) -> 39.6 | U18: =I18*(1+$G18) -> 41.976 | V18: =J18*(1+$G18) -> 41.976 | W18: =K18*(1+$G18) -> 41.976 | X18: =L18*(1+$G18) -> 41.976 | Y18: =M18*(1+$G18) -> 41.976 | Z18: =N18*(1+$G18) -> 41.976 | AA18: =O18*(1+$G18) -> 41.976 | AB18: =P18*(1+$G18) -> 41.976 | ... AF18: =T18*(1+$G18) -> 41.976
D19: =CaseData!C19 -> 3 | E19: =CaseData!D19 -> 2 | G19: =INDEX(CaseData!$K$8:$K$12,MATCH("Client "&$D19,CaseData!$I$8:$I$12,0)) -> 0.06 | I19: =SUMIFS(CaseData!$F$8:$F$307,CaseData!$B$8:$B$307,I$5,CaseData!$C$8:$C$307,$D19,CaseData!$D$8:$D$307,$E19) -> 17.85 | J19: =SUMIFS(CaseData!$F$8:$F$307,CaseData!$B$8:$B$307,J$5,CaseData!$C$8:$C$307,$D19,CaseData!$D$8:$D$307,$E19) -> 17.85 | K19: =SUMIFS(CaseData!$F$8:$F$307,CaseData!$B$8:$B$307,K$5,CaseData!$C$8:$C$307,$D19,CaseData!$D$8:$D$307,$E19) -> 17.85 | L19: =SUMIFS(CaseData!$F$8:$F$307,CaseData!$B$8:$B$307,L$5,CaseData!$C$8:$C$307,$D19,CaseData!$D$8:$D$307,$E19) -> 17.85 | M19: =SUMIFS(CaseData!$F$8:$F$307,CaseData!$B$8:$B$307,M$5,CaseData!$C$8:$C$307,$D19,CaseData!$D$8:$D$307,$E19) -> 17.85 | N19: =SUMIFS(CaseData!$F$8:$F$307,CaseData!$B$8:$B$307,N$5,CaseData!$C$8:$C$307,$D19,CaseData!$D$8:$D$307,$E19) -> 17.85 | O19: =SUMIFS(CaseData!$F$8:$F$307,CaseData!$B$8:$B$307,O$5,CaseData!$C$8:$C$307,$D19,CaseData!$D$8:$D$307,$E19) -> 17.85 | P19: =SUMIFS(CaseData!$F$8:$F$307,CaseData!$B$8:$B$307,P$5,CaseData!$C$8:$C$307,$D19,CaseData!$D$8:$D$307,$E19) -> 17.85 | ... T19: =SUMIFS(CaseData!$F$8:$F$307,CaseData!$B$8:$B$307,T$5,CaseData!$C$8:$C$307,$D19,CaseData!$D$8:$D$307,$E19) -> 17.85 | U19: =I19*(1+$G19) -> 18.921 | V19: =J19*(1+$G19) -> 18.921 | W19: =K19*(1+$G19) -> 18.921 | X19: =L19*(1+$G19) -> 18.921 | Y19: =M19*(1+$G19) -> 18.921 | Z19: =N19*(1+$G19) -> 18.921 | AA19: =O19*(1+$G19) -> 18.921 | AB19: =P19*(1+$G19) -> 18.921 | ... AF19: =T19*(1+$G19) -> 18.921
... D32: =CaseData!C32 -> 5 | E32: =CaseData!D32 -> 5 | G32: =INDEX(CaseData!$K$8:$K$12,MATCH("Client "&$D32,CaseData!$I$8:$I$12,0)) -> 0.07 | I32: =SUMIFS(CaseData!$F$8:$F$307,CaseData!$B$8:$B$307,I$5,CaseData!$C$8:$C$307,$D32,CaseData!$D$8:$D$307,$E32) -> 12.67 | J32: =SUMIFS(CaseData!$F$8:$F$307,CaseData!$B$8:$B$307,J$5,CaseData!$C$8:$C$307,$D32,CaseData!$D$8:$D$307,$E32) -> 12.67 | K32: =SUMIFS(CaseData!$F$8:$F$307,CaseData!$B$8:$B$307,K$5,CaseData!$C$8:$C$307,$D32,CaseData!$D$8:$D$307,$E32) -> 12.67 | L32: =SUMIFS(CaseData!$F$8:$F$307,CaseData!$B$8:$B$307,L$5,CaseData!$C$8:$C$307,$D32,CaseData!$D$8:$D$307,$E32) -> 12.67 | M32: =SUMIFS(CaseData!$F$8:$F$307,CaseData!$B$8:$B$307,M$5,CaseData!$C$8:$C$307,$D32,CaseData!$D$8:$D$307,$E32) -> 12.67 | N32: =SUMIFS(CaseData!$F$8:$F$307,CaseData!$B$8:$B$307,N$5,CaseData!$C$8:$C$307,$D32,CaseData!$D$8:$D$307,$E32) -> 12.67 | O32: =SUMIFS(CaseData!$F$8:$F$307,CaseData!$B$8:$B$307,O$5,CaseData!$C$8:$C$307,$D32,CaseData!$D$8:$D$307,$E32) -> 12.67 | P32: =SUMIFS(CaseData!$F$8:$F$307,CaseData!$B$8:$B$307,P$5,CaseData!$C$8:$C$307,$D32,CaseData!$D$8:$D$307,$E32) -> 12.67 | ... T32: =SUMIFS(CaseData!$F$8:$F$307,CaseData!$B$8:$B$307,T$5,CaseData!$C$8:$C$307,$D32,CaseData!$D$8:$D$307,$E32) -> 12.67 | U32: =I32*(1+$G32) -> 13.5569 | V32: =J32*(1+$G32) -> 13.5569 | W32: =K32*(1+$G32) -> 13.5569 | X32: =L32*(1+$G32) -> 13.5569 | Y32: =M32*(1+$G32) -> 13.5569 | Z32: =N32*(1+$G32) -> 13.5569 | AA32: =O32*(1+$G32) -> 13.5569 | AB32: =P32*(1+$G32) -> 13.5569 | ... AF32: =T32*(1+$G32) -> 13.5569
B34: Direct Cost per unit
D35: =D$8 -> 1 | E35: =E$8 -> 1 | G35: =INDEX(CaseData!$N$8:$N$12,MATCH($E35,CaseData!$M$8:$M$12,0)) -> 0.07 | I35: =SUMIFS(CaseData!$G$8:$G$307,CaseData!$B$8:$B$307,I$5,CaseData!$C$8:$C$307,$D35,CaseData!$D$8:$D$307,$E35) -> 25 | J35: =SUMIFS(CaseData!$G$8:$G$307,CaseData!$B$8:$B$307,J$5,CaseData!$C$8:$C$307,$D35,CaseData!$D$8:$D$307,$E35) -> 25 | K35: =SUMIFS(CaseData!$G$8:$G$307,CaseData!$B$8:$B$307,K$5,CaseData!$C$8:$C$307,$D35,CaseData!$D$8:$D$307,$E35) -> 25 | L35: =SUMIFS(CaseData!$G$8:$G$307,CaseData!$B$8:$B$307,L$5,CaseData!$C$8:$C$307,$D35,CaseData!$D$8:$D$307,$E35) -> 25 | M35: =SUMIFS(CaseData!$G$8:$G$307,CaseData!$B$8:$B$307,M$5,CaseData!$C$8:$C$307,$D35,CaseData!$D$8:$D$307,$E35) -> 25 | N35: =SUMIFS(CaseData!$G$8:$G$307,CaseData!$B$8:$B$307,N$5,CaseData!$C$8:$C$307,$D35,CaseData!$D$8:$D$307,$E35) -> 25 | O35: =SUMIFS(CaseData!$G$8:$G$307,CaseData!$B$8:$B$307,O$5,CaseData!$C$8:$C$307,$D35,CaseData!$D$8:$D$307,$E35) -> 25 | P35: =SUMIFS(CaseData!$G$8:$G$307,CaseData!$B$8:$B$307,P$5,CaseData!$C$8:$C$307,$D35,CaseData!$D$8:$D$307,$E35) -> 25 | ... T35: =SUMIFS(CaseData!$G$8:$G$307,CaseData!$B$8:$B$307,T$5,CaseData!$C$8:$C$307,$D35,CaseData!$D$8:$D$307,$E35) -> 25 | U35: =I35*(1+$G35) -> 26.75 | V35: =J35*(1+$G35) -> 26.75 | W35: =K35*(1+$G35) -> 26.75 | X35: =L35*(1+$G35) -> 26.75 | Y35: =M35*(1+$G35) -> 26.75 | Z35: =N35*(1+$G35) -> 26.75 | AA35: =O35*(1+$G35) -> 26.75 | AB35: =P35*(1+$G35) -> 26.75 | ... AF35: =T35*(1+$G35) -> 26.75
D36: =D$9 -> 1 | E36: =E$9 -> 2 | G36: =INDEX(CaseData!$N$8:$N$12,MATCH($E36,CaseData!$M$8:$M$12,0)) -> 0.09 | I36: =SUMIFS(CaseData!$G$8:$G$307,CaseData!$B$8:$B$307,I$5,CaseData!$C$8:$C$307,$D36,CaseData!$D$8:$D$307,$E36) -> 7.31 | J36: =SUMIFS(CaseData!$G$8:$G$307,CaseData!$B$8:$B$307,J$5,CaseData!$C$8:$C$307,$D36,CaseData!$D$8:$D$307,$E36) -> 7.31 | K36: =SUMIFS(CaseData!$G$8:$G$307,CaseData!$B$8:$B$307,K$5,CaseData!$C$8:$C$307,$D36,CaseData!$D$8:$D$307,$E36) -> 7.31 | L36: =SUMIFS(CaseData!$G$8:$G$307,CaseData!$B$8:$B$307,L$5,CaseData!$C$8:$C$307,$D36,CaseData!$D$8:$D$307,$E36) -> 7.31 | M36: =SUMIFS(CaseData!$G$8:$G$307,CaseData!$B$8:$B$307,M$5,CaseData!$C$8:$C$307,$D36,CaseData!$D$8:$D$307,$E36) -> 7.31 | N36: =SUMIFS(CaseData!$G$8:$G$307,CaseData!$B$8:$B$307,N$5,CaseData!$C$8:$C$307,$D36,CaseData!$D$8:$D$307,$E36) -> 7.31 | O36: =SUMIFS(CaseData!$G$8:$G$307,CaseData!$B$8:$B$307,O$5,CaseData!$C$8:$C$307,$D36,CaseData!$D$8:$D$307,$E36) -> 7.31 | P36: =SUMIFS(CaseData!$G$8:$G$307,CaseData!$B$8:$B$307,P$5,CaseData!$C$8:$C$307,$D36,CaseData!$D$8:$D$307,$E36) -> 7.31 | ... T36: =SUMIFS(CaseData!$G$8:$G$307,CaseData!$B$8:$B$307,T$5,CaseData!$C$8:$C$307,$D36,CaseData!$D$8:$D$307,$E36) -> 7.31 | U36: =I36*(1+$G36) -> 7.9679 | V36: =J36*(1+$G36) -> 7.9679 | W36: =K36*(1+$G36) -> 7.9679 | X36: =L36*(1+$G36) -> 7.9679 | Y36: =M36*(1+$G36) -> 7.9679 | Z36: =N36*(1+$G36) -> 7.9679 | AA36: =O36*(1+$G36) -> 7.9679 | AB36: =P36*(1+$G36) -> 7.9679 | ... AF36: =T36*(1+$G36) -> 7.9679
D37: =D$10 -> 1 | E37: =E$10 -> 3 | G37: =INDEX(CaseData!$N$8:$N$12,MATCH($E37,CaseData!$M$8:$M$12,0)) -> 0.08 | I37: =SUMIFS(CaseData!$G$8:$G$307,CaseData!$B$8:$B$307,I$5,CaseData!$C$8:$C$307,$D37,CaseData!$D$8:$D$307,$E37) -> 5.12 | J37: =SUMIFS(CaseData!$G$8:$G$307,CaseData!$B$8:$B$307,J$5,CaseData!$C$8:$C$307,$D37,CaseData!$D$8:$D$307,$E37) -> 5.12 | K37: =SUMIFS(CaseData!$G$8:$G$307,CaseData!$B$8:$B$307,K$5,CaseData!$C$8:$C$307,$D37,CaseData!$D$8:$D$307,$E37) -> 5.12 | L37: =SUMIFS(CaseData!$G$8:$G$307,CaseData!$B$8:$B$307,L$5,CaseData!$C$8:$C$307,$D37,CaseData!$D$8:$D$307,$E37) -> 5.12 | M37: =SUMIFS(CaseData!$G$8:$G$307,CaseData!$B$8:$B$307,M$5,CaseData!$C$8:$C$307,$D37,CaseData!$D$8:$D$307,$E37) -> 5.12 | N37: =SUMIFS(CaseData!$G$8:$G$307,CaseData!$B$8:$B$307,N$5,CaseData!$C$8:$C$307,$D37,CaseData!$D$8:$D$307,$E37) -> 5.12 | O37: =SUMIFS(CaseData!$G$8:$G$307,CaseData!$B$8:$B$307,O$5,CaseData!$C$8:$C$307,$D37,CaseData!$D$8:$D$307,$E37) -> 5.12 | P37: =SUMIFS(CaseData!$G$8:$G$307,CaseData!$B$8:$B$307,P$5,CaseData!$C$8:$C$307,$D37,CaseData!$D$8:$D$307,$E37) -> 5.12 | ... T37: =SUMIFS(CaseData!$G$8:$G$307,CaseData!$B$8:$B$307,T$5,CaseData!$C$8:$C$307,$D37,CaseData!$D$8:$D$307,$E37) -> 5.12 | U37: =I37*(1+$G37) -> 5.5296 | V37: =J37*(1+$G37) -> 5.5296 | W37: =K37*(1+$G37) -> 5.5296 | X37: =L37*(1+$G37) -> 5.5296 | Y37: =M37*(1+$G37) -> 5.5296 | Z37: =N37*(1+$G37) -> 5.5296 | AA37: =O37*(1+$G37) -> 5.5296 | AB37: =P37*(1+$G37) -> 5.5296 | ... AF37: =T37*(1+$G37) -> 5.5296
D38: =D$11 -> 1 | E38: =E$11 -> 4 | G38: =INDEX(CaseData!$N$8:$N$12,MATCH($E38,CaseData!$M$8:$M$12,0)) -> 0.07 | I38: =SUMIFS(CaseData!$G$8:$G$307,CaseData!$B$8:$B$307,I$5,CaseData!$C$8:$C$307,$D38,CaseData!$D$8:$D$307,$E38) -> 6.48 | J38: =SUMIFS(CaseData!$G$8:$G$307,CaseData!$B$8:$B$307,J$5,CaseData!$C$8:$C$307,$D38,CaseData!$D$8:$D$307,$E38) -> 6.48 | K38: =SUMIFS(CaseData!$G$8:$G$307,CaseData!$B$8:$B$307,K$5,CaseData!$C$8:$C$307,$D38,CaseData!$D$8:$D$307,$E38) -> 6.48 | L38: =SUMIFS(CaseData!$G$8:$G$307,CaseData!$B$8:$B$307,L$5,CaseData!$C$8:$C$307,$D38,CaseData!$D$8:$D$307,$E38) -> 6.48 | M38: =SUMIFS(CaseData!$G$8:$G$307,CaseData!$B$8:$B$307,M$5,CaseData!$C$8:$C$307,$D38,CaseData!$D$8:$D$307,$E38) -> 6.48 | N38: =SUMIFS(CaseData!$G$8:$G$307,CaseData!$B$8:$B$307,N$5,CaseData!$C$8:$C$307,$D38,CaseData!$D$8:$D$307,$E38) -> 6.48 | O38: =SUMIFS(CaseData!$G$8:$G$307,CaseData!$B$8:$B$307,O$5,CaseData!$C$8:$C$307,$D38,CaseData!$D$8:$D$307,$E38) -> 6.48 | P38: =SUMIFS(CaseData!$G$8:$G$307,CaseData!$B$8:$B$307,P$5,CaseData!$C$8:$C$307,$D38,CaseData!$D$8:$D$307,$E38) -> 6.48 | ... T38: =SUMIFS(CaseData!$G$8:$G$307,CaseData!$B$8:$B$307,T$5,CaseData!$C$8:$C$307,$D38,CaseData!$D$8:$D$307,$E38) -> 6.48 | U38: =I38*(1+$G38) -> 6.9336 | V38: =J38*(1+$G38) -> 6.9336 | W38: =K38*(1+$G38) -> 6.9336 | X38: =L38*(1+$G38) -> 6.9336 | Y38: =M38*(1+$G38) -> 6.9336 | Z38: =N38*(1+$G38) -> 6.9336 | AA38: =O38*(1+$G38) -> 6.9336 | AB38: =P38*(1+$G38) -> 6.9336 | ... AF38: =T38*(1+$G38) -> 6.9336
D39: =D$12 -> 1 | E39: =E$12 -> 5 | G39: =INDEX(CaseData!$N$8:$N$12,MATCH($E39,CaseData!$M$8:$M$12,0)) -> 0.05 | I39: =SUMIFS(CaseData!$G$8:$G$307,CaseData!$B$8:$B$307,I$5,CaseData!$C$8:$C$307,$D39,CaseData!$D$8:$D$307,$E39) -> 6.26 | J39: =SUMIFS(CaseData!$G$8:$G$307,CaseData!$B$8:$B$307,J$5,CaseData!$C$8:$C$307,$D39,CaseData!$D$8:$D$307,$E39) -> 6.26 | K39: =SUMIFS(CaseData!$G$8:$G$307,CaseData!$B$8:$B$307,K$5,CaseData!$C$8:$C$307,$D39,CaseData!$D$8:$D$307,$E39) -> 6.26 | L39: =SUMIFS(CaseData!$G$8:$G$307,CaseData!$B$8:$B$307,L$5,CaseData!$C$8:$C$307,$D39,CaseData!$D$8:$D$307,$E39) -> 6.26 | M39: =SUMIFS(CaseData!$G$8:$G$307,CaseData!$B$8:$B$307,M$5,CaseData!$C$8:$C$307,$D39,CaseData!$D$8:$D$307,$E39) -> 6.26 | N39: =SUMIFS(CaseData!$G$8:$G$307,CaseData!$B$8:$B$307,N$5,CaseData!$C$8:$C$307,$D39,CaseData!$D$8:$D$307,$E39) -> 6.26 | O39: =SUMIFS(CaseData!$G$8:$G$307,CaseData!$B$8:$B$307,O$5,CaseData!$C$8:$C$307,$D39,CaseData!$D$8:$D$307,$E39) -> 6.26 | P39: =SUMIFS(CaseData!$G$8:$G$307,CaseData!$B$8:$B$307,P$5,CaseData!$C$8:$C$307,$D39,CaseData!$D$8:$D$307,$E39) -> 6.26 | ... T39: =SUMIFS(CaseData!$G$8:$G$307,CaseData!$B$8:$B$307,T$5,CaseData!$C$8:$C$307,$D39,CaseData!$D$8:$D$307,$E39) -> 6.26 | U39: =I39*(1+$G39) -> 6.573 | V39: =J39*(1+$G39) -> 6.573 | W39: =K39*(1+$G39) -> 6.573 | X39: =L39*(1+$G39) -> 6.573 | Y39: =M39*(1+$G39) -> 6.573 | Z39: =N39*(1+$G39) -> 6.573 | AA39: =O39*(1+$G39) -> 6.573 | AB39: =P39*(1+$G39) -> 6.573 | ... AF39: =T39*(1+$G39) -> 6.573
D40: =D$13 -> 2 | E40: =E$13 -> 1 | G40: =INDEX(CaseData!$N$8:$N$12,MATCH($E40,CaseData!$M$8:$M$12,0)) -> 0.07 | I40: =SUMIFS(CaseData!$G$8:$G$307,CaseData!$B$8:$B$307,I$5,CaseData!$C$8:$C$307,$D40,CaseData!$D$8:$D$307,$E40) -> 25 | J40: =SUMIFS(CaseData!$G$8:$G$307,CaseData!$B$8:$B$307,J$5,CaseData!$C$8:$C$307,$D40,CaseData!$D$8:$D$307,$E40) -> 25 | K40: =SUMIFS(CaseData!$G$8:$G$307,CaseData!$B$8:$B$307,K$5,CaseData!$C$8:$C$307,$D40,CaseData!$D$8:$D$307,$E40) -> 25 | L40: =SUMIFS(CaseData!$G$8:$G$307,CaseData!$B$8:$B$307,L$5,CaseData!$C$8:$C$307,$D40,CaseData!$D$8:$D$307,$E40) -> 25 | M40: =SUMIFS(CaseData!$G$8:$G$307,CaseData!$B$8:$B$307,M$5,CaseData!$C$8:$C$307,$D40,CaseData!$D$8:$D$307,$E40) -> 25 | N40: =SUMIFS(CaseData!$G$8:$G$307,CaseData!$B$8:$B$307,N$5,CaseData!$C$8:$C$307,$D40,CaseData!$D$8:$D$307,$E40) -> 25 | O40: =SUMIFS(CaseData!$G$8:$G$307,CaseData!$B$8:$B$307,O$5,CaseData!$C$8:$C$307,$D40,CaseData!$D$8:$D$307,$E40) -> 25 | P40: =SUMIFS(CaseData!$G$8:$G$307,CaseData!$B$8:$B$307,P$5,CaseData!$C$8:$C$307,$D40,CaseData!$D$8:$D$307,$E40) -> 25 | ... T40: =SUMIFS(CaseData!$G$8:$G$307,CaseData!$B$8:$B$307,T$5,CaseData!$C$8:$C$307,$D40,CaseData!$D$8:$D$307,$E40) -> 25 | U40: =I40*(1+$G40) -> 26.75 | V40: =J40*(1+$G40) -> 26.75 | W40: =K40*(1+$G40) -> 26.75 | X40: =L40*(1+$G40) -> 26.75 | Y40: =M40*(1+$G40) -> 26.75 | Z40: =N40*(1+$G40) -> 26.75 | AA40: =O40*(1+$G40) -> 26.75 | AB40: =P40*(1+$G40) -> 26.75 | ... AF40: =T40*(1+$G40) -> 26.75
D41: =D$14 -> 2 | E41: =E$14 -> 2 | G41: =INDEX(CaseData!$N$8:$N$12,MATCH($E41,CaseData!$M$8:$M$12,0)) -> 0.09 | I41: =SUMIFS(CaseData!$G$8:$G$307,CaseData!$B$8:$B$307,I$5,CaseData!$C$8:$C$307,$D41,CaseData!$D$8:$D$307,$E41) -> 7.31 | J41: =SUMIFS(CaseData!$G$8:$G$307,CaseData!$B$8:$B$307,J$5,CaseData!$C$8:$C$307,$D41,CaseData!$D$8:$D$307,$E41) -> 7.31 | K41: =SUMIFS(CaseData!$G$8:$G$307,CaseData!$B$8:$B$307,K$5,CaseData!$C$8:$C$307,$D41,CaseData!$D$8:$D$307,$E41) -> 7.31 | L41: =SUMIFS(CaseData!$G$8:$G$307,CaseData!$B$8:$B$307,L$5,CaseData!$C$8:$C$307,$D41,CaseData!$D$8:$D$307,$E41) -> 7.31 | M41: =SUMIFS(CaseData!$G$8:$G$307,CaseData!$B$8:$B$307,M$5,CaseData!$C$8:$C$307,$D41,CaseData!$D$8:$D$307,$E41) -> 7.31 | N41: =SUMIFS(CaseData!$G$8:$G$307,CaseData!$B$8:$B$307,N$5,CaseData!$C$8:$C$307,$D41,CaseData!$D$8:$D$307,$E41) -> 7.31 | O41: =SUMIFS(CaseData!$G$8:$G$307,CaseData!$B$8:$B$307,O$5,CaseData!$C$8:$C$307,$D41,CaseData!$D$8:$D$307,$E41) -> 7.31 | P41: =SUMIFS(CaseData!$G$8:$G$307,CaseData!$B$8:$B$307,P$5,CaseData!$C$8:$C$307,$D41,CaseData!$D$8:$D$307,$E41) -> 7.31 | ... T41: =SUMIFS(CaseData!$G$8:$G$307,CaseData!$B$8:$B$307,T$5,CaseData!$C$8:$C$307,$D41,CaseData!$D$8:$D$307,$E41) -> 7.31 | U41: =I41*(1+$G41) -> 7.9679 | V41: =J41*(1+$G41) -> 7.9679 | W41: =K41*(1+$G41) -> 7.9679 | X41: =L41*(1+$G41) -> 7.9679 | Y41: =M41*(1+$G41) -> 7.9679 | Z41: =N41*(1+$G41) -> 7.9679 | AA41: =O41*(1+$G41) -> 7.9679 | AB41: =P41*(1+$G41) -> 7.9679 | ... AF41: =T41*(1+$G41) -> 7.9679
D42: =D$15 -> 2 | E42: =E$15 -> 3 | G42: =INDEX(CaseData!$N$8:$N$12,MATCH($E42,CaseData!$M$8:$M$12,0)) -> 0.08 | I42: =SUMIFS(CaseData!$G$8:$G$307,CaseData!$B$8:$B$307,I$5,CaseData!$C$8:$C$307,$D42,CaseData!$D$8:$D$307,$E42) -> 5.12 | J42: =SUMIFS(CaseData!$G$8:$G$307,CaseData!$B$8:$B$307,J$5,CaseData!$C$8:$C$307,$D42,CaseData!$D$8:$D$307,$E42) -> 5.12 | K42: =SUMIFS(CaseData!$G$8:$G$307,CaseData!$B$8:$B$307,K$5,CaseData!$C$8:$C$307,$D42,CaseData!$D$8:$D$307,$E42) -> 5.12 | L42: =SUMIFS(CaseData!$G$8:$G$307,CaseData!$B$8:$B$307,L$5,CaseData!$C$8:$C$307,$D42,CaseData!$D$8:$D$307,$E42) -> 5.12 | M42: =SUMIFS(CaseData!$G$8:$G$307,CaseData!$B$8:$B$307,M$5,CaseData!$C$8:$C$307,$D42,CaseData!$D$8:$D$307,$E42) -> 5.12 | N42: =SUMIFS(CaseData!$G$8:$G$307,CaseData!$B$8:$B$307,N$5,CaseData!$C$8:$C$307,$D42,CaseData!$D$8:$D$307,$E42) -> 5.12 | O42: =SUMIFS(CaseData!$G$8:$G$307,CaseData!$B$8:$B$307,O$5,CaseData!$C$8:$C$307,$D42,CaseData!$D$8:$D$307,$E42) -> 5.12 | P42: =SUMIFS(CaseData!$G$8:$G$307,CaseData!$B$8:$B$307,P$5,CaseData!$C$8:$C$307,$D42,CaseData!$D$8:$D$307,$E42) -> 5.12 | ... T42: =SUMIFS(CaseData!$G$8:$G$307,CaseData!$B$8:$B$307,T$5,CaseData!$C$8:$C$307,$D42,CaseData!$D$8:$D$307,$E42) -> 5.12 | U42: =I42*(1+$G42) -> 5.5296 | V42: =J42*(1+$G42) -> 5.5296 | W42: =K42*(1+$G42) -> 5.5296 | X42: =L42*(1+$G42) -> 5.5296 | Y42: =M42*(1+$G42) -> 5.5296 | Z42: =N42*(1+$G42) -> 5.5296 | AA42: =O42*(1+$G42) -> 5.5296 | AB42: =P42*(1+$G42) -> 5.5296 | ... AF42: =T42*(1+$G42) -> 5.5296
D43: =D$16 -> 2 | E43: =E$16 -> 4 | G43: =INDEX(CaseData!$N$8:$N$12,MATCH($E43,CaseData!$M$8:$M$12,0)) -> 0.07 | I43: =SUMIFS(CaseData!$G$8:$G$307,CaseData!$B$8:$B$307,I$5,CaseData!$C$8:$C$307,$D43,CaseData!$D$8:$D$307,$E43) -> 6.48 | J43: =SUMIFS(CaseData!$G$8:$G$307,CaseData!$B$8:$B$307,J$5,CaseData!$C$8:$C$307,$D43,CaseData!$D$8:$D$307,$E43) -> 6.48 | K43: =SUMIFS(CaseData!$G$8:$G$307,CaseData!$B$8:$B$307,K$5,CaseData!$C$8:$C$307,$D43,CaseData!$D$8:$D$307,$E43) -> 6.48 | L43: =SUMIFS(CaseData!$G$8:$G$307,CaseData!$B$8:$B$307,L$5,CaseData!$C$8:$C$307,$D43,CaseData!$D$8:$D$307,$E43) -> 6.48 | M43: =SUMIFS(CaseData!$G$8:$G$307,CaseData!$B$8:$B$307,M$5,CaseData!$C$8:$C$307,$D43,CaseData!$D$8:$D$307,$E43) -> 6.48 | N43: =SUMIFS(CaseData!$G$8:$G$307,CaseData!$B$8:$B$307,N$5,CaseData!$C$8:$C$307,$D43,CaseData!$D$8:$D$307,$E43) -> 6.48 | O43: =SUMIFS(CaseData!$G$8:$G$307,CaseData!$B$8:$B$307,O$5,CaseData!$C$8:$C$307,$D43,CaseData!$D$8:$D$307,$E43) -> 6.48 | P43: =SUMIFS(CaseData!$G$8:$G$307,CaseData!$B$8:$B$307,P$5,CaseData!$C$8:$C$307,$D43,CaseData!$D$8:$D$307,$E43) -> 6.48 | ... T43: =SUMIFS(CaseData!$G$8:$G$307,CaseData!$B$8:$B$307,T$5,CaseData!$C$8:$C$307,$D43,CaseData!$D$8:$D$307,$E43) -> 6.48 | U43: =I43*(1+$G43) -> 6.9336 | V43: =J43*(1+$G43) -> 6.9336 | W43: =K43*(1+$G43) -> 6.9336 | X43: =L43*(1+$G43) -> 6.9336 | Y43: =M43*(1+$G43) -> 6.9336 | Z43: =N43*(1+$G43) -> 6.9336 | AA43: =O43*(1+$G43) -> 6.9336 | AB43: =P43*(1+$G43) -> 6.9336 | ... AF43: =T43*(1+$G43) -> 6.9336
D44: =D$17 -> 2 | E44: =E$17 -> 5 | G44: =INDEX(CaseData!$N$8:$N$12,MATCH($E44,CaseData!$M$8:$M$12,0)) -> 0.05 | I44: =SUMIFS(CaseData!$G$8:$G$307,CaseData!$B$8:$B$307,I$5,CaseData!$C$8:$C$307,$D44,CaseData!$D$8:$D$307,$E44) -> 6.26 | J44: =SUMIFS(CaseData!$G$8:$G$307,CaseData!$B$8:$B$307,J$5,CaseData!$C$8:$C$307,$D44,CaseData!$D$8:$D$307,$E44) -> 6.26 | K44: =SUMIFS(CaseData!$G$8:$G$307,CaseData!$B$8:$B$307,K$5,CaseData!$C$8:$C$307,$D44,CaseData!$D$8:$D$307,$E44) -> 6.26 | L44: =SUMIFS(CaseData!$G$8:$G$307,CaseData!$B$8:$B$307,L$5,CaseData!$C$8:$C$307,$D44,CaseData!$D$8:$D$307,$E44) -> 6.26 | M44: =SUMIFS(CaseData!$G$8:$G$307,CaseData!$B$8:$B$307,M$5,CaseData!$C$8:$C$307,$D44,CaseData!$D$8:$D$307,$E44) -> 6.26 | N44: =SUMIFS(CaseData!$G$8:$G$307,CaseData!$B$8:$B$307,N$5,CaseData!$C$8:$C$307,$D44,CaseData!$D$8:$D$307,$E44) -> 6.26 | O44: =SUMIFS(CaseData!$G$8:$G$307,CaseData!$B$8:$B$307,O$5,CaseData!$C$8:$C$307,$D44,CaseData!$D$8:$D$307,$E44) -> 6.26 | P44: =SUMIFS(CaseData!$G$8:$G$307,CaseData!$B$8:$B$307,P$5,CaseData!$C$8:$C$307,$D44,CaseData!$D$8:$D$307,$E44) -> 6.26 | ... T44: =SUMIFS(CaseData!$G$8:$G$307,CaseData!$B$8:$B$307,T$5,CaseData!$C$8:$C$307,$D44,CaseData!$D$8:$D$307,$E44) -> 6.26 | U44: =I44*(1+$G44) -> 6.573 | V44: =J44*(1+$G44) -> 6.573 | W44: =K44*(1+$G44) -> 6.573 | X44: =L44*(1+$G44) -> 6.573 | Y44: =M44*(1+$G44) -> 6.573 | Z44: =N44*(1+$G44) -> 6.573 | AA44: =O44*(1+$G44) -> 6.573 | AB44: =P44*(1+$G44) -> 6.573 | ... AF44: =T44*(1+$G44) -> 6.573
D45: =D$18 -> 3 | E45: =E$18 -> 1 | G45: =INDEX(CaseData!$N$8:$N$12,MATCH($E45,CaseData!$M$8:$M$12,0)) -> 0.07 | I45: =SUMIFS(CaseData!$G$8:$G$307,CaseData!$B$8:$B$307,I$5,CaseData!$C$8:$C$307,$D45,CaseData!$D$8:$D$307,$E45) -> 25 | J45: =SUMIFS(CaseData!$G$8:$G$307,CaseData!$B$8:$B$307,J$5,CaseData!$C$8:$C$307,$D45,CaseData!$D$8:$D$307,$E45) -> 25 | K45: =SUMIFS(CaseData!$G$8:$G$307,CaseData!$B$8:$B$307,K$5,CaseData!$C$8:$C$307,$D45,CaseData!$D$8:$D$307,$E45) -> 25 | L45: =SUMIFS(CaseData!$G$8:$G$307,CaseData!$B$8:$B$307,L$5,CaseData!$C$8:$C$307,$D45,CaseData!$D$8:$D$307,$E45) -> 25 | M45: =SUMIFS(CaseData!$G$8:$G$307,CaseData!$B$8:$B$307,M$5,CaseData!$C$8:$C$307,$D45,CaseData!$D$8:$D$307,$E45) -> 25 | N45: =SUMIFS(CaseData!$G$8:$G$307,CaseData!$B$8:$B$307,N$5,CaseData!$C$8:$C$307,$D45,CaseData!$D$8:$D$307,$E45) -> 25 | O45: =SUMIFS(CaseData!$G$8:$G$307,CaseData!$B$8:$B$307,O$5,CaseData!$C$8:$C$307,$D45,CaseData!$D$8:$D$307,$E45) -> 25 | P45: =SUMIFS(CaseData!$G$8:$G$307,CaseData!$B$8:$B$307,P$5,CaseData!$C$8:$C$307,$D45,CaseData!$D$8:$D$307,$E45) -> 25 | ... T45: =SUMIFS(CaseData!$G$8:$G$307,CaseData!$B$8:$B$307,T$5,CaseData!$C$8:$C$307,$D45,CaseData!$D$8:$D$307,$E45) -> 25 | U45: =I45*(1+$G45) -> 26.75 | V45: =J45*(1+$G45) -> 26.75 | W45: =K45*(1+$G45) -> 26.75 | X45: =L45*(1+$G45) -> 26.75 | Y45: =M45*(1+$G45) -> 26.75 | Z45: =N45*(1+$G45) -> 26.75 | AA45: =O45*(1+$G45) -> 26.75 | AB45: =P45*(1+$G45) -> 26.75 | ... AF45: =T45*(1+$G45) -> 26.75
D46: =D$19 -> 3 | E46: =E$19 -> 2 | G46: =INDEX(CaseData!$N$8:$N$12,MATCH($E46,CaseData!$M$8:$M$12,0)) -> 0.09 | I46: =SUMIFS(CaseData!$G$8:$G$307,CaseData!$B$8:$B$307,I$5,CaseData!$C$8:$C$307,$D46,CaseData!$D$8:$D$307,$E46) -> 7.31 | J46: =SUMIFS(CaseData!$G$8:$G$307,CaseData!$B$8:$B$307,J$5,CaseData!$C$8:$C$307,$D46,CaseData!$D$8:$D$307,$E46) -> 7.31 | K46: =SUMIFS(CaseData!$G$8:$G$307,CaseData!$B$8:$B$307,K$5,CaseData!$C$8:$C$307,$D46,CaseData!$D$8:$D$307,$E46) -> 7.31 | L46: =SUMIFS(CaseData!$G$8:$G$307,CaseData!$B$8:$B$307,L$5,CaseData!$C$8:$C$307,$D46,CaseData!$D$8:$D$307,$E46) -> 7.31 | M46: =SUMIFS(CaseData!$G$8:$G$307,CaseData!$B$8:$B$307,M$5,CaseData!$C$8:$C$307,$D46,CaseData!$D$8:$D$307,$E46) -> 7.31 | N46: =SUMIFS(CaseData!$G$8:$G$307,CaseData!$B$8:$B$307,N$5,CaseData!$C$8:$C$307,$D46,CaseData!$D$8:$D$307,$E46) -> 7.31 | O46: =SUMIFS(CaseData!$G$8:$G$307,CaseData!$B$8:$B$307,O$5,CaseData!$C$8:$C$307,$D46,CaseData!$D$8:$D$307,$E46) -> 7.31 | P46: =SUMIFS(CaseData!$G$8:$G$307,CaseData!$B$8:$B$307,P$5,CaseData!$C$8:$C$307,$D46,CaseData!$D$8:$D$307,$E46) -> 7.31 | ... T46: =SUMIFS(CaseData!$G$8:$G$307,CaseData!$B$8:$B$307,T$5,CaseData!$C$8:$C$307,$D46,CaseData!$D$8:$D$307,$E46) -> 7.31 | U46: =I46*(1+$G46) -> 7.9679 | V46: =J46*(1+$G46) -> 7.9679 | W46: =K46*(1+$G46) -> 7.9679 | X46: =L46*(1+$G46) -> 7.9679 | Y46: =M46*(1+$G46) -> 7.9679 | Z46: =N46*(1+$G46) -> 7.9679 | AA46: =O46*(1+$G46) -> 7.9679 | AB46: =P46*(1+$G46) -> 7.9679 | ... AF46: =T46*(1+$G46) -> 7.9679
D47: =D$20 -> 3 | E47: =E$20 -> 3 | G47: =INDEX(CaseData!$N$8:$N$12,MATCH($E47,CaseData!$M$8:$M$12,0)) -> 0.08 | I47: =SUMIFS(CaseData!$G$8:$G$307,CaseData!$B$8:$B$307,I$5,CaseData!$C$8:$C$307,$D47,CaseData!$D$8:$D$307,$E47) -> 5.12 | J47: =SUMIFS(CaseData!$G$8:$G$307,CaseData!$B$8:$B$307,J$5,CaseData!$C$8:$C$307,$D47,CaseData!$D$8:$D$307,$E47) -> 5.12 | K47: =SUMIFS(CaseData!$G$8:$G$307,CaseData!$B$8:$B$307,K$5,CaseData!$C$8:$C$307,$D47,CaseData!$D$8:$D$307,$E47) -> 5.12 | L47: =SUMIFS(CaseData!$G$8:$G$307,CaseData!$B$8:$B$307,L$5,CaseData!$C$8:$C$307,$D47,CaseData!$D$8:$D$307,$E47) -> 5.12 | M47: =SUMIFS(CaseData!$G$8:$G$307,CaseData!$B$8:$B$307,M$5,CaseData!$C$8:$C$307,$D47,CaseData!$D$8:$D$307,$E47) -> 5.12 | N47: =SUMIFS(CaseData!$G$8:$G$307,CaseData!$B$8:$B$307,N$5,CaseData!$C$8:$C$307,$D47,CaseData!$D$8:$D$307,$E47) -> 5.12 | O47: =SUMIFS(CaseData!$G$8:$G$307,CaseData!$B$8:$B$307,O$5,CaseData!$C$8:$C$307,$D47,CaseData!$D$8:$D$307,$E47) -> 5.12 | P47: =SUMIFS(CaseData!$G$8:$G$307,CaseData!$B$8:$B$307,P$5,CaseData!$C$8:$C$307,$D47,CaseData!$D$8:$D$307,$E47) -> 5.12 | ... T47: =SUMIFS(CaseData!$G$8:$G$307,CaseData!$B$8:$B$307,T$5,CaseData!$C$8:$C$307,$D47,CaseData!$D$8:$D$307,$E47) -> 5.12 | U47: =I47*(1+$G47) -> 5.5296 | V47: =J47*(1+$G47) -> 5.5296 | W47: =K47*(1+$G47) -> 5.5296 | X47: =L47*(1+$G47) -> 5.5296 | Y47: =M47*(1+$G47) -> 5.5296 | Z47: =N47*(1+$G47) -> 5.5296 | AA47: =O47*(1+$G47) -> 5.5296 | AB47: =P47*(1+$G47) -> 5.5296 | ... AF47: =T47*(1+$G47) -> 5.5296
D48: =D$21 -> 3 | E48: =E$21 -> 4 | G48: =INDEX(CaseData!$N$8:$N$12,MATCH($E48,CaseData!$M$8:$M$12,0)) -> 0.07 | I48: =SUMIFS(CaseData!$G$8:$G$307,CaseData!$B$8:$B$307,I$5,CaseData!$C$8:$C$307,$D48,CaseData!$D$8:$D$307,$E48) -> 6.48 | J48: =SUMIFS(CaseData!$G$8:$G$307,CaseData!$B$8:$B$307,J$5,CaseData!$C$8:$C$307,$D48,CaseData!$D$8:$D$307,$E48) -> 6.48 | K48: =SUMIFS(CaseData!$G$8:$G$307,CaseData!$B$8:$B$307,K$5,CaseData!$C$8:$C$307,$D48,CaseData!$D$8:$D$307,$E48) -> 6.48 | L48: =SUMIFS(CaseData!$G$8:$G$307,CaseData!$B$8:$B$307,L$5,CaseData!$C$8:$C$307,$D48,CaseData!$D$8:$D$307,$E48) -> 6.48 | M48: =SUMIFS(CaseData!$G$8:$G$307,CaseData!$B$8:$B$307,M$5,CaseData!$C$8:$C$307,$D48,CaseData!$D$8:$D$307,$E48) -> 6.48 | N48: =SUMIFS(CaseData!$G$8:$G$307,CaseData!$B$8:$B$307,N$5,CaseData!$C$8:$C$307,$D48,CaseData!$D$8:$D$307,$E48) -> 6.48 | O48: =SUMIFS(CaseData!$G$8:$G$307,CaseData!$B$8:$B$307,O$5,CaseData!$C$8:$C$307,$D48,CaseData!$D$8:$D$307,$E48) -> 6.48 | P48: =SUMIFS(CaseData!$G$8:$G$307,CaseData!$B$8:$B$307,P$5,CaseData!$C$8:$C$307,$D48,CaseData!$D$8:$D$307,$E48) -> 6.48 | ... T48: =SUMIFS(CaseData!$G$8:$G$307,CaseData!$B$8:$B$307,T$5,CaseData!$C$8:$C$307,$D48,CaseData!$D$8:$D$307,$E48) -> 6.48 | U48: =I48*(1+$G48) -> 6.9336 | V48: =J48*(1+$G48) -> 6.9336 | W48: =K48*(1+$G48) -> 6.9336 | X48: =L48*(1+$G48) -> 6.9336 | Y48: =M48*(1+$G48) -> 6.9336 | Z48: =N48*(1+$G48) -> 6.9336 | AA48: =O48*(1+$G48) -> 6.9336 | AB48: =P48*(1+$G48) -> 6.9336 | ... AF48: =T48*(1+$G48) -> 6.9336
D49: =D$22 -> 3 | E49: =E$22 -> 5 | G49: =INDEX(CaseData!$N$8:$N$12,MATCH($E49,CaseData!$M$8:$M$12,0)) -> 0.05 | I49: =SUMIFS(CaseData!$G$8:$G$307,CaseData!$B$8:$B$307,I$5,CaseData!$C$8:$C$307,$D49,CaseData!$D$8:$D$307,$E49) -> 6.26 | J49: =SUMIFS(CaseData!$G$8:$G$307,CaseData!$B$8:$B$307,J$5,CaseData!$C$8:$C$307,$D49,CaseData!$D$8:$D$307,$E49) -> 6.26 | K49: =SUMIFS(CaseData!$G$8:$G$307,CaseData!$B$8:$B$307,K$5,CaseData!$C$8:$C$307,$D49,CaseData!$D$8:$D$307,$E49) -> 6.26 | L49: =SUMIFS(CaseData!$G$8:$G$307,CaseData!$B$8:$B$307,L$5,CaseData!$C$8:$C$307,$D49,CaseData!$D$8:$D$307,$E49) -> 6.26 | M49: =SUMIFS(CaseData!$G$8:$G$307,CaseData!$B$8:$B$307,M$5,CaseData!$C$8:$C$307,$D49,CaseData!$D$8:$D$307,$E49) -> 6.26 | N49: =SUMIFS(CaseData!$G$8:$G$307,CaseData!$B$8:$B$307,N$5,CaseData!$C$8:$C$307,$D49,CaseData!$D$8:$D$307,$E49) -> 6.26 | O49: =SUMIFS(CaseData!$G$8:$G$307,CaseData!$B$8:$B$307,O$5,CaseData!$C$8:$C$307,$D49,CaseData!$D$8:$D$307,$E49) -> 6.26 | P49: =SUMIFS(CaseData!$G$8:$G$307,CaseData!$B$8:$B$307,P$5,CaseData!$C$8:$C$307,$D49,CaseData!$D$8:$D$307,$E49) -> 6.26 | ... T49: =SUMIFS(CaseData!$G$8:$G$307,CaseData!$B$8:$B$307,T$5,CaseData!$C$8:$C$307,$D49,CaseData!$D$8:$D$307,$E49) -> 6.26 | U49: =I49*(1+$G49) -> 6.573 | V49: =J49*(1+$G49) -> 6.573 | W49: =K49*(1+$G49) -> 6.573 | X49: =L49*(1+$G49) -> 6.573 | Y49: =M49*(1+$G49) -> 6.573 | Z49: =N49*(1+$G49) -> 6.573 | AA49: =O49*(1+$G49) -> 6.573 | AB49: =P49*(1+$G49) -> 6.573 | ... AF49: =T49*(1+$G49) -> 6.573
D50: =D$23 -> 4 | E50: =E$23 -> 1 | G50: =INDEX(CaseData!$N$8:$N$12,MATCH($E50,CaseData!$M$8:$M$12,0)) -> 0.07 | I50: =SUMIFS(CaseData!$G$8:$G$307,CaseData!$B$8:$B$307,I$5,CaseData!$C$8:$C$307,$D50,CaseData!$D$8:$D$307,$E50) -> 25 | J50: =SUMIFS(CaseData!$G$8:$G$307,CaseData!$B$8:$B$307,J$5,CaseData!$C$8:$C$307,$D50,CaseData!$D$8:$D$307,$E50) -> 25 | K50: =SUMIFS(CaseData!$G$8:$G$307,CaseData!$B$8:$B$307,K$5,CaseData!$C$8:$C$307,$D50,CaseData!$D$8:$D$307,$E50) -> 25 | L50: =SUMIFS(CaseData!$G$8:$G$307,CaseData!$B$8:$B$307,L$5,CaseData!$C$8:$C$307,$D50,CaseData!$D$8:$D$307,$E50) -> 25 | M50: =SUMIFS(CaseData!$G$8:$G$307,CaseData!$B$8:$B$307,M$5,CaseData!$C$8:$C$307,$D50,CaseData!$D$8:$D$307,$E50) -> 25 | N50: =SUMIFS(CaseData!$G$8:$G$307,CaseData!$B$8:$B$307,N$5,CaseData!$C$8:$C$307,$D50,CaseData!$D$8:$D$307,$E50) -> 25 | O50: =SUMIFS(CaseData!$G$8:$G$307,CaseData!$B$8:$B$307,O$5,CaseData!$C$8:$C$307,$D50,CaseData!$D$8:$D$307,$E50) -> 25 | P50: =SUMIFS(CaseData!$G$8:$G$307,CaseData!$B$8:$B$307,P$5,CaseData!$C$8:$C$307,$D50,CaseData!$D$8:$D$307,$E50) -> 25 | ... T50: =SUMIFS(CaseData!$G$8:$G$307,CaseData!$B$8:$B$307,T$5,CaseData!$C$8:$C$307,$D50,CaseData!$D$8:$D$307,$E50) -> 25 | U50: =I50*(1+$G50) -> 26.75 | V50: =J50*(1+$G50) -> 26.75 | W50: =K50*(1+$G50) -> 26.75 | X50: =L50*(1+$G50) -> 26.75 | Y50: =M50*(1+$G50) -> 26.75 | Z50: =N50*(1+$G50) -> 26.75 | AA50: =O50*(1+$G50) -> 26.75 | AB50: =P50*(1+$G50) -> 26.75 | ... AF50: =T50*(1+$G50) -> 26.75
D51: =D$24 -> 4 | E51: =E$24 -> 2 | G51: =INDEX(CaseData!$N$8:$N$12,MATCH($E51,CaseData!$M$8:$M$12,0)) -> 0.09 | I51: =SUMIFS(CaseData!$G$8:$G$307,CaseData!$B$8:$B$307,I$5,CaseData!$C$8:$C$307,$D51,CaseData!$D$8:$D$307,$E51) -> 7.31 | J51: =SUMIFS(CaseData!$G$8:$G$307,CaseData!$B$8:$B$307,J$5,CaseData!$C$8:$C$307,$D51,CaseData!$D$8:$D$307,$E51) -> 7.31 | K51: =SUMIFS(CaseData!$G$8:$G$307,CaseData!$B$8:$B$307,K$5,CaseData!$C$8:$C$307,$D51,CaseData!$D$8:$D$307,$E51) -> 7.31 | L51: =SUMIFS(CaseData!$G$8:$G$307,CaseData!$B$8:$B$307,L$5,CaseData!$C$8:$C$307,$D51,CaseData!$D$8:$D$307,$E51) -> 7.31 | M51: =SUMIFS(CaseData!$G$8:$G$307,CaseData!$B$8:$B$307,M$5,CaseData!$C$8:$C$307,$D51,CaseData!$D$8:$D$307,$E51) -> 7.31 | N51: =SUMIFS(CaseData!$G$8:$G$307,CaseData!$B$8:$B$307,N$5,CaseData!$C$8:$C$307,$D51,CaseData!$D$8:$D$307,$E51) -> 7.31 | O51: =SUMIFS(CaseData!$G$8:$G$307,CaseData!$B$8:$B$307,O$5,CaseData!$C$8:$C$307,$D51,CaseData!$D$8:$D$307,$E51) -> 7.31 | P51: =SUMIFS(CaseData!$G$8:$G$307,CaseData!$B$8:$B$307,P$5,CaseData!$C$8:$C$307,$D51,CaseData!$D$8:$D$307,$E51) -> 7.31 | ... T51: =SUMIFS(CaseData!$G$8:$G$307,CaseData!$B$8:$B$307,T$5,CaseData!$C$8:$C$307,$D51,CaseData!$D$8:$D$307,$E51) -> 7.31 | U51: =I51*(1+$G51) -> 7.9679 | V51: =J51*(1+$G51) -> 7.9679 | W51: =K51*(1+$G51) -> 7.9679 | X51: =L51*(1+$G51) -> 7.9679 | Y51: =M51*(1+$G51) -> 7.9679 | Z51: =N51*(1+$G51) -> 7.9679 | AA51: =O51*(1+$G51) -> 7.9679 | AB51: =P51*(1+$G51) -> 7.9679 | ... AF51: =T51*(1+$G51) -> 7.9679
D52: =D$25 -> 4 | E52: =E$25 -> 3 | G52: =INDEX(CaseData!$N$8:$N$12,MATCH($E52,CaseData!$M$8:$M$12,0)) -> 0.08 | I52: =SUMIFS(CaseData!$G$8:$G$307,CaseData!$B$8:$B$307,I$5,CaseData!$C$8:$C$307,$D52,CaseData!$D$8:$D$307,$E52) -> 5.12 | J52: =SUMIFS(CaseData!$G$8:$G$307,CaseData!$B$8:$B$307,J$5,CaseData!$C$8:$C$307,$D52,CaseData!$D$8:$D$307,$E52) -> 5.12 | K52: =SUMIFS(CaseData!$G$8:$G$307,CaseData!$B$8:$B$307,K$5,CaseData!$C$8:$C$307,$D52,CaseData!$D$8:$D$307,$E52) -> 5.12 | L52: =SUMIFS(CaseData!$G$8:$G$307,CaseData!$B$8:$B$307,L$5,CaseData!$C$8:$C$307,$D52,CaseData!$D$8:$D$307,$E52) -> 5.12 | M52: =SUMIFS(CaseData!$G$8:$G$307,CaseData!$B$8:$B$307,M$5,CaseData!$C$8:$C$307,$D52,CaseData!$D$8:$D$307,$E52) -> 5.12 | N52: =SUMIFS(CaseData!$G$8:$G$307,CaseData!$B$8:$B$307,N$5,CaseData!$C$8:$C$307,$D52,CaseData!$D$8:$D$307,$E52) -> 5.12 | O52: =SUMIFS(CaseData!$G$8:$G$307,CaseData!$B$8:$B$307,O$5,CaseData!$C$8:$C$307,$D52,CaseData!$D$8:$D$307,$E52) -> 5.12 | P52: =SUMIFS(CaseData!$G$8:$G$307,CaseData!$B$8:$B$307,P$5,CaseData!$C$8:$C$307,$D52,CaseData!$D$8:$D$307,$E52) -> 5.12 | ... T52: =SUMIFS(CaseData!$G$8:$G$307,CaseData!$B$8:$B$307,T$5,CaseData!$C$8:$C$307,$D52,CaseData!$D$8:$D$307,$E52) -> 5.12 | U52: =I52*(1+$G52) -> 5.5296 | V52: =J52*(1+$G52) -> 5.5296 | W52: =K52*(1+$G52) -> 5.5296 | X52: =L52*(1+$G52) -> 5.5296 | Y52: =M52*(1+$G52) -> 5.5296 | Z52: =N52*(1+$G52) -> 5.5296 | AA52: =O52*(1+$G52) -> 5.5296 | AB52: =P52*(1+$G52) -> 5.5296 | ... AF52: =T52*(1+$G52) -> 5.5296
D53: =D$26 -> 4 | E53: =E$26 -> 4 | G53: =INDEX(CaseData!$N$8:$N$12,MATCH($E53,CaseData!$M$8:$M$12,0)) -> 0.07 | I53: =SUMIFS(CaseData!$G$8:$G$307,CaseData!$B$8:$B$307,I$5,CaseData!$C$8:$C$307,$D53,CaseData!$D$8:$D$307,$E53) -> 6.48 | J53: =SUMIFS(CaseData!$G$8:$G$307,CaseData!$B$8:$B$307,J$5,CaseData!$C$8:$C$307,$D53,CaseData!$D$8:$D$307,$E53) -> 6.48 | K53: =SUMIFS(CaseData!$G$8:$G$307,CaseData!$B$8:$B$307,K$5,CaseData!$C$8:$C$307,$D53,CaseData!$D$8:$D$307,$E53) -> 6.48 | L53: =SUMIFS(CaseData!$G$8:$G$307,CaseData!$B$8:$B$307,L$5,CaseData!$C$8:$C$307,$D53,CaseData!$D$8:$D$307,$E53) -> 6.48 | M53: =SUMIFS(CaseData!$G$8:$G$307,CaseData!$B$8:$B$307,M$5,CaseData!$C$8:$C$307,$D53,CaseData!$D$8:$D$307,$E53) -> 6.48 | N53: =SUMIFS(CaseData!$G$8:$G$307,CaseData!$B$8:$B$307,N$5,CaseData!$C$8:$C$307,$D53,CaseData!$D$8:$D$307,$E53) -> 6.48 | O53: =SUMIFS(CaseData!$G$8:$G$307,CaseData!$B$8:$B$307,O$5,CaseData!$C$8:$C$307,$D53,CaseData!$D$8:$D$307,$E53) -> 6.48 | P53: =SUMIFS(CaseData!$G$8:$G$307,CaseData!$B$8:$B$307,P$5,CaseData!$C$8:$C$307,$D53,CaseData!$D$8:$D$307,$E53) -> 6.48 | ... T53: =SUMIFS(CaseData!$G$8:$G$307,CaseData!$B$8:$B$307,T$5,CaseData!$C$8:$C$307,$D53,CaseData!$D$8:$D$307,$E53) -> 6.48 | U53: =I53*(1+$G53) -> 6.9336 | V53: =J53*(1+$G53) -> 6.9336 | W53: =K53*(1+$G53) -> 6.9336 | X53: =L53*(1+$G53) -> 6.9336 | Y53: =M53*(1+$G53) -> 6.9336 | Z53: =N53*(1+$G53) -> 6.9336 | AA53: =O53*(1+$G53) -> 6.9336 | AB53: =P53*(1+$G53) -> 6.9336 | ... AF53: =T53*(1+$G53) -> 6.9336
D54: =D$27 -> 4 | E54: =E$27 -> 5 | G54: =INDEX(CaseData!$N$8:$N$12,MATCH($E54,CaseData!$M$8:$M$12,0)) -> 0.05 | I54: =SUMIFS(CaseData!$G$8:$G$307,CaseData!$B$8:$B$307,I$5,CaseData!$C$8:$C$307,$D54,CaseData!$D$8:$D$307,$E54) -> 6.26 | J54: =SUMIFS(CaseData!$G$8:$G$307,CaseData!$B$8:$B$307,J$5,CaseData!$C$8:$C$307,$D54,CaseData!$D$8:$D$307,$E54) -> 6.26 | K54: =SUMIFS(CaseData!$G$8:$G$307,CaseData!$B$8:$B$307,K$5,CaseData!$C$8:$C$307,$D54,CaseData!$D$8:$D$307,$E54) -> 6.26 | L54: =SUMIFS(CaseData!$G$8:$G$307,CaseData!$B$8:$B$307,L$5,CaseData!$C$8:$C$307,$D54,CaseData!$D$8:$D$307,$E54) -> 6.26 | M54: =SUMIFS(CaseData!$G$8:$G$307,CaseData!$B$8:$B$307,M$5,CaseData!$C$8:$C$307,$D54,CaseData!$D$8:$D$307,$E54) -> 6.26 | N54: =SUMIFS(CaseData!$G$8:$G$307,CaseData!$B$8:$B$307,N$5,CaseData!$C$8:$C$307,$D54,CaseData!$D$8:$D$307,$E54) -> 6.26 | O54: =SUMIFS(CaseData!$G$8:$G$307,CaseData!$B$8:$B$307,O$5,CaseData!$C$8:$C$307,$D54,CaseData!$D$8:$D$307,$E54) -> 6.26 | P54: =SUMIFS(CaseData!$G$8:$G$307,CaseData!$B$8:$B$307,P$5,CaseData!$C$8:$C$307,$D54,CaseData!$D$8:$D$307,$E54) -> 6.26 | ... T54: =SUMIFS(CaseData!$G$8:$G$307,CaseData!$B$8:$B$307,T$5,CaseData!$C$8:$C$307,$D54,CaseData!$D$8:$D$307,$E54) -> 6.26 | U54: =I54*(1+$G54) -> 6.573 | V54: =J54*(1+$G54) -> 6.573 | W54: =K54*(1+$G54) -> 6.573 | X54: =L54*(1+$G54) -> 6.573 | Y54: =M54*(1+$G54) -> 6.573 | Z54: =N54*(1+$G54) -> 6.573 | AA54: =O54*(1+$G54) -> 6.573 | AB54: =P54*(1+$G54) -> 6.573 | ... AF54: =T54*(1+$G54) -> 6.573
D55: =D$28 -> 5 | E55: =E$28 -> 1 | G55: =INDEX(CaseData!$N$8:$N$12,MATCH($E55,CaseData!$M$8:$M$12,0)) -> 0.07 | I55: =SUMIFS(CaseData!$G$8:$G$307,CaseData!$B$8:$B$307,I$5,CaseData!$C$8:$C$307,$D55,CaseData!$D$8:$D$307,$E55) -> 25 | J55: =SUMIFS(CaseData!$G$8:$G$307,CaseData!$B$8:$B$307,J$5,CaseData!$C$8:$C$307,$D55,CaseData!$D$8:$D$307,$E55) -> 25 | K55: =SUMIFS(CaseData!$G$8:$G$307,CaseData!$B$8:$B$307,K$5,CaseData!$C$8:$C$307,$D55,CaseData!$D$8:$D$307,$E55) -> 25 | L55: =SUMIFS(CaseData!$G$8:$G$307,CaseData!$B$8:$B$307,L$5,CaseData!$C$8:$C$307,$D55,CaseData!$D$8:$D$307,$E55) -> 25 | M55: =SUMIFS(CaseData!$G$8:$G$307,CaseData!$B$8:$B$307,M$5,CaseData!$C$8:$C$307,$D55,CaseData!$D$8:$D$307,$E55) -> 25 | N55: =SUMIFS(CaseData!$G$8:$G$307,CaseData!$B$8:$B$307,N$5,CaseData!$C$8:$C$307,$D55,CaseData!$D$8:$D$307,$E55) -> 25 | O55: =SUMIFS(CaseData!$G$8:$G$307,CaseData!$B$8:$B$307,O$5,CaseData!$C$8:$C$307,$D55,CaseData!$D$8:$D$307,$E55) -> 25 | P55: =SUMIFS(CaseData!$G$8:$G$307,CaseData!$B$8:$B$307,P$5,CaseData!$C$8:$C$307,$D55,CaseData!$D$8:$D$307,$E55) -> 25 | ... T55: =SUMIFS(CaseData!$G$8:$G$307,CaseData!$B$8:$B$307,T$5,CaseData!$C$8:$C$307,$D55,CaseData!$D$8:$D$307,$E55) -> 25 | U55: =I55*(1+$G55) -> 26.75 | V55: =J55*(1+$G55) -> 26.75 | W55: =K55*(1+$G55) -> 26.75 | X55: =L55*(1+$G55) -> 26.75 | Y55: =M55*(1+$G55) -> 26.75 | Z55: =N55*(1+$G55) -> 26.75 | AA55: =O55*(1+$G55) -> 26.75 | AB55: =P55*(1+$G55) -> 26.75 | ... AF55: =T55*(1+$G55) -> 26.75
D56: =D$29 -> 5 | E56: =E$29 -> 2 | G56: =INDEX(CaseData!$N$8:$N$12,MATCH($E56,CaseData!$M$8:$M$12,0)) -> 0.09 | I56: =SUMIFS(CaseData!$G$8:$G$307,CaseData!$B$8:$B$307,I$5,CaseData!$C$8:$C$307,$D56,CaseData!$D$8:$D$307,$E56) -> 7.31 | J56: =SUMIFS(CaseData!$G$8:$G$307,CaseData!$B$8:$B$307,J$5,CaseData!$C$8:$C$307,$D56,CaseData!$D$8:$D$307,$E56) -> 7.31 | K56: =SUMIFS(CaseData!$G$8:$G$307,CaseData!$B$8:$B$307,K$5,CaseData!$C$8:$C$307,$D56,CaseData!$D$8:$D$307,$E56) -> 7.31 | L56: =SUMIFS(CaseData!$G$8:$G$307,CaseData!$B$8:$B$307,L$5,CaseData!$C$8:$C$307,$D56,CaseData!$D$8:$D$307,$E56) -> 7.31 | M56: =SUMIFS(CaseData!$G$8:$G$307,CaseData!$B$8:$B$307,M$5,CaseData!$C$8:$C$307,$D56,CaseData!$D$8:$D$307,$E56) -> 7.31 | N56: =SUMIFS(CaseData!$G$8:$G$307,CaseData!$B$8:$B$307,N$5,CaseData!$C$8:$C$307,$D56,CaseData!$D$8:$D$307,$E56) -> 7.31 | O56: =SUMIFS(CaseData!$G$8:$G$307,CaseData!$B$8:$B$307,O$5,CaseData!$C$8:$C$307,$D56,CaseData!$D$8:$D$307,$E56) -> 7.31 | P56: =SUMIFS(CaseData!$G$8:$G$307,CaseData!$B$8:$B$307,P$5,CaseData!$C$8:$C$307,$D56,CaseData!$D$8:$D$307,$E56) -> 7.31 | ... T56: =SUMIFS(CaseData!$G$8:$G$307,CaseData!$B$8:$B$307,T$5,CaseData!$C$8:$C$307,$D56,CaseData!$D$8:$D$307,$E56) -> 7.31 | U56: =I56*(1+$G56) -> 7.9679 | V56: =J56*(1+$G56) -> 7.9679 | W56: =K56*(1+$G56) -> 7.9679 | X56: =L56*(1+$G56) -> 7.9679 | Y56: =M56*(1+$G56) -> 7.9679 | Z56: =N56*(1+$G56) -> 7.9679 | AA56: =O56*(1+$G56) -> 7.9679 | AB56: =P56*(1+$G56) -> 7.9679 | ... AF56: =T56*(1+$G56) -> 7.9679
D57: =D$30 -> 5 | E57: =E$30 -> 3 | G57: =INDEX(CaseData!$N$8:$N$12,MATCH($E57,CaseData!$M$8:$M$12,0)) -> 0.08 | I57: =SUMIFS(CaseData!$G$8:$G$307,CaseData!$B$8:$B$307,I$5,CaseData!$C$8:$C$307,$D57,CaseData!$D$8:$D$307,$E57) -> 5.12 | J57: =SUMIFS(CaseData!$G$8:$G$307,CaseData!$B$8:$B$307,J$5,CaseData!$C$8:$C$307,$D57,CaseData!$D$8:$D$307,$E57) -> 5.12 | K57: =SUMIFS(CaseData!$G$8:$G$307,CaseData!$B$8:$B$307,K$5,CaseData!$C$8:$C$307,$D57,CaseData!$D$8:$D$307,$E57) -> 5.12 | L57: =SUMIFS(CaseData!$G$8:$G$307,CaseData!$B$8:$B$307,L$5,CaseData!$C$8:$C$307,$D57,CaseData!$D$8:$D$307,$E57) -> 5.12 | M57: =SUMIFS(CaseData!$G$8:$G$307,CaseData!$B$8:$B$307,M$5,CaseData!$C$8:$C$307,$D57,CaseData!$D$8:$D$307,$E57) -> 5.12 | N57: =SUMIFS(CaseData!$G$8:$G$307,CaseData!$B$8:$B$307,N$5,CaseData!$C$8:$C$307,$D57,CaseData!$D$8:$D$307,$E57) -> 5.12 | O57: =SUMIFS(CaseData!$G$8:$G$307,CaseData!$B$8:$B$307,O$5,CaseData!$C$8:$C$307,$D57,CaseData!$D$8:$D$307,$E57) -> 5.12 | P57: =SUMIFS(CaseData!$G$8:$G$307,CaseData!$B$8:$B$307,P$5,CaseData!$C$8:$C$307,$D57,CaseData!$D$8:$D$307,$E57) -> 5.12 | ... T57: =SUMIFS(CaseData!$G$8:$G$307,CaseData!$B$8:$B$307,T$5,CaseData!$C$8:$C$307,$D57,CaseData!$D$8:$D$307,$E57) -> 5.12 | U57: =I57*(1+$G57) -> 5.5296 | V57: =J57*(1+$G57) -> 5.5296 | W57: =K57*(1+$G57) -> 5.5296 | X57: =L57*(1+$G57) -> 5.5296 | Y57: =M57*(1+$G57) -> 5.5296 | Z57: =N57*(1+$G57) -> 5.5296 | AA57: =O57*(1+$G57) -> 5.5296 | AB57: =P57*(1+$G57) -> 5.5296 | ... AF57: =T57*(1+$G57) -> 5.5296
D58: =D$31 -> 5 | E58: =E$31 -> 4 | G58: =INDEX(CaseData!$N$8:$N$12,MATCH($E58,CaseData!$M$8:$M$12,0)) -> 0.07 | I58: =SUMIFS(CaseData!$G$8:$G$307,CaseData!$B$8:$B$307,I$5,CaseData!$C$8:$C$307,$D58,CaseData!$D$8:$D$307,$E58) -> 6.48 | J58: =SUMIFS(CaseData!$G$8:$G$307,CaseData!$B$8:$B$307,J$5,CaseData!$C$8:$C$307,$D58,CaseData!$D$8:$D$307,$E58) -> 6.48 | K58: =SUMIFS(CaseData!$G$8:$G$307,CaseData!$B$8:$B$307,K$5,CaseData!$C$8:$C$307,$D58,CaseData!$D$8:$D$307,$E58) -> 6.48 | L58: =SUMIFS(CaseData!$G$8:$G$307,CaseData!$B$8:$B$307,L$5,CaseData!$C$8:$C$307,$D58,CaseData!$D$8:$D$307,$E58) -> 6.48 | M58: =SUMIFS(CaseData!$G$8:$G$307,CaseData!$B$8:$B$307,M$5,CaseData!$C$8:$C$307,$D58,CaseData!$D$8:$D$307,$E58) -> 6.48 | N58: =SUMIFS(CaseData!$G$8:$G$307,CaseData!$B$8:$B$307,N$5,CaseData!$C$8:$C$307,$D58,CaseData!$D$8:$D$307,$E58) -> 6.48 | O58: =SUMIFS(CaseData!$G$8:$G$307,CaseData!$B$8:$B$307,O$5,CaseData!$C$8:$C$307,$D58,CaseData!$D$8:$D$307,$E58) -> 6.48 | P58: =SUMIFS(CaseData!$G$8:$G$307,CaseData!$B$8:$B$307,P$5,CaseData!$C$8:$C$307,$D58,CaseData!$D$8:$D$307,$E58) -> 6.48 | ... T58: =SUMIFS(CaseData!$G$8:$G$307,CaseData!$B$8:$B$307,T$5,CaseData!$C$8:$C$307,$D58,CaseData!$D$8:$D$307,$E58) -> 6.48 | U58: =I58*(1+$G58) -> 6.9336 | V58: =J58*(1+$G58) -> 6.9336 | W58: =K58*(1+$G58) -> 6.9336 | X58: =L58*(1+$G58) -> 6.9336 | Y58: =M58*(1+$G58) -> 6.9336 | Z58: =N58*(1+$G58) -> 6.9336 | AA58: =O58*(1+$G58) -> 6.9336 | AB58: =P58*(1+$G58) -> 6.9336 | ... AF58: =T58*(1+$G58) -> 6.9336
D59: =D$32 -> 5 | E59: =E$32 -> 5 | G59: =INDEX(CaseData!$N$8:$N$12,MATCH($E59,CaseData!$M$8:$M$12,0)) -> 0.05 | I59: =SUMIFS(CaseData!$G$8:$G$307,CaseData!$B$8:$B$307,I$5,CaseData!$C$8:$C$307,$D59,CaseData!$D$8:$D$307,$E59) -> 6.26 | J59: =SUMIFS(CaseData!$G$8:$G$307,CaseData!$B$8:$B$307,J$5,CaseData!$C$8:$C$307,$D59,CaseData!$D$8:$D$307,$E59) -> 6.26 | K59: =SUMIFS(CaseData!$G$8:$G$307,CaseData!$B$8:$B$307,K$5,CaseData!$C$8:$C$307,$D59,CaseData!$D$8:$D$307,$E59) -> 6.26 | L59: =SUMIFS(CaseData!$G$8:$G$307,CaseData!$B$8:$B$307,L$5,CaseData!$C$8:$C$307,$D59,CaseData!$D$8:$D$307,$E59) -> 6.26 | M59: =SUMIFS(CaseData!$G$8:$G$307,CaseData!$B$8:$B$307,M$5,CaseData!$C$8:$C$307,$D59,CaseData!$D$8:$D$307,$E59) -> 6.26 | N59: =SUMIFS(CaseData!$G$8:$G$307,CaseData!$B$8:$B$307,N$5,CaseData!$C$8:$C$307,$D59,CaseData!$D$8:$D$307,$E59) -> 6.26 | O59: =SUMIFS(CaseData!$G$8:$G$307,CaseData!$B$8:$B$307,O$5,CaseData!$C$8:$C$307,$D59,CaseData!$D$8:$D$307,$E59) -> 6.26 | P59: =SUMIFS(CaseData!$G$8:$G$307,CaseData!$B$8:$B$307,P$5,CaseData!$C$8:$C$307,$D59,CaseData!$D$8:$D$307,$E59) -> 6.26 | ... T59: =SUMIFS(CaseData!$G$8:$G$307,CaseData!$B$8:$B$307,T$5,CaseData!$C$8:$C$307,$D59,CaseData!$D$8:$D$307,$E59) -> 6.26 | U59: =I59*(1+$G59) -> 6.573 | V59: =J59*(1+$G59) -> 6.573 | W59: =K59*(1+$G59) -> 6.573 | X59: =L59*(1+$G59) -> 6.573 | Y59: =M59*(1+$G59) -> 6.573 | Z59: =N59*(1+$G59) -> 6.573 | AA59: =O59*(1+$G59) -> 6.573 | AB59: =P59*(1+$G59) -> 6.573 | ... AF59: =T59*(1+$G59) -> 6.573
B61: GP per unit
D62: =D$8 -> 1 | E62: =E$8 -> 1 | I62: =I8-I35 -> 15 | J62: =J8-J35 -> 15 | K62: =K8-K35 -> 15 | L62: =L8-L35 -> 15 | M62: =M8-M35 -> 15 | N62: =N8-N35 -> 15 | O62: =O8-O35 -> 15 | P62: =P8-P35 -> 15 | ... AF62: =AF8-AF35 -> 16.05
D63: =D$9 -> 1 | E63: =E$9 -> 2 | I63: =I9-I36 -> 9.69 | J63: =J9-J36 -> 9.69 | K63: =K9-K36 -> 9.69 | L63: =L9-L36 -> 9.69 | M63: =M9-M36 -> 9.69 | N63: =N9-N36 -> 9.69 | O63: =O9-O36 -> 9.69 | P63: =P9-P36 -> 9.69 | ... AF63: =AF9-AF36 -> 10.2221
D64: =D$10 -> 1 | E64: =E$10 -> 3 | I64: =I10-I37 -> 7.68 | J64: =J10-J37 -> 7.68 | K64: =K10-K37 -> 7.68 | L64: =L10-L37 -> 7.68 | M64: =M10-M37 -> 7.68 | N64: =N10-N37 -> 7.68 | O64: =O10-O37 -> 7.68 | P64: =P10-P37 -> 7.68 | ... AF64: =AF10-AF37 -> 8.1664
D65: =D$11 -> 1 | E65: =E$11 -> 4 | I65: =I11-I38 -> 4.32 | J65: =J11-J38 -> 4.32 | K65: =K11-K38 -> 4.32 | L65: =L11-L38 -> 4.32 | M65: =M11-M38 -> 4.32 | N65: =N11-N38 -> 4.32 | O65: =O11-O38 -> 4.32 | P65: =P11-P38 -> 4.32 | ... AF65: =AF11-AF38 -> 4.6224
D66: =D$12 -> 1 | E66: =E$12 -> 5 | I66: =I12-I39 -> 8.64 | J66: =J12-J39 -> 8.64 | K66: =K12-K39 -> 8.64 | L66: =L12-L39 -> 8.64 | M66: =M12-M39 -> 8.64 | N66: =N12-N39 -> 8.64 | O66: =O12-O39 -> 8.64 | P66: =P12-P39 -> 8.64 | ... AF66: =AF12-AF39 -> 9.37
D67: =D$13 -> 2 | E67: =E$13 -> 1 | I67: =I13-I40 -> 9 | J67: =J13-J40 -> 9 | K67: =K13-K40 -> 9 | L67: =L13-L40 -> 9 | M67: =M13-M40 -> 9 | N67: =N13-N40 -> 9 | O67: =O13-O40 -> 9 | P67: =P13-P40 -> 9 | ... AF67: =AF13-AF40 -> 9.29
D68: =D$14 -> 2 | E68: =E$14 -> 2 | I68: =I14-I41 -> 9.01 | J68: =J14-J41 -> 9.01 | K68: =K14-K41 -> 9.01 | L68: =L14-L41 -> 9.01 | M68: =M14-M41 -> 9.01 | N68: =N14-N41 -> 9.01 | O68: =O14-O41 -> 9.01 | P68: =P14-P41 -> 9.01 | ... AF68: =AF14-AF41 -> 9.3313
D69: =D$15 -> 2 | E69: =E$15 -> 3 | I69: =I15-I42 -> 9.09 | J69: =J15-J42 -> 9.09 | K69: =K15-K42 -> 9.09 | L69: =L15-L42 -> 9.09 | M69: =M15-M42 -> 9.09 | N69: =N15-N42 -> 9.09 | O69: =O15-O42 -> 9.09 | P69: =P15-P42 -> 9.09 | ... AF69: =AF15-AF42 -> 9.533
D70: =D$16 -> 2 | E70: =E$16 -> 4 | I70: =I16-I43 -> 3.35 | J70: =J16-J43 -> 3.35 | K70: =K16-K43 -> 3.35 | L70: =L16-L43 -> 3.35 | M70: =M16-M43 -> 3.35 | N70: =N16-N43 -> 3.35 | O70: =O16-O43 -> 3.35 | P70: =P16-P43 -> 3.35 | ... AF70: =AF16-AF43 -> 3.4862
D71: =D$17 -> 2 | E71: =E$17 -> 5 | I71: =I17-I44 -> 7.9 | J71: =J17-J44 -> 7.9 | K71: =K17-K44 -> 7.9 | L71: =L17-L44 -> 7.9 | M71: =M17-M44 -> 7.9 | N71: =N17-N44 -> 7.9 | O71: =O17-O44 -> 7.9 | P71: =P17-P44 -> 7.9 | ... AF71: =AF17-AF44 -> 8.4366
D72: =D$18 -> 3 | E72: =E$18 -> 1 | I72: =I18-I45 -> 14.6 | J72: =J18-J45 -> 14.6 | K72: =K18-K45 -> 14.6 | L72: =L18-L45 -> 14.6 | M72: =M18-M45 -> 14.6 | N72: =N18-N45 -> 14.6 | O72: =O18-O45 -> 14.6 | P72: =P18-P45 -> 14.6 | ... AF72: =AF18-AF45 -> 15.226
D73: =D$19 -> 3 | E73: =E$19 -> 2 | I73: =I19-I46 -> 10.54 | J73: =J19-J46 -> 10.54 | K73: =K19-K46 -> 10.54 | L73: =L19-L46 -> 10.54 | M73: =M19-M46 -> 10.54 | N73: =N19-N46 -> 10.54 | O73: =O19-O46 -> 10.54 | P73: =P19-P46 -> 10.54 | ... AF73: =AF19-AF46 -> 10.9531
D74: =D$20 -> 3 | E74: =E$20 -> 3 | I74: =I20-I47 -> 9.6 | J74: =J20-J47 -> 9.6 | K74: =K20-K47 -> 9.6 | L74: =L20-L47 -> 9.6 | M74: =M20-M47 -> 9.6 | N74: =N20-N47 -> 9.6 | O74: =O20-O47 -> 9.6 | P74: =P20-P47 -> 9.6 | ... AF74: =AF20-AF47 -> 10.0736
D75: =D$21 -> 3 | E75: =E$21 -> 4 | I75: =I21-I48 -> 4.32 | J75: =J21-J48 -> 4.32 | K75: =K21-K48 -> 4.32 | L75: =L21-L48 -> 4.32 | M75: =M21-M48 -> 4.32 | N75: =N21-N48 -> 4.32 | O75: =O21-O48 -> 4.32 | P75: =P21-P48 -> 4.32 | ... AF75: =AF21-AF48 -> 4.5144
D76: =D$22 -> 3 | E76: =E$22 -> 5 | I76: =I22-I49 -> 9.39 | J76: =J22-J49 -> 9.39 | K76: =K22-K49 -> 9.39 | L76: =L22-L49 -> 9.39 | M76: =M22-M49 -> 9.39 | N76: =N22-N49 -> 9.39 | O76: =O22-O49 -> 9.39 | P76: =P22-P49 -> 9.39 | ... AF76: =AF22-AF49 -> 10.016
D77: =D$23 -> 4 | E77: =E$23 -> 1 | I77: =I23-I50 -> 19.4 | J77: =J23-J50 -> 19.4 | K77: =K23-K50 -> 19.4 | L77: =L23-L50 -> 19.4 | M77: =M23-M50 -> 19.4 | N77: =N23-N50 -> 19.4 | O77: =O23-O50 -> 19.4 | P77: =P23-P50 -> 19.4 | ... AF77: =AF23-AF50 -> 21.202
D78: =D$24 -> 4 | E78: =E$24 -> 2 | I78: =I24-I51 -> 9.86 | J78: =J24-J51 -> 9.86 | K78: =K24-K51 -> 9.86 | L78: =L24-L51 -> 9.86 | M78: =M24-M51 -> 9.86 | N78: =N24-N51 -> 9.86 | O78: =O24-O51 -> 9.86 | P78: =P24-P51 -> 9.86 | ... AF78: =AF24-AF51 -> 10.5757
D79: =D$25 -> 4 | E79: =E$25 -> 3 | I79: =I25-I52 -> 8.45 | J79: =J25-J52 -> 8.45 | K79: =K25-K52 -> 8.45 | L79: =L25-L52 -> 8.45 | M79: =M25-M52 -> 8.45 | N79: =N25-N52 -> 8.45 | O79: =O25-O52 -> 8.45 | P79: =P25-P52 -> 8.45 | ... AF79: =AF25-AF52 -> 9.126
D80: =D$26 -> 4 | E80: =E$26 -> 4 | I80: =I26-I53 -> 5.94 | J80: =J26-J53 -> 5.94 | K80: =K26-K53 -> 5.94 | L80: =L26-L53 -> 5.94 | M80: =M26-M53 -> 5.94 | N80: =N26-N53 -> 5.94 | O80: =O26-O53 -> 5.94 | P80: =P26-P53 -> 5.94 | ... AF80: =AF26-AF53 -> 6.48
D81: =D$27 -> 4 | E81: =E$27 -> 5 | I81: =I27-I54 -> 7.9 | J81: =J27-J54 -> 7.9 | K81: =K27-K54 -> 7.9 | L81: =L27-L54 -> 7.9 | M81: =M27-M54 -> 7.9 | N81: =N27-N54 -> 7.9 | O81: =O27-O54 -> 7.9 | P81: =P27-P54 -> 7.9 | ... AF81: =AF27-AF54 -> 8.7198
D82: =D$28 -> 5 | E82: =E$28 -> 1 | I82: =I28-I55 -> 12.6 | J82: =J28-J55 -> 12.6 | K82: =K28-K55 -> 12.6 | L82: =L28-L55 -> 12.6 | M82: =M28-M55 -> 12.6 | N82: =N28-N55 -> 12.6 | O82: =O28-O55 -> 12.6 | P82: =P28-P55 -> 12.6 | ... AF82: =AF28-AF55 -> 13.482
D83: =D$29 -> 5 | E83: =E$29 -> 2 | I83: =I29-I56 -> 7.82 | J83: =J29-J56 -> 7.82 | K83: =K29-K56 -> 7.82 | L83: =L29-L56 -> 7.82 | M83: =M29-M56 -> 7.82 | N83: =N29-N56 -> 7.82 | O83: =O29-O56 -> 7.82 | P83: =P29-P56 -> 7.82 | ... AF83: =AF29-AF56 -> 8.2212
D84: =D$30 -> 5 | E84: =E$30 -> 3 | I84: =I30-I57 -> 7.94 | J84: =J30-J57 -> 7.94 | K84: =K30-K57 -> 7.94 | L84: =L30-L57 -> 7.94 | M84: =M30-M57 -> 7.94 | N84: =N30-N57 -> 7.94 | O84: =O30-O57 -> 7.94 | P84: =P30-P57 -> 7.94 | ... AF84: =AF30-AF57 -> 8.4446
D85: =D$31 -> 5 | E85: =E$31 -> 4 | I85: =I31-I58 -> 3.13 | J85: =J31-J58 -> 3.13 | K85: =K31-K58 -> 3.13 | L85: =L31-L58 -> 3.13 | M85: =M31-M58 -> 3.13 | N85: =N31-N58 -> 3.13 | O85: =O31-O58 -> 3.13 | P85: =P31-P58 -> 3.13 | ... AF85: =AF31-AF58 -> 3.3491
D86: =D$32 -> 5 | E86: =E$32 -> 5 | I86: =I32-I59 -> 6.41 | J86: =J32-J59 -> 6.41 | K86: =K32-K59 -> 6.41 | L86: =L32-L59 -> 6.41 | M86: =M32-M59 -> 6.41 | N86: =N32-N59 -> 6.41 | O86: =O32-O59 -> 6.41 | P86: =P32-P59 -> 6.41 | ... AF86: =AF32-AF59 -> 6.9839
B88: Profitability Rank (using GP per Unit)
D89: =D$8 -> 1 | E89: =E$8 -> 1 | I89: =RANK(I62,I$62:I$86) -> 2 | J89: =RANK(J62,J$62:J$86) -> 2 | K89: =RANK(K62,K$62:K$86) -> 2 | L89: =RANK(L62,L$62:L$86) -> 2 | M89: =RANK(M62,M$62:M$86) -> 2 | N89: =RANK(N62,N$62:N$86) -> 2 | O89: =RANK(O62,O$62:O$86) -> 2 | P89: =RANK(P62,P$62:P$86) -> 2 | ... AF89: =RANK(AF62,AF$62:AF$86) -> 2
D90: =D$9 -> 1 | E90: =E$9 -> 2 | I90: =RANK(I63,I$62:I$86) -> 7 | J90: =RANK(J63,J$62:J$86) -> 7 | K90: =RANK(K63,K$62:K$86) -> 7 | L90: =RANK(L63,L$62:L$86) -> 7 | M90: =RANK(M63,M$62:M$86) -> 7 | N90: =RANK(N63,N$62:N$86) -> 7 | O90: =RANK(O63,O$62:O$86) -> 7 | P90: =RANK(P63,P$62:P$86) -> 7 | ... AF90: =RANK(AF63,AF$62:AF$86) -> 7
D91: =D$10 -> 1 | E91: =E$10 -> 3 | I91: =RANK(I64,I$62:I$86) -> 19 | J91: =RANK(J64,J$62:J$86) -> 19 | K91: =RANK(K64,K$62:K$86) -> 19 | L91: =RANK(L64,L$62:L$86) -> 19 | M91: =RANK(M64,M$62:M$86) -> 19 | N91: =RANK(N64,N$62:N$86) -> 19 | O91: =RANK(O64,O$62:O$86) -> 19 | P91: =RANK(P64,P$62:P$86) -> 19 | ... AF91: =RANK(AF64,AF$62:AF$86) -> 19
D92: =D$11 -> 1 | E92: =E$11 -> 4 | I92: =RANK(I65,I$62:I$86) -> 22 | J92: =RANK(J65,J$62:J$86) -> 22 | K92: =RANK(K65,K$62:K$86) -> 22 | L92: =RANK(L65,L$62:L$86) -> 22 | M92: =RANK(M65,M$62:M$86) -> 22 | N92: =RANK(N65,N$62:N$86) -> 22 | O92: =RANK(O65,O$62:O$86) -> 22 | P92: =RANK(P65,P$62:P$86) -> 22 | ... AF92: =RANK(AF65,AF$62:AF$86) -> 22
D93: =D$12 -> 1 | E93: =E$12 -> 5 | I93: =RANK(I66,I$62:I$86) -> 13 | J93: =RANK(J66,J$62:J$86) -> 13 | K93: =RANK(K66,K$62:K$86) -> 13 | L93: =RANK(L66,L$62:L$86) -> 13 | M93: =RANK(M66,M$62:M$86) -> 13 | N93: =RANK(N66,N$62:N$86) -> 13 | O93: =RANK(O66,O$62:O$86) -> 13 | P93: =RANK(P66,P$62:P$86) -> 13 | ... AF93: =RANK(AF66,AF$62:AF$86) -> 11
D94: =D$13 -> 2 | E94: =E$13 -> 1 | I94: =RANK(I67,I$62:I$86) -> 12 | J94: =RANK(J67,J$62:J$86) -> 12 | K94: =RANK(K67,K$62:K$86) -> 12 | L94: =RANK(L67,L$62:L$86) -> 12 | M94: =RANK(M67,M$62:M$86) -> 12 | N94: =RANK(N67,N$62:N$86) -> 12 | O94: =RANK(O67,O$62:O$86) -> 12 | P94: =RANK(P67,P$62:P$86) -> 12 | ... AF94: =RANK(AF67,AF$62:AF$86) -> 13
D95: =D$14 -> 2 | E95: =E$14 -> 2 | I95: =RANK(I68,I$62:I$86) -> 11 | J95: =RANK(J68,J$62:J$86) -> 11 | K95: =RANK(K68,K$62:K$86) -> 11 | L95: =RANK(L68,L$62:L$86) -> 11 | M95: =RANK(M68,M$62:M$86) -> 11 | N95: =RANK(N68,N$62:N$86) -> 11 | O95: =RANK(O68,O$62:O$86) -> 11 | P95: =RANK(P68,P$62:P$86) -> 11 | ... AF95: =RANK(AF68,AF$62:AF$86) -> 12
D96: =D$15 -> 2 | E96: =E$15 -> 3 | I96: =RANK(I69,I$62:I$86) -> 10 | J96: =RANK(J69,J$62:J$86) -> 10 | K96: =RANK(K69,K$62:K$86) -> 10 | L96: =RANK(L69,L$62:L$86) -> 10 | M96: =RANK(M69,M$62:M$86) -> 10 | N96: =RANK(N69,N$62:N$86) -> 10 | O96: =RANK(O69,O$62:O$86) -> 10 | P96: =RANK(P69,P$62:P$86) -> 10 | ... AF96: =RANK(AF69,AF$62:AF$86) -> 10
D97: =D$16 -> 2 | E97: =E$16 -> 4 | I97: =RANK(I70,I$62:I$86) -> 24 | J97: =RANK(J70,J$62:J$86) -> 24 | K97: =RANK(K70,K$62:K$86) -> 24 | L97: =RANK(L70,L$62:L$86) -> 24 | M97: =RANK(M70,M$62:M$86) -> 24 | N97: =RANK(N70,N$62:N$86) -> 24 | O97: =RANK(O70,O$62:O$86) -> 24 | P97: =RANK(P70,P$62:P$86) -> 24 | ... AF97: =RANK(AF70,AF$62:AF$86) -> 24
D98: =D$17 -> 2 | E98: =E$17 -> 5 | I98: =RANK(I71,I$62:I$86) -> 16 | J98: =RANK(J71,J$62:J$86) -> 16 | K98: =RANK(K71,K$62:K$86) -> 16 | L98: =RANK(L71,L$62:L$86) -> 16 | M98: =RANK(M71,M$62:M$86) -> 16 | N98: =RANK(N71,N$62:N$86) -> 16 | O98: =RANK(O71,O$62:O$86) -> 16 | P98: =RANK(P71,P$62:P$86) -> 16 | ... AF98: =RANK(AF71,AF$62:AF$86) -> 17
D99: =D$18 -> 3 | E99: =E$18 -> 1 | I99: =RANK(I72,I$62:I$86) -> 3 | J99: =RANK(J72,J$62:J$86) -> 3 | K99: =RANK(K72,K$62:K$86) -> 3 | L99: =RANK(L72,L$62:L$86) -> 3 | M99: =RANK(M72,M$62:M$86) -> 3 | N99: =RANK(N72,N$62:N$86) -> 3 | O99: =RANK(O72,O$62:O$86) -> 3 | P99: =RANK(P72,P$62:P$86) -> 3 | ... AF99: =RANK(AF72,AF$62:AF$86) -> 3
D100: =D$19 -> 3 | E100: =E$19 -> 2 | I100: =RANK(I73,I$62:I$86) -> 5 | J100: =RANK(J73,J$62:J$86) -> 5 | K100: =RANK(K73,K$62:K$86) -> 5 | L100: =RANK(L73,L$62:L$86) -> 5 | M100: =RANK(M73,M$62:M$86) -> 5 | N100: =RANK(N73,N$62:N$86) -> 5 | O100: =RANK(O73,O$62:O$86) -> 5 | P100: =RANK(P73,P$62:P$86) -> 5 | ... AF100: =RANK(AF73,AF$62:AF$86) -> 5
D101: =D$20 -> 3 | E101: =E$20 -> 3 | I101: =RANK(I74,I$62:I$86) -> 8 | J101: =RANK(J74,J$62:J$86) -> 8 | K101: =RANK(K74,K$62:K$86) -> 8 | L101: =RANK(L74,L$62:L$86) -> 8 | M101: =RANK(M74,M$62:M$86) -> 8 | N101: =RANK(N74,N$62:N$86) -> 8 | O101: =RANK(O74,O$62:O$86) -> 8 | P101: =RANK(P74,P$62:P$86) -> 8 | ... AF101: =RANK(AF74,AF$62:AF$86) -> 8
D102: =D$21 -> 3 | E102: =E$21 -> 4 | I102: =RANK(I75,I$62:I$86) -> 22 | J102: =RANK(J75,J$62:J$86) -> 22 | K102: =RANK(K75,K$62:K$86) -> 22 | L102: =RANK(L75,L$62:L$86) -> 22 | M102: =RANK(M75,M$62:M$86) -> 22 | N102: =RANK(N75,N$62:N$86) -> 22 | O102: =RANK(O75,O$62:O$86) -> 22 | P102: =RANK(P75,P$62:P$86) -> 22 | ... AF102: =RANK(AF75,AF$62:AF$86) -> 23
D103: =D$22 -> 3 | E103: =E$22 -> 5 | I103: =RANK(I76,I$62:I$86) -> 9 | J103: =RANK(J76,J$62:J$86) -> 9 | K103: =RANK(K76,K$62:K$86) -> 9 | L103: =RANK(L76,L$62:L$86) -> 9 | M103: =RANK(M76,M$62:M$86) -> 9 | N103: =RANK(N76,N$62:N$86) -> 9 | O103: =RANK(O76,O$62:O$86) -> 9 | P103: =RANK(P76,P$62:P$86) -> 9 | ... AF103: =RANK(AF76,AF$62:AF$86) -> 9
D104: =D$23 -> 4 | E104: =E$23 -> 1 | I104: =RANK(I77,I$62:I$86) -> 1 | J104: =RANK(J77,J$62:J$86) -> 1 | K104: =RANK(K77,K$62:K$86) -> 1 | L104: =RANK(L77,L$62:L$86) -> 1 | M104: =RANK(M77,M$62:M$86) -> 1 | N104: =RANK(N77,N$62:N$86) -> 1 | O104: =RANK(O77,O$62:O$86) -> 1 | P104: =RANK(P77,P$62:P$86) -> 1 | ... AF104: =RANK(AF77,AF$62:AF$86) -> 1
D105: =D$24 -> 4 | E105: =E$24 -> 2 | I105: =RANK(I78,I$62:I$86) -> 6 | J105: =RANK(J78,J$62:J$86) -> 6 | K105: =RANK(K78,K$62:K$86) -> 6 | L105: =RANK(L78,L$62:L$86) -> 6 | M105: =RANK(M78,M$62:M$86) -> 6 | N105: =RANK(N78,N$62:N$86) -> 6 | O105: =RANK(O78,O$62:O$86) -> 6 | P105: =RANK(P78,P$62:P$86) -> 6 | ... AF105: =RANK(AF78,AF$62:AF$86) -> 6
D106: =D$25 -> 4 | E106: =E$25 -> 3 | I106: =RANK(I79,I$62:I$86) -> 14 | J106: =RANK(J79,J$62:J$86) -> 14 | K106: =RANK(K79,K$62:K$86) -> 14 | L106: =RANK(L79,L$62:L$86) -> 14 | M106: =RANK(M79,M$62:M$86) -> 14 | N106: =RANK(N79,N$62:N$86) -> 14 | O106: =RANK(O79,O$62:O$86) -> 14 | P106: =RANK(P79,P$62:P$86) -> 14 | ... AF106: =RANK(AF79,AF$62:AF$86) -> 14
D107: =D$26 -> 4 | E107: =E$26 -> 4 | I107: =RANK(I80,I$62:I$86) -> 21 | J107: =RANK(J80,J$62:J$86) -> 21 | K107: =RANK(K80,K$62:K$86) -> 21 | L107: =RANK(L80,L$62:L$86) -> 21 | M107: =RANK(M80,M$62:M$86) -> 21 | N107: =RANK(N80,N$62:N$86) -> 21 | O107: =RANK(O80,O$62:O$86) -> 21 | P107: =RANK(P80,P$62:P$86) -> 21 | ... AF107: =RANK(AF80,AF$62:AF$86) -> 21
D108: =D$27 -> 4 | E108: =E$27 -> 5 | I108: =RANK(I81,I$62:I$86) -> 16 | J108: =RANK(J81,J$62:J$86) -> 16 | K108: =RANK(K81,K$62:K$86) -> 16 | L108: =RANK(L81,L$62:L$86) -> 16 | M108: =RANK(M81,M$62:M$86) -> 16 | N108: =RANK(N81,N$62:N$86) -> 16 | O108: =RANK(O81,O$62:O$86) -> 16 | P108: =RANK(P81,P$62:P$86) -> 16 | ... AF108: =RANK(AF81,AF$62:AF$86) -> 15
D109: =D$28 -> 5 | E109: =E$28 -> 1 | I109: =RANK(I82,I$62:I$86) -> 4 | J109: =RANK(J82,J$62:J$86) -> 4 | K109: =RANK(K82,K$62:K$86) -> 4 | L109: =RANK(L82,L$62:L$86) -> 4 | M109: =RANK(M82,M$62:M$86) -> 4 | N109: =RANK(N82,N$62:N$86) -> 4 | O109: =RANK(O82,O$62:O$86) -> 4 | P109: =RANK(P82,P$62:P$86) -> 4 | ... AF109: =RANK(AF82,AF$62:AF$86) -> 4
D110: =D$29 -> 5 | E110: =E$29 -> 2 | I110: =RANK(I83,I$62:I$86) -> 18 | J110: =RANK(J83,J$62:J$86) -> 18 | K110: =RANK(K83,K$62:K$86) -> 18 | L110: =RANK(L83,L$62:L$86) -> 18 | M110: =RANK(M83,M$62:M$86) -> 18 | N110: =RANK(N83,N$62:N$86) -> 18 | O110: =RANK(O83,O$62:O$86) -> 18 | P110: =RANK(P83,P$62:P$86) -> 18 | ... AF110: =RANK(AF83,AF$62:AF$86) -> 18
D111: =D$30 -> 5 | E111: =E$30 -> 3 | I111: =RANK(I84,I$62:I$86) -> 15 | J111: =RANK(J84,J$62:J$86) -> 15 | K111: =RANK(K84,K$62:K$86) -> 15 | L111: =RANK(L84,L$62:L$86) -> 15 | M111: =RANK(M84,M$62:M$86) -> 15 | N111: =RANK(N84,N$62:N$86) -> 15 | O111: =RANK(O84,O$62:O$86) -> 15 | P111: =RANK(P84,P$62:P$86) -> 15 | ... AF111: =RANK(AF84,AF$62:AF$86) -> 16
D112: =D$31 -> 5 | E112: =E$31 -> 4 | I112: =RANK(I85,I$62:I$86) -> 25 | J112: =RANK(J85,J$62:J$86) -> 25 | K112: =RANK(K85,K$62:K$86) -> 25 | L112: =RANK(L85,L$62:L$86) -> 25 | M112: =RANK(M85,M$62:M$86) -> 25 | N112: =RANK(N85,N$62:N$86) -> 25 | O112: =RANK(O85,O$62:O$86) -> 25 | P112: =RANK(P85,P$62:P$86) -> 25 | ... AF112: =RANK(AF85,AF$62:AF$86) -> 25
D113: =D$32 -> 5 | E113: =E$32 -> 5 | I113: =RANK(I86,I$62:I$86) -> 20 | J113: =RANK(J86,J$62:J$86) -> 20 | K113: =RANK(K86,K$62:K$86) -> 20 | L113: =RANK(L86,L$62:L$86) -> 20 | M113: =RANK(M86,M$62:M$86) -> 20 | N113: =RANK(N86,N$62:N$86) -> 20 | O113: =RANK(O86,O$62:O$86) -> 20 | P113: =RANK(P86,P$62:P$86) -> 20 | ... AF113: =RANK(AF86,AF$62:AF$86) -> 20
B115: Volume
B117: Demand
D118: =D$8 -> 1 | E118: =E$8 -> 1 | G118: =INDEX(CaseData!$J$8:$J$12,MATCH("Client "&$D118,CaseData!$I$8:$I$12,0)) -> 0.02 | I118: =SUMIFS(CaseData!$E$8:$E$307,CaseData!$B$8:$B$307,I$5,CaseData!$C$8:$C$307,$D118,CaseData!$D$8:$D$307,$E118) -> 10438 | J118: =SUMIFS(CaseData!$E$8:$E$307,CaseData!$B$8:$B$307,J$5,CaseData!$C$8:$C$307,$D118,CaseData!$D$8:$D$307,$E118) -> 4960 | K118: =SUMIFS(CaseData!$E$8:$E$307,CaseData!$B$8:$B$307,K$5,CaseData!$C$8:$C$307,$D118,CaseData!$D$8:$D$307,$E118) -> 4960 | L118: =SUMIFS(CaseData!$E$8:$E$307,CaseData!$B$8:$B$307,L$5,CaseData!$C$8:$C$307,$D118,CaseData!$D$8:$D$307,$E118) -> 5920 | M118: =SUMIFS(CaseData!$E$8:$E$307,CaseData!$B$8:$B$307,M$5,CaseData!$C$8:$C$307,$D118,CaseData!$D$8:$D$307,$E118) -> 4400 | N118: =SUMIFS(CaseData!$E$8:$E$307,CaseData!$B$8:$B$307,N$5,CaseData!$C$8:$C$307,$D118,CaseData!$D$8:$D$307,$E118) -> 5120 | O118: =SUMIFS(CaseData!$E$8:$E$307,CaseData!$B$8:$B$307,O$5,CaseData!$C$8:$C$307,$D118,CaseData!$D$8:$D$307,$E118) -> 5680 | P118: =SUMIFS(CaseData!$E$8:$E$307,CaseData!$B$8:$B$307,P$5,CaseData!$C$8:$C$307,$D118,CaseData!$D$8:$D$307,$E118) -> 11920 | ... T118: =SUMIFS(CaseData!$E$8:$E$307,CaseData!$B$8:$B$307,T$5,CaseData!$C$8:$C$307,$D118,CaseData!$D$8:$D$307,$E118) -> 11840 | U118: =I118*(1+$G118) -> 10646.76 | V118: =J118*(1+$G118) -> 5059.2 | W118: =K118*(1+$G118) -> 5059.2 | X118: =L118*(1+$G118) -> 6038.4 | Y118: =M118*(1+$G118) -> 4488 | Z118: =N118*(1+$G118) -> 5222.4 | AA118: =O118*(1+$G118) -> 5793.6 | AB118: =P118*(1+$G118) -> 12158.4 | ... AF118: =T118*(1+$G118) -> 12076.8
D119: =D$9 -> 1 | E119: =E$9 -> 2 | G119: =INDEX(CaseData!$J$8:$J$12,MATCH("Client "&$D119,CaseData!$I$8:$I$12,0)) -> 0.02 | I119: =SUMIFS(CaseData!$E$8:$E$307,CaseData!$B$8:$B$307,I$5,CaseData!$C$8:$C$307,$D119,CaseData!$D$8:$D$307,$E119) -> 516 | J119: =SUMIFS(CaseData!$E$8:$E$307,CaseData!$B$8:$B$307,J$5,CaseData!$C$8:$C$307,$D119,CaseData!$D$8:$D$307,$E119) -> 1222 | K119: =SUMIFS(CaseData!$E$8:$E$307,CaseData!$B$8:$B$307,K$5,CaseData!$C$8:$C$307,$D119,CaseData!$D$8:$D$307,$E119) -> 1110 | L119: =SUMIFS(CaseData!$E$8:$E$307,CaseData!$B$8:$B$307,L$5,CaseData!$C$8:$C$307,$D119,CaseData!$D$8:$D$307,$E119) -> 1084 | M119: =SUMIFS(CaseData!$E$8:$E$307,CaseData!$B$8:$B$307,M$5,CaseData!$C$8:$C$307,$D119,CaseData!$D$8:$D$307,$E119) -> 1264 | N119: =SUMIFS(CaseData!$E$8:$E$307,CaseData!$B$8:$B$307,N$5,CaseData!$C$8:$C$307,$D119,CaseData!$D$8:$D$307,$E119) -> 606 | O119: =SUMIFS(CaseData!$E$8:$E$307,CaseData!$B$8:$B$307,O$5,CaseData!$C$8:$C$307,$D119,CaseData!$D$8:$D$307,$E119) -> 930 | P119: =SUMIFS(CaseData!$E$8:$E$307,CaseData!$B$8:$B$307,P$5,CaseData!$C$8:$C$307,$D119,CaseData!$D$8:$D$307,$E119) -> 760 | ... T119: =SUMIFS(CaseData!$E$8:$E$307,CaseData!$B$8:$B$307,T$5,CaseData!$C$8:$C$307,$D119,CaseData!$D$8:$D$307,$E119) -> 718 | U119: =I119*(1+$G119) -> 526.32 | V119: =J119*(1+$G119) -> 1246.44 | W119: =K119*(1+$G119) -> 1132.2 | X119: =L119*(1+$G119) -> 1105.68 | Y119: =M119*(1+$G119) -> 1289.28 | Z119: =N119*(1+$G119) -> 618.12 | AA119: =O119*(1+$G119) -> 948.6 | AB119: =P119*(1+$G119) -> 775.2 | ... AF119: =T119*(1+$G119) -> 732.36
D120: =D$10 -> 1 | E120: =E$10 -> 3 | G120: =INDEX(CaseData!$J$8:$J$12,MATCH("Client "&$D120,CaseData!$I$8:$I$12,0)) -> 0.02 | I120: =SUMIFS(CaseData!$E$8:$E$307,CaseData!$B$8:$B$307,I$5,CaseData!$C$8:$C$307,$D120,CaseData!$D$8:$D$307,$E120) -> 24860 | J120: =SUMIFS(CaseData!$E$8:$E$307,CaseData!$B$8:$B$307,J$5,CaseData!$C$8:$C$307,$D120,CaseData!$D$8:$D$307,$E120) -> 28698 | K120: =SUMIFS(CaseData!$E$8:$E$307,CaseData!$B$8:$B$307,K$5,CaseData!$C$8:$C$307,$D120,CaseData!$D$8:$D$307,$E120) -> 17784 | L120: =SUMIFS(CaseData!$E$8:$E$307,CaseData!$B$8:$B$307,L$5,CaseData!$C$8:$C$307,$D120,CaseData!$D$8:$D$307,$E120) -> 11722 | M120: =SUMIFS(CaseData!$E$8:$E$307,CaseData!$B$8:$B$307,M$5,CaseData!$C$8:$C$307,$D120,CaseData!$D$8:$D$307,$E120) -> 30112 | N120: =SUMIFS(CaseData!$E$8:$E$307,CaseData!$B$8:$B$307,N$5,CaseData!$C$8:$C$307,$D120,CaseData!$D$8:$D$307,$E120) -> 23444 | O120: =SUMIFS(CaseData!$E$8:$E$307,CaseData!$B$8:$B$307,O$5,CaseData!$C$8:$C$307,$D120,CaseData!$D$8:$D$307,$E120) -> 10712 | P120: =SUMIFS(CaseData!$E$8:$E$307,CaseData!$B$8:$B$307,P$5,CaseData!$C$8:$C$307,$D120,CaseData!$D$8:$D$307,$E120) -> 19200 | ... T120: =SUMIFS(CaseData!$E$8:$E$307,CaseData!$B$8:$B$307,T$5,CaseData!$C$8:$C$307,$D120,CaseData!$D$8:$D$307,$E120) -> 15966 | U120: =I120*(1+$G120) -> 25357.2 | V120: =J120*(1+$G120) -> 29271.96 | W120: =K120*(1+$G120) -> 18139.68 | X120: =L120*(1+$G120) -> 11956.44 | Y120: =M120*(1+$G120) -> 30714.24 | Z120: =N120*(1+$G120) -> 23912.88 | AA120: =O120*(1+$G120) -> 10926.24 | AB120: =P120*(1+$G120) -> 19584 | ... AF120: =T120*(1+$G120) -> 16285.32
...

Sheet CaseSolution - Summary
B2: =CaseData!B2 -> Big Fish Co.
B3: Summary
E5: ='CaseSolution - Calculations'!U5 -> 43861 | F5: ='CaseSolution - Calculations'!V5 -> 43890 | G5: ='CaseSolution - Calculations'!W5 -> 43921 | H5: ='CaseSolution - Calculations'!X5 -> 43951 | I5: ='CaseSolution - Calculations'!Y5 -> 43982 | J5: ='CaseSolution - Calculations'!Z5 -> 44012 | K5: ='CaseSolution - Calculations'!AA5 -> 44043 | L5: ='CaseSolution - Calculations'!AB5 -> 44074 | ... P5: ='CaseSolution - Calculations'!AF5 -> 44196 | Q5: Total | R5: Rank
B7: Sales by Client
B9: 1 | C9: ="Client "&B9 -> Client 1 | E9: =SUMIF('CaseSolution - Calculations'!$D$233:$D$257,$B9,'CaseSolution - Calculations'!U$233:U$257) -> 465255.09 | F9: =SUMIF('CaseSolution - Calculations'!$D$233:$D$257,$B9,'CaseSolution - Calculations'!V$233:V$257) -> 239206.5 | G9: =SUMIF('CaseSolution - Calculations'!$D$233:$D$257,$B9,'CaseSolution - Calculations'!W$233:W$257) -> 237128.48 | H9: =SUMIF('CaseSolution - Calculations'!$D$233:$D$257,$B9,'CaseSolution - Calculations'!X$233:X$257) -> 278555.84 | I9: =SUMIF('CaseSolution - Calculations'!$D$233:$D$257,$B9,'CaseSolution - Calculations'!Y$233:Y$257) -> 353406.45 | J9: =SUMIF('CaseSolution - Calculations'!$D$233:$D$257,$B9,'CaseSolution - Calculations'!Z$233:Z$257) -> 455370.72 | K9: =SUMIF('CaseSolution - Calculations'!$D$233:$D$257,$B9,'CaseSolution - Calculations'!AA$233:AA$257) -> 445532.62 | L9: =SUMIF('CaseSolution - Calculations'!$D$233:$D$257,$B9,'CaseSolution - Calculations'!AB$233:AB$257) -> 534480.41 | ... P9: =SUMIF('CaseSolution - Calculations'!$D$233:$D$257,$B9,'CaseSolution - Calculations'!AF$233:AF$257) -> 530208.67 | Q9: =SUM(E9:P9) -> 4738211.4 | R9: =RANK(Q9,$Q$9:$Q$13)+COUNTIF(Q$9:Q9, Q9)-1 -> 3 | S9: <<-- Note rank adjustment made to ensure unique ranks for each section
B10: 2 | C10: ="Client "&B10 -> Client 2 | E10: =SUMIF('CaseSolution - Calculations'!$D$233:$D$257,$B10,'CaseSolution - Calculations'!U$233:U$257) -> 196205.13 | F10: =SUMIF('CaseSolution - Calculations'!$D$233:$D$257,$B10,'CaseSolution - Calculations'!V$233:V$257) -> 205465.91 | G10: =SUMIF('CaseSolution - Calculations'!$D$233:$D$257,$B10,'CaseSolution - Calculations'!W$233:W$257) -> 88478.315 | H10: =SUMIF('CaseSolution - Calculations'!$D$233:$D$257,$B10,'CaseSolution - Calculations'!X$233:X$257) -> 0 | I10: =SUMIF('CaseSolution - Calculations'!$D$233:$D$257,$B10,'CaseSolution - Calculations'!Y$233:Y$257) -> 356951.62 | J10: =SUMIF('CaseSolution - Calculations'!$D$233:$D$257,$B10,'CaseSolution - Calculations'!Z$233:Z$257) -> 408808.04 | K10: =SUMIF('CaseSolution - Calculations'!$D$233:$D$257,$B10,'CaseSolution - Calculations'!AA$233:AA$257) -> 478364.3 | L10: =SUMIF('CaseSolution - Calculations'!$D$233:$D$257,$B10,'CaseSolution - Calculations'!AB$233:AB$257) -> 379898.96 | ... P10: =SUMIF('CaseSolution - Calculations'!$D$233:$D$257,$B10,'CaseSolution - Calculations'!AF$233:AF$257) -> 489225.72 | Q10: =SUM(E10:P10) -> 3057575.4 | R10: =RANK(Q10,$Q$9:$Q$13)+COUNTIF(Q$9:Q10, Q10)-1 -> 4
B11: 3 | C11: ="Client "&B11 -> Client 3 | E11: =SUMIF('CaseSolution - Calculations'!$D$233:$D$257,$B11,'CaseSolution - Calculations'!U$233:U$257) -> 1008120 | F11: =SUMIF('CaseSolution - Calculations'!$D$233:$D$257,$B11,'CaseSolution - Calculations'!V$233:V$257) -> 1166334.6 | G11: =SUMIF('CaseSolution - Calculations'!$D$233:$D$257,$B11,'CaseSolution - Calculations'!W$233:W$257) -> 1113695.8 | H11: =SUMIF('CaseSolution - Calculations'!$D$233:$D$257,$B11,'CaseSolution - Calculations'!X$233:X$257) -> 971973.94 | I11: =SUMIF('CaseSolution - Calculations'!$D$233:$D$257,$B11,'CaseSolution - Calculations'!Y$233:Y$257) -> 1094743.3 | J11: =SUMIF('CaseSolution - Calculations'!$D$233:$D$257,$B11,'CaseSolution - Calculations'!Z$233:Z$257) -> 947009.91 | K11: =SUMIF('CaseSolution - Calculations'!$D$233:$D$257,$B11,'CaseSolution - Calculations'!AA$233:AA$257) -> 884676.63 | L11: =SUMIF('CaseSolution - Calculations'!$D$233:$D$257,$B11,'CaseSolution - Calculations'!AB$233:AB$257) -> 716452.51 | ... P11: =SUMIF('CaseSolution - Calculations'!$D$233:$D$257,$B11,'CaseSolution - Calculations'!AF$233:AF$257) -> 887082.2 | Q11: =SUM(E11:P11) -> 12009800 | R11: =RANK(Q11,$Q$9:$Q$13)+COUNTIF(Q$9:Q11, Q11)-1 -> 2
B12: 4 | C12: ="Client "&B12 -> Client 4 | E12: =SUMIF('CaseSolution - Calculations'!$D$233:$D$257,$B12,'CaseSolution - Calculations'!U$233:U$257) -> 2609106.4 | F12: =SUMIF('CaseSolution - Calculations'!$D$233:$D$257,$B12,'CaseSolution - Calculations'!V$233:V$257) -> 2016183.1 | G12: =SUMIF('CaseSolution - Calculations'!$D$233:$D$257,$B12,'CaseSolution - Calculations'!W$233:W$257) -> 2617854.2 | H12: =SUMIF('CaseSolution - Calculations'!$D$233:$D$257,$B12,'CaseSolution - Calculations'!X$233:X$257) -> 3339089.9 | I12: =SUMIF('CaseSolution - Calculations'!$D$233:$D$257,$B12,'CaseSolution - Calculations'!Y$233:Y$257) -> 1965966 | J12: =SUMIF('CaseSolution - Calculations'!$D$233:$D$257,$B12,'CaseSolution - Calculations'!Z$233:Z$257) -> 1920737 | K12: =SUMIF('CaseSolution - Calculations'!$D$233:$D$257,$B12,'CaseSolution - Calculations'!AA$233:AA$257) -> 1715634.6 | L12: =SUMIF('CaseSolution - Calculations'!$D$233:$D$257,$B12,'CaseSolution - Calculations'!AB$233:AB$257) -> 2755115.8 | ... P12: =SUMIF('CaseSolution - Calculations'!$D$233:$D$257,$B12,'CaseSolution - Calculations'!AF$233:AF$257) -> 1779514.4 | Q12: =SUM(E12:P12) -> 28589247 | R12: =RANK(Q12,$Q$9:$Q$13)+COUNTIF(Q$9:Q12, Q12)-1 -> 1
B13: 5 | C13: ="Client "&B13 -> Client 5 | E13: =SUMIF('CaseSolution - Calculations'!$D$233:$D$257,$B13,'CaseSolution - Calculations'!U$233:U$257) -> 201000.68 | F13: =SUMIF('CaseSolution - Calculations'!$D$233:$D$257,$B13,'CaseSolution - Calculations'!V$233:V$257) -> 336551.94 | G13: =SUMIF('CaseSolution - Calculations'!$D$233:$D$257,$B13,'CaseSolution - Calculations'!W$233:W$257) -> 336551.94 | H13: =SUMIF('CaseSolution - Calculations'!$D$233:$D$257,$B13,'CaseSolution - Calculations'!X$233:X$257) -> 292156.74 | I13: =SUMIF('CaseSolution - Calculations'!$D$233:$D$257,$B13,'CaseSolution - Calculations'!Y$233:Y$257) -> 228994.11 | J13: =SUMIF('CaseSolution - Calculations'!$D$233:$D$257,$B13,'CaseSolution - Calculations'!Z$233:Z$257) -> 247682.68 | K13: =SUMIF('CaseSolution - Calculations'!$D$233:$D$257,$B13,'CaseSolution - Calculations'!AA$233:AA$257) -> 238377.82 | L13: =SUMIF('CaseSolution - Calculations'!$D$233:$D$257,$B13,'CaseSolution - Calculations'!AB$233:AB$257) -> 140203.69 | ... P13: =SUMIF('CaseSolution - Calculations'!$D$233:$D$257,$B13,'CaseSolution - Calculations'!AF$233:AF$257) -> 156605.47 | Q13: =SUM(E13:P13) -> 2692257.9 | R13: =RANK(Q13,$Q$9:$Q$13)+COUNTIF(Q$9:Q13, Q13)-1 -> 5
C14: Total | E14: =SUM(E9:E13) -> 4479687.3 | F14: =SUM(F9:F13) -> 3963742 | G14: =SUM(G9:G13) -> 4393708.7 | H14: =SUM(H9:H13) -> 4881776.4 | I14: =SUM(I9:I13) -> 4000061.4 | J14: =SUM(J9:J13) -> 3979608.4 | K14: =SUM(K9:K13) -> 3762586 | L14: =SUM(L9:L13) -> 4526151.4 | ... Q14: =SUM(Q9:Q13) -> 51087091
B16: Ranked
B17: 1 | C17: =INDEX(C$9:C$13,MATCH($B17,$R$9:$R$13,0)) -> Client 4 | E17: =INDEX(E$9:E$13,MATCH($B17,$R$9:$R$13,0)) -> 2609106.4 | F17: =INDEX(F$9:F$13,MATCH($B17,$R$9:$R$13,0)) -> 2016183.1 | G17: =INDEX(G$9:G$13,MATCH($B17,$R$9:$R$13,0)) -> 2617854.2 | H17: =INDEX(H$9:H$13,MATCH($B17,$R$9:$R$13,0)) -> 3339089.9 | I17: =INDEX(I$9:I$13,MATCH($B17,$R$9:$R$13,0)) -> 1965966 | J17: =INDEX(J$9:J$13,MATCH($B17,$R$9:$R$13,0)) -> 1920737 | K17: =INDEX(K$9:K$13,MATCH($B17,$R$9:$R$13,0)) -> 1715634.6 | L17: =INDEX(L$9:L$13,MATCH($B17,$R$9:$R$13,0)) -> 2755115.8 | ... P17: =INDEX(P$9:P$13,MATCH($B17,$R$9:$R$13,0)) -> 1779514.4 | Q17: =SUM(E17:P17) -> 28589247
B18: 2 | C18: =INDEX(C$9:C$13,MATCH($B18,$R$9:$R$13,0)) -> Client 3 | E18: =INDEX(E$9:E$13,MATCH($B18,$R$9:$R$13,0)) -> 1008120 | F18: =INDEX(F$9:F$13,MATCH($B18,$R$9:$R$13,0)) -> 1166334.6 | G18: =INDEX(G$9:G$13,MATCH($B18,$R$9:$R$13,0)) -> 1113695.8 | H18: =INDEX(H$9:H$13,MATCH($B18,$R$9:$R$13,0)) -> 971973.94 | I18: =INDEX(I$9:I$13,MATCH($B18,$R$9:$R$13,0)) -> 1094743.3 | J18: =INDEX(J$9:J$13,MATCH($B18,$R$9:$R$13,0)) -> 947009.91 | K18: =INDEX(K$9:K$13,MATCH($B18,$R$9:$R$13,0)) -> 884676.63 | L18: =INDEX(L$9:L$13,MATCH($B18,$R$9:$R$13,0)) -> 716452.51 | ... P18: =INDEX(P$9:P$13,MATCH($B18,$R$9:$R$13,0)) -> 887082.2 | Q18: =SUM(E18:P18) -> 12009800
B19: 3 | C19: =INDEX(C$9:C$13,MATCH($B19,$R$9:$R$13,0)) -> Client 1 | E19: =INDEX(E$9:E$13,MATCH($B19,$R$9:$R$13,0)) -> 465255.09 | F19: =INDEX(F$9:F$13,MATCH($B19,$R$9:$R$13,0)) -> 239206.5 | G19: =INDEX(G$9:G$13,MATCH($B19,$R$9:$R$13,0)) -> 237128.48 | H19: =INDEX(H$9:H$13,MATCH($B19,$R$9:$R$13,0)) -> 278555.84 | I19: =INDEX(I$9:I$13,MATCH($B19,$R$9:$R$13,0)) -> 353406.45 | J19: =INDEX(J$9:J$13,MATCH($B19,$R$9:$R$13,0)) -> 455370.72 | K19: =INDEX(K$9:K$13,MATCH($B19,$R$9:$R$13,0)) -> 445532.62 | L19: =INDEX(L$9:L$13,MATCH($B19,$R$9:$R$13,0)) -> 534480.41 | ... P19: =INDEX(P$9:P$13,MATCH($B19,$R$9:$R$13,0)) -> 530208.67 | Q19: =SUM(E19:P19) -> 4738211.4
B20: 4 | C20: =INDEX(C$9:C$13,MATCH($B20,$R$9:$R$13,0)) -> Client 2 | E20: =INDEX(E$9:E$13,MATCH($B20,$R$9:$R$13,0)) -> 196205.13 | F20: =INDEX(F$9:F$13,MATCH($B20,$R$9:$R$13,0)) -> 205465.91 | G20: =INDEX(G$9:G$13,MATCH($B20,$R$9:$R$13,0)) -> 88478.315 | H20: =INDEX(H$9:H$13,MATCH($B20,$R$9:$R$13,0)) -> 0 | I20: =INDEX(I$9:I$13,MATCH($B20,$R$9:$R$13,0)) -> 356951.62 | J20: =INDEX(J$9:J$13,MATCH($B20,$R$9:$R$13,0)) -> 408808.04 | K20: =INDEX(K$9:K$13,MATCH($B20,$R$9:$R$13,0)) -> 478364.3 | L20: =INDEX(L$9:L$13,MATCH($B20,$R$9:$R$13,0)) -> 379898.96 | ... P20: =INDEX(P$9:P$13,MATCH($B20,$R$9:$R$13,0)) -> 489225.72 | Q20: =SUM(E20:P20) -> 3057575.4
B21: 5 | C21: =INDEX(C$9:C$13,MATCH($B21,$R$9:$R$13,0)) -> Client 5 | E21: =INDEX(E$9:E$13,MATCH($B21,$R$9:$R$13,0)) -> 201000.68 | F21: =INDEX(F$9:F$13,MATCH($B21,$R$9:$R$13,0)) -> 336551.94 | G21: =INDEX(G$9:G$13,MATCH($B21,$R$9:$R$13,0)) -> 336551.94 | H21: =INDEX(H$9:H$13,MATCH($B21,$R$9:$R$13,0)) -> 292156.74 | I21: =INDEX(I$9:I$13,MATCH($B21,$R$9:$R$13,0)) -> 228994.11 | J21: =INDEX(J$9:J$13,MATCH($B21,$R$9:$R$13,0)) -> 247682.68 | K21: =INDEX(K$9:K$13,MATCH($B21,$R$9:$R$13,0)) -> 238377.82 | L21: =INDEX(L$9:L$13,MATCH($B21,$R$9:$R$13,0)) -> 140203.69 | ... P21: =INDEX(P$9:P$13,MATCH($B21,$R$9:$R$13,0)) -> 156605.47 | Q21: =SUM(E21:P21) -> 2692257.9
C22: Total | E22: =SUM(E17:E21) -> 4479687.3 | F22: =SUM(F17:F21) -> 3963742 | G22: =SUM(G17:G21) -> 4393708.7 | H22: =SUM(H17:H21) -> 4881776.4 | I22: =SUM(I17:I21) -> 4000061.4 | J22: =SUM(J17:J21) -> 3979608.4 | K22: =SUM(K17:K21) -> 3762586 | L22: =SUM(L17:L21) -> 4526151.4 | ... Q22: =SUM(Q17:Q21) -> 51087091
B24: COGS by Product
B26: 1 | C26: ="Product "&B26 -> Product 1 | E26: =SUMIF('CaseSolution - Calculations'!$E$261:$E$285,$B26,'CaseSolution - Calculations'!U$261:U$285) -> 1723557.1 | F26: =SUMIF('CaseSolution - Calculations'!$E$261:$E$285,$B26,'CaseSolution - Calculations'!V$261:V$285) -> 1287513.9 | G26: =SUMIF('CaseSolution - Calculations'!$E$261:$E$285,$B26,'CaseSolution - Calculations'!W$261:W$285) -> 1632961.2 | H26: =SUMIF('CaseSolution - Calculations'!$E$261:$E$285,$B26,'CaseSolution - Calculations'!X$261:X$285) -> 2056926.3 | I26: =SUMIF('CaseSolution - Calculations'!$E$261:$E$285,$B26,'CaseSolution - Calculations'!Y$261:Y$285) -> 1320722.4 | J26: =SUMIF('CaseSolution - Calculations'!$E$261:$E$285,$B26,'CaseSolution - Calculations'!Z$261:Z$285) -> 1337494.6 | K26: =SUMIF('CaseSolution - Calculations'!$E$261:$E$285,$B26,'CaseSolution - Calculations'!AA$261:AA$285) -> 1189469.8 | L26: =SUMIF('CaseSolution - Calculations'!$E$261:$E$285,$B26,'CaseSolution - Calculations'!AB$261:AB$285) -> 1805591.8 | ... P26: =SUMIF('CaseSolution - Calculations'!$E$261:$E$285,$B26,'CaseSolution - Calculations'!AF$261:AF$285) -> 1227494.4 | Q26: =SUM(E26:P26) -> 18606705 | R26: =RANK(Q26,$Q$26:$Q$30)+COUNTIF(Q$26:Q26, Q26)-1 -> 1
B27: 2 | C27: ="Product "&B27 -> Product 2 | E27: =SUMIF('CaseSolution - Calculations'!$E$261:$E$285,$B27,'CaseSolution - Calculations'!U$261:U$285) -> 397972.22 | F27: =SUMIF('CaseSolution - Calculations'!$E$261:$E$285,$B27,'CaseSolution - Calculations'!V$261:V$285) -> 382305.26 | G27: =SUMIF('CaseSolution - Calculations'!$E$261:$E$285,$B27,'CaseSolution - Calculations'!W$261:W$285) -> 419266.12 | H27: =SUMIF('CaseSolution - Calculations'!$E$261:$E$285,$B27,'CaseSolution - Calculations'!X$261:X$285) -> 391174.49 | I27: =SUMIF('CaseSolution - Calculations'!$E$261:$E$285,$B27,'CaseSolution - Calculations'!Y$261:Y$285) -> 370246 | J27: =SUMIF('CaseSolution - Calculations'!$E$261:$E$285,$B27,'CaseSolution - Calculations'!Z$261:Z$285) -> 239220.26 | K27: =SUMIF('CaseSolution - Calculations'!$E$261:$E$285,$B27,'CaseSolution - Calculations'!AA$261:AA$285) -> 258980.18 | L27: =SUMIF('CaseSolution - Calculations'!$E$261:$E$285,$B27,'CaseSolution - Calculations'!AB$261:AB$285) -> 269083.47 | ... P27: =SUMIF('CaseSolution - Calculations'!$E$261:$E$285,$B27,'CaseSolution - Calculations'!AF$261:AF$285) -> 331643.28 | Q27: =SUM(E27:P27) -> 4054788.6 | R27: =RANK(Q27,$Q$26:$Q$30)+COUNTIF(Q$26:Q27, Q27)-1 -> 2
B28: 3 | C28: ="Product "&B28 -> Product 3 | E28: =SUMIF('CaseSolution - Calculations'!$E$261:$E$285,$B28,'CaseSolution - Calculations'!U$261:U$285) -> 88328.614 | F28: =SUMIF('CaseSolution - Calculations'!$E$261:$E$285,$B28,'CaseSolution - Calculations'!V$261:V$285) -> 99038.011 | G28: =SUMIF('CaseSolution - Calculations'!$E$261:$E$285,$B28,'CaseSolution - Calculations'!W$261:W$285) -> 49943.126 | H28: =SUMIF('CaseSolution - Calculations'!$E$261:$E$285,$B28,'CaseSolution - Calculations'!X$261:X$285) -> 14461.452 | I28: =SUMIF('CaseSolution - Calculations'!$E$261:$E$285,$B28,'CaseSolution - Calculations'!Y$261:Y$285) -> 147254.35 | J28: =SUMIF('CaseSolution - Calculations'!$E$261:$E$285,$B28,'CaseSolution - Calculations'!Z$261:Z$285) -> 156634.32 | K28: =SUMIF('CaseSolution - Calculations'!$E$261:$E$285,$B28,'CaseSolution - Calculations'!AA$261:AA$285) -> 198788.12 | L28: =SUMIF('CaseSolution - Calculations'!$E$261:$E$285,$B28,'CaseSolution - Calculations'!AB$261:AB$285) -> 150936.07 | ... P28: =SUMIF('CaseSolution - Calculations'!$E$261:$E$285,$B28,'CaseSolution - Calculations'!AF$261:AF$285) -> 194567.71 | Q28: =SUM(E28:P28) -> 1310248.8 | R28: =RANK(Q28,$Q$26:$Q$30)+COUNTIF(Q$26:Q28, Q28)-1 -> 4
B29: 4 | C29: ="Product "&B29 -> Product 4 | E29: =SUMIF('CaseSolution - Calculations'!$E$261:$E$285,$B29,'CaseSolution - Calculations'!U$261:U$285) -> 0 | F29: =SUMIF('CaseSolution - Calculations'!$E$261:$E$285,$B29,'CaseSolution - Calculations'!V$261:V$285) -> 0 | G29: =SUMIF('CaseSolution - Calculations'!$E$261:$E$285,$B29,'CaseSolution - Calculations'!W$261:W$285) -> 0 | H29: =SUMIF('CaseSolution - Calculations'!$E$261:$E$285,$B29,'CaseSolution - Calculations'!X$261:X$285) -> 0 | I29: =SUMIF('CaseSolution - Calculations'!$E$261:$E$285,$B29,'CaseSolution - Calculations'!Y$261:Y$285) -> 0 | J29: =SUMIF('CaseSolution - Calculations'!$E$261:$E$285,$B29,'CaseSolution - Calculations'!Z$261:Z$285) -> 0 | K29: =SUMIF('CaseSolution - Calculations'!$E$261:$E$285,$B29,'CaseSolution - Calculations'!AA$261:AA$285) -> 0 | L29: =SUMIF('CaseSolution - Calculations'!$E$261:$E$285,$B29,'CaseSolution - Calculations'!AB$261:AB$285) -> 0 | ... P29: =SUMIF('CaseSolution - Calculations'!$E$261:$E$285,$B29,'CaseSolution - Calculations'!AF$261:AF$285) -> 0 | Q29: =SUM(E29:P29) -> 0 | R29: =RANK(Q29,$Q$26:$Q$30)+COUNTIF(Q$26:Q29, Q29)-1 -> 5
B30: 5 | C30: ="Product "&B30 -> Product 5 | E30: =SUMIF('CaseSolution - Calculations'!$E$261:$E$285,$B30,'CaseSolution - Calculations'!U$261:U$285) -> 129141.31 | F30: =SUMIF('CaseSolution - Calculations'!$E$261:$E$285,$B30,'CaseSolution - Calculations'!V$261:V$285) -> 236479.71 | G30: =SUMIF('CaseSolution - Calculations'!$E$261:$E$285,$B30,'CaseSolution - Calculations'!W$261:W$285) -> 179464.99 | H30: =SUMIF('CaseSolution - Calculations'!$E$261:$E$285,$B30,'CaseSolution - Calculations'!X$261:X$285) -> 140639.06 | I30: =SUMIF('CaseSolution - Calculations'!$E$261:$E$285,$B30,'CaseSolution - Calculations'!Y$261:Y$285) -> 180953.38 | J30: =SUMIF('CaseSolution - Calculations'!$E$261:$E$285,$B30,'CaseSolution - Calculations'!Z$261:Z$285) -> 273769.92 | K30: =SUMIF('CaseSolution - Calculations'!$E$261:$E$285,$B30,'CaseSolution - Calculations'!AA$261:AA$285) -> 243733.94 | L30: =SUMIF('CaseSolution - Calculations'!$E$261:$E$285,$B30,'CaseSolution - Calculations'!AB$261:AB$285) -> 140887.52 | ... P30: =SUMIF('CaseSolution - Calculations'!$E$261:$E$285,$B30,'CaseSolution - Calculations'!AF$261:AF$285) -> 179464.99 | Q30: =SUM(E30:P30) -> 2356945.8 | R30: =RANK(Q30,$Q$26:$Q$30)+COUNTIF(Q$26:Q30, Q30)-1 -> 3
C31: Total | E31: =SUM(E26:E30) -> 2338999.2 | F31: =SUM(F26:F30) -> 2005336.9 | G31: =SUM(G26:G30) -> 2281635.5 | H31: =SUM(H26:H30) -> 2603201.3 | I31: =SUM(I26:I30) -> 2019176.1 | J31: =SUM(J26:J30) -> 2007119.2 | K31: =SUM(K26:K30) -> 1890972 | L31: =SUM(L26:L30) -> 2366498.9 | ... Q31: =SUM(Q26:Q30) -> 26328688
B33: Ranked
B34: 1 | C34: =INDEX(C$26:C$30,MATCH($B34,$R$26:$R$30,0)) -> Product 1 | E34: =INDEX(E$26:E$30,MATCH($B34,$R$26:$R$30,0)) -> 1723557.1 | F34: =INDEX(F$26:F$30,MATCH($B34,$R$26:$R$30,0)) -> 1287513.9 | G34: =INDEX(G$26:G$30,MATCH($B34,$R$26:$R$30,0)) -> 1632961.2 | H34: =INDEX(H$26:H$30,MATCH($B34,$R$26:$R$30,0)) -> 2056926.3 | I34: =INDEX(I$26:I$30,MATCH($B34,$R$26:$R$30,0)) -> 1320722.4 | J34: =INDEX(J$26:J$30,MATCH($B34,$R$26:$R$30,0)) -> 1337494.6 | K34: =INDEX(K$26:K$30,MATCH($B34,$R$26:$R$30,0)) -> 1189469.8 | L34: =INDEX(L$26:L$30,MATCH($B34,$R$26:$R$30,0)) -> 1805591.8 | ... P34: =INDEX(P$26:P$30,MATCH($B34,$R$26:$R$30,0)) -> 1227494.4 | Q34: =SUM(E34:P34) -> 18606705
B35: 2 | C35: =INDEX(C$26:C$30,MATCH($B35,$R$26:$R$30,0)) -> Product 2 | E35: =INDEX(E$26:E$30,MATCH($B35,$R$26:$R$30,0)) -> 397972.22 | F35: =INDEX(F$26:F$30,MATCH($B35,$R$26:$R$30,0)) -> 382305.26 | G35: =INDEX(G$26:G$30,MATCH($B35,$R$26:$R$30,0)) -> 419266.12 | H35: =INDEX(H$26:H$30,MATCH($B35,$R$26:$R$30,0)) -> 391174.49 | I35: =INDEX(I$26:I$30,MATCH($B35,$R$26:$R$30,0)) -> 370246 | J35: =INDEX(J$26:J$30,MATCH($B35,$R$26:$R$30,0)) -> 239220.26 | K35: =INDEX(K$26:K$30,MATCH($B35,$R$26:$R$30,0)) -> 258980.18 | L35: =INDEX(L$26:L$30,MATCH($B35,$R$26:$R$30,0)) -> 269083.47 | ... P35: =INDEX(P$26:P$30,MATCH($B35,$R$26:$R$30,0)) -> 331643.28 | Q35: =SUM(E35:P35) -> 4054788.6
B36: 3 | C36: =INDEX(C$26:C$30,MATCH($B36,$R$26:$R$30,0)) -> Product 5 | E36: =INDEX(E$26:E$30,MATCH($B36,$R$26:$R$30,0)) -> 129141.31 | F36: =INDEX(F$26:F$30,MATCH($B36,$R$26:$R$30,0)) -> 236479.71 | G36: =INDEX(G$26:G$30,MATCH($B36,$R$26:$R$30,0)) -> 179464.99 | H36: =INDEX(H$26:H$30,MATCH($B36,$R$26:$R$30,0)) -> 140639.06 | I36: =INDEX(I$26:I$30,MATCH($B36,$R$26:$R$30,0)) -> 180953.38 | J36: =INDEX(J$26:J$30,MATCH($B36,$R$26:$R$30,0)) -> 273769.92 | K36: =INDEX(K$26:K$30,MATCH($B36,$R$26:$R$30,0)) -> 243733.94 | L36: =INDEX(L$26:L$30,MATCH($B36,$R$26:$R$30,0)) -> 140887.52 | ... P36: =INDEX(P$26:P$30,MATCH($B36,$R$26:$R$30,0)) -> 179464.99 | Q36: =SUM(E36:P36) -> 2356945.8
B37: 4 | C37: =INDEX(C$26:C$30,MATCH($B37,$R$26:$R$30,0)) -> Product 3 | E37: =INDEX(E$26:E$30,MATCH($B37,$R$26:$R$30,0)) -> 88328.614 | F37: =INDEX(F$26:F$30,MATCH($B37,$R$26:$R$30,0)) -> 99038.011 | G37: =INDEX(G$26:G$30,MATCH($B37,$R$26:$R$30,0)) -> 49943.126 | H37: =INDEX(H$26:H$30,MATCH($B37,$R$26:$R$30,0)) -> 14461.452 | I37: =INDEX(I$26:I$30,MATCH($B37,$R$26:$R$30,0)) -> 147254.35 | J37: =INDEX(J$26:J$30,MATCH($B37,$R$26:$R$30,0)) -> 156634.32 | K37: =INDEX(K$26:K$30,MATCH($B37,$R$26:$R$30,0)) -> 198788.12 | L37: =INDEX(L$26:L$30,MATCH($B37,$R$26:$R$30,0)) -> 150936.07 | ... P37: =INDEX(P$26:P$30,MATCH($B37,$R$26:$R$30,0)) -> 194567.71 | Q37: =SUM(E37:P37) -> 1310248.8
B38: 5 | C38: =INDEX(C$26:C$30,MATCH($B38,$R$26:$R$30,0)) -> Product 4 | E38: =INDEX(E$26:E$30,MATCH($B38,$R$26:$R$30,0)) -> 0 | F38: =INDEX(F$26:F$30,MATCH($B38,$R$26:$R$30,0)) -> 0 | G38: =INDEX(G$26:G$30,MATCH($B38,$R$26:$R$30,0)) -> 0 | H38: =INDEX(H$26:H$30,MATCH($B38,$R$26:$R$30,0)) -> 0 | I38: =INDEX(I$26:I$30,MATCH($B38,$R$26:$R$30,0)) -> 0 | J38: =INDEX(J$26:J$30,MATCH($B38,$R$26:$R$30,0)) -> 0 | K38: =INDEX(K$26:K$30,MATCH($B38,$R$26:$R$30,0)) -> 0 | L38: =INDEX(L$26:L$30,MATCH($B38,$R$26:$R$30,0)) -> 0 | ... P38: =INDEX(P$26:P$30,MATCH($B38,$R$26:$R$30,0)) -> 0 | Q38: =SUM(E38:P38) -> 0
C39: Total | E39: =SUM(E34:E38) -> 2338999.2 | F39: =SUM(F34:F38) -> 2005336.9 | G39: =SUM(G34:G38) -> 2281635.5 | H39: =SUM(H34:H38) -> 2603201.3 | I39: =SUM(I34:I38) -> 2019176.1 | J39: =SUM(J34:J38) -> 2007119.2 | K39: =SUM(K34:K38) -> 1890972 | L39: =SUM(L34:L38) -> 2366498.9 | ... Q39: =SUM(Q34:Q38) -> 26328688
B41: Production by Product
B43: 1 | C43: ="Product "&B43 -> Product 1 | E43: =SUMIF('CaseSolution - Calculations'!$E$175:$E$199,$B43,'CaseSolution - Calculations'!U$175:U$199) -> 64432.04 | F43: =SUMIF('CaseSolution - Calculations'!$E$175:$E$199,$B43,'CaseSolution - Calculations'!V$175:V$199) -> 48131.36 | G43: =SUMIF('CaseSolution - Calculations'!$E$175:$E$199,$B43,'CaseSolution - Calculations'!W$175:W$199) -> 61045.28 | H43: =SUMIF('CaseSolution - Calculations'!$E$175:$E$199,$B43,'CaseSolution - Calculations'!X$175:X$199) -> 76894.44 | I43: =SUMIF('CaseSolution - Calculations'!$E$175:$E$199,$B43,'CaseSolution - Calculations'!Y$175:Y$199) -> 49372.8 | J43: =SUMIF('CaseSolution - Calculations'!$E$175:$E$199,$B43,'CaseSolution - Calculations'!Z$175:Z$199) -> 49999.8 | K43: =SUMIF('CaseSolution - Calculations'!$E$175:$E$199,$B43,'CaseSolution - Calculations'!AA$175:AA$199) -> 44466.16 | L43: =SUMIF('CaseSolution - Calculations'!$E$175:$E$199,$B43,'CaseSolution - Calculations'!AB$175:AB$199) -> 67498.76 | ... P43: =SUMIF('CaseSolution - Calculations'!$E$175:$E$199,$B43,'CaseSolution - Calculations'!AF$175:AF$199) -> 45887.64 | Q43: =SUM(E43:P43) -> 695577.76 | R43: =RANK(Q43,$Q$43:$Q$47)+COUNTIF(Q$43:Q43, Q43)-1 -> 1
B44: 2 | C44: ="Product "&B44 -> Product 2 | E44: =SUMIF('CaseSolution - Calculations'!$E$175:$E$199,$B44,'CaseSolution - Calculations'!U$175:U$199) -> 49946.94 | F44: =SUMIF('CaseSolution - Calculations'!$E$175:$E$199,$B44,'CaseSolution - Calculations'!V$175:V$199) -> 47980.68 | G44: =SUMIF('CaseSolution - Calculations'!$E$175:$E$199,$B44,'CaseSolution - Calculations'!W$175:W$199) -> 52619.4 | H44: =SUMIF('CaseSolution - Calculations'!$E$175:$E$199,$B44,'CaseSolution - Calculations'!X$175:X$199) -> 49093.8 | I44: =SUMIF('CaseSolution - Calculations'!$E$175:$E$199,$B44,'CaseSolution - Calculations'!Y$175:Y$199) -> 46467.2 | J44: =SUMIF('CaseSolution - Calculations'!$E$175:$E$199,$B44,'CaseSolution - Calculations'!Z$175:Z$199) -> 30023 | K44: =SUMIF('CaseSolution - Calculations'!$E$175:$E$199,$B44,'CaseSolution - Calculations'!AA$175:AA$199) -> 32502.94 | L44: =SUMIF('CaseSolution - Calculations'!$E$175:$E$199,$B44,'CaseSolution - Calculations'!AB$175:AB$199) -> 33770.94 | ... P44: =SUMIF('CaseSolution - Calculations'!$E$175:$E$199,$B44,'CaseSolution - Calculations'!AF$175:AF$199) -> 41622.42 | Q44: =SUM(E44:P44) -> 508890.5 | R44: =RANK(Q44,$Q$43:$Q$47)+COUNTIF(Q$43:Q44, Q44)-1 -> 2
B45: 3 | C45: ="Product "&B45 -> Product 3 | E45: =SUMIF('CaseSolution - Calculations'!$E$175:$E$199,$B45,'CaseSolution - Calculations'!U$175:U$199) -> 15973.78 | F45: =SUMIF('CaseSolution - Calculations'!$E$175:$E$199,$B45,'CaseSolution - Calculations'!V$175:V$199) -> 17910.52 | G45: =SUMIF('CaseSolution - Calculations'!$E$175:$E$199,$B45,'CaseSolution - Calculations'!W$175:W$199) -> 9031.96 | H45: =SUMIF('CaseSolution - Calculations'!$E$175:$E$199,$B45,'CaseSolution - Calculations'!X$175:X$199) -> 2615.28 | I45: =SUMIF('CaseSolution - Calculations'!$E$175:$E$199,$B45,'CaseSolution - Calculations'!Y$175:Y$199) -> 26630.2 | J45: =SUMIF('CaseSolution - Calculations'!$E$175:$E$199,$B45,'CaseSolution - Calculations'!Z$175:Z$199) -> 28326.52 | K45: =SUMIF('CaseSolution - Calculations'!$E$175:$E$199,$B45,'CaseSolution - Calculations'!AA$175:AA$199) -> 35949.82 | L45: =SUMIF('CaseSolution - Calculations'!$E$175:$E$199,$B45,'CaseSolution - Calculations'!AB$175:AB$199) -> 27296.02 | ... P45: =SUMIF('CaseSolution - Calculations'!$E$175:$E$199,$B45,'CaseSolution - Calculations'!AF$175:AF$199) -> 35186.58 | Q45: =SUM(E45:P45) -> 236951.82 | R45: =RANK(Q45,$Q$43:$Q$47)+COUNTIF(Q$43:Q45, Q45)-1 -> 4
B46: 4 | C46: ="Product "&B46 -> Product 4 | E46: =SUMIF('CaseSolution - Calculations'!$E$175:$E$199,$B46,'CaseSolution - Calculations'!U$175:U$199) -> 0 | F46: =SUMIF('CaseSolution - Calculations'!$E$175:$E$199,$B46,'CaseSolution - Calculations'!V$175:V$199) -> 0 | G46: =SUMIF('CaseSolution - Calculations'!$E$175:$E$199,$B46,'CaseSolution - Calculations'!W$175:W$199) -> 0 | H46: =SUMIF('CaseSolution - Calculations'!$E$175:$E$199,$B46,'CaseSolution - Calculations'!X$175:X$199) -> 0 | I46: =SUMIF('CaseSolution - Calculations'!$E$175:$E$199,$B46,'CaseSolution - Calculations'!Y$175:Y$199) -> 0 | J46: =SUMIF('CaseSolution - Calculations'!$E$175:$E$199,$B46,'CaseSolution - Calculations'!Z$175:Z$199) -> 0 | K46: =SUMIF('CaseSolution - Calculations'!$E$175:$E$199,$B46,'CaseSolution - Calculations'!AA$175:AA$199) -> 0 | L46: =SUMIF('CaseSolution - Calculations'!$E$175:$E$199,$B46,'CaseSolution - Calculations'!AB$175:AB$199) -> 0 | ... P46: =SUMIF('CaseSolution - Calculations'!$E$175:$E$199,$B46,'CaseSolution - Calculations'!AF$175:AF$199) -> 0 | Q46: =SUM(E46:P46) -> 0 | R46: =RANK(Q46,$Q$43:$Q$47)+COUNTIF(Q$43:Q46, Q46)-1 -> 5
B47: 5 | C47: ="Product "&B47 -> Product 5 | E47: =SUMIF('CaseSolution - Calculations'!$E$175:$E$199,$B47,'CaseSolution - Calculations'!U$175:U$199) -> 19647.24 | F47: =SUMIF('CaseSolution - Calculations'!$E$175:$E$199,$B47,'CaseSolution - Calculations'!V$175:V$199) -> 35977.44 | G47: =SUMIF('CaseSolution - Calculations'!$E$175:$E$199,$B47,'CaseSolution - Calculations'!W$175:W$199) -> 27303.36 | H47: =SUMIF('CaseSolution - Calculations'!$E$175:$E$199,$B47,'CaseSolution - Calculations'!X$175:X$199) -> 21396.48 | I47: =SUMIF('CaseSolution - Calculations'!$E$175:$E$199,$B47,'CaseSolution - Calculations'!Y$175:Y$199) -> 27529.8 | J47: =SUMIF('CaseSolution - Calculations'!$E$175:$E$199,$B47,'CaseSolution - Calculations'!Z$175:Z$199) -> 41650.68 | K47: =SUMIF('CaseSolution - Calculations'!$E$175:$E$199,$B47,'CaseSolution - Calculations'!AA$175:AA$199) -> 37081.08 | L47: =SUMIF('CaseSolution - Calculations'!$E$175:$E$199,$B47,'CaseSolution - Calculations'!AB$175:AB$199) -> 21434.28 | ... P47: =SUMIF('CaseSolution - Calculations'!$E$175:$E$199,$B47,'CaseSolution - Calculations'!AF$175:AF$199) -> 27303.36 | Q47: =SUM(E47:P47) -> 358579.92 | R47: =RANK(Q47,$Q$43:$Q$47)+COUNTIF(Q$43:Q47, Q47)-1 -> 3
C48: Total | E48: =SUM(E43:E47) -> 150000 | F48: =SUM(F43:F47) -> 150000 | G48: =SUM(G43:G47) -> 150000 | H48: =SUM(H43:H47) -> 150000 | I48: =SUM(I43:I47) -> 150000 | J48: =SUM(J43:J47) -> 150000 | K48: =SUM(K43:K47) -> 150000 | L48: =SUM(L43:L47) -> 150000 | ... Q48: =SUM(Q43:Q47) -> 1800000
B50: Ranked
B51: 1 | C51: =INDEX(C$43:C$47,MATCH($B51,$R$43:$R$47,0)) -> Product 1 | E51: =INDEX(E$43:E$47,MATCH($B51,$R$43:$R$47,0)) -> 64432.04 | F51: =INDEX(F$43:F$47,MATCH($B51,$R$43:$R$47,0)) -> 48131.36 | G51: =INDEX(G$43:G$47,MATCH($B51,$R$43:$R$47,0)) -> 61045.28 | H51: =INDEX(H$43:H$47,MATCH($B51,$R$43:$R$47,0)) -> 76894.44 | I51: =INDEX(I$43:I$47,MATCH($B51,$R$43:$R$47,0)) -> 49372.8 | J51: =INDEX(J$43:J$47,MATCH($B51,$R$43:$R$47,0)) -> 49999.8 | K51: =INDEX(K$43:K$47,MATCH($B51,$R$43:$R$47,0)) -> 44466.16 | L51: =INDEX(L$43:L$47,MATCH($B51,$R$43:$R$47,0)) -> 67498.76 | ... P51: =INDEX(P$43:P$47,MATCH($B51,$R$43:$R$47,0)) -> 45887.64 | Q51: =SUM(E51:P51) -> 695577.76
B52: 2 | C52: =INDEX(C$43:C$47,MATCH($B52,$R$43:$R$47,0)) -> Product 2 | E52: =INDEX(E$43:E$47,MATCH($B52,$R$43:$R$47,0)) -> 49946.94 | F52: =INDEX(F$43:F$47,MATCH($B52,$R$43:$R$47,0)) -> 47980.68 | G52: =INDEX(G$43:G$47,MATCH($B52,$R$43:$R$47,0)) -> 52619.4 | H52: =INDEX(H$43:H$47,MATCH($B52,$R$43:$R$47,0)) -> 49093.8 | I52: =INDEX(I$43:I$47,MATCH($B52,$R$43:$R$47,0)) -> 46467.2 | J52: =INDEX(J$43:J$47,MATCH($B52,$R$43:$R$47,0)) -> 30023 | K52: =INDEX(K$43:K$47,MATCH($B52,$R$43:$R$47,0)) -> 32502.94 | L52: =INDEX(L$43:L$47,MATCH($B52,$R$43:$R$47,0)) -> 33770.94 | ... P52: =INDEX(P$43:P$47,MATCH($B52,$R$43:$R$47,0)) -> 41622.42 | Q52: =SUM(E52:P52) -> 508890.5
B53: 3 | C53: =INDEX(C$43:C$47,MATCH($B53,$R$43:$R$47,0)) -> Product 5 | E53: =INDEX(E$43:E$47,MATCH($B53,$R$43:$R$47,0)) -> 19647.24 | F53: =INDEX(F$43:F$47,MATCH($B53,$R$43:$R$47,0)) -> 35977.44 | G53: =INDEX(G$43:G$47,MATCH($B53,$R$43:$R$47,0)) -> 27303.36 | H53: =INDEX(H$43:H$47,MATCH($B53,$R$43:$R$47,0)) -> 21396.48 | I53: =INDEX(I$43:I$47,MATCH($B53,$R$43:$R$47,0)) -> 27529.8 | J53: =INDEX(J$43:J$47,MATCH($B53,$R$43:$R$47,0)) -> 41650.68 | K53: =INDEX(K$43:K$47,MATCH($B53,$R$43:$R$47,0)) -> 37081.08 | L53: =INDEX(L$43:L$47,MATCH($B53,$R$43:$R$47,0)) -> 21434.28 | ... P53: =INDEX(P$43:P$47,MATCH($B53,$R$43:$R$47,0)) -> 27303.36 | Q53: =SUM(E53:P53) -> 358579.92
B54: 4 | C54: =INDEX(C$43:C$47,MATCH($B54,$R$43:$R$47,0)) -> Product 3 | E54: =INDEX(E$43:E$47,MATCH($B54,$R$43:$R$47,0)) -> 15973.78 | F54: =INDEX(F$43:F$47,MATCH($B54,$R$43:$R$47,0)) -> 17910.52 | G54: =INDEX(G$43:G$47,MATCH($B54,$R$43:$R$47,0)) -> 9031.96 | H54: =INDEX(H$43:H$47,MATCH($B54,$R$43:$R$47,0)) -> 2615.28 | I54: =INDEX(I$43:I$47,MATCH($B54,$R$43:$R$47,0)) -> 26630.2 | J54: =INDEX(J$43:J$47,MATCH($B54,$R$43:$R$47,0)) -> 28326.52 | K54: =INDEX(K$43:K$47,MATCH($B54,$R$43:$R$47,0)) -> 35949.82 | L54: =INDEX(L$43:L$47,MATCH($B54,$R$43:$R$47,0)) -> 27296.02 | ... P54: =INDEX(P$43:P$47,MATCH($B54,$R$43:$R$47,0)) -> 35186.58 | Q54: =SUM(E54:P54) -> 236951.82
B55: 5 | C55: =INDEX(C$43:C$47,MATCH($B55,$R$43:$R$47,0)) -> Product 4 | E55: =INDEX(E$43:E$47,MATCH($B55,$R$43:$R$47,0)) -> 0 | F55: =INDEX(F$43:F$47,MATCH($B55,$R$43:$R$47,0)) -> 0 | G55: =INDEX(G$43:G$47,MATCH($B55,$R$43:$R$47,0)) -> 0 | H55: =INDEX(H$43:H$47,MATCH($B55,$R$43:$R$47,0)) -> 0 | I55: =INDEX(I$43:I$47,MATCH($B55,$R$43:$R$47,0)) -> 0 | J55: =INDEX(J$43:J$47,MATCH($B55,$R$43:$R$47,0)) -> 0 | K55: =INDEX(K$43:K$47,MATCH($B55,$R$43:$R$47,0)) -> 0 | L55: =INDEX(L$43:L$47,MATCH($B55,$R$43:$R$47,0)) -> 0 | ... P55: =INDEX(P$43:P$47,MATCH($B55,$R$43:$R$47,0)) -> 0 | Q55: =SUM(E55:P55) -> 0
C56: Total | E56: =SUM(E51:E55) -> 150000 | F56: =SUM(F51:F55) -> 150000 | G56: =SUM(G51:G55) -> 150000 | H56: =SUM(H51:H55) -> 150000 | I56: =SUM(I51:I55) -> 150000 | J56: =SUM(J51:J55) -> 150000 | K56: =SUM(K51:K55) -> 150000 | L56: =SUM(L51:L55) -> 150000 | ... Q56: =SUM(Q51:Q55) -> 1800000

Sheet Tmp
A1: =company -> Big Fish Co.
A2: {=topic} -> CFM Topic: Costs
A3: TMP SCHEDULE | J3: {=EOMONTH( start_date, _xlfn.SEQUENCE( 1, periods, 1, 1 ) - 1 )} -> 43496 | K3: 43524 | L3: 43555 | M3: 43585 | N3: 43616 | O3: 43646 | P3: 43677 | Q3: 43708 | R3: 43738 | S3: 43769 | T3: 43799 | U3: 43830 | V3: 43861 | W3: 43890 | X3: 43921 | Y3: 43951 | Z3: 43982 | AA3: 44012 | AB3: 44043 | AC3: 44074 | AD3: 44104 | AE3: 44135 | AF3: 44165 | AG3: 44196
A40: End of schedule
