Workbook
Name company: Assumptions!$F$7
Name it_expansion_date: Assumptions!$F$41
Name periods_bldg: Assumptions!$F$18
Name periods_it: Assumptions!$F$26
Name start_date: Assumptions!$F$9
Name topic: Assumptions!$E$8 & ": " & Assumptions!$F$8

Sheet Calculations
A1: {=company} -> Galway Inc.
A2: {=topic} -> CFM topic: Capex and Depreciation
A3: CALCULATIONS SCHEDULE | J3: {=EOMONTH( start_date, _xlfn.SEQUENCE( 1, MAX( periods_bldg, periods_it ), 0, 12 ) )} -> 43465 | K3: 43830 | L3: 44196 | M3: 44561 | N3: 44926 | O3: 45291 | P3: 45657 | Q3: 46022 | R3: 46387 | S3: 46752
A5: BUILDINGS
B7: Depreciation of existing assets
E9: Depreciation of existing building assets | G9: USD m | J9: {=_xlfn.LET( _xlpm.model_operating_flag,_xlfn.ANCHORARRAY( Time!J9), _xlpm.PPE, Assumptions!$F$13, _xlpm.useful_life, Assumptions!$F$14, _xlpm.depreciation, _xlpm.PPE / _xlpm.useful_life, _xlpm.model_operating_flag * _xlpm.depreciation )} -> 101.72 | K9: 101.72 | L9: 101.72 | M9: 101.72 | N9: 101.72 | O9: 101.72 | P9: 101.72 | Q9: 101.72 | R9: 101.72 | S9: 101.72
B11: Depreciation of new building assets
E13: Annual spent on new assets | G13: USD m | J13: {=_xlfn.LET( _xlpm.initial_spent, Assumptions!$F$16, _xlpm.annual_growth, Assumptions!$F$17, _xlpm.period,_xlfn.ANCHORARRAY( Time!J8), _xlpm.initial_spent * ( 1 + _xlpm.annual_growth ) ^ _xlpm.period )} -> 132.7625 | K13: 142.71969 | L13: 153.42366 | M13: 164.93044 | N13: 177.30022 | O13: 190.59774 | P13: 204.89257 | Q13: 220.25951 | R13: 236.77897 | S13: 254.5374
E15: Depreciation of new building assets | F15: Acquisition date | G15: Acqusition cost | H15: Remaining value | J15: {=_xlfn.ANCHORARRAY(J3)} -> 43465 | K15: 43830 | L15: 44196 | M15: 44561 | N15: 44926 | O15: 45291 | P15: 45657 | Q15: 46022 | R15: 46387 | S15: 46752
F16: {=TRANSPOSE(_xlfn.ANCHORARRAY( J3) )} -> 43465 | G16: {=TRANSPOSE(_xlfn.ANCHORARRAY( J13) )} -> 132.7625 | H16: {=_xlfn.ANCHORARRAY(G16) - _xlfn.BYROW(_xlfn.ANCHORARRAY(J16), _xleta.SUM )} -> 0 | J16: {=_xlfn.LET( _xlpm.acquisition_cost,_xlfn.ANCHORARRAY( $G$16), _xlpm.acquisition_date,_xlfn.ANCHORARRAY( $F$16), _xlpm.current_date,_xlfn.ANCHORARRAY( J15), _xlpm.useful_life, Assumptions!$F$19, _xlpm.period, YEAR( _xlpm.current_date ) - YEAR( _xlpm.acquisition_date ), _xlpm.rate, 1 / _xlpm.useful_life * 2, _xlpm.book_value, _xlpm.acquisition_cost * ( 1 - _xlpm.rate / 2 ) * ( 1 - _xlpm.rate ) ^ ( _xlpm.period - 1 ), IF( _xlpm.period < 0, 0, IF( _xlpm.period = 0, _xlpm.acquisition_cost * _xlpm.rate / 2, IF( _xlpm.period < _xlpm.useful_life, _xlpm.book_value * _xlpm.rate, IF( _xlpm.period = _xlpm.useful_life, _xlpm.book_value, 0 ) ) ) ) )} -> 18.966071 | K16: 32.513265 | L16: 23.223761 | M16: 16.588401 | N16: 11.848858 | O16: 8.4634697 | P16: 6.0453355 | Q16: 15.113339 | R16: 0 | S16: 0
F17: 43830 | G17: 142.71969 | H17: 0 | J17: 0 | K17: 20.388527 | L17: 34.95176 | M17: 24.965543 | N17: 17.832531 | O17: 12.737522 | P17: 9.09823 | Q17: 6.4987357 | R17: 16.246839 | S17: 0
F18: 44196 | G18: 153.42366 | H18: 0 | J18: 0 | K18: 0 | L18: 21.917666 | M18: 37.573142 | N18: 26.837959 | O18: 19.169971 | P18: 13.692836 | Q18: 9.7805972 | R18: 6.9861409 | S18: 17.465352
F19: 44561 | G19: 164.93044 | H19: 18.775254 | J19: 0 | K19: 0 | L19: 0 | M19: 23.561491 | N19: 40.391128 | O19: 28.850806 | P19: 20.607718 | Q19: 14.719799 | R19: 10.514142 | S19: 7.5101014
F20: 44926 | G20: 177.30022 | H20: 28.256757 | J20: 0 | K20: 0 | L20: 0 | M20: 0 | N20: 25.328603 | O20: 43.420462 | P20: 31.014616 | Q20: 22.153297 | R20: 15.823784 | S20: 11.302703
F21: 45291 | G21: 190.59774 | H21: 42.526419 | J21: 0 | K21: 0 | L21: 0 | M21: 0 | N21: 0 | O21: 27.228248 | P21: 46.676997 | Q21: 33.340712 | R21: 23.814794 | S21: 17.010567
F22: 45657 | G22: 204.89257 | H22: 64.00226 | J22: 0 | K22: 0 | L22: 0 | M22: 0 | N22: 0 | O22: 0 | P22: 29.270367 | Q22: 50.177772 | R22: 35.841266 | S22: 25.600904
F23: 46022 | G23: 220.25951 | H23: 96.323402 | J23: 0 | K23: 0 | L23: 0 | M23: 0 | N23: 0 | O23: 0 | P23: 0 | Q23: 31.465644 | R23: 53.941105 | S23: 38.529361
F24: 46387 | G24: 236.77897 | H24: 144.96672 | J24: 0 | K24: 0 | L24: 0 | M24: 0 | N24: 0 | O24: 0 | P24: 0 | Q24: 0 | R24: 33.825568 | S24: 57.986688
F25: 46752 | G25: 254.5374 | H25: 218.17491 | J25: 0 | K25: 0 | L25: 0 | M25: 0 | N25: 0 | O25: 0 | P25: 0 | Q25: 0 | R25: 0 | S25: 36.362485
G26: USD m | J26: {=_xlfn.BYCOL(_xlfn.ANCHORARRAY(J16), _xleta.SUM )} -> 18.966071 | K26: 52.901792 | L26: 80.093187 | M26: 102.68858 | N26: 122.23908 | O26: 139.87048 | P26: 156.4061 | Q26: 183.2499 | R26: 196.99364 | S26: 211.76816
B30: Net PP&E - buildings
E32: PP&E initial balance | G32: USD m | J32: {=_xlfn.DROP( _xlfn.HSTACK( Assumptions!$F$13,_xlfn.ANCHORARRAY( J37) ), , -1 )} -> 2543 | K32: 2555.0764 | L32: 2543.1743 | M32: 2514.7848 | N32: 2475.3067 | O32: 2428.6478 | P32: 1825.6551 | Q32: 1772.4215 | R32: 1707.7111 | S32: 1645.7765
E33: Sale of building assets | G33: USD m | J33: {=_xlfn.LET( _xlpm.date_sale_assets, Assumptions!$F$45, _xlpm.carrying_value, Assumptions!$F$46 * -1, _xlpm.current_date,_xlfn.ANCHORARRAY( J3), IF( _xlpm.current_date = _xlpm.date_sale_assets, _xlpm.carrying_value, 0 ) )} -> 0 | K33: 0 | L33: 0 | M33: 0 | N33: 0 | O33: -552 | P33: 0 | Q33: 0 | R33: 0 | S33: 0
E34: Depreciation of existing assets | G34: USD m | J34: {=_xlfn.ANCHORARRAY(J9) * -1} -> -101.72 | K34: -101.72 | L34: -101.72 | M34: -101.72 | N34: -101.72 | O34: -101.72 | P34: -101.72 | Q34: -101.72 | R34: -101.72 | S34: -101.72
E35: Annual spent on new buildings | G35: USD m | J35: {=_xlfn.ANCHORARRAY( J13)} -> 132.7625 | K35: 142.71969 | L35: 153.42366 | M35: 164.93044 | N35: 177.30022 | O35: 190.59774 | P35: 204.89257 | Q35: 220.25951 | R35: 236.77897 | S35: 254.5374
E36: Depreciation of new buildings | G36: USD m | J36: {=_xlfn.ANCHORARRAY( J26) * -1} -> -18.966071 | K36: -52.901792 | L36: -80.093187 | M36: -102.68858 | N36: -122.23908 | O36: -139.87048 | P36: -156.4061 | Q36: -183.2499 | R36: -196.99364 | S36: -211.76816
E37: PP&E final balance | G37: USD m | J37: {=_xlfn.LET( _xlpm.initial_PPE, Assumptions!$F$13, _xlpm.movement,_xlfn.ANCHORARRAY( J33) +_xlfn.ANCHORARRAY( J34) +_xlfn.ANCHORARRAY( J35) +_xlfn.ANCHORARRAY( J36), _xlfn.SCAN( _xlpm.initial_PPE, _xlpm.movement, _xleta.SUM ) )} -> 2555.0764 | K37: 2543.1743 | L37: 2514.7848 | M37: 2475.3067 | N37: 2428.6478 | O37: 1825.6551 | P37: 1772.4215 | Q37: 1707.7111 | R37: 1645.7765 | S37: 1586.8257
A40: IT CAPEX
B42: Depreciation of IT capex - base
E44: Annual base investment plan | F44: Acquisition date | G44: Acqusition cost | H44: Remaining value | J44: {=_xlfn.ANCHORARRAY( J3)} -> 43465 | K44: 43830 | L44: 44196 | M44: 44561 | N44: 44926 | O44: 45291 | P44: 45657 | Q44: 46022 | R44: 46387 | S44: 46752
F45: {=TRANSPOSE(_xlfn.ANCHORARRAY( J3) )} -> 43465 | G45: {=_xlfn.SEQUENCE( COUNTA(_xlfn.ANCHORARRAY( F45) ), 1, Assumptions!$F$25, 0 )} -> 50 | H45: {=_xlfn.ANCHORARRAY( G45) - _xlfn.BYROW(_xlfn.ANCHORARRAY( J45), _xleta.SUM )} -> 0 | J45: {=_xlfn.LET( _xlpm.acquisition_cost,_xlfn.ANCHORARRAY( $G$45), _xlpm.acquisition_date,_xlfn.ANCHORARRAY( $F$45), _xlpm.useful_life, Assumptions!$F$24, _xlpm.depreciation_cost, _xlpm.acquisition_cost / _xlpm.useful_life, _xlpm.current_date,_xlfn.ANCHORARRAY( J3), _xlpm.period, YEAR( _xlpm.current_date ) - YEAR( _xlpm.acquisition_date ), _xlpm.accumulated_depreciation, _xlpm.depreciation_cost * ( _xlpm.period - 0.5 ), _xlpm.book_value, _xlpm.acquisition_cost - _xlpm.accumulated_depreciation, IF( _xlpm.period < 0, 0, IF( _xlpm.period = 0, _xlpm.depreciation_cost / 2, IF( _xlpm.period < _xlpm.useful_life, _xlpm.depreciation_cost, IF( _xlpm.book_value > 0, _xlpm.book_value, 0 ) ) ) ) )} -> 5 | K45: 10 | L45: 10 | M45: 10 | N45: 10 | O45: 5 | P45: 0 | Q45: 0 | R45: 0 | S45: 0
F46: 43830 | G46: 50 | H46: 0 | J46: 0 | K46: 5 | L46: 10 | M46: 10 | N46: 10 | O46: 10 | P46: 5 | Q46: 0 | R46: 0 | S46: 0
F47: 44196 | G47: 50 | H47: 0 | J47: 0 | K47: 0 | L47: 5 | M47: 10 | N47: 10 | O47: 10 | P47: 10 | Q47: 5 | R47: 0 | S47: 0
F48: 44561 | G48: 50 | H48: 0 | J48: 0 | K48: 0 | L48: 0 | M48: 5 | N48: 10 | O48: 10 | P48: 10 | Q48: 10 | R48: 5 | S48: 0
F49: 44926 | G49: 50 | H49: 0 | J49: 0 | K49: 0 | L49: 0 | M49: 0 | N49: 5 | O49: 10 | P49: 10 | Q49: 10 | R49: 10 | S49: 5
F50: 45291 | G50: 50 | H50: 5 | J50: 0 | K50: 0 | L50: 0 | M50: 0 | N50: 0 | O50: 5 | P50: 10 | Q50: 10 | R50: 10 | S50: 10
F51: 45657 | G51: 50 | H51: 15 | J51: 0 | K51: 0 | L51: 0 | M51: 0 | N51: 0 | O51: 0 | P51: 5 | Q51: 10 | R51: 10 | S51: 10
F52: 46022 | G52: 50 | H52: 25 | J52: 0 | K52: 0 | L52: 0 | M52: 0 | N52: 0 | O52: 0 | P52: 0 | Q52: 5 | R52: 10 | S52: 10
F53: 46387 | G53: 50 | H53: 35 | J53: 0 | K53: 0 | L53: 0 | M53: 0 | N53: 0 | O53: 0 | P53: 0 | Q53: 0 | R53: 5 | S53: 10
F54: 46752 | G54: 50 | H54: 45 | J54: 0 | K54: 0 | L54: 0 | M54: 0 | N54: 0 | O54: 0 | P54: 0 | Q54: 0 | R54: 0 | S54: 5
G55: USD m | J55: {=_xlfn.BYCOL(_xlfn.ANCHORARRAY( J45), _xleta.SUM )} -> 5 | K55: 15 | L55: 25 | M55: 35 | N55: 45 | O55: 50 | P55: 50 | Q55: 50 | R55: 50 | S55: 50
B58: Depreciation of IT assets - investment plan
E60: Forecasted investment plan | F60: Acquisition date | G60: Acqusition cost | H60: Remaining value | J60: {=_xlfn.ANCHORARRAY($J$3)} -> 43465 | K60: 43830 | L60: 44196 | M60: 44561 | N60: 44926 | O60: 45291 | P60: 45657 | Q60: 46022 | R60: 46387 | S60: 46752
F61: {=EOMONTH( it_expansion_date, _xlfn.SEQUENCE( periods_it, 1, 0, 12 ) )} -> 43465 | G61: {=Assumptions!$F$30:$F$39} -> 5 | H61: {=_xlfn.ANCHORARRAY(G61) - _xlfn.BYROW(_xlfn.ANCHORARRAY(J61), _xleta.SUM )} -> 0 | J61: {=_xlfn.LET( _xlpm.acquisition_cost,_xlfn.ANCHORARRAY( $G$61), _xlpm.acquisition_date,_xlfn.ANCHORARRAY( $F$61), _xlpm.useful_life, Assumptions!$F$24, _xlpm.depreciation_cost, _xlpm.acquisition_cost / _xlpm.useful_life, _xlpm.period, YEAR(_xlfn.ANCHORARRAY( Calculations!J3) ) - YEAR( _xlpm.acquisition_date ), _xlpm.current_date,_xlfn.ANCHORARRAY( J3), _xlpm.accumulated_depreciation, _xlpm.depreciation_cost * ( _xlpm.period - 0.5 ), _xlpm.book_value, _xlpm.acquisition_cost - _xlpm.accumulated_depreciation, IF( _xlpm.period < 0, 0, IF( _xlpm.period = 0, _xlpm.depreciation_cost / 2, IF( _xlpm.period < _xlpm.useful_life, _xlpm.depreciation_cost, IF( _xlpm.book_value > 0, _xlpm.book_value, 0 ) ) ) ) )} -> 0.5 | K61: 1 | L61: 1 | M61: 1 | N61: 1 | O61: 0.5 | P61: 0 | Q61: 0 | R61: 0 | S61: 0
F62: 43830 | G62: 15 | H62: 0 | J62: 0 | K62: 1.5 | L62: 3 | M62: 3 | N62: 3 | O62: 3 | P62: 1.5 | Q62: 0 | R62: 0 | S62: 0
F63: 44196 | G63: 7.5 | H63: 0 | J63: 0 | K63: 0 | L63: 0.75 | M63: 1.5 | N63: 1.5 | O63: 1.5 | P63: 1.5 | Q63: 0.75 | R63: 0 | S63: 0
F64: 44561 | G64: 20.2 | H64: 0 | J64: 0 | K64: 0 | L64: 0 | M64: 2.02 | N64: 4.04 | O64: 4.04 | P64: 4.04 | Q64: 4.04 | R64: 2.02 | S64: 0
F65: 44926 | G65: 60.7 | H65: 0 | J65: 0 | K65: 0 | L65: 0 | M65: 0 | N65: 6.07 | O65: 12.14 | P65: 12.14 | Q65: 12.14 | R65: 12.14 | S65: 6.07
F66: 45291 | G66: 1 | H66: 0.1 | J66: 0 | K66: 0 | L66: 0 | M66: 0 | N66: 0 | O66: 0.1 | P66: 0.2 | Q66: 0.2 | R66: 0.2 | S66: 0.2
F67: 45657 | G67: 0.3 | H67: 0.09 | J67: 0 | K67: 0 | L67: 0 | M67: 0 | N67: 0 | O67: 0 | P67: 0.03 | Q67: 0.06 | R67: 0.06 | S67: 0.06
F68: 46022 | G68: 0 | H68: 0 | J68: 0 | K68: 0 | L68: 0 | M68: 0 | N68: 0 | O68: 0 | P68: 0 | Q68: 0 | R68: 0 | S68: 0
F69: 46387 | G69: 0 | H69: 0 | J69: 0 | K69: 0 | L69: 0 | M69: 0 | N69: 0 | O69: 0 | P69: 0 | Q69: 0 | R69: 0 | S69: 0
F70: 46752 | G70: 0.5 | H70: 0.45 | J70: 0 | K70: 0 | L70: 0 | M70: 0 | N70: 0 | O70: 0 | P70: 0 | Q70: 0 | R70: 0 | S70: 0.05
G71: {=_xlfn.BYCOL(_xlfn.ANCHORARRAY( G61), _xleta.SUM )} -> 110.2 | J71: {=_xlfn.BYCOL(_xlfn.ANCHORARRAY( J61), _xleta.SUM )} -> 0.5 | K71: 2.5 | L71: 4.75 | M71: 7.52 | N71: 15.61 | O71: 21.28 | P71: 19.41 | Q71: 17.19 | R71: 14.42 | S71: 6.38
B73: Net IT assets
E75: IT assets initial balance | J75: {=_xlfn.DROP( _xlfn.HSTACK( 0,_xlfn.ANCHORARRAY( J80) ),, -1 )} -> 0 | K75: 49.5 | L75: 97 | M75: 124.75 | N75: 152.43 | O75: 202.52 | P75: 182.24 | Q75: 163.13 | R75: 145.94 | S75: 131.52
E76: IT capex | J76: {=_xlfn.SEQUENCE( 1, periods_it, Assumptions!$F$25, 0 )} -> 50 | K76: 50 | L76: 50 | M76: 50 | N76: 50 | O76: 50 | P76: 50 | Q76: 50 | R76: 50 | S76: 50
E77: IT expansion plan | J77: {=_xlfn.BYCOL( ( YEAR(_xlfn.ANCHORARRAY( $F$61) ) = YEAR(_xlfn.ANCHORARRAY( J3) ) ) *_xlfn.ANCHORARRAY( $G$61), _xleta.SUM )} -> 5 | K77: 15 | L77: 7.5 | M77: 20.2 | N77: 60.7 | O77: 1 | P77: 0.3 | Q77: 0 | R77: 0 | S77: 0.5
E78: IT depreciation costs - base | J78: {=_xlfn.ANCHORARRAY( J55) * -1} -> -5 | K78: -15 | L78: -25 | M78: -35 | N78: -45 | O78: -50 | P78: -50 | Q78: -50 | R78: -50 | S78: -50
E79: IT depreciation costs | J79: {=_xlfn.ANCHORARRAY( J71) * -1} -> -0.5 | K79: -2.5 | L79: -4.75 | M79: -7.52 | N79: -15.61 | O79: -21.28 | P79: -19.41 | Q79: -17.19 | R79: -14.42 | S79: -6.38
E80: IT assets final balance | J80: {=_xlfn.LET( _xlpm.initial_balance, 0, _xlpm.movements,_xlfn.ANCHORARRAY( J76) +_xlfn.ANCHORARRAY( J77) +_xlfn.ANCHORARRAY( J78) +_xlfn.ANCHORARRAY( J79), _xlfn.SCAN( _xlpm.initial_balance, _xlpm.movements, _xleta.SUM ) )} -> 49.5 | K80: 97 | L80: 124.75 | M80: 152.43 | N80: 202.52 | O80: 182.24 | P80: 163.13 | Q80: 145.94 | R80: 131.52 | S80: 125.64
A83: Summary
B85: Total depreciation costs
E87: =E$9 -> Depreciation of existing building assets | G87: =G$9 -> USD m | J87: =J$9 -> 101.72 | K87: =K$9 -> 101.72 | L87: =L$9 -> 101.72 | M87: =M$9 -> 101.72 | N87: =N$9 -> 101.72 | O87: =O$9 -> 101.72 | P87: =P$9 -> 101.72 | Q87: =Q$9 -> 101.72 | ... S87: =S$9 -> 101.72
E88: Depreciation of new building assets | G88: =G$26 -> USD m | J88: =J$26 -> 18.966071 | K88: =K$26 -> 52.901792 | L88: =L$26 -> 80.093187 | M88: =M$26 -> 102.68858 | N88: =N$26 -> 122.23908 | O88: =O$26 -> 139.87048 | P88: =P$26 -> 156.4061 | Q88: =Q$26 -> 183.2499 | ... S88: =S$26 -> 211.76816
E89: Depreciation of IT assets - base | G89: =G$55 -> USD m | J89: =J$55 -> 5 | K89: =K$55 -> 15 | L89: =L$55 -> 25 | M89: =M$55 -> 35 | N89: =N$55 -> 45 | O89: =O$55 -> 50 | P89: =P$55 -> 50 | Q89: =Q$55 -> 50 | ... S89: =S$55 -> 50
E90: Depreciation of IT assets - investment | G90: USD m | J90: =J$71 -> 0.5 | K90: =K$71 -> 2.5 | L90: =L$71 -> 4.75 | M90: =M$71 -> 7.52 | N90: =N$71 -> 15.61 | O90: =O$71 -> 21.28 | P90: =P$71 -> 19.41 | Q90: =Q$71 -> 17.19 | ... S90: =S$71 -> 6.38
E91: Total depreciation costs | G91: USD m | J91: {=_xlfn.BYCOL( J87:S90, _xleta.SUM )} -> 126.18607 | K91: 172.12179 | L91: 211.56319 | M91: 246.92858 | N91: 284.56908 | O91: 312.87048 | P91: 327.5361 | Q91: 352.1599 | R91: 363.13364 | S91: 369.86816
B93: Net PP&E
D94: Opening balance PP&E | G94: USD m | J94: {=_xlfn.DROP( _xlfn.HSTACK( Assumptions!$F$13,_xlfn.ANCHORARRAY( Calculations!J99) ),, -1 )} -> 2543 | K94: 2604.5764 | L94: 2640.1743 | M94: 2639.5348 | N94: 2627.7367 | O94: 2631.1678 | P94: 2007.8951 | Q94: 1935.5515 | R94: 1853.6511 | S94: 1777.2965
E95: Capital spending - buildings | G95: USD m | J95: {=_xlfn.ANCHORARRAY( J13)} -> 132.7625 | K95: 142.71969 | L95: 153.42366 | M95: 164.93044 | N95: 177.30022 | O95: 190.59774 | P95: 204.89257 | Q95: 220.25951 | R95: 236.77897 | S95: 254.5374
E96: Capital spending - IT | G96: USD m | J96: {=_xlfn.ANCHORARRAY( J76) +_xlfn.ANCHORARRAY( J77)} -> 55 | K96: 65 | L96: 57.5 | M96: 70.2 | N96: 110.7 | O96: 51 | P96: 50.3 | Q96: 50 | R96: 50 | S96: 50.5
E97: Sale of assets | G97: USD m | J97: {=_xlfn.ANCHORARRAY(J33)} -> 0 | K97: 0 | L97: 0 | M97: 0 | N97: 0 | O97: -552 | P97: 0 | Q97: 0 | R97: 0 | S97: 0
E98: Depreciation costs | G98: USD m | J98: {=_xlfn.ANCHORARRAY( J91) * -1} -> -126.18607 | K98: -172.12179 | L98: -211.56319 | M98: -246.92858 | N98: -284.56908 | O98: -312.87048 | P98: -327.5361 | Q98: -352.1599 | R98: -363.13364 | S98: -369.86816
D99: Closing balance PP&E | G99: USD m | J99: {=_xlfn.LET( _xlpm.initial_PPE, Assumptions!$F$13, _xlpm.movements,_xlfn.ANCHORARRAY( Calculations!J95) +_xlfn.ANCHORARRAY( Calculations!J96) +_xlfn.ANCHORARRAY( Calculations!J97) +_xlfn.ANCHORARRAY( Calculations!J98), _xlfn.SCAN( _xlpm.initial_PPE, _xlpm.movements, _xleta.SUM ) )} -> 2604.5764 | K99: 2640.1743 | L99: 2639.5348 | M99: 2627.7367 | N99: 2631.1678 | O99: 2007.8951 | P99: 1935.5515 | Q99: 1853.6511 | R99: 1777.2965 | S99: 1712.4657

Sheet Assumptions
A1: {=company} -> Galway Inc.
A2: {=topic} -> CFM topic: Capex and Depreciation
A3: ASSUMPTIONS SCHEDULE
A5: Model technical inputs
E7: Company name | F7: Galway Inc. | G7: label
E8: CFM topic | F8: Capex and Depreciation | G8: label
E9: End of first forecasting year | F9: 43465 | G9: date
A11: PP&E - Buildings
E13: Net PP&E - Buildings in 2017 | F13: 2543 | G13: USD m
E14: Estimated useful life - existing bldg | F14: 25 | G14: years
E16: Spent in 2017 - buildings | F16: 123.5 | G16: USD m
E17: Annual spent on building growth factor | F17: 0.075 | G17: %
E18: Duration of the building investment plan | F18: 10 | G18: years
E19: Estimated useful life - new bldg assets | F19: 7 | G19: years
E20: Method of depreciation | F20: DD | G20: method
A22: IT Department
E24: Estimated useful life - IT equipment | F24: 5 | G24: years
E25: Annual spent on IT equipment | F25: 50 | G25: USD m
E26: Duration of the IT equipment investment plan | F26: 10 | G26: years
E27: Method of depreciation | F27: straight line | G27: method
C29: Additional expansion plan
E30: Year 1 | F30: 5 | G30: USD m
E31: Year 2 | F31: 15 | G31: USD m
E32: Year 3 | F32: 7.5 | G32: USD m
E33: Year 4 | F33: 20.2 | G33: USD m
E34: Year 5 | F34: 60.7 | G34: USD m
E35: Year 6 | F35: 1 | G35: USD m
E36: Year 7 | F36: 0.3 | G36: USD m
E37: Year 8 | F37: 0 | G37: USD m
E38: Year 9 | F38: 0 | G38: USD m
E39: Year 10 | F39: 0.5 | G39: USD m
E41: Start date of the additional expansion plan | F41: 43465 | G41: date
A43: Scenario assumptions
E45: Date of sale of building | F45: 45291 | G45: date
E46: Carrying value of building sold | F46: 552 | G46: USD m
A48: End of schedule

Sheet Time
A1: {=company} -> Galway Inc.
A2: {=topic} -> CFM topic: Capex and Depreciation
A3: TIME SCHEDULE
A5: MODEL TIMELINE AND COUNTER
E7: Model timeline | G7: date | J7: {=EOMONTH( start_date, _xlfn.SEQUENCE( 1, MAX( periods_bldg, periods_it ), 0, 12 ) )} -> 43465 | K7: 43830 | L7: 44196 | M7: 44561 | N7: 44926 | O7: 45291 | P7: 45657 | Q7: 46022 | R7: 46387 | S7: 46752
E8: Model period counter | G8: counter | J8: {=_xlfn.SEQUENCE( 1, MAX( periods_bldg, periods_it ), 1, 1 )} -> 1 | K8: 2 | L8: 3 | M8: 4 | N8: 5 | O8: 6 | P8: 7 | Q8: 8 | R8: 9 | S8: 10
E9: Model operating period flag | G9: flag | J9: {=_xlfn.SEQUENCE( 1, periods_bldg, 1, 0 )} -> 1 | K9: 1 | L9: 1 | M9: 1 | N9: 1 | O9: 1 | P9: 1 | Q9: 1 | R9: 1 | S9: 1
A13: MODEL FLAGS
A48: End of schedule

Sheet Tmp
A1: {=company} -> Galway Inc.
A2: {=topic} -> CFM topic: Capex and Depreciation
A3: TMP SCHEDULE
A45: End of schedule

Sheet Dep_Ans
B2: CFM Sample Exam Questions
B3: Fully Depreciated Assets
D6: 2017 | E6: =D6+1 -> 2018 | F6: =E6+1 -> 2019 | G6: =F6+1 -> 2020 | H6: =G6+1 -> 2021 | I6: =H6+1 -> 2022 | J6: =I6+1 -> 2023 | K6: =J6+1 -> 2024 | L6: =K6+1 -> 2025 | ... N6: =M6+1 -> 2027
B8: Depreciation on Existing Assets (Buildings)
B9: Useful Life | C9: 25
B11: Sale of Assets | C11: =$D$104 -> 0
B12: Year of Sale | C12: 2020
B14: Opening | E14: =D16 -> 2543 | F14: =E16 -> 2543 | G14: =F16 -> 2543 | H14: =G16 -> 2543 | I14: =H16 -> 2543 | J14: =I16 -> 2543 | K14: =J16 -> 2543 | L14: =K16 -> 2543 | ... N14: =M16 -> 2543
B15: Sale of Assets | E15: =IF(E$6=$C$12,-$C$11,0) -> 0 | F15: =IF(F$6=$C$12,-$C$11,0) -> 0 | G15: =IF(G$6=$C$12,-$C$11,0) -> 0 | H15: =IF(H$6=$C$12,-$C$11,0) -> 0 | I15: =IF(I$6=$C$12,-$C$11,0) -> 0 | J15: =IF(J$6=$C$12,-$C$11,0) -> 0 | K15: =IF(K$6=$C$12,-$C$11,0) -> 0 | L15: =IF(L$6=$C$12,-$C$11,0) -> 0 | ... N15: =IF(N$6=$C$12,-$C$11,0) -> 0
B16: Ending | D16: 2543 | E16: =SUM(E14:E15) -> 2543 | F16: =SUM(F14:F15) -> 2543 | G16: =SUM(G14:G15) -> 2543 | H16: =SUM(H14:H15) -> 2543 | I16: =SUM(I14:I15) -> 2543 | J16: =SUM(J14:J15) -> 2543 | K16: =SUM(K14:K15) -> 2543 | L16: =SUM(L14:L15) -> 2543 | ... N16: =SUM(N14:N15) -> 2543
B18: Depreciation | E18: =E14/$C$9 -> 101.72 | F18: =F14/$C$9 -> 101.72 | G18: =G14/$C$9 -> 101.72 | H18: =H14/$C$9 -> 101.72 | I18: =I14/$C$9 -> 101.72 | J18: =J14/$C$9 -> 101.72 | K18: =K14/$C$9 -> 101.72 | L18: =L14/$C$9 -> 101.72 | ... N18: =N14/$C$9 -> 101.72
B20: Depreciation on New Assets (Buildings)
B21: Capex | D21: 123.5 | E21: =D21*(1+E22) -> 132.7625 | F21: =E21*(1+F22) -> 142.71969 | G21: =F21*(1+G22) -> 153.42366 | H21: =G21*(1+H22) -> 164.93044 | I21: =H21*(1+I22) -> 177.30022 | J21: =I21*(1+J22) -> 190.59774 | K21: =J21*(1+K22) -> 204.89257 | L21: =K21*(1+L22) -> 220.25951 | ... N21: =M21*(1+N22) -> 254.5374
B22: Growth | E22: 0.075 | F22: =E22 -> 0.075 | G22: =F22 -> 0.075 | H22: =G22 -> 0.075 | I22: =H22 -> 0.075 | J22: =I22 -> 0.075 | K22: =J22 -> 0.075 | L22: =K22 -> 0.075 | M22: =L22 -> 0.075 | N22: =M22 -> 0.075
B25: Useful Life | C25: 7
B26: Depreciation Rate (% of Book Value) | C26: =1/C25*2 -> 0.28571429
B28: Depreciation Expense | P28: Check
B29: {=TRANSPOSE(E6:N6)} -> 2018 | C29: =INDEX($D$21:$N$21,MATCH($B29,$D$6:$N$6,0)) -> 132.7625 | E29: =IF(E$6=$B29,($C29-SUM($D29:D29))*$C$26/2,IF(E$6<$B29+$C$25,($C29-SUM($D29:D29))*$C$26,$C29-SUM($D29:D29))) -> 18.966071 | F29: =IF(F$6=$B29,($C29-SUM($D29:E29))*$C$26/2,IF(F$6<$B29+$C$25,($C29-SUM($D29:E29))*$C$26,$C29-SUM($D29:E29))) -> 32.513265 | G29: =IF(G$6=$B29,($C29-SUM($D29:F29))*$C$26/2,IF(G$6<$B29+$C$25,($C29-SUM($D29:F29))*$C$26,$C29-SUM($D29:F29))) -> 23.223761 | H29: =IF(H$6=$B29,($C29-SUM($D29:G29))*$C$26/2,IF(H$6<$B29+$C$25,($C29-SUM($D29:G29))*$C$26,$C29-SUM($D29:G29))) -> 16.588401 | I29: =IF(I$6=$B29,($C29-SUM($D29:H29))*$C$26/2,IF(I$6<$B29+$C$25,($C29-SUM($D29:H29))*$C$26,$C29-SUM($D29:H29))) -> 11.848858 | J29: =IF(J$6=$B29,($C29-SUM($D29:I29))*$C$26/2,IF(J$6<$B29+$C$25,($C29-SUM($D29:I29))*$C$26,$C29-SUM($D29:I29))) -> 8.4634697 | K29: =IF(K$6=$B29,($C29-SUM($D29:J29))*$C$26/2,IF(K$6<$B29+$C$25,($C29-SUM($D29:J29))*$C$26,$C29-SUM($D29:J29))) -> 6.0453355 | L29: =IF(L$6=$B29,($C29-SUM($D29:K29))*$C$26/2,IF(L$6<$B29+$C$25,($C29-SUM($D29:K29))*$C$26,$C29-SUM($D29:K29))) -> 15.113339 | ... N29: =IF(N$6=$B29,($C29-SUM($D29:M29))*$C$26/2,IF(N$6<$B29+$C$25,($C29-SUM($D29:M29))*$C$26,$C29-SUM($D29:M29))) -> 0 | P29: =SUM(E29:N29) -> 132.7625 | Q29: =P29<=C29 -> TRUE
B30: 2019 | C30: =INDEX($D$21:$N$21,MATCH($B30,$D$6:$N$6,0)) -> 142.71969 | F30: =IF(F$6=$B30,($C30-SUM($D30:E30))*$C$26/2,IF(F$6<$B30+$C$25,($C30-SUM($D30:E30))*$C$26,$C30-SUM($D30:E30))) -> 20.388527 | G30: =IF(G$6=$B30,($C30-SUM($D30:F30))*$C$26/2,IF(G$6<$B30+$C$25,($C30-SUM($D30:F30))*$C$26,$C30-SUM($D30:F30))) -> 34.95176 | H30: =IF(H$6=$B30,($C30-SUM($D30:G30))*$C$26/2,IF(H$6<$B30+$C$25,($C30-SUM($D30:G30))*$C$26,$C30-SUM($D30:G30))) -> 24.965543 | I30: =IF(I$6=$B30,($C30-SUM($D30:H30))*$C$26/2,IF(I$6<$B30+$C$25,($C30-SUM($D30:H30))*$C$26,$C30-SUM($D30:H30))) -> 17.832531 | J30: =IF(J$6=$B30,($C30-SUM($D30:I30))*$C$26/2,IF(J$6<$B30+$C$25,($C30-SUM($D30:I30))*$C$26,$C30-SUM($D30:I30))) -> 12.737522 | K30: =IF(K$6=$B30,($C30-SUM($D30:J30))*$C$26/2,IF(K$6<$B30+$C$25,($C30-SUM($D30:J30))*$C$26,$C30-SUM($D30:J30))) -> 9.09823 | L30: =IF(L$6=$B30,($C30-SUM($D30:K30))*$C$26/2,IF(L$6<$B30+$C$25,($C30-SUM($D30:K30))*$C$26,$C30-SUM($D30:K30))) -> 6.4987357 | M30: =IF(M$6=$B30,($C30-SUM($D30:L30))*$C$26/2,IF(M$6<$B30+$C$25,($C30-SUM($D30:L30))*$C$26,$C30-SUM($D30:L30))) -> 16.246839 | N30: =IF(N$6=$B30,($C30-SUM($D30:M30))*$C$26/2,IF(N$6<$B30+$C$25,($C30-SUM($D30:M30))*$C$26,$C30-SUM($D30:M30))) -> 0 | P30: =SUM(E30:N30) -> 142.71969 | Q30: =P30<=C30 -> TRUE
B31: 2020 | C31: =INDEX($D$21:$N$21,MATCH($B31,$D$6:$N$6,0)) -> 153.42366 | G31: =IF(G$6=$B31,($C31-SUM($D31:F31))*$C$26/2,IF(G$6<$B31+$C$25,($C31-SUM($D31:F31))*$C$26,$C31-SUM($D31:F31))) -> 21.917666 | H31: =IF(H$6=$B31,($C31-SUM($D31:G31))*$C$26/2,IF(H$6<$B31+$C$25,($C31-SUM($D31:G31))*$C$26,$C31-SUM($D31:G31))) -> 37.573142 | I31: =IF(I$6=$B31,($C31-SUM($D31:H31))*$C$26/2,IF(I$6<$B31+$C$25,($C31-SUM($D31:H31))*$C$26,$C31-SUM($D31:H31))) -> 26.837959 | J31: =IF(J$6=$B31,($C31-SUM($D31:I31))*$C$26/2,IF(J$6<$B31+$C$25,($C31-SUM($D31:I31))*$C$26,$C31-SUM($D31:I31))) -> 19.169971 | K31: =IF(K$6=$B31,($C31-SUM($D31:J31))*$C$26/2,IF(K$6<$B31+$C$25,($C31-SUM($D31:J31))*$C$26,$C31-SUM($D31:J31))) -> 13.692836 | L31: =IF(L$6=$B31,($C31-SUM($D31:K31))*$C$26/2,IF(L$6<$B31+$C$25,($C31-SUM($D31:K31))*$C$26,$C31-SUM($D31:K31))) -> 9.7805972 | M31: =IF(M$6=$B31,($C31-SUM($D31:L31))*$C$26/2,IF(M$6<$B31+$C$25,($C31-SUM($D31:L31))*$C$26,$C31-SUM($D31:L31))) -> 6.9861409 | N31: =IF(N$6=$B31,($C31-SUM($D31:M31))*$C$26/2,IF(N$6<$B31+$C$25,($C31-SUM($D31:M31))*$C$26,$C31-SUM($D31:M31))) -> 17.465352 | P31: =SUM(E31:N31) -> 153.42366 | Q31: =P31<=C31 -> TRUE
B32: 2021 | C32: =INDEX($D$21:$N$21,MATCH($B32,$D$6:$N$6,0)) -> 164.93044 | H32: =IF(H$6=$B32,($C32-SUM($D32:G32))*$C$26/2,IF(H$6<$B32+$C$25,($C32-SUM($D32:G32))*$C$26,$C32-SUM($D32:G32))) -> 23.561491 | I32: =IF(I$6=$B32,($C32-SUM($D32:H32))*$C$26/2,IF(I$6<$B32+$C$25,($C32-SUM($D32:H32))*$C$26,$C32-SUM($D32:H32))) -> 40.391128 | J32: =IF(J$6=$B32,($C32-SUM($D32:I32))*$C$26/2,IF(J$6<$B32+$C$25,($C32-SUM($D32:I32))*$C$26,$C32-SUM($D32:I32))) -> 28.850806 | K32: =IF(K$6=$B32,($C32-SUM($D32:J32))*$C$26/2,IF(K$6<$B32+$C$25,($C32-SUM($D32:J32))*$C$26,$C32-SUM($D32:J32))) -> 20.607718 | L32: =IF(L$6=$B32,($C32-SUM($D32:K32))*$C$26/2,IF(L$6<$B32+$C$25,($C32-SUM($D32:K32))*$C$26,$C32-SUM($D32:K32))) -> 14.719799 | M32: =IF(M$6=$B32,($C32-SUM($D32:L32))*$C$26/2,IF(M$6<$B32+$C$25,($C32-SUM($D32:L32))*$C$26,$C32-SUM($D32:L32))) -> 10.514142 | N32: =IF(N$6=$B32,($C32-SUM($D32:M32))*$C$26/2,IF(N$6<$B32+$C$25,($C32-SUM($D32:M32))*$C$26,$C32-SUM($D32:M32))) -> 7.5101014 | P32: =SUM(E32:N32) -> 146.15519 | Q32: =P32<=C32 -> TRUE
B33: 2022 | C33: =INDEX($D$21:$N$21,MATCH($B33,$D$6:$N$6,0)) -> 177.30022 | I33: =IF(I$6=$B33,($C33-SUM($D33:H33))*$C$26/2,IF(I$6<$B33+$C$25,($C33-SUM($D33:H33))*$C$26,$C33-SUM($D33:H33))) -> 25.328603 | J33: =IF(J$6=$B33,($C33-SUM($D33:I33))*$C$26/2,IF(J$6<$B33+$C$25,($C33-SUM($D33:I33))*$C$26,$C33-SUM($D33:I33))) -> 43.420462 | K33: =IF(K$6=$B33,($C33-SUM($D33:J33))*$C$26/2,IF(K$6<$B33+$C$25,($C33-SUM($D33:J33))*$C$26,$C33-SUM($D33:J33))) -> 31.014616 | L33: =IF(L$6=$B33,($C33-SUM($D33:K33))*$C$26/2,IF(L$6<$B33+$C$25,($C33-SUM($D33:K33))*$C$26,$C33-SUM($D33:K33))) -> 22.153297 | M33: =IF(M$6=$B33,($C33-SUM($D33:L33))*$C$26/2,IF(M$6<$B33+$C$25,($C33-SUM($D33:L33))*$C$26,$C33-SUM($D33:L33))) -> 15.823784 | N33: =IF(N$6=$B33,($C33-SUM($D33:M33))*$C$26/2,IF(N$6<$B33+$C$25,($C33-SUM($D33:M33))*$C$26,$C33-SUM($D33:M33))) -> 11.302703 | P33: =SUM(E33:N33) -> 149.04347 | Q33: =P33<=C33 -> TRUE
B34: 2023 | C34: =INDEX($D$21:$N$21,MATCH($B34,$D$6:$N$6,0)) -> 190.59774 | J34: =IF(J$6=$B34,($C34-SUM($D34:I34))*$C$26/2,IF(J$6<$B34+$C$25,($C34-SUM($D34:I34))*$C$26,$C34-SUM($D34:I34))) -> 27.228248 | K34: =IF(K$6=$B34,($C34-SUM($D34:J34))*$C$26/2,IF(K$6<$B34+$C$25,($C34-SUM($D34:J34))*$C$26,$C34-SUM($D34:J34))) -> 46.676997 | L34: =IF(L$6=$B34,($C34-SUM($D34:K34))*$C$26/2,IF(L$6<$B34+$C$25,($C34-SUM($D34:K34))*$C$26,$C34-SUM($D34:K34))) -> 33.340712 | M34: =IF(M$6=$B34,($C34-SUM($D34:L34))*$C$26/2,IF(M$6<$B34+$C$25,($C34-SUM($D34:L34))*$C$26,$C34-SUM($D34:L34))) -> 23.814794 | N34: =IF(N$6=$B34,($C34-SUM($D34:M34))*$C$26/2,IF(N$6<$B34+$C$25,($C34-SUM($D34:M34))*$C$26,$C34-SUM($D34:M34))) -> 17.010567 | P34: =SUM(E34:N34) -> 148.07132 | Q34: =P34<=C34 -> TRUE
B35: 2024 | C35: =INDEX($D$21:$N$21,MATCH($B35,$D$6:$N$6,0)) -> 204.89257 | K35: =IF(K$6=$B35,($C35-SUM($D35:J35))*$C$26/2,IF(K$6<$B35+$C$25,($C35-SUM($D35:J35))*$C$26,$C35-SUM($D35:J35))) -> 29.270367 | L35: =IF(L$6=$B35,($C35-SUM($D35:K35))*$C$26/2,IF(L$6<$B35+$C$25,($C35-SUM($D35:K35))*$C$26,$C35-SUM($D35:K35))) -> 50.177772 | M35: =IF(M$6=$B35,($C35-SUM($D35:L35))*$C$26/2,IF(M$6<$B35+$C$25,($C35-SUM($D35:L35))*$C$26,$C35-SUM($D35:L35))) -> 35.841266 | N35: =IF(N$6=$B35,($C35-SUM($D35:M35))*$C$26/2,IF(N$6<$B35+$C$25,($C35-SUM($D35:M35))*$C$26,$C35-SUM($D35:M35))) -> 25.600904 | P35: =SUM(E35:N35) -> 140.89031 | Q35: =P35<=C35 -> TRUE
B36: 2025 | C36: =INDEX($D$21:$N$21,MATCH($B36,$D$6:$N$6,0)) -> 220.25951 | L36: =IF(L$6=$B36,($C36-SUM($D36:K36))*$C$26/2,IF(L$6<$B36+$C$25,($C36-SUM($D36:K36))*$C$26,$C36-SUM($D36:K36))) -> 31.465644 | M36: =IF(M$6=$B36,($C36-SUM($D36:L36))*$C$26/2,IF(M$6<$B36+$C$25,($C36-SUM($D36:L36))*$C$26,$C36-SUM($D36:L36))) -> 53.941105 | N36: =IF(N$6=$B36,($C36-SUM($D36:M36))*$C$26/2,IF(N$6<$B36+$C$25,($C36-SUM($D36:M36))*$C$26,$C36-SUM($D36:M36))) -> 38.529361 | P36: =SUM(E36:N36) -> 123.93611 | Q36: =P36<=C36 -> TRUE
B37: 2026 | C37: =INDEX($D$21:$N$21,MATCH($B37,$D$6:$N$6,0)) -> 236.77897 | M37: =IF(M$6=$B37,($C37-SUM($D37:L37))*$C$26/2,IF(M$6<$B37+$C$25,($C37-SUM($D37:L37))*$C$26,$C37-SUM($D37:L37))) -> 33.825568 | N37: =IF(N$6=$B37,($C37-SUM($D37:M37))*$C$26/2,IF(N$6<$B37+$C$25,($C37-SUM($D37:M37))*$C$26,$C37-SUM($D37:M37))) -> 57.986688 | P37: =SUM(E37:N37) -> 91.812256 | Q37: =P37<=C37 -> TRUE
B38: 2027 | C38: =INDEX($D$21:$N$21,MATCH($B38,$D$6:$N$6,0)) -> 254.5374 | N38: =IF(N$6=$B38,($C38-SUM($D38:M38))*$C$26/2,IF(N$6<$B38+$C$25,($C38-SUM($D38:M38))*$C$26,$C38-SUM($D38:M38))) -> 36.362485 | P38: =SUM(E38:N38) -> 36.362485 | Q38: =P38<=C38 -> TRUE
B40: Total | E40: =SUM(E29:E38) -> 18.966071 | F40: =SUM(F29:F38) -> 52.901792 | G40: =SUM(G29:G38) -> 80.093187 | H40: =SUM(H29:H38) -> 102.68858 | I40: =SUM(I29:I38) -> 122.23908 | J40: =SUM(J29:J38) -> 139.87048 | K40: =SUM(K29:K38) -> 156.4061 | L40: =SUM(L29:L38) -> 183.2499 | ... N40: =SUM(N29:N38) -> 211.76816
B42: Total Building Depreciation | E42: =E40+E18 -> 120.68607 | F42: =F40+F18 -> 154.62179 | G42: =G40+G18 -> 181.81319 | H42: =H40+H18 -> 204.40858 | I42: =I40+I18 -> 223.95908 | J42: =J40+J18 -> 241.59048 | K42: =K40+K18 -> 258.1261 | L42: =L40+L18 -> 284.9699 | ... N42: =N40+N18 -> 313.48816
B45: IT Department Assets
B47: Start Year of Expansion Project | C47: =$D$106 -> 2018
B48: 1 | C48: 5
B49: =B48+1 -> 2 | C49: 15
B50: =B49+1 -> 3 | C50: 7.5
B51: =B50+1 -> 4 | C51: 20.2
B52: =B51+1 -> 5 | C52: 60.7
B53: =B52+1 -> 6 | C53: 1
B54: =B53+1 -> 7 | C54: 0.3
B55: =B54+1 -> 8 | C55: 0
B56: =B55+1 -> 9 | C56: 0
B57: =B56+1 -> 10 | C57: 0.5
B59: Expansion Project Year | E59: =IF(E$6>=$C$47,D59+1,0) -> 1 | F59: =IF(F$6>=$C$47,E59+1,0) -> 2 | G59: =IF(G$6>=$C$47,F59+1,0) -> 3 | H59: =IF(H$6>=$C$47,G59+1,0) -> 4 | I59: =IF(I$6>=$C$47,H59+1,0) -> 5 | J59: =IF(J$6>=$C$47,I59+1,0) -> 6 | K59: =IF(K$6>=$C$47,J59+1,0) -> 7 | L59: =IF(L$6>=$C$47,K59+1,0) -> 8 | ... N59: =IF(N$6>=$C$47,M59+1,0) -> 10
B61: Capital Spending
B62: Expansion Project | E62: =IFERROR(VLOOKUP(E59,$B$48:$C$57,COLUMNS($B$48:$C$48),FALSE),0) -> 5 | F62: =IFERROR(VLOOKUP(F59,$B$48:$C$57,COLUMNS($B$48:$C$48),FALSE),0) -> 15 | G62: =IFERROR(VLOOKUP(G59,$B$48:$C$57,COLUMNS($B$48:$C$48),FALSE),0) -> 7.5 | H62: =IFERROR(VLOOKUP(H59,$B$48:$C$57,COLUMNS($B$48:$C$48),FALSE),0) -> 20.2 | I62: =IFERROR(VLOOKUP(I59,$B$48:$C$57,COLUMNS($B$48:$C$48),FALSE),0) -> 60.7 | J62: =IFERROR(VLOOKUP(J59,$B$48:$C$57,COLUMNS($B$48:$C$48),FALSE),0) -> 1 | K62: =IFERROR(VLOOKUP(K59,$B$48:$C$57,COLUMNS($B$48:$C$48),FALSE),0) -> 0.3 | L62: =IFERROR(VLOOKUP(L59,$B$48:$C$57,COLUMNS($B$48:$C$48),FALSE),0) -> 0 | ... N62: =IFERROR(VLOOKUP(N59,$B$48:$C$57,COLUMNS($B$48:$C$48),FALSE),0) -> 0.5
B63: Base Plan | C63: 50 | E63: =$C63 -> 50 | F63: =$C63 -> 50 | G63: =$C63 -> 50 | H63: =$C63 -> 50 | I63: =$C63 -> 50 | J63: =$C63 -> 50 | K63: =$C63 -> 50 | L63: =$C63 -> 50 | ... N63: =$C63 -> 50
B64: Total Capital Spending | E64: =SUM(E62:E63) -> 55 | F64: =SUM(F62:F63) -> 65 | G64: =SUM(G62:G63) -> 57.5 | H64: =SUM(H62:H63) -> 70.2 | I64: =SUM(I62:I63) -> 110.7 | J64: =SUM(J62:J63) -> 51 | K64: =SUM(K62:K63) -> 50.3 | L64: =SUM(L62:L63) -> 50 | ... N64: =SUM(N62:N63) -> 50.5
B66: Useful Life | C66: 5
B68: Depreciation Expense | P68: Check
B69: {=TRANSPOSE(E6:N6)} -> 2018 | C69: =INDEX($D$64:$N$64,MATCH($B69,$D$6:$N$6,0)) -> 55 | E69: =IF(E$6=$B69,$C69/$C$66/2,MIN($C69/$C$66,$C69-SUM($D69:D69))) -> 5.5 | F69: =IF(F$6=$B69,$C69/$C$66/2,MIN($C69/$C$66,$C69-SUM($D69:E69))) -> 11 | G69: =IF(G$6=$B69,$C69/$C$66/2,MIN($C69/$C$66,$C69-SUM($D69:F69))) -> 11 | H69: =IF(H$6=$B69,$C69/$C$66/2,MIN($C69/$C$66,$C69-SUM($D69:G69))) -> 11 | I69: =IF(I$6=$B69,$C69/$C$66/2,MIN($C69/$C$66,$C69-SUM($D69:H69))) -> 11 | J69: =IF(J$6=$B69,$C69/$C$66/2,MIN($C69/$C$66,$C69-SUM($D69:I69))) -> 5.5 | K69: =IF(K$6=$B69,$C69/$C$66/2,MIN($C69/$C$66,$C69-SUM($D69:J69))) -> 0 | L69: =IF(L$6=$B69,$C69/$C$66/2,MIN($C69/$C$66,$C69-SUM($D69:K69))) -> 0 | ... N69: =IF(N$6=$B69,$C69/$C$66/2,MIN($C69/$C$66,$C69-SUM($D69:M69))) -> 0 | P69: =SUM(E69:N69) -> 55 | Q69: =P69<=C69 -> TRUE
B70: 2019 | C70: =INDEX($D$64:$N$64,MATCH($B70,$D$6:$N$6,0)) -> 65 | F70: =IF(F$6=$B70,$C70/$C$66/2,MIN($C70/$C$66,$C70-SUM($D70:E70))) -> 6.5 | G70: =IF(G$6=$B70,$C70/$C$66/2,MIN($C70/$C$66,$C70-SUM($D70:F70))) -> 13 | H70: =IF(H$6=$B70,$C70/$C$66/2,MIN($C70/$C$66,$C70-SUM($D70:G70))) -> 13 | I70: =IF(I$6=$B70,$C70/$C$66/2,MIN($C70/$C$66,$C70-SUM($D70:H70))) -> 13 | J70: =IF(J$6=$B70,$C70/$C$66/2,MIN($C70/$C$66,$C70-SUM($D70:I70))) -> 13 | K70: =IF(K$6=$B70,$C70/$C$66/2,MIN($C70/$C$66,$C70-SUM($D70:J70))) -> 6.5 | L70: =IF(L$6=$B70,$C70/$C$66/2,MIN($C70/$C$66,$C70-SUM($D70:K70))) -> 0 | M70: =IF(M$6=$B70,$C70/$C$66/2,MIN($C70/$C$66,$C70-SUM($D70:L70))) -> 0 | N70: =IF(N$6=$B70,$C70/$C$66/2,MIN($C70/$C$66,$C70-SUM($D70:M70))) -> 0 | P70: =SUM(E70:N70) -> 65 | Q70: =P70<=C70 -> TRUE
B71: 2020 | C71: =INDEX($D$64:$N$64,MATCH($B71,$D$6:$N$6,0)) -> 57.5 | G71: =IF(G$6=$B71,$C71/$C$66/2,MIN($C71/$C$66,$C71-SUM($D71:F71))) -> 5.75 | H71: =IF(H$6=$B71,$C71/$C$66/2,MIN($C71/$C$66,$C71-SUM($D71:G71))) -> 11.5 | I71: =IF(I$6=$B71,$C71/$C$66/2,MIN($C71/$C$66,$C71-SUM($D71:H71))) -> 11.5 | J71: =IF(J$6=$B71,$C71/$C$66/2,MIN($C71/$C$66,$C71-SUM($D71:I71))) -> 11.5 | K71: =IF(K$6=$B71,$C71/$C$66/2,MIN($C71/$C$66,$C71-SUM($D71:J71))) -> 11.5 | L71: =IF(L$6=$B71,$C71/$C$66/2,MIN($C71/$C$66,$C71-SUM($D71:K71))) -> 5.75 | M71: =IF(M$6=$B71,$C71/$C$66/2,MIN($C71/$C$66,$C71-SUM($D71:L71))) -> 0 | N71: =IF(N$6=$B71,$C71/$C$66/2,MIN($C71/$C$66,$C71-SUM($D71:M71))) -> 0 | P71: =SUM(E71:N71) -> 57.5 | Q71: =P71<=C71 -> TRUE
B72: 2021 | C72: =INDEX($D$64:$N$64,MATCH($B72,$D$6:$N$6,0)) -> 70.2 | H72: =IF(H$6=$B72,$C72/$C$66/2,MIN($C72/$C$66,$C72-SUM($D72:G72))) -> 7.02 | I72: =IF(I$6=$B72,$C72/$C$66/2,MIN($C72/$C$66,$C72-SUM($D72:H72))) -> 14.04 | J72: =IF(J$6=$B72,$C72/$C$66/2,MIN($C72/$C$66,$C72-SUM($D72:I72))) -> 14.04 | K72: =IF(K$6=$B72,$C72/$C$66/2,MIN($C72/$C$66,$C72-SUM($D72:J72))) -> 14.04 | L72: =IF(L$6=$B72,$C72/$C$66/2,MIN($C72/$C$66,$C72-SUM($D72:K72))) -> 14.04 | M72: =IF(M$6=$B72,$C72/$C$66/2,MIN($C72/$C$66,$C72-SUM($D72:L72))) -> 7.02 | N72: =IF(N$6=$B72,$C72/$C$66/2,MIN($C72/$C$66,$C72-SUM($D72:M72))) -> 0 | P72: =SUM(E72:N72) -> 70.2 | Q72: =P72<=C72 -> TRUE
B73: 2022 | C73: =INDEX($D$64:$N$64,MATCH($B73,$D$6:$N$6,0)) -> 110.7 | I73: =IF(I$6=$B73,$C73/$C$66/2,MIN($C73/$C$66,$C73-SUM($D73:H73))) -> 11.07 | J73: =IF(J$6=$B73,$C73/$C$66/2,MIN($C73/$C$66,$C73-SUM($D73:I73))) -> 22.14 | K73: =IF(K$6=$B73,$C73/$C$66/2,MIN($C73/$C$66,$C73-SUM($D73:J73))) -> 22.14 | L73: =IF(L$6=$B73,$C73/$C$66/2,MIN($C73/$C$66,$C73-SUM($D73:K73))) -> 22.14 | M73: =IF(M$6=$B73,$C73/$C$66/2,MIN($C73/$C$66,$C73-SUM($D73:L73))) -> 22.14 | N73: =IF(N$6=$B73,$C73/$C$66/2,MIN($C73/$C$66,$C73-SUM($D73:M73))) -> 11.07 | P73: =SUM(E73:N73) -> 110.7 | Q73: =P73<=C73 -> TRUE
B74: 2023 | C74: =INDEX($D$64:$N$64,MATCH($B74,$D$6:$N$6,0)) -> 51 | J74: =IF(J$6=$B74,$C74/$C$66/2,MIN($C74/$C$66,$C74-SUM($D74:I74))) -> 5.1 | K74: =IF(K$6=$B74,$C74/$C$66/2,MIN($C74/$C$66,$C74-SUM($D74:J74))) -> 10.2 | L74: =IF(L$6=$B74,$C74/$C$66/2,MIN($C74/$C$66,$C74-SUM($D74:K74))) -> 10.2 | M74: =IF(M$6=$B74,$C74/$C$66/2,MIN($C74/$C$66,$C74-SUM($D74:L74))) -> 10.2 | N74: =IF(N$6=$B74,$C74/$C$66/2,MIN($C74/$C$66,$C74-SUM($D74:M74))) -> 10.2 | P74: =SUM(E74:N74) -> 45.9 | Q74: =P74<=C74 -> TRUE
B75: 2024 | C75: =INDEX($D$64:$N$64,MATCH($B75,$D$6:$N$6,0)) -> 50.3 | K75: =IF(K$6=$B75,$C75/$C$66/2,MIN($C75/$C$66,$C75-SUM($D75:J75))) -> 5.03 | L75: =IF(L$6=$B75,$C75/$C$66/2,MIN($C75/$C$66,$C75-SUM($D75:K75))) -> 10.06 | M75: =IF(M$6=$B75,$C75/$C$66/2,MIN($C75/$C$66,$C75-SUM($D75:L75))) -> 10.06 | N75: =IF(N$6=$B75,$C75/$C$66/2,MIN($C75/$C$66,$C75-SUM($D75:M75))) -> 10.06 | P75: =SUM(E75:N75) -> 35.21 | Q75: =P75<=C75 -> TRUE
B76: 2025 | C76: =INDEX($D$64:$N$64,MATCH($B76,$D$6:$N$6,0)) -> 50 | L76: =IF(L$6=$B76,$C76/$C$66/2,MIN($C76/$C$66,$C76-SUM($D76:K76))) -> 5 | M76: =IF(M$6=$B76,$C76/$C$66/2,MIN($C76/$C$66,$C76-SUM($D76:L76))) -> 10 | N76: =IF(N$6=$B76,$C76/$C$66/2,MIN($C76/$C$66,$C76-SUM($D76:M76))) -> 10 | P76: =SUM(E76:N76) -> 25 | Q76: =P76<=C76 -> TRUE
B77: 2026 | C77: =INDEX($D$64:$N$64,MATCH($B77,$D$6:$N$6,0)) -> 50 | M77: =IF(M$6=$B77,$C77/$C$66/2,MIN($C77/$C$66,$C77-SUM($D77:L77))) -> 5 | N77: =IF(N$6=$B77,$C77/$C$66/2,MIN($C77/$C$66,$C77-SUM($D77:M77))) -> 10 | P77: =SUM(E77:N77) -> 15 | Q77: =P77<=C77 -> TRUE
B78: 2027 | C78: =INDEX($D$64:$N$64,MATCH($B78,$D$6:$N$6,0)) -> 50.5 | N78: =IF(N$6=$B78,$C78/$C$66/2,MIN($C78/$C$66,$C78-SUM($D78:M78))) -> 5.05 | P78: =SUM(E78:N78) -> 5.05 | Q78: =P78<=C78 -> TRUE
B80: Total | E80: =SUM(E69:E78) -> 5.5 | F80: =SUM(F69:F78) -> 17.5 | G80: =SUM(G69:G78) -> 29.75 | H80: =SUM(H69:H78) -> 42.52 | I80: =SUM(I69:I78) -> 60.61 | J80: =SUM(J69:J78) -> 71.28 | K80: =SUM(K69:K78) -> 69.41 | L80: =SUM(L69:L78) -> 67.19 | ... N80: =SUM(N69:N78) -> 56.38
B83: Summary
B85: Total Depreciation
B86: Exisiting Buildings | E86: =E18 -> 101.72 | F86: =F18 -> 101.72 | G86: =G18 -> 101.72 | H86: =H18 -> 101.72 | I86: =I18 -> 101.72 | J86: =J18 -> 101.72 | K86: =K18 -> 101.72 | L86: =L18 -> 101.72 | ... N86: =N18 -> 101.72
B87: New Buildings | E87: =E40 -> 18.966071 | F87: =F40 -> 52.901792 | G87: =G40 -> 80.093187 | H87: =H40 -> 102.68858 | I87: =I40 -> 122.23908 | J87: =J40 -> 139.87048 | K87: =K40 -> 156.4061 | L87: =L40 -> 183.2499 | ... N87: =N40 -> 211.76816
B88: IT Department | E88: =E80 -> 5.5 | F88: =F80 -> 17.5 | G88: =G80 -> 29.75 | H88: =H80 -> 42.52 | I88: =I80 -> 60.61 | J88: =J80 -> 71.28 | K88: =K80 -> 69.41 | L88: =L80 -> 67.19 | ... N88: =N80 -> 56.38
B89: Total | E89: =SUM(E86:E88) -> 126.18607 | F89: =SUM(F86:F88) -> 172.12179 | G89: =SUM(G86:G88) -> 211.56319 | H89: =SUM(H86:H88) -> 246.92858 | I89: =SUM(I86:I88) -> 284.56908 | J89: =SUM(J86:J88) -> 312.87048 | K89: =SUM(K86:K88) -> 327.5361 | L89: =SUM(L86:L88) -> 352.1599 | ... N89: =SUM(N86:N88) -> 369.86816
B91: Net PP&E
B92: Opening PP&E Balance | E92: =D97 -> 2543 | F92: =E97 -> 2604.5764 | G92: =F97 -> 2640.1743 | H92: =G97 -> 2639.5348 | I92: =H97 -> 2627.7367 | J92: =I97 -> 2631.1678 | K92: =J97 -> 2559.8951 | L92: =K97 -> 2487.5515 | ... N92: =M97 -> 2329.2965
B93: Building Capital Spending | E93: =E21 -> 132.7625 | F93: =F21 -> 142.71969 | G93: =G21 -> 153.42366 | H93: =H21 -> 164.93044 | I93: =I21 -> 177.30022 | J93: =J21 -> 190.59774 | K93: =K21 -> 204.89257 | L93: =L21 -> 220.25951 | ... N93: =N21 -> 254.5374
B94: IT Department Capital Spending | E94: =E64 -> 55 | F94: =F64 -> 65 | G94: =G64 -> 57.5 | H94: =H64 -> 70.2 | I94: =I64 -> 110.7 | J94: =J64 -> 51 | K94: =K64 -> 50.3 | L94: =L64 -> 50 | ... N94: =N64 -> 50.5
B95: Sale of Assets | E95: =E15 -> 0 | F95: =F15 -> 0 | G95: =G15 -> 0 | H95: =H15 -> 0 | I95: =I15 -> 0 | J95: =J15 -> 0 | K95: =K15 -> 0 | L95: =L15 -> 0 | ... N95: =N15 -> 0
B96: Total Depreciation Expense | E96: =-E89 -> -126.18607 | F96: =-F89 -> -172.12179 | G96: =-G89 -> -211.56319 | H96: =-H89 -> -246.92858 | I96: =-I89 -> -284.56908 | J96: =-J89 -> -312.87048 | K96: =-K89 -> -327.5361 | L96: =-L89 -> -352.1599 | ... N96: =-N89 -> -369.86816
B97: Closing PP&E Balance | D97: =D16 -> 2543 | E97: =SUM(E92:E96) -> 2604.5764 | F97: =SUM(F92:F96) -> 2640.1743 | G97: =SUM(G92:G96) -> 2639.5348 | H97: =SUM(H92:H96) -> 2627.7367 | I97: =SUM(I92:I96) -> 2631.1678 | J97: =SUM(J92:J96) -> 2559.8951 | K97: =SUM(K92:K96) -> 2487.5515 | L97: =SUM(L92:L96) -> 2405.6511 | ... N97: =SUM(N92:N96) -> 2264.4657
B100: Scenario Analysis
B102: Scenario | D102: 1 | E102: 1 | F102: 2 | G102: 3 | H102: 4 | I102: 5
B104: Building Sale Amount | D104: =INDEX($E104:$I104,MATCH($D$102,$E$102:$I$102,0)) -> 0 | E104: 0 | F104: 0 | G104: 0 | H104: 0 | I104: 500
B105: IT Spending Delay (years) | D105: =INDEX($E105:$I105,MATCH($D$102,$E$102:$I$102,0)) -> 0 | E105: 0 | F105: 1 | G105: 3 | H105: 5 | I105: 0
B106: IT Spending Start Year | D106: =INDEX($E106:$I106,MATCH($D$102,$E$102:$I$102,0)) -> 2018 | E106: =$E$6+E105 -> 2018 | F106: =$E$6+F105 -> 2019 | G106: =$E$6+G105 -> 2021 | H106: =$E$6+H105 -> 2023 | I106: =$E$6+I105 -> 2018
B108: Depreciation Expense | E108: =E89 -> 126.18607 | F108: =F89 -> 172.12179 | G108: =G89 -> 211.56319 | H108: =H89 -> 246.92858 | I108: =I89 -> 284.56908 | J108: =J89 -> 312.87048 | K108: =K89 -> 327.5361 | L108: =L89 -> 352.1599 | ... N108: =N89 -> 369.86816
B109: Base Case | D109: 1 | E109: 126.18607 | F109: 172.12179 | G109: 211.56319 | H109: 246.92858 | I109: 284.56908 | J109: 312.87048 | K109: 327.5361 | L109: 352.1599 | M109: 363.13364 | N109: 369.86816
B110: 1 Year IT Delay | D110: 2 | E110: 125.68607 | F110: 170.12179 | G110: 209.31319 | H110: 244.15858 | I110: 276.47908 | J110: 307.20048 | K110: 329.4061 | L110: 354.3799 | M110: 365.90364 | N110: 377.90816
B111: 3 Year IT Delay | D111: 3 | E111: 125.68607 | F111: 169.62179 | G111: 206.81319 | H111: 239.90858 | I111: 271.45908 | J111: 296.34048 | K111: 315.6461 | L111: 350.5799 | M111: 369.99364 | N111: 382.89816
B112: 5 Year IT Delay | D112: 4 | E112: 125.68607 | F112: 169.62179 | G112: 206.81319 | H112: 239.40858 | I112: 268.95908 | J112: 292.09048 | K112: 310.6261 | L112: 339.7199 | M112: 356.23364 | N112: 379.09816
B113: Asset Sale | D113: 5 | E113: 126.18607 | F113: 172.12179 | G113: 211.56319 | H113: 226.92858 | I113: 264.56908 | J113: 292.87048 | K113: 307.5361 | L113: 332.1599 | M113: 343.13364 | N113: 349.86816
B115: Ending Net PP&E | E115: =E97 -> 2604.5764 | F115: =F97 -> 2640.1743 | G115: =G97 -> 2639.5348 | H115: =H97 -> 2627.7367 | I115: =I97 -> 2631.1678 | J115: =J97 -> 2559.8951 | K115: =K97 -> 2487.5515 | L115: =L97 -> 2405.6511 | ... N115: =N97 -> 2264.4657
B116: Base Case | D116: 1 | E116: 2604.5764 | F116: 2640.1743 | G116: 2639.5348 | H116: 2627.7367 | I116: 2631.1678 | J116: 2559.8951 | K116: 2487.5515 | L116: 2405.6511 | M116: 2329.2965 | N116: 2264.4657
B117: 1 Year IT Delay | D117: 2 | E117: 2600.0764 | F117: 2627.6743 | G117: 2636.7848 | H117: 2615.0567 | I117: 2586.0778 | J117: 2580.1751 | K117: 2506.6615 | L117: 2422.8411 | M117: 2343.7165 | N117: 2270.3457
B118: 3 Year IT Delay | D118: 3 | E118: 2600.0764 | F118: 2623.1743 | G118: 2619.7848 | H118: 2599.8067 | I118: 2570.6478 | J118: 2522.4051 | K118: 2481.8515 | L118: 2462.2311 | M118: 2380.0165 | N118: 2301.9557
B119: 5 Year IT Delay | D119: 4 | E119: 2600.0764 | F119: 2623.1743 | G119: 2619.7848 | H119: 2595.3067 | I119: 2553.6478 | J119: 2507.1551 | K119: 2466.4215 | L119: 2404.4611 | M119: 2355.2065 | N119: 2341.3457
B120: Asset Sale | D120: 5 | E120: 2604.5764 | F120: 2640.1743 | G120: 2139.5348 | H120: 2147.7367 | I120: 2171.1678 | J120: 2119.8951 | K120: 2067.5515 | L120: 2005.6511 | M120: 1949.2965 | N120: 1904.4657
B123: Answers
E125: =E$6 -> 2018 | F125: =F$6 -> 2019 | G125: =G$6 -> 2020 | H125: =H$6 -> 2021 | I125: =I$6 -> 2022 | J125: =J$6 -> 2023 | K125: =K$6 -> 2024 | L125: =L$6 -> 2025 | ... N125: =N$6 -> 2027
B126: (1)
B127: Depreciation Expense | E127: =E109 -> 126.18607 | F127: =F109 -> 172.12179 | G127: =G109 -> 211.56319 | H127: =H109 -> 246.92858 | I127: =I109 -> 284.56908 | J127: =J109 -> 312.87048 | K127: =K109 -> 327.5361 | L127: =L109 -> 352.1599 | ... N127: =N109 -> 369.86816
B129: (2)
B130: Depreciation Expense - 1 yr Delay | E130: =E110 -> 125.68607 | F130: =F110 -> 170.12179 | G130: =G110 -> 209.31319 | H130: =H110 -> 244.15858 | I130: =I110 -> 276.47908 | J130: =J110 -> 307.20048 | K130: =K110 -> 329.4061 | L130: =L110 -> 354.3799 | ... N130: =N110 -> 377.90816
B131: Depreciation Expense - 3 yr Delay | E131: =E111 -> 125.68607 | F131: =F111 -> 169.62179 | G131: =G111 -> 206.81319 | H131: =H111 -> 239.90858 | I131: =I111 -> 271.45908 | J131: =J111 -> 296.34048 | K131: =K111 -> 315.6461 | L131: =L111 -> 350.5799 | ... N131: =N111 -> 382.89816
B132: Depreciation Expense - 5 yr Delay | E132: =E112 -> 125.68607 | F132: =F112 -> 169.62179 | G132: =G112 -> 206.81319 | H132: =H112 -> 239.40858 | I132: =I112 -> 268.95908 | J132: =J112 -> 292.09048 | K132: =K112 -> 310.6261 | L132: =L112 -> 339.7199 | ... N132: =N112 -> 379.09816
B134: (3)
B135: Depreciation Expense - with Asset Sale | E135: =E113 -> 126.18607 | F135: =F113 -> 172.12179 | G135: =G113 -> 211.56319 | H135: =H113 -> 226.92858 | I135: =I113 -> 264.56908 | J135: =J113 -> 292.87048 | K135: =K113 -> 307.5361 | L135: =L113 -> 332.1599 | ... N135: =N113 -> 349.86816
B137: (4)
...
