Workbook
Name company: CaseData!$G$3
Name ListAssetClasses: CaseData!$C$15:$C$17
Name ListDepMethods: CaseData!$C$22:$C$25
Name periods: CaseData!$G$11
Name start_date: CaseData!$G$6
Name topic: "CFM Topic: " & CaseData!$G$4

Sheet Answers
A1: {=company} -> Big Dog Construction
A2: {=topic} -> CFM Topic: CAPEX and Depreciation
A3: TAX SCHEDULE | F3: Constant | G3: Unit | H3: Total | J3: {=EOMONTH( start_date, _xlfn.SEQUENCE( 1, periods, 0, 12 ) )} -> 43861 | K3: 44227 | L3: 44592 | M3: 44957 | N3: 45322 | O3: 45688 | P3: 46053 | Q3: 46418 | R3: 46783 | S3: 47149 | T3: 47514 | U3: 47879 | V3: 48244 | W3: 48610 | X3: 48975 | Y3: 49340 | Z3: 49705 | AA3: 50071 | AB3: 50436 | AC3: 50801 | AD3: 51166 | AE3: 51532 | AF3: 51897 | AG3: 52262 | AH3: 52627
E5: Depreciation method | F5: 4
B7: Long term assets
E9: Long term assets initial balance | G9: USD m | J9: {=_xlfn.DROP( _xlfn.HSTACK( 0,_xlfn.ANCHORARRAY( $J$12) ),, -1)} -> 0 | K9: 1995882.4 | L9: 2141691.2 | M9: 3229720.6 | N9: 3129625 | O9: 4102713.2 | P9: 4997205.9 | Q9: 5501860.3 | R9: 4755051.5 | S9: 3992404.4 | T9: 3802742.6 | U9: 3850441.2 | V9: 3995213.2 | W9: 3606676.5 | X9: 4491698.5 | Y9: 4753220.6 | Z9: 5020352.9 | AA9: 5090147.1 | AB9: 5120411.8 | AC9: 4546411.8 | AD9: 4087808.8 | AE9: 4378889.7 | AF9: 4460823.5 | AG9: 4094132.4 | AH9: 4438933.8
E10: Long term assets CAPEX | G10: USD m | H10: {=_xlfn.BYROW(_xlfn.ANCHORARRAY( $J$10), _xleta.SUM )} -> 24507000 | J10: {=IF( _xlfn.DROP( TRANSPOSE( INDEX(_xlfn.ANCHORARRAY( Calculations!$E$7),, 2 ) ),, 1 ) = "", 0, _xlfn.DROP( TRANSPOSE( INDEX(_xlfn.ANCHORARRAY( Calculations!$E$7),, 2 ) ),, 1 ) )} -> 2262000 | K10: 448000 | L10: 1553000 | M10: 378000 | N10: 1606000 | O10: 1679000 | P10: 1395000 | Q10: 85000 | R10: 0 | S10: 571000 | T10: 833000 | U10: 964000 | V10: 390000 | W10: 1784000 | X10: 1199000 | Y10: 1239000 | Z10: 1044000 | AA10: 1012000 | AB10: 331000 | AC10: 385000 | AD10: 1165000 | AE10: 966000 | AF10: 475000 | AG10: 1241000 | AH10: 1502000
E11: Depreciation | G11: USD m | H11: {=_xlfn.BYROW(_xlfn.ANCHORARRAY( $J$11), _xleta.SUM )} -> -19538978 | J11: {=_xlfn.LET( _xlpm.declining,_xlfn.ANCHORARRAY( Calculations!$J$63), _xlpm.straight,_xlfn.ANCHORARRAY( Calculations!$J$93), _xlpm.adjusted_MACS,_xlfn.ANCHORARRAY( Calculations!$J$124), _xlpm.sum_of_digits,_xlfn.ANCHORARRAY( Calculations!$J$154), _xlpm.selector, Answers!$F$5, CHOOSE( _xlpm.selector, _xlpm.declining, _xlpm.straight, _xlpm.adjusted_MACS, _xlpm.sum_of_digits ) * -1 )} -> -266117.65 | K11: -302191.18 | L11: -464970.59 | M11: -478095.59 | N11: -632911.76 | O11: -784507.35 | P11: -890345.59 | Q11: -831808.82 | R11: -762647.06 | S11: -760661.76 | T11: -785301.47 | U11: -819227.94 | V11: -778536.76 | W11: -898977.94 | X11: -937477.94 | Y11: -971867.65 | Z11: -974205.88 | AA11: -981735.29 | AB11: -905000 | AC11: -843602.94 | AD11: -873919.12 | AE11: -884066.18 | AF11: -841691.18 | AG11: -896198.53 | AH11: -972911.76
E12: Long term assets final balance | G12: USD m | J12: {=_xlfn.LET( _xlpm.initial_balance, 0, _xlpm.movements,_xlfn.ANCHORARRAY( $J$10) +_xlfn.ANCHORARRAY( $J$11), _xlfn.SCAN( _xlpm.initial_balance, _xlpm.movements, _xleta.SUM ) )} -> 1995882.4 | K12: 2141691.2 | L12: 3229720.6 | M12: 3129625 | N12: 4102713.2 | O12: 4997205.9 | P12: 5501860.3 | Q12: 4755051.5 | R12: 3992404.4 | S12: 3802742.6 | T12: 3850441.2 | U12: 3995213.2 | V12: 3606676.5 | W12: 4491698.5 | X12: 4753220.6 | Y12: 5020352.9 | Z12: 5090147.1 | AA12: 5120411.8 | AB12: 4546411.8 | AC12: 4087808.8 | AD12: 4378889.7 | AE12: 4460823.5 | AF12: 4094132.4 | AG12: 4438933.8 | AH12: 4968022.1
B14: Medium term assets
E16: Medium term assets initial balance | G16: USD m | J16: {=_xlfn.DROP( _xlfn.HSTACK( 0,_xlfn.ANCHORARRAY( $J$19) ),, -1)} -> 0 | K16: 1491000 | L16: 1551472.2 | M16: 1663444.4 | N16: 1639194.4 | O16: 1584722.2 | P16: 2438666.7 | Q16: 1781777.8 | R16: 2000138.9 | S16: 2372027.8 | T16: 2522277.8 | U16: 3483638.9 | V16: 2718833.3 | W16: 2540166.7 | X16: 2481972.2 | Y16: 2961888.9 | Z16: 2165750 | AA16: 3121944.4 | AB16: 2450000 | AC16: 2089333.3 | AD16: 2479777.8 | AE16: 2685583.3 | AF16: 2873666.7 | AG16: 3108194.4 | AH16: 2790944.4
E17: Medium term assets CAPEX | G17: USD m | H17: {=_xlfn.BYROW(_xlfn.ANCHORARRAY( $J$17), _xleta.SUM )} -> 27830000 | J17: {=IF( _xlfn.DROP( TRANSPOSE( INDEX(_xlfn.ANCHORARRAY( Calculations!$E$7),, 3 ) ),, 1 ) = "", 0, _xlfn.DROP( TRANSPOSE( INDEX(_xlfn.ANCHORARRAY( Calculations!$E$7),, 3 ) ),, 1 ) )} -> 1917000 | K17: 557000 | L17: 694000 | M17: 604000 | N17: 603000 | O17: 1787000 | P17: 135000 | Q17: 1074000 | R17: 1315000 | S17: 1164000 | T17: 2276000 | U17: 387000 | V17: 939000 | W17: 1038000 | X17: 1729000 | Y17: 228000 | Z17: 2222000 | AA17: 407000 | AB17: 594000 | AC17: 1460000 | AD17: 1332000 | AE17: 1368000 | AF17: 1485000 | AG17: 875000 | AH17: 1640000
E18: Depreciation | G18: USD m | H18: {=_xlfn.BYROW(_xlfn.ANCHORARRAY( $J$18), _xleta.SUM )} -> -24685111 | J18: {=_xlfn.LET( _xlpm.declining,_xlfn.ANCHORARRAY( Calculations!$J$186), _xlpm.straight,_xlfn.ANCHORARRAY( Calculations!$J$216), _xlpm.adjusted_MACS,_xlfn.ANCHORARRAY( Calculations!$J$247), _xlpm.sum_of_digits,_xlfn.ANCHORARRAY( Calculations!$J$277), _xlpm.selector, Answers!$F$5, CHOOSE( _xlpm.selector, _xlpm.declining, _xlpm.straight, _xlpm.adjusted_MACS, _xlpm.sum_of_digits ) * -1 )} -> -426000 | K18: -496527.78 | L18: -582027.78 | M18: -628250 | N18: -657472.22 | O18: -933055.56 | P18: -791888.89 | Q18: -855638.89 | R18: -943111.11 | S18: -1013750 | T18: -1314638.9 | U18: -1151805.6 | V18: -1117666.7 | W18: -1096194.4 | X18: -1249083.3 | Y18: -1024138.9 | Z18: -1265805.6 | AA18: -1078944.4 | AB18: -954666.67 | AC18: -1069555.6 | AD18: -1126194.4 | AE18: -1179916.7 | AF18: -1250472.2 | AG18: -1192250 | AH18: -1286055.6
E19: Medium term assets final balance | G19: USD m | J19: {=_xlfn.LET( _xlpm.initial_balance, 0, _xlpm.movements,_xlfn.ANCHORARRAY( $J$17) +_xlfn.ANCHORARRAY( $J$18), _xlfn.SCAN( _xlpm.initial_balance, _xlpm.movements, _xleta.SUM ) )} -> 1491000 | K19: 1551472.2 | L19: 1663444.4 | M19: 1639194.4 | N19: 1584722.2 | O19: 2438666.7 | P19: 1781777.8 | Q19: 2000138.9 | R19: 2372027.8 | S19: 2522277.8 | T19: 3483638.9 | U19: 2718833.3 | V19: 2540166.7 | W19: 2481972.2 | X19: 2961888.9 | Y19: 2165750 | Z19: 3121944.4 | AA19: 2450000 | AB19: 2089333.3 | AC19: 2479777.8 | AD19: 2685583.3 | AE19: 2873666.7 | AF19: 3108194.4 | AG19: 2790944.4 | AH19: 3144888.9
B21: Short term assets
E23: Short term assets initial balance | G23: USD m | J23: {=_xlfn.DROP( _xlfn.HSTACK( 0,_xlfn.ANCHORARRAY( $J$26) ),, -1)} -> 0 | K23: 1210666.7 | L23: 862400 | M23: 860133.33 | N23: 1537733.3 | O23: 1380200 | P23: 1493133.3 | Q23: 1288866.7 | R23: 742666.67 | S23: 810533.33 | T23: 1430800 | U23: 1448733.3 | V23: 1724200 | W23: 1364466.7 | X23: 1257933.3 | Y23: 1392200 | Z23: 935400 | AA23: 1532933.3 | AB23: 1251666.7 | AC23: 1622200 | AD23: 1668200 | AE23: 1458000 | AF23: 1631800 | AG23: 1627933.3 | AH23: 1229066.7
E24: Short term assets CAPEX | G24: USD m | H24: {=_xlfn.BYROW(_xlfn.ANCHORARRAY( J24), _xleta.SUM )} -> 25342000 | J24: {=IF( _xlfn.DROP( TRANSPOSE( INDEX(_xlfn.ANCHORARRAY( Calculations!$E$7),, 4 ) ),, 1 ) = "", 0, _xlfn.DROP( TRANSPOSE( INDEX(_xlfn.ANCHORARRAY( Calculations!$E$7),, 4 ) ),, 1 ) )} -> 1816000 | K24: 204000 | L24: 623000 | M24: 1690000 | N24: 849000 | O24: 1161000 | P24: 813000 | Q24: 193000 | R24: 740000 | S24: 1563000 | T24: 994000 | U24: 1447000 | V24: 724000 | W24: 919000 | X24: 1175000 | Y24: 350000 | Z24: 1645000 | AA24: 668000 | AB24: 1504000 | AC24: 1235000 | AD24: 928000 | AE24: 1370000 | AF24: 1218000 | AG24: 609000 | AH24: 904000
E25: Depreciation | G25: USD m | H25: {=_xlfn.BYROW(_xlfn.ANCHORARRAY( J25), _xleta.SUM )} -> -24160800 | J25: {=_xlfn.LET( _xlpm.declining,_xlfn.ANCHORARRAY( Calculations!$J$309), _xlpm.straight,_xlfn.ANCHORARRAY( Calculations!$J$339), _xlpm.adjusted_MACS,_xlfn.ANCHORARRAY( Calculations!$J$370), _xlpm.sum_of_digits,_xlfn.ANCHORARRAY( Calculations!$J$400), _xlpm.selector, Answers!$F$5, CHOOSE( _xlpm.selector, _xlpm.declining, _xlpm.straight, _xlpm.adjusted_MACS, _xlpm.sum_of_digits ) * -1 )} -> -605333.33 | K25: -552266.67 | L25: -625266.67 | M25: -1012400 | N25: -1006533.3 | O25: -1048066.7 | P25: -1017266.7 | Q25: -739200 | R25: -672133.33 | S25: -942733.33 | T25: -976066.67 | U25: -1171533.3 | V25: -1083733.3 | W25: -1025533.3 | X25: -1040733.3 | Y25: -806800 | Z25: -1047466.7 | AA25: -949266.67 | AB25: -1133466.7 | AC25: -1189000 | AD25: -1138200 | AE25: -1196200 | AF25: -1221866.7 | AG25: -1007866.7 | AH25: -951866.67
E26: Short term assets final balance | G26: USD m | J26: {=_xlfn.LET( _xlpm.initial_balance, 0, _xlpm.movements,_xlfn.ANCHORARRAY( $J$24) +_xlfn.ANCHORARRAY( $J$25), _xlfn.SCAN( _xlpm.initial_balance, _xlpm.movements, _xleta.SUM ) )} -> 1210666.7 | K26: 862400 | L26: 860133.33 | M26: 1537733.3 | N26: 1380200 | O26: 1493133.3 | P26: 1288866.7 | Q26: 742666.67 | R26: 810533.33 | S26: 1430800 | T26: 1448733.3 | U26: 1724200 | V26: 1364466.7 | W26: 1257933.3 | X26: 1392200 | Y26: 935400 | Z26: 1532933.3 | AA26: 1251666.7 | AB26: 1622200 | AC26: 1668200 | AD26: 1458000 | AE26: 1631800 | AF26: 1627933.3 | AG26: 1229066.7 | AH26: 1181200
B28: Assets schedule
E30: Assets opening balance | G30: USD m | J30: {=_xlfn.ANCHORARRAY( J9) +_xlfn.ANCHORARRAY( J16) +_xlfn.ANCHORARRAY( J23)} -> 0 | K30: 4697549 | L30: 4555563.4 | M30: 5753298.4 | N30: 6306552.8 | O30: 7067635.5 | P30: 8929005.9 | Q30: 8572504.7 | R30: 7497857 | S30: 7174965.5 | T30: 7755820.4 | U30: 8782813.4 | V30: 8438246.6 | W30: 7511309.8 | X30: 8231604.1 | Y30: 9107309.5 | Z30: 8121502.9 | AA30: 9745024.8 | AB30: 8822078.4 | AC30: 8257945.1 | AD30: 8235786.6 | AE30: 8522473 | AF30: 8966290.2 | AG30: 8830260.1 | AH30: 8458944.9
E31: CAPEX | G31: USD m | H31: {=_xlfn.BYROW(_xlfn.ANCHORARRAY( J31), _xleta.SUM )} -> 77679000 | J31: {=_xlfn.ANCHORARRAY( J10) +_xlfn.ANCHORARRAY( J17) +_xlfn.ANCHORARRAY( J24)} -> 5995000 | K31: 1209000 | L31: 2870000 | M31: 2672000 | N31: 3058000 | O31: 4627000 | P31: 2343000 | Q31: 1352000 | R31: 2055000 | S31: 3298000 | T31: 4103000 | U31: 2798000 | V31: 2053000 | W31: 3741000 | X31: 4103000 | Y31: 1817000 | Z31: 4911000 | AA31: 2087000 | AB31: 2429000 | AC31: 3080000 | AD31: 3425000 | AE31: 3704000 | AF31: 3178000 | AG31: 2725000 | AH31: 4046000
E32: Depreciation | G32: USD m | H32: {=_xlfn.BYROW(_xlfn.ANCHORARRAY( J32), _xleta.SUM )} -> -68384889 | J32: {=_xlfn.ANCHORARRAY( J11) +_xlfn.ANCHORARRAY( J18) +_xlfn.ANCHORARRAY( J25)} -> -1297451 | K32: -1350985.6 | L32: -1672265 | M32: -2118745.6 | N32: -2296917.3 | O32: -2765629.6 | P32: -2699501.1 | Q32: -2426647.7 | R32: -2377891.5 | S32: -2717145.1 | T32: -3076007 | U32: -3142566.8 | V32: -2979936.8 | W32: -3020705.7 | X32: -3227294.6 | Y32: -2802806.5 | Z32: -3287478.1 | AA32: -3009946.4 | AB32: -2993133.3 | AC32: -3102158.5 | AD32: -3138313.6 | AE32: -3260182.8 | AF32: -3314030.1 | AG32: -3096315.2 | AH32: -3210834
E33: Assets closing balance | G33: USD m | H33: {=_xlfn.BYCOL(H30:H32, _xleta.SUM )} -> 9294110.9 | J33: {=_xlfn.ANCHORARRAY( J12) +_xlfn.ANCHORARRAY( J19) +_xlfn.ANCHORARRAY( J26)} -> 4697549 | K33: 4555563.4 | L33: 5753298.4 | M33: 6306552.8 | N33: 7067635.5 | O33: 8929005.9 | P33: 8572504.7 | Q33: 7497857 | R33: 7174965.5 | S33: 7755820.4 | T33: 8782813.4 | U33: 8438246.6 | V33: 7511309.8 | W33: 8231604.1 | X33: 9107309.5 | Y33: 8121502.9 | Z33: 9745024.8 | AA33: 8822078.4 | AB33: 8257945.1 | AC33: 8235786.6 | AD33: 8522473 | AE33: 8966290.2 | AF33: 8830260.1 | AG33: 8458944.9 | AH33: 9294110.9
B35: Tax deduction
E37: Depreciation | G37: USD m | J37: {=_xlfn.ANCHORARRAY( J32) * -1} -> 1297451 | K37: 1350985.6 | L37: 1672265 | M37: 2118745.6 | N37: 2296917.3 | O37: 2765629.6 | P37: 2699501.1 | Q37: 2426647.7 | R37: 2377891.5 | S37: 2717145.1 | T37: 3076007 | U37: 3142566.8 | V37: 2979936.8 | W37: 3020705.7 | X37: 3227294.6 | Y37: 2802806.5 | Z37: 3287478.1 | AA37: 3009946.4 | AB37: 2993133.3 | AC37: 3102158.5 | AD37: 3138313.6 | AE37: 3260182.8 | AF37: 3314030.1 | AG37: 3096315.2 | AH37: 3210834
E38: Tax deduction | G38: USD m | J38: {=_xlfn.LET( _xlpm.tax_deduction, CaseData!$G$7, _xlpm.depreciation,_xlfn.ANCHORARRAY( Answers!$J$37), _xlpm.tax_deduction * _xlpm.depreciation )} -> 389235.29 | K38: 405295.69 | L38: 501679.51 | M38: 635623.68 | N38: 689075.2 | O38: 829688.87 | P38: 809850.34 | Q38: 727994.31 | R38: 713367.45 | S38: 815143.53 | T38: 922802.11 | U38: 942770.05 | V38: 893981.03 | W38: 906211.72 | X38: 968188.38 | Y38: 840841.96 | Z38: 986243.43 | AA38: 902983.92 | AB38: 897940 | AC38: 930647.55 | AD38: 941494.07 | AE38: 978054.85 | AF38: 994209.02 | AG38: 928894.56 | AH38: 963250.2
J41: NPV | K41: XNPV
J42: =_xlfn.LET( _xlpm.rate, CaseData!$G$8, _xlpm.deduction,_xlfn.ANCHORARRAY( Answers!$J$38), NPV( _xlpm.rate, _xlpm.deduction ) ) -> 7119925.4 | K42: =_xlfn.LET( _xlpm.rate, CaseData!$G$8, _xlpm.deduction,_xlfn.ANCHORARRAY( Answers!$J$38), XNPV( _xlpm.rate, _xlpm.deduction,_xlfn.ANCHORARRAY( J3) ) ) -> 7755756
H43: {=ListDepMethods} -> Declining Balance | I43: 1 | J43: 6827908.5 | K43: 7437668
H44: Straight Line | I44: 2 | J44: 6276501.2 | K44: 6836712.6
H45: Adjusted MACRS | I45: 3 | J45: 6995081.2 | K45: 7619765.4
H46: Sum of Years Digits | I46: 4 | J46: 7119925.4 | K46: 7755756
B48: Answers
C50: c | D50: i | E50: 905400
D51: ii | E51: 650133.31
D52: iii | E52: 24457487
D53: iv | E53: 4087808.8

Sheet Calculations
A1: {=company} -> Big Dog Construction
A2: {=topic} -> CFM Topic: CAPEX and Depreciation
A3: CALCULATIONS SCHEDULE | F3: Constant | G3: Unit | H3: Total | J3: {=EOMONTH( start_date, _xlfn.SEQUENCE( 1, periods, 0, 12 ) )} -> 43861 | K3: 44227 | L3: 44592 | M3: 44957 | N3: 45322 | O3: 45688 | P3: 46053 | Q3: 46418 | R3: 46783 | S3: 47149 | T3: 47514 | U3: 47879 | V3: 48244 | W3: 48610 | X3: 48975 | Y3: 49340 | Z3: 49705 | AA3: 50071 | AB3: 50436 | AC3: 50801 | AD3: 51166 | AE3: 51532 | AF3: 51897 | AG3: 52262 | AH3: 52627
B5: Capital expenditures
E7: {=_xlfn.PIVOTBY( YEAR(CaseData!$D$134:$D$433), CaseData!$F$134:$F$433,CaseData!$E$134:$E$433, _xleta.SUM,,0,,0 )} | F7: Long Term | G7: Medium Term | H7: Short Term
E8: 2020 | F8: 2262000 | G8: 1917000 | H8: 1816000
E9: 2021 | F9: 448000 | G9: 557000 | H9: 204000
E10: 2022 | F10: 1553000 | G10: 694000 | H10: 623000
E11: 2023 | F11: 378000 | G11: 604000 | H11: 1690000
E12: 2024 | F12: 1606000 | G12: 603000 | H12: 849000
E13: 2025 | F13: 1679000 | G13: 1787000 | H13: 1161000
E14: 2026 | F14: 1395000 | G14: 135000 | H14: 813000
E15: 2027 | F15: 85000 | G15: 1074000 | H15: 193000
E16: 2028 | G16: 1315000 | H16: 740000
E17: 2029 | F17: 571000 | G17: 1164000 | H17: 1563000
E18: 2030 | F18: 833000 | G18: 2276000 | H18: 994000
E19: 2031 | F19: 964000 | G19: 387000 | H19: 1447000
E20: 2032 | F20: 390000 | G20: 939000 | H20: 724000
E21: 2033 | F21: 1784000 | G21: 1038000 | H21: 919000
E22: 2034 | F22: 1199000 | G22: 1729000 | H22: 1175000
E23: 2035 | F23: 1239000 | G23: 228000 | H23: 350000
E24: 2036 | F24: 1044000 | G24: 2222000 | H24: 1645000
E25: 2037 | F25: 1012000 | G25: 407000 | H25: 668000
E26: 2038 | F26: 331000 | G26: 594000 | H26: 1504000
E27: 2039 | F27: 385000 | G27: 1460000 | H27: 1235000
E28: 2040 | F28: 1165000 | G28: 1332000 | H28: 928000
... E32: 2044 | F32: 1502000 | G32: 1640000 | H32: 904000
B34: Long Term Assets
C36: Declining balance
F37: Date | G37: Cost | J37: {=_xlfn.ANCHORARRAY($J$3)} -> 43861 | K37: 44227 | L37: 44592 | M37: 44957 | N37: 45322 | O37: 45688 | P37: 46053 | Q37: 46418 | R37: 46783 | S37: 47149 | T37: 47514 | U37: 47879 | V37: 48244 | W37: 48610 | X37: 48975 | Y37: 49340 | Z37: 49705 | AA37: 50071 | AB37: 50436 | AC37: 50801 | AD37: 51166 | AE37: 51532 | AF37: 51897 | AG37: 52262 | AH37: 52627
F38: {=_xlfn.LET( _xlpm.assets,_xlfn.ANCHORARRAY(E7), _xlpm.long_term, INDEX( _xlpm.assets,, 2 ), _xlpm.acq_date, INDEX( _xlpm.assets,, 1 ), _xlfn.DROP( _xlfn.HSTACK( _xlpm.acq_date, _xlpm.long_term ), 1 ) )} -> 2020 | G38: 2262000 | H38: {=IFERROR( _xlfn.BYROW(_xlfn.ANCHORARRAY( J38), _xleta.SUM ), 0 )} -> 2181704 | J38: {=_xlfn.LET( _xlpm.acquisition_date, INDEX(_xlfn.ANCHORARRAY( F38),, 1 ), _xlpm.acquisition_cost, INDEX(_xlfn.ANCHORARRAY( F38),, 2 ), _xlpm.current_date,_xlfn.ANCHORARRAY( J3), _xlpm.period, YEAR( _xlpm.current_date ) - _xlpm.acquisition_date, _xlpm.depreciation_rate, CaseData!$I$32, _xlpm.book_value, _xlpm.acquisition_cost * ( 1 - _xlpm.depreciation_rate ) ^ _xlpm.period, _xlpm.depreciation, _xlpm.depreciation_rate * _xlpm.book_value, IFERROR( IF( _xlpm.period < 0, 0, IF( _xlpm.period >= 0, _xlpm.depreciation, 0 ) ), 0 ) )} -> 282750 | K38: 247406.25 | L38: 216480.47 | M38: 189420.41 | N38: 165742.86 | O38: 145025 | P38: 126896.88 | Q38: 111034.77 | R38: 97155.421 | S38: 85010.993 | T38: 74384.619 | U38: 65086.542 | V38: 56950.724 | W38: 49831.884 | X38: 43602.898 | Y38: 38152.536 | Z38: 33383.469 | AA38: 29210.535 | AB38: 25559.218 | AC38: 22364.316 | AD38: 19568.777 | AE38: 17122.679 | AF38: 14982.345 | AG38: 13109.551 | AH38: 11470.858
F39: 2021 | G39: 448000 | H39: 429825.13 | J39: 0 | K39: 56000 | L39: 49000 | M39: 42875 | N39: 37515.625 | O39: 32826.172 | P39: 28722.9 | Q39: 25132.538 | R39: 21990.971 | S39: 19242.099 | T39: 16836.837 | U39: 14732.232 | V39: 12890.703 | W39: 11279.365 | X39: 9869.4447 | Y39: 8635.7641 | Z39: 7556.2936 | AA39: 6611.7569 | AB39: 5785.2873 | AC39: 5062.1264 | AD39: 4429.3606 | AE39: 3875.6905 | AF39: 3391.2292 | AG39: 2967.3255 | AH39: 2596.4098
F40: 2022 | G40: 1553000 | H40: 1480996 | J40: 0 | K40: 0 | L40: 194125 | M40: 169859.38 | N40: 148626.95 | O40: 130048.58 | P40: 113792.51 | Q40: 99568.447 | R40: 87122.391 | S40: 76232.092 | T40: 66703.081 | U40: 58365.196 | V40: 51069.546 | W40: 44685.853 | X40: 39100.121 | Y40: 34212.606 | Z40: 29936.03 | AA40: 26194.027 | AB40: 22919.773 | AC40: 20054.802 | AD40: 17547.951 | AE40: 15354.457 | AF40: 13435.15 | AG40: 11755.757 | AH40: 10286.287
F41: 2023 | G41: 378000 | H41: 357970.55 | J41: 0 | K41: 0 | L41: 0 | M41: 47250 | N41: 41343.75 | O41: 36175.781 | P41: 31653.809 | Q41: 27697.083 | R41: 24234.947 | S41: 21205.579 | T41: 18554.881 | U41: 16235.521 | V41: 14206.081 | W41: 12430.321 | X41: 10876.531 | Y41: 9516.9645 | Z41: 8327.3439 | AA41: 7286.4259 | AB41: 6375.6227 | AC41: 5578.6699 | AD41: 4881.3361 | AE41: 4271.1691 | AF41: 3737.273 | AG41: 3270.1139 | AH41: 2861.3496
F42: 2024 | G42: 1606000 | H42: 1508744.4 | J42: 0 | K42: 0 | L42: 0 | M42: 0 | N42: 200750 | O42: 175656.25 | P42: 153699.22 | Q42: 134486.82 | R42: 117675.96 | S42: 102966.47 | T42: 90095.66 | U42: 78833.703 | V42: 68979.49 | W42: 60357.054 | X42: 52812.422 | Y42: 46210.869 | Z42: 40434.511 | AA42: 35380.197 | AB42: 30957.672 | AC42: 27087.963 | AD42: 23701.968 | AE42: 20739.222 | AF42: 18146.819 | AG42: 15878.467 | AH42: 13893.658
F43: 2025 | G43: 1679000 | H43: 1562798.5 | J43: 0 | K43: 0 | L43: 0 | M43: 0 | N43: 0 | O43: 209875 | P43: 183640.62 | Q43: 160685.55 | R43: 140599.85 | S43: 123024.87 | T43: 107646.76 | U43: 94190.917 | V43: 82417.053 | W43: 72114.921 | X43: 63100.556 | Y43: 55212.987 | Z43: 48311.363 | AA43: 42272.443 | AB43: 36988.387 | AC43: 32364.839 | AD43: 28319.234 | AE43: 24779.33 | AF43: 21681.914 | AG43: 18971.674 | AH43: 16600.215
F44: 2026 | G44: 1395000 | H44: 1284661.5 | J44: 0 | K44: 0 | L44: 0 | M44: 0 | N44: 0 | O44: 0 | P44: 174375 | Q44: 152578.12 | R44: 133505.86 | S44: 116817.63 | T44: 102215.42 | U44: 89438.496 | V44: 78258.684 | W44: 68476.348 | X44: 59916.805 | Y44: 52427.204 | Z44: 45873.804 | AA44: 40139.578 | AB44: 35122.131 | AC44: 30731.865 | AD44: 26890.381 | AE44: 23529.084 | AF44: 20587.948 | AG44: 18014.455 | AH44: 15762.648
F45: 2027 | G45: 85000 | H45: 77316.415 | J45: 0 | K45: 0 | L45: 0 | M45: 0 | N45: 0 | O45: 0 | P45: 0 | Q45: 10625 | R45: 9296.875 | S45: 8134.7656 | T45: 7117.9199 | U45: 6228.1799 | V45: 5449.6574 | W45: 4768.4503 | X45: 4172.394 | Y45: 3650.8447 | Z45: 3194.4891 | AA45: 2795.178 | AB45: 2445.7807 | AC45: 2140.0582 | AD45: 1872.5509 | AE45: 1638.482 | AF45: 1433.6718 | AG45: 1254.4628 | AH45: 1097.6549
F46: 2028 | H46: 0 | J46: 0 | K46: 0 | L46: 0 | M46: 0 | N46: 0 | O46: 0 | P46: 0 | Q46: 0 | R46: 0 | S46: 0 | T46: 0 | U46: 0 | V46: 0 | W46: 0 | X46: 0 | Y46: 0 | Z46: 0 | AA46: 0 | AB46: 0 | AC46: 0 | AD46: 0 | AE46: 0 | AF46: 0 | AG46: 0 | AH46: 0
F47: 2029 | G47: 571000 | H47: 503583.69 | J47: 0 | K47: 0 | L47: 0 | M47: 0 | N47: 0 | O47: 0 | P47: 0 | Q47: 0 | R47: 0 | S47: 71375 | T47: 62453.125 | U47: 54646.484 | V47: 47815.674 | W47: 41838.715 | X47: 36608.875 | Y47: 32032.766 | Z47: 28028.67 | AA47: 24525.086 | AB47: 21459.451 | AC47: 18777.019 | AD47: 16429.892 | AE47: 14376.155 | AF47: 12579.136 | AG47: 11006.744 | AH47: 9630.901
F48: 2030 | G48: 833000 | H48: 720600.13 | J48: 0 | K48: 0 | L48: 0 | M48: 0 | N48: 0 | O48: 0 | P48: 0 | Q48: 0 | R48: 0 | S48: 0 | T48: 104125 | U48: 91109.375 | V48: 79720.703 | W48: 69755.615 | X48: 61036.163 | Y48: 53406.643 | Z48: 46730.813 | AA48: 40889.461 | AB48: 35778.278 | AC48: 31305.994 | AD48: 27392.744 | AE48: 23968.651 | AF48: 20972.57 | AG48: 18350.999 | AH48: 16057.124
F49: 2031 | G49: 964000 | H49: 815341.49 | J49: 0 | K49: 0 | L49: 0 | M49: 0 | N49: 0 | O49: 0 | P49: 0 | Q49: 0 | R49: 0 | S49: 0 | T49: 0 | U49: 120500 | V49: 105437.5 | W49: 92257.812 | X49: 80725.586 | Y49: 70634.888 | Z49: 61805.527 | AA49: 54079.836 | AB49: 47319.856 | AC49: 41404.874 | AD49: 36229.265 | AE49: 31700.607 | AF49: 27738.031 | AG49: 24270.777 | AH49: 21236.93
F50: 2032 | G50: 390000 | H50: 321266.37 | J50: 0 | K50: 0 | L50: 0 | M50: 0 | N50: 0 | O50: 0 | P50: 0 | Q50: 0 | R50: 0 | S50: 0 | T50: 0 | U50: 0 | V50: 48750 | W50: 42656.25 | X50: 37324.219 | Y50: 32658.691 | Z50: 28576.355 | AA50: 25004.311 | AB50: 21878.772 | AC50: 19143.925 | AD50: 16750.935 | AE50: 14657.068 | AF50: 12824.934 | AG50: 11221.818 | AH50: 9819.0904
F51: 2033 | G51: 1784000 | H51: 1424671.6 | J51: 0 | K51: 0 | L51: 0 | M51: 0 | N51: 0 | O51: 0 | P51: 0 | Q51: 0 | R51: 0 | S51: 0 | T51: 0 | U51: 0 | V51: 0 | W51: 223000 | X51: 195125 | Y51: 170734.38 | Z51: 149392.58 | AA51: 130718.51 | AB51: 114378.69 | AC51: 100081.36 | AD51: 87571.187 | AE51: 76624.788 | AF51: 67046.69 | AG51: 58665.853 | AH51: 51332.622
F52: 2034 | G52: 1199000 | H52: 923000.84 | J52: 0 | K52: 0 | L52: 0 | M52: 0 | N52: 0 | O52: 0 | P52: 0 | Q52: 0 | R52: 0 | S52: 0 | T52: 0 | U52: 0 | V52: 0 | W52: 0 | X52: 149875 | Y52: 131140.62 | Z52: 114748.05 | AA52: 100404.54 | AB52: 87853.973 | AC52: 76872.227 | AD52: 67263.198 | AE52: 58855.299 | AF52: 51498.386 | AG52: 45061.088 | AH52: 39428.452
F53: 2035 | G53: 1239000 | H53: 913049.36 | J53: 0 | K53: 0 | L53: 0 | M53: 0 | N53: 0 | O53: 0 | P53: 0 | Q53: 0 | R53: 0 | S53: 0 | T53: 0 | U53: 0 | V53: 0 | W53: 0 | X53: 0 | Y53: 154875 | Z53: 135515.62 | AA53: 118576.17 | AB53: 103754.15 | AC53: 90784.882 | AD53: 79436.771 | AE53: 69507.175 | AF53: 60818.778 | AG53: 53216.431 | AH53: 46564.377
F54: 2036 | G54: 1044000 | H54: 730113.26 | J54: 0 | K54: 0 | L54: 0 | M54: 0 | N54: 0 | O54: 0 | P54: 0 | Q54: 0 | R54: 0 | S54: 0 | T54: 0 | U54: 0 | V54: 0 | W54: 0 | X54: 0 | Y54: 0 | Z54: 130500 | AA54: 114187.5 | AB54: 99914.062 | AC54: 87424.805 | AD54: 76496.704 | AE54: 66934.616 | AF54: 58567.789 | AG54: 51246.815 | AH54: 44840.964
F55: 2037 | G55: 1012000 | H55: 664267.78 | J55: 0 | K55: 0 | L55: 0 | M55: 0 | N55: 0 | O55: 0 | P55: 0 | Q55: 0 | R55: 0 | S55: 0 | T55: 0 | U55: 0 | V55: 0 | W55: 0 | X55: 0 | Y55: 0 | Z55: 0 | AA55: 126500 | AB55: 110687.5 | AC55: 96851.562 | AD55: 84745.117 | AE55: 74151.978 | AF55: 64882.98 | AG55: 56772.608 | AH55: 49676.032
F56: 2038 | G56: 331000 | H56: 201017.66 | J56: 0 | K56: 0 | L56: 0 | M56: 0 | N56: 0 | O56: 0 | P56: 0 | Q56: 0 | R56: 0 | S56: 0 | T56: 0 | U56: 0 | V56: 0 | W56: 0 | X56: 0 | Y56: 0 | Z56: 0 | AA56: 0 | AB56: 41375 | AC56: 36203.125 | AD56: 31677.734 | AE56: 27718.018 | AF56: 24253.265 | AG56: 21221.607 | AH56: 18568.906
F57: 2039 | G57: 385000 | H57: 212213.8 | J57: 0 | K57: 0 | L57: 0 | M57: 0 | N57: 0 | O57: 0 | P57: 0 | Q57: 0 | R57: 0 | S57: 0 | T57: 0 | U57: 0 | V57: 0 | W57: 0 | X57: 0 | Y57: 0 | Z57: 0 | AA57: 0 | AB57: 0 | AC57: 48125 | AD57: 42109.375 | AE57: 36845.703 | AF57: 32239.99 | AG57: 28209.991 | AH57: 24683.743
F58: 2040 | G58: 1165000 | H58: 567461.09 | J58: 0 | K58: 0 | L58: 0 | M58: 0 | N58: 0 | O58: 0 | P58: 0 | Q58: 0 | R58: 0 | S58: 0 | T58: 0 | U58: 0 | V58: 0 | W58: 0 | X58: 0 | Y58: 0 | Z58: 0 | AA58: 0 | AB58: 0 | AC58: 0 | AD58: 145625 | AE58: 127421.88 | AF58: 111494.14 | AG58: 97557.373 | AH58: 85362.701
... F62: 2044 | G62: 1502000 | H62: 187750 | J62: 0 | K62: 0 | L62: 0 | M62: 0 | N62: 0 | O62: 0 | P62: 0 | Q62: 0 | R62: 0 | S62: 0 | T62: 0 | U62: 0 | V62: 0 | W62: 0 | X62: 0 | Y62: 0 | Z62: 0 | AA62: 0 | AB62: 0 | AC62: 0 | AD62: 0 | AE62: 0 | AF62: 0 | AG62: 0 | AH62: 187750
J63: {=_xlfn.BYCOL(_xlfn.ANCHORARRAY( J38), _xleta.SUM )} -> 282750 | K63: 303406.25 | L63: 459605.47 | M63: 449404.79 | N63: 593979.19 | O63: 729606.79 | P63: 812780.94 | Q63: 721808.32 | R63: 631582.28 | S63: 624009.5 | T63: 650133.31 | U63: 689366.65 | V63: 651945.82 | W63: 793452.59 | X63: 844146.01 | Y63: 893502.76 | Z63: 912314.92 | AA63: 924775.55 | AB63: 850553.61 | AC63: 792359.41 | AD63: 838939.48 | AE63: 854822.05 | AF63: 807344.29 | AG63: 861551.25 | AH63: 941607.35
C66: Straight line
F67: Date | G67: Cost | J67: {=_xlfn.ANCHORARRAY($J$3)} -> 43861 | K67: 44227 | L67: 44592 | M67: 44957 | N67: 45322 | O67: 45688 | P67: 46053 | Q67: 46418 | R67: 46783 | S67: 47149 | T67: 47514 | U67: 47879 | V67: 48244 | W67: 48610 | X67: 48975 | Y67: 49340 | Z67: 49705 | AA67: 50071 | AB67: 50436 | AC67: 50801 | AD67: 51166 | AE67: 51532 | AF67: 51897 | AG67: 52262 | AH67: 52627
F68: {=_xlfn.LET( _xlpm.assets,_xlfn.ANCHORARRAY( $E$7), _xlpm.long_term, INDEX( _xlpm.assets,, 2 ), _xlpm.acq_date, INDEX( _xlpm.assets,, 1 ), _xlfn.DROP( _xlfn.HSTACK( _xlpm.acq_date, _xlpm.long_term ), 1 ) )} -> 2020 | G68: 2262000 | H68: {=IFERROR( _xlfn.BYROW(_xlfn.ANCHORARRAY( J68), _xleta.SUM ), 0 )} -> 2262000 | J68: {=_xlfn.LET( _xlpm.acquisition_date, INDEX(_xlfn.ANCHORARRAY( F68),, 1 ), _xlpm.acquisition_cost, INDEX(_xlfn.ANCHORARRAY( F68),, 2 ), _xlpm.current_date,_xlfn.ANCHORARRAY( J3), _xlpm.period, YEAR( _xlpm.current_date ) - _xlpm.acquisition_date, _xlpm.useful_life, CaseData!$I$33, _xlpm.depreciation, _xlpm.acquisition_cost / _xlpm.useful_life, _xlpm.accumulated_depr, _xlpm.acquisition_cost * ( _xlpm.period ), _xlpm.book_value, _xlpm.acquisition_cost - _xlpm.accumulated_depr, IFERROR( IF( _xlpm.period < 0, 0, IF( _xlpm.period < _xlpm.useful_life, _xlpm.depreciation, IF( _xlpm.book_value > 0, _xlpm.book_value, 0 ) ) ), 0 ) )} -> 141375 | K68: 141375 | L68: 141375 | M68: 141375 | N68: 141375 | O68: 141375 | P68: 141375 | Q68: 141375 | R68: 141375 | S68: 141375 | T68: 141375 | U68: 141375 | V68: 141375 | W68: 141375 | X68: 141375 | Y68: 141375 | Z68: 0 | AA68: 0 | AB68: 0 | AC68: 0 | AD68: 0 | AE68: 0 | AF68: 0 | AG68: 0 | AH68: 0
F69: 2021 | G69: 448000 | H69: 448000 | J69: 0 | K69: 28000 | L69: 28000 | M69: 28000 | N69: 28000 | O69: 28000 | P69: 28000 | Q69: 28000 | R69: 28000 | S69: 28000 | T69: 28000 | U69: 28000 | V69: 28000 | W69: 28000 | X69: 28000 | Y69: 28000 | Z69: 28000 | AA69: 0 | AB69: 0 | AC69: 0 | AD69: 0 | AE69: 0 | AF69: 0 | AG69: 0 | AH69: 0
F70: 2022 | G70: 1553000 | H70: 1553000 | J70: 0 | K70: 0 | L70: 97062.5 | M70: 97062.5 | N70: 97062.5 | O70: 97062.5 | P70: 97062.5 | Q70: 97062.5 | R70: 97062.5 | S70: 97062.5 | T70: 97062.5 | U70: 97062.5 | V70: 97062.5 | W70: 97062.5 | X70: 97062.5 | Y70: 97062.5 | Z70: 97062.5 | AA70: 97062.5 | AB70: 0 | AC70: 0 | AD70: 0 | AE70: 0 | AF70: 0 | AG70: 0 | AH70: 0
F71: 2023 | G71: 378000 | H71: 378000 | J71: 0 | K71: 0 | L71: 0 | M71: 23625 | N71: 23625 | O71: 23625 | P71: 23625 | Q71: 23625 | R71: 23625 | S71: 23625 | T71: 23625 | U71: 23625 | V71: 23625 | W71: 23625 | X71: 23625 | Y71: 23625 | Z71: 23625 | AA71: 23625 | AB71: 23625 | AC71: 0 | AD71: 0 | AE71: 0 | AF71: 0 | AG71: 0 | AH71: 0
F72: 2024 | G72: 1606000 | H72: 1606000 | J72: 0 | K72: 0 | L72: 0 | M72: 0 | N72: 100375 | O72: 100375 | P72: 100375 | Q72: 100375 | R72: 100375 | S72: 100375 | T72: 100375 | U72: 100375 | V72: 100375 | W72: 100375 | X72: 100375 | Y72: 100375 | Z72: 100375 | AA72: 100375 | AB72: 100375 | AC72: 100375 | AD72: 0 | AE72: 0 | AF72: 0 | AG72: 0 | AH72: 0
F73: 2025 | G73: 1679000 | H73: 1679000 | J73: 0 | K73: 0 | L73: 0 | M73: 0 | N73: 0 | O73: 104937.5 | P73: 104937.5 | Q73: 104937.5 | R73: 104937.5 | S73: 104937.5 | T73: 104937.5 | U73: 104937.5 | V73: 104937.5 | W73: 104937.5 | X73: 104937.5 | Y73: 104937.5 | Z73: 104937.5 | AA73: 104937.5 | AB73: 104937.5 | AC73: 104937.5 | AD73: 104937.5 | AE73: 0 | AF73: 0 | AG73: 0 | AH73: 0
F74: 2026 | G74: 1395000 | H74: 1395000 | J74: 0 | K74: 0 | L74: 0 | M74: 0 | N74: 0 | O74: 0 | P74: 87187.5 | Q74: 87187.5 | R74: 87187.5 | S74: 87187.5 | T74: 87187.5 | U74: 87187.5 | V74: 87187.5 | W74: 87187.5 | X74: 87187.5 | Y74: 87187.5 | Z74: 87187.5 | AA74: 87187.5 | AB74: 87187.5 | AC74: 87187.5 | AD74: 87187.5 | AE74: 87187.5 | AF74: 0 | AG74: 0 | AH74: 0
F75: 2027 | G75: 85000 | H75: 85000 | J75: 0 | K75: 0 | L75: 0 | M75: 0 | N75: 0 | O75: 0 | P75: 0 | Q75: 5312.5 | R75: 5312.5 | S75: 5312.5 | T75: 5312.5 | U75: 5312.5 | V75: 5312.5 | W75: 5312.5 | X75: 5312.5 | Y75: 5312.5 | Z75: 5312.5 | AA75: 5312.5 | AB75: 5312.5 | AC75: 5312.5 | AD75: 5312.5 | AE75: 5312.5 | AF75: 5312.5 | AG75: 0 | AH75: 0
F76: 2028 | H76: 0 | J76: 0 | K76: 0 | L76: 0 | M76: 0 | N76: 0 | O76: 0 | P76: 0 | Q76: 0 | R76: 0 | S76: 0 | T76: 0 | U76: 0 | V76: 0 | W76: 0 | X76: 0 | Y76: 0 | Z76: 0 | AA76: 0 | AB76: 0 | AC76: 0 | AD76: 0 | AE76: 0 | AF76: 0 | AG76: 0 | AH76: 0
F77: 2029 | G77: 571000 | H77: 571000 | J77: 0 | K77: 0 | L77: 0 | M77: 0 | N77: 0 | O77: 0 | P77: 0 | Q77: 0 | R77: 0 | S77: 35687.5 | T77: 35687.5 | U77: 35687.5 | V77: 35687.5 | W77: 35687.5 | X77: 35687.5 | Y77: 35687.5 | Z77: 35687.5 | AA77: 35687.5 | AB77: 35687.5 | AC77: 35687.5 | AD77: 35687.5 | AE77: 35687.5 | AF77: 35687.5 | AG77: 35687.5 | AH77: 35687.5
F78: 2030 | G78: 833000 | H78: 780937.5 | J78: 0 | K78: 0 | L78: 0 | M78: 0 | N78: 0 | O78: 0 | P78: 0 | Q78: 0 | R78: 0 | S78: 0 | T78: 52062.5 | U78: 52062.5 | V78: 52062.5 | W78: 52062.5 | X78: 52062.5 | Y78: 52062.5 | Z78: 52062.5 | AA78: 52062.5 | AB78: 52062.5 | AC78: 52062.5 | AD78: 52062.5 | AE78: 52062.5 | AF78: 52062.5 | AG78: 52062.5 | AH78: 52062.5
F79: 2031 | G79: 964000 | H79: 843500 | J79: 0 | K79: 0 | L79: 0 | M79: 0 | N79: 0 | O79: 0 | P79: 0 | Q79: 0 | R79: 0 | S79: 0 | T79: 0 | U79: 60250 | V79: 60250 | W79: 60250 | X79: 60250 | Y79: 60250 | Z79: 60250 | AA79: 60250 | AB79: 60250 | AC79: 60250 | AD79: 60250 | AE79: 60250 | AF79: 60250 | AG79: 60250 | AH79: 60250
F80: 2032 | G80: 390000 | H80: 316875 | J80: 0 | K80: 0 | L80: 0 | M80: 0 | N80: 0 | O80: 0 | P80: 0 | Q80: 0 | R80: 0 | S80: 0 | T80: 0 | U80: 0 | V80: 24375 | W80: 24375 | X80: 24375 | Y80: 24375 | Z80: 24375 | AA80: 24375 | AB80: 24375 | AC80: 24375 | AD80: 24375 | AE80: 24375 | AF80: 24375 | AG80: 24375 | AH80: 24375
F81: 2033 | G81: 1784000 | H81: 1338000 | J81: 0 | K81: 0 | L81: 0 | M81: 0 | N81: 0 | O81: 0 | P81: 0 | Q81: 0 | R81: 0 | S81: 0 | T81: 0 | U81: 0 | V81: 0 | W81: 111500 | X81: 111500 | Y81: 111500 | Z81: 111500 | AA81: 111500 | AB81: 111500 | AC81: 111500 | AD81: 111500 | AE81: 111500 | AF81: 111500 | AG81: 111500 | AH81: 111500
F82: 2034 | G82: 1199000 | H82: 824312.5 | J82: 0 | K82: 0 | L82: 0 | M82: 0 | N82: 0 | O82: 0 | P82: 0 | Q82: 0 | R82: 0 | S82: 0 | T82: 0 | U82: 0 | V82: 0 | W82: 0 | X82: 74937.5 | Y82: 74937.5 | Z82: 74937.5 | AA82: 74937.5 | AB82: 74937.5 | AC82: 74937.5 | AD82: 74937.5 | AE82: 74937.5 | AF82: 74937.5 | AG82: 74937.5 | AH82: 74937.5
F83: 2035 | G83: 1239000 | H83: 774375 | J83: 0 | K83: 0 | L83: 0 | M83: 0 | N83: 0 | O83: 0 | P83: 0 | Q83: 0 | R83: 0 | S83: 0 | T83: 0 | U83: 0 | V83: 0 | W83: 0 | X83: 0 | Y83: 77437.5 | Z83: 77437.5 | AA83: 77437.5 | AB83: 77437.5 | AC83: 77437.5 | AD83: 77437.5 | AE83: 77437.5 | AF83: 77437.5 | AG83: 77437.5 | AH83: 77437.5
F84: 2036 | G84: 1044000 | H84: 587250 | J84: 0 | K84: 0 | L84: 0 | M84: 0 | N84: 0 | O84: 0 | P84: 0 | Q84: 0 | R84: 0 | S84: 0 | T84: 0 | U84: 0 | V84: 0 | W84: 0 | X84: 0 | Y84: 0 | Z84: 65250 | AA84: 65250 | AB84: 65250 | AC84: 65250 | AD84: 65250 | AE84: 65250 | AF84: 65250 | AG84: 65250 | AH84: 65250
F85: 2037 | G85: 1012000 | H85: 506000 | J85: 0 | K85: 0 | L85: 0 | M85: 0 | N85: 0 | O85: 0 | P85: 0 | Q85: 0 | R85: 0 | S85: 0 | T85: 0 | U85: 0 | V85: 0 | W85: 0 | X85: 0 | Y85: 0 | Z85: 0 | AA85: 63250 | AB85: 63250 | AC85: 63250 | AD85: 63250 | AE85: 63250 | AF85: 63250 | AG85: 63250 | AH85: 63250
F86: 2038 | G86: 331000 | H86: 144812.5 | J86: 0 | K86: 0 | L86: 0 | M86: 0 | N86: 0 | O86: 0 | P86: 0 | Q86: 0 | R86: 0 | S86: 0 | T86: 0 | U86: 0 | V86: 0 | W86: 0 | X86: 0 | Y86: 0 | Z86: 0 | AA86: 0 | AB86: 20687.5 | AC86: 20687.5 | AD86: 20687.5 | AE86: 20687.5 | AF86: 20687.5 | AG86: 20687.5 | AH86: 20687.5
F87: 2039 | G87: 385000 | H87: 144375 | J87: 0 | K87: 0 | L87: 0 | M87: 0 | N87: 0 | O87: 0 | P87: 0 | Q87: 0 | R87: 0 | S87: 0 | T87: 0 | U87: 0 | V87: 0 | W87: 0 | X87: 0 | Y87: 0 | Z87: 0 | AA87: 0 | AB87: 0 | AC87: 24062.5 | AD87: 24062.5 | AE87: 24062.5 | AF87: 24062.5 | AG87: 24062.5 | AH87: 24062.5
F88: 2040 | G88: 1165000 | H88: 364062.5 | J88: 0 | K88: 0 | L88: 0 | M88: 0 | N88: 0 | O88: 0 | P88: 0 | Q88: 0 | R88: 0 | S88: 0 | T88: 0 | U88: 0 | V88: 0 | W88: 0 | X88: 0 | Y88: 0 | Z88: 0 | AA88: 0 | AB88: 0 | AC88: 0 | AD88: 72812.5 | AE88: 72812.5 | AF88: 72812.5 | AG88: 72812.5 | AH88: 72812.5
... F92: 2044 | G92: 1502000 | H92: 93875 | J92: 0 | K92: 0 | L92: 0 | M92: 0 | N92: 0 | O92: 0 | P92: 0 | Q92: 0 | R92: 0 | S92: 0 | T92: 0 | U92: 0 | V92: 0 | W92: 0 | X92: 0 | Y92: 0 | Z92: 0 | AA92: 0 | AB92: 0 | AC92: 0 | AD92: 0 | AE92: 0 | AF92: 0 | AG92: 0 | AH92: 93875
J93: {=_xlfn.BYCOL(_xlfn.ANCHORARRAY( J68), _xleta.SUM )} -> 141375 | K93: 169375 | L93: 266437.5 | M93: 290062.5 | N93: 390437.5 | O93: 495375 | P93: 582562.5 | Q93: 587875 | R93: 587875 | S93: 623562.5 | T93: 675625 | U93: 735875 | V93: 760250 | W93: 871750 | X93: 946687.5 | Y93: 1024125 | Z93: 948000 | AA93: 983250 | AB93: 906875 | AC93: 907312.5 | AD93: 879750 | AE93: 835187.5 | AF93: 777687.5 | AG93: 849937.5 | AH93: 943812.5
C97: Adjusted MACS
F98: Date | G98: Cost | J98: {=_xlfn.ANCHORARRAY($J$3)} -> 43861 | K98: 44227 | L98: 44592 | M98: 44957 | N98: 45322 | O98: 45688 | P98: 46053 | Q98: 46418 | R98: 46783 | S98: 47149 | T98: 47514 | U98: 47879 | V98: 48244 | W98: 48610 | X98: 48975 | Y98: 49340 | Z98: 49705 | AA98: 50071 | AB98: 50436 | AC98: 50801 | AD98: 51166 | AE98: 51532 | AF98: 51897 | AG98: 52262 | AH98: 52627
F99: {=_xlfn.LET( _xlpm.assets,_xlfn.ANCHORARRAY( $E$7), _xlpm.long_term, INDEX( _xlpm.assets,, 2 ), _xlpm.acq_date, INDEX( _xlpm.assets,, 1 ), _xlfn.DROP( _xlfn.HSTACK( _xlpm.acq_date, _xlpm.long_term ), 1 ) )} -> 2020 | G99: 2262000 | H99: {=_xlfn.BYROW(_xlfn.ANCHORARRAY( J99), _xleta.SUM )} -> 2262000 | J99: {=_xlfn.LET( _xlpm.acquisition_date, INDEX(_xlfn.ANCHORARRAY( F99),, 1 ), _xlpm.acquisition_cost, INDEX(_xlfn.ANCHORARRAY( F99),, 2 ), _xlpm.current_date,_xlfn.ANCHORARRAY( $J$3), _xlpm.period, YEAR( _xlpm.current_date ) - _xlpm.acquisition_date + 1, _xlpm.current_class, CaseData!$I$34, _xlpm.classes, CaseData!$E$39:$T$39, _xlpm.class_year, CaseData!$D$41:$D$60, _xlpm.class_percentage, CaseData!$E$41:$T$60, _xlpm.rate, INDEX( _xlpm.class_percentage, MATCH( _xlpm.period, _xlpm.class_year, 0 ), MATCH( _xlpm.current_class, _xlpm.classes, 0 ) ), IFERROR( IF( _xlpm.period < 0, 0, _xlpm.acquisition_cost * _xlpm.rate ), 0 ) )} -> 282750 | K99: 246558 | L99: 217152 | M99: 190008 | N99: 165126 | O99: 144768 | P99: 126672 | Q99: 110838 | R99: 97266 | S99: 97266 | T99: 97266 | U99: 97266 | V99: 97266 | W99: 97266 | X99: 97266 | Y99: 97266 | Z99: 0 | AA99: 0 | AB99: 0 | AC99: 0 | AD99: 0 | AE99: 0 | AF99: 0 | AG99: 0 | AH99: 0
F100: 2021 | G100: 448000 | H100: 448000 | J100: 0 | K100: 56000 | L100: 48832 | M100: 43008 | N100: 37632 | O100: 32704 | P100: 28672 | Q100: 25088 | R100: 21952 | S100: 19264 | T100: 19264 | U100: 19264 | V100: 19264 | W100: 19264 | X100: 19264 | Y100: 19264 | Z100: 19264 | AA100: 0 | AB100: 0 | AC100: 0 | AD100: 0 | AE100: 0 | AF100: 0 | AG100: 0 | AH100: 0
F101: 2022 | G101: 1553000 | H101: 1553000 | J101: 0 | K101: 0 | L101: 194125 | M101: 169277 | N101: 149088 | O101: 130452 | P101: 113369 | Q101: 99392 | R101: 86968 | S101: 76097 | T101: 66779 | U101: 66779 | V101: 66779 | W101: 66779 | X101: 66779 | Y101: 66779 | Z101: 66779 | AA101: 66779 | AB101: 0 | AC101: 0 | AD101: 0 | AE101: 0 | AF101: 0 | AG101: 0 | AH101: 0
F102: 2023 | G102: 378000 | H102: 378000 | J102: 0 | K102: 0 | L102: 0 | M102: 47250 | N102: 41202 | O102: 36288 | P102: 31752 | Q102: 27594 | R102: 24192 | S102: 21168 | T102: 18522 | U102: 16254 | V102: 16254 | W102: 16254 | X102: 16254 | Y102: 16254 | Z102: 16254 | AA102: 16254 | AB102: 16254 | AC102: 0 | AD102: 0 | AE102: 0 | AF102: 0 | AG102: 0 | AH102: 0
F103: 2024 | G103: 1606000 | H103: 1606000 | J103: 0 | K103: 0 | L103: 0 | M103: 0 | N103: 200750 | O103: 175054 | P103: 154176 | Q103: 134904 | R103: 117238 | S103: 102784 | T103: 89936 | U103: 78694 | V103: 69058 | W103: 69058 | X103: 69058 | Y103: 69058 | Z103: 69058 | AA103: 69058 | AB103: 69058 | AC103: 69058 | AD103: 0 | AE103: 0 | AF103: 0 | AG103: 0 | AH103: 0
F104: 2025 | G104: 1679000 | H104: 1679000 | J104: 0 | K104: 0 | L104: 0 | M104: 0 | N104: 0 | O104: 209875 | P104: 183011 | Q104: 161184 | R104: 141036 | S104: 122567 | T104: 107456 | U104: 94024 | V104: 82271 | W104: 72197 | X104: 72197 | Y104: 72197 | Z104: 72197 | AA104: 72197 | AB104: 72197 | AC104: 72197 | AD104: 72197 | AE104: 0 | AF104: 0 | AG104: 0 | AH104: 0
F105: 2026 | G105: 1395000 | H105: 1395000 | J105: 0 | K105: 0 | L105: 0 | M105: 0 | N105: 0 | O105: 0 | P105: 174375 | Q105: 152055 | R105: 133920 | S105: 117180 | T105: 101835 | U105: 89280 | V105: 78120 | W105: 68355 | X105: 59985 | Y105: 59985 | Z105: 59985 | AA105: 59985 | AB105: 59985 | AC105: 59985 | AD105: 59985 | AE105: 59985 | AF105: 0 | AG105: 0 | AH105: 0
F106: 2027 | G106: 85000 | H106: 85000 | J106: 0 | K106: 0 | L106: 0 | M106: 0 | N106: 0 | O106: 0 | P106: 0 | Q106: 10625 | R106: 9265 | S106: 8160 | T106: 7140 | U106: 6205 | V106: 5440 | W106: 4760 | X106: 4165 | Y106: 3655 | Z106: 3655 | AA106: 3655 | AB106: 3655 | AC106: 3655 | AD106: 3655 | AE106: 3655 | AF106: 3655 | AG106: 0 | AH106: 0
F107: 2028 | H107: 0 | J107: 0 | K107: 0 | L107: 0 | M107: 0 | N107: 0 | O107: 0 | P107: 0 | Q107: 0 | R107: 0 | S107: 0 | T107: 0 | U107: 0 | V107: 0 | W107: 0 | X107: 0 | Y107: 0 | Z107: 0 | AA107: 0 | AB107: 0 | AC107: 0 | AD107: 0 | AE107: 0 | AF107: 0 | AG107: 0 | AH107: 0
F108: 2029 | G108: 571000 | H108: 571000 | J108: 0 | K108: 0 | L108: 0 | M108: 0 | N108: 0 | O108: 0 | P108: 0 | Q108: 0 | R108: 0 | S108: 71375 | T108: 62239 | U108: 54816 | V108: 47964 | W108: 41683 | X108: 36544 | Y108: 31976 | Z108: 27979 | AA108: 24553 | AB108: 24553 | AC108: 24553 | AD108: 24553 | AE108: 24553 | AF108: 24553 | AG108: 24553 | AH108: 24553
F109: 2030 | G109: 833000 | H109: 797181 | J109: 0 | K109: 0 | L109: 0 | M109: 0 | N109: 0 | O109: 0 | P109: 0 | Q109: 0 | R109: 0 | S109: 0 | T109: 104125 | U109: 90797 | V109: 79968 | W109: 69972 | X109: 60809 | Y109: 53312 | Z109: 46648 | AA109: 40817 | AB109: 35819 | AC109: 35819 | AD109: 35819 | AE109: 35819 | AF109: 35819 | AG109: 35819 | AH109: 35819
F110: 2031 | G110: 964000 | H110: 881096 | J110: 0 | K110: 0 | L110: 0 | M110: 0 | N110: 0 | O110: 0 | P110: 0 | Q110: 0 | R110: 0 | S110: 0 | T110: 0 | U110: 120500 | V110: 105076 | W110: 92544 | X110: 80976 | Y110: 70372 | Z110: 61696 | AA110: 53984 | AB110: 47236 | AC110: 41452 | AD110: 41452 | AE110: 41452 | AF110: 41452 | AG110: 41452 | AH110: 41452
F111: 2032 | G111: 390000 | H111: 339690 | J111: 0 | K111: 0 | L111: 0 | M111: 0 | N111: 0 | O111: 0 | P111: 0 | Q111: 0 | R111: 0 | S111: 0 | T111: 0 | U111: 0 | V111: 48750 | W111: 42510 | X111: 37440 | Y111: 32760 | Z111: 28470 | AA111: 24960 | AB111: 21840 | AC111: 19110 | AD111: 16770 | AE111: 16770 | AF111: 16770 | AG111: 16770 | AH111: 16770
F112: 2033 | G112: 1784000 | H112: 1477152 | J112: 0 | K112: 0 | L112: 0 | M112: 0 | N112: 0 | O112: 0 | P112: 0 | Q112: 0 | R112: 0 | S112: 0 | T112: 0 | U112: 0 | V112: 0 | W112: 223000 | X112: 194456 | Y112: 171264 | Z112: 149856 | AA112: 130232 | AB112: 114176 | AC112: 99904 | AD112: 87416 | AE112: 76712 | AF112: 76712 | AG112: 76712 | AH112: 76712
F113: 2034 | G113: 1199000 | H113: 941215 | J113: 0 | K113: 0 | L113: 0 | M113: 0 | N113: 0 | O113: 0 | P113: 0 | Q113: 0 | R113: 0 | S113: 0 | T113: 0 | U113: 0 | V113: 0 | W113: 0 | X113: 149875 | Y113: 130691 | Z113: 115104 | AA113: 100716 | AB113: 87527 | AC113: 76736 | AD113: 67144 | AE113: 58751 | AF113: 51557 | AG113: 51557 | AH113: 51557
F114: 2035 | G114: 1239000 | H114: 919338 | J114: 0 | K114: 0 | L114: 0 | M114: 0 | N114: 0 | O114: 0 | P114: 0 | Q114: 0 | R114: 0 | S114: 0 | T114: 0 | U114: 0 | V114: 0 | W114: 0 | X114: 0 | Y114: 154875 | Z114: 135051 | AA114: 118944 | AB114: 104076 | AC114: 90447 | AD114: 79296 | AE114: 69384 | AF114: 60711 | AG114: 53277 | AH114: 53277
F115: 2036 | G115: 1044000 | H115: 729756 | J115: 0 | K115: 0 | L115: 0 | M115: 0 | N115: 0 | O115: 0 | P115: 0 | Q115: 0 | R115: 0 | S115: 0 | T115: 0 | U115: 0 | V115: 0 | W115: 0 | X115: 0 | Y115: 0 | Z115: 130500 | AA115: 113796 | AB115: 100224 | AC115: 87696 | AD115: 76212 | AE115: 66816 | AF115: 58464 | AG115: 51156 | AH115: 44892
F116: 2037 | G116: 1012000 | H116: 663872 | J116: 0 | K116: 0 | L116: 0 | M116: 0 | N116: 0 | O116: 0 | P116: 0 | Q116: 0 | R116: 0 | S116: 0 | T116: 0 | U116: 0 | V116: 0 | W116: 0 | X116: 0 | Y116: 0 | Z116: 0 | AA116: 126500 | AB116: 110308 | AC116: 97152 | AD116: 85008 | AE116: 73876 | AF116: 64768 | AG116: 56672 | AH116: 49588
F117: 2038 | G117: 331000 | H117: 200917 | J117: 0 | K117: 0 | L117: 0 | M117: 0 | N117: 0 | O117: 0 | P117: 0 | Q117: 0 | R117: 0 | S117: 0 | T117: 0 | U117: 0 | V117: 0 | W117: 0 | X117: 0 | Y117: 0 | Z117: 0 | AA117: 0 | AB117: 41375 | AC117: 36079 | AD117: 31776 | AE117: 27804 | AF117: 24163 | AG117: 21184 | AH117: 18536
F118: 2039 | G118: 385000 | H118: 212135 | J118: 0 | K118: 0 | L118: 0 | M118: 0 | N118: 0 | O118: 0 | P118: 0 | Q118: 0 | R118: 0 | S118: 0 | T118: 0 | U118: 0 | V118: 0 | W118: 0 | X118: 0 | Y118: 0 | Z118: 0 | AA118: 0 | AB118: 0 | AC118: 48125 | AD118: 41965 | AE118: 36960 | AF118: 32340 | AG118: 28105 | AH118: 24640
...

Sheet Time
A1: {=company} -> Big Dog Construction
A2: {=topic} -> CFM Topic: CAPEX and Depreciation
A3: TIME SCHEDULE | F3: Constant | G3: Unit | H3: Total | J3: {=EOMONTH( start_date, _xlfn.SEQUENCE( 1, periods, 0, 12 ) )} -> 43861 | K3: 44227 | L3: 44592 | M3: 44957 | N3: 45322 | O3: 45688 | P3: 46053 | Q3: 46418 | R3: 46783 | S3: 47149 | T3: 47514 | U3: 47879 | V3: 48244 | W3: 48610 | X3: 48975 | Y3: 49340 | Z3: 49705 | AA3: 50071 | AB3: 50436 | AC3: 50801 | AD3: 51166 | AE3: 51532 | AF3: 51897 | AG3: 52262 | AH3: 52627
B5: Model timeline and flags
E7: Model timeline | G7: date | J7: {=EOMONTH( start_date, _xlfn.SEQUENCE( 1, periods, 0, 12 ) )} -> 43861 | K7: 44227 | L7: 44592 | M7: 44957 | N7: 45322 | O7: 45688 | P7: 46053 | Q7: 46418 | R7: 46783 | S7: 47149 | T7: 47514 | U7: 47879 | V7: 48244 | W7: 48610 | X7: 48975 | Y7: 49340 | Z7: 49705 | AA7: 50071 | AB7: 50436 | AC7: 50801 | AD7: 51166 | AE7: 51532 | AF7: 51897 | AG7: 52262 | AH7: 52627

Sheet Tmp
A1: {=company} -> Big Dog Construction
A2: {=topic} -> CFM Topic: CAPEX and Depreciation
A3: TMP SCHEDULE | F3: Constant | G3: Unit | H3: Total | J3: {=EOMONTH( start_date, _xlfn.SEQUENCE( 1, periods, 0, 12 ) )} -> 43861 | K3: 44227 | L3: 44592 | M3: 44957 | N3: 45322 | O3: 45688 | P3: 46053 | Q3: 46418 | R3: 46783 | S3: 47149 | T3: 47514 | U3: 47879 | V3: 48244 | W3: 48610 | X3: 48975 | Y3: 49340 | Z3: 49705 | AA3: 50071 | AB3: 50436 | AC3: 50801 | AD3: 51166 | AE3: 51532 | AF3: 51897 | AG3: 52262 | AH3: 52627

Sheet CaseData
A1: General Assumptions
C3: Company name | G3: Big Dog Construction
C4: CFM Topic | G4: CAPEX and Depreciation
C6: Model Start Date (do not change) | E6: [date] | G6: 43831
C7: Tax Rate | E7: [%] | G7: 0.3
C8: Discount Rate per Annum | E8: [%] | G8: 0.09
C9: Discount Date for Present Value of Tax Benefits | E9: [date] | G9: =G6-1 -> 43830
C11: Model periods | E11: years | G11: 25
B13: Names of Asset Classes
C14: ListAssetClasses
C15: Short Term
C16: Medium Term
C17: Long Term
B20: Names of Depreciation Methods
C21: ListDepMethods
C22: Declining Balance
C23: Straight Line
C24: Adjusted MACRS
C25: Sum of Years Digits
A28: Depreciation Assumptions
B30: General Depreciation Assumption Data
G31: {=TRANSPOSE(ListAssetClasses)} -> Short Term | H31: Medium Term | I31: Long Term
C32: {=ListDepMethods} -> Declining Balance | E32: Annual % | F32: [%] | G32: 0.4 | H32: 0.25 | I32: 0.125
C33: Straight Line | E33: Useful Life | F33: [years] | G33: 5 | H33: 8 | I33: 16
C34: Adjusted MACRS | D34: (See below) | E34: Class # | F34: [#] | G34: 5 | H34: 8 | I34: 16
C35: Sum of Years Digits | D35: (See below) | E35: Useful Life | F35: [years] | G35: 5 | H35: 8 | I35: 16
B38: =$C$24&" Tables" -> Adjusted MACRS Tables
D39: Class # --> | E39: 5 | F39: =E39+1 -> 6 | G39: =F39+1 -> 7 | H39: =G39+1 -> 8 | I39: =H39+1 -> 9 | J39: =I39+1 -> 10 | K39: =J39+1 -> 11 | L39: =K39+1 -> 12 | M39: =L39+1 -> 13 | ... T39: =S39+1 -> 20
D40: Year
D41: 1 | E41: 0.4 | F41: 0.333 | G41: 0.286 | H41: 0.25 | I41: 0.222 | J41: 0.2 | K41: 0.182 | L41: 0.167 | M41: 0.154 | N41: 0.143 | O41: 0.133 | P41: 0.125 | Q41: 0.118 | R41: 0.111 | S41: 0.105 | T41: 0.1
D42: =D41+1 -> 2 | E42: 0.24 | F42: 0.222 | G42: 0.204 | H42: 0.188 | I42: 0.173 | J42: 0.16 | K42: 0.149 | L42: 0.139 | M42: 0.13 | N42: 0.122 | O42: 0.116 | P42: 0.109 | Q42: 0.104 | R42: 0.099 | S42: 0.094 | T42: 0.09
D43: =D42+1 -> 3 | E43: 0.144 | F43: 0.148 | G43: 0.146 | H43: 0.141 | I43: 0.134 | J43: 0.128 | K43: 0.122 | L43: 0.116 | M43: 0.11 | N43: 0.105 | O43: 0.1 | P43: 0.096 | Q43: 0.092 | R43: 0.088 | S43: 0.084 | T43: 0.081
D44: =D43+1 -> 4 | E44: 0.108 | F44: 0.099 | G44: 0.104 | H44: 0.105 | I44: 0.105 | J44: 0.102 | K44: 0.1 | L44: 0.096 | M44: 0.093 | N44: 0.09 | O44: 0.087 | P44: 0.084 | Q44: 0.081 | R44: 0.078 | S44: 0.075 | T44: 0.073
D45: =D44+1 -> 5 | E45: 0.108 | F45: 0.099 | G45: 0.087 | H45: 0.079 | I45: 0.081 | J45: 0.082 | K45: 0.081 | L45: 0.08 | M45: 0.079 | N45: 0.077 | O45: 0.075 | P45: 0.073 | Q45: 0.071 | R45: 0.069 | S45: 0.067 | T45: 0.066
D46: =D45+1 -> 6 | E46: 0 | F46: 0.099 | G46: 0.087 | H46: 0.079 | I46: 0.071 | J46: 0.066 | K46: 0.067 | L46: 0.067 | M46: 0.067 | N46: 0.066 | O46: 0.065 | P46: 0.064 | Q46: 0.063 | R46: 0.062 | S46: 0.06 | T46: 0.059
D47: =D46+1 -> 7 | E47: 0 | F47: 0 | G47: 0.086 | H47: 0.079 | I47: 0.071 | J47: 0.066 | K47: 0.06 | L47: 0.056 | M47: 0.056 | N47: 0.057 | O47: 0.057 | P47: 0.056 | Q47: 0.056 | R47: 0.055 | S47: 0.054 | T47: 0.053
D48: =D47+1 -> 8 | E48: 0 | F48: 0 | G48: 0 | H48: 0.079 | I48: 0.071 | J48: 0.066 | K48: 0.06 | L48: 0.056 | M48: 0.052 | N48: 0.049 | O48: 0.049 | P48: 0.049 | Q48: 0.049 | R48: 0.049 | S48: 0.048 | T48: 0.048
D49: =D48+1 -> 9 | E49: 0 | F49: 0 | G49: 0 | H49: 0 | I49: 0.072 | J49: 0.066 | K49: 0.06 | L49: 0.056 | M49: 0.052 | N49: 0.049 | O49: 0.045 | P49: 0.043 | Q49: 0.043 | R49: 0.043 | S49: 0.043 | T49: 0.043
D50: =D49+1 -> 10 | E50: 0 | F50: 0 | G50: 0 | H50: 0 | I50: 0 | J50: 0.064 | K50: 0.06 | L50: 0.056 | M50: 0.052 | N50: 0.049 | O50: 0.045 | P50: 0.043 | Q50: 0.041 | R50: 0.038 | S50: 0.039 | T50: 0.039
D51: =D50+1 -> 11 | E51: 0 | F51: 0 | G51: 0 | H51: 0 | I51: 0 | J51: 0 | K51: 0.059 | L51: 0.056 | M51: 0.052 | N51: 0.049 | O51: 0.045 | P51: 0.043 | Q51: 0.041 | R51: 0.038 | S51: 0.037 | T51: 0.035
D52: =D51+1 -> 12 | E52: 0 | F52: 0 | G52: 0 | H52: 0 | I52: 0 | J52: 0 | K52: 0 | L52: 0.055 | M52: 0.052 | N52: 0.049 | O52: 0.045 | P52: 0.043 | Q52: 0.041 | R52: 0.038 | S52: 0.037 | T52: 0.035
C53: 0 | D53: =D52+1 -> 13 | E53: 0 | F53: 0 | G53: 0 | H53: 0 | I53: 0 | J53: 0 | K53: 0 | L53: 0 | M53: 0.051 | N53: 0.049 | O53: 0.045 | P53: 0.043 | Q53: 0.041 | R53: 0.038 | S53: 0.037 | T53: 0.035
D54: =D53+1 -> 14 | E54: 0 | F54: 0 | G54: 0 | H54: 0 | I54: 0 | J54: 0 | K54: 0 | L54: 0 | M54: 0 | N54: 0.046 | O54: 0.045 | P54: 0.043 | Q54: 0.041 | R54: 0.038 | S54: 0.037 | T54: 0.035
D55: =D54+1 -> 15 | E55: 0 | F55: 0 | G55: 0 | H55: 0 | I55: 0 | J55: 0 | K55: 0 | L55: 0 | M55: 0 | N55: 0 | O55: 0.048 | P55: 0.043 | Q55: 0.041 | R55: 0.038 | S55: 0.037 | T55: 0.035
D56: =D55+1 -> 16 | E56: 0 | F56: 0 | G56: 0 | H56: 0 | I56: 0 | J56: 0 | K56: 0 | L56: 0 | M56: 0 | N56: 0 | O56: 0 | P56: 0.043 | Q56: 0.041 | R56: 0.038 | S56: 0.037 | T56: 0.035
D57: =D56+1 -> 17 | E57: 0 | F57: 0 | G57: 0 | H57: 0 | I57: 0 | J57: 0 | K57: 0 | L57: 0 | M57: 0 | N57: 0 | O57: 0 | P57: 0 | Q57: 0.036 | R57: 0.038 | S57: 0.037 | T57: 0.035
D58: =D57+1 -> 18 | E58: 0 | F58: 0 | G58: 0 | H58: 0 | I58: 0 | J58: 0 | K58: 0 | L58: 0 | M58: 0 | N58: 0 | O58: 0 | P58: 0 | Q58: 0 | R58: 0.042 | S58: 0.037 | T58: 0.035
D59: =D58+1 -> 19 | E59: 0 | F59: 0 | G59: 0 | H59: 0 | I59: 0 | J59: 0 | K59: 0 | L59: 0 | M59: 0 | N59: 0 | O59: 0 | P59: 0 | Q59: 0 | R59: 0 | S59: 0.035 | T59: 0.035
D60: =D59+1 -> 20 | E60: 0 | F60: 0 | G60: 0 | H60: 0 | I60: 0 | J60: 0 | K60: 0 | L60: 0 | M60: 0 | N60: 0 | O60: 0 | P60: 0 | Q60: 0 | R60: 0 | S60: 0 | T60: 0.033
B63: =$C$25&" Tables" -> Sum of Years Digits Tables
D64: Useful Life --> | E64: 5 | F64: =E64+1 -> 6 | G64: =F64+1 -> 7 | H64: =G64+1 -> 8 | I64: =H64+1 -> 9 | J64: =I64+1 -> 10 | K64: =J64+1 -> 11 | L64: =K64+1 -> 12 | M64: =L64+1 -> 13 | ... T64: =S64+1 -> 20
D65: Year | E65: =E$64*(E$64+1)/2 -> 15 | F65: =F$64*(F$64+1)/2 -> 21 | G65: =G$64*(G$64+1)/2 -> 28 | H65: =H$64*(H$64+1)/2 -> 36 | I65: =I$64*(I$64+1)/2 -> 45 | J65: =J$64*(J$64+1)/2 -> 55 | K65: =K$64*(K$64+1)/2 -> 66 | L65: =L$64*(L$64+1)/2 -> 78 | ... T65: =T$64*(T$64+1)/2 -> 210
D66: 1 | E66: =MAX(0,E$64+1-$D66)/E$65 -> 0.33333333 | F66: =MAX(0,F$64+1-$D66)/F$65 -> 0.28571429 | G66: =MAX(0,G$64+1-$D66)/G$65 -> 0.25 | H66: =MAX(0,H$64+1-$D66)/H$65 -> 0.22222222 | I66: =MAX(0,I$64+1-$D66)/I$65 -> 0.2 | J66: =MAX(0,J$64+1-$D66)/J$65 -> 0.18181818 | K66: =MAX(0,K$64+1-$D66)/K$65 -> 0.16666667 | L66: =MAX(0,L$64+1-$D66)/L$65 -> 0.15384615 | ... T66: =MAX(0,T$64+1-$D66)/T$65 -> 0.095238095
D67: =D66+1 -> 2 | E67: =MAX(0,E$64+1-$D67)/E$65 -> 0.26666667 | F67: =MAX(0,F$64+1-$D67)/F$65 -> 0.23809524 | G67: =MAX(0,G$64+1-$D67)/G$65 -> 0.21428571 | H67: =MAX(0,H$64+1-$D67)/H$65 -> 0.19444444 | I67: =MAX(0,I$64+1-$D67)/I$65 -> 0.17777778 | J67: =MAX(0,J$64+1-$D67)/J$65 -> 0.16363636 | K67: =MAX(0,K$64+1-$D67)/K$65 -> 0.15151515 | L67: =MAX(0,L$64+1-$D67)/L$65 -> 0.14102564 | ... T67: =MAX(0,T$64+1-$D67)/T$65 -> 0.09047619
D68: =D67+1 -> 3 | E68: =MAX(0,E$64+1-$D68)/E$65 -> 0.2 | F68: =MAX(0,F$64+1-$D68)/F$65 -> 0.19047619 | G68: =MAX(0,G$64+1-$D68)/G$65 -> 0.17857143 | H68: =MAX(0,H$64+1-$D68)/H$65 -> 0.16666667 | I68: =MAX(0,I$64+1-$D68)/I$65 -> 0.15555556 | J68: =MAX(0,J$64+1-$D68)/J$65 -> 0.14545455 | K68: =MAX(0,K$64+1-$D68)/K$65 -> 0.13636364 | L68: =MAX(0,L$64+1-$D68)/L$65 -> 0.12820513 | ... T68: =MAX(0,T$64+1-$D68)/T$65 -> 0.085714286
D69: =D68+1 -> 4 | E69: =MAX(0,E$64+1-$D69)/E$65 -> 0.13333333 | F69: =MAX(0,F$64+1-$D69)/F$65 -> 0.14285714 | G69: =MAX(0,G$64+1-$D69)/G$65 -> 0.14285714 | H69: =MAX(0,H$64+1-$D69)/H$65 -> 0.13888889 | I69: =MAX(0,I$64+1-$D69)/I$65 -> 0.13333333 | J69: =MAX(0,J$64+1-$D69)/J$65 -> 0.12727273 | K69: =MAX(0,K$64+1-$D69)/K$65 -> 0.12121212 | L69: =MAX(0,L$64+1-$D69)/L$65 -> 0.11538462 | ... T69: =MAX(0,T$64+1-$D69)/T$65 -> 0.080952381
D70: =D69+1 -> 5 | E70: =MAX(0,E$64+1-$D70)/E$65 -> 0.066666667 | F70: =MAX(0,F$64+1-$D70)/F$65 -> 0.095238095 | G70: =MAX(0,G$64+1-$D70)/G$65 -> 0.10714286 | H70: =MAX(0,H$64+1-$D70)/H$65 -> 0.11111111 | I70: =MAX(0,I$64+1-$D70)/I$65 -> 0.11111111 | J70: =MAX(0,J$64+1-$D70)/J$65 -> 0.10909091 | K70: =MAX(0,K$64+1-$D70)/K$65 -> 0.10606061 | L70: =MAX(0,L$64+1-$D70)/L$65 -> 0.1025641 | ... T70: =MAX(0,T$64+1-$D70)/T$65 -> 0.076190476
D71: =D70+1 -> 6 | E71: =MAX(0,E$64+1-$D71)/E$65 -> 0 | F71: =MAX(0,F$64+1-$D71)/F$65 -> 0.047619048 | G71: =MAX(0,G$64+1-$D71)/G$65 -> 0.071428571 | H71: =MAX(0,H$64+1-$D71)/H$65 -> 0.083333333 | I71: =MAX(0,I$64+1-$D71)/I$65 -> 0.088888889 | J71: =MAX(0,J$64+1-$D71)/J$65 -> 0.090909091 | K71: =MAX(0,K$64+1-$D71)/K$65 -> 0.090909091 | L71: =MAX(0,L$64+1-$D71)/L$65 -> 0.08974359 | ... T71: =MAX(0,T$64+1-$D71)/T$65 -> 0.071428571
D72: =D71+1 -> 7 | E72: =MAX(0,E$64+1-$D72)/E$65 -> 0 | F72: =MAX(0,F$64+1-$D72)/F$65 -> 0 | G72: =MAX(0,G$64+1-$D72)/G$65 -> 0.035714286 | H72: =MAX(0,H$64+1-$D72)/H$65 -> 0.055555556 | I72: =MAX(0,I$64+1-$D72)/I$65 -> 0.066666667 | J72: =MAX(0,J$64+1-$D72)/J$65 -> 0.072727273 | K72: =MAX(0,K$64+1-$D72)/K$65 -> 0.075757576 | L72: =MAX(0,L$64+1-$D72)/L$65 -> 0.076923077 | ... T72: =MAX(0,T$64+1-$D72)/T$65 -> 0.066666667
D73: =D72+1 -> 8 | E73: =MAX(0,E$64+1-$D73)/E$65 -> 0 | F73: =MAX(0,F$64+1-$D73)/F$65 -> 0 | G73: =MAX(0,G$64+1-$D73)/G$65 -> 0 | H73: =MAX(0,H$64+1-$D73)/H$65 -> 0.027777778 | I73: =MAX(0,I$64+1-$D73)/I$65 -> 0.044444444 | J73: =MAX(0,J$64+1-$D73)/J$65 -> 0.054545455 | K73: =MAX(0,K$64+1-$D73)/K$65 -> 0.060606061 | L73: =MAX(0,L$64+1-$D73)/L$65 -> 0.064102564 | ... T73: =MAX(0,T$64+1-$D73)/T$65 -> 0.061904762
D74: =D73+1 -> 9 | E74: =MAX(0,E$64+1-$D74)/E$65 -> 0 | F74: =MAX(0,F$64+1-$D74)/F$65 -> 0 | G74: =MAX(0,G$64+1-$D74)/G$65 -> 0 | H74: =MAX(0,H$64+1-$D74)/H$65 -> 0 | I74: =MAX(0,I$64+1-$D74)/I$65 -> 0.022222222 | J74: =MAX(0,J$64+1-$D74)/J$65 -> 0.036363636 | K74: =MAX(0,K$64+1-$D74)/K$65 -> 0.045454545 | L74: =MAX(0,L$64+1-$D74)/L$65 -> 0.051282051 | ... T74: =MAX(0,T$64+1-$D74)/T$65 -> 0.057142857
D75: =D74+1 -> 10 | E75: =MAX(0,E$64+1-$D75)/E$65 -> 0 | F75: =MAX(0,F$64+1-$D75)/F$65 -> 0 | G75: =MAX(0,G$64+1-$D75)/G$65 -> 0 | H75: =MAX(0,H$64+1-$D75)/H$65 -> 0 | I75: =MAX(0,I$64+1-$D75)/I$65 -> 0 | J75: =MAX(0,J$64+1-$D75)/J$65 -> 0.018181818 | K75: =MAX(0,K$64+1-$D75)/K$65 -> 0.03030303 | L75: =MAX(0,L$64+1-$D75)/L$65 -> 0.038461538 | ... T75: =MAX(0,T$64+1-$D75)/T$65 -> 0.052380952
D76: =D75+1 -> 11 | E76: =MAX(0,E$64+1-$D76)/E$65 -> 0 | F76: =MAX(0,F$64+1-$D76)/F$65 -> 0 | G76: =MAX(0,G$64+1-$D76)/G$65 -> 0 | H76: =MAX(0,H$64+1-$D76)/H$65 -> 0 | I76: =MAX(0,I$64+1-$D76)/I$65 -> 0 | J76: =MAX(0,J$64+1-$D76)/J$65 -> 0 | K76: =MAX(0,K$64+1-$D76)/K$65 -> 0.015151515 | L76: =MAX(0,L$64+1-$D76)/L$65 -> 0.025641026 | ... T76: =MAX(0,T$64+1-$D76)/T$65 -> 0.047619048
D77: =D76+1 -> 12 | E77: =MAX(0,E$64+1-$D77)/E$65 -> 0 | F77: =MAX(0,F$64+1-$D77)/F$65 -> 0 | G77: =MAX(0,G$64+1-$D77)/G$65 -> 0 | H77: =MAX(0,H$64+1-$D77)/H$65 -> 0 | I77: =MAX(0,I$64+1-$D77)/I$65 -> 0 | J77: =MAX(0,J$64+1-$D77)/J$65 -> 0 | K77: =MAX(0,K$64+1-$D77)/K$65 -> 0 | L77: =MAX(0,L$64+1-$D77)/L$65 -> 0.012820513 | ... T77: =MAX(0,T$64+1-$D77)/T$65 -> 0.042857143
D78: =D77+1 -> 13 | E78: =MAX(0,E$64+1-$D78)/E$65 -> 0 | F78: =MAX(0,F$64+1-$D78)/F$65 -> 0 | G78: =MAX(0,G$64+1-$D78)/G$65 -> 0 | H78: =MAX(0,H$64+1-$D78)/H$65 -> 0 | I78: =MAX(0,I$64+1-$D78)/I$65 -> 0 | J78: =MAX(0,J$64+1-$D78)/J$65 -> 0 | K78: =MAX(0,K$64+1-$D78)/K$65 -> 0 | L78: =MAX(0,L$64+1-$D78)/L$65 -> 0 | ... T78: =MAX(0,T$64+1-$D78)/T$65 -> 0.038095238
... D85: =D84+1 -> 20 | E85: =MAX(0,E$64+1-$D85)/E$65 -> 0 | F85: =MAX(0,F$64+1-$D85)/F$65 -> 0 | G85: =MAX(0,G$64+1-$D85)/G$65 -> 0 | H85: =MAX(0,H$64+1-$D85)/H$65 -> 0 | I85: =MAX(0,I$64+1-$D85)/I$65 -> 0 | J85: =MAX(0,J$64+1-$D85)/J$65 -> 0 | K85: =MAX(0,K$64+1-$D85)/K$65 -> 0 | L85: =MAX(0,L$64+1-$D85)/L$65 -> 0 | ... T85: =MAX(0,T$64+1-$D85)/T$65 -> 0.0047619048
B88: Explanation and example of Depreciation Methods
C89: All examples will be for an asset purchased in the year 2020 for $100.
B91: 1 | C91: =INDEX(ListDepMethods,B91) -> Declining Balance
C92: The depreciation each year is the provided % rate multiplied by the remaining asset balance.
C93: Example - rate of 30% | D93: 2020 | E93: 2021 | F93: 2022 | G93: 2023
C94: Opening Balance | D94: 0 | E94: 70 | F94: 49 | G94: 34.3
C95: New Capex | D95: 100 | E95: 0 | F95: 0 | G95: 0
C96: Depreciation | D96: -30 | E96: -21 | F96: -14.7 | G96: -10.29
C97: Closing Balance | D97: 70 | E97: 49 | F97: 34.3 | G97: 24.01
B99: 2 | C99: =INDEX(ListDepMethods,B99) -> Straight Line
C100: The asset is depreciated in an equal amount over each year of its useful life.
C101: Example - useful life of 3 years | D101: 2020 | E101: 2021 | F101: 2022 | G101: 2023
C102: Opening Balance | D102: 0 | E102: 66.666667 | F102: 33.333333 | G102: 0
C103: New Capex | D103: 100 | E103: 0 | F103: 0 | G103: 0
C104: Depreciation | D104: -33.333333 | E104: -33.333333 | F104: -33.333333 | G104: 0
C105: Closing Balance | D105: 66.666667 | E105: 33.333333 | F105: 0 | G105: 0
B107: 3 | C107: =INDEX(ListDepMethods,B107) -> Adjusted MACRS
C108: The asset is depreciated a certain % each year of its life, based on the provided table.
C109: The profile of % rates is applied to the initial cost of the asset to calculate the annual depreciation.
C110: Example - Class # 5 | D110: 2020 | E110: 2021 | F110: 2022 | G110: 2023
C111: Opening Balance | D111: 0 | E111: 60 | F111: 36 | G111: 21.6
C112: New Capex | D112: 100 | E112: 0 | F112: 0 | G112: 0
C113: Depreciation | D113: -40 | E113: -24 | F113: -14.4 | G113: -10.8
C114: Closing Balance | D114: 60 | E114: 36 | F114: 21.6 | G114: 10.8
B116: 4 | C116: =INDEX(ListDepMethods,B116) -> Sum of Years Digits
C117: The asset is depreciated a certain % each year of its life, based on the provided table.
C118: The profile of % rates is applied to the initial cost of the asset to calculate the annual depreciation.
C119: Example - useful life of 5 years | D119: 2020 | E119: 2021 | F119: 2022 | G119: 2023
C120: Opening Balance | D120: 0 | E120: 66.666667 | F120: 40 | G120: 20
C121: New Capex | D121: 100 | E121: 0 | F121: 0 | G121: 0
C122: Depreciation | D122: -33.333333 | E122: -26.666667 | F122: -20 | G122: -13.333333
C123: Closing Balance | D123: 66.666667 | E123: 40 | F123: 20 | G123: 6.6666667
A129: Capital Expenditure Assumptions
B131: Capital Expenditures
...
