Workbook
Name company: CaseData!$G$3
Name ListAssetClasses1: CaseData!$C$15:$C$17
Name ListDepMethods1: CaseData!$C$22:$C$25
Name periods: CaseData!$G$5
Name selector: Answers!$F$5
Name start_date: CaseData!$G$7
Name topic: "CFM Topic: " & CaseData!$G$4

Sheet Answers
A1: =company -> Mineral to Rock
A2: {=topic} -> CFM Topic: CAPEX and depreciation
A3: ANSWERS SCHEDULE | J3: {=EOMONTH( start_date, _xlfn.SEQUENCE( 1, periods, 0, 12 ) )} -> 44592 | K3: 44957 | L3: 45322 | M3: 45688 | N3: 46053 | O3: 46418 | P3: 46783 | Q3: 47149 | R3: 47514 | S3: 47879 | T3: 48244 | U3: 48610 | V3: 48975 | W3: 49340 | X3: 49705 | Y3: 50071 | Z3: 50436 | AA3: 50801 | AB3: 51166 | AC3: 51532 | AD3: 51897 | AE3: 52262 | AF3: 52627 | AG3: 52993 | AH3: 53358
E5: Depreciation method | F5: 1
B7: Long Term assets
E9: Long Term assets opening balance | G9: USD m | J9: {=_xlfn.DROP( _xlfn.HSTACK( 0,_xlfn.ANCHORARRAY( J12) ),, -1 )} -> 0 | K9: 2909497.5 | L9: 3074760.4 | M9: 4641580.1 | N9: 4479504.3 | O9: 5925507.4 | P9: 7266573.8 | Q9: 8060074 | R9: 7065255.4 | S9: 6111284.6 | T9: 6034858.1 | U9: 6313316.9 | V9: 6727876.9 | W9: 6352790.3 | X9: 7831386.8 | Y9: 8355807.5 | Z9: 8866503.9 | AA9: 9063715.8 | AB9: 9201930.9 | AC9: 8454862.6 | AD9: 7893035.7 | AE9: 8423089.1 | AF9: 8630777 | AG9: 8186630.4 | AH9: 8799717.1
E10: CAPEX | G10: USD m | J10: {=IF( _xlfn.DROP( TRANSPOSE( INDEX(_xlfn.ANCHORARRAY( Calculations!$E$8),, 2 ) ), , 1 ) = "", 0, _xlfn.DROP( TRANSPOSE( INDEX(_xlfn.ANCHORARRAY( Calculations!E8),, 2 ) ), , 1 ) )} -> 3393000 | K10: 672000 | L10: 2329500 | M10: 567000 | N10: 2409000 | O10: 2518500 | P10: 2092500 | Q10: 127500 | R10: 0 | S10: 856500 | T10: 1249500 | U10: 1446000 | V10: 585000 | W10: 2676000 | X10: 1798500 | Y10: 1858500 | Z10: 1566000 | AA10: 1518000 | AB10: 496500 | AC10: 577500 | AD10: 1747500 | AE10: 1449000 | AF10: 712500 | AG10: 1861500 | AH10: 2253000
E11: Depreciation | G11: USD m | J11: {=_xlfn.LET( _xlpm.depreciation_method, selector, _xlpm.declining_balance,_xlfn.ANCHORARRAY( Calculations!J65), _xlpm.straight_line,_xlfn.ANCHORARRAY( Calculations!J94), _xlpm.units_of_production,_xlfn.ANCHORARRAY( Calculations!J123), _xlpm.sum_of_digits,_xlfn.ANCHORARRAY( Calculations!J152), CHOOSE( selector, _xlpm.declining_balance, _xlpm.straight_line, _xlpm.units_of_production, _xlpm.sum_of_digits ) ) * - 1} -> -483502.5 | K11: -506737.12 | L11: -762680.31 | M11: -729075.76 | N11: -962996.9 | O11: -1177433.6 | P11: -1298999.8 | Q11: -1122318.6 | R11: -953970.81 | S11: -932926.44 | T11: -971041.22 | U11: -1031440 | V11: -960086.53 | W11: -1197403.6 | X11: -1274079.3 | Y11: -1347803.6 | Z11: -1368788.1 | AA11: -1379784.9 | AB11: -1243568.4 | AC11: -1139326.9 | AD11: -1217446.6 | AE11: -1241312.1 | AF11: -1156646.5 | AG11: -1248413.3 | AH11: -1382203.8
E12: Long Term assets closing balance | G12: USD m | J12: {=_xlfn.LET( _xlpm.opening_balance, 0, _xlpm.mouvements,_xlfn.ANCHORARRAY( J10) +_xlfn.ANCHORARRAY( J11), _xlfn.SCAN( _xlpm.opening_balance, _xlpm.mouvements, _xleta.SUM ) )} -> 2909497.5 | K12: 3074760.4 | L12: 4641580.1 | M12: 4479504.3 | N12: 5925507.4 | O12: 7266573.8 | P12: 8060074 | Q12: 7065255.4 | R12: 6111284.6 | S12: 6034858.1 | T12: 6313316.9 | U12: 6727876.9 | V12: 6352790.3 | W12: 7831386.8 | X12: 8355807.5 | Y12: 8866503.9 | Z12: 9063715.8 | AA12: 9201930.9 | AB12: 8454862.6 | AC12: 7893035.7 | AD12: 8423089.1 | AE12: 8630777 | AF12: 8186630.4 | AG12: 8799717.1 | AH12: 9670513.3
B14: Medium Term assets
E16: Medium Term assets opening balance | G16: USD m | J16: {=_xlfn.DROP( _xlfn.HSTACK( 0,_xlfn.ANCHORARRAY( J19) ),, -1 )} -> 0 | K16: 2260861.9 | L16: 2441429.2 | M16: 2752342.6 | N16: 2898868 | O16: 3021438.4 | P16: 4522986 | Q16: 3768513.5 | R16: 4293508.6 | S16: 5002732.9 | T16: 5396486.8 | U16: 7032753.5 | V16: 6111428.3 | W16: 6054947 | X16: 6143777.6 | Y16: 7045085.8 | Z16: 6002534.6 | AA16: 7550078.7 | AB16: 6646356 | AC16: 6173382.1 | AD16: 6838189.9 | AE16: 7227093.4 | AF16: 7593428.7 | AG16: 8038410.3 | AH16: 7688911.8
E17: CAPEX | G17: USD m | J17: {=IF( _xlfn.DROP( TRANSPOSE( INDEX(_xlfn.ANCHORARRAY( Calculations!$E$8),, 3 ) ), , 1 ) = "", 0, _xlfn.DROP( TRANSPOSE( INDEX(_xlfn.ANCHORARRAY( Calculations!$E$8),,3 ) ), , 1 ) )} -> 2875500 | K17: 835500 | L17: 1041000 | M17: 906000 | N17: 904500 | O17: 2680500 | P17: 202500 | Q17: 1611000 | R17: 1972500 | S17: 1746000 | T17: 3414000 | U17: 580500 | V17: 1408500 | W17: 1557000 | X17: 2593500 | Y17: 342000 | Z17: 3333000 | AA17: 610500 | AB17: 891000 | AC17: 2190000 | AD17: 1998000 | AE17: 2052000 | AF17: 2227500 | AG17: 1312500 | AH17: 2460000
E18: Depreciation | G18: USD m | J18: {=_xlfn.LET( _xlpm.depreciation_method, selector, _xlpm.declining_balance,_xlfn.ANCHORARRAY( Calculations!$J184), _xlpm.straight_line,_xlfn.ANCHORARRAY( Calculations!$J213), _xlpm.units_of_production,_xlfn.ANCHORARRAY( Calculations!$J242), _xlpm.sum_of_digits,_xlfn.ANCHORARRAY( Calculations!$J271), CHOOSE( selector, _xlpm.declining_balance, _xlpm.straight_line, _xlpm.units_of_production, _xlpm.sum_of_digits ) ) * - 1} -> -614638.12 | K18: -654932.67 | L18: -730086.57 | M18: -759474.59 | N18: -781929.68 | O18: -1178952.4 | P18: -956972.47 | Q18: -1086004.9 | R18: -1263275.7 | S18: -1352246.2 | T18: -1777733.3 | U18: -1501825.2 | V18: -1464981.4 | W18: -1468169.3 | X18: -1692191.8 | Y18: -1384551.2 | Z18: -1785455.9 | AA18: -1514222.7 | AB18: -1363973.8 | AC18: -1525192.2 | AD18: -1609096.5 | AE18: -1685664.8 | AF18: -1782518.3 | AG18: -1661998.6 | AH18: -1813873.9
E19: Medium Term assets closing balance | G19: USD m | J19: {=_xlfn.LET( _xlpm.opening_balance, 0, _xlpm.mouvements,_xlfn.ANCHORARRAY( J17) +_xlfn.ANCHORARRAY( J18), _xlfn.SCAN( _xlpm.opening_balance, _xlpm.mouvements, _xleta.SUM ) )} -> 2260861.9 | K19: 2441429.2 | L19: 2752342.6 | M19: 2898868 | N19: 3021438.4 | O19: 4522986 | P19: 3768513.5 | Q19: 4293508.6 | R19: 5002732.9 | S19: 5396486.8 | T19: 7032753.5 | U19: 6111428.3 | V19: 6054947 | W19: 6143777.6 | X19: 7045085.8 | Y19: 6002534.6 | Z19: 7550078.7 | AA19: 6646356 | AB19: 6173382.1 | AC19: 6838189.9 | AD19: 7227093.4 | AE19: 7593428.7 | AF19: 8038410.3 | AG19: 7688911.8 | AH19: 8335037.9
B21: Short Term assets
E23: Short Term assets opening balance | G23: USD m | J23: {=_xlfn.DROP( _xlfn.HSTACK( 0,_xlfn.ANCHORARRAY( J26) ),, -1 )} -> 0 | K23: 1559490 | L23: 1094194.5 | M23: 1204983.2 | N23: 2203229.5 | O23: 2087093.7 | P23: 2319802.8 | Q23: 2188131.5 | R23: 1610726.1 | S23: 1769403.1 | T23: 2588401.7 | U23: 2602973.4 | V23: 3033549.1 | W23: 2698325.8 | X23: 2705844.2 | Y23: 2960835.5 | Z23: 2432268.3 | AA23: 3265450.1 | AB23: 2940220 | AC23: 3501803.5 | AD23: 3630430.7 | AE23: 3479220.6 | AF23: 3806942.6 | AG23: 3902897.2 | AH23: 3473800.9
E24: CAPEX | G24: USD m | J24: {=IF( _xlfn.DROP( TRANSPOSE( INDEX(_xlfn.ANCHORARRAY( Calculations!$E$8),, 4 ) ), , 1 ) = "", 0, _xlfn.DROP( TRANSPOSE( INDEX(_xlfn.ANCHORARRAY( Calculations!$E$8),, 4 ) ), , 1 ) )} -> 2724000 | K24: 306000 | L24: 934500 | M24: 2535000 | N24: 1273500 | O24: 1741500 | P24: 1219500 | Q24: 289500 | R24: 1110000 | S24: 2344500 | T24: 1491000 | U24: 2170500 | V24: 1086000 | W24: 1378500 | X24: 1762500 | Y24: 525000 | Z24: 2467500 | AA24: 1002000 | AB24: 2256000 | AC24: 1852500 | AD24: 1392000 | AE24: 2055000 | AF24: 1827000 | AG24: 913500 | AH24: 1356000
E25: Depreciation | G25: USD m | J25: {=_xlfn.LET( _xlpm.depreciation_method, selector, _xlpm.declining_balance,_xlfn.ANCHORARRAY( Calculations!J303), _xlpm.straight_line,_xlfn.ANCHORARRAY( Calculations!J332), _xlpm.units_of_production,_xlfn.ANCHORARRAY( Calculations!J361), _xlpm.sum_of_digits,_xlfn.ANCHORARRAY( Calculations!J390), CHOOSE( selector, _xlpm.declining_balance, _xlpm.straight_line, _xlpm.units_of_production, _xlpm.sum_of_digits ) ) * - 1} -> -1164510 | K25: -771295.5 | L25: -823711.28 | M25: -1536753.7 | N25: -1389635.8 | O25: -1508790.9 | P25: -1351171.3 | Q25: -866905.44 | R25: -951322.99 | S25: -1525501.4 | T25: -1476428.3 | U25: -1739924.3 | V25: -1421223.4 | W25: -1370981.6 | X25: -1507508.6 | Y25: -1053567.2 | Z25: -1634318.2 | AA25: -1327230 | AB25: -1694416.5 | AC25: -1723872.8 | AD25: -1543210.1 | AE25: -1727278 | AF25: -1731045.4 | AG25: -1342596.2 | AH25: -1318117.9
E26: Short Term assets closing balance | G26: USD m | J26: {=_xlfn.LET( _xlpm.opening_balance, 0, _xlpm.mouvements,_xlfn.ANCHORARRAY( J24) +_xlfn.ANCHORARRAY( J25), _xlfn.SCAN( _xlpm.opening_balance, _xlpm.mouvements, _xleta.SUM ) )} -> 1559490 | K26: 1094194.5 | L26: 1204983.2 | M26: 2203229.5 | N26: 2087093.7 | O26: 2319802.8 | P26: 2188131.5 | Q26: 1610726.1 | R26: 1769403.1 | S26: 2588401.7 | T26: 2602973.4 | U26: 3033549.1 | V26: 2698325.8 | W26: 2705844.2 | X26: 2960835.5 | Y26: 2432268.3 | Z26: 3265450.1 | AA26: 2940220 | AB26: 3501803.5 | AC26: 3630430.7 | AD26: 3479220.6 | AE26: 3806942.6 | AF26: 3902897.2 | AG26: 3473800.9 | AH26: 3511683
B28: Assets Schedule
E30: Assets opening balance | G30: USD m | J30: {=_xlfn.ANCHORARRAY( J9) +_xlfn.ANCHORARRAY( J16) +_xlfn.ANCHORARRAY( J23)} -> 0 | K30: 6729849.4 | L30: 6610384.1 | M30: 8598905.9 | N30: 9581601.9 | O30: 11034040 | P30: 14109363 | Q30: 14016719 | R30: 12969490 | S30: 12883421 | T30: 14019747 | U30: 15949044 | V30: 15872854 | W30: 15106063 | X30: 16681009 | Y30: 18361729 | Z30: 17301307 | AA30: 19879245 | AB30: 18788507 | AC30: 18130048 | AD30: 18361656 | AE30: 19129403 | AF30: 20031148 | AG30: 20127938 | AH30: 19962430
E31: CAPEX | G31: USD m | J31: {=_xlfn.ANCHORARRAY( J10) +_xlfn.ANCHORARRAY( J17) +_xlfn.ANCHORARRAY( J24)} -> 8992500 | K31: 1813500 | L31: 4305000 | M31: 4008000 | N31: 4587000 | O31: 6940500 | P31: 3514500 | Q31: 2028000 | R31: 3082500 | S31: 4947000 | T31: 6154500 | U31: 4197000 | V31: 3079500 | W31: 5611500 | X31: 6154500 | Y31: 2725500 | Z31: 7366500 | AA31: 3130500 | AB31: 3643500 | AC31: 4620000 | AD31: 5137500 | AE31: 5556000 | AF31: 4767000 | AG31: 4087500 | AH31: 6069000
E32: Depreciation | G32: USD m | J32: {=_xlfn.ANCHORARRAY( J11) +_xlfn.ANCHORARRAY( J18) +_xlfn.ANCHORARRAY( J25)} -> -2262650.6 | K32: -1932965.3 | L32: -2316478.2 | M32: -3025304.1 | N32: -3134562.4 | O32: -3865176.9 | P32: -3607143.6 | Q32: -3075229 | R32: -3168569.5 | S32: -3810674 | T32: -4225202.8 | U32: -4273189.5 | V32: -3846291.3 | W32: -4036554.5 | X32: -4473779.7 | Y32: -3785922.1 | Z32: -4788562.2 | AA32: -4221237.6 | AB32: -4301958.8 | AC32: -4388391.9 | AD32: -4369753.1 | AE32: -4654254.9 | AF32: -4670210.3 | AG32: -4253008.1 | AH32: -4514195.6
E33: Assets closing balance | G33: USD m | J33: {=_xlfn.BYCOL(_xlfn.ANCHORARRAY( J30) +_xlfn.ANCHORARRAY( J31) +_xlfn.ANCHORARRAY( J32), _xleta.SUM )} -> 6729849.4 | K33: 6610384.1 | L33: 8598905.9 | M33: 9581601.9 | N33: 11034040 | O33: 14109363 | P33: 14016719 | Q33: 12969490 | R33: 12883421 | S33: 14019747 | T33: 15949044 | U33: 15872854 | V33: 15106063 | W33: 16681009 | X33: 18361729 | Y33: 17301307 | Z33: 19879245 | AA33: 18788507 | AB33: 18130048 | AC33: 18361656 | AD33: 19129403 | AE33: 20031148 | AF33: 20127938 | AG33: 19962430 | AH33: 21517234
B35: Tax deduction
E37: Depreciation | G37: USD m | J37: {=_xlfn.ANCHORARRAY( J32) * -1} -> 2262650.6 | K37: 1932965.3 | L37: 2316478.2 | M37: 3025304.1 | N37: 3134562.4 | O37: 3865176.9 | P37: 3607143.6 | Q37: 3075229 | R37: 3168569.5 | S37: 3810674 | T37: 4225202.8 | U37: 4273189.5 | V37: 3846291.3 | W37: 4036554.5 | X37: 4473779.7 | Y37: 3785922.1 | Z37: 4788562.2 | AA37: 4221237.6 | AB37: 4301958.8 | AC37: 4388391.9 | AD37: 4369753.1 | AE37: 4654254.9 | AF37: 4670210.3 | AG37: 4253008.1 | AH37: 4514195.6
E38: Tax deduction | G38: USD m | J38: {=_xlfn.LET( _xlpm.tax_rate, CaseData!$G$8, _xlpm.depreciation,_xlfn.ANCHORARRAY( Answers!$J$37), _xlpm.depreciation * _xlpm.tax_rate )} -> 565662.66 | K38: 483241.32 | L38: 579119.54 | M38: 756326.01 | N38: 783640.59 | O38: 966294.23 | P38: 901785.89 | Q38: 768807.24 | R38: 792142.37 | S38: 952668.5 | T38: 1056300.7 | U38: 1068297.4 | V38: 961572.82 | W38: 1009138.6 | X38: 1118444.9 | Y38: 946480.51 | Z38: 1197140.6 | AA38: 1055309.4 | AB38: 1075489.7 | AC38: 1097098 | AD38: 1092438.3 | AE38: 1163563.7 | AF38: 1167552.6 | AG38: 1063252 | AH38: 1128548.9
E40: NPV | G40: USD m | H40: =_xlfn.LET( _xlpm.discount_rate, CaseData!$G$9, _xlpm.tax_deduction,_xlfn.ANCHORARRAY( Answers!J38), NPV( _xlpm.discount_rate, _xlpm.tax_deduction ) ) -> 7549234.7
E41: XNPV | G41: USD m | H41: =_xlfn.LET( _xlpm.discount_rate, CaseData!$G$9, _xlpm.tax_deduction,_xlfn.ANCHORARRAY( Answers!J38), XNPV( _xlpm.discount_rate, _xlpm.tax_deduction,_xlfn.ANCHORARRAY( J3) ) ) -> 8299633.5
J43: NPV | K43: XNPV
H44: Declining Balance | J44: =_xlfn.LET( _xlpm.discount_rate, CaseData!$G$9, _xlpm.tax_deduction,_xlfn.ANCHORARRAY( Answers!J38), NPV( _xlpm.discount_rate, _xlpm.tax_deduction ) ) -> 7549234.7 | K44: =H41 -> 8299633.5
H45: {=ListDepMethods1} -> Declining Balance | I45: 1 | J45: 7549234.7 | K45: 8299633.5
H46: Straight Line | I46: 2 | J46: 6602901 | K46: 7258752.7
H47: Units of Production | I47: 3 | J47: 7445364 | K47: 8185326.5
H48: Sum of Years Digits | I48: 4 | J48: 7602001.9 | K48: 8357542.9

Sheet Calculations
A1: =company -> Mineral to Rock
A2: {=topic} -> CFM Topic: CAPEX and depreciation
A3: CALCULATION SCHEDULE | J3: {=EOMONTH( start_date, _xlfn.SEQUENCE( 1, periods, 0, 12 ) )} -> 44592 | K3: 44957 | L3: 45322 | M3: 45688 | N3: 46053 | O3: 46418 | P3: 46783 | Q3: 47149 | R3: 47514 | S3: 47879 | T3: 48244 | U3: 48610 | V3: 48975 | W3: 49340 | X3: 49705 | Y3: 50071 | Z3: 50436 | AA3: 50801 | AB3: 51166 | AC3: 51532 | AD3: 51897 | AE3: 52262 | AF3: 52627 | AG3: 52993 | AH3: 53358
B5: CAPEX
D7: Capital investments | K7: Salvage value
E8: {=_xlfn.PIVOTBY( YEAR( CaseData!$D$138:$D$437 ), CaseData!$F$138:$F$437, CaseData!$E$138:$E$437, _xleta.SUM,,0,,0 )} | F8: Long Term | G8: Medium Term | H8: Short Term | K8: {=_xlfn.LET( _xlpm.capex, _xlfn.DROP( _xlfn.CHOOSECOLS(_xlfn.ANCHORARRAY(E8), {2,3,4} ), 1 ), _xlpm.years, _xlfn.DROP( INDEX(_xlfn.ANCHORARRAY( E8),, 1 ), 1 ), _xlpm.residual_rate, CaseData!$G$11, IFERROR( _xlfn.VSTACK( _xlfn.HSTACK("", "Long Term", "Medium Term", "Short Term" ), _xlfn.HSTACK( _xlpm.years, _xlpm.capex * _xlpm.residual_rate ) ), 0 ) )} | L8: Long Term | M8: Medium Term | N8: Short Term
E9: 2022 | F9: 3393000 | G9: 2875500 | H9: 2724000 | K9: 2022 | L9: 169650 | M9: 143775 | N9: 136200
E10: 2023 | F10: 672000 | G10: 835500 | H10: 306000 | K10: 2023 | L10: 33600 | M10: 41775 | N10: 15300
E11: 2024 | F11: 2329500 | G11: 1041000 | H11: 934500 | K11: 2024 | L11: 116475 | M11: 52050 | N11: 46725
E12: 2025 | F12: 567000 | G12: 906000 | H12: 2535000 | K12: 2025 | L12: 28350 | M12: 45300 | N12: 126750
E13: 2026 | F13: 2409000 | G13: 904500 | H13: 1273500 | K13: 2026 | L13: 120450 | M13: 45225 | N13: 63675
E14: 2027 | F14: 2518500 | G14: 2680500 | H14: 1741500 | K14: 2027 | L14: 125925 | M14: 134025 | N14: 87075
E15: 2028 | F15: 2092500 | G15: 202500 | H15: 1219500 | K15: 2028 | L15: 104625 | M15: 10125 | N15: 60975
E16: 2029 | F16: 127500 | G16: 1611000 | H16: 289500 | K16: 2029 | L16: 6375 | M16: 80550 | N16: 14475
E17: 2030 | G17: 1972500 | H17: 1110000 | K17: 2030 | L17: 0 | M17: 98625 | N17: 55500
E18: 2031 | F18: 856500 | G18: 1746000 | H18: 2344500 | K18: 2031 | L18: 42825 | M18: 87300 | N18: 117225
E19: 2032 | F19: 1249500 | G19: 3414000 | H19: 1491000 | K19: 2032 | L19: 62475 | M19: 170700 | N19: 74550
E20: 2033 | F20: 1446000 | G20: 580500 | H20: 2170500 | K20: 2033 | L20: 72300 | M20: 29025 | N20: 108525
E21: 2034 | F21: 585000 | G21: 1408500 | H21: 1086000 | K21: 2034 | L21: 29250 | M21: 70425 | N21: 54300
E22: 2035 | F22: 2676000 | G22: 1557000 | H22: 1378500 | K22: 2035 | L22: 133800 | M22: 77850 | N22: 68925
E23: 2036 | F23: 1798500 | G23: 2593500 | H23: 1762500 | K23: 2036 | L23: 89925 | M23: 129675 | N23: 88125
E24: 2037 | F24: 1858500 | G24: 342000 | H24: 525000 | K24: 2037 | L24: 92925 | M24: 17100 | N24: 26250
E25: 2038 | F25: 1566000 | G25: 3333000 | H25: 2467500 | K25: 2038 | L25: 78300 | M25: 166650 | N25: 123375
E26: 2039 | F26: 1518000 | G26: 610500 | H26: 1002000 | K26: 2039 | L26: 75900 | M26: 30525 | N26: 50100
E27: 2040 | F27: 496500 | G27: 891000 | H27: 2256000 | K27: 2040 | L27: 24825 | M27: 44550 | N27: 112800
E28: 2041 | F28: 577500 | G28: 2190000 | H28: 1852500 | K28: 2041 | L28: 28875 | M28: 109500 | N28: 92625
E29: 2042 | F29: 1747500 | G29: 1998000 | H29: 1392000 | K29: 2042 | L29: 87375 | M29: 99900 | N29: 69600
... E33: 2046 | F33: 2253000 | G33: 2460000 | H33: 1356000 | K33: 2046 | L33: 112650 | M33: 123000 | N33: 67800
B36: Long Term assets
C38: Declining balance
F39: Date | G39: Cost | J39: {=_xlfn.ANCHORARRAY(J3)} -> 44592 | K39: 44957 | L39: 45322 | M39: 45688 | N39: 46053 | O39: 46418 | P39: 46783 | Q39: 47149 | R39: 47514 | S39: 47879 | T39: 48244 | U39: 48610 | V39: 48975 | W39: 49340 | X39: 49705 | Y39: 50071 | Z39: 50436 | AA39: 50801 | AB39: 51166 | AC39: 51532 | AD39: 51897 | AE39: 52262 | AF39: 52627 | AG39: 52993 | AH39: 53358
F40: {=_xlfn.LET( _xlpm.date, INDEX(_xlfn.ANCHORARRAY( $E$8),, 1 ), _xlpm.asset, INDEX(_xlfn.ANCHORARRAY( $E$8),, 2 ), _xlfn.DROP( _xlfn.HSTACK( _xlpm.date, _xlpm.asset ), 1 ) )} -> 2022 | G40: 3393000 | H40: {=_xlfn.BYROW(_xlfn.ANCHORARRAY( J40), _xleta.SUM )} -> 3167915.4 | J40: {=_xlfn.LET( _xlpm.acquisition_date, INDEX(_xlfn.ANCHORARRAY( $F40),,1 ), _xlpm.acquisition_cost, INDEX(_xlfn.ANCHORARRAY( $F40),,2 ), _xlpm.current_date,_xlfn.ANCHORARRAY( J3), _xlpm.salvage_value, CaseData!$G$11, _xlpm.depreciable_amount, _xlpm.acquisition_cost * ( 1 - _xlpm.salvage_value ), _xlpm.depreciation_rate, CaseData!$I$32, _xlpm.period, YEAR( _xlpm.current_date ) - _xlpm.acquisition_date, _xlpm.book_value, _xlpm.depreciable_amount * ( 1 - _xlpm.depreciation_rate ) ^ _xlpm.period, _xlpm.depreciation, _xlpm.depreciation_rate * _xlpm.book_value, IFERROR( IF( _xlpm.period < 0, 0, IF( _xlpm.period >= 0, _xlpm.depreciation, 0 ) ), 0 ) )} -> 483502.5 | K40: 410977.12 | L40: 349330.56 | M40: 296930.97 | N40: 252391.33 | O40: 214532.63 | P40: 182352.73 | Q40: 154999.82 | R40: 131749.85 | S40: 111987.37 | T40: 95189.267 | U40: 80910.877 | V40: 68774.245 | W40: 58458.108 | X40: 49689.392 | Y40: 42235.983 | Z40: 35900.586 | AA40: 30515.498 | AB40: 25938.173 | AC40: 22047.447 | AD40: 18740.33 | AE40: 15929.281 | AF40: 13539.889 | AG40: 11508.905 | AH40: 9782.5695
F41: 2023 | G41: 672000 | H41: 625483.43 | J41: 0 | K41: 95760 | L41: 81396 | M41: 69186.6 | N41: 58808.61 | O41: 49987.318 | P41: 42489.221 | Q41: 36115.838 | R41: 30698.462 | S41: 26093.693 | T41: 22179.639 | U41: 18852.693 | V41: 16024.789 | W41: 13621.071 | X41: 11577.91 | Y41: 9841.2236 | Z41: 8365.04 | AA41: 7110.284 | AB41: 6043.7414 | AC41: 5137.1802 | AD41: 4366.6032 | AE41: 3711.6127 | AF41: 3154.8708 | AG41: 2681.6402 | AH41: 2279.3941
F42: 2024 | G42: 2329500 | H42: 2160347.9 | J42: 0 | K42: 0 | L42: 331953.75 | M42: 282160.69 | N42: 239836.58 | O42: 203861.1 | P42: 173281.93 | Q42: 147289.64 | R42: 125196.2 | S42: 106416.77 | T42: 90454.252 | U42: 76886.114 | V42: 65353.197 | W42: 55550.217 | X42: 47217.685 | Y42: 40135.032 | Z42: 34114.777 | AA42: 28997.561 | AB42: 24647.927 | AC42: 20950.738 | AD42: 17808.127 | AE42: 15136.908 | AF42: 12866.372 | AG42: 10936.416 | AH42: 9295.9535
F43: 2025 | G43: 567000 | H43: 523565.77 | J43: 0 | K43: 0 | L43: 0 | M43: 80797.5 | N43: 68677.875 | O43: 58376.194 | P43: 49619.765 | Q43: 42176.8 | R43: 35850.28 | S43: 30472.738 | T43: 25901.827 | U43: 22016.553 | V43: 18714.07 | W43: 15906.96 | X43: 13520.916 | Y43: 11492.778 | Z43: 9768.8616 | AA43: 8303.5324 | AB43: 7058.0025 | AC43: 5999.3021 | AD43: 5099.4068 | AE43: 4334.4958 | AF43: 3684.3214 | AG43: 3131.6732 | AH43: 2661.9222
F44: 2026 | G44: 2409000 | H44: 2213152.3 | J44: 0 | K44: 0 | L44: 0 | M44: 0 | N44: 343282.5 | O44: 291790.12 | P44: 248021.61 | Q44: 210818.37 | R44: 179195.61 | S44: 152316.27 | T44: 129468.83 | U44: 110048.5 | V44: 93541.229 | W44: 79510.044 | X44: 67583.538 | Y44: 57446.007 | Z44: 48829.106 | AA44: 41504.74 | AB44: 35279.029 | AC44: 29987.175 | AD44: 25489.099 | AE44: 21665.734 | AF44: 18415.874 | AG44: 15653.493 | AH44: 13305.469
F45: 2027 | G45: 2518500 | H45: 2299839.9 | J45: 0 | K45: 0 | L45: 0 | M45: 0 | N45: 0 | O45: 358886.25 | P45: 305053.31 | Q45: 259295.32 | R45: 220401.02 | S45: 187340.87 | T45: 159239.74 | U45: 135353.78 | V45: 115050.71 | W45: 97793.103 | X45: 83124.137 | Y45: 70655.517 | Z45: 60057.189 | AA45: 51048.611 | AB45: 43391.319 | AC45: 36882.621 | AD45: 31350.228 | AE45: 26647.694 | AF45: 22650.54 | AG45: 19252.959 | AH45: 16365.015
F46: 2028 | G46: 2092500 | H46: 1897229 | J46: 0 | K46: 0 | L46: 0 | M46: 0 | N46: 0 | O46: 0 | P46: 298181.25 | Q46: 253454.06 | R46: 215435.95 | S46: 183120.56 | T46: 155652.48 | U46: 132304.6 | V46: 112458.91 | W46: 95590.077 | X46: 81251.565 | Y46: 69063.831 | Z46: 58704.256 | AA46: 49898.618 | AB46: 42413.825 | AC46: 36051.751 | AD46: 30643.989 | AE46: 26047.39 | AF46: 22140.282 | AG46: 18819.239 | AH46: 15996.354
F47: 2029 | G47: 127500 | H47: 114627.08 | J47: 0 | K47: 0 | L47: 0 | M47: 0 | N47: 0 | O47: 0 | P47: 0 | Q47: 18168.75 | R47: 15443.438 | S47: 13126.922 | T47: 11157.884 | U47: 9484.2011 | V47: 8061.5709 | W47: 6852.3353 | X47: 5824.485 | Y47: 4950.8122 | Z47: 4208.1904 | AA47: 3576.9618 | AB47: 3040.4176 | AC47: 2584.3549 | AD47: 2196.7017 | AE47: 1867.1964 | AF47: 1587.117 | AG47: 1349.0494 | AH47: 1146.692
F48: 2030 | H48: 0 | J48: 0 | K48: 0 | L48: 0 | M48: 0 | N48: 0 | O48: 0 | P48: 0 | Q48: 0 | R48: 0 | S48: 0 | T48: 0 | U48: 0 | V48: 0 | W48: 0 | X48: 0 | Y48: 0 | Z48: 0 | AA48: 0 | AB48: 0 | AC48: 0 | AD48: 0 | AE48: 0 | AF48: 0 | AG48: 0 | AH48: 0
F49: 2031 | G49: 856500 | H49: 753258.75 | J49: 0 | K49: 0 | L49: 0 | M49: 0 | N49: 0 | O49: 0 | P49: 0 | Q49: 0 | R49: 0 | S49: 122051.25 | T49: 103743.56 | U49: 88182.028 | V49: 74954.724 | W49: 63711.515 | X49: 54154.788 | Y49: 46031.57 | Z49: 39126.834 | AA49: 33257.809 | AB49: 28269.138 | AC49: 24028.767 | AD49: 20424.452 | AE49: 17360.784 | AF49: 14756.667 | AG49: 12543.167 | AH49: 10661.692
F50: 2032 | G50: 1249500 | H50: 1083333.4 | J50: 0 | K50: 0 | L50: 0 | M50: 0 | N50: 0 | O50: 0 | P50: 0 | Q50: 0 | R50: 0 | S50: 0 | T50: 178053.75 | U50: 151345.69 | V50: 128643.83 | W50: 109347.26 | X50: 92945.17 | Y50: 79003.395 | Z50: 67152.886 | AA50: 57079.953 | AB50: 48517.96 | AC50: 41240.266 | AD50: 35054.226 | AE50: 29796.092 | AF50: 25326.678 | AG50: 21527.677 | AH50: 18298.525
F51: 2033 | G51: 1446000 | H51: 1232525.3 | J51: 0 | K51: 0 | L51: 0 | M51: 0 | N51: 0 | O51: 0 | P51: 0 | Q51: 0 | R51: 0 | S51: 0 | T51: 0 | U51: 206055 | V51: 175146.75 | W51: 148874.74 | X51: 126543.53 | Y51: 107562 | Z51: 91427.698 | AA51: 77713.543 | AB51: 66056.512 | AC51: 56148.035 | AD51: 47725.83 | AE51: 40566.955 | AF51: 34481.912 | AG51: 29309.625 | AH51: 24913.181
F52: 2034 | G52: 585000 | H52: 488556.77 | J52: 0 | K52: 0 | L52: 0 | M52: 0 | N52: 0 | O52: 0 | P52: 0 | Q52: 0 | R52: 0 | S52: 0 | T52: 0 | U52: 0 | V52: 83362.5 | W52: 70858.125 | X52: 60229.406 | Y52: 51194.995 | Z52: 43515.746 | AA52: 36988.384 | AB52: 31440.126 | AC52: 26724.108 | AD52: 22715.491 | AE52: 19308.168 | AF52: 16411.943 | AG52: 13950.151 | AH52: 11857.628
F53: 2035 | G53: 2676000 | H53: 2180593 | J53: 0 | K53: 0 | L53: 0 | M53: 0 | N53: 0 | O53: 0 | P53: 0 | Q53: 0 | R53: 0 | S53: 0 | T53: 0 | U53: 0 | V53: 0 | W53: 381330 | X53: 324130.5 | Y53: 275510.92 | Z53: 234184.29 | AA53: 199056.64 | AB53: 169198.15 | AC53: 143818.42 | AD53: 122245.66 | AE53: 103908.81 | AF53: 88322.49 | AG53: 75074.117 | AH53: 63812.999
F54: 2036 | G54: 1798500 | H54: 1422656.5 | J54: 0 | K54: 0 | L54: 0 | M54: 0 | N54: 0 | O54: 0 | P54: 0 | Q54: 0 | R54: 0 | S54: 0 | T54: 0 | U54: 0 | V54: 0 | W54: 0 | X54: 256286.25 | Y54: 217843.31 | Z54: 185166.82 | AA54: 157391.79 | AB54: 133783.02 | AC54: 113715.57 | AD54: 96658.235 | AE54: 82159.5 | AF54: 69835.575 | AG54: 59360.239 | AH54: 50456.203
F55: 2037 | G55: 1858500 | H55: 1417978.5 | J55: 0 | K55: 0 | L55: 0 | M55: 0 | N55: 0 | O55: 0 | P55: 0 | Q55: 0 | R55: 0 | S55: 0 | T55: 0 | U55: 0 | V55: 0 | W55: 0 | X55: 0 | Y55: 264836.25 | Z55: 225110.81 | AA55: 191344.19 | AB55: 162642.56 | AC55: 138246.18 | AD55: 117509.25 | AE55: 99882.863 | AF55: 84900.434 | AG55: 72165.369 | AH55: 61340.563
F56: 2038 | G56: 1566000 | H56: 1143123.5 | J56: 0 | K56: 0 | L56: 0 | M56: 0 | N56: 0 | O56: 0 | P56: 0 | Q56: 0 | R56: 0 | S56: 0 | T56: 0 | U56: 0 | V56: 0 | W56: 0 | X56: 0 | Y56: 0 | Z56: 223155 | AA56: 189681.75 | AB56: 161229.49 | AC56: 137045.06 | AD56: 116488.3 | AE56: 99015.059 | AF56: 84162.8 | AG56: 71538.38 | AH56: 60807.623
F57: 2039 | G57: 1518000 | H57: 1049141.4 | J57: 0 | K57: 0 | L57: 0 | M57: 0 | N57: 0 | O57: 0 | P57: 0 | Q57: 0 | R57: 0 | S57: 0 | T57: 0 | U57: 0 | V57: 0 | W57: 0 | X57: 0 | Y57: 0 | Z57: 0 | AA57: 216315 | AB57: 183867.75 | AC57: 156287.59 | AD57: 132844.45 | AE57: 112917.78 | AF57: 95980.115 | AG57: 81583.097 | AH57: 69345.633
F58: 2040 | G58: 496500 | H58: 320466.8 | J58: 0 | K58: 0 | L58: 0 | M58: 0 | N58: 0 | O58: 0 | P58: 0 | Q58: 0 | R58: 0 | S58: 0 | T58: 0 | U58: 0 | V58: 0 | W58: 0 | X58: 0 | Y58: 0 | Z58: 0 | AA58: 0 | AB58: 70751.25 | AC58: 60138.562 | AD58: 51117.778 | AE58: 43450.111 | AF58: 36932.595 | AG58: 31392.705 | AH58: 26683.8
F59: 2041 | G59: 577500 | H59: 341711.35 | J59: 0 | K59: 0 | L59: 0 | M59: 0 | N59: 0 | O59: 0 | P59: 0 | Q59: 0 | R59: 0 | S59: 0 | T59: 0 | U59: 0 | V59: 0 | W59: 0 | X59: 0 | Y59: 0 | Z59: 0 | AA59: 0 | AB59: 0 | AC59: 82293.75 | AD59: 69949.688 | AE59: 59457.234 | AF59: 50538.649 | AG59: 42957.852 | AH59: 36514.174
F60: 2042 | G60: 1747500 | H60: 923518.72 | J60: 0 | K60: 0 | L60: 0 | M60: 0 | N60: 0 | O60: 0 | P60: 0 | Q60: 0 | R60: 0 | S60: 0 | T60: 0 | U60: 0 | V60: 0 | W60: 0 | X60: 0 | Y60: 0 | Z60: 0 | AA60: 0 | AB60: 0 | AC60: 0 | AD60: 249018.75 | AE60: 211665.94 | AF60: 179916.05 | AG60: 152928.64 | AH60: 129989.34
... F64: 2046 | G64: 2253000 | H64: 321052.5 | J64: 0 | K64: 0 | L64: 0 | M64: 0 | N64: 0 | O64: 0 | P64: 0 | Q64: 0 | R64: 0 | S64: 0 | T64: 0 | U64: 0 | V64: 0 | W64: 0 | X64: 0 | Y64: 0 | Z64: 0 | AA64: 0 | AB64: 0 | AC64: 0 | AD64: 0 | AE64: 0 | AF64: 0 | AG64: 0 | AH64: 321052.5
J65: {=_xlfn.BYCOL(_xlfn.ANCHORARRAY( J40), _xleta.SUM )} -> 483502.5 | K65: 506737.12 | L65: 762680.31 | M65: 729075.76 | N65: 962996.9 | O65: 1177433.6 | P65: 1298999.8 | Q65: 1122318.6 | R65: 953970.81 | S65: 932926.44 | T65: 971041.22 | U65: 1031440 | V65: 960086.53 | W65: 1197403.6 | X65: 1274079.3 | Y65: 1347803.6 | Z65: 1368788.1 | AA65: 1379784.9 | AB65: 1243568.4 | AC65: 1139326.9 | AD65: 1217446.6 | AE65: 1241312.1 | AF65: 1156646.5 | AG65: 1248413.3 | AH65: 1382203.8
C67: Straight line
F68: Date | G68: Cost | J68: {=_xlfn.ANCHORARRAY(J3)} -> 44592 | K68: 44957 | L68: 45322 | M68: 45688 | N68: 46053 | O68: 46418 | P68: 46783 | Q68: 47149 | R68: 47514 | S68: 47879 | T68: 48244 | U68: 48610 | V68: 48975 | W68: 49340 | X68: 49705 | Y68: 50071 | Z68: 50436 | AA68: 50801 | AB68: 51166 | AC68: 51532 | AD68: 51897 | AE68: 52262 | AF68: 52627 | AG68: 52993 | AH68: 53358
F69: {=_xlfn.LET( _xlpm.date, INDEX(_xlfn.ANCHORARRAY( $E$8),, 1 ), _xlpm.asset, INDEX(_xlfn.ANCHORARRAY( $E$8),, 2 ), _xlfn.DROP( _xlfn.HSTACK( _xlpm.date, _xlpm.asset ), 1 ) )} -> 2022 | G69: 3393000 | H69: {=_xlfn.BYROW(_xlfn.ANCHORARRAY( J69), _xleta.SUM )} -> 3223350 | J69: {=_xlfn.LET( _xlpm.acquisition_date, INDEX(_xlfn.ANCHORARRAY( $F69),,1 ), _xlpm.acquisition_cost, INDEX(_xlfn.ANCHORARRAY( $F69),,2 ), _xlpm.current_date,_xlfn.ANCHORARRAY( J3), _xlpm.salvage_value, CaseData!$G$11, _xlpm.depreciable_amount, _xlpm.acquisition_cost * ( 1 - _xlpm.salvage_value ), _xlpm.useful_life, CaseData!$I$33, _xlpm.period, YEAR( _xlpm.current_date ) - _xlpm.acquisition_date, _xlpm.depreciation, _xlpm.depreciable_amount / _xlpm.useful_life, _xlpm.accumulated_depr, _xlpm.depreciation * ( _xlpm.period ), _xlpm.book_value, _xlpm.depreciable_amount - _xlpm.accumulated_depr, IFERROR( IF( _xlpm.period < 0, 0, IF( _xlpm.period < _xlpm.useful_life, _xlpm.depreciation, IF( _xlpm.book_value > 0, _xlpm.book_value, 0 ) ) ), 0 ) )} -> 214890 | K69: 214890 | L69: 214890 | M69: 214890 | N69: 214890 | O69: 214890 | P69: 214890 | Q69: 214890 | R69: 214890 | S69: 214890 | T69: 214890 | U69: 214890 | V69: 214890 | W69: 214890 | X69: 214890 | Y69: 0 | Z69: 0 | AA69: 0 | AB69: 0 | AC69: 0 | AD69: 0 | AE69: 0 | AF69: 0 | AG69: 0 | AH69: 0
F70: 2023 | G70: 672000 | H70: 638400 | J70: 0 | K70: 42560 | L70: 42560 | M70: 42560 | N70: 42560 | O70: 42560 | P70: 42560 | Q70: 42560 | R70: 42560 | S70: 42560 | T70: 42560 | U70: 42560 | V70: 42560 | W70: 42560 | X70: 42560 | Y70: 42560 | Z70: 0 | AA70: 0 | AB70: 0 | AC70: 0 | AD70: 0 | AE70: 0 | AF70: 0 | AG70: 0 | AH70: 0
F71: 2024 | G71: 2329500 | H71: 2213025 | J71: 0 | K71: 0 | L71: 147535 | M71: 147535 | N71: 147535 | O71: 147535 | P71: 147535 | Q71: 147535 | R71: 147535 | S71: 147535 | T71: 147535 | U71: 147535 | V71: 147535 | W71: 147535 | X71: 147535 | Y71: 147535 | Z71: 147535 | AA71: 0 | AB71: 0 | AC71: 0 | AD71: 0 | AE71: 0 | AF71: 0 | AG71: 0 | AH71: 0
F72: 2025 | G72: 567000 | H72: 538650 | J72: 0 | K72: 0 | L72: 0 | M72: 35910 | N72: 35910 | O72: 35910 | P72: 35910 | Q72: 35910 | R72: 35910 | S72: 35910 | T72: 35910 | U72: 35910 | V72: 35910 | W72: 35910 | X72: 35910 | Y72: 35910 | Z72: 35910 | AA72: 35910 | AB72: 0 | AC72: 0 | AD72: 0 | AE72: 0 | AF72: 0 | AG72: 0 | AH72: 0
F73: 2026 | G73: 2409000 | H73: 2288550 | J73: 0 | K73: 0 | L73: 0 | M73: 0 | N73: 152570 | O73: 152570 | P73: 152570 | Q73: 152570 | R73: 152570 | S73: 152570 | T73: 152570 | U73: 152570 | V73: 152570 | W73: 152570 | X73: 152570 | Y73: 152570 | Z73: 152570 | AA73: 152570 | AB73: 152570 | AC73: 0 | AD73: 0 | AE73: 0 | AF73: 0 | AG73: 0 | AH73: 0
F74: 2027 | G74: 2518500 | H74: 2392575 | J74: 0 | K74: 0 | L74: 0 | M74: 0 | N74: 0 | O74: 159505 | P74: 159505 | Q74: 159505 | R74: 159505 | S74: 159505 | T74: 159505 | U74: 159505 | V74: 159505 | W74: 159505 | X74: 159505 | Y74: 159505 | Z74: 159505 | AA74: 159505 | AB74: 159505 | AC74: 159505 | AD74: 0 | AE74: 0 | AF74: 0 | AG74: 0 | AH74: 0
F75: 2028 | G75: 2092500 | H75: 1987875 | J75: 0 | K75: 0 | L75: 0 | M75: 0 | N75: 0 | O75: 0 | P75: 132525 | Q75: 132525 | R75: 132525 | S75: 132525 | T75: 132525 | U75: 132525 | V75: 132525 | W75: 132525 | X75: 132525 | Y75: 132525 | Z75: 132525 | AA75: 132525 | AB75: 132525 | AC75: 132525 | AD75: 132525 | AE75: 0 | AF75: 0 | AG75: 0 | AH75: 0
F76: 2029 | G76: 127500 | H76: 121125 | J76: 0 | K76: 0 | L76: 0 | M76: 0 | N76: 0 | O76: 0 | P76: 0 | Q76: 8075 | R76: 8075 | S76: 8075 | T76: 8075 | U76: 8075 | V76: 8075 | W76: 8075 | X76: 8075 | Y76: 8075 | Z76: 8075 | AA76: 8075 | AB76: 8075 | AC76: 8075 | AD76: 8075 | AE76: 8075 | AF76: 0 | AG76: 0 | AH76: 0
F77: 2030 | H77: 0 | J77: 0 | K77: 0 | L77: 0 | M77: 0 | N77: 0 | O77: 0 | P77: 0 | Q77: 0 | R77: 0 | S77: 0 | T77: 0 | U77: 0 | V77: 0 | W77: 0 | X77: 0 | Y77: 0 | Z77: 0 | AA77: 0 | AB77: 0 | AC77: 0 | AD77: 0 | AE77: 0 | AF77: 0 | AG77: 0 | AH77: 0
F78: 2031 | G78: 856500 | H78: 813675 | J78: 0 | K78: 0 | L78: 0 | M78: 0 | N78: 0 | O78: 0 | P78: 0 | Q78: 0 | R78: 0 | S78: 54245 | T78: 54245 | U78: 54245 | V78: 54245 | W78: 54245 | X78: 54245 | Y78: 54245 | Z78: 54245 | AA78: 54245 | AB78: 54245 | AC78: 54245 | AD78: 54245 | AE78: 54245 | AF78: 54245 | AG78: 54245 | AH78: 0
F79: 2032 | G79: 1249500 | H79: 1187025 | J79: 0 | K79: 0 | L79: 0 | M79: 0 | N79: 0 | O79: 0 | P79: 0 | Q79: 0 | R79: 0 | S79: 0 | T79: 79135 | U79: 79135 | V79: 79135 | W79: 79135 | X79: 79135 | Y79: 79135 | Z79: 79135 | AA79: 79135 | AB79: 79135 | AC79: 79135 | AD79: 79135 | AE79: 79135 | AF79: 79135 | AG79: 79135 | AH79: 79135
F80: 2033 | G80: 1446000 | H80: 1282120 | J80: 0 | K80: 0 | L80: 0 | M80: 0 | N80: 0 | O80: 0 | P80: 0 | Q80: 0 | R80: 0 | S80: 0 | T80: 0 | U80: 91580 | V80: 91580 | W80: 91580 | X80: 91580 | Y80: 91580 | Z80: 91580 | AA80: 91580 | AB80: 91580 | AC80: 91580 | AD80: 91580 | AE80: 91580 | AF80: 91580 | AG80: 91580 | AH80: 91580
F81: 2034 | G81: 585000 | H81: 481650 | J81: 0 | K81: 0 | L81: 0 | M81: 0 | N81: 0 | O81: 0 | P81: 0 | Q81: 0 | R81: 0 | S81: 0 | T81: 0 | U81: 0 | V81: 37050 | W81: 37050 | X81: 37050 | Y81: 37050 | Z81: 37050 | AA81: 37050 | AB81: 37050 | AC81: 37050 | AD81: 37050 | AE81: 37050 | AF81: 37050 | AG81: 37050 | AH81: 37050
F82: 2035 | G82: 2676000 | H82: 2033760 | J82: 0 | K82: 0 | L82: 0 | M82: 0 | N82: 0 | O82: 0 | P82: 0 | Q82: 0 | R82: 0 | S82: 0 | T82: 0 | U82: 0 | V82: 0 | W82: 169480 | X82: 169480 | Y82: 169480 | Z82: 169480 | AA82: 169480 | AB82: 169480 | AC82: 169480 | AD82: 169480 | AE82: 169480 | AF82: 169480 | AG82: 169480 | AH82: 169480
F83: 2036 | G83: 1798500 | H83: 1252955 | J83: 0 | K83: 0 | L83: 0 | M83: 0 | N83: 0 | O83: 0 | P83: 0 | Q83: 0 | R83: 0 | S83: 0 | T83: 0 | U83: 0 | V83: 0 | W83: 0 | X83: 113905 | Y83: 113905 | Z83: 113905 | AA83: 113905 | AB83: 113905 | AC83: 113905 | AD83: 113905 | AE83: 113905 | AF83: 113905 | AG83: 113905 | AH83: 113905
F84: 2037 | G84: 1858500 | H84: 1177050 | J84: 0 | K84: 0 | L84: 0 | M84: 0 | N84: 0 | O84: 0 | P84: 0 | Q84: 0 | R84: 0 | S84: 0 | T84: 0 | U84: 0 | V84: 0 | W84: 0 | X84: 0 | Y84: 117705 | Z84: 117705 | AA84: 117705 | AB84: 117705 | AC84: 117705 | AD84: 117705 | AE84: 117705 | AF84: 117705 | AG84: 117705 | AH84: 117705
F85: 2038 | G85: 1566000 | H85: 892620 | J85: 0 | K85: 0 | L85: 0 | M85: 0 | N85: 0 | O85: 0 | P85: 0 | Q85: 0 | R85: 0 | S85: 0 | T85: 0 | U85: 0 | V85: 0 | W85: 0 | X85: 0 | Y85: 0 | Z85: 99180 | AA85: 99180 | AB85: 99180 | AC85: 99180 | AD85: 99180 | AE85: 99180 | AF85: 99180 | AG85: 99180 | AH85: 99180
F86: 2039 | G86: 1518000 | H86: 769120 | J86: 0 | K86: 0 | L86: 0 | M86: 0 | N86: 0 | O86: 0 | P86: 0 | Q86: 0 | R86: 0 | S86: 0 | T86: 0 | U86: 0 | V86: 0 | W86: 0 | X86: 0 | Y86: 0 | Z86: 0 | AA86: 96140 | AB86: 96140 | AC86: 96140 | AD86: 96140 | AE86: 96140 | AF86: 96140 | AG86: 96140 | AH86: 96140
F87: 2040 | G87: 496500 | H87: 220115 | J87: 0 | K87: 0 | L87: 0 | M87: 0 | N87: 0 | O87: 0 | P87: 0 | Q87: 0 | R87: 0 | S87: 0 | T87: 0 | U87: 0 | V87: 0 | W87: 0 | X87: 0 | Y87: 0 | Z87: 0 | AA87: 0 | AB87: 31445 | AC87: 31445 | AD87: 31445 | AE87: 31445 | AF87: 31445 | AG87: 31445 | AH87: 31445
F88: 2041 | G88: 577500 | H88: 219450 | J88: 0 | K88: 0 | L88: 0 | M88: 0 | N88: 0 | O88: 0 | P88: 0 | Q88: 0 | R88: 0 | S88: 0 | T88: 0 | U88: 0 | V88: 0 | W88: 0 | X88: 0 | Y88: 0 | Z88: 0 | AA88: 0 | AB88: 0 | AC88: 36575 | AD88: 36575 | AE88: 36575 | AF88: 36575 | AG88: 36575 | AH88: 36575
F89: 2042 | G89: 1747500 | H89: 553375 | J89: 0 | K89: 0 | L89: 0 | M89: 0 | N89: 0 | O89: 0 | P89: 0 | Q89: 0 | R89: 0 | S89: 0 | T89: 0 | U89: 0 | V89: 0 | W89: 0 | X89: 0 | Y89: 0 | Z89: 0 | AA89: 0 | AB89: 0 | AC89: 0 | AD89: 110675 | AE89: 110675 | AF89: 110675 | AG89: 110675 | AH89: 110675
... F93: 2046 | G93: 2253000 | H93: 142690 | J93: 0 | K93: 0 | L93: 0 | M93: 0 | N93: 0 | O93: 0 | P93: 0 | Q93: 0 | R93: 0 | S93: 0 | T93: 0 | U93: 0 | V93: 0 | W93: 0 | X93: 0 | Y93: 0 | Z93: 0 | AA93: 0 | AB93: 0 | AC93: 0 | AD93: 0 | AE93: 0 | AF93: 0 | AG93: 0 | AH93: 142690
J94: {=_xlfn.BYCOL(_xlfn.ANCHORARRAY( J69), _xleta.SUM )} -> 214890 | K94: 257450 | L94: 404985 | M94: 440895 | N94: 593465 | O94: 752970 | P94: 885495 | Q94: 893570 | R94: 893570 | S94: 947815 | T94: 1026950 | U94: 1118530 | V94: 1155580 | W94: 1325060 | X94: 1438965 | Y94: 1341780 | Z94: 1398400 | AA94: 1347005 | AB94: 1342540 | AC94: 1226545 | AD94: 1177715 | AE94: 1136960 | AF94: 1174010 | AG94: 1291905 | AH94: 1380350
C96: Units of production
F97: Date | G97: Cost | J97: {=_xlfn.ANCHORARRAY(J3)} -> 44592 | K97: 44957 | L97: 45322 | M97: 45688 | N97: 46053 | O97: 46418 | P97: 46783 | Q97: 47149 | R97: 47514 | S97: 47879 | T97: 48244 | U97: 48610 | V97: 48975 | W97: 49340 | X97: 49705 | Y97: 50071 | Z97: 50436 | AA97: 50801 | AB97: 51166 | AC97: 51532 | AD97: 51897 | AE97: 52262 | AF97: 52627 | AG97: 52993 | AH97: 53358
F98: {=_xlfn.LET( _xlpm.date, INDEX(_xlfn.ANCHORARRAY( $E$8),, 1 ), _xlpm.asset, INDEX(_xlfn.ANCHORARRAY( $E$8),, 2 ), _xlfn.DROP( _xlfn.HSTACK( _xlpm.date, _xlpm.asset ), 1 ) )} -> 2022 | G98: 3393000 | H98: {=_xlfn.BYROW(_xlfn.ANCHORARRAY( J98), _xleta.SUM )} -> 3223350 | J98: {=_xlfn.LET( _xlpm.acquisition_date, INDEX(_xlfn.ANCHORARRAY( $F98),,1 ), _xlpm.acquisition_cost, INDEX(_xlfn.ANCHORARRAY( $F98),,2 ), _xlpm.current_date,_xlfn.ANCHORARRAY( J3), _xlpm.salvage_value, CaseData!$G$11, _xlpm.depreciable_amount, _xlpm.acquisition_cost * ( 1 - _xlpm.salvage_value ), _xlpm.useful_life, CaseData!$I$34, _xlpm.period, YEAR( _xlpm.current_date ) - _xlpm.acquisition_date + 1, _xlpm.units_of_production, CaseData!$E$39, _xlpm.rate, _xlpm.depreciable_amount / _xlpm.units_of_production, _xlpm.production_table, CaseData!$E$42:$T$61, _xlpm.production_rows, CaseData!$D$42:$D$61, _xlpm.production_columns, CaseData!$E$40:$T$40, _xlpm.depreciation_amount, INDEX( _xlpm.production_table, MATCH( _xlpm.period, _xlpm.production_rows, 0 ), MATCH( _xlpm.useful_life, _xlpm.production_columns, 0 ) ), IFERROR( IF( _xlpm.period < 0, 0, _xlpm.depreciation_amount * _xlpm.rate ), 0) )} -> 428705.55 | K98: 373908.6 | L98: 322335 | M98: 280431.45 | N98: 241751.25 | O98: 209517.75 | P98: 183730.95 | Q98: 157944.15 | R98: 145050.75 | S98: 145050.75 | T98: 145050.75 | U98: 145050.75 | V98: 145050.75 | W98: 145050.75 | X98: 154720.8 | Y98: 0 | Z98: 0 | AA98: 0 | AB98: 0 | AC98: 0 | AD98: 0 | AE98: 0 | AF98: 0 | AG98: 0 | AH98: 0
F99: 2023 | G99: 672000 | H99: 638400 | J99: 0 | K99: 84907.2 | L99: 74054.4 | M99: 63840 | N99: 55540.8 | O99: 47880 | P99: 41496 | Q99: 36388.8 | R99: 31281.6 | S99: 28728 | T99: 28728 | U99: 28728 | V99: 28728 | W99: 28728 | X99: 28728 | Y99: 30643.2 | Z99: 0 | AA99: 0 | AB99: 0 | AC99: 0 | AD99: 0 | AE99: 0 | AF99: 0 | AG99: 0 | AH99: 0
F100: 2024 | G100: 2329500 | H100: 2213025 | J100: 0 | K100: 0 | L100: 294332.33 | M100: 256710.9 | N100: 221302.5 | O100: 192533.17 | P100: 165976.88 | Q100: 143846.62 | R100: 126142.43 | S100: 108438.23 | T100: 99586.125 | U100: 99586.125 | V100: 99586.125 | W100: 99586.125 | X100: 99586.125 | Y100: 99586.125 | Z100: 106225.2 | AA100: 0 | AB100: 0 | AC100: 0 | AD100: 0 | AE100: 0 | AF100: 0 | AG100: 0 | AH100: 0
F101: 2025 | G101: 567000 | H101: 538650 | J101: 0 | K101: 0 | L101: 0 | M101: 71640.45 | N101: 62483.4 | O101: 53865 | P101: 46862.55 | Q101: 40398.75 | R101: 35012.25 | S101: 30703.05 | T101: 26393.85 | U101: 24239.25 | V101: 24239.25 | W101: 24239.25 | X101: 24239.25 | Y101: 24239.25 | Z101: 24239.25 | AA101: 25855.2 | AB101: 0 | AC101: 0 | AD101: 0 | AE101: 0 | AF101: 0 | AG101: 0 | AH101: 0
F102: 2026 | G102: 2409000 | H102: 2288550 | J102: 0 | K102: 0 | L102: 0 | M102: 0 | N102: 304377.15 | O102: 265471.8 | P102: 228855 | Q102: 199103.85 | R102: 171641.25 | S102: 148755.75 | T102: 130447.35 | U102: 112138.95 | V102: 102984.75 | W102: 102984.75 | X102: 102984.75 | Y102: 102984.75 | Z102: 102984.75 | AA102: 102984.75 | AB102: 109850.4 | AC102: 0 | AD102: 0 | AE102: 0 | AF102: 0 | AG102: 0 | AH102: 0
F103: 2027 | G103: 2518500 | H103: 2392575 | J103: 0 | K103: 0 | L103: 0 | M103: 0 | N103: 0 | O103: 318212.47 | P103: 277538.7 | Q103: 239257.5 | R103: 208154.02 | S103: 179443.12 | T103: 155517.38 | U103: 136376.77 | V103: 117236.17 | W103: 107665.88 | X103: 107665.88 | Y103: 107665.88 | Z103: 107665.88 | AA103: 107665.88 | AB103: 107665.88 | AC103: 114843.6 | AD103: 0 | AE103: 0 | AF103: 0 | AG103: 0 | AH103: 0
F104: 2028 | G104: 2092500 | H104: 1987875 | J104: 0 | K104: 0 | L104: 0 | M104: 0 | N104: 0 | O104: 0 | P104: 264387.38 | Q104: 230593.5 | R104: 198787.5 | S104: 172945.12 | T104: 149090.62 | U104: 129211.88 | V104: 113308.88 | W104: 97405.875 | X104: 89454.375 | Y104: 89454.375 | Z104: 89454.375 | AA104: 89454.375 | AB104: 89454.375 | AC104: 89454.375 | AD104: 95418 | AE104: 0 | AF104: 0 | AG104: 0 | AH104: 0
F105: 2029 | G105: 127500 | H105: 121125 | J105: 0 | K105: 0 | L105: 0 | M105: 0 | N105: 0 | O105: 0 | P105: 0 | Q105: 16109.625 | R105: 14050.5 | S105: 12112.5 | T105: 10537.875 | U105: 9084.375 | V105: 7873.125 | W105: 6904.125 | X105: 5935.125 | Y105: 5450.625 | Z105: 5450.625 | AA105: 5450.625 | AB105: 5450.625 | AC105: 5450.625 | AD105: 5450.625 | AE105: 5814 | AF105: 0 | AG105: 0 | AH105: 0
F106: 2030 | H106: 0 | J106: 0 | K106: 0 | L106: 0 | M106: 0 | N106: 0 | O106: 0 | P106: 0 | Q106: 0 | R106: 0 | S106: 0 | T106: 0 | U106: 0 | V106: 0 | W106: 0 | X106: 0 | Y106: 0 | Z106: 0 | AA106: 0 | AB106: 0 | AC106: 0 | AD106: 0 | AE106: 0 | AF106: 0 | AG106: 0 | AH106: 0
F107: 2031 | G107: 856500 | H107: 813675 | J107: 0 | K107: 0 | L107: 0 | M107: 0 | N107: 0 | O107: 0 | P107: 0 | Q107: 0 | R107: 0 | S107: 108218.78 | T107: 94386.3 | U107: 81367.5 | V107: 70789.725 | W107: 61025.625 | X107: 52888.875 | Y107: 46379.475 | Z107: 39870.075 | AA107: 36615.375 | AB107: 36615.375 | AC107: 36615.375 | AD107: 36615.375 | AE107: 36615.375 | AF107: 36615.375 | AG107: 39056.4 | AH107: 0
F108: 2032 | G108: 1249500 | H108: 1187025 | J108: 0 | K108: 0 | L108: 0 | M108: 0 | N108: 0 | O108: 0 | P108: 0 | Q108: 0 | R108: 0 | S108: 0 | T108: 157874.33 | U108: 137694.9 | V108: 118702.5 | W108: 103271.18 | X108: 89026.875 | Y108: 77156.625 | Z108: 67660.425 | AA108: 58164.225 | AB108: 53416.125 | AC108: 53416.125 | AD108: 53416.125 | AE108: 53416.125 | AF108: 53416.125 | AG108: 53416.125 | AH108: 56977.2
F109: 2033 | G109: 1446000 | H109: 1307762.4 | J109: 0 | K109: 0 | L109: 0 | M109: 0 | N109: 0 | O109: 0 | P109: 0 | Q109: 0 | R109: 0 | S109: 0 | T109: 0 | U109: 182702.1 | V109: 159349.2 | W109: 137370 | X109: 119511.9 | Y109: 103027.5 | Z109: 89290.5 | AA109: 78300.9 | AB109: 67311.3 | AC109: 61816.5 | AD109: 61816.5 | AE109: 61816.5 | AF109: 61816.5 | AG109: 61816.5 | AH109: 61816.5
F110: 2034 | G110: 585000 | H110: 504065.25 | J110: 0 | K110: 0 | L110: 0 | M110: 0 | N110: 0 | O110: 0 | P110: 0 | Q110: 0 | R110: 0 | S110: 0 | T110: 0 | U110: 0 | V110: 73914.75 | W110: 64467 | X110: 55575 | Y110: 48350.25 | Z110: 41681.25 | AA110: 36123.75 | AB110: 31677.75 | AC110: 27231.75 | AD110: 25008.75 | AE110: 25008.75 | AF110: 25008.75 | AG110: 25008.75 | AH110: 25008.75
F111: 2035 | G111: 2676000 | H111: 2191376.4 | J111: 0 | K111: 0 | L111: 0 | M111: 0 | N111: 0 | O111: 0 | P111: 0 | Q111: 0 | R111: 0 | S111: 0 | T111: 0 | U111: 0 | V111: 0 | W111: 338112.6 | X111: 294895.2 | Y111: 254220 | Z111: 221171.4 | AA111: 190665 | AB111: 165243 | AC111: 144905.4 | AD111: 124567.8 | AE111: 114399 | AF111: 114399 | AG111: 114399 | AH111: 114399
F112: 2036 | G112: 1798500 | H112: 1395905.8 | J112: 0 | K112: 0 | L112: 0 | M112: 0 | N112: 0 | O112: 0 | P112: 0 | Q112: 0 | R112: 0 | S112: 0 | T112: 0 | U112: 0 | V112: 0 | W112: 0 | X112: 227240.48 | Y112: 198194.7 | Z112: 170857.5 | AA112: 148646.02 | AB112: 128143.12 | AC112: 111057.38 | AD112: 97388.775 | AE112: 83720.175 | AF112: 76885.875 | AG112: 76885.875 | AH112: 76885.875
F113: 2037 | G113: 1858500 | H113: 1363023.9 | J113: 0 | K113: 0 | L113: 0 | M113: 0 | N113: 0 | O113: 0 | P113: 0 | Q113: 0 | R113: 0 | S113: 0 | T113: 0 | U113: 0 | V113: 0 | W113: 0 | X113: 0 | Y113: 234821.47 | Z113: 204806.7 | AA113: 176557.5 | AB113: 153605.02 | AC113: 132418.12 | AD113: 114762.38 | AE113: 100637.77 | AF113: 86513.175 | AG113: 79450.875 | AH113: 79450.875
F114: 2038 | G114: 1566000 | H114: 1081557.9 | J114: 0 | K114: 0 | L114: 0 | M114: 0 | N114: 0 | O114: 0 | P114: 0 | Q114: 0 | R114: 0 | S114: 0 | T114: 0 | U114: 0 | V114: 0 | W114: 0 | X114: 0 | Y114: 0 | Z114: 197864.1 | AA114: 172573.2 | AB114: 148770 | AC114: 129429.9 | AD114: 111577.5 | AE114: 96700.5 | AF114: 84798.9 | AG114: 72897.3 | AH114: 66946.5
F115: 2039 | G115: 1518000 | H115: 983512.2 | J115: 0 | K115: 0 | L115: 0 | M115: 0 | N115: 0 | O115: 0 | P115: 0 | Q115: 0 | R115: 0 | S115: 0 | T115: 0 | U115: 0 | V115: 0 | W115: 0 | X115: 0 | Y115: 0 | Z115: 0 | AA115: 191799.3 | AB115: 167283.6 | AC115: 144210 | AD115: 125462.7 | AE115: 108157.5 | AF115: 93736.5 | AG115: 82199.7 | AH115: 70662.9
F116: 2040 | G116: 496500 | H116: 298570.28 | J116: 0 | K116: 0 | L116: 0 | M116: 0 | N116: 0 | O116: 0 | P116: 0 | Q116: 0 | R116: 0 | S116: 0 | T116: 0 | U116: 0 | V116: 0 | W116: 0 | X116: 0 | Y116: 0 | Z116: 0 | AA116: 0 | AB116: 62732.775 | AC116: 54714.3 | AD116: 47167.5 | AE116: 41035.725 | AF116: 35375.625 | AG116: 30658.875 | AH116: 26885.475
...

Sheet CaseData
A1: General Assumptions
C3: Company name | E3: [label] | G3: Mineral to Rock
C4: CFM Topic | E4: [label] | G4: CAPEX and depreciation
C5: Number of periods | E5: [years] | G5: 25
C7: Model Start Date (do not change) | E7: [date] | G7: 44562
C8: Tax Rate | E8: [%] | G8: 0.25
C9: Discount Rate per Annum | E9: [%] | G9: 0.1
C10: Discount Date for Present Value of Tax Benefits | E10: [date] | G10: =G7-1 -> 44561
C11: Salvage Value (% of CAPEX) | E11: [%] | G11: 0.05
B13: Names of Asset Classes
C14: ListAssetClasses1
C15: Short Term
C16: Medium Term
C17: Long Term
B20: Names of Depreciation Methods
C21: ListDepMethods1
C22: Declining Balance
C23: Straight Line
C24: Units of Production
C25: Sum of Years Digits
A28: Depreciation Assumptions
B30: General Depreciation Assumption Data
G31: {=TRANSPOSE(ListAssetClasses1)} -> Short Term | H31: Medium Term | I31: Long Term
C32: {=ListDepMethods1} -> Declining Balance | E32: Annual % | F32: [%] | G32: 0.45 | H32: 0.225 | I32: 0.15
C33: Straight Line | E33: Useful Life | F33: [years] | G33: 5 | H33: 10 | I33: 15
C34: Units of Production | D34: (See below) | E34: Useful Life | F34: [years] | G34: 5 | H34: 10 | I34: 15
C35: Sum of Years Digits | D35: (See below) | E35: Useful Life | F35: [years] | G35: 5 | H35: 10 | I35: 15
B38: =$C$24&" Tables" -> Units of Production Tables
D39: Total Prod. --> | E39: 1000000 | F39: =$E$39 -> 1000000 | G39: =$E$39 -> 1000000 | H39: =$E$39 -> 1000000 | I39: =$E$39 -> 1000000 | J39: =$E$39 -> 1000000 | K39: =$E$39 -> 1000000 | L39: =$E$39 -> 1000000 | M39: =$E$39 -> 1000000 | ... T39: =$E$39 -> 1000000
D40: Useful Life --> | E40: 5 | F40: =E40+1 -> 6 | G40: =F40+1 -> 7 | H40: =G40+1 -> 8 | I40: =H40+1 -> 9 | J40: =I40+1 -> 10 | K40: =J40+1 -> 11 | L40: =K40+1 -> 12 | M40: =L40+1 -> 13 | ... T40: =S40+1 -> 20
D41: Year
D42: 1 | E42: 400000 | F42: 333000 | G42: 286000 | H42: 250000 | I42: 222000 | J42: 200000 | K42: 182000 | L42: 167000 | M42: 154000 | N42: 143000 | O42: 133000 | P42: 125000 | Q42: 118000 | R42: 111000 | S42: 105000 | T42: 100000
D43: =D42+1 -> 2 | E43: 240000 | F43: 222000 | G43: 204000 | H43: 188000 | I43: 173000 | J43: 160000 | K43: 149000 | L43: 139000 | M43: 130000 | N43: 122000 | O43: 116000 | P43: 109000 | Q43: 104000 | R43: 99000 | S43: 94000 | T43: 90000
D44: =D43+1 -> 3 | E44: 144000 | F44: 148000 | G44: 146000 | H44: 141000 | I44: 134000 | J44: 128000 | K44: 122000 | L44: 116000 | M44: 110000 | N44: 105000 | O44: 100000 | P44: 96000 | Q44: 92000 | R44: 88000 | S44: 84000 | T44: 81000
D45: =D44+1 -> 4 | E45: 108000 | F45: 99000 | G45: 104000 | H45: 105000 | I45: 105000 | J45: 102000 | K45: 100000 | L45: 96000 | M45: 93000 | N45: 90000 | O45: 87000 | P45: 84000 | Q45: 81000 | R45: 78000 | S45: 75000 | T45: 73000
D46: =D45+1 -> 5 | E46: 108000 | F46: 99000 | G46: 87000 | H46: 79000 | I46: 81000 | J46: 82000 | K46: 81000 | L46: 80000 | M46: 79000 | N46: 77000 | O46: 75000 | P46: 73000 | Q46: 71000 | R46: 69000 | S46: 67000 | T46: 66000
D47: =D46+1 -> 6 | E47: 0 | F47: 99000 | G47: 87000 | H47: 79000 | I47: 71000 | J47: 66000 | K47: 67000 | L47: 67000 | M47: 67000 | N47: 66000 | O47: 65000 | P47: 64000 | Q47: 63000 | R47: 62000 | S47: 60000 | T47: 59000
D48: =D47+1 -> 7 | E48: 0 | F48: 0 | G48: 86000 | H48: 79000 | I48: 71000 | J48: 66000 | K48: 60000 | L48: 56000 | M48: 56000 | N48: 57000 | O48: 57000 | P48: 56000 | Q48: 56000 | R48: 55000 | S48: 54000 | T48: 53000
D49: =D48+1 -> 8 | E49: 0 | F49: 0 | G49: 0 | H49: 79000 | I49: 71000 | J49: 66000 | K49: 60000 | L49: 56000 | M49: 52000 | N49: 49000 | O49: 49000 | P49: 49000 | Q49: 49000 | R49: 49000 | S49: 48000 | T49: 48000
D50: =D49+1 -> 9 | E50: 0 | F50: 0 | G50: 0 | H50: 0 | I50: 72000 | J50: 66000 | K50: 60000 | L50: 56000 | M50: 52000 | N50: 49000 | O50: 45000 | P50: 43000 | Q50: 43000 | R50: 43000 | S50: 43000 | T50: 43000
D51: =D50+1 -> 10 | E51: 0 | F51: 0 | G51: 0 | H51: 0 | I51: 0 | J51: 64000 | K51: 60000 | L51: 56000 | M51: 52000 | N51: 49000 | O51: 45000 | P51: 43000 | Q51: 41000 | R51: 38000 | S51: 39000 | T51: 39000
D52: =D51+1 -> 11 | E52: 0 | F52: 0 | G52: 0 | H52: 0 | I52: 0 | J52: 0 | K52: 59000 | L52: 56000 | M52: 52000 | N52: 49000 | O52: 45000 | P52: 43000 | Q52: 41000 | R52: 38000 | S52: 37000 | T52: 35000
D53: =D52+1 -> 12 | E53: 0 | F53: 0 | G53: 0 | H53: 0 | I53: 0 | J53: 0 | K53: 0 | L53: 55000 | M53: 52000 | N53: 49000 | O53: 45000 | P53: 43000 | Q53: 41000 | R53: 38000 | S53: 37000 | T53: 35000
D54: =D53+1 -> 13 | E54: 0 | F54: 0 | G54: 0 | H54: 0 | I54: 0 | J54: 0 | K54: 0 | L54: 0 | M54: 51000 | N54: 49000 | O54: 45000 | P54: 43000 | Q54: 41000 | R54: 38000 | S54: 37000 | T54: 35000
... D61: =D60+1 -> 20 | E61: 0 | F61: 0 | G61: 0 | H61: 0 | I61: 0 | J61: 0 | K61: 0 | L61: 0 | M61: 0 | N61: 0 | O61: 0 | P61: 0 | Q61: 0 | R61: 0 | S61: 0 | T61: 33000
B64: =$C$25&" Tables" -> Sum of Years Digits Tables
D65: Useful Life --> | E65: 5 | F65: =E65+1 -> 6 | G65: =F65+1 -> 7 | H65: =G65+1 -> 8 | I65: =H65+1 -> 9 | J65: =I65+1 -> 10 | K65: =J65+1 -> 11 | L65: =K65+1 -> 12 | M65: =L65+1 -> 13 | ... T65: =S65+1 -> 20
D66: Year | E66: =E$65*(E$65+1)/2 -> 15 | F66: =F$65*(F$65+1)/2 -> 21 | G66: =G$65*(G$65+1)/2 -> 28 | H66: =H$65*(H$65+1)/2 -> 36 | I66: =I$65*(I$65+1)/2 -> 45 | J66: =J$65*(J$65+1)/2 -> 55 | K66: =K$65*(K$65+1)/2 -> 66 | L66: =L$65*(L$65+1)/2 -> 78 | ... T66: =T$65*(T$65+1)/2 -> 210
D67: 1 | E67: =MAX(0,E$65+1-$D67)/E$66 -> 0.33333333 | F67: =MAX(0,F$65+1-$D67)/F$66 -> 0.28571429 | G67: =MAX(0,G$65+1-$D67)/G$66 -> 0.25 | H67: =MAX(0,H$65+1-$D67)/H$66 -> 0.22222222 | I67: =MAX(0,I$65+1-$D67)/I$66 -> 0.2 | J67: =MAX(0,J$65+1-$D67)/J$66 -> 0.18181818 | K67: =MAX(0,K$65+1-$D67)/K$66 -> 0.16666667 | L67: =MAX(0,L$65+1-$D67)/L$66 -> 0.15384615 | ... T67: =MAX(0,T$65+1-$D67)/T$66 -> 0.095238095
D68: =D67+1 -> 2 | E68: =MAX(0,E$65+1-$D68)/E$66 -> 0.26666667 | F68: =MAX(0,F$65+1-$D68)/F$66 -> 0.23809524 | G68: =MAX(0,G$65+1-$D68)/G$66 -> 0.21428571 | H68: =MAX(0,H$65+1-$D68)/H$66 -> 0.19444444 | I68: =MAX(0,I$65+1-$D68)/I$66 -> 0.17777778 | J68: =MAX(0,J$65+1-$D68)/J$66 -> 0.16363636 | K68: =MAX(0,K$65+1-$D68)/K$66 -> 0.15151515 | L68: =MAX(0,L$65+1-$D68)/L$66 -> 0.14102564 | ... T68: =MAX(0,T$65+1-$D68)/T$66 -> 0.09047619
D69: =D68+1 -> 3 | E69: =MAX(0,E$65+1-$D69)/E$66 -> 0.2 | F69: =MAX(0,F$65+1-$D69)/F$66 -> 0.19047619 | G69: =MAX(0,G$65+1-$D69)/G$66 -> 0.17857143 | H69: =MAX(0,H$65+1-$D69)/H$66 -> 0.16666667 | I69: =MAX(0,I$65+1-$D69)/I$66 -> 0.15555556 | J69: =MAX(0,J$65+1-$D69)/J$66 -> 0.14545455 | K69: =MAX(0,K$65+1-$D69)/K$66 -> 0.13636364 | L69: =MAX(0,L$65+1-$D69)/L$66 -> 0.12820513 | ... T69: =MAX(0,T$65+1-$D69)/T$66 -> 0.085714286
D70: =D69+1 -> 4 | E70: =MAX(0,E$65+1-$D70)/E$66 -> 0.13333333 | F70: =MAX(0,F$65+1-$D70)/F$66 -> 0.14285714 | G70: =MAX(0,G$65+1-$D70)/G$66 -> 0.14285714 | H70: =MAX(0,H$65+1-$D70)/H$66 -> 0.13888889 | I70: =MAX(0,I$65+1-$D70)/I$66 -> 0.13333333 | J70: =MAX(0,J$65+1-$D70)/J$66 -> 0.12727273 | K70: =MAX(0,K$65+1-$D70)/K$66 -> 0.12121212 | L70: =MAX(0,L$65+1-$D70)/L$66 -> 0.11538462 | ... T70: =MAX(0,T$65+1-$D70)/T$66 -> 0.080952381
D71: =D70+1 -> 5 | E71: =MAX(0,E$65+1-$D71)/E$66 -> 0.066666667 | F71: =MAX(0,F$65+1-$D71)/F$66 -> 0.095238095 | G71: =MAX(0,G$65+1-$D71)/G$66 -> 0.10714286 | H71: =MAX(0,H$65+1-$D71)/H$66 -> 0.11111111 | I71: =MAX(0,I$65+1-$D71)/I$66 -> 0.11111111 | J71: =MAX(0,J$65+1-$D71)/J$66 -> 0.10909091 | K71: =MAX(0,K$65+1-$D71)/K$66 -> 0.10606061 | L71: =MAX(0,L$65+1-$D71)/L$66 -> 0.1025641 | ... T71: =MAX(0,T$65+1-$D71)/T$66 -> 0.076190476
D72: =D71+1 -> 6 | E72: =MAX(0,E$65+1-$D72)/E$66 -> 0 | F72: =MAX(0,F$65+1-$D72)/F$66 -> 0.047619048 | G72: =MAX(0,G$65+1-$D72)/G$66 -> 0.071428571 | H72: =MAX(0,H$65+1-$D72)/H$66 -> 0.083333333 | I72: =MAX(0,I$65+1-$D72)/I$66 -> 0.088888889 | J72: =MAX(0,J$65+1-$D72)/J$66 -> 0.090909091 | K72: =MAX(0,K$65+1-$D72)/K$66 -> 0.090909091 | L72: =MAX(0,L$65+1-$D72)/L$66 -> 0.08974359 | ... T72: =MAX(0,T$65+1-$D72)/T$66 -> 0.071428571
D73: =D72+1 -> 7 | E73: =MAX(0,E$65+1-$D73)/E$66 -> 0 | F73: =MAX(0,F$65+1-$D73)/F$66 -> 0 | G73: =MAX(0,G$65+1-$D73)/G$66 -> 0.035714286 | H73: =MAX(0,H$65+1-$D73)/H$66 -> 0.055555556 | I73: =MAX(0,I$65+1-$D73)/I$66 -> 0.066666667 | J73: =MAX(0,J$65+1-$D73)/J$66 -> 0.072727273 | K73: =MAX(0,K$65+1-$D73)/K$66 -> 0.075757576 | L73: =MAX(0,L$65+1-$D73)/L$66 -> 0.076923077 | ... T73: =MAX(0,T$65+1-$D73)/T$66 -> 0.066666667
D74: =D73+1 -> 8 | E74: =MAX(0,E$65+1-$D74)/E$66 -> 0 | F74: =MAX(0,F$65+1-$D74)/F$66 -> 0 | G74: =MAX(0,G$65+1-$D74)/G$66 -> 0 | H74: =MAX(0,H$65+1-$D74)/H$66 -> 0.027777778 | I74: =MAX(0,I$65+1-$D74)/I$66 -> 0.044444444 | J74: =MAX(0,J$65+1-$D74)/J$66 -> 0.054545455 | K74: =MAX(0,K$65+1-$D74)/K$66 -> 0.060606061 | L74: =MAX(0,L$65+1-$D74)/L$66 -> 0.064102564 | ... T74: =MAX(0,T$65+1-$D74)/T$66 -> 0.061904762
D75: =D74+1 -> 9 | E75: =MAX(0,E$65+1-$D75)/E$66 -> 0 | F75: =MAX(0,F$65+1-$D75)/F$66 -> 0 | G75: =MAX(0,G$65+1-$D75)/G$66 -> 0 | H75: =MAX(0,H$65+1-$D75)/H$66 -> 0 | I75: =MAX(0,I$65+1-$D75)/I$66 -> 0.022222222 | J75: =MAX(0,J$65+1-$D75)/J$66 -> 0.036363636 | K75: =MAX(0,K$65+1-$D75)/K$66 -> 0.045454545 | L75: =MAX(0,L$65+1-$D75)/L$66 -> 0.051282051 | ... T75: =MAX(0,T$65+1-$D75)/T$66 -> 0.057142857
D76: =D75+1 -> 10 | E76: =MAX(0,E$65+1-$D76)/E$66 -> 0 | F76: =MAX(0,F$65+1-$D76)/F$66 -> 0 | G76: =MAX(0,G$65+1-$D76)/G$66 -> 0 | H76: =MAX(0,H$65+1-$D76)/H$66 -> 0 | I76: =MAX(0,I$65+1-$D76)/I$66 -> 0 | J76: =MAX(0,J$65+1-$D76)/J$66 -> 0.018181818 | K76: =MAX(0,K$65+1-$D76)/K$66 -> 0.03030303 | L76: =MAX(0,L$65+1-$D76)/L$66 -> 0.038461538 | ... T76: =MAX(0,T$65+1-$D76)/T$66 -> 0.052380952
D77: =D76+1 -> 11 | E77: =MAX(0,E$65+1-$D77)/E$66 -> 0 | F77: =MAX(0,F$65+1-$D77)/F$66 -> 0 | G77: =MAX(0,G$65+1-$D77)/G$66 -> 0 | H77: =MAX(0,H$65+1-$D77)/H$66 -> 0 | I77: =MAX(0,I$65+1-$D77)/I$66 -> 0 | J77: =MAX(0,J$65+1-$D77)/J$66 -> 0 | K77: =MAX(0,K$65+1-$D77)/K$66 -> 0.015151515 | L77: =MAX(0,L$65+1-$D77)/L$66 -> 0.025641026 | ... T77: =MAX(0,T$65+1-$D77)/T$66 -> 0.047619048
D78: =D77+1 -> 12 | E78: =MAX(0,E$65+1-$D78)/E$66 -> 0 | F78: =MAX(0,F$65+1-$D78)/F$66 -> 0 | G78: =MAX(0,G$65+1-$D78)/G$66 -> 0 | H78: =MAX(0,H$65+1-$D78)/H$66 -> 0 | I78: =MAX(0,I$65+1-$D78)/I$66 -> 0 | J78: =MAX(0,J$65+1-$D78)/J$66 -> 0 | K78: =MAX(0,K$65+1-$D78)/K$66 -> 0 | L78: =MAX(0,L$65+1-$D78)/L$66 -> 0.012820513 | ... T78: =MAX(0,T$65+1-$D78)/T$66 -> 0.042857143
D79: =D78+1 -> 13 | E79: =MAX(0,E$65+1-$D79)/E$66 -> 0 | F79: =MAX(0,F$65+1-$D79)/F$66 -> 0 | G79: =MAX(0,G$65+1-$D79)/G$66 -> 0 | H79: =MAX(0,H$65+1-$D79)/H$66 -> 0 | I79: =MAX(0,I$65+1-$D79)/I$66 -> 0 | J79: =MAX(0,J$65+1-$D79)/J$66 -> 0 | K79: =MAX(0,K$65+1-$D79)/K$66 -> 0 | L79: =MAX(0,L$65+1-$D79)/L$66 -> 0 | ... T79: =MAX(0,T$65+1-$D79)/T$66 -> 0.038095238
... D86: =D85+1 -> 20 | E86: =MAX(0,E$65+1-$D86)/E$66 -> 0 | F86: =MAX(0,F$65+1-$D86)/F$66 -> 0 | G86: =MAX(0,G$65+1-$D86)/G$66 -> 0 | H86: =MAX(0,H$65+1-$D86)/H$66 -> 0 | I86: =MAX(0,I$65+1-$D86)/I$66 -> 0 | J86: =MAX(0,J$65+1-$D86)/J$66 -> 0 | K86: =MAX(0,K$65+1-$D86)/K$66 -> 0 | L86: =MAX(0,L$65+1-$D86)/L$66 -> 0 | ... T86: =MAX(0,T$65+1-$D86)/T$66 -> 0.0047619048
B89: Explanation and example of Depreciation Methods
C90: All examples will be for an asset purchased in the year 2022 for $100, with a salvage value of $5
B92: 1 | C92: =INDEX(ListDepMethods1,B92) -> Declining Balance
C93: The depreciation each year is the provided % rate multiplied by the remaining asset balance minus the salvage value.
C94: Example - rate of 40% | D94: 2022 | E94: 2023 | F94: 2024 | G94: 2025
C95: Opening Balance | D95: 0 | E95: 62 | F95: 39.2 | G95: 25.52
C96: New Capex | D96: 100 | E96: 0 | F96: 0 | G96: 0
C97: Depreciation | D97: -38 | E97: -22.8 | F97: -13.68 | G97: -8.208
C98: Closing Balance | D98: 62 | E98: 39.2 | F98: 25.52 | G98: 17.312
B100: 2 | C100: =INDEX(ListDepMethods1,B100) -> Straight Line
C101: The asset is depreciated in an equal amount over each year of its useful life, taking into account the salvage value.
C102: Example - useful life of 3 years | D102: 2022 | E102: 2023 | F102: 2024 | G102: 2025
C103: Opening Balance | D103: 0 | E103: 68.333333 | F103: 36.666667 | G103: 0
C104: New Capex | D104: 100 | E104: 0 | F104: 0 | G104: 0
C105: Depreciation | D105: -31.666667 | E105: -31.666667 | F105: -31.666667 | G105: 0
C106: Closing Balance | D106: 68.333333 | E106: 36.666667 | F106: 5 | G106: 0
B108: 3 | C108: =INDEX(ListDepMethods1,B108) -> Units of Production
C109: The asset is depreciated a certain amount each year of its life, based on its estimated production profile.
C110: The estimated production profile is multiplied by the Units of Production Rate to calculate the annual depreciation (Units of Production Rate = [Initial Cost of the Asset - Salvage Value] / Estimated Total Production over its useful life).
C112: Total Production | D112: 1000000
C114: Example - useful life of 5 years | D114: 2022 | E114: 2023 | F114: 2024 | G114: 2025
C115: Opening Balance | D115: 0 | E115: 62 | F115: 39.2 | G115: 25.52
C116: New Capex | D116: 100 | E116: 0 | F116: 0 | G116: 0
C117: Depreciation | D117: -38 | E117: -22.8 | F117: -13.68 | G117: -10.26
C118: Closing Balance | D118: 62 | E118: 39.2 | F118: 25.52 | G118: 15.26
C120: Yearly Production | D120: 400000 | E120: 240000 | F120: 144000 | G120: 108000
B122: 4 | C122: =INDEX(ListDepMethods1,B122) -> Sum of Years Digits
C123: The asset is depreciated a certain % each year of its life, based on the provided table.
C124: The profile of % rates is applied to the initial cost of the asset minus the salvage value to calculate the annual depreciation.
C125: Example - useful life of 5 years | D125: 2022 | E125: 2023 | F125: 2024 | G125: 2025
C126: Opening Balance | D126: 0 | E126: 68.333333 | F126: 43 | G126: 24
C127: New Capex | D127: 100 | E127: 0 | F127: 0 | G127: 0
C128: Depreciation | D128: -31.666667 | E128: -25.333333 | F128: -19 | G128: -12.666667
C129: Closing Balance | D129: 68.333333 | E129: 43 | F129: 24 | G129: 11.333333
A132: Capital Expenditure Assumptions
B134: Capital Expenditures | G134: column built as part of solution
D135: Date of
D136: Purchase | E136: Amount | F136: Asset Class | G136: Year
...

Sheet CaseSolution
C2: Case 1 Answers
C3: c) i)Depn MTA, 2027 SL | F3: =K160 -> 878085
C4: ii)Depn STA, 2032 DB | F4: =-P58 -> 1476428.3
C5: iii)Depn LTA, all 25yrs, Units of Production | F5: =SUM(F196:AD196) -> 27255766
C6: iv) Closing Bal, MTA pool, Dec 2041, SYD | F6: =$Y$329 -> 6126199.1
C7: e)
C8: =INDEX(ListDepMethods1,MATCH(F8,$F$41:$F$44,0)) -> Sum of Years Digits | E8: NPV | F8: =MAX(F41:F44) -> 7602001.9
E9: XNPV | F9: =MAX(G41:G44) -> 7597275.7
E10: =CaseData!$G$10 -> 44561 | F10: =DATE(F11,12,31) -> 44926 | G10: =DATE(G11,12,31) -> 45291 | H10: =DATE(H11,12,31) -> 45657 | I10: =DATE(I11,12,31) -> 46022 | J10: =DATE(J11,12,31) -> 46387 | K10: =DATE(K11,12,31) -> 46752 | L10: =DATE(L11,12,31) -> 47118 | M10: =DATE(M11,12,31) -> 47483 | ... AD10: =DATE(AD11,12,31) -> 53692
C11: Year | D11: Units | E11: =YEAR(E10) -> 2021 | F11: =YEAR(CaseData!$G$7) -> 2022 | G11: =F11+1 -> 2023 | H11: =G11+1 -> 2024 | I11: =H11+1 -> 2025 | J11: =I11+1 -> 2026 | K11: =J11+1 -> 2027 | L11: =K11+1 -> 2028 | M11: =L11+1 -> 2029 | N11: =M11+1 -> 2030 | ... AD11: =AC11+1 -> 2046
A12: 1 | C12: Summary
C13: Capex
B14: 1 | C14: {=INDEX(ListAssetClasses1,B14)} -> Short Term | D14: $ | F14: =SUMIFS(CaseData!$E$138:$E$437,CaseData!$F$138:$F$437,$C14,CaseData!$G$138:$G$437,F$11) -> 2724000 | G14: =SUMIFS(CaseData!$E$138:$E$437,CaseData!$F$138:$F$437,$C14,CaseData!$G$138:$G$437,G$11) -> 306000 | H14: =SUMIFS(CaseData!$E$138:$E$437,CaseData!$F$138:$F$437,$C14,CaseData!$G$138:$G$437,H$11) -> 934500 | I14: =SUMIFS(CaseData!$E$138:$E$437,CaseData!$F$138:$F$437,$C14,CaseData!$G$138:$G$437,I$11) -> 2535000 | J14: =SUMIFS(CaseData!$E$138:$E$437,CaseData!$F$138:$F$437,$C14,CaseData!$G$138:$G$437,J$11) -> 1273500 | K14: =SUMIFS(CaseData!$E$138:$E$437,CaseData!$F$138:$F$437,$C14,CaseData!$G$138:$G$437,K$11) -> 1741500 | L14: =SUMIFS(CaseData!$E$138:$E$437,CaseData!$F$138:$F$437,$C14,CaseData!$G$138:$G$437,L$11) -> 1219500 | M14: =SUMIFS(CaseData!$E$138:$E$437,CaseData!$F$138:$F$437,$C14,CaseData!$G$138:$G$437,M$11) -> 289500 | ... AD14: =SUMIFS(CaseData!$E$138:$E$437,CaseData!$F$138:$F$437,$C14,CaseData!$G$138:$G$437,AD$11) -> 1356000
B15: =B14+1 -> 2 | C15: {=INDEX(ListAssetClasses1,B15)} -> Medium Term | D15: $ | F15: =SUMIFS(CaseData!$E$138:$E$437,CaseData!$F$138:$F$437,$C15,CaseData!$G$138:$G$437,F$11) -> 2875500 | G15: =SUMIFS(CaseData!$E$138:$E$437,CaseData!$F$138:$F$437,$C15,CaseData!$G$138:$G$437,G$11) -> 835500 | H15: =SUMIFS(CaseData!$E$138:$E$437,CaseData!$F$138:$F$437,$C15,CaseData!$G$138:$G$437,H$11) -> 1041000 | I15: =SUMIFS(CaseData!$E$138:$E$437,CaseData!$F$138:$F$437,$C15,CaseData!$G$138:$G$437,I$11) -> 906000 | J15: =SUMIFS(CaseData!$E$138:$E$437,CaseData!$F$138:$F$437,$C15,CaseData!$G$138:$G$437,J$11) -> 904500 | K15: =SUMIFS(CaseData!$E$138:$E$437,CaseData!$F$138:$F$437,$C15,CaseData!$G$138:$G$437,K$11) -> 2680500 | L15: =SUMIFS(CaseData!$E$138:$E$437,CaseData!$F$138:$F$437,$C15,CaseData!$G$138:$G$437,L$11) -> 202500 | M15: =SUMIFS(CaseData!$E$138:$E$437,CaseData!$F$138:$F$437,$C15,CaseData!$G$138:$G$437,M$11) -> 1611000 | ... AD15: =SUMIFS(CaseData!$E$138:$E$437,CaseData!$F$138:$F$437,$C15,CaseData!$G$138:$G$437,AD$11) -> 2460000
B16: =B15+1 -> 3 | C16: {=INDEX(ListAssetClasses1,B16)} -> Long Term | D16: $ | F16: =SUMIFS(CaseData!$E$138:$E$437,CaseData!$F$138:$F$437,$C16,CaseData!$G$138:$G$437,F$11) -> 3393000 | G16: =SUMIFS(CaseData!$E$138:$E$437,CaseData!$F$138:$F$437,$C16,CaseData!$G$138:$G$437,G$11) -> 672000 | H16: =SUMIFS(CaseData!$E$138:$E$437,CaseData!$F$138:$F$437,$C16,CaseData!$G$138:$G$437,H$11) -> 2329500 | I16: =SUMIFS(CaseData!$E$138:$E$437,CaseData!$F$138:$F$437,$C16,CaseData!$G$138:$G$437,I$11) -> 567000 | J16: =SUMIFS(CaseData!$E$138:$E$437,CaseData!$F$138:$F$437,$C16,CaseData!$G$138:$G$437,J$11) -> 2409000 | K16: =SUMIFS(CaseData!$E$138:$E$437,CaseData!$F$138:$F$437,$C16,CaseData!$G$138:$G$437,K$11) -> 2518500 | L16: =SUMIFS(CaseData!$E$138:$E$437,CaseData!$F$138:$F$437,$C16,CaseData!$G$138:$G$437,L$11) -> 2092500 | M16: =SUMIFS(CaseData!$E$138:$E$437,CaseData!$F$138:$F$437,$C16,CaseData!$G$138:$G$437,M$11) -> 127500 | ... AD16: =SUMIFS(CaseData!$E$138:$E$437,CaseData!$F$138:$F$437,$C16,CaseData!$G$138:$G$437,AD$11) -> 2253000
C17: Total Capex | D17: $ | F17: =SUM(F14:F16) -> 8992500 | G17: =SUM(G14:G16) -> 1813500 | H17: =SUM(H14:H16) -> 4305000 | I17: =SUM(I14:I16) -> 4008000 | J17: =SUM(J14:J16) -> 4587000 | K17: =SUM(K14:K16) -> 6940500 | L17: =SUM(L14:L16) -> 3514500 | M17: =SUM(M14:M16) -> 2028000 | ... AD17: =SUM(AD14:AD16) -> 6069000
C19: Total Depreciation
C20: =CaseData!C22 -> Declining Balance | D20: $ | F20: =F51 -> 2262650.6 | G20: =G51 -> 1932965.3 | H20: =H51 -> 2316478.2 | I20: =I51 -> 3025304.1 | J20: =J51 -> 3134562.4 | K20: =K51 -> 3865176.9 | L20: =L51 -> 3607143.6 | M20: =M51 -> 3075229 | ... AD20: =AD51 -> 4514195.6
C21: =CaseData!C23 -> Straight Line | D21: $ | F21: =F83 -> 1005622.5 | G21: =G83 -> 1185695 | H21: =H83 -> 1609680 | I21: =I83 -> 2213310 | J21: =J83 -> 2693772.5 | K21: =K83 -> 2921250 | L21: =L83 -> 3246577.5 | M21: =M83 -> 3285147.5 | ... AD21: =AD83 -> 4468182.5
C22: =CaseData!C24 -> Units of Production | D22: $ | F22: =F197 -> 2010170.6 | G22: =G197 -> 1791988.8 | H22: =H197 -> 2162689.7 | I22: =I197 -> 2880936.7 | J22: =J197 -> 3127196.7 | K22: =K197 -> 3616872.3 | L22: =L197 -> 3556968.2 | M22: =M197 -> 3199680.7 | ... AD22: =AD197 -> 4497084.8
C23: =CaseData!C25 -> Sum of Years Digits | D23: $ | F23: =F317 -> 1762196 | G23: =G317 -> 1834160.7 | H23: =H317 -> 2298342.6 | I23: =I317 -> 2941126.6 | J23: =J317 -> 3222226.2 | K23: =K317 -> 3855943.1 | L23: =L317 -> 3841741.7 | M23: =M317 -> 3465064.5 | ... AD23: =AD317 -> 4543630.9
A25: =MAX(A$11:A24)+1 -> 2 | C25: Net PP&E
C26: Modeled Depn | D26: $ | E26: Straight Line | F26: =INDEX(F20:F23,MATCH($E$26,$C$20:$C$23,0)) -> 1005622.5 | G26: =INDEX(G20:G23,MATCH($E$26,$C$20:$C$23,0)) -> 1185695 | H26: =INDEX(H20:H23,MATCH($E$26,$C$20:$C$23,0)) -> 1609680 | I26: =INDEX(I20:I23,MATCH($E$26,$C$20:$C$23,0)) -> 2213310 | J26: =INDEX(J20:J23,MATCH($E$26,$C$20:$C$23,0)) -> 2693772.5 | K26: =INDEX(K20:K23,MATCH($E$26,$C$20:$C$23,0)) -> 2921250 | L26: =INDEX(L20:L23,MATCH($E$26,$C$20:$C$23,0)) -> 3246577.5 | M26: =INDEX(M20:M23,MATCH($E$26,$C$20:$C$23,0)) -> 3285147.5 | ... AD26: =INDEX(AD20:AD23,MATCH($E$26,$C$20:$C$23,0)) -> 4468182.5
C28: Net PP&E
C29: Opening Balance | D29: $ | F29: 0 | G29: =F32 -> 7986877.5 | H29: =G32 -> 8614682.5 | I29: =H32 -> 11310002 | J29: =I32 -> 13104692 | K29: =J32 -> 14997920 | L29: =K32 -> 19017170 | M29: =L32 -> 19285092 | N29: =M32 -> 18027945 | ... AD29: =AC32 -> 24835690
C30: New Capex | D30: $ | F30: =F17 -> 8992500 | G30: =G17 -> 1813500 | H30: =H17 -> 4305000 | I30: =I17 -> 4008000 | J30: =J17 -> 4587000 | K30: =K17 -> 6940500 | L30: =L17 -> 3514500 | M30: =M17 -> 2028000 | ... AD30: =AD17 -> 6069000
C31: Depreciation | D31: $ | F31: =-F26 -> -1005622.5 | G31: =-G26 -> -1185695 | H31: =-H26 -> -1609680 | I31: =-I26 -> -2213310 | J31: =-J26 -> -2693772.5 | K31: =-K26 -> -2921250 | L31: =-L26 -> -3246577.5 | M31: =-M26 -> -3285147.5 | ... AD31: =-AD26 -> -4468182.5
C32: Closing Balance | D32: $ | F32: =SUM(F29:F31) -> 7986877.5 | G32: =SUM(G29:G31) -> 8614682.5 | H32: =SUM(H29:H31) -> 11310002 | I32: =SUM(I29:I31) -> 13104692 | J32: =SUM(J29:J31) -> 14997920 | K32: =SUM(K29:K31) -> 19017170 | L32: =SUM(L29:L31) -> 19285092 | M32: =SUM(M29:M31) -> 18027945 | ... AD32: =SUM(AD29:AD31) -> 26436508
A34: =MAX(A$11:A33)+1 -> 3 | C34: Tax Deduction
C35: Tax Rate | D35: =CaseData!$G$8 -> 0.25
C36: Tax Deduction | D36: $ | E36: 0 | F36: =-$D$35*F31 -> 251405.62 | G36: =-$D$35*G31 -> 296423.75 | H36: =-$D$35*H31 -> 402420 | I36: =-$D$35*I31 -> 553327.5 | J36: =-$D$35*J31 -> 673443.12 | K36: =-$D$35*K31 -> 730312.5 | L36: =-$D$35*L31 -> 811644.38 | M36: =-$D$35*M31 -> 821286.88 | ... AD36: =-$D$35*AD31 -> 1117045.6
C37: NPV | D37: =CaseData!$G$9 -> 0.1 | E37: =NPV($D$37,F36:AD36) -> 6602901
C38: XNPV | D38: =CaseData!$G$9 -> 0.1 | E38: =XNPV($D$37,E36:AD36,E10:AD10) -> 6598440.4
F39: NPV | G39: XNPV
F40: =E37 -> 6602901 | G40: =E38 -> 6598440.4
B41: 1 | D41: $ | E41: {=INDEX(ListDepMethods1,B41)} -> Declining Balance | F41: 7549234.7 | G41: 7544640.6
B42: =B41+1 -> 2 | D42: $ | E42: {=INDEX(ListDepMethods1,B42)} -> Straight Line | F42: 6602901 | G42: 6598440.4
B43: =B42+1 -> 3 | D43: $ | E43: {=INDEX(ListDepMethods1,B43)} -> Units of Production | F43: 7445364 | G43: 7440731.6
B44: =B43+1 -> 4 | D44: $ | E44: {=INDEX(ListDepMethods1,B44)} -> Sum of Years Digits | F44: 7602001.9 | G44: 7597275.7
A46: =MAX(A$11:A45)+1 -> 4 | C46: =CaseData!C22 -> Declining Balance
C47: Total Depreciation
B48: 1 | C48: {=INDEX(ListAssetClasses1,B48)} -> Short Term | D48: $ | F48: =-F58 -> 1164510 | G48: =-G58 -> 771295.5 | H48: =-H58 -> 823711.28 | I48: =-I58 -> 1536753.7 | J48: =-J58 -> 1389635.8 | K48: =-K58 -> 1508790.9 | L48: =-L58 -> 1351171.3 | M48: =-M58 -> 866905.44 | ... AD48: =-AD58 -> 1318117.9
B49: =B48+1 -> 2 | C49: {=INDEX(ListAssetClasses1,B49)} -> Medium Term | D49: $ | F49: =-F66 -> 614638.12 | G49: =-G66 -> 654932.67 | H49: =-H66 -> 730086.57 | I49: =-I66 -> 759474.59 | J49: =-J66 -> 781929.68 | K49: =-K66 -> 1178952.4 | L49: =-L66 -> 956972.47 | M49: =-M66 -> 1086004.9 | ... AD49: =-AD66 -> 1813873.9
B50: =B49+1 -> 3 | C50: {=INDEX(ListAssetClasses1,B50)} -> Long Term | D50: $ | F50: =-F74 -> 483502.5 | G50: =-G74 -> 506737.12 | H50: =-H74 -> 762680.31 | I50: =-I74 -> 729075.76 | J50: =-J74 -> 962996.9 | K50: =-K74 -> 1177433.6 | L50: =-L74 -> 1298999.8 | M50: =-M74 -> 1122318.6 | ... AD50: =-AD74 -> 1382203.8
C51: Total Depreciation | D51: $ | F51: =SUM(F48:F50) -> 2262650.6 | G51: =SUM(G48:G50) -> 1932965.3 | H51: =SUM(H48:H50) -> 2316478.2 | I51: =SUM(I48:I50) -> 3025304.1 | J51: =SUM(J48:J50) -> 3134562.4 | K51: =SUM(K48:K50) -> 3865176.9 | L51: =SUM(L48:L50) -> 3607143.6 | M51: =SUM(M48:M50) -> 3075229 | ... AD51: =SUM(AD48:AD50) -> 4514195.6
B53: 1 | C53: {=INDEX(ListAssetClasses1,B53)} -> Short Term | D53: =INDEX(CaseData!$G$32:$I$32,MATCH($C53,CaseData!$G$31:$I$31,0)) -> 0.45
C54: Opening Balance | D54: $ | F54: =$F$29 -> 0 | G54: =F59 -> 1559490 | H54: =G59 -> 1094194.5 | I54: =H59 -> 1204983.2 | J54: =I59 -> 2203229.5 | K54: =J59 -> 2087093.7 | L54: =K59 -> 2319802.8 | M54: =L59 -> 2188131.5 | N54: =M59 -> 1610726.1 | ... AD54: =AC59 -> 3473800.9
C55: New Capex | D55: $ | F55: {=INDEX(F$14:F$16,$B53)} -> 2724000 | G55: {=INDEX(G$14:G$16,$B53)} -> 306000 | H55: {=INDEX(H$14:H$16,$B53)} -> 934500 | I55: {=INDEX(I$14:I$16,$B53)} -> 2535000 | J55: {=INDEX(J$14:J$16,$B53)} -> 1273500 | K55: {=INDEX(K$14:K$16,$B53)} -> 1741500 | L55: {=INDEX(L$14:L$16,$B53)} -> 1219500 | M55: {=INDEX(M$14:M$16,$B53)} -> 289500 | ... AD55: {=INDEX(AD$14:AD$16,$B53)} -> 1356000
C56: Salvage Value | D56: $ | E56: =CaseData!$G$11 -> 0.05 | F56: =SUM($F55:F55)*$E56 -> 136200 | G56: =SUM($F55:G55)*$E56 -> 151500 | H56: =SUM($F55:H55)*$E56 -> 198225 | I56: =SUM($F55:I55)*$E56 -> 324975 | J56: =SUM($F55:J55)*$E56 -> 388650 | K56: =SUM($F55:K55)*$E56 -> 475725 | L56: =SUM($F55:L55)*$E56 -> 536700 | M56: =SUM($F55:M55)*$E56 -> 551175 | ... AD56: =SUM($F55:AD55)*$E56 -> 1900650
C57: Depreciable Amount | D57: $ | F57: =SUM(F54:F55)-F56 -> 2587800 | G57: =SUM(G54:G55)-G56 -> 1713990 | H57: =SUM(H54:H55)-H56 -> 1830469.5 | I57: =SUM(I54:I55)-I56 -> 3415008.2 | J57: =SUM(J54:J55)-J56 -> 3088079.5 | K57: =SUM(K54:K55)-K56 -> 3352868.7 | L57: =SUM(L54:L55)-L56 -> 3002602.8 | M57: =SUM(M54:M55)-M56 -> 1926456.5 | ... AD57: =SUM(AD54:AD55)-AD56 -> 2929150.9
C58: Depreciation | D58: $ | F58: =-F57*$D53 -> -1164510 | G58: =-G57*$D53 -> -771295.5 | H58: =-H57*$D53 -> -823711.28 | I58: =-I57*$D53 -> -1536753.7 | J58: =-J57*$D53 -> -1389635.8 | K58: =-K57*$D53 -> -1508790.9 | L58: =-L57*$D53 -> -1351171.3 | M58: =-M57*$D53 -> -866905.44 | ... AD58: =-AD57*$D53 -> -1318117.9
C59: Closing Balance | D59: $ | F59: =SUM(F54:F55,F58) -> 1559490 | G59: =SUM(G54:G55,G58) -> 1094194.5 | H59: =SUM(H54:H55,H58) -> 1204983.2 | I59: =SUM(I54:I55,I58) -> 2203229.5 | J59: =SUM(J54:J55,J58) -> 2087093.7 | K59: =SUM(K54:K55,K58) -> 2319802.8 | L59: =SUM(L54:L55,L58) -> 2188131.5 | M59: =SUM(M54:M55,M58) -> 1610726.1 | ... AD59: =SUM(AD54:AD55,AD58) -> 3511683
B61: 2 | C61: {=INDEX(ListAssetClasses1,B61)} -> Medium Term | D61: =INDEX(CaseData!$G$32:$I$32,MATCH($C61,CaseData!$G$31:$I$31,0)) -> 0.225
C62: Opening Balance | D62: $ | F62: =$F$29 -> 0 | G62: =F67 -> 2260861.9 | H62: =G67 -> 2441429.2 | I62: =H67 -> 2752342.6 | J62: =I67 -> 2898868 | K62: =J67 -> 3021438.4 | L62: =K67 -> 4522986 | M62: =L67 -> 3768513.5 | N62: =M67 -> 4293508.6 | ... AD62: =AC67 -> 7688911.8
C63: New Capex | D63: $ | F63: {=INDEX(F$14:F$16,$B61)} -> 2875500 | G63: {=INDEX(G$14:G$16,$B61)} -> 835500 | H63: {=INDEX(H$14:H$16,$B61)} -> 1041000 | I63: {=INDEX(I$14:I$16,$B61)} -> 906000 | J63: {=INDEX(J$14:J$16,$B61)} -> 904500 | K63: {=INDEX(K$14:K$16,$B61)} -> 2680500 | L63: {=INDEX(L$14:L$16,$B61)} -> 202500 | M63: {=INDEX(M$14:M$16,$B61)} -> 1611000 | ... AD63: {=INDEX(AD$14:AD$16,$B61)} -> 2460000
C64: Salvage Value | D64: $ | E64: =CaseData!$G$11 -> 0.05 | F64: =SUM($F63:F63)*$E64 -> 143775 | G64: =SUM($F63:G63)*$E64 -> 185550 | H64: =SUM($F63:H63)*$E64 -> 237600 | I64: =SUM($F63:I63)*$E64 -> 282900 | J64: =SUM($F63:J63)*$E64 -> 328125 | K64: =SUM($F63:K63)*$E64 -> 462150 | L64: =SUM($F63:L63)*$E64 -> 472275 | M64: =SUM($F63:M63)*$E64 -> 552825 | ... AD64: =SUM($F63:AD63)*$E64 -> 2087250
C65: Depreciable Amount | D65: $ | F65: =SUM(F62:F63)-F64 -> 2731725 | G65: =SUM(G62:G63)-G64 -> 2910811.9 | H65: =SUM(H62:H63)-H64 -> 3244829.2 | I65: =SUM(I62:I63)-I64 -> 3375442.6 | J65: =SUM(J62:J63)-J64 -> 3475243 | K65: =SUM(K62:K63)-K64 -> 5239788.4 | L65: =SUM(L62:L63)-L64 -> 4253211 | M65: =SUM(M62:M63)-M64 -> 4826688.5 | ... AD65: =SUM(AD62:AD63)-AD64 -> 8061661.8
C66: Depreciation | D66: $ | F66: =-F65*$D61 -> -614638.12 | G66: =-G65*$D61 -> -654932.67 | H66: =-H65*$D61 -> -730086.57 | I66: =-I65*$D61 -> -759474.59 | J66: =-J65*$D61 -> -781929.68 | K66: =-K65*$D61 -> -1178952.4 | L66: =-L65*$D61 -> -956972.47 | M66: =-M65*$D61 -> -1086004.9 | ... AD66: =-AD65*$D61 -> -1813873.9
C67: Closing Balance | D67: $ | F67: =SUM(F62:F63,F66) -> 2260861.9 | G67: =SUM(G62:G63,G66) -> 2441429.2 | H67: =SUM(H62:H63,H66) -> 2752342.6 | I67: =SUM(I62:I63,I66) -> 2898868 | J67: =SUM(J62:J63,J66) -> 3021438.4 | K67: =SUM(K62:K63,K66) -> 4522986 | L67: =SUM(L62:L63,L66) -> 3768513.5 | M67: =SUM(M62:M63,M66) -> 4293508.6 | ... AD67: =SUM(AD62:AD63,AD66) -> 8335037.9
B69: 3 | C69: {=INDEX(ListAssetClasses1,B69)} -> Long Term | D69: =INDEX(CaseData!$G$32:$I$32,MATCH($C69,CaseData!$G$31:$I$31,0)) -> 0.15
C70: Opening Balance | D70: $ | F70: =$F$29 -> 0 | G70: =F75 -> 2909497.5 | H70: =G75 -> 3074760.4 | I70: =H75 -> 4641580.1 | J70: =I75 -> 4479504.3 | K70: =J75 -> 5925507.4 | L70: =K75 -> 7266573.8 | M70: =L75 -> 8060074 | N70: =M75 -> 7065255.4 | ... AD70: =AC75 -> 8799717.1
C71: New Capex | D71: $ | F71: {=INDEX(F$14:F$16,$B69)} -> 3393000 | G71: {=INDEX(G$14:G$16,$B69)} -> 672000 | H71: {=INDEX(H$14:H$16,$B69)} -> 2329500 | I71: {=INDEX(I$14:I$16,$B69)} -> 567000 | J71: {=INDEX(J$14:J$16,$B69)} -> 2409000 | K71: {=INDEX(K$14:K$16,$B69)} -> 2518500 | L71: {=INDEX(L$14:L$16,$B69)} -> 2092500 | M71: {=INDEX(M$14:M$16,$B69)} -> 127500 | ... AD71: {=INDEX(AD$14:AD$16,$B69)} -> 2253000
C72: Salvage Value | D72: $ | E72: =CaseData!$G$11 -> 0.05 | F72: =SUM($F71:F71)*$E72 -> 169650 | G72: =SUM($F71:G71)*$E72 -> 203250 | H72: =SUM($F71:H71)*$E72 -> 319725 | I72: =SUM($F71:I71)*$E72 -> 348075 | J72: =SUM($F71:J71)*$E72 -> 468525 | K72: =SUM($F71:K71)*$E72 -> 594450 | L72: =SUM($F71:L71)*$E72 -> 699075 | M72: =SUM($F71:M71)*$E72 -> 705450 | ... AD72: =SUM($F71:AD71)*$E72 -> 1838025
C73: Depreciable Amount | D73: $ | F73: =SUM(F70:F71)-F72 -> 3223350 | G73: =SUM(G70:G71)-G72 -> 3378247.5 | H73: =SUM(H70:H71)-H72 -> 5084535.4 | I73: =SUM(I70:I71)-I72 -> 4860505.1 | J73: =SUM(J70:J71)-J72 -> 6419979.3 | K73: =SUM(K70:K71)-K72 -> 7849557.4 | L73: =SUM(L70:L71)-L72 -> 8659998.8 | M73: =SUM(M70:M71)-M72 -> 7482124 | ... AD73: =SUM(AD70:AD71)-AD72 -> 9214692.1
C74: Depreciation | D74: $ | F74: =-F73*$D69 -> -483502.5 | G74: =-G73*$D69 -> -506737.12 | H74: =-H73*$D69 -> -762680.31 | I74: =-I73*$D69 -> -729075.76 | J74: =-J73*$D69 -> -962996.9 | K74: =-K73*$D69 -> -1177433.6 | L74: =-L73*$D69 -> -1298999.8 | M74: =-M73*$D69 -> -1122318.6 | ... AD74: =-AD73*$D69 -> -1382203.8
C75: Closing Balance | D75: $ | F75: =SUM(F70:F71,F74) -> 2909497.5 | G75: =SUM(G70:G71,G74) -> 3074760.4 | H75: =SUM(H70:H71,H74) -> 4641580.1 | I75: =SUM(I70:I71,I74) -> 4479504.3 | J75: =SUM(J70:J71,J74) -> 5925507.4 | K75: =SUM(K70:K71,K74) -> 7266573.8 | L75: =SUM(L70:L71,L74) -> 8060074 | M75: =SUM(M70:M71,M74) -> 7065255.4 | ... AD75: =SUM(AD70:AD71,AD74) -> 9670513.3
A77: =MAX(A$11:A76)+1 -> 5 | C77: Straight Line
C78: Summary
C79: Total Depreciation | D79: Years
B80: 1 | C80: {=INDEX(ListAssetClasses1,B80)} -> Short Term | D80: =INDEX(CaseData!$G$33:$I$33,MATCH(C80,CaseData!$G$31:$I$31,0)) -> 5 | F80: =F131 -> 517560 | G80: =G131 -> 575700 | H80: =H131 -> 753255 | I80: =I131 -> 1234905 | J80: =J131 -> 1476870 | K80: =K131 -> 1290195 | L80: =L131 -> 1463760 | M80: =M131 -> 1341210 | ... AD80: =AD131 -> 1433265
B81: =B80+1 -> 2 | C81: {=INDEX(ListAssetClasses1,B81)} -> Medium Term | D81: =INDEX(CaseData!$G$33:$I$33,MATCH(C81,CaseData!$G$31:$I$31,0)) -> 10 | F81: =F160 -> 273172.5 | G81: =G160 -> 352545 | H81: =H160 -> 451440 | I81: =I160 -> 537510 | J81: =J160 -> 623437.5 | K81: =K160 -> 878085 | L81: =L160 -> 897322.5 | M81: =M160 -> 1050367.5 | ... AD81: =AD160 -> 1654567.5
B82: =B81+1 -> 3 | C82: {=INDEX(ListAssetClasses1,B82)} -> Long Term | D82: =INDEX(CaseData!$G$33:$I$33,MATCH(C82,CaseData!$G$31:$I$31,0)) -> 15 | F82: =F189 -> 214890 | G82: =G189 -> 257450 | H82: =H189 -> 404985 | I82: =I189 -> 440895 | J82: =J189 -> 593465 | K82: =K189 -> 752970 | L82: =L189 -> 885495 | M82: =M189 -> 893570 | ... AD82: =AD189 -> 1380350
C83: Total Depreciation | D83: $ | F83: =SUM(F80:F82) -> 1005622.5 | G83: =SUM(G80:G82) -> 1185695 | H83: =SUM(H80:H82) -> 1609680 | I83: =SUM(I80:I82) -> 2213310 | J83: =SUM(J80:J82) -> 2693772.5 | K83: =SUM(K80:K82) -> 2921250 | L83: =SUM(L80:L82) -> 3246577.5 | M83: =SUM(M80:M82) -> 3285147.5 | ... AD83: =SUM(AD80:AD82) -> 4468182.5
B85: 1 | C85: {=INDEX(ListAssetClasses1,B85)} -> Short Term
C86: Opening Balance | D86: $ | F86: =$F$29 -> 0 | G86: =F89 -> 2206440 | H86: =G89 -> 1936740 | I86: =H89 -> 2117985 | J86: =I89 -> 3418080 | K86: =J89 -> 3214710 | L86: =K89 -> 3666015 | M86: =L89 -> 3421755 | N86: =M89 -> 2370045 | ... AD86: =AC89 -> 4613880
C87: New Capex | D87: $ | F87: {=INDEX(F$14:F$16,$B85)} -> 2724000 | G87: {=INDEX(G$14:G$16,$B85)} -> 306000 | H87: {=INDEX(H$14:H$16,$B85)} -> 934500 | I87: {=INDEX(I$14:I$16,$B85)} -> 2535000 | J87: {=INDEX(J$14:J$16,$B85)} -> 1273500 | K87: {=INDEX(K$14:K$16,$B85)} -> 1741500 | L87: {=INDEX(L$14:L$16,$B85)} -> 1219500 | M87: {=INDEX(M$14:M$16,$B85)} -> 289500 | ... AD87: {=INDEX(AD$14:AD$16,$B85)} -> 1356000
C88: Depreciation | D88: $ | F88: =-F80 -> -517560 | G88: =-G80 -> -575700 | H88: =-H80 -> -753255 | I88: =-I80 -> -1234905 | J88: =-J80 -> -1476870 | K88: =-K80 -> -1290195 | L88: =-L80 -> -1463760 | M88: =-M80 -> -1341210 | ... AD88: =-AD80 -> -1433265
C89: Closing Balance | D89: $ | F89: =SUM(F86:F88) -> 2206440 | G89: =SUM(G86:G88) -> 1936740 | H89: =SUM(H86:H88) -> 2117985 | I89: =SUM(I86:I88) -> 3418080 | J89: =SUM(J86:J88) -> 3214710 | K89: =SUM(K86:K88) -> 3666015 | L89: =SUM(L86:L88) -> 3421755 | M89: =SUM(M86:M88) -> 2370045 | ... AD89: =SUM(AD86:AD88) -> 4536615
B91: 2 | C91: {=INDEX(ListAssetClasses1,B91)} -> Medium Term
C92: Opening Balance | D92: $ | F92: =$F$29 -> 0 | G92: =F95 -> 2602327.5 | H92: =G95 -> 3085282.5 | I92: =H95 -> 3674842.5 | J92: =I95 -> 4043332.5 | K92: =J95 -> 4324395 | L92: =K95 -> 6126810 | M92: =L95 -> 5431987.5 | N92: =M95 -> 5992620 | ... AD92: =AC95 -> 9501360
C93: New Capex | D93: $ | F93: {=INDEX(F$14:F$16,$B91)} -> 2875500 | G93: {=INDEX(G$14:G$16,$B91)} -> 835500 | H93: {=INDEX(H$14:H$16,$B91)} -> 1041000 | I93: {=INDEX(I$14:I$16,$B91)} -> 906000 | J93: {=INDEX(J$14:J$16,$B91)} -> 904500 | K93: {=INDEX(K$14:K$16,$B91)} -> 2680500 | L93: {=INDEX(L$14:L$16,$B91)} -> 202500 | M93: {=INDEX(M$14:M$16,$B91)} -> 1611000 | ... AD93: {=INDEX(AD$14:AD$16,$B91)} -> 2460000
C94: Depreciation | D94: $ | F94: =-F81 -> -273172.5 | G94: =-G81 -> -352545 | H94: =-H81 -> -451440 | I94: =-I81 -> -537510 | J94: =-J81 -> -623437.5 | K94: =-K81 -> -878085 | L94: =-L81 -> -897322.5 | M94: =-M81 -> -1050367.5 | ... AD94: =-AD81 -> -1654567.5
C95: Closing Balance | D95: $ | F95: =SUM(F92:F94) -> 2602327.5 | G95: =SUM(G92:G94) -> 3085282.5 | H95: =SUM(H92:H94) -> 3674842.5 | I95: =SUM(I92:I94) -> 4043332.5 | J95: =SUM(J92:J94) -> 4324395 | K95: =SUM(K92:K94) -> 6126810 | L95: =SUM(L92:L94) -> 5431987.5 | M95: =SUM(M92:M94) -> 5992620 | ... AD95: =SUM(AD92:AD94) -> 10306792
B97: 3 | C97: {=INDEX(ListAssetClasses1,B97)} -> Long Term
C98: Opening Balance | D98: $ | F98: =$F$29 -> 0 | G98: =F101 -> 3178110 | H98: =G101 -> 3592660 | I98: =H101 -> 5517175 | J98: =I101 -> 5643280 | K98: =J101 -> 7458815 | L98: =K101 -> 9224345 | M98: =L101 -> 10431350 | N98: =M101 -> 9665280 | ... AD98: =AC101 -> 10720450
C99: New Capex | D99: $ | F99: {=INDEX(F$14:F$16,$B97)} -> 3393000 | G99: {=INDEX(G$14:G$16,$B97)} -> 672000 | H99: {=INDEX(H$14:H$16,$B97)} -> 2329500 | I99: {=INDEX(I$14:I$16,$B97)} -> 567000 | J99: {=INDEX(J$14:J$16,$B97)} -> 2409000 | K99: {=INDEX(K$14:K$16,$B97)} -> 2518500 | L99: {=INDEX(L$14:L$16,$B97)} -> 2092500 | M99: {=INDEX(M$14:M$16,$B97)} -> 127500 | ... AD99: {=INDEX(AD$14:AD$16,$B97)} -> 2253000
C100: Depreciation | D100: $ | F100: =-F82 -> -214890 | G100: =-G82 -> -257450 | H100: =-H82 -> -404985 | I100: =-I82 -> -440895 | J100: =-J82 -> -593465 | K100: =-K82 -> -752970 | L100: =-L82 -> -885495 | M100: =-M82 -> -893570 | ... AD100: =-AD82 -> -1380350
C101: Closing Balance | D101: $ | F101: =SUM(F98:F100) -> 3178110 | G101: =SUM(G98:G100) -> 3592660 | H101: =SUM(H98:H100) -> 5517175 | I101: =SUM(I98:I100) -> 5643280 | J101: =SUM(J98:J100) -> 7458815 | K101: =SUM(K98:K100) -> 9224345 | L101: =SUM(L98:L100) -> 10431350 | M101: =SUM(M98:M100) -> 9665280 | ... AD101: =SUM(AD98:AD100) -> 11593100
C103: Straight Line Depreciation Waterfall Schedules
B104: 1 | C104: {=INDEX(ListAssetClasses1,B104)} -> Short Term | D104: {=INDEX($D$80:$D$82,B104)} -> 5
C105: Capex Year | D105: Depreciable | E105: Depreciable Amount | G105: =1-CaseData!$G$11 -> 0.95
B106: =B104 -> 1 | C106: =$F$11 -> 2022 | D106: {=INDEX($F$14:$AD$16,$B106,MATCH($C106,$F$11:$AD$11,0))*$G$105} -> 2587800 | F106: =IF(F$11<$C106,0,MIN($D106/$D$104,$D106-SUM($E106:E106))) -> 517560 | G106: =IF(G$11<$C106,0,MIN($D106/$D$104,$D106-SUM($E106:F106))) -> 517560 | H106: =IF(H$11<$C106,0,MIN($D106/$D$104,$D106-SUM($E106:G106))) -> 517560 | I106: =IF(I$11<$C106,0,MIN($D106/$D$104,$D106-SUM($E106:H106))) -> 517560 | J106: =IF(J$11<$C106,0,MIN($D106/$D$104,$D106-SUM($E106:I106))) -> 517560 | K106: =IF(K$11<$C106,0,MIN($D106/$D$104,$D106-SUM($E106:J106))) -> 0 | L106: =IF(L$11<$C106,0,MIN($D106/$D$104,$D106-SUM($E106:K106))) -> 0 | M106: =IF(M$11<$C106,0,MIN($D106/$D$104,$D106-SUM($E106:L106))) -> 0 | ... AD106: =IF(AD$11<$C106,0,MIN($D106/$D$104,$D106-SUM($E106:AC106))) -> 0
B107: =B106 -> 1 | C107: =C106+1 -> 2023 | D107: {=INDEX($F$14:$AD$16,$B107,MATCH($C107,$F$11:$AD$11,0))*$G$105} -> 290700 | F107: =IF(F$11<$C107,0,MIN($D107/$D$104,$D107-SUM($E107:E107))) -> 0 | G107: =IF(G$11<$C107,0,MIN($D107/$D$104,$D107-SUM($E107:F107))) -> 58140 | H107: =IF(H$11<$C107,0,MIN($D107/$D$104,$D107-SUM($E107:G107))) -> 58140 | I107: =IF(I$11<$C107,0,MIN($D107/$D$104,$D107-SUM($E107:H107))) -> 58140 | J107: =IF(J$11<$C107,0,MIN($D107/$D$104,$D107-SUM($E107:I107))) -> 58140 | K107: =IF(K$11<$C107,0,MIN($D107/$D$104,$D107-SUM($E107:J107))) -> 58140 | L107: =IF(L$11<$C107,0,MIN($D107/$D$104,$D107-SUM($E107:K107))) -> 0 | M107: =IF(M$11<$C107,0,MIN($D107/$D$104,$D107-SUM($E107:L107))) -> 0 | ... AD107: =IF(AD$11<$C107,0,MIN($D107/$D$104,$D107-SUM($E107:AC107))) -> 0
B108: =B107 -> 1 | C108: =C107+1 -> 2024 | D108: {=INDEX($F$14:$AD$16,$B108,MATCH($C108,$F$11:$AD$11,0))*$G$105} -> 887775 | F108: =IF(F$11<$C108,0,MIN($D108/$D$104,$D108-SUM($E108:E108))) -> 0 | G108: =IF(G$11<$C108,0,MIN($D108/$D$104,$D108-SUM($E108:F108))) -> 0 | H108: =IF(H$11<$C108,0,MIN($D108/$D$104,$D108-SUM($E108:G108))) -> 177555 | I108: =IF(I$11<$C108,0,MIN($D108/$D$104,$D108-SUM($E108:H108))) -> 177555 | J108: =IF(J$11<$C108,0,MIN($D108/$D$104,$D108-SUM($E108:I108))) -> 177555 | K108: =IF(K$11<$C108,0,MIN($D108/$D$104,$D108-SUM($E108:J108))) -> 177555 | L108: =IF(L$11<$C108,0,MIN($D108/$D$104,$D108-SUM($E108:K108))) -> 177555 | M108: =IF(M$11<$C108,0,MIN($D108/$D$104,$D108-SUM($E108:L108))) -> 0 | ... AD108: =IF(AD$11<$C108,0,MIN($D108/$D$104,$D108-SUM($E108:AC108))) -> 0
B109: =B108 -> 1 | C109: =C108+1 -> 2025 | D109: {=INDEX($F$14:$AD$16,$B109,MATCH($C109,$F$11:$AD$11,0))*$G$105} -> 2408250 | F109: =IF(F$11<$C109,0,MIN($D109/$D$104,$D109-SUM($E109:E109))) -> 0 | G109: =IF(G$11<$C109,0,MIN($D109/$D$104,$D109-SUM($E109:F109))) -> 0 | H109: =IF(H$11<$C109,0,MIN($D109/$D$104,$D109-SUM($E109:G109))) -> 0 | I109: =IF(I$11<$C109,0,MIN($D109/$D$104,$D109-SUM($E109:H109))) -> 481650 | J109: =IF(J$11<$C109,0,MIN($D109/$D$104,$D109-SUM($E109:I109))) -> 481650 | K109: =IF(K$11<$C109,0,MIN($D109/$D$104,$D109-SUM($E109:J109))) -> 481650 | L109: =IF(L$11<$C109,0,MIN($D109/$D$104,$D109-SUM($E109:K109))) -> 481650 | M109: =IF(M$11<$C109,0,MIN($D109/$D$104,$D109-SUM($E109:L109))) -> 481650 | ... AD109: =IF(AD$11<$C109,0,MIN($D109/$D$104,$D109-SUM($E109:AC109))) -> 0
B110: =B109 -> 1 | C110: =C109+1 -> 2026 | D110: {=INDEX($F$14:$AD$16,$B110,MATCH($C110,$F$11:$AD$11,0))*$G$105} -> 1209825 | F110: =IF(F$11<$C110,0,MIN($D110/$D$104,$D110-SUM($E110:E110))) -> 0 | G110: =IF(G$11<$C110,0,MIN($D110/$D$104,$D110-SUM($E110:F110))) -> 0 | H110: =IF(H$11<$C110,0,MIN($D110/$D$104,$D110-SUM($E110:G110))) -> 0 | I110: =IF(I$11<$C110,0,MIN($D110/$D$104,$D110-SUM($E110:H110))) -> 0 | J110: =IF(J$11<$C110,0,MIN($D110/$D$104,$D110-SUM($E110:I110))) -> 241965 | K110: =IF(K$11<$C110,0,MIN($D110/$D$104,$D110-SUM($E110:J110))) -> 241965 | L110: =IF(L$11<$C110,0,MIN($D110/$D$104,$D110-SUM($E110:K110))) -> 241965 | M110: =IF(M$11<$C110,0,MIN($D110/$D$104,$D110-SUM($E110:L110))) -> 241965 | ... AD110: =IF(AD$11<$C110,0,MIN($D110/$D$104,$D110-SUM($E110:AC110))) -> 0
B111: =B110 -> 1 | C111: =C110+1 -> 2027 | D111: {=INDEX($F$14:$AD$16,$B111,MATCH($C111,$F$11:$AD$11,0))*$G$105} -> 1654425 | F111: =IF(F$11<$C111,0,MIN($D111/$D$104,$D111-SUM($E111:E111))) -> 0 | G111: =IF(G$11<$C111,0,MIN($D111/$D$104,$D111-SUM($E111:F111))) -> 0 | H111: =IF(H$11<$C111,0,MIN($D111/$D$104,$D111-SUM($E111:G111))) -> 0 | I111: =IF(I$11<$C111,0,MIN($D111/$D$104,$D111-SUM($E111:H111))) -> 0 | J111: =IF(J$11<$C111,0,MIN($D111/$D$104,$D111-SUM($E111:I111))) -> 0 | K111: =IF(K$11<$C111,0,MIN($D111/$D$104,$D111-SUM($E111:J111))) -> 330885 | L111: =IF(L$11<$C111,0,MIN($D111/$D$104,$D111-SUM($E111:K111))) -> 330885 | M111: =IF(M$11<$C111,0,MIN($D111/$D$104,$D111-SUM($E111:L111))) -> 330885 | ... AD111: =IF(AD$11<$C111,0,MIN($D111/$D$104,$D111-SUM($E111:AC111))) -> 0
B112: =B111 -> 1 | C112: =C111+1 -> 2028 | D112: {=INDEX($F$14:$AD$16,$B112,MATCH($C112,$F$11:$AD$11,0))*$G$105} -> 1158525 | F112: =IF(F$11<$C112,0,MIN($D112/$D$104,$D112-SUM($E112:E112))) -> 0 | G112: =IF(G$11<$C112,0,MIN($D112/$D$104,$D112-SUM($E112:F112))) -> 0 | H112: =IF(H$11<$C112,0,MIN($D112/$D$104,$D112-SUM($E112:G112))) -> 0 | I112: =IF(I$11<$C112,0,MIN($D112/$D$104,$D112-SUM($E112:H112))) -> 0 | J112: =IF(J$11<$C112,0,MIN($D112/$D$104,$D112-SUM($E112:I112))) -> 0 | K112: =IF(K$11<$C112,0,MIN($D112/$D$104,$D112-SUM($E112:J112))) -> 0 | L112: =IF(L$11<$C112,0,MIN($D112/$D$104,$D112-SUM($E112:K112))) -> 231705 | M112: =IF(M$11<$C112,0,MIN($D112/$D$104,$D112-SUM($E112:L112))) -> 231705 | ... AD112: =IF(AD$11<$C112,0,MIN($D112/$D$104,$D112-SUM($E112:AC112))) -> 0
B113: =B112 -> 1 | C113: =C112+1 -> 2029 | D113: {=INDEX($F$14:$AD$16,$B113,MATCH($C113,$F$11:$AD$11,0))*$G$105} -> 275025 | F113: =IF(F$11<$C113,0,MIN($D113/$D$104,$D113-SUM($E113:E113))) -> 0 | G113: =IF(G$11<$C113,0,MIN($D113/$D$104,$D113-SUM($E113:F113))) -> 0 | H113: =IF(H$11<$C113,0,MIN($D113/$D$104,$D113-SUM($E113:G113))) -> 0 | I113: =IF(I$11<$C113,0,MIN($D113/$D$104,$D113-SUM($E113:H113))) -> 0 | J113: =IF(J$11<$C113,0,MIN($D113/$D$104,$D113-SUM($E113:I113))) -> 0 | K113: =IF(K$11<$C113,0,MIN($D113/$D$104,$D113-SUM($E113:J113))) -> 0 | L113: =IF(L$11<$C113,0,MIN($D113/$D$104,$D113-SUM($E113:K113))) -> 0 | M113: =IF(M$11<$C113,0,MIN($D113/$D$104,$D113-SUM($E113:L113))) -> 55005 | ... AD113: =IF(AD$11<$C113,0,MIN($D113/$D$104,$D113-SUM($E113:AC113))) -> 0
B114: =B113 -> 1 | C114: =C113+1 -> 2030 | D114: {=INDEX($F$14:$AD$16,$B114,MATCH($C114,$F$11:$AD$11,0))*$G$105} -> 1054500 | F114: =IF(F$11<$C114,0,MIN($D114/$D$104,$D114-SUM($E114:E114))) -> 0 | G114: =IF(G$11<$C114,0,MIN($D114/$D$104,$D114-SUM($E114:F114))) -> 0 | H114: =IF(H$11<$C114,0,MIN($D114/$D$104,$D114-SUM($E114:G114))) -> 0 | I114: =IF(I$11<$C114,0,MIN($D114/$D$104,$D114-SUM($E114:H114))) -> 0 | J114: =IF(J$11<$C114,0,MIN($D114/$D$104,$D114-SUM($E114:I114))) -> 0 | K114: =IF(K$11<$C114,0,MIN($D114/$D$104,$D114-SUM($E114:J114))) -> 0 | L114: =IF(L$11<$C114,0,MIN($D114/$D$104,$D114-SUM($E114:K114))) -> 0 | M114: =IF(M$11<$C114,0,MIN($D114/$D$104,$D114-SUM($E114:L114))) -> 0 | ... AD114: =IF(AD$11<$C114,0,MIN($D114/$D$104,$D114-SUM($E114:AC114))) -> 0
...
