Workbook
Name Capacity: CaseData!$E$4
Name company: LEFT( CaseData!$A$1, 20 )
Name homeGames: 'AltSolution (Daily Sales)'!$I$48
Name homeGames: 'CaseSolution (Original)'!$G$48
Name periods: Calculations!$F$9
Name SeasonTicketPrice: CaseData!$E$3
Name soldPrice: 'AltSolution (Daily Sales)'!$E$3
Name soldPrice: 'CaseSolution (Original)'!$E$3
Name SpreadSTs: CaseData!$E$5
Name topic: "CFM Topic: " & CaseData!$J$24

Sheet Calculations
A1: {=company} -> Wichita Warblers Inc
A2: {=topic} -> CFM Topic: Working Capital
A3: CALCULATIONS SCHEDULE | F3: Constant | G3: Unit | H3: Total | J3: {=_xlfn.ANCHORARRAY(J11)} -> 44003 | K3: 44004 | L3: 44005 | M3: 44006 | N3: 44007 | O3: 44008 | P3: 44009 | Q3: 44010 | R3: 44011 | S3: 44012 | T3: 44013 | U3: 44014 | V3: 44015 | W3: 44016 | X3: 44017 | Y3: 44018 | Z3: 44019 | AA3: 44020 | AB3: 44021 | AC3: 44022 | AD3: 44023 | AE3: 44024 | AF3: 44025 | AG3: 44026 | AH3: 44027 | AI3: 44028 | AJ3: 44029 | AK3: 44030 | AL3: 44031 | AM3: 44032 | AN3: 44033 | AO3: 44034 | AP3: 44035 | AQ3: 44036 | AR3: 44037 | AS3: 44038 | AT3: 44039 | AU3: 44040 | AV3: 44041 | AW3: 44042 | AX3: 44043 | AY3: 44044 | AZ3: 44045 | BA3: 44046 | BB3: 44047 | BC3: 44048 | BD3: 44049 | BE3: 44050 | BF3: 44051 | BG3: 44052 | BH3: 44053 | BI3: 44054 | BJ3: 44055 | BK3: 44056 | BL3: 44057 | BM3: 44058 | BN3: 44059 | BO3: 44060 | BP3: 44061 | BQ3: 44062 | BR3: 44063 | BS3: 44064 | BT3: 44065 | BU3: 44066 | BV3: 44067 | BW3: 44068 | BX3: 44069 | BY3: 44070 | BZ3: 44071 | CA3: 44072 | CB3: 44073 | CC3: 44074 | CD3: 44075 | CE3: 44076 | CF3: 44077 | CG3: 44078 | CH3: 44079 | CI3: 44080 | CJ3: 44081 | CK3: 44082 | CL3: 44083 | CM3: 44084 | CN3: 44085 | CO3: 44086 | CP3: 44087 | CQ3: 44088 | CR3: 44089 | CS3: 44090 | CT3: 44091 | CU3: 44092 | CV3: 44093 | CW3: 44094 | CX3: 44095 | CY3: 44096 | CZ3: 44097 | DA3: 44098 | DB3: 44099 | DC3: 44100 | DD3: 44101 | DE3: 44102 | DF3: 44103 | DG3: 44104 | DH3: 44105 | DI3: 44106 | DJ3: 44107 | DK3: 44108 | DL3: 44109 | DM3: 44110 | DN3: 44111 | DO3: 44112 | DP3: 44113 | DQ3: 44114 | DR3: 44115 | DS3: 44116 | DT3: 44117 | DU3: 44118 | DV3: 44119 | DW3: 44120 | DX3: 44121 | DY3: 44122 | DZ3: 44123 | EA3: 44124 | EB3: 44125 | EC3: 44126 | ED3: 44127 | EE3: 44128 | EF3: 44129 | EG3: 44130 | EH3: 44131 | EI3: 44132 | EJ3: 44133 | EK3: 44134 | EL3: 44135 | EM3: 44136 | EN3: 44137 | EO3: 44138 | EP3: 44139 | EQ3: 44140 | ER3: 44141 | ES3: 44142 | ET3: 44143 | EU3: 44144 | EV3: 44145 | EW3: 44146 | EX3: 44147 | EY3: 44148 | EZ3: 44149 | FA3: 44150 | FB3: 44151 | FC3: 44152 | FD3: 44153 | FE3: 44154 | FF3: 44155 | FG3: 44156 | FH3: 44157 | FI3: 44158 | FJ3: 44159 | FK3: 44160 | FL3: 44161 | FM3: 44162 | FN3: 44163 | FO3: 44164 | FP3: 44165 | FQ3: 44166 | FR3: 44167 | FS3: 44168 | FT3: 44169 | FU3: 44170 | FV3: 44171 | FW3: 44172 | FX3: 44173 | FY3: 44174 | FZ3: 44175 | GA3: 44176 | GB3: 44177 | GC3: 44178 | GD3: 44179 | GE3: 44180 | GF3: 44181 | GG3: 44182 | GH3: 44183 | GI3: 44184 | GJ3: 44185 | GK3: 44186 | GL3: 44187 | GM3: 44188 | GN3: 44189 | GO3: 44190 | GP3: 44191 | GQ3: 44192 | GR3: 44193 | GS3: 44194 | GT3: 44195 | GU3: 44196 | GV3: 44197 | GW3: 44198 | GX3: 44199 | GY3: 44200 | GZ3: 44201 | HA3: 44202 | HB3: 44203 | HC3: 44204 | HD3: 44205 | HE3: 44206 | HF3: 44207 | HG3: 44208 | HH3: 44209 | HI3: 44210 | HJ3: 44211 | HK3: 44212 | HL3: 44213 | HM3: 44214 | HN3: 44215 | HO3: 44216 | HP3: 44217 | HQ3: 44218 | HR3: 44219 | HS3: 44220 | HT3: 44221 | HU3: 44222 | HV3: 44223 | HW3: 44224 | HX3: 44225 | HY3: 44226 | HZ3: 44227 | IA3: 44228 | IB3: 44229 | IC3: 44230 | ID3: 44231 | IE3: 44232 | IF3: 44233 | IG3: 44234 | IH3: 44235 | II3: 44236 | IJ3: 44237 | IK3: 44238 | IL3: 44239 | IM3: 44240 | IN3: 44241 | IO3: 44242 | IP3: 44243 | IQ3: 44244 | IR3: 44245 | IS3: 44246 | IT3: 44247 | IU3: 44248 | IV3: 44249 | IW3: 44250 | IX3: 44251 | IY3: 44252 | IZ3: 44253 | JA3: 44254 | JB3: 44255 | JC3: 44256 | JD3: 44257 | JE3: 44258 | JF3: 44259 | JG3: 44260 | JH3: 44261 | JI3: 44262 | JJ3: 44263 | JK3: 44264 | JL3: 44265 | JM3: 44266 | JN3: 44267 | JO3: 44268 | JP3: 44269 | JQ3: 44270 | JR3: 44271 | JS3: 44272 | JT3: 44273 | JU3: 44274 | JV3: 44275 | JW3: 44276 | JX3: 44277 | JY3: 44278 | JZ3: 44279 | KA3: 44280 | KB3: 44281 | KC3: 44282 | KD3: 44283 | KE3: 44284 | KF3: 44285 | KG3: 44286 | KH3: 44287 | KI3: 44288 | KJ3: 44289 | KK3: 44290 | KL3: 44291 | KM3: 44292 | KN3: 44293 | KO3: 44294 | KP3: 44295 | KQ3: 44296 | KR3: 44297 | KS3: 44298 | KT3: 44299 | KU3: 44300 | KV3: 44301 | KW3: 44302 | KX3: 44303 | KY3: 44304 | KZ3: 44305 | LA3: 44306 | LB3: 44307 | LC3: 44308 | LD3: 44309 | LE3: 44310 | LF3: 44311 | LG3: 44312 | LH3: 44313 | LI3: 44314 | LJ3: 44315 | LK3: 44316 | LL3: 44317 | LM3: 44318 | LN3: 44319 | LO3: 44320 | LP3: 44321 | LQ3: 44322 | LR3: 44323 | LS3: 44324 | LT3: 44325 | LU3: 44326 | LV3: 44327 | LW3: 44328 | LX3: 44329 | LY3: 44330 | LZ3: 44331 | MA3: 44332 | MB3: 44333 | MC3: 44334 | MD3: 44335 | ME3: 44336 | MF3: 44337 | MG3: 44338 | MH3: 44339 | MI3: 44340 | MJ3: 44341 | MK3: 44342 | ML3: 44343 | MM3: 44344 | MN3: 44345 | MO3: 44346 | MP3: 44347 | MQ3: 44348 | MR3: 44349 | MS3: 44350 | MT3: 44351 | MU3: 44352 | MV3: 44353
A5: Model timeline
E7: Beginning date | F7: =MIN( tbl_SeasonTicketSale[Week ending] ) - 6 -> 44003 | G7: date
E8: Ending date | F8: =MAX( tbl_GameDates[Date] ) + 1 -> 44353 | G8: date
E9: Number of days | F9: =F8 - F7 + 1 -> 351 | G9: days
E11: Model timeline | G11: date | J11: {=_xlfn.SEQUENCE( 1, periods, $F$7, 1 )} -> 44003 | K11: 44004 | L11: 44005 | M11: 44006 | N11: 44007 | O11: 44008 | P11: 44009 | Q11: 44010 | R11: 44011 | S11: 44012 | T11: 44013 | U11: 44014 | V11: 44015 | W11: 44016 | X11: 44017 | Y11: 44018 | Z11: 44019 | AA11: 44020 | AB11: 44021 | AC11: 44022 | AD11: 44023 | AE11: 44024 | AF11: 44025 | AG11: 44026 | AH11: 44027 | AI11: 44028 | AJ11: 44029 | AK11: 44030 | AL11: 44031 | AM11: 44032 | AN11: 44033 | AO11: 44034 | AP11: 44035 | AQ11: 44036 | AR11: 44037 | AS11: 44038 | AT11: 44039 | AU11: 44040 | AV11: 44041 | AW11: 44042 | AX11: 44043 | AY11: 44044 | AZ11: 44045 | BA11: 44046 | BB11: 44047 | BC11: 44048 | BD11: 44049 | BE11: 44050 | BF11: 44051 | BG11: 44052 | BH11: 44053 | BI11: 44054 | BJ11: 44055 | BK11: 44056 | BL11: 44057 | BM11: 44058 | BN11: 44059 | BO11: 44060 | BP11: 44061 | BQ11: 44062 | BR11: 44063 | BS11: 44064 | BT11: 44065 | BU11: 44066 | BV11: 44067 | BW11: 44068 | BX11: 44069 | BY11: 44070 | BZ11: 44071 | CA11: 44072 | CB11: 44073 | CC11: 44074 | CD11: 44075 | CE11: 44076 | CF11: 44077 | CG11: 44078 | CH11: 44079 | CI11: 44080 | CJ11: 44081 | CK11: 44082 | CL11: 44083 | CM11: 44084 | CN11: 44085 | CO11: 44086 | CP11: 44087 | CQ11: 44088 | CR11: 44089 | CS11: 44090 | CT11: 44091 | CU11: 44092 | CV11: 44093 | CW11: 44094 | CX11: 44095 | CY11: 44096 | CZ11: 44097 | DA11: 44098 | DB11: 44099 | DC11: 44100 | DD11: 44101 | DE11: 44102 | DF11: 44103 | DG11: 44104 | DH11: 44105 | DI11: 44106 | DJ11: 44107 | DK11: 44108 | DL11: 44109 | DM11: 44110 | DN11: 44111 | DO11: 44112 | DP11: 44113 | DQ11: 44114 | DR11: 44115 | DS11: 44116 | DT11: 44117 | DU11: 44118 | DV11: 44119 | DW11: 44120 | DX11: 44121 | DY11: 44122 | DZ11: 44123 | EA11: 44124 | EB11: 44125 | EC11: 44126 | ED11: 44127 | EE11: 44128 | EF11: 44129 | EG11: 44130 | EH11: 44131 | EI11: 44132 | EJ11: 44133 | EK11: 44134 | EL11: 44135 | EM11: 44136 | EN11: 44137 | EO11: 44138 | EP11: 44139 | EQ11: 44140 | ER11: 44141 | ES11: 44142 | ET11: 44143 | EU11: 44144 | EV11: 44145 | EW11: 44146 | EX11: 44147 | EY11: 44148 | EZ11: 44149 | FA11: 44150 | FB11: 44151 | FC11: 44152 | FD11: 44153 | FE11: 44154 | FF11: 44155 | FG11: 44156 | FH11: 44157 | FI11: 44158 | FJ11: 44159 | FK11: 44160 | FL11: 44161 | FM11: 44162 | FN11: 44163 | FO11: 44164 | FP11: 44165 | FQ11: 44166 | FR11: 44167 | FS11: 44168 | FT11: 44169 | FU11: 44170 | FV11: 44171 | FW11: 44172 | FX11: 44173 | FY11: 44174 | FZ11: 44175 | GA11: 44176 | GB11: 44177 | GC11: 44178 | GD11: 44179 | GE11: 44180 | GF11: 44181 | GG11: 44182 | GH11: 44183 | GI11: 44184 | GJ11: 44185 | GK11: 44186 | GL11: 44187 | GM11: 44188 | GN11: 44189 | GO11: 44190 | GP11: 44191 | GQ11: 44192 | GR11: 44193 | GS11: 44194 | GT11: 44195 | GU11: 44196 | GV11: 44197 | GW11: 44198 | GX11: 44199 | GY11: 44200 | GZ11: 44201 | HA11: 44202 | HB11: 44203 | HC11: 44204 | HD11: 44205 | HE11: 44206 | HF11: 44207 | HG11: 44208 | HH11: 44209 | HI11: 44210 | HJ11: 44211 | HK11: 44212 | HL11: 44213 | HM11: 44214 | HN11: 44215 | HO11: 44216 | HP11: 44217 | HQ11: 44218 | HR11: 44219 | HS11: 44220 | HT11: 44221 | HU11: 44222 | HV11: 44223 | HW11: 44224 | HX11: 44225 | HY11: 44226 | HZ11: 44227 | IA11: 44228 | IB11: 44229 | IC11: 44230 | ID11: 44231 | IE11: 44232 | IF11: 44233 | IG11: 44234 | IH11: 44235 | II11: 44236 | IJ11: 44237 | IK11: 44238 | IL11: 44239 | IM11: 44240 | IN11: 44241 | IO11: 44242 | IP11: 44243 | IQ11: 44244 | IR11: 44245 | IS11: 44246 | IT11: 44247 | IU11: 44248 | IV11: 44249 | IW11: 44250 | IX11: 44251 | IY11: 44252 | IZ11: 44253 | JA11: 44254 | JB11: 44255 | JC11: 44256 | JD11: 44257 | JE11: 44258 | JF11: 44259 | JG11: 44260 | JH11: 44261 | JI11: 44262 | JJ11: 44263 | JK11: 44264 | JL11: 44265 | JM11: 44266 | JN11: 44267 | JO11: 44268 | JP11: 44269 | JQ11: 44270 | JR11: 44271 | JS11: 44272 | JT11: 44273 | JU11: 44274 | JV11: 44275 | JW11: 44276 | JX11: 44277 | JY11: 44278 | JZ11: 44279 | KA11: 44280 | KB11: 44281 | KC11: 44282 | KD11: 44283 | KE11: 44284 | KF11: 44285 | KG11: 44286 | KH11: 44287 | KI11: 44288 | KJ11: 44289 | KK11: 44290 | KL11: 44291 | KM11: 44292 | KN11: 44293 | KO11: 44294 | KP11: 44295 | KQ11: 44296 | KR11: 44297 | KS11: 44298 | KT11: 44299 | KU11: 44300 | KV11: 44301 | KW11: 44302 | KX11: 44303 | KY11: 44304 | KZ11: 44305 | LA11: 44306 | LB11: 44307 | LC11: 44308 | LD11: 44309 | LE11: 44310 | LF11: 44311 | LG11: 44312 | LH11: 44313 | LI11: 44314 | LJ11: 44315 | LK11: 44316 | LL11: 44317 | LM11: 44318 | LN11: 44319 | LO11: 44320 | LP11: 44321 | LQ11: 44322 | LR11: 44323 | LS11: 44324 | LT11: 44325 | LU11: 44326 | LV11: 44327 | LW11: 44328 | LX11: 44329 | LY11: 44330 | LZ11: 44331 | MA11: 44332 | MB11: 44333 | MC11: 44334 | MD11: 44335 | ME11: 44336 | MF11: 44337 | MG11: 44338 | MH11: 44339 | MI11: 44340 | MJ11: 44341 | MK11: 44342 | ML11: 44343 | MM11: 44344 | MN11: 44345 | MO11: 44346 | MP11: 44347 | MQ11: 44348 | MR11: 44349 | MS11: 44350 | MT11: 44351 | MU11: 44352 | MV11: 44353
E12: Weekend date | G12: date | J12: {=_xlfn.ANCHORARRAY( J11) - WEEKDAY(_xlfn.ANCHORARRAY( J11) ) + 7} -> 44009 | K12: 44009 | L12: 44009 | M12: 44009 | N12: 44009 | O12: 44009 | P12: 44009 | Q12: 44016 | R12: 44016 | S12: 44016 | T12: 44016 | U12: 44016 | V12: 44016 | W12: 44016 | X12: 44023 | Y12: 44023 | Z12: 44023 | AA12: 44023 | AB12: 44023 | AC12: 44023 | AD12: 44023 | AE12: 44030 | AF12: 44030 | AG12: 44030 | AH12: 44030 | AI12: 44030 | AJ12: 44030 | AK12: 44030 | AL12: 44037 | AM12: 44037 | AN12: 44037 | AO12: 44037 | AP12: 44037 | AQ12: 44037 | AR12: 44037 | AS12: 44044 | AT12: 44044 | AU12: 44044 | AV12: 44044 | AW12: 44044 | AX12: 44044 | AY12: 44044 | AZ12: 44051 | BA12: 44051 | BB12: 44051 | BC12: 44051 | BD12: 44051 | BE12: 44051 | BF12: 44051 | BG12: 44058 | BH12: 44058 | BI12: 44058 | BJ12: 44058 | BK12: 44058 | BL12: 44058 | BM12: 44058 | BN12: 44065 | BO12: 44065 | BP12: 44065 | BQ12: 44065 | BR12: 44065 | BS12: 44065 | BT12: 44065 | BU12: 44072 | BV12: 44072 | BW12: 44072 | BX12: 44072 | BY12: 44072 | BZ12: 44072 | CA12: 44072 | CB12: 44079 | CC12: 44079 | CD12: 44079 | CE12: 44079 | CF12: 44079 | CG12: 44079 | CH12: 44079 | CI12: 44086 | CJ12: 44086 | CK12: 44086 | CL12: 44086 | CM12: 44086 | CN12: 44086 | CO12: 44086 | CP12: 44093 | CQ12: 44093 | CR12: 44093 | CS12: 44093 | CT12: 44093 | CU12: 44093 | CV12: 44093 | CW12: 44100 | CX12: 44100 | CY12: 44100 | CZ12: 44100 | DA12: 44100 | DB12: 44100 | DC12: 44100 | DD12: 44107 | DE12: 44107 | DF12: 44107 | DG12: 44107 | DH12: 44107 | DI12: 44107 | DJ12: 44107 | DK12: 44114 | DL12: 44114 | DM12: 44114 | DN12: 44114 | DO12: 44114 | DP12: 44114 | DQ12: 44114 | DR12: 44121 | DS12: 44121 | DT12: 44121 | DU12: 44121 | DV12: 44121 | DW12: 44121 | DX12: 44121 | DY12: 44128 | DZ12: 44128 | EA12: 44128 | EB12: 44128 | EC12: 44128 | ED12: 44128 | EE12: 44128 | EF12: 44135 | EG12: 44135 | EH12: 44135 | EI12: 44135 | EJ12: 44135 | EK12: 44135 | EL12: 44135 | EM12: 44142 | EN12: 44142 | EO12: 44142 | EP12: 44142 | EQ12: 44142 | ER12: 44142 | ES12: 44142 | ET12: 44149 | EU12: 44149 | EV12: 44149 | EW12: 44149 | EX12: 44149 | EY12: 44149 | EZ12: 44149 | FA12: 44156 | FB12: 44156 | FC12: 44156 | FD12: 44156 | FE12: 44156 | FF12: 44156 | FG12: 44156 | FH12: 44163 | FI12: 44163 | FJ12: 44163 | FK12: 44163 | FL12: 44163 | FM12: 44163 | FN12: 44163 | FO12: 44170 | FP12: 44170 | FQ12: 44170 | FR12: 44170 | FS12: 44170 | FT12: 44170 | FU12: 44170 | FV12: 44177 | FW12: 44177 | FX12: 44177 | FY12: 44177 | FZ12: 44177 | GA12: 44177 | GB12: 44177 | GC12: 44184 | GD12: 44184 | GE12: 44184 | GF12: 44184 | GG12: 44184 | GH12: 44184 | GI12: 44184 | GJ12: 44191 | GK12: 44191 | GL12: 44191 | GM12: 44191 | GN12: 44191 | GO12: 44191 | GP12: 44191 | GQ12: 44198 | GR12: 44198 | GS12: 44198 | GT12: 44198 | GU12: 44198 | GV12: 44198 | GW12: 44198 | GX12: 44205 | GY12: 44205 | GZ12: 44205 | HA12: 44205 | HB12: 44205 | HC12: 44205 | HD12: 44205 | HE12: 44212 | HF12: 44212 | HG12: 44212 | HH12: 44212 | HI12: 44212 | HJ12: 44212 | HK12: 44212 | HL12: 44219 | HM12: 44219 | HN12: 44219 | HO12: 44219 | HP12: 44219 | HQ12: 44219 | HR12: 44219 | HS12: 44226 | HT12: 44226 | HU12: 44226 | HV12: 44226 | HW12: 44226 | HX12: 44226 | HY12: 44226 | HZ12: 44233 | IA12: 44233 | IB12: 44233 | IC12: 44233 | ID12: 44233 | IE12: 44233 | IF12: 44233 | IG12: 44240 | IH12: 44240 | II12: 44240 | IJ12: 44240 | IK12: 44240 | IL12: 44240 | IM12: 44240 | IN12: 44247 | IO12: 44247 | IP12: 44247 | IQ12: 44247 | IR12: 44247 | IS12: 44247 | IT12: 44247 | IU12: 44254 | IV12: 44254 | IW12: 44254 | IX12: 44254 | IY12: 44254 | IZ12: 44254 | JA12: 44254 | JB12: 44261 | JC12: 44261 | JD12: 44261 | JE12: 44261 | JF12: 44261 | JG12: 44261 | JH12: 44261 | JI12: 44268 | JJ12: 44268 | JK12: 44268 | JL12: 44268 | JM12: 44268 | JN12: 44268 | JO12: 44268 | JP12: 44275 | JQ12: 44275 | JR12: 44275 | JS12: 44275 | JT12: 44275 | JU12: 44275 | JV12: 44275 | JW12: 44282 | JX12: 44282 | JY12: 44282 | JZ12: 44282 | KA12: 44282 | KB12: 44282 | KC12: 44282 | KD12: 44289 | KE12: 44289 | KF12: 44289 | KG12: 44289 | KH12: 44289 | KI12: 44289 | KJ12: 44289 | KK12: 44296 | KL12: 44296 | KM12: 44296 | KN12: 44296 | KO12: 44296 | KP12: 44296 | KQ12: 44296 | KR12: 44303 | KS12: 44303 | KT12: 44303 | KU12: 44303 | KV12: 44303 | KW12: 44303 | KX12: 44303 | KY12: 44310 | KZ12: 44310 | LA12: 44310 | LB12: 44310 | LC12: 44310 | LD12: 44310 | LE12: 44310 | LF12: 44317 | LG12: 44317 | LH12: 44317 | LI12: 44317 | LJ12: 44317 | LK12: 44317 | LL12: 44317 | LM12: 44324 | LN12: 44324 | LO12: 44324 | LP12: 44324 | LQ12: 44324 | LR12: 44324 | LS12: 44324 | LT12: 44331 | LU12: 44331 | LV12: 44331 | LW12: 44331 | LX12: 44331 | LY12: 44331 | LZ12: 44331 | MA12: 44338 | MB12: 44338 | MC12: 44338 | MD12: 44338 | ME12: 44338 | MF12: 44338 | MG12: 44338 | MH12: 44345 | MI12: 44345 | MJ12: 44345 | MK12: 44345 | ML12: 44345 | MM12: 44345 | MN12: 44345 | MO12: 44352 | MP12: 44352 | MQ12: 44352 | MR12: 44352 | MS12: 44352 | MT12: 44352 | MU12: 44352 | MV12: 44359
E13: Month end | G13: date | J13: {=_xlfn.BYCOL(_xlfn.ANCHORARRAY( J11), _xlfn.LAMBDA(_xlpm.d, EOMONTH( _xlpm.d, 0 ) ) )} -> 44012 | K13: 44012 | L13: 44012 | M13: 44012 | N13: 44012 | O13: 44012 | P13: 44012 | Q13: 44012 | R13: 44012 | S13: 44012 | T13: 44043 | U13: 44043 | V13: 44043 | W13: 44043 | X13: 44043 | Y13: 44043 | Z13: 44043 | AA13: 44043 | AB13: 44043 | AC13: 44043 | AD13: 44043 | AE13: 44043 | AF13: 44043 | AG13: 44043 | AH13: 44043 | AI13: 44043 | AJ13: 44043 | AK13: 44043 | AL13: 44043 | AM13: 44043 | AN13: 44043 | AO13: 44043 | AP13: 44043 | AQ13: 44043 | AR13: 44043 | AS13: 44043 | AT13: 44043 | AU13: 44043 | AV13: 44043 | AW13: 44043 | AX13: 44043 | AY13: 44074 | AZ13: 44074 | BA13: 44074 | BB13: 44074 | BC13: 44074 | BD13: 44074 | BE13: 44074 | BF13: 44074 | BG13: 44074 | BH13: 44074 | BI13: 44074 | BJ13: 44074 | BK13: 44074 | BL13: 44074 | BM13: 44074 | BN13: 44074 | BO13: 44074 | BP13: 44074 | BQ13: 44074 | BR13: 44074 | BS13: 44074 | BT13: 44074 | BU13: 44074 | BV13: 44074 | BW13: 44074 | BX13: 44074 | BY13: 44074 | BZ13: 44074 | CA13: 44074 | CB13: 44074 | CC13: 44074 | CD13: 44104 | CE13: 44104 | CF13: 44104 | CG13: 44104 | CH13: 44104 | CI13: 44104 | CJ13: 44104 | CK13: 44104 | CL13: 44104 | CM13: 44104 | CN13: 44104 | CO13: 44104 | CP13: 44104 | CQ13: 44104 | CR13: 44104 | CS13: 44104 | CT13: 44104 | CU13: 44104 | CV13: 44104 | CW13: 44104 | CX13: 44104 | CY13: 44104 | CZ13: 44104 | DA13: 44104 | DB13: 44104 | DC13: 44104 | DD13: 44104 | DE13: 44104 | DF13: 44104 | DG13: 44104 | DH13: 44135 | DI13: 44135 | DJ13: 44135 | DK13: 44135 | DL13: 44135 | DM13: 44135 | DN13: 44135 | DO13: 44135 | DP13: 44135 | DQ13: 44135 | DR13: 44135 | DS13: 44135 | DT13: 44135 | DU13: 44135 | DV13: 44135 | DW13: 44135 | DX13: 44135 | DY13: 44135 | DZ13: 44135 | EA13: 44135 | EB13: 44135 | EC13: 44135 | ED13: 44135 | EE13: 44135 | EF13: 44135 | EG13: 44135 | EH13: 44135 | EI13: 44135 | EJ13: 44135 | EK13: 44135 | EL13: 44135 | EM13: 44165 | EN13: 44165 | EO13: 44165 | EP13: 44165 | EQ13: 44165 | ER13: 44165 | ES13: 44165 | ET13: 44165 | EU13: 44165 | EV13: 44165 | EW13: 44165 | EX13: 44165 | EY13: 44165 | EZ13: 44165 | FA13: 44165 | FB13: 44165 | FC13: 44165 | FD13: 44165 | FE13: 44165 | FF13: 44165 | FG13: 44165 | FH13: 44165 | FI13: 44165 | FJ13: 44165 | FK13: 44165 | FL13: 44165 | FM13: 44165 | FN13: 44165 | FO13: 44165 | FP13: 44165 | FQ13: 44196 | FR13: 44196 | FS13: 44196 | FT13: 44196 | FU13: 44196 | FV13: 44196 | FW13: 44196 | FX13: 44196 | FY13: 44196 | FZ13: 44196 | GA13: 44196 | GB13: 44196 | GC13: 44196 | GD13: 44196 | GE13: 44196 | GF13: 44196 | GG13: 44196 | GH13: 44196 | GI13: 44196 | GJ13: 44196 | GK13: 44196 | GL13: 44196 | GM13: 44196 | GN13: 44196 | GO13: 44196 | GP13: 44196 | GQ13: 44196 | GR13: 44196 | GS13: 44196 | GT13: 44196 | GU13: 44196 | GV13: 44227 | GW13: 44227 | GX13: 44227 | GY13: 44227 | GZ13: 44227 | HA13: 44227 | HB13: 44227 | HC13: 44227 | HD13: 44227 | HE13: 44227 | HF13: 44227 | HG13: 44227 | HH13: 44227 | HI13: 44227 | HJ13: 44227 | HK13: 44227 | HL13: 44227 | HM13: 44227 | HN13: 44227 | HO13: 44227 | HP13: 44227 | HQ13: 44227 | HR13: 44227 | HS13: 44227 | HT13: 44227 | HU13: 44227 | HV13: 44227 | HW13: 44227 | HX13: 44227 | HY13: 44227 | HZ13: 44227 | IA13: 44255 | IB13: 44255 | IC13: 44255 | ID13: 44255 | IE13: 44255 | IF13: 44255 | IG13: 44255 | IH13: 44255 | II13: 44255 | IJ13: 44255 | IK13: 44255 | IL13: 44255 | IM13: 44255 | IN13: 44255 | IO13: 44255 | IP13: 44255 | IQ13: 44255 | IR13: 44255 | IS13: 44255 | IT13: 44255 | IU13: 44255 | IV13: 44255 | IW13: 44255 | IX13: 44255 | IY13: 44255 | IZ13: 44255 | JA13: 44255 | JB13: 44255 | JC13: 44286 | JD13: 44286 | JE13: 44286 | JF13: 44286 | JG13: 44286 | JH13: 44286 | JI13: 44286 | JJ13: 44286 | JK13: 44286 | JL13: 44286 | JM13: 44286 | JN13: 44286 | JO13: 44286 | JP13: 44286 | JQ13: 44286 | JR13: 44286 | JS13: 44286 | JT13: 44286 | JU13: 44286 | JV13: 44286 | JW13: 44286 | JX13: 44286 | JY13: 44286 | JZ13: 44286 | KA13: 44286 | KB13: 44286 | KC13: 44286 | KD13: 44286 | KE13: 44286 | KF13: 44286 | KG13: 44286 | KH13: 44316 | KI13: 44316 | KJ13: 44316 | KK13: 44316 | KL13: 44316 | KM13: 44316 | KN13: 44316 | KO13: 44316 | KP13: 44316 | KQ13: 44316 | KR13: 44316 | KS13: 44316 | KT13: 44316 | KU13: 44316 | KV13: 44316 | KW13: 44316 | KX13: 44316 | KY13: 44316 | KZ13: 44316 | LA13: 44316 | LB13: 44316 | LC13: 44316 | LD13: 44316 | LE13: 44316 | LF13: 44316 | LG13: 44316 | LH13: 44316 | LI13: 44316 | LJ13: 44316 | LK13: 44316 | LL13: 44347 | LM13: 44347 | LN13: 44347 | LO13: 44347 | LP13: 44347 | LQ13: 44347 | LR13: 44347 | LS13: 44347 | LT13: 44347 | LU13: 44347 | LV13: 44347 | LW13: 44347 | LX13: 44347 | LY13: 44347 | LZ13: 44347 | MA13: 44347 | MB13: 44347 | MC13: 44347 | MD13: 44347 | ME13: 44347 | MF13: 44347 | MG13: 44347 | MH13: 44347 | MI13: 44347 | MJ13: 44347 | MK13: 44347 | ML13: 44347 | MM13: 44347 | MN13: 44347 | MO13: 44347 | MP13: 44347 | MQ13: 44377 | MR13: 44377 | MS13: 44377 | MT13: 44377 | MU13: 44377 | MV13: 44377
E14: Game date | G14: date | J14: {=_xlfn.XLOOKUP(_xlfn.ANCHORARRAY( J11), tbl_GameDates[Date], tbl_GameDates[Date], "n/a", 1 )} -> 44058 | K14: 44058 | L14: 44058 | M14: 44058 | N14: 44058 | O14: 44058 | P14: 44058 | Q14: 44058 | R14: 44058 | S14: 44058 | T14: 44058 | U14: 44058 | V14: 44058 | W14: 44058 | X14: 44058 | Y14: 44058 | Z14: 44058 | AA14: 44058 | AB14: 44058 | AC14: 44058 | AD14: 44058 | AE14: 44058 | AF14: 44058 | AG14: 44058 | AH14: 44058 | AI14: 44058 | AJ14: 44058 | AK14: 44058 | AL14: 44058 | AM14: 44058 | AN14: 44058 | AO14: 44058 | AP14: 44058 | AQ14: 44058 | AR14: 44058 | AS14: 44058 | AT14: 44058 | AU14: 44058 | AV14: 44058 | AW14: 44058 | AX14: 44058 | AY14: 44058 | AZ14: 44058 | BA14: 44058 | BB14: 44058 | BC14: 44058 | BD14: 44058 | BE14: 44058 | BF14: 44058 | BG14: 44058 | BH14: 44058 | BI14: 44058 | BJ14: 44058 | BK14: 44058 | BL14: 44058 | BM14: 44058 | BN14: 44065 | BO14: 44065 | BP14: 44065 | BQ14: 44065 | BR14: 44065 | BS14: 44065 | BT14: 44065 | BU14: 44072 | BV14: 44072 | BW14: 44072 | BX14: 44072 | BY14: 44072 | BZ14: 44072 | CA14: 44072 | CB14: 44079 | CC14: 44079 | CD14: 44079 | CE14: 44079 | CF14: 44079 | CG14: 44079 | CH14: 44079 | CI14: 44086 | CJ14: 44086 | CK14: 44086 | CL14: 44086 | CM14: 44086 | CN14: 44086 | CO14: 44086 | CP14: 44093 | CQ14: 44093 | CR14: 44093 | CS14: 44093 | CT14: 44093 | CU14: 44093 | CV14: 44093 | CW14: 44100 | CX14: 44100 | CY14: 44100 | CZ14: 44100 | DA14: 44100 | DB14: 44100 | DC14: 44100 | DD14: 44107 | DE14: 44107 | DF14: 44107 | DG14: 44107 | DH14: 44107 | DI14: 44107 | DJ14: 44107 | DK14: 44114 | DL14: 44114 | DM14: 44114 | DN14: 44114 | DO14: 44114 | DP14: 44114 | DQ14: 44114 | DR14: 44121 | DS14: 44121 | DT14: 44121 | DU14: 44121 | DV14: 44121 | DW14: 44121 | DX14: 44121 | DY14: 44128 | DZ14: 44128 | EA14: 44128 | EB14: 44128 | EC14: 44128 | ED14: 44128 | EE14: 44128 | EF14: 44135 | EG14: 44135 | EH14: 44135 | EI14: 44135 | EJ14: 44135 | EK14: 44135 | EL14: 44135 | EM14: 44142 | EN14: 44142 | EO14: 44142 | EP14: 44142 | EQ14: 44142 | ER14: 44142 | ES14: 44142 | ET14: 44149 | EU14: 44149 | EV14: 44149 | EW14: 44149 | EX14: 44149 | EY14: 44149 | EZ14: 44149 | FA14: 44156 | FB14: 44156 | FC14: 44156 | FD14: 44156 | FE14: 44156 | FF14: 44156 | FG14: 44156 | FH14: 44163 | FI14: 44163 | FJ14: 44163 | FK14: 44163 | FL14: 44163 | FM14: 44163 | FN14: 44163 | FO14: 44170 | FP14: 44170 | FQ14: 44170 | FR14: 44170 | FS14: 44170 | FT14: 44170 | FU14: 44170 | FV14: 44177 | FW14: 44177 | FX14: 44177 | FY14: 44177 | FZ14: 44177 | GA14: 44177 | GB14: 44177 | GC14: 44198 | GD14: 44198 | GE14: 44198 | GF14: 44198 | GG14: 44198 | GH14: 44198 | GI14: 44198 | GJ14: 44198 | GK14: 44198 | GL14: 44198 | GM14: 44198 | GN14: 44198 | GO14: 44198 | GP14: 44198 | GQ14: 44198 | GR14: 44198 | GS14: 44198 | GT14: 44198 | GU14: 44198 | GV14: 44198 | GW14: 44198 | GX14: 44205 | GY14: 44205 | GZ14: 44205 | HA14: 44205 | HB14: 44205 | HC14: 44205 | HD14: 44205 | HE14: 44212 | HF14: 44212 | HG14: 44212 | HH14: 44212 | HI14: 44212 | HJ14: 44212 | HK14: 44212 | HL14: 44219 | HM14: 44219 | HN14: 44219 | HO14: 44219 | HP14: 44219 | HQ14: 44219 | HR14: 44219 | HS14: 44226 | HT14: 44226 | HU14: 44226 | HV14: 44226 | HW14: 44226 | HX14: 44226 | HY14: 44226 | HZ14: 44233 | IA14: 44233 | IB14: 44233 | IC14: 44233 | ID14: 44233 | IE14: 44233 | IF14: 44233 | IG14: 44240 | IH14: 44240 | II14: 44240 | IJ14: 44240 | IK14: 44240 | IL14: 44240 | IM14: 44240 | IN14: 44247 | IO14: 44247 | IP14: 44247 | IQ14: 44247 | IR14: 44247 | IS14: 44247 | IT14: 44247 | IU14: 44254 | IV14: 44254 | IW14: 44254 | IX14: 44254 | IY14: 44254 | IZ14: 44254 | JA14: 44254 | JB14: 44261 | JC14: 44261 | JD14: 44261 | JE14: 44261 | JF14: 44261 | JG14: 44261 | JH14: 44261 | JI14: 44268 | JJ14: 44268 | JK14: 44268 | JL14: 44268 | JM14: 44268 | JN14: 44268 | JO14: 44268 | JP14: 44275 | JQ14: 44275 | JR14: 44275 | JS14: 44275 | JT14: 44275 | JU14: 44275 | JV14: 44275 | JW14: 44282 | JX14: 44282 | JY14: 44282 | JZ14: 44282 | KA14: 44282 | KB14: 44282 | KC14: 44282 | KD14: 44289 | KE14: 44289 | KF14: 44289 | KG14: 44289 | KH14: 44289 | KI14: 44289 | KJ14: 44289 | KK14: 44296 | KL14: 44296 | KM14: 44296 | KN14: 44296 | KO14: 44296 | KP14: 44296 | KQ14: 44296 | KR14: 44303 | KS14: 44303 | KT14: 44303 | KU14: 44303 | KV14: 44303 | KW14: 44303 | KX14: 44303 | KY14: 44310 | KZ14: 44310 | LA14: 44310 | LB14: 44310 | LC14: 44310 | LD14: 44310 | LE14: 44310 | LF14: 44317 | LG14: 44317 | LH14: 44317 | LI14: 44317 | LJ14: 44317 | LK14: 44317 | LL14: 44317 | LM14: 44324 | LN14: 44324 | LO14: 44324 | LP14: 44324 | LQ14: 44324 | LR14: 44324 | LS14: 44324 | LT14: 44331 | LU14: 44331 | LV14: 44331 | LW14: 44331 | LX14: 44331 | LY14: 44331 | LZ14: 44331 | MA14: 44338 | MB14: 44338 | MC14: 44338 | MD14: 44338 | ME14: 44338 | MF14: 44338 | MG14: 44338 | MH14: 44352 | MI14: 44352 | MJ14: 44352 | MK14: 44352 | ML14: 44352 | MM14: 44352 | MN14: 44352 | MO14: 44352 | MP14: 44352 | MQ14: 44352 | MR14: 44352 | MS14: 44352 | MT14: 44352 | MU14: 44352 | MV14: n/a
E15: Days to next game | G15: days | J15: {=IFERROR(_xlfn.ANCHORARRAY( J14) -_xlfn.ANCHORARRAY( J11), "n/a" )} -> 55 | K15: 54 | L15: 53 | M15: 52 | N15: 51 | O15: 50 | P15: 49 | Q15: 48 | R15: 47 | S15: 46 | T15: 45 | U15: 44 | V15: 43 | W15: 42 | X15: 41 | Y15: 40 | Z15: 39 | AA15: 38 | AB15: 37 | AC15: 36 | AD15: 35 | AE15: 34 | AF15: 33 | AG15: 32 | AH15: 31 | AI15: 30 | AJ15: 29 | AK15: 28 | AL15: 27 | AM15: 26 | AN15: 25 | AO15: 24 | AP15: 23 | AQ15: 22 | AR15: 21 | AS15: 20 | AT15: 19 | AU15: 18 | AV15: 17 | AW15: 16 | AX15: 15 | AY15: 14 | AZ15: 13 | BA15: 12 | BB15: 11 | BC15: 10 | BD15: 9 | BE15: 8 | BF15: 7 | BG15: 6 | BH15: 5 | BI15: 4 | BJ15: 3 | BK15: 2 | BL15: 1 | BM15: 0 | BN15: 6 | BO15: 5 | BP15: 4 | BQ15: 3 | BR15: 2 | BS15: 1 | BT15: 0 | BU15: 6 | BV15: 5 | BW15: 4 | BX15: 3 | BY15: 2 | BZ15: 1 | CA15: 0 | CB15: 6 | CC15: 5 | CD15: 4 | CE15: 3 | CF15: 2 | CG15: 1 | CH15: 0 | CI15: 6 | CJ15: 5 | CK15: 4 | CL15: 3 | CM15: 2 | CN15: 1 | CO15: 0 | CP15: 6 | CQ15: 5 | CR15: 4 | CS15: 3 | CT15: 2 | CU15: 1 | CV15: 0 | CW15: 6 | CX15: 5 | CY15: 4 | CZ15: 3 | DA15: 2 | DB15: 1 | DC15: 0 | DD15: 6 | DE15: 5 | DF15: 4 | DG15: 3 | DH15: 2 | DI15: 1 | DJ15: 0 | DK15: 6 | DL15: 5 | DM15: 4 | DN15: 3 | DO15: 2 | DP15: 1 | DQ15: 0 | DR15: 6 | DS15: 5 | DT15: 4 | DU15: 3 | DV15: 2 | DW15: 1 | DX15: 0 | DY15: 6 | DZ15: 5 | EA15: 4 | EB15: 3 | EC15: 2 | ED15: 1 | EE15: 0 | EF15: 6 | EG15: 5 | EH15: 4 | EI15: 3 | EJ15: 2 | EK15: 1 | EL15: 0 | EM15: 6 | EN15: 5 | EO15: 4 | EP15: 3 | EQ15: 2 | ER15: 1 | ES15: 0 | ET15: 6 | EU15: 5 | EV15: 4 | EW15: 3 | EX15: 2 | EY15: 1 | EZ15: 0 | FA15: 6 | FB15: 5 | FC15: 4 | FD15: 3 | FE15: 2 | FF15: 1 | FG15: 0 | FH15: 6 | FI15: 5 | FJ15: 4 | FK15: 3 | FL15: 2 | FM15: 1 | FN15: 0 | FO15: 6 | FP15: 5 | FQ15: 4 | FR15: 3 | FS15: 2 | FT15: 1 | FU15: 0 | FV15: 6 | FW15: 5 | FX15: 4 | FY15: 3 | FZ15: 2 | GA15: 1 | GB15: 0 | GC15: 20 | GD15: 19 | GE15: 18 | GF15: 17 | GG15: 16 | GH15: 15 | GI15: 14 | GJ15: 13 | GK15: 12 | GL15: 11 | GM15: 10 | GN15: 9 | GO15: 8 | GP15: 7 | GQ15: 6 | GR15: 5 | GS15: 4 | GT15: 3 | GU15: 2 | GV15: 1 | GW15: 0 | GX15: 6 | GY15: 5 | GZ15: 4 | HA15: 3 | HB15: 2 | HC15: 1 | HD15: 0 | HE15: 6 | HF15: 5 | HG15: 4 | HH15: 3 | HI15: 2 | HJ15: 1 | HK15: 0 | HL15: 6 | HM15: 5 | HN15: 4 | HO15: 3 | HP15: 2 | HQ15: 1 | HR15: 0 | HS15: 6 | HT15: 5 | HU15: 4 | HV15: 3 | HW15: 2 | HX15: 1 | HY15: 0 | HZ15: 6 | IA15: 5 | IB15: 4 | IC15: 3 | ID15: 2 | IE15: 1 | IF15: 0 | IG15: 6 | IH15: 5 | II15: 4 | IJ15: 3 | IK15: 2 | IL15: 1 | IM15: 0 | IN15: 6 | IO15: 5 | IP15: 4 | IQ15: 3 | IR15: 2 | IS15: 1 | IT15: 0 | IU15: 6 | IV15: 5 | IW15: 4 | IX15: 3 | IY15: 2 | IZ15: 1 | JA15: 0 | JB15: 6 | JC15: 5 | JD15: 4 | JE15: 3 | JF15: 2 | JG15: 1 | JH15: 0 | JI15: 6 | JJ15: 5 | JK15: 4 | JL15: 3 | JM15: 2 | JN15: 1 | JO15: 0 | JP15: 6 | JQ15: 5 | JR15: 4 | JS15: 3 | JT15: 2 | JU15: 1 | JV15: 0 | JW15: 6 | JX15: 5 | JY15: 4 | JZ15: 3 | KA15: 2 | KB15: 1 | KC15: 0 | KD15: 6 | KE15: 5 | KF15: 4 | KG15: 3 | KH15: 2 | KI15: 1 | KJ15: 0 | KK15: 6 | KL15: 5 | KM15: 4 | KN15: 3 | KO15: 2 | KP15: 1 | KQ15: 0 | KR15: 6 | KS15: 5 | KT15: 4 | KU15: 3 | KV15: 2 | KW15: 1 | KX15: 0 | KY15: 6 | KZ15: 5 | LA15: 4 | LB15: 3 | LC15: 2 | LD15: 1 | LE15: 0 | LF15: 6 | LG15: 5 | LH15: 4 | LI15: 3 | LJ15: 2 | LK15: 1 | LL15: 0 | LM15: 6 | LN15: 5 | LO15: 4 | LP15: 3 | LQ15: 2 | LR15: 1 | LS15: 0 | LT15: 6 | LU15: 5 | LV15: 4 | LW15: 3 | LX15: 2 | LY15: 1 | LZ15: 0 | MA15: 6 | MB15: 5 | MC15: 4 | MD15: 3 | ME15: 2 | MF15: 1 | MG15: 0 | MH15: 13 | MI15: 12 | MJ15: 11 | MK15: 10 | ML15: 9 | MM15: 8 | MN15: 7 | MO15: 6 | MP15: 5 | MQ15: 4 | MR15: 3 | MS15: 2 | MT15: 1 | MU15: 0 | MV15: n/a
E16: Weekday | G16: day | J16: {=WEEKDAY(_xlfn.ANCHORARRAY( J11), 1 )} -> 1 | K16: 2 | L16: 3 | M16: 4 | N16: 5 | O16: 6 | P16: 7 | Q16: 1 | R16: 2 | S16: 3 | T16: 4 | U16: 5 | V16: 6 | W16: 7 | X16: 1 | Y16: 2 | Z16: 3 | AA16: 4 | AB16: 5 | AC16: 6 | AD16: 7 | AE16: 1 | AF16: 2 | AG16: 3 | AH16: 4 | AI16: 5 | AJ16: 6 | AK16: 7 | AL16: 1 | AM16: 2 | AN16: 3 | AO16: 4 | AP16: 5 | AQ16: 6 | AR16: 7 | AS16: 1 | AT16: 2 | AU16: 3 | AV16: 4 | AW16: 5 | AX16: 6 | AY16: 7 | AZ16: 1 | BA16: 2 | BB16: 3 | BC16: 4 | BD16: 5 | BE16: 6 | BF16: 7 | BG16: 1 | BH16: 2 | BI16: 3 | BJ16: 4 | BK16: 5 | BL16: 6 | BM16: 7 | BN16: 1 | BO16: 2 | BP16: 3 | BQ16: 4 | BR16: 5 | BS16: 6 | BT16: 7 | BU16: 1 | BV16: 2 | BW16: 3 | BX16: 4 | BY16: 5 | BZ16: 6 | CA16: 7 | CB16: 1 | CC16: 2 | CD16: 3 | CE16: 4 | CF16: 5 | CG16: 6 | CH16: 7 | CI16: 1 | CJ16: 2 | CK16: 3 | CL16: 4 | CM16: 5 | CN16: 6 | CO16: 7 | CP16: 1 | CQ16: 2 | CR16: 3 | CS16: 4 | CT16: 5 | CU16: 6 | CV16: 7 | CW16: 1 | CX16: 2 | CY16: 3 | CZ16: 4 | DA16: 5 | DB16: 6 | DC16: 7 | DD16: 1 | DE16: 2 | DF16: 3 | DG16: 4 | DH16: 5 | DI16: 6 | DJ16: 7 | DK16: 1 | DL16: 2 | DM16: 3 | DN16: 4 | DO16: 5 | DP16: 6 | DQ16: 7 | DR16: 1 | DS16: 2 | DT16: 3 | DU16: 4 | DV16: 5 | DW16: 6 | DX16: 7 | DY16: 1 | DZ16: 2 | EA16: 3 | EB16: 4 | EC16: 5 | ED16: 6 | EE16: 7 | EF16: 1 | EG16: 2 | EH16: 3 | EI16: 4 | EJ16: 5 | EK16: 6 | EL16: 7 | EM16: 1 | EN16: 2 | EO16: 3 | EP16: 4 | EQ16: 5 | ER16: 6 | ES16: 7 | ET16: 1 | EU16: 2 | EV16: 3 | EW16: 4 | EX16: 5 | EY16: 6 | EZ16: 7 | FA16: 1 | FB16: 2 | FC16: 3 | FD16: 4 | FE16: 5 | FF16: 6 | FG16: 7 | FH16: 1 | FI16: 2 | FJ16: 3 | FK16: 4 | FL16: 5 | FM16: 6 | FN16: 7 | FO16: 1 | FP16: 2 | FQ16: 3 | FR16: 4 | FS16: 5 | FT16: 6 | FU16: 7 | FV16: 1 | FW16: 2 | FX16: 3 | FY16: 4 | FZ16: 5 | GA16: 6 | GB16: 7 | GC16: 1 | GD16: 2 | GE16: 3 | GF16: 4 | GG16: 5 | GH16: 6 | GI16: 7 | GJ16: 1 | GK16: 2 | GL16: 3 | GM16: 4 | GN16: 5 | GO16: 6 | GP16: 7 | GQ16: 1 | GR16: 2 | GS16: 3 | GT16: 4 | GU16: 5 | GV16: 6 | GW16: 7 | GX16: 1 | GY16: 2 | GZ16: 3 | HA16: 4 | HB16: 5 | HC16: 6 | HD16: 7 | HE16: 1 | HF16: 2 | HG16: 3 | HH16: 4 | HI16: 5 | HJ16: 6 | HK16: 7 | HL16: 1 | HM16: 2 | HN16: 3 | HO16: 4 | HP16: 5 | HQ16: 6 | HR16: 7 | HS16: 1 | HT16: 2 | HU16: 3 | HV16: 4 | HW16: 5 | HX16: 6 | HY16: 7 | HZ16: 1 | IA16: 2 | IB16: 3 | IC16: 4 | ID16: 5 | IE16: 6 | IF16: 7 | IG16: 1 | IH16: 2 | II16: 3 | IJ16: 4 | IK16: 5 | IL16: 6 | IM16: 7 | IN16: 1 | IO16: 2 | IP16: 3 | IQ16: 4 | IR16: 5 | IS16: 6 | IT16: 7 | IU16: 1 | IV16: 2 | IW16: 3 | IX16: 4 | IY16: 5 | IZ16: 6 | JA16: 7 | JB16: 1 | JC16: 2 | JD16: 3 | JE16: 4 | JF16: 5 | JG16: 6 | JH16: 7 | JI16: 1 | JJ16: 2 | JK16: 3 | JL16: 4 | JM16: 5 | JN16: 6 | JO16: 7 | JP16: 1 | JQ16: 2 | JR16: 3 | JS16: 4 | JT16: 5 | JU16: 6 | JV16: 7 | JW16: 1 | JX16: 2 | JY16: 3 | JZ16: 4 | KA16: 5 | KB16: 6 | KC16: 7 | KD16: 1 | KE16: 2 | KF16: 3 | KG16: 4 | KH16: 5 | KI16: 6 | KJ16: 7 | KK16: 1 | KL16: 2 | KM16: 3 | KN16: 4 | KO16: 5 | KP16: 6 | KQ16: 7 | KR16: 1 | KS16: 2 | KT16: 3 | KU16: 4 | KV16: 5 | KW16: 6 | KX16: 7 | KY16: 1 | KZ16: 2 | LA16: 3 | LB16: 4 | LC16: 5 | LD16: 6 | LE16: 7 | LF16: 1 | LG16: 2 | LH16: 3 | LI16: 4 | LJ16: 5 | LK16: 6 | LL16: 7 | LM16: 1 | LN16: 2 | LO16: 3 | LP16: 4 | LQ16: 5 | LR16: 6 | LS16: 7 | LT16: 1 | LU16: 2 | LV16: 3 | LW16: 4 | LX16: 5 | LY16: 6 | LZ16: 7 | MA16: 1 | MB16: 2 | MC16: 3 | MD16: 4 | ME16: 5 | MF16: 6 | MG16: 7 | MH16: 1 | MI16: 2 | MJ16: 3 | MK16: 4 | ML16: 5 | MM16: 6 | MN16: 7 | MO16: 1 | MP16: 2 | MQ16: 3 | MR16: 4 | MS16: 5 | MT16: 6 | MU16: 7 | MV16: 1
A18: Season Tickets
E20: Weekly sales | G20: tickets | J20: {=_xlfn.XLOOKUP(_xlfn.ANCHORARRAY( J12), tbl_SeasonTicketSale[Week ending], tbl_SeasonTicketSale[Sales], 0,,)} -> 4800 | K20: 4800 | L20: 4800 | M20: 4800 | N20: 4800 | O20: 4800 | P20: 4800 | Q20: 3800 | R20: 3800 | S20: 3800 | T20: 3800 | U20: 3800 | V20: 3800 | W20: 3800 | X20: 3400 | Y20: 3400 | Z20: 3400 | AA20: 3400 | AB20: 3400 | AC20: 3400 | AD20: 3400 | AE20: 2800 | AF20: 2800 | AG20: 2800 | AH20: 2800 | AI20: 2800 | AJ20: 2800 | AK20: 2800 | AL20: 2700 | AM20: 2700 | AN20: 2700 | AO20: 2700 | AP20: 2700 | AQ20: 2700 | AR20: 2700 | AS20: 2750 | AT20: 2750 | AU20: 2750 | AV20: 2750 | AW20: 2750 | AX20: 2750 | AY20: 2750 | AZ20: 2600 | BA20: 2600 | BB20: 2600 | BC20: 2600 | BD20: 2600 | BE20: 2600 | BF20: 2600 | BG20: 2800 | BH20: 2800 | BI20: 2800 | BJ20: 2800 | BK20: 2800 | BL20: 2800 | BM20: 2800 | BN20: 1400 | BO20: 1400 | BP20: 1400 | BQ20: 1400 | BR20: 1400 | BS20: 1400 | BT20: 1400 | BU20: 800 | BV20: 800 | BW20: 800 | BX20: 800 | BY20: 800 | BZ20: 800 | CA20: 800 | CB20: 500 | CC20: 500 | CD20: 500 | CE20: 500 | CF20: 500 | CG20: 500 | CH20: 500 | CI20: 200 | CJ20: 200 | CK20: 200 | CL20: 200 | CM20: 200 | CN20: 200 | CO20: 200 | CP20: 150 | CQ20: 150 | CR20: 150 | CS20: 150 | CT20: 150 | CU20: 150 | CV20: 150 | CW20: 50 | CX20: 50 | CY20: 50 | CZ20: 50 | DA20: 50 | DB20: 50 | DC20: 50 | DD20: 50 | DE20: 50 | DF20: 50 | DG20: 50 | DH20: 50 | DI20: 50 | DJ20: 50 | DK20: 50 | DL20: 50 | DM20: 50 | DN20: 50 | DO20: 50 | DP20: 50 | DQ20: 50 | DR20: 50 | DS20: 50 | DT20: 50 | DU20: 50 | DV20: 50 | DW20: 50 | DX20: 50 | DY20: 50 | DZ20: 50 | EA20: 50 | EB20: 50 | EC20: 50 | ED20: 50 | EE20: 50 | EF20: 50 | EG20: 50 | EH20: 50 | EI20: 50 | EJ20: 50 | EK20: 50 | EL20: 50 | EM20: 50 | EN20: 50 | EO20: 50 | EP20: 50 | EQ20: 50 | ER20: 50 | ES20: 50 | ET20: 50 | EU20: 50 | EV20: 50 | EW20: 50 | EX20: 50 | EY20: 50 | EZ20: 50 | FA20: 50 | FB20: 50 | FC20: 50 | FD20: 50 | FE20: 50 | FF20: 50 | FG20: 50 | FH20: 50 | FI20: 50 | FJ20: 50 | FK20: 50 | FL20: 50 | FM20: 50 | FN20: 50 | FO20: 50 | FP20: 50 | FQ20: 50 | FR20: 50 | FS20: 50 | FT20: 50 | FU20: 50 | FV20: 250 | FW20: 250 | FX20: 250 | FY20: 250 | FZ20: 250 | GA20: 250 | GB20: 250 | GC20: 250 | GD20: 250 | GE20: 250 | GF20: 250 | GG20: 250 | GH20: 250 | GI20: 250 | GJ20: 50 | GK20: 50 | GL20: 50 | GM20: 50 | GN20: 50 | GO20: 50 | GP20: 50 | GQ20: 50 | GR20: 50 | GS20: 50 | GT20: 50 | GU20: 50 | GV20: 50 | GW20: 50 | GX20: 50 | GY20: 50 | GZ20: 50 | HA20: 50 | HB20: 50 | HC20: 50 | HD20: 50 | HE20: 50 | HF20: 50 | HG20: 50 | HH20: 50 | HI20: 50 | HJ20: 50 | HK20: 50 | HL20: 50 | HM20: 50 | HN20: 50 | HO20: 50 | HP20: 50 | HQ20: 50 | HR20: 50 | HS20: 0 | HT20: 0 | HU20: 0 | HV20: 0 | HW20: 0 | HX20: 0 | HY20: 0 | HZ20: 0 | IA20: 0 | IB20: 0 | IC20: 0 | ID20: 0 | IE20: 0 | IF20: 0 | IG20: 0 | IH20: 0 | II20: 0 | IJ20: 0 | IK20: 0 | IL20: 0 | IM20: 0 | IN20: 0 | IO20: 0 | IP20: 0 | IQ20: 0 | IR20: 0 | IS20: 0 | IT20: 0 | IU20: 0 | IV20: 0 | IW20: 0 | IX20: 0 | IY20: 0 | IZ20: 0 | JA20: 0 | JB20: 0 | JC20: 0 | JD20: 0 | JE20: 0 | JF20: 0 | JG20: 0 | JH20: 0 | JI20: 0 | JJ20: 0 | JK20: 0 | JL20: 0 | JM20: 0 | JN20: 0 | JO20: 0 | JP20: 0 | JQ20: 0 | JR20: 0 | JS20: 0 | JT20: 0 | JU20: 0 | JV20: 0 | JW20: 0 | JX20: 0 | JY20: 0 | JZ20: 0 | KA20: 0 | KB20: 0 | KC20: 0 | KD20: 0 | KE20: 0 | KF20: 0 | KG20: 0 | KH20: 0 | KI20: 0 | KJ20: 0 | KK20: 0 | KL20: 0 | KM20: 0 | KN20: 0 | KO20: 0 | KP20: 0 | KQ20: 0 | KR20: 0 | KS20: 0 | KT20: 0 | KU20: 0 | KV20: 0 | KW20: 0 | KX20: 0 | KY20: 0 | KZ20: 0 | LA20: 0 | LB20: 0 | LC20: 0 | LD20: 0 | LE20: 0 | LF20: 0 | LG20: 0 | LH20: 0 | LI20: 0 | LJ20: 0 | LK20: 0 | LL20: 0 | LM20: 0 | LN20: 0 | LO20: 0 | LP20: 0 | LQ20: 0 | LR20: 0 | LS20: 0 | LT20: 0 | LU20: 0 | LV20: 0 | LW20: 0 | LX20: 0 | LY20: 0 | LZ20: 0 | MA20: 0 | MB20: 0 | MC20: 0 | MD20: 0 | ME20: 0 | MF20: 0 | MG20: 0 | MH20: 0 | MI20: 0 | MJ20: 0 | MK20: 0 | ML20: 0 | MM20: 0 | MN20: 0 | MO20: 0 | MP20: 0 | MQ20: 0 | MR20: 0 | MS20: 0 | MT20: 0 | MU20: 0 | MV20: 0
E21: Sales date flag | G21: flag | J21: {=IF( ISNUMBER( _xlfn.XMATCH(_xlfn.ANCHORARRAY( J11), tbl_SeasonTicketSale[Date sold] ) ), 1, 0 )} -> 1 | K21: 0 | L21: 0 | M21: 0 | N21: 0 | O21: 0 | P21: 0 | Q21: 1 | R21: 0 | S21: 0 | T21: 0 | U21: 0 | V21: 0 | W21: 0 | X21: 1 | Y21: 0 | Z21: 0 | AA21: 0 | AB21: 0 | AC21: 0 | AD21: 0 | AE21: 1 | AF21: 0 | AG21: 0 | AH21: 0 | AI21: 0 | AJ21: 0 | AK21: 0 | AL21: 1 | AM21: 0 | AN21: 0 | AO21: 0 | AP21: 0 | AQ21: 0 | AR21: 0 | AS21: 1 | AT21: 0 | AU21: 0 | AV21: 0 | AW21: 0 | AX21: 0 | AY21: 0 | AZ21: 1 | BA21: 0 | BB21: 0 | BC21: 0 | BD21: 0 | BE21: 0 | BF21: 0 | BG21: 1 | BH21: 0 | BI21: 0 | BJ21: 0 | BK21: 0 | BL21: 0 | BM21: 0 | BN21: 1 | BO21: 0 | BP21: 0 | BQ21: 0 | BR21: 0 | BS21: 0 | BT21: 0 | BU21: 1 | BV21: 0 | BW21: 0 | BX21: 0 | BY21: 0 | BZ21: 0 | CA21: 0 | CB21: 1 | CC21: 0 | CD21: 0 | CE21: 0 | CF21: 0 | CG21: 0 | CH21: 0 | CI21: 1 | CJ21: 0 | CK21: 0 | CL21: 0 | CM21: 0 | CN21: 0 | CO21: 0 | CP21: 1 | CQ21: 0 | CR21: 0 | CS21: 0 | CT21: 0 | CU21: 0 | CV21: 0 | CW21: 1 | CX21: 0 | CY21: 0 | CZ21: 0 | DA21: 0 | DB21: 0 | DC21: 0 | DD21: 1 | DE21: 0 | DF21: 0 | DG21: 0 | DH21: 0 | DI21: 0 | DJ21: 0 | DK21: 1 | DL21: 0 | DM21: 0 | DN21: 0 | DO21: 0 | DP21: 0 | DQ21: 0 | DR21: 1 | DS21: 0 | DT21: 0 | DU21: 0 | DV21: 0 | DW21: 0 | DX21: 0 | DY21: 1 | DZ21: 0 | EA21: 0 | EB21: 0 | EC21: 0 | ED21: 0 | EE21: 0 | EF21: 1 | EG21: 0 | EH21: 0 | EI21: 0 | EJ21: 0 | EK21: 0 | EL21: 0 | EM21: 1 | EN21: 0 | EO21: 0 | EP21: 0 | EQ21: 0 | ER21: 0 | ES21: 0 | ET21: 1 | EU21: 0 | EV21: 0 | EW21: 0 | EX21: 0 | EY21: 0 | EZ21: 0 | FA21: 1 | FB21: 0 | FC21: 0 | FD21: 0 | FE21: 0 | FF21: 0 | FG21: 0 | FH21: 1 | FI21: 0 | FJ21: 0 | FK21: 0 | FL21: 0 | FM21: 0 | FN21: 0 | FO21: 1 | FP21: 0 | FQ21: 0 | FR21: 0 | FS21: 0 | FT21: 0 | FU21: 0 | FV21: 1 | FW21: 0 | FX21: 0 | FY21: 0 | FZ21: 0 | GA21: 0 | GB21: 0 | GC21: 1 | GD21: 0 | GE21: 0 | GF21: 0 | GG21: 0 | GH21: 0 | GI21: 0 | GJ21: 1 | GK21: 0 | GL21: 0 | GM21: 0 | GN21: 0 | GO21: 0 | GP21: 0 | GQ21: 1 | GR21: 0 | GS21: 0 | GT21: 0 | GU21: 0 | GV21: 0 | GW21: 0 | GX21: 1 | GY21: 0 | GZ21: 0 | HA21: 0 | HB21: 0 | HC21: 0 | HD21: 0 | HE21: 1 | HF21: 0 | HG21: 0 | HH21: 0 | HI21: 0 | HJ21: 0 | HK21: 0 | HL21: 1 | HM21: 0 | HN21: 0 | HO21: 0 | HP21: 0 | HQ21: 0 | HR21: 0 | HS21: 0 | HT21: 0 | HU21: 0 | HV21: 0 | HW21: 0 | HX21: 0 | HY21: 0 | HZ21: 0 | IA21: 0 | IB21: 0 | IC21: 0 | ID21: 0 | IE21: 0 | IF21: 0 | IG21: 0 | IH21: 0 | II21: 0 | IJ21: 0 | IK21: 0 | IL21: 0 | IM21: 0 | IN21: 0 | IO21: 0 | IP21: 0 | IQ21: 0 | IR21: 0 | IS21: 0 | IT21: 0 | IU21: 0 | IV21: 0 | IW21: 0 | IX21: 0 | IY21: 0 | IZ21: 0 | JA21: 0 | JB21: 0 | JC21: 0 | JD21: 0 | JE21: 0 | JF21: 0 | JG21: 0 | JH21: 0 | JI21: 0 | JJ21: 0 | JK21: 0 | JL21: 0 | JM21: 0 | JN21: 0 | JO21: 0 | JP21: 0 | JQ21: 0 | JR21: 0 | JS21: 0 | JT21: 0 | JU21: 0 | JV21: 0 | JW21: 0 | JX21: 0 | JY21: 0 | JZ21: 0 | KA21: 0 | KB21: 0 | KC21: 0 | KD21: 0 | KE21: 0 | KF21: 0 | KG21: 0 | KH21: 0 | KI21: 0 | KJ21: 0 | KK21: 0 | KL21: 0 | KM21: 0 | KN21: 0 | KO21: 0 | KP21: 0 | KQ21: 0 | KR21: 0 | KS21: 0 | KT21: 0 | KU21: 0 | KV21: 0 | KW21: 0 | KX21: 0 | KY21: 0 | KZ21: 0 | LA21: 0 | LB21: 0 | LC21: 0 | LD21: 0 | LE21: 0 | LF21: 0 | LG21: 0 | LH21: 0 | LI21: 0 | LJ21: 0 | LK21: 0 | LL21: 0 | LM21: 0 | LN21: 0 | LO21: 0 | LP21: 0 | LQ21: 0 | LR21: 0 | LS21: 0 | LT21: 0 | LU21: 0 | LV21: 0 | LW21: 0 | LX21: 0 | LY21: 0 | LZ21: 0 | MA21: 0 | MB21: 0 | MC21: 0 | MD21: 0 | ME21: 0 | MF21: 0 | MG21: 0 | MH21: 0 | MI21: 0 | MJ21: 0 | MK21: 0 | ML21: 0 | MM21: 0 | MN21: 0 | MO21: 0 | MP21: 0 | MQ21: 0 | MR21: 0 | MS21: 0 | MT21: 0 | MU21: 0 | MV21: 0
E22: Daily sales of season tickets | G22: tickets | H22: {=_xlfn.BYROW(_xlfn.ANCHORARRAY( J22), _xleta.SUM )} -> 30000 | J22: {=IF( SpreadSTs,_xlfn.ANCHORARRAY( J20) / 7,_xlfn.ANCHORARRAY( J20) *_xlfn.ANCHORARRAY( J21) )} -> 4800 | K22: 0 | L22: 0 | M22: 0 | N22: 0 | O22: 0 | P22: 0 | Q22: 3800 | R22: 0 | S22: 0 | T22: 0 | U22: 0 | V22: 0 | W22: 0 | X22: 3400 | Y22: 0 | Z22: 0 | AA22: 0 | AB22: 0 | AC22: 0 | AD22: 0 | AE22: 2800 | AF22: 0 | AG22: 0 | AH22: 0 | AI22: 0 | AJ22: 0 | AK22: 0 | AL22: 2700 | AM22: 0 | AN22: 0 | AO22: 0 | AP22: 0 | AQ22: 0 | AR22: 0 | AS22: 2750 | AT22: 0 | AU22: 0 | AV22: 0 | AW22: 0 | AX22: 0 | AY22: 0 | AZ22: 2600 | BA22: 0 | BB22: 0 | BC22: 0 | BD22: 0 | BE22: 0 | BF22: 0 | BG22: 2800 | BH22: 0 | BI22: 0 | BJ22: 0 | BK22: 0 | BL22: 0 | BM22: 0 | BN22: 1400 | BO22: 0 | BP22: 0 | BQ22: 0 | BR22: 0 | BS22: 0 | BT22: 0 | BU22: 800 | BV22: 0 | BW22: 0 | BX22: 0 | BY22: 0 | BZ22: 0 | CA22: 0 | CB22: 500 | CC22: 0 | CD22: 0 | CE22: 0 | CF22: 0 | CG22: 0 | CH22: 0 | CI22: 200 | CJ22: 0 | CK22: 0 | CL22: 0 | CM22: 0 | CN22: 0 | CO22: 0 | CP22: 150 | CQ22: 0 | CR22: 0 | CS22: 0 | CT22: 0 | CU22: 0 | CV22: 0 | CW22: 50 | CX22: 0 | CY22: 0 | CZ22: 0 | DA22: 0 | DB22: 0 | DC22: 0 | DD22: 50 | DE22: 0 | DF22: 0 | DG22: 0 | DH22: 0 | DI22: 0 | DJ22: 0 | DK22: 50 | DL22: 0 | DM22: 0 | DN22: 0 | DO22: 0 | DP22: 0 | DQ22: 0 | DR22: 50 | DS22: 0 | DT22: 0 | DU22: 0 | DV22: 0 | DW22: 0 | DX22: 0 | DY22: 50 | DZ22: 0 | EA22: 0 | EB22: 0 | EC22: 0 | ED22: 0 | EE22: 0 | EF22: 50 | EG22: 0 | EH22: 0 | EI22: 0 | EJ22: 0 | EK22: 0 | EL22: 0 | EM22: 50 | EN22: 0 | EO22: 0 | EP22: 0 | EQ22: 0 | ER22: 0 | ES22: 0 | ET22: 50 | EU22: 0 | EV22: 0 | EW22: 0 | EX22: 0 | EY22: 0 | EZ22: 0 | FA22: 50 | FB22: 0 | FC22: 0 | FD22: 0 | FE22: 0 | FF22: 0 | FG22: 0 | FH22: 50 | FI22: 0 | FJ22: 0 | FK22: 0 | FL22: 0 | FM22: 0 | FN22: 0 | FO22: 50 | FP22: 0 | FQ22: 0 | FR22: 0 | FS22: 0 | FT22: 0 | FU22: 0 | FV22: 250 | FW22: 0 | FX22: 0 | FY22: 0 | FZ22: 0 | GA22: 0 | GB22: 0 | GC22: 250 | GD22: 0 | GE22: 0 | GF22: 0 | GG22: 0 | GH22: 0 | GI22: 0 | GJ22: 50 | GK22: 0 | GL22: 0 | GM22: 0 | GN22: 0 | GO22: 0 | GP22: 0 | GQ22: 50 | GR22: 0 | GS22: 0 | GT22: 0 | GU22: 0 | GV22: 0 | GW22: 0 | GX22: 50 | GY22: 0 | GZ22: 0 | HA22: 0 | HB22: 0 | HC22: 0 | HD22: 0 | HE22: 50 | HF22: 0 | HG22: 0 | HH22: 0 | HI22: 0 | HJ22: 0 | HK22: 0 | HL22: 50 | HM22: 0 | HN22: 0 | HO22: 0 | HP22: 0 | HQ22: 0 | HR22: 0 | HS22: 0 | HT22: 0 | HU22: 0 | HV22: 0 | HW22: 0 | HX22: 0 | HY22: 0 | HZ22: 0 | IA22: 0 | IB22: 0 | IC22: 0 | ID22: 0 | IE22: 0 | IF22: 0 | IG22: 0 | IH22: 0 | II22: 0 | IJ22: 0 | IK22: 0 | IL22: 0 | IM22: 0 | IN22: 0 | IO22: 0 | IP22: 0 | IQ22: 0 | IR22: 0 | IS22: 0 | IT22: 0 | IU22: 0 | IV22: 0 | IW22: 0 | IX22: 0 | IY22: 0 | IZ22: 0 | JA22: 0 | JB22: 0 | JC22: 0 | JD22: 0 | JE22: 0 | JF22: 0 | JG22: 0 | JH22: 0 | JI22: 0 | JJ22: 0 | JK22: 0 | JL22: 0 | JM22: 0 | JN22: 0 | JO22: 0 | JP22: 0 | JQ22: 0 | JR22: 0 | JS22: 0 | JT22: 0 | JU22: 0 | JV22: 0 | JW22: 0 | JX22: 0 | JY22: 0 | JZ22: 0 | KA22: 0 | KB22: 0 | KC22: 0 | KD22: 0 | KE22: 0 | KF22: 0 | KG22: 0 | KH22: 0 | KI22: 0 | KJ22: 0 | KK22: 0 | KL22: 0 | KM22: 0 | KN22: 0 | KO22: 0 | KP22: 0 | KQ22: 0 | KR22: 0 | KS22: 0 | KT22: 0 | KU22: 0 | KV22: 0 | KW22: 0 | KX22: 0 | KY22: 0 | KZ22: 0 | LA22: 0 | LB22: 0 | LC22: 0 | LD22: 0 | LE22: 0 | LF22: 0 | LG22: 0 | LH22: 0 | LI22: 0 | LJ22: 0 | LK22: 0 | LL22: 0 | LM22: 0 | LN22: 0 | LO22: 0 | LP22: 0 | LQ22: 0 | LR22: 0 | LS22: 0 | LT22: 0 | LU22: 0 | LV22: 0 | LW22: 0 | LX22: 0 | LY22: 0 | LZ22: 0 | MA22: 0 | MB22: 0 | MC22: 0 | MD22: 0 | ME22: 0 | MF22: 0 | MG22: 0 | MH22: 0 | MI22: 0 | MJ22: 0 | MK22: 0 | ML22: 0 | MM22: 0 | MN22: 0 | MO22: 0 | MP22: 0 | MQ22: 0 | MR22: 0 | MS22: 0 | MT22: 0 | MU22: 0 | MV22: 0
E24: Cash from season tickets sale | G24: USD | H24: {=_xlfn.BYROW(_xlfn.ANCHORARRAY( J24), _xleta.SUM )} -> 22500000 | J24: {=_xlfn.ANCHORARRAY( J22) * SeasonTicketPrice} -> 3600000 | K24: 0 | L24: 0 | M24: 0 | N24: 0 | O24: 0 | P24: 0 | Q24: 2850000 | R24: 0 | S24: 0 | T24: 0 | U24: 0 | V24: 0 | W24: 0 | X24: 2550000 | Y24: 0 | Z24: 0 | AA24: 0 | AB24: 0 | AC24: 0 | AD24: 0 | AE24: 2100000 | AF24: 0 | AG24: 0 | AH24: 0 | AI24: 0 | AJ24: 0 | AK24: 0 | AL24: 2025000 | AM24: 0 | AN24: 0 | AO24: 0 | AP24: 0 | AQ24: 0 | AR24: 0 | AS24: 2062500 | AT24: 0 | AU24: 0 | AV24: 0 | AW24: 0 | AX24: 0 | AY24: 0 | AZ24: 1950000 | BA24: 0 | BB24: 0 | BC24: 0 | BD24: 0 | BE24: 0 | BF24: 0 | BG24: 2100000 | BH24: 0 | BI24: 0 | BJ24: 0 | BK24: 0 | BL24: 0 | BM24: 0 | BN24: 1050000 | BO24: 0 | BP24: 0 | BQ24: 0 | BR24: 0 | BS24: 0 | BT24: 0 | BU24: 600000 | BV24: 0 | BW24: 0 | BX24: 0 | BY24: 0 | BZ24: 0 | CA24: 0 | CB24: 375000 | CC24: 0 | CD24: 0 | CE24: 0 | CF24: 0 | CG24: 0 | CH24: 0 | CI24: 150000 | CJ24: 0 | CK24: 0 | CL24: 0 | CM24: 0 | CN24: 0 | CO24: 0 | CP24: 112500 | CQ24: 0 | CR24: 0 | CS24: 0 | CT24: 0 | CU24: 0 | CV24: 0 | CW24: 37500 | CX24: 0 | CY24: 0 | CZ24: 0 | DA24: 0 | DB24: 0 | DC24: 0 | DD24: 37500 | DE24: 0 | DF24: 0 | DG24: 0 | DH24: 0 | DI24: 0 | DJ24: 0 | DK24: 37500 | DL24: 0 | DM24: 0 | DN24: 0 | DO24: 0 | DP24: 0 | DQ24: 0 | DR24: 37500 | DS24: 0 | DT24: 0 | DU24: 0 | DV24: 0 | DW24: 0 | DX24: 0 | DY24: 37500 | DZ24: 0 | EA24: 0 | EB24: 0 | EC24: 0 | ED24: 0 | EE24: 0 | EF24: 37500 | EG24: 0 | EH24: 0 | EI24: 0 | EJ24: 0 | EK24: 0 | EL24: 0 | EM24: 37500 | EN24: 0 | EO24: 0 | EP24: 0 | EQ24: 0 | ER24: 0 | ES24: 0 | ET24: 37500 | EU24: 0 | EV24: 0 | EW24: 0 | EX24: 0 | EY24: 0 | EZ24: 0 | FA24: 37500 | FB24: 0 | FC24: 0 | FD24: 0 | FE24: 0 | FF24: 0 | FG24: 0 | FH24: 37500 | FI24: 0 | FJ24: 0 | FK24: 0 | FL24: 0 | FM24: 0 | FN24: 0 | FO24: 37500 | FP24: 0 | FQ24: 0 | FR24: 0 | FS24: 0 | FT24: 0 | FU24: 0 | FV24: 187500 | FW24: 0 | FX24: 0 | FY24: 0 | FZ24: 0 | GA24: 0 | GB24: 0 | GC24: 187500 | GD24: 0 | GE24: 0 | GF24: 0 | GG24: 0 | GH24: 0 | GI24: 0 | GJ24: 37500 | GK24: 0 | GL24: 0 | GM24: 0 | GN24: 0 | GO24: 0 | GP24: 0 | GQ24: 37500 | GR24: 0 | GS24: 0 | GT24: 0 | GU24: 0 | GV24: 0 | GW24: 0 | GX24: 37500 | GY24: 0 | GZ24: 0 | HA24: 0 | HB24: 0 | HC24: 0 | HD24: 0 | HE24: 37500 | HF24: 0 | HG24: 0 | HH24: 0 | HI24: 0 | HJ24: 0 | HK24: 0 | HL24: 37500 | HM24: 0 | HN24: 0 | HO24: 0 | HP24: 0 | HQ24: 0 | HR24: 0 | HS24: 0 | HT24: 0 | HU24: 0 | HV24: 0 | HW24: 0 | HX24: 0 | HY24: 0 | HZ24: 0 | IA24: 0 | IB24: 0 | IC24: 0 | ID24: 0 | IE24: 0 | IF24: 0 | IG24: 0 | IH24: 0 | II24: 0 | IJ24: 0 | IK24: 0 | IL24: 0 | IM24: 0 | IN24: 0 | IO24: 0 | IP24: 0 | IQ24: 0 | IR24: 0 | IS24: 0 | IT24: 0 | IU24: 0 | IV24: 0 | IW24: 0 | IX24: 0 | IY24: 0 | IZ24: 0 | JA24: 0 | JB24: 0 | JC24: 0 | JD24: 0 | JE24: 0 | JF24: 0 | JG24: 0 | JH24: 0 | JI24: 0 | JJ24: 0 | JK24: 0 | JL24: 0 | JM24: 0 | JN24: 0 | JO24: 0 | JP24: 0 | JQ24: 0 | JR24: 0 | JS24: 0 | JT24: 0 | JU24: 0 | JV24: 0 | JW24: 0 | JX24: 0 | JY24: 0 | JZ24: 0 | KA24: 0 | KB24: 0 | KC24: 0 | KD24: 0 | KE24: 0 | KF24: 0 | KG24: 0 | KH24: 0 | KI24: 0 | KJ24: 0 | KK24: 0 | KL24: 0 | KM24: 0 | KN24: 0 | KO24: 0 | KP24: 0 | KQ24: 0 | KR24: 0 | KS24: 0 | KT24: 0 | KU24: 0 | KV24: 0 | KW24: 0 | KX24: 0 | KY24: 0 | KZ24: 0 | LA24: 0 | LB24: 0 | LC24: 0 | LD24: 0 | LE24: 0 | LF24: 0 | LG24: 0 | LH24: 0 | LI24: 0 | LJ24: 0 | LK24: 0 | LL24: 0 | LM24: 0 | LN24: 0 | LO24: 0 | LP24: 0 | LQ24: 0 | LR24: 0 | LS24: 0 | LT24: 0 | LU24: 0 | LV24: 0 | LW24: 0 | LX24: 0 | LY24: 0 | LZ24: 0 | MA24: 0 | MB24: 0 | MC24: 0 | MD24: 0 | ME24: 0 | MF24: 0 | MG24: 0 | MH24: 0 | MI24: 0 | MJ24: 0 | MK24: 0 | ML24: 0 | MM24: 0 | MN24: 0 | MO24: 0 | MP24: 0 | MQ24: 0 | MR24: 0 | MS24: 0 | MT24: 0 | MU24: 0 | MV24: 0
E25: Pct of games played | G25: % | J25: {=_xlfn.LET( _xlpm.days_to_game,_xlfn.ANCHORARRAY( J15), _xlpm.number_of_games, ROWS( tbl_GameDates[Date] ), _xlfn.SCAN( 0, _xlpm.days_to_game, _xlfn.LAMBDA(_xlpm.acc,_xlpm.dtg, IF( _xlpm.dtg = 0, _xlpm.acc + 1 / _xlpm.number_of_games, _xlpm.acc ) ) ) )} -> 0 | K25: 0 | L25: 0 | M25: 0 | N25: 0 | O25: 0 | P25: 0 | Q25: 0 | R25: 0 | S25: 0 | T25: 0 | U25: 0 | V25: 0 | W25: 0 | X25: 0 | Y25: 0 | Z25: 0 | AA25: 0 | AB25: 0 | AC25: 0 | AD25: 0 | AE25: 0 | AF25: 0 | AG25: 0 | AH25: 0 | AI25: 0 | AJ25: 0 | AK25: 0 | AL25: 0 | AM25: 0 | AN25: 0 | AO25: 0 | AP25: 0 | AQ25: 0 | AR25: 0 | AS25: 0 | AT25: 0 | AU25: 0 | AV25: 0 | AW25: 0 | AX25: 0 | AY25: 0 | AZ25: 0 | BA25: 0 | BB25: 0 | BC25: 0 | BD25: 0 | BE25: 0 | BF25: 0 | BG25: 0 | BH25: 0 | BI25: 0 | BJ25: 0 | BK25: 0 | BL25: 0 | BM25: 0.025 | BN25: 0.025 | BO25: 0.025 | BP25: 0.025 | BQ25: 0.025 | BR25: 0.025 | BS25: 0.025 | BT25: 0.05 | BU25: 0.05 | BV25: 0.05 | BW25: 0.05 | BX25: 0.05 | BY25: 0.05 | BZ25: 0.05 | CA25: 0.075 | CB25: 0.075 | CC25: 0.075 | CD25: 0.075 | CE25: 0.075 | CF25: 0.075 | CG25: 0.075 | CH25: 0.1 | CI25: 0.1 | CJ25: 0.1 | CK25: 0.1 | CL25: 0.1 | CM25: 0.1 | CN25: 0.1 | CO25: 0.125 | CP25: 0.125 | CQ25: 0.125 | CR25: 0.125 | CS25: 0.125 | CT25: 0.125 | CU25: 0.125 | CV25: 0.15 | CW25: 0.15 | CX25: 0.15 | CY25: 0.15 | CZ25: 0.15 | DA25: 0.15 | DB25: 0.15 | DC25: 0.175 | DD25: 0.175 | DE25: 0.175 | DF25: 0.175 | DG25: 0.175 | DH25: 0.175 | DI25: 0.175 | DJ25: 0.2 | DK25: 0.2 | DL25: 0.2 | DM25: 0.2 | DN25: 0.2 | DO25: 0.2 | DP25: 0.2 | DQ25: 0.225 | DR25: 0.225 | DS25: 0.225 | DT25: 0.225 | DU25: 0.225 | DV25: 0.225 | DW25: 0.225 | DX25: 0.25 | DY25: 0.25 | DZ25: 0.25 | EA25: 0.25 | EB25: 0.25 | EC25: 0.25 | ED25: 0.25 | EE25: 0.275 | EF25: 0.275 | EG25: 0.275 | EH25: 0.275 | EI25: 0.275 | EJ25: 0.275 | EK25: 0.275 | EL25: 0.3 | EM25: 0.3 | EN25: 0.3 | EO25: 0.3 | EP25: 0.3 | EQ25: 0.3 | ER25: 0.3 | ES25: 0.325 | ET25: 0.325 | EU25: 0.325 | EV25: 0.325 | EW25: 0.325 | EX25: 0.325 | EY25: 0.325 | EZ25: 0.35 | FA25: 0.35 | FB25: 0.35 | FC25: 0.35 | FD25: 0.35 | FE25: 0.35 | FF25: 0.35 | FG25: 0.375 | FH25: 0.375 | FI25: 0.375 | FJ25: 0.375 | FK25: 0.375 | FL25: 0.375 | FM25: 0.375 | FN25: 0.4 | FO25: 0.4 | FP25: 0.4 | FQ25: 0.4 | FR25: 0.4 | FS25: 0.4 | FT25: 0.4 | FU25: 0.425 | FV25: 0.425 | FW25: 0.425 | FX25: 0.425 | FY25: 0.425 | FZ25: 0.425 | GA25: 0.425 | GB25: 0.45 | GC25: 0.45 | GD25: 0.45 | GE25: 0.45 | GF25: 0.45 | GG25: 0.45 | GH25: 0.45 | GI25: 0.45 | GJ25: 0.45 | GK25: 0.45 | GL25: 0.45 | GM25: 0.45 | GN25: 0.45 | GO25: 0.45 | GP25: 0.45 | GQ25: 0.45 | GR25: 0.45 | GS25: 0.45 | GT25: 0.45 | GU25: 0.45 | GV25: 0.45 | GW25: 0.475 | GX25: 0.475 | GY25: 0.475 | GZ25: 0.475 | HA25: 0.475 | HB25: 0.475 | HC25: 0.475 | HD25: 0.5 | HE25: 0.5 | HF25: 0.5 | HG25: 0.5 | HH25: 0.5 | HI25: 0.5 | HJ25: 0.5 | HK25: 0.525 | HL25: 0.525 | HM25: 0.525 | HN25: 0.525 | HO25: 0.525 | HP25: 0.525 | HQ25: 0.525 | HR25: 0.55 | HS25: 0.55 | HT25: 0.55 | HU25: 0.55 | HV25: 0.55 | HW25: 0.55 | HX25: 0.55 | HY25: 0.575 | HZ25: 0.575 | IA25: 0.575 | IB25: 0.575 | IC25: 0.575 | ID25: 0.575 | IE25: 0.575 | IF25: 0.6 | IG25: 0.6 | IH25: 0.6 | II25: 0.6 | IJ25: 0.6 | IK25: 0.6 | IL25: 0.6 | IM25: 0.625 | IN25: 0.625 | IO25: 0.625 | IP25: 0.625 | IQ25: 0.625 | IR25: 0.625 | IS25: 0.625 | IT25: 0.65 | IU25: 0.65 | IV25: 0.65 | IW25: 0.65 | IX25: 0.65 | IY25: 0.65 | IZ25: 0.65 | JA25: 0.675 | JB25: 0.675 | JC25: 0.675 | JD25: 0.675 | JE25: 0.675 | JF25: 0.675 | JG25: 0.675 | JH25: 0.7 | JI25: 0.7 | JJ25: 0.7 | JK25: 0.7 | JL25: 0.7 | JM25: 0.7 | JN25: 0.7 | JO25: 0.725 | JP25: 0.725 | JQ25: 0.725 | JR25: 0.725 | JS25: 0.725 | JT25: 0.725 | JU25: 0.725 | JV25: 0.75 | JW25: 0.75 | JX25: 0.75 | JY25: 0.75 | JZ25: 0.75 | KA25: 0.75 | KB25: 0.75 | KC25: 0.775 | KD25: 0.775 | KE25: 0.775 | KF25: 0.775 | KG25: 0.775 | KH25: 0.775 | KI25: 0.775 | KJ25: 0.8 | KK25: 0.8 | KL25: 0.8 | KM25: 0.8 | KN25: 0.8 | KO25: 0.8 | KP25: 0.8 | KQ25: 0.825 | KR25: 0.825 | KS25: 0.825 | KT25: 0.825 | KU25: 0.825 | KV25: 0.825 | KW25: 0.825 | KX25: 0.85 | KY25: 0.85 | KZ25: 0.85 | LA25: 0.85 | LB25: 0.85 | LC25: 0.85 | LD25: 0.85 | LE25: 0.875 | LF25: 0.875 | LG25: 0.875 | LH25: 0.875 | LI25: 0.875 | LJ25: 0.875 | LK25: 0.875 | LL25: 0.9 | LM25: 0.9 | LN25: 0.9 | LO25: 0.9 | LP25: 0.9 | LQ25: 0.9 | LR25: 0.9 | LS25: 0.925 | LT25: 0.925 | LU25: 0.925 | LV25: 0.925 | LW25: 0.925 | LX25: 0.925 | LY25: 0.925 | LZ25: 0.95 | MA25: 0.95 | MB25: 0.95 | MC25: 0.95 | MD25: 0.95 | ME25: 0.95 | MF25: 0.95 | MG25: 0.975 | MH25: 0.975 | MI25: 0.975 | MJ25: 0.975 | MK25: 0.975 | ML25: 0.975 | MM25: 0.975 | MN25: 0.975 | MO25: 0.975 | MP25: 0.975 | MQ25: 0.975 | MR25: 0.975 | MS25: 0.975 | MT25: 0.975 | MU25: 1 | MV25: 1
E26: Cumulative cash from season ticket sale | G26: USD | J26: {=_xlfn.LET( _xlpm.cash_from_sales,_xlfn.ANCHORARRAY( J24), _xlfn.SCAN( 0, _xlpm.cash_from_sales, _xlfn.LAMBDA(_xlpm.a,_xlpm.cash, _xlpm.a + _xlpm.cash ) ) )} -> 3600000 | K26: 3600000 | L26: 3600000 | M26: 3600000 | N26: 3600000 | O26: 3600000 | P26: 3600000 | Q26: 6450000 | R26: 6450000 | S26: 6450000 | T26: 6450000 | U26: 6450000 | V26: 6450000 | W26: 6450000 | X26: 9000000 | Y26: 9000000 | Z26: 9000000 | AA26: 9000000 | AB26: 9000000 | AC26: 9000000 | AD26: 9000000 | AE26: 11100000 | AF26: 11100000 | AG26: 11100000 | AH26: 11100000 | AI26: 11100000 | AJ26: 11100000 | AK26: 11100000 | AL26: 13125000 | AM26: 13125000 | AN26: 13125000 | AO26: 13125000 | AP26: 13125000 | AQ26: 13125000 | AR26: 13125000 | AS26: 15187500 | AT26: 15187500 | AU26: 15187500 | AV26: 15187500 | AW26: 15187500 | AX26: 15187500 | AY26: 15187500 | AZ26: 17137500 | BA26: 17137500 | BB26: 17137500 | BC26: 17137500 | BD26: 17137500 | BE26: 17137500 | BF26: 17137500 | BG26: 19237500 | BH26: 19237500 | BI26: 19237500 | BJ26: 19237500 | BK26: 19237500 | BL26: 19237500 | BM26: 19237500 | BN26: 20287500 | BO26: 20287500 | BP26: 20287500 | BQ26: 20287500 | BR26: 20287500 | BS26: 20287500 | BT26: 20287500 | BU26: 20887500 | BV26: 20887500 | BW26: 20887500 | BX26: 20887500 | BY26: 20887500 | BZ26: 20887500 | CA26: 20887500 | CB26: 21262500 | CC26: 21262500 | CD26: 21262500 | CE26: 21262500 | CF26: 21262500 | CG26: 21262500 | CH26: 21262500 | CI26: 21412500 | CJ26: 21412500 | CK26: 21412500 | CL26: 21412500 | CM26: 21412500 | CN26: 21412500 | CO26: 21412500 | CP26: 21525000 | CQ26: 21525000 | CR26: 21525000 | CS26: 21525000 | CT26: 21525000 | CU26: 21525000 | CV26: 21525000 | CW26: 21562500 | CX26: 21562500 | CY26: 21562500 | CZ26: 21562500 | DA26: 21562500 | DB26: 21562500 | DC26: 21562500 | DD26: 21600000 | DE26: 21600000 | DF26: 21600000 | DG26: 21600000 | DH26: 21600000 | DI26: 21600000 | DJ26: 21600000 | DK26: 21637500 | DL26: 21637500 | DM26: 21637500 | DN26: 21637500 | DO26: 21637500 | DP26: 21637500 | DQ26: 21637500 | DR26: 21675000 | DS26: 21675000 | DT26: 21675000 | DU26: 21675000 | DV26: 21675000 | DW26: 21675000 | DX26: 21675000 | DY26: 21712500 | DZ26: 21712500 | EA26: 21712500 | EB26: 21712500 | EC26: 21712500 | ED26: 21712500 | EE26: 21712500 | EF26: 21750000 | EG26: 21750000 | EH26: 21750000 | EI26: 21750000 | EJ26: 21750000 | EK26: 21750000 | EL26: 21750000 | EM26: 21787500 | EN26: 21787500 | EO26: 21787500 | EP26: 21787500 | EQ26: 21787500 | ER26: 21787500 | ES26: 21787500 | ET26: 21825000 | EU26: 21825000 | EV26: 21825000 | EW26: 21825000 | EX26: 21825000 | EY26: 21825000 | EZ26: 21825000 | FA26: 21862500 | FB26: 21862500 | FC26: 21862500 | FD26: 21862500 | FE26: 21862500 | FF26: 21862500 | FG26: 21862500 | FH26: 21900000 | FI26: 21900000 | FJ26: 21900000 | FK26: 21900000 | FL26: 21900000 | FM26: 21900000 | FN26: 21900000 | FO26: 21937500 | FP26: 21937500 | FQ26: 21937500 | FR26: 21937500 | FS26: 21937500 | FT26: 21937500 | FU26: 21937500 | FV26: 22125000 | FW26: 22125000 | FX26: 22125000 | FY26: 22125000 | FZ26: 22125000 | GA26: 22125000 | GB26: 22125000 | GC26: 22312500 | GD26: 22312500 | GE26: 22312500 | GF26: 22312500 | GG26: 22312500 | GH26: 22312500 | GI26: 22312500 | GJ26: 22350000 | GK26: 22350000 | GL26: 22350000 | GM26: 22350000 | GN26: 22350000 | GO26: 22350000 | GP26: 22350000 | GQ26: 22387500 | GR26: 22387500 | GS26: 22387500 | GT26: 22387500 | GU26: 22387500 | GV26: 22387500 | GW26: 22387500 | GX26: 22425000 | GY26: 22425000 | GZ26: 22425000 | HA26: 22425000 | HB26: 22425000 | HC26: 22425000 | HD26: 22425000 | HE26: 22462500 | HF26: 22462500 | HG26: 22462500 | HH26: 22462500 | HI26: 22462500 | HJ26: 22462500 | HK26: 22462500 | HL26: 22500000 | HM26: 22500000 | HN26: 22500000 | HO26: 22500000 | HP26: 22500000 | HQ26: 22500000 | HR26: 22500000 | HS26: 22500000 | HT26: 22500000 | HU26: 22500000 | HV26: 22500000 | HW26: 22500000 | HX26: 22500000 | HY26: 22500000 | HZ26: 22500000 | IA26: 22500000 | IB26: 22500000 | IC26: 22500000 | ID26: 22500000 | IE26: 22500000 | IF26: 22500000 | IG26: 22500000 | IH26: 22500000 | II26: 22500000 | IJ26: 22500000 | IK26: 22500000 | IL26: 22500000 | IM26: 22500000 | IN26: 22500000 | IO26: 22500000 | IP26: 22500000 | IQ26: 22500000 | IR26: 22500000 | IS26: 22500000 | IT26: 22500000 | IU26: 22500000 | IV26: 22500000 | IW26: 22500000 | IX26: 22500000 | IY26: 22500000 | IZ26: 22500000 | JA26: 22500000 | JB26: 22500000 | JC26: 22500000 | JD26: 22500000 | JE26: 22500000 | JF26: 22500000 | JG26: 22500000 | JH26: 22500000 | JI26: 22500000 | JJ26: 22500000 | JK26: 22500000 | JL26: 22500000 | JM26: 22500000 | JN26: 22500000 | JO26: 22500000 | JP26: 22500000 | JQ26: 22500000 | JR26: 22500000 | JS26: 22500000 | JT26: 22500000 | JU26: 22500000 | JV26: 22500000 | JW26: 22500000 | JX26: 22500000 | JY26: 22500000 | JZ26: 22500000 | KA26: 22500000 | KB26: 22500000 | KC26: 22500000 | KD26: 22500000 | KE26: 22500000 | KF26: 22500000 | KG26: 22500000 | KH26: 22500000 | KI26: 22500000 | KJ26: 22500000 | KK26: 22500000 | KL26: 22500000 | KM26: 22500000 | KN26: 22500000 | KO26: 22500000 | KP26: 22500000 | KQ26: 22500000 | KR26: 22500000 | KS26: 22500000 | KT26: 22500000 | KU26: 22500000 | KV26: 22500000 | KW26: 22500000 | KX26: 22500000 | KY26: 22500000 | KZ26: 22500000 | LA26: 22500000 | LB26: 22500000 | LC26: 22500000 | LD26: 22500000 | LE26: 22500000 | LF26: 22500000 | LG26: 22500000 | LH26: 22500000 | LI26: 22500000 | LJ26: 22500000 | LK26: 22500000 | LL26: 22500000 | LM26: 22500000 | LN26: 22500000 | LO26: 22500000 | LP26: 22500000 | LQ26: 22500000 | LR26: 22500000 | LS26: 22500000 | LT26: 22500000 | LU26: 22500000 | LV26: 22500000 | LW26: 22500000 | LX26: 22500000 | LY26: 22500000 | LZ26: 22500000 | MA26: 22500000 | MB26: 22500000 | MC26: 22500000 | MD26: 22500000 | ME26: 22500000 | MF26: 22500000 | MG26: 22500000 | MH26: 22500000 | MI26: 22500000 | MJ26: 22500000 | MK26: 22500000 | ML26: 22500000 | MM26: 22500000 | MN26: 22500000 | MO26: 22500000 | MP26: 22500000 | MQ26: 22500000 | MR26: 22500000 | MS26: 22500000 | MT26: 22500000 | MU26: 22500000 | MV26: 22500000
E27: Cumulative revenue from season ticket sale | G27: USD | J27: {=_xlfn.LET( _xlpm.pct_games_played,_xlfn.ANCHORARRAY( J25), _xlpm.cumulative_cash,_xlfn.ANCHORARRAY( J26), _xlpm.cumulative_cash * _xlpm.pct_games_played )} -> 0 | K27: 0 | L27: 0 | M27: 0 | N27: 0 | O27: 0 | P27: 0 | Q27: 0 | R27: 0 | S27: 0 | T27: 0 | U27: 0 | V27: 0 | W27: 0 | X27: 0 | Y27: 0 | Z27: 0 | AA27: 0 | AB27: 0 | AC27: 0 | AD27: 0 | AE27: 0 | AF27: 0 | AG27: 0 | AH27: 0 | AI27: 0 | AJ27: 0 | AK27: 0 | AL27: 0 | AM27: 0 | AN27: 0 | AO27: 0 | AP27: 0 | AQ27: 0 | AR27: 0 | AS27: 0 | AT27: 0 | AU27: 0 | AV27: 0 | AW27: 0 | AX27: 0 | AY27: 0 | AZ27: 0 | BA27: 0 | BB27: 0 | BC27: 0 | BD27: 0 | BE27: 0 | BF27: 0 | BG27: 0 | BH27: 0 | BI27: 0 | BJ27: 0 | BK27: 0 | BL27: 0 | BM27: 480937.5 | BN27: 507187.5 | BO27: 507187.5 | BP27: 507187.5 | BQ27: 507187.5 | BR27: 507187.5 | BS27: 507187.5 | BT27: 1014375 | BU27: 1044375 | BV27: 1044375 | BW27: 1044375 | BX27: 1044375 | BY27: 1044375 | BZ27: 1044375 | CA27: 1566562.5 | CB27: 1594687.5 | CC27: 1594687.5 | CD27: 1594687.5 | CE27: 1594687.5 | CF27: 1594687.5 | CG27: 1594687.5 | CH27: 2126250 | CI27: 2141250 | CJ27: 2141250 | CK27: 2141250 | CL27: 2141250 | CM27: 2141250 | CN27: 2141250 | CO27: 2676562.5 | CP27: 2690625 | CQ27: 2690625 | CR27: 2690625 | CS27: 2690625 | CT27: 2690625 | CU27: 2690625 | CV27: 3228750 | CW27: 3234375 | CX27: 3234375 | CY27: 3234375 | CZ27: 3234375 | DA27: 3234375 | DB27: 3234375 | DC27: 3773437.5 | DD27: 3780000 | DE27: 3780000 | DF27: 3780000 | DG27: 3780000 | DH27: 3780000 | DI27: 3780000 | DJ27: 4320000 | DK27: 4327500 | DL27: 4327500 | DM27: 4327500 | DN27: 4327500 | DO27: 4327500 | DP27: 4327500 | DQ27: 4868437.5 | DR27: 4876875 | DS27: 4876875 | DT27: 4876875 | DU27: 4876875 | DV27: 4876875 | DW27: 4876875 | DX27: 5418750 | DY27: 5428125 | DZ27: 5428125 | EA27: 5428125 | EB27: 5428125 | EC27: 5428125 | ED27: 5428125 | EE27: 5970937.5 | EF27: 5981250 | EG27: 5981250 | EH27: 5981250 | EI27: 5981250 | EJ27: 5981250 | EK27: 5981250 | EL27: 6525000 | EM27: 6536250 | EN27: 6536250 | EO27: 6536250 | EP27: 6536250 | EQ27: 6536250 | ER27: 6536250 | ES27: 7080937.5 | ET27: 7093125 | EU27: 7093125 | EV27: 7093125 | EW27: 7093125 | EX27: 7093125 | EY27: 7093125 | EZ27: 7638750 | FA27: 7651875 | FB27: 7651875 | FC27: 7651875 | FD27: 7651875 | FE27: 7651875 | FF27: 7651875 | FG27: 8198437.5 | FH27: 8212500 | FI27: 8212500 | FJ27: 8212500 | FK27: 8212500 | FL27: 8212500 | FM27: 8212500 | FN27: 8760000 | FO27: 8775000 | FP27: 8775000 | FQ27: 8775000 | FR27: 8775000 | FS27: 8775000 | FT27: 8775000 | FU27: 9323437.5 | FV27: 9403125 | FW27: 9403125 | FX27: 9403125 | FY27: 9403125 | FZ27: 9403125 | GA27: 9403125 | GB27: 9956250 | GC27: 10040625 | GD27: 10040625 | GE27: 10040625 | GF27: 10040625 | GG27: 10040625 | GH27: 10040625 | GI27: 10040625 | GJ27: 10057500 | GK27: 10057500 | GL27: 10057500 | GM27: 10057500 | GN27: 10057500 | GO27: 10057500 | GP27: 10057500 | GQ27: 10074375 | GR27: 10074375 | GS27: 10074375 | GT27: 10074375 | GU27: 10074375 | GV27: 10074375 | GW27: 10634063 | GX27: 10651875 | GY27: 10651875 | GZ27: 10651875 | HA27: 10651875 | HB27: 10651875 | HC27: 10651875 | HD27: 11212500 | HE27: 11231250 | HF27: 11231250 | HG27: 11231250 | HH27: 11231250 | HI27: 11231250 | HJ27: 11231250 | HK27: 11792813 | HL27: 11812500 | HM27: 11812500 | HN27: 11812500 | HO27: 11812500 | HP27: 11812500 | HQ27: 11812500 | HR27: 12375000 | HS27: 12375000 | HT27: 12375000 | HU27: 12375000 | HV27: 12375000 | HW27: 12375000 | HX27: 12375000 | HY27: 12937500 | HZ27: 12937500 | IA27: 12937500 | IB27: 12937500 | IC27: 12937500 | ID27: 12937500 | IE27: 12937500 | IF27: 13500000 | IG27: 13500000 | IH27: 13500000 | II27: 13500000 | IJ27: 13500000 | IK27: 13500000 | IL27: 13500000 | IM27: 14062500 | IN27: 14062500 | IO27: 14062500 | IP27: 14062500 | IQ27: 14062500 | IR27: 14062500 | IS27: 14062500 | IT27: 14625000 | IU27: 14625000 | IV27: 14625000 | IW27: 14625000 | IX27: 14625000 | IY27: 14625000 | IZ27: 14625000 | JA27: 15187500 | JB27: 15187500 | JC27: 15187500 | JD27: 15187500 | JE27: 15187500 | JF27: 15187500 | JG27: 15187500 | JH27: 15750000 | JI27: 15750000 | JJ27: 15750000 | JK27: 15750000 | JL27: 15750000 | JM27: 15750000 | JN27: 15750000 | JO27: 16312500 | JP27: 16312500 | JQ27: 16312500 | JR27: 16312500 | JS27: 16312500 | JT27: 16312500 | JU27: 16312500 | JV27: 16875000 | JW27: 16875000 | JX27: 16875000 | JY27: 16875000 | JZ27: 16875000 | KA27: 16875000 | KB27: 16875000 | KC27: 17437500 | KD27: 17437500 | KE27: 17437500 | KF27: 17437500 | KG27: 17437500 | KH27: 17437500 | KI27: 17437500 | KJ27: 18000000 | KK27: 18000000 | KL27: 18000000 | KM27: 18000000 | KN27: 18000000 | KO27: 18000000 | KP27: 18000000 | KQ27: 18562500 | KR27: 18562500 | KS27: 18562500 | KT27: 18562500 | KU27: 18562500 | KV27: 18562500 | KW27: 18562500 | KX27: 19125000 | KY27: 19125000 | KZ27: 19125000 | LA27: 19125000 | LB27: 19125000 | LC27: 19125000 | LD27: 19125000 | LE27: 19687500 | LF27: 19687500 | LG27: 19687500 | LH27: 19687500 | LI27: 19687500 | LJ27: 19687500 | LK27: 19687500 | LL27: 20250000 | LM27: 20250000 | LN27: 20250000 | LO27: 20250000 | LP27: 20250000 | LQ27: 20250000 | LR27: 20250000 | LS27: 20812500 | LT27: 20812500 | LU27: 20812500 | LV27: 20812500 | LW27: 20812500 | LX27: 20812500 | LY27: 20812500 | LZ27: 21375000 | MA27: 21375000 | MB27: 21375000 | MC27: 21375000 | MD27: 21375000 | ME27: 21375000 | MF27: 21375000 | MG27: 21937500 | MH27: 21937500 | MI27: 21937500 | MJ27: 21937500 | MK27: 21937500 | ML27: 21937500 | MM27: 21937500 | MN27: 21937500 | MO27: 21937500 | MP27: 21937500 | MQ27: 21937500 | MR27: 21937500 | MS27: 21937500 | MT27: 21937500 | MU27: 22500000 | MV27: 22500000
E28: Revenue from sale of season tickets | G28: USD | J28: {=_xlfn.LET( _xlpm.current_period_revenue,_xlfn.ANCHORARRAY( J27), _xlpm.prior_period_revenue, _xlfn.HSTACK( 0, _xlfn.DROP( _xlpm.current_period_revenue,, -1 ) ), _xlpm.current_period_revenue - _xlpm.prior_period_revenue )} -> 0 | K28: 0 | L28: 0 | M28: 0 | N28: 0 | O28: 0 | P28: 0 | Q28: 0 | R28: 0 | S28: 0 | T28: 0 | U28: 0 | V28: 0 | W28: 0 | X28: 0 | Y28: 0 | Z28: 0 | AA28: 0 | AB28: 0 | AC28: 0 | AD28: 0 | AE28: 0 | AF28: 0 | AG28: 0 | AH28: 0 | AI28: 0 | AJ28: 0 | AK28: 0 | AL28: 0 | AM28: 0 | AN28: 0 | AO28: 0 | AP28: 0 | AQ28: 0 | AR28: 0 | AS28: 0 | AT28: 0 | AU28: 0 | AV28: 0 | AW28: 0 | AX28: 0 | AY28: 0 | AZ28: 0 | BA28: 0 | BB28: 0 | BC28: 0 | BD28: 0 | BE28: 0 | BF28: 0 | BG28: 0 | BH28: 0 | BI28: 0 | BJ28: 0 | BK28: 0 | BL28: 0 | BM28: 480937.5 | BN28: 26250 | BO28: 0 | BP28: 0 | BQ28: 0 | BR28: 0 | BS28: 0 | BT28: 507187.5 | BU28: 30000 | BV28: 0 | BW28: 0 | BX28: 0 | BY28: 0 | BZ28: 0 | CA28: 522187.5 | CB28: 28125 | CC28: 0 | CD28: 0 | CE28: 0 | CF28: 0 | CG28: 0 | CH28: 531562.5 | CI28: 15000 | CJ28: 0 | CK28: 0 | CL28: 0 | CM28: 0 | CN28: 0 | CO28: 535312.5 | CP28: 14062.5 | CQ28: 0 | CR28: 0 | CS28: 0 | CT28: 0 | CU28: 0 | CV28: 538125 | CW28: 5625 | CX28: 0 | CY28: 0 | CZ28: 0 | DA28: 0 | DB28: 0 | DC28: 539062.5 | DD28: 6562.5 | DE28: 0 | DF28: 0 | DG28: 0 | DH28: 0 | DI28: 0 | DJ28: 540000 | DK28: 7500 | DL28: 0 | DM28: 0 | DN28: 0 | DO28: 0 | DP28: 0 | DQ28: 540937.5 | DR28: 8437.5 | DS28: 0 | DT28: 0 | DU28: 0 | DV28: 0 | DW28: 0 | DX28: 541875 | DY28: 9375 | DZ28: 0 | EA28: 0 | EB28: 0 | EC28: 0 | ED28: 0 | EE28: 542812.5 | EF28: 10312.5 | EG28: 0 | EH28: 0 | EI28: 0 | EJ28: 0 | EK28: 0 | EL28: 543750 | EM28: 11250 | EN28: 0 | EO28: 0 | EP28: 0 | EQ28: 0 | ER28: 0 | ES28: 544687.5 | ET28: 12187.5 | EU28: 0 | EV28: 0 | EW28: 0 | EX28: 0 | EY28: 0 | EZ28: 545625 | FA28: 13125 | FB28: 0 | FC28: 0 | FD28: 0 | FE28: 0 | FF28: 0 | FG28: 546562.5 | FH28: 14062.5 | FI28: 0 | FJ28: 0 | FK28: 0 | FL28: 0 | FM28: 0 | FN28: 547500 | FO28: 15000 | FP28: 0 | FQ28: 0 | FR28: 0 | FS28: 0 | FT28: 0 | FU28: 548437.5 | FV28: 79687.5 | FW28: 0 | FX28: 0 | FY28: 0 | FZ28: 0 | GA28: 0 | GB28: 553125 | GC28: 84375 | GD28: 0 | GE28: 0 | GF28: 0 | GG28: 0 | GH28: 0 | GI28: 0 | GJ28: 16875 | GK28: 0 | GL28: 0 | GM28: 0 | GN28: 0 | GO28: 0 | GP28: 0 | GQ28: 16875 | GR28: 0 | GS28: 0 | GT28: 0 | GU28: 0 | GV28: 0 | GW28: 559687.5 | GX28: 17812.5 | GY28: 0 | GZ28: 0 | HA28: 0 | HB28: 0 | HC28: 0 | HD28: 560625 | HE28: 18750 | HF28: 0 | HG28: 0 | HH28: 0 | HI28: 0 | HJ28: 0 | HK28: 561562.5 | HL28: 19687.5 | HM28: 0 | HN28: 0 | HO28: 0 | HP28: 0 | HQ28: 0 | HR28: 562500 | HS28: 0 | HT28: 0 | HU28: 0 | HV28: 0 | HW28: 0 | HX28: 0 | HY28: 562500 | HZ28: 0 | IA28: 0 | IB28: 0 | IC28: 0 | ID28: 0 | IE28: 0 | IF28: 562500 | IG28: 0 | IH28: 0 | II28: 0 | IJ28: 0 | IK28: 0 | IL28: 0 | IM28: 562500 | IN28: 0 | IO28: 0 | IP28: 0 | IQ28: 0 | IR28: 0 | IS28: 0 | IT28: 562500 | IU28: 0 | IV28: 0 | IW28: 0 | IX28: 0 | IY28: 0 | IZ28: 0 | JA28: 562500 | JB28: 0 | JC28: 0 | JD28: 0 | JE28: 0 | JF28: 0 | JG28: 0 | JH28: 562500 | JI28: 0 | JJ28: 0 | JK28: 0 | JL28: 0 | JM28: 0 | JN28: 0 | JO28: 562500 | JP28: 0 | JQ28: 0 | JR28: 0 | JS28: 0 | JT28: 0 | JU28: 0 | JV28: 562500 | JW28: 0 | JX28: 0 | JY28: 0 | JZ28: 0 | KA28: 0 | KB28: 0 | KC28: 562500 | KD28: 0 | KE28: 0 | KF28: 0 | KG28: 0 | KH28: 0 | KI28: 0 | KJ28: 562500 | KK28: 0 | KL28: 0 | KM28: 0 | KN28: 0 | KO28: 0 | KP28: 0 | KQ28: 562500 | KR28: 0 | KS28: 0 | KT28: 0 | KU28: 0 | KV28: 0 | KW28: 0 | KX28: 562500 | KY28: 0 | KZ28: 0 | LA28: 0 | LB28: 0 | LC28: 0 | LD28: 0 | LE28: 562500 | LF28: 0 | LG28: 0 | LH28: 0 | LI28: 0 | LJ28: 0 | LK28: 0 | LL28: 562500 | LM28: 0 | LN28: 0 | LO28: 0 | LP28: 0 | LQ28: 0 | LR28: 0 | LS28: 562500 | LT28: 0 | LU28: 0 | LV28: 0 | LW28: 0 | LX28: 0 | LY28: 0 | LZ28: 562500 | MA28: 0 | MB28: 0 | MC28: 0 | MD28: 0 | ME28: 0 | MF28: 0 | MG28: 562500 | MH28: 0 | MI28: 0 | MJ28: 0 | MK28: 0 | ML28: 0 | MM28: 0 | MN28: 0 | MO28: 0 | MP28: 0 | MQ28: 0 | MR28: 0 | MS28: 0 | MT28: 0 | MU28: 562500 | MV28: 0
E30: Unearned revenue from sale of season tickets | G30: USD | J30: {=_xlfn.ANCHORARRAY( J26) -_xlfn.ANCHORARRAY( J27)} -> 3600000 | K30: 3600000 | L30: 3600000 | M30: 3600000 | N30: 3600000 | O30: 3600000 | P30: 3600000 | Q30: 6450000 | R30: 6450000 | S30: 6450000 | T30: 6450000 | U30: 6450000 | V30: 6450000 | W30: 6450000 | X30: 9000000 | Y30: 9000000 | Z30: 9000000 | AA30: 9000000 | AB30: 9000000 | AC30: 9000000 | AD30: 9000000 | AE30: 11100000 | AF30: 11100000 | AG30: 11100000 | AH30: 11100000 | AI30: 11100000 | AJ30: 11100000 | AK30: 11100000 | AL30: 13125000 | AM30: 13125000 | AN30: 13125000 | AO30: 13125000 | AP30: 13125000 | AQ30: 13125000 | AR30: 13125000 | AS30: 15187500 | AT30: 15187500 | AU30: 15187500 | AV30: 15187500 | AW30: 15187500 | AX30: 15187500 | AY30: 15187500 | AZ30: 17137500 | BA30: 17137500 | BB30: 17137500 | BC30: 17137500 | BD30: 17137500 | BE30: 17137500 | BF30: 17137500 | BG30: 19237500 | BH30: 19237500 | BI30: 19237500 | BJ30: 19237500 | BK30: 19237500 | BL30: 19237500 | BM30: 18756562 | BN30: 19780312 | BO30: 19780312 | BP30: 19780312 | BQ30: 19780312 | BR30: 19780312 | BS30: 19780312 | BT30: 19273125 | BU30: 19843125 | BV30: 19843125 | BW30: 19843125 | BX30: 19843125 | BY30: 19843125 | BZ30: 19843125 | CA30: 19320938 | CB30: 19667812 | CC30: 19667812 | CD30: 19667812 | CE30: 19667812 | CF30: 19667812 | CG30: 19667812 | CH30: 19136250 | CI30: 19271250 | CJ30: 19271250 | CK30: 19271250 | CL30: 19271250 | CM30: 19271250 | CN30: 19271250 | CO30: 18735938 | CP30: 18834375 | CQ30: 18834375 | CR30: 18834375 | CS30: 18834375 | CT30: 18834375 | CU30: 18834375 | CV30: 18296250 | CW30: 18328125 | CX30: 18328125 | CY30: 18328125 | CZ30: 18328125 | DA30: 18328125 | DB30: 18328125 | DC30: 17789062 | DD30: 17820000 | DE30: 17820000 | DF30: 17820000 | DG30: 17820000 | DH30: 17820000 | DI30: 17820000 | DJ30: 17280000 | DK30: 17310000 | DL30: 17310000 | DM30: 17310000 | DN30: 17310000 | DO30: 17310000 | DP30: 17310000 | DQ30: 16769062 | DR30: 16798125 | DS30: 16798125 | DT30: 16798125 | DU30: 16798125 | DV30: 16798125 | DW30: 16798125 | DX30: 16256250 | DY30: 16284375 | DZ30: 16284375 | EA30: 16284375 | EB30: 16284375 | EC30: 16284375 | ED30: 16284375 | EE30: 15741562 | EF30: 15768750 | EG30: 15768750 | EH30: 15768750 | EI30: 15768750 | EJ30: 15768750 | EK30: 15768750 | EL30: 15225000 | EM30: 15251250 | EN30: 15251250 | EO30: 15251250 | EP30: 15251250 | EQ30: 15251250 | ER30: 15251250 | ES30: 14706562 | ET30: 14731875 | EU30: 14731875 | EV30: 14731875 | EW30: 14731875 | EX30: 14731875 | EY30: 14731875 | EZ30: 14186250 | FA30: 14210625 | FB30: 14210625 | FC30: 14210625 | FD30: 14210625 | FE30: 14210625 | FF30: 14210625 | FG30: 13664062 | FH30: 13687500 | FI30: 13687500 | FJ30: 13687500 | FK30: 13687500 | FL30: 13687500 | FM30: 13687500 | FN30: 13140000 | FO30: 13162500 | FP30: 13162500 | FQ30: 13162500 | FR30: 13162500 | FS30: 13162500 | FT30: 13162500 | FU30: 12614062 | FV30: 12721875 | FW30: 12721875 | FX30: 12721875 | FY30: 12721875 | FZ30: 12721875 | GA30: 12721875 | GB30: 12168750 | GC30: 12271875 | GD30: 12271875 | GE30: 12271875 | GF30: 12271875 | GG30: 12271875 | GH30: 12271875 | GI30: 12271875 | GJ30: 12292500 | GK30: 12292500 | GL30: 12292500 | GM30: 12292500 | GN30: 12292500 | GO30: 12292500 | GP30: 12292500 | GQ30: 12313125 | GR30: 12313125 | GS30: 12313125 | GT30: 12313125 | GU30: 12313125 | GV30: 12313125 | GW30: 11753437 | GX30: 11773125 | GY30: 11773125 | GZ30: 11773125 | HA30: 11773125 | HB30: 11773125 | HC30: 11773125 | HD30: 11212500 | HE30: 11231250 | HF30: 11231250 | HG30: 11231250 | HH30: 11231250 | HI30: 11231250 | HJ30: 11231250 | HK30: 10669687 | HL30: 10687500 | HM30: 10687500 | HN30: 10687500 | HO30: 10687500 | HP30: 10687500 | HQ30: 10687500 | HR30: 10125000 | HS30: 10125000 | HT30: 10125000 | HU30: 10125000 | HV30: 10125000 | HW30: 10125000 | HX30: 10125000 | HY30: 9562500 | HZ30: 9562500 | IA30: 9562500 | IB30: 9562500 | IC30: 9562500 | ID30: 9562500 | IE30: 9562500 | IF30: 9000000 | IG30: 9000000 | IH30: 9000000 | II30: 9000000 | IJ30: 9000000 | IK30: 9000000 | IL30: 9000000 | IM30: 8437500 | IN30: 8437500 | IO30: 8437500 | IP30: 8437500 | IQ30: 8437500 | IR30: 8437500 | IS30: 8437500 | IT30: 7875000 | IU30: 7875000 | IV30: 7875000 | IW30: 7875000 | IX30: 7875000 | IY30: 7875000 | IZ30: 7875000 | JA30: 7312500 | JB30: 7312500 | JC30: 7312500 | JD30: 7312500 | JE30: 7312500 | JF30: 7312500 | JG30: 7312500 | JH30: 6750000 | JI30: 6750000 | JJ30: 6750000 | JK30: 6750000 | JL30: 6750000 | JM30: 6750000 | JN30: 6750000 | JO30: 6187500 | JP30: 6187500 | JQ30: 6187500 | JR30: 6187500 | JS30: 6187500 | JT30: 6187500 | JU30: 6187500 | JV30: 5625000 | JW30: 5625000 | JX30: 5625000 | JY30: 5625000 | JZ30: 5625000 | KA30: 5625000 | KB30: 5625000 | KC30: 5062500 | KD30: 5062500 | KE30: 5062500 | KF30: 5062500 | KG30: 5062500 | KH30: 5062500 | KI30: 5062500 | KJ30: 4500000 | KK30: 4500000 | KL30: 4500000 | KM30: 4500000 | KN30: 4500000 | KO30: 4500000 | KP30: 4500000 | KQ30: 3937500 | KR30: 3937500 | KS30: 3937500 | KT30: 3937500 | KU30: 3937500 | KV30: 3937500 | KW30: 3937500 | KX30: 3375000 | KY30: 3375000 | KZ30: 3375000 | LA30: 3375000 | LB30: 3375000 | LC30: 3375000 | LD30: 3375000 | LE30: 2812500 | LF30: 2812500 | LG30: 2812500 | LH30: 2812500 | LI30: 2812500 | LJ30: 2812500 | LK30: 2812500 | LL30: 2250000 | LM30: 2250000 | LN30: 2250000 | LO30: 2250000 | LP30: 2250000 | LQ30: 2250000 | LR30: 2250000 | LS30: 1687500 | LT30: 1687500 | LU30: 1687500 | LV30: 1687500 | LW30: 1687500 | LX30: 1687500 | LY30: 1687500 | LZ30: 1125000 | MA30: 1125000 | MB30: 1125000 | MC30: 1125000 | MD30: 1125000 | ME30: 1125000 | MF30: 1125000 | MG30: 562500 | MH30: 562500 | MI30: 562500 | MJ30: 562500 | MK30: 562500 | ML30: 562500 | MM30: 562500 | MN30: 562500 | MO30: 562500 | MP30: 562500 | MQ30: 562500 | MR30: 562500 | MS30: 562500 | MT30: 562500 | MU30: 0 | MV30: 0
A32: Single Game Tickets
E34: Game importance | G34: number | J34: {=_xlfn.XLOOKUP(_xlfn.ANCHORARRAY( J14), tbl_GameDates[Date], tbl_GameDates[Importance], "n/a" )} -> 3 | K34: 3 | L34: 3 | M34: 3 | N34: 3 | O34: 3 | P34: 3 | Q34: 3 | R34: 3 | S34: 3 | T34: 3 | U34: 3 | V34: 3 | W34: 3 | X34: 3 | Y34: 3 | Z34: 3 | AA34: 3 | AB34: 3 | AC34: 3 | AD34: 3 | AE34: 3 | AF34: 3 | AG34: 3 | AH34: 3 | AI34: 3 | AJ34: 3 | AK34: 3 | AL34: 3 | AM34: 3 | AN34: 3 | AO34: 3 | AP34: 3 | AQ34: 3 | AR34: 3 | AS34: 3 | AT34: 3 | AU34: 3 | AV34: 3 | AW34: 3 | AX34: 3 | AY34: 3 | AZ34: 3 | BA34: 3 | BB34: 3 | BC34: 3 | BD34: 3 | BE34: 3 | BF34: 3 | BG34: 3 | BH34: 3 | BI34: 3 | BJ34: 3 | BK34: 3 | BL34: 3 | BM34: 3 | BN34: 2 | BO34: 2 | BP34: 2 | BQ34: 2 | BR34: 2 | BS34: 2 | BT34: 2 | BU34: 1 | BV34: 1 | BW34: 1 | BX34: 1 | BY34: 1 | BZ34: 1 | CA34: 1 | CB34: 3 | CC34: 3 | CD34: 3 | CE34: 3 | CF34: 3 | CG34: 3 | CH34: 3 | CI34: 1 | CJ34: 1 | CK34: 1 | CL34: 1 | CM34: 1 | CN34: 1 | CO34: 1 | CP34: 2 | CQ34: 2 | CR34: 2 | CS34: 2 | CT34: 2 | CU34: 2 | CV34: 2 | CW34: 1 | CX34: 1 | CY34: 1 | CZ34: 1 | DA34: 1 | DB34: 1 | DC34: 1 | DD34: 2 | DE34: 2 | DF34: 2 | DG34: 2 | DH34: 2 | DI34: 2 | DJ34: 2 | DK34: 2 | DL34: 2 | DM34: 2 | DN34: 2 | DO34: 2 | DP34: 2 | DQ34: 2 | DR34: 1 | DS34: 1 | DT34: 1 | DU34: 1 | DV34: 1 | DW34: 1 | DX34: 1 | DY34: 2 | DZ34: 2 | EA34: 2 | EB34: 2 | EC34: 2 | ED34: 2 | EE34: 2 | EF34: 1 | EG34: 1 | EH34: 1 | EI34: 1 | EJ34: 1 | EK34: 1 | EL34: 1 | EM34: 4 | EN34: 4 | EO34: 4 | EP34: 4 | EQ34: 4 | ER34: 4 | ES34: 4 | ET34: 1 | EU34: 1 | EV34: 1 | EW34: 1 | EX34: 1 | EY34: 1 | EZ34: 1 | FA34: 2 | FB34: 2 | FC34: 2 | FD34: 2 | FE34: 2 | FF34: 2 | FG34: 2 | FH34: 2 | FI34: 2 | FJ34: 2 | FK34: 2 | FL34: 2 | FM34: 2 | FN34: 2 | FO34: 2 | FP34: 2 | FQ34: 2 | FR34: 2 | FS34: 2 | FT34: 2 | FU34: 2 | FV34: 1 | FW34: 1 | FX34: 1 | FY34: 1 | FZ34: 1 | GA34: 1 | GB34: 1 | GC34: 1 | GD34: 1 | GE34: 1 | GF34: 1 | GG34: 1 | GH34: 1 | GI34: 1 | GJ34: 1 | GK34: 1 | GL34: 1 | GM34: 1 | GN34: 1 | GO34: 1 | GP34: 1 | GQ34: 1 | GR34: 1 | GS34: 1 | GT34: 1 | GU34: 1 | GV34: 1 | GW34: 1 | GX34: 1 | GY34: 1 | GZ34: 1 | HA34: 1 | HB34: 1 | HC34: 1 | HD34: 1 | HE34: 3 | HF34: 3 | HG34: 3 | HH34: 3 | HI34: 3 | HJ34: 3 | HK34: 3 | HL34: 1 | HM34: 1 | HN34: 1 | HO34: 1 | HP34: 1 | HQ34: 1 | HR34: 1 | HS34: 4 | HT34: 4 | HU34: 4 | HV34: 4 | HW34: 4 | HX34: 4 | HY34: 4 | HZ34: 2 | IA34: 2 | IB34: 2 | IC34: 2 | ID34: 2 | IE34: 2 | IF34: 2 | IG34: 2 | IH34: 2 | II34: 2 | IJ34: 2 | IK34: 2 | IL34: 2 | IM34: 2 | IN34: 2 | IO34: 2 | IP34: 2 | IQ34: 2 | IR34: 2 | IS34: 2 | IT34: 2 | IU34: 3 | IV34: 3 | IW34: 3 | IX34: 3 | IY34: 3 | IZ34: 3 | JA34: 3 | JB34: 1 | JC34: 1 | JD34: 1 | JE34: 1 | JF34: 1 | JG34: 1 | JH34: 1 | JI34: 2 | JJ34: 2 | JK34: 2 | JL34: 2 | JM34: 2 | JN34: 2 | JO34: 2 | JP34: 2 | JQ34: 2 | JR34: 2 | JS34: 2 | JT34: 2 | JU34: 2 | JV34: 2 | JW34: 3 | JX34: 3 | JY34: 3 | JZ34: 3 | KA34: 3 | KB34: 3 | KC34: 3 | KD34: 1 | KE34: 1 | KF34: 1 | KG34: 1 | KH34: 1 | KI34: 1 | KJ34: 1 | KK34: 2 | KL34: 2 | KM34: 2 | KN34: 2 | KO34: 2 | KP34: 2 | KQ34: 2 | KR34: 2 | KS34: 2 | KT34: 2 | KU34: 2 | KV34: 2 | KW34: 2 | KX34: 2 | KY34: 1 | KZ34: 1 | LA34: 1 | LB34: 1 | LC34: 1 | LD34: 1 | LE34: 1 | LF34: 1 | LG34: 1 | LH34: 1 | LI34: 1 | LJ34: 1 | LK34: 1 | LL34: 1 | LM34: 1 | LN34: 1 | LO34: 1 | LP34: 1 | LQ34: 1 | LR34: 1 | LS34: 1 | LT34: 3 | LU34: 3 | LV34: 3 | LW34: 3 | LX34: 3 | LY34: 3 | LZ34: 3 | MA34: 4 | MB34: 4 | MC34: 4 | MD34: 4 | ME34: 4 | MF34: 4 | MG34: 4 | MH34: 5 | MI34: 5 | MJ34: 5 | MK34: 5 | ML34: 5 | MM34: 5 | MN34: 5 | MO34: 5 | MP34: 5 | MQ34: 5 | MR34: 5 | MS34: 5 | MT34: 5 | MU34: 5 | MV34: n/a
E35: Base crowd | G35: tickets | J35: {=_xlfn.XLOOKUP(_xlfn.ANCHORARRAY( J34), tbl_ImpLU[Importance], tbl_ImpLU[Base crowd], 0 )} -> 32000 | K35: 32000 | L35: 32000 | M35: 32000 | N35: 32000 | O35: 32000 | P35: 32000 | Q35: 32000 | R35: 32000 | S35: 32000 | T35: 32000 | U35: 32000 | V35: 32000 | W35: 32000 | X35: 32000 | Y35: 32000 | Z35: 32000 | AA35: 32000 | AB35: 32000 | AC35: 32000 | AD35: 32000 | AE35: 32000 | AF35: 32000 | AG35: 32000 | AH35: 32000 | AI35: 32000 | AJ35: 32000 | AK35: 32000 | AL35: 32000 | AM35: 32000 | AN35: 32000 | AO35: 32000 | AP35: 32000 | AQ35: 32000 | AR35: 32000 | AS35: 32000 | AT35: 32000 | AU35: 32000 | AV35: 32000 | AW35: 32000 | AX35: 32000 | AY35: 32000 | AZ35: 32000 | BA35: 32000 | BB35: 32000 | BC35: 32000 | BD35: 32000 | BE35: 32000 | BF35: 32000 | BG35: 32000 | BH35: 32000 | BI35: 32000 | BJ35: 32000 | BK35: 32000 | BL35: 32000 | BM35: 32000 | BN35: 25000 | BO35: 25000 | BP35: 25000 | BQ35: 25000 | BR35: 25000 | BS35: 25000 | BT35: 25000 | BU35: 15000 | BV35: 15000 | BW35: 15000 | BX35: 15000 | BY35: 15000 | BZ35: 15000 | CA35: 15000 | CB35: 32000 | CC35: 32000 | CD35: 32000 | CE35: 32000 | CF35: 32000 | CG35: 32000 | CH35: 32000 | CI35: 15000 | CJ35: 15000 | CK35: 15000 | CL35: 15000 | CM35: 15000 | CN35: 15000 | CO35: 15000 | CP35: 25000 | CQ35: 25000 | CR35: 25000 | CS35: 25000 | CT35: 25000 | CU35: 25000 | CV35: 25000 | CW35: 15000 | CX35: 15000 | CY35: 15000 | CZ35: 15000 | DA35: 15000 | DB35: 15000 | DC35: 15000 | DD35: 25000 | DE35: 25000 | DF35: 25000 | DG35: 25000 | DH35: 25000 | DI35: 25000 | DJ35: 25000 | DK35: 25000 | DL35: 25000 | DM35: 25000 | DN35: 25000 | DO35: 25000 | DP35: 25000 | DQ35: 25000 | DR35: 15000 | DS35: 15000 | DT35: 15000 | DU35: 15000 | DV35: 15000 | DW35: 15000 | DX35: 15000 | DY35: 25000 | DZ35: 25000 | EA35: 25000 | EB35: 25000 | EC35: 25000 | ED35: 25000 | EE35: 25000 | EF35: 15000 | EG35: 15000 | EH35: 15000 | EI35: 15000 | EJ35: 15000 | EK35: 15000 | EL35: 15000 | EM35: 40000 | EN35: 40000 | EO35: 40000 | EP35: 40000 | EQ35: 40000 | ER35: 40000 | ES35: 40000 | ET35: 15000 | EU35: 15000 | EV35: 15000 | EW35: 15000 | EX35: 15000 | EY35: 15000 | EZ35: 15000 | FA35: 25000 | FB35: 25000 | FC35: 25000 | FD35: 25000 | FE35: 25000 | FF35: 25000 | FG35: 25000 | FH35: 25000 | FI35: 25000 | FJ35: 25000 | FK35: 25000 | FL35: 25000 | FM35: 25000 | FN35: 25000 | FO35: 25000 | FP35: 25000 | FQ35: 25000 | FR35: 25000 | FS35: 25000 | FT35: 25000 | FU35: 25000 | FV35: 15000 | FW35: 15000 | FX35: 15000 | FY35: 15000 | FZ35: 15000 | GA35: 15000 | GB35: 15000 | GC35: 15000 | GD35: 15000 | GE35: 15000 | GF35: 15000 | GG35: 15000 | GH35: 15000 | GI35: 15000 | GJ35: 15000 | GK35: 15000 | GL35: 15000 | GM35: 15000 | GN35: 15000 | GO35: 15000 | GP35: 15000 | GQ35: 15000 | GR35: 15000 | GS35: 15000 | GT35: 15000 | GU35: 15000 | GV35: 15000 | GW35: 15000 | GX35: 15000 | GY35: 15000 | GZ35: 15000 | HA35: 15000 | HB35: 15000 | HC35: 15000 | HD35: 15000 | HE35: 32000 | HF35: 32000 | HG35: 32000 | HH35: 32000 | HI35: 32000 | HJ35: 32000 | HK35: 32000 | HL35: 15000 | HM35: 15000 | HN35: 15000 | HO35: 15000 | HP35: 15000 | HQ35: 15000 | HR35: 15000 | HS35: 40000 | HT35: 40000 | HU35: 40000 | HV35: 40000 | HW35: 40000 | HX35: 40000 | HY35: 40000 | HZ35: 25000 | IA35: 25000 | IB35: 25000 | IC35: 25000 | ID35: 25000 | IE35: 25000 | IF35: 25000 | IG35: 25000 | IH35: 25000 | II35: 25000 | IJ35: 25000 | IK35: 25000 | IL35: 25000 | IM35: 25000 | IN35: 25000 | IO35: 25000 | IP35: 25000 | IQ35: 25000 | IR35: 25000 | IS35: 25000 | IT35: 25000 | IU35: 32000 | IV35: 32000 | IW35: 32000 | IX35: 32000 | IY35: 32000 | IZ35: 32000 | JA35: 32000 | JB35: 15000 | JC35: 15000 | JD35: 15000 | JE35: 15000 | JF35: 15000 | JG35: 15000 | JH35: 15000 | JI35: 25000 | JJ35: 25000 | JK35: 25000 | JL35: 25000 | JM35: 25000 | JN35: 25000 | JO35: 25000 | JP35: 25000 | JQ35: 25000 | JR35: 25000 | JS35: 25000 | JT35: 25000 | JU35: 25000 | JV35: 25000 | JW35: 32000 | JX35: 32000 | JY35: 32000 | JZ35: 32000 | KA35: 32000 | KB35: 32000 | KC35: 32000 | KD35: 15000 | KE35: 15000 | KF35: 15000 | KG35: 15000 | KH35: 15000 | KI35: 15000 | KJ35: 15000 | KK35: 25000 | KL35: 25000 | KM35: 25000 | KN35: 25000 | KO35: 25000 | KP35: 25000 | KQ35: 25000 | KR35: 25000 | KS35: 25000 | KT35: 25000 | KU35: 25000 | KV35: 25000 | KW35: 25000 | KX35: 25000 | KY35: 15000 | KZ35: 15000 | LA35: 15000 | LB35: 15000 | LC35: 15000 | LD35: 15000 | LE35: 15000 | LF35: 15000 | LG35: 15000 | LH35: 15000 | LI35: 15000 | LJ35: 15000 | LK35: 15000 | LL35: 15000 | LM35: 15000 | LN35: 15000 | LO35: 15000 | LP35: 15000 | LQ35: 15000 | LR35: 15000 | LS35: 15000 | LT35: 32000 | LU35: 32000 | LV35: 32000 | LW35: 32000 | LX35: 32000 | LY35: 32000 | LZ35: 32000 | MA35: 40000 | MB35: 40000 | MC35: 40000 | MD35: 40000 | ME35: 40000 | MF35: 40000 | MG35: 40000 | MH35: 50000 | MI35: 50000 | MJ35: 50000 | MK35: 50000 | ML35: 50000 | MM35: 50000 | MN35: 50000 | MO35: 50000 | MP35: 50000 | MQ35: 50000 | MR35: 50000 | MS35: 50000 | MT35: 50000 | MU35: 50000 | MV35: 0
E36: Tickets available (week) | G36: tickets | J36: {=_xlfn.XLOOKUP(_xlfn.ANCHORARRAY( J14), tbl_GameDates[Date], tbl_GameDates[Ticket availability], 0 )} -> 24350 | K36: 24350 | L36: 24350 | M36: 24350 | N36: 24350 | O36: 24350 | P36: 24350 | Q36: 24350 | R36: 24350 | S36: 24350 | T36: 24350 | U36: 24350 | V36: 24350 | W36: 24350 | X36: 24350 | Y36: 24350 | Z36: 24350 | AA36: 24350 | AB36: 24350 | AC36: 24350 | AD36: 24350 | AE36: 24350 | AF36: 24350 | AG36: 24350 | AH36: 24350 | AI36: 24350 | AJ36: 24350 | AK36: 24350 | AL36: 24350 | AM36: 24350 | AN36: 24350 | AO36: 24350 | AP36: 24350 | AQ36: 24350 | AR36: 24350 | AS36: 24350 | AT36: 24350 | AU36: 24350 | AV36: 24350 | AW36: 24350 | AX36: 24350 | AY36: 24350 | AZ36: 24350 | BA36: 24350 | BB36: 24350 | BC36: 24350 | BD36: 24350 | BE36: 24350 | BF36: 24350 | BG36: 24350 | BH36: 24350 | BI36: 24350 | BJ36: 24350 | BK36: 24350 | BL36: 24350 | BM36: 24350 | BN36: 22950 | BO36: 22950 | BP36: 22950 | BQ36: 22950 | BR36: 22950 | BS36: 22950 | BT36: 22950 | BU36: 22150 | BV36: 22150 | BW36: 22150 | BX36: 22150 | BY36: 22150 | BZ36: 22150 | CA36: 22150 | CB36: 21650 | CC36: 21650 | CD36: 21650 | CE36: 21650 | CF36: 21650 | CG36: 21650 | CH36: 21650 | CI36: 21450 | CJ36: 21450 | CK36: 21450 | CL36: 21450 | CM36: 21450 | CN36: 21450 | CO36: 21450 | CP36: 21300 | CQ36: 21300 | CR36: 21300 | CS36: 21300 | CT36: 21300 | CU36: 21300 | CV36: 21300 | CW36: 21250 | CX36: 21250 | CY36: 21250 | CZ36: 21250 | DA36: 21250 | DB36: 21250 | DC36: 21250 | DD36: 21200 | DE36: 21200 | DF36: 21200 | DG36: 21200 | DH36: 21200 | DI36: 21200 | DJ36: 21200 | DK36: 21150 | DL36: 21150 | DM36: 21150 | DN36: 21150 | DO36: 21150 | DP36: 21150 | DQ36: 21150 | DR36: 21100 | DS36: 21100 | DT36: 21100 | DU36: 21100 | DV36: 21100 | DW36: 21100 | DX36: 21100 | DY36: 21050 | DZ36: 21050 | EA36: 21050 | EB36: 21050 | EC36: 21050 | ED36: 21050 | EE36: 21050 | EF36: 21000 | EG36: 21000 | EH36: 21000 | EI36: 21000 | EJ36: 21000 | EK36: 21000 | EL36: 21000 | EM36: 20950 | EN36: 20950 | EO36: 20950 | EP36: 20950 | EQ36: 20950 | ER36: 20950 | ES36: 20950 | ET36: 20900 | EU36: 20900 | EV36: 20900 | EW36: 20900 | EX36: 20900 | EY36: 20900 | EZ36: 20900 | FA36: 20850 | FB36: 20850 | FC36: 20850 | FD36: 20850 | FE36: 20850 | FF36: 20850 | FG36: 20850 | FH36: 20800 | FI36: 20800 | FJ36: 20800 | FK36: 20800 | FL36: 20800 | FM36: 20800 | FN36: 20800 | FO36: 20750 | FP36: 20750 | FQ36: 20750 | FR36: 20750 | FS36: 20750 | FT36: 20750 | FU36: 20750 | FV36: 20500 | FW36: 20500 | FX36: 20500 | FY36: 20500 | FZ36: 20500 | GA36: 20500 | GB36: 20500 | GC36: 20150 | GD36: 20150 | GE36: 20150 | GF36: 20150 | GG36: 20150 | GH36: 20150 | GI36: 20150 | GJ36: 20150 | GK36: 20150 | GL36: 20150 | GM36: 20150 | GN36: 20150 | GO36: 20150 | GP36: 20150 | GQ36: 20150 | GR36: 20150 | GS36: 20150 | GT36: 20150 | GU36: 20150 | GV36: 20150 | GW36: 20150 | GX36: 20100 | GY36: 20100 | GZ36: 20100 | HA36: 20100 | HB36: 20100 | HC36: 20100 | HD36: 20100 | HE36: 20050 | HF36: 20050 | HG36: 20050 | HH36: 20050 | HI36: 20050 | HJ36: 20050 | HK36: 20050 | HL36: 20000 | HM36: 20000 | HN36: 20000 | HO36: 20000 | HP36: 20000 | HQ36: 20000 | HR36: 20000 | HS36: 20000 | HT36: 20000 | HU36: 20000 | HV36: 20000 | HW36: 20000 | HX36: 20000 | HY36: 20000 | HZ36: 20000 | IA36: 20000 | IB36: 20000 | IC36: 20000 | ID36: 20000 | IE36: 20000 | IF36: 20000 | IG36: 20000 | IH36: 20000 | II36: 20000 | IJ36: 20000 | IK36: 20000 | IL36: 20000 | IM36: 20000 | IN36: 20000 | IO36: 20000 | IP36: 20000 | IQ36: 20000 | IR36: 20000 | IS36: 20000 | IT36: 20000 | IU36: 20000 | IV36: 20000 | IW36: 20000 | IX36: 20000 | IY36: 20000 | IZ36: 20000 | JA36: 20000 | JB36: 20000 | JC36: 20000 | JD36: 20000 | JE36: 20000 | JF36: 20000 | JG36: 20000 | JH36: 20000 | JI36: 20000 | JJ36: 20000 | JK36: 20000 | JL36: 20000 | JM36: 20000 | JN36: 20000 | JO36: 20000 | JP36: 20000 | JQ36: 20000 | JR36: 20000 | JS36: 20000 | JT36: 20000 | JU36: 20000 | JV36: 20000 | JW36: 20000 | JX36: 20000 | JY36: 20000 | JZ36: 20000 | KA36: 20000 | KB36: 20000 | KC36: 20000 | KD36: 20000 | KE36: 20000 | KF36: 20000 | KG36: 20000 | KH36: 20000 | KI36: 20000 | KJ36: 20000 | KK36: 20000 | KL36: 20000 | KM36: 20000 | KN36: 20000 | KO36: 20000 | KP36: 20000 | KQ36: 20000 | KR36: 20000 | KS36: 20000 | KT36: 20000 | KU36: 20000 | KV36: 20000 | KW36: 20000 | KX36: 20000 | KY36: 20000 | KZ36: 20000 | LA36: 20000 | LB36: 20000 | LC36: 20000 | LD36: 20000 | LE36: 20000 | LF36: 20000 | LG36: 20000 | LH36: 20000 | LI36: 20000 | LJ36: 20000 | LK36: 20000 | LL36: 20000 | LM36: 20000 | LN36: 20000 | LO36: 20000 | LP36: 20000 | LQ36: 20000 | LR36: 20000 | LS36: 20000 | LT36: 20000 | LU36: 20000 | LV36: 20000 | LW36: 20000 | LX36: 20000 | LY36: 20000 | LZ36: 20000 | MA36: 20000 | MB36: 20000 | MC36: 20000 | MD36: 20000 | ME36: 20000 | MF36: 20000 | MG36: 20000 | MH36: 20000 | MI36: 20000 | MJ36: 20000 | MK36: 20000 | ML36: 20000 | MM36: 20000 | MN36: 20000 | MO36: 20000 | MP36: 20000 | MQ36: 20000 | MR36: 20000 | MS36: 20000 | MT36: 20000 | MU36: 20000 | MV36: 0
E38: Pct of ticket demand leading up to the game | G38: % | J38: {=_xlfn.XLOOKUP(_xlfn.ANCHORARRAY( J15), tbl_Demand[Days to game], tbl_Demand[% of demand], 0 )} -> 0 | K38: 0 | L38: 0 | M38: 0 | N38: 0 | O38: 0 | P38: 0 | Q38: 0 | R38: 0 | S38: 0 | T38: 0 | U38: 0 | V38: 0 | W38: 0 | X38: 0 | Y38: 0 | Z38: 0 | AA38: 0 | AB38: 0 | AC38: 0 | AD38: 0 | AE38: 0 | AF38: 0 | AG38: 0 | AH38: 0 | AI38: 0 | AJ38: 0 | AK38: 0 | AL38: 0 | AM38: 0 | AN38: 0 | AO38: 0 | AP38: 0 | AQ38: 0 | AR38: 0 | AS38: 0 | AT38: 0 | AU38: 0 | AV38: 0 | AW38: 0 | AX38: 0 | AY38: 0 | AZ38: 0 | BA38: 0 | BB38: 0 | BC38: 0 | BD38: 0 | BE38: 0 | BF38: 0 | BG38: 0.25 | BH38: 0.22 | BI38: 0.08 | BJ38: 0.05 | BK38: 0.05 | BL38: 0.15 | BM38: 0.2 | BN38: 0.25 | BO38: 0.22 | BP38: 0.08 | BQ38: 0.05 | BR38: 0.05 | BS38: 0.15 | BT38: 0.2 | BU38: 0.25 | BV38: 0.22 | BW38: 0.08 | BX38: 0.05 | BY38: 0.05 | BZ38: 0.15 | CA38: 0.2 | CB38: 0.25 | CC38: 0.22 | CD38: 0.08 | CE38: 0.05 | CF38: 0.05 | CG38: 0.15 | CH38: 0.2 | CI38: 0.25 | CJ38: 0.22 | CK38: 0.08 | CL38: 0.05 | CM38: 0.05 | CN38: 0.15 | CO38: 0.2 | CP38: 0.25 | CQ38: 0.22 | CR38: 0.08 | CS38: 0.05 | CT38: 0.05 | CU38: 0.15 | CV38: 0.2 | CW38: 0.25 | CX38: 0.22 | CY38: 0.08 | CZ38: 0.05 | DA38: 0.05 | DB38: 0.15 | DC38: 0.2 | DD38: 0.25 | DE38: 0.22 | DF38: 0.08 | DG38: 0.05 | DH38: 0.05 | DI38: 0.15 | DJ38: 0.2 | DK38: 0.25 | DL38: 0.22 | DM38: 0.08 | DN38: 0.05 | DO38: 0.05 | DP38: 0.15 | DQ38: 0.2 | DR38: 0.25 | DS38: 0.22 | DT38: 0.08 | DU38: 0.05 | DV38: 0.05 | DW38: 0.15 | DX38: 0.2 | DY38: 0.25 | DZ38: 0.22 | EA38: 0.08 | EB38: 0.05 | EC38: 0.05 | ED38: 0.15 | EE38: 0.2 | EF38: 0.25 | EG38: 0.22 | EH38: 0.08 | EI38: 0.05 | EJ38: 0.05 | EK38: 0.15 | EL38: 0.2 | EM38: 0.25 | EN38: 0.22 | EO38: 0.08 | EP38: 0.05 | EQ38: 0.05 | ER38: 0.15 | ES38: 0.2 | ET38: 0.25 | EU38: 0.22 | EV38: 0.08 | EW38: 0.05 | EX38: 0.05 | EY38: 0.15 | EZ38: 0.2 | FA38: 0.25 | FB38: 0.22 | FC38: 0.08 | FD38: 0.05 | FE38: 0.05 | FF38: 0.15 | FG38: 0.2 | FH38: 0.25 | FI38: 0.22 | FJ38: 0.08 | FK38: 0.05 | FL38: 0.05 | FM38: 0.15 | FN38: 0.2 | FO38: 0.25 | FP38: 0.22 | FQ38: 0.08 | FR38: 0.05 | FS38: 0.05 | FT38: 0.15 | FU38: 0.2 | FV38: 0.25 | FW38: 0.22 | FX38: 0.08 | FY38: 0.05 | FZ38: 0.05 | GA38: 0.15 | GB38: 0.2 | GC38: 0 | GD38: 0 | GE38: 0 | GF38: 0 | GG38: 0 | GH38: 0 | GI38: 0 | GJ38: 0 | GK38: 0 | GL38: 0 | GM38: 0 | GN38: 0 | GO38: 0 | GP38: 0 | GQ38: 0.25 | GR38: 0.22 | GS38: 0.08 | GT38: 0.05 | GU38: 0.05 | GV38: 0.15 | GW38: 0.2 | GX38: 0.25 | GY38: 0.22 | GZ38: 0.08 | HA38: 0.05 | HB38: 0.05 | HC38: 0.15 | HD38: 0.2 | HE38: 0.25 | HF38: 0.22 | HG38: 0.08 | HH38: 0.05 | HI38: 0.05 | HJ38: 0.15 | HK38: 0.2 | HL38: 0.25 | HM38: 0.22 | HN38: 0.08 | HO38: 0.05 | HP38: 0.05 | HQ38: 0.15 | HR38: 0.2 | HS38: 0.25 | HT38: 0.22 | HU38: 0.08 | HV38: 0.05 | HW38: 0.05 | HX38: 0.15 | HY38: 0.2 | HZ38: 0.25 | IA38: 0.22 | IB38: 0.08 | IC38: 0.05 | ID38: 0.05 | IE38: 0.15 | IF38: 0.2 | IG38: 0.25 | IH38: 0.22 | II38: 0.08 | IJ38: 0.05 | IK38: 0.05 | IL38: 0.15 | IM38: 0.2 | IN38: 0.25 | IO38: 0.22 | IP38: 0.08 | IQ38: 0.05 | IR38: 0.05 | IS38: 0.15 | IT38: 0.2 | IU38: 0.25 | IV38: 0.22 | IW38: 0.08 | IX38: 0.05 | IY38: 0.05 | IZ38: 0.15 | JA38: 0.2 | JB38: 0.25 | JC38: 0.22 | JD38: 0.08 | JE38: 0.05 | JF38: 0.05 | JG38: 0.15 | JH38: 0.2 | JI38: 0.25 | JJ38: 0.22 | JK38: 0.08 | JL38: 0.05 | JM38: 0.05 | JN38: 0.15 | JO38: 0.2 | JP38: 0.25 | JQ38: 0.22 | JR38: 0.08 | JS38: 0.05 | JT38: 0.05 | JU38: 0.15 | JV38: 0.2 | JW38: 0.25 | JX38: 0.22 | JY38: 0.08 | JZ38: 0.05 | KA38: 0.05 | KB38: 0.15 | KC38: 0.2 | KD38: 0.25 | KE38: 0.22 | KF38: 0.08 | KG38: 0.05 | KH38: 0.05 | KI38: 0.15 | KJ38: 0.2 | KK38: 0.25 | KL38: 0.22 | KM38: 0.08 | KN38: 0.05 | KO38: 0.05 | KP38: 0.15 | KQ38: 0.2 | KR38: 0.25 | KS38: 0.22 | KT38: 0.08 | KU38: 0.05 | KV38: 0.05 | KW38: 0.15 | KX38: 0.2 | KY38: 0.25 | KZ38: 0.22 | LA38: 0.08 | LB38: 0.05 | LC38: 0.05 | LD38: 0.15 | LE38: 0.2 | LF38: 0.25 | LG38: 0.22 | LH38: 0.08 | LI38: 0.05 | LJ38: 0.05 | LK38: 0.15 | LL38: 0.2 | LM38: 0.25 | LN38: 0.22 | LO38: 0.08 | LP38: 0.05 | LQ38: 0.05 | LR38: 0.15 | LS38: 0.2 | LT38: 0.25 | LU38: 0.22 | LV38: 0.08 | LW38: 0.05 | LX38: 0.05 | LY38: 0.15 | LZ38: 0.2 | MA38: 0.25 | MB38: 0.22 | MC38: 0.08 | MD38: 0.05 | ME38: 0.05 | MF38: 0.15 | MG38: 0.2 | MH38: 0 | MI38: 0 | MJ38: 0 | MK38: 0 | ML38: 0 | MM38: 0 | MN38: 0 | MO38: 0.25 | MP38: 0.22 | MQ38: 0.08 | MR38: 0.05 | MS38: 0.05 | MT38: 0.15 | MU38: 0.2 | MV38: 0
E39: Ticket demand | G39: tickets | J39: {=_xlfn.ANCHORARRAY( J35) *_xlfn.ANCHORARRAY( J38)} -> 0 | K39: 0 | L39: 0 | M39: 0 | N39: 0 | O39: 0 | P39: 0 | Q39: 0 | R39: 0 | S39: 0 | T39: 0 | U39: 0 | V39: 0 | W39: 0 | X39: 0 | Y39: 0 | Z39: 0 | AA39: 0 | AB39: 0 | AC39: 0 | AD39: 0 | AE39: 0 | AF39: 0 | AG39: 0 | AH39: 0 | AI39: 0 | AJ39: 0 | AK39: 0 | AL39: 0 | AM39: 0 | AN39: 0 | AO39: 0 | AP39: 0 | AQ39: 0 | AR39: 0 | AS39: 0 | AT39: 0 | AU39: 0 | AV39: 0 | AW39: 0 | AX39: 0 | AY39: 0 | AZ39: 0 | BA39: 0 | BB39: 0 | BC39: 0 | BD39: 0 | BE39: 0 | BF39: 0 | BG39: 8000 | BH39: 7040 | BI39: 2560 | BJ39: 1600 | BK39: 1600 | BL39: 4800 | BM39: 6400 | BN39: 6250 | BO39: 5500 | BP39: 2000 | BQ39: 1250 | BR39: 1250 | BS39: 3750 | BT39: 5000 | BU39: 3750 | BV39: 3300 | BW39: 1200 | BX39: 750 | BY39: 750 | BZ39: 2250 | CA39: 3000 | CB39: 8000 | CC39: 7040 | CD39: 2560 | CE39: 1600 | CF39: 1600 | CG39: 4800 | CH39: 6400 | CI39: 3750 | CJ39: 3300 | CK39: 1200 | CL39: 750 | CM39: 750 | CN39: 2250 | CO39: 3000 | CP39: 6250 | CQ39: 5500 | CR39: 2000 | CS39: 1250 | CT39: 1250 | CU39: 3750 | CV39: 5000 | CW39: 3750 | CX39: 3300 | CY39: 1200 | CZ39: 750 | DA39: 750 | DB39: 2250 | DC39: 3000 | DD39: 6250 | DE39: 5500 | DF39: 2000 | DG39: 1250 | DH39: 1250 | DI39: 3750 | DJ39: 5000 | DK39: 6250 | DL39: 5500 | DM39: 2000 | DN39: 1250 | DO39: 1250 | DP39: 3750 | DQ39: 5000 | DR39: 3750 | DS39: 3300 | DT39: 1200 | DU39: 750 | DV39: 750 | DW39: 2250 | DX39: 3000 | DY39: 6250 | DZ39: 5500 | EA39: 2000 | EB39: 1250 | EC39: 1250 | ED39: 3750 | EE39: 5000 | EF39: 3750 | EG39: 3300 | EH39: 1200 | EI39: 750 | EJ39: 750 | EK39: 2250 | EL39: 3000 | EM39: 10000 | EN39: 8800 | EO39: 3200 | EP39: 2000 | EQ39: 2000 | ER39: 6000 | ES39: 8000 | ET39: 3750 | EU39: 3300 | EV39: 1200 | EW39: 750 | EX39: 750 | EY39: 2250 | EZ39: 3000 | FA39: 6250 | FB39: 5500 | FC39: 2000 | FD39: 1250 | FE39: 1250 | FF39: 3750 | FG39: 5000 | FH39: 6250 | FI39: 5500 | FJ39: 2000 | FK39: 1250 | FL39: 1250 | FM39: 3750 | FN39: 5000 | FO39: 6250 | FP39: 5500 | FQ39: 2000 | FR39: 1250 | FS39: 1250 | FT39: 3750 | FU39: 5000 | FV39: 3750 | FW39: 3300 | FX39: 1200 | FY39: 750 | FZ39: 750 | GA39: 2250 | GB39: 3000 | GC39: 0 | GD39: 0 | GE39: 0 | GF39: 0 | GG39: 0 | GH39: 0 | GI39: 0 | GJ39: 0 | GK39: 0 | GL39: 0 | GM39: 0 | GN39: 0 | GO39: 0 | GP39: 0 | GQ39: 3750 | GR39: 3300 | GS39: 1200 | GT39: 750 | GU39: 750 | GV39: 2250 | GW39: 3000 | GX39: 3750 | GY39: 3300 | GZ39: 1200 | HA39: 750 | HB39: 750 | HC39: 2250 | HD39: 3000 | HE39: 8000 | HF39: 7040 | HG39: 2560 | HH39: 1600 | HI39: 1600 | HJ39: 4800 | HK39: 6400 | HL39: 3750 | HM39: 3300 | HN39: 1200 | HO39: 750 | HP39: 750 | HQ39: 2250 | HR39: 3000 | HS39: 10000 | HT39: 8800 | HU39: 3200 | HV39: 2000 | HW39: 2000 | HX39: 6000 | HY39: 8000 | HZ39: 6250 | IA39: 5500 | IB39: 2000 | IC39: 1250 | ID39: 1250 | IE39: 3750 | IF39: 5000 | IG39: 6250 | IH39: 5500 | II39: 2000 | IJ39: 1250 | IK39: 1250 | IL39: 3750 | IM39: 5000 | IN39: 6250 | IO39: 5500 | IP39: 2000 | IQ39: 1250 | IR39: 1250 | IS39: 3750 | IT39: 5000 | IU39: 8000 | IV39: 7040 | IW39: 2560 | IX39: 1600 | IY39: 1600 | IZ39: 4800 | JA39: 6400 | JB39: 3750 | JC39: 3300 | JD39: 1200 | JE39: 750 | JF39: 750 | JG39: 2250 | JH39: 3000 | JI39: 6250 | JJ39: 5500 | JK39: 2000 | JL39: 1250 | JM39: 1250 | JN39: 3750 | JO39: 5000 | JP39: 6250 | JQ39: 5500 | JR39: 2000 | JS39: 1250 | JT39: 1250 | JU39: 3750 | JV39: 5000 | JW39: 8000 | JX39: 7040 | JY39: 2560 | JZ39: 1600 | KA39: 1600 | KB39: 4800 | KC39: 6400 | KD39: 3750 | KE39: 3300 | KF39: 1200 | KG39: 750 | KH39: 750 | KI39: 2250 | KJ39: 3000 | KK39: 6250 | KL39: 5500 | KM39: 2000 | KN39: 1250 | KO39: 1250 | KP39: 3750 | KQ39: 5000 | KR39: 6250 | KS39: 5500 | KT39: 2000 | KU39: 1250 | KV39: 1250 | KW39: 3750 | KX39: 5000 | KY39: 3750 | KZ39: 3300 | LA39: 1200 | LB39: 750 | LC39: 750 | LD39: 2250 | LE39: 3000 | LF39: 3750 | LG39: 3300 | LH39: 1200 | LI39: 750 | LJ39: 750 | LK39: 2250 | LL39: 3000 | LM39: 3750 | LN39: 3300 | LO39: 1200 | LP39: 750 | LQ39: 750 | LR39: 2250 | LS39: 3000 | LT39: 8000 | LU39: 7040 | LV39: 2560 | LW39: 1600 | LX39: 1600 | LY39: 4800 | LZ39: 6400 | MA39: 10000 | MB39: 8800 | MC39: 3200 | MD39: 2000 | ME39: 2000 | MF39: 6000 | MG39: 8000 | MH39: 0 | MI39: 0 | MJ39: 0 | MK39: 0 | ML39: 0 | MM39: 0 | MN39: 0 | MO39: 12500 | MP39: 11000 | MQ39: 4000 | MR39: 2500 | MS39: 2500 | MT39: 7500 | MU39: 10000 | MV39: 0
E40: Tickets available (day) | G40: tickets | J40: {=_xlfn.LET( _xlpm.game_day,_xlfn.ANCHORARRAY( J14), _xlpm.tickets_available,_xlfn.ANCHORARRAY( J36), _xlpm.demand_prev, _xlfn.HSTACK( 0, _xlfn.TAKE(_xlfn.ANCHORARRAY( J39),, COLUMNS(_xlfn.ANCHORARRAY( J39) ) -1 ) ), _xlfn.SCAN( 0, _xlfn.SEQUENCE(,COLUMNS(_xlpm.game_day)), _xlfn.LAMBDA(_xlpm.rem,_xlpm.i, IF( OR( _xlpm.i = 1, INDEX( _xlpm.game_day, 1, _xlpm.i ) <> INDEX( _xlpm.game_day, 1, _xlpm.i - 1 ) ), INDEX( _xlpm.tickets_available, 1, _xlpm.i ), MAX( _xlpm.rem - INDEX( _xlpm.demand_prev, 1, _xlpm.i ), 0 ) ) ) ) )} -> 24350 | K40: 24350 | L40: 24350 | M40: 24350 | N40: 24350 | O40: 24350 | P40: 24350 | Q40: 24350 | R40: 24350 | S40: 24350 | T40: 24350 | U40: 24350 | V40: 24350 | W40: 24350 | X40: 24350 | Y40: 24350 | Z40: 24350 | AA40: 24350 | AB40: 24350 | AC40: 24350 | AD40: 24350 | AE40: 24350 | AF40: 24350 | AG40: 24350 | AH40: 24350 | AI40: 24350 | AJ40: 24350 | AK40: 24350 | AL40: 24350 | AM40: 24350 | AN40: 24350 | AO40: 24350 | AP40: 24350 | AQ40: 24350 | AR40: 24350 | AS40: 24350 | AT40: 24350 | AU40: 24350 | AV40: 24350 | AW40: 24350 | AX40: 24350 | AY40: 24350 | AZ40: 24350 | BA40: 24350 | BB40: 24350 | BC40: 24350 | BD40: 24350 | BE40: 24350 | BF40: 24350 | BG40: 24350 | BH40: 16350 | BI40: 9310 | BJ40: 6750 | BK40: 5150 | BL40: 3550 | BM40: 0 | BN40: 22950 | BO40: 16700 | BP40: 11200 | BQ40: 9200 | BR40: 7950 | BS40: 6700 | BT40: 2950 | BU40: 22150 | BV40: 18400 | BW40: 15100 | BX40: 13900 | BY40: 13150 | BZ40: 12400 | CA40: 10150 | CB40: 21650 | CC40: 13650 | CD40: 6610 | CE40: 4050 | CF40: 2450 | CG40: 850 | CH40: 0 | CI40: 21450 | CJ40: 17700 | CK40: 14400 | CL40: 13200 | CM40: 12450 | CN40: 11700 | CO40: 9450 | CP40: 21300 | CQ40: 15050 | CR40: 9550 | CS40: 7550 | CT40: 6300 | CU40: 5050 | CV40: 1300 | CW40: 21250 | CX40: 17500 | CY40: 14200 | CZ40: 13000 | DA40: 12250 | DB40: 11500 | DC40: 9250 | DD40: 21200 | DE40: 14950 | DF40: 9450 | DG40: 7450 | DH40: 6200 | DI40: 4950 | DJ40: 1200 | DK40: 21150 | DL40: 14900 | DM40: 9400 | DN40: 7400 | DO40: 6150 | DP40: 4900 | DQ40: 1150 | DR40: 21100 | DS40: 17350 | DT40: 14050 | DU40: 12850 | DV40: 12100 | DW40: 11350 | DX40: 9100 | DY40: 21050 | DZ40: 14800 | EA40: 9300 | EB40: 7300 | EC40: 6050 | ED40: 4800 | EE40: 1050 | EF40: 21000 | EG40: 17250 | EH40: 13950 | EI40: 12750 | EJ40: 12000 | EK40: 11250 | EL40: 9000 | EM40: 20950 | EN40: 10950 | EO40: 2150 | EP40: 0 | EQ40: 0 | ER40: 0 | ES40: 0 | ET40: 20900 | EU40: 17150 | EV40: 13850 | EW40: 12650 | EX40: 11900 | EY40: 11150 | EZ40: 8900 | FA40: 20850 | FB40: 14600 | FC40: 9100 | FD40: 7100 | FE40: 5850 | FF40: 4600 | FG40: 850 | FH40: 20800 | FI40: 14550 | FJ40: 9050 | FK40: 7050 | FL40: 5800 | FM40: 4550 | FN40: 800 | FO40: 20750 | FP40: 14500 | FQ40: 9000 | FR40: 7000 | FS40: 5750 | FT40: 4500 | FU40: 750 | FV40: 20500 | FW40: 16750 | FX40: 13450 | FY40: 12250 | FZ40: 11500 | GA40: 10750 | GB40: 8500 | GC40: 20150 | GD40: 20150 | GE40: 20150 | GF40: 20150 | GG40: 20150 | GH40: 20150 | GI40: 20150 | GJ40: 20150 | GK40: 20150 | GL40: 20150 | GM40: 20150 | GN40: 20150 | GO40: 20150 | GP40: 20150 | GQ40: 20150 | GR40: 16400 | GS40: 13100 | GT40: 11900 | GU40: 11150 | GV40: 10400 | GW40: 8150 | GX40: 20100 | GY40: 16350 | GZ40: 13050 | HA40: 11850 | HB40: 11100 | HC40: 10350 | HD40: 8100 | HE40: 20050 | HF40: 12050 | HG40: 5010 | HH40: 2450 | HI40: 850 | HJ40: 0 | HK40: 0 | HL40: 20000 | HM40: 16250 | HN40: 12950 | HO40: 11750 | HP40: 11000 | HQ40: 10250 | HR40: 8000 | HS40: 20000 | HT40: 10000 | HU40: 1200 | HV40: 0 | HW40: 0 | HX40: 0 | HY40: 0 | HZ40: 20000 | IA40: 13750 | IB40: 8250 | IC40: 6250 | ID40: 5000 | IE40: 3750 | IF40: 0 | IG40: 20000 | IH40: 13750 | II40: 8250 | IJ40: 6250 | IK40: 5000 | IL40: 3750 | IM40: 0 | IN40: 20000 | IO40: 13750 | IP40: 8250 | IQ40: 6250 | IR40: 5000 | IS40: 3750 | IT40: 0 | IU40: 20000 | IV40: 12000 | IW40: 4960 | IX40: 2400 | IY40: 800 | IZ40: 0 | JA40: 0 | JB40: 20000 | JC40: 16250 | JD40: 12950 | JE40: 11750 | JF40: 11000 | JG40: 10250 | JH40: 8000 | JI40: 20000 | JJ40: 13750 | JK40: 8250 | JL40: 6250 | JM40: 5000 | JN40: 3750 | JO40: 0 | JP40: 20000 | JQ40: 13750 | JR40: 8250 | JS40: 6250 | JT40: 5000 | JU40: 3750 | JV40: 0 | JW40: 20000 | JX40: 12000 | JY40: 4960 | JZ40: 2400 | KA40: 800 | KB40: 0 | KC40: 0 | KD40: 20000 | KE40: 16250 | KF40: 12950 | KG40: 11750 | KH40: 11000 | KI40: 10250 | KJ40: 8000 | KK40: 20000 | KL40: 13750 | KM40: 8250 | KN40: 6250 | KO40: 5000 | KP40: 3750 | KQ40: 0 | KR40: 20000 | KS40: 13750 | KT40: 8250 | KU40: 6250 | KV40: 5000 | KW40: 3750 | KX40: 0 | KY40: 20000 | KZ40: 16250 | LA40: 12950 | LB40: 11750 | LC40: 11000 | LD40: 10250 | LE40: 8000 | LF40: 20000 | LG40: 16250 | LH40: 12950 | LI40: 11750 | LJ40: 11000 | LK40: 10250 | LL40: 8000 | LM40: 20000 | LN40: 16250 | LO40: 12950 | LP40: 11750 | LQ40: 11000 | LR40: 10250 | LS40: 8000 | LT40: 20000 | LU40: 12000 | LV40: 4960 | LW40: 2400 | LX40: 800 | LY40: 0 | LZ40: 0 | MA40: 20000 | MB40: 10000 | MC40: 1200 | MD40: 0 | ME40: 0 | MF40: 0 | MG40: 0 | MH40: 20000 | MI40: 20000 | MJ40: 20000 | MK40: 20000 | ML40: 20000 | MM40: 20000 | MN40: 20000 | MO40: 20000 | MP40: 7500 | MQ40: 0 | MR40: 0 | MS40: 0 | MT40: 0 | MU40: 0 | MV40: 0
E41: Daily sales of single game tickets | G41: tickets | J41: {=_xlfn.BYCOL( J39:MV40, _xleta.MIN )} -> 0 | K41: 0 | L41: 0 | M41: 0 | N41: 0 | O41: 0 | P41: 0 | Q41: 0 | R41: 0 | S41: 0 | T41: 0 | U41: 0 | V41: 0 | W41: 0 | X41: 0 | Y41: 0 | Z41: 0 | AA41: 0 | AB41: 0 | AC41: 0 | AD41: 0 | AE41: 0 | AF41: 0 | AG41: 0 | AH41: 0 | AI41: 0 | AJ41: 0 | AK41: 0 | AL41: 0 | AM41: 0 | AN41: 0 | AO41: 0 | AP41: 0 | AQ41: 0 | AR41: 0 | AS41: 0 | AT41: 0 | AU41: 0 | AV41: 0 | AW41: 0 | AX41: 0 | AY41: 0 | AZ41: 0 | BA41: 0 | BB41: 0 | BC41: 0 | BD41: 0 | BE41: 0 | BF41: 0 | BG41: 8000 | BH41: 7040 | BI41: 2560 | BJ41: 1600 | BK41: 1600 | BL41: 3550 | BM41: 0 | BN41: 6250 | BO41: 5500 | BP41: 2000 | BQ41: 1250 | BR41: 1250 | BS41: 3750 | BT41: 2950 | BU41: 3750 | BV41: 3300 | BW41: 1200 | BX41: 750 | BY41: 750 | BZ41: 2250 | CA41: 3000 | CB41: 8000 | CC41: 7040 | CD41: 2560 | CE41: 1600 | CF41: 1600 | CG41: 850 | CH41: 0 | CI41: 3750 | CJ41: 3300 | CK41: 1200 | CL41: 750 | CM41: 750 | CN41: 2250 | CO41: 3000 | CP41: 6250 | CQ41: 5500 | CR41: 2000 | CS41: 1250 | CT41: 1250 | CU41: 3750 | CV41: 1300 | CW41: 3750 | CX41: 3300 | CY41: 1200 | CZ41: 750 | DA41: 750 | DB41: 2250 | DC41: 3000 | DD41: 6250 | DE41: 5500 | DF41: 2000 | DG41: 1250 | DH41: 1250 | DI41: 3750 | DJ41: 1200 | DK41: 6250 | DL41: 5500 | DM41: 2000 | DN41: 1250 | DO41: 1250 | DP41: 3750 | DQ41: 1150 | DR41: 3750 | DS41: 3300 | DT41: 1200 | DU41: 750 | DV41: 750 | DW41: 2250 | DX41: 3000 | DY41: 6250 | DZ41: 5500 | EA41: 2000 | EB41: 1250 | EC41: 1250 | ED41: 3750 | EE41: 1050 | EF41: 3750 | EG41: 3300 | EH41: 1200 | EI41: 750 | EJ41: 750 | EK41: 2250 | EL41: 3000 | EM41: 10000 | EN41: 8800 | EO41: 2150 | EP41: 0 | EQ41: 0 | ER41: 0 | ES41: 0 | ET41: 3750 | EU41: 3300 | EV41: 1200 | EW41: 750 | EX41: 750 | EY41: 2250 | EZ41: 3000 | FA41: 6250 | FB41: 5500 | FC41: 2000 | FD41: 1250 | FE41: 1250 | FF41: 3750 | FG41: 850 | FH41: 6250 | FI41: 5500 | FJ41: 2000 | FK41: 1250 | FL41: 1250 | FM41: 3750 | FN41: 800 | FO41: 6250 | FP41: 5500 | FQ41: 2000 | FR41: 1250 | FS41: 1250 | FT41: 3750 | FU41: 750 | FV41: 3750 | FW41: 3300 | FX41: 1200 | FY41: 750 | FZ41: 750 | GA41: 2250 | GB41: 3000 | GC41: 0 | GD41: 0 | GE41: 0 | GF41: 0 | GG41: 0 | GH41: 0 | GI41: 0 | GJ41: 0 | GK41: 0 | GL41: 0 | GM41: 0 | GN41: 0 | GO41: 0 | GP41: 0 | GQ41: 3750 | GR41: 3300 | GS41: 1200 | GT41: 750 | GU41: 750 | GV41: 2250 | GW41: 3000 | GX41: 3750 | GY41: 3300 | GZ41: 1200 | HA41: 750 | HB41: 750 | HC41: 2250 | HD41: 3000 | HE41: 8000 | HF41: 7040 | HG41: 2560 | HH41: 1600 | HI41: 850 | HJ41: 0 | HK41: 0 | HL41: 3750 | HM41: 3300 | HN41: 1200 | HO41: 750 | HP41: 750 | HQ41: 2250 | HR41: 3000 | HS41: 10000 | HT41: 8800 | HU41: 1200 | HV41: 0 | HW41: 0 | HX41: 0 | HY41: 0 | HZ41: 6250 | IA41: 5500 | IB41: 2000 | IC41: 1250 | ID41: 1250 | IE41: 3750 | IF41: 0 | IG41: 6250 | IH41: 5500 | II41: 2000 | IJ41: 1250 | IK41: 1250 | IL41: 3750 | IM41: 0 | IN41: 6250 | IO41: 5500 | IP41: 2000 | IQ41: 1250 | IR41: 1250 | IS41: 3750 | IT41: 0 | IU41: 8000 | IV41: 7040 | IW41: 2560 | IX41: 1600 | IY41: 800 | IZ41: 0 | JA41: 0 | JB41: 3750 | JC41: 3300 | JD41: 1200 | JE41: 750 | JF41: 750 | JG41: 2250 | JH41: 3000 | JI41: 6250 | JJ41: 5500 | JK41: 2000 | JL41: 1250 | JM41: 1250 | JN41: 3750 | JO41: 0 | JP41: 6250 | JQ41: 5500 | JR41: 2000 | JS41: 1250 | JT41: 1250 | JU41: 3750 | JV41: 0 | JW41: 8000 | JX41: 7040 | JY41: 2560 | JZ41: 1600 | KA41: 800 | KB41: 0 | KC41: 0 | KD41: 3750 | KE41: 3300 | KF41: 1200 | KG41: 750 | KH41: 750 | KI41: 2250 | KJ41: 3000 | KK41: 6250 | KL41: 5500 | KM41: 2000 | KN41: 1250 | KO41: 1250 | KP41: 3750 | KQ41: 0 | KR41: 6250 | KS41: 5500 | KT41: 2000 | KU41: 1250 | KV41: 1250 | KW41: 3750 | KX41: 0 | KY41: 3750 | KZ41: 3300 | LA41: 1200 | LB41: 750 | LC41: 750 | LD41: 2250 | LE41: 3000 | LF41: 3750 | LG41: 3300 | LH41: 1200 | LI41: 750 | LJ41: 750 | LK41: 2250 | LL41: 3000 | LM41: 3750 | LN41: 3300 | LO41: 1200 | LP41: 750 | LQ41: 750 | LR41: 2250 | LS41: 3000 | LT41: 8000 | LU41: 7040 | LV41: 2560 | LW41: 1600 | LX41: 800 | LY41: 0 | LZ41: 0 | MA41: 10000 | MB41: 8800 | MC41: 1200 | MD41: 0 | ME41: 0 | MF41: 0 | MG41: 0 | MH41: 0 | MI41: 0 | MJ41: 0 | MK41: 0 | ML41: 0 | MM41: 0 | MN41: 0 | MO41: 12500 | MP41: 7500 | MQ41: 0 | MR41: 0 | MS41: 0 | MT41: 0 | MU41: 0 | MV41: 0
E43: Cash from single game ticket sale | G43: USD | H43: {=_xlfn.BYROW(_xlfn.ANCHORARRAY( J43), _xleta.SUM )} -> 30611500 | J43: {=_xlfn.LET( _xlpm.price, _xlfn.XLOOKUP(_xlfn.ANCHORARRAY( J34), tbl_ImpLU[Importance], tbl_ImpLU[Ticket price ($)], 0 ), _xlpm.volume,_xlfn.ANCHORARRAY( J41), _xlpm.price * _xlpm.volume )} -> 0 | K43: 0 | L43: 0 | M43: 0 | N43: 0 | O43: 0 | P43: 0 | Q43: 0 | R43: 0 | S43: 0 | T43: 0 | U43: 0 | V43: 0 | W43: 0 | X43: 0 | Y43: 0 | Z43: 0 | AA43: 0 | AB43: 0 | AC43: 0 | AD43: 0 | AE43: 0 | AF43: 0 | AG43: 0 | AH43: 0 | AI43: 0 | AJ43: 0 | AK43: 0 | AL43: 0 | AM43: 0 | AN43: 0 | AO43: 0 | AP43: 0 | AQ43: 0 | AR43: 0 | AS43: 0 | AT43: 0 | AU43: 0 | AV43: 0 | AW43: 0 | AX43: 0 | AY43: 0 | AZ43: 0 | BA43: 0 | BB43: 0 | BC43: 0 | BD43: 0 | BE43: 0 | BF43: 0 | BG43: 400000 | BH43: 352000 | BI43: 128000 | BJ43: 80000 | BK43: 80000 | BL43: 177500 | BM43: 0 | BN43: 250000 | BO43: 220000 | BP43: 80000 | BQ43: 50000 | BR43: 50000 | BS43: 150000 | BT43: 118000 | BU43: 112500 | BV43: 99000 | BW43: 36000 | BX43: 22500 | BY43: 22500 | BZ43: 67500 | CA43: 90000 | CB43: 400000 | CC43: 352000 | CD43: 128000 | CE43: 80000 | CF43: 80000 | CG43: 42500 | CH43: 0 | CI43: 112500 | CJ43: 99000 | CK43: 36000 | CL43: 22500 | CM43: 22500 | CN43: 67500 | CO43: 90000 | CP43: 250000 | CQ43: 220000 | CR43: 80000 | CS43: 50000 | CT43: 50000 | CU43: 150000 | CV43: 52000 | CW43: 112500 | CX43: 99000 | CY43: 36000 | CZ43: 22500 | DA43: 22500 | DB43: 67500 | DC43: 90000 | DD43: 250000 | DE43: 220000 | DF43: 80000 | DG43: 50000 | DH43: 50000 | DI43: 150000 | DJ43: 48000 | DK43: 250000 | DL43: 220000 | DM43: 80000 | DN43: 50000 | DO43: 50000 | DP43: 150000 | DQ43: 46000 | DR43: 112500 | DS43: 99000 | DT43: 36000 | DU43: 22500 | DV43: 22500 | DW43: 67500 | DX43: 90000 | DY43: 250000 | DZ43: 220000 | EA43: 80000 | EB43: 50000 | EC43: 50000 | ED43: 150000 | EE43: 42000 | EF43: 112500 | EG43: 99000 | EH43: 36000 | EI43: 22500 | EJ43: 22500 | EK43: 67500 | EL43: 90000 | EM43: 600000 | EN43: 528000 | EO43: 129000 | EP43: 0 | EQ43: 0 | ER43: 0 | ES43: 0 | ET43: 112500 | EU43: 99000 | EV43: 36000 | EW43: 22500 | EX43: 22500 | EY43: 67500 | EZ43: 90000 | FA43: 250000 | FB43: 220000 | FC43: 80000 | FD43: 50000 | FE43: 50000 | FF43: 150000 | FG43: 34000 | FH43: 250000 | FI43: 220000 | FJ43: 80000 | FK43: 50000 | FL43: 50000 | FM43: 150000 | FN43: 32000 | FO43: 250000 | FP43: 220000 | FQ43: 80000 | FR43: 50000 | FS43: 50000 | FT43: 150000 | FU43: 30000 | FV43: 112500 | FW43: 99000 | FX43: 36000 | FY43: 22500 | FZ43: 22500 | GA43: 67500 | GB43: 90000 | GC43: 0 | GD43: 0 | GE43: 0 | GF43: 0 | GG43: 0 | GH43: 0 | GI43: 0 | GJ43: 0 | GK43: 0 | GL43: 0 | GM43: 0 | GN43: 0 | GO43: 0 | GP43: 0 | GQ43: 112500 | GR43: 99000 | GS43: 36000 | GT43: 22500 | GU43: 22500 | GV43: 67500 | GW43: 90000 | GX43: 112500 | GY43: 99000 | GZ43: 36000 | HA43: 22500 | HB43: 22500 | HC43: 67500 | HD43: 90000 | HE43: 400000 | HF43: 352000 | HG43: 128000 | HH43: 80000 | HI43: 42500 | HJ43: 0 | HK43: 0 | HL43: 112500 | HM43: 99000 | HN43: 36000 | HO43: 22500 | HP43: 22500 | HQ43: 67500 | HR43: 90000 | HS43: 600000 | HT43: 528000 | HU43: 72000 | HV43: 0 | HW43: 0 | HX43: 0 | HY43: 0 | HZ43: 250000 | IA43: 220000 | IB43: 80000 | IC43: 50000 | ID43: 50000 | IE43: 150000 | IF43: 0 | IG43: 250000 | IH43: 220000 | II43: 80000 | IJ43: 50000 | IK43: 50000 | IL43: 150000 | IM43: 0 | IN43: 250000 | IO43: 220000 | IP43: 80000 | IQ43: 50000 | IR43: 50000 | IS43: 150000 | IT43: 0 | IU43: 400000 | IV43: 352000 | IW43: 128000 | IX43: 80000 | IY43: 40000 | IZ43: 0 | JA43: 0 | JB43: 112500 | JC43: 99000 | JD43: 36000 | JE43: 22500 | JF43: 22500 | JG43: 67500 | JH43: 90000 | JI43: 250000 | JJ43: 220000 | JK43: 80000 | JL43: 50000 | JM43: 50000 | JN43: 150000 | JO43: 0 | JP43: 250000 | JQ43: 220000 | JR43: 80000 | JS43: 50000 | JT43: 50000 | JU43: 150000 | JV43: 0 | JW43: 400000 | JX43: 352000 | JY43: 128000 | JZ43: 80000 | KA43: 40000 | KB43: 0 | KC43: 0 | KD43: 112500 | KE43: 99000 | KF43: 36000 | KG43: 22500 | KH43: 22500 | KI43: 67500 | KJ43: 90000 | KK43: 250000 | KL43: 220000 | KM43: 80000 | KN43: 50000 | KO43: 50000 | KP43: 150000 | KQ43: 0 | KR43: 250000 | KS43: 220000 | KT43: 80000 | KU43: 50000 | KV43: 50000 | KW43: 150000 | KX43: 0 | KY43: 112500 | KZ43: 99000 | LA43: 36000 | LB43: 22500 | LC43: 22500 | LD43: 67500 | LE43: 90000 | LF43: 112500 | LG43: 99000 | LH43: 36000 | LI43: 22500 | LJ43: 22500 | LK43: 67500 | LL43: 90000 | LM43: 112500 | LN43: 99000 | LO43: 36000 | LP43: 22500 | LQ43: 22500 | LR43: 67500 | LS43: 90000 | LT43: 400000 | LU43: 352000 | LV43: 128000 | LW43: 80000 | LX43: 40000 | LY43: 0 | LZ43: 0 | MA43: 600000 | MB43: 528000 | MC43: 72000 | MD43: 0 | ME43: 0 | MF43: 0 | MG43: 0 | MH43: 0 | MI43: 0 | MJ43: 0 | MK43: 0 | ML43: 0 | MM43: 0 | MN43: 0 | MO43: 937500 | MP43: 562500 | MQ43: 0 | MR43: 0 | MS43: 0 | MT43: 0 | MU43: 0 | MV43: 0
E44: Revenue from sale of single game tickets | G44: USD | J44: {=IF(_xlfn.ANCHORARRAY( J15) = 0, SUMIFS(_xlfn.ANCHORARRAY( J43),_xlfn.ANCHORARRAY( J14),_xlfn.ANCHORARRAY( J11) ), 0 )} -> 0 | K44: 0 | L44: 0 | M44: 0 | N44: 0 | O44: 0 | P44: 0 | Q44: 0 | R44: 0 | S44: 0 | T44: 0 | U44: 0 | V44: 0 | W44: 0 | X44: 0 | Y44: 0 | Z44: 0 | AA44: 0 | AB44: 0 | AC44: 0 | AD44: 0 | AE44: 0 | AF44: 0 | AG44: 0 | AH44: 0 | AI44: 0 | AJ44: 0 | AK44: 0 | AL44: 0 | AM44: 0 | AN44: 0 | AO44: 0 | AP44: 0 | AQ44: 0 | AR44: 0 | AS44: 0 | AT44: 0 | AU44: 0 | AV44: 0 | AW44: 0 | AX44: 0 | AY44: 0 | AZ44: 0 | BA44: 0 | BB44: 0 | BC44: 0 | BD44: 0 | BE44: 0 | BF44: 0 | BG44: 0 | BH44: 0 | BI44: 0 | BJ44: 0 | BK44: 0 | BL44: 0 | BM44: 1217500 | BN44: 0 | BO44: 0 | BP44: 0 | BQ44: 0 | BR44: 0 | BS44: 0 | BT44: 918000 | BU44: 0 | BV44: 0 | BW44: 0 | BX44: 0 | BY44: 0 | BZ44: 0 | CA44: 450000 | CB44: 0 | CC44: 0 | CD44: 0 | CE44: 0 | CF44: 0 | CG44: 0 | CH44: 1082500 | CI44: 0 | CJ44: 0 | CK44: 0 | CL44: 0 | CM44: 0 | CN44: 0 | CO44: 450000 | CP44: 0 | CQ44: 0 | CR44: 0 | CS44: 0 | CT44: 0 | CU44: 0 | CV44: 852000 | CW44: 0 | CX44: 0 | CY44: 0 | CZ44: 0 | DA44: 0 | DB44: 0 | DC44: 450000 | DD44: 0 | DE44: 0 | DF44: 0 | DG44: 0 | DH44: 0 | DI44: 0 | DJ44: 848000 | DK44: 0 | DL44: 0 | DM44: 0 | DN44: 0 | DO44: 0 | DP44: 0 | DQ44: 846000 | DR44: 0 | DS44: 0 | DT44: 0 | DU44: 0 | DV44: 0 | DW44: 0 | DX44: 450000 | DY44: 0 | DZ44: 0 | EA44: 0 | EB44: 0 | EC44: 0 | ED44: 0 | EE44: 842000 | EF44: 0 | EG44: 0 | EH44: 0 | EI44: 0 | EJ44: 0 | EK44: 0 | EL44: 450000 | EM44: 0 | EN44: 0 | EO44: 0 | EP44: 0 | EQ44: 0 | ER44: 0 | ES44: 1257000 | ET44: 0 | EU44: 0 | EV44: 0 | EW44: 0 | EX44: 0 | EY44: 0 | EZ44: 450000 | FA44: 0 | FB44: 0 | FC44: 0 | FD44: 0 | FE44: 0 | FF44: 0 | FG44: 834000 | FH44: 0 | FI44: 0 | FJ44: 0 | FK44: 0 | FL44: 0 | FM44: 0 | FN44: 832000 | FO44: 0 | FP44: 0 | FQ44: 0 | FR44: 0 | FS44: 0 | FT44: 0 | FU44: 830000 | FV44: 0 | FW44: 0 | FX44: 0 | FY44: 0 | FZ44: 0 | GA44: 0 | GB44: 450000 | GC44: 0 | GD44: 0 | GE44: 0 | GF44: 0 | GG44: 0 | GH44: 0 | GI44: 0 | GJ44: 0 | GK44: 0 | GL44: 0 | GM44: 0 | GN44: 0 | GO44: 0 | GP44: 0 | GQ44: 0 | GR44: 0 | GS44: 0 | GT44: 0 | GU44: 0 | GV44: 0 | GW44: 450000 | GX44: 0 | GY44: 0 | GZ44: 0 | HA44: 0 | HB44: 0 | HC44: 0 | HD44: 450000 | HE44: 0 | HF44: 0 | HG44: 0 | HH44: 0 | HI44: 0 | HJ44: 0 | HK44: 1002500 | HL44: 0 | HM44: 0 | HN44: 0 | HO44: 0 | HP44: 0 | HQ44: 0 | HR44: 450000 | HS44: 0 | HT44: 0 | HU44: 0 | HV44: 0 | HW44: 0 | HX44: 0 | HY44: 1200000 | HZ44: 0 | IA44: 0 | IB44: 0 | IC44: 0 | ID44: 0 | IE44: 0 | IF44: 800000 | IG44: 0 | IH44: 0 | II44: 0 | IJ44: 0 | IK44: 0 | IL44: 0 | IM44: 800000 | IN44: 0 | IO44: 0 | IP44: 0 | IQ44: 0 | IR44: 0 | IS44: 0 | IT44: 800000 | IU44: 0 | IV44: 0 | IW44: 0 | IX44: 0 | IY44: 0 | IZ44: 0 | JA44: 1000000 | JB44: 0 | JC44: 0 | JD44: 0 | JE44: 0 | JF44: 0 | JG44: 0 | JH44: 450000 | JI44: 0 | JJ44: 0 | JK44: 0 | JL44: 0 | JM44: 0 | JN44: 0 | JO44: 800000 | JP44: 0 | JQ44: 0 | JR44: 0 | JS44: 0 | JT44: 0 | JU44: 0 | JV44: 800000 | JW44: 0 | JX44: 0 | JY44: 0 | JZ44: 0 | KA44: 0 | KB44: 0 | KC44: 1000000 | KD44: 0 | KE44: 0 | KF44: 0 | KG44: 0 | KH44: 0 | KI44: 0 | KJ44: 450000 | KK44: 0 | KL44: 0 | KM44: 0 | KN44: 0 | KO44: 0 | KP44: 0 | KQ44: 800000 | KR44: 0 | KS44: 0 | KT44: 0 | KU44: 0 | KV44: 0 | KW44: 0 | KX44: 800000 | KY44: 0 | KZ44: 0 | LA44: 0 | LB44: 0 | LC44: 0 | LD44: 0 | LE44: 450000 | LF44: 0 | LG44: 0 | LH44: 0 | LI44: 0 | LJ44: 0 | LK44: 0 | LL44: 450000 | LM44: 0 | LN44: 0 | LO44: 0 | LP44: 0 | LQ44: 0 | LR44: 0 | LS44: 450000 | LT44: 0 | LU44: 0 | LV44: 0 | LW44: 0 | LX44: 0 | LY44: 0 | LZ44: 1000000 | MA44: 0 | MB44: 0 | MC44: 0 | MD44: 0 | ME44: 0 | MF44: 0 | MG44: 1200000 | MH44: 0 | MI44: 0 | MJ44: 0 | MK44: 0 | ML44: 0 | MM44: 0 | MN44: 0 | MO44: 0 | MP44: 0 | MQ44: 0 | MR44: 0 | MS44: 0 | MT44: 0 | MU44: 1500000 | MV44: 0
E46: Unearned revenue from sale of single game tickets | G46: USD | J46: {=_xlfn.SCAN( 0,_xlfn.ANCHORARRAY( J43) -_xlfn.ANCHORARRAY( J44), _xleta.SUM )} -> 0 | K46: 0 | L46: 0 | M46: 0 | N46: 0 | O46: 0 | P46: 0 | Q46: 0 | R46: 0 | S46: 0 | T46: 0 | U46: 0 | V46: 0 | W46: 0 | X46: 0 | Y46: 0 | Z46: 0 | AA46: 0 | AB46: 0 | AC46: 0 | AD46: 0 | AE46: 0 | AF46: 0 | AG46: 0 | AH46: 0 | AI46: 0 | AJ46: 0 | AK46: 0 | AL46: 0 | AM46: 0 | AN46: 0 | AO46: 0 | AP46: 0 | AQ46: 0 | AR46: 0 | AS46: 0 | AT46: 0 | AU46: 0 | AV46: 0 | AW46: 0 | AX46: 0 | AY46: 0 | AZ46: 0 | BA46: 0 | BB46: 0 | BC46: 0 | BD46: 0 | BE46: 0 | BF46: 0 | BG46: 400000 | BH46: 752000 | BI46: 880000 | BJ46: 960000 | BK46: 1040000 | BL46: 1217500 | BM46: 0 | BN46: 250000 | BO46: 470000 | BP46: 550000 | BQ46: 600000 | BR46: 650000 | BS46: 800000 | BT46: 0 | BU46: 112500 | BV46: 211500 | BW46: 247500 | BX46: 270000 | BY46: 292500 | BZ46: 360000 | CA46: 0 | CB46: 400000 | CC46: 752000 | CD46: 880000 | CE46: 960000 | CF46: 1040000 | CG46: 1082500 | CH46: 0 | CI46: 112500 | CJ46: 211500 | CK46: 247500 | CL46: 270000 | CM46: 292500 | CN46: 360000 | CO46: 0 | CP46: 250000 | CQ46: 470000 | CR46: 550000 | CS46: 600000 | CT46: 650000 | CU46: 800000 | CV46: 0 | CW46: 112500 | CX46: 211500 | CY46: 247500 | CZ46: 270000 | DA46: 292500 | DB46: 360000 | DC46: 0 | DD46: 250000 | DE46: 470000 | DF46: 550000 | DG46: 600000 | DH46: 650000 | DI46: 800000 | DJ46: 0 | DK46: 250000 | DL46: 470000 | DM46: 550000 | DN46: 600000 | DO46: 650000 | DP46: 800000 | DQ46: 0 | DR46: 112500 | DS46: 211500 | DT46: 247500 | DU46: 270000 | DV46: 292500 | DW46: 360000 | DX46: 0 | DY46: 250000 | DZ46: 470000 | EA46: 550000 | EB46: 600000 | EC46: 650000 | ED46: 800000 | EE46: 0 | EF46: 112500 | EG46: 211500 | EH46: 247500 | EI46: 270000 | EJ46: 292500 | EK46: 360000 | EL46: 0 | EM46: 600000 | EN46: 1128000 | EO46: 1257000 | EP46: 1257000 | EQ46: 1257000 | ER46: 1257000 | ES46: 0 | ET46: 112500 | EU46: 211500 | EV46: 247500 | EW46: 270000 | EX46: 292500 | EY46: 360000 | EZ46: 0 | FA46: 250000 | FB46: 470000 | FC46: 550000 | FD46: 600000 | FE46: 650000 | FF46: 800000 | FG46: 0 | FH46: 250000 | FI46: 470000 | FJ46: 550000 | FK46: 600000 | FL46: 650000 | FM46: 800000 | FN46: 0 | FO46: 250000 | FP46: 470000 | FQ46: 550000 | FR46: 600000 | FS46: 650000 | FT46: 800000 | FU46: 0 | FV46: 112500 | FW46: 211500 | FX46: 247500 | FY46: 270000 | FZ46: 292500 | GA46: 360000 | GB46: 0 | GC46: 0 | GD46: 0 | GE46: 0 | GF46: 0 | GG46: 0 | GH46: 0 | GI46: 0 | GJ46: 0 | GK46: 0 | GL46: 0 | GM46: 0 | GN46: 0 | GO46: 0 | GP46: 0 | GQ46: 112500 | GR46: 211500 | GS46: 247500 | GT46: 270000 | GU46: 292500 | GV46: 360000 | GW46: 0 | GX46: 112500 | GY46: 211500 | GZ46: 247500 | HA46: 270000 | HB46: 292500 | HC46: 360000 | HD46: 0 | HE46: 400000 | HF46: 752000 | HG46: 880000 | HH46: 960000 | HI46: 1002500 | HJ46: 1002500 | HK46: 0 | HL46: 112500 | HM46: 211500 | HN46: 247500 | HO46: 270000 | HP46: 292500 | HQ46: 360000 | HR46: 0 | HS46: 600000 | HT46: 1128000 | HU46: 1200000 | HV46: 1200000 | HW46: 1200000 | HX46: 1200000 | HY46: 0 | HZ46: 250000 | IA46: 470000 | IB46: 550000 | IC46: 600000 | ID46: 650000 | IE46: 800000 | IF46: 0 | IG46: 250000 | IH46: 470000 | II46: 550000 | IJ46: 600000 | IK46: 650000 | IL46: 800000 | IM46: 0 | IN46: 250000 | IO46: 470000 | IP46: 550000 | IQ46: 600000 | IR46: 650000 | IS46: 800000 | IT46: 0 | IU46: 400000 | IV46: 752000 | IW46: 880000 | IX46: 960000 | IY46: 1000000 | IZ46: 1000000 | JA46: 0 | JB46: 112500 | JC46: 211500 | JD46: 247500 | JE46: 270000 | JF46: 292500 | JG46: 360000 | JH46: 0 | JI46: 250000 | JJ46: 470000 | JK46: 550000 | JL46: 600000 | JM46: 650000 | JN46: 800000 | JO46: 0 | JP46: 250000 | JQ46: 470000 | JR46: 550000 | JS46: 600000 | JT46: 650000 | JU46: 800000 | JV46: 0 | JW46: 400000 | JX46: 752000 | JY46: 880000 | JZ46: 960000 | KA46: 1000000 | KB46: 1000000 | KC46: 0 | KD46: 112500 | KE46: 211500 | KF46: 247500 | KG46: 270000 | KH46: 292500 | KI46: 360000 | KJ46: 0 | KK46: 250000 | KL46: 470000 | KM46: 550000 | KN46: 600000 | KO46: 650000 | KP46: 800000 | KQ46: 0 | KR46: 250000 | KS46: 470000 | KT46: 550000 | KU46: 600000 | KV46: 650000 | KW46: 800000 | KX46: 0 | KY46: 112500 | KZ46: 211500 | LA46: 247500 | LB46: 270000 | LC46: 292500 | LD46: 360000 | LE46: 0 | LF46: 112500 | LG46: 211500 | LH46: 247500 | LI46: 270000 | LJ46: 292500 | LK46: 360000 | LL46: 0 | LM46: 112500 | LN46: 211500 | LO46: 247500 | LP46: 270000 | LQ46: 292500 | LR46: 360000 | LS46: 0 | LT46: 400000 | LU46: 752000 | LV46: 880000 | LW46: 960000 | LX46: 1000000 | LY46: 1000000 | LZ46: 0 | MA46: 600000 | MB46: 1128000 | MC46: 1200000 | MD46: 1200000 | ME46: 1200000 | MF46: 1200000 | MG46: 0 | MH46: 0 | MI46: 0 | MJ46: 0 | MK46: 0 | ML46: 0 | MM46: 0 | MN46: 0 | MO46: 937500 | MP46: 1500000 | MQ46: 1500000 | MR46: 1500000 | MS46: 1500000 | MT46: 1500000 | MU46: 0 | MV46: 0
A49: End of schedule

Sheet CaseData
A1: Wichita Warblers Inc - Inputs and Assumptions
B3: Season Ticket Price | D3: ($) | E3: 750
B4: Stadium Capacity | D4: (# seats) | E4: 50000
B5: Spread season ticket sale | D5: [TRUE, FALSE] | E5: FALSE
B7: Season Ticket Sales By Week | F7: Game Dates & Importance | J7: Sales Timing For Single Game Tickets | M7: Game Assumptions By Importance
B8: Week ending | C8: Date sold | D8: Sales | F8: Date | G8: Importance | H8: Ticket availability | J8: Days to game | K8: % of demand | M8: Importance | N8: Base crowd | O8: Ticket price ($)
B9: 44009 | C9: =B9-6 -> 44003 | D9: 4800 | F9: 44058 | G9: 3 | H9: =Capacity - SUMIFS( tbl_SeasonTicketSale[Sales], tbl_SeasonTicketSale[Week ending], "<=" & tbl_GameDates[[#This Row],[Date]] ) -> 24350 | J9: 6 | K9: 0.25 | M9: 1 | N9: 15000 | O9: 30
B10: 44016 | C10: =B10-6 -> 44010 | D10: 3800 | F10: 44065 | G10: 2 | H10: =Capacity - SUMIFS( tbl_SeasonTicketSale[Sales], tbl_SeasonTicketSale[Week ending], "<=" & tbl_GameDates[[#This Row],[Date]] ) -> 22950 | J10: 5 | K10: 0.22 | M10: 2 | N10: 25000 | O10: 40
B11: 44023 | C11: =B11-6 -> 44017 | D11: 3400 | F11: 44072 | G11: 1 | H11: =Capacity - SUMIFS( tbl_SeasonTicketSale[Sales], tbl_SeasonTicketSale[Week ending], "<=" & tbl_GameDates[[#This Row],[Date]] ) -> 22150 | J11: 4 | K11: 0.08 | M11: 3 | N11: 32000 | O11: 50
B12: 44030 | C12: =B12-6 -> 44024 | D12: 2800 | F12: 44079 | G12: 3 | H12: =Capacity - SUMIFS( tbl_SeasonTicketSale[Sales], tbl_SeasonTicketSale[Week ending], "<=" & tbl_GameDates[[#This Row],[Date]] ) -> 21650 | J12: 3 | K12: 0.05 | M12: 4 | N12: 40000 | O12: 60
B13: 44037 | C13: =B13-6 -> 44031 | D13: 2700 | F13: 44086 | G13: 1 | H13: =Capacity - SUMIFS( tbl_SeasonTicketSale[Sales], tbl_SeasonTicketSale[Week ending], "<=" & tbl_GameDates[[#This Row],[Date]] ) -> 21450 | J13: 2 | K13: 0.05 | M13: 5 | N13: 50000 | O13: 75
B14: 44044 | C14: =B14-6 -> 44038 | D14: 2750 | F14: 44093 | G14: 2 | H14: =Capacity - SUMIFS( tbl_SeasonTicketSale[Sales], tbl_SeasonTicketSale[Week ending], "<=" & tbl_GameDates[[#This Row],[Date]] ) -> 21300 | J14: 1 | K14: 0.15
B15: 44051 | C15: =B15-6 -> 44045 | D15: 2600 | F15: 44100 | G15: 1 | H15: =Capacity - SUMIFS( tbl_SeasonTicketSale[Sales], tbl_SeasonTicketSale[Week ending], "<=" & tbl_GameDates[[#This Row],[Date]] ) -> 21250 | J15: 0 | K15: 0.2
B16: 44058 | C16: =B16-6 -> 44052 | D16: 2800 | F16: 44107 | G16: 2 | H16: =Capacity - SUMIFS( tbl_SeasonTicketSale[Sales], tbl_SeasonTicketSale[Week ending], "<=" & tbl_GameDates[[#This Row],[Date]] ) -> 21200 | J16: Total | K16: =SUM(K9:K15) -> 1
B17: 44065 | C17: =B17-6 -> 44059 | D17: 1400 | F17: 44114 | G17: 2 | H17: =Capacity - SUMIFS( tbl_SeasonTicketSale[Sales], tbl_SeasonTicketSale[Week ending], "<=" & tbl_GameDates[[#This Row],[Date]] ) -> 21150
B18: 44072 | C18: =B18-6 -> 44066 | D18: 800 | F18: 44121 | G18: 1 | H18: =Capacity - SUMIFS( tbl_SeasonTicketSale[Sales], tbl_SeasonTicketSale[Week ending], "<=" & tbl_GameDates[[#This Row],[Date]] ) -> 21100
B19: 44079 | C19: =B19-6 -> 44073 | D19: 500 | F19: 44128 | G19: 2 | H19: =Capacity - SUMIFS( tbl_SeasonTicketSale[Sales], tbl_SeasonTicketSale[Week ending], "<=" & tbl_GameDates[[#This Row],[Date]] ) -> 21050
B20: 44086 | C20: =B20-6 -> 44080 | D20: 200 | F20: 44135 | G20: 1 | H20: =Capacity - SUMIFS( tbl_SeasonTicketSale[Sales], tbl_SeasonTicketSale[Week ending], "<=" & tbl_GameDates[[#This Row],[Date]] ) -> 21000
B21: 44093 | C21: =B21-6 -> 44087 | D21: 150 | F21: 44142 | G21: 4 | H21: =Capacity - SUMIFS( tbl_SeasonTicketSale[Sales], tbl_SeasonTicketSale[Week ending], "<=" & tbl_GameDates[[#This Row],[Date]] ) -> 20950
B22: 44100 | C22: =B22-6 -> 44094 | D22: 50 | F22: 44149 | G22: 1 | H22: =Capacity - SUMIFS( tbl_SeasonTicketSale[Sales], tbl_SeasonTicketSale[Week ending], "<=" & tbl_GameDates[[#This Row],[Date]] ) -> 20900
B23: 44107 | C23: =B23-6 -> 44101 | D23: 50 | F23: 44156 | G23: 2 | H23: =Capacity - SUMIFS( tbl_SeasonTicketSale[Sales], tbl_SeasonTicketSale[Week ending], "<=" & tbl_GameDates[[#This Row],[Date]] ) -> 20850
B24: 44114 | C24: =B24-6 -> 44108 | D24: 50 | F24: 44163 | G24: 2 | H24: =Capacity - SUMIFS( tbl_SeasonTicketSale[Sales], tbl_SeasonTicketSale[Week ending], "<=" & tbl_GameDates[[#This Row],[Date]] ) -> 20800 | J24: Working Capital
B25: 44121 | C25: =B25-6 -> 44115 | D25: 50 | F25: 44170 | G25: 2 | H25: =Capacity - SUMIFS( tbl_SeasonTicketSale[Sales], tbl_SeasonTicketSale[Week ending], "<=" & tbl_GameDates[[#This Row],[Date]] ) -> 20750
B26: 44128 | C26: =B26-6 -> 44122 | D26: 50 | F26: 44177 | G26: 1 | H26: =Capacity - SUMIFS( tbl_SeasonTicketSale[Sales], tbl_SeasonTicketSale[Week ending], "<=" & tbl_GameDates[[#This Row],[Date]] ) -> 20500
B27: 44135 | C27: =B27-6 -> 44129 | D27: 50 | F27: 44198 | G27: 1 | H27: =Capacity - SUMIFS( tbl_SeasonTicketSale[Sales], tbl_SeasonTicketSale[Week ending], "<=" & tbl_GameDates[[#This Row],[Date]] ) -> 20150
B28: 44142 | C28: =B28-6 -> 44136 | D28: 50 | F28: 44205 | G28: 1 | H28: =Capacity - SUMIFS( tbl_SeasonTicketSale[Sales], tbl_SeasonTicketSale[Week ending], "<=" & tbl_GameDates[[#This Row],[Date]] ) -> 20100
B29: 44149 | C29: =B29-6 -> 44143 | D29: 50 | F29: 44212 | G29: 3 | H29: =Capacity - SUMIFS( tbl_SeasonTicketSale[Sales], tbl_SeasonTicketSale[Week ending], "<=" & tbl_GameDates[[#This Row],[Date]] ) -> 20050
B30: 44156 | C30: =B30-6 -> 44150 | D30: 50 | F30: 44219 | G30: 1 | H30: =Capacity - SUMIFS( tbl_SeasonTicketSale[Sales], tbl_SeasonTicketSale[Week ending], "<=" & tbl_GameDates[[#This Row],[Date]] ) -> 20000
B31: 44163 | C31: =B31-6 -> 44157 | D31: 50 | F31: 44226 | G31: 4 | H31: =Capacity - SUMIFS( tbl_SeasonTicketSale[Sales], tbl_SeasonTicketSale[Week ending], "<=" & tbl_GameDates[[#This Row],[Date]] ) -> 20000
B32: 44170 | C32: =B32-6 -> 44164 | D32: 50 | F32: 44233 | G32: 2 | H32: =Capacity - SUMIFS( tbl_SeasonTicketSale[Sales], tbl_SeasonTicketSale[Week ending], "<=" & tbl_GameDates[[#This Row],[Date]] ) -> 20000
B33: 44177 | C33: =B33-6 -> 44171 | D33: 250 | F33: 44240 | G33: 2 | H33: =Capacity - SUMIFS( tbl_SeasonTicketSale[Sales], tbl_SeasonTicketSale[Week ending], "<=" & tbl_GameDates[[#This Row],[Date]] ) -> 20000
B34: 44184 | C34: =B34-6 -> 44178 | D34: 250 | F34: 44247 | G34: 2 | H34: =Capacity - SUMIFS( tbl_SeasonTicketSale[Sales], tbl_SeasonTicketSale[Week ending], "<=" & tbl_GameDates[[#This Row],[Date]] ) -> 20000
B35: 44191 | C35: =B35-6 -> 44185 | D35: 50 | F35: 44254 | G35: 3 | H35: =Capacity - SUMIFS( tbl_SeasonTicketSale[Sales], tbl_SeasonTicketSale[Week ending], "<=" & tbl_GameDates[[#This Row],[Date]] ) -> 20000
B36: 44198 | C36: =B36-6 -> 44192 | D36: 50 | F36: 44261 | G36: 1 | H36: =Capacity - SUMIFS( tbl_SeasonTicketSale[Sales], tbl_SeasonTicketSale[Week ending], "<=" & tbl_GameDates[[#This Row],[Date]] ) -> 20000
... B39: 44219 | C39: =B39-6 -> 44213 | D39: 50 | F39: 44282 | G39: 3 | H39: =Capacity - SUMIFS( tbl_SeasonTicketSale[Sales], tbl_SeasonTicketSale[Week ending], "<=" & tbl_GameDates[[#This Row],[Date]] ) -> 20000
B40: Total | D40: =SUM(D9:D39) -> 30000 | F40: 44289 | G40: 1 | H40: =Capacity - SUMIFS( tbl_SeasonTicketSale[Sales], tbl_SeasonTicketSale[Week ending], "<=" & tbl_GameDates[[#This Row],[Date]] ) -> 20000
F41: 44296 | G41: 2 | H41: =Capacity - SUMIFS( tbl_SeasonTicketSale[Sales], tbl_SeasonTicketSale[Week ending], "<=" & tbl_GameDates[[#This Row],[Date]] ) -> 20000
F42: 44303 | G42: 2 | H42: =Capacity - SUMIFS( tbl_SeasonTicketSale[Sales], tbl_SeasonTicketSale[Week ending], "<=" & tbl_GameDates[[#This Row],[Date]] ) -> 20000
F43: 44310 | G43: 1 | H43: =Capacity - SUMIFS( tbl_SeasonTicketSale[Sales], tbl_SeasonTicketSale[Week ending], "<=" & tbl_GameDates[[#This Row],[Date]] ) -> 20000
F44: 44317 | G44: 1 | H44: =Capacity - SUMIFS( tbl_SeasonTicketSale[Sales], tbl_SeasonTicketSale[Week ending], "<=" & tbl_GameDates[[#This Row],[Date]] ) -> 20000
F45: 44324 | G45: 1 | H45: =Capacity - SUMIFS( tbl_SeasonTicketSale[Sales], tbl_SeasonTicketSale[Week ending], "<=" & tbl_GameDates[[#This Row],[Date]] ) -> 20000
F46: 44331 | G46: 3 | H46: =Capacity - SUMIFS( tbl_SeasonTicketSale[Sales], tbl_SeasonTicketSale[Week ending], "<=" & tbl_GameDates[[#This Row],[Date]] ) -> 20000
F47: 44338 | G47: 4 | H47: =Capacity - SUMIFS( tbl_SeasonTicketSale[Sales], tbl_SeasonTicketSale[Week ending], "<=" & tbl_GameDates[[#This Row],[Date]] ) -> 20000
F48: 44352 | G48: 5 | H48: =Capacity - SUMIFS( tbl_SeasonTicketSale[Sales], tbl_SeasonTicketSale[Week ending], "<=" & tbl_GameDates[[#This Row],[Date]] ) -> 20000
A51: Monthly Summary Table
C53: Season Tickets | G53: Single Game Tickets | L53: Total
B54: Month End | C54: Cash Received | D54: Revenue | E54: Unearned Revenue Balance | F54: # Of Tickets Sold | G54: Cash Received | H54: Revenue | I54: Unearned Revenue Balance | J54: # Of Tickets Sold | K54: Cash Received | L54: Revenue | M54: Unearned Revenue | N54: # Of Tickets Sold
B55: 44012 | C55: {=SUMIFS(_xlfn.ANCHORARRAY( Calculations!J24),_xlfn.ANCHORARRAY( Calculations!J13), CaseData!$B$55:$B$67 )} -> 6450000 | D55: {=SUMIFS(_xlfn.ANCHORARRAY( Calculations!J28),_xlfn.ANCHORARRAY( Calculations!J13), CaseData!B55:B67)} -> 0 | E55: {=_xlfn.XLOOKUP( $B$55:$B$67,_xlfn.ANCHORARRAY( Calculations!J11),_xlfn.ANCHORARRAY( Calculations!J30),, -1 )} -> 6450000 | F55: {=SUMIFS(_xlfn.ANCHORARRAY( Calculations!J22),_xlfn.ANCHORARRAY( Calculations!$J$13), CaseData!$B$55:$B$67)} -> 8600 | G55: {=SUMIFS(_xlfn.ANCHORARRAY( Calculations!J$43),_xlfn.ANCHORARRAY( Calculations!J$13), CaseData!$B$55:$B$67 )} -> 0 | H55: {=SUMIFS(_xlfn.ANCHORARRAY( Calculations!J44),_xlfn.ANCHORARRAY( Calculations!J13), CaseData!$B$55:$B$67 )} -> 0 | I55: {=_xlfn.XLOOKUP( $B$55:$B$67,_xlfn.ANCHORARRAY( Calculations!J11),_xlfn.ANCHORARRAY( Calculations!J46),, -1 )} -> 0 | J55: {=SUMIFS(_xlfn.ANCHORARRAY( Calculations!J41),_xlfn.ANCHORARRAY( Calculations!$J$13), CaseData!$B$55:$B$67)} -> 0 | K55: {=_xlfn.ANCHORARRAY( C55) +_xlfn.ANCHORARRAY( G55)} -> 6450000 | L55: {=_xlfn.ANCHORARRAY( D55) +_xlfn.ANCHORARRAY( H55)} -> 0 | M55: {=_xlfn.ANCHORARRAY( E55) +_xlfn.ANCHORARRAY( I55)} -> 6450000 | N55: {=_xlfn.ANCHORARRAY( F55) +_xlfn.ANCHORARRAY( J55)} -> 8600
B56: 44043 | C56: 8737500 | D56: 0 | E56: 15187500 | F56: 11650 | G56: 0 | H56: 0 | I56: 0 | J56: 0 | K56: 8737500 | L56: 0 | M56: 15187500 | N56: 11650
B57: 44074 | C57: 6075000 | D57: 1594687.5 | E57: 19667812 | F57: 8100 | G57: 3337500 | H57: 2585500 | I57: 752000 | J57: 77340 | K57: 9412500 | L57: 4180187.5 | M57: 20419812 | N57: 85440
B58: 44104 | C58: 337500 | D58: 2185312.5 | E58: 17820000 | F58: 450 | G58: 2682500 | H58: 2834500 | I58: 600000 | J58: 72910 | K58: 3020000 | L58: 5019812.5 | M58: 18420000 | N58: 73360
B59: 44135 | C59: 150000 | D59: 2745000 | E59: 15225000 | F59: 200 | G59: 2836000 | H59: 3436000 | I59: 0 | J59: 78400 | K59: 2986000 | L59: 6181000 | M59: 15225000 | N59: 78600
B60: 44165 | C60: 187500 | D60: 2250000 | E60: 13162500 | F60: 250 | G60: 3843000 | H60: 3373000 | I60: 470000 | J60: 89350 | K60: 4030500 | L60: 5623000 | M60: 13632500 | N60: 89600
B61: 44196 | C61: 450000 | D61: 1299375 | E61: 12313125 | F61: 600 | G61: 1102500 | H61: 1280000 | I61: 292500 | J61: 33750 | K61: 1552500 | L61: 2579375 | M61: 12605625 | N61: 34350
B62: 44227 | C62: 112500 | D62: 2863125 | E62: 9562500 | F62: 150 | G62: 3510000 | H62: 3552500 | I62: 250000 | J62: 81550 | K62: 3622500 | L62: 6415625 | M62: 9812500 | N62: 81700
B63: 44255 | C63: 0 | D63: 2250000 | E63: 7312500 | F63: 0 | G63: 3262500 | H63: 3400000 | I63: 112500 | J63: 77500 | K63: 3262500 | L63: 5650000 | M63: 7425000 | N63: 77500
B64: 44286 | C64: 0 | D64: 2250000 | E64: 5062500 | F64: 0 | G64: 3207500 | H64: 3050000 | I64: 270000 | J64: 80250 | K64: 3207500 | L64: 5300000 | M64: 5332500 | N64: 80250
B65: 44316 | C65: 0 | D65: 2250000 | E65: 2812500 | F65: 0 | G65: 2590000 | H65: 2500000 | I65: 360000 | J65: 73000 | K65: 2590000 | L65: 4750000 | M65: 3172500 | N65: 73000
B66: 44347 | C66: 0 | D66: 2250000 | E66: 562500 | F66: 0 | G66: 4240000 | H66: 3100000 | I66: 1500000 | J66: 78000 | K66: 4240000 | L66: 5350000 | M66: 2062500 | N66: 78000
B67: 44377 | C67: 0 | D67: 562500 | E67: 0 | F67: 0 | G67: 0 | H67: 1500000 | I67: 0 | J67: 0 | K67: 0 | L67: 2062500 | M67: 0 | N67: 0
C68: =SUM(_xlfn.ANCHORARRAY(C55)) -> 22500000 | D68: =SUM(_xlfn.ANCHORARRAY(D55)) -> 22500000 | F68: =SUM(_xlfn.ANCHORARRAY(F55)) -> 30000 | G68: =SUM(_xlfn.ANCHORARRAY(G55)) -> 30611500 | H68: =SUM(_xlfn.ANCHORARRAY(H55)) -> 30611500 | K68: =SUM(_xlfn.ANCHORARRAY(K55)) -> 53111500 | L68: =SUM(_xlfn.ANCHORARRAY(L55)) -> 53111500
A70: Game Summary Table
C71: Revenue | F71: # Of Tickets Sold | J71: # of Single Game Tickets Sold by Days to Game
B72: Game Date | C72: Season Tickets | D72: Single Game Tickets | E72: Total | F72: Season Tickets | G72: Single Game Tickets | H72: Total | I72: 6 | J72: 5 | K72: 4 | L72: 3 | M72: 2 | N72: 1 | O72: 0 | P72: Total
B73: =F9 -> 44058 | C73: {=SUMIFS(_xlfn.ANCHORARRAY( Calculations!J28),_xlfn.ANCHORARRAY( Calculations!J14), CaseData!$B$73:$B$112 )} -> 480937.5 | D73: {=SUMIFS(_xlfn.ANCHORARRAY( Calculations!J44),_xlfn.ANCHORARRAY( Calculations!J14), CaseData!$B$73:$B$112 )} -> 1217500 | E73: {=_xlfn.ANCHORARRAY( C73) +_xlfn.ANCHORARRAY( D73)} -> 1698437.5 | F73: {=SUMIFS(_xlfn.ANCHORARRAY( Calculations!J22),_xlfn.ANCHORARRAY( Calculations!J14), "<=" & CaseData!$B$73:$B$112 )} -> 25650 | G73: {=SUMIFS(_xlfn.ANCHORARRAY( Calculations!J41),_xlfn.ANCHORARRAY( Calculations!J14), CaseData!$B$73:$B$112 )} -> 24350 | H73: {=_xlfn.ANCHORARRAY( F73) +_xlfn.ANCHORARRAY( G73)} -> 50000 | I73: {=SUMIFS(_xlfn.ANCHORARRAY( Calculations!J41),_xlfn.ANCHORARRAY( Calculations!J14), CaseData!$B$73:$B$112,_xlfn.ANCHORARRAY( Calculations!J15), CaseData!$I$72:$O$72 )} -> 8000 | J73: 7040 | K73: 2560 | L73: 1600 | M73: 1600 | N73: 3550 | O73: 0 | P73: {=_xlfn.BYROW(_xlfn.ANCHORARRAY( I73), _xleta.SUM )} -> 24350
B74: =F10 -> 44065 | C74: 533437.5 | D74: 918000 | E74: 1451437.5 | F74: 27050 | G74: 22950 | H74: 50000 | I74: 6250 | J74: 5500 | K74: 2000 | L74: 1250 | M74: 1250 | N74: 3750 | O74: 2950 | P74: 22950
B75: =F11 -> 44072 | C75: 552187.5 | D75: 450000 | E75: 1002187.5 | F75: 27850 | G75: 15000 | H75: 42850 | I75: 3750 | J75: 3300 | K75: 1200 | L75: 750 | M75: 750 | N75: 2250 | O75: 3000 | P75: 15000
B76: =F12 -> 44079 | C76: 559687.5 | D76: 1082500 | E76: 1642187.5 | F76: 28350 | G76: 21650 | H76: 50000 | I76: 8000 | J76: 7040 | K76: 2560 | L76: 1600 | M76: 1600 | N76: 850 | O76: 0 | P76: 21650
B77: =F13 -> 44086 | C77: 550312.5 | D77: 450000 | E77: 1000312.5 | F77: 28550 | G77: 15000 | H77: 43550 | I77: 3750 | J77: 3300 | K77: 1200 | L77: 750 | M77: 750 | N77: 2250 | O77: 3000 | P77: 15000
B78: =F14 -> 44093 | C78: 552187.5 | D78: 852000 | E78: 1404187.5 | F78: 28700 | G78: 21300 | H78: 50000 | I78: 6250 | J78: 5500 | K78: 2000 | L78: 1250 | M78: 1250 | N78: 3750 | O78: 1300 | P78: 21300
B79: =F15 -> 44100 | C79: 544687.5 | D79: 450000 | E79: 994687.5 | F79: 28750 | G79: 15000 | H79: 43750 | I79: 3750 | J79: 3300 | K79: 1200 | L79: 750 | M79: 750 | N79: 2250 | O79: 3000 | P79: 15000
B80: =F16 -> 44107 | C80: 546562.5 | D80: 848000 | E80: 1394562.5 | F80: 28800 | G80: 21200 | H80: 50000 | I80: 6250 | J80: 5500 | K80: 2000 | L80: 1250 | M80: 1250 | N80: 3750 | O80: 1200 | P80: 21200
B81: =F17 -> 44114 | C81: 548437.5 | D81: 846000 | E81: 1394437.5 | F81: 28850 | G81: 21150 | H81: 50000 | I81: 6250 | J81: 5500 | K81: 2000 | L81: 1250 | M81: 1250 | N81: 3750 | O81: 1150 | P81: 21150
B82: =F18 -> 44121 | C82: 550312.5 | D82: 450000 | E82: 1000312.5 | F82: 28900 | G82: 15000 | H82: 43900 | I82: 3750 | J82: 3300 | K82: 1200 | L82: 750 | M82: 750 | N82: 2250 | O82: 3000 | P82: 15000
B83: =F19 -> 44128 | C83: 552187.5 | D83: 842000 | E83: 1394187.5 | F83: 28950 | G83: 21050 | H83: 50000 | I83: 6250 | J83: 5500 | K83: 2000 | L83: 1250 | M83: 1250 | N83: 3750 | O83: 1050 | P83: 21050
B84: =F20 -> 44135 | C84: 554062.5 | D84: 450000 | E84: 1004062.5 | F84: 29000 | G84: 15000 | H84: 44000 | I84: 3750 | J84: 3300 | K84: 1200 | L84: 750 | M84: 750 | N84: 2250 | O84: 3000 | P84: 15000
B85: =F21 -> 44142 | C85: 555937.5 | D85: 1257000 | E85: 1812937.5 | F85: 29050 | G85: 20950 | H85: 50000 | I85: 10000 | J85: 8800 | K85: 2150 | L85: 0 | M85: 0 | N85: 0 | O85: 0 | P85: 20950
... B112: =F48 -> 44352 | C112: 562500 | D112: 1500000 | E112: 2062500 | F112: 30000 | G112: 20000 | H112: 50000 | I112: 12500 | J112: 7500 | K112: 0 | L112: 0 | M112: 0 | N112: 0 | O112: 0 | P112: 20000

Sheet CaseSolution (Original)
A1: Wichita Warblers Inc - Inputs and Assumptions
B3: Season Ticket Price | D3: ($) | E3: 750
B4: Stadium Capacity | D4: (# seats) | E4: 50000
B6: Season Ticket Sales By Week | F6: Game Dates & Importance | I6: Sales Timing For Single Game Tickets | L6: Game Assumptions By Importance
B7: Week ending | C7: Week start | D7: Sales | F7: Date | G7: Importance | I7: Days to game | J7: % of demand | L7: Importance | M7: Base crowd | N7: Ticket price ($)
B8: 44009 | C8: =B8-6 -> 44003 | D8: 4800 | F8: 44058 | G8: 3 | I8: 6 | J8: 0.25 | L8: 1 | M8: 15000 | N8: 30
B9: 44016 | C9: =B9-6 -> 44010 | D9: 3800 | F9: 44065 | G9: 2 | I9: 5 | J9: 0.22 | L9: 2 | M9: 25000 | N9: 40
B10: 44023 | C10: =B10-6 -> 44017 | D10: 3400 | F10: 44072 | G10: 1 | I10: 4 | J10: 0.08 | L10: 3 | M10: 32000 | N10: 50
B11: 44030 | C11: =B11-6 -> 44024 | D11: 2800 | F11: 44079 | G11: 3 | I11: 3 | J11: 0.05 | L11: 4 | M11: 40000 | N11: 60
B12: 44037 | C12: =B12-6 -> 44031 | D12: 2700 | F12: 44086 | G12: 1 | I12: 2 | J12: 0.05 | L12: 5 | M12: 50000 | N12: 75
B13: 44044 | C13: =B13-6 -> 44038 | D13: 2750 | F13: 44093 | G13: 2 | I13: 1 | J13: 0.15
B14: 44051 | C14: =B14-6 -> 44045 | D14: 2600 | F14: 44100 | G14: 1 | I14: 0 | J14: 0.2
B15: 44058 | C15: =B15-6 -> 44052 | D15: 2800 | F15: 44107 | G15: 2 | I15: Total | J15: =SUM(J8:J14) -> 1
B16: 44065 | C16: =B16-6 -> 44059 | D16: 1400 | F16: 44114 | G16: 2
B17: 44072 | C17: =B17-6 -> 44066 | D17: 800 | F17: 44121 | G17: 1
B18: 44079 | C18: =B18-6 -> 44073 | D18: 500 | F18: 44128 | G18: 2
B19: 44086 | C19: =B19-6 -> 44080 | D19: 200 | F19: 44135 | G19: 1
B20: 44093 | C20: =B20-6 -> 44087 | D20: 150 | F20: 44142 | G20: 4
B21: 44100 | C21: =B21-6 -> 44094 | D21: 50 | F21: 44149 | G21: 1
B22: 44107 | C22: =B22-6 -> 44101 | D22: 50 | F22: 44156 | G22: 2
B23: 44114 | C23: =B23-6 -> 44108 | D23: 50 | F23: 44163 | G23: 2
B24: 44121 | C24: =B24-6 -> 44115 | D24: 50 | F24: 44170 | G24: 2
B25: 44128 | C25: =B25-6 -> 44122 | D25: 50 | F25: 44177 | G25: 1
B26: 44135 | C26: =B26-6 -> 44129 | D26: 50 | F26: 44198 | G26: 1
B27: 44142 | C27: =B27-6 -> 44136 | D27: 50 | F27: 44205 | G27: 1
... B38: 44219 | C38: =B38-6 -> 44213 | D38: 50 | F38: 44282 | G38: 3
B39: Total | D39: =SUM(D8:D38) -> 30000 | F39: 44289 | G39: 1
F40: 44296 | G40: 2
F41: 44303 | G41: 2
F42: 44310 | G42: 1
F43: 44317 | G43: 1
F44: 44324 | G44: 1
F45: 44331 | G45: 3
F46: 44338 | G46: 4
F47: 44352 | G47: 5
F48: Total Games | G48: =COUNT(G8:G47) -> 40
A51: Monthly Summary Table
C53: Season Tickets | G53: Single Game Tickets | K53: Total
B54: Month End | C54: Cash Received | D54: Revenue | E54: Unearned Revenue Balance | F54: # Of Tickets Sold | G54: Cash Received | H54: Revenue | I54: Unearned Revenue Balance | J54: # Of Tickets Sold | K54: Cash Received | L54: Revenue | M54: Unearned Revenue | N54: # Of Tickets Sold
B55: 44012 | C55: =G183 -> 6450000 | D55: =K183 -> 0 | E55: =SUM(C$55:C55)-SUM(D$55:D55) -> 6450000 | F55: =F183 -> 8600 | G55: =D304 -> 0 | H55: =E304 -> 0 | I55: =SUM(G$55:G55)-SUM(H$55:H55) -> 0 | J55: =C304 -> 0 | K55: =G55+C55 -> 6450000 | L55: =H55+D55 -> 0 | M55: =I55+E55 -> 6450000 | N55: =F55+J55 -> 8600
B56: 44043 | C56: =G184 -> 8737500 | D56: =K184 -> 0 | E56: =SUM(C$55:C56)-SUM(D$55:D56) -> 15187500 | F56: =F184 -> 11650 | G56: =D305 -> 0 | H56: =E305 -> 0 | I56: =SUM(G$55:G56)-SUM(H$55:H56) -> 0 | J56: =C305 -> 0 | K56: =G56+C56 -> 8737500 | L56: =H56+D56 -> 0 | M56: =I56+E56 -> 15187500 | N56: =F56+J56 -> 11650
B57: 44074 | C57: =G185 -> 6075000 | D57: =K185 -> 1594687.5 | E57: =SUM(C$55:C57)-SUM(D$55:D57) -> 19667812 | F57: =F185 -> 8100 | G57: =D306 -> 3337500 | H57: =E306 -> 2585500 | I57: =SUM(G$55:G57)-SUM(H$55:H57) -> 752000 | J57: =C306 -> 77340 | K57: =G57+C57 -> 9412500 | L57: =H57+D57 -> 4180187.5 | M57: =I57+E57 -> 20419812 | N57: =F57+J57 -> 85440
B58: 44104 | C58: =G186 -> 337500 | D58: =K186 -> 2185312.5 | E58: =SUM(C$55:C58)-SUM(D$55:D58) -> 17820000 | F58: =F186 -> 450 | G58: =D307 -> 2682500 | H58: =E307 -> 2834500 | I58: =SUM(G$55:G58)-SUM(H$55:H58) -> 600000 | J58: =C307 -> 72910 | K58: =G58+C58 -> 3020000 | L58: =H58+D58 -> 5019812.5 | M58: =I58+E58 -> 18420000 | N58: =F58+J58 -> 73360
B59: 44135 | C59: =G187 -> 150000 | D59: =K187 -> 2745000 | E59: =SUM(C$55:C59)-SUM(D$55:D59) -> 15225000 | F59: =F187 -> 200 | G59: =D308 -> 2836000 | H59: =E308 -> 3436000 | I59: =SUM(G$55:G59)-SUM(H$55:H59) -> 0 | J59: =C308 -> 78400 | K59: =G59+C59 -> 2986000 | L59: =H59+D59 -> 6181000 | M59: =I59+E59 -> 15225000 | N59: =F59+J59 -> 78600
B60: 44165 | C60: =G188 -> 187500 | D60: =K188 -> 2250000 | E60: =SUM(C$55:C60)-SUM(D$55:D60) -> 13162500 | F60: =F188 -> 250 | G60: =D309 -> 3843000 | H60: =E309 -> 3373000 | I60: =SUM(G$55:G60)-SUM(H$55:H60) -> 470000 | J60: =C309 -> 89350 | K60: =G60+C60 -> 4030500 | L60: =H60+D60 -> 5623000 | M60: =I60+E60 -> 13632500 | N60: =F60+J60 -> 89600
B61: 44196 | C61: =G189 -> 450000 | D61: =K189 -> 1299375 | E61: =SUM(C$55:C61)-SUM(D$55:D61) -> 12313125 | F61: =F189 -> 600 | G61: =D310 -> 1102500 | H61: =E310 -> 1280000 | I61: =SUM(G$55:G61)-SUM(H$55:H61) -> 292500 | J61: =C310 -> 33750 | K61: =G61+C61 -> 1552500 | L61: =H61+D61 -> 2579375 | M61: =I61+E61 -> 12605625 | N61: =F61+J61 -> 34350
B62: 44227 | C62: =G190 -> 112500 | D62: =K190 -> 2863125 | E62: =SUM(C$55:C62)-SUM(D$55:D62) -> 9562500 | F62: =F190 -> 150 | G62: =D311 -> 3510000 | H62: =E311 -> 3552500 | I62: =SUM(G$55:G62)-SUM(H$55:H62) -> 250000 | J62: =C311 -> 81550 | K62: =G62+C62 -> 3622500 | L62: =H62+D62 -> 6415625 | M62: =I62+E62 -> 9812500 | N62: =F62+J62 -> 81700
B63: 44255 | C63: =G191 -> 0 | D63: =K191 -> 2250000 | E63: =SUM(C$55:C63)-SUM(D$55:D63) -> 7312500 | F63: =F191 -> 0 | G63: =D312 -> 3262500 | H63: =E312 -> 3400000 | I63: =SUM(G$55:G63)-SUM(H$55:H63) -> 112500 | J63: =C312 -> 77500 | K63: =G63+C63 -> 3262500 | L63: =H63+D63 -> 5650000 | M63: =I63+E63 -> 7425000 | N63: =F63+J63 -> 77500
B64: 44286 | C64: =G192 -> 0 | D64: =K192 -> 2250000 | E64: =SUM(C$55:C64)-SUM(D$55:D64) -> 5062500 | F64: =F192 -> 0 | G64: =D313 -> 3207500 | H64: =E313 -> 3050000 | I64: =SUM(G$55:G64)-SUM(H$55:H64) -> 270000 | J64: =C313 -> 80250 | K64: =G64+C64 -> 3207500 | L64: =H64+D64 -> 5300000 | M64: =I64+E64 -> 5332500 | N64: =F64+J64 -> 80250
B65: 44316 | C65: =G193 -> 0 | D65: =K193 -> 2250000 | E65: =SUM(C$55:C65)-SUM(D$55:D65) -> 2812500 | F65: =F193 -> 0 | G65: =D314 -> 2590000 | H65: =E314 -> 2500000 | I65: =SUM(G$55:G65)-SUM(H$55:H65) -> 360000 | J65: =C314 -> 73000 | K65: =G65+C65 -> 2590000 | L65: =H65+D65 -> 4750000 | M65: =I65+E65 -> 3172500 | N65: =F65+J65 -> 73000
B66: 44347 | C66: =G194 -> 0 | D66: =K194 -> 2250000 | E66: =SUM(C$55:C66)-SUM(D$55:D66) -> 562500 | F66: =F194 -> 0 | G66: =D315 -> 4240000 | H66: =E315 -> 3100000 | I66: =SUM(G$55:G66)-SUM(H$55:H66) -> 1500000 | J66: =C315 -> 78000 | K66: =G66+C66 -> 4240000 | L66: =H66+D66 -> 5350000 | M66: =I66+E66 -> 2062500 | N66: =F66+J66 -> 78000
B67: 44377 | C67: =G195 -> 0 | D67: =K195 -> 562500 | E67: =SUM(C$55:C67)-SUM(D$55:D67) -> 0 | F67: =F195 -> 0 | G67: =D316 -> 0 | H67: =E316 -> 1500000 | I67: =SUM(G$55:G67)-SUM(H$55:H67) -> 0 | J67: =C316 -> 0 | K67: =G67+C67 -> 0 | L67: =H67+D67 -> 2062500 | M67: =I67+E67 -> 0 | N67: =F67+J67 -> 0
C68: =SUM(C55:C67) -> 22500000 | D68: =SUM(D55:D67) -> 22500000 | F68: =SUM(F55:F67) -> 30000 | G68: =SUM(G55:G67) -> 30611500 | H68: =SUM(H55:H67) -> 30611500 | K68: =SUM(K55:K67) -> 53111500 | L68: =SUM(L55:L67) -> 53111500 | N68: =SUM(N55:N67) -> 772050
A71: Game Summary Table
C73: Revenue | F73: # Of Tickets Sold | I73: # of Single Game Tickets Sold by Days to Game
B74: Game Date | C74: Season Tickets | D74: Single Game Tickets | E74: Total | F74: Season Tickets | G74: Single Game Tickets | H74: Total | I74: 6 | J74: 5 | K74: 4 | L74: 3 | M74: 2 | N74: 1 | O74: 0 | P74: Total | Q74: Check
B75: =F8 -> 44058 | C75: =SUMIF($B$125:$B$174,"<="&B75,$J$125:$J$174) -> 480937.5 | D75: =Y206 -> 1217500 | E75: =SUM(C75:D75) -> 1698437.5 | F75: =F206 -> 25650 | G75: =H206 -> 24350 | H75: =SUM(F75:G75) -> 50000 | I75: =P206 -> 8000 | J75: =Q206 -> 7040 | K75: =R206 -> 2560 | L75: =S206 -> 1600 | M75: =T206 -> 1600 | N75: =U206 -> 3550 | O75: =V206 -> 0 | P75: =SUM(I75:O75) -> 24350 | Q75: =P75=G75 -> TRUE
B76: =F9 -> 44065 | C76: =SUMIFS($J$125:$J$174,$B$125:$B$174,"<="&B76,$B$125:$B$174,">"&B75) -> 533437.5 | D76: =Y207 -> 918000 | E76: =SUM(C76:D76) -> 1451437.5 | F76: =F207 -> 27050 | G76: =H207 -> 22950 | H76: =SUM(F76:G76) -> 50000 | I76: =P207 -> 6250 | J76: =Q207 -> 5500 | K76: =R207 -> 2000 | L76: =S207 -> 1250 | M76: =T207 -> 1250 | N76: =U207 -> 3750 | O76: =V207 -> 2950 | P76: =SUM(I76:O76) -> 22950 | Q76: =P76=G76 -> TRUE
B77: =F10 -> 44072 | C77: =SUMIFS($J$125:$J$174,$B$125:$B$174,"<="&B77,$B$125:$B$174,">"&B76) -> 552187.5 | D77: =Y208 -> 450000 | E77: =SUM(C77:D77) -> 1002187.5 | F77: =F208 -> 27850 | G77: =H208 -> 15000 | H77: =SUM(F77:G77) -> 42850 | I77: =P208 -> 3750 | J77: =Q208 -> 3300 | K77: =R208 -> 1200 | L77: =S208 -> 750 | M77: =T208 -> 750 | N77: =U208 -> 2250 | O77: =V208 -> 3000 | P77: =SUM(I77:O77) -> 15000 | Q77: =P77=G77 -> TRUE
B78: =F11 -> 44079 | C78: =SUMIFS($J$125:$J$174,$B$125:$B$174,"<="&B78,$B$125:$B$174,">"&B77) -> 559687.5 | D78: =Y209 -> 1082500 | E78: =SUM(C78:D78) -> 1642187.5 | F78: =F209 -> 28350 | G78: =H209 -> 21650 | H78: =SUM(F78:G78) -> 50000 | I78: =P209 -> 8000 | J78: =Q209 -> 7040 | K78: =R209 -> 2560 | L78: =S209 -> 1600 | M78: =T209 -> 1600 | N78: =U209 -> 850 | O78: =V209 -> 0 | P78: =SUM(I78:O78) -> 21650 | Q78: =P78=G78 -> TRUE
B79: =F12 -> 44086 | C79: =SUMIFS($J$125:$J$174,$B$125:$B$174,"<="&B79,$B$125:$B$174,">"&B78) -> 550312.5 | D79: =Y210 -> 450000 | E79: =SUM(C79:D79) -> 1000312.5 | F79: =F210 -> 28550 | G79: =H210 -> 15000 | H79: =SUM(F79:G79) -> 43550 | I79: =P210 -> 3750 | J79: =Q210 -> 3300 | K79: =R210 -> 1200 | L79: =S210 -> 750 | M79: =T210 -> 750 | N79: =U210 -> 2250 | O79: =V210 -> 3000 | P79: =SUM(I79:O79) -> 15000 | Q79: =P79=G79 -> TRUE
B80: =F13 -> 44093 | C80: =SUMIFS($J$125:$J$174,$B$125:$B$174,"<="&B80,$B$125:$B$174,">"&B79) -> 552187.5 | D80: =Y211 -> 852000 | E80: =SUM(C80:D80) -> 1404187.5 | F80: =F211 -> 28700 | G80: =H211 -> 21300 | H80: =SUM(F80:G80) -> 50000 | I80: =P211 -> 6250 | J80: =Q211 -> 5500 | K80: =R211 -> 2000 | L80: =S211 -> 1250 | M80: =T211 -> 1250 | N80: =U211 -> 3750 | O80: =V211 -> 1300 | P80: =SUM(I80:O80) -> 21300 | Q80: =P80=G80 -> TRUE
B81: =F14 -> 44100 | C81: =SUMIFS($J$125:$J$174,$B$125:$B$174,"<="&B81,$B$125:$B$174,">"&B80) -> 544687.5 | D81: =Y212 -> 450000 | E81: =SUM(C81:D81) -> 994687.5 | F81: =F212 -> 28750 | G81: =H212 -> 15000 | H81: =SUM(F81:G81) -> 43750 | I81: =P212 -> 3750 | J81: =Q212 -> 3300 | K81: =R212 -> 1200 | L81: =S212 -> 750 | M81: =T212 -> 750 | N81: =U212 -> 2250 | O81: =V212 -> 3000 | P81: =SUM(I81:O81) -> 15000 | Q81: =P81=G81 -> TRUE
B82: =F15 -> 44107 | C82: =SUMIFS($J$125:$J$174,$B$125:$B$174,"<="&B82,$B$125:$B$174,">"&B81) -> 546562.5 | D82: =Y213 -> 848000 | E82: =SUM(C82:D82) -> 1394562.5 | F82: =F213 -> 28800 | G82: =H213 -> 21200 | H82: =SUM(F82:G82) -> 50000 | I82: =P213 -> 6250 | J82: =Q213 -> 5500 | K82: =R213 -> 2000 | L82: =S213 -> 1250 | M82: =T213 -> 1250 | N82: =U213 -> 3750 | O82: =V213 -> 1200 | P82: =SUM(I82:O82) -> 21200 | Q82: =P82=G82 -> TRUE
B83: =F16 -> 44114 | C83: =SUMIFS($J$125:$J$174,$B$125:$B$174,"<="&B83,$B$125:$B$174,">"&B82) -> 548437.5 | D83: =Y214 -> 846000 | E83: =SUM(C83:D83) -> 1394437.5 | F83: =F214 -> 28850 | G83: =H214 -> 21150 | H83: =SUM(F83:G83) -> 50000 | I83: =P214 -> 6250 | J83: =Q214 -> 5500 | K83: =R214 -> 2000 | L83: =S214 -> 1250 | M83: =T214 -> 1250 | N83: =U214 -> 3750 | O83: =V214 -> 1150 | P83: =SUM(I83:O83) -> 21150 | Q83: =P83=G83 -> TRUE
B84: =F17 -> 44121 | C84: =SUMIFS($J$125:$J$174,$B$125:$B$174,"<="&B84,$B$125:$B$174,">"&B83) -> 550312.5 | D84: =Y215 -> 450000 | E84: =SUM(C84:D84) -> 1000312.5 | F84: =F215 -> 28900 | G84: =H215 -> 15000 | H84: =SUM(F84:G84) -> 43900 | I84: =P215 -> 3750 | J84: =Q215 -> 3300 | K84: =R215 -> 1200 | L84: =S215 -> 750 | M84: =T215 -> 750 | N84: =U215 -> 2250 | O84: =V215 -> 3000 | P84: =SUM(I84:O84) -> 15000 | Q84: =P84=G84 -> TRUE
B85: =F18 -> 44128 | C85: =SUMIFS($J$125:$J$174,$B$125:$B$174,"<="&B85,$B$125:$B$174,">"&B84) -> 552187.5 | D85: =Y216 -> 842000 | E85: =SUM(C85:D85) -> 1394187.5 | F85: =F216 -> 28950 | G85: =H216 -> 21050 | H85: =SUM(F85:G85) -> 50000 | I85: =P216 -> 6250 | J85: =Q216 -> 5500 | K85: =R216 -> 2000 | L85: =S216 -> 1250 | M85: =T216 -> 1250 | N85: =U216 -> 3750 | O85: =V216 -> 1050 | P85: =SUM(I85:O85) -> 21050 | Q85: =P85=G85 -> TRUE
B86: =F19 -> 44135 | C86: =SUMIFS($J$125:$J$174,$B$125:$B$174,"<="&B86,$B$125:$B$174,">"&B85) -> 554062.5 | D86: =Y217 -> 450000 | E86: =SUM(C86:D86) -> 1004062.5 | F86: =F217 -> 29000 | G86: =H217 -> 15000 | H86: =SUM(F86:G86) -> 44000 | I86: =P217 -> 3750 | J86: =Q217 -> 3300 | K86: =R217 -> 1200 | L86: =S217 -> 750 | M86: =T217 -> 750 | N86: =U217 -> 2250 | O86: =V217 -> 3000 | P86: =SUM(I86:O86) -> 15000 | Q86: =P86=G86 -> TRUE
B87: =F20 -> 44142 | C87: =SUMIFS($J$125:$J$174,$B$125:$B$174,"<="&B87,$B$125:$B$174,">"&B86) -> 555937.5 | D87: =Y218 -> 1257000 | E87: =SUM(C87:D87) -> 1812937.5 | F87: =F218 -> 29050 | G87: =H218 -> 20950 | H87: =SUM(F87:G87) -> 50000 | I87: =P218 -> 10000 | J87: =Q218 -> 8800 | K87: =R218 -> 2150 | L87: =S218 -> 0 | M87: =T218 -> 0 | N87: =U218 -> 0 | O87: =V218 -> 0 | P87: =SUM(I87:O87) -> 20950 | Q87: =P87=G87 -> TRUE
... B114: =F47 -> 44352 | C114: =SUMIFS($J$125:$J$174,$B$125:$B$174,"<="&B114,$B$125:$B$174,">"&B113) -> 562500 | D114: =Y245 -> 1500000 | E114: =SUM(C114:D114) -> 2062500 | F114: =F245 -> 30000 | G114: =H245 -> 20000 | H114: =SUM(F114:G114) -> 50000 | I114: =P245 -> 12500 | J114: =Q245 -> 7500 | K114: =R245 -> 0 | L114: =S245 -> 0 | M114: =T245 -> 0 | N114: =U245 -> 0 | O114: =V245 -> 0 | P114: =SUM(I114:O114) -> 20000 | Q114: =P114=G114 -> TRUE
C115: =SUM(C75:C114) -> 22500000 | D115: =SUM(D75:D114) -> 30611500 | E115: =SUM(E75:E114) -> 53111500
A117: Season Ticket Data
B119: Total Home Games | D119: =homeGames -> 40
B120: Season Ticket Price ($) | D120: =soldPrice -> 750
A122: Weekly Data
B124: Week ending | C124: Date Sold | D124: # Of Tickets Sold | E124: Cash Received | F124: Cumul Cash Received | G124: Home Games Played | H124: % Home Games Played | I124: Cumul Revenue | J124: Revenue | K124: Unearned Revenue Balance | L124: Cumul # Tickets Sold | M124: Month End | O124: Cumul Revenue New Tickets | P124: Cumul Revenue Old Tickets | Q124: Cumul Revenue Recognized | R124: Check
B125: =B8 -> 44009 | C125: =C8 -> 44003 | D125: =D8 -> 4800 | E125: =D125*$D$120 -> 3600000 | F125: =SUM($E$125:$E125) -> 3600000 | G125: =COUNTIF($F$8:$F$47,"<="&B125) -> 0 | H125: =G125/$D$119 -> 0 | I125: =H125*F125 -> 0 | J125: 0 | K125: =F125-I125 -> 3600000 | L125: =SUM($D$125:$D125) -> 4800 | M125: =EOMONTH(C125,0) -> 44012
B126: =B9 -> 44016 | C126: =C9 -> 44010 | D126: =D9 -> 3800 | E126: =D126*$D$120 -> 2850000 | F126: =SUM($E$125:$E126) -> 6450000 | G126: =COUNTIF($F$8:$F$47,"<="&B126) -> 0 | H126: =G126/$D$119 -> 0 | I126: =H126*F126 -> 0 | J126: =I126-I125 -> 0 | K126: =F126-I126 -> 6450000 | L126: =SUM($D$125:$D126) -> 8600 | M126: =EOMONTH(C126,0) -> 44012 | O126: =$H126*E126 -> 0 | P126: =$H126*F125 -> 0 | Q126: =SUM(O126:P126) -> 0 | R126: =Q126=I126 -> TRUE
B127: =B10 -> 44023 | C127: =C10 -> 44017 | D127: =D10 -> 3400 | E127: =D127*$D$120 -> 2550000 | F127: =SUM($E$125:$E127) -> 9000000 | G127: =COUNTIF($F$8:$F$47,"<="&B127) -> 0 | H127: =G127/$D$119 -> 0 | I127: =H127*F127 -> 0 | J127: =I127-I126 -> 0 | K127: =F127-I127 -> 9000000 | L127: =SUM($D$125:$D127) -> 12000 | M127: =EOMONTH(C127,0) -> 44043 | O127: =$H127*E127 -> 0 | P127: =$H127*F126 -> 0 | Q127: =SUM(O127:P127) -> 0 | R127: =Q127=I127 -> TRUE
B128: =B11 -> 44030 | C128: =C11 -> 44024 | D128: =D11 -> 2800 | E128: =D128*$D$120 -> 2100000 | F128: =SUM($E$125:$E128) -> 11100000 | G128: =COUNTIF($F$8:$F$47,"<="&B128) -> 0 | H128: =G128/$D$119 -> 0 | I128: =H128*F128 -> 0 | J128: =I128-I127 -> 0 | K128: =F128-I128 -> 11100000 | L128: =SUM($D$125:$D128) -> 14800 | M128: =EOMONTH(C128,0) -> 44043 | O128: =$H128*E128 -> 0 | P128: =$H128*F127 -> 0 | Q128: =SUM(O128:P128) -> 0 | R128: =Q128=I128 -> TRUE
B129: =B12 -> 44037 | C129: =C12 -> 44031 | D129: =D12 -> 2700 | E129: =D129*$D$120 -> 2025000 | F129: =SUM($E$125:$E129) -> 13125000 | G129: =COUNTIF($F$8:$F$47,"<="&B129) -> 0 | H129: =G129/$D$119 -> 0 | I129: =H129*F129 -> 0 | J129: =I129-I128 -> 0 | K129: =F129-I129 -> 13125000 | L129: =SUM($D$125:$D129) -> 17500 | M129: =EOMONTH(C129,0) -> 44043 | O129: =$H129*E129 -> 0 | P129: =$H129*F128 -> 0 | Q129: =SUM(O129:P129) -> 0 | R129: =Q129=I129 -> TRUE
B130: =B13 -> 44044 | C130: =C13 -> 44038 | D130: =D13 -> 2750 | E130: =D130*$D$120 -> 2062500 | F130: =SUM($E$125:$E130) -> 15187500 | G130: =COUNTIF($F$8:$F$47,"<="&B130) -> 0 | H130: =G130/$D$119 -> 0 | I130: =H130*F130 -> 0 | J130: =I130-I129 -> 0 | K130: =F130-I130 -> 15187500 | L130: =SUM($D$125:$D130) -> 20250 | M130: =EOMONTH(C130,0) -> 44043 | O130: =$H130*E130 -> 0 | P130: =$H130*F129 -> 0 | Q130: =SUM(O130:P130) -> 0 | R130: =Q130=I130 -> TRUE
B131: =B14 -> 44051 | C131: =C14 -> 44045 | D131: =D14 -> 2600 | E131: =D131*$D$120 -> 1950000 | F131: =SUM($E$125:$E131) -> 17137500 | G131: =COUNTIF($F$8:$F$47,"<="&B131) -> 0 | H131: =G131/$D$119 -> 0 | I131: =H131*F131 -> 0 | J131: =I131-I130 -> 0 | K131: =F131-I131 -> 17137500 | L131: =SUM($D$125:$D131) -> 22850 | M131: =EOMONTH(C131,0) -> 44074 | O131: =$H131*E131 -> 0 | P131: =$H131*F130 -> 0 | Q131: =SUM(O131:P131) -> 0 | R131: =Q131=I131 -> TRUE
B132: =B15 -> 44058 | C132: =C15 -> 44052 | D132: =D15 -> 2800 | E132: =D132*$D$120 -> 2100000 | F132: =SUM($E$125:$E132) -> 19237500 | G132: =COUNTIF($F$8:$F$47,"<="&B132) -> 1 | H132: =G132/$D$119 -> 0.025 | I132: =H132*F132 -> 480937.5 | J132: =I132-I131 -> 480937.5 | K132: =F132-I132 -> 18756562 | L132: =SUM($D$125:$D132) -> 25650 | M132: =EOMONTH(C132,0) -> 44074 | O132: =$H132*E132 -> 52500 | P132: =$H132*F131 -> 428437.5 | Q132: =SUM(O132:P132) -> 480937.5 | R132: =Q132=I132 -> TRUE
B133: =B16 -> 44065 | C133: =C16 -> 44059 | D133: =D16 -> 1400 | E133: =D133*$D$120 -> 1050000 | F133: =SUM($E$125:$E133) -> 20287500 | G133: =COUNTIF($F$8:$F$47,"<="&B133) -> 2 | H133: =G133/$D$119 -> 0.05 | I133: =H133*F133 -> 1014375 | J133: =I133-I132 -> 533437.5 | K133: =F133-I133 -> 19273125 | L133: =SUM($D$125:$D133) -> 27050 | M133: =EOMONTH(C133,0) -> 44074 | O133: =$H133*E133 -> 52500 | P133: =$H133*F132 -> 961875 | Q133: =SUM(O133:P133) -> 1014375 | R133: =Q133=I133 -> TRUE
B134: =B17 -> 44072 | C134: =C17 -> 44066 | D134: =D17 -> 800 | E134: =D134*$D$120 -> 600000 | F134: =SUM($E$125:$E134) -> 20887500 | G134: =COUNTIF($F$8:$F$47,"<="&B134) -> 3 | H134: =G134/$D$119 -> 0.075 | I134: =H134*F134 -> 1566562.5 | J134: =I134-I133 -> 552187.5 | K134: =F134-I134 -> 19320938 | L134: =SUM($D$125:$D134) -> 27850 | M134: =EOMONTH(C134,0) -> 44074 | O134: =$H134*E134 -> 45000 | P134: =$H134*F133 -> 1521562.5 | Q134: =SUM(O134:P134) -> 1566562.5 | R134: =Q134=I134 -> TRUE
B135: =B18 -> 44079 | C135: =C18 -> 44073 | D135: =D18 -> 500 | E135: =D135*$D$120 -> 375000 | F135: =SUM($E$125:$E135) -> 21262500 | G135: =COUNTIF($F$8:$F$47,"<="&B135) -> 4 | H135: =G135/$D$119 -> 0.1 | I135: =H135*F135 -> 2126250 | J135: =I135-I134 -> 559687.5 | K135: =F135-I135 -> 19136250 | L135: =SUM($D$125:$D135) -> 28350 | M135: =EOMONTH(C135,0) -> 44074 | O135: =$H135*E135 -> 37500 | P135: =$H135*F134 -> 2088750 | Q135: =SUM(O135:P135) -> 2126250 | R135: =Q135=I135 -> TRUE
B136: =B19 -> 44086 | C136: =C19 -> 44080 | D136: =D19 -> 200 | E136: =D136*$D$120 -> 150000 | F136: =SUM($E$125:$E136) -> 21412500 | G136: =COUNTIF($F$8:$F$47,"<="&B136) -> 5 | H136: =G136/$D$119 -> 0.125 | I136: =H136*F136 -> 2676562.5 | J136: =I136-I135 -> 550312.5 | K136: =F136-I136 -> 18735938 | L136: =SUM($D$125:$D136) -> 28550 | M136: =EOMONTH(C136,0) -> 44104 | O136: =$H136*E136 -> 18750 | P136: =$H136*F135 -> 2657812.5 | Q136: =SUM(O136:P136) -> 2676562.5 | R136: =Q136=I136 -> TRUE
B137: =B20 -> 44093 | C137: =C20 -> 44087 | D137: =D20 -> 150 | E137: =D137*$D$120 -> 112500 | F137: =SUM($E$125:$E137) -> 21525000 | G137: =COUNTIF($F$8:$F$47,"<="&B137) -> 6 | H137: =G137/$D$119 -> 0.15 | I137: =H137*F137 -> 3228750 | J137: =I137-I136 -> 552187.5 | K137: =F137-I137 -> 18296250 | L137: =SUM($D$125:$D137) -> 28700 | M137: =EOMONTH(C137,0) -> 44104 | O137: =$H137*E137 -> 16875 | P137: =$H137*F136 -> 3211875 | Q137: =SUM(O137:P137) -> 3228750 | R137: =Q137=I137 -> TRUE
... B155: =B38 -> 44219 | C155: =C38 -> 44213 | D155: =D38 -> 50 | E155: =D155*$D$120 -> 37500 | F155: =SUM($E$125:$E155) -> 22500000 | G155: =COUNTIF($F$8:$F$47,"<="&B155) -> 22 | H155: =G155/$D$119 -> 0.55 | I155: =H155*F155 -> 12375000 | J155: =I155-I154 -> 582187.5 | K155: =F155-I155 -> 10125000 | L155: =SUM($D$125:$D155) -> 30000 | M155: =EOMONTH(C155,0) -> 44227 | O155: =$H155*E155 -> 20625 | P155: =$H155*F154 -> 12354375 | Q155: =SUM(O155:P155) -> 12375000 | R155: =Q155=I155 -> TRUE
B156: =B155+7 -> 44226 | D156: 0 | E156: =D156*$D$120 -> 0 | F156: =SUM($E$125:$E156) -> 22500000 | G156: =COUNTIF($F$8:$F$47,"<="&B156) -> 23 | H156: =G156/$D$119 -> 0.575 | I156: =H156*F156 -> 12937500 | J156: =I156-I155 -> 562500 | K156: =F156-I156 -> 9562500 | L156: =SUM($D$125:$D156) -> 30000 | O156: =$H156*E156 -> 0 | P156: =$H156*F155 -> 12937500 | Q156: =SUM(O156:P156) -> 12937500 | R156: =Q156=I156 -> TRUE
B157: =B156+7 -> 44233 | D157: 0 | E157: =D157*$D$120 -> 0 | F157: =SUM($E$125:$E157) -> 22500000 | G157: =COUNTIF($F$8:$F$47,"<="&B157) -> 24 | H157: =G157/$D$119 -> 0.6 | I157: =H157*F157 -> 13500000 | J157: =I157-I156 -> 562500 | K157: =F157-I157 -> 9000000 | L157: =SUM($D$125:$D157) -> 30000 | O157: =$H157*E157 -> 0 | P157: =$H157*F156 -> 13500000 | Q157: =SUM(O157:P157) -> 13500000 | R157: =Q157=I157 -> TRUE
B158: =B157+7 -> 44240 | D158: 0 | E158: =D158*$D$120 -> 0 | F158: =SUM($E$125:$E158) -> 22500000 | G158: =COUNTIF($F$8:$F$47,"<="&B158) -> 25 | H158: =G158/$D$119 -> 0.625 | I158: =H158*F158 -> 14062500 | J158: =I158-I157 -> 562500 | K158: =F158-I158 -> 8437500 | L158: =SUM($D$125:$D158) -> 30000 | O158: =$H158*E158 -> 0 | P158: =$H158*F157 -> 14062500 | Q158: =SUM(O158:P158) -> 14062500 | R158: =Q158=I158 -> TRUE
B159: =B158+7 -> 44247 | D159: 0 | E159: =D159*$D$120 -> 0 | F159: =SUM($E$125:$E159) -> 22500000 | G159: =COUNTIF($F$8:$F$47,"<="&B159) -> 26 | H159: =G159/$D$119 -> 0.65 | I159: =H159*F159 -> 14625000 | J159: =I159-I158 -> 562500 | K159: =F159-I159 -> 7875000 | L159: =SUM($D$125:$D159) -> 30000 | O159: =$H159*E159 -> 0 | P159: =$H159*F158 -> 14625000 | Q159: =SUM(O159:P159) -> 14625000 | R159: =Q159=I159 -> TRUE
B160: =B159+7 -> 44254 | D160: 0 | E160: =D160*$D$120 -> 0 | F160: =SUM($E$125:$E160) -> 22500000 | G160: =COUNTIF($F$8:$F$47,"<="&B160) -> 27 | H160: =G160/$D$119 -> 0.675 | I160: =H160*F160 -> 15187500 | J160: =I160-I159 -> 562500 | K160: =F160-I160 -> 7312500 | L160: =SUM($D$125:$D160) -> 30000 | O160: =$H160*E160 -> 0 | P160: =$H160*F159 -> 15187500 | Q160: =SUM(O160:P160) -> 15187500 | R160: =Q160=I160 -> TRUE
B161: =B160+7 -> 44261 | D161: 0 | E161: =D161*$D$120 -> 0 | F161: =SUM($E$125:$E161) -> 22500000 | G161: =COUNTIF($F$8:$F$47,"<="&B161) -> 28 | H161: =G161/$D$119 -> 0.7 | I161: =H161*F161 -> 15750000 | J161: =I161-I160 -> 562500 | K161: =F161-I161 -> 6750000 | L161: =SUM($D$125:$D161) -> 30000 | O161: =$H161*E161 -> 0 | P161: =$H161*F160 -> 15750000 | Q161: =SUM(O161:P161) -> 15750000 | R161: =Q161=I161 -> TRUE
B162: =B161+7 -> 44268 | D162: 0 | E162: =D162*$D$120 -> 0 | F162: =SUM($E$125:$E162) -> 22500000 | G162: =COUNTIF($F$8:$F$47,"<="&B162) -> 29 | H162: =G162/$D$119 -> 0.725 | I162: =H162*F162 -> 16312500 | J162: =I162-I161 -> 562500 | K162: =F162-I162 -> 6187500 | L162: =SUM($D$125:$D162) -> 30000 | O162: =$H162*E162 -> 0 | P162: =$H162*F161 -> 16312500 | Q162: =SUM(O162:P162) -> 16312500 | R162: =Q162=I162 -> TRUE
B163: =B162+7 -> 44275 | D163: 0 | E163: =D163*$D$120 -> 0 | F163: =SUM($E$125:$E163) -> 22500000 | G163: =COUNTIF($F$8:$F$47,"<="&B163) -> 30 | H163: =G163/$D$119 -> 0.75 | I163: =H163*F163 -> 16875000 | J163: =I163-I162 -> 562500 | K163: =F163-I163 -> 5625000 | L163: =SUM($D$125:$D163) -> 30000 | O163: =$H163*E163 -> 0 | P163: =$H163*F162 -> 16875000 | Q163: =SUM(O163:P163) -> 16875000 | R163: =Q163=I163 -> TRUE
B164: =B163+7 -> 44282 | D164: 0 | E164: =D164*$D$120 -> 0 | F164: =SUM($E$125:$E164) -> 22500000 | G164: =COUNTIF($F$8:$F$47,"<="&B164) -> 31 | H164: =G164/$D$119 -> 0.775 | I164: =H164*F164 -> 17437500 | J164: =I164-I163 -> 562500 | K164: =F164-I164 -> 5062500 | L164: =SUM($D$125:$D164) -> 30000 | O164: =$H164*E164 -> 0 | P164: =$H164*F163 -> 17437500 | Q164: =SUM(O164:P164) -> 17437500 | R164: =Q164=I164 -> TRUE
B165: =B164+7 -> 44289 | D165: 0 | E165: =D165*$D$120 -> 0 | F165: =SUM($E$125:$E165) -> 22500000 | G165: =COUNTIF($F$8:$F$47,"<="&B165) -> 32 | H165: =G165/$D$119 -> 0.8 | I165: =H165*F165 -> 18000000 | J165: =I165-I164 -> 562500 | K165: =F165-I165 -> 4500000 | L165: =SUM($D$125:$D165) -> 30000 | O165: =$H165*E165 -> 0 | P165: =$H165*F164 -> 18000000 | Q165: =SUM(O165:P165) -> 18000000 | R165: =Q165=I165 -> TRUE
...

Sheet AltSolution (Daily Sales)
A1: Wichita Warblers Inc - Inputs and Assumptions
B3: Season Ticket Price | D3: ($) | E3: 750
B4: Stadium Capacity | D4: (# seats) | E4: 50000
B6: Season Ticket Sales By Week | H6: Game Dates & Importance | K6: Sales Timing For Single Game Tickets | N6: Game Assumptions By Importance
B7: Week ending | C7: Week start | D7: Starting Month | E7: Following Month | F7: Sales | H7: Date | I7: Importance | K7: Days to game | L7: % of demand | N7: Importance | O7: Base crowd | P7: Ticket price ($)
B8: 44009 | C8: =B8-6 -> 44003 | D8: =7-E8 -> 7 | E8: =IF(MONTH(B8)=MONTH(C8),0,DAY(B8)) -> 0 | F8: 4800 | H8: 44058 | I8: 3 | K8: 6 | L8: 0.25 | N8: 1 | O8: 15000 | P8: 30
B9: 44016 | C9: =B9-6 -> 44010 | D9: =7-E9 -> 3 | E9: =IF(MONTH(B9)=MONTH(C9),0,DAY(B9)) -> 4 | F9: 3800 | H9: 44065 | I9: 2 | K9: 5 | L9: 0.22 | N9: 2 | O9: 25000 | P9: 40
B10: 44023 | C10: =B10-6 -> 44017 | D10: =7-E10 -> 7 | E10: =IF(MONTH(B10)=MONTH(C10),0,DAY(B10)) -> 0 | F10: 3400 | H10: 44072 | I10: 1 | K10: 4 | L10: 0.08 | N10: 3 | O10: 32000 | P10: 50
B11: 44030 | C11: =B11-6 -> 44024 | D11: =7-E11 -> 7 | E11: =IF(MONTH(B11)=MONTH(C11),0,DAY(B11)) -> 0 | F11: 2800 | H11: 44079 | I11: 3 | K11: 3 | L11: 0.05 | N11: 4 | O11: 40000 | P11: 60
B12: 44037 | C12: =B12-6 -> 44031 | D12: =7-E12 -> 7 | E12: =IF(MONTH(B12)=MONTH(C12),0,DAY(B12)) -> 0 | F12: 2700 | H12: 44086 | I12: 1 | K12: 2 | L12: 0.05 | N12: 5 | O12: 50000 | P12: 75
B13: 44044 | C13: =B13-6 -> 44038 | D13: =7-E13 -> 6 | E13: =IF(MONTH(B13)=MONTH(C13),0,DAY(B13)) -> 1 | F13: 2750 | H13: 44093 | I13: 2 | K13: 1 | L13: 0.15
B14: 44051 | C14: =B14-6 -> 44045 | D14: =7-E14 -> 7 | E14: =IF(MONTH(B14)=MONTH(C14),0,DAY(B14)) -> 0 | F14: 2600 | H14: 44100 | I14: 1 | K14: 0 | L14: 0.2
B15: 44058 | C15: =B15-6 -> 44052 | D15: =7-E15 -> 7 | E15: =IF(MONTH(B15)=MONTH(C15),0,DAY(B15)) -> 0 | F15: 2800 | H15: 44107 | I15: 2 | K15: Total | L15: =SUM(L8:L14) -> 1
B16: 44065 | C16: =B16-6 -> 44059 | D16: =7-E16 -> 7 | E16: =IF(MONTH(B16)=MONTH(C16),0,DAY(B16)) -> 0 | F16: 1400 | H16: 44114 | I16: 2
B17: 44072 | C17: =B17-6 -> 44066 | D17: =7-E17 -> 7 | E17: =IF(MONTH(B17)=MONTH(C17),0,DAY(B17)) -> 0 | F17: 800 | H17: 44121 | I17: 1
B18: 44079 | C18: =B18-6 -> 44073 | D18: =7-E18 -> 2 | E18: =IF(MONTH(B18)=MONTH(C18),0,DAY(B18)) -> 5 | F18: 500 | H18: 44128 | I18: 2
B19: 44086 | C19: =B19-6 -> 44080 | D19: =7-E19 -> 7 | E19: =IF(MONTH(B19)=MONTH(C19),0,DAY(B19)) -> 0 | F19: 200 | H19: 44135 | I19: 1
B20: 44093 | C20: =B20-6 -> 44087 | D20: =7-E20 -> 7 | E20: =IF(MONTH(B20)=MONTH(C20),0,DAY(B20)) -> 0 | F20: 150 | H20: 44142 | I20: 4 | K20: Changes Key
B21: 44100 | C21: =B21-6 -> 44094 | D21: =7-E21 -> 7 | E21: =IF(MONTH(B21)=MONTH(C21),0,DAY(B21)) -> 0 | F21: 50 | H21: 44149 | I21: 1 | L21: New cells
B22: 44107 | C22: =B22-6 -> 44101 | D22: =7-E22 -> 4 | E22: =IF(MONTH(B22)=MONTH(C22),0,DAY(B22)) -> 3 | F22: 50 | H22: 44156 | I22: 2 | L22: Edited existing cells
B23: 44114 | C23: =B23-6 -> 44108 | D23: =7-E23 -> 7 | E23: =IF(MONTH(B23)=MONTH(C23),0,DAY(B23)) -> 0 | F23: 50 | H23: 44163 | I23: 2
B24: 44121 | C24: =B24-6 -> 44115 | D24: =7-E24 -> 7 | E24: =IF(MONTH(B24)=MONTH(C24),0,DAY(B24)) -> 0 | F24: 50 | H24: 44170 | I24: 2
B25: 44128 | C25: =B25-6 -> 44122 | D25: =7-E25 -> 7 | E25: =IF(MONTH(B25)=MONTH(C25),0,DAY(B25)) -> 0 | F25: 50 | H25: 44177 | I25: 1
B26: 44135 | C26: =B26-6 -> 44129 | D26: =7-E26 -> 7 | E26: =IF(MONTH(B26)=MONTH(C26),0,DAY(B26)) -> 0 | F26: 50 | H26: 44198 | I26: 1
B27: 44142 | C27: =B27-6 -> 44136 | D27: =7-E27 -> 7 | E27: =IF(MONTH(B27)=MONTH(C27),0,DAY(B27)) -> 0 | F27: 50 | H27: 44205 | I27: 1
B28: 44149 | C28: =B28-6 -> 44143 | D28: =7-E28 -> 7 | E28: =IF(MONTH(B28)=MONTH(C28),0,DAY(B28)) -> 0 | F28: 50 | H28: 44212 | I28: 3
B29: 44156 | C29: =B29-6 -> 44150 | D29: =7-E29 -> 7 | E29: =IF(MONTH(B29)=MONTH(C29),0,DAY(B29)) -> 0 | F29: 50 | H29: 44219 | I29: 1
B30: 44163 | C30: =B30-6 -> 44157 | D30: =7-E30 -> 7 | E30: =IF(MONTH(B30)=MONTH(C30),0,DAY(B30)) -> 0 | F30: 50 | H30: 44226 | I30: 4
B31: 44170 | C31: =B31-6 -> 44164 | D31: =7-E31 -> 2 | E31: =IF(MONTH(B31)=MONTH(C31),0,DAY(B31)) -> 5 | F31: 50 | H31: 44233 | I31: 2
B32: 44177 | C32: =B32-6 -> 44171 | D32: =7-E32 -> 7 | E32: =IF(MONTH(B32)=MONTH(C32),0,DAY(B32)) -> 0 | F32: 250 | H32: 44240 | I32: 2
B33: 44184 | C33: =B33-6 -> 44178 | D33: =7-E33 -> 7 | E33: =IF(MONTH(B33)=MONTH(C33),0,DAY(B33)) -> 0 | F33: 250 | H33: 44247 | I33: 2
B34: 44191 | C34: =B34-6 -> 44185 | D34: =7-E34 -> 7 | E34: =IF(MONTH(B34)=MONTH(C34),0,DAY(B34)) -> 0 | F34: 50 | H34: 44254 | I34: 3
... B38: 44219 | C38: =B38-6 -> 44213 | D38: =7-E38 -> 7 | E38: =IF(MONTH(B38)=MONTH(C38),0,DAY(B38)) -> 0 | F38: 50 | H38: 44282 | I38: 3
B39: Total | F39: =SUM(F8:F38) -> 30000 | H39: 44289 | I39: 1
H40: 44296 | I40: 2
H41: 44303 | I41: 2
H42: 44310 | I42: 1
H43: 44317 | I43: 1
H44: 44324 | I44: 1
H45: 44331 | I45: 3
H46: 44338 | I46: 4
H47: 44352 | I47: 5
H48: Total Games | I48: =COUNT(I8:I47) -> 40
A51: Monthly Summary Table
C53: Season Tickets | G53: Single Game Tickets | K53: Total
B54: Month End | C54: Cash Received | D54: Revenue | E54: Unearned Revenue Balance | F54: # Of Tickets Sold | G54: Cash Received | H54: Revenue | I54: Unearned Revenue Balance | J54: # Of Tickets Sold | K54: Cash Received | L54: Revenue | M54: Unearned Revenue | N54: # Of Tickets Sold
B55: 44012 | C55: =G183 -> 4821428.6 | D55: =K183 -> 0 | E55: =SUM(C$55:C55)-SUM(D$55:D55) -> 4821428.6 | F55: =F183 -> 6428.5714 | G55: =D304 -> 0 | H55: =E304 -> 0 | I55: =SUM(G$55:G55)-SUM(H$55:H55) -> 0 | J55: =C304 -> 0 | K55: =G55+C55 -> 4821428.6 | L55: =H55+D55 -> 0 | M55: =I55+E55 -> 4821428.6 | N55: =F55+J55 -> 6428.5714
B56: 44043 | C56: =G184 -> 10071429 | D56: =K184 -> 0 | E56: =SUM(C$55:C56)-SUM(D$55:D56) -> 14892857 | F56: =F184 -> 13428.571 | G56: =D305 -> 0 | H56: =E305 -> 0 | I56: =SUM(G$55:G56)-SUM(H$55:H56) -> 0 | J56: =C305 -> 0 | K56: =G56+C56 -> 10071429 | L56: =H56+D56 -> 0 | M56: =I56+E56 -> 14892857 | N56: =F56+J56 -> 13428.571
B57: 44074 | C57: =G185 -> 6101785.7 | D57: =K185 -> 1574598.2 | E57: =SUM(C$55:C57)-SUM(D$55:D57) -> 19420045 | F57: =F185 -> 8135.7143 | G57: =D306 -> 3337500 | H57: =E306 -> 2585500 | I57: =SUM(G$55:G57)-SUM(H$55:H57) -> 752000 | J57: =C306 -> 77340 | K57: =G57+C57 -> 9439285.7 | L57: =H57+D57 -> 4160098.2 | M57: =I57+E57 -> 20172045 | N57: =F57+J57 -> 85475.714
B58: 44104 | C58: =G186 -> 589285.71 | D58: =K186 -> 2202589.3 | E58: =SUM(C$55:C58)-SUM(D$55:D58) -> 17806741 | F58: =F186 -> 785.71429 | G58: =D307 -> 2682500 | H58: =E307 -> 2834500 | I58: =SUM(G$55:G58)-SUM(H$55:H58) -> 600000 | J58: =C307 -> 72910 | K58: =G58+C58 -> 3271785.7 | L58: =H58+D58 -> 5037089.3 | M58: =I58+E58 -> 18406741 | N58: =F58+J58 -> 73695.714
B59: 44135 | C59: =G187 -> 166071.43 | D59: =K187 -> 2747812.5 | E59: =SUM(C$55:C59)-SUM(D$55:D59) -> 15225000 | F59: =F187 -> 221.42857 | G59: =D308 -> 2836000 | H59: =E308 -> 3436000 | I59: =SUM(G$55:G59)-SUM(H$55:H59) -> 0 | J59: =C308 -> 78400 | K59: =G59+C59 -> 3002071.4 | L59: =H59+D59 -> 6183812.5 | M59: =I59+E59 -> 15225000 | N59: =F59+J59 -> 78621.429
B60: 44165 | C60: =G188 -> 160714.29 | D60: =K188 -> 2239285.7 | E60: =SUM(C$55:C60)-SUM(D$55:D60) -> 13146429 | F60: =F188 -> 214.28571 | G60: =D309 -> 3843000 | H60: =E309 -> 3373000 | I60: =SUM(G$55:G60)-SUM(H$55:H60) -> 470000 | J60: =C309 -> 89350 | K60: =G60+C60 -> 4003714.3 | L60: =H60+D60 -> 5612285.7 | M60: =I60+E60 -> 13616429 | N60: =F60+J60 -> 89564.286
B61: 44196 | C61: =G189 -> 466071.43 | D61: =K189 -> 1305267.9 | E61: =SUM(C$55:C61)-SUM(D$55:D61) -> 12307232 | F61: =F189 -> 621.42857 | G61: =D310 -> 1102500 | H61: =E310 -> 1280000 | I61: =SUM(G$55:G61)-SUM(H$55:H61) -> 292500 | J61: =C310 -> 33750 | K61: =G61+C61 -> 1568571.4 | L61: =H61+D61 -> 2585267.9 | M61: =I61+E61 -> 12599732 | N61: =F61+J61 -> 34371.429
B62: 44227 | C62: =G190 -> 123214.29 | D62: =K190 -> 2867946.4 | E62: =SUM(C$55:C62)-SUM(D$55:D62) -> 9562500 | F62: =F190 -> 164.28571 | G62: =D311 -> 3510000 | H62: =E311 -> 3552500 | I62: =SUM(G$55:G62)-SUM(H$55:H62) -> 250000 | J62: =C311 -> 81550 | K62: =G62+C62 -> 3633214.3 | L62: =H62+D62 -> 6420446.4 | M62: =I62+E62 -> 9812500 | N62: =F62+J62 -> 81714.286
B63: 44255 | C63: =G191 -> 0 | D63: =K191 -> 2250000 | E63: =SUM(C$55:C63)-SUM(D$55:D63) -> 7312500 | F63: =F191 -> 0 | G63: =D312 -> 3262500 | H63: =E312 -> 3400000 | I63: =SUM(G$55:G63)-SUM(H$55:H63) -> 112500 | J63: =C312 -> 77500 | K63: =G63+C63 -> 3262500 | L63: =H63+D63 -> 5650000 | M63: =I63+E63 -> 7425000 | N63: =F63+J63 -> 77500
B64: 44286 | C64: =G192 -> 0 | D64: =K192 -> 2250000 | E64: =SUM(C$55:C64)-SUM(D$55:D64) -> 5062500 | F64: =F192 -> 0 | G64: =D313 -> 3207500 | H64: =E313 -> 3050000 | I64: =SUM(G$55:G64)-SUM(H$55:H64) -> 270000 | J64: =C313 -> 80250 | K64: =G64+C64 -> 3207500 | L64: =H64+D64 -> 5300000 | M64: =I64+E64 -> 5332500 | N64: =F64+J64 -> 80250
B65: 44316 | C65: =G193 -> 0 | D65: =K193 -> 2250000 | E65: =SUM(C$55:C65)-SUM(D$55:D65) -> 2812500 | F65: =F193 -> 0 | G65: =D314 -> 2590000 | H65: =E314 -> 2500000 | I65: =SUM(G$55:G65)-SUM(H$55:H65) -> 360000 | J65: =C314 -> 73000 | K65: =G65+C65 -> 2590000 | L65: =H65+D65 -> 4750000 | M65: =I65+E65 -> 3172500 | N65: =F65+J65 -> 73000
B66: 44347 | C66: =G194 -> 0 | D66: =K194 -> 2250000 | E66: =SUM(C$55:C66)-SUM(D$55:D66) -> 562500 | F66: =F194 -> 0 | G66: =D315 -> 4240000 | H66: =E315 -> 3100000 | I66: =SUM(G$55:G66)-SUM(H$55:H66) -> 1500000 | J66: =C315 -> 78000 | K66: =G66+C66 -> 4240000 | L66: =H66+D66 -> 5350000 | M66: =I66+E66 -> 2062500 | N66: =F66+J66 -> 78000
B67: 44377 | C67: =G195 -> 0 | D67: =K195 -> 562500 | E67: =SUM(C$55:C67)-SUM(D$55:D67) -> 0 | F67: =F195 -> 0 | G67: =D316 -> 0 | H67: =E316 -> 1500000 | I67: =SUM(G$55:G67)-SUM(H$55:H67) -> 0 | J67: =C316 -> 0 | K67: =G67+C67 -> 0 | L67: =H67+D67 -> 2062500 | M67: =I67+E67 -> 0 | N67: =F67+J67 -> 0
C68: =SUM(C55:C67) -> 22500000 | D68: =SUM(D55:D67) -> 22500000 | F68: =SUM(F55:F67) -> 30000 | G68: =SUM(G55:G67) -> 30611500 | H68: =SUM(H55:H67) -> 30611500 | K68: =SUM(K55:K67) -> 53111500 | L68: =SUM(L55:L67) -> 53111500 | N68: =SUM(N55:N67) -> 772050
B69: Rec | C69: =C68-'CaseSolution (Original)'!C68 -> 0 | D69: =D68-'CaseSolution (Original)'!D68 -> 0 | F69: =F68-'CaseSolution (Original)'!F68 -> 0 | G69: =G68-'CaseSolution (Original)'!G68 -> 0 | H69: =H68-'CaseSolution (Original)'!H68 -> 0 | K69: =K68-'CaseSolution (Original)'!K68 -> 0 | L69: =L68-'CaseSolution (Original)'!L68 -> 0 | N69: =N68-'CaseSolution (Original)'!N68 -> 0
A71: Game Summary Table
C73: Revenue | F73: # Of Tickets Sold | I73: # of Single Game Tickets Sold by Days to Game
B74: Game Date | C74: Season Tickets | D74: Single Game Tickets | E74: Total | F74: Season Tickets | G74: Single Game Tickets | H74: Total | I74: 6 | J74: 5 | K74: 4 | L74: 3 | M74: 2 | N74: 1 | O74: 0 | P74: Total | Q74: Check
B75: =H8 -> 44058 | C75: =SUMIF($B$125:$B$174,"<="&B75,$K$125:$K$174) -> 480937.5 | D75: =AM206 -> 1217500 | E75: =SUM(C75:D75) -> 1698437.5 | F75: =F206 -> 25650 | G75: =H206 -> 24350 | H75: =SUM(F75:G75) -> 50000 | I75: =AD206 -> 8000 | J75: =AE206 -> 7040 | K75: =AF206 -> 2560 | L75: =AG206 -> 1600 | M75: =AH206 -> 1600 | N75: =AI206 -> 3550 | O75: =AJ206 -> 0 | P75: =SUM(I75:O75) -> 24350 | Q75: =P75=G75 -> TRUE
B76: =H9 -> 44065 | C76: =SUMIFS($K$125:$K$174,$B$125:$B$174,"<="&B76,$B$125:$B$174,">"&B75) -> 533437.5 | D76: =AM207 -> 918000 | E76: =SUM(C76:D76) -> 1451437.5 | F76: =F207 -> 27050 | G76: =H207 -> 22950 | H76: =SUM(F76:G76) -> 50000 | I76: =AD207 -> 6250 | J76: =AE207 -> 5500 | K76: =AF207 -> 2000 | L76: =AG207 -> 1250 | M76: =AH207 -> 1250 | N76: =AI207 -> 3750 | O76: =AJ207 -> 2950 | P76: =SUM(I76:O76) -> 22950 | Q76: =P76=G76 -> TRUE
B77: =H10 -> 44072 | C77: =SUMIFS($K$125:$K$174,$B$125:$B$174,"<="&B77,$B$125:$B$174,">"&B76) -> 552187.5 | D77: =AM208 -> 450000 | E77: =SUM(C77:D77) -> 1002187.5 | F77: =F208 -> 27850 | G77: =H208 -> 15000 | H77: =SUM(F77:G77) -> 42850 | I77: =AD208 -> 3750 | J77: =AE208 -> 3300 | K77: =AF208 -> 1200 | L77: =AG208 -> 750 | M77: =AH208 -> 750 | N77: =AI208 -> 2250 | O77: =AJ208 -> 3000 | P77: =SUM(I77:O77) -> 15000 | Q77: =P77=G77 -> TRUE
B78: =H11 -> 44079 | C78: =SUMIFS($K$125:$K$174,$B$125:$B$174,"<="&B78,$B$125:$B$174,">"&B77) -> 559687.5 | D78: =AM209 -> 1082500 | E78: =SUM(C78:D78) -> 1642187.5 | F78: =F209 -> 28350 | G78: =H209 -> 21650 | H78: =SUM(F78:G78) -> 50000 | I78: =AD209 -> 8000 | J78: =AE209 -> 7040 | K78: =AF209 -> 2560 | L78: =AG209 -> 1600 | M78: =AH209 -> 1600 | N78: =AI209 -> 850 | O78: =AJ209 -> 0 | P78: =SUM(I78:O78) -> 21650 | Q78: =P78=G78 -> TRUE
B79: =H12 -> 44086 | C79: =SUMIFS($K$125:$K$174,$B$125:$B$174,"<="&B79,$B$125:$B$174,">"&B78) -> 550312.5 | D79: =AM210 -> 450000 | E79: =SUM(C79:D79) -> 1000312.5 | F79: =F210 -> 28550 | G79: =H210 -> 15000 | H79: =SUM(F79:G79) -> 43550 | I79: =AD210 -> 3750 | J79: =AE210 -> 3300 | K79: =AF210 -> 1200 | L79: =AG210 -> 750 | M79: =AH210 -> 750 | N79: =AI210 -> 2250 | O79: =AJ210 -> 3000 | P79: =SUM(I79:O79) -> 15000 | Q79: =P79=G79 -> TRUE
B80: =H13 -> 44093 | C80: =SUMIFS($K$125:$K$174,$B$125:$B$174,"<="&B80,$B$125:$B$174,">"&B79) -> 552187.5 | D80: =AM211 -> 852000 | E80: =SUM(C80:D80) -> 1404187.5 | F80: =F211 -> 28700 | G80: =H211 -> 21300 | H80: =SUM(F80:G80) -> 50000 | I80: =AD211 -> 6250 | J80: =AE211 -> 5500 | K80: =AF211 -> 2000 | L80: =AG211 -> 1250 | M80: =AH211 -> 1250 | N80: =AI211 -> 3750 | O80: =AJ211 -> 1300 | P80: =SUM(I80:O80) -> 21300 | Q80: =P80=G80 -> TRUE
B81: =H14 -> 44100 | C81: =SUMIFS($K$125:$K$174,$B$125:$B$174,"<="&B81,$B$125:$B$174,">"&B80) -> 544687.5 | D81: =AM212 -> 450000 | E81: =SUM(C81:D81) -> 994687.5 | F81: =F212 -> 28750 | G81: =H212 -> 15000 | H81: =SUM(F81:G81) -> 43750 | I81: =AD212 -> 3750 | J81: =AE212 -> 3300 | K81: =AF212 -> 1200 | L81: =AG212 -> 750 | M81: =AH212 -> 750 | N81: =AI212 -> 2250 | O81: =AJ212 -> 3000 | P81: =SUM(I81:O81) -> 15000 | Q81: =P81=G81 -> TRUE
B82: =H15 -> 44107 | C82: =SUMIFS($K$125:$K$174,$B$125:$B$174,"<="&B82,$B$125:$B$174,">"&B81) -> 546562.5 | D82: =AM213 -> 848000 | E82: =SUM(C82:D82) -> 1394562.5 | F82: =F213 -> 28800 | G82: =H213 -> 21200 | H82: =SUM(F82:G82) -> 50000 | I82: =AD213 -> 6250 | J82: =AE213 -> 5500 | K82: =AF213 -> 2000 | L82: =AG213 -> 1250 | M82: =AH213 -> 1250 | N82: =AI213 -> 3750 | O82: =AJ213 -> 1200 | P82: =SUM(I82:O82) -> 21200 | Q82: =P82=G82 -> TRUE
B83: =H16 -> 44114 | C83: =SUMIFS($K$125:$K$174,$B$125:$B$174,"<="&B83,$B$125:$B$174,">"&B82) -> 548437.5 | D83: =AM214 -> 846000 | E83: =SUM(C83:D83) -> 1394437.5 | F83: =F214 -> 28850 | G83: =H214 -> 21150 | H83: =SUM(F83:G83) -> 50000 | I83: =AD214 -> 6250 | J83: =AE214 -> 5500 | K83: =AF214 -> 2000 | L83: =AG214 -> 1250 | M83: =AH214 -> 1250 | N83: =AI214 -> 3750 | O83: =AJ214 -> 1150 | P83: =SUM(I83:O83) -> 21150 | Q83: =P83=G83 -> TRUE
B84: =H17 -> 44121 | C84: =SUMIFS($K$125:$K$174,$B$125:$B$174,"<="&B84,$B$125:$B$174,">"&B83) -> 550312.5 | D84: =AM215 -> 450000 | E84: =SUM(C84:D84) -> 1000312.5 | F84: =F215 -> 28900 | G84: =H215 -> 15000 | H84: =SUM(F84:G84) -> 43900 | I84: =AD215 -> 3750 | J84: =AE215 -> 3300 | K84: =AF215 -> 1200 | L84: =AG215 -> 750 | M84: =AH215 -> 750 | N84: =AI215 -> 2250 | O84: =AJ215 -> 3000 | P84: =SUM(I84:O84) -> 15000 | Q84: =P84=G84 -> TRUE
B85: =H18 -> 44128 | C85: =SUMIFS($K$125:$K$174,$B$125:$B$174,"<="&B85,$B$125:$B$174,">"&B84) -> 552187.5 | D85: =AM216 -> 842000 | E85: =SUM(C85:D85) -> 1394187.5 | F85: =F216 -> 28950 | G85: =H216 -> 21050 | H85: =SUM(F85:G85) -> 50000 | I85: =AD216 -> 6250 | J85: =AE216 -> 5500 | K85: =AF216 -> 2000 | L85: =AG216 -> 1250 | M85: =AH216 -> 1250 | N85: =AI216 -> 3750 | O85: =AJ216 -> 1050 | P85: =SUM(I85:O85) -> 21050 | Q85: =P85=G85 -> TRUE
B86: =H19 -> 44135 | C86: =SUMIFS($K$125:$K$174,$B$125:$B$174,"<="&B86,$B$125:$B$174,">"&B85) -> 554062.5 | D86: =AM217 -> 450000 | E86: =SUM(C86:D86) -> 1004062.5 | F86: =F217 -> 29000 | G86: =H217 -> 15000 | H86: =SUM(F86:G86) -> 44000 | I86: =AD217 -> 3750 | J86: =AE217 -> 3300 | K86: =AF217 -> 1200 | L86: =AG217 -> 750 | M86: =AH217 -> 750 | N86: =AI217 -> 2250 | O86: =AJ217 -> 3000 | P86: =SUM(I86:O86) -> 15000 | Q86: =P86=G86 -> TRUE
B87: =H20 -> 44142 | C87: =SUMIFS($K$125:$K$174,$B$125:$B$174,"<="&B87,$B$125:$B$174,">"&B86) -> 555937.5 | D87: =AM218 -> 1257000 | E87: =SUM(C87:D87) -> 1812937.5 | F87: =F218 -> 29050 | G87: =H218 -> 20950 | H87: =SUM(F87:G87) -> 50000 | I87: =AD218 -> 10000 | J87: =AE218 -> 8800 | K87: =AF218 -> 2150 | L87: =AG218 -> 0 | M87: =AH218 -> 0 | N87: =AI218 -> 0 | O87: =AJ218 -> 0 | P87: =SUM(I87:O87) -> 20950 | Q87: =P87=G87 -> TRUE
... B114: =H47 -> 44352 | C114: =SUMIFS($K$125:$K$174,$B$125:$B$174,"<="&B114,$B$125:$B$174,">"&B113) -> 562500 | D114: =AM245 -> 1500000 | E114: =SUM(C114:D114) -> 2062500 | F114: =F245 -> 30000 | G114: =H245 -> 20000 | H114: =SUM(F114:G114) -> 50000 | I114: =AD245 -> 12500 | J114: =AE245 -> 7500 | K114: =AF245 -> 0 | L114: =AG245 -> 0 | M114: =AH245 -> 0 | N114: =AI245 -> 0 | O114: =AJ245 -> 0 | P114: =SUM(I114:O114) -> 20000 | Q114: =P114=G114 -> TRUE
C115: =SUM(C75:C114) -> 22500000 | D115: =SUM(D75:D114) -> 30611500 | E115: =SUM(E75:E114) -> 53111500
B116: Rec | C116: =C115-'CaseSolution (Original)'!C115 -> 0 | D116: =D115-'CaseSolution (Original)'!D115 -> 0 | E116: =E115-'CaseSolution (Original)'!E115 -> 0
A117: Season Ticket Data
B119: Total Home Games | D119: =homeGames -> 40
B120: Season Ticket Price ($) | D120: =soldPrice -> 750
A122: Weekly Data
B124: Week ending | C124: Date Sold | D124: # Of Tickets Sold (In Month) | E124: # Of Tickets Sold (Following Month) | F124: Cash Received | G124: Cumul Cash Received | H124: Home Games Played | I124: % Home Games Played | J124: Cumul Revenue | K124: Revenue | L124: Unearned Revenue Balance | M124: Cumul # Tickets Sold | N124: Month End (Date Sold) | O124: Month End (Week Ending) | P124: Cumul Revenue New Tickets | Q124: Cumul Revenue Old Tickets | R124: Cumul Revenue Recognized | S124: Check
B125: =B8 -> 44009 | C125: =C8 -> 44003 | D125: =(D8/7)*$F8 -> 4800 | E125: =(E8/7)*$F8 -> 0 | F125: =(D125+E125)*$D$120 -> 3600000 | G125: =SUM($F$125:$F125) -> 3600000 | H125: =COUNTIF($H$8:$H$47,"<="&B125) -> 0 | I125: =H125/$D$119 -> 0 | J125: =I125*G125 -> 0 | K125: 0 | L125: =G125-J125 -> 3600000 | M125: =SUM($D$125:$E125) -> 4800 | N125: =EOMONTH(C125,0) -> 44012 | O125: =EOMONTH(B125,0) -> 44012
B126: =B9 -> 44016 | C126: =C9 -> 44010 | D126: =(D9/7)*$F9 -> 1628.5714 | E126: =(E9/7)*$F9 -> 2171.4286 | F126: =(D126+E126)*$D$120 -> 2850000 | G126: =SUM($F$125:$F126) -> 6450000 | H126: =COUNTIF($H$8:$H$47,"<="&B126) -> 0 | I126: =H126/$D$119 -> 0 | J126: =I126*G126 -> 0 | K126: =J126-J125 -> 0 | L126: =G126-J126 -> 6450000 | M126: =SUM($D$125:$E126) -> 8600 | N126: =EOMONTH(C126,0) -> 44012 | O126: =EOMONTH(B126,0) -> 44043 | P126: =$I126*F126 -> 0 | Q126: =$I126*G125 -> 0 | R126: =SUM(P126:Q126) -> 0 | S126: =R126=J126 -> TRUE
B127: =B10 -> 44023 | C127: =C10 -> 44017 | D127: =(D10/7)*$F10 -> 3400 | E127: =(E10/7)*$F10 -> 0 | F127: =(D127+E127)*$D$120 -> 2550000 | G127: =SUM($F$125:$F127) -> 9000000 | H127: =COUNTIF($H$8:$H$47,"<="&B127) -> 0 | I127: =H127/$D$119 -> 0 | J127: =I127*G127 -> 0 | K127: =J127-J126 -> 0 | L127: =G127-J127 -> 9000000 | M127: =SUM($D$125:$E127) -> 12000 | N127: =EOMONTH(C127,0) -> 44043 | O127: =EOMONTH(B127,0) -> 44043 | P127: =$I127*F127 -> 0 | Q127: =$I127*G126 -> 0 | R127: =SUM(P127:Q127) -> 0 | S127: =R127=J127 -> TRUE
B128: =B11 -> 44030 | C128: =C11 -> 44024 | D128: =(D11/7)*$F11 -> 2800 | E128: =(E11/7)*$F11 -> 0 | F128: =(D128+E128)*$D$120 -> 2100000 | G128: =SUM($F$125:$F128) -> 11100000 | H128: =COUNTIF($H$8:$H$47,"<="&B128) -> 0 | I128: =H128/$D$119 -> 0 | J128: =I128*G128 -> 0 | K128: =J128-J127 -> 0 | L128: =G128-J128 -> 11100000 | M128: =SUM($D$125:$E128) -> 14800 | N128: =EOMONTH(C128,0) -> 44043 | O128: =EOMONTH(B128,0) -> 44043 | P128: =$I128*F128 -> 0 | Q128: =$I128*G127 -> 0 | R128: =SUM(P128:Q128) -> 0 | S128: =R128=J128 -> TRUE
B129: =B12 -> 44037 | C129: =C12 -> 44031 | D129: =(D12/7)*$F12 -> 2700 | E129: =(E12/7)*$F12 -> 0 | F129: =(D129+E129)*$D$120 -> 2025000 | G129: =SUM($F$125:$F129) -> 13125000 | H129: =COUNTIF($H$8:$H$47,"<="&B129) -> 0 | I129: =H129/$D$119 -> 0 | J129: =I129*G129 -> 0 | K129: =J129-J128 -> 0 | L129: =G129-J129 -> 13125000 | M129: =SUM($D$125:$E129) -> 17500 | N129: =EOMONTH(C129,0) -> 44043 | O129: =EOMONTH(B129,0) -> 44043 | P129: =$I129*F129 -> 0 | Q129: =$I129*G128 -> 0 | R129: =SUM(P129:Q129) -> 0 | S129: =R129=J129 -> TRUE
B130: =B13 -> 44044 | C130: =C13 -> 44038 | D130: =(D13/7)*$F13 -> 2357.1429 | E130: =(E13/7)*$F13 -> 392.85714 | F130: =(D130+E130)*$D$120 -> 2062500 | G130: =SUM($F$125:$F130) -> 15187500 | H130: =COUNTIF($H$8:$H$47,"<="&B130) -> 0 | I130: =H130/$D$119 -> 0 | J130: =I130*G130 -> 0 | K130: =J130-J129 -> 0 | L130: =G130-J130 -> 15187500 | M130: =SUM($D$125:$E130) -> 20250 | N130: =EOMONTH(C130,0) -> 44043 | O130: =EOMONTH(B130,0) -> 44074 | P130: =$I130*F130 -> 0 | Q130: =$I130*G129 -> 0 | R130: =SUM(P130:Q130) -> 0 | S130: =R130=J130 -> TRUE
B131: =B14 -> 44051 | C131: =C14 -> 44045 | D131: =(D14/7)*$F14 -> 2600 | E131: =(E14/7)*$F14 -> 0 | F131: =(D131+E131)*$D$120 -> 1950000 | G131: =SUM($F$125:$F131) -> 17137500 | H131: =COUNTIF($H$8:$H$47,"<="&B131) -> 0 | I131: =H131/$D$119 -> 0 | J131: =I131*G131 -> 0 | K131: =J131-J130 -> 0 | L131: =G131-J131 -> 17137500 | M131: =SUM($D$125:$E131) -> 22850 | N131: =EOMONTH(C131,0) -> 44074 | O131: =EOMONTH(B131,0) -> 44074 | P131: =$I131*F131 -> 0 | Q131: =$I131*G130 -> 0 | R131: =SUM(P131:Q131) -> 0 | S131: =R131=J131 -> TRUE
B132: =B15 -> 44058 | C132: =C15 -> 44052 | D132: =(D15/7)*$F15 -> 2800 | E132: =(E15/7)*$F15 -> 0 | F132: =(D132+E132)*$D$120 -> 2100000 | G132: =SUM($F$125:$F132) -> 19237500 | H132: =COUNTIF($H$8:$H$47,"<="&B132) -> 1 | I132: =H132/$D$119 -> 0.025 | J132: =I132*G132 -> 480937.5 | K132: =J132-J131 -> 480937.5 | L132: =G132-J132 -> 18756562 | M132: =SUM($D$125:$E132) -> 25650 | N132: =EOMONTH(C132,0) -> 44074 | O132: =EOMONTH(B132,0) -> 44074 | P132: =$I132*F132 -> 52500 | Q132: =$I132*G131 -> 428437.5 | R132: =SUM(P132:Q132) -> 480937.5 | S132: =R132=J132 -> TRUE
B133: =B16 -> 44065 | C133: =C16 -> 44059 | D133: =(D16/7)*$F16 -> 1400 | E133: =(E16/7)*$F16 -> 0 | F133: =(D133+E133)*$D$120 -> 1050000 | G133: =SUM($F$125:$F133) -> 20287500 | H133: =COUNTIF($H$8:$H$47,"<="&B133) -> 2 | I133: =H133/$D$119 -> 0.05 | J133: =I133*G133 -> 1014375 | K133: =J133-J132 -> 533437.5 | L133: =G133-J133 -> 19273125 | M133: =SUM($D$125:$E133) -> 27050 | N133: =EOMONTH(C133,0) -> 44074 | O133: =EOMONTH(B133,0) -> 44074 | P133: =$I133*F133 -> 52500 | Q133: =$I133*G132 -> 961875 | R133: =SUM(P133:Q133) -> 1014375 | S133: =R133=J133 -> TRUE
B134: =B17 -> 44072 | C134: =C17 -> 44066 | D134: =(D17/7)*$F17 -> 800 | E134: =(E17/7)*$F17 -> 0 | F134: =(D134+E134)*$D$120 -> 600000 | G134: =SUM($F$125:$F134) -> 20887500 | H134: =COUNTIF($H$8:$H$47,"<="&B134) -> 3 | I134: =H134/$D$119 -> 0.075 | J134: =I134*G134 -> 1566562.5 | K134: =J134-J133 -> 552187.5 | L134: =G134-J134 -> 19320938 | M134: =SUM($D$125:$E134) -> 27850 | N134: =EOMONTH(C134,0) -> 44074 | O134: =EOMONTH(B134,0) -> 44074 | P134: =$I134*F134 -> 45000 | Q134: =$I134*G133 -> 1521562.5 | R134: =SUM(P134:Q134) -> 1566562.5 | S134: =R134=J134 -> TRUE
B135: =B18 -> 44079 | C135: =C18 -> 44073 | D135: =(D18/7)*$F18 -> 142.85714 | E135: =(E18/7)*$F18 -> 357.14286 | F135: =(D135+E135)*$D$120 -> 375000 | G135: =SUM($F$125:$F135) -> 21262500 | H135: =COUNTIF($H$8:$H$47,"<="&B135) -> 4 | I135: =H135/$D$119 -> 0.1 | J135: =I135*G135 -> 2126250 | K135: =J135-J134 -> 559687.5 | L135: =G135-J135 -> 19136250 | M135: =SUM($D$125:$E135) -> 28350 | N135: =EOMONTH(C135,0) -> 44074 | O135: =EOMONTH(B135,0) -> 44104 | P135: =$I135*F135 -> 37500 | Q135: =$I135*G134 -> 2088750 | R135: =SUM(P135:Q135) -> 2126250 | S135: =R135=J135 -> TRUE
B136: =B19 -> 44086 | C136: =C19 -> 44080 | D136: =(D19/7)*$F19 -> 200 | E136: =(E19/7)*$F19 -> 0 | F136: =(D136+E136)*$D$120 -> 150000 | G136: =SUM($F$125:$F136) -> 21412500 | H136: =COUNTIF($H$8:$H$47,"<="&B136) -> 5 | I136: =H136/$D$119 -> 0.125 | J136: =I136*G136 -> 2676562.5 | K136: =J136-J135 -> 550312.5 | L136: =G136-J136 -> 18735938 | M136: =SUM($D$125:$E136) -> 28550 | N136: =EOMONTH(C136,0) -> 44104 | O136: =EOMONTH(B136,0) -> 44104 | P136: =$I136*F136 -> 18750 | Q136: =$I136*G135 -> 2657812.5 | R136: =SUM(P136:Q136) -> 2676562.5 | S136: =R136=J136 -> TRUE
B137: =B20 -> 44093 | C137: =C20 -> 44087 | D137: =(D20/7)*$F20 -> 150 | E137: =(E20/7)*$F20 -> 0 | F137: =(D137+E137)*$D$120 -> 112500 | G137: =SUM($F$125:$F137) -> 21525000 | H137: =COUNTIF($H$8:$H$47,"<="&B137) -> 6 | I137: =H137/$D$119 -> 0.15 | J137: =I137*G137 -> 3228750 | K137: =J137-J136 -> 552187.5 | L137: =G137-J137 -> 18296250 | M137: =SUM($D$125:$E137) -> 28700 | N137: =EOMONTH(C137,0) -> 44104 | O137: =EOMONTH(B137,0) -> 44104 | P137: =$I137*F137 -> 16875 | Q137: =$I137*G136 -> 3211875 | R137: =SUM(P137:Q137) -> 3228750 | S137: =R137=J137 -> TRUE
... B155: =B38 -> 44219 | C155: =C38 -> 44213 | D155: =(D38/7)*$F38 -> 50 | E155: =(E38/7)*$F38 -> 0 | F155: =(D155+E155)*$D$120 -> 37500 | G155: =SUM($F$125:$F155) -> 22500000 | H155: =COUNTIF($H$8:$H$47,"<="&B155) -> 22 | I155: =H155/$D$119 -> 0.55 | J155: =I155*G155 -> 12375000 | K155: =J155-J154 -> 582187.5 | L155: =G155-J155 -> 10125000 | M155: =SUM($D$125:$E155) -> 30000 | N155: =EOMONTH(C155,0) -> 44227 | O155: =EOMONTH(B155,0) -> 44227 | P155: =$I155*F155 -> 20625 | Q155: =$I155*G154 -> 12354375 | R155: =SUM(P155:Q155) -> 12375000 | S155: =R155=J155 -> TRUE
B156: =B155+7 -> 44226 | D156: 0 | E156: 0 | F156: =D156*$D$120 -> 0 | G156: =SUM($F$125:$F156) -> 22500000 | H156: =COUNTIF($H$8:$H$47,"<="&B156) -> 23 | I156: =H156/$D$119 -> 0.575 | J156: =I156*G156 -> 12937500 | K156: =J156-J155 -> 562500 | L156: =G156-J156 -> 9562500 | M156: =SUM($D$125:$E156) -> 30000 | P156: =$I156*F156 -> 0 | Q156: =$I156*G155 -> 12937500 | R156: =SUM(P156:Q156) -> 12937500 | S156: =R156=J156 -> TRUE
...

Sheet Tmp
A1: {=company} -> Wichita Warblers Inc
A2: {=topic} -> CFM Topic: Working Capital
A3: TMP SCHEDULE | F3: Constant | G3: Unit | H3: Total
A5: Chapter
A43: End of schedule
