Workbook
Name company: CaseData!$C$55
Name days_per_month: CaseData!$L$33
Name periods: CaseData!$C$57
Name start_date: CaseData!$C$3
Name topic: "CFM Topic: " & CaseData!$C$56

Sheet Working Capital
A1: =company -> Sweet Dreams Co.
A2: {=topic} -> CFM Topic: Working Capital
A3: WORKING CAPITAL SCHEDULE | F3: Constant | G3: Unit | H3: Total | J3: {=EOMONTH( start_date, _xlfn.SEQUENCE( 1, periods, 0, 1 ) )} -> 44592 | K3: 44620 | L3: 44651 | M3: 44681 | N3: 44712 | O3: 44742 | P3: 44773 | Q3: 44804 | R3: 44834 | S3: 44865 | T3: 44895 | U3: 44926
A5: Working capital
E8: Accounts receivable | G8: USD | J8: {=_xlfn.ANCHORARRAY('Accounts Receivables'!J103)} -> 1177500 | K8: 1221863 | L8: 1307818.5 | M8: 1416863.5 | N8: 1523910 | O8: 1630955 | P8: 1736000.5 | Q8: 1846043.5 | R8: 1952091 | S8: 2059136 | T8: 2164182.5 | U8: 2274227.5
E9: Inventory | G9: USD | J9: {=_xlfn.ANCHORARRAY(Inventory!J128)} -> 64959.044 | K9: 70608.896 | L9: 76154.322 | M9: 81489.402 | N9: 87033.586 | O9: 92370.663 | P9: 97912.64 | Q9: 103039.81 | R9: 108792.01 | S9: 113925.51 | T9: 119671.27 | U9: 119671.27
E10: Accounts payable | G10: USD | J10: {=_xlfn.ANCHORARRAY( 'Accounts Payable'!J151)} -> 155978.3 | K10: 169502.84 | L10: 183521.61 | M10: 197908.02 | N10: 211399.22 | O10: 225781.25 | P10: 239281.41 | Q10: 253531.87 | R10: 267117.12 | S10: 281407.67 | T10: 295000.2 | U10: 306591.69
E12: Working capital | G12: USD | J12: {=_xlfn.ANCHORARRAY( J8) +_xlfn.ANCHORARRAY( J9) -_xlfn.ANCHORARRAY( J10)} -> 1086480.7 | K12: 1122969.1 | L12: 1200451.2 | M12: 1300444.9 | N12: 1399544.4 | O12: 1497544.4 | P12: 1594631.7 | Q12: 1695551.4 | R12: 1793765.9 | S12: 1891653.8 | T12: 1988853.6 | U12: 2087307.1
A45: End of schedule

Sheet Accounts Payable
A1: =company -> Sweet Dreams Co.
A2: {=topic} -> CFM Topic: Working Capital
A3: ACCOUNTS PAYABLE SCHEDULE | F3: Constant | G3: Unit | H3: Total | J3: {=EOMONTH( start_date, _xlfn.SEQUENCE( 1, periods, 0, 1 ) )} -> 44592 | K3: 44620 | L3: 44651 | M3: 44681 | N3: 44712 | O3: 44742 | P3: 44773 | Q3: 44804 | R3: 44834 | S3: 44865 | T3: 44895 | U3: 44926
A5: Accounts payable
B7: Payment Terms
C9: Supplier I
E11: Payment terms | F11: =INDEX( CaseData!$L$26:$L$30, MATCH( $C9, CaseData!$I$26:$I$30, 0 ) ) / days_per_month -> 0.5 | G11: months
F13: Months | G13: POs | J13: {=_xlfn.SEQUENCE( 1, periods, 1, 1 )} -> 1 | K13: 2 | L13: 3 | M13: 4 | N13: 5 | O13: 6 | P13: 7 | Q13: 8 | R13: 9 | S13: 10 | T13: 11 | U13: 12
F14: =$F15 - 1 -> 0 | G14: =INDEX( CaseData!$M$26:$M$30, MATCH( $C9, CaseData!$I$26:$I$30, 0 ) ) -> 75000 | J14: {=IF(_xlfn.ANCHORARRAY( J13) - $F14:$F26 < 0, 0, IF(_xlfn.ANCHORARRAY( J13) - $F14:$F26 < INT($F11), 1, IF(_xlfn.ANCHORARRAY( J13) - $F14:$F26 < $F11, MOD($F11, 1), 0 ) ) )} -> 0 | K14: 0 | L14: 0 | M14: 0 | N14: 0 | O14: 0 | P14: 0 | Q14: 0 | R14: 0 | S14: 0 | T14: 0 | U14: 0
F15: {=_xlfn.SEQUENCE( periods, 1, 1, 1 )} -> 1 | G15: {=_xlfn.LET( _xlpm.purchase_orders,_xlfn.ANCHORARRAY( 'Purchasing Plan'!$J$99), _xlpm.suppliers,_xlfn.ANCHORARRAY( 'Purchasing Plan'!$E$99), _xlpm.current_supplier, $C9, _xlpm.zero_row, _xlfn.SEQUENCE( 1, COLUMNS( _xlpm.purchase_orders ), 0, 0 ), IFERROR( TRANSPOSE( INDEX( _xlpm.purchase_orders, MATCH( _xlpm.current_supplier, _xlpm.suppliers, 0 ), 0 ) ), TRANSPOSE( _xlpm.zero_row ) ) )} -> 0 | J15: 0.5 | K15: 0 | L15: 0 | M15: 0 | N15: 0 | O15: 0 | P15: 0 | Q15: 0 | R15: 0 | S15: 0 | T15: 0 | U15: 0
F16: 2 | G16: 0 | J16: 0 | K16: 0.5 | L16: 0 | M16: 0 | N16: 0 | O16: 0 | P16: 0 | Q16: 0 | R16: 0 | S16: 0 | T16: 0 | U16: 0
F17: 3 | G17: 0 | J17: 0 | K17: 0 | L17: 0.5 | M17: 0 | N17: 0 | O17: 0 | P17: 0 | Q17: 0 | R17: 0 | S17: 0 | T17: 0 | U17: 0
F18: 4 | G18: 0 | J18: 0 | K18: 0 | L18: 0 | M18: 0.5 | N18: 0 | O18: 0 | P18: 0 | Q18: 0 | R18: 0 | S18: 0 | T18: 0 | U18: 0
F19: 5 | G19: 0 | J19: 0 | K19: 0 | L19: 0 | M19: 0 | N19: 0.5 | O19: 0 | P19: 0 | Q19: 0 | R19: 0 | S19: 0 | T19: 0 | U19: 0
F20: 6 | G20: 0 | J20: 0 | K20: 0 | L20: 0 | M20: 0 | N20: 0 | O20: 0.5 | P20: 0 | Q20: 0 | R20: 0 | S20: 0 | T20: 0 | U20: 0
F21: 7 | G21: 0 | J21: 0 | K21: 0 | L21: 0 | M21: 0 | N21: 0 | O21: 0 | P21: 0.5 | Q21: 0 | R21: 0 | S21: 0 | T21: 0 | U21: 0
F22: 8 | G22: 0 | J22: 0 | K22: 0 | L22: 0 | M22: 0 | N22: 0 | O22: 0 | P22: 0 | Q22: 0.5 | R22: 0 | S22: 0 | T22: 0 | U22: 0
F23: 9 | G23: 0 | J23: 0 | K23: 0 | L23: 0 | M23: 0 | N23: 0 | O23: 0 | P23: 0 | Q23: 0 | R23: 0.5 | S23: 0 | T23: 0 | U23: 0
F24: 10 | G24: 0 | J24: 0 | K24: 0 | L24: 0 | M24: 0 | N24: 0 | O24: 0 | P24: 0 | Q24: 0 | R24: 0 | S24: 0.5 | T24: 0 | U24: 0
F25: 11 | G25: 0 | J25: 0 | K25: 0 | L25: 0 | M25: 0 | N25: 0 | O25: 0 | P25: 0 | Q25: 0 | R25: 0 | S25: 0 | T25: 0.5 | U25: 0
F26: 12 | G26: 0 | J26: 0 | K26: 0 | L26: 0 | M26: 0 | N26: 0 | O26: 0 | P26: 0 | Q26: 0 | R26: 0 | S26: 0 | T26: 0 | U26: 0.5
E27: Accounts payable closing balance | J27: {=_xlfn.BYCOL(_xlfn.ANCHORARRAY( J14), _xlfn.LAMBDA(_xlpm.month_col, SUMPRODUCT( $G14:$G26, _xlpm.month_col ) ) )} -> 0 | K27: 0 | L27: 0 | M27: 0 | N27: 0 | O27: 0 | P27: 0 | Q27: 0 | R27: 0 | S27: 0 | T27: 0 | U27: 0
E30: Accounts payable opening balance | G30: USD | J30: {=_xlfn.DROP( _xlfn.HSTACK( $G14,_xlfn.ANCHORARRAY( J33) ),, - 1 )} -> 75000 | K30: 0 | L30: 0 | M30: 0 | N30: 0 | O30: 0 | P30: 0 | Q30: 0 | R30: 0 | S30: 0 | T30: 0 | U30: 0
E31: Purchase Orders | G31: USD | J31: {=TRANSPOSE(_xlfn.ANCHORARRAY( $G15) )} -> 0 | K31: 0 | L31: 0 | M31: 0 | N31: 0 | O31: 0 | P31: 0 | Q31: 0 | R31: 0 | S31: 0 | T31: 0 | U31: 0
E32: Payments made to supplier | G32: USD | J32: {=_xlfn.LET( _xlpm.ap_opening,_xlfn.ANCHORARRAY( J30), _xlpm.po,_xlfn.ANCHORARRAY( J31), _xlpm.ap_closing,_xlfn.ANCHORARRAY( J33), ( _xlpm.ap_opening + _xlpm.po - _xlpm.ap_closing ) * - 1 )} -> -75000 | K32: 0 | L32: 0 | M32: 0 | N32: 0 | O32: 0 | P32: 0 | Q32: 0 | R32: 0 | S32: 0 | T32: 0 | U32: 0
E33: Supplier I: Accounts payable closing balance | G33: USD | J33: {=_xlfn.ANCHORARRAY( J27)} -> 0 | K33: 0 | L33: 0 | M33: 0 | N33: 0 | O33: 0 | P33: 0 | Q33: 0 | R33: 0 | S33: 0 | T33: 0 | U33: 0
C36: Supplier II
E38: Payment terms | F38: =INDEX( CaseData!$L$26:$L$30, MATCH( $C36, CaseData!$I$26:$I$30, 0 ) ) / days_per_month -> 1 | G38: months
F40: Months | G40: POs | J40: {=_xlfn.SEQUENCE( 1, periods, 1, 1 )} -> 1 | K40: 2 | L40: 3 | M40: 4 | N40: 5 | O40: 6 | P40: 7 | Q40: 8 | R40: 9 | S40: 10 | T40: 11 | U40: 12
F41: =$F42 - 1 -> 0 | G41: =INDEX( CaseData!$M$26:$M$30, MATCH( $C36, CaseData!$I$26:$I$30, 0 ) ) -> 0 | J41: {=IF(_xlfn.ANCHORARRAY( J40) - $F41:$F53 < 0, 0, IF(_xlfn.ANCHORARRAY( J40) - $F41:$F53 < INT($F38), 1, IF(_xlfn.ANCHORARRAY( J40) - $F41:$F53 < $F38, MOD($F38, 1), 0 ) ) )} -> 0 | K41: 0 | L41: 0 | M41: 0 | N41: 0 | O41: 0 | P41: 0 | Q41: 0 | R41: 0 | S41: 0 | T41: 0 | U41: 0
F42: {=_xlfn.SEQUENCE( periods, 1, 1, 1 )} -> 1 | G42: {=_xlfn.LET( _xlpm.purchase_orders,_xlfn.ANCHORARRAY( 'Purchasing Plan'!$J$99), _xlpm.suppliers,_xlfn.ANCHORARRAY( 'Purchasing Plan'!$E$99), _xlpm.current_supplier, $C36, _xlpm.zero_row, _xlfn.SEQUENCE( 1, COLUMNS( _xlpm.purchase_orders ), 0, 0 ), IFERROR( TRANSPOSE( INDEX( _xlpm.purchase_orders, MATCH( _xlpm.current_supplier, _xlpm.suppliers, 0 ), 0 ) ), TRANSPOSE( _xlpm.zero_row ) ) )} -> 75542.091 | J42: 1 | K42: 0 | L42: 0 | M42: 0 | N42: 0 | O42: 0 | P42: 0 | Q42: 0 | R42: 0 | S42: 0 | T42: 0 | U42: 0
F43: 2 | G43: 82056.489 | J43: 0 | K43: 1 | L43: 0 | M43: 0 | N43: 0 | O43: 0 | P43: 0 | Q43: 0 | R43: 0 | S43: 0 | T43: 0 | U43: 0
F44: 3 | G44: 88960.502 | J44: 0 | K44: 0 | L44: 1 | M44: 0 | N44: 0 | O44: 0 | P44: 0 | Q44: 0 | R44: 0 | S44: 0 | T44: 0 | U44: 0
F45: 4 | G45: 95851.232 | J45: 0 | K45: 0 | L45: 0 | M45: 1 | N45: 0 | O45: 0 | P45: 0 | Q45: 0 | R45: 0 | S45: 0 | T45: 0 | U45: 0
F46: 5 | G46: 102444.86 | J46: 0 | K46: 0 | L46: 0 | M46: 0 | N46: 1 | O46: 0 | P46: 0 | Q46: 0 | R46: 0 | S46: 0 | T46: 0 | U46: 0
F47: 6 | G47: 109334.06 | J47: 0 | K47: 0 | L47: 0 | M47: 0 | N47: 0 | O47: 1 | P47: 0 | Q47: 0 | R47: 0 | S47: 0 | T47: 0 | U47: 0
F48: 7 | G48: 115930.64 | J48: 0 | K48: 0 | L48: 0 | M48: 0 | N48: 0 | O48: 0 | P48: 1 | Q48: 0 | R48: 0 | S48: 0 | T48: 0 | U48: 0
F49: 8 | G49: 122731.55 | J49: 0 | K49: 0 | L49: 0 | M49: 0 | N49: 0 | O49: 0 | P49: 0 | Q49: 1 | R49: 0 | S49: 0 | T49: 0 | U49: 0
F50: 9 | G50: 129267.18 | J50: 0 | K50: 0 | L50: 0 | M50: 0 | N50: 0 | O50: 0 | P50: 0 | Q50: 0 | R50: 1 | S50: 0 | T50: 0 | U50: 0
F51: 10 | G51: 136216.23 | J51: 0 | K51: 0 | L51: 0 | M51: 0 | N51: 0 | O51: 0 | P51: 0 | Q51: 0 | R51: 0 | S51: 1 | T51: 0 | U51: 0
F52: 11 | G52: 142756.08 | J52: 0 | K52: 0 | L52: 0 | M52: 0 | N52: 0 | O52: 0 | P52: 0 | Q52: 0 | R52: 0 | S52: 0 | T52: 1 | U52: 0
F53: 12 | G53: 148306.6 | J53: 0 | K53: 0 | L53: 0 | M53: 0 | N53: 0 | O53: 0 | P53: 0 | Q53: 0 | R53: 0 | S53: 0 | T53: 0 | U53: 1
E54: Accounts payable closing balance | J54: {=_xlfn.BYCOL(_xlfn.ANCHORARRAY( J41), _xlfn.LAMBDA(_xlpm.month_col, SUMPRODUCT( $G41:$G53, _xlpm.month_col ) ) )} -> 75542.091 | K54: 82056.489 | L54: 88960.502 | M54: 95851.232 | N54: 102444.86 | O54: 109334.06 | P54: 115930.64 | Q54: 122731.55 | R54: 129267.18 | S54: 136216.23 | T54: 142756.08 | U54: 148306.6
E57: Accounts payable opening balance | G57: USD | J57: {=_xlfn.DROP( _xlfn.HSTACK( $G41,_xlfn.ANCHORARRAY( J60) ),, - 1 )} -> 0 | K57: 75542.091 | L57: 82056.489 | M57: 88960.502 | N57: 95851.232 | O57: 102444.86 | P57: 109334.06 | Q57: 115930.64 | R57: 122731.55 | S57: 129267.18 | T57: 136216.23 | U57: 142756.08
E58: Purchase Orders | G58: USD | J58: {=TRANSPOSE(_xlfn.ANCHORARRAY( $G42) )} -> 75542.091 | K58: 82056.489 | L58: 88960.502 | M58: 95851.232 | N58: 102444.86 | O58: 109334.06 | P58: 115930.64 | Q58: 122731.55 | R58: 129267.18 | S58: 136216.23 | T58: 142756.08 | U58: 148306.6
E59: Payments made to supplier | G59: USD | J59: {=_xlfn.LET( _xlpm.ap_opening,_xlfn.ANCHORARRAY( J57), _xlpm.po,_xlfn.ANCHORARRAY( J58), _xlpm.ap_closing,_xlfn.ANCHORARRAY( J60), ( _xlpm.ap_opening + _xlpm.po - _xlpm.ap_closing ) * - 1 )} -> 0 | K59: -75542.091 | L59: -82056.489 | M59: -88960.502 | N59: -95851.232 | O59: -102444.86 | P59: -109334.06 | Q59: -115930.64 | R59: -122731.55 | S59: -129267.18 | T59: -136216.23 | U59: -142756.08
E60: Supplier II: Accounts payable closing balance | G60: USD | J60: {=_xlfn.ANCHORARRAY( J54)} -> 75542.091 | K60: 82056.489 | L60: 88960.502 | M60: 95851.232 | N60: 102444.86 | O60: 109334.06 | P60: 115930.64 | Q60: 122731.55 | R60: 129267.18 | S60: 136216.23 | T60: 142756.08 | U60: 148306.6
C63: Supplier III
E65: Payment terms | F65: =INDEX( CaseData!$L$26:$L$30, MATCH( $C63, CaseData!$I$26:$I$30, 0 ) ) / days_per_month -> 1 | G65: months
F67: Months | G67: POs | J67: {=_xlfn.SEQUENCE( 1, periods, 1, 1 )} -> 1 | K67: 2 | L67: 3 | M67: 4 | N67: 5 | O67: 6 | P67: 7 | Q67: 8 | R67: 9 | S67: 10 | T67: 11 | U67: 12
F68: =$F69 - 1 -> 0 | G68: =INDEX( CaseData!$M$26:$M$30, MATCH( $C63, CaseData!$I$26:$I$30, 0 ) ) -> 0 | J68: {=IF(_xlfn.ANCHORARRAY( J67) - $F68:$F80 < 0, 0, IF(_xlfn.ANCHORARRAY( J67) - $F68:$F80 < INT($F65), 1, IF(_xlfn.ANCHORARRAY( J67) - $F68:$F80 < $F65, MOD($F65, 1), 0 ) ) )} -> 0 | K68: 0 | L68: 0 | M68: 0 | N68: 0 | O68: 0 | P68: 0 | Q68: 0 | R68: 0 | S68: 0 | T68: 0 | U68: 0
F69: {=_xlfn.SEQUENCE( periods, 1, 1, 1 )} -> 1 | G69: {=_xlfn.LET( _xlpm.purchase_orders,_xlfn.ANCHORARRAY( 'Purchasing Plan'!$J$99), _xlpm.suppliers,_xlfn.ANCHORARRAY( 'Purchasing Plan'!$E$99), _xlpm.current_supplier, $C63, _xlpm.zero_row, _xlfn.SEQUENCE( 1, COLUMNS( _xlpm.purchase_orders ), 0, 0 ), IFERROR( TRANSPOSE( INDEX( _xlpm.purchase_orders, MATCH( _xlpm.current_supplier, _xlpm.suppliers, 0 ), 0 ) ), TRANSPOSE( _xlpm.zero_row ) ) )} -> 34809.008 | J69: 1 | K69: 0 | L69: 0 | M69: 0 | N69: 0 | O69: 0 | P69: 0 | Q69: 0 | R69: 0 | S69: 0 | T69: 0 | U69: 0
F70: 2 | G70: 37826.19 | J70: 0 | K70: 1 | L70: 0 | M70: 0 | N70: 0 | O70: 0 | P70: 0 | Q70: 0 | R70: 0 | S70: 0 | T70: 0 | U70: 0
F71: 3 | G71: 40956.774 | J71: 0 | K71: 0 | L71: 1 | M71: 0 | N71: 0 | O71: 0 | P71: 0 | Q71: 0 | R71: 0 | S71: 0 | T71: 0 | U71: 0
F72: 4 | G72: 44167.262 | J72: 0 | K72: 0 | L72: 0 | M72: 1 | N72: 0 | O72: 0 | P72: 0 | Q72: 0 | R72: 0 | S72: 0 | T72: 0 | U72: 0
F73: 5 | G73: 47178.342 | J73: 0 | K73: 0 | L73: 0 | M73: 0 | N73: 1 | O73: 0 | P73: 0 | Q73: 0 | R73: 0 | S73: 0 | T73: 0 | U73: 0
F74: 6 | G74: 50387.853 | J74: 0 | K74: 0 | L74: 0 | M74: 0 | N74: 0 | O74: 1 | P74: 0 | Q74: 0 | R74: 0 | S74: 0 | T74: 0 | U74: 0
F75: 7 | G75: 53400.931 | J75: 0 | K75: 0 | L75: 0 | M75: 0 | N75: 0 | O75: 0 | P75: 1 | Q75: 0 | R75: 0 | S75: 0 | T75: 0 | U75: 0
F76: 8 | G76: 56580.479 | J76: 0 | K76: 0 | L76: 0 | M76: 0 | N76: 0 | O76: 0 | P76: 0 | Q76: 1 | R76: 0 | S76: 0 | T76: 0 | U76: 0
F77: 9 | G77: 59611.198 | J77: 0 | K77: 0 | L77: 0 | M77: 0 | N77: 0 | O77: 0 | P77: 0 | Q77: 0 | R77: 1 | S77: 0 | T77: 0 | U77: 0
F78: 10 | G78: 62801.658 | J78: 0 | K78: 0 | L78: 0 | M78: 0 | N78: 0 | O78: 0 | P78: 0 | Q78: 0 | R78: 0 | S78: 1 | T78: 0 | U78: 0
F79: 11 | G79: 65834.028 | J79: 0 | K79: 0 | L79: 0 | M79: 0 | N79: 0 | O79: 0 | P79: 0 | Q79: 0 | R79: 0 | S79: 0 | T79: 1 | U79: 0
F80: 12 | G80: 68423.427 | J80: 0 | K80: 0 | L80: 0 | M80: 0 | N80: 0 | O80: 0 | P80: 0 | Q80: 0 | R80: 0 | S80: 0 | T80: 0 | U80: 1
E81: Accounts payable closing balance | J81: {=_xlfn.BYCOL(_xlfn.ANCHORARRAY( J68), _xlfn.LAMBDA(_xlpm.month_col, SUMPRODUCT( $G68:$G80, _xlpm.month_col ) ) )} -> 34809.008 | K81: 37826.19 | L81: 40956.774 | M81: 44167.262 | N81: 47178.342 | O81: 50387.853 | P81: 53400.931 | Q81: 56580.479 | R81: 59611.198 | S81: 62801.658 | T81: 65834.028 | U81: 68423.427
E84: Accounts payable opening balance | G84: USD | J84: {=_xlfn.DROP( _xlfn.HSTACK( $G68,_xlfn.ANCHORARRAY( J87) ),, - 1 )} -> 0 | K84: 34809.008 | L84: 37826.19 | M84: 40956.774 | N84: 44167.262 | O84: 47178.342 | P84: 50387.853 | Q84: 53400.931 | R84: 56580.479 | S84: 59611.198 | T84: 62801.658 | U84: 65834.028
E85: Purchase Orders | G85: USD | J85: {=TRANSPOSE(_xlfn.ANCHORARRAY( $G69) )} -> 34809.008 | K85: 37826.19 | L85: 40956.774 | M85: 44167.262 | N85: 47178.342 | O85: 50387.853 | P85: 53400.931 | Q85: 56580.479 | R85: 59611.198 | S85: 62801.658 | T85: 65834.028 | U85: 68423.427
E86: Payments made to supplier | G86: USD | J86: {=_xlfn.LET( _xlpm.ap_opening,_xlfn.ANCHORARRAY( J84), _xlpm.po,_xlfn.ANCHORARRAY( J85), _xlpm.ap_closing,_xlfn.ANCHORARRAY( J87), ( _xlpm.ap_opening + _xlpm.po - _xlpm.ap_closing ) * - 1 )} -> 0 | K86: -34809.008 | L86: -37826.19 | M86: -40956.774 | N86: -44167.262 | O86: -47178.342 | P86: -50387.853 | Q86: -53400.931 | R86: -56580.479 | S86: -59611.198 | T86: -62801.658 | U86: -65834.028
E87: Supplier III: Accounts payable closing balance | G87: USD | J87: {=_xlfn.ANCHORARRAY( J81)} -> 34809.008 | K87: 37826.19 | L87: 40956.774 | M87: 44167.262 | N87: 47178.342 | O87: 50387.853 | P87: 53400.931 | Q87: 56580.479 | R87: 59611.198 | S87: 62801.658 | T87: 65834.028 | U87: 68423.427
C90: Supplier IV
E92: Payment terms | F92: =INDEX( CaseData!$L$26:$L$30, MATCH( $C90, CaseData!$I$26:$I$30, 0 ) ) / days_per_month -> 1 | G92: months
F94: Months | G94: POs | J94: {=_xlfn.SEQUENCE( 1, periods, 1, 1 )} -> 1 | K94: 2 | L94: 3 | M94: 4 | N94: 5 | O94: 6 | P94: 7 | Q94: 8 | R94: 9 | S94: 10 | T94: 11 | U94: 12
F95: =$F96 - 1 -> 0 | G95: =INDEX( CaseData!$M$26:$M$30, MATCH( $C90, CaseData!$I$26:$I$30, 0 ) ) -> 100000 | J95: {=IF(_xlfn.ANCHORARRAY( J94) - $F95:$F107 < 0, 0, IF(_xlfn.ANCHORARRAY( J94) - $F95:$F107 < INT($F92), 1, IF(_xlfn.ANCHORARRAY( J94) - $F95:$F107 < $F92, MOD($F92, 1), 0 ) ) )} -> 0 | K95: 0 | L95: 0 | M95: 0 | N95: 0 | O95: 0 | P95: 0 | Q95: 0 | R95: 0 | S95: 0 | T95: 0 | U95: 0
F96: {=_xlfn.SEQUENCE( periods, 1, 1, 1 )} -> 1 | G96: {=_xlfn.LET( _xlpm.purchase_orders,_xlfn.ANCHORARRAY( 'Purchasing Plan'!$J$99), _xlpm.suppliers,_xlfn.ANCHORARRAY( 'Purchasing Plan'!$E$99), _xlpm.current_supplier, $C90, _xlpm.zero_row, _xlfn.SEQUENCE( 1, COLUMNS( _xlpm.purchase_orders ), 0, 0 ), IFERROR( TRANSPOSE( INDEX( _xlpm.purchase_orders, MATCH( _xlpm.current_supplier, _xlpm.suppliers, 0 ), 0 ) ), TRANSPOSE( _xlpm.zero_row ) ) )} -> 14291.746 | J96: 1 | K96: 0 | L96: 0 | M96: 0 | N96: 0 | O96: 0 | P96: 0 | Q96: 0 | R96: 0 | S96: 0 | T96: 0 | U96: 0
F97: 2 | G97: 15564.201 | J97: 0 | K97: 1 | L97: 0 | M97: 0 | N97: 0 | O97: 0 | P97: 0 | Q97: 0 | R97: 0 | S97: 0 | T97: 0 | U97: 0
F98: 3 | G98: 16731.417 | J98: 0 | K98: 0 | L98: 1 | M98: 0 | N98: 0 | O98: 0 | P98: 0 | Q98: 0 | R98: 0 | S98: 0 | T98: 0 | U98: 0
F99: 4 | G99: 18139.487 | J99: 0 | K99: 0 | L99: 0 | M99: 1 | N99: 0 | O99: 0 | P99: 0 | Q99: 0 | R99: 0 | S99: 0 | T99: 0 | U99: 0
F100: 5 | G100: 19307.939 | J100: 0 | K100: 0 | L100: 0 | M100: 0 | N100: 1 | O100: 0 | P100: 0 | Q100: 0 | R100: 0 | S100: 0 | T100: 0 | U100: 0
F101: 6 | G101: 20714.923 | J101: 0 | K101: 0 | L101: 0 | M101: 0 | N101: 0 | O101: 1 | P101: 0 | Q101: 0 | R101: 0 | S101: 0 | T101: 0 | U101: 0
F102: 7 | G102: 21885.815 | J102: 0 | K102: 0 | L102: 0 | M102: 0 | N102: 0 | O102: 0 | P102: 1 | Q102: 0 | R102: 0 | S102: 0 | T102: 0 | U102: 0
F103: 8 | G103: 23304.562 | J103: 0 | K103: 0 | L103: 0 | M103: 0 | N103: 0 | O103: 0 | P103: 0 | Q103: 1 | R103: 0 | S103: 0 | T103: 0 | U103: 0
F104: 9 | G104: 24592.121 | J104: 0 | K104: 0 | L104: 0 | M104: 0 | N104: 0 | O104: 0 | P104: 0 | Q104: 0 | R104: 1 | S104: 0 | T104: 0 | U104: 0
F105: 10 | G105: 25879.627 | J105: 0 | K105: 0 | L105: 0 | M105: 0 | N105: 0 | O105: 0 | P105: 0 | Q105: 0 | R105: 0 | S105: 1 | T105: 0 | U105: 0
F106: 11 | G106: 27167.251 | J106: 0 | K106: 0 | L106: 0 | M106: 0 | N106: 0 | O106: 0 | P106: 0 | Q106: 0 | R106: 0 | S106: 0 | T106: 1 | U106: 0
F107: 12 | G107: 28325.994 | J107: 0 | K107: 0 | L107: 0 | M107: 0 | N107: 0 | O107: 0 | P107: 0 | Q107: 0 | R107: 0 | S107: 0 | T107: 0 | U107: 1
E108: Accounts payable closing balance | J108: {=_xlfn.BYCOL(_xlfn.ANCHORARRAY( J95), _xlfn.LAMBDA(_xlpm.month_col, SUMPRODUCT( $G95:$G107, _xlpm.month_col ) ) )} -> 14291.746 | K108: 15564.201 | L108: 16731.417 | M108: 18139.487 | N108: 19307.939 | O108: 20714.923 | P108: 21885.815 | Q108: 23304.562 | R108: 24592.121 | S108: 25879.627 | T108: 27167.251 | U108: 28325.994
E111: Accounts payable opening balance | G111: USD | J111: {=_xlfn.DROP( _xlfn.HSTACK( $G95,_xlfn.ANCHORARRAY( J114) ),, - 1 )} -> 100000 | K111: 14291.746 | L111: 15564.201 | M111: 16731.417 | N111: 18139.487 | O111: 19307.939 | P111: 20714.923 | Q111: 21885.815 | R111: 23304.562 | S111: 24592.121 | T111: 25879.627 | U111: 27167.251
E112: Purchase Orders | G112: USD | J112: {=TRANSPOSE(_xlfn.ANCHORARRAY( $G96) )} -> 14291.746 | K112: 15564.201 | L112: 16731.417 | M112: 18139.487 | N112: 19307.939 | O112: 20714.923 | P112: 21885.815 | Q112: 23304.562 | R112: 24592.121 | S112: 25879.627 | T112: 27167.251 | U112: 28325.994
E113: Payments made to supplier | G113: USD | J113: {=_xlfn.LET( _xlpm.ap_opening,_xlfn.ANCHORARRAY( J111), _xlpm.po,_xlfn.ANCHORARRAY( J112), _xlpm.ap_closing,_xlfn.ANCHORARRAY( J114), ( _xlpm.ap_opening + _xlpm.po - _xlpm.ap_closing ) * - 1 )} -> -100000 | K113: -14291.746 | L113: -15564.201 | M113: -16731.417 | N113: -18139.487 | O113: -19307.939 | P113: -20714.923 | Q113: -21885.815 | R113: -23304.562 | S113: -24592.121 | T113: -25879.627 | U113: -27167.251
E114: Supplier IV: Accounts payable closing balance | G114: USD | J114: {=_xlfn.ANCHORARRAY( J108)} -> 14291.746 | K114: 15564.201 | L114: 16731.417 | M114: 18139.487 | N114: 19307.939 | O114: 20714.923 | P114: 21885.815 | Q114: 23304.562 | R114: 24592.121 | S114: 25879.627 | T114: 27167.251 | U114: 28325.994
C117: Supplier V
E119: Payment terms | F119: =INDEX( CaseData!$L$26:$L$30, MATCH( $C117, CaseData!$I$26:$I$30, 0 ) ) / days_per_month -> 0.5 | G119: months
F121: Months | G121: POs | J121: {=_xlfn.SEQUENCE( 1, periods, 1, 1 )} -> 1 | K121: 2 | L121: 3 | M121: 4 | N121: 5 | O121: 6 | P121: 7 | Q121: 8 | R121: 9 | S121: 10 | T121: 11 | U121: 12
F122: =$F123 - 1 -> 0 | G122: =INDEX( CaseData!$M$26:$M$30, MATCH( $C117, CaseData!$I$26:$I$30, 0 ) ) -> 75000 | J122: {=IF(_xlfn.ANCHORARRAY( J121) - $F122:$F134 < 0, 0, IF(_xlfn.ANCHORARRAY( J121) - $F122:$F134 < INT($F119), 1, IF(_xlfn.ANCHORARRAY( J121) - $F122:$F134 < $F119, MOD($F119, 1), 0 ) ) )} -> 0 | K122: 0 | L122: 0 | M122: 0 | N122: 0 | O122: 0 | P122: 0 | Q122: 0 | R122: 0 | S122: 0 | T122: 0 | U122: 0
F123: {=_xlfn.SEQUENCE( periods, 1, 1, 1 )} -> 1 | G123: {=_xlfn.LET( _xlpm.purchase_orders,_xlfn.ANCHORARRAY( 'Purchasing Plan'!$J$99), _xlpm.suppliers,_xlfn.ANCHORARRAY( 'Purchasing Plan'!$E$99), _xlpm.current_supplier, $C117, _xlpm.zero_row, _xlfn.SEQUENCE( 1, COLUMNS( _xlpm.purchase_orders ), 0, 0 ), IFERROR( TRANSPOSE( INDEX( _xlpm.purchase_orders, MATCH( _xlpm.current_supplier, _xlpm.suppliers, 0 ), 0 ) ), TRANSPOSE( _xlpm.zero_row ) ) )} -> 62670.904 | J123: 0.5 | K123: 0 | L123: 0 | M123: 0 | N123: 0 | O123: 0 | P123: 0 | Q123: 0 | R123: 0 | S123: 0 | T123: 0 | U123: 0
F124: 2 | G124: 68111.925 | J124: 0 | K124: 0.5 | L124: 0 | M124: 0 | N124: 0 | O124: 0 | P124: 0 | Q124: 0 | R124: 0 | S124: 0 | T124: 0 | U124: 0
F125: 3 | G125: 73745.827 | J125: 0 | K125: 0 | L125: 0.5 | M125: 0 | N125: 0 | O125: 0 | P125: 0 | Q125: 0 | R125: 0 | S125: 0 | T125: 0 | U125: 0
F126: 4 | G126: 79500.084 | J126: 0 | K126: 0 | L126: 0 | M126: 0.5 | N126: 0 | O126: 0 | P126: 0 | Q126: 0 | R126: 0 | S126: 0 | T126: 0 | U126: 0
F127: 5 | G127: 84936.154 | J127: 0 | K127: 0 | L127: 0 | M127: 0 | N127: 0.5 | O127: 0 | P127: 0 | Q127: 0 | R127: 0 | S127: 0 | T127: 0 | U127: 0
F128: 6 | G128: 90688.831 | J128: 0 | K128: 0 | L128: 0 | M128: 0 | N128: 0 | O128: 0.5 | P128: 0 | Q128: 0 | R128: 0 | S128: 0 | T128: 0 | U128: 0
F129: 7 | G129: 96128.044 | J129: 0 | K129: 0 | L129: 0 | M129: 0 | N129: 0 | O129: 0 | P129: 0.5 | Q129: 0 | R129: 0 | S129: 0 | T129: 0 | U129: 0
...

Sheet Purchasing Plan
A1: =company -> Sweet Dreams Co.
A2: {=topic} -> CFM Topic: Working Capital
A3: PURCHASING PLAN SCHEDULE | F3: Constant | G3: Unit | H3: Total | J3: {=EOMONTH( start_date, _xlfn.SEQUENCE( 1, periods, 0, 1 ) )} -> 44592 | K3: 44620 | L3: 44651 | M3: 44681 | N3: 44712 | O3: 44742 | P3: 44773 | Q3: 44804 | R3: 44834 | S3: 44865 | T3: 44895 | U3: 44926
A5: Ingredients used in product manufactured
E8: Product A
E9: {=TRANSPOSE( CaseData!$C$39:$J$39 )} -> Flour | F9: {=TRANSPOSE( CaseData!$C40:$J40)} -> 0.3 | G9: kg | J9: {=_xlfn.LET( _xlpm.volume, INDEX( Inventory!$J$91:$U$93, MATCH( $E8,_xlfn.ANCHORARRAY( Inventory!$E$59), 0), 0 ), _xlpm.quantities, INDEX(_xlfn.ANCHORARRAY( $F9), 0, 1 ), _xlpm.volume * _xlpm.quantities)} -> 32270.368 | K9: 35002.738 | L9: 38091.168 | M9: 40965.969 | N9: 43840.876 | O9: 46715.572 | P9: 49590.478 | Q9: 52394.741 | R9: 55128.818 | S9: 58145.932 | T9: 60882.869 | U9: 63245.766
E10: Sugar | F10: 0.25 | G10: kg | J10: 26891.973 | K10: 29168.948 | L10: 31742.64 | M10: 34138.308 | N10: 36534.063 | O10: 38929.643 | P10: 41325.398 | Q10: 43662.284 | R10: 45940.682 | S10: 48454.943 | T10: 50735.724 | U10: 52704.805
E11: Butter | F11: 0.15 | G11: kg | J11: 16135.184 | K11: 17501.369 | L11: 19045.584 | M11: 20482.985 | N11: 21920.438 | O11: 23357.786 | P11: 24795.239 | Q11: 26197.371 | R11: 27564.409 | S11: 29072.966 | T11: 30441.434 | U11: 31622.883
E12: Milk | F12: 0.15 | G12: kg | J12: 16135.184 | K12: 17501.369 | L12: 19045.584 | M12: 20482.985 | N12: 21920.438 | O12: 23357.786 | P12: 24795.239 | Q12: 26197.371 | R12: 27564.409 | S12: 29072.966 | T12: 30441.434 | U12: 31622.883
E13: Eggs | F13: 0.15 | G13: kg | J13: 16135.184 | K13: 17501.369 | L13: 19045.584 | M13: 20482.985 | N13: 21920.438 | O13: 23357.786 | P13: 24795.239 | Q13: 26197.371 | R13: 27564.409 | S13: 29072.966 | T13: 30441.434 | U13: 31622.883
E14: Chocolate | F14: 0.1 | G14: kg | J14: 10756.789 | K14: 11667.579 | L14: 12697.056 | M14: 13655.323 | N14: 14613.625 | O14: 15571.857 | P14: 16530.159 | Q14: 17464.914 | R14: 18376.273 | S14: 19381.977 | T14: 20294.29 | U14: 21081.922
E15: Raisins | F15: 0 | G15: kg | J15: 0 | K15: 0 | L15: 0 | M15: 0 | N15: 0 | O15: 0 | P15: 0 | Q15: 0 | R15: 0 | S15: 0 | T15: 0 | U15: 0
E16: Bananas | F16: 0 | G16: kg | J16: 0 | K16: 0 | L16: 0 | M16: 0 | N16: 0 | O16: 0 | P16: 0 | Q16: 0 | R16: 0 | S16: 0 | T16: 0 | U16: 0
E17: Total ingredients | G17: kg | J17: {=_xlfn.BYCOL(_xlfn.ANCHORARRAY( J9), _xleta.SUM )} -> 118324.68 | K17: 128343.37 | L17: 139667.62 | M17: 150208.55 | N17: 160749.88 | O17: 171290.43 | P17: 181831.75 | Q17: 192114.05 | R17: 202139 | S17: 213201.75 | T17: 223237.18 | U17: 231901.14
E18: of which lost due to baking | G18: kg | J18: {=_xlfn.LET( _xlpm.volume, INDEX(_xlfn.ANCHORARRAY( Inventory!$J$59), MATCH( $E8,_xlfn.ANCHORARRAY( Inventory!E59), 0), 0 ), _xlpm.ingredients, INDEX(_xlfn.ANCHORARRAY( J17), 1, 0 ), _xlpm.ingredients - _xlpm.volume )} -> 12915.072 | K18: 14300.632 | L18: 15092.665 | M18: 16051.166 | N18: 17009.117 | O18: 17967.7 | P18: 18925.651 | Q18: 19625.982 | R18: 21006.657 | S18: 21547.871 | T18: 22919.731 | U18: 21081.922
E22: Product B
E23: {=TRANSPOSE( CaseData!$C$39:$J$39 )} -> Flour | F23: {=TRANSPOSE( CaseData!$C41:$J41)} -> 0.321 | G23: kg | J23: {=_xlfn.LET( _xlpm.volume, INDEX( Inventory!$J$91:$U$93, MATCH( $E22,_xlfn.ANCHORARRAY( Inventory!$E$59), 0), 0 ), _xlpm.quantities, INDEX(_xlfn.ANCHORARRAY( $F23), 0, 1 ), _xlpm.volume * _xlpm.quantities)} -> 21035.584 | K23: 22908.472 | L23: 24626.461 | M23: 26698.956 | N23: 28418.765 | O23: 30489.662 | P23: 32213.062 | Q23: 34301.272 | R23: 36196.39 | S23: 38091.432 | T23: 39986.646 | U23: 41692.164
E24: Sugar | F24: 0.24 | G24: kg | J24: 15727.539 | K24: 17127.83 | L24: 18412.307 | M24: 19961.836 | N24: 21247.674 | O24: 22796.009 | P24: 24084.532 | Q24: 25645.811 | R24: 27062.722 | S24: 28479.575 | T24: 29896.558 | U24: 31171.711
E25: Butter | F25: 0.155 | G25: kg | J25: 10157.369 | K25: 11061.723 | L25: 11891.282 | M25: 12892.019 | N25: 13722.456 | O25: 14722.422 | P25: 15554.594 | Q25: 16562.92 | R25: 17478.008 | S25: 18393.059 | T25: 19308.194 | U25: 20131.73
E26: Milk | F26: 0.161 | G26: kg | J26: 10550.558 | K26: 11489.919 | L26: 12351.59 | M26: 13391.065 | N26: 14253.648 | O26: 15292.323 | P26: 16156.707 | Q26: 17204.065 | R26: 18154.576 | S26: 19105.048 | T26: 20055.608 | U26: 20911.023
E27: Eggs | F27: 0.138 | G27: kg | J27: 9043.3352 | K27: 9848.502 | L27: 10587.077 | M27: 11478.056 | N27: 12217.413 | O27: 13107.705 | P27: 13848.606 | Q27: 14746.341 | R27: 15561.065 | S27: 16375.756 | T27: 17190.521 | U27: 17923.734
E28: Chocolate | F28: 0 | G28: kg | J28: 0 | K28: 0 | L28: 0 | M28: 0 | N28: 0 | O28: 0 | P28: 0 | Q28: 0 | R28: 0 | S28: 0 | T28: 0 | U28: 0
E29: Raisins | F29: 0.1 | G29: kg | J29: 6553.1414 | K29: 7136.5957 | L29: 7671.7948 | M29: 8317.4317 | N29: 8853.1977 | O29: 9498.3371 | P29: 10035.222 | Q29: 10685.755 | R29: 11276.134 | S29: 11866.49 | T29: 12456.899 | U29: 12988.213
E30: Bananas | F30: 0 | G30: kg | J30: 0 | K30: 0 | L30: 0 | M30: 0 | N30: 0 | O30: 0 | P30: 0 | Q30: 0 | R30: 0 | S30: 0 | T30: 0 | U30: 0
E31: Total ingredients | G31: kg | J31: {=_xlfn.BYCOL(_xlfn.ANCHORARRAY( J23), _xleta.SUM )} -> 73067.527 | K31: 79573.042 | L31: 85540.512 | M31: 92739.363 | N31: 98713.154 | O31: 105906.46 | P31: 111892.72 | Q31: 119146.16 | R31: 125728.89 | S31: 132311.36 | T31: 138894.43 | U31: 144818.58
E32: of which lost due to baking | G32: kg | J32: {=_xlfn.LET( _xlpm.volume, INDEX(_xlfn.ANCHORARRAY( Inventory!$J$59), MATCH( $E22,_xlfn.ANCHORARRAY( Inventory!$E$59), 0), 0 ), _xlpm.ingredients, INDEX(_xlfn.ANCHORARRAY( J31), 1, 0 ), _xlpm.ingredients - _xlpm.volume )} -> 8126.4614 | K32: 8728.4882 | L32: 9481.9259 | M32: 10087.158 | N32: 10839.831 | O32: 11446.602 | P32: 12197.721 | Q32: 12879.001 | R32: 13557.903 | S32: 14236.879 | T32: 14915.783 | U32: 14936.445
E36: Product C
E37: {=TRANSPOSE( CaseData!$C$39:$J$39 )} -> Flour | F37: {=TRANSPOSE( CaseData!$C42:$J42)} -> 0.306 | G37: kg | J37: {=_xlfn.LET( _xlpm.volume, INDEX( Inventory!$J$91:$U$93, MATCH( $E36,_xlfn.ANCHORARRAY( Inventory!$E$59), 0), 0 ), _xlpm.quantities, INDEX(_xlfn.ANCHORARRAY( $F37), 0, 1 ), _xlpm.volume * _xlpm.quantities)} -> 8813.4821 | K37: 9593.465 | L37: 10373.386 | M37: 11153.332 | N37: 11933.315 | O37: 12713.235 | P37: 13493.154 | Q37: 14273.102 | R37: 15053.084 | S37: 15833.004 | T37: 16612.952 | U37: 17158.959
E38: Sugar | F38: 0.233 | G38: kg | J38: 6710.9194 | K38: 7304.8279 | L38: 7898.6891 | M38: 8492.5698 | N38: 9086.4783 | O38: 9680.3392 | P38: 10274.199 | Q38: 10868.081 | R38: 11461.989 | S38: 12055.85 | T38: 12649.731 | U38: 13065.481
E39: Butter | F39: 0.149 | G39: kg | J39: 4291.5321 | K39: 4671.3277 | L39: 5051.093 | M39: 5430.8708 | N39: 5810.6664 | O39: 6190.4315 | P39: 6570.1961 | Q39: 6949.9745 | R39: 7329.7699 | S39: 7709.5348 | T39: 8089.3132 | U39: 8355.1791
E40: Milk | F40: 0.137 | G40: kg | J40: 3945.9054 | K40: 4295.1134 | L40: 4644.2936 | M40: 4993.4852 | N40: 5342.6933 | O40: 5691.8733 | P40: 6041.0528 | Q40: 6390.245 | R40: 6739.4528 | S40: 7088.6326 | T40: 7437.8249 | U40: 7682.2788
E41: Eggs | F41: 0.155 | G41: kg | J41: 4464.3455 | K41: 4859.4349 | L41: 5254.4927 | M41: 5649.5636 | N41: 6044.653 | O41: 6439.7107 | P41: 6834.7677 | Q41: 7229.8393 | R41: 7624.9284 | S41: 8019.9858 | T41: 8415.0573 | U41: 8691.6293
E42: Chocolate | F42: 0.05 | G42: kg | J42: 1440.1115 | K42: 1567.5596 | L42: 1694.9977 | M42: 1822.4399 | N42: 1949.8881 | O42: 2077.326 | P42: 2204.7638 | Q42: 2332.2062 | R42: 2459.6543 | S42: 2587.0922 | T42: 2714.5346 | U42: 2803.7514
E43: Raisins | F43: 0 | G43: kg | J43: 0 | K43: 0 | L43: 0 | M43: 0 | N43: 0 | O43: 0 | P43: 0 | Q43: 0 | R43: 0 | S43: 0 | T43: 0 | U43: 0
E44: Bananas | F44: 0.2 | G44: kg | J44: 5760.4458 | K44: 6270.2386 | L44: 6779.9906 | M44: 7289.7595 | N44: 7799.5522 | O44: 8309.3041 | P44: 8819.0552 | Q44: 9328.8249 | R44: 9838.6173 | S44: 10348.369 | T44: 10858.139 | U44: 11215.006
E45: Total ingredients | G45: kg | J45: {=_xlfn.BYCOL(_xlfn.ANCHORARRAY( J37), _xleta.SUM )} -> 35426.742 | K45: 38561.967 | L45: 41696.942 | M45: 44832.021 | N45: 47967.246 | O45: 51102.22 | P45: 54237.189 | Q45: 57372.273 | R45: 60507.496 | S45: 63642.468 | T45: 66777.552 | U45: 68972.284
E46: of which lost due to baking | G46: kg | J46: {=_xlfn.LET( _xlpm.volume, INDEX(_xlfn.ANCHORARRAY( Inventory!$J$59), MATCH( $E36,_xlfn.ANCHORARRAY( Inventory!$E$59), 0), 0 ), _xlpm.ingredients, INDEX(_xlfn.ANCHORARRAY( J45), 1, 0 ), _xlpm.ingredients - _xlpm.volume )} -> 7389.2278 | K46: 7975.403 | L46: 8561.6159 | M46: 9147.9385 | N46: 9734.1137 | O46: 10320.325 | P46: 10906.542 | Q46: 11492.864 | R46: 12079.037 | S46: 12665.253 | T46: 13251.574 | U46: 12897.256
A49: Purchase plan (in kg)
B51: Purchase orders by ingredient
E53: {=TRANSPOSE( CaseData!$C$39:$J$39 )} -> Flour | G53: kg | J53: {=_xlfn.LET( _xlpm.kg_data, IF( $J$9:$U$46="", 0, $J$9:$U$46 ), _xlpm.kg_rows, $E$9:$E$46, _xlpm.current_product,_xlfn.ANCHORARRAY( E53), _xlpm.match_matrix, --( _xlpm.kg_rows = TRANSPOSE( _xlpm.current_product ) ), MMULT( TRANSPOSE( _xlpm.match_matrix ), _xlpm.kg_data ) )} -> 62119.434 | K53: 67504.675 | L53: 73091.015 | M53: 78818.257 | N53: 84192.955 | O53: 89918.469 | P53: 95296.695 | Q53: 100969.12 | R53: 106378.29 | S53: 112070.37 | T53: 117482.47 | U53: 122096.89
E54: Sugar | G54: kg | J54: 49330.432 | K54: 53601.606 | L54: 58053.637 | M54: 62592.714 | N54: 66868.216 | O54: 71405.991 | P54: 75684.13 | Q54: 80176.176 | R54: 84465.393 | S54: 88990.368 | T54: 93282.013 | U54: 96941.998
E55: Butter | G55: kg | J55: 30584.085 | K55: 33234.42 | L55: 35987.959 | M55: 38805.875 | N55: 41453.561 | O55: 44270.64 | P55: 46920.029 | Q55: 49710.265 | R55: 52372.187 | S55: 55175.56 | T55: 57838.941 | U55: 60109.792
E56: Milk | G56: kg | J56: 30631.647 | K56: 33286.401 | L56: 36041.467 | M56: 38867.535 | N56: 41516.779 | O56: 44341.982 | P56: 46992.999 | Q56: 49791.68 | R56: 52458.438 | S56: 55266.647 | T56: 57934.867 | U56: 60216.185
E57: Eggs | G57: kg | J57: 29642.865 | K57: 32209.306 | L57: 34887.154 | M57: 37610.604 | N57: 40182.504 | O57: 42905.202 | P57: 45478.613 | Q57: 48173.551 | R57: 50750.402 | S57: 53468.707 | T57: 56047.012 | U57: 58238.246
E58: Chocolate | G58: kg | J58: 12196.901 | K58: 13235.139 | L58: 14392.054 | M58: 15477.763 | N58: 16563.513 | O58: 17649.183 | P58: 18734.923 | Q58: 19797.12 | R58: 20835.927 | S58: 21969.07 | T58: 23008.824 | U58: 23885.673
E59: Raisins | G59: kg | J59: 6553.1414 | K59: 7136.5957 | L59: 7671.7948 | M59: 8317.4317 | N59: 8853.1977 | O59: 9498.3371 | P59: 10035.222 | Q59: 10685.755 | R59: 11276.134 | S59: 11866.49 | T59: 12456.899 | U59: 12988.213
E60: Bananas | G60: kg | J60: 5760.4458 | K60: 6270.2386 | L60: 6779.9906 | M60: 7289.7595 | N60: 7799.5522 | O60: 8309.3041 | P60: 8819.0552 | Q60: 9328.8249 | R60: 9838.6173 | S60: 10348.369 | T60: 10858.139 | U60: 11215.006
E61: Total purchase order by ingredients | G61: kg | J61: {=_xlfn.BYCOL(_xlfn.ANCHORARRAY( J53), _xleta.SUM )} -> 226818.95 | K61: 246478.38 | L61: 266905.07 | M61: 287779.94 | N61: 307430.28 | O61: 328299.11 | P61: 347961.67 | Q61: 368632.49 | R61: 388375.39 | S61: 409155.58 | T61: 428909.16 | U61: 445692
B64: Purchase orders by supplier
E66: {=_xlfn._xlws.SORT( _xlfn.UNIQUE(_xlfn.ANCHORARRAY( $F$86) ) )} -> Supplier II | G66: kg | J66: {=_xlfn.LET( _xlpm.ingredients,_xlfn.ANCHORARRAY( J53), _xlpm.suppliers,_xlfn.ANCHORARRAY( $F$86), _xlpm.current_supplier,_xlfn.ANCHORARRAY( E66), _xlpm.match_matrix, --( _xlpm.suppliers = TRANSPOSE( _xlpm.current_supplier ) ), MMULT( TRANSPOSE( _xlpm.match_matrix ), _xlpm.ingredients ) )} -> 91170.197 | K66: 99046.051 | L66: 107332.84 | M66: 115681.08 | N66: 123614.23 | O66: 131960.38 | P66: 139897.67 | Q66: 148146.85 | R66: 156051.72 | S66: 164428.14 | T66: 172337.85 | U66: 179065.92
E67: Supplier III | G67: kg | J67: 92751.081 | K67: 100791.08 | L67: 109132.48 | M67: 117685.79 | N67: 125709.73 | O67: 134260.45 | P67: 142289.69 | Q67: 150760.8 | R67: 158836.73 | S67: 167337.01 | T67: 175417.33 | U67: 182313.07
E68: Supplier IV | G68: kg | J68: 6553.1414 | K68: 7136.5957 | L68: 7671.7948 | M68: 8317.4317 | N68: 8853.1977 | O68: 9498.3371 | P68: 10035.222 | Q68: 10685.755 | R68: 11276.134 | S68: 11866.49 | T68: 12456.899 | U68: 12988.213
E69: Supplier V | G69: kg | J69: 36344.531 | K69: 39504.659 | L69: 42767.95 | M69: 46095.634 | N69: 49253.113 | O69: 52579.944 | P69: 55739.084 | Q69: 59039.09 | R69: 62210.804 | S69: 65523.928 | T69: 68697.08 | U69: 71324.798
E70: Total purchase orders by supplier | G70: kg | J70: {=_xlfn.BYCOL(_xlfn.ANCHORARRAY( J66), _xleta.SUM )} -> 226818.95 | K70: 246478.38 | L70: 266905.07 | M70: 287779.94 | N70: 307430.28 | O70: 328299.11 | P70: 347961.67 | Q70: 368632.49 | R70: 388375.39 | S70: 409155.58 | T70: 428909.16 | U70: 445692
B73: Purchase orders by product
E75: {=CaseData!$A$40:$A$42} -> Product A | G75: kg | J75: {=_xlfn.LET( _xlpm.ingredients, $J$8:$U$46, _xlpm.labels, $E$8:$E$46, _xlpm.ingredient_list,_xlfn.ANCHORARRAY( E53), _xlpm.is_ingredient_row, COUNTIF( _xlpm.ingredient_list, _xlpm.labels ) > 0, _xlpm.current_row, _xlfn._xlws.FILTER( _xlpm.labels, _xlpm.is_ingredient_row ), _xlpm.current_ingredients, _xlfn._xlws.FILTER( _xlpm.ingredients, _xlpm.is_ingredient_row ), _xlpm.product_list,_xlfn.ANCHORARRAY( $E$108), _xlpm.product_tag_all, _xlfn.SCAN( "", _xlpm.labels, _xlfn.LAMBDA(_xlpm.carry,_xlpm.lbl, IF( COUNTIF( _xlpm.product_list, _xlpm.lbl ) > 0, _xlpm.lbl, _xlpm.carry ) ) ), _xlpm.product_tag, _xlfn._xlws.FILTER( _xlpm.product_tag_all, _xlpm.is_ingredient_row ), _xlpm.match_matrix, --( _xlpm.product_tag = TRANSPOSE( _xlpm.product_list ) ), MMULT( TRANSPOSE( _xlpm.match_matrix ), _xlpm.current_ingredients ) )} -> 118324.68 | K75: 128343.37 | L75: 139667.62 | M75: 150208.55 | N75: 160749.88 | O75: 171290.43 | P75: 181831.75 | Q75: 192114.05 | R75: 202139 | S75: 213201.75 | T75: 223237.18 | U75: 231901.14
E76: Product B | G76: kg | J76: 73067.527 | K76: 79573.042 | L76: 85540.512 | M76: 92739.363 | N76: 98713.154 | O76: 105906.46 | P76: 111892.72 | Q76: 119146.16 | R76: 125728.89 | S76: 132311.36 | T76: 138894.43 | U76: 144818.58
E77: Product C | G77: kg | J77: 35426.742 | K77: 38561.967 | L77: 41696.942 | M77: 44832.021 | N77: 47967.246 | O77: 51102.22 | P77: 54237.189 | Q77: 57372.273 | R77: 60507.496 | S77: 63642.468 | T77: 66777.552 | U77: 68972.284
E78: Total purchase orders by product | G78: kg | J78: {=_xlfn.BYCOL(_xlfn.ANCHORARRAY( J75), _xleta.SUM )} -> 226818.95 | K78: 246478.38 | L78: 266905.07 | M78: 287779.94 | N78: 307430.28 | O78: 328299.11 | P78: 347961.67 | Q78: 368632.49 | R78: 388375.39 | S78: 409155.58 | T78: 428909.16 | U78: 445692
A81: Purchase plan (in USD)
B83: Purchase orders by ingredient
F84: Selected
E85: Ingredient | F85: Supplier | G85: Currency | H85: Price
E86: {=TRANSPOSE( CaseData!$C$39:$J$39 )} -> Flour | F86: {=_xlfn.LET( _xlpm.prices, CaseData!$C$46:$J$50, _xlpm.suppliers, CaseData!$A$46:$A$50, _xlpm.min_row, _xlfn.BYCOL( _xlpm.prices, _xlfn.LAMBDA(_xlpm.c, MATCH( MIN( _xlpm.c ), _xlpm.c, 0 ) ) ), INDEX( _xlpm.suppliers, TRANSPOSE( _xlpm.min_row ) ) )} -> Supplier III | G86: USD | H86: {=_xlfn.LET( _xlpm.prices, CaseData!$C$46:$J$50, TRANSPOSE( _xlfn.BYCOL( _xlpm.prices, _xlfn.LAMBDA(_xlpm.c, MIN(_xlpm.c) ) ) ) )} -> 0.2531 | J86: {=_xlfn.ANCHORARRAY( J53) *_xlfn.ANCHORARRAY( H86)} -> 15722.429 | K86: 17085.433 | L86: 18499.336 | M86: 19948.901 | N86: 21309.237 | O86: 22758.364 | P86: 24119.593 | Q86: 25555.283 | R86: 26924.346 | S86: 28365.01 | T86: 29734.812 | U86: 30902.723
E87: Sugar | F87: Supplier II | G87: USD | H87: 0.1932 | J87: 9530.6395 | K87: 10355.83 | L87: 11215.963 | M87: 12092.912 | N87: 12918.939 | O87: 13795.638 | P87: 14622.174 | Q87: 15490.037 | R87: 16318.714 | S87: 17192.939 | T87: 18022.085 | U87: 18729.194
E88: Butter | F88: Supplier V | G88: USD | H88: 1.8693 | J88: 57170.831 | K88: 62125.101 | L88: 67272.292 | M88: 72539.821 | N88: 77489.141 | O88: 82755.107 | P88: 87707.61 | Q88: 92923.398 | R88: 97899.328 | S88: 103139.67 | T88: 108118.33 | U88: 112363.24
E89: Milk | F89: Supplier III | G89: USD | H89: 0.6231 | J89: 19086.579 | K89: 20740.757 | L89: 22457.438 | M89: 24218.361 | N89: 25869.105 | O89: 27629.489 | P89: 29281.338 | Q89: 31025.196 | R89: 32686.852 | S89: 34436.648 | T89: 36099.216 | U89: 37520.705
E90: Eggs | F90: Supplier II | G90: USD | H90: 1.6248 | J90: 48163.726 | K90: 52333.68 | L90: 56684.647 | M90: 61109.709 | N90: 65288.532 | O90: 69712.372 | P90: 73893.65 | Q90: 78272.386 | R90: 82459.254 | S90: 86875.956 | T90: 91065.186 | U90: 94625.503
E91: Chocolate | F91: Supplier II | G91: USD | H91: 1.4633 | J91: 17847.725 | K91: 19366.979 | L91: 21059.892 | M91: 22648.611 | N91: 24237.389 | O91: 25826.05 | P91: 27414.813 | Q91: 28969.126 | R91: 30489.212 | S91: 32147.339 | T91: 33668.812 | U91: 34951.906
E92: Raisins | F92: Supplier IV | G92: USD | H92: 2.1809 | J92: 14291.746 | K92: 15564.201 | L92: 16731.417 | M92: 18139.487 | N92: 19307.939 | O92: 20714.923 | P92: 21885.815 | Q92: 23304.562 | R92: 24592.121 | S92: 25879.627 | T92: 27167.251 | U92: 28325.994
E93: Bananas | F93: Supplier V | G93: USD | H93: 0.9548 | J93: 5500.0737 | K93: 5986.8238 | L93: 6473.535 | M93: 6960.2623 | N93: 7447.0125 | O93: 7933.7235 | P93: 8420.4339 | Q93: 8907.162 | R93: 9393.9118 | S93: 9880.6225 | T93: 10367.351 | U93: 10708.087
E94: Total purchase orders by ingredients | G94: USD | J94: {=_xlfn.BYCOL(_xlfn.ANCHORARRAY( J86), _xleta.SUM )} -> 187313.75 | K94: 203558.81 | L94: 220394.52 | M94: 237658.06 | N94: 253867.3 | O94: 271125.67 | P94: 287345.43 | Q94: 304447.15 | R94: 320763.74 | S94: 337917.82 | T94: 354243.05 | U94: 368127.35
B97: Purchase orders by supplier
E99: {=_xlfn._xlws.SORT( _xlfn.UNIQUE(_xlfn.ANCHORARRAY( $F$86) ) )} -> Supplier II | G99: USD | J99: {=_xlfn.LET( _xlpm.ingredients,_xlfn.ANCHORARRAY( J86), _xlpm.suppliers,_xlfn.ANCHORARRAY( F86), _xlpm.current_supplier,_xlfn.ANCHORARRAY( E99), _xlpm.match_matrix, --( _xlpm.suppliers = TRANSPOSE( _xlpm.current_supplier ) ), MMULT( TRANSPOSE( _xlpm.match_matrix ), _xlpm.ingredients ) )} -> 75542.091 | K99: 82056.489 | L99: 88960.502 | M99: 95851.232 | N99: 102444.86 | O99: 109334.06 | P99: 115930.64 | Q99: 122731.55 | R99: 129267.18 | S99: 136216.23 | T99: 142756.08 | U99: 148306.6
E100: Supplier III | G100: USD | J100: 34809.008 | K100: 37826.19 | L100: 40956.774 | M100: 44167.262 | N100: 47178.342 | O100: 50387.853 | P100: 53400.931 | Q100: 56580.479 | R100: 59611.198 | S100: 62801.658 | T100: 65834.028 | U100: 68423.427
E101: Supplier IV | G101: USD | J101: 14291.746 | K101: 15564.201 | L101: 16731.417 | M101: 18139.487 | N101: 19307.939 | O101: 20714.923 | P101: 21885.815 | Q101: 23304.562 | R101: 24592.121 | S101: 25879.627 | T101: 27167.251 | U101: 28325.994
E102: Supplier V | G102: USD | J102: 62670.904 | K102: 68111.925 | L102: 73745.827 | M102: 79500.084 | N102: 84936.154 | O102: 90688.831 | P102: 96128.044 | Q102: 101830.56 | R102: 107293.24 | S102: 113020.3 | T102: 118485.68 | U102: 123071.32
E103: Total purchase orders by supplier | G103: USD | J103: {=_xlfn.BYCOL(_xlfn.ANCHORARRAY( J99), _xleta.SUM )} -> 187313.75 | K103: 203558.81 | L103: 220394.52 | M103: 237658.06 | N103: 253867.3 | O103: 271125.67 | P103: 287345.43 | Q103: 304447.15 | R103: 320763.74 | S103: 337917.82 | T103: 354243.05 | U103: 368127.35
B106: Purchase orders by product
E108: {=CaseData!$A$40:$A$42} -> Product A | G108: USD | J108: {=_xlfn.LET( _xlpm.ingredients, $J$8:$U$46, _xlpm.labels, $E$8:$E$46, _xlpm.ingredient_list,_xlfn.ANCHORARRAY( $E$86), _xlpm.list_price,_xlfn.ANCHORARRAY( $H$86), _xlpm.is_ingredient_row, COUNTIF( _xlpm.ingredient_list, _xlpm.labels ) > 0, _xlpm.current_row, _xlfn._xlws.FILTER( _xlpm.labels, _xlpm.is_ingredient_row ), _xlpm.current_ingredients, _xlfn._xlws.FILTER( _xlpm.ingredients, _xlpm.is_ingredient_row ), _xlpm.value, _xlpm.current_ingredients * _xlfn.XLOOKUP( _xlpm.current_row, _xlpm.ingredient_list, _xlpm.list_price ), _xlpm.product_list,_xlfn.ANCHORARRAY( $E$108), _xlpm.product_tag_all, _xlfn.SCAN( "", _xlpm.labels, _xlfn.LAMBDA(_xlpm.carry,_xlpm.lbl, IF( COUNTIF( _xlpm.product_list, _xlpm.lbl ) > 0, _xlpm.lbl, _xlpm.carry ) ) ), _xlpm.product_tag, _xlfn._xlws.FILTER( _xlpm.product_tag_all, _xlpm.is_ingredient_row ), _xlpm.match_matrix, --( _xlpm.product_tag = TRANSPOSE( _xlpm.product_list ) ), MMULT( TRANSPOSE( _xlpm.match_matrix ), _xlpm.value ) )} -> 95535.348 | K108: 103624.44 | L108: 112767.63 | M108: 121278.39 | N108: 129789.45 | O108: 138299.89 | P108: 146810.96 | Q108: 155112.89 | R108: 163207.03 | S108: 172139.09 | T108: 180241.7 | U108: 187236.98
E109: Product B | G109: USD | J109: 62909.247 | K109: 68510.326 | L109: 73648.163 | M109: 79846.188 | N109: 84989.467 | O109: 91182.716 | P109: 96336.735 | Q109: 102581.76 | R109: 108249.32 | S109: 113916.65 | T109: 119584.5 | U109: 124685.04
E110: Product C | G110: USD | J110: 28869.154 | K110: 31424.041 | L110: 33978.723 | M110: 36533.49 | N110: 39088.376 | O110: 41643.058 | P110: 44197.736 | Q110: 46752.507 | R110: 49307.391 | S110: 51862.071 | T110: 54416.842 | U110: 56205.324
E111: Total purchase orders by product | G111: USD | J111: {=_xlfn.BYCOL(_xlfn.ANCHORARRAY( J108), _xleta.SUM )} -> 187313.75 | K111: 203558.81 | L111: 220394.52 | M111: 237658.06 | N111: 253867.3 | O111: 271125.67 | P111: 287345.43 | Q111: 304447.15 | R111: 320763.74 | S111: 337917.82 | T111: 354243.05 | U111: 368127.35
A114: Other direct costs
B116: Other direct costs by product
E118: {=CaseData!$A$40:$A$42} -> Product A | G118: USD | J118: {=_xlfn.LET( _xlpm.ingredients_cost,_xlfn.ANCHORARRAY( J108), _xlpm.direct_cost_pct_product, CaseData!$L$40:$L$42, _xlpm.direct_cost_rows, CaseData!$A$40:$A$42, _xlpm.current_product,_xlfn.ANCHORARRAY( E118), _xlpm.ingredients_cost * _xlfn.XLOOKUP( _xlpm.current_product, _xlpm.direct_cost_rows, _xlpm.direct_cost_pct_product, 0 ) )} -> 47767.674 | K118: 51812.22 | L118: 56383.817 | M118: 60639.194 | N118: 64894.726 | O118: 69149.946 | P118: 73405.479 | Q118: 77556.443 | R118: 81603.514 | S118: 86069.547 | T118: 90120.851 | U118: 93618.491
E119: Product B | G119: USD | J119: 37745.548 | K119: 41106.196 | L119: 44188.898 | M119: 47907.713 | N119: 50993.68 | O119: 54709.629 | P119: 57802.041 | Q119: 61549.055 | R119: 64949.592 | S119: 68349.99 | T119: 71750.7 | U119: 74811.024
E120: Product C | G120: USD | J120: 21651.865 | K120: 23568.03 | L120: 25484.042 | M120: 27400.117 | N120: 29316.282 | O120: 31232.293 | P120: 33148.302 | Q120: 35064.38 | R120: 36980.544 | S120: 38896.554 | T120: 40812.632 | U120: 42153.993
E121: Othe direct costs by product | G121: USD | J121: {=_xlfn.BYCOL(_xlfn.ANCHORARRAY( J118), _xleta.SUM )} -> 107165.09 | K121: 116486.45 | L121: 126056.76 | M121: 135947.02 | N121: 145204.69 | O121: 155091.87 | P121: 164355.82 | Q121: 174169.88 | R121: 183533.65 | S121: 193316.09 | T121: 202684.18 | U121: 210583.51
A124: Direct costs
B126: Direct costs
E128: {=CaseData!$A$40:$A$42} -> Product A | G128: USD | J128: {=_xlfn.LET( _xlpm.ingredients_costs,_xlfn.ANCHORARRAY( J108), _xlpm.other_direct_costs,_xlfn.ANCHORARRAY( J118), _xlpm.ingredients_costs + _xlpm.other_direct_costs )} -> 143303.02 | K128: 155436.66 | L128: 169151.45 | M128: 181917.58 | N128: 194684.18 | O128: 207449.84 | P128: 220216.44 | Q128: 232669.33 | R128: 244810.54 | S128: 258208.64 | T128: 270362.55 | U128: 280855.47
E129: Product B | G129: USD | J129: 100654.79 | K129: 109616.52 | L129: 117837.06 | M129: 127753.9 | N129: 135983.15 | O129: 145892.35 | P129: 154138.78 | Q129: 164130.81 | R129: 173198.91 | S129: 182266.64 | T129: 191335.2 | U129: 199496.06
E130: Product C | G130: USD | J130: 50521.019 | K130: 54992.071 | L130: 59462.765 | M130: 63933.607 | N130: 68404.659 | O130: 72875.351 | P130: 77346.037 | Q130: 81816.887 | R130: 86287.935 | S130: 90758.625 | T130: 95229.474 | U130: 98359.317
E131: Direct costs | G131: USD | J131: {=_xlfn.BYCOL(_xlfn.ANCHORARRAY( J128), _xleta.SUM )} -> 294478.84 | K131: 320045.25 | L131: 346451.28 | M131: 373605.09 | N131: 399071.98 | O131: 426217.54 | P131: 451701.25 | Q131: 478617.03 | R131: 504297.39 | S131: 531233.91 | T131: 556927.23 | U131: 578710.85
B133: Average direct costs
E135: {=CaseData!$A$40:$A$42} -> Product A | G135: USD / kg | J135: {=_xlfn.LET( _xlpm.product_manufactured, Inventory!$J$91:$U$93, _xlpm.direct_costs,_xlfn.ANCHORARRAY( J128), _xlpm.direct_costs / _xlpm.product_manufactured )} -> 1.33221 | K135: 1.33221 | L135: 1.33221 | M135: 1.33221 | N135: 1.33221 | O135: 1.33221 | P135: 1.33221 | Q135: 1.33221 | R135: 1.33221 | S135: 1.33221 | T135: 1.33221 | U135: 1.33221
E136: Product B | G136: USD / kg | J136: 1.5359778 | K136: 1.5359778 | L136: 1.5359778 | M136: 1.5359778 | N136: 1.5359778 | O136: 1.5359778 | P136: 1.5359778 | Q136: 1.5359778 | R136: 1.5359778 | S136: 1.5359778 | T136: 1.5359778 | U136: 1.5359778
E137: Product C | G137: USD / kg | J137: 1.7540663 | K137: 1.7540663 | L137: 1.7540663 | M137: 1.7540663 | N137: 1.7540663 | O137: 1.7540663 | P137: 1.7540663 | Q137: 1.7540663 | R137: 1.7540663 | S137: 1.7540663 | T137: 1.7540663 | U137: 1.7540663
A175: End of schedule

Sheet Inventory
A1: {=company} -> Sweet Dreams Co.
A2: {=topic} -> CFM Topic: Working Capital
A3: INVENTORY SCHEDULE | F3: Constant | G3: Unit | H3: Total | J3: {=EOMONTH( start_date, _xlfn.SEQUENCE( 1, periods, 0, 1 ) )} -> 44592 | K3: 44620 | L3: 44651 | M3: 44681 | N3: 44712 | O3: 44742 | P3: 44773 | Q3: 44804 | R3: 44834 | S3: 44865 | T3: 44895 | U3: 44926
A5: Sales
B7: Product sales (after discount)
E9: {=IF( INDEX( CaseData!$A$7:$A$20,,1 ) = "", "", INDEX( CaseData!$A$7:$A$20,,1 ) )} -> Retailer 1 | G9: USD | J9: {=_xlfn.LET( _xlpm.revenue_data, CaseData!$C$7:$N$20, _xlpm.revenue_columns, CaseData!$C$3:$N$3, _xlpm.current_row,_xlfn.ANCHORARRAY( $E$9), _xlpm.current_column,_xlfn.ANCHORARRAY( $J$3), _xlpm.row_position, _xlfn.SEQUENCE( ROWS( _xlpm.current_row ) ), _xlpm.revenue, INDEX( _xlpm.revenue_data, _xlpm.row_position, _xlfn.XMATCH( _xlpm.current_column, _xlpm.revenue_columns ) ), IF( _xlpm.revenue = "","", _xlpm.revenue ) )} -> 210000 | K9: 229091 | L9: 248182 | M9: 267272 | N9: 284364 | O9: 305454 | P9: 324546 | Q9: 343636 | R9: 360728 | S9: 381818 | T9: 400909 | U9: 420000
E10: Product A | G10: USD | J10: 125000 | K10: 136364 | L10: 147727 | M10: 159091 | N10: 170455 | O10: 181818 | P10: 193182 | Q10: 204545 | R10: 213909 | S10: 227273 | T10: 238636 | U10: 250000
E11: Product B | G11: USD | J11: 50000 | K11: 54545 | L11: 59091 | M11: 63636 | N11: 66182 | O11: 72727 | P11: 77273 | Q11: 81818 | R11: 86364 | S11: 90909 | T11: 95455 | U11: 100000
E12: Product C | G12: USD | J12: 35000 | K12: 38182 | L12: 41364 | M12: 44545 | N12: 47727 | O12: 50909 | P12: 54091 | Q12: 57273 | R12: 60455 | S12: 63636 | T12: 66818 | U12: 70000
E14: Retailer 2 | G14: USD | J14: 105000 | K14: 114545 | L14: 124091 | M14: 133636 | N14: 143182 | O14: 152727 | P14: 160273 | Q14: 171818 | R14: 181364 | S14: 190909 | T14: 198455 | U14: 210000
E15: Product A | G15: USD | J15: 50000 | K15: 54545 | L15: 59091 | M15: 63636 | N15: 68182 | O15: 72727 | P15: 77273 | Q15: 81818 | R15: 86364 | S15: 90909 | T15: 93455 | U15: 100000
E16: Product B | G16: USD | J16: 40000 | K16: 43636 | L16: 47273 | M16: 50909 | N16: 54545 | O16: 58182 | P16: 59818 | Q16: 65455 | R16: 69091 | S16: 72727 | T16: 76364 | U16: 80000
E17: Product C | G17: USD | J17: 15000 | K17: 16364 | L17: 17727 | M17: 19091 | N17: 20455 | O17: 21818 | P17: 23182 | Q17: 24545 | R17: 25909 | S17: 27273 | T17: 28636 | U17: 30000
E19: Retailer 3 | G19: USD | J19: 195000 | K19: 210727 | L19: 228455 | M19: 248182 | N19: 265910 | O19: 283637 | P19: 301363 | Q19: 319090 | R19: 336818 | S19: 354545 | T19: 372273 | U19: 390000
E20: Product A | G20: USD | J20: 50000 | K20: 52545 | L20: 59091 | M20: 63636 | N20: 68182 | O20: 72727 | P20: 77273 | Q20: 81818 | R20: 86364 | S20: 90909 | T20: 95455 | U20: 100000
E21: Product B | G21: USD | J21: 100000 | K21: 109091 | L21: 116182 | M21: 127273 | N21: 136364 | O21: 145455 | P21: 154545 | Q21: 163636 | R21: 172727 | S21: 181818 | T21: 190909 | U21: 200000
E22: Product C | G22: USD | J22: 45000 | K22: 49091 | L22: 53182 | M22: 57273 | N22: 61364 | O22: 65455 | P22: 69545 | Q22: 73636 | R22: 77727 | S22: 81818 | T22: 85909 | U22: 90000
B24: Product sales (before discount)
E26: {=IF( INDEX( CaseData!$A$7:$A$20,,1 ) = "", "", INDEX( CaseData!$A$7:$A$20,,1 ) )} -> Retailer 1 | G26: USD | J26: {=_xlfn.LET( _xlpm.revenue,_xlfn.ANCHORARRAY( J9), _xlpm.current_row,_xlfn.ANCHORARRAY( E26), _xlpm.retailer_list, CaseData!$A$26:$A$28, _xlpm.retailer_fill, _xlfn.SCAN( "", _xlpm.current_row, _xlfn.LAMBDA(_xlpm.carry,_xlpm.lbl, IF( COUNTIF( _xlpm.retailer_list, _xlpm.lbl ) > 0, _xlpm.lbl, _xlpm.carry ) ) ), _xlpm.discount_rate, CaseData!$D$26:$D$28, _xlpm.discount, INDEX( _xlpm.discount_rate, _xlfn.XMATCH( _xlpm.retailer_fill, _xlpm.retailer_list ) ), IF( _xlpm.current_row = "", "", _xlpm.revenue / ( 1 - _xlpm.discount ) ) )} -> 225806.45 | K26: 246334.41 | L26: 266862.37 | M26: 287389.25 | N26: 305767.74 | O26: 328445.16 | P26: 348974.19 | Q26: 369501.08 | R26: 387879.57 | S26: 410556.99 | T26: 431084.95 | U26: 451612.9
E27: Product A | G27: USD | J27: 134408.6 | K27: 146627.96 | L27: 158846.24 | M27: 171065.59 | N27: 183284.95 | O27: 195503.23 | P27: 207722.58 | Q27: 219940.86 | R27: 230009.68 | S27: 244379.57 | T27: 256597.85 | U27: 268817.2
E28: Product B | G28: USD | J28: 53763.441 | K28: 58650.538 | L28: 63538.71 | M28: 68425.806 | N28: 71163.441 | O28: 78201.075 | P28: 83089.247 | Q28: 87976.344 | R28: 92864.516 | S28: 97751.613 | T28: 102639.78 | U28: 107526.88
E29: Product C | G29: USD | J29: 37634.409 | K29: 41055.914 | L29: 44477.419 | M29: 47897.849 | N29: 51319.355 | O29: 54740.86 | P29: 58162.366 | Q29: 61583.871 | R29: 65005.376 | S29: 68425.806 | T29: 71847.312 | U29: 75268.817
E31: Retailer 2 | G31: USD | J31: 110526.32 | K31: 120573.68 | L31: 130622.11 | M31: 140669.47 | N31: 150717.89 | O31: 160765.26 | P31: 168708.42 | Q31: 180861.05 | R31: 190909.47 | S31: 200956.84 | T31: 208900 | U31: 221052.63
E32: Product A | G32: USD | J32: 52631.579 | K32: 57415.789 | L32: 62201.053 | M32: 66985.263 | N32: 71770.526 | O32: 76554.737 | P32: 81340 | Q32: 86124.211 | R32: 90909.474 | S32: 95693.684 | T32: 98373.684 | U32: 105263.16
E33: Product B | G33: USD | J33: 42105.263 | K33: 45932.632 | L33: 49761.053 | M33: 53588.421 | N33: 57415.789 | O33: 61244.211 | P33: 62966.316 | Q33: 68900 | R33: 72727.368 | S33: 76554.737 | T33: 80383.158 | U33: 84210.526
E34: Product C | G34: USD | J34: 15789.474 | K34: 17225.263 | L34: 18660 | M34: 20095.789 | N34: 21531.579 | O34: 22966.316 | P34: 24402.105 | Q34: 25836.842 | R34: 27272.632 | S34: 28708.421 | T34: 30143.158 | U34: 31578.947
E36: Retailer 3 | G36: USD | J36: 211956.52 | K36: 229051.09 | L36: 248320.65 | M36: 269763.04 | N36: 289032.61 | O36: 308301.09 | P36: 327568.48 | Q36: 346836.96 | R36: 366106.52 | S36: 385375 | T36: 404644.57 | U36: 423913.04
E37: Product A | G37: USD | J37: 54347.826 | K37: 57114.13 | L37: 64229.348 | M37: 69169.565 | N37: 74110.87 | O37: 79051.087 | P37: 83992.391 | Q37: 88932.609 | R37: 93873.913 | S37: 98814.13 | T37: 103755.43 | U37: 108695.65
E38: Product B | G38: USD | J38: 108695.65 | K38: 118577.17 | L38: 126284.78 | M38: 138340.22 | N38: 148221.74 | O38: 158103.26 | P38: 167983.7 | Q38: 177865.22 | R38: 187746.74 | S38: 197628.26 | T38: 207509.78 | U38: 217391.3
E39: Product C | G39: USD | J39: 48913.043 | K39: 53359.783 | L39: 57806.522 | M39: 62253.261 | N39: 66700 | O39: 71146.739 | P39: 75592.391 | Q39: 80039.13 | R39: 84485.87 | S39: 88932.609 | T39: 93379.348 | U39: 97826.087
A41: Volume sold
E43: {=IF( INDEX( CaseData!$A$7:$A$20,,1 ) = "", "", INDEX( CaseData!$A$7:$A$20,,1 ) )} -> Retailer 1 | G43: kg | J43: {=_xlfn.LET( _xlpm.revenue,_xlfn.ANCHORARRAY( J26), _xlpm.current_row,_xlfn.ANCHORARRAY( E26), _xlpm.retailer_list, CaseData!$A$26:$A$28, _xlpm.product_list, CaseData!$A$31:$A$33, _xlpm.list_price, CaseData!$D$31:$D$33, _xlpm.retailer_fill, _xlfn.SCAN( "", _xlpm.current_row, _xlfn.LAMBDA(_xlpm.carry,_xlpm.lbl, IF( COUNTIF( _xlpm.retailer_list, _xlpm.lbl ) > 0, _xlpm.lbl, _xlpm.carry ) ) ), _xlpm.is_retailer_row, COUNTIF( _xlpm.retailer_list, _xlpm.current_row ) > 0, _xlpm.kg, IFERROR( _xlpm.revenue / _xlfn.XLOOKUP( _xlpm.current_row, _xlpm.product_list, _xlpm.list_price ), 0 ), _xlfn.MAKEARRAY( ROWS( _xlpm.current_row ), COLUMNS( _xlpm.kg ), _xlfn.LAMBDA(_xlpm.r,_xlpm.c, IF( INDEX( _xlpm.current_row, _xlpm.r, 1 ) = "", "", IF( INDEX( _xlpm.is_retailer_row, _xlpm.r, 1 ), SUMPRODUCT( ( _xlpm.retailer_fill = INDEX( _xlpm.retailer_fill, _xlpm.r, 1 ) ) * INDEX( _xlpm.kg, 0, _xlpm.c ) ), INDEX( _xlpm.kg, _xlpm.r, _xlpm.c ) ) ) ) ) )} -> 86072.269 | K43: 93897.089 | L43: 101721.78 | M43: 109546.31 | N43: 116688.76 | O43: 125195.82 | P43: 133020.98 | Q43: 140845.34 | R43: 147731.4 | S43: 156495.02 | T43: 164319.72 | U43: 172144.54
E44: Product A | G44: kg | J44: 58693.713 | K44: 64029.676 | L44: 69365.169 | M44: 74701.132 | N44: 80037.094 | O44: 85372.588 | P44: 90708.551 | Q44: 96044.044 | R44: 100440.91 | S44: 106715.97 | T44: 112051.46 | U44: 117387.43
E45: Product B | G45: kg | J45: 17067.759 | K45: 18619.218 | L45: 20171.019 | M45: 21722.478 | N45: 22591.569 | O45: 24825.738 | P45: 26377.539 | Q45: 27928.998 | R45: 29480.799 | S45: 31032.258 | T45: 32584.059 | U45: 34135.518
E46: Product C | G46: kg | J46: 10310.797 | K46: 11248.196 | L46: 12185.594 | M46: 13122.698 | N46: 14060.097 | O46: 14997.496 | P46: 15934.895 | Q46: 16872.293 | R46: 17809.692 | S46: 18746.796 | T46: 19684.195 | U46: 20621.594
E48: Retailer 2 | G48: kg | J48: 40675.856 | K48: 44373.435 | L48: 48071.52 | M48: 51769.1 | N48: 55467.139 | O48: 59164.764 | P48: 62194.466 | Q48: 66560.428 | R48: 70258.467 | S48: 73956.047 | T48: 76734.803 | U48: 81351.711
E49: Product A | G49: kg | J49: 22983.222 | K49: 25072.397 | L49: 27162.032 | M49: 29251.207 | N49: 31340.841 | O49: 33430.016 | P49: 35519.651 | Q49: 37608.826 | R49: 39698.46 | S49: 41787.635 | T49: 42957.941 | U49: 45966.444
E50: Product B | G50: kg | J50: 13366.75 | K50: 14581.788 | L50: 15797.16 | M50: 17012.197 | N50: 18227.235 | O50: 19442.607 | P50: 19989.307 | Q50: 21873.016 | R50: 23088.053 | S50: 24303.091 | T50: 25518.463 | U50: 26733.5
E51: Product C | G51: kg | J51: 4325.8832 | K51: 4719.2502 | L51: 5112.3288 | M51: 5505.6957 | N51: 5899.0627 | O51: 6292.1413 | P51: 6685.5083 | Q51: 7078.5869 | R51: 7471.9539 | S51: 7865.3208 | T51: 8258.3994 | U51: 8651.7664
E53: Retailer 3 | G53: kg | J53: 71640.065 | K53: 77203.334 | L53: 83975.561 | M53: 91178.268 | N53: 97691.318 | O53: 104203.89 | P53: 110716.3 | Q53: 117228.88 | R53: 123741.93 | S53: 130254.5 | T53: 136767.55 | U53: 143280.13
E54: Product A | G54: kg | J54: 23732.675 | K54: 24940.668 | L54: 28047.75 | M54: 30205.05 | N54: 32362.825 | O54: 34520.125 | P54: 36677.9 | Q54: 38835.2 | R54: 40992.975 | S54: 43150.275 | T54: 45308.05 | U54: 47465.35
E55: Product B | G55: kg | J55: 34506.556 | K55: 37643.547 | L55: 40090.407 | M55: 43917.529 | N55: 47054.52 | O55: 50191.511 | P55: 53328.157 | Q55: 56465.148 | R55: 59602.139 | S55: 62739.13 | T55: 65876.121 | U55: 69013.112
E56: Product C | G56: kg | J56: 13400.834 | K56: 14619.119 | L56: 15837.403 | M56: 17055.688 | N56: 18273.973 | O56: 19492.257 | P56: 20710.244 | Q56: 21928.529 | R56: 23146.814 | S56: 24365.098 | T56: 25583.383 | U56: 26801.668
E58: Total
E59: {=INDEX( CaseData!$A$31:$A$33,, 1 )} -> Product A | G59: kg | J59: {=_xlfn.LET( _xlpm.kg_data, IF(_xlfn.ANCHORARRAY( J43)="", 0,_xlfn.ANCHORARRAY( J43) ), _xlpm.kg_rows,_xlfn.ANCHORARRAY( E43), _xlpm.current_product,_xlfn.ANCHORARRAY( E59), _xlpm.match_matrix, --( _xlpm.kg_rows = TRANSPOSE( _xlpm.current_product ) ), MMULT( TRANSPOSE( _xlpm.match_matrix ), _xlpm.kg_data ) )} -> 105409.61 | K59: 114042.74 | L59: 124574.95 | M59: 134157.39 | N59: 143740.76 | O59: 153322.73 | P59: 162906.1 | Q59: 172488.07 | R59: 181132.34 | S59: 191653.88 | T59: 200317.45 | U59: 210819.22
E60: Product B | G60: kg | J60: 64941.065 | K60: 70844.553 | L60: 76058.586 | M60: 82652.205 | N60: 87873.324 | O60: 94459.856 | P60: 99695.003 | Q60: 106267.16 | R60: 112170.99 | S60: 118074.48 | T60: 123978.64 | U60: 129882.13
E61: Product C | G61: kg | J61: 28037.514 | K61: 30586.564 | L61: 33135.326 | M61: 35684.082 | N61: 38233.133 | O61: 40781.895 | P61: 43330.647 | Q61: 45879.409 | R61: 48428.46 | S61: 50977.215 | T61: 53525.977 | U61: 56075.028
A63: Inventory available for sale (net of baking loss)
B65: Product A
E67: Opening balance | G67: kg | J67: {=_xlfn.LET( _xlpm.inventory_target, INDEX( CaseData!$C$31:$C$33, MATCH( $B65,_xlfn.ANCHORARRAY( $E$59), 0 ), 1 ), _xlpm.opening_balance, INDEX(_xlfn.ANCHORARRAY( $J$59), MATCH( $B65,_xlfn.ANCHORARRAY( $E$59), 0 ), 1 ) * _xlpm.inventory_target, _xlfn.DROP( _xlfn.HSTACK( _xlpm.opening_balance,_xlfn.ANCHORARRAY( $J70) ),, -1 ) )} -> 26352.403 | K67: 28510.685 | L67: 31143.738 | M67: 33539.347 | N67: 35935.19 | O67: 38330.682 | P67: 40726.525 | Q67: 43122.017 | R67: 45283.086 | S67: 47913.47 | T67: 50079.363 | U67: 52704.805
D68: add | E68: Product manufactured | G68: kg | J68: {=_xlfn.LET( _xlpm.opening_balance,_xlfn.ANCHORARRAY( $J67), _xlpm.product_sold,_xlfn.ANCHORARRAY( $J69), _xlpm.closing_balance,_xlfn.ANCHORARRAY( $J70), - _xlpm.product_sold + ( _xlpm.closing_balance - _xlpm.opening_balance ) )} -> 107567.89 | K68: 116675.79 | L68: 126970.56 | M68: 136553.23 | N68: 146136.25 | O68: 155718.57 | P68: 165301.59 | Q68: 174649.14 | R68: 183762.73 | S68: 193819.77 | T68: 202942.9 | U68: 210819.22
D69: less | E69: Product sold | G69: kg | J69: {=_xlfn._xlws.FILTER(_xlfn.ANCHORARRAY( $J$59),_xlfn.ANCHORARRAY( $E$59) = $B65) * - 1} -> -105409.61 | K69: -114042.74 | L69: -124574.95 | M69: -134157.39 | N69: -143740.76 | O69: -153322.73 | P69: -162906.1 | Q69: -172488.07 | R69: -181132.34 | S69: -191653.88 | T69: -200317.45 | U69: -210819.22
E70: Closing balance | G70: kg | J70: {=_xlfn.LET( _xlpm.next_month_inventory, _xlfn.DROP( INDEX(_xlfn.ANCHORARRAY( $J$59), MATCH( $B65,_xlfn.ANCHORARRAY( $E$59), 0 ), 0 ),,1 ), _xlpm.last_month_inventory, INDEX( _xlpm.next_month_inventory, 1, periods - 1 ), _xlpm.inventory_sold, _xlfn.HSTACK( _xlpm.next_month_inventory, _xlpm.last_month_inventory ), _xlpm.target_inventory, INDEX( CaseData!$C$31:$C$33, MATCH( $B65,_xlfn.ANCHORARRAY( $E$59), 0 ), 1 ), _xlpm.inventory_sold * _xlpm.target_inventory )} -> 28510.685 | K70: 31143.738 | L70: 33539.347 | M70: 35935.19 | N70: 38330.682 | O70: 40726.525 | P70: 43122.017 | Q70: 45283.086 | R70: 47913.47 | S70: 50079.363 | T70: 52704.805 | U70: 52704.805
B73: Product B
E75: Opening balance | G75: kg | J75: {=_xlfn.LET( _xlpm.inventory_target, INDEX( CaseData!$C$31:$C$33, MATCH( $B73,_xlfn.ANCHORARRAY( $E$59), 0 ), 1 ), _xlpm.opening_balance, INDEX(_xlfn.ANCHORARRAY( $J$59), MATCH( $B73,_xlfn.ANCHORARRAY( $E$59), 0 ), 1 ) * _xlpm.inventory_target, _xlfn.DROP( _xlfn.HSTACK( _xlpm.opening_balance,_xlfn.ANCHORARRAY( $J78) ),, -1 ) )} -> 6494.1065 | K75: 7084.4553 | L75: 7605.8586 | M75: 8265.2205 | N75: 8787.3324 | O75: 9445.9856 | P75: 9969.5003 | Q75: 10626.716 | R75: 11217.099 | S75: 11807.448 | T75: 12397.864 | U75: 12988.213
D76: add | E76: Product manufactured | G76: kg | J76: {=_xlfn.LET( _xlpm.opening_balance,_xlfn.ANCHORARRAY( $J75), _xlpm.product_sold,_xlfn.ANCHORARRAY( $J77), _xlpm.closing_balance,_xlfn.ANCHORARRAY( $J78), - _xlpm.product_sold + ( _xlpm.closing_balance - _xlpm.opening_balance ) )} -> 65531.414 | K76: 71365.957 | L76: 76717.948 | M76: 83174.317 | N76: 88531.977 | O76: 94983.371 | P76: 100352.22 | Q76: 106857.55 | R76: 112761.34 | S76: 118664.9 | T76: 124568.99 | U76: 129882.13
D77: less | E77: Product sold | G77: kg | J77: {=_xlfn._xlws.FILTER(_xlfn.ANCHORARRAY( $J$59),_xlfn.ANCHORARRAY( $E$59) = $B73) * - 1} -> -64941.065 | K77: -70844.553 | L77: -76058.586 | M77: -82652.205 | N77: -87873.324 | O77: -94459.856 | P77: -99695.003 | Q77: -106267.16 | R77: -112170.99 | S77: -118074.48 | T77: -123978.64 | U77: -129882.13
E78: Closing balance | G78: kg | J78: {=_xlfn.LET( _xlpm.next_month_inventory, _xlfn.DROP( INDEX(_xlfn.ANCHORARRAY( $J$59), MATCH( $B73,_xlfn.ANCHORARRAY( $E$59), 0 ), 0 ),,1 ), _xlpm.last_month_inventory, INDEX( _xlpm.next_month_inventory, 1, periods - 1 ), _xlpm.inventory_sold, _xlfn.HSTACK( _xlpm.next_month_inventory, _xlpm.last_month_inventory ), _xlpm.target_inventory, INDEX( CaseData!$C$31:$C$33, MATCH( $B73,_xlfn.ANCHORARRAY( $E$59), 0 ), 1 ), _xlpm.inventory_sold * _xlpm.target_inventory )} -> 7084.4553 | K78: 7605.8586 | L78: 8265.2205 | M78: 8787.3324 | N78: 9445.9856 | O78: 9969.5003 | P78: 10626.716 | Q78: 11217.099 | R78: 11807.448 | S78: 12397.864 | T78: 12988.213 | U78: 12988.213
B81: Product C
E83: Opening balance | G83: kg | J83: {=_xlfn.LET( _xlpm.inventory_target, INDEX( CaseData!$C$31:$C$33, MATCH( $B81,_xlfn.ANCHORARRAY( $E$59), 0 ), 1 ), _xlpm.opening_balance, INDEX(_xlfn.ANCHORARRAY( $J$59), MATCH( $B81,_xlfn.ANCHORARRAY( $E$59), 0 ), 1 ) * _xlpm.inventory_target, _xlfn.DROP( _xlfn.HSTACK( _xlpm.opening_balance,_xlfn.ANCHORARRAY( $J86) ),, -1 ) )} -> 8411.2542 | K83: 9175.9693 | L83: 9940.5979 | M83: 10705.225 | N83: 11469.94 | O83: 12234.568 | P83: 12999.194 | Q83: 13763.823 | R83: 14528.538 | S83: 15293.165 | T83: 16057.793 | U83: 16822.508
D84: add | E84: Product manufactured | G84: kg | J84: {=_xlfn.LET( _xlpm.opening_balance,_xlfn.ANCHORARRAY( $J83), _xlpm.product_sold,_xlfn.ANCHORARRAY( $J85), _xlpm.closing_balance,_xlfn.ANCHORARRAY( $J86), - _xlpm.product_sold + ( _xlpm.closing_balance - _xlpm.opening_balance ) )} -> 28802.229 | K84: 31351.193 | L84: 33899.953 | M84: 36448.797 | N84: 38997.761 | O84: 41546.52 | P84: 44095.276 | Q84: 46644.124 | R84: 49193.086 | S84: 51741.844 | T84: 54290.693 | U84: 56075.028
D85: less | E85: Product sold | G85: kg | J85: {=_xlfn._xlws.FILTER(_xlfn.ANCHORARRAY( $J$59),_xlfn.ANCHORARRAY( $E$59) = $B81) * - 1} -> -28037.514 | K85: -30586.564 | L85: -33135.326 | M85: -35684.082 | N85: -38233.133 | O85: -40781.895 | P85: -43330.647 | Q85: -45879.409 | R85: -48428.46 | S85: -50977.215 | T85: -53525.977 | U85: -56075.028
E86: Closing balance | G86: kg | J86: {=_xlfn.LET( _xlpm.next_month_inventory, _xlfn.DROP( INDEX(_xlfn.ANCHORARRAY( $J$59), MATCH( $B81,_xlfn.ANCHORARRAY( $E$59), 0 ), 0 ),,1 ), _xlpm.last_month_inventory, INDEX( _xlpm.next_month_inventory, 1, periods - 1 ), _xlpm.inventory_sold, _xlfn.HSTACK( _xlpm.next_month_inventory, _xlpm.last_month_inventory ), _xlpm.target_inventory, INDEX( CaseData!$C$31:$C$33, MATCH( $B81,_xlfn.ANCHORARRAY( $E$59), 0 ), 1 ), _xlpm.inventory_sold * _xlpm.target_inventory )} -> 9175.9693 | K86: 9940.5979 | L86: 10705.225 | M86: 11469.94 | N86: 12234.568 | O86: 12999.194 | P86: 13763.823 | Q86: 14528.538 | R86: 15293.165 | S86: 16057.793 | T86: 16822.508 | U86: 16822.508
B89: Product manufactured
E91: {=INDEX(_xlfn.ANCHORARRAY( $E$59), 0, 1 )} -> Product A | G91: kg | J91: {=_xlfn.ANCHORARRAY( $J$68)} -> 107567.89 | K91: 116675.79 | L91: 126970.56 | M91: 136553.23 | N91: 146136.25 | O91: 155718.57 | P91: 165301.59 | Q91: 174649.14 | R91: 183762.73 | S91: 193819.77 | T91: 202942.9 | U91: 210819.22
E92: Product B | G92: kg | J92: {=_xlfn.ANCHORARRAY( $J$76)} -> 65531.414 | K92: 71365.957 | L92: 76717.948 | M92: 83174.317 | N92: 88531.977 | O92: 94983.371 | P92: 100352.22 | Q92: 106857.55 | R92: 112761.34 | S92: 118664.9 | T92: 124568.99 | U92: 129882.13
E93: Product C | G93: kg | J93: {=_xlfn.ANCHORARRAY( $J$84)} -> 28802.229 | K93: 31351.193 | L93: 33899.953 | M93: 36448.797 | N93: 38997.761 | O93: 41546.52 | P93: 44095.276 | Q93: 46644.124 | R93: 49193.086 | S93: 51741.844 | T93: 54290.693 | U93: 56075.028
E94: Total product manufactured | G94: kg | J94: {=_xlfn.BYCOL( _xlfn.VSTACK(_xlfn.ANCHORARRAY( J91),_xlfn.ANCHORARRAY( J92),_xlfn.ANCHORARRAY( J93) ), _xleta.SUM )} -> 201901.54 | K94: 219392.94 | L94: 237588.46 | M94: 256176.35 | N94: 273665.99 | O94: 292248.46 | P94: 309749.09 | Q94: 328150.81 | R94: 345717.15 | S94: 364226.51 | T94: 381802.58 | U94: 396776.38
A97: Inventory valuation
B99: Product A
E101: Opening balance | G101: USD | J101: {=_xlfn.ANCHORARRAY( $J67) * 'Purchasing Plan'!$J$135} -> 35106.934 | K101: 37982.22 | L101: 41489.999 | M101: 44681.454 | N101: 47873.22 | O101: 51064.518 | P101: 54256.284 | Q101: 57447.583 | R101: 60326.579 | S101: 63830.804 | T101: 66716.229 | U101: 70213.868
D102: add | E102: Product manufactured | G102: USD | J102: {=_xlfn.ANCHORARRAY($J68)*'Purchasing Plan'!$J$135} -> 143303.02 | K102: 155436.66 | L102: 169151.45 | M102: 181917.58 | N102: 194684.18 | O102: 207449.84 | P102: 220216.44 | Q102: 232669.33 | R102: 244810.54 | S102: 258208.64 | T102: 270362.55 | U102: 280855.47
D103: less | E103: Product sold | G103: USD | J103: {=_xlfn.ANCHORARRAY($J69)*'Purchasing Plan'!$J$135} -> -140427.74 | K103: -151928.88 | L103: -165960 | M103: -178725.81 | N103: -191492.88 | O103: -204258.07 | P103: -217025.14 | Q103: -229790.33 | R103: -241306.32 | S103: -255323.22 | T103: -266864.91 | U103: -280855.47
E104: Closing balance | G104: USD | J104: {=_xlfn.ANCHORARRAY($J70)*'Purchasing Plan'!$J$135} -> 37982.22 | K104: 41489.999 | L104: 44681.454 | M104: 47873.22 | N104: 51064.518 | O104: 54256.284 | P104: 57447.583 | Q104: 60326.579 | R104: 63830.804 | S104: 66716.229 | T104: 70213.868 | U104: 70213.868
B107: Product B
E109: Opening balance | G109: USD | J109: {=_xlfn.ANCHORARRAY($J75)*'Purchasing Plan'!$J$136} -> 9974.8032 | K109: 10881.566 | L109: 11682.43 | M109: 12695.195 | N109: 13497.147 | O109: 14508.824 | P109: 15312.931 | Q109: 16322.4 | R109: 17229.215 | S109: 18135.977 | T109: 19042.844 | U109: 19949.606
D110: add | E110: Product manufactured | G110: USD | J110: {=_xlfn.ANCHORARRAY($J76)*'Purchasing Plan'!$J$136} -> 100654.79 | K110: 109616.52 | L110: 117837.06 | M110: 127753.9 | N110: 135983.15 | O110: 145892.35 | P110: 154138.78 | Q110: 164130.81 | R110: 173198.91 | S110: 182266.64 | T110: 191335.2 | U110: 199496.06
D111: less | E111: Product sold | G111: USD | J111: {=_xlfn.ANCHORARRAY($J77)*'Purchasing Plan'!$J$136} -> -99748.032 | K111: -108815.66 | L111: -116824.3 | M111: -126951.95 | N111: -134971.47 | O111: -145088.24 | P111: -153129.31 | Q111: -163224 | R111: -172292.15 | S111: -181359.77 | T111: -190428.44 | U111: -199496.06
E112: Closing balance | G112: USD | J112: {=_xlfn.ANCHORARRAY($J78)*'Purchasing Plan'!$J$136} -> 10881.566 | K112: 11682.43 | L112: 12695.195 | M112: 13497.147 | N112: 14508.824 | O112: 15312.931 | P112: 16322.4 | Q112: 17229.215 | R112: 18135.977 | S112: 19042.844 | T112: 19949.606 | U112: 19949.606
B115: Product C
E117: Opening balance | G117: USD | J117: {=_xlfn.ANCHORARRAY($J83)*'Purchasing Plan'!$J$137} -> 14753.897 | K117: 16095.259 | L117: 17436.468 | M117: 18777.674 | N117: 20119.035 | O117: 21460.244 | P117: 22801.448 | Q117: 24142.658 | R117: 25484.019 | S117: 26825.225 | T117: 28166.434 | U117: 29507.795
D118: add | E118: Product manufactured | G118: USD | J118: {=_xlfn.ANCHORARRAY($J84)*'Purchasing Plan'!$J$137} -> 50521.019 | K118: 54992.071 | L118: 59462.765 | M118: 63933.607 | N118: 68404.659 | O118: 72875.351 | P118: 77346.037 | Q118: 81816.887 | R118: 86287.935 | S118: 90758.625 | T118: 95229.474 | U118: 98359.317
D119: less | E119: Product sold | G119: USD | J119: {=_xlfn.ANCHORARRAY($J85)*'Purchasing Plan'!$J$137} -> -49179.658 | K119: -53650.862 | L119: -58121.559 | M119: -62592.246 | N119: -67063.449 | O119: -71534.147 | P119: -76004.828 | Q119: -80475.526 | R119: -84946.729 | S119: -89417.416 | T119: -93888.113 | U119: -98359.317
E120: Closing balance | G120: USD | J120: {=_xlfn.ANCHORARRAY($J86)*'Purchasing Plan'!$J$137} -> 16095.259 | K120: 17436.468 | L120: 18777.674 | M120: 20119.035 | N120: 21460.244 | O120: 22801.448 | P120: 24142.658 | Q120: 25484.019 | R120: 26825.225 | S120: 28166.434 | T120: 29507.795 | U120: 29507.795
B123: Inventory
E125: {=INDEX(_xlfn.ANCHORARRAY( $E$59), 0, 1 )} -> Product A | G125: USD | J125: {=_xlfn.ANCHORARRAY( J104)} -> 37982.22 | K125: 41489.999 | L125: 44681.454 | M125: 47873.22 | N125: 51064.518 | O125: 54256.284 | P125: 57447.583 | Q125: 60326.579 | R125: 63830.804 | S125: 66716.229 | T125: 70213.868 | U125: 70213.868
E126: Product B | G126: USD | J126: {=_xlfn.ANCHORARRAY( J112)} -> 10881.566 | K126: 11682.43 | L126: 12695.195 | M126: 13497.147 | N126: 14508.824 | O126: 15312.931 | P126: 16322.4 | Q126: 17229.215 | R126: 18135.977 | S126: 19042.844 | T126: 19949.606 | U126: 19949.606
E127: Product C | G127: USD | J127: {=_xlfn.ANCHORARRAY( J120)} -> 16095.259 | K127: 17436.468 | L127: 18777.674 | M127: 20119.035 | N127: 21460.244 | O127: 22801.448 | P127: 24142.658 | Q127: 25484.019 | R127: 26825.225 | S127: 28166.434 | T127: 29507.795 | U127: 29507.795
E128: Inventory | G128: USD | J128: {=_xlfn.BYCOL( J125:U127, _xleta.SUM )} -> 64959.044 | K128: 70608.896 | L128: 76154.322 | M128: 81489.402 | N128: 87033.586 | O128: 92370.663 | P128: 97912.64 | Q128: 103039.81 | R128: 108792.01 | S128: 113925.51 | T128: 119671.27 | U128: 119671.27
A185: End of schedule

Sheet Accounts Receivables
A1: {=company} -> Sweet Dreams Co.
A2: {=topic} -> CFM Topic: Working Capital
A3: ACCOUNTS RECEIVABLE SCHEDULE | F3: Constant | G3: Unit | H3: Total | J3: {=EOMONTH( start_date, _xlfn.SEQUENCE( 1, periods, 0, 1 ) )} -> 44592 | K3: 44620 | L3: 44651 | M3: 44681 | N3: 44712 | O3: 44742 | P3: 44773 | Q3: 44804 | R3: 44834 | S3: 44865 | T3: 44895 | U3: 44926
A5: Accounts receivables
B7: Payment Terms
C9: Retailer 1
E11: Payment terms | F11: =INDEX( CaseData!$C$63:$C$65, MATCH( 'Accounts Receivables'!$C9, CaseData!$A$63:$A$65, 0 ) ) / days_per_month -> 3 | G11: months
F13: Months | G13: Sales | J13: {=_xlfn.SEQUENCE( 1, periods, 1, 1 )} -> 1 | K13: 2 | L13: 3 | M13: 4 | N13: 5 | O13: 6 | P13: 7 | Q13: 8 | R13: 9 | S13: 10 | T13: 11 | U13: 12
F14: =F15-1 -> -2 | G14: {=_xlfn.SEQUENCE( $F$11, 1, $G17, 0 )} -> 210000 | J14: {=IF(_xlfn.ANCHORARRAY( J13) - $F$14:$F$28 < 0, 0, IF(_xlfn.ANCHORARRAY( J13) - $F$14:$F$28 < INT($F$11), 1, IF(_xlfn.ANCHORARRAY( J13) - $F$14:$F$28 < $F$11, MOD($F$11, 1), 0 ) ) )} -> 0 | K14: 0 | L14: 0 | M14: 0 | N14: 0 | O14: 0 | P14: 0 | Q14: 0 | R14: 0 | S14: 0 | T14: 0 | U14: 0
F15: =F16-1 -> -1 | G15: 210000 | J15: 1 | K15: 0 | L15: 0 | M15: 0 | N15: 0 | O15: 0 | P15: 0 | Q15: 0 | R15: 0 | S15: 0 | T15: 0 | U15: 0
F16: =F17-1 -> 0 | G16: 210000 | J16: 1 | K16: 1 | L16: 0 | M16: 0 | N16: 0 | O16: 0 | P16: 0 | Q16: 0 | R16: 0 | S16: 0 | T16: 0 | U16: 0
F17: {=_xlfn.SEQUENCE( periods, 1, 1, 1 )} -> 1 | G17: {=_xlfn.LET( _xlpm.revenue_table, CaseData!$C$7:$N$20, _xlpm.revenue_rows, CaseData!$A$7:$A$20, _xlpm.revenue_columns, CaseData!$C$3:$N$3, _xlpm.current_retailer, $C9, _xlpm.current_month,_xlfn.ANCHORARRAY( 'Accounts Receivables'!$J$3), _xlpm.revenue, INDEX( _xlpm.revenue_table, MATCH( _xlpm.current_retailer, _xlpm.revenue_rows, 0 ), MATCH( _xlpm.current_month, _xlpm.revenue_columns, 0 ) ), TRANSPOSE( _xlpm.revenue ) )} -> 210000 | J17: 1 | K17: 1 | L17: 1 | M17: 0 | N17: 0 | O17: 0 | P17: 0 | Q17: 0 | R17: 0 | S17: 0 | T17: 0 | U17: 0
F18: 2 | G18: 229091 | J18: 0 | K18: 1 | L18: 1 | M18: 1 | N18: 0 | O18: 0 | P18: 0 | Q18: 0 | R18: 0 | S18: 0 | T18: 0 | U18: 0
F19: 3 | G19: 248182 | J19: 0 | K19: 0 | L19: 1 | M19: 1 | N19: 1 | O19: 0 | P19: 0 | Q19: 0 | R19: 0 | S19: 0 | T19: 0 | U19: 0
F20: 4 | G20: 267272 | J20: 0 | K20: 0 | L20: 0 | M20: 1 | N20: 1 | O20: 1 | P20: 0 | Q20: 0 | R20: 0 | S20: 0 | T20: 0 | U20: 0
F21: 5 | G21: 284364 | J21: 0 | K21: 0 | L21: 0 | M21: 0 | N21: 1 | O21: 1 | P21: 1 | Q21: 0 | R21: 0 | S21: 0 | T21: 0 | U21: 0
F22: 6 | G22: 305454 | J22: 0 | K22: 0 | L22: 0 | M22: 0 | N22: 0 | O22: 1 | P22: 1 | Q22: 1 | R22: 0 | S22: 0 | T22: 0 | U22: 0
F23: 7 | G23: 324546 | J23: 0 | K23: 0 | L23: 0 | M23: 0 | N23: 0 | O23: 0 | P23: 1 | Q23: 1 | R23: 1 | S23: 0 | T23: 0 | U23: 0
F24: 8 | G24: 343636 | J24: 0 | K24: 0 | L24: 0 | M24: 0 | N24: 0 | O24: 0 | P24: 0 | Q24: 1 | R24: 1 | S24: 1 | T24: 0 | U24: 0
F25: 9 | G25: 360728 | J25: 0 | K25: 0 | L25: 0 | M25: 0 | N25: 0 | O25: 0 | P25: 0 | Q25: 0 | R25: 1 | S25: 1 | T25: 1 | U25: 0
F26: 10 | G26: 381818 | J26: 0 | K26: 0 | L26: 0 | M26: 0 | N26: 0 | O26: 0 | P26: 0 | Q26: 0 | R26: 0 | S26: 1 | T26: 1 | U26: 1
F27: 11 | G27: 400909 | J27: 0 | K27: 0 | L27: 0 | M27: 0 | N27: 0 | O27: 0 | P27: 0 | Q27: 0 | R27: 0 | S27: 0 | T27: 1 | U27: 1
F28: 12 | G28: 420000 | J28: 0 | K28: 0 | L28: 0 | M28: 0 | N28: 0 | O28: 0 | P28: 0 | Q28: 0 | R28: 0 | S28: 0 | T28: 0 | U28: 1
E29: Accounts receivable closing balance | J29: {=_xlfn.BYCOL(_xlfn.ANCHORARRAY( $J14), _xlfn.LAMBDA(_xlpm.month_col, SUMPRODUCT( $G14:$G28, _xlpm.month_col ) ) )} -> 630000 | K29: 649091 | L29: 687273 | M29: 744545 | N29: 799818 | O29: 857090 | P29: 914364 | Q29: 973636 | R29: 1028910 | S29: 1086182 | T29: 1143455 | U29: 1202727
E32: Accounts receivable opening balance | G32: USD | J32: {=_xlfn.DROP( _xlfn.HSTACK( SUM( $G$14:$G$16 ) / 3 * $F11,_xlfn.ANCHORARRAY( J35) ),, -1 )} -> 630000 | K32: 630000 | L32: 649091 | M32: 687273 | N32: 744545 | O32: 799818 | P32: 857090 | Q32: 914364 | R32: 973636 | S32: 1028910 | T32: 1086182 | U32: 1143455
D33: plus | E33: Sales | G33: USD | J33: {=TRANSPOSE(_xlfn.ANCHORARRAY( G17))} -> 210000 | K33: 229091 | L33: 248182 | M33: 267272 | N33: 284364 | O33: 305454 | P33: 324546 | Q33: 343636 | R33: 360728 | S33: 381818 | T33: 400909 | U33: 420000
D34: minus | E34: Payments received from retailers | G34: USD | J34: {=_xlfn.LET( _xlpm.ar_opening,_xlfn.ANCHORARRAY( J32), _xlpm.revenue,_xlfn.ANCHORARRAY( J33), _xlpm.ar_closing,_xlfn.ANCHORARRAY( J35), ( _xlpm.ar_opening + _xlpm.revenue - _xlpm.ar_closing ) * - 1)} -> -210000 | K34: -210000 | L34: -210000 | M34: -210000 | N34: -229091 | O34: -248182 | P34: -267272 | Q34: -284364 | R34: -305454 | S34: -324546 | T34: -343636 | U34: -360728
E35: Retailer 1: Accounts receivable closing balance | G35: USD | J35: {=J29:U29} -> 630000 | K35: 649091 | L35: 687273 | M35: 744545 | N35: 799818 | O35: 857090 | P35: 914364 | Q35: 973636 | R35: 1028910 | S35: 1086182 | T35: 1143455 | U35: 1202727
C38: Retailer 2
E40: Payment terms | F40: =INDEX( CaseData!$C$63:$C$65, MATCH( 'Accounts Receivables'!$C38, CaseData!$A$63:$A$65, 0 ) ) / days_per_month -> 1.5 | G40: months
F42: Months | G42: Sales | J42: {=_xlfn.SEQUENCE( 1, periods, 1, 1 )} -> 1 | K42: 2 | L42: 3 | M42: 4 | N42: 5 | O42: 6 | P42: 7 | Q42: 8 | R42: 9 | S42: 10 | T42: 11 | U42: 12
F43: =F44-1 -> -2 | G43: {=_xlfn.SEQUENCE( $F$11, 1, $G46, 0 )} -> 105000 | J43: {=IF(_xlfn.ANCHORARRAY( J42) - $F$14:$F$28 < 0, 0, IF(_xlfn.ANCHORARRAY( J42) - $F$14:$F$28 < INT($F$40), 1, IF(_xlfn.ANCHORARRAY( J42) - $F$14:$F$28 < $F$40, MOD($F$40, 1), 0 ) ) )} -> 0 | K43: 0 | L43: 0 | M43: 0 | N43: 0 | O43: 0 | P43: 0 | Q43: 0 | R43: 0 | S43: 0 | T43: 0 | U43: 0
F44: =F45-1 -> -1 | G44: 105000 | J44: 0 | K44: 0 | L44: 0 | M44: 0 | N44: 0 | O44: 0 | P44: 0 | Q44: 0 | R44: 0 | S44: 0 | T44: 0 | U44: 0
F45: =F46-1 -> 0 | G45: 105000 | J45: 0.5 | K45: 0 | L45: 0 | M45: 0 | N45: 0 | O45: 0 | P45: 0 | Q45: 0 | R45: 0 | S45: 0 | T45: 0 | U45: 0
F46: {=_xlfn.SEQUENCE( periods, 1, 1, 1 )} -> 1 | G46: {=_xlfn.LET( _xlpm.revenue_table, CaseData!$C$7:$N$20, _xlpm.revenue_rows, CaseData!$A$7:$A$20, _xlpm.revenue_columns, CaseData!$C$3:$N$3, _xlpm.current_retailer, $C38, _xlpm.current_month,_xlfn.ANCHORARRAY( 'Accounts Receivables'!$J$3), _xlpm.revenue, INDEX( _xlpm.revenue_table, MATCH( _xlpm.current_retailer, _xlpm.revenue_rows, 0 ), MATCH( _xlpm.current_month, _xlpm.revenue_columns, 0 ) ), TRANSPOSE( _xlpm.revenue ) )} -> 105000 | J46: 1 | K46: 0.5 | L46: 0 | M46: 0 | N46: 0 | O46: 0 | P46: 0 | Q46: 0 | R46: 0 | S46: 0 | T46: 0 | U46: 0
F47: 2 | G47: 114545 | J47: 0 | K47: 1 | L47: 0.5 | M47: 0 | N47: 0 | O47: 0 | P47: 0 | Q47: 0 | R47: 0 | S47: 0 | T47: 0 | U47: 0
F48: 3 | G48: 124091 | J48: 0 | K48: 0 | L48: 1 | M48: 0.5 | N48: 0 | O48: 0 | P48: 0 | Q48: 0 | R48: 0 | S48: 0 | T48: 0 | U48: 0
F49: 4 | G49: 133636 | J49: 0 | K49: 0 | L49: 0 | M49: 1 | N49: 0.5 | O49: 0 | P49: 0 | Q49: 0 | R49: 0 | S49: 0 | T49: 0 | U49: 0
F50: 5 | G50: 143182 | J50: 0 | K50: 0 | L50: 0 | M50: 0 | N50: 1 | O50: 0.5 | P50: 0 | Q50: 0 | R50: 0 | S50: 0 | T50: 0 | U50: 0
F51: 6 | G51: 152727 | J51: 0 | K51: 0 | L51: 0 | M51: 0 | N51: 0 | O51: 1 | P51: 0.5 | Q51: 0 | R51: 0 | S51: 0 | T51: 0 | U51: 0
F52: 7 | G52: 160273 | J52: 0 | K52: 0 | L52: 0 | M52: 0 | N52: 0 | O52: 0 | P52: 1 | Q52: 0.5 | R52: 0 | S52: 0 | T52: 0 | U52: 0
F53: 8 | G53: 171818 | J53: 0 | K53: 0 | L53: 0 | M53: 0 | N53: 0 | O53: 0 | P53: 0 | Q53: 1 | R53: 0.5 | S53: 0 | T53: 0 | U53: 0
F54: 9 | G54: 181364 | J54: 0 | K54: 0 | L54: 0 | M54: 0 | N54: 0 | O54: 0 | P54: 0 | Q54: 0 | R54: 1 | S54: 0.5 | T54: 0 | U54: 0
F55: 10 | G55: 190909 | J55: 0 | K55: 0 | L55: 0 | M55: 0 | N55: 0 | O55: 0 | P55: 0 | Q55: 0 | R55: 0 | S55: 1 | T55: 0.5 | U55: 0
F56: 11 | G56: 198455 | J56: 0 | K56: 0 | L56: 0 | M56: 0 | N56: 0 | O56: 0 | P56: 0 | Q56: 0 | R56: 0 | S56: 0 | T56: 1 | U56: 0.5
F57: 12 | G57: 210000 | J57: 0 | K57: 0 | L57: 0 | M57: 0 | N57: 0 | O57: 0 | P57: 0 | Q57: 0 | R57: 0 | S57: 0 | T57: 0 | U57: 1
E58: Accounts receivable closing balance | J58: {=_xlfn.BYCOL(_xlfn.ANCHORARRAY( $J43), _xlfn.LAMBDA(_xlpm.month_col, SUMPRODUCT( $G43:$G57, _xlpm.month_col ) ) )} -> 157500 | K58: 167045 | L58: 181363.5 | M58: 195681.5 | N58: 210000 | O58: 224318 | P58: 236636.5 | Q58: 251954.5 | R58: 267273 | S58: 281591 | T58: 293909.5 | U58: 309227.5
E61: Accounts receivable opening balance | G61: USD | J61: {=_xlfn.DROP( _xlfn.HSTACK( SUM(_xlfn.ANCHORARRAY( G43) ) / 3 * $F40,_xlfn.ANCHORARRAY( J64) ),, -1 )} -> 157500 | K61: 157500 | L61: 167045 | M61: 181363.5 | N61: 195681.5 | O61: 210000 | P61: 224318 | Q61: 236636.5 | R61: 251954.5 | S61: 267273 | T61: 281591 | U61: 293909.5
D62: plus | E62: Sales | G62: USD | J62: {=TRANSPOSE(_xlfn.ANCHORARRAY( G46))} -> 105000 | K62: 114545 | L62: 124091 | M62: 133636 | N62: 143182 | O62: 152727 | P62: 160273 | Q62: 171818 | R62: 181364 | S62: 190909 | T62: 198455 | U62: 210000
D63: minus | E63: Payments received from retailers | G63: USD | J63: {=_xlfn.LET( _xlpm.ar_opening,_xlfn.ANCHORARRAY( J61), _xlpm.revenue,_xlfn.ANCHORARRAY( J62), _xlpm.ar_closing,_xlfn.ANCHORARRAY( J64), ( _xlpm.ar_opening + _xlpm.revenue - _xlpm.ar_closing ) * - 1)} -> -105000 | K63: -105000 | L63: -109772.5 | M63: -119318 | N63: -128863.5 | O63: -138409 | P63: -147954.5 | Q63: -156500 | R63: -166045.5 | S63: -176591 | T63: -186136.5 | U63: -194682
E64: Retailer 2: Accounts receivable closing balance | G64: USD | J64: {=J58:U58} -> 157500 | K64: 167045 | L64: 181363.5 | M64: 195681.5 | N64: 210000 | O64: 224318 | P64: 236636.5 | Q64: 251954.5 | R64: 267273 | S64: 281591 | T64: 293909.5 | U64: 309227.5
C67: Retailer 3
E69: Payment terms | F69: =INDEX( CaseData!$C$63:$C$65, MATCH( 'Accounts Receivables'!$C67, CaseData!$A$63:$A$65, 0 ) ) / days_per_month -> 2 | G69: months
F71: Months | G71: Sales | J71: {=_xlfn.SEQUENCE( 1, periods, 1, 1 )} -> 1 | K71: 2 | L71: 3 | M71: 4 | N71: 5 | O71: 6 | P71: 7 | Q71: 8 | R71: 9 | S71: 10 | T71: 11 | U71: 12
F72: =F73-1 -> -2 | G72: {=_xlfn.SEQUENCE( $F$11, 1, $G75, 0 )} -> 195000 | J72: {=IF(_xlfn.ANCHORARRAY( J71) - $F$14:$F$28 < 0, 0, IF(_xlfn.ANCHORARRAY( J71) - $F$14:$F$28 < INT($F$69), 1, IF(_xlfn.ANCHORARRAY( J71) - $F$14:$F$28 < $F$69, MOD($F$69, 1), 0 ) ) )} -> 0 | K72: 0 | L72: 0 | M72: 0 | N72: 0 | O72: 0 | P72: 0 | Q72: 0 | R72: 0 | S72: 0 | T72: 0 | U72: 0
F73: =F74-1 -> -1 | G73: 195000 | J73: 0 | K73: 0 | L73: 0 | M73: 0 | N73: 0 | O73: 0 | P73: 0 | Q73: 0 | R73: 0 | S73: 0 | T73: 0 | U73: 0
F74: =F75-1 -> 0 | G74: 195000 | J74: 1 | K74: 0 | L74: 0 | M74: 0 | N74: 0 | O74: 0 | P74: 0 | Q74: 0 | R74: 0 | S74: 0 | T74: 0 | U74: 0
F75: {=_xlfn.SEQUENCE( periods, 1, 1, 1 )} -> 1 | G75: {=_xlfn.LET( _xlpm.revenue_table, CaseData!$C$7:$N$20, _xlpm.revenue_rows, CaseData!$A$7:$A$20, _xlpm.revenue_columns, CaseData!$C$3:$N$3, _xlpm.current_retailer, $C67, _xlpm.current_month,_xlfn.ANCHORARRAY( 'Accounts Receivables'!$J$3), _xlpm.revenue, INDEX( _xlpm.revenue_table, MATCH( _xlpm.current_retailer, _xlpm.revenue_rows, 0 ), MATCH( _xlpm.current_month, _xlpm.revenue_columns, 0 ) ), TRANSPOSE( _xlpm.revenue ) )} -> 195000 | J75: 1 | K75: 1 | L75: 0 | M75: 0 | N75: 0 | O75: 0 | P75: 0 | Q75: 0 | R75: 0 | S75: 0 | T75: 0 | U75: 0
F76: 2 | G76: 210727 | J76: 0 | K76: 1 | L76: 1 | M76: 0 | N76: 0 | O76: 0 | P76: 0 | Q76: 0 | R76: 0 | S76: 0 | T76: 0 | U76: 0
F77: 3 | G77: 228455 | J77: 0 | K77: 0 | L77: 1 | M77: 1 | N77: 0 | O77: 0 | P77: 0 | Q77: 0 | R77: 0 | S77: 0 | T77: 0 | U77: 0
F78: 4 | G78: 248182 | J78: 0 | K78: 0 | L78: 0 | M78: 1 | N78: 1 | O78: 0 | P78: 0 | Q78: 0 | R78: 0 | S78: 0 | T78: 0 | U78: 0
F79: 5 | G79: 265910 | J79: 0 | K79: 0 | L79: 0 | M79: 0 | N79: 1 | O79: 1 | P79: 0 | Q79: 0 | R79: 0 | S79: 0 | T79: 0 | U79: 0
F80: 6 | G80: 283637 | J80: 0 | K80: 0 | L80: 0 | M80: 0 | N80: 0 | O80: 1 | P80: 1 | Q80: 0 | R80: 0 | S80: 0 | T80: 0 | U80: 0
F81: 7 | G81: 301363 | J81: 0 | K81: 0 | L81: 0 | M81: 0 | N81: 0 | O81: 0 | P81: 1 | Q81: 1 | R81: 0 | S81: 0 | T81: 0 | U81: 0
F82: 8 | G82: 319090 | J82: 0 | K82: 0 | L82: 0 | M82: 0 | N82: 0 | O82: 0 | P82: 0 | Q82: 1 | R82: 1 | S82: 0 | T82: 0 | U82: 0
F83: 9 | G83: 336818 | J83: 0 | K83: 0 | L83: 0 | M83: 0 | N83: 0 | O83: 0 | P83: 0 | Q83: 0 | R83: 1 | S83: 1 | T83: 0 | U83: 0
F84: 10 | G84: 354545 | J84: 0 | K84: 0 | L84: 0 | M84: 0 | N84: 0 | O84: 0 | P84: 0 | Q84: 0 | R84: 0 | S84: 1 | T84: 1 | U84: 0
F85: 11 | G85: 372273 | J85: 0 | K85: 0 | L85: 0 | M85: 0 | N85: 0 | O85: 0 | P85: 0 | Q85: 0 | R85: 0 | S85: 0 | T85: 1 | U85: 1
F86: 12 | G86: 390000 | J86: 0 | K86: 0 | L86: 0 | M86: 0 | N86: 0 | O86: 0 | P86: 0 | Q86: 0 | R86: 0 | S86: 0 | T86: 0 | U86: 1
E87: Accounts receivable closing balance | J87: {=_xlfn.BYCOL(_xlfn.ANCHORARRAY( $J72), _xlfn.LAMBDA(_xlpm.month_col, SUMPRODUCT( $G72:$G86, _xlpm.month_col ) ) )} -> 390000 | K87: 405727 | L87: 439182 | M87: 476637 | N87: 514092 | O87: 549547 | P87: 585000 | Q87: 620453 | R87: 655908 | S87: 691363 | T87: 726818 | U87: 762273
E90: Accounts receivable opening balance | G90: USD | J90: {=_xlfn.DROP( _xlfn.HSTACK( SUM(_xlfn.ANCHORARRAY( G72) ) / 3 * $F69,_xlfn.ANCHORARRAY( J93) ),, -1 )} -> 390000 | K90: 390000 | L90: 405727 | M90: 439182 | N90: 476637 | O90: 514092 | P90: 549547 | Q90: 585000 | R90: 620453 | S90: 655908 | T90: 691363 | U90: 726818
D91: plus | E91: Sales | G91: USD | J91: {=TRANSPOSE(_xlfn.ANCHORARRAY( G75))} -> 195000 | K91: 210727 | L91: 228455 | M91: 248182 | N91: 265910 | O91: 283637 | P91: 301363 | Q91: 319090 | R91: 336818 | S91: 354545 | T91: 372273 | U91: 390000
D92: minus | E92: Payments received from retailers | G92: USD | J92: {=_xlfn.LET( _xlpm.ar_opening,_xlfn.ANCHORARRAY( J90), _xlpm.revenue,_xlfn.ANCHORARRAY( J91), _xlpm.ar_closing,_xlfn.ANCHORARRAY( J93), ( _xlpm.ar_opening + _xlpm.revenue - _xlpm.ar_closing ) * - 1)} -> -195000 | K92: -195000 | L92: -195000 | M92: -210727 | N92: -228455 | O92: -248182 | P92: -265910 | Q92: -283637 | R92: -301363 | S92: -319090 | T92: -336818 | U92: -354545
E93: Retailer 3: Accounts receivable closing balance | G93: USD | J93: {=J87:U87} -> 390000 | K93: 405727 | L93: 439182 | M93: 476637 | N93: 514092 | O93: 549547 | P93: 585000 | Q93: 620453 | R93: 655908 | S93: 691363 | T93: 726818 | U93: 762273
A96: SUMMARY
B98: Accounts receivables
E100: A/R opening balance | G100: USD m | J100: {=_xlfn.ANCHORARRAY( J32) +_xlfn.ANCHORARRAY( J61) +_xlfn.ANCHORARRAY( J90)} -> 1177500 | K100: 1177500 | L100: 1221863 | M100: 1307818.5 | N100: 1416863.5 | O100: 1523910 | P100: 1630955 | Q100: 1736000.5 | R100: 1846043.5 | S100: 1952091 | T100: 2059136 | U100: 2164182.5
E101: Sales | G101: USD m | J101: {=_xlfn.ANCHORARRAY( J33) +_xlfn.ANCHORARRAY( J62) +_xlfn.ANCHORARRAY( J91)} -> 510000 | K101: 554363 | L101: 600728 | M101: 649090 | N101: 693456 | O101: 741818 | P101: 786182 | Q101: 834544 | R101: 878910 | S101: 927272 | T101: 971637 | U101: 1020000
E102: Payments received from retailers from retailers | G102: USD m | J102: {=_xlfn.ANCHORARRAY( J34) +_xlfn.ANCHORARRAY( J63) +_xlfn.ANCHORARRAY( J92)} -> -510000 | K102: -510000 | L102: -514772.5 | M102: -540045 | N102: -586409.5 | O102: -634773 | P102: -681136.5 | Q102: -724501 | R102: -772862.5 | S102: -820227 | T102: -866590.5 | U102: -909955
E103: A/R closing balance | G103: USD m | J103: {=_xlfn.ANCHORARRAY( J35) +_xlfn.ANCHORARRAY( J64) +_xlfn.ANCHORARRAY( J93)} -> 1177500 | K103: 1221863 | L103: 1307818.5 | M103: 1416863.5 | N103: 1523910 | O103: 1630955 | P103: 1736000.5 | Q103: 1846043.5 | R103: 1952091 | S103: 2059136 | T103: 2164182.5 | U103: 2274227.5
A128: End of schedule

Sheet CaseData
A1: 1. Sales Assumptions
A3: Retailer/Product - Base Case Scenario | C3: 44592 | D3: =EOMONTH(C3,1) -> 44620 | E3: =EOMONTH(D3,1) -> 44651 | F3: =EOMONTH(E3,1) -> 44681 | G3: =EOMONTH(F3,1) -> 44712 | H3: =EOMONTH(G3,1) -> 44742 | I3: =EOMONTH(H3,1) -> 44773 | J3: =EOMONTH(I3,1) -> 44804 | K3: =EOMONTH(J3,1) -> 44834 | ... N3: =EOMONTH(M3,1) -> 44926 | O3: Total
A5: Total Sales | B5: [$] | C5: =SUBTOTAL(9,C7:C21) -> 510000 | D5: =SUBTOTAL(9,D7:D21) -> 554363 | E5: =SUBTOTAL(9,E7:E21) -> 600728 | F5: =SUBTOTAL(9,F7:F21) -> 649090 | G5: =SUBTOTAL(9,G7:G21) -> 693456 | H5: =SUBTOTAL(9,H7:H21) -> 741818 | I5: =SUBTOTAL(9,I7:I21) -> 786182 | J5: =SUBTOTAL(9,J7:J21) -> 834544 | ... O5: =SUBTOTAL(9,O7:O21) -> 9168000
A7: Retailer 1 | B7: [$] | C7: =SUBTOTAL(9,C8:C10) -> 210000 | D7: =SUBTOTAL(9,D8:D10) -> 229091 | E7: =SUBTOTAL(9,E8:E10) -> 248182 | F7: =SUBTOTAL(9,F8:F10) -> 267272 | G7: =SUBTOTAL(9,G8:G10) -> 284364 | H7: =SUBTOTAL(9,H8:H10) -> 305454 | I7: =SUBTOTAL(9,I8:I10) -> 324546 | J7: =SUBTOTAL(9,J8:J10) -> 343636 | ... O7: =SUBTOTAL(9,O8:O10) -> 3776000
A8: Product A | B8: [$] | C8: 125000 | D8: 136364 | E8: 147727 | F8: 159091 | G8: 170455 | H8: 181818 | I8: 193182 | J8: 204545 | K8: 213909 | L8: 227273 | M8: 238636 | N8: 250000 | O8: =SUM(C8:N8) -> 2248000
A9: Product B | B9: [$] | C9: 50000 | D9: 54545 | E9: 59091 | F9: 63636 | G9: 66182 | H9: 72727 | I9: 77273 | J9: 81818 | K9: 86364 | L9: 90909 | M9: 95455 | N9: 100000 | O9: =SUM(C9:N9) -> 898000
A10: Product C | B10: [$] | C10: 35000 | D10: 38182 | E10: 41364 | F10: 44545 | G10: 47727 | H10: 50909 | I10: 54091 | J10: 57273 | K10: 60455 | L10: 63636 | M10: 66818 | N10: 70000 | O10: =SUM(C10:N10) -> 630000
A12: Retailer 2 | B12: [$] | C12: =SUBTOTAL(9,C13:C15) -> 105000 | D12: =SUBTOTAL(9,D13:D15) -> 114545 | E12: =SUBTOTAL(9,E13:E15) -> 124091 | F12: =SUBTOTAL(9,F13:F15) -> 133636 | G12: =SUBTOTAL(9,G13:G15) -> 143182 | H12: =SUBTOTAL(9,H13:H15) -> 152727 | I12: =SUBTOTAL(9,I13:I15) -> 160273 | J12: =SUBTOTAL(9,J13:J15) -> 171818 | ... O12: =SUBTOTAL(9,O13:O15) -> 1886000
A13: Product A | B13: [$] | C13: 50000 | D13: 54545 | E13: 59091 | F13: 63636 | G13: 68182 | H13: 72727 | I13: 77273 | J13: 81818 | K13: 86364 | L13: 90909 | M13: 93455 | N13: 100000 | O13: =SUM(C13:N13) -> 898000
A14: Product B | B14: [$] | C14: 40000 | D14: 43636 | E14: 47273 | F14: 50909 | G14: 54545 | H14: 58182 | I14: 59818 | J14: 65455 | K14: 69091 | L14: 72727 | M14: 76364 | N14: 80000 | O14: =SUM(C14:N14) -> 718000
A15: Product C | B15: [$] | C15: 15000 | D15: 16364 | E15: 17727 | F15: 19091 | G15: 20455 | H15: 21818 | I15: 23182 | J15: 24545 | K15: 25909 | L15: 27273 | M15: 28636 | N15: 30000 | O15: =SUM(C15:N15) -> 270000
A17: Retailer 3 | B17: [$] | C17: =SUBTOTAL(9,C18:C20) -> 195000 | D17: =SUBTOTAL(9,D18:D20) -> 210727 | E17: =SUBTOTAL(9,E18:E20) -> 228455 | F17: =SUBTOTAL(9,F18:F20) -> 248182 | G17: =SUBTOTAL(9,G18:G20) -> 265910 | H17: =SUBTOTAL(9,H18:H20) -> 283637 | I17: =SUBTOTAL(9,I18:I20) -> 301363 | J17: =SUBTOTAL(9,J18:J20) -> 319090 | ... O17: =SUBTOTAL(9,O18:O20) -> 3506000
A18: Product A | B18: [$] | C18: 50000 | D18: 52545 | E18: 59091 | F18: 63636 | G18: 68182 | H18: 72727 | I18: 77273 | J18: 81818 | K18: 86364 | L18: 90909 | M18: 95455 | N18: 100000 | O18: =SUM(C18:N18) -> 898000
A19: Product B | B19: [$] | C19: 100000 | D19: 109091 | E19: 116182 | F19: 127273 | G19: 136364 | H19: 145455 | I19: 154545 | J19: 163636 | K19: 172727 | L19: 181818 | M19: 190909 | N19: 200000 | O19: =SUM(C19:N19) -> 1798000
A20: Product C | B20: [$] | C20: 45000 | D20: 49091 | E20: 53182 | F20: 57273 | G20: 61364 | H20: 65455 | I20: 69545 | J20: 73636 | K20: 77727 | L20: 81818 | M20: 85909 | N20: 90000 | O20: =SUM(C20:N20) -> 810000
A22: 2. Working Capital Assumptions
A24: Retailer Deferred Payment Days and Price Discounts | I24: Supplier Deferred Payment Days and Opening A/P
C25: Days | D25: Discount | L25: Days | M25: Opening A/P
A26: Retailer 1 | B26: [days] | C26: 90 | D26: 0.07 | I26: Supplier I | K26: [days] | L26: 15 | M26: 75000
A27: Retailer 2 | B27: [days] | C27: 45 | D27: 0.05 | I27: Supplier II | K27: [days] | L27: 30 | M27: 0
A28: Retailer 3 | B28: [days] | C28: 60 | D28: 0.08 | I28: Supplier III | K28: [days] | L28: 30 | M28: 0
I29: Supplier IV | K29: [days] | L29: 30 | M29: 100000
A30: Product Target Inventory (% of next month's unit sales) and List Prices | C30: % | D30: List Price ($/kg) | I30: Supplier V | K30: [days] | L30: 15 | M30: 75000
A31: Product A | B31: [%] | C31: 0.25 | D31: 2.29
A32: Product B | B32: [%] | C32: 0.1 | D32: 3.15
A33: Product C | B33: [%] | C33: 0.3 | D33: 3.65 | I33: Days per Month | K33: [days] | L33: 30
A35: 3. Other Assumptions
A37: Product Ingredients
C38: Ingredients (per 1 kg of Product) | L38: Other Direct Costs
A39: Product | C39: Flour | D39: Sugar | E39: Butter | F39: Milk | G39: Eggs | H39: Chocolate | I39: Raisins | J39: Bananas | L39: (as % of Ingredient Cost)
A40: Product A | B40: [kg] | C40: 0.3 | D40: 0.25 | E40: 0.15 | F40: 0.15 | G40: 0.15 | H40: 0.1 | I40: 0 | J40: 0 | L40: 0.5
A41: Product B | B41: [kg] | C41: 0.321 | D41: 0.24 | E41: 0.155 | F41: 0.161 | G41: 0.138 | H41: 0 | I41: 0.1 | J41: 0 | L41: 0.6
A42: Product C | B42: [kg] | C42: 0.306 | D42: 0.233 | E42: 0.149 | F42: 0.137 | G42: 0.155 | H42: 0.05 | I42: 0 | J42: 0.2 | L42: 0.75
A45: Supplier Prices | C45: Flour | D45: Sugar | E45: Butter | F45: Milk | G45: Eggs | H45: Chocolate | I45: Raisins | J45: Bananas
A46: Supplier I | B46: [$/kg] | C46: 0.2781 | D46: 0.2077 | E46: 2.01 | F46: 0.67 | G46: 1.675 | H46: 1.608 | I46: 2.345 | J46: 1.005
A47: Supplier II | B47: [$/kg] | C47: 0.2725 | D47: 0.1932 | E47: 1.9497 | F47: 0.7236 | G47: 1.6248 | H47: 1.4633 | I47: 2.2512 | J47: 1.0251
A48: Supplier III | B48: [$/kg] | C48: 0.2531 | D48: 0.2015 | E48: 1.9698 | F48: 0.6231 | G48: 1.742 | H48: 1.5115 | I48: 2.4154 | J48: 0.9749
A49: Supplier IV | B49: [$/kg] | C49: 0.2864 | D49: 0.2181 | E49: 2.0502 | F49: 0.6968 | G49: 1.7923 | H49: 1.5758 | I49: 2.1809 | J49: 0.9749
A50: Supplier V | B50: [$/kg] | C50: 0.2586 | D50: 0.2015 | E50: 1.8693 | F50: 0.7169 | G50: 1.7085 | H50: 1.6562 | I50: 2.2981 | J50: 0.9548
A53: Supporting assumptions
A55: Company name | B55: [name] | C55: Sweet Dreams Co.
A56: CFM Topic | B56: [name] | C56: Working Capital
A57: Model periods | B57: [months] | C57: 12
A59: Max deferred days | B59: [days] | C59: 120
A61: Retailer Deferred Payment Days and Price Discounts
C62: Days
A63: Retailer 1 | B63: [days] | C63: =C26 -> 90 | D63: =C63 / days_per_month -> 3
A64: Retailer 2 | B64: [days] | C64: =C27 -> 45 | D64: =C64 / days_per_month -> 1.5
A65: Retailer 3 | B65: [days] | C65: =C28 -> 60 | D65: =C65 / days_per_month -> 2
A67: Days Segmented by Month
C68: {=_xlfn.SEQUENCE( 1, periods, 1, 1 )} -> 1 | D68: 2 | E68: 3 | F68: 4 | G68: 5 | H68: 6 | I68: 7 | J68: 8 | K68: 9 | L68: 10 | M68: 11 | N68: 12
A69: Retailer 1 | B69: [days] | C69: =IF( C$68 <= QUOTIENT( $C26, days_per_month ), days_per_month, IF( AND( C$68 = QUOTIENT( $C26, days_per_month ) + 1, MOD( $C26, days_per_month ) > 0), MOD( $C26, days_per_month ), 0 ) ) -> 30 | D69: =IF( D$68 <= QUOTIENT( $C26, days_per_month ), days_per_month, IF( AND( D$68 = QUOTIENT( $C26, days_per_month ) + 1, MOD( $C26, days_per_month ) > 0), MOD( $C26, days_per_month ), 0 ) ) -> 30 | E69: =IF( E$68 <= QUOTIENT( $C26, days_per_month ), days_per_month, IF( AND( E$68 = QUOTIENT( $C26, days_per_month ) + 1, MOD( $C26, days_per_month ) > 0), MOD( $C26, days_per_month ), 0 ) ) -> 30 | F69: =IF( F$68 <= QUOTIENT( $C26, days_per_month ), days_per_month, IF( AND( F$68 = QUOTIENT( $C26, days_per_month ) + 1, MOD( $C26, days_per_month ) > 0), MOD( $C26, days_per_month ), 0 ) ) -> 0 | G69: =IF( G$68 <= QUOTIENT( $C26, days_per_month ), days_per_month, IF( AND( G$68 = QUOTIENT( $C26, days_per_month ) + 1, MOD( $C26, days_per_month ) > 0), MOD( $C26, days_per_month ), 0 ) ) -> 0 | H69: =IF( H$68 <= QUOTIENT( $C26, days_per_month ), days_per_month, IF( AND( H$68 = QUOTIENT( $C26, days_per_month ) + 1, MOD( $C26, days_per_month ) > 0), MOD( $C26, days_per_month ), 0 ) ) -> 0 | I69: =IF( I$68 <= QUOTIENT( $C26, days_per_month ), days_per_month, IF( AND( I$68 = QUOTIENT( $C26, days_per_month ) + 1, MOD( $C26, days_per_month ) > 0), MOD( $C26, days_per_month ), 0 ) ) -> 0 | J69: =IF( J$68 <= QUOTIENT( $C26, days_per_month ), days_per_month, IF( AND( J$68 = QUOTIENT( $C26, days_per_month ) + 1, MOD( $C26, days_per_month ) > 0), MOD( $C26, days_per_month ), 0 ) ) -> 0 | ... N69: =IF( N$68 <= QUOTIENT( $C26, days_per_month ), days_per_month, IF( AND( N$68 = QUOTIENT( $C26, days_per_month ) + 1, MOD( $C26, days_per_month ) > 0), MOD( $C26, days_per_month ), 0 ) ) -> 0
A70: Retailer 2 | B70: [days] | C70: =IF( C$68 <= QUOTIENT( $C27, days_per_month ), days_per_month, IF( AND( C$68 = QUOTIENT( $C27, days_per_month ) + 1, MOD( $C27, days_per_month ) > 0), MOD( $C27, days_per_month ), 0 ) ) -> 30 | D70: =IF( D$68 <= QUOTIENT( $C27, days_per_month ), days_per_month, IF( AND( D$68 = QUOTIENT( $C27, days_per_month ) + 1, MOD( $C27, days_per_month ) > 0), MOD( $C27, days_per_month ), 0 ) ) -> 15 | E70: =IF( E$68 <= QUOTIENT( $C27, days_per_month ), days_per_month, IF( AND( E$68 = QUOTIENT( $C27, days_per_month ) + 1, MOD( $C27, days_per_month ) > 0), MOD( $C27, days_per_month ), 0 ) ) -> 0 | F70: =IF( F$68 <= QUOTIENT( $C27, days_per_month ), days_per_month, IF( AND( F$68 = QUOTIENT( $C27, days_per_month ) + 1, MOD( $C27, days_per_month ) > 0), MOD( $C27, days_per_month ), 0 ) ) -> 0 | G70: =IF( G$68 <= QUOTIENT( $C27, days_per_month ), days_per_month, IF( AND( G$68 = QUOTIENT( $C27, days_per_month ) + 1, MOD( $C27, days_per_month ) > 0), MOD( $C27, days_per_month ), 0 ) ) -> 0 | H70: =IF( H$68 <= QUOTIENT( $C27, days_per_month ), days_per_month, IF( AND( H$68 = QUOTIENT( $C27, days_per_month ) + 1, MOD( $C27, days_per_month ) > 0), MOD( $C27, days_per_month ), 0 ) ) -> 0 | I70: =IF( I$68 <= QUOTIENT( $C27, days_per_month ), days_per_month, IF( AND( I$68 = QUOTIENT( $C27, days_per_month ) + 1, MOD( $C27, days_per_month ) > 0), MOD( $C27, days_per_month ), 0 ) ) -> 0 | J70: =IF( J$68 <= QUOTIENT( $C27, days_per_month ), days_per_month, IF( AND( J$68 = QUOTIENT( $C27, days_per_month ) + 1, MOD( $C27, days_per_month ) > 0), MOD( $C27, days_per_month ), 0 ) ) -> 0 | ... N70: =IF( N$68 <= QUOTIENT( $C27, days_per_month ), days_per_month, IF( AND( N$68 = QUOTIENT( $C27, days_per_month ) + 1, MOD( $C27, days_per_month ) > 0), MOD( $C27, days_per_month ), 0 ) ) -> 0
A71: Retailer 3 | B71: [days] | C71: =IF( C$68 <= QUOTIENT( $C28, days_per_month ), days_per_month, IF( AND( C$68 = QUOTIENT( $C28, days_per_month ) + 1, MOD( $C28, days_per_month ) > 0), MOD( $C28, days_per_month ), 0 ) ) -> 30 | D71: =IF( D$68 <= QUOTIENT( $C28, days_per_month ), days_per_month, IF( AND( D$68 = QUOTIENT( $C28, days_per_month ) + 1, MOD( $C28, days_per_month ) > 0), MOD( $C28, days_per_month ), 0 ) ) -> 30 | E71: =IF( E$68 <= QUOTIENT( $C28, days_per_month ), days_per_month, IF( AND( E$68 = QUOTIENT( $C28, days_per_month ) + 1, MOD( $C28, days_per_month ) > 0), MOD( $C28, days_per_month ), 0 ) ) -> 0 | F71: =IF( F$68 <= QUOTIENT( $C28, days_per_month ), days_per_month, IF( AND( F$68 = QUOTIENT( $C28, days_per_month ) + 1, MOD( $C28, days_per_month ) > 0), MOD( $C28, days_per_month ), 0 ) ) -> 0 | G71: =IF( G$68 <= QUOTIENT( $C28, days_per_month ), days_per_month, IF( AND( G$68 = QUOTIENT( $C28, days_per_month ) + 1, MOD( $C28, days_per_month ) > 0), MOD( $C28, days_per_month ), 0 ) ) -> 0 | H71: =IF( H$68 <= QUOTIENT( $C28, days_per_month ), days_per_month, IF( AND( H$68 = QUOTIENT( $C28, days_per_month ) + 1, MOD( $C28, days_per_month ) > 0), MOD( $C28, days_per_month ), 0 ) ) -> 0 | I71: =IF( I$68 <= QUOTIENT( $C28, days_per_month ), days_per_month, IF( AND( I$68 = QUOTIENT( $C28, days_per_month ) + 1, MOD( $C28, days_per_month ) > 0), MOD( $C28, days_per_month ), 0 ) ) -> 0 | J71: =IF( J$68 <= QUOTIENT( $C28, days_per_month ), days_per_month, IF( AND( J$68 = QUOTIENT( $C28, days_per_month ) + 1, MOD( $C28, days_per_month ) > 0), MOD( $C28, days_per_month ), 0 ) ) -> 0 | ... N71: =IF( N$68 <= QUOTIENT( $C28, days_per_month ), days_per_month, IF( AND( N$68 = QUOTIENT( $C28, days_per_month ) + 1, MOD( $C28, days_per_month ) > 0), MOD( $C28, days_per_month ), 0 ) ) -> 0
A73: 2021 Revenue
A74: (assumed to be exactly equal to January 2022 sales ) | C74: 1 | D74: 2 | E74: 3
C75: 44500 | D75: {=EOMONTH( $C$75, _xlfn.SEQUENCE( 1, periods - 10, 1, 1 ) )} -> 44530 | E75: 44561
A76: Retailer 1 | B76: [$] | C76: =C7 -> 210000 | D76: =$C76 -> 210000 | E76: =$C76 -> 210000
A77: Retailer 2 | B77: [$] | C77: =C12 -> 105000 | D77: =$C77 -> 105000 | E77: =$C77 -> 105000
A78: Retailer 3 | B78: [$] | C78: =C17 -> 195000 | D78: =$C78 -> 195000 | E78: =$C78 -> 195000
C80: 1 | D80: 2 | E80: 3
A81: 2021 Accounts receivable balance | C81: =C75 -> 44500 | D81: =D75 -> 44530 | E81: =E75 -> 44561
A82: Retailer 1 | B82: [$] | E82: {=_xlfn.XLOOKUP( $E$80, $C$74:$E$74, $C76:$E76, 0 ) * _xlfn.XLOOKUP( $E$80,_xlfn.ANCHORARRAY( $C$68), $C69:$N69, 1 ) / days_per_month + _xlfn.XLOOKUP( $D$80, $C$74:$E$74, $C76:$E76, 0 ) * _xlfn.XLOOKUP( $D$80,_xlfn.ANCHORARRAY( $C$68), $C69:$N69, 1 ) / days_per_month + _xlfn.XLOOKUP( $C$80, $C$74:$E$74, $C76:$E76, 0 ) * _xlfn.XLOOKUP( $C$80,_xlfn.ANCHORARRAY( $C$68), $C69:$N69, 1 ) / days_per_month} -> 630000
A83: Retailer 2 | B83: [$] | E83: {=_xlfn.XLOOKUP( $E$80, $C$74:$E$74, $C77:$E77, 0 ) * _xlfn.XLOOKUP( $E$80,_xlfn.ANCHORARRAY( $C$68), $C70:$N70, 1 ) / days_per_month + _xlfn.XLOOKUP( $D$80, $C$74:$E$74, $C77:$E77, 0 ) * _xlfn.XLOOKUP( $D$80,_xlfn.ANCHORARRAY( $C$68), $C70:$N70, 1 ) / days_per_month + _xlfn.XLOOKUP( $C$80, $C$74:$E$74, $C77:$E77, 0 ) * _xlfn.XLOOKUP( $C$80,_xlfn.ANCHORARRAY( $C$68), $C70:$N70, 1 ) / days_per_month} -> 157500
A84: Retailer 3 | B84: [$] | E84: {=_xlfn.XLOOKUP( $E$80, $C$74:$E$74, $C78:$E78, 0 ) * _xlfn.XLOOKUP( $E$80,_xlfn.ANCHORARRAY( $C$68), $C71:$N71, 1 ) / days_per_month + _xlfn.XLOOKUP( $D$80, $C$74:$E$74, $C78:$E78, 0 ) * _xlfn.XLOOKUP( $D$80,_xlfn.ANCHORARRAY( $C$68), $C71:$N71, 1 ) / days_per_month + _xlfn.XLOOKUP( $C$80, $C$74:$E$74, $C78:$E78, 0 ) * _xlfn.XLOOKUP( $C$80,_xlfn.ANCHORARRAY( $C$68), $C71:$N71, 1 ) / days_per_month} -> 390000

Sheet Tmp
F3: Constant | G3: Unit | H3: Total | J3: {=EOMONTH( start_date, _xlfn.SEQUENCE( 1, periods, 0, 1 ) )} -> 44592 | K3: 44620 | L3: 44651 | M3: 44681 | N3: 44712 | O3: 44742 | P3: 44773 | Q3: 44804 | R3: 44834 | S3: 44865 | T3: 44895 | U3: 44926
A45: End of schedule
