Workbook
Name company: CaseData!$E$55
Name quarters: CaseData!$E$58
Name start_date: CaseData!$E$6
Name topic: "CFM Topic: " & CaseData!$E$56
Name years: CaseData!$E$57

Sheet Calculations
A1: =company -> Waterworks Corp
A2: {=topic} -> CFM Topic: Working capital | J2: {=_xlfn.ANCHORARRAY(J7)} -> 44927 | K2: 45017 | L2: 45108 | M2: 45200 | N2: 45292 | O2: 45383 | P2: 45474 | Q2: 45566 | R2: 45658 | S2: 45748 | T2: 45839 | U2: 45931 | V2: 46023 | W2: 46113 | X2: 46204 | Y2: 46296 | Z2: 46388 | AA2: 46478 | AB2: 46569 | AC2: 46661 | AD2: 46753 | AE2: 46844 | AF2: 46935 | AG2: 47027 | AH2: 47119 | AI2: 47209 | AJ2: 47300 | AK2: 47392
A3: CALCULATIONS SCHEDULE | F3: Constant | G3: Unit | H3: Total | J3: {=_xlfn.ANCHORARRAY(J8)} -> 45016 | K3: 45107 | L3: 45199 | M3: 45291 | N3: 45382 | O3: 45473 | P3: 45565 | Q3: 45657 | R3: 45747 | S3: 45838 | T3: 45930 | U3: 46022 | V3: 46112 | W3: 46203 | X3: 46295 | Y3: 46387 | Z3: 46477 | AA3: 46568 | AB3: 46660 | AC3: 46752 | AD3: 46843 | AE3: 46934 | AF3: 47026 | AG3: 47118 | AH3: 47208 | AI3: 47299 | AJ3: 47391 | AK3: 47483
A5: Model timeline
E7: Model period beginning | G7: date | J7: {=EDATE( start_date, _xlfn.SEQUENCE( 1, years * quarters, 0, 3 ) )} -> 44927 | K7: 45017 | L7: 45108 | M7: 45200 | N7: 45292 | O7: 45383 | P7: 45474 | Q7: 45566 | R7: 45658 | S7: 45748 | T7: 45839 | U7: 45931 | V7: 46023 | W7: 46113 | X7: 46204 | Y7: 46296 | Z7: 46388 | AA7: 46478 | AB7: 46569 | AC7: 46661 | AD7: 46753 | AE7: 46844 | AF7: 46935 | AG7: 47027 | AH7: 47119 | AI7: 47209 | AJ7: 47300 | AK7: 47392
E8: Model period ending | G8: date | J8: {=EOMONTH( start_date, _xlfn.SEQUENCE( 1, years * quarters, 2, 3 ) )} -> 45016 | K8: 45107 | L8: 45199 | M8: 45291 | N8: 45382 | O8: 45473 | P8: 45565 | Q8: 45657 | R8: 45747 | S8: 45838 | T8: 45930 | U8: 46022 | V8: 46112 | W8: 46203 | X8: 46295 | Y8: 46387 | Z8: 46477 | AA8: 46568 | AB8: 46660 | AC8: 46752 | AD8: 46843 | AE8: 46934 | AF8: 47026 | AG8: 47118 | AH8: 47208 | AI8: 47299 | AJ8: 47391 | AK8: 47483
E10: Quarter | G10: label | J10: {=MONTH(_xlfn.ANCHORARRAY( J8) ) / 3} -> 1 | K10: 2 | L10: 3 | M10: 4 | N10: 1 | O10: 2 | P10: 3 | Q10: 4 | R10: 1 | S10: 2 | T10: 3 | U10: 4 | V10: 1 | W10: 2 | X10: 3 | Y10: 4 | Z10: 1 | AA10: 2 | AB10: 3 | AC10: 4 | AD10: 1 | AE10: 2 | AF10: 3 | AG10: 4 | AH10: 1 | AI10: 2 | AJ10: 3 | AK10: 4
E11: Year | G11: label | J11: {=YEAR(_xlfn.ANCHORARRAY( J8) )} -> 2023 | K11: 2023 | L11: 2023 | M11: 2023 | N11: 2024 | O11: 2024 | P11: 2024 | Q11: 2024 | R11: 2025 | S11: 2025 | T11: 2025 | U11: 2025 | V11: 2026 | W11: 2026 | X11: 2026 | Y11: 2026 | Z11: 2027 | AA11: 2027 | AB11: 2027 | AC11: 2027 | AD11: 2028 | AE11: 2028 | AF11: 2028 | AG11: 2028 | AH11: 2029 | AI11: 2029 | AJ11: 2029 | AK11: 2029
A13: Revenue
B15: Volume
E17: Demand | G17: units | J17: {=_xlfn.LET( _xlpm.first_year_demand, CaseData!$E$11:$H$11, _xlpm.first_year_quarters, CaseData!$E$10:$H$10, _xlpm.current_quarter, "Q" &_xlfn.ANCHORARRAY( J$10), _xlpm.demand, INDEX( _xlpm.first_year_demand, MATCH( _xlpm.current_quarter, _xlpm.first_year_quarters, 0 ) ), _xlpm.growth_rate, CaseData!$E$13, _xlpm.current_year,_xlfn.ANCHORARRAY( $J$11), _xlpm.period, _xlpm.current_year - YEAR( start_date ), _xlpm.growth_factor, IF( _xlpm.period = 0, 1, ( 1 + _xlpm.growth_rate ) ^ _xlpm.period ), _xlpm.demand * _xlpm.growth_factor )} -> 225000 | K17: 375000 | L17: 300000 | M17: 600000 | N17: 236250 | O17: 393750 | P17: 315000 | Q17: 630000 | R17: 248062.5 | S17: 413437.5 | T17: 330750 | U17: 661500 | V17: 260465.63 | W17: 434109.38 | X17: 347287.5 | Y17: 694575 | Z17: 273488.91 | AA17: 455814.84 | AB17: 364651.88 | AC17: 729303.75 | AD17: 287163.35 | AE17: 478605.59 | AF17: 382884.47 | AG17: 765768.94 | AH17: 301521.52 | AI17: 502535.87 | AJ17: 402028.69 | AK17: 804057.38
E18: Rollover-in demand | G18: units | J18: =CaseData!$E$15*I27 -> 0 | K18: =CaseData!$E$15*J27 -> 0 | L18: =CaseData!$E$15*K27 -> 0 | M18: =CaseData!$E$15*L27 -> 0 | N18: =CaseData!$E$15*M27 -> 0 | O18: =CaseData!$E$15*N27 -> 0 | P18: =CaseData!$E$15*O27 -> 0 | Q18: =CaseData!$E$15*P27 -> 0 | ... AK18: =CaseData!$E$15*AJ27 -> 338955.3
E19: Total demand | G19: units | J19: =J17+J18 -> 225000 | K19: =K17+K18 -> 375000 | L19: =L17+L18 -> 300000 | M19: =M17+M18 -> 600000 | N19: =N17+N18 -> 236250 | O19: =O17+O18 -> 393750 | P19: =P17+P18 -> 315000 | Q19: =Q17+Q18 -> 630000 | ... AK19: =AK17+AK18 -> 1143012.7
E21: Inventory opening balance | G21: units | J21: =I25 -> 0 | K21: =J25 -> 185000 | L21: =K25 -> 220000 | M21: =L25 -> 330000 | N21: =M25 -> 140000 | O21: =N25 -> 313750 | P21: =O25 -> 330000 | Q21: =P25 -> 425000 | ... AK21: =AJ25 -> 0
E22: Production | G22: units | J22: {=_xlfn.SEQUENCE(1, years*quarters, CaseData!$E$8, 0)} -> 410000 | K22: 410000 | L22: 410000 | M22: 410000 | N22: 410000 | O22: 410000 | P22: 410000 | Q22: 410000 | R22: 410000 | S22: 410000 | T22: 410000 | U22: 410000 | V22: 410000 | W22: 410000 | X22: 410000 | Y22: 410000 | Z22: 410000 | AA22: 410000 | AB22: 410000 | AC22: 410000 | AD22: 410000 | AE22: 410000 | AF22: 410000 | AG22: 410000 | AH22: 410000 | AI22: 410000 | AJ22: 410000 | AK22: 410000
E23: Inventory available for sale | G23: units | J23: =J21+J22 -> 410000 | K23: =K21+K22 -> 595000 | L23: =L21+L22 -> 630000 | M23: =M21+M22 -> 740000 | N23: =N21+N22 -> 550000 | O23: =O21+O22 -> 723750 | P23: =P21+P22 -> 740000 | Q23: =Q21+Q22 -> 835000 | ... AK23: =AK21+AK22 -> 410000
E24: Units sold | G24: units | J24: =MIN(J23,J19) -> 225000 | K24: =MIN(K23,K19) -> 375000 | L24: =MIN(L23,L19) -> 300000 | M24: =MIN(M23,M19) -> 600000 | N24: =MIN(N23,N19) -> 236250 | O24: =MIN(O23,O19) -> 393750 | P24: =MIN(P23,P19) -> 315000 | Q24: =MIN(Q23,Q19) -> 630000 | ... AK24: =MIN(AK23,AK19) -> 410000
E25: Inventory closing balance | G25: units | J25: =J23-J24 -> 185000 | K25: =K23-K24 -> 220000 | L25: =L23-L24 -> 330000 | M25: =M23-M24 -> 140000 | N25: =N23-N24 -> 313750 | O25: =O23-O24 -> 330000 | P25: =P23-P24 -> 425000 | Q25: =Q23-Q24 -> 205000 | ... AK25: =AK23-AK24 -> 0
E27: Demand not met in the current quarter | G27: units | J27: =J19-J24 -> 0 | K27: =K19-K24 -> 0 | L27: =L19-L24 -> 0 | M27: =M19-M24 -> 0 | N27: =N19-N24 -> 0 | O27: =O19-O24 -> 0 | P27: =P19-P24 -> 0 | Q27: =Q19-Q24 -> 0 | ... AK27: =AK19-AK24 -> 733012.68
E28: Sale of units permanently lost to other suppliers | G28: units | J28: 0 | K28: =(1-CaseData!$E$15)*J27 -> 0 | L28: =(1-CaseData!$E$15)*K27 -> 0 | M28: =(1-CaseData!$E$15)*L27 -> 0 | N28: =(1-CaseData!$E$15)*M27 -> 0 | O28: =(1-CaseData!$E$15)*N27 -> 0 | P28: =(1-CaseData!$E$15)*O27 -> 0 | Q28: =(1-CaseData!$E$15)*P27 -> 0 | R28: =(1-CaseData!$E$15)*Q27 -> 0 | ... AK28: =(1-CaseData!$E$15)*AJ27 -> 0
E30: =E$24 -> Units sold | G30: units | J30: =J$24 -> 225000 | K30: =K$24 -> 375000 | L30: =L$24 -> 300000 | M30: =M$24 -> 600000 | N30: =N$24 -> 236250 | O30: =O$24 -> 393750 | P30: =P$24 -> 315000 | Q30: =Q$24 -> 630000 | ... AK30: =AK$24 -> 410000
B32: Production cost
E34: Hourly salary rate | G34: USD / hr | J34: {=_xlfn.LET( _xlpm.hourly_salary_rate, CaseData!$E$18, _xlpm.year_on_year_pct, CaseData!$F$18, _xlpm.period,_xlfn.ANCHORARRAY( J11) - YEAR( start_date ), ROUND( IF( _xlpm.period = 0, _xlpm.hourly_salary_rate, _xlpm.hourly_salary_rate * ( 1 + _xlpm.year_on_year_pct ) ^ _xlpm.period ), 2 ) )} -> 27.75 | K34: 27.75 | L34: 27.75 | M34: 27.75 | N34: 29.69 | O34: 29.69 | P34: 29.69 | Q34: 29.69 | R34: 31.77 | S34: 31.77 | T34: 31.77 | U34: 31.77 | V34: 33.99 | W34: 33.99 | X34: 33.99 | Y34: 33.99 | Z34: 36.37 | AA34: 36.37 | AB34: 36.37 | AC34: 36.37 | AD34: 38.92 | AE34: 38.92 | AF34: 38.92 | AG34: 38.92 | AH34: 41.65 | AI34: 41.65 | AJ34: 41.65 | AK34: 41.65
E35: Production time | G35: hr / unit | J35: {=_xlfn.LET( _xlpm.production_time, CaseData!$E$19, _xlpm.year_on_year_pct, CaseData!$F$19, _xlpm.period,_xlfn.ANCHORARRAY( J11) - YEAR( start_date ), IF( _xlpm.period = 0, _xlpm.production_time, _xlpm.production_time * ( 1 + _xlpm.year_on_year_pct ) ^ _xlpm.period ) )} -> 21.9 | K35: 21.9 | L35: 21.9 | M35: 21.9 | N35: 21.462 | O35: 21.462 | P35: 21.462 | Q35: 21.462 | R35: 21.03276 | S35: 21.03276 | T35: 21.03276 | U35: 21.03276 | V35: 20.612105 | W35: 20.612105 | X35: 20.612105 | Y35: 20.612105 | Z35: 20.199863 | AA35: 20.199863 | AB35: 20.199863 | AC35: 20.199863 | AD35: 19.795865 | AE35: 19.795865 | AF35: 19.795865 | AG35: 19.795865 | AH35: 19.399948 | AI35: 19.399948 | AJ35: 19.399948 | AK35: 19.399948
E36: Materials | G36: USD / unit | J36: {=_xlfn.LET( _xlpm.material_cost, CaseData!$E$20, _xlpm.year_on_year_pct, CaseData!$F$20, _xlpm.period,_xlfn.ANCHORARRAY( J11) - YEAR( start_date ), IF( _xlpm.period = 0, _xlpm.material_cost, _xlpm.material_cost * ( 1 + _xlpm.year_on_year_pct ) ^ _xlpm.period ) )} -> 480 | K36: 480 | L36: 480 | M36: 480 | N36: 499.2 | O36: 499.2 | P36: 499.2 | Q36: 499.2 | R36: 519.168 | S36: 519.168 | T36: 519.168 | U36: 519.168 | V36: 539.93472 | W36: 539.93472 | X36: 539.93472 | Y36: 539.93472 | Z36: 561.53211 | AA36: 561.53211 | AB36: 561.53211 | AC36: 561.53211 | AD36: 583.99339 | AE36: 583.99339 | AF36: 583.99339 | AG36: 583.99339 | AH36: 607.35313 | AI36: 607.35313 | AJ36: 607.35313 | AK36: 607.35313
E38: Salaries | G38: USD m | J38: {=_xlfn.LET( _xlpm.hourly_salary_rate,_xlfn.ANCHORARRAY( J34), _xlpm.unit_production_time,_xlfn.ANCHORARRAY( J35), _xlpm.production,_xlfn.ANCHORARRAY( J22), _xlpm.hourly_salary_rate * _xlpm.unit_production_time * _xlpm.production / 1000 )} -> 249167.25 | K38: 249167.25 | L38: 249167.25 | M38: 249167.25 | N38: 261254.78 | O38: 261254.78 | P38: 261254.78 | Q38: 261254.78 | R38: 273966.42 | S38: 273966.42 | T38: 273966.42 | U38: 273966.42 | V38: 287248.23 | W38: 287248.23 | X38: 287248.23 | Y38: 287248.23 | Z38: 301214.29 | AA38: 301214.29 | AB38: 301214.29 | AC38: 301214.29 | AD38: 315886.58 | AE38: 315886.58 | AF38: 315886.58 | AG38: 315886.58 | AH38: 331283.21 | AI38: 331283.21 | AJ38: 331283.21 | AK38: 331283.21
E39: Materials | G39: USD m | J39: {=_xlfn.LET( _xlpm.production,_xlfn.ANCHORARRAY( J22), _xlpm.material_costs,_xlfn.ANCHORARRAY( J36), _xlpm.production * _xlpm.material_costs / 1000 )} -> 196800 | K39: 196800 | L39: 196800 | M39: 196800 | N39: 204672 | O39: 204672 | P39: 204672 | Q39: 204672 | R39: 212858.88 | S39: 212858.88 | T39: 212858.88 | U39: 212858.88 | V39: 221373.24 | W39: 221373.24 | X39: 221373.24 | Y39: 221373.24 | Z39: 230228.16 | AA39: 230228.16 | AB39: 230228.16 | AC39: 230228.16 | AD39: 239437.29 | AE39: 239437.29 | AF39: 239437.29 | AG39: 239437.29 | AH39: 249014.78 | AI39: 249014.78 | AJ39: 249014.78 | AK39: 249014.78
E40: Production costs | G40: USD m | J40: {=_xlfn.BYCOL(_xlfn.ANCHORARRAY( J38):_xlfn.ANCHORARRAY(J39), _xleta.SUM )} -> 445967.25 | K40: 445967.25 | L40: 445967.25 | M40: 445967.25 | N40: 465926.78 | O40: 465926.78 | P40: 465926.78 | Q40: 465926.78 | R40: 486825.3 | S40: 486825.3 | T40: 486825.3 | U40: 486825.3 | V40: 508621.47 | W40: 508621.47 | X40: 508621.47 | Y40: 508621.47 | Z40: 531442.46 | AA40: 531442.46 | AB40: 531442.46 | AC40: 531442.46 | AD40: 555323.88 | AE40: 555323.88 | AF40: 555323.88 | AG40: 555323.88 | AH40: 580298 | AI40: 580298 | AJ40: 580298 | AK40: 580298
E42: Average cost per unit | G42: USD | J42: {=_xlfn.LET( _xlpm.production,_xlfn.ANCHORARRAY( J22), _xlpm.costs,_xlfn.ANCHORARRAY( J40), _xlpm.costs / _xlpm.production * 1000 )} -> 1087.725 | K42: 1087.725 | L42: 1087.725 | M42: 1087.725 | N42: 1136.4068 | O42: 1136.4068 | P42: 1136.4068 | Q42: 1136.4068 | R42: 1187.3788 | S42: 1187.3788 | T42: 1187.3788 | U42: 1187.3788 | V42: 1240.5402 | W42: 1240.5402 | X42: 1240.5402 | Y42: 1240.5402 | Z42: 1296.2011 | AA42: 1296.2011 | AB42: 1296.2011 | AC42: 1296.2011 | AD42: 1354.4485 | AE42: 1354.4485 | AF42: 1354.4485 | AG42: 1354.4485 | AH42: 1415.361 | AI42: 1415.361 | AJ42: 1415.361 | AK42: 1415.361
E43: Check | G43: USD | J43: {=_xlfn.LET( _xlpm.hourly_salary_rate,_xlfn.ANCHORARRAY( J34), _xlpm.production_time,_xlfn.ANCHORARRAY( J35), _xlpm.material_cost,_xlfn.ANCHORARRAY( J36), _xlpm.cost_per_unit,_xlfn.ANCHORARRAY( J42), ROUNDDOWN( _xlpm.cost_per_unit - ( (_xlpm.hourly_salary_rate * _xlpm.production_time ) + _xlpm.material_cost ), 2 ) )} -> 0 | K43: 0 | L43: 0 | M43: 0 | N43: 0 | O43: 0 | P43: 0 | Q43: 0 | R43: 0 | S43: 0 | T43: 0 | U43: 0 | V43: 0 | W43: 0 | X43: 0 | Y43: 0 | Z43: 0 | AA43: 0 | AB43: 0 | AC43: 0 | AD43: 0 | AE43: 0 | AF43: 0 | AG43: 0 | AH43: 0 | AI43: 0 | AJ43: 0 | AK43: 0
B45: Revenue
E47: Sell price | G47: USD | J47: {=_xlfn.LET( _xlpm.cost_per_unit,_xlfn.ANCHORARRAY( J42), _xlpm.mark_up, CaseData!$E$23, _xlpm.year_on_year_pct, CaseData!$E$24, _xlpm.period,_xlfn.ANCHORARRAY( $J$11) - YEAR( start_date ), _xlpm.growth_rate, 1 + ( _xlpm.mark_up + ( _xlpm.year_on_year_pct * _xlpm.period ) ), ROUND( _xlpm.cost_per_unit * _xlpm.growth_rate, 2 ) )} -> 1414.04 | K47: 1414.04 | L47: 1414.04 | M47: 1414.04 | N47: 1471.65 | O47: 1471.65 | P47: 1471.65 | Q47: 1471.65 | R47: 1531.72 | S47: 1531.72 | T47: 1531.72 | U47: 1531.72 | V47: 1594.09 | W47: 1594.09 | X47: 1594.09 | Y47: 1594.09 | Z47: 1659.14 | AA47: 1659.14 | AB47: 1659.14 | AC47: 1659.14 | AD47: 1726.92 | AE47: 1726.92 | AF47: 1726.92 | AG47: 1726.92 | AH47: 1797.51 | AI47: 1797.51 | AJ47: 1797.51 | AK47: 1797.51
E48: =E$24 -> Units sold | G48: units | J48: =J$24 -> 225000 | K48: =K$24 -> 375000 | L48: =L$24 -> 300000 | M48: =M$24 -> 600000 | N48: =N$24 -> 236250 | O48: =O$24 -> 393750 | P48: =P$24 -> 315000 | Q48: =Q$24 -> 630000 | ... AK48: =AK$24 -> 410000
E49: Revenue | G49: USD m | J49: {=_xlfn.ANCHORARRAY( J47) * $J$48:$AK$48 / 1000} -> 318159 | K49: 530265 | L49: 424212 | M49: 848424 | N49: 347677.31 | O49: 579462.19 | P49: 463569.75 | Q49: 927139.5 | R49: 379962.29 | S49: 633270.49 | T49: 506616.39 | U49: 1013232.8 | V49: 415205.65 | W49: 692009.41 | X49: 553607.53 | Y49: 1107215.1 | Z49: 453756.38 | AA49: 756260.64 | AB49: 605008.51 | AC49: 1063271.3 | AD49: 648648.81 | AE49: 767425.59 | AF49: 708037.2 | AG49: 708037.2 | AH49: 736979.1 | AI49: 736979.1 | AJ49: 736979.1 | AK49: 736979.1
B52: FIFO Cost of Goods Sold and Inventory
B54: FIFO units sold
E56: Production | G56: units | J56: {=_xlfn.ANCHORARRAY( J22)} -> 410000 | K56: 410000 | L56: 410000 | M56: 410000 | N56: 410000 | O56: 410000 | P56: 410000 | Q56: 410000 | R56: 410000 | S56: 410000 | T56: 410000 | U56: 410000 | V56: 410000 | W56: 410000 | X56: 410000 | Y56: 410000 | Z56: 410000 | AA56: 410000 | AB56: 410000 | AC56: 410000 | AD56: 410000 | AE56: 410000 | AF56: 410000 | AG56: 410000 | AH56: 410000 | AI56: 410000 | AJ56: 410000 | AK56: 410000
E57: Units sold | G57: units | J57: =J$30 -> 225000 | K57: =K$30 -> 375000 | L57: =L$30 -> 300000 | M57: =M$30 -> 600000 | N57: =N$30 -> 236250 | O57: =O$30 -> 393750 | P57: =P$30 -> 315000 | Q57: =Q$30 -> 630000 | ... AK57: =AK$30 -> 410000
E58: Inventory beginning balance | G58: units | J58: =J$21 -> 0 | K58: =K$21 -> 185000 | L58: =L$21 -> 220000 | M58: =M$21 -> 330000 | N58: =N$21 -> 140000 | O58: =O$21 -> 313750 | P58: =P$21 -> 330000 | Q58: =Q$21 -> 425000 | ... AK58: =AK$21 -> 0
E60: Units sold from inventory | G60: units | J60: {=_xlfn.LET( _xlpm.units_sold, $J$57:$AK$57, _xlpm.inventory_beginning_balance, $J$58:$AK$58, _xlpm.period,_xlfn.ANCHORARRAY( J11) - YEAR( start_date ), IF( _xlpm.inventory_beginning_balance < _xlpm.units_sold, _xlpm.inventory_beginning_balance, _xlpm.units_sold ) )} -> 0 | K60: 185000 | L60: 220000 | M60: 330000 | N60: 140000 | O60: 313750 | P60: 315000 | Q60: 425000 | R60: 205000 | S60: 366937.5 | T60: 330750 | U60: 442750 | V60: 191250 | W60: 340784.38 | X60: 316675 | Y60: 379387.5 | Z60: 94812.5 | AA60: 231323.59 | AB60: 185508.75 | AC60: 230856.87 | AD60: 0 | AE60: 34389.773 | AF60: 0 | AG60: 0 | AH60: 0 | AI60: 0 | AJ60: 0 | AK60: 0
E61: Units sold from current production | G61: units | J61: {=_xlfn.LET( _xlpm.units_sold, $J$57:$AK$57, _xlpm.units_sold_from_inventory,_xlfn.ANCHORARRAY( J60), _xlpm.units_sold - _xlpm.units_sold_from_inventory )} -> 225000 | K61: 190000 | L61: 80000 | M61: 270000 | N61: 96250 | O61: 80000 | P61: 0 | Q61: 205000 | R61: 43062.5 | S61: 46500 | T61: 0 | U61: 218750 | V61: 69215.625 | W61: 93325 | X61: 30612.5 | Y61: 315187.5 | Z61: 178676.41 | AA61: 224491.25 | AB61: 179143.13 | AC61: 410000 | AD61: 375610.23 | AE61: 410000 | AF61: 410000 | AG61: 410000 | AH61: 410000 | AI61: 410000 | AJ61: 410000 | AK61: 410000
E62: FIFO units sold | G62: units | J62: {=_xlfn.BYCOL( $J$60:$AK$61, _xleta.SUM )} -> 225000 | K62: 375000 | L62: 300000 | M62: 600000 | N62: 236250 | O62: 393750 | P62: 315000 | Q62: 630000 | R62: 248062.5 | S62: 413437.5 | T62: 330750 | U62: 661500 | V62: 260465.63 | W62: 434109.38 | X62: 347287.5 | Y62: 694575 | Z62: 273488.91 | AA62: 455814.84 | AB62: 364651.88 | AC62: 640856.87 | AD62: 375610.23 | AE62: 444389.77 | AF62: 410000 | AG62: 410000 | AH62: 410000 | AI62: 410000 | AJ62: 410000 | AK62: 410000
B65: FIFO COGS from current production
E67: Cost per unit | G67: USD | J67: {=_xlfn.ANCHORARRAY( J42)} -> 1087.725 | K67: 1087.725 | L67: 1087.725 | M67: 1087.725 | N67: 1136.4068 | O67: 1136.4068 | P67: 1136.4068 | Q67: 1136.4068 | R67: 1187.3788 | S67: 1187.3788 | T67: 1187.3788 | U67: 1187.3788 | V67: 1240.5402 | W67: 1240.5402 | X67: 1240.5402 | Y67: 1240.5402 | Z67: 1296.2011 | AA67: 1296.2011 | AB67: 1296.2011 | AC67: 1296.2011 | AD67: 1354.4485 | AE67: 1354.4485 | AF67: 1354.4485 | AG67: 1354.4485 | AH67: 1415.361 | AI67: 1415.361 | AJ67: 1415.361 | AK67: 1415.361
E68: Units sold from current production | G68: units | J68: {=_xlfn.ANCHORARRAY( J61)} -> 225000 | K68: 190000 | L68: 80000 | M68: 270000 | N68: 96250 | O68: 80000 | P68: 0 | Q68: 205000 | R68: 43062.5 | S68: 46500 | T68: 0 | U68: 218750 | V68: 69215.625 | W68: 93325 | X68: 30612.5 | Y68: 315187.5 | Z68: 178676.41 | AA68: 224491.25 | AB68: 179143.13 | AC68: 410000 | AD68: 375610.23 | AE68: 410000 | AF68: 410000 | AG68: 410000 | AH68: 410000 | AI68: 410000 | AJ68: 410000 | AK68: 410000
E69: FIFO COGS from current production | G69: USD m | J69: {=_xlfn.ANCHORARRAY( J67) *_xlfn.ANCHORARRAY( J68) / 1000} -> 244738.13 | K69: 206667.75 | L69: 87018 | M69: 293685.75 | N69: 109379.15 | O69: 90912.542 | P69: 0 | Q69: 232963.39 | R69: 51131.499 | S69: 55213.114 | T69: 0 | U69: 259739.11 | V69: 85864.763 | W69: 115773.41 | X69: 37976.036 | Y69: 391002.75 | Z69: 231600.56 | AA69: 290985.81 | AB69: 232205.52 | AC69: 531442.46 | AD69: 508744.7 | AE69: 555323.88 | AF69: 555323.88 | AG69: 555323.88 | AH69: 580298 | AI69: 580298 | AJ69: 580298 | AK69: 580298
B72: FIFO COGS from inventory
E74: Units added in the quarters
F75: {=TRANSPOSE(_xlfn.UNIQUE(_xlfn.ANCHORARRAY($J$11),TRUE))} -> 2023 | G75: units | J75: {=_xlfn.LET( _xlpm.production,_xlfn.ANCHORARRAY( J56), _xlpm.units_sold_from_production,_xlfn.ANCHORARRAY( J61), _xlpm.units_added_in_quarter, _xlpm.production - _xlpm.units_sold_from_production, _xlpm.periods,_xlfn.ANCHORARRAY( $J$11) -_xlfn.ANCHORARRAY( F75), IF( _xlpm.periods = 0, _xlpm.units_added_in_quarter, 0 ) )} -> 185000 | K75: 220000 | L75: 330000 | M75: 140000 | N75: 0 | O75: 0 | P75: 0 | Q75: 0 | R75: 0 | S75: 0 | T75: 0 | U75: 0 | V75: 0 | W75: 0 | X75: 0 | Y75: 0 | Z75: 0 | AA75: 0 | AB75: 0 | AC75: 0 | AD75: 0 | AE75: 0 | AF75: 0 | AG75: 0 | AH75: 0 | AI75: 0 | AJ75: 0 | AK75: 0
F76: 2024 | G76: units | J76: 0 | K76: 0 | L76: 0 | M76: 0 | N76: 313750 | O76: 330000 | P76: 410000 | Q76: 205000 | R76: 0 | S76: 0 | T76: 0 | U76: 0 | V76: 0 | W76: 0 | X76: 0 | Y76: 0 | Z76: 0 | AA76: 0 | AB76: 0 | AC76: 0 | AD76: 0 | AE76: 0 | AF76: 0 | AG76: 0 | AH76: 0 | AI76: 0 | AJ76: 0 | AK76: 0
F77: 2025 | G77: units | J77: 0 | K77: 0 | L77: 0 | M77: 0 | N77: 0 | O77: 0 | P77: 0 | Q77: 0 | R77: 366937.5 | S77: 363500 | T77: 410000 | U77: 191250 | V77: 0 | W77: 0 | X77: 0 | Y77: 0 | Z77: 0 | AA77: 0 | AB77: 0 | AC77: 0 | AD77: 0 | AE77: 0 | AF77: 0 | AG77: 0 | AH77: 0 | AI77: 0 | AJ77: 0 | AK77: 0
F78: 2026 | G78: units | J78: 0 | K78: 0 | L78: 0 | M78: 0 | N78: 0 | O78: 0 | P78: 0 | Q78: 0 | R78: 0 | S78: 0 | T78: 0 | U78: 0 | V78: 340784.38 | W78: 316675 | X78: 379387.5 | Y78: 94812.5 | Z78: 0 | AA78: 0 | AB78: 0 | AC78: 0 | AD78: 0 | AE78: 0 | AF78: 0 | AG78: 0 | AH78: 0 | AI78: 0 | AJ78: 0 | AK78: 0
F79: 2027 | G79: units | J79: 0 | K79: 0 | L79: 0 | M79: 0 | N79: 0 | O79: 0 | P79: 0 | Q79: 0 | R79: 0 | S79: 0 | T79: 0 | U79: 0 | V79: 0 | W79: 0 | X79: 0 | Y79: 0 | Z79: 231323.59 | AA79: 185508.75 | AB79: 230856.87 | AC79: 0 | AD79: 0 | AE79: 0 | AF79: 0 | AG79: 0 | AH79: 0 | AI79: 0 | AJ79: 0 | AK79: 0
F80: 2028 | G80: units | J80: 0 | K80: 0 | L80: 0 | M80: 0 | N80: 0 | O80: 0 | P80: 0 | Q80: 0 | R80: 0 | S80: 0 | T80: 0 | U80: 0 | V80: 0 | W80: 0 | X80: 0 | Y80: 0 | Z80: 0 | AA80: 0 | AB80: 0 | AC80: 0 | AD80: 34389.773 | AE80: 0 | AF80: 0 | AG80: 0 | AH80: 0 | AI80: 0 | AJ80: 0 | AK80: 0
F81: 2029 | G81: units | J81: 0 | K81: 0 | L81: 0 | M81: 0 | N81: 0 | O81: 0 | P81: 0 | Q81: 0 | R81: 0 | S81: 0 | T81: 0 | U81: 0 | V81: 0 | W81: 0 | X81: 0 | Y81: 0 | Z81: 0 | AA81: 0 | AB81: 0 | AC81: 0 | AD81: 0 | AE81: 0 | AF81: 0 | AG81: 0 | AH81: 0 | AI81: 0 | AJ81: 0 | AK81: 0
E83: Units sold in the quarter by vintage | G83: Cost per unit
F84: {=TRANSPOSE(_xlfn.UNIQUE(_xlfn.ANCHORARRAY($J$11),TRUE))} -> 2023 | G84: {=TRANSPOSE(_xlfn.UNIQUE(_xlfn.ANCHORARRAY( $J$42), TRUE))} -> 1087.725 | J84: =MIN( I96, J$60 - SUM( J$83:J83 ) ) -> 0 | K84: =MIN( J96, K$60 - SUM( K$83:K83 ) ) -> 185000 | L84: =MIN( K96, L$60 - SUM( L$83:L83 ) ) -> 220000 | M84: =MIN( L96, M$60 - SUM( M$83:M83 ) ) -> 330000 | N84: =MIN( M96, N$60 - SUM( N$83:N83 ) ) -> 140000 | O84: =MIN( N96, O$60 - SUM( O$83:O83 ) ) -> 0 | P84: =MIN( O96, P$60 - SUM( P$83:P83 ) ) -> 0 | Q84: =MIN( P96, Q$60 - SUM( Q$83:Q83 ) ) -> 0 | ... AK84: =MIN( AJ96, AK$60 - SUM( AK$83:AK83 ) ) -> 0
F85: 2024 | G85: 1136.4068 | J85: =MIN( I97, J$60 - SUM( J$83:J84 ) ) -> 0 | K85: =MIN( J97, K$60 - SUM( K$83:K84 ) ) -> 0 | L85: =MIN( K97, L$60 - SUM( L$83:L84 ) ) -> 0 | M85: =MIN( L97, M$60 - SUM( M$83:M84 ) ) -> 0 | N85: =MIN( M97, N$60 - SUM( N$83:N84 ) ) -> 0 | O85: =MIN( N97, O$60 - SUM( O$83:O84 ) ) -> 313750 | P85: =MIN( O97, P$60 - SUM( P$83:P84 ) ) -> 315000 | Q85: =MIN( P97, Q$60 - SUM( Q$83:Q84 ) ) -> 425000 | ... AK85: =MIN( AJ97, AK$60 - SUM( AK$83:AK84 ) ) -> 0
F86: 2025 | G86: 1187.3788 | J86: =MIN( I98, J$60 - SUM( J$83:J85 ) ) -> 0 | K86: =MIN( J98, K$60 - SUM( K$83:K85 ) ) -> 0 | L86: =MIN( K98, L$60 - SUM( L$83:L85 ) ) -> 0 | M86: =MIN( L98, M$60 - SUM( M$83:M85 ) ) -> 0 | N86: =MIN( M98, N$60 - SUM( N$83:N85 ) ) -> 0 | O86: =MIN( N98, O$60 - SUM( O$83:O85 ) ) -> 0 | P86: =MIN( O98, P$60 - SUM( P$83:P85 ) ) -> 0 | Q86: =MIN( P98, Q$60 - SUM( Q$83:Q85 ) ) -> 0 | ... AK86: =MIN( AJ98, AK$60 - SUM( AK$83:AK85 ) ) -> 0
F87: 2026 | G87: 1240.5402 | J87: =MIN( I99, J$60 - SUM( J$83:J86 ) ) -> 0 | K87: =MIN( J99, K$60 - SUM( K$83:K86 ) ) -> 0 | L87: =MIN( K99, L$60 - SUM( L$83:L86 ) ) -> 0 | M87: =MIN( L99, M$60 - SUM( M$83:M86 ) ) -> 0 | N87: =MIN( M99, N$60 - SUM( N$83:N86 ) ) -> 0 | O87: =MIN( N99, O$60 - SUM( O$83:O86 ) ) -> 0 | P87: =MIN( O99, P$60 - SUM( P$83:P86 ) ) -> 0 | Q87: =MIN( P99, Q$60 - SUM( Q$83:Q86 ) ) -> 0 | ... AK87: =MIN( AJ99, AK$60 - SUM( AK$83:AK86 ) ) -> 0
F88: 2027 | G88: 1296.2011 | J88: =MIN( I100, J$60 - SUM( J$83:J87 ) ) -> 0 | K88: =MIN( J100, K$60 - SUM( K$83:K87 ) ) -> 0 | L88: =MIN( K100, L$60 - SUM( L$83:L87 ) ) -> 0 | M88: =MIN( L100, M$60 - SUM( M$83:M87 ) ) -> 0 | N88: =MIN( M100, N$60 - SUM( N$83:N87 ) ) -> 0 | O88: =MIN( N100, O$60 - SUM( O$83:O87 ) ) -> 0 | P88: =MIN( O100, P$60 - SUM( P$83:P87 ) ) -> 0 | Q88: =MIN( P100, Q$60 - SUM( Q$83:Q87 ) ) -> 0 | ... AK88: =MIN( AJ100, AK$60 - SUM( AK$83:AK87 ) ) -> 0
F89: 2028 | G89: 1354.4485 | J89: =MIN( I101, J$60 - SUM( J$83:J88 ) ) -> 0 | K89: =MIN( J101, K$60 - SUM( K$83:K88 ) ) -> 0 | L89: =MIN( K101, L$60 - SUM( L$83:L88 ) ) -> 0 | M89: =MIN( L101, M$60 - SUM( M$83:M88 ) ) -> 0 | N89: =MIN( M101, N$60 - SUM( N$83:N88 ) ) -> 0 | O89: =MIN( N101, O$60 - SUM( O$83:O88 ) ) -> 0 | P89: =MIN( O101, P$60 - SUM( P$83:P88 ) ) -> 0 | Q89: =MIN( P101, Q$60 - SUM( Q$83:Q88 ) ) -> 0 | ... AK89: =MIN( AJ101, AK$60 - SUM( AK$83:AK88 ) ) -> 0
F90: 2029 | G90: 1415.361 | J90: =MIN( I102, J$60 - SUM( J$83:J89 ) ) -> 0 | K90: =MIN( J102, K$60 - SUM( K$83:K89 ) ) -> 0 | L90: =MIN( K102, L$60 - SUM( L$83:L89 ) ) -> 0 | M90: =MIN( L102, M$60 - SUM( M$83:M89 ) ) -> 0 | N90: =MIN( M102, N$60 - SUM( N$83:N89 ) ) -> 0 | O90: =MIN( N102, O$60 - SUM( O$83:O89 ) ) -> 0 | P90: =MIN( O102, P$60 - SUM( P$83:P89 ) ) -> 0 | Q90: =MIN( P102, Q$60 - SUM( Q$83:Q89 ) ) -> 0 | ... AK90: =MIN( AJ102, AK$60 - SUM( AK$83:AK89 ) ) -> 0
E91: FIFO COGS from inventory | G91: USD m | J91: =_xlfn.LET( _xlpm.volume, J84:J90, _xlpm.cost,_xlfn.ANCHORARRAY( $G$84), SUMPRODUCT( _xlpm.volume, _xlpm.cost ) / 1000 ) -> 0 | K91: =_xlfn.LET( _xlpm.volume, K84:K90, _xlpm.cost,_xlfn.ANCHORARRAY( $G$84), SUMPRODUCT( _xlpm.volume, _xlpm.cost ) / 1000 ) -> 201229.13 | L91: =_xlfn.LET( _xlpm.volume, L84:L90, _xlpm.cost,_xlfn.ANCHORARRAY( $G$84), SUMPRODUCT( _xlpm.volume, _xlpm.cost ) / 1000 ) -> 239299.5 | M91: =_xlfn.LET( _xlpm.volume, M84:M90, _xlpm.cost,_xlfn.ANCHORARRAY( $G$84), SUMPRODUCT( _xlpm.volume, _xlpm.cost ) / 1000 ) -> 358949.25 | N91: =_xlfn.LET( _xlpm.volume, N84:N90, _xlpm.cost,_xlfn.ANCHORARRAY( $G$84), SUMPRODUCT( _xlpm.volume, _xlpm.cost ) / 1000 ) -> 152281.5 | O91: =_xlfn.LET( _xlpm.volume, O84:O90, _xlpm.cost,_xlfn.ANCHORARRAY( $G$84), SUMPRODUCT( _xlpm.volume, _xlpm.cost ) / 1000 ) -> 356547.63 | P91: =_xlfn.LET( _xlpm.volume, P84:P90, _xlpm.cost,_xlfn.ANCHORARRAY( $G$84), SUMPRODUCT( _xlpm.volume, _xlpm.cost ) / 1000 ) -> 357968.14 | Q91: =_xlfn.LET( _xlpm.volume, Q84:Q90, _xlpm.cost,_xlfn.ANCHORARRAY( $G$84), SUMPRODUCT( _xlpm.volume, _xlpm.cost ) / 1000 ) -> 482972.88 | ... AK91: =_xlfn.LET( _xlpm.volume, AK84:AK90, _xlpm.cost,_xlfn.ANCHORARRAY( $G$84), SUMPRODUCT( _xlpm.volume, _xlpm.cost ) / 1000 ) -> 0
E92: Average FIFO cost per unit | G92: USD / unit | J92: {=_xlfn.LET( _xlpm.units_sold, $J$84:$AG$90, _xlpm.cost,_xlfn.ANCHORARRAY( G84), _xlpm.avg_cost, _xlfn.LAMBDA(_xlpm.units_col, IFERROR( SUMPRODUCT( _xlpm.units_col, _xlpm.cost ) / SUM( _xlpm.units_col ), 0 ) ), _xlfn.BYCOL( _xlpm.units_sold, _xlpm.avg_cost ) )} -> 0 | K92: 1087.725 | L92: 1087.725 | M92: 1087.725 | N92: 1087.725 | O92: 1136.4068 | P92: 1136.4068 | Q92: 1136.4068 | R92: 1136.4068 | S92: 1187.3788 | T92: 1187.3788 | U92: 1187.3788 | V92: 1187.3788 | W92: 1240.5402 | X92: 1240.5402 | Y92: 1240.5402 | Z92: 1240.5402 | AA92: 1296.2011 | AB92: 1296.2011 | AC92: 1296.2011 | AD92: 0 | AE92: 1354.4485 | AF92: 0 | AG92: 0
E95: Inventory ending balance by vintage | G95: Cost per unit
F96: {=TRANSPOSE(_xlfn.UNIQUE(_xlfn.ANCHORARRAY($J$11),TRUE))} -> 2023 | G96: {=TRANSPOSE(_xlfn.UNIQUE(_xlfn.ANCHORARRAY( $J$42), TRUE))} -> 1087.725 | J96: =I96 + J75 - J84 -> 185000 | K96: =J96 + K75 - K84 -> 220000 | L96: =K96 + L75 - L84 -> 330000 | M96: =L96 + M75 - M84 -> 140000 | N96: =M96 + N75 - N84 -> 0 | O96: =N96 + O75 - O84 -> 0 | P96: =O96 + P75 - P84 -> 0 | Q96: =P96 + Q75 - Q84 -> 0 | ... AK96: =AJ96 + AK75 - AK84 -> 0
F97: 2024 | G97: 1136.4068 | J97: =I97 + J76 - J85 -> 0 | K97: =J97 + K76 - K85 -> 0 | L97: =K97 + L76 - L85 -> 0 | M97: =L97 + M76 - M85 -> 0 | N97: =M97 + N76 - N85 -> 313750 | O97: =N97 + O76 - O85 -> 330000 | P97: =O97 + P76 - P85 -> 425000 | Q97: =P97 + Q76 - Q85 -> 205000 | ... AK97: =AJ97 + AK76 - AK85 -> 0
F98: 2025 | G98: 1187.3788 | J98: =I98 + J77 - J86 -> 0 | K98: =J98 + K77 - K86 -> 0 | L98: =K98 + L77 - L86 -> 0 | M98: =L98 + M77 - M86 -> 0 | N98: =M98 + N77 - N86 -> 0 | O98: =N98 + O77 - O86 -> 0 | P98: =O98 + P77 - P86 -> 0 | Q98: =P98 + Q77 - Q86 -> 0 | ... AK98: =AJ98 + AK77 - AK86 -> 0
F99: 2026 | G99: 1240.5402 | J99: =I99 + J78 - J87 -> 0 | K99: =J99 + K78 - K87 -> 0 | L99: =K99 + L78 - L87 -> 0 | M99: =L99 + M78 - M87 -> 0 | N99: =M99 + N78 - N87 -> 0 | O99: =N99 + O78 - O87 -> 0 | P99: =O99 + P78 - P87 -> 0 | Q99: =P99 + Q78 - Q87 -> 0 | ... AK99: =AJ99 + AK78 - AK87 -> 0
F100: 2027 | G100: 1296.2011 | J100: =I100 + J79 - J88 -> 0 | K100: =J100 + K79 - K88 -> 0 | L100: =K100 + L79 - L88 -> 0 | M100: =L100 + M79 - M88 -> 0 | N100: =M100 + N79 - N88 -> 0 | O100: =N100 + O79 - O88 -> 0 | P100: =O100 + P79 - P88 -> 0 | Q100: =P100 + Q79 - Q88 -> 0 | ... AK100: =AJ100 + AK79 - AK88 -> 0
F101: 2028 | G101: 1354.4485 | J101: =I101 + J80 - J89 -> 0 | K101: =J101 + K80 - K89 -> 0 | L101: =K101 + L80 - L89 -> 0 | M101: =L101 + M80 - M89 -> 0 | N101: =M101 + N80 - N89 -> 0 | O101: =N101 + O80 - O89 -> 0 | P101: =O101 + P80 - P89 -> 0 | Q101: =P101 + Q80 - Q89 -> 0 | ... AK101: =AJ101 + AK80 - AK89 -> 0
F102: 2029 | G102: 1415.361 | J102: =I102 + J81 - J90 -> 0 | K102: =J102 + K81 - K90 -> 0 | L102: =K102 + L81 - L90 -> 0 | M102: =L102 + M81 - M90 -> 0 | N102: =M102 + N81 - N90 -> 0 | O102: =N102 + O81 - O90 -> 0 | P102: =O102 + P81 - P90 -> 0 | Q102: =P102 + Q81 - Q90 -> 0 | ... AK102: =AJ102 + AK81 - AK90 -> 0
E103: FIFO inventory | G103: USD m | J103: =_xlfn.LET( _xlpm.volume, J96:J102, _xlpm.cost,_xlfn.ANCHORARRAY( $G$96), SUMPRODUCT( _xlpm.volume, _xlpm.cost ) / 1000 ) -> 201229.13 | K103: =_xlfn.LET( _xlpm.volume, K96:K102, _xlpm.cost,_xlfn.ANCHORARRAY( $G$96), SUMPRODUCT( _xlpm.volume, _xlpm.cost ) / 1000 ) -> 239299.5 | L103: =_xlfn.LET( _xlpm.volume, L96:L102, _xlpm.cost,_xlfn.ANCHORARRAY( $G$96), SUMPRODUCT( _xlpm.volume, _xlpm.cost ) / 1000 ) -> 358949.25 | M103: =_xlfn.LET( _xlpm.volume, M96:M102, _xlpm.cost,_xlfn.ANCHORARRAY( $G$96), SUMPRODUCT( _xlpm.volume, _xlpm.cost ) / 1000 ) -> 152281.5 | N103: =_xlfn.LET( _xlpm.volume, N96:N102, _xlpm.cost,_xlfn.ANCHORARRAY( $G$96), SUMPRODUCT( _xlpm.volume, _xlpm.cost ) / 1000 ) -> 356547.63 | O103: =_xlfn.LET( _xlpm.volume, O96:O102, _xlpm.cost,_xlfn.ANCHORARRAY( $G$96), SUMPRODUCT( _xlpm.volume, _xlpm.cost ) / 1000 ) -> 375014.24 | P103: =_xlfn.LET( _xlpm.volume, P96:P102, _xlpm.cost,_xlfn.ANCHORARRAY( $G$96), SUMPRODUCT( _xlpm.volume, _xlpm.cost ) / 1000 ) -> 482972.88 | Q103: =_xlfn.LET( _xlpm.volume, Q96:Q102, _xlpm.cost,_xlfn.ANCHORARRAY( $G$96), SUMPRODUCT( _xlpm.volume, _xlpm.cost ) / 1000 ) -> 232963.39 | ... AK103: =_xlfn.LET( _xlpm.volume, AK96:AK102, _xlpm.cost,_xlfn.ANCHORARRAY( $G$96), SUMPRODUCT( _xlpm.volume, _xlpm.cost ) / 1000 ) -> 0
E104: Average FIFO cost per unit | G104: USD / unit | J104: {=_xlfn.LET( _xlpm.units_sold, $J$96:$AG$102, _xlpm.cost,_xlfn.ANCHORARRAY( G96), _xlpm.avg_cost, _xlfn.LAMBDA(_xlpm.units_col, IFERROR( SUMPRODUCT( _xlpm.units_col, _xlpm.cost ) / SUM( _xlpm.units_col ), 0 ) ), _xlfn.BYCOL( _xlpm.units_sold, _xlpm.avg_cost ) )} -> 1087.725 | K104: 1087.725 | L104: 1087.725 | M104: 1087.725 | N104: 1136.4068 | O104: 1136.4068 | P104: 1136.4068 | Q104: 1136.4068 | R104: 1187.3788 | S104: 1187.3788 | T104: 1187.3788 | U104: 1187.3788 | V104: 1240.5402 | W104: 1240.5402 | X104: 1240.5402 | Y104: 1240.5402 | Z104: 1296.2011 | AA104: 1296.2011 | AB104: 1296.2011 | AC104: 0 | AD104: 1354.4485 | AE104: 0 | AF104: 0 | AG104: 0
B107: FIFO inventory
E109: Inventory opening balance | G109: USD m | J109: =I113 -> 0 | K109: =J113 -> 201229.13 | L109: =K113 -> 239299.5 | M109: =L113 -> 358949.25 | N109: =M113 -> 152281.5 | O109: =N113 -> 356547.63 | P109: =O113 -> 375014.24 | Q109: =P113 -> 482972.88 | ... AK109: =AJ113 -> 0
E110: Production | G110: USD m | J110: {=_xlfn.ANCHORARRAY( J22) *_xlfn.ANCHORARRAY( J42) / 1000} -> 445967.25 | K110: 445967.25 | L110: 445967.25 | M110: 445967.25 | N110: 465926.78 | O110: 465926.78 | P110: 465926.78 | Q110: 465926.78 | R110: 486825.3 | S110: 486825.3 | T110: 486825.3 | U110: 486825.3 | V110: 508621.47 | W110: 508621.47 | X110: 508621.47 | Y110: 508621.47 | Z110: 531442.46 | AA110: 531442.46 | AB110: 531442.46 | AC110: 531442.46 | AD110: 555323.88 | AE110: 555323.88 | AF110: 555323.88 | AG110: 555323.88 | AH110: 580298 | AI110: 580298 | AJ110: 580298 | AK110: 580298
E111: Units sold from inventory | G111: USD m | J111: {=$J$91:$AK$91 * -1} -> 0 | K111: -201229.13 | L111: -239299.5 | M111: -358949.25 | N111: -152281.5 | O111: -356547.63 | P111: -357968.14 | Q111: -482972.88 | R111: -232963.39 | S111: -435693.8 | T111: -392725.53 | U111: -525711.96 | V111: -227086.19 | W111: -422756.7 | X111: -392848.06 | Y111: -470645.43 | Z111: -117618.71 | AA111: -299841.9 | AB111: -240456.65 | AC111: -299236.94 | AD111: 0 | AE111: -46579.176 | AF111: 0 | AG111: 0 | AH111: 0 | AI111: 0 | AJ111: 0 | AK111: 0
E112: Units sold from current production | G112: USD m | J112: =J69 * -1 -> -244738.13 | K112: =K69 * -1 -> -206667.75 | L112: =L69 * -1 -> -87018 | M112: =M69 * -1 -> -293685.75 | N112: =N69 * -1 -> -109379.15 | O112: =O69 * -1 -> -90912.542 | P112: =P69 * -1 -> 0 | Q112: =Q69 * -1 -> -232963.39 | ... AK112: =AK69 * -1 -> -580298
E113: Inventory closing balance | G113: USD m | J113: =SUM( J109:J112) -> 201229.13 | K113: =SUM( K109:K112) -> 239299.5 | L113: =SUM( L109:L112) -> 358949.25 | M113: =SUM( M109:M112) -> 152281.5 | N113: =SUM( N109:N112) -> 356547.63 | O113: =SUM( O109:O112) -> 375014.24 | P113: =SUM( P109:P112) -> 482972.88 | Q113: =SUM( Q109:Q112) -> 232963.39 | ... AK113: =SUM( AK109:AK112) -> 0
A117: WAC Cost of Goods Sold and Inventory
E120: Inventory beginning balance | G120: units | J120: =I124 -> 0 | K120: =J124 -> 185000 | L120: =K124 -> 220000 | M120: =L124 -> 330000 | N120: =M124 -> 140000 | O120: =N124 -> 313750 | P120: =O124 -> 330000 | Q120: =P124 -> 425000 | ... AK120: =AJ124 -> 0
E121: Production | G121: units | J121: {=_xlfn.ANCHORARRAY( J22)} -> 410000 | K121: 410000 | L121: 410000 | M121: 410000 | N121: 410000 | O121: 410000 | P121: 410000 | Q121: 410000 | R121: 410000 | S121: 410000 | T121: 410000 | U121: 410000 | V121: 410000 | W121: 410000 | X121: 410000 | Y121: 410000 | Z121: 410000 | AA121: 410000 | AB121: 410000 | AC121: 410000 | AD121: 410000 | AE121: 410000 | AF121: 410000 | AG121: 410000 | AH121: 410000 | AI121: 410000 | AJ121: 410000 | AK121: 410000
E122: Available for sale | G122: units | J122: =SUM( J120:J121) -> 410000 | K122: =SUM( K120:K121) -> 595000 | L122: =SUM( L120:L121) -> 630000 | M122: =SUM( M120:M121) -> 740000 | N122: =SUM( N120:N121) -> 550000 | O122: =SUM( O120:O121) -> 723750 | P122: =SUM( P120:P121) -> 740000 | Q122: =SUM( Q120:Q121) -> 835000 | ... AK122: =SUM( AK120:AK121) -> 410000
E123: Units sold | G123: units | J123: {=$J$30:$AK$30 * - 1} -> -225000 | K123: -375000 | L123: -300000 | M123: -600000 | N123: -236250 | O123: -393750 | P123: -315000 | Q123: -630000 | R123: -248062.5 | S123: -413437.5 | T123: -330750 | U123: -661500 | V123: -260465.63 | W123: -434109.38 | X123: -347287.5 | Y123: -694575 | Z123: -273488.91 | AA123: -455814.84 | AB123: -364651.88 | AC123: -640856.87 | AD123: -375610.23 | AE123: -444389.77 | AF123: -410000 | AG123: -410000 | AH123: -410000 | AI123: -410000 | AJ123: -410000 | AK123: -410000
E124: Inventory ending balance | G124: units | J124: =SUM( J122:J123) -> 185000 | K124: =SUM( K122:K123) -> 220000 | L124: =SUM( L122:L123) -> 330000 | M124: =SUM( M122:M123) -> 140000 | N124: =SUM( N122:N123) -> 313750 | O124: =SUM( O122:O123) -> 330000 | P124: =SUM( P122:P123) -> 425000 | Q124: =SUM( Q122:Q123) -> 205000 | ... AK124: =SUM( AK122:AK123) -> 0
E127: Inventory beginning balance | G127: USD m | J127: =I137 -> 0 | K127: =J137 -> 201229.13 | L127: =K137 -> 239299.5 | M127: =L137 -> 358949.25 | N127: =M137 -> 152281.5 | O127: =N137 -> 352659.72 | P127: =O137 -> 373241.51 | Q127: =P137 -> 481954.76 | ... AK127: =AJ137 -> 0
E128: Production costs | G128: USD m | J128: {=_xlfn.ANCHORARRAY( J22) *_xlfn.ANCHORARRAY( J42) / 1000} -> 445967.25 | K128: 445967.25 | L128: 445967.25 | M128: 445967.25 | N128: 465926.78 | O128: 465926.78 | P128: 465926.78 | Q128: 465926.78 | R128: 486825.3 | S128: 486825.3 | T128: 486825.3 | U128: 486825.3 | V128: 508621.47 | W128: 508621.47 | X128: 508621.47 | Y128: 508621.47 | Z128: 531442.46 | AA128: 531442.46 | AB128: 531442.46 | AC128: 531442.46 | AD128: 555323.88 | AE128: 555323.88 | AF128: 555323.88 | AG128: 555323.88 | AH128: 580298 | AI128: 580298 | AJ128: 580298 | AK128: 580298
E129: Available for sale | G129: USD m | J129: =SUM( J127:J128) -> 445967.25 | K129: =SUM( K127:K128) -> 647196.38 | L129: =SUM( L127:L128) -> 685266.75 | M129: =SUM( M127:M128) -> 804916.5 | N129: =SUM( N127:N128) -> 618208.28 | O129: =SUM( O127:O128) -> 818586.5 | P129: =SUM( P127:P128) -> 839168.29 | Q129: =SUM( Q127:Q128) -> 947881.54 | ... AK129: =SUM( AK127:AK128) -> 580298
E131: Weighted average cost | G131: USD m | J131: =J129/J122*1000 -> 1087.725 | K131: =K129/K122*1000 -> 1087.725 | L131: =L129/L122*1000 -> 1087.725 | M131: =M129/M122*1000 -> 1087.725 | N131: =N129/N122*1000 -> 1124.0151 | O131: =O129/O122*1000 -> 1131.0349 | P131: =P129/P122*1000 -> 1134.0112 | Q131: =Q129/Q122*1000 -> 1135.1875 | ... AK131: =AK129/AK122*1000 -> 1415.361
E132: Units sold | G132: units | J132: =J30 -> 225000 | K132: =K30 -> 375000 | L132: =L30 -> 300000 | M132: =M30 -> 600000 | N132: =N30 -> 236250 | O132: =O30 -> 393750 | P132: =P30 -> 315000 | Q132: =Q30 -> 630000 | ... AK132: =AK30 -> 410000
E133: WAC Cost of Goods Sold | G133: USD m | J133: =J131*J132/1000 -> 244738.13 | K133: =K131*K132/1000 -> 407896.88 | L133: =L131*L132/1000 -> 326317.5 | M133: =M131*M132/1000 -> 652635 | N133: =N131*N132/1000 -> 265548.56 | O133: =O131*O132/1000 -> 445344.99 | P133: =P131*P132/1000 -> 357213.53 | Q133: =Q131*Q132/1000 -> 715168.11 | ... AK133: =AK131*AK132/1000 -> 580298
E135: Available for sale | G135: USD m | J135: =J129 -> 445967.25 | K135: =K129 -> 647196.38 | L135: =L129 -> 685266.75 | M135: =M129 -> 804916.5 | N135: =N129 -> 618208.28 | O135: =O129 -> 818586.5 | P135: =P129 -> 839168.29 | Q135: =Q129 -> 947881.54 | ... AK135: =AK129 -> 580298
E136: WAC Cost of Goods Sold | G136: USD m | J136: =J133*-1 -> -244738.13 | K136: =K133*-1 -> -407896.88 | L136: =L133*-1 -> -326317.5 | M136: =M133*-1 -> -652635 | N136: =N133*-1 -> -265548.56 | O136: =O133*-1 -> -445344.99 | P136: =P133*-1 -> -357213.53 | Q136: =Q133*-1 -> -715168.11 | ... AK136: =AK133*-1 -> -580298
E137: Ending inventory | G137: USD m | J137: =SUM( J135:J136) -> 201229.13 | K137: =SUM( K135:K136) -> 239299.5 | L137: =SUM( L135:L136) -> 358949.25 | M137: =SUM( M135:M136) -> 152281.5 | N137: =SUM( N135:N136) -> 352659.72 | O137: =SUM( O135:O136) -> 373241.51 | P137: =SUM( P135:P136) -> 481954.76 | Q137: =SUM( Q135:Q136) -> 232713.43 | ... AK137: =SUM( AK135:AK136) -> 0
A140: Income statement
E142: =E$49 -> Revenue | F142: =F$49 -> 0 | G142: =G$49 -> USD m | H142: =H$49 -> 0 | I142: =I$49 -> 0 | J142: =J$49 -> 318159 | K142: =K$49 -> 530265 | L142: =L$49 -> 424212 | ... AK142: =AK$49 -> 736979.1
E144: Cost of Goods Sold
E145: FIFO | G145: USD m | J145: =SUM( J$111, J$112 ) -> -244738.13 | K145: =SUM( K$111, K$112 ) -> -407896.88 | L145: =SUM( L$111, L$112 ) -> -326317.5 | M145: =SUM( M$111, M$112 ) -> -652635 | N145: =SUM( N$111, N$112 ) -> -261660.65 | O145: =SUM( O$111, O$112 ) -> -447460.17 | P145: =SUM( P$111, P$112 ) -> -357968.14 | Q145: =SUM( Q$111, Q$112 ) -> -715936.27 | ... AK145: =SUM( AK$111, AK$112 ) -> -580298
...

Sheet CaseData
B2: Waterworks Corp forecast model - Assumptions
B4: Assumption | D4: Units | E4: Value
B6: Model start date | D6: [date] | E6: 44927
B8: Production | D8: [units / quarter] | E8: 410000
E10: Q1 | F10: Q2 | G10: Q3 | H10: Q4
B11: Year 1 demand | D11: [units] | E11: 225000 | F11: 375000 | G11: 300000 | H11: 600000
B13: New demand growth YoY | D13: [%] | E13: 0.05
B15: Unmet Demand Rollover | D15: [%] | E15: 1
B17: Production costs | E17: Year 1 | F17: % ∆ YoY | G17: Note
C18: Salaries | D18: [$ / hr] | E18: 27.75 | F18: 0.07 | G18: Rounded to nearest $0.01
C19: Production time | D19: [hrs / unit] | E19: 21.9 | F19: -0.02 | G19: Not rounded
C20: Materials | D20: [$ / unit] | E20: 480 | F20: 0.04 | G20: Not rounded
B22: Mark-up
C23: Year 1 mark-up | D23: [%] | E23: 0.3
C24: YoY change | D24: [% pts] | E24: -0.005
C25: Note: final sale price rounded to nearest $0.01
B27: Overhead | D27: [$ / quarter] | E27: 37500000
B29: Tax rate | D29: [%] | E29: 0.35
B31: Inventory opening balance | D31: [units] | E31: 0
D32: [$ / quarter] | E32: 0
B34: Example of Weighted Average Cost Accounting Methodology
E36: Year 1 | F36: Year 2
C37: Beginning Inventory | D37: [units] | E37: 0 | F37: 500
C38: Production | D38: [units] | E38: 1000 | F38: 500
C39: Units Available for Sale | D39: [units] | E39: 1000 | F39: =SUM(F37:F38) -> 1000 | G39: A
C41: Units Sold | D41: [units] | E41: 500 | F41: 500
C42: Ending Inventory | D42: [units] | E42: 500 | F42: 500
C44: Production Cost | D44: [$/unit] | E44: 150 | F44: 100
C46: Beginning Inventory | D46: [$] | E46: 0 | F46: 75000
C47: Production Costs | D47: [$] | E47: 150000 | F47: =F38*F44 -> 50000
C48: Cost of Available Units | D48: [$] | E48: 150000 | F48: 125000 | G48: B
C50: WAC | D50: [$/unit] | E50: 150 | F50: 125 | G50: B/A
C52: COGS Period | E52: 75000 | F52: 62500
C53: Ending Inventory | E53: 75000 | F53: 62500
C55: Company name | E55: Waterworks Corp
C56: CFM Topic | E56: Working capital
C57: Model years | E57: 7 | F57: years
C58: Number of periods | E58: 4 | F58: quarters

Sheet Tmp
A1: =company -> Waterworks Corp
A2: {=topic} -> CFM Topic: Working capital
A3: TMP SCHEDULE | F3: Constant | G3: Unit | H3: Total
