Workbook
Name company: CaseData!$B$1
Name periods: CaseData!$C$59
Name start_date: CaseData!$C$58
Name topic: "CFM Topic: " & CaseData!$C$57

Sheet Calculations
A1: {=company} -> JAK Holdings Inc.
A2: {=topic} -> CFM Topic: Income Tax
A3: CALCULATION SCHEDULE | F3: Constant | G3: Unit | H3: Total | J3: {=YEAR( EOMONTH( start_date, _xlfn.SEQUENCE( 1, periods, 0, 12 ) ) )} -> 2019 | K3: 2020 | L3: 2021 | M3: 2022 | N3: 2023
E5: Country | F5: U.S.
A7: Tax schedule
E9: Projected Accounting Pre-tax Income | G9: USD m | J9: {=_xlfn.LET( _xlpm.values, CaseData!$F$9:$I$13, _xlpm.years, VALUE( RIGHT( CaseData!$B$9:$B$13, 4 ) ), _xlpm.countries, CaseData!$F$3:$I$3, _xlpm.current_year,_xlfn.ANCHORARRAY( $J$3), _xlpm.current_country, $F$5, _xlpm.fx_rate, INDEX( CaseData!$F$7:$I$7, 1, MATCH( _xlpm.current_country, _xlpm.countries, 0 ) ), _xlpm.projected, INDEX( _xlpm.values, MATCH( _xlpm.current_year, _xlpm.years, 0 ), MATCH( _xlpm.current_country, _xlpm.countries, 0 ) ), _xlpm.projected / _xlpm.fx_rate )} -> 17840 | K9: 17062 | L9: 19307 | M9: 17314 | N9: 14576
D10: plus | E10: Non deductible expenses | G10: {=$G$9:$G$9} -> USD m | J10: {=_xlfn.LET( _xlpm.values, CaseData!$F$35:$I$39, _xlpm.years, VALUE( RIGHT( CaseData!$B$9:$B$13, 4 ) ), _xlpm.countries, CaseData!$F$3:$I$3, _xlpm.current_year,_xlfn.ANCHORARRAY( $J$3), _xlpm.current_country, $F$5, _xlpm.fx_rate, INDEX( CaseData!$F$7:$I$7, 1, MATCH( _xlpm.current_country, _xlpm.countries, 0 ) ), _xlpm.projected, INDEX( _xlpm.values, MATCH( _xlpm.current_year, _xlpm.years, 0 ), MATCH( _xlpm.current_country, _xlpm.countries, 0 ) ), _xlpm.projected / _xlpm.fx_rate )} -> 6742 | K10: 0 | L10: 0 | M10: 0 | N10: 0
E11: Taxable Income for Accounting Purposes (A) | G11: {=$G$9:$G$9} -> USD m | J11: {=_xlfn.ANCHORARRAY( J9) +_xlfn.ANCHORARRAY( J10)} -> 24582 | K11: 17062 | L11: 19307 | M11: 17314 | N11: 14576
D13: plus | E13: Accounting depreciation | G13: {=$G$9:$G$9} -> USD m | J13: {=_xlfn.LET( _xlpm.values, CaseData!$F$23:$I$27, _xlpm.years, VALUE( RIGHT( CaseData!$B$9:$B$13, 4 ) ), _xlpm.countries, CaseData!$F$3:$I$3, _xlpm.current_year,_xlfn.ANCHORARRAY( $J$3), _xlpm.current_country, $F$5, _xlpm.fx_rate, INDEX( CaseData!$F$7:$I$7, 1, MATCH( _xlpm.current_country, _xlpm.countries, 0 ) ), _xlpm.projected, INDEX( _xlpm.values, MATCH( _xlpm.current_year, _xlpm.years, 0 ), MATCH( _xlpm.current_country, _xlpm.countries, 0 ) ), _xlpm.projected / _xlpm.fx_rate )} -> 5432 | K13: 5595 | L13: 5875 | M13: 6169 | N13: 6416
D14: minus | E14: Taxable depreciation | G14: USD m | J14: {=$J$31:$N$31} -> 8825.742 | K14: 8402.8997 | L14: 8319.2721 | M14: 8124.1606 | N14: 7596.7168
D15: minus | E15: Incremental deduction for tax purposes | G15: USD m | J15: {=_xlfn.LET( _xlpm.values, CaseData!$F$42:$I$46, _xlpm.years, VALUE( RIGHT( CaseData!$B$9:$B$13, 4 ) ), _xlpm.countries, CaseData!$F$3:$I$3, _xlpm.current_year,_xlfn.ANCHORARRAY( $J$3), _xlpm.current_country, $F$5, _xlpm.fx_rate, INDEX( CaseData!$F$7:$I$7, 1, MATCH( _xlpm.current_country, _xlpm.countries, 0 ) ), _xlpm.projected, INDEX( _xlpm.values, MATCH( _xlpm.current_year, _xlpm.years, 0 ), MATCH( _xlpm.current_country, _xlpm.countries, 0 ) ), _xlpm.projected / _xlpm.fx_rate )} -> 5709 | K15: 5972 | L15: 2317 | M15: 3809 | N15: 3790
E16: Taxable Income for Tax Purposes before NOL | G16: USD m | J16: =J11 + J13 - J14 - J15 -> 15479.258 | K16: =K11 + K13 - K14 - K15 -> 8282.1003 | L16: =L11 + L13 - L14 - L15 -> 14545.728 | M16: =M11 + M13 - M14 - M15 -> 11549.839 | N16: =N11 + N13 - N14 - N15 -> 9605.2832
E18: Utilization of Tax Loss Carry Forwards | G18: USD m | J18: =J$36 -> 15479.258 | K18: =K$36 -> 8282.1003 | L18: =L$36 -> 14545.728 | M18: =M$36 -> 5106.9138 | N18: =N$36 -> 4400
E19: Taxable Income for Tax Purposes after NOL | G19: USD m | J19: =J16 - J18 -> 0 | K19: =K16 - K18 -> 0 | L19: =L16 - L18 -> 0 | M19: =M16 - M18 -> 6442.9256 | N19: =N16 - N18 -> 5205.2832
E22: Current corporate tax rate | F22: {=_xlfn.LET( _xlpm.countries, CaseData!$F$3:$I$3, _xlpm.current_country, $F$5, _xlfn.XLOOKUP( _xlpm.current_country, _xlpm.countries, CaseData!$F$5:$I$5, 0, 0 ) )} -> 0.256
E23: Current tax | G23: USD m | J23: =J19 * $F$22 -> 0 | K23: =K19 * $F$22 -> 0 | L23: =L19 * $F$22 -> 0 | M23: =M19 * $F$22 -> 1649.389 | N23: =N19 * $F$22 -> 1332.5525
E24: Deferred tax | G24: USD m | J24: =J25 - J23 -> 6292.992 | K24: =K25 - K23 -> 4367.872 | L24: =L25 - L23 -> 4942.592 | M24: =M25 - M23 -> 2782.995 | N24: =N25 - N23 -> 2398.9035
E25: Tax | G25: USD m | J25: =J$11 * $F$22 -> 6292.992 | K25: =K$11 * $F$22 -> 4367.872 | L25: =L$11 * $F$22 -> 4942.592 | M25: =M$11 * $F$22 -> 4432.384 | N25: =N$11 * $F$22 -> 3731.456
A27: Taxable depreciation
E29: Tax Basis in Depreciable Assets opening balance | G29: {=$G$9:$G$9} -> USD m | J29: {=_xlfn.LET( _xlpm.countries, CaseData!$F$3:$I$3, _xlpm.current_country, $F$5, _xlpm.opening_balance, _xlfn.XLOOKUP( _xlpm.current_country, _xlpm.countries, CaseData!$F$29:$I$29, 0, 0 ), _xlpm.fx_rate, _xlfn.XLOOKUP( _xlpm.current_country, _xlpm.countries, CaseData!$F$7:$I$7, 0, 0 ), _xlpm.opening_balance / _xlpm.fx_rate )} -> 65510 | K29: =J32 -> 62928.258 | L29: =K32 -> 59913.358 | M29: =L32 -> 59317.086 | N29: =M32 -> 57925.926
D30: plus | E30: Addition to fixed assets | G30: USD m | J30: {=_xlfn.LET( _xlpm.values, CaseData!$F$16:$I$20, _xlpm.years, VALUE( RIGHT( CaseData!$B$9:$B$13, 4 ) ), _xlpm.countries, CaseData!$F$3:$I$3, _xlpm.current_year,_xlfn.ANCHORARRAY( $J$3), _xlpm.current_country, $F$5, _xlpm.fx_rate, INDEX( CaseData!$F$7:$I$7, 1, MATCH( _xlpm.current_country, _xlpm.countries, 0 ) ), _xlpm.projected, INDEX( _xlpm.values, MATCH( _xlpm.current_year, _xlpm.years, 0 ), MATCH( _xlpm.current_country, _xlpm.countries, 0 ) ), _xlpm.projected / _xlpm.fx_rate )} -> 6244 | K30: 5388 | L30: 7723 | M30: 6733 | N30: 3836
D31: minus | E31: Taxable Depreciation at blended rate | F31: {=_xlfn.LET( _xlpm.countries, CaseData!$F$3:$I$3, _xlpm.current_country, $F$5, _xlfn.XLOOKUP( _xlpm.current_country, _xlpm.countries, CaseData!$F$31:$I$31, 0, 0 ) )} -> 0.123 | G31: USD m | J31: =SUM( J29:J30 ) * $F$31 -> 8825.742 | K31: =SUM( K29:K30 ) * $F$31 -> 8402.8997 | L31: =SUM( L29:L30 ) * $F$31 -> 8319.2721 | M31: =SUM( M29:M30 ) * $F$31 -> 8124.1606 | N31: =SUM( N29:N30 ) * $F$31 -> 7596.7168
E32: Tax Basis in Depreciable Assets closing balance | G32: USD m | J32: =J29 + J30 - J31 -> 62928.258 | K32: =K29 + K30 - K31 -> 59913.358 | L32: =L29 + L30 - L31 -> 59317.086 | M32: =M29 + M30 - M31 -> 57925.926 | N32: =N29 + N30 - N31 -> 54165.209
A34: Tax Loss Carry Forward
E36: Utilization of Tax Loss Carry Forwards | G36: USD m | J36: =MIN( J16, SUM( I47:I52 ) ) -> 15479.258 | K36: =MIN( K16, SUM( J47:J52 ) ) -> 8282.1003 | L36: =MIN( L16, SUM( K47:K52 ) ) -> 14545.728 | M36: =MIN( M16, SUM( L47:L52 ) ) -> 5106.9138 | N36: =MIN( N16, SUM( M47:M52 ) ) -> 4400
E37: 43830 | G37: USD m | J37: =MIN( J36, I47) -> 3425 | K37: =MIN( K36, J47) -> 0 | L37: =MIN( L36, K47) -> 0 | M37: =MIN( M36, L47) -> 0 | N37: =MIN( N36, M47) -> 0
E38: 44196 | G38: USD m | J38: =MIN( I48, J36 - SUM( J$37:J37 ) ) -> 12054.258 | K38: =MIN( J48, K$36 - SUM( K$37:K37 ) ) -> 2066.742 | L38: =MIN( K48, L$36 - SUM( L$37:L37 ) ) -> 0 | M38: =MIN( L48, M$36 - SUM( M$37:M37 ) ) -> 0 | N38: =MIN( M48, N$36 - SUM( N$37:N37 ) ) -> 0
E39: 44561 | G39: USD m | J39: =MIN( I49, J$36 - SUM( J$37:J38 ) ) -> 0 | K39: =MIN( J49, K$36 - SUM( K$37:K38 ) ) -> 0 | L39: =MIN( K49, L$36 - SUM( L$37:L38 ) ) -> 0 | M39: =MIN( L49, M$36 - SUM( M$37:M38 ) ) -> 0 | N39: =MIN( M49, N$36 - SUM( N$37:N38 ) ) -> 0
E40: 44926 | G40: USD m | J40: =MIN( I50, J$36 - SUM( J$37:J39 ) ) -> 0 | K40: =MIN( J50, K$36 - SUM( K$37:K39 ) ) -> 6215.3583 | L40: =MIN( K50, L$36 - SUM( L$37:L39 ) ) -> 6105.6417 | M40: =MIN( L50, M$36 - SUM( M$37:M39 ) ) -> 0 | N40: =MIN( M50, N$36 - SUM( N$37:N39 ) ) -> 0
E41: 45291 | G41: USD m | J41: =MIN( I51, J$36 - SUM( J$37:J40 ) ) -> 0 | K41: =MIN( J51, K$36 - SUM( K$37:K40 ) ) -> 0 | L41: =MIN( K51, L$36 - SUM( L$37:L40 ) ) -> 8440.0862 | M41: =MIN( L51, M$36 - SUM( M$37:M40 ) ) -> 706.9138 | N41: =MIN( M51, N$36 - SUM( N$37:N40 ) ) -> 0
E42: Expiring thereafter | G42: USD m
J45: {=YEAR( EOMONTH( start_date, _xlfn.SEQUENCE( 1, periods, 0, 12 ) ) )} -> 2019 | K45: 2020 | L45: 2021 | M45: 2022 | N45: 2023
E46: Tax Loss Carry Forwards Ending Balances | G46: USD m
E47: 43830 | G47: USD m | I47: {=_xlfn.LET( _xlpm.values, CaseData!$F$49:$I$54, _xlpm.years, VALUE( RIGHT( CaseData!$B$9:$B$13, 4 ) ), _xlpm.countries, CaseData!$F$3:$I$3, _xlpm.current_year,_xlfn.ANCHORARRAY( $J$3), _xlpm.current_country, $F$5, _xlpm.fx_rate, INDEX( CaseData!$F$7:$I$7, 1, MATCH( _xlpm.current_country, _xlpm.countries, 0 ) ), _xlpm.projected, INDEX( _xlpm.values, MATCH( _xlpm.current_year, _xlpm.years, 0 ), MATCH( _xlpm.current_country, _xlpm.countries, 0 ) ), TRANSPOSE( _xlpm.projected / _xlpm.fx_rate ) )} -> 3425 | J47: =IF( J$45 < $E47, I47 - J37, 0 ) -> 0 | K47: =IF( K$45 < $E47, J47 - K37, 0 ) -> 0 | L47: =IF( L$45 < $E47, K47 - L37, 0 ) -> 0 | M47: =IF( M$45 < $E47, L47 - M37, 0 ) -> 0 | N47: =IF( N$45 < $E47, M47 - N37, 0 ) -> 0
E48: 44196 | G48: USD m | I48: 14121 | J48: =IF( J$45 < $E48, I48 - J38, 0 ) -> 2066.742 | K48: =IF( K$45 < $E48, J48 - K38, 0 ) -> 0 | L48: =IF( L$45 < $E48, K48 - L38, 0 ) -> 0 | M48: =IF( M$45 < $E48, L48 - M38, 0 ) -> 0 | N48: =IF( N$45 < $E48, M48 - N38, 0 ) -> 0
E49: 44561 | G49: USD m | I49: 0 | J49: =IF( J$45 < $E49, I49 - J39, 0 ) -> 0 | K49: =IF( K$45 < $E49, J49 - K39, 0 ) -> 0 | L49: =IF( L$45 < $E49, K49 - L39, 0 ) -> 0 | M49: =IF( M$45 < $E49, L49 - M39, 0 ) -> 0 | N49: =IF( N$45 < $E49, M49 - N39, 0 ) -> 0
E50: 44926 | G50: USD m | I50: 12321 | J50: =IF( J$45 < $E50, I50 - J40, 0 ) -> 12321 | K50: =IF( K$45 < $E50, J50 - K40, 0 ) -> 6105.6417 | L50: =IF( L$45 < $E50, K50 - L40, 0 ) -> 0 | M50: =IF( M$45 < $E50, L50 - M40, 0 ) -> 0 | N50: =IF( N$45 < $E50, M50 - N40, 0 ) -> 0
E51: 45291 | G51: USD m | I51: 9147 | J51: =IF( J$45 < $E51, I51 - J41, 0 ) -> 9147 | K51: =IF( K$45 < $E51, J51 - K41, 0 ) -> 9147 | L51: =IF( L$45 < $E51, K51 - L41, 0 ) -> 706.9138 | M51: =IF( M$45 < $E51, L51 - M41, 0 ) -> 0 | N51: =IF( N$45 < $E51, M51 - N41, 0 ) -> 0
E52: Expiring thereafter | G52: USD m m | I52: {=_xlfn.LET( _xlpm.countries, CaseData!$F$3:$I$3, _xlpm.current_country, $F$5, _xlpm.expiring_after, _xlfn.XLOOKUP( _xlpm.current_country, _xlpm.countries, CaseData!$F$54:$I$54, 0, 0 ), _xlpm.fx_rate, _xlfn.XLOOKUP( _xlpm.current_country, _xlpm.countries, CaseData!$F$7:$I$7, 0, 0 ), _xlfn.SEQUENCE( 1, periods + 1, _xlpm.expiring_after / _xlpm.fx_rate, 0 ) )} -> 4400 | J52: 4400 | K52: 4400 | L52: 4400 | M52: 4400 | N52: 4400
A54: Consolidation
E56: Current Tax in USD >>
J57: =J23 -> 0 | K57: =K23 -> 0 | L57: =L23 -> 0 | M57: =M23 -> 1649.389 | N57: =N23 -> 1332.5525
I58: {=TRANSPOSE(CaseData!$F$3:$I$3)} -> U.S. | J58: 0 | K58: 0 | L58: 0 | M58: 1649.389 | N58: 1332.5525
I59: Canada | J59: 0 | K59: 0 | L59: 0 | M59: 0 | N59: 0
I60: Mexico | J60: 0 | K60: 0 | L60: 2419.4552 | M60: 3367.9383 | N60: 3105.0547
I61: Germany | J61: 0 | K61: 0 | L61: 0 | M61: 0 | N61: 102.14548
I62: Total | J62: =SUM(J58:J61) -> 0 | K62: =SUM(K58:K61) -> 0 | L62: =SUM(L58:L61) -> 2419.4552 | M62: =SUM(M58:M61) -> 5017.3273 | N62: =SUM(N58:N61) -> 4539.7526
E65: Deferred Tax in USD >> | J65: =J24 -> 6292.992 | K65: =K24 -> 4367.872 | L65: =L24 -> 4942.592 | M65: =M24 -> 2782.995 | N65: =N24 -> 2398.9035
I66: {=TRANSPOSE(CaseData!$F$3:$I$3)} -> U.S. | J66: 6292.992 | K66: 4367.872 | L66: 4942.592 | M66: 2782.995 | N66: 2398.9035
I67: Canada | J67: 5595.814 | K67: 5360.3953 | L67: 5676.9574 | M67: 4991.0388 | N67: 6134.2364
I68: Mexico | J68: 4139.1156 | K68: 4639.8225 | L68: 1789.1104 | M68: 805.27886 | N68: 649.35859
I69: Germany | J69: 15381.447 | K69: 11584.889 | L69: 17394.209 | M69: 12141.774 | N69: 11058.944
I70: Total | J70: =SUM(J66:J69) -> 31409.369 | K70: =SUM(K66:K69) -> 25952.979 | L70: =SUM(L66:L69) -> 29802.869 | M70: =SUM(M66:M69) -> 20721.087 | N70: =SUM(N66:N69) -> 20241.442
E73: Total Tax in USD >> | J73: =J25 -> 6292.992 | K73: =K25 -> 4367.872 | L73: =L25 -> 4942.592 | M73: =M25 -> 4432.384 | N73: =N25 -> 3731.456
I74: {=TRANSPOSE(CaseData!$F$3:$I$3)} -> U.S. | J74: 6292.992 | K74: 4367.872 | L74: 4942.592 | M74: 4432.384 | N74: 3731.456
I75: Canada | J75: 5595.814 | K75: 5360.3953 | L75: 5676.9574 | M75: 4991.0388 | N75: 6134.2364
I76: Mexico | J76: 4139.1156 | K76: 4639.8225 | L76: 4208.5656 | M76: 4173.2172 | N76: 3754.4133
I77: Germany | J77: 15381.447 | K77: 11584.889 | L77: 17394.209 | M77: 12141.774 | N77: 11161.089
I78: Total | J78: =SUM(J74:J77) -> 31409.369 | K78: =SUM(K74:K77) -> 25952.979 | L78: =SUM(L74:L77) -> 32222.324 | M78: =SUM(M74:M77) -> 25738.414 | N78: =SUM(N74:N77) -> 24781.195
A80: End of schedule

Sheet CaseData
B1: JAK Holdings Inc.
B2: (in thousands, local currency as indicated)
F3: U.S. | G3: Canada | H3: Mexico | I3: Germany
F4: (USD) | G4: (CAD) | H4: (MXN) | I4: (EUR)
B5: Corporate Tax Rate | F5: 0.256 | G5: 0.265 | H5: 0.31 | I5: 0.326
B7: Exchange Rate (per USD) | F7: 1 | G7: 1.29 | H7: 19.89 | I7: 0.85
B8: Projected Accounting Pre-tax Income:
B9: Fiscal 2019 | F9: 17840 | G9: 27240 | H9: 265571 | I9: 29762
B10: Fiscal 2020 | F10: 17062 | G10: 26094 | H10: 208746 | I10: 30206
B11: Fiscal 2021 | F11: 19307 | G11: 27635 | H11: 270027 | I11: 32919
B12: Fiscal 2022 | F12: 17314 | G12: 24296 | H12: 267759 | I12: 31658
B13: Fiscal 2023 | F13: 14576 | G13: 29861 | H13: 240888 | I13: 29101
B15: Additions to Fixed Assets:
B16: Fiscal 2019 | F16: 6244 | G16: 9729 | H16: 79671 | I16: 16641
B17: Fiscal 2020 | F17: 5388 | G17: 16605 | H17: 80287 | I17: 8487
B18: Fiscal 2021 | F18: 7723 | G18: 9212 | H18: 67507 | I18: 9810
B19: Fiscal 2022 | F19: 6733 | G19: 9718 | H19: 80328 | I19: 19922
B20: Fiscal 2023 | F20: 3836 | G20: 16288 | H20: 80296 | I20: 16301
B22: Accounting Depreciation:
B23: Fiscal 2019 | F23: 5432 | G23: 7394 | H23: 66127 | I23: 14311
B24: Fiscal 2020 | F24: 5595 | G24: 7690 | H24: 69433 | I24: 14740
B25: Fiscal 2021 | F25: 5875 | G25: 7998 | H25: 72905 | I25: 15624
B26: Fiscal 2022 | F26: 6169 | G26: 8478 | H26: 76550 | I26: 16405
B27: Fiscal 2023 | F27: 6416 | G27: 8817 | H27: 80378 | I27: 16897
B29: Tax Basis in Depreciable Assets | F29: 65510 | G29: 85696 | H29: 645400 | I29: 163002
B31: Blended Tax Depreciation Rate | F31: 0.123 | G31: 0.142 | H31: 0.165 | I31: 0.156
B32: (% of beginning basis + additions to fixed assets)
B34: Expenses Not Deductible:
B35: Fiscal 2019 | F35: 6742 | G35: 0 | H35: 0 | I35: 10343
B36: Fiscal 2020 | F36: 0 | G36: 0 | H36: 88951 | I36: 0
B37: Fiscal 2021 | F37: 0 | G37: 0 | H37: 0 | I37: 12434
B38: Fiscal 2022 | F38: 0 | G38: 0 | H38: 0 | I38: 0
B39: Fiscal 2023 | F39: 0 | G39: 0 | H39: 0 | I39: 0
B41: Incremental Deductions for Tax Purposes:
B42: Fiscal 2019 | F42: 5709 | G42: 7355 | H42: 69048 | I42: 6036
B43: Fiscal 2020 | F43: 5972 | G43: 8350 | H43: 50099 | I43: 3551
B44: Fiscal 2021 | F44: 2317 | G44: 6080 | H44: 62106 | I44: 10537
B45: Fiscal 2022 | F45: 3809 | G45: 4373 | H45: 26776 | I45: 6970
B46: Fiscal 2023 | F46: 3790 | G46: 9854 | H46: 24089 | I46: 9642
B48: Tax Loss Carry Forwards:
B49: Expiring in Fiscal 2019 | F49: 3425 | G49: 24360 | H49: 343423 | I49: 0
B50: Expiring in Fiscal 2020 | F50: 14121 | G50: 7508 | H50: 23454 | I50: 0
B51: Expiring in Fiscal 2021 | F51: 0 | G51: 5390 | H51: 0 | I51: 98323
B52: Expiring in Fiscal 2022 | F52: 12321 | G52: 9655 | H52: 0 | I52: 0
B53: Expiring in Fiscal 2023 | F53: 9147 | G53: 16897 | H53: 0 | I53: 0
B54: Expiring Thereafter | F54: 4400 | G54: 21411 | H54: 0 | I54: 0
B57: Topic | C57: Income Tax | D57: text
B58: Start date | C58: 43830 | D58: date
B59: Periods | C59: 5 | D59: years

Sheet Tmp
A1: {=company} -> JAK Holdings Inc.
A2: {=topic} -> CFM Topic: Income Tax
A3: TMP SCHEDULE | F3: Constant | G3: Unit | H3: Total | J3: {=YEAR( EOMONTH( start_date, _xlfn.SEQUENCE( 1, periods, 0, 12 ) ) )} -> 2019 | K3: 2020 | L3: 2021 | M3: 2022 | N3: 2023
A50: End of schedule

Sheet CaseSolution
B1: JAK Holdings Inc.
B2: (in thousands, local currency as indicated)
F3: U.S. | G3: Canada | H3: Mexico | I3: Germany
F4: (USD) | G4: (CAD) | H4: (MXN) | I4: (EUR)
B5: Corporate Tax Rate | F5: =CaseData!F5 -> 0.256 | G5: =CaseData!G5 -> 0.265 | H5: =CaseData!H5 -> 0.31 | I5: =CaseData!I5 -> 0.326
B7: Exchange Rate (per USD) | F7: =CaseData!F7 -> 1 | G7: =CaseData!G7 -> 1.29 | H7: =CaseData!H7 -> 19.89 | I7: =CaseData!I7 -> 0.85
B8: Projected Accounting Pre-tax Income:
B9: Fiscal 2019 | F9: =CaseData!F9 -> 17840 | G9: =CaseData!G9 -> 27240 | H9: =CaseData!H9 -> 265571 | I9: =CaseData!I9 -> 29762
B10: Fiscal 2020 | F10: =CaseData!F10 -> 17062 | G10: =CaseData!G10 -> 26094 | H10: =CaseData!H10 -> 208746 | I10: =CaseData!I10 -> 30206
B11: Fiscal 2021 | F11: =CaseData!F11 -> 19307 | G11: =CaseData!G11 -> 27635 | H11: =CaseData!H11 -> 270027 | I11: =CaseData!I11 -> 32919
B12: Fiscal 2022 | F12: =CaseData!F12 -> 17314 | G12: =CaseData!G12 -> 24296 | H12: =CaseData!H12 -> 267759 | I12: =CaseData!I12 -> 31658
B13: Fiscal 2023 | F13: =CaseData!F13 -> 14576 | G13: =CaseData!G13 -> 29861 | H13: =CaseData!H13 -> 240888 | I13: =CaseData!I13 -> 29101
B15: Additions to Fixed Assets:
B16: Fiscal 2019 | F16: =CaseData!F16 -> 6244 | G16: =CaseData!G16 -> 9729 | H16: =CaseData!H16 -> 79671 | I16: =CaseData!I16 -> 16641
B17: Fiscal 2020 | F17: =CaseData!F17 -> 5388 | G17: =CaseData!G17 -> 16605 | H17: =CaseData!H17 -> 80287 | I17: =CaseData!I17 -> 8487
B18: Fiscal 2021 | F18: =CaseData!F18 -> 7723 | G18: =CaseData!G18 -> 9212 | H18: =CaseData!H18 -> 67507 | I18: =CaseData!I18 -> 9810
B19: Fiscal 2022 | F19: =CaseData!F19 -> 6733 | G19: =CaseData!G19 -> 9718 | H19: =CaseData!H19 -> 80328 | I19: =CaseData!I19 -> 19922
B20: Fiscal 2023 | F20: =CaseData!F20 -> 3836 | G20: =CaseData!G20 -> 16288 | H20: =CaseData!H20 -> 80296 | I20: =CaseData!I20 -> 16301
B22: Accounting Depreciation:
B23: Fiscal 2019 | F23: =CaseData!F23 -> 5432 | G23: =CaseData!G23 -> 7394 | H23: =CaseData!H23 -> 66127 | I23: =CaseData!I23 -> 14311
B24: Fiscal 2020 | F24: =CaseData!F24 -> 5595 | G24: =CaseData!G24 -> 7690 | H24: =CaseData!H24 -> 69433 | I24: =CaseData!I24 -> 14740
B25: Fiscal 2021 | F25: =CaseData!F25 -> 5875 | G25: =CaseData!G25 -> 7998 | H25: =CaseData!H25 -> 72905 | I25: =CaseData!I25 -> 15624
B26: Fiscal 2022 | F26: =CaseData!F26 -> 6169 | G26: =CaseData!G26 -> 8478 | H26: =CaseData!H26 -> 76550 | I26: =CaseData!I26 -> 16405
B27: Fiscal 2023 | F27: =CaseData!F27 -> 6416 | G27: =CaseData!G27 -> 8817 | H27: =CaseData!H27 -> 80378 | I27: =CaseData!I27 -> 16897
B29: Tax Basis in Depreciable Assets | F29: =CaseData!F29 -> 65510 | G29: =CaseData!G29 -> 85696 | H29: =CaseData!H29 -> 645400 | I29: =CaseData!I29 -> 163002
B31: Blended Tax Depreciation Rate | F31: =CaseData!F31 -> 0.123 | G31: =CaseData!G31 -> 0.142 | H31: =CaseData!H31 -> 0.165 | I31: =CaseData!I31 -> 0.156
B32: (% of beginning basis + additions to fixed assets)
B34: Expenses Not Deductible:
B35: Fiscal 2019 | F35: =CaseData!F35 -> 6742 | G35: =CaseData!G35 -> 0 | H35: =CaseData!H35 -> 0 | I35: =CaseData!I35 -> 10343
B36: Fiscal 2020 | F36: =CaseData!F36 -> 0 | G36: =CaseData!G36 -> 0 | H36: =CaseData!H36 -> 88951 | I36: =CaseData!I36 -> 0
B37: Fiscal 2021 | F37: =CaseData!F37 -> 0 | G37: =CaseData!G37 -> 0 | H37: =CaseData!H37 -> 0 | I37: =CaseData!I37 -> 12434
B38: Fiscal 2022 | F38: =CaseData!F38 -> 0 | G38: =CaseData!G38 -> 0 | H38: =CaseData!H38 -> 0 | I38: =CaseData!I38 -> 0
B39: Fiscal 2023 | F39: =CaseData!F39 -> 0 | G39: =CaseData!G39 -> 0 | H39: =CaseData!H39 -> 0 | I39: =CaseData!I39 -> 0
B41: Incremental Deductions for Tax Purposes:
B42: Fiscal 2019 | F42: =CaseData!F42 -> 5709 | G42: =CaseData!G42 -> 7355 | H42: =CaseData!H42 -> 69048 | I42: =CaseData!I42 -> 6036
B43: Fiscal 2020 | F43: =CaseData!F43 -> 5972 | G43: =CaseData!G43 -> 8350 | H43: =CaseData!H43 -> 50099 | I43: =CaseData!I43 -> 3551
B44: Fiscal 2021 | F44: =CaseData!F44 -> 2317 | G44: =CaseData!G44 -> 6080 | H44: =CaseData!H44 -> 62106 | I44: =CaseData!I44 -> 10537
B45: Fiscal 2022 | F45: =CaseData!F45 -> 3809 | G45: =CaseData!G45 -> 4373 | H45: =CaseData!H45 -> 26776 | I45: =CaseData!I45 -> 6970
B46: Fiscal 2023 | F46: =CaseData!F46 -> 3790 | G46: =CaseData!G46 -> 9854 | H46: =CaseData!H46 -> 24089 | I46: =CaseData!I46 -> 9642
B48: Tax Loss Carry Forwards:
B49: Expiring in Fiscal 2019 | F49: =CaseData!F49 -> 3425 | G49: =CaseData!G49 -> 24360 | H49: =CaseData!H49 -> 343423 | I49: =CaseData!I49 -> 0
B50: Expiring in Fiscal 2020 | F50: =CaseData!F50 -> 14121 | G50: =CaseData!G50 -> 7508 | H50: =CaseData!H50 -> 23454 | I50: =CaseData!I50 -> 0
B51: Expiring in Fiscal 2021 | F51: =CaseData!F51 -> 0 | G51: =CaseData!G51 -> 5390 | H51: =CaseData!H51 -> 0 | I51: =CaseData!I51 -> 98323
B52: Expiring in Fiscal 2022 | F52: =CaseData!F52 -> 12321 | G52: =CaseData!G52 -> 9655 | H52: =CaseData!H52 -> 0 | I52: =CaseData!I52 -> 0
B53: Expiring in Fiscal 2023 | F53: =CaseData!F53 -> 9147 | G53: =CaseData!G53 -> 16897 | H53: =CaseData!H53 -> 0 | I53: =CaseData!I53 -> 0
B54: Expiring Thereafter | F54: =CaseData!F54 -> 4400 | G54: =CaseData!G54 -> 21411 | H54: =CaseData!H54 -> 0 | I54: =CaseData!I54 -> 0
B57: Tax Schedules
B59: UNITED STATES (USD) | D59: Tax Rate | E59: =F5 -> 0.256 | F59: 2019 | G59: =F59+1 -> 2020 | H59: =G59+1 -> 2021 | I59: =H59+1 -> 2022 | J59: =I59+1 -> 2023
B60: Tax Calculation:
B61: Projected Accounting Pre-tax Income | F61: {=TRANSPOSE(F9:F13)} -> 17840 | G61: 17062 | H61: 19307 | I61: 17314 | J61: 14576
B62: Plus: Non-Deductible Expenses | F62: {=TRANSPOSE(F35:F39)} -> 6742 | G62: 0 | H62: 0 | I62: 0 | J62: 0
B63: Taxable Income for Accounting Purposes (A) | F63: =SUM(F61:F62) -> 24582 | G63: =SUM(G61:G62) -> 17062 | H63: =SUM(H61:H62) -> 19307 | I63: =SUM(I61:I62) -> 17314 | J63: =SUM(J61:J62) -> 14576
B65: Plus: Accounting Depreciation | F65: {=TRANSPOSE(F23:F27)} -> 5432 | G65: 5595 | H65: 5875 | I65: 6169 | J65: 6416
B66: Less: Tax Depreciation | F66: =F82 -> -8825.742 | G66: =G82 -> -8402.8997 | H66: =H82 -> -8319.2721 | I66: =I82 -> -8124.1606 | J66: =J82 -> -7596.7168
B67: Less: Incremental Deductions for Tax Purposes | F67: {=-TRANSPOSE(F42:F46)} -> -5709 | G67: -5972 | H67: -2317 | I67: -3809 | J67: -3790
B68: Taxable Income for Gov't Purposes before NOLs | F68: =SUM(F63:F67) -> 15479.258 | G68: =SUM(G63:G67) -> 8282.1003 | H68: =SUM(H63:H67) -> 14545.728 | I68: =SUM(I63:I67) -> 11549.839 | J68: =SUM(J63:J67) -> 9605.2832
B70: Less: NOLs Used | F70: =-F95 -> -15479.258 | G70: =-G95 -> -8282.1003 | H70: =-H95 -> -14545.728 | I70: =-I95 -> -5106.9138 | J70: =-J95 -> 0
B71: Taxable Income for Gov't Purposes After NOLs (B) | F71: =SUM(F68:F70) -> 0 | G71: =SUM(G68:G70) -> 0 | H71: =SUM(H68:H70) -> 0 | I71: =SUM(I68:I70) -> 6442.9256 | J71: =SUM(J68:J70) -> 9605.2832
B73: Tax Summary:
B74: Current Tax Expense (Rate * B) | F74: =$E$59*F71 -> 0 | G74: =$E$59*G71 -> 0 | H74: =$E$59*H71 -> 0 | I74: =$E$59*I71 -> 1649.389 | J74: =$E$59*J71 -> 2458.9525
B75: Deferred Tax Expense | F75: =F76-F74 -> 6292.992 | G75: =G76-G74 -> 4367.872 | H75: =H76-H74 -> 4942.592 | I75: =I76-I74 -> 2782.995 | J75: =J76-J74 -> 1272.5035
B76: Total Tax Expense (Rate * A) | F76: =$E$59*F63 -> 6292.992 | G76: =$E$59*G63 -> 4367.872 | H76: =$E$59*H63 -> 4942.592 | I76: =$E$59*I63 -> 4432.384 | J76: =$E$59*J63 -> 3731.456
B79: Tax Depreciation Schedule: | D79: Tax Dep'n Rate | E79: =F31 -> 0.123
B80: Opening Tax Basis in Depreciable Assets | F80: =E83 -> 65510 | G80: =F83 -> 62928.258 | H80: =G83 -> 59913.358 | I80: =H83 -> 59317.086 | J80: =I83 -> 57925.926
B81: Plus: Additions to Fixed Assets | F81: {=TRANSPOSE(F16:F20)} -> 6244 | G81: 5388 | H81: 7723 | I81: 6733 | J81: 3836
B82: Less: Tax Depreciation Claimed | F82: =-$E$79*SUM(F80:F81) -> -8825.742 | G82: =-$E$79*SUM(G80:G81) -> -8402.8997 | H82: =-$E$79*SUM(H80:H81) -> -8319.2721 | I82: =-$E$79*SUM(I80:I81) -> -8124.1606 | J82: =-$E$79*SUM(J80:J81) -> -7596.7168
B83: Closing Tax Basis in Depreciable Assets | E83: =F29 -> 65510 | F83: =SUM(F80:F82) -> 62928.258 | G83: =SUM(G80:G82) -> 59913.358 | H83: =SUM(H80:H82) -> 59317.086 | I83: =SUM(I80:I82) -> 57925.926 | J83: =SUM(J80:J82) -> 54165.209
B86: TLCF Schedule:
B87: Taxable Income for Gov't Purposes before NOLs | F87: =F68 -> 15479.258 | G87: =G68 -> 8282.1003 | H87: =H68 -> 14545.728 | I87: =I68 -> 11549.839 | J87: =J68 -> 9605.2832
B88: TLCFs Used
B89: {=TRANSPOSE(F59:J59)} -> 2019 | E89: =F49 -> 3425 | F89: =MIN(E98,F$87-SUM(F$88:F88)) -> 3425 | G89: =MIN(F98,G$87-SUM(G$88:G88)) -> 0 | H89: =MIN(G98,H$87-SUM(H$88:H88)) -> 0 | I89: =MIN(H98,I$87-SUM(I$88:I88)) -> 0 | J89: =MIN(I98,J$87-SUM(J$88:J88)) -> 0
B90: 2020 | E90: =F50 -> 14121 | F90: =MIN(E99,F$87-SUM(F$88:F89)) -> 12054.258 | G90: =MIN(F99,G$87-SUM(G$88:G89)) -> 2066.742 | H90: =MIN(G99,H$87-SUM(H$88:H89)) -> 0 | I90: =MIN(H99,I$87-SUM(I$88:I89)) -> 0 | J90: =MIN(I99,J$87-SUM(J$88:J89)) -> 0
B91: 2021 | E91: =F51 -> 0 | F91: =MIN(E100,F$87-SUM(F$88:F90)) -> 0 | G91: =MIN(F100,G$87-SUM(G$88:G90)) -> 0 | H91: =MIN(G100,H$87-SUM(H$88:H90)) -> 0 | I91: =MIN(H100,I$87-SUM(I$88:I90)) -> 0 | J91: =MIN(I100,J$87-SUM(J$88:J90)) -> 0
B92: 2022 | E92: =F52 -> 12321 | F92: =MIN(E101,F$87-SUM(F$88:F91)) -> 0 | G92: =MIN(F101,G$87-SUM(G$88:G91)) -> 6215.3583 | H92: =MIN(G101,H$87-SUM(H$88:H91)) -> 6105.6417 | I92: =MIN(H101,I$87-SUM(I$88:I91)) -> 0 | J92: =MIN(I101,J$87-SUM(J$88:J91)) -> 0
B93: 2023 | E93: =F53 -> 9147 | F93: =MIN(E102,F$87-SUM(F$88:F92)) -> 0 | G93: =MIN(F102,G$87-SUM(G$88:G92)) -> 0 | H93: =MIN(G102,H$87-SUM(H$88:H92)) -> 8440.0862 | I93: =MIN(H102,I$87-SUM(I$88:I92)) -> 706.9138 | J93: =MIN(I102,J$87-SUM(J$88:J92)) -> 0
B94: Expiring Thereafter | E94: =F54 -> 4400 | F94: =MIN(E103,F$87-SUM(F$88:F93)) -> 0 | G94: =MIN(F103,G$87-SUM(G$88:G93)) -> 0 | H94: =MIN(G103,H$87-SUM(H$88:H93)) -> 0 | I94: =MIN(H103,I$87-SUM(I$88:I93)) -> 4400 | J94: =MIN(I103,J$87-SUM(J$88:J93)) -> 0
B95: Total TLCFs Used | F95: =SUM(F89:F94) -> 15479.258 | G95: =SUM(G89:G94) -> 8282.1003 | H95: =SUM(H89:H94) -> 14545.728 | I95: =SUM(I89:I94) -> 5106.9138 | J95: =SUM(J89:J94) -> 0
B97: TLCFs Remaining
B98: =B89 -> 2019 | E98: =E89 -> 3425 | F98: =IF($B98<=F$59,0,E98-F89) -> 0 | G98: =IF($B98<=G$59,0,F98-G89) -> 0 | H98: =IF($B98<=H$59,0,G98-H89) -> 0 | I98: =IF($B98<=I$59,0,H98-I89) -> 0 | J98: =IF($B98<=J$59,0,I98-J89) -> 0
B99: =B90 -> 2020 | E99: =E90 -> 14121 | F99: =IF($B99<=F$59,0,E99-F90) -> 2066.742 | G99: =IF($B99<=G$59,0,F99-G90) -> 0 | H99: =IF($B99<=H$59,0,G99-H90) -> 0 | I99: =IF($B99<=I$59,0,H99-I90) -> 0 | J99: =IF($B99<=J$59,0,I99-J90) -> 0
B100: =B91 -> 2021 | E100: =E91 -> 0 | F100: =IF($B100<=F$59,0,E100-F91) -> 0 | G100: =IF($B100<=G$59,0,F100-G91) -> 0 | H100: =IF($B100<=H$59,0,G100-H91) -> 0 | I100: =IF($B100<=I$59,0,H100-I91) -> 0 | J100: =IF($B100<=J$59,0,I100-J91) -> 0
B101: =B92 -> 2022 | E101: =E92 -> 12321 | F101: =IF($B101<=F$59,0,E101-F92) -> 12321 | G101: =IF($B101<=G$59,0,F101-G92) -> 6105.6417 | H101: =IF($B101<=H$59,0,G101-H92) -> 0 | I101: =IF($B101<=I$59,0,H101-I92) -> 0 | J101: =IF($B101<=J$59,0,I101-J92) -> 0
B102: =B93 -> 2023 | E102: =E93 -> 9147 | F102: =IF($B102<=F$59,0,E102-F93) -> 9147 | G102: =IF($B102<=G$59,0,F102-G93) -> 9147 | H102: =IF($B102<=H$59,0,G102-H93) -> 706.9138 | I102: =IF($B102<=I$59,0,H102-I93) -> 0 | J102: =IF($B102<=J$59,0,I102-J93) -> 0
B103: =B94 -> Expiring Thereafter | E103: =E94 -> 4400 | F103: =IF($B103<=F$59,0,E103-F94) -> 4400 | G103: =IF($B103<=G$59,0,F103-G94) -> 4400 | H103: =IF($B103<=H$59,0,G103-H94) -> 4400 | I103: =IF($B103<=I$59,0,H103-I94) -> 0 | J103: =IF($B103<=J$59,0,I103-J94) -> 0
B104: Total TLCFs Remaining | F104: =SUM(F98:F103) -> 27934.742 | G104: =SUM(G98:G103) -> 19652.642 | H104: =SUM(H98:H103) -> 5106.9138 | I104: =SUM(I98:I103) -> 0 | J104: =SUM(J98:J103) -> 0
B107: CANADA (CAD) | D107: Tax Rate | E107: =G5 -> 0.265 | F107: =F59 -> 2019 | G107: =G59 -> 2020 | H107: =H59 -> 2021 | I107: =I59 -> 2022 | J107: =J59 -> 2023
B108: Tax Calculation:
B109: Projected Accounting Pre-tax Income | F109: {=TRANSPOSE(G9:G13)} -> 27240 | G109: 26094 | H109: 27635 | I109: 24296 | J109: 29861
B110: Plus: Non-Deductible Expenses | F110: {=TRANSPOSE(G35:G39)} -> 0 | G110: 0 | H110: 0 | I110: 0 | J110: 0
B111: Taxable Income for Accounting Purposes (A) | F111: =SUM(F109:F110) -> 27240 | G111: =SUM(G109:G110) -> 26094 | H111: =SUM(H109:H110) -> 27635 | I111: =SUM(I109:I110) -> 24296 | J111: =SUM(J109:J110) -> 29861
B113: Plus: Accounting Depreciation | F113: {=TRANSPOSE(G23:G27)} -> 7394 | G113: 7690 | H113: 7998 | I113: 8478 | J113: 8817
B114: Less: Tax Depreciation | F114: =F130 -> -13550.35 | G114: =G130 -> -13984.11 | H114: =H130 -> -13306.471 | I114: =I130 -> -12796.908 | J114: =J130 -> -13292.643
B115: Less: Incremental Deductions for Tax Purposes | F115: {=-TRANSPOSE(G42:G46)} -> -7355 | G115: -8350 | H115: -6080 | I115: -4373 | J115: -9854
B116: Taxable Income for Gov't Purposes before NOLs | F116: =SUM(F111:F115) -> 13728.65 | G116: =SUM(G111:G115) -> 11449.89 | H116: =SUM(H111:H115) -> 16246.529 | I116: =SUM(I111:I115) -> 15604.092 | J116: =SUM(J111:J115) -> 15531.357
B118: Less: NOLs Used | F118: =-F143 -> -13728.65 | G118: =-G143 -> -11449.89 | H118: =-H143 -> -16246.529 | I118: =-I143 -> -15604.092 | J118: =-J143 -> -15531.357
B119: Taxable Income for Gov't Purposes After NOLs (B) | F119: =SUM(F116:F118) -> 0 | G119: =SUM(G116:G118) -> 0 | H119: =SUM(H116:H118) -> 0 | I119: =SUM(I116:I118) -> 0 | J119: =SUM(J116:J118) -> 0
B121: Tax Summary:
B122: Current Tax Expense (Rate * B) | F122: =$E$107*F119 -> 0 | G122: =$E$107*G119 -> 0 | H122: =$E$107*H119 -> 0 | I122: =$E$107*I119 -> 0 | J122: =$E$107*J119 -> 0
B123: Deferred Tax Expense | F123: =F124-F122 -> 7218.6 | G123: =G124-G122 -> 6914.91 | H123: =H124-H122 -> 7323.275 | I123: =I124-I122 -> 6438.44 | J123: =J124-J122 -> 7913.165
B124: Total Tax Expense (Rate * A) | F124: =$E$107*F111 -> 7218.6 | G124: =$E$107*G111 -> 6914.91 | H124: =$E$107*H111 -> 7323.275 | I124: =$E$107*I111 -> 6438.44 | J124: =$E$107*J111 -> 7913.165
...
