Workbook
Name company: CaseData!$B$2
Name periods: CaseData!$C$70
Name start_date: CaseData!$C$69
Name topic: "CFM Topic: " & CaseData!$C$68

Sheet Calculations
A1: {=company} -> BCS Holdings Inc.
A2: {=topic} -> CFM Topic: Income Tax
A3: CALCULATIONS SCHEDULE | F3: Constant | G3: Unit | H3: Total | J3: {=YEAR( EOMONTH( start_date, _xlfn.SEQUENCE( 1, periods, 0, 12 ) ) )} -> 2023 | K3: 2024 | L3: 2025 | M3: 2026 | N3: 2027
E5: Country | F5: U.S.
A7: Tax schedule
E9: Projected Accounting Pre-tax Income | G9: USD m | J9: {=_xlfn.LET( _xlpm.values, CaseData!$F$11:$H$15, _xlpm.years, VALUE( RIGHT( CaseData!$B$11:$B$15, 4 ) ), _xlpm.countries, CaseData!$F$4:$I$4, _xlpm.current_year,_xlfn.ANCHORARRAY( $J$3), _xlpm.current_country, $F$5, _xlpm.fx_rate, INDEX( CaseData!$F$8:$I$8, 1, MATCH( _xlpm.current_country, _xlpm.countries, 0 ) ), _xlpm.projected, INDEX( _xlpm.values, MATCH( _xlpm.current_year, _xlpm.years, 0 ), MATCH( _xlpm.current_country, _xlpm.countries, 0 ) ), _xlpm.projected / _xlpm.fx_rate )} -> 26760 | K9: 25593 | L9: 28960.5 | M9: 25971 | N9: 21864
D10: plus | E10: Non deductible expenses | G10: {=$G$9:$G$9} -> USD m | J10: {=_xlfn.LET( _xlpm.values, CaseData!$F$37:$H$41, _xlpm.years, VALUE( RIGHT( CaseData!$B$11:$B$15, 4 ) ), _xlpm.countries, CaseData!$F$4:$I$4, _xlpm.current_year,_xlfn.ANCHORARRAY( $J$3), _xlpm.current_country, $F$5, _xlpm.fx_rate, INDEX( CaseData!$F$8:$I$8, 1, MATCH( _xlpm.current_country, _xlpm.countries, 0 ) ), _xlpm.projected, INDEX( _xlpm.values, MATCH( _xlpm.current_year, _xlpm.years, 0 ), MATCH( _xlpm.current_country, _xlpm.countries, 0 ) ), _xlpm.projected / _xlpm.fx_rate )} -> 10113 | K10: 0 | L10: 0 | M10: 0 | N10: 0
E11: Taxable Income for Accounting Purposes (A) | G11: {=$G$9:$G$9} -> USD m | J11: =SUM(J9:J10) -> 36873 | K11: =SUM(K9:K10) -> 25593 | L11: =SUM(L9:L10) -> 28960.5 | M11: =SUM(M9:M10) -> 25971 | N11: =SUM(N9:N10) -> 21864
D13: plus | E13: Accounting depreciation | G13: {=$G$9:$G$9} -> USD m | J13: {=_xlfn.LET( _xlpm.values, CaseData!$F$25:$H$29, _xlpm.years, VALUE( RIGHT( CaseData!$B$11:$B$15, 4 ) ), _xlpm.countries, CaseData!$F$4:$I$4, _xlpm.current_year,_xlfn.ANCHORARRAY( $J$3), _xlpm.current_country, $F$5, _xlpm.fx_rate, INDEX( CaseData!$F$8:$I$8, 1, MATCH( _xlpm.current_country, _xlpm.countries, 0 ) ), _xlpm.projected, INDEX( _xlpm.values, MATCH( _xlpm.current_year, _xlpm.years, 0 ), MATCH( _xlpm.current_country, _xlpm.countries, 0 ) ), _xlpm.projected / _xlpm.fx_rate )} -> 8148 | K13: 8392.5 | L13: 8812.5 | M13: 9253.5 | N13: 9624
D14: minus | E14: Taxable depreciation | G14: USD m | J14: =J32 -> 13238.613 | K14: =K32 -> 12604.35 | L14: =L32 -> 12478.908 | M14: =M32 -> 12186.241 | N14: =N32 -> 11395.075
D15: minus | E15: Incremental deduction for tax purposes | G15: USD m | J15: {=_xlfn.LET( _xlpm.values, CaseData!$F$44:$H$48, _xlpm.years, VALUE( RIGHT( CaseData!$B$11:$B$15, 4 ) ), _xlpm.countries, CaseData!$F$4:$I$4, _xlpm.current_year,_xlfn.ANCHORARRAY( $J$3), _xlpm.current_country, $F$5, _xlpm.fx_rate, INDEX( CaseData!$F$8:$I$8, 1, MATCH( _xlpm.current_country, _xlpm.countries, 0 ) ), _xlpm.projected, INDEX( _xlpm.values, MATCH( _xlpm.current_year, _xlpm.years, 0 ), MATCH( _xlpm.current_country, _xlpm.countries, 0 ) ), _xlpm.projected / _xlpm.fx_rate )} -> 8563.5 | K15: 8958 | L15: 3475.5 | M15: 5713.5 | N15: 5685
D16: minus | E16: Qualifying Expenses | G16: USD m | J16: =J39 -> 3500 | K16: =K39 -> 3780 | L16: =L39 -> 4082.5 | M16: =M39 -> 4409 | N16: =N39 -> 4761.5
E17: Taxable Income for Tax Purposes before NOL | G17: USD m | J17: =J11 + J13 - J14 - J15 - J16 -> 19718.887 | K17: =K11 + K13 - K14 - K15 - K16 -> 8643.1504 | L17: =L11 + L13 - L14 - L15 - L16 -> 17736.092 | M17: =M11 + M13 - M14 - M15 - M16 -> 12915.759 | N17: =N11 + N13 - N14 - N15 - N16 -> 9646.4247
D19: minus | E19: Utilization of Tax Loss Carry Forwards | G19: USD m | J19: =J43 -> 19718.887 | K19: =K43 -> 8643.1504 | L19: =L43 -> 17736.092 | M19: =M43 -> 12915.759 | N19: =N43 -> 6600
E20: Taxable Income for Tax Purposes after NOL | G20: USD m | J20: =J17 - J19 -> 0 | K20: =K17 - K19 -> 0 | L20: =L17 - L19 -> 0 | M20: =M17 - M19 -> 0 | N20: =N17 - N19 -> 3046.4247
E23: Current corporate tax rate | F23: {=_xlfn.LET( _xlpm.countries, CaseData!$F$4:$H$4, _xlpm.current_country, $F$5, _xlfn.XLOOKUP( _xlpm.current_country, _xlpm.countries, CaseData!$F$6:$H$6, 0, 0 ) )} -> 0.21
E24: Current tax | G24: USD m | J24: =$F$23 * J20 -> 0 | K24: =$F$23 * K20 -> 0 | L24: =$F$23 * L20 -> 0 | M24: =$F$23 * M20 -> 0 | N24: =$F$23 * N20 -> 639.74919
E25: Deferred tax | G25: USD m | J25: =J26 - J24 -> 7743.33 | K25: =K26 - K24 -> 5374.53 | L25: =L26 - L24 -> 6081.705 | M25: =M26 - M24 -> 5453.91 | N25: =N26 - N24 -> 3951.6908
E26: Tax | G26: USD m | J26: =$F$23 * J11 -> 7743.33 | K26: =$F$23 * K11 -> 5374.53 | L26: =$F$23 * L11 -> 6081.705 | M26: =$F$23 * M11 -> 5453.91 | N26: =$F$23 * N11 -> 4591.44
A28: Taxable depreciation
E30: Tax Basis in Depreciable Assets opening balance | G30: {=$G$9:$G$9} -> USD m | J30: {=_xlfn.LET( _xlpm.countries, CaseData!$F$4:$H$4, _xlpm.current_country, $F$5, _xlfn.XLOOKUP( _xlpm.current_country, _xlpm.countries, CaseData!$F$31:$H$31, 0, 0 ) )} -> 98265 | K30: =J33 -> 94392.387 | L30: =K33 -> 89870.037 | M30: =L33 -> 88975.629 | N30: =M33 -> 86888.888
D31: plus | E31: Addition to fixed assets | G31: USD m | J31: {=_xlfn.LET( _xlpm.values, CaseData!$F$18:$H$22, _xlpm.years, VALUE( RIGHT( CaseData!$B$11:$B$15, 4 ) ), _xlpm.countries, CaseData!$F$4:$I$4, _xlpm.current_year,_xlfn.ANCHORARRAY( $J$3), _xlpm.current_country, $F$5, _xlpm.fx_rate, INDEX( CaseData!$F$8:$I$8, 1, MATCH( _xlpm.current_country, _xlpm.countries, 0 ) ), _xlpm.projected, INDEX( _xlpm.values, MATCH( _xlpm.current_year, _xlpm.years, 0 ), MATCH( _xlpm.current_country, _xlpm.countries, 0 ) ), _xlpm.projected / _xlpm.fx_rate )} -> 9366 | K31: 8082 | L31: 11584.5 | M31: 10099.5 | N31: 5754
D32: minus | E32: Taxable Depreciation at blended rate | F32: {=_xlfn.LET( _xlpm.countries, CaseData!$F$4:$H$4, _xlpm.current_country, $F$5, _xlfn.XLOOKUP( _xlpm.current_country, _xlpm.countries, CaseData!$F$33:$H$33, 0, 0 ) )} -> 0.123 | G32: USD m | J32: =$F$32 * SUM( J30:J31 ) -> 13238.613 | K32: =$F$32 * SUM( K30:K31 ) -> 12604.35 | L32: =$F$32 * SUM( L30:L31 ) -> 12478.908 | M32: =$F$32 * SUM( M30:M31 ) -> 12186.241 | N32: =$F$32 * SUM( N30:N31 ) -> 11395.075
E33: Tax Basis in Depreciable Assets closing balance | G33: USD m | J33: =J30 + J31 - J32 -> 94392.387 | K33: =K30 + K31 - K32 -> 89870.037 | L33: =L30 + L31 - L32 -> 88975.629 | M33: =M30 + M31 - M32 -> 86888.888 | N33: =N30 + N31 - N32 -> 81247.813
A35: Qualifying expenses
E37: Qualifying expenses (not capped) | G37: {=$G$9:$G$9} -> USD m | J37: {=_xlfn.LET( _xlpm.values, CaseData!$F$54:$H$58, _xlpm.years, VALUE( RIGHT( CaseData!$B$11:$B$15, 4 ) ), _xlpm.countries, CaseData!$F$4:$I$4, _xlpm.current_year,_xlfn.ANCHORARRAY( $J$3), _xlpm.current_country, $F$5, _xlpm.fx_rate, INDEX( CaseData!$F$8:$I$8, 1, MATCH( _xlpm.current_country, _xlpm.countries, 0 ) ), _xlpm.projected, INDEX( _xlpm.values, MATCH( _xlpm.current_year, _xlpm.years, 0 ), MATCH( _xlpm.current_country, _xlpm.countries, 0 ) ), _xlpm.projected / _xlpm.fx_rate )} -> 3500 | K37: 3780 | L37: 4082.5 | M37: 4409 | N37: 4761.5
E38: Qualifying Expenses: % of Expenditure Deductible | F38: {=_xlfn.LET( _xlpm.countries, CaseData!$F$4:$H$4, _xlpm.current_country, $F$5, _xlfn.XLOOKUP( _xlpm.current_country, _xlpm.countries, CaseData!$F$50:$H$50, 0, 0 ) )} -> 1 | G38: % | J38: =J37 * $F$38 -> 3500 | K38: =K37 * $F$38 -> 3780 | L38: =L37 * $F$38 -> 4082.5 | M38: =M37 * $F$38 -> 4409 | N38: =N37 * $F$38 -> 4761.5
E39: Qualifying Expenses: Maximum Dollar Deductible | F39: {=_xlfn.LET( _xlpm.countries, CaseData!$F$4:$H$4, _xlpm.current_country, $F$5, _xlfn.XLOOKUP( _xlpm.current_country, _xlpm.countries, CaseData!$F$51:$H$51, 0, 0 ) )} -> No limit | G39: {=$G$9:$G$9} -> USD m | J39: =IF( $F$39 = "No limit", J$38, MIN( J38, $F$39 ) ) -> 3500 | K39: =IF( $F$39 = "No limit", K$38, MIN( K38, $F$39 ) ) -> 3780 | L39: =IF( $F$39 = "No limit", L$38, MIN( L38, $F$39 ) ) -> 4082.5 | M39: =IF( $F$39 = "No limit", M$38, MIN( M38, $F$39 ) ) -> 4409 | N39: =IF( $F$39 = "No limit", N$38, MIN( N38, $F$39 ) ) -> 4761.5
A41: Tax Loss Carry Forward
E43: Utilization of Tax Loss Carry Forwards | G43: USD m | J43: =MIN( J17, SUM( I54:I59 ) ) -> 19718.887 | K43: =MIN( K17, SUM( J54:J59 ) ) -> 8643.1504 | L43: =MIN( L17, SUM( K54:K59 ) ) -> 17736.092 | M43: =MIN( M17, SUM( L54:L59 ) ) -> 12915.759 | N43: =MIN( N17, SUM( M54:M59 ) ) -> 6600
E44: 45291 | G44: USD m | J44: =MIN( J43, I54 ) -> 5137.5 | K44: =MIN( K43, J54 ) -> 0 | L44: =MIN( L43, K54 ) -> 0 | M44: =MIN( M43, L54 ) -> 0 | N44: =MIN( N43, M54 ) -> 0
E45: 45657 | G45: USD m | J45: =MIN( I55, J$43 - SUM( J$44:J44 ) ) -> 14581.387 | K45: =MIN( J55, K$43 - SUM( K$44:K44 ) ) -> 6600.113 | L45: =MIN( K55, L$43 - SUM( L$44:L44 ) ) -> 0 | M45: =MIN( L55, M$43 - SUM( M$44:M44 ) ) -> 0 | N45: =MIN( M55, N$43 - SUM( N$44:N44 ) ) -> 0
E46: 46022 | G46: USD m | J46: =MIN( I56, J$43 - SUM( J$44:J45 ) ) -> 0 | K46: =MIN( J56, K$43 - SUM( K$44:K45 ) ) -> 0 | L46: =MIN( K56, L$43 - SUM( L$44:L45 ) ) -> 0 | M46: =MIN( L56, M$43 - SUM( M$44:M45 ) ) -> 0 | N46: =MIN( M56, N$43 - SUM( N$44:N45 ) ) -> 0
E47: 46387 | G47: USD m | J47: =MIN( I57, J$43 - SUM( J$44:J46 ) ) -> 0 | K47: =MIN( J57, K$43 - SUM( K$44:K46 ) ) -> 2043.0374 | L47: =MIN( K57, L$43 - SUM( L$44:L46 ) ) -> 16438.463 | M47: =MIN( L57, M$43 - SUM( M$44:M46 ) ) -> 0 | N47: =MIN( M57, N$43 - SUM( N$44:N46 ) ) -> 0
E48: 46752 | G48: USD m | J48: =MIN( I58, J$43 - SUM( J$44:J47 ) ) -> 0 | K48: =MIN( J58, K$43 - SUM( K$44:K47 ) ) -> 0 | L48: =MIN( K58, L$43 - SUM( L$44:L47 ) ) -> 1297.6293 | M48: =MIN( L58, M$43 - SUM( M$44:M47 ) ) -> 12422.871 | N48: =MIN( M58, N$43 - SUM( N$44:N47 ) ) -> 0
E49: Expiring thereafter | G49: USD m | J49: =MIN( I59, J$43 - SUM( J$44:J48 ) ) -> 0 | K49: =MIN( J59, K$43 - SUM( K$44:K48 ) ) -> 0 | L49: =MIN( K59, L$43 - SUM( L$44:L48 ) ) -> 0 | M49: =MIN( L59, M$43 - SUM( M$44:M48 ) ) -> 492.8884 | N49: =MIN( M59, N$43 - SUM( N$44:N48 ) ) -> 6600
J52: {=YEAR( EOMONTH( start_date, _xlfn.SEQUENCE( 1, periods, 0, 12 ) ) )} -> 2023 | K52: 2024 | L52: 2025 | M52: 2026 | N52: 2027
E53: Tax Loss Carry Forwards Ending Balances
E54: 45291 | G54: USD m | I54: {=_xlfn.LET( _xlpm.values, CaseData!$F$61:$H$66, _xlpm.years, VALUE( RIGHT( CaseData!$B$11:$B$15, 4 ) ), _xlpm.countries, CaseData!$F$4:$H$4, _xlpm.current_year,_xlfn.ANCHORARRAY( $J$3), _xlpm.current_country, $F$5, _xlpm.fx_rate, INDEX( CaseData!$F$8:$H$8, 1, MATCH( _xlpm.current_country, _xlpm.countries, 0 ) ), _xlpm.projected, INDEX( _xlpm.values, MATCH( _xlpm.current_year, _xlpm.years, 0 ), MATCH( _xlpm.current_country, _xlpm.countries, 0 ) ), TRANSPOSE( _xlpm.projected / _xlpm.fx_rate ) )} -> 5137.5 | J54: =IF( J$52 < $E54, I54 - J44, 0 ) -> 0 | K54: =IF( K$52 < $E54, J54 - K44, 0 ) -> 0 | L54: =IF( L$52 < $E54, K54 - L44, 0 ) -> 0 | M54: =IF( M$52 < $E54, L54 - M44, 0 ) -> 0 | N54: =IF( N$52 < $E54, M54 - N44, 0 ) -> 0
E55: 45657 | G55: USD m | I55: 21181.5 | J55: =IF( J$52 < $E55, I55 - J45, 0 ) -> 6600.113 | K55: =IF( K$52 < $E55, J55 - K45, 0 ) -> 0 | L55: =IF( L$52 < $E55, K55 - L45, 0 ) -> 0 | M55: =IF( M$52 < $E55, L55 - M45, 0 ) -> 0 | N55: =IF( N$52 < $E55, M55 - N45, 0 ) -> 0
E56: 46022 | G56: USD m | I56: 0 | J56: =IF( J$52 < $E56, I56 - J46, 0 ) -> 0 | K56: =IF( K$52 < $E56, J56 - K46, 0 ) -> 0 | L56: =IF( L$52 < $E56, K56 - L46, 0 ) -> 0 | M56: =IF( M$52 < $E56, L56 - M46, 0 ) -> 0 | N56: =IF( N$52 < $E56, M56 - N46, 0 ) -> 0
E57: 46387 | G57: USD m | I57: 18481.5 | J57: =IF( J$52 < $E57, I57 - J47, 0 ) -> 18481.5 | K57: =IF( K$52 < $E57, J57 - K47, 0 ) -> 16438.463 | L57: =IF( L$52 < $E57, K57 - L47, 0 ) -> 0 | M57: =IF( M$52 < $E57, L57 - M47, 0 ) -> 0 | N57: =IF( N$52 < $E57, M57 - N47, 0 ) -> 0
E58: 46752 | G58: USD m | I58: 13720.5 | J58: =IF( J$52 < $E58, I58 - J48, 0 ) -> 13720.5 | K58: =IF( K$52 < $E58, J58 - K48, 0 ) -> 13720.5 | L58: =IF( L$52 < $E58, K58 - L48, 0 ) -> 12422.871 | M58: =IF( M$52 < $E58, L58 - M48, 0 ) -> 0 | N58: =IF( N$52 < $E58, M58 - N48, 0 ) -> 0
E59: Expiring thereafter | G59: USD m | I59: {=_xlfn.LET( _xlpm.countries, CaseData!$F$4:$H$4, _xlpm.current_country, $F$5, _xlpm.expiring_after, _xlfn.XLOOKUP( _xlpm.current_country, _xlpm.countries, CaseData!$F$66:$H$66, 0, 0 ), _xlpm.fx_rate, _xlfn.XLOOKUP( _xlpm.current_country, _xlpm.countries, CaseData!$F$8:$H$8, 0, 0 ), _xlfn.SEQUENCE( 1, periods + 1, _xlpm.expiring_after / _xlpm.fx_rate, 0 ) )} -> 6600 | J59: 6600 | K59: 6600 | L59: 6600 | M59: 6600 | N59: 6600
A62: Consolidation
E64: Current Tax in USD >> | J64: =J24 -> 0 | K64: =K24 -> 0 | L64: =L24 -> 0 | M64: =M24 -> 0 | N64: =N24 -> 639.74919
I65: {=TRANSPOSE( CaseData!$F$4:$H$4 )} -> U.S. | J65: 0 | K65: 0 | L65: 0 | M65: 0 | N65: 639.74919
I66: Canada | J66: 0 | K66: 0 | L66: 0 | M66: 0 | N66: 0
I67: Italy | J67: 0 | K67: 0 | L67: 0 | M67: 0 | N67: 0
E70: Deferred Tax in USD >> | J70: =J25 -> 7743.33 | K70: =K25 -> 5374.53 | L70: =L25 -> 6081.705 | M70: =M25 -> 5453.91 | N70: =N25 -> 3951.6908
I71: {=TRANSPOSE( CaseData!$F$4:$H$4 )} -> U.S. | J71: 7743.33 | K71: 5374.53 | L71: 6081.705 | M71: 5453.91 | N71: 3951.6908
I72: Canada | J72: 8662.32 | K72: 8297.892 | L72: 8787.93 | M72: 7726.128 | N72: 9495.798
I73: Italy | J73: 14437.8 | K73: 10874.16 | L73: 16327.08 | M73: 11396.88 | N73: 10476.36
E76: Total Tax in USD >> | J76: =J26 -> 7743.33 | K76: =K26 -> 5374.53 | L76: =L26 -> 6081.705 | M76: =M26 -> 5453.91 | N76: =N26 -> 4591.44
I77: {=TRANSPOSE( CaseData!$F$4:$H$4 )} -> U.S. | J77: 7743.33 | K77: 5374.53 | L77: 6081.705 | M77: 5453.91 | N77: 4591.44
I78: Canada | J78: 8662.32 | K78: 8297.892 | L78: 8787.93 | M78: 7726.128 | N78: 9495.798
I79: Italy | J79: 14437.8 | K79: 10874.16 | L79: 16327.08 | M79: 11396.88 | N79: 10476.36
A81: End of schedule

Sheet CaseData
B2: BCS Holdings Inc.
B3: (in thousands, local currency as indicated)
F4: U.S. | G4: Canada | H4: Italy
F5: (USD) | G5: (CAD) | H5: (EUR)
B6: Corporate Tax Rate | F6: 0.21 | G6: 0.265 | H6: 0.24
B8: Exchange Rate (per USD) | F8: 1 | G8: 1.25 | H8: 1
B10: Projected Accounting Pre-tax Income:
B11: Fiscal 2023 | F11: 26760 | G11: 40860 | H11: 44643
B12: Fiscal 2024 | F12: 25593 | G12: 39141 | H12: 45309
B13: Fiscal 2025 | F13: 28960.5 | G13: 41452.5 | H13: 49378.5
B14: Fiscal 2026 | F14: 25971 | G14: 36444 | H14: 47487
B15: Fiscal 2027 | F15: 21864 | G15: 44791.5 | H15: 43651.5
B17: Additions to Fixed Assets:
B18: Fiscal 2023 | F18: 9366 | G18: 14593.5 | H18: 24961.5
B19: Fiscal 2024 | F19: 8082 | G19: 24907.5 | H19: 12730.5
B20: Fiscal 2025 | F20: 11584.5 | G20: 13818 | H20: 14715
B21: Fiscal 2026 | F21: 10099.5 | G21: 14577 | H21: 29883
B22: Fiscal 2027 | F22: 5754 | G22: 24432 | H22: 24451.5
B24: Accounting Depreciation:
B25: Fiscal 2023 | F25: 8148 | G25: 11091 | H25: 21466.5
B26: Fiscal 2024 | F26: 8392.5 | G26: 11535 | H26: 22110
B27: Fiscal 2025 | F27: 8812.5 | G27: 11997 | H27: 23436
B28: Fiscal 2026 | F28: 9253.5 | G28: 12717 | H28: 24607.5
B29: Fiscal 2027 | F29: 9624 | G29: 13225.5 | H29: 25345.5
B31: Tax Basis in Depreciable Assets | F31: 98265 | G31: 128544 | H31: 244503
B33: Blended Tax Depreciation Rate | F33: 0.123 | G33: 0.142 | H33: 0.156
B34: (% of beginning basis + additions to fixed assets)
B36: Expenses Not Deductible:
B37: Fiscal 2023 | F37: 10113 | G37: 0 | H37: 15514.5
B38: Fiscal 2024 | F38: 0 | G38: 0 | H38: 0
B39: Fiscal 2025 | F39: 0 | G39: 0 | H39: 18651
B40: Fiscal 2026 | F40: 0 | G40: 0 | H40: 0
B41: Fiscal 2027 | F41: 0 | G41: 0 | H41: 0
B43: Incremental Deductions for Tax Purposes:
B44: Fiscal 2023 | F44: 8563.5 | G44: 11032.5 | H44: 9054
B45: Fiscal 2024 | F45: 8958 | G45: 12525 | H45: 5326.5
B46: Fiscal 2025 | F46: 3475.5 | G46: 9120 | H46: 15805.5
B47: Fiscal 2026 | F47: 5713.5 | G47: 6559.5 | H47: 10455
B48: Fiscal 2027 | F48: 5685 | G48: 14781 | H48: 14463
B50: Qualifying Expenses: % of Expenditure Deductible | F50: 1 | G50: 0.35 | H50: 0.2
B51: Qualifying Expenses: Maximum Dollar Deductible | F51: No limit | G51: 3000 | H51: 4000
B53: Qualifying Expenses
B54: Fiscal 2023 | F54: 3500 | G54: 7500 | H54: 16750
B55: Fiscal 2024 | F55: 3780 | G55: 8100 | H55: 18090
B56: Fiscal 2025 | F56: 4082.5 | G56: 8748 | H56: 19537
B57: Fiscal 2026 | F57: 4409 | G57: 9447 | H57: 21100
B58: Fiscal 2027 | F58: 4761.5 | G58: 10203.5 | H58: 22788.5
B60: Accumulated Tax Losses:
B61: Expiring in Fiscal 2023 | F61: 5137.5 | G61: 36540 | H61: 0
B62: Expiring in Fiscal 2024 | F62: 21181.5 | G62: 11262 | H62: 0
B63: Expiring in Fiscal 2025 | F63: 0 | G63: 8085 | H63: 147484.5
B64: Expiring in Fiscal 2026 | F64: 18481.5 | G64: 14482.5 | H64: 0
B65: Expiring in Fiscal 2027 | F65: 13720.5 | G65: 25345.5 | H65: 0
B66: Expiring Thereafter | F66: 6600 | G66: 32116.5 | H66: 0
B68: Topic | C68: Income Tax | D68: text
B69: Start date | C69: 45291 | D69: date
B70: Periods | C70: 5 | D70: years

Sheet CaseSolution
B2: =CaseData!B2 -> BCS Holdings Inc.
B3: =CaseData!B3 -> (in thousands, local currency as indicated)
B5: Answer Table
B7: Tasks to Complete / Questions:
A8: a) | B8: See below
A9: b) | B9: Use all US tax losses? | C9: If so, when?
B10: =IF(SUM(E66:E71)=SUM(F66:J71)=TRUE,"Yes","No") -> Yes | C10: =IF(B10="Yes",INDEX($F$21:$J$21,MATCH(0,$F$81:$J$81,0)),"N/A") -> 2027
A11: c) | B11: Effective tax rate in 2025:
B12: =H241 -> 0.27978866
A13: d) | B13: Total income tax expense in 2026:
B14: =I233 -> 24576.918
A15: e) | B15: Deferred income tax expense in 2027:
B16: =J227 -> 19350.192
B19: Tax Schedules
F20: =CaseData!B11 -> Fiscal 2023 | G20: =CaseData!B12 -> Fiscal 2024 | H20: =CaseData!B13 -> Fiscal 2025 | I20: =CaseData!B14 -> Fiscal 2026 | J20: =CaseData!B15 -> Fiscal 2027
B21: UNITED STATES (USD) | D21: Tax Rate | E21: =CaseData!F6 -> 0.21 | F21: =_xlfn.NUMBERVALUE(RIGHT(F20,4)) -> 2023 | G21: =_xlfn.NUMBERVALUE(RIGHT(G20,4)) -> 2024 | H21: =_xlfn.NUMBERVALUE(RIGHT(H20,4)) -> 2025 | I21: =_xlfn.NUMBERVALUE(RIGHT(I20,4)) -> 2026 | J21: =_xlfn.NUMBERVALUE(RIGHT(J20,4)) -> 2027
B22: Tax Calculation:
B23: Projected Accounting Pre-tax Income | F23: =INDEX(CaseData!$F$11:$F$15,MATCH(F$20,CaseData!$B$11:$B$15,0)) -> 26760 | G23: =INDEX(CaseData!$F$11:$F$15,MATCH(G$20,CaseData!$B$11:$B$15,0)) -> 25593 | H23: =INDEX(CaseData!$F$11:$F$15,MATCH(H$20,CaseData!$B$11:$B$15,0)) -> 28960.5 | I23: =INDEX(CaseData!$F$11:$F$15,MATCH(I$20,CaseData!$B$11:$B$15,0)) -> 25971 | J23: =INDEX(CaseData!$F$11:$F$15,MATCH(J$20,CaseData!$B$11:$B$15,0)) -> 21864
B24: Plus: Non-Deductible Expenses | F24: =INDEX(CaseData!$F$37:$F$41,MATCH(F$20,CaseData!$B$37:$B$41,0)) -> 10113 | G24: =INDEX(CaseData!$F$37:$F$41,MATCH(G$20,CaseData!$B$37:$B$41,0)) -> 0 | H24: =INDEX(CaseData!$F$37:$F$41,MATCH(H$20,CaseData!$B$37:$B$41,0)) -> 0 | I24: =INDEX(CaseData!$F$37:$F$41,MATCH(I$20,CaseData!$B$37:$B$41,0)) -> 0 | J24: =INDEX(CaseData!$F$37:$F$41,MATCH(J$20,CaseData!$B$37:$B$41,0)) -> 0
B25: Taxable Income for Accounting Purposes (A) | F25: =SUM(F23:F24) -> 36873 | G25: =SUM(G23:G24) -> 25593 | H25: =SUM(H23:H24) -> 28960.5 | I25: =SUM(I23:I24) -> 25971 | J25: =SUM(J23:J24) -> 21864
B27: Plus: Accounting Depreciation | F27: =INDEX(CaseData!$F$25:$F$29,MATCH(F$20,CaseData!$B$25:$B$29,0)) -> 8148 | G27: =INDEX(CaseData!$F$25:$F$29,MATCH(G$20,CaseData!$B$25:$B$29,0)) -> 8392.5 | H27: =INDEX(CaseData!$F$25:$F$29,MATCH(H$20,CaseData!$B$25:$B$29,0)) -> 8812.5 | I27: =INDEX(CaseData!$F$25:$F$29,MATCH(I$20,CaseData!$B$25:$B$29,0)) -> 9253.5 | J27: =INDEX(CaseData!$F$25:$F$29,MATCH(J$20,CaseData!$B$25:$B$29,0)) -> 9624
B28: Less: Tax Depreciation | F28: =F45 -> -13238.613 | G28: =G45 -> -12604.35 | H28: =H45 -> -12478.908 | I28: =I45 -> -12186.241 | J28: =J45 -> -11395.075
B29: Less: Incremental Deductions for Tax Purposes | F29: =-INDEX(CaseData!$F$44:$F$48,MATCH(F$20,CaseData!$B$44:$B$48,0)) -> -8563.5 | G29: =-INDEX(CaseData!$F$44:$F$48,MATCH(G$20,CaseData!$B$44:$B$48,0)) -> -8958 | H29: =-INDEX(CaseData!$F$44:$F$48,MATCH(H$20,CaseData!$B$44:$B$48,0)) -> -3475.5 | I29: =-INDEX(CaseData!$F$44:$F$48,MATCH(I$20,CaseData!$B$44:$B$48,0)) -> -5713.5 | J29: =-INDEX(CaseData!$F$44:$F$48,MATCH(J$20,CaseData!$B$44:$B$48,0)) -> -5685
B30: Less: Qualifying Expense Deductions | F30: =-F56 -> -3500 | G30: =-G56 -> -3780 | H30: =-H56 -> -4082.5 | I30: =-I56 -> -4409 | J30: =-J56 -> -4761.5
B31: Taxable Income for Gov't Purposes before Acc. Losses | F31: =SUM(F25:F30) -> 19718.887 | G31: =SUM(G25:G30) -> 8643.1504 | H31: =SUM(H25:H30) -> 17736.092 | I31: =SUM(I25:I30) -> 12915.759 | J31: =SUM(J25:J30) -> 9646.4247
B33: Less: Acc. Losses Used | F33: =-F72 -> -19718.887 | G33: =-G72 -> -8643.1504 | H33: =-H72 -> -17736.092 | I33: =-I72 -> -12915.759 | J33: =-J72 -> -6107.1116
B34: Taxable Income for Gov't Purposes After Acc. Losses (B) | F34: =SUM(F31:F33) -> 0 | G34: =SUM(G31:G33) -> 0 | H34: =SUM(H31:H33) -> 0 | I34: =SUM(I31:I33) -> 0 | J34: =SUM(J31:J33) -> 3539.3131
B36: Tax Summary:
B37: Current Tax Expense (Rate * B) | F37: =$E$21*F34 -> 0 | G37: =$E$21*G34 -> 0 | H37: =$E$21*H34 -> 0 | I37: =$E$21*I34 -> 0 | J37: =$E$21*J34 -> 743.25576
B38: Deferred Tax Expense | F38: =F39-F37 -> 7743.33 | G38: =G39-G37 -> 5374.53 | H38: =H39-H37 -> 6081.705 | I38: =I39-I37 -> 5453.91 | J38: =J39-J37 -> 3848.1842
B39: Total Tax Expense (Rate * A) | F39: =$E$21*F25 -> 7743.33 | G39: =$E$21*G25 -> 5374.53 | H39: =$E$21*H25 -> 6081.705 | I39: =$E$21*I25 -> 5453.91 | J39: =$E$21*J25 -> 4591.44
B42: Tax Depreciation Schedule: | D42: Tax Dep'n Rate | E42: =CaseData!F33 -> 0.123
B43: Opening Tax Basis in Depreciable Assets | F43: =E46 -> 98265 | G43: =F46 -> 94392.387 | H43: =G46 -> 89870.037 | I43: =H46 -> 88975.629 | J43: =I46 -> 86888.888
B44: Plus: Additions to Fixed Assets | F44: =INDEX(CaseData!$F$18:$F$22,MATCH(F$20,CaseData!$B$18:$B$22,0)) -> 9366 | G44: =INDEX(CaseData!$F$18:$F$22,MATCH(G$20,CaseData!$B$18:$B$22,0)) -> 8082 | H44: =INDEX(CaseData!$F$18:$F$22,MATCH(H$20,CaseData!$B$18:$B$22,0)) -> 11584.5 | I44: =INDEX(CaseData!$F$18:$F$22,MATCH(I$20,CaseData!$B$18:$B$22,0)) -> 10099.5 | J44: =INDEX(CaseData!$F$18:$F$22,MATCH(J$20,CaseData!$B$18:$B$22,0)) -> 5754
B45: Less: Tax Depreciation Claimed | F45: =-$E$42*SUM(F43:F44) -> -13238.613 | G45: =-$E$42*SUM(G43:G44) -> -12604.35 | H45: =-$E$42*SUM(H43:H44) -> -12478.908 | I45: =-$E$42*SUM(I43:I44) -> -12186.241 | J45: =-$E$42*SUM(J43:J44) -> -11395.075
B46: Closing Tax Basis in Depreciable Assets | E46: =CaseData!F31 -> 98265 | F46: =SUM(F43:F45) -> 94392.387 | G46: =SUM(G43:G45) -> 89870.037 | H46: =SUM(H43:H45) -> 88975.629 | I46: =SUM(I43:I45) -> 86888.888 | J46: =SUM(J43:J45) -> 81247.813
B49: Qualifying Expense Schedule:
B50: Qualifying Expenses | F50: =INDEX(CaseData!$F$54:$F$58,MATCH(F$20,CaseData!$B$54:$B$58,0)) -> 3500 | G50: =INDEX(CaseData!$F$54:$F$58,MATCH(G$20,CaseData!$B$54:$B$58,0)) -> 3780 | H50: =INDEX(CaseData!$F$54:$F$58,MATCH(H$20,CaseData!$B$54:$B$58,0)) -> 4082.5 | I50: =INDEX(CaseData!$F$54:$F$58,MATCH(I$20,CaseData!$B$54:$B$58,0)) -> 4409 | J50: =INDEX(CaseData!$F$54:$F$58,MATCH(J$20,CaseData!$B$54:$B$58,0)) -> 4761.5
B51: % of Expenditure Deductible | F51: =CaseData!$F$50 -> 1 | G51: =CaseData!$F$50 -> 1 | H51: =CaseData!$F$50 -> 1 | I51: =CaseData!$F$50 -> 1 | J51: =CaseData!$F$50 -> 1
B52: Maximum Dollar Deductible | F52: =CaseData!$F$51 -> No limit | G52: =CaseData!$F$51 -> No limit | H52: =CaseData!$F$51 -> No limit | I52: =CaseData!$F$51 -> No limit | J52: =CaseData!$F$51 -> No limit
B54: % of Expenditure Deductible Amount | F54: =F50*F51 -> 3500 | G54: =G50*G51 -> 3780 | H54: =H50*H51 -> 4082.5 | I54: =I50*I51 -> 4409 | J54: =J50*J51 -> 4761.5
B55: Maximum Dollar Deductible Amount | F55: =F52 -> No limit | G55: =G52 -> No limit | H55: =H52 -> No limit | I55: =I52 -> No limit | J55: =J52 -> No limit
B56: Actual Deduction Amount | F56: =MIN(F54,F55) -> 3500 | G56: =MIN(G54,G55) -> 3780 | H56: =MIN(H54,H55) -> 4082.5 | I56: =MIN(I54,I55) -> 4409 | J56: =MIN(J54,J55) -> 4761.5
B59: TLCF Schedule:
B60: Taxable Income for Gov't Purposes before Acc. Losses | F60: =F31 -> 19718.887 | G60: =G31 -> 8643.1504 | H60: =H31 -> 17736.092 | I60: =I31 -> 12915.759 | J60: =J31 -> 9646.4247
B61: TLCFs Added
B62: Expiring Thereafter | F62: =IF(F60<0,-F60,0) -> 0 | G62: =IF(G60<0,-G60,0) -> 0 | H62: =IF(H60<0,-H60,0) -> 0 | I62: =IF(I60<0,-I60,0) -> 0 | J62: =IF(J60<0,-J60,0) -> 0
B63: Total TLCFs Added | F63: =SUM(F62:F62) -> 0 | G63: =SUM(G62:G62) -> 0 | H63: =SUM(H62:H62) -> 0 | I63: =SUM(I62:I62) -> 0 | J63: =SUM(J62:J62) -> 0
B65: TLCFs Used
B66: =$F$21 -> 2023 | E66: =CaseData!F61 -> 5137.5 | F66: =MAX(MIN(E75,F$60-SUM(F$65:F65)),0) -> 5137.5 | G66: =MAX(MIN(F75,G$60-SUM(G$65:G65)),0) -> 0 | H66: =MAX(MIN(G75,H$60-SUM(H$65:H65)),0) -> 0 | I66: =MAX(MIN(H75,I$60-SUM(I$65:I65)),0) -> 0 | J66: =MAX(MIN(I75,J$60-SUM(J$65:J65)),0) -> 0
B67: =$G$21 -> 2024 | E67: =CaseData!F62 -> 21181.5 | F67: =MAX(MIN(E76,F$60-SUM(F$65:F66)),0) -> 14581.387 | G67: =MAX(MIN(F76,G$60-SUM(G$65:G66)),0) -> 6600.113 | H67: =MAX(MIN(G76,H$60-SUM(H$65:H66)),0) -> 0 | I67: =MAX(MIN(H76,I$60-SUM(I$65:I66)),0) -> 0 | J67: =MAX(MIN(I76,J$60-SUM(J$65:J66)),0) -> 0
B68: =$H$21 -> 2025 | E68: =CaseData!F63 -> 0 | F68: =MAX(MIN(E77,F$60-SUM(F$65:F67)),0) -> 0 | G68: =MAX(MIN(F77,G$60-SUM(G$65:G67)),0) -> 0 | H68: =MAX(MIN(G77,H$60-SUM(H$65:H67)),0) -> 0 | I68: =MAX(MIN(H77,I$60-SUM(I$65:I67)),0) -> 0 | J68: =MAX(MIN(I77,J$60-SUM(J$65:J67)),0) -> 0
B69: =$I$21 -> 2026 | E69: =CaseData!F64 -> 18481.5 | F69: =MAX(MIN(E78,F$60-SUM(F$65:F68)),0) -> 0 | G69: =MAX(MIN(F78,G$60-SUM(G$65:G68)),0) -> 2043.0374 | H69: =MAX(MIN(G78,H$60-SUM(H$65:H68)),0) -> 16438.463 | I69: =MAX(MIN(H78,I$60-SUM(I$65:I68)),0) -> 0 | J69: =MAX(MIN(I78,J$60-SUM(J$65:J68)),0) -> 0
B70: =$J$21 -> 2027 | E70: =CaseData!F65 -> 13720.5 | F70: =MAX(MIN(E79,F$60-SUM(F$65:F69)),0) -> 0 | G70: =MAX(MIN(F79,G$60-SUM(G$65:G69)),0) -> 0 | H70: =MAX(MIN(G79,H$60-SUM(H$65:H69)),0) -> 1297.6293 | I70: =MAX(MIN(H79,I$60-SUM(I$65:I69)),0) -> 12422.871 | J70: =MAX(MIN(I79,J$60-SUM(J$65:J69)),0) -> 0
B71: Expiring Thereafter | E71: =CaseData!F66 -> 6600 | F71: =MAX(MIN(E80,F$60-SUM(F$65:F70)),0) -> 0 | G71: =MAX(MIN(F80,G$60-SUM(G$65:G70)),0) -> 0 | H71: =MAX(MIN(G80,H$60-SUM(H$65:H70)),0) -> 0 | I71: =MAX(MIN(H80,I$60-SUM(I$65:I70)),0) -> 492.8884 | J71: =MAX(MIN(I80,J$60-SUM(J$65:J70)),0) -> 6107.1116
B72: Total TLCFs Used | F72: =SUM(F66:F71) -> 19718.887 | G72: =SUM(G66:G71) -> 8643.1504 | H72: =SUM(H66:H71) -> 17736.092 | I72: =SUM(I66:I71) -> 12915.759 | J72: =SUM(J66:J71) -> 6107.1116
B74: TLCFs Remaining
B75: =B66 -> 2023 | E75: =E66 -> 5137.5 | F75: =IF($B75<=F$21,0,E75-F66) -> 0 | G75: =IF($B75<=G$21,0,F75-G66) -> 0 | H75: =IF($B75<=H$21,0,G75-H66) -> 0 | I75: =IF($B75<=I$21,0,H75-I66) -> 0 | J75: =IF($B75<=J$21,0,I75-J66) -> 0
B76: =B67 -> 2024 | E76: =E67 -> 21181.5 | F76: =IF($B76<=F$21,0,E76-F67) -> 6600.113 | G76: =IF($B76<=G$21,0,F76-G67) -> 0 | H76: =IF($B76<=H$21,0,G76-H67) -> 0 | I76: =IF($B76<=I$21,0,H76-I67) -> 0 | J76: =IF($B76<=J$21,0,I76-J67) -> 0
B77: =B68 -> 2025 | E77: =E68 -> 0 | F77: =IF($B77<=F$21,0,E77-F68) -> 0 | G77: =IF($B77<=G$21,0,F77-G68) -> 0 | H77: =IF($B77<=H$21,0,G77-H68) -> 0 | I77: =IF($B77<=I$21,0,H77-I68) -> 0 | J77: =IF($B77<=J$21,0,I77-J68) -> 0
B78: =B69 -> 2026 | E78: =E69 -> 18481.5 | F78: =IF($B78<=F$21,0,E78-F69) -> 18481.5 | G78: =IF($B78<=G$21,0,F78-G69) -> 16438.463 | H78: =IF($B78<=H$21,0,G78-H69) -> 0 | I78: =IF($B78<=I$21,0,H78-I69) -> 0 | J78: =IF($B78<=J$21,0,I78-J69) -> 0
B79: =B70 -> 2027 | E79: =E70 -> 13720.5 | F79: =IF($B79<=F$21,0,E79-F70) -> 13720.5 | G79: =IF($B79<=G$21,0,F79-G70) -> 13720.5 | H79: =IF($B79<=H$21,0,G79-H70) -> 12422.871 | I79: =IF($B79<=I$21,0,H79-I70) -> 0 | J79: =IF($B79<=J$21,0,I79-J70) -> 0
B80: =B71 -> Expiring Thereafter | E80: =E71 -> 6600 | F80: =IF($B80<=F$21,0,E80+F62-F71) -> 6600 | G80: =IF($B80<=G$21,0,F80+G62-G71) -> 6600 | H80: =IF($B80<=H$21,0,G80+H62-H71) -> 6600 | I80: =IF($B80<=I$21,0,H80+I62-I71) -> 6107.1116 | J80: =IF($B80<=J$21,0,I80+J62-J71) -> 0
B81: Total TLCFs Remaining | F81: =SUM(F75:F80) -> 45402.113 | G81: =SUM(G75:G80) -> 36758.963 | H81: =SUM(H75:H80) -> 19022.871 | I81: =SUM(I75:I80) -> 6107.1116 | J81: =SUM(J75:J80) -> 0
B84: CANADA (CAD) | D84: Tax Rate | E84: =CaseData!G6 -> 0.265 | F84: =F21 -> 2023 | G84: =G21 -> 2024 | H84: =H21 -> 2025 | I84: =I21 -> 2026 | J84: =J21 -> 2027
B85: Tax Calculation:
B86: Projected Accounting Pre-tax Income | F86: =INDEX(CaseData!$G$11:$G$15,MATCH(F$20,CaseData!$B$11:$B$15,0)) -> 40860 | G86: =INDEX(CaseData!$G$11:$G$15,MATCH(G$20,CaseData!$B$11:$B$15,0)) -> 39141 | H86: =INDEX(CaseData!$G$11:$G$15,MATCH(H$20,CaseData!$B$11:$B$15,0)) -> 41452.5 | I86: =INDEX(CaseData!$G$11:$G$15,MATCH(I$20,CaseData!$B$11:$B$15,0)) -> 36444 | J86: =INDEX(CaseData!$G$11:$G$15,MATCH(J$20,CaseData!$B$11:$B$15,0)) -> 44791.5
B87: Plus: Non-Deductible Expenses | F87: =INDEX(CaseData!$G$37:$G$41,MATCH(F$20,CaseData!$B$37:$B$41,0)) -> 0 | G87: =INDEX(CaseData!$G$37:$G$41,MATCH(G$20,CaseData!$B$37:$B$41,0)) -> 0 | H87: =INDEX(CaseData!$G$37:$G$41,MATCH(H$20,CaseData!$B$37:$B$41,0)) -> 0 | I87: =INDEX(CaseData!$G$37:$G$41,MATCH(I$20,CaseData!$B$37:$B$41,0)) -> 0 | J87: =INDEX(CaseData!$G$37:$G$41,MATCH(J$20,CaseData!$B$37:$B$41,0)) -> 0
B88: Taxable Income for Accounting Purposes (A) | F88: =SUM(F86:F87) -> 40860 | G88: =SUM(G86:G87) -> 39141 | H88: =SUM(H86:H87) -> 41452.5 | I88: =SUM(I86:I87) -> 36444 | J88: =SUM(J86:J87) -> 44791.5
B90: Plus: Accounting Depreciation | F90: =INDEX(CaseData!$G$25:$G$29,MATCH(F$20,CaseData!$B$25:$B$29,0)) -> 11091 | G90: =INDEX(CaseData!$G$25:$G$29,MATCH(G$20,CaseData!$B$25:$B$29,0)) -> 11535 | H90: =INDEX(CaseData!$G$25:$G$29,MATCH(H$20,CaseData!$B$25:$B$29,0)) -> 11997 | I90: =INDEX(CaseData!$G$25:$G$29,MATCH(I$20,CaseData!$B$25:$B$29,0)) -> 12717 | J90: =INDEX(CaseData!$G$25:$G$29,MATCH(J$20,CaseData!$B$25:$B$29,0)) -> 13225.5
B91: Less: Tax Depreciation | F91: =F108 -> -20325.525 | G91: =G108 -> -20976.165 | H91: =H108 -> -19959.706 | I91: =I108 -> -19195.362 | J91: =J108 -> -19938.964
B92: Less: Incremental Deductions for Tax Purposes | F92: =-INDEX(CaseData!$G$44:$G$48,MATCH(F$20,CaseData!$B$44:$B$48,0)) -> -11032.5 | G92: =-INDEX(CaseData!$G$44:$G$48,MATCH(G$20,CaseData!$B$44:$B$48,0)) -> -12525 | H92: =-INDEX(CaseData!$G$44:$G$48,MATCH(H$20,CaseData!$B$44:$B$48,0)) -> -9120 | I92: =-INDEX(CaseData!$G$44:$G$48,MATCH(I$20,CaseData!$B$44:$B$48,0)) -> -6559.5 | J92: =-INDEX(CaseData!$G$44:$G$48,MATCH(J$20,CaseData!$B$44:$B$48,0)) -> -14781
B93: Less: Qualifying Expense Deductions | F93: =-F119 -> -2625 | G93: =-G119 -> -2835 | H93: =-H119 -> -3000 | I93: =-I119 -> -3000 | J93: =-J119 -> -3000
B94: Taxable Income for Gov't Purposes before Acc. Losses | F94: =SUM(F88:F93) -> 17967.975 | G94: =SUM(G88:G93) -> 14339.835 | H94: =SUM(H88:H93) -> 21369.794 | I94: =SUM(I88:I93) -> 20406.138 | J94: =SUM(J88:J93) -> 20297.036
B96: Less: Acc. Losses Used | F96: =-F135 -> -17967.975 | G96: =-G135 -> -14339.835 | H96: =-H135 -> -21369.794 | I96: =-I135 -> -20406.138 | J96: =-J135 -> -20297.036
B97: Taxable Income for Gov't Purposes After Acc. Losses (B) | F97: =SUM(F94:F96) -> 0 | G97: =SUM(G94:G96) -> 0 | H97: =SUM(H94:H96) -> 0 | I97: =SUM(I94:I96) -> 0 | J97: =SUM(J94:J96) -> 0
B99: Tax Summary:
B100: Current Tax Expense (Rate * B) | F100: =$E$84*F97 -> 0 | G100: =$E$84*G97 -> 0 | H100: =$E$84*H97 -> 0 | I100: =$E$84*I97 -> 0 | J100: =$E$84*J97 -> 0
B101: Deferred Tax Expense | F101: =F102-F100 -> 10827.9 | G101: =G102-G100 -> 10372.365 | H101: =H102-H100 -> 10984.913 | I101: =I102-I100 -> 9657.66 | J101: =J102-J100 -> 11869.748
B102: Total Tax Expense (Rate * A) | F102: =$E$84*F88 -> 10827.9 | G102: =$E$84*G88 -> 10372.365 | H102: =$E$84*H88 -> 10984.913 | I102: =$E$84*I88 -> 9657.66 | J102: =$E$84*J88 -> 11869.748
B105: Tax Depreciation Schedule: | D105: Tax Dep'n Rate | E105: =CaseData!G33 -> 0.142
B106: Opening Tax Basis in Depreciable Assets | F106: =E109 -> 128544 | G106: =F109 -> 122811.98 | H106: =G109 -> 126743.31 | I106: =H109 -> 120601.6 | J106: =I109 -> 115983.24
B107: Plus: Additions to Fixed Assets | F107: =INDEX(CaseData!$G$18:$G$22,MATCH(F$20,CaseData!$B$18:$B$22,0)) -> 14593.5 | G107: =INDEX(CaseData!$G$18:$G$22,MATCH(G$20,CaseData!$B$18:$B$22,0)) -> 24907.5 | H107: =INDEX(CaseData!$G$18:$G$22,MATCH(H$20,CaseData!$B$18:$B$22,0)) -> 13818 | I107: =INDEX(CaseData!$G$18:$G$22,MATCH(I$20,CaseData!$B$18:$B$22,0)) -> 14577 | J107: =INDEX(CaseData!$G$18:$G$22,MATCH(J$20,CaseData!$B$18:$B$22,0)) -> 24432
B108: Less: Tax Depreciation Claimed | F108: =-$E$105*SUM(F106:F107) -> -20325.525 | G108: =-$E$105*SUM(G106:G107) -> -20976.165 | H108: =-$E$105*SUM(H106:H107) -> -19959.706 | I108: =-$E$105*SUM(I106:I107) -> -19195.362 | J108: =-$E$105*SUM(J106:J107) -> -19938.964
B109: Closing Tax Basis in Depreciable Assets | E109: =CaseData!G31 -> 128544 | F109: =SUM(F106:F108) -> 122811.98 | G109: =SUM(G106:G108) -> 126743.31 | H109: =SUM(H106:H108) -> 120601.6 | I109: =SUM(I106:I108) -> 115983.24 | J109: =SUM(J106:J108) -> 120476.28
B112: Qualifying Expense Schedule:
B113: Qualifying Expenses | F113: =INDEX(CaseData!$G$54:$G$58,MATCH(F$20,CaseData!$B$54:$B$58,0)) -> 7500 | G113: =INDEX(CaseData!$G$54:$G$58,MATCH(G$20,CaseData!$B$54:$B$58,0)) -> 8100 | H113: =INDEX(CaseData!$G$54:$G$58,MATCH(H$20,CaseData!$B$54:$B$58,0)) -> 8748 | I113: =INDEX(CaseData!$G$54:$G$58,MATCH(I$20,CaseData!$B$54:$B$58,0)) -> 9447 | J113: =INDEX(CaseData!$G$54:$G$58,MATCH(J$20,CaseData!$B$54:$B$58,0)) -> 10203.5
B114: % of Expenditure Deductible | F114: =CaseData!$G$50 -> 0.35 | G114: =CaseData!$G$50 -> 0.35 | H114: =CaseData!$G$50 -> 0.35 | I114: =CaseData!$G$50 -> 0.35 | J114: =CaseData!$G$50 -> 0.35
B115: Maximum Dollar Deductible | F115: =CaseData!$G$51 -> 3000 | G115: =CaseData!$G$51 -> 3000 | H115: =CaseData!$G$51 -> 3000 | I115: =CaseData!$G$51 -> 3000 | J115: =CaseData!$G$51 -> 3000
B117: % of Expenditure Deductible Amount | F117: =F113*F114 -> 2625 | G117: =G113*G114 -> 2835 | H117: =H113*H114 -> 3061.8 | I117: =I113*I114 -> 3306.45 | J117: =J113*J114 -> 3571.225
B118: Maximum Dollar Deductible Amount | F118: =F115 -> 3000 | G118: =G115 -> 3000 | H118: =H115 -> 3000 | I118: =I115 -> 3000 | J118: =J115 -> 3000
B119: Actual Deduction Amount | F119: =MIN(F117,F118) -> 2625 | G119: =MIN(G117,G118) -> 2835 | H119: =MIN(H117,H118) -> 3000 | I119: =MIN(I117,I118) -> 3000 | J119: =MIN(J117,J118) -> 3000
B122: TLCF Schedule:
B123: Taxable Income for Gov't Purposes before Acc. Losses | F123: =F94 -> 17967.975 | G123: =G94 -> 14339.835 | H123: =H94 -> 21369.794 | I123: =I94 -> 20406.138 | J123: =J94 -> 20297.036
B124: TLCFs Added
B125: Expiring Thereafter | F125: =IF(F123<0,-F123,0) -> 0 | G125: =IF(G123<0,-G123,0) -> 0 | H125: =IF(H123<0,-H123,0) -> 0 | I125: =IF(I123<0,-I123,0) -> 0 | J125: =IF(J123<0,-J123,0) -> 0
B126: Total TLCFs Added | F126: =SUM(F125:F125) -> 0 | G126: =SUM(G125:G125) -> 0 | H126: =SUM(H125:H125) -> 0 | I126: =SUM(I125:I125) -> 0 | J126: =SUM(J125:J125) -> 0
B128: TLCFs Used
B129: =B75 -> 2023 | E129: =CaseData!G61 -> 36540 | F129: =MAX(MIN(E138,F$123-SUM(F$128:F128)),0) -> 17967.975 | G129: =MAX(MIN(F138,G$123-SUM(G$128:G128)),0) -> 0 | H129: =MAX(MIN(G138,H$123-SUM(H$128:H128)),0) -> 0 | I129: =MAX(MIN(H138,I$123-SUM(I$128:I128)),0) -> 0 | J129: =MAX(MIN(I138,J$123-SUM(J$128:J128)),0) -> 0
B130: =B76 -> 2024 | E130: =CaseData!G62 -> 11262 | F130: =MAX(MIN(E139,F$123-SUM(F$128:F129)),0) -> 0 | G130: =MAX(MIN(F139,G$123-SUM(G$128:G129)),0) -> 11262 | H130: =MAX(MIN(G139,H$123-SUM(H$128:H129)),0) -> 0 | I130: =MAX(MIN(H139,I$123-SUM(I$128:I129)),0) -> 0 | J130: =MAX(MIN(I139,J$123-SUM(J$128:J129)),0) -> 0
...
