Workbook
Name company: CaseData!$B$1
Name Date: CaseData!$T$29:$Y$29
Name periods: CaseData!$D$47
Name start_date: CaseData!$D$46
Name topic: "CFM Topic: " & CaseData!$D$48

Sheet Debt
A1: {=company} -> Streamwise Ltd.
A2: {=topic} -> CFM Topic: Debt
A3: DEBT SCHEDULE | F3: Unit | G3: =EOMONTH( $H$3, - 1 ) -> 43373 | H3: {=EOMONTH( start_date, _xlfn.SEQUENCE( 1, periods, 0, 1 ) )} -> 43404 | I3: 43434 | J3: 43465 | K3: 43496 | L3: 43524 | M3: 43555
A5: Total Debt / EBIDTA
E8: =E$141 -> Total Debt | F8: =F$141 -> USD | G8: =SUM($G38, $G57, $G76, $G94 ) -> 686848 | H8: =H$141 -> 681911.17 | I8: =I$141 -> 678265.46 | J8: =J$141 -> 682917.34 | K8: =K$141 -> 680818.37 | L8: =L$141 -> 678745.64 | M8: =M$141 -> 677104.93
E9: EBIDTA | F9: USD | G9: =CaseData!$S$53 -> 191177 | H9: =CaseData!E$63 -> 193220 | I9: =CaseData!F$63 -> 189600 | J9: =CaseData!G$63 -> 186312 | K9: =CaseData!H$63 -> 185545 | L9: =CaseData!I$63 -> 185313 | M9: =CaseData!J$63 -> 183795
E10: Total Debt / EBIDTA | F10: multiple | G10: =G8 / G9 -> 3.5927334 | H10: =H8 / H9 -> 3.5291956 | I10: =I8 / I9 -> 3.5773495 | J10: =J8 / J9 -> 3.6654501 | K10: =K8 / K9 -> 3.6692898 | L10: =L8 / L9 -> 3.6626985 | M10: =M8 / M9 -> 3.6840226
A13: Taxes
E16: Free Cash Flow Before Debt Service & Taxes | F16: USD | H16: =CaseData!E$65 -> 10393.67 | I16: =CaseData!F$65 -> 8667.573 | J16: =CaseData!G$65 -> 6355.84 | K16: =CaseData!H$65 -> 8884.205 | L16: =CaseData!I$65 -> 11026.2 | M16: =CaseData!J$65 -> 5745.409
D17: less | E17: =E$112 -> Interest expenses accrued | F17: USD | H17: =H$112 * - 1 -> -3811.228 | I17: =I$112 * - 1 -> -3806.6267 | J17: =J$112 * - 1 -> -3806.2239 | K17: =K$112 * - 1 -> -3363.4927 | L17: =L$112 * - 1 -> -3453.4365 | M17: =M$112 * - 1 -> -3557.7918
E18: Taxable income | F18: USD | H18: =SUM(H16:H17) -> 6582.442 | I18: =SUM(I16:I17) -> 4860.9463 | J18: =SUM(J16:J17) -> 2549.6161 | K18: =SUM(K16:K17) -> 5520.7123 | L18: =SUM(L16:L17) -> 7572.7635 | M18: =SUM(M16:M17) -> 2187.6172
E20: Applicable tax rate | F20: % | G20: =CaseData!$K$8 -> 0.25
E21: Taxes paid | F21: USD | H21: =H$18 * $G$20 -> 1645.6105 | I21: =I$18 * $G$20 -> 1215.2366 | J21: =J$18 * $G$20 -> 637.40402 | K21: =K$18 * $G$20 -> 1380.1781 | L21: =L$18 * $G$20 -> 1893.1909 | M21: =M$18 * $G$20 -> 546.9043
A24: Revolver
C27: Free cash flow after repayment of debt service and taxes
E29: Free Cash Flow Before Debt Service & Taxes | F29: USD | H29: =CaseData!E$65 -> 10393.67 | I29: =CaseData!F$65 -> 8667.573 | J29: =CaseData!G$65 -> 6355.84 | K29: =CaseData!H$65 -> 8884.205 | L29: =CaseData!I$65 -> 11026.2 | M29: =CaseData!J$65 -> 5745.409
E30: Principal addition / (repayment) | F30: USD | H30: =H$131 -> -2179.6875 | I30: =I$131 -> -2152.4414 | J30: =J$131 -> 12874.464 | K30: =K$131 -> -2098.9667 | L30: =L$131 -> -2072.7296 | M30: =M$131 -> -2046.8205
D31: less | E31: =E$112 -> Interest expenses accrued | F31: USD | H31: =H$112 * - 1 -> -3811.228 | I31: =I$112 * - 1 -> -3806.6267 | J31: =J$112 * - 1 -> -3806.2239 | K31: =K$112 * - 1 -> -3363.4927 | L31: =L$112 * - 1 -> -3453.4365 | M31: =M$112 * - 1 -> -3557.7918
D32: less | E32: Taxes paid | F32: USD | H32: =H$21 * - 1 -> -1645.6105 | I32: =I$21 * - 1 -> -1215.2366 | J32: =J$21 * - 1 -> -637.40402 | K32: =K$21 * - 1 -> -1380.1781 | L32: =L$21 * - 1 -> -1893.1909 | M32: =M$21 * - 1 -> -546.9043
E33: Free cash flow after repayment of debt service and taxes | F33: USD | H33: =SUM( H29:H32) -> 2757.144 | I33: =SUM( I29:I32) -> 1493.2683 | J33: =SUM( J29:J32) -> 14786.676 | K33: =SUM( K29:K32) -> 2041.5676 | L33: =SUM( L29:L32) -> 3606.843 | M33: =SUM( M29:M32) -> -406.10757
E36: Revolver beginning balance | F36: USD | H36: =G$38 -> 12473 | I36: =H$38 -> 9715.856 | J36: =I$38 -> 8222.5877 | K36: =J$38 -> 0 | L36: =K$38 -> 0 | M36: =L$38 -> 0
E37: Revolver Drawdown / (Repayment) | F37: USD | H37: =- MIN( H36, H33) -> -2757.144 | I37: =- MIN( I36, I33) -> -1493.2683 | J37: =- MIN( J36, J33) -> -8222.5877 | K37: =- MIN( K36, K33) -> 0 | L37: =- MIN( L36, L33) -> 0 | M37: =- MIN( M36, M33) -> 406.10757
E38: Revolver closing balance | F38: USD | G38: =CaseData!$E$8 -> 12473 | H38: =SUM(H36:H37) -> 9715.856 | I38: =SUM(I36:I37) -> 8222.5877 | J38: =SUM(J36:J37) -> 0 | K38: =SUM(K36:K37) -> 0 | L38: =SUM(L36:L37) -> 0 | M38: =SUM(M36:M37) -> 406.10757
C40: Revolver interest expenses
E42: LIBOR | F42: % | H42: =CaseData!E$66 -> 0.0225 | I42: =CaseData!F$66 -> 0.0235 | J42: =CaseData!G$66 -> 0.0245 | K42: =CaseData!H$66 -> 0.0255 | L42: =CaseData!I$66 -> 0.0265 | M42: =CaseData!J$66 -> 0.027
E43: Spread to LIBOR based on Total Debt / EBIDTA | F43: % | H43: =_xlfn.XLOOKUP(G$10, CaseData!$G$11:$G$14, CaseData!$I$11:$I$14,,-1)/10000 -> 0.03 | I43: =_xlfn.XLOOKUP(H$10, CaseData!$G$11:$G$14, CaseData!$I$11:$I$14,,-1)/10000 -> 0.03 | J43: =_xlfn.XLOOKUP(I$10, CaseData!$G$11:$G$14, CaseData!$I$11:$I$14,,-1)/10000 -> 0.03 | K43: =_xlfn.XLOOKUP(J$10, CaseData!$G$11:$G$14, CaseData!$I$11:$I$14,,-1)/10000 -> 0.03 | L43: =_xlfn.XLOOKUP(K$10, CaseData!$G$11:$G$14, CaseData!$I$11:$I$14,,-1)/10000 -> 0.03 | M43: =_xlfn.XLOOKUP(L$10, CaseData!$G$11:$G$14, CaseData!$I$11:$I$14,,-1)/10000 -> 0.03
E44: Effective interest rate on revolver | F44: % | H44: =SUM(H42:H43) -> 0.0525 | I44: =SUM(I42:I43) -> 0.0535 | J44: =SUM(J42:J43) -> 0.0545 | K44: =SUM(K42:K43) -> 0.0555 | L44: =SUM(L42:L43) -> 0.0565 | M44: =SUM(M42:M43) -> 0.057
E47: Drawn Interest Expense | F47: USD | H47: =IF( H$3 = start_date, CaseData!$E$8 * H$44, H$36 * Debt!H$44 ) / 12 -> 54.569375 | I47: =IF( I$3 = start_date, CaseData!$E$8 * I$44, I$36 * Debt!I$44 ) / 12 -> 43.316525 | J47: =IF( J$3 = start_date, CaseData!$E$8 * J$44, J$36 * Debt!J$44 ) / 12 -> 37.344252 | K47: =IF( K$3 = start_date, CaseData!$E$8 * K$44, K$36 * Debt!K$44 ) / 12 -> 0 | L47: =IF( L$3 = start_date, CaseData!$E$8 * L$44, L$36 * Debt!L$44 ) / 12 -> 0 | M47: =IF( M$3 = start_date, CaseData!$E$8 * M$44, M$36 * Debt!M$44 ) / 12 -> 0
E48: Standby fee on undrawn revolver facility | F48: USD | H48: =IF(H$3 = start_date, ( CaseData!$E$7 - CaseData!$E$8 ) * ( CaseData!$E$10/10000 ) / 12, ( CaseData!$E$7 - Debt!H$36 ) * ( CaseData!$E$10 / 10000 ) / 12 ) -> 25.018 | I48: =IF(I$3=start_date, (CaseData!$E$7-CaseData!$E$8)*(CaseData!$E$10/10000)/12, (CaseData!$E$7-Debt!I$36)*(CaseData!$E$10/10000)/12) -> 26.856096 | J48: =IF(J$3=start_date, (CaseData!$E$7-CaseData!$E$8)*(CaseData!$E$10/10000)/12, (CaseData!$E$7-Debt!J$36)*(CaseData!$E$10/10000)/12) -> 27.851608 | K48: =IF(K$3=start_date, (CaseData!$E$7-CaseData!$E$8)*(CaseData!$E$10/10000)/12, (CaseData!$E$7-Debt!K$36)*(CaseData!$E$10/10000)/12) -> 33.333333 | L48: =IF(L$3=start_date, (CaseData!$E$7-CaseData!$E$8)*(CaseData!$E$10/10000)/12, (CaseData!$E$7-Debt!L$36)*(CaseData!$E$10/10000)/12) -> 33.333333 | M48: =IF(M$3=start_date, (CaseData!$E$7-CaseData!$E$8)*(CaseData!$E$10/10000)/12, (CaseData!$E$7-Debt!M$36)*(CaseData!$E$10/10000)/12) -> 33.333333
E49: Revolver interest expenses | F49: USD | H49: =SUM(H47:H48) -> 79.587375 | I49: =SUM(I47:I48) -> 70.172621 | J49: =SUM(J47:J48) -> 65.195861 | K49: =SUM(K47:K48) -> 33.333333 | L49: =SUM(L47:L48) -> 33.333333 | M49: =SUM(M47:M48) -> 33.333333
A52: Senior Secured Term Loan
E55: Senior Secured Term Loan opening balance | F55: USD | H55: =G$57 -> 174375 | I55: =H$57 -> 172195.31 | J55: =I$57 -> 170042.87 | K55: =J$57 -> 167917.34 | L55: =K$57 -> 165818.37 | M55: =L$57 -> 163745.64
E56: Senior Secured Term Loan drawdown / (repayments) | F56: USD | H56: =IF( H$3 = start_date, CaseData!$E$17 * CaseData!$E$20, H$55 * CaseData!$E$20 ) * - 1 -> -2179.6875 | I56: =IF( I$3 = start_date, CaseData!$E$17 * CaseData!$E$20, I$55 * CaseData!$E$20 ) * - 1 -> -2152.4414 | J56: =IF( J$3 = start_date, CaseData!$E$17 * CaseData!$E$20, J$55 * CaseData!$E$20 ) * - 1 -> -2125.5359 | K56: =IF( K$3 = start_date, CaseData!$E$17 * CaseData!$E$20, K$55 * CaseData!$E$20 ) * - 1 -> -2098.9667 | L56: =IF( L$3 = start_date, CaseData!$E$17 * CaseData!$E$20, L$55 * CaseData!$E$20 ) * - 1 -> -2072.7296 | M56: =IF( M$3 = start_date, CaseData!$E$17 * CaseData!$E$20, M$55 * CaseData!$E$20 ) * - 1 -> -2046.8205
E57: Senior Secured Term Loan closing balance | F57: USD | G57: =CaseData!$E$17 -> 174375 | H57: =SUM(H55:H56) -> 172195.31 | I57: =SUM(I55:I56) -> 170042.87 | J57: =SUM(J55:J56) -> 167917.34 | K57: =SUM(K55:K56) -> 165818.37 | L57: =SUM(L55:L56) -> 163745.64 | M57: =SUM(M55:M56) -> 161698.82
C60: Senior Secured Term Loan interest expenses
E62: LIBOR | F62: % | H62: =CaseData!E$66 -> 0.0225 | I62: =CaseData!F$66 -> 0.0235 | J62: =CaseData!G$66 -> 0.0245 | K62: =CaseData!H$66 -> 0.0255 | L62: =CaseData!I$66 -> 0.0265 | M62: =CaseData!J$66 -> 0.027
E63: Spread to LIBOR based on Total Debt / EBIDTA | F63: % | H63: =_xlfn.XLOOKUP( G$10, CaseData!$G$11:$G$14, CaseData!$I$11:$I$14,,-1 ) / 10000 -> 0.03 | I63: =_xlfn.XLOOKUP( H$10, CaseData!$G$11:$G$14, CaseData!$I$11:$I$14,,-1 ) / 10000 -> 0.03 | J63: =_xlfn.XLOOKUP( I$10, CaseData!$G$11:$G$14, CaseData!$I$11:$I$14,,-1 ) / 10000 -> 0.03 | K63: =_xlfn.XLOOKUP( J$10, CaseData!$G$11:$G$14, CaseData!$I$11:$I$14,,-1 ) / 10000 -> 0.03 | L63: =_xlfn.XLOOKUP( K$10, CaseData!$G$11:$G$14, CaseData!$I$11:$I$14,,-1 ) / 10000 -> 0.03 | M63: =_xlfn.XLOOKUP( L$10, CaseData!$G$11:$G$14, CaseData!$I$11:$I$14,,-1 ) / 10000 -> 0.03
E64: Effective interest rate on Senior Secured Term Loan | F64: % | H64: =SUM(H62:H63) -> 0.0525 | I64: =SUM(I62:I63) -> 0.0535 | J64: =SUM(J62:J63) -> 0.0545 | K64: =SUM(K62:K63) -> 0.0555 | L64: =SUM(L62:L63) -> 0.0565 | M64: =SUM(M62:M63) -> 0.057
E67: Senior Secured Term Loan interest expenses | F67: USD | H67: =H$55 * H64 / 12 -> 762.89062 | I67: =I$55 * I64 / 12 -> 767.7041 | J67: =J$55 * J64 / 12 -> 772.27804 | K67: =K$55 * K64 / 12 -> 776.61768 | L67: =L$55 * L64 / 12 -> 780.72815 | M67: =M$55 * M64 / 12 -> 777.79178
E68: (monthly amortization)
A71: Subordinated Notes
E74: Subordinated Notes opening balance | F74: USD | H74: =G$76 -> 500000 | I74: =H$76 -> 500000 | J74: =I$76 -> 500000 | K74: =J$76 -> 0 | L74: =K$76 -> 0 | M74: =L$76 -> 0
E75: Subordinated Notes drawdown / (repayment) | F75: USD | H75: =IF( H$3 = Debt!$M$166, CaseData!$I$17 * - 1, 0 ) -> 0 | I75: =IF( I$3 = Debt!$M$166, CaseData!$I$17 * - 1, 0 ) -> 0 | J75: =IF( J$3 = Debt!$M$166, CaseData!$I$17 * - 1, 0 ) -> -500000 | K75: =IF( K$3 = Debt!$M$166, CaseData!$I$17 * - 1, 0 ) -> 0 | L75: =IF( L$3 = Debt!$M$166, CaseData!$I$17 * - 1, 0 ) -> 0 | M75: =IF( M$3 = Debt!$M$166, CaseData!$I$17 * - 1, 0 ) -> 0
E76: Subordinated Notes closing balance | F76: USD | G76: =CaseData!$I$17 -> 500000 | H76: =SUM( H74:H75) -> 500000 | I76: =SUM( I74:I75) -> 500000 | J76: =SUM( J74:J75) -> 0 | K76: =SUM( K74:K75) -> 0 | L76: =SUM( L74:L75) -> 0 | M76: =SUM( M74:M75) -> 0
C78: Subordinated Notes interest expenses
E80: Effective interest rate on Subordinated Notes | F80: % | H80: =CaseData!$I$19 -> 0.07125 | I80: =CaseData!$I$19 -> 0.07125 | J80: =CaseData!$I$19 -> 0.07125 | K80: =CaseData!$I$19 -> 0.07125 | L80: =CaseData!$I$19 -> 0.07125 | M80: =CaseData!$I$19 -> 0.07125
E81: Subordinated Notes interest accrued | F81: USD | H81: =H$74 * H$80 / 12 -> 2968.75 | I81: =I$74 * I$80 / 12 -> 2968.75 | J81: =J$74 * J$80 / 12 -> 2968.75 | K81: =K$74 * K$80 / 12 -> 0 | L81: =L$74 * L$80 / 12 -> 0 | M81: =M$74 * M$80 / 12 -> 0
E83: Call price | F83: % | H83: =IF( H$3 <= CaseData!$H$24, CaseData!$I$24, IF( OR( H$3 > CaseData!$H$24, H$3 < CaseData!$H$25 ), CaseData!$I$25, 0 ) ) -> 1.03 | I83: =IF( I$3 <= CaseData!$H$24, CaseData!$I$24, IF( OR( I$3 > CaseData!$H$24, I$3 < CaseData!$H$25 ), CaseData!$I$25, 0 ) ) -> 1.03 | J83: =IF( J$3 <= CaseData!$H$24, CaseData!$I$24, IF( OR( J$3 > CaseData!$H$24, J$3 < CaseData!$H$25 ), CaseData!$I$25, 0 ) ) -> 1.03 | K83: =IF( K$3 <= CaseData!$H$24, CaseData!$I$24, IF( OR( K$3 > CaseData!$H$24, K$3 < CaseData!$H$25 ), CaseData!$I$25, 0 ) ) -> 1.02 | L83: =IF( L$3 <= CaseData!$H$24, CaseData!$I$24, IF( OR( L$3 > CaseData!$H$24, L$3 < CaseData!$H$25 ), CaseData!$I$25, 0 ) ) -> 1.02 | M83: =IF( M$3 <= CaseData!$H$24, CaseData!$I$24, IF( OR( M$3 > CaseData!$H$24, M$3 < CaseData!$H$25 ), CaseData!$I$25, 0 ) ) -> 1.02
E84: Cash Needed to Refinance | F84: USD | H84: =H$75 * H$83 * - 1 -> 0 | I84: =I$75 * I$83 * - 1 -> 0 | J84: =J$75 * J$83 * - 1 -> 515000 | K84: =K$75 * K$83 * - 1 -> 0 | L84: =L$75 * L$83 * - 1 -> 0 | M84: =M$75 * M$83 * - 1 -> 0
E85: Subordinated Notes interest expenses | F85: USD | H85: =IF( H$84 > 0, H$81 * COUNT( $H81:H81 ), 0 ) -> 0 | I85: =IF( I$84 > 0, I$81 * COUNT( $H81:I81 ), 0 ) -> 0 | J85: =IF( J$84 > 0, J$81 * COUNT( $H81:J81 ), 0 ) -> 8906.25 | K85: =IF( K$84 > 0, K$81 * COUNT( $H81:K81 ), 0 ) -> 0 | L85: =IF( L$84 > 0, L$81 * COUNT( $H81:L81 ), 0 ) -> 0 | M85: =IF( M$84 > 0, M$81 * COUNT( $H81:M81 ), 0 ) -> 0
E86: ( payable semi-annually)
A89: New Subordinated Notes
E92: New Subordinated Notes opening balance | F92: USD | H92: =G$94 -> 0 | I92: =H$94 -> 0 | J92: =I$94 -> 0 | K92: =J$94 -> 515000 | L92: =K$94 -> 515000 | M92: =L$94 -> 515000
E93: Subordinated Notes issue / (repayment) | F93: USD | H93: =IF( H$84 > 0, H$84, 0 ) -> 0 | I93: =IF( I$84 > 0, I$84, 0 ) -> 0 | J93: =IF( J$84 > 0, J$84, 0 ) -> 515000 | K93: =IF( K$84 > 0, K$84, 0 ) -> 0 | L93: =IF( L$84 > 0, L$84, 0 ) -> 0 | M93: =IF( M$84 > 0, M$84, 0 ) -> 0
E94: New Subordinated Notes closing balance | F94: USD | G94: 0 | H94: =SUM( H92:H93) -> 0 | I94: =SUM( I92:I93) -> 0 | J94: =SUM( J92:J93) -> 515000 | K94: =SUM( K92:K93) -> 515000 | L94: =SUM( L92:L93) -> 515000 | M94: =SUM( M92:M93) -> 515000
C96: New Subordinated Notes interest expenses
E98: Effective interest rate on New Subordinated Notes | F98: % | H98: {=_xlfn.XLOOKUP( H$3,_xlfn.ANCHORARRAY( CaseData!$N$18), CaseData!$P$18:$P$23,, -1 )} -> 0.0505 | I98: {=_xlfn.XLOOKUP( I$3,_xlfn.ANCHORARRAY( CaseData!$N$18), CaseData!$P$18:$P$23,, -1 )} -> 0.0525 | J98: {=_xlfn.XLOOKUP( J$3,_xlfn.ANCHORARRAY( CaseData!$N$18), CaseData!$P$18:$P$23,, -1 )} -> 0.057 | K98: {=_xlfn.XLOOKUP( K$3,_xlfn.ANCHORARRAY( CaseData!$N$18), CaseData!$P$18:$P$23,, -1 )} -> 0.0595 | L98: {=_xlfn.XLOOKUP( L$3,_xlfn.ANCHORARRAY( CaseData!$N$18), CaseData!$P$18:$P$23,, -1 )} -> 0.0615 | M98: {=_xlfn.XLOOKUP( M$3,_xlfn.ANCHORARRAY( CaseData!$N$18), CaseData!$P$18:$P$23,, -1 )} -> 0.064
E99: New Subordinated Notes interest expenses accrued | F99: USD | H99: =H$92 * H$98 / 12 -> 0 | I99: =I$92 * I$98 / 12 -> 0 | J99: =J$92 * J$98 / 12 -> 0 | K99: =K$92 * K$98 / 12 -> 2553.5417 | L99: =L$92 * L$98 / 12 -> 2639.375 | M99: =M$92 * M$98 / 12 -> 2746.6667
E101: New Subordinated Notes interest expenses | F101: USD | H101: =IF( H$84 > 0, H$99 * COUNT( $H99:H99 ), 0 ) -> 0 | I101: =IF( I$84 > 0, I$99 * COUNT( $H99:I99 ), 0 ) -> 0 | J101: =IF( J$84 > 0, J$99 * COUNT( $H99:J99 ), 0 ) -> 0 | K101: =IF( K$84 > 0, K$99 * COUNT( $H99:K99 ), 0 ) -> 0 | L101: =IF( L$84 > 0, L$99 * COUNT( $H99:L99 ), 0 ) -> 0 | M101: =IF( M$84 > 0, M$99 * COUNT( $H99:M99 ), 0 ) -> 0
E102: ( payable semi-annually)
A105: Interest expenses
E108: =E$49 -> Revolver interest expenses | F108: =F$49 -> USD | H108: =H$49 -> 79.587375 | I108: =I$49 -> 70.172621 | J108: =J$49 -> 65.195861 | K108: =K$49 -> 33.333333 | L108: =L$49 -> 33.333333 | M108: =M$49 -> 33.333333
E109: =E$67 -> Senior Secured Term Loan interest expenses | F109: =F$67 -> USD | H109: =H$67 -> 762.89062 | I109: =I$67 -> 767.7041 | J109: =J$67 -> 772.27804 | K109: =K$67 -> 776.61768 | L109: =L$67 -> 780.72815 | M109: =M$67 -> 777.79178
E110: =E$81 -> Subordinated Notes interest accrued | F110: =F$81 -> USD | H110: =H$81 -> 2968.75 | I110: =I$81 -> 2968.75 | J110: =J$81 -> 2968.75 | K110: =K$81 -> 0 | L110: =L$81 -> 0 | M110: =M$81 -> 0
E111: =E$99 -> New Subordinated Notes interest expenses accrued | F111: =F$99 -> USD | H111: =H$99 -> 0 | I111: =I$99 -> 0 | J111: =J$99 -> 0 | K111: =K$99 -> 2553.5417 | L111: =L$99 -> 2639.375 | M111: =M$99 -> 2746.6667
E112: Interest expenses accrued | F112: USD | H112: =SUM(H108:H111) -> 3811.228 | I112: =SUM(I108:I111) -> 3806.6267 | J112: =SUM(J108:J111) -> 3806.2239 | K112: =SUM(K108:K111) -> 3363.4927 | L112: =SUM(L108:L111) -> 3453.4365 | M112: =SUM(M108:M111) -> 3557.7918
A115: Interest paid
E118: =E$49 -> Revolver interest expenses | F118: =F$49 -> USD | H118: =H$49 -> 79.587375 | I118: =I$49 -> 70.172621 | J118: =J$49 -> 65.195861 | K118: =K$49 -> 33.333333 | L118: =L$49 -> 33.333333 | M118: =M$49 -> 33.333333
E119: =E$67 -> Senior Secured Term Loan interest expenses | F119: =F$67 -> USD | H119: =H$67 -> 762.89062 | I119: =I$67 -> 767.7041 | J119: =J$67 -> 772.27804 | K119: =K$67 -> 776.61768 | L119: =L$67 -> 780.72815 | M119: =M$67 -> 777.79178
E120: =E$85 -> Subordinated Notes interest expenses | F120: =F$85 -> USD | H120: =H$85 -> 0 | I120: =I$85 -> 0 | J120: =J$85 -> 8906.25 | K120: =K$85 -> 0 | L120: =L$85 -> 0 | M120: =M$85 -> 0
E121: =E$101 -> New Subordinated Notes interest expenses | F121: =F$99 -> USD | H121: =H$101 -> 0 | I121: =I$101 -> 0 | J121: =J$101 -> 0 | K121: =K$101 -> 0 | L121: =L$101 -> 0 | M121: =M$101 -> 0
E122: Interest paid | F122: USD | H122: =SUM(H118:H121) -> 842.478 | I122: =SUM(I118:I121) -> 837.87672 | J122: =SUM(J118:J121) -> 9743.7239 | K122: =SUM(K118:K121) -> 809.95101 | L122: =SUM(L118:L121) -> 814.06149 | M122: =SUM(M118:M121) -> 811.12512
A125: Principal additions / (repayments)
E128: =E$56 -> Senior Secured Term Loan drawdown / (repayments) | F128: =F$56 -> USD | H128: =H$56 -> -2179.6875 | I128: =I$56 -> -2152.4414 | J128: =J$56 -> -2125.5359 | K128: =K$56 -> -2098.9667 | L128: =L$56 -> -2072.7296 | M128: =M$56 -> -2046.8205
E129: =E$75 -> Subordinated Notes drawdown / (repayment) | F129: =F$75 -> USD | H129: =H$75 -> 0 | I129: =I$75 -> 0 | J129: =J$75 -> -500000 | K129: =K$75 -> 0 | L129: =L$75 -> 0 | M129: =M$75 -> 0
E130: =E$93 -> Subordinated Notes issue / (repayment) | F130: =F$93 -> USD | H130: =H$93 -> 0 | I130: =I$93 -> 0 | J130: =J$93 -> 515000 | K130: =K$93 -> 0 | L130: =L$93 -> 0 | M130: =M$93 -> 0
E131: Principal additions / (repayments) | F131: =F$93 -> USD | H131: =SUM(H128:H130) -> -2179.6875 | I131: =SUM(I128:I130) -> -2152.4414 | J131: =SUM(J128:J130) -> 12874.464 | K131: =SUM(K128:K130) -> -2098.9667 | L131: =SUM(L128:L130) -> -2072.7296 | M131: =SUM(M128:M130) -> -2046.8205
A134: Total Debt
E137: =E$38 -> Revolver closing balance | F137: =F$38 -> USD | G137: =G$38 -> 12473 | H137: =H$38 -> 9715.856 | I137: =I$38 -> 8222.5877 | J137: =J$38 -> 0 | K137: =K$38 -> 0 | L137: =L$38 -> 0 | M137: =M$38 -> 406.10757
E138: =E$57 -> Senior Secured Term Loan closing balance | F138: =F$57 -> USD | G138: =G$57 -> 174375 | H138: =H$57 -> 172195.31 | I138: =I$57 -> 170042.87 | J138: =J$57 -> 167917.34 | K138: =K$57 -> 165818.37 | L138: =L$57 -> 163745.64 | M138: =M$57 -> 161698.82
E139: =E$76 -> Subordinated Notes closing balance | F139: =F$76 -> USD | G139: =G$76 -> 500000 | H139: =H$76 -> 500000 | I139: =I$76 -> 500000 | J139: =J$76 -> 0 | K139: =K$76 -> 0 | L139: =L$76 -> 0 | M139: =M$76 -> 0
E140: =E$94 -> New Subordinated Notes closing balance | F140: =F$94 -> USD | G140: =G$94 -> 0 | H140: =H$94 -> 0 | I140: =I$94 -> 0 | J140: =J$94 -> 515000 | K140: =K$94 -> 515000 | L140: =L$94 -> 515000 | M140: =M$94 -> 515000
E141: Total Debt | F141: USD | H141: =SUM(H137:H140) -> 681911.17 | I141: =SUM(I137:I140) -> 678265.46 | J141: =SUM(J137:J140) -> 682917.34 | K141: =SUM(K137:K140) -> 680818.37 | L141: =SUM(L137:L140) -> 678745.64 | M141: =SUM(M137:M140) -> 677104.93
A144: Interest Coverage Ratio (ICR)
E147: TTM EBIDTA | F147: USD | H147: =CaseData!E$63 -> 193220 | I147: =CaseData!F$63 -> 189600 | J147: =CaseData!G$63 -> 186312 | K147: =CaseData!H$63 -> 185545 | L147: =CaseData!I$63 -> 185313 | M147: =CaseData!J$63 -> 183795
E148: TTM Capex | F148: USD | H148: =CaseData!E$64 -> 81423 | I148: =CaseData!F$64 -> 63499 | J148: =CaseData!G$64 -> 89256 | K148: =CaseData!H$64 -> 86777 | L148: =CaseData!I$64 -> 77656 | M148: =CaseData!J$64 -> 83704
E149: =E$161 -> TTM Interest expenses | F149: =F$161 -> USD | H149: =H$161 -> 46899.411 | I149: =I$161 -> 46794.687 | J149: =J$161 -> 46583.153 | K149: =K$161 -> 41431.273 | L149: =L$161 -> 42295.894 | M149: =M$161 -> 43424.491
E150: Interest Coverage Ratio (ICR) | F150: USD | H150: =( H147 - H148 ) / H149 -> 2.3837613 | I150: =( I147 - I148 ) / I149 -> 2.6947718 | J150: =( J147 - J148 ) / J149 -> 2.0835 | K150: =( K147 - K148 ) / K149 -> 2.3838997 | L150: =( L147 - L148 ) / L149 -> 2.5453298 | M150: =( M147 - M148 ) / M149 -> 2.3049435
E152: Mandatory ICR | F152: multiple | G152: =CaseData!$E$13 -> 2.25
E153: EBITDA Cushion | F153: USD | H153: =H$147 - ( $G$152 * H$149 + H$148 ) -> 6273.3252 | I153: =I$147 - ( $G$152 * I$149 + I$148 ) -> 20812.955 | J153: =J$147 - ( $G$152 * J$149 + J$148 ) -> -7756.0934 | K153: =K$147 - ( $G$152 * K$149 + K$148 ) -> 5547.6366 | L153: =L$147 - ( $G$152 * L$149 + L$148 ) -> 12491.238 | M153: =M$147 - ( $G$152 * M$149 + M$148 ) -> 2385.8947
C155: TTM Interest expenses
E157: Revolver interest expenses | F157: USD | H157: {=_xlfn.LET( _xlpm.historicals, CaseData!$E$31:$S$31 + CaseData!$E$32:$S$32, _xlpm.forecast, Debt!$H$118:$M$118, _xlpm.hist_count, COLUMNS( _xlpm.historicals ), _xlpm.fcst_count, COLUMNS( _xlpm.forecast ), _xlpm.full, _xlfn.HSTACK( _xlpm.historicals, _xlpm.forecast ), _xlfn.MAKEARRAY( 1, _xlpm.fcst_count, _xlfn.LAMBDA(_xlpm.i,_xlpm.j, SUM( _xlfn.TAKE( _xlfn.TAKE( _xlpm.full, , _xlpm.hist_count + _xlpm.j ), , -12 ) ) ) ) )} -> 1360.1014 | I157: 1353.407 | J157: 1302.1079 | K157: 1206.9452 | L157: 1096.0805 | M157: 1025.7129
E158: Senior Secured Term Loan interest expenses | F158: USD | H158: {=_xlfn.LET( _xlpm.historicals, CaseData!$E$36:$S$36, _xlpm.forecast, Debt!$H$119:$M$119, _xlpm.hist_count, COLUMNS( _xlpm.historicals ), _xlpm.fcst_count, COLUMNS( _xlpm.forecast ), _xlpm.full, _xlfn.HSTACK( _xlpm.historicals, _xlpm.forecast ), _xlfn.MAKEARRAY( 1, _xlpm.fcst_count, _xlfn.LAMBDA(_xlpm.i,_xlpm.j, SUM( _xlfn.TAKE( _xlfn.TAKE( _xlpm.full, , _xlpm.hist_count + _xlpm.j ), , -12 ) ) ) ) )} -> 9914.3096 | I158: 9816.2797 | J158: 9656.0448 | K158: 9581.8274 | L158: 9527.3136 | M158: 9438.7784
E159: Subordinated Notes interest expenses | F159: USD | H159: =H$81 * 12 -> 35625 | I159: =I$81 * 12 -> 35625 | J159: =J$81 * 12 -> 35625 | K159: =K$81 * 12 -> 0 | L159: =L$81 * 12 -> 0 | M159: =M$81 * 12 -> 0
E160: New Subordinated Notes interest expenses | F160: USD | H160: =H$99 * 12 -> 0 | I160: =I$99 * 12 -> 0 | J160: =J$99 * 12 -> 0 | K160: =K$99 * 12 -> 30642.5 | L160: =L$99 * 12 -> 31672.5 | M160: =M$99 * 12 -> 32960
E161: TTM Interest expenses | F161: USD | H161: =SUM(H157:H160) -> 46899.411 | I161: =SUM(I157:I160) -> 46794.687 | J161: =SUM(J157:J160) -> 46583.153 | K161: =SUM(K157:K160) -> 41431.273 | L161: =SUM(L157:L160) -> 42295.894 | M161: =SUM(M157:M160) -> 43424.491
A164: Answers
C166: d) | E166: In which refinincing scenarios does the minimum ICR occur? | M166: 43465
I167: Refinancing date | J167: =MIN( H153:M153 ) -> -7756.0934 | K167: =MIN(H150:M150 ) -> 2.0835
E168: {=TRANSPOSE(_xlfn.ANCHORARRAY( H3) )} -> 43404 | F168: =IF( J168 = $J$167, "✓","X") -> X | I168: 43404 | J168: 2540.4738 | K168: 2.308596
...

Sheet CaseData
B1: Streamwise Ltd.
B2: (in thousands of $)
B4: Existing Debt as at Sep. 30, 2018
B6: Revolving Credit Facility:
B7: Max. Amount | E7: 50000 | G7: Annual Drawn Rates | K7: Cash Taxes
B8: Balance Outstanding | E8: 12473 | G8: payable monthly based on prev. month | K8: 0.25
G9: Total Debt / | I9: Spread to
B10: Annual Undrawn Rate | E10: 80 | G10: EBITDA >= | I10: LIBOR
B11: (payable monthly) | G11: 0 | I11: 100
G12: 2 | I12: 175
B13: Interest Coverage Ratio | E13: 2.25 | G13: 3 | I13: 225
G14: 3.5 | I14: 300
B16: Senior Secured Term Loan: | G16: Subordinated Notes:
B17: Balance Outstanding | E17: 174375 | G17: Face Amount | I17: 500000 | K17: Call Date | N17: Annual Coupons:
B18: Original Amount | E18: 225000 | G18: Amortization | I18: 0 | N18: {=TRANSPOSE( E62:J62)} -> 43404 | P18: 0.0505
G19: Annual Coupon | I19: 0.07125 | N19: 43434 | P19: 0.0525
B20: Monthy Amortization | E20: 0.0125 | G20: Payable semi-annually on: | I20: Sep. 30 | N20: 43465 | P20: 0.057
I21: Mar. 31 | N21: 43496 | P21: 0.0595
B22: Annual Drawn Rate | E22: Same | G22: Final Maturity | I22: Mar. 31, 2019 | N22: 43524 | P22: 0.0615
B23: (payable monthly) | E23: as revolver | G23: Early Call Prices: | N23: 43555 | P23: 0.064
G24: On or before | H24: 43465 | I24: 1.03
B25: Final Maturity | E25: Jun. 30, 2022 | G25: Before | H25: 43555 | I25: 1.02 | N25: Payable semi-annually on: | P25: =EOMONTH(Debt!M166,6) -> 43646
P26: =EOMONTH(P25,6) -> 43830
B27: Historical Debt Details
B29: Revolving Credit Facility: | E29: 42947 | F29: 42978 | G29: 43008 | H29: 43039 | I29: 43069 | J29: 43100 | K29: 43131 | L29: 43159 | M29: 43190 | N29: 43220 | O29: 43251 | P29: 43281 | Q29: 43312 | R29: 43343 | S29: 43373 | T29: =EOMONTH(S29,1) -> 43404 | U29: =EOMONTH(T29,1) -> 43434 | V29: =EOMONTH(U29,1) -> 43465 | W29: =EOMONTH(V29,1) -> 43496 | X29: =EOMONTH(W29,1) -> 43524 | Y29: =EOMONTH(X29,1) -> 43555
B30: Ending Balance | D30: 10029 | E30: 5395 | F30: 11094 | G30: 12111 | H30: 12263 | I30: 21116 | J30: 26477 | K30: 31004 | L30: 18530 | M30: 8274 | N30: 31247 | O30: 33481 | P30: 15891 | Q30: 36380 | R30: 13877 | S30: 12473 | T30: =MAX(S30-E77,0) -> 10348.668 | U30: =MAX(T30-F77,0) -> 9287.7534 | V30: =MAX(U30-G77,0) -> 9964.186 | W30: =MAX(V30-H77,0) -> 6523.832 | X30: =MAX(W30-I77,0) -> 1475.4315 | Y30: =MAX(X30-J77,0) -> 377.27158
B31: Drawn Interest | E31: 44.337 | F31: 24.929 | G31: 49.137 | H31: 53.884 | I31: 51.709 | J31: 97.239 | K31: 112.814 | L31: 131.534 | M31: 82.721 | N31: 36.771 | O31: 130.274 | P31: 141.792 | Q31: 68.583 | R31: 165.832 | S31: 60.272 | T31: =S$30*T$57*(30/360) -> 54.569375 | U31: =T$30*U$57*(30/360) -> 28.890033 | V31: =U$30*V$57*(30/360) -> 26.702291 | W31: =V$30*W$57*(30/360) -> 29.477383 | X31: =W$30*X$57*(30/360) -> 19.843322 | Y31: =X$30*Y$57*(30/360) -> 4.549247
B32: Undrawn Interest | E32: 26.647 | F32: 29.737 | G32: 25.937 | H32: 25.259 | I32: 25.158 | J32: 19.256 | K32: 15.682 | L32: 12.664 | M32: 20.98 | N32: 27.817 | O32: 12.502 | P32: 11.013 | Q32: 22.739 | R32: 9.08 | S32: 24.082 | T32: =($E$7-S$30)*$E$10/10000*(30/360) -> 25.018 | U32: =($E$7-T$30)*$E$10/10000*(30/360) -> 26.434221 | V32: =($E$7-U$30)*$E$10/10000*(30/360) -> 27.141498 | W32: =($E$7-V$30)*$E$10/10000*(30/360) -> 26.690543 | X32: =($E$7-W$30)*$E$10/10000*(30/360) -> 28.984112 | Y32: =($E$7-X$30)*$E$10/10000*(30/360) -> 32.349712
B34: Senior Secured Term Loan:
B35: Ending Balance | D35: 216562.5 | E35: 213750 | F35: 210937.5 | G35: 208125 | H35: 205312.5 | I35: 202500 | J35: 199687.5 | K35: 196875 | L35: 194062.5 | M35: 191250 | N35: 188437.5 | O35: 185625 | P35: 182812.5 | Q35: 180000 | R35: 177187.5 | S35: 174375 | T35: =S35-(R35-S35) -> 171562.5 | U35: =T35-(S35-T35) -> 168750 | V35: =U35-(T35-U35) -> 165937.5 | W35: =V35-(U35-V35) -> 163125 | X35: =W35-(V35-W35) -> 160312.5 | Y35: =X35-(W35-X35) -> 157500
B36: Interest | E36: 957.387 | F36: 987.703 | G36: 934.277 | H36: 925.983 | I36: 865.734 | J36: 932.513 | K36: 850.835 | L36: 835.242 | M36: 866.327 | N36: 849.947 | O36: 785.627 | P36: 786.122 | Q36: 788.988 | R36: 820.5 | S36: 769.584 | T36: =(30/360)*T57*S35 -> 762.89062 | U36: =(30/360)*U57*T35 -> 478.94531 | V36: =(30/360)*V57*U35 -> 485.15625 | W36: =(30/360)*W57*V35 -> 490.89844 | X36: =(30/360)*X57*W35 -> 496.17187 | Y36: =(30/360)*Y57*X35 -> 494.29687
B38: Principal Repayment | E38: =D35-E35 -> 2812.5 | F38: =E35-F35 -> 2812.5 | G38: =F35-G35 -> 2812.5 | H38: =G35-H35 -> 2812.5 | I38: =H35-I35 -> 2812.5 | J38: =I35-J35 -> 2812.5 | K38: =J35-K35 -> 2812.5 | L38: =K35-L35 -> 2812.5 | ... Y38: =X35-Y35 -> 2812.5
B40: Subordinated Notes:
B41: Ending Balance | D41: 500000 | E41: 500000 | F41: 500000 | G41: 500000 | H41: 500000 | I41: 500000 | J41: 500000 | K41: 500000 | L41: 500000 | M41: 500000 | N41: 500000 | O41: 500000 | P41: 500000 | Q41: 500000 | R41: 500000 | S41: 500000 | T41: =IF(Debt!$M$166<T29,0,S41) -> 500000 | U41: =IF(Debt!$M$166<U29,0,T41) -> 500000 | V41: =IF(Debt!$M$166<V29,0,U41) -> 500000 | W41: =IF(Debt!$M$166<W29,0,V41) -> 0 | X41: =IF(Debt!$M$166<X29,0,W41) -> 0 | Y41: =IF(Debt!$M$166<Y29,0,X41) -> 0
B42: Interest | E42: 2968.75 | F42: 2968.75 | G42: 2968.75 | H42: 2968.75 | I42: 2968.75 | J42: 2968.75 | K42: 2968.75 | L42: 2968.75 | M42: 2968.75 | N42: 2968.75 | O42: 2968.75 | P42: 2968.75 | Q42: 2968.75 | R42: 2968.75 | S42: 2968.75 | T42: =IF(T41=0,0,S42) -> 2968.75 | U42: =IF(U41=0,0,T42) -> 2968.75 | V42: =IF(V41=0,0,U42) -> 2968.75 | W42: =IF(W41=0,0,V42) -> 0 | X42: =IF(X41=0,0,W42) -> 0 | Y42: =IF(Y41=0,0,X42) -> 0
B43: Interest Paid | G43: =SUM(B42:G42) -> 8906.25 | M43: =SUM(H42:M42) -> 17812.5 | S43: =SUM(N42:S42) -> 17812.5
B44: Call Payment | T44: =IF(T$29=Debt!$M$166,T$41*$I$24,0) -> 0 | U44: =IF(U$29=Debt!$M$166,U$41*$I$24,0) -> 0 | V44: =IF(V$29=Debt!$M$166,V$41*$I$24,0) -> 515000 | W44: =IF(W$29=Debt!$M$166,W$41*$I$25,0) -> 0 | X44: =IF(X$29=Debt!$M$166,X$41*$I$25,0) -> 0 | Y44: =IF(Y$29=Debt!$M$166,Y$41,0) -> 0
B46: Model start date | D46: 43404 | E46: date
B47: Number of periods | D47: 6 | E47: months
B48: Topic | D48: Debt
B52: Total Debt | D52: 726591.5 | E52: 719145 | F52: 722031.5 | G52: 720236 | H52: 717575.5 | I52: 723616 | J52: 726164.5 | K52: 727879 | L52: 712592.5 | M52: 699524 | N52: 719684.5 | O52: 719106 | P52: 698703.5 | Q52: 716380 | R52: 691064.5 | S52: 686848 | T52: =SUM(T35,T30,T40) -> 181911.17 | U52: =SUM(U35,U30,U40) -> 178037.75 | V52: =SUM(V35,V30,V40) -> 175901.69 | W52: =SUM(W35,W30,W40) -> 169648.83 | X52: =SUM(X35,X30,X40) -> 161787.93 | Y52: =SUM(Y35,Y30,Y40) -> 157877.27
B53: TTM EBITDA | D53: 183244 | E53: 191930 | F53: 199032 | G53: 175519 | H53: 170868 | I53: 156913 | J53: 179890 | K53: 174023 | L53: 198141 | M53: 191052 | N53: 189901 | O53: 165475 | P53: 198550 | Q53: 187963 | R53: 180401 | S53: 191177 | T53: =E63 -> 193220 | U53: =F63 -> 189600 | V53: =G63 -> 186312 | W53: =H63 -> 185545 | X53: =I63 -> 185313 | Y53: =J63 -> 183795
B54: Total Debt / EBITDA | D54: 3.9651585 | E54: 3.7469129 | F54: 3.6277156 | G54: 4.1034646 | H54: 4.1995897 | I54: 4.6115746 | J54: 4.0367141 | K54: 4.1826598 | L54: 3.596391 | M54: 3.6614325 | N54: 3.7897878 | O54: 4.3457078 | P54: 3.5190305 | Q54: 3.811282 | R54: 3.8307132 | S54: 3.5927334 | T54: =T52/T53 -> 0.94147173 | U54: =U52/U53 -> 0.93901769 | V54: =V52/V53 -> 0.9441243 | W54: =W52/W53 -> 0.91432716 | X54: =X52/X53 -> 0.87305225 | Y54: =Y52/Y53 -> 0.85898567
B55: LIBOR | D55: 0.02317 | E55: 0.02305 | F55: 0.02545 | G55: 0.02315 | H55: 0.02339 | I55: 0.0206 | J55: 0.02526 | K55: 0.02113 | L55: 0.02091 | M55: 0.02357 | N55: 0.02333 | O55: 0.02003 | P55: 0.02082 | Q55: 0.02179 | R55: 0.0247 | S55: 0.02212 | T55: =E66 -> 0.0225 | U55: =F66 -> 0.0235 | V55: =G66 -> 0.0245 | W55: =H66 -> 0.0255 | X55: =I66 -> 0.0265 | Y55: =J66 -> 0.027
B56: Spread | E56: 0.03 | F56: 0.03 | G56: 0.03 | H56: 0.03 | I56: 0.03 | J56: 0.03 | K56: 0.03 | L56: 0.03 | M56: 0.03 | N56: 0.03 | O56: 0.03 | P56: 0.03 | Q56: 0.03 | R56: 0.03 | S56: 0.03 | T56: =VLOOKUP(S$54,$G$11:$I$14,3,TRUE)/10000 -> 0.03 | U56: =VLOOKUP(T$54,$G$11:$I$14,3,TRUE)/10000 -> 0.01 | V56: =VLOOKUP(U$54,$G$11:$I$14,3,TRUE)/10000 -> 0.01 | W56: =VLOOKUP(V$54,$G$11:$I$14,3,TRUE)/10000 -> 0.01 | X56: =VLOOKUP(W$54,$G$11:$I$14,3,TRUE)/10000 -> 0.01 | Y56: =VLOOKUP(X$54,$G$11:$I$14,3,TRUE)/10000 -> 0.01
B57: Rate | E57: 0.05305 | F57: 0.05545 | G57: 0.05315 | H57: 0.05339 | I57: 0.0506 | J57: 0.05526 | K57: 0.05113 | L57: 0.05091 | M57: 0.05357 | N57: 0.05333 | O57: 0.05003 | P57: 0.05082 | Q57: 0.05179 | R57: 0.0547 | S57: 0.05212 | T57: =SUM(T55:T56) -> 0.0525 | U57: =SUM(U55:U56) -> 0.0335 | V57: =SUM(V55:V56) -> 0.0345 | W57: =SUM(W55:W56) -> 0.0355 | X57: =SUM(X55:X56) -> 0.0365 | Y57: =SUM(Y55:Y56) -> 0.037
B60: Forecasted Data
E62: 43404 | F62: 43434 | G62: 43465 | H62: 43496 | I62: 43524 | J62: 43555
B63: TTM EBITDA | E63: 193220 | F63: 189600 | G63: 186312 | H63: 185545 | I63: 185313 | J63: 183795
B64: TTM Capex | E64: 81423 | F64: 63499 | G64: 89256 | H64: 86777 | I64: 77656 | J64: 83704
B65: Free Cash Flow Before Debt Service & Taxes | E65: 10393.67 | F65: 8667.573 | G65: 6355.84 | H65: 8884.205 | I65: 11026.2 | J65: 5745.409
B66: LIBOR | E66: 0.0225 | F66: 0.0235 | G66: 0.0245 | H66: 0.0255 | I66: 0.0265 | J66: 0.027
B68: Cashflow
B70: Free Cash Flow Before Debt Service & Taxes | E70: =E65 -> 10393.67 | F70: =F65 -> 8667.573 | G70: =G65 -> 6355.84 | H70: =H65 -> 8884.205 | I70: =I65 -> 11026.2 | J70: =J65 -> 5745.409
B71: Senior Debt - Principal Payment | E71: =-$E$38 -> -2812.5 | F71: =-$E$38 -> -2812.5 | G71: =-$E$38 -> -2812.5 | H71: =-$E$38 -> -2812.5 | I71: =-$E$38 -> -2812.5 | J71: =-$E$38 -> -2812.5
B72: Senior Debt - Interest Payment | E72: =-T36 -> -762.89062 | F72: =-U36 -> -478.94531 | G72: =-V36 -> -485.15625 | H72: =-W36 -> -490.89844 | I72: =-X36 -> -496.17187 | J72: =-Y36 -> -494.29687
B73: Subordinated Notes Interest | E73: =-T42 -> -2968.75 | F73: =-U42 -> -2968.75 | G73: =-V42 -> -2968.75 | H73: =-W42 -> 0 | I73: =-X42 -> 0 | J73: =-Y42 -> 0
B74: Revolver Interest | E74: =-SUM(T31:T32) -> -79.587375 | F74: =-SUM(U31:U32) -> -55.324254 | G74: =-SUM(V31:V32) -> -53.843789 | H74: =-SUM(W31:W32) -> -56.167926 | I74: =-SUM(X31:X32) -> -48.827434 | J74: =-SUM(Y31:Y32) -> -36.898959
B75: Cash flow before tax | E75: =SUM(E70:E74) -> 3769.942 | F75: =SUM(F70:F74) -> 2352.0534 | G75: =SUM(G70:G74) -> 35.589961 | H75: =SUM(H70:H74) -> 5524.6386 | I75: =SUM(I70:I74) -> 7668.7007 | J75: =SUM(J70:J74) -> 2401.7132
B76: Tax | E76: =-E84 -> -1645.6105 | F76: =-F84 -> -1291.1384 | G76: =-G84 -> -712.02249 | H76: =-H84 -> -2084.2847 | I76: =-I84 -> -2620.3002 | J76: =-J84 -> -1303.5533
B77: Net Cash Inflow | E77: =SUM(E75:E76) -> 2124.3315 | F77: =SUM(F75:F76) -> 1060.9151 | G77: =SUM(G75:G76) -> -676.43253 | H77: =SUM(H75:H76) -> 3440.354 | I77: =SUM(I75:I76) -> 5048.4005 | J77: =SUM(J75:J76) -> 1098.1599
B79: Tax Expense
B81: Free Cash Flow Before Debt Service & Taxes | E81: =E70 -> 10393.67 | F81: =F70 -> 8667.573 | G81: =G70 -> 6355.84 | H81: =H70 -> 8884.205 | I81: =I70 -> 11026.2 | J81: =J70 -> 5745.409
B82: Interest Expense | E82: =SUM(E72:E74) -> -3811.228 | F82: =SUM(F72:F74) -> -3503.0196 | G82: =SUM(G72:G74) -> -3507.75 | H82: =SUM(H72:H74) -> -547.06636 | I82: =SUM(I72:I74) -> -544.99931 | J82: =SUM(J72:J74) -> -531.19583
B83: Taxable FCF | E83: =SUM(E81:E82) -> 6582.442 | F83: =SUM(F81:F82) -> 5164.5534 | G83: =SUM(G81:G82) -> 2848.09 | H83: =SUM(H81:H82) -> 8337.1386 | I83: =SUM(I81:I82) -> 10481.201 | J83: =SUM(J81:J82) -> 5214.2132
B84: Tax | E84: =E83*$K$8 -> 1645.6105 | F84: =F83*$K$8 -> 1291.1384 | G84: =G83*$K$8 -> 712.02249 | H84: =H83*$K$8 -> 2084.2847 | I84: =I83*$K$8 -> 2620.3002 | J84: =J83*$K$8 -> 1303.5533
B87: Interest (Accrued) for Tax

Sheet CaseSolution
B1: Streamwise Ltd.
B2: (in thousands of $)
B4: =CaseData!B4 -> Existing Debt as at Sep. 30, 2018
B6: Revolving Credit Facility:
B7: Max. Amount | E7: =CaseData!E7 -> 50000 | G7: Annual Drawn Rates | K7: Taxes
B8: Balance Outstanding | E8: =CaseData!E8 -> 12473 | G8: payable monthly based on prev. month
G9: Total Debt / | I9: Spread to | K9: Applicable Rate: | M9: 0.25
B10: Annual Undrawn Rate | E10: =CaseData!E10 -> 80 | G10: EBITDA >= | I10: LIBOR
B11: (payable monthly) | G11: =CaseData!G11 -> 0 | I11: =CaseData!I11 -> 100
G12: =CaseData!G12 -> 2 | I12: =CaseData!I12 -> 175
B13: Interest Coverage Ratio | E13: =CaseData!E13 -> 2.25 | G13: =CaseData!G13 -> 3 | I13: =CaseData!I13 -> 225
G14: =CaseData!G14 -> 3.5 | I14: =CaseData!I14 -> 300
B16: Senior Secured Term Loan: | G16: Subordinated Notes: | K16: New Senior Notes:
B17: Balance Outstanding | E17: =CaseData!E17 -> 174375 | G17: Face Amount | I17: =CaseData!I17 -> 500000 | K17: Date Issued | M17: 43465
B18: Original Amount | E18: =CaseData!E18 -> 225000 | G18: Amortization | I18: =CaseData!I18 -> 0 | K18: Annual Coupons:
G19: Annual Coupon | I19: =CaseData!I19 -> 0.07125 | K19: {=TRANSPOSE(E65:J65)} -> 43404 | M19: 0.0505
B20: Monthy Amortization | E20: =CaseData!E20 -> 0.0125 | G20: Payable semi-annually on: | I20: 43373 | K20: 43434 | M20: 0.0525
I21: =EOMONTH(I20,6) -> 43555 | K21: 43465 | M21: 0.057
B22: Annual Drawn Rate | E22: Same | G22: Final Maturity | I22: =I21 -> 43555 | K22: 43496 | M22: 0.0595
B23: (payable monthly) | E23: as revolver | G23: Period | H23: Date | I23: Call Prices | K23: 43524 | M23: 0.0615
G24: After | H24: =S31 -> 43373 | I24: 1.03 | K24: 43555 | M24: 0.064
B25: Final Maturity | E25: =CaseData!E25 -> Jun. 30, 2022 | G25: After | H25: 43465 | I25: 1.02
G26: After | H26: 43524 | I26: 1 | K26: Payable semi-annually on: | M26: =EOMONTH(M17,6) -> 43646
M27: =EOMONTH(M26,6) -> 43830
B29: Historical Debt Details
B31: =B6 -> Revolving Credit Facility: | E31: =CaseData!E29 -> 42947 | F31: =CaseData!F29 -> 42978 | G31: =CaseData!G29 -> 43008 | H31: =CaseData!H29 -> 43039 | I31: =CaseData!I29 -> 43069 | J31: =CaseData!J29 -> 43100 | K31: =CaseData!K29 -> 43131 | L31: =CaseData!L29 -> 43159 | ... S31: =CaseData!S29 -> 43373
B32: Ending Balance | D32: =CaseData!D30 -> 10029 | E32: =CaseData!E30 -> 5395 | F32: =CaseData!F30 -> 11094 | G32: =CaseData!G30 -> 12111 | H32: =CaseData!H30 -> 12263 | I32: =CaseData!I30 -> 21116 | J32: =CaseData!J30 -> 26477 | K32: =CaseData!K30 -> 31004 | ... S32: =CaseData!S30 -> 12473
B33: Drawn Interest | E33: =CaseData!E31 -> 44.337 | F33: =CaseData!F31 -> 24.929 | G33: =CaseData!G31 -> 49.137 | H33: =CaseData!H31 -> 53.884 | I33: =CaseData!I31 -> 51.709 | J33: =CaseData!J31 -> 97.239 | K33: =CaseData!K31 -> 112.814 | L33: =CaseData!L31 -> 131.534 | ... S33: =CaseData!S31 -> 60.272
B34: Undrawn Interest | E34: =CaseData!E32 -> 26.647 | F34: =CaseData!F32 -> 29.737 | G34: =CaseData!G32 -> 25.937 | H34: =CaseData!H32 -> 25.259 | I34: =CaseData!I32 -> 25.158 | J34: =CaseData!J32 -> 19.256 | K34: =CaseData!K32 -> 15.682 | L34: =CaseData!L32 -> 12.664 | ... S34: =CaseData!S32 -> 24.082
B35: Total Reveolver Interest | E35: =E33+E34 -> 70.984 | F35: =F33+F34 -> 54.666 | G35: =G33+G34 -> 75.074 | H35: =H33+H34 -> 79.143 | I35: =I33+I34 -> 76.867 | J35: =J33+J34 -> 116.495 | K35: =K33+K34 -> 128.496 | L35: =L33+L34 -> 144.198 | ... S35: =S33+S34 -> 84.354
B37: Senior Secured Term Loan:
B38: Ending Balance | D38: =CaseData!D35 -> 216562.5 | E38: =CaseData!E35 -> 213750 | F38: =CaseData!F35 -> 210937.5 | G38: =CaseData!G35 -> 208125 | H38: =CaseData!H35 -> 205312.5 | I38: =CaseData!I35 -> 202500 | J38: =CaseData!J35 -> 199687.5 | K38: =CaseData!K35 -> 196875 | ... S38: =CaseData!S35 -> 174375
B39: Interest | E39: =CaseData!E36 -> 957.387 | F39: =CaseData!F36 -> 987.703 | G39: =CaseData!G36 -> 934.277 | H39: =CaseData!H36 -> 925.983 | I39: =CaseData!I36 -> 865.734 | J39: =CaseData!J36 -> 932.513 | K39: =CaseData!K36 -> 850.835 | L39: =CaseData!L36 -> 835.242 | ... S39: =CaseData!S36 -> 769.584
B41: =G16 -> Subordinated Notes:
B42: Ending Balance | D42: =CaseData!D41 -> 500000 | E42: =CaseData!E41 -> 500000 | F42: =CaseData!F41 -> 500000 | G42: =CaseData!G41 -> 500000 | H42: =CaseData!H41 -> 500000 | I42: =CaseData!I41 -> 500000 | J42: =CaseData!J41 -> 500000 | K42: =CaseData!K41 -> 500000 | ... S42: =CaseData!S41 -> 500000
B43: Interest | E43: =CaseData!E42 -> 2968.75 | F43: =CaseData!F42 -> 2968.75 | G43: =CaseData!G42 -> 2968.75 | H43: =CaseData!H42 -> 2968.75 | I43: =CaseData!I42 -> 2968.75 | J43: =CaseData!J42 -> 2968.75 | K43: =CaseData!K42 -> 2968.75 | L43: =CaseData!L42 -> 2968.75 | ... S43: =CaseData!S42 -> 2968.75
B46: Total Debt | D46: =D32+D38+D42 -> 726591.5 | E46: =E32+E38+E42 -> 719145 | F46: =F32+F38+F42 -> 722031.5 | G46: =G32+G38+G42 -> 720236 | H46: =H32+H38+H42 -> 717575.5 | I46: =I32+I38+I42 -> 723616 | J46: =J32+J38+J42 -> 726164.5 | K46: =K32+K38+K42 -> 727879 | ... S46: =S32+S38+S42 -> 686848
B47: TTM EBITDA | D47: =CaseData!D53 -> 183244 | E47: =CaseData!E53 -> 191930 | F47: =CaseData!F53 -> 199032 | G47: =CaseData!G53 -> 175519 | H47: =CaseData!H53 -> 170868 | I47: =CaseData!I53 -> 156913 | J47: =CaseData!J53 -> 179890 | K47: =CaseData!K53 -> 174023 | ... S47: =CaseData!S53 -> 191177
B48: Total Debt / EBITDA | D48: =D46/D47 -> 3.9651585 | E48: =E46/E47 -> 3.7469129 | F48: =F46/F47 -> 3.6277156 | G48: =G46/G47 -> 4.1034646 | H48: =H46/H47 -> 4.1995897 | I48: =I46/I47 -> 4.6115746 | J48: =J46/J47 -> 4.0367141 | K48: =K46/K47 -> 4.1826598 | ... S48: =S46/S47 -> 3.5927334
B49: LIBOR | D49: =CaseData!D55 -> 0.02317 | E49: =CaseData!E55 -> 0.02305 | F49: =CaseData!F55 -> 0.02545 | G49: =CaseData!G55 -> 0.02315 | H49: =CaseData!H55 -> 0.02339 | I49: =CaseData!I55 -> 0.0206 | J49: =CaseData!J55 -> 0.02526 | K49: =CaseData!K55 -> 0.02113 | ... S49: =CaseData!S55 -> 0.02212
B50: Spread | E50: =CaseData!E56 -> 0.03 | F50: =CaseData!F56 -> 0.03 | G50: =CaseData!G56 -> 0.03 | H50: =CaseData!H56 -> 0.03 | I50: =CaseData!I56 -> 0.03 | J50: =CaseData!J56 -> 0.03 | K50: =CaseData!K56 -> 0.03 | L50: =CaseData!L56 -> 0.03 | ... S50: =CaseData!S56 -> 0.03
B51: Rate | E51: =E49+E50 -> 0.05305 | F51: =F49+F50 -> 0.05545 | G51: =G49+G50 -> 0.05315 | H51: =H49+H50 -> 0.05339 | I51: =I49+I50 -> 0.0506 | J51: =J49+J50 -> 0.05526 | K51: =K49+K50 -> 0.05113 | L51: =L49+L50 -> 0.05091 | ... S51: =S49+S50 -> 0.05212
B52: Total Interest | E52: =E33+E34+E39+E43 -> 3997.121 | F52: =F33+F34+F39+F43 -> 4011.119 | G52: =G33+G34+G39+G43 -> 3978.101 | H52: =H33+H34+H39+H43 -> 3973.876 | I52: =I33+I34+I39+I43 -> 3911.351 | J52: =J33+J34+J39+J43 -> 4017.758 | K52: =K33+K34+K39+K43 -> 3948.081 | L52: =L33+L34+L39+L43 -> 3948.19 | ... S52: =S33+S34+S39+S43 -> 3822.688
B55: Forecasted Data
D57: =CaseData!$S$29 -> 43373 | E57: =EOMONTH(S31,1) -> 43404 | F57: =EOMONTH(E57,1) -> 43434 | G57: =EOMONTH(F57,1) -> 43465 | H57: =EOMONTH(G57,1) -> 43496 | I57: =EOMONTH(H57,1) -> 43524 | J57: =EOMONTH(I57,1) -> 43555
B58: TTM EBITDA | D58: =CaseData!S53 -> 191177 | E58: =CaseData!E63 -> 193220 | F58: =CaseData!F63 -> 189600 | G58: =CaseData!G63 -> 186312 | H58: =CaseData!H63 -> 185545 | I58: =CaseData!I63 -> 185313 | J58: =CaseData!J63 -> 183795
B59: TTM Capex | E59: =CaseData!E64 -> 81423 | F59: =CaseData!F64 -> 63499 | G59: =CaseData!G64 -> 89256 | H59: =CaseData!H64 -> 86777 | I59: =CaseData!I64 -> 77656 | J59: =CaseData!J64 -> 83704
B60: FCF Before Debt Service & Taxes | E60: =CaseData!E65 -> 10393.67 | F60: =CaseData!F65 -> 8667.573 | G60: =CaseData!G65 -> 6355.84 | H60: =CaseData!H65 -> 8884.205 | I60: =CaseData!I65 -> 11026.2 | J60: =CaseData!J65 -> 5745.409
B61: LIBOR | E61: =CaseData!E66 -> 0.0225 | F61: =CaseData!F66 -> 0.0235 | G61: =CaseData!G66 -> 0.0245 | H61: =CaseData!H66 -> 0.0255 | I61: =CaseData!I66 -> 0.0265 | J61: =CaseData!J66 -> 0.027
B63: New Calculations
D65: =CaseData!$S$29 -> 43373 | E65: =E57 -> 43404 | F65: =F57 -> 43434 | G65: =G57 -> 43465 | H65: =H57 -> 43496 | I65: =I57 -> 43524 | J65: =J57 -> 43555
B67: Total Debt / EBITDA | D67: =D139/D58 -> 3.5927334 | E67: =E139/E58 -> 3.513831 | F67: =F139/F58 -> 3.5459873 | G67: =G139/G58 -> 3.7105853 | H67: =H139/H58 -> 3.6901198 | I67: =I139/I58 -> 3.6501648 | J67: =J139/J58 -> 3.6589679
B69: Taxes | D69: =D$65 -> 43373 | E69: =E$65 -> 43404 | F69: =F$65 -> 43434 | G69: =G$65 -> 43465 | H69: =H$65 -> 43496 | I69: =I$65 -> 43524 | J69: =J$65 -> 43555
B70: FCF Before Debt Service & Taxes | E70: =E60 -> 10393.67 | F70: =F60 -> 8667.573 | G70: =G60 -> 6355.84 | H70: =H60 -> 8884.205 | I70: =I60 -> 11026.2 | J70: =J60 -> 5745.409
B71: Less: Interest Expense (Accrued) | E71: =-E153 -> -3811.228 | F71: =-F153 -> -3794.9483 | G71: =-G153 -> -3782.3202 | H71: =-H153 -> -3288.1676 | I71: =-I153 -> -3274.1366 | J71: =-J153 -> -3245.6022
B72: Taxable Income | E72: =SUM(E70:E71) -> 6582.442 | F72: =SUM(F70:F71) -> 4872.6247 | G72: =SUM(G70:G71) -> 2573.5198 | H72: =SUM(H70:H71) -> 5596.0374 | I72: =SUM(I70:I71) -> 7752.0634 | J72: =SUM(J70:J71) -> 2499.8068
B74: Cash Taxes | E74: =E72*$M$9 -> 1645.6105 | F74: =F72*$M$9 -> 1218.1562 | G74: =G72*$M$9 -> 643.37994 | H74: =H72*$M$9 -> 1399.0093 | I74: =I72*$M$9 -> 1938.0159 | J74: =J72*$M$9 -> 624.9517
B76: Revolver | D76: =D$65 -> 43373 | E76: =E$65 -> 43404 | F76: =F$65 -> 43434 | G76: =G$65 -> 43465 | H76: =H$65 -> 43496 | I76: =I$65 -> 43524 | J76: =J$65 -> 43555
B77: Beginning Balance | E77: =D79 -> 12473 | F77: =E79 -> 7379.9185 | G77: =F79 -> 3569.2 | H77: =G79 -> 10389.06 | I77: =H79 -> 6558.2822 | J77: =I79 -> 1110.4846
B78: Additions / Repayments | E78: =-MIN(E77,E95) -> -5093.0815 | F78: =-MIN(F77,F95) -> -3810.7185 | G78: =-MIN(G77,G95) -> 6819.8602 | H78: =-MIN(H77,H95) -> -3830.778 | I78: =-MIN(I77,I95) -> -5447.7976 | J78: =-MIN(J77,J95) -> -1110.4846
B79: Ending Balance | D79: =S32 -> 12473 | E79: =SUM(E77:E78) -> 7379.9185 | F79: =SUM(F77:F78) -> 3569.2 | G79: =SUM(G77:G78) -> 10389.06 | H79: =SUM(H77:H78) -> 6558.2822 | I79: =SUM(I77:I78) -> 1110.4846 | J79: =SUM(J77:J78) -> 0
B81: LIBOR | E81: =E61 -> 0.0225 | F81: =F61 -> 0.0235 | G81: =G61 -> 0.0245 | H81: =H61 -> 0.0255 | I81: =I61 -> 0.0265 | J81: =J61 -> 0.027
B82: Spread | E82: =VLOOKUP(D67,$G$11:$I$14,COLUMNS($G$11:$I$14),TRUE)/10000 -> 0.03 | F82: =VLOOKUP(E67,$G$11:$I$14,COLUMNS($G$11:$I$14),TRUE)/10000 -> 0.03 | G82: =VLOOKUP(F67,$G$11:$I$14,COLUMNS($G$11:$I$14),TRUE)/10000 -> 0.03 | H82: =VLOOKUP(G67,$G$11:$I$14,COLUMNS($G$11:$I$14),TRUE)/10000 -> 0.03 | I82: =VLOOKUP(H67,$G$11:$I$14,COLUMNS($G$11:$I$14),TRUE)/10000 -> 0.03 | J82: =VLOOKUP(I67,$G$11:$I$14,COLUMNS($G$11:$I$14),TRUE)/10000 -> 0.03
B83: Effective Interest Rate (Annual) | E83: =E81+E82 -> 0.0525 | F83: =F81+F82 -> 0.0535 | G83: =G81+G82 -> 0.0545 | H83: =H81+H82 -> 0.0555 | I83: =I81+I82 -> 0.0565 | J83: =J81+J82 -> 0.057
B85: Drawn Interest Expense | E85: =D79*E83/12 -> 54.569375 | F85: =E79*F83/12 -> 32.902137 | G85: =F79*G83/12 -> 16.210117 | H85: =G79*H83/12 -> 48.049403 | I85: =H79*I83/12 -> 30.878578 | J85: =I79*J83/12 -> 5.2748019
B86: Standby Fee | E86: =($E$7-D79)*$E$10/120000 -> 25.018 | F86: =($E$7-E79)*$E$10/120000 -> 28.413388 | G86: =($E$7-F79)*$E$10/120000 -> 30.953867 | H86: =($E$7-G79)*$E$10/120000 -> 26.407293 | I86: =($E$7-H79)*$E$10/120000 -> 28.961145 | J86: =($E$7-I79)*$E$10/120000 -> 32.59301
B87: Total Revolver Interest | E87: =SUM(E85:E86) -> 79.587375 | F87: =SUM(F85:F86) -> 61.315524 | G87: =SUM(G85:G86) -> 47.163983 | H87: =SUM(H85:H86) -> 74.456697 | I87: =SUM(I85:I86) -> 59.839724 | J87: =SUM(J85:J86) -> 37.867812
B90: FCF Available for (Needed From) Revolver:
B91: FCF Before Debt Service & Taxes | E91: =E70 -> 10393.67 | F91: =F70 -> 8667.573 | G91: =G70 -> 6355.84 | H91: =H70 -> 8884.205 | I91: =I70 -> 11026.2 | J91: =J70 -> 5745.409
B92: Principal Additions / (Repayments) | E92: =E146 -> -2812.5 | F92: =F146 -> -2812.5 | G92: =G146 -> -2812.5 | H92: =H146 -> -2812.5 | I92: =I146 -> -2812.5 | J92: =J146 -> -2812.5
B93: Less: Cash Interest | E93: =-E160 -> -842.478 | F93: =-F160 -> -826.19834 | G93: =-G160 -> -9719.8202 | H93: =-H160 -> -841.91763 | I93: =-I160 -> -827.8866 | J93: =-J160 -> -799.35219
B94: Less: Taxes | E94: =-E74 -> -1645.6105 | F94: =-F74 -> -1218.1562 | G94: =-G74 -> -643.37994 | H94: =-H74 -> -1399.0093 | I94: =-I74 -> -1938.0159 | J94: =-J74 -> -624.9517
B95: FCF Available for (Needed From) Revolver | E95: =SUM(E91:E94) -> 5093.0815 | F95: =SUM(F91:F94) -> 3810.7185 | G95: =SUM(G91:G94) -> -6819.8602 | H95: =SUM(H91:H94) -> 3830.778 | I95: =SUM(I91:I94) -> 5447.7976 | J95: =SUM(J91:J94) -> 1508.6051
B97: Senior Term Loan | D97: =D$65 -> 43373 | E97: =E$65 -> 43404 | F97: =F$65 -> 43434 | G97: =G$65 -> 43465 | H97: =H$65 -> 43496 | I97: =I$65 -> 43524 | J97: =J$65 -> 43555
B98: Beginning Balance | E98: =D100 -> 174375 | F98: =E100 -> 171562.5 | G98: =F100 -> 168750 | H98: =G100 -> 165937.5 | I98: =H100 -> 163125 | J98: =I100 -> 160312.5
B99: Additions / Repayments | E99: =-$E$18*$E$20 -> -2812.5 | F99: =-$E$18*$E$20 -> -2812.5 | G99: =-$E$18*$E$20 -> -2812.5 | H99: =-$E$18*$E$20 -> -2812.5 | I99: =-$E$18*$E$20 -> -2812.5 | J99: =-$E$18*$E$20 -> -2812.5
B100: Ending Balance | D100: =S38 -> 174375 | E100: =SUM(E98:E99) -> 171562.5 | F100: =SUM(F98:F99) -> 168750 | G100: =SUM(G98:G99) -> 165937.5 | H100: =SUM(H98:H99) -> 163125 | I100: =SUM(I98:I99) -> 160312.5 | J100: =SUM(J98:J99) -> 157500
B102: LIBOR | E102: =E81 -> 0.0225 | F102: =F81 -> 0.0235 | G102: =G81 -> 0.0245 | H102: =H81 -> 0.0255 | I102: =I81 -> 0.0265 | J102: =J81 -> 0.027
B103: Spread | E103: =E82 -> 0.03 | F103: =F82 -> 0.03 | G103: =G82 -> 0.03 | H103: =H82 -> 0.03 | I103: =I82 -> 0.03 | J103: =J82 -> 0.03
B104: Effective Interest Rate (Annual) | E104: =E102+E103 -> 0.0525 | F104: =F102+F103 -> 0.0535 | G104: =G102+G103 -> 0.0545 | H104: =H102+H103 -> 0.0555 | I104: =I102+I103 -> 0.0565 | J104: =J102+J103 -> 0.057
B106: Interest Expense | E106: =D100*E104/12 -> 762.89062 | F106: =E100*F104/12 -> 764.88281 | G106: =F100*G104/12 -> 766.40625 | H106: =G100*H104/12 -> 767.46094 | I106: =H100*I104/12 -> 768.04688 | J106: =I100*J104/12 -> 761.48438
B108: Existing Subordinated Notes | D108: =D$65 -> 43373 | E108: =E$65 -> 43404 | F108: =F$65 -> 43434 | G108: =G$65 -> 43465 | H108: =H$65 -> 43496 | I108: =I$65 -> 43524 | J108: =J$65 -> 43555
B109: Beginning Balance | E109: =D111 -> 500000 | F109: =E111 -> 500000 | G109: =F111 -> 500000 | H109: =G111 -> 0 | I109: =H111 -> 0 | J109: =I111 -> 0
B110: Additions / Repayments | E110: =IF(E65=$M$17,-E109,0) -> 0 | F110: =IF(F65=$M$17,-F109,0) -> 0 | G110: =IF(G65=$M$17,-G109,0) -> -500000 | H110: =IF(H65=$M$17,-H109,0) -> 0 | I110: =IF(I65=$M$17,-I109,0) -> 0 | J110: =IF(J65=$M$17,-J109,0) -> 0
B111: Ending Balance | D111: =S42 -> 500000 | E111: =SUM(E109:E110) -> 500000 | F111: =SUM(F109:F110) -> 500000 | G111: =SUM(G109:G110) -> 0 | H111: =SUM(H109:H110) -> 0 | I111: =SUM(I109:I110) -> 0 | J111: =SUM(J109:J110) -> 0
B113: Call Price | E113: =IF(E65=$M$17,INDEX($I$24:$I$26,MATCH(EOMONTH(E$108,-1),$H$24:$H$26,1)),0) -> 0 | F113: =IF(F65=$M$17,INDEX($I$24:$I$26,MATCH(EOMONTH(F$108,-1),$H$24:$H$26,1)),0) -> 0 | G113: =IF(G65=$M$17,INDEX($I$24:$I$26,MATCH(EOMONTH(G$108,-1),$H$24:$H$26,1)),0) -> 1.03 | H113: =IF(H65=$M$17,INDEX($I$24:$I$26,MATCH(EOMONTH(H$108,-1),$H$24:$H$26,1)),0) -> 0 | I113: =IF(I65=$M$17,INDEX($I$24:$I$26,MATCH(EOMONTH(I$108,-1),$H$24:$H$26,1)),0) -> 0 | J113: =IF(J65=$M$17,INDEX($I$24:$I$26,MATCH(EOMONTH(J$108,-1),$H$24:$H$26,1)),0) -> 0
B114: Cash Needed to Refinance | E114: =-E110*E113 -> 0 | F114: =-F110*F113 -> 0 | G114: =-G110*G113 -> 515000 | H114: =-H110*H113 -> 0 | I114: =-I110*I113 -> 0 | J114: =-J110*J113 -> 0
B116: Effective Interest Rate (Annual) | E116: =$I$19 -> 0.07125 | F116: =$I$19 -> 0.07125 | G116: =$I$19 -> 0.07125 | H116: =$I$19 -> 0.07125 | I116: =$I$19 -> 0.07125 | J116: =$I$19 -> 0.07125
B118: Interest Expense | E118: =D111*E116/12 -> 2968.75 | F118: =E111*F116/12 -> 2968.75 | G118: =F111*G116/12 -> 2968.75 | H118: =G111*H116/12 -> 0 | I118: =H111*I116/12 -> 0 | J118: =I111*J116/12 -> 0
B120: Cash Interest Payment? | E120: =IF(E113>0,1,0) -> 0 | F120: =IF(F113>0,1,0) -> 0 | G120: =IF(G113>0,1,0) -> 1 | H120: =IF(H113>0,1,0) -> 0 | I120: =IF(I113>0,1,0) -> 0 | J120: =IF(J113>0,1,0) -> 0
B121: Cash Interest | E121: =$E$118*COUNT($E$120:E120)*E120 -> 0 | F121: =$E$118*COUNT($E$120:F120)*F120 -> 0 | G121: =$E$118*COUNT($E$120:G120)*G120 -> 8906.25 | H121: =$E$118*COUNT($E$120:H120)*H120 -> 0 | I121: =$E$118*COUNT($E$120:I120)*I120 -> 0 | J121: =$E$118*COUNT($E$120:J120)*J120 -> 0
B123: New Senior Notes | D123: =D$65 -> 43373 | E123: =E$65 -> 43404 | F123: =F$65 -> 43434 | G123: =G$65 -> 43465 | H123: =H$65 -> 43496 | I123: =I$65 -> 43524 | J123: =J$65 -> 43555
B124: Outstanding? | E124: =IF(E128>0,1,0) -> 0 | F124: =IF(F128>0,1,0) -> 0 | G124: =IF(G128>0,1,0) -> 1 | H124: =IF(H128>0,1,0) -> 1 | I124: =IF(I128>0,1,0) -> 1 | J124: =IF(J128>0,1,0) -> 1
B126: Beginning Balance | E126: =D128 -> 0 | F126: =E128 -> 0 | G126: =F128 -> 0 | H126: =G128 -> 515000 | I126: =H128 -> 515000 | J126: =I128 -> 515000
B127: Additions / Repayments | E127: =E114 -> 0 | F127: =F114 -> 0 | G127: =G114 -> 515000 | H127: =H114 -> 0 | I127: =I114 -> 0 | J127: =J114 -> 0
B128: Ending Balance | D128: 0 | E128: =SUM(E126:E127) -> 0 | F128: =SUM(F126:F127) -> 0 | G128: =SUM(G126:G127) -> 515000 | H128: =SUM(H126:H127) -> 515000 | I128: =SUM(I126:I127) -> 515000 | J128: =SUM(J126:J127) -> 515000
B130: Effective Interest Rate (Annual) | E130: =IF(E113=0,D130,VLOOKUP(E65,$K$19:$M$24,COLUMNS($K$19:$M$24),TRUE)) -> 0 | F130: =IF(F113=0,E130,VLOOKUP(F65,$K$19:$M$24,COLUMNS($K$19:$M$24),TRUE)) -> 0 | G130: =IF(G113=0,F130,VLOOKUP(G65,$K$19:$M$24,COLUMNS($K$19:$M$24),TRUE)) -> 0.057 | H130: =IF(H113=0,G130,VLOOKUP(H65,$K$19:$M$24,COLUMNS($K$19:$M$24),TRUE)) -> 0.057 | I130: =IF(I113=0,H130,VLOOKUP(I65,$K$19:$M$24,COLUMNS($K$19:$M$24),TRUE)) -> 0.057 | J130: =IF(J113=0,I130,VLOOKUP(J65,$K$19:$M$24,COLUMNS($K$19:$M$24),TRUE)) -> 0.057
B132: Interest Expense | E132: =D128*E130/12 -> 0 | F132: =E128*F130/12 -> 0 | G132: =F128*G130/12 -> 0 | H132: =G128*H130/12 -> 2446.25 | I132: =H128*I130/12 -> 2446.25 | J132: =I128*J130/12 -> 2446.25
B134: Total Debt - End of Period | D134: =D$65 -> 43373 | E134: =E$65 -> 43404 | F134: =F$65 -> 43434 | G134: =G$65 -> 43465 | H134: =H$65 -> 43496 | I134: =I$65 -> 43524 | J134: =J$65 -> 43555
B135: Revolver | D135: =D79 -> 12473 | E135: =E79 -> 7379.9185 | F135: =F79 -> 3569.2 | G135: =G79 -> 10389.06 | H135: =H79 -> 6558.2822 | I135: =I79 -> 1110.4846 | J135: =J79 -> 0
...
