Workbook
Name company: Case1Data!$A$1
Name EBIDTA_scenarios: Case1Data!$E$108:$E$111
Name EBIDTA_selector: Debt!$F$15
Name periods: Case1Data!$H$41
Name sculpting_scenarios: Case1Data!$E$104:$E$106
Name sculpting_selector: Debt!$F$8
Name start_date: Case1Data!$H$39
Name topic: "CFM Topic: " & Case1Data!$E$96

Sheet Debt
A1: {=company} -> Blackrat SPV Pty Ltd
A2: {=topic} -> CFM Topic: Debt | J2: {=EDATE( start_date + 1, _xlfn.SEQUENCE(1, periods, 0, 3 ) )} -> 43466 | K2: 43556 | L2: 43647 | M2: 43739 | N2: 43831 | O2: 43922 | P2: 44013 | Q2: 44105 | R2: 44197 | S2: 44287 | T2: 44378 | U2: 44470 | V2: 44562 | W2: 44652 | X2: 44743 | Y2: 44835 | Z2: 44927 | AA2: 45017 | AB2: 45108 | AC2: 45200 | AD2: 45292 | AE2: 45383 | AF2: 45474 | AG2: 45566 | AH2: 45658 | AI2: 45748 | AJ2: 45839 | AK2: 45931 | AL2: 46023 | AM2: 46113 | AN2: 46204 | AO2: 46296 | AP2: 46388 | AQ2: 46478 | AR2: 46569 | AS2: 46661 | AT2: 46753 | AU2: 46844 | AV2: 46935 | AW2: 47027
A3: DEBT SCHEDULE | F3: Constant | G3: Unit | H3: Total | J3: {=EOMONTH( start_date, _xlfn.SEQUENCE( 1, periods, 3, 3 ) )} -> 43555 | K3: 43646 | L3: 43738 | M3: 43830 | N3: 43921 | O3: 44012 | P3: 44104 | Q3: 44196 | R3: 44286 | S3: 44377 | T3: 44469 | U3: 44561 | V3: 44651 | W3: 44742 | X3: 44834 | Y3: 44926 | Z3: 45016 | AA3: 45107 | AB3: 45199 | AC3: 45291 | AD3: 45382 | AE3: 45473 | AF3: 45565 | AG3: 45657 | AH3: 45747 | AI3: 45838 | AJ3: 45930 | AK3: 46022 | AL3: 46112 | AM3: 46203 | AN3: 46295 | AO3: 46387 | AP3: 46477 | AQ3: 46568 | AR3: 46660 | AS3: 46752 | AT3: 46843 | AU3: 46934 | AV3: 47026 | AW3: 47118
A5: Scenarios
E8: Debt sculpting scenarios | F8: 1
E10: Scenario name | F10: =INDEX( Case1Data!$G$17:$I$19, MATCH( Debt!$E10, Case1Data!$D$17:$D$19, 0 ), MATCH( sculpting_selector, Case1Data!$G$16:$I$16, 0 ) ) -> Passive
E11: Sculpted senior DSCR | F11: =INDEX( Case1Data!$G$17:$I$19, MATCH( Debt!$E11, Case1Data!$D$17:$D$19, 0 ), MATCH( sculpting_selector, Case1Data!$G$16:$I$16, 0 ) ) -> 2
E12: Annual interest rate | F12: =INDEX( Case1Data!$G$17:$I$19, MATCH( Debt!$E12, Case1Data!$D$17:$D$19, 0 ), MATCH( sculpting_selector, Case1Data!$G$16:$I$16, 0 ) ) -> 0.045
E15: Selected EBIDTA scenario | F15: 1
A19: Senior Debt
E22: Senior Debt BEG | G22: USD | J22: =I24 -> 10000000 | K22: =J24 -> 9771868.5 | L22: =K24 -> 9544849.5 | M22: =L24 -> 9318438.1 | N22: =M24 -> 9090564 | O22: =N24 -> 8859628.9 | P22: =O24 -> 8633291.7 | Q22: =P24 -> 8404698.7 | ... AW22: =AV24 -> 0
E23: Senior Debt addition / (repayment) | G23: USD | J23: =- MIN( J$22, J$44 ) -> -228131.5 | K23: =- MIN( K$22, K$44 ) -> -227018.98 | L23: =- MIN( L$22, L$44 ) -> -226411.44 | M23: =- MIN( M$22, M$44 ) -> -227874.07 | N23: =- MIN( N$22, N$44 ) -> -230935.15 | O23: =- MIN( O$22, O$44 ) -> -226337.18 | P23: =- MIN( P$22, P$44 ) -> -228592.97 | Q23: =- MIN( Q$22, Q$44 ) -> -228913.64 | ... AW23: =- MIN( AW$22, AW$44 ) -> 0
E24: Senior Debt | G24: USD | I24: =Case1Data!H$13 -> 10000000 | J24: =SUM( J22:J23 ) -> 9771868.5 | K24: =SUM( K22:K23 ) -> 9544849.5 | L24: =SUM( L22:L23 ) -> 9318438.1 | M24: =SUM( M22:M23 ) -> 9090564 | N24: =SUM( N22:N23 ) -> 8859628.9 | O24: =SUM( O22:O23 ) -> 8633291.7 | P24: =SUM( P22:P23 ) -> 8404698.7 | Q24: =SUM( Q22:Q23 ) -> 8175785.1 | ... AW24: =SUM( AW22:AW23 ) -> 0
C27: Senior Debt interest
E28: Annual interest rate on Senior Debt | F28: =$F$12 -> 0.045 | G28: %
E29: Senior Debt interest expenses | G29: USD | J29: =J22 * $F$28 / 4 -> 112500 | K29: =K22 * $F$28 / 4 -> 109933.52 | L29: =L22 * $F$28 / 4 -> 107379.56 | M29: =M22 * $F$28 / 4 -> 104832.43 | N29: =N22 * $F$28 / 4 -> 102268.85 | O29: =O22 * $F$28 / 4 -> 99670.825 | P29: =P22 * $F$28 / 4 -> 97124.531 | Q29: =Q22 * $F$28 / 4 -> 94552.86 | ... AW29: =AW22 * $F$28 / 4 -> 0
A32: Debt Service Coverage Ratio ("DSCR")
E35: Target DSCR | G35: factor | J35: {=_xlfn.SEQUENCE( 1, periods, Debt!$F$11, 0 )} -> 2 | K35: 2 | L35: 2 | M35: 2 | N35: 2 | O35: 2 | P35: 2 | Q35: 2 | R35: 2 | S35: 2 | T35: 2 | U35: 2 | V35: 2 | W35: 2 | X35: 2 | Y35: 2 | Z35: 2 | AA35: 2 | AB35: 2 | AC35: 2 | AD35: 2 | AE35: 2 | AF35: 2 | AG35: 2 | AH35: 2 | AI35: 2 | AJ35: 2 | AK35: 2 | AL35: 2 | AM35: 2 | AN35: 2 | AO35: 2 | AP35: 2 | AQ35: 2 | AR35: 2 | AS35: 2 | AT35: 2 | AU35: 2 | AV35: 2 | AW35: 2
E37: EBIDTA | G37: USD | J37: {=INDEX( Case1Data!$G$52:$J$91, MATCH(_xlfn.ANCHORARRAY( Debt!J3), Case1Data!$E$52:$E$91, 0 ), MATCH( EBIDTA_selector, Case1Data!$G$49:$J$49, 0 ) )} -> 679388 | K37: 672030 | L37: 665707 | M37: 663538 | N37: 664533 | O37: 650141 | P37: 649560 | Q37: 645058 | R37: 676898 | S37: 642290 | T37: 652741 | U37: 643964 | V37: 642292 | W37: 671775 | X37: 674599 | Y37: 685274 | Z37: 660287 | AA37: 677193 | AB37: 687307 | AC37: 699274 | AD37: 719236 | AE37: 693326 | AF37: 713143 | AG37: 698365 | AH37: 699462 | AI37: 706344 | AJ37: 738541 | AK37: 706443 | AL37: 696744 | AM37: 714636 | AN37: 755656 | AO37: 750348 | AP37: 740563 | AQ37: 731253 | AR37: 755344 | AS37: 768793 | AT37: 764348 | AU37: 758728 | AV37: 771909 | AW37: 772307
D38: plus | E38: =E$57 -> Debt Service Reserve Account ("DSRA") interest income | G38: =G$57 -> USD | J38: =J$57 -> 1875 | K38: =K$57 -> 1875 | L38: =L$57 -> 1875 | M38: =M$57 -> 1875 | N38: =N$57 -> 1875 | O38: =O$57 -> 1875 | P38: =P$57 -> 1875 | Q38: =Q$57 -> 1875 | ... AW38: =AW$57 -> 0
E39: Cash available for debt service | G39: USD | J39: =SUM(J37:J38) -> 681263 | K39: =SUM(K37:K38) -> 673905 | L39: =SUM(L37:L38) -> 667582 | M39: =SUM(M37:M38) -> 665413 | N39: =SUM(N37:N38) -> 666408 | O39: =SUM(O37:O38) -> 652016 | P39: =SUM(P37:P38) -> 651435 | Q39: =SUM(Q37:Q38) -> 646933 | ... AW39: =SUM(AW37:AW38) -> 772307
E41: Target DSCR | F41: =$F$11 -> 2 | G41: factor
E42: Target Senior Debt Service | G42: USD | J42: =J$39 / J$35 -> 340631.5 | K42: =K$39 / K$35 -> 336952.5 | L42: =L$39 / L$35 -> 333791 | M42: =M$39 / M$35 -> 332706.5 | N42: =N$39 / N$35 -> 333204 | O42: =O$39 / O$35 -> 326008 | P42: =P$39 / P$35 -> 325717.5 | Q42: =Q$39 / Q$35 -> 323466.5 | ... AW42: =AW$39 / AW$35 -> 386153.5
D43: less | E43: =E$29 -> Senior Debt interest expenses | G43: =G$29 -> USD | J43: =J$29 * - 1 -> -112500 | K43: =K$29 * - 1 -> -109933.52 | L43: =L$29 * - 1 -> -107379.56 | M43: =M$29 * - 1 -> -104832.43 | N43: =N$29 * - 1 -> -102268.85 | O43: =O$29 * - 1 -> -99670.825 | P43: =P$29 * - 1 -> -97124.531 | Q43: =Q$29 * - 1 -> -94552.86 | ... AW43: =AW$29 * - 1 -> 0
E44: Target Debt Repayment | G44: USD | J44: =SUM(J42:J43) -> 228131.5 | K44: =SUM(K42:K43) -> 227018.98 | L44: =SUM(L42:L43) -> 226411.44 | M44: =SUM(M42:M43) -> 227874.07 | N44: =SUM(N42:N43) -> 230935.15 | O44: =SUM(O42:O43) -> 226337.18 | P44: =SUM(P42:P43) -> 228592.97 | Q44: =SUM(Q42:Q43) -> 228913.64 | ... AW44: =SUM(AW42:AW43) -> 386153.5
E46: Actual DSCR | G46: factor | J46: =IFERROR( J$39 / ( J29 - J23 ), 0 ) -> 2 | K46: =IFERROR( K$39 / ( K29 - K23 ), 0 ) -> 2 | L46: =IFERROR( L$39 / ( L29 - L23 ), 0 ) -> 2 | M46: =IFERROR( M$39 / ( M29 - M23 ), 0 ) -> 2 | N46: =IFERROR( N$39 / ( N29 - N23 ), 0 ) -> 2 | O46: =IFERROR( O$39 / ( O29 - O23 ), 0 ) -> 2 | P46: =IFERROR( P$39 / ( P29 - P23 ), 0 ) -> 2 | Q46: =IFERROR( Q$39 / ( Q29 - Q23 ), 0 ) -> 2 | ... AW46: =IFERROR( AW$39 / ( AW29 - AW23 ), 0 ) -> 0
A49: Debt Service Reserve Account ("DSRA") interest income
E52: Debt Service Reserve Account ("DSCA") BEG | G52: USD | J52: =I54 -> 500000 | K52: =J54 -> 500000 | L52: =K54 -> 500000 | M52: =L54 -> 500000 | N52: =M54 -> 500000 | O52: =N54 -> 500000 | P52: =O54 -> 500000 | Q52: =P54 -> 500000 | ... AW52: =AV54 -> 0
E53: Debt Service Reserve Account ("DSCA") addition / (release) | G53: USD | J53: =IF( J$24 = 0, - J$52, 0 ) -> 0 | K53: =IF( K$24 = 0, - K$52, 0 ) -> 0 | L53: =IF( L$24 = 0, - L$52, 0 ) -> 0 | M53: =IF( M$24 = 0, - M$52, 0 ) -> 0 | N53: =IF( N$24 = 0, - N$52, 0 ) -> 0 | O53: =IF( O$24 = 0, - O$52, 0 ) -> 0 | P53: =IF( P$24 = 0, - P$52, 0 ) -> 0 | Q53: =IF( Q$24 = 0, - Q$52, 0 ) -> 0 | ... AW53: =IF( AW$24 = 0, - AW$52, 0 ) -> 0
E54: Debt Service Reserve Account ("DSCA") | G54: USD | I54: =Case1Data!$H$23 -> 500000 | J54: =SUM(J52:J53) -> 500000 | K54: =SUM(K52:K53) -> 500000 | L54: =SUM(L52:L53) -> 500000 | M54: =SUM(M52:M53) -> 500000 | N54: =SUM(N52:N53) -> 500000 | O54: =SUM(O52:O53) -> 500000 | P54: =SUM(P52:P53) -> 500000 | Q54: =SUM(Q52:Q53) -> 500000 | ... AW54: =SUM(AW52:AW53) -> 0
E56: Interest rate on "DSRA" | F56: =Case1Data!$H$25 -> 0.015 | G56: %
E57: Debt Service Reserve Account ("DSRA") interest income | G57: USD | J57: =J$52 * $F$56 / 4 -> 1875 | K57: =K$52 * $F$56 / 4 -> 1875 | L57: =L$52 * $F$56 / 4 -> 1875 | M57: =M$52 * $F$56 / 4 -> 1875 | N57: =N$52 * $F$56 / 4 -> 1875 | O57: =O$52 * $F$56 / 4 -> 1875 | P57: =P$52 * $F$56 / 4 -> 1875 | Q57: =Q$52 * $F$56 / 4 -> 1875 | ... AW57: =AW$52 * $F$56 / 4 -> 0
A60: Junior Debt
E63: Junior Debt BEG | G63: USD | J63: =I$65 -> 6000000 | K63: =J$65 -> 5850000 | L63: =K$65 -> 5700000 | M63: =L$65 -> 5550000 | N63: =M$65 -> 5400000 | O63: =N$65 -> 5250000 | P63: =O$65 -> 5100000 | Q63: =P$65 -> 4950000 | ... AW63: =AV$65 -> 150000
E64: Junior Debt addition / (repayment) | G64: USD | J64: =MIN( $I$65 / Case1Data!$H$30, J$63 ) * - 1 -> -150000 | K64: =MIN( $I$65 / Case1Data!$H$30, K$63 ) * - 1 -> -150000 | L64: =MIN( $I$65 / Case1Data!$H$30, L$63 ) * - 1 -> -150000 | M64: =MIN( $I$65 / Case1Data!$H$30, M$63 ) * - 1 -> -150000 | N64: =MIN( $I$65 / Case1Data!$H$30, N$63 ) * - 1 -> -150000 | O64: =MIN( $I$65 / Case1Data!$H$30, O$63 ) * - 1 -> -150000 | P64: =MIN( $I$65 / Case1Data!$H$30, P$63 ) * - 1 -> -150000 | Q64: =MIN( $I$65 / Case1Data!$H$30, Q$63 ) * - 1 -> -150000 | ... AW64: =MIN( $I$65 / Case1Data!$H$30, AW$63 ) * - 1 -> -150000
E65: Junior Debt | G65: USD | I65: =Case1Data!$H$28 -> 6000000 | J65: =SUM(J63:J64) -> 5850000 | K65: =SUM(K63:K64) -> 5700000 | L65: =SUM(L63:L64) -> 5550000 | M65: =SUM(M63:M64) -> 5400000 | N65: =SUM(N63:N64) -> 5250000 | O65: =SUM(O63:O64) -> 5100000 | P65: =SUM(P63:P64) -> 4950000 | Q65: =SUM(Q63:Q64) -> 4800000 | ... AW65: =SUM(AW63:AW64) -> 0
C68: Junior Debt interest
E69: Annual interest rate on Junior Debt | F69: =Case1Data!$H$29 -> 0.07 | G69: %
E70: Junior Debt interest expenses | G70: USD | J70: =J$63 * $F$69 / 4 -> 105000 | K70: =K$63 * $F$69 / 4 -> 102375 | L70: =L$63 * $F$69 / 4 -> 99750 | M70: =M$63 * $F$69 / 4 -> 97125 | N70: =N$63 * $F$69 / 4 -> 94500 | O70: =O$63 * $F$69 / 4 -> 91875 | P70: =P$63 * $F$69 / 4 -> 89250 | Q70: =Q$63 * $F$69 / 4 -> 86625 | ... AW70: =AW$63 * $F$69 / 4 -> 2625
A73: Returns and value
C76: Equity Cashflow
E77: =E$37 -> EBIDTA | G77: =G$37 -> USD | H77: {=_xlfn.BYROW( J77:AW84, _xleta.SUM )} -> 27959338 | I77: =I$17 -> 0 | J77: =J$37 -> 679388 | K77: =K$37 -> 672030 | L77: =L$37 -> 665707 | M77: =M$37 -> 663538 | N77: =N$37 -> 664533 | O77: =O$37 -> 650141 | P77: =P$37 -> 649560 | Q77: =Q$37 -> 645058 | ... AW77: =AW$37 -> 772307
E78: =E$57 -> Debt Service Reserve Account ("DSRA") interest income | G78: =G$57 -> USD | H78: 67500 | I78: =I$57 -> 0 | J78: =J$57 -> 1875 | K78: =K$57 -> 1875 | L78: =L$57 -> 1875 | M78: =M$57 -> 1875 | N78: =N$57 -> 1875 | O78: =O$57 -> 1875 | P78: =P$57 -> 1875 | ... AW78: =AW$57 -> 0
E79: Debt Service Reserve Account ("DSRA") (addition) / release | G79: =G$53 -> USD | H79: 500000 | J79: =J$53 * - 1 -> 0 | K79: =K$53 * - 1 -> 0 | L79: =L$53 * - 1 -> 0 | M79: =M$53 * - 1 -> 0 | N79: =N$53 * - 1 -> 0 | O79: =O$53 * - 1 -> 0 | P79: =P$53 * - 1 -> 0 | Q79: =Q$53 * - 1 -> 0 | ... AW79: =AW$53 * - 1 -> 0
E80: =E$23 -> Senior Debt addition / (repayment) | G80: =G$23 -> USD | H80: -10000000 | I80: =I$23 -> 0 | J80: =J$23 -> -228131.5 | K80: =K$23 -> -227018.98 | L80: =L$23 -> -226411.44 | M80: =M$23 -> -227874.07 | N80: =N$23 -> -230935.15 | O80: =O$23 -> -226337.18 | P80: =P$23 -> -228592.97 | ... AW80: =AW$23 -> 0
E81: =E$29 -> Senior Debt interest expenses | G81: =G$29 -> USD | H81: -2234122.2 | I81: =I$29 -> 0 | J81: =J$29 * - 1 -> -112500 | K81: =K$29 * - 1 -> -109933.52 | L81: =L$29 * - 1 -> -107379.56 | M81: =M$29 * - 1 -> -104832.43 | N81: =N$29 * - 1 -> -102268.85 | O81: =O$29 * - 1 -> -99670.825 | P81: =P$29 * - 1 -> -97124.531 | Q81: =Q$29 * - 1 -> -94552.86 | ... AW81: =AW$29 * - 1 -> 0
E82: =E$64 -> Junior Debt addition / (repayment) | G82: =G$64 -> USD | H82: -6000000 | I82: =I$64 -> 0 | J82: =J$64 -> -150000 | K82: =K$64 -> -150000 | L82: =L$64 -> -150000 | M82: =M$64 -> -150000 | N82: =N$64 -> -150000 | O82: =O$64 -> -150000 | P82: =P$64 -> -150000 | ... AW82: =AW$64 -> -150000
E83: =E$70 -> Junior Debt interest expenses | G83: =G$70 -> USD | H83: -2152500 | I83: =I$70 -> 0 | J83: =J$70 * - 1 -> -105000 | K83: =K$70 * - 1 -> -102375 | L83: =L$70 * - 1 -> -99750 | M83: =M$70 * - 1 -> -97125 | N83: =N$70 * - 1 -> -94500 | O83: =O$70 * - 1 -> -91875 | P83: =P$70 * - 1 -> -89250 | Q83: =Q$70 * - 1 -> -86625 | ... AW83: =AW$70 * - 1 -> -2625
E84: Equity Distribution | G84: USD | H84: 8140215.8 | J84: =SUM(J77:J83) -> 85631.5 | K84: =SUM(K77:K83) -> 84577.5 | L84: =SUM(L77:L83) -> 84041 | M84: =SUM(M77:M83) -> 85581.5 | N84: =SUM(N77:N83) -> 88704 | O84: =SUM(O77:O83) -> 84133 | P84: =SUM(P77:P83) -> 86467.5 | Q84: =SUM(Q77:Q83) -> 86841.5 | ... AW84: =SUM(AW77:AW83) -> 619682
E86: Date of investment | F86: =start_date -> 43465
E87: Equity investment | F87: =Case1Data!$H$34 * - 1 -> -4000000 | G87: USD | J87: {=_xlfn.SEQUENCE( 1, periods, 0, 0 )} -> 0 | K87: 0 | L87: 0 | M87: 0 | N87: 0 | O87: 0 | P87: 0 | Q87: 0 | R87: 0 | S87: 0 | T87: 0 | U87: 0 | V87: 0 | W87: 0 | X87: 0 | Y87: 0 | Z87: 0 | AA87: 0 | AB87: 0 | AC87: 0 | AD87: 0 | AE87: 0 | AF87: 0 | AG87: 0 | AH87: 0 | AI87: 0 | AJ87: 0 | AK87: 0 | AL87: 0 | AM87: 0 | AN87: 0 | AO87: 0 | AP87: 0 | AQ87: 0 | AR87: 0 | AS87: 0 | AT87: 0 | AU87: 0 | AV87: 0 | AW87: 0
E88: Equity cashflow | G88: USD | J88: =J84 + J87 -> 85631.5 | K88: =K84 + K87 -> 84577.5 | L88: =L84 + L87 -> 84041 | M88: =M84 + M87 -> 85581.5 | N88: =N84 + N87 -> 88704 | O88: =O84 + O87 -> 84133 | P88: =P84 + P87 -> 86467.5 | Q88: =Q84 + Q87 -> 86841.5 | ... AW88: =AW84 + AW87 -> 619682
E90: IRR | F90: =XIRR( _xlfn.HSTACK( $F$87, $J$88:$AW$88 ), _xlfn.HSTACK( start_date,_xlfn.ANCHORARRAY( J3) ) ) -> 0.11439549 | G90: %
E91: NPV | F91: =XNPV( Case1Data!$H$35, _xlfn.HSTACK( Debt!$F$87, Debt!$J$88:$AW$88 ), _xlfn.HSTACK( start_date,_xlfn.ANCHORARRAY( J3) ) ) -> 456463.88 | G91: USD
A94: Answers
C96: c) | E96: Q1 2027
C97: d) | E97: 2152500
C99: e) | I99: Distribution of equity on 31/3/2020 under Aggressive sculpting scenario and EBIDTA 2 | J99: {=Case1Data!$G$17:$I$17} -> Passive | K99: Neutral | L99: Aggressive
I100: =N88 -> 88704 | J100: 1 | K100: 2 | L100: 3
H101: {=TRANSPOSE( Case1Data!$G$50:$J$50)} -> Base Case | I101: 1 | J101: 88704 | K101: 51681.333 | L101: 29903.294
H102: Case 2 | I102: 2 | J102: 167128.5 | K102: 121392 | L102: 94488.176
H103: Case 3 | I103: 3 | J103: 120499 | K103: 79943.556 | L103: 56087.412
H104: Case 4 | I104: 4 | J104: 102093.5 | K104: 63583.111 | L104: 40929.941
C106: f) | I106: Under which scenario combination the IRR is the highest | J106: {=Case1Data!$G$17:$I$17} -> Passive | K106: Neutral | L106: Aggressive
I107: =$F$90 -> 0.11439549 | J107: 1 | K107: 2 | L107: 3
E108: Passive / EBIDTA 2 | H108: {=TRANSPOSE( Case1Data!$G$50:$J$50)} -> Base Case | I108: 1 | J108: 0.11439549 | K108: 0.101513 | L108: 0.093689504
H109: Case 2 | I109: 2 | J109: 0.18833821 | K109: 0.17128327 | L109: 0.16166523
H110: Case 3 | I110: 3 | J110: 0.12684518 | K110: 0.11314749 | L110: 0.10482313
H111: Case 4 | I111: 4 | J111: 0.14833984 | K111: 0.13353439 | L111: 0.12480724
C113: g) | I113: Under which scenario combination the NPV the lowest | J113: {=Case1Data!$G$17:$I$17} -> Passive | K113: Neutral | L113: Aggressive
I114: =$F$91 -> 456463.88 | J114: 1 | K114: 2 | L114: 3
E115: Aggressive / Base case | H115: {=TRANSPOSE( Case1Data!$G$50:$J$50)} -> Base Case | I115: 1 | J115: 456463.88 | K115: 169615.06 | L115: -35704.706
H116: Case 2 | I116: 2 | J116: 2430210.2 | K116: 2169637.1 | L116: 1979546.5
H117: Case 3 | I117: 3 | J117: 756919.36 | K117: 476045 | L117: 269899.44
H118: Case 4 | I118: 4 | J118: 1325222.5 | K118: 1050944.8 | L118: 849944.61
A121: Model timeline
E123: Quarter | G123: quarter | J123: {=MONTH(_xlfn.ANCHORARRAY( J3) ) / 3} -> 1 | K123: 2 | L123: 3 | M123: 4 | N123: 1 | O123: 2 | P123: 3 | Q123: 4 | R123: 1 | S123: 2 | T123: 3 | U123: 4 | V123: 1 | W123: 2 | X123: 3 | Y123: 4 | Z123: 1 | AA123: 2 | AB123: 3 | AC123: 4 | AD123: 1 | AE123: 2 | AF123: 3 | AG123: 4 | AH123: 1 | AI123: 2 | AJ123: 3 | AK123: 4 | AL123: 1 | AM123: 2 | AN123: 3 | AO123: 4 | AP123: 1 | AQ123: 2 | AR123: 3 | AS123: 4 | AT123: 1 | AU123: 2 | AV123: 3 | AW123: 4
E124: Year | G124: year | J124: {=YEAR(_xlfn.ANCHORARRAY( J3) )} -> 2019 | K124: 2019 | L124: 2019 | M124: 2019 | N124: 2020 | O124: 2020 | P124: 2020 | Q124: 2020 | R124: 2021 | S124: 2021 | T124: 2021 | U124: 2021 | V124: 2022 | W124: 2022 | X124: 2022 | Y124: 2022 | Z124: 2023 | AA124: 2023 | AB124: 2023 | AC124: 2023 | AD124: 2024 | AE124: 2024 | AF124: 2024 | AG124: 2024 | AH124: 2025 | AI124: 2025 | AJ124: 2025 | AK124: 2025 | AL124: 2026 | AM124: 2026 | AN124: 2026 | AO124: 2026 | AP124: 2027 | AQ124: 2027 | AR124: 2027 | AS124: 2027 | AT124: 2028 | AU124: 2028 | AV124: 2028 | AW124: 2028

Sheet Case1Data
A1: Blackrat SPV Pty Ltd
A3: 1 | C3: Assumptions
A10: =MAX(A$3:A9)+0.01 -> 1.01 | C10: Assumptions
B12: Senior Facility
D13: Facility balance at model start date | F13: [$] | H13: 10000000
C15: Sculpting and interest rate scenarios
D16: Scenario number | F16: [#] | G16: 1 | H16: 2 | I16: 3
D17: Scenario name | F17: [text] | G17: Passive | H17: Neutral | I17: Aggressive
D18: Sculpted senior DSCR | F18: [x] | G18: 2 | H18: 1.8 | I18: 1.7
D19: Annual interest rate | F19: [% p.a.] | G19: 0.045 | H19: 0.05 | I19: 0.055
B22: Debt Service Reserve Account
D23: Initial balance at project start (already funded) | F23: [$] | H23: 500000
D24: Required minimum balance during term of Senior Facility | F24: [$] | H24: 500000
D25: Interest rate earned on account balance | F25: [% p.a.] | H25: 0.015
B27: Junior Facility
D28: Facility balance at model start date | F28: [$] | H28: 6000000
D29: Annual interest rate | F29: [% p.a.] | H29: 0.07
D30: Amortisation quarters | F30: [#] | H30: 40
D31: Scheduled final payment date | F31: [date] | H31: =EOMONTH(H39,3*H30) -> 47118
B33: Equity
D34: Contribution amount at model start date | F34: [$] | H34: 4000000
D35: Discount rate for Net Present Value calculations | F35: [% p.a.] | H35: 0.095
B38: Other Assumptions
D39: Model start date (Project start date) | F39: [date] | H39: 43465
D40: Initial quarter end date | F40: [date] | H40: =EOMONTH(H39,3) -> 43555
D41: Number of quarters in project | F41: [# qtrs] | H41: 40
D42: Final quarter end date (Project end date) | F42: [date] | H42: =EOMONTH(H39,H41*3) -> 47118
D44: Interest rate earned on cash account balance | F44: [% p.a.] | H44: 0.015
C47: EBITDA Profiles ($)
E49: Profile number --> | G49: 1 | H49: 2 | I49: 3 | J49: 4
E50: Profile name --> | G50: Base Case | H50: Case 2 | I50: Case 3 | J50: Case 4 | M50: {=TRANSPOSE(G50:J50)} -> Base Case
E51: Quarter Ending | G51: [$] | H51: [$] | I51: [$] | J51: [$] | M51: Case 2
E52: =$H$40 -> 43555 | G52: 679388 | H52: 812279 | I52: 629617 | J52: 722459 | M52: Case 3
E53: =EOMONTH(E52,3) -> 43646 | G53: 672030 | H53: 706344 | I53: 803471 | J53: 685565 | M53: Case 4
E54: =EOMONTH(E53,3) -> 43738 | G54: 665707 | H54: 770727 | I54: 676023 | J54: 715368
E55: =EOMONTH(E54,3) -> 43830 | G55: 663538 | H55: 789594 | I55: 727805 | J55: 696176
E56: =EOMONTH(E55,3) -> 43921 | G56: 664533 | H56: 821382 | I56: 728123 | J56: 691312
E57: =EOMONTH(E56,3) -> 44012 | G57: 650141 | H57: 713913 | I57: 691525 | J57: 708600
E58: =EOMONTH(E57,3) -> 44104 | G58: 649560 | H58: 673308 | I58: 595978 | J58: 677140
E59: =EOMONTH(E58,3) -> 44196 | G59: 645058 | H59: 677950 | I59: 616922 | J59: 702624
E60: =EOMONTH(E59,3) -> 44286 | G60: 676898 | H60: 648728 | I60: 707559 | J60: 677462
E61: =EOMONTH(E60,3) -> 44377 | G61: 642290 | H61: 809610 | I61: 590734 | J61: 708052
E62: =EOMONTH(E61,3) -> 44469 | G62: 652741 | H62: 773370 | I62: 663876 | J62: 672161
E63: =EOMONTH(E62,3) -> 44561 | G63: 643964 | H63: 805384 | I63: 726276 | J63: 638978
E64: =EOMONTH(E63,3) -> 44651 | G64: 642292 | H64: 713333 | I64: 647828 | J64: 695189
E65: =EOMONTH(E64,3) -> 44742 | G65: 671775 | H65: 737873 | I65: 708470 | J65: 724269
... E91: =EOMONTH(E90,3) -> 47118 | G91: 772307 | H91: 800839 | I91: 707446 | J91: 771585
A93: Model technical inputs
D96: CFM Topic | E96: Debt
D98: Model period beginning | F98: date | J98: {=EDATE(start_date + 1,_xlfn.SEQUENCE(1,periods,0,3))} -> 43466 | K98: 43556 | L98: 43647 | M98: 43739 | N98: 43831 | O98: 43922 | P98: 44013 | Q98: 44105 | R98: 44197 | S98: 44287 | T98: 44378 | U98: 44470 | V98: 44562 | W98: 44652 | X98: 44743 | Y98: 44835 | Z98: 44927 | AA98: 45017 | AB98: 45108 | AC98: 45200 | AD98: 45292 | AE98: 45383 | AF98: 45474 | AG98: 45566 | AH98: 45658 | AI98: 45748 | AJ98: 45839 | AK98: 45931 | AL98: 46023 | AM98: 46113 | AN98: 46204 | AO98: 46296 | AP98: 46388 | AQ98: 46478 | AR98: 46569 | AS98: 46661 | AT98: 46753 | AU98: 46844 | AV98: 46935 | AW98: 47027
D99: Model period ending | F99: date | J99: {=EOMONTH( start_date, _xlfn.SEQUENCE( 1, periods, 3, 3 ) )} -> 43555 | K99: 43646 | L99: 43738 | M99: 43830 | N99: 43921 | O99: 44012 | P99: 44104 | Q99: 44196 | R99: 44286 | S99: 44377 | T99: 44469 | U99: 44561 | V99: 44651 | W99: 44742 | X99: 44834 | Y99: 44926 | Z99: 45016 | AA99: 45107 | AB99: 45199 | AC99: 45291 | AD99: 45382 | AE99: 45473 | AF99: 45565 | AG99: 45657 | AH99: 45747 | AI99: 45838 | AJ99: 45930 | AK99: 46022 | AL99: 46112 | AM99: 46203 | AN99: 46295 | AO99: 46387 | AP99: 46477 | AQ99: 46568 | AR99: 46660 | AS99: 46752 | AT99: 46843 | AU99: 46934 | AV99: 47026 | AW99: 47118
D100: Model period counter | F100: counter | J100: {=_xlfn.SEQUENCE( 1, periods, 1, 1 )} -> 1 | K100: 2 | L100: 3 | M100: 4 | N100: 5 | O100: 6 | P100: 7 | Q100: 8 | R100: 9 | S100: 10 | T100: 11 | U100: 12 | V100: 13 | W100: 14 | X100: 15 | Y100: 16 | Z100: 17 | AA100: 18 | AB100: 19 | AC100: 20 | AD100: 21 | AE100: 22 | AF100: 23 | AG100: 24 | AH100: 25 | AI100: 26 | AJ100: 27 | AK100: 28 | AL100: 29 | AM100: 30 | AN100: 31 | AO100: 32 | AP100: 33 | AQ100: 34 | AR100: 35 | AS100: 36 | AT100: 37 | AU100: 38 | AV100: 39 | AW100: 40
D101: Model first period flag | F101: flag | J101: {=IF(_xlfn.ANCHORARRAY( J100) = 1, 1, 0 )} -> 1 | K101: 0 | L101: 0 | M101: 0 | N101: 0 | O101: 0 | P101: 0 | Q101: 0 | R101: 0 | S101: 0 | T101: 0 | U101: 0 | V101: 0 | W101: 0 | X101: 0 | Y101: 0 | Z101: 0 | AA101: 0 | AB101: 0 | AC101: 0 | AD101: 0 | AE101: 0 | AF101: 0 | AG101: 0 | AH101: 0 | AI101: 0 | AJ101: 0 | AK101: 0 | AL101: 0 | AM101: 0 | AN101: 0 | AO101: 0 | AP101: 0 | AQ101: 0 | AR101: 0 | AS101: 0 | AT101: 0 | AU101: 0 | AV101: 0 | AW101: 0
D104: Sculpting scenarios | E104: {=TRANSPOSE($G$17:$I$17 )} -> Passive
E105: Neutral
E106: Aggressive
D108: EBIDTA scenarios | E108: {=TRANSPOSE( $G$50:$J$50 )} -> Base Case
E109: Case 2
E110: Case 3
E111: Case 4
C116: End Sheet

Sheet Case1Solution
A1: Blackrat SPV Pty Ltd
A3: 2 | C3: Solution
C9: Date | F9: =Case1Data!H39 -> 43465 | G9: =EOMONTH(F9,3) -> 43555 | H9: =EOMONTH(G9,3) -> 43646 | I9: =EOMONTH(H9,3) -> 43738 | J9: =EOMONTH(I9,3) -> 43830 | K9: =EOMONTH(J9,3) -> 43921 | L9: =EOMONTH(K9,3) -> 44012 | M9: =EOMONTH(L9,3) -> 44104 | N9: =EOMONTH(M9,3) -> 44196 | ... AT9: =EOMONTH(AS9,3) -> 47118
C10: Quarter | G10: =F10+1 -> 1 | H10: =G10+1 -> 2 | I10: =H10+1 -> 3 | J10: =I10+1 -> 4 | K10: =J10+1 -> 5 | L10: =K10+1 -> 6 | M10: =L10+1 -> 7 | N10: =M10+1 -> 8 | ... AT10: =AS10+1 -> 40
A12: =MAX(A$2:A11)+0.01 -> 2.01 | C12: Answers
C14: a) | D14: Schedules | E14: See below
C15: b) | D15: Scenarios | E15: See below
C16: c) | D16: Neutral / Base Case Sr. Debt Repaid | E16: =P24 -> 46477
C17: d) | D17: Total Jr. Facility Interest | E17: =SUM(G91:AT91) -> 2152500
C18: e) | D18: Aggressive / Case 2, Equity Distribution in Mar 2020 | E18: =$Q$32 -> 94488.176
C19: f) | D19: Situation with Highest IRR | E19: =G23&" / "&F25 -> Passive / Case 2
C20: g) | D20: Situation with Lowest NPV | E20: =I30&" / "&F31 -> Aggressive / Base Case
D22: IRR Sensitivity | G22: Sculpting and interest rate scenarios | K22: Sr. Debt Repayment Date | O22: Sculpting and interest rate scenarios
F23: =E111 -> 0.16166523 | G23: =Case1Data!$G$17 -> Passive | H23: =Case1Data!$H$17 -> Neutral | I23: =Case1Data!$I$17 -> Aggressive | N23: =E56 -> 46022 | O23: =Case1Data!$G$17 -> Passive | P23: =Case1Data!$H$17 -> Neutral | Q23: =Case1Data!$I$17 -> Aggressive
E24: EBITDA | F24: =Case1Data!$G$50 -> Base Case | G24: 0.11439549 | H24: 0.101513 | I24: 0.093689504 | M24: EBITDA | N24: =Case1Data!$G$50 -> Base Case | O24: 46752 | P24: 46477 | Q24: 46295
E25: Profiles | F25: =Case1Data!$H$50 -> Case 2 | G25: 0.18833821 | H25: 0.17128327 | I25: 0.16166523 | M25: Profiles | N25: =Case1Data!$H$50 -> Case 2 | O25: 46387 | P25: 46112 | Q25: 46022
F26: =Case1Data!$I$50 -> Case 3 | G26: 0.12684518 | H26: 0.11314749 | I26: 0.10482313 | N26: =Case1Data!$I$50 -> Case 3 | O26: 46660 | P26: 46387 | Q26: 46295
F27: =Case1Data!$J$50 -> Case 4 | G27: 0.14833984 | H27: 0.13353439 | I27: 0.12480724 | N27: =Case1Data!$J$50 -> Case 4 | O27: 46568 | P27: 46295 | Q27: 46203
D29: NPV Sensitivity | G29: Sculpting and interest rate scenarios | K29: Mar 2020 Equity Distribution | O29: Sculpting and interest rate scenarios
F30: =$E$112 -> 1979546.5 | G30: =Case1Data!$G$17 -> Passive | H30: =Case1Data!$H$17 -> Neutral | I30: =Case1Data!$I$17 -> Aggressive | N30: =K104 -> 94488.176 | O30: =Case1Data!$G$17 -> Passive | P30: =Case1Data!$H$17 -> Neutral | Q30: =Case1Data!$I$17 -> Aggressive
E31: EBITDA | F31: =Case1Data!$G$50 -> Base Case | G31: 456463.88 | H31: 169615.06 | I31: -35704.706 | M31: EBITDA | N31: =Case1Data!$G$50 -> Base Case | O31: 88704 | P31: 51681.333 | Q31: 29903.294
E32: Profiles | F32: =Case1Data!$H$50 -> Case 2 | G32: 2430210.2 | H32: 2169637.1 | I32: 1979546.5 | M32: Profiles | N32: =Case1Data!$H$50 -> Case 2 | O32: 167128.5 | P32: 121392 | Q32: 94488.176
F33: =Case1Data!$I$50 -> Case 3 | G33: 756919.36 | H33: 476045 | I33: 269899.44 | N33: =Case1Data!$I$50 -> Case 3 | O33: 120499 | P33: 79943.556 | Q33: 56087.412
F34: =Case1Data!$J$50 -> Case 4 | G34: 1325222.5 | H34: 1050944.8 | I34: 849944.61 | N34: =Case1Data!$J$50 -> Case 4 | O34: 102093.5 | P34: 63583.111 | Q34: 40929.941
A36: =MAX(A$2:A35)+0.01 -> 2.02 | C36: Scenarios
C38: Sculpting and interest rate scenarios
D39: Selected Case | E39: Aggressive
D40: Sculpted senior DSCR | E40: =INDEX(Case1Data!$G$18:$I$18,MATCH(E$39,Case1Data!$G$17:$I$17,0)) -> 1.7
D41: Annual interest rate | E41: =INDEX(Case1Data!$G$19:$I$19,MATCH(E$39,Case1Data!$G$17:$I$17,0)) -> 0.055
C43: EBITDA Profiles ($)
D44: Selected Case | E44: Case 2
D45: EBITDA | G45: =INDEX(Case1Data!$G$52:$J$91,MATCH(G$9,Case1Data!$E$52:$E$91,0),MATCH($E44,Case1Data!$G$50:$J$50,0)) -> 812279 | H45: =INDEX(Case1Data!$G$52:$J$91,MATCH(H$9,Case1Data!$E$52:$E$91,0),MATCH($E44,Case1Data!$G$50:$J$50,0)) -> 706344 | I45: =INDEX(Case1Data!$G$52:$J$91,MATCH(I$9,Case1Data!$E$52:$E$91,0),MATCH($E44,Case1Data!$G$50:$J$50,0)) -> 770727 | J45: =INDEX(Case1Data!$G$52:$J$91,MATCH(J$9,Case1Data!$E$52:$E$91,0),MATCH($E44,Case1Data!$G$50:$J$50,0)) -> 789594 | K45: =INDEX(Case1Data!$G$52:$J$91,MATCH(K$9,Case1Data!$E$52:$E$91,0),MATCH($E44,Case1Data!$G$50:$J$50,0)) -> 821382 | L45: =INDEX(Case1Data!$G$52:$J$91,MATCH(L$9,Case1Data!$E$52:$E$91,0),MATCH($E44,Case1Data!$G$50:$J$50,0)) -> 713913 | M45: =INDEX(Case1Data!$G$52:$J$91,MATCH(M$9,Case1Data!$E$52:$E$91,0),MATCH($E44,Case1Data!$G$50:$J$50,0)) -> 673308 | N45: =INDEX(Case1Data!$G$52:$J$91,MATCH(N$9,Case1Data!$E$52:$E$91,0),MATCH($E44,Case1Data!$G$50:$J$50,0)) -> 677950 | ... AT45: =INDEX(Case1Data!$G$52:$J$91,MATCH(AT$9,Case1Data!$E$52:$E$91,0),MATCH($E44,Case1Data!$G$50:$J$50,0)) -> 800839
A47: =MAX(A$2:A46)+0.01 -> 2.03 | C47: Senior Facility
C49: Opening Balance | G49: =F51 -> 10000000 | H49: =G51 -> 9658585.9 | I49: =H51 -> 9374792 | J49: =I51 -> 9049223.7 | K49: =J51 -> 8708080.5 | L49: =K51 -> 8343547.8 | M49: =L51 -> 8037219.8 | N49: =M51 -> 7750565.1 | ... AT49: =AS51 -> 0
C50: Issuance / (Repayment) | G50: =-MIN(G49,G68) -> -341414.12 | H50: =-MIN(H49,H68) -> -283793.86 | I50: =-MIN(I49,I68) -> -325568.37 | J50: =-MIN(J49,J68) -> -341143.17 | K50: =-MIN(K49,K68) -> -364532.72 | L50: =-MIN(L49,L68) -> -306327.98 | M50: =-MIN(M49,M68) -> -286654.7 | N50: =-MIN(N49,N68) -> -293326.79 | ... AT50: =-MIN(AT49,AT68) -> 0
C51: Closing Balance | F51: =Case1Data!H13 -> 10000000 | G51: =SUM(G49:G50) -> 9658585.9 | H51: =SUM(H49:H50) -> 9374792 | I51: =SUM(I49:I50) -> 9049223.7 | J51: =SUM(J49:J50) -> 8708080.5 | K51: =SUM(K49:K50) -> 8343547.8 | L51: =SUM(L49:L50) -> 8037219.8 | M51: =SUM(M49:M50) -> 7750565.1 | N51: =SUM(N49:N50) -> 7457238.3 | ... AT51: =SUM(AT49:AT50) -> 0
C53: Interest Rate | E53: =E41 -> 0.055 | G53: =$E53 -> 0.055 | H53: =$E53 -> 0.055 | I53: =$E53 -> 0.055 | J53: =$E53 -> 0.055 | K53: =$E53 -> 0.055 | L53: =$E53 -> 0.055 | M53: =$E53 -> 0.055 | N53: =$E53 -> 0.055 | ... AT53: =$E53 -> 0.055
C54: Interest Expense | G54: =G49*G53/4 -> 137500 | H54: =H49*H53/4 -> 132805.56 | I54: =I49*I53/4 -> 128903.39 | J54: =J49*J53/4 -> 124426.83 | K54: =K49*K53/4 -> 119736.11 | L54: =L49*L53/4 -> 114723.78 | M54: =M49*M53/4 -> 110511.77 | N54: =N49*N53/4 -> 106570.27 | ... AT54: =AT49*AT53/4 -> 0
C56: Repayment Period | E56: =INDEX(F9:AT9,MATCH(0,F51:AT51,0)) -> 46022
A58: =MAX(A$2:A57)+0.01 -> 2.04 | C58: DSCR
C60: Target DSCR | E60: =E40 -> 1.7 | G60: =$E60 -> 1.7 | H60: =$E60 -> 1.7 | I60: =$E60 -> 1.7 | J60: =$E60 -> 1.7 | K60: =$E60 -> 1.7 | L60: =$E60 -> 1.7 | M60: =$E60 -> 1.7 | N60: =$E60 -> 1.7 | ... AT60: =$E60 -> 1.7
C62: EBITDA | G62: =G$45 -> 812279 | H62: =H$45 -> 706344 | I62: =I$45 -> 770727 | J62: =J$45 -> 789594 | K62: =K$45 -> 821382 | L62: =L$45 -> 713913 | M62: =M$45 -> 673308 | N62: =N$45 -> 677950 | ... AT62: =AT$45 -> 800839
C63: Interest Income | G63: =G80 -> 1875 | H63: =H80 -> 1875 | I63: =I80 -> 1875 | J63: =J80 -> 1875 | K63: =K80 -> 1875 | L63: =L80 -> 1875 | M63: =M80 -> 1875 | N63: =N80 -> 1875 | ... AT63: =AT80 -> 0
C64: Cash Available for Debt Service | G64: =SUM(G62:G63) -> 814154 | H64: =SUM(H62:H63) -> 708219 | I64: =SUM(I62:I63) -> 772602 | J64: =SUM(J62:J63) -> 791469 | K64: =SUM(K62:K63) -> 823257 | L64: =SUM(L62:L63) -> 715788 | M64: =SUM(M62:M63) -> 675183 | N64: =SUM(N62:N63) -> 679825 | ... AT64: =SUM(AT62:AT63) -> 800839
C66: Target Sr. Debt Service | G66: =G64/G60 -> 478914.12 | H66: =H64/H60 -> 416599.41 | I66: =I64/I60 -> 454471.76 | J66: =J64/J60 -> 465570 | K66: =K64/K60 -> 484268.82 | L66: =L64/L60 -> 421051.76 | M66: =M64/M60 -> 397166.47 | N66: =N64/N60 -> 399897.06 | ... AT66: =AT64/AT60 -> 471081.76
C67: Less: Sr. Debt Interest Expense | G67: =-G54 -> -137500 | H67: =-H54 -> -132805.56 | I67: =-I54 -> -128903.39 | J67: =-J54 -> -124426.83 | K67: =-K54 -> -119736.11 | L67: =-L54 -> -114723.78 | M67: =-M54 -> -110511.77 | N67: =-N54 -> -106570.27 | ... AT67: =-AT54 -> 0
C68: Target Debt Repayment | G68: =SUM(G66:G67) -> 341414.12 | H68: =SUM(H66:H67) -> 283793.86 | I68: =SUM(I66:I67) -> 325568.37 | J68: =SUM(J66:J67) -> 341143.17 | K68: =SUM(K66:K67) -> 364532.72 | L68: =SUM(L66:L67) -> 306327.98 | M68: =SUM(M66:M67) -> 286654.7 | N68: =SUM(N66:N67) -> 293326.79 | ... AT68: =SUM(AT66:AT67) -> 471081.76
C70: Actual DSCR | G70: =IFERROR(G64/(G54-G50),0) -> 1.7 | H70: =IFERROR(H64/(H54-H50),0) -> 1.7 | I70: =IFERROR(I64/(I54-I50),0) -> 1.7 | J70: =IFERROR(J64/(J54-J50),0) -> 1.7 | K70: =IFERROR(K64/(K54-K50),0) -> 1.7 | L70: =IFERROR(L64/(L54-L50),0) -> 1.7 | M70: =IFERROR(M64/(M54-M50),0) -> 1.7 | N70: =IFERROR(N64/(N54-N50),0) -> 1.7 | ... AT70: =IFERROR(AT64/(AT54-AT50),0) -> 0
A72: =MAX(A$2:A71)+0.01 -> 2.05 | C72: DSRA
C74: NB: It was not required to make this section any more complicated / dynamic
C75: Opening Balance | G75: =F77 -> 500000 | H75: =G77 -> 500000 | I75: =H77 -> 500000 | J75: =I77 -> 500000 | K75: =J77 -> 500000 | L75: =K77 -> 500000 | M75: =L77 -> 500000 | N75: =M77 -> 500000 | ... AT75: =AS77 -> 0
C76: Issuance / (Repayment) | G76: =IF(G51=0,-G75,0) -> 0 | H76: =IF(H51=0,-H75,0) -> 0 | I76: =IF(I51=0,-I75,0) -> 0 | J76: =IF(J51=0,-J75,0) -> 0 | K76: =IF(K51=0,-K75,0) -> 0 | L76: =IF(L51=0,-L75,0) -> 0 | M76: =IF(M51=0,-M75,0) -> 0 | N76: =IF(N51=0,-N75,0) -> 0 | ... AT76: =IF(AT51=0,-AT75,0) -> 0
C77: Closing Balance | F77: =Case1Data!H23 -> 500000 | G77: =SUM(G75:G76) -> 500000 | H77: =SUM(H75:H76) -> 500000 | I77: =SUM(I75:I76) -> 500000 | J77: =SUM(J75:J76) -> 500000 | K77: =SUM(K75:K76) -> 500000 | L77: =SUM(L75:L76) -> 500000 | M77: =SUM(M75:M76) -> 500000 | N77: =SUM(N75:N76) -> 500000 | ... AT77: =SUM(AT75:AT76) -> 0
C79: Interest Rate | E79: =Case1Data!H25 -> 0.015 | G79: =$E79 -> 0.015 | H79: =$E79 -> 0.015 | I79: =$E79 -> 0.015 | J79: =$E79 -> 0.015 | K79: =$E79 -> 0.015 | L79: =$E79 -> 0.015 | M79: =$E79 -> 0.015 | N79: =$E79 -> 0.015 | ... AT79: =$E79 -> 0.015
C80: Interest Income | G80: =G75*G79/4 -> 1875 | H80: =H75*H79/4 -> 1875 | I80: =I75*I79/4 -> 1875 | J80: =J75*J79/4 -> 1875 | K80: =K75*K79/4 -> 1875 | L80: =L75*L79/4 -> 1875 | M80: =M75*M79/4 -> 1875 | N80: =N75*N79/4 -> 1875 | ... AT80: =AT75*AT79/4 -> 0
A82: =MAX(A$2:A81)+0.01 -> 2.06 | C82: Junior Facility
C84: Amortization Quarters | E84: =Case1Data!H30 -> 40
C86: Opening Balance | G86: =F88 -> 6000000 | H86: =G88 -> 5850000 | I86: =H88 -> 5700000 | J86: =I88 -> 5550000 | K86: =J88 -> 5400000 | L86: =K88 -> 5250000 | M86: =L88 -> 5100000 | N86: =M88 -> 4950000 | ... AT86: =AS88 -> 150000
C87: Issuance / (Repayment) | E87: =F88/E84 -> 150000 | G87: =-MIN(G86,$E87) -> -150000 | H87: =-MIN(H86,$E87) -> -150000 | I87: =-MIN(I86,$E87) -> -150000 | J87: =-MIN(J86,$E87) -> -150000 | K87: =-MIN(K86,$E87) -> -150000 | L87: =-MIN(L86,$E87) -> -150000 | M87: =-MIN(M86,$E87) -> -150000 | N87: =-MIN(N86,$E87) -> -150000 | ... AT87: =-MIN(AT86,$E87) -> -150000
C88: Closing Balance | F88: =Case1Data!$H$28 -> 6000000 | G88: =SUM(G86:G87) -> 5850000 | H88: =SUM(H86:H87) -> 5700000 | I88: =SUM(I86:I87) -> 5550000 | J88: =SUM(J86:J87) -> 5400000 | K88: =SUM(K86:K87) -> 5250000 | L88: =SUM(L86:L87) -> 5100000 | M88: =SUM(M86:M87) -> 4950000 | N88: =SUM(N86:N87) -> 4800000 | ... AT88: =SUM(AT86:AT87) -> 0
C90: Interest Rate | E90: =Case1Data!H29 -> 0.07 | G90: =$E90 -> 0.07 | H90: =$E90 -> 0.07 | I90: =$E90 -> 0.07 | J90: =$E90 -> 0.07 | K90: =$E90 -> 0.07 | L90: =$E90 -> 0.07 | M90: =$E90 -> 0.07 | N90: =$E90 -> 0.07 | ... AT90: =$E90 -> 0.07
C91: Interest Expense | G91: =G86*G90/4 -> 105000 | H91: =H86*H90/4 -> 102375 | I91: =I86*I90/4 -> 99750 | J91: =J86*J90/4 -> 97125 | K91: =K86*K90/4 -> 94500 | L91: =L86*L90/4 -> 91875 | M91: =M86*M90/4 -> 89250 | N91: =N86*N90/4 -> 86625 | ... AT91: =AT86*AT90/4 -> 2625
A93: =MAX(A$2:A92)+0.01 -> 2.07 | C93: Returns & Value
C95: Equity Cash Flows
C97: EBITDA | G97: =G45 -> 812279 | H97: =H45 -> 706344 | I97: =I45 -> 770727 | J97: =J45 -> 789594 | K97: =K45 -> 821382 | L97: =L45 -> 713913 | M97: =M45 -> 673308 | N97: =N45 -> 677950 | ... AT97: =AT45 -> 800839
C98: Interest Income | G98: =G80 -> 1875 | H98: =H80 -> 1875 | I98: =I80 -> 1875 | J98: =J80 -> 1875 | K98: =K80 -> 1875 | L98: =L80 -> 1875 | M98: =M80 -> 1875 | N98: =N80 -> 1875 | ... AT98: =AT80 -> 0
C99: DSRA Release | G99: =-G76 -> 0 | H99: =-H76 -> 0 | I99: =-I76 -> 0 | J99: =-J76 -> 0 | K99: =-K76 -> 0 | L99: =-L76 -> 0 | M99: =-M76 -> 0 | N99: =-N76 -> 0 | ... AT99: =-AT76 -> 0
C100: Sr. Debt Repayment | G100: =G50 -> -341414.12 | H100: =H50 -> -283793.86 | I100: =I50 -> -325568.37 | J100: =J50 -> -341143.17 | K100: =K50 -> -364532.72 | L100: =L50 -> -306327.98 | M100: =M50 -> -286654.7 | N100: =N50 -> -293326.79 | ... AT100: =AT50 -> 0
C101: Sr. Debt Interest Expense | G101: =-G54 -> -137500 | H101: =-H54 -> -132805.56 | I101: =-I54 -> -128903.39 | J101: =-J54 -> -124426.83 | K101: =-K54 -> -119736.11 | L101: =-L54 -> -114723.78 | M101: =-M54 -> -110511.77 | N101: =-N54 -> -106570.27 | ... AT101: =-AT54 -> 0
C102: Junior Debt Repayment | G102: =G87 -> -150000 | H102: =H87 -> -150000 | I102: =I87 -> -150000 | J102: =J87 -> -150000 | K102: =K87 -> -150000 | L102: =L87 -> -150000 | M102: =M87 -> -150000 | N102: =N87 -> -150000 | ... AT102: =AT87 -> -150000
C103: Junior Debt Interest Expense | G103: =-G91 -> -105000 | H103: =-H91 -> -102375 | I103: =-I91 -> -99750 | J103: =-J91 -> -97125 | K103: =-K91 -> -94500 | L103: =-L91 -> -91875 | M103: =-M91 -> -89250 | N103: =-N91 -> -86625 | ... AT103: =-AT91 -> -2625
C104: Equity Distribution | G104: =SUM(G97:G103) -> 80239.882 | H104: =SUM(H97:H103) -> 39244.588 | I104: =SUM(I97:I103) -> 68380.235 | J104: =SUM(J97:J103) -> 78774 | K104: =SUM(K97:K103) -> 94488.176 | L104: =SUM(L97:L103) -> 52861.235 | M104: =SUM(M97:M103) -> 38766.529 | N104: =SUM(N97:N103) -> 43302.941 | ... AT104: =SUM(AT97:AT103) -> 648214
C106: Equity Investment | F106: =-Case1Data!H34 -> -4000000 | G106: 0 | H106: 0 | I106: 0 | J106: 0 | K106: 0 | L106: 0 | M106: 0 | N106: 0 | O106: 0 | P106: 0 | Q106: 0 | R106: 0 | S106: 0 | T106: 0 | U106: 0 | V106: 0 | W106: 0 | X106: 0 | Y106: 0 | Z106: 0 | AA106: 0 | AB106: 0 | AC106: 0 | AD106: 0 | AE106: 0 | AF106: 0 | AG106: 0 | AH106: 0 | AI106: 0 | AJ106: 0 | AK106: 0 | AL106: 0 | AM106: 0 | AN106: 0 | AO106: 0 | AP106: 0 | AQ106: 0 | AR106: 0 | AS106: 0 | AT106: 0
C107: Equity Cash Flows | F107: =F104+F106 -> -4000000 | G107: =G104+G106 -> 80239.882 | H107: =H104+H106 -> 39244.588 | I107: =I104+I106 -> 68380.235 | J107: =J104+J106 -> 78774 | K107: =K104+K106 -> 94488.176 | L107: =L104+L106 -> 52861.235 | M107: =M104+M106 -> 38766.529 | ... AT107: =AT104+AT106 -> 648214
C109: Cash Flow Date | F109: =F9 -> 43465 | G109: =G9 -> 43555 | H109: =H9 -> 43646 | I109: =I9 -> 43738 | J109: =J9 -> 43830 | K109: =K9 -> 43921 | L109: =L9 -> 44012 | M109: =M9 -> 44104 | ... AT109: =AT9 -> 47118
C111: IRR | E111: =XIRR(F107:AT107,F109:AT109) -> 0.16166523
C112: NPV | E112: =XNPV(E113,F107:AT107,F109:AT109) -> 1979546.5
C113: Discount Rate | E113: =Case1Data!H35 -> 0.095
