Workbook
Name company: CaseData!$B$1
Name periods: CaseData!$L$8
Name start_date: CaseData!$L$7
Name topic: "CFM Topic: " & CaseData!$L$10

Sheet Debt
A1: =company -> YHF Ltd.
A2: {=topic} -> CFM Topic: Debt
A3: DEBT SCHEDULE | F3: Constant | G3: Unit | H3: Total | J3: =J$9 -> 43982 | K3: =K$9 -> 44012 | L3: =L$9 -> 44043 | M3: =M$9 -> 44074 | N3: =N$9 -> 44104 | O3: =O$9 -> 44135
A6: Model timeline
E8: Model start date | F8: =start_date -> 43952 | G8: date
E9: Model timeline | G9: date | J9: {=EOMONTH( start_date, _xlfn.SEQUENCE( 1, periods, 0, 1 ) )} -> 43982 | K9: 44012 | L9: 44043 | M9: 44074 | N9: 44104 | O9: 44135
E10: Model counter | G10: counter | J10: {=_xlfn.SEQUENCE( 1, periods, 1, 1 )} -> 1 | K10: 2 | L10: 3 | M10: 4 | N10: 5 | O10: 6
E11: Model first period flag | G11: flag | J11: =IF( J10 = 1, 1, 0 ) -> 1 | K11: =IF( K10 = 1, 1, 0 ) -> 0 | L11: =IF( L10 = 1, 1, 0 ) -> 0 | M11: =IF( M10 = 1, 1, 0 ) -> 0 | N11: =IF( N10 = 1, 1, 0 ) -> 0 | O11: =IF( O10 = 1, 1, 0 ) -> 0
A13: Total Debt / EBIDTA
F15: 43951
E16: Total Debt | F16: =CaseData!$S$43 -> 686848 | G16: USD | J16: =J$172 -> 681851.48 | K16: =K$172 -> 678153.14 | L16: =L$172 -> 676192.03 | M16: =M$172 -> 680818.37 | N16: =N$172 -> 678745.64 | O16: =O$172 -> 677079.93
E17: EBIDTA | F17: =CaseData!$S$44 -> 191177 | G17: USD | J17: =CaseData!E$54 -> 193220 | K17: =CaseData!F$54 -> 189600 | L17: =CaseData!G$54 -> 186312 | M17: =CaseData!H$54 -> 185545 | N17: =CaseData!I$54 -> 185313 | O17: =CaseData!J$54 -> 183795
E18: Total Debt / EBIDTA | F18: =CaseData!$S$45 -> 3.5927334 | G18: multiple | J18: =IFERROR( J16 / J17, "to be calc" ) -> 3.5288866 | K18: =IFERROR( K16 / K17, "to be calc" ) -> 3.5767571 | L18: =IFERROR( L16 / L17, "to be calc" ) -> 3.6293531 | M18: =IFERROR( M16 / M17, "to be calc" ) -> 3.6692898 | N18: =IFERROR( N16 / N17, "to be calc" ) -> 3.6626985 | O18: =IFERROR( O16 / O17, "to be calc" ) -> 3.6838865
A20: Taxes
E22: Free Cash Flow Before Debt Service & Taxes | G22: USD | H22: =SUM( J22:O22) -> 51072.897 | J22: =CaseData!E$56 -> 10393.67 | K22: =CaseData!F$56 -> 8667.573 | L22: =CaseData!G$56 -> 6355.84 | M22: =CaseData!H$56 -> 8884.205 | N22: =CaseData!I$56 -> 11026.2 | O22: =CaseData!J$56 -> 5745.409
D23: less | E23: =E$154 -> Interest expenses accrued | G23: =G$154 -> USD | H23: =SUM( J23:O23) -> -24452.594 | I23: =I$154 -> 0 | J23: =J$154 * - 1 -> -3731.6406 | K23: =K$154 * - 1 -> -3736.4541 | L23: =L$154 * - 1 -> -3741.028 | M23: =M$154 * - 1 -> -6298.9093 | N23: =N$154 * - 1 -> -3420.1032 | O23: =O$154 * - 1 -> -3524.4585
E24: Taxable income | G24: USD | H24: =SUM( J24:O24) -> 26620.303 | J24: =SUM(J22:J23) -> 6662.0294 | K24: =SUM(K22:K23) -> 4931.1189 | L24: =SUM(L22:L23) -> 2614.812 | M24: =SUM(M22:M23) -> 2585.2957 | N24: =SUM(N22:N23) -> 7606.0968 | O24: =SUM(O22:O23) -> 2220.9505
E26: Applicable tax rate | F26: =CaseData!$L$11 -> 0.25 | G26: %
E27: Taxes paid | G27: USD | H27: =SUM( J27:O27) -> 6655.0758 | J27: =J$24 * $F$26 -> 1665.5073 | K27: =K$24 * $F$26 -> 1232.7797 | L27: =L$24 * $F$26 -> 653.70299 | M27: =M$24 * $F$26 -> 646.32391 | N27: =N$24 * $F$26 -> 1901.5242 | O27: =O$24 * $F$26 -> 555.23764
A29: Revolver
C32: Free cash flow after repayment of debt service and taxes
E33: Free Cash Flow Before Debt Service & Taxes | G33: USD | J33: =CaseData!E$56 -> 10393.67 | K33: =CaseData!F$56 -> 8667.573 | L33: =CaseData!G$56 -> 6355.84 | M33: =CaseData!H$56 -> 8884.205 | N33: =CaseData!I$56 -> 11026.2 | O33: =CaseData!J$56 -> 5745.409
E34: =E$142 -> Principal addition / (repayment) | G34: =G$142 -> USD | J34: =J$142 -> -2179.6875 | K34: =K$142 -> -2152.4414 | L34: =L$142 -> -2125.5359 | M34: =M$142 -> 12901.033 | N34: =N$142 -> -2072.7296 | O34: =O$142 -> -2046.8205
D35: less | E35: =E$154 -> Interest expenses accrued | G35: =G$154 -> USD | J35: =J$154 * - 1 -> -3731.6406 | K35: =K$154 * - 1 -> -3736.4541 | L35: =L$154 * - 1 -> -3741.028 | M35: =M$154 * - 1 -> -6298.9093 | N35: =N$154 * - 1 -> -3420.1032 | O35: =O$154 * - 1 -> -3524.4585
D36: less | E36: =E$27 -> Taxes paid | G36: =G$27 -> USD | J36: =J$27 * - 1 -> -1665.5073 | K36: =K$27 * - 1 -> -1232.7797 | L36: =L$27 * - 1 -> -653.70299 | M36: =M$27 * - 1 -> -646.32391 | N36: =N$27 * - 1 -> -1901.5242 | O36: =O$27 * - 1 -> -555.23764
E37: Free cash flow after repayment of debt service and taxes | J37: =SUM(J33:J36) -> 2816.8345 | K37: =SUM(K33:K36) -> 1545.8978 | L37: =SUM(L33:L36) -> -164.42692 | M37: =SUM(M33:M36) -> 14840.005 | N37: =SUM(N33:N36) -> 3631.843 | O37: =SUM(O33:O36) -> -381.10757
E39: Revolver balance as of 30/04/2020 | F39: =CaseData!$E$8 -> 12473 | G39: USD
E41: Revolver beginning balance | G41: USD | J41: =IF( J$11 = 1, $F$39, I43) -> 12473 | K41: =IF( K$11 = 1, $F$39, J43) -> 9656.1655 | L41: =IF( L$11 = 1, $F$39, K43) -> 8110.2677 | M41: =IF( M$11 = 1, $F$39, L43) -> 8274.6946 | N41: =IF( N$11 = 1, $F$39, M43) -> 0 | O41: =IF( O$11 = 1, $F$39, N43) -> 0
E42: Revolver drawdown / (repayment) | G42: USD | J42: =- MIN( J$37, J$41 ) -> -2816.8345 | K42: =- MIN( K$37, K$41 ) -> -1545.8978 | L42: =- MIN( L$37, L$41 ) -> 164.42692 | M42: =- MIN( M$37, M$41 ) -> -8274.6946 | N42: =- MIN( N$37, N$41 ) -> 0 | O42: =- MIN( O$37, O$41 ) -> 381.10757
E43: Revolver | G43: USD | J43: =SUM(J41:J42) -> 9656.1655 | K43: =SUM(K41:K42) -> 8110.2677 | L43: =SUM(L41:L42) -> 8274.6946 | M43: =SUM(M41:M42) -> 0 | N43: =SUM(N41:N42) -> 0 | O43: =SUM(O41:O42) -> 381.10757
C46: Revolver interest expenses
E47: LIBOR | G47: % | J47: =CaseData!E$57 -> 0.0225 | K47: =CaseData!F$57 -> 0.0235 | L47: =CaseData!G$57 -> 0.0245 | M47: =CaseData!H$57 -> 0.0255 | N47: =CaseData!I$57 -> 0.0265 | O47: =CaseData!J$57 -> 0.027
E48: Spread to LIBOR on drawn funds based on Total Debt / EBIDTA | G48: % | J48: {=_xlfn.XLOOKUP( IF( J$11 = 1, $F$18, I$18 ), CaseData!$G$11:$G$14, CaseData!$I$11:$I$14 / 10000,,-1 )} -> 0.03 | K48: {=_xlfn.XLOOKUP( IF( K$11 = 1, $F$18, J$18 ), CaseData!$G$11:$G$14, CaseData!$I$11:$I$14 / 10000,,-1 )} -> 0.03 | L48: {=_xlfn.XLOOKUP( IF( L$11 = 1, $F$18, K$18 ), CaseData!$G$11:$G$14, CaseData!$I$11:$I$14 / 10000,,-1 )} -> 0.03 | M48: {=_xlfn.XLOOKUP( IF( M$11 = 1, $F$18, L$18 ), CaseData!$G$11:$G$14, CaseData!$I$11:$I$14 / 10000,,-1 )} -> 0.03 | N48: {=_xlfn.XLOOKUP( IF( N$11 = 1, $F$18, M$18 ), CaseData!$G$11:$G$14, CaseData!$I$11:$I$14 / 10000,,-1 )} -> 0.03 | O48: {=_xlfn.XLOOKUP( IF( O$11 = 1, $F$18, N$18 ), CaseData!$G$11:$G$14, CaseData!$I$11:$I$14 / 10000,,-1 )} -> 0.03
E49: Effective interest rate on revolver | G49: % | J49: =SUM(J47:J48) -> 0.0525 | K49: =SUM(K47:K48) -> 0.0535 | L49: =SUM(L47:L48) -> 0.0545 | M49: =SUM(M47:M48) -> 0.0555 | N49: =SUM(N47:N48) -> 0.0565 | O49: =SUM(O47:O48) -> 0.057
E52: Annual Commitment Fee (on Undrawn Portion) | F52: =CaseData!E$10 -> 80 | G52: bps
E53: Maximum facility size | F53: =CaseData!$E$7 -> 50000 | G53: USD
E55: Commitment fee on undrawn amount | G55: USD | H55: =SUM( J55:O55) -> 182.38518 | J55: =( $F$53 - J$43 ) * $F$52 / 10000 / 12 -> 26.89589 | K55: =( $F$53 - K$43 ) * $F$52 / 10000 / 12 -> 27.926488 | L55: =( $F$53 - L$43 ) * $F$52 / 10000 / 12 -> 27.81687 | M55: =( $F$53 - M$43 ) * $F$52 / 10000 / 12 -> 33.333333 | N55: =( $F$53 - N$43 ) * $F$52 / 10000 / 12 -> 33.333333 | O55: =( $F$53 - O$43 ) * $F$52 / 10000 / 12 -> 33.079262
E56: Drawn interest expenses | G56: USD | H56: =SUM( J56:O56) -> 172.72437 | J56: =IF( J$11 = 1, $F$39 * J$49 / 12, I$43 * J$49 / 12 ) -> 54.569375 | K56: =IF( K$11 = 1, $F$39 * K$49 / 12, J$43 * K$49 / 12 ) -> 43.050404 | L56: =IF( L$11 = 1, $F$39 * L$49 / 12, K$43 * L$49 / 12 ) -> 36.834132 | M56: =IF( M$11 = 1, $F$39 * M$49 / 12, L$43 * M$49 / 12 ) -> 38.270463 | N56: =IF( N$11 = 1, $F$39 * N$49 / 12, M$43 * N$49 / 12 ) -> 0 | O56: =IF( O$11 = 1, $F$39 * O$49 / 12, N$43 * O$49 / 12 ) -> 0
E57: Revolver interest expenses | G57: USD | H57: =SUM( J57:O57) -> 355.10955 | J57: =SUM(J55:J56) -> 81.465265 | K57: =SUM(K55:K56) -> 70.976893 | L57: =SUM(L55:L56) -> 64.651003 | M57: =SUM(M55:M56) -> 71.603796 | N57: =SUM(N55:N56) -> 33.333333 | O57: =SUM(O55:O56) -> 33.079262
A60: Senior Secured Term Loan
E63: Senior Secured Term Loan balance as of 30/04/2020 | F63: =CaseData!$E$17 -> 174375 | G63: USD
E65: Senior Secured Term Loan beginning balance | G65: USD | J65: =IF( J$11 = 1, $F$63, I67) -> 174375 | K65: =IF( K$11 = 1, $F$39, J67) -> 172195.31 | L65: =IF( L$11 = 1, $F$39, K67) -> 170042.87 | M65: =IF( M$11 = 1, $F$39, L67) -> 167917.34 | N65: =IF( N$11 = 1, $F$39, M67) -> 165818.37 | O65: =IF( O$11 = 1, $F$39, N67) -> 163745.64
E66: Senior Secured Term Loan drawdown / (repayment) | G66: USD | J66: =J$71 * - 1 -> -2179.6875 | K66: =K$71 * - 1 -> -2152.4414 | L66: =L$71 * - 1 -> -2125.5359 | M66: =M$71 * - 1 -> -2098.9667 | N66: =N$71 * - 1 -> -2072.7296 | O66: =O$71 * - 1 -> -2046.8205
E67: Senior Secured Term Loan | G67: USD | J67: =SUM(J65:J66) -> 172195.31 | K67: =SUM(K65:K66) -> 170042.87 | L67: =SUM(L65:L66) -> 167917.34 | M67: =SUM(M65:M66) -> 165818.37 | N67: =SUM(N65:N66) -> 163745.64 | O67: =SUM(O65:O66) -> 161698.82
C69: Senior Secured Term Loan repayment
E70: Monthy Amortization | F70: =CaseData!$E$20 -> 0.0125 | G70: %
E71: Senior Secured Term Loan repayment | G71: USD | H71: =SUM(J71:O71) -> 12676.182 | J71: =J65 * $F$70 -> 2179.6875 | K71: =K65 * $F$70 -> 2152.4414 | L71: =L65 * $F$70 -> 2125.5359 | M71: =M65 * $F$70 -> 2098.9667 | N71: =N65 * $F$70 -> 2072.7296 | O71: =O65 * $F$70 -> 2046.8205
C73: Senior Secured Term Loan interest expenses
E74: LIBOR | G74: % | J74: =CaseData!E$57 -> 0.0225 | K74: =CaseData!F$57 -> 0.0235 | L74: =CaseData!G$57 -> 0.0245 | M74: =CaseData!H$57 -> 0.0255 | N74: =CaseData!I$57 -> 0.0265 | O74: =CaseData!J$57 -> 0.027
E75: Spread to LIBOR on drawn funds based on Total Debt / EBIDTA | G75: % | J75: {=_xlfn.XLOOKUP( IF( J$11 = 1, $F$18, I$18 ), CaseData!$G$11:$G$14, CaseData!$I$11:$I$14 / 10000,,-1 )} -> 0.03 | K75: {=_xlfn.XLOOKUP( IF( K$11 = 1, $F$18, J$18 ), CaseData!$G$11:$G$14, CaseData!$I$11:$I$14 / 10000,,-1 )} -> 0.03 | L75: {=_xlfn.XLOOKUP( IF( L$11 = 1, $F$18, K$18 ), CaseData!$G$11:$G$14, CaseData!$I$11:$I$14 / 10000,,-1 )} -> 0.03 | M75: {=_xlfn.XLOOKUP( IF( M$11 = 1, $F$18, L$18 ), CaseData!$G$11:$G$14, CaseData!$I$11:$I$14 / 10000,,-1 )} -> 0.03 | N75: {=_xlfn.XLOOKUP( IF( N$11 = 1, $F$18, M$18 ), CaseData!$G$11:$G$14, CaseData!$I$11:$I$14 / 10000,,-1 )} -> 0.03 | O75: {=_xlfn.XLOOKUP( IF( O$11 = 1, $F$18, N$18 ), CaseData!$G$11:$G$14, CaseData!$I$11:$I$14 / 10000,,-1 )} -> 0.03
E76: Effective interest rate on Senior Secured Term Loan | G76: % | J76: =SUM(J74:J75) -> 0.0525 | K76: =SUM(K74:K75) -> 0.0535 | L76: =SUM(L74:L75) -> 0.0545 | M76: =SUM(M74:M75) -> 0.0555 | N76: =SUM(N74:N75) -> 0.0565 | O76: =SUM(O74:O75) -> 0.057
E79: Senior Secured Term Loan interest expenses | G79: USD | H79: =SUM( J79:O79) -> 4638.0104 | J79: =J$65 * J$76 / 12 -> 762.89062 | K79: =K$65 * K$76 / 12 -> 767.7041 | L79: =L$65 * L$76 / 12 -> 772.27804 | M79: =M$65 * M$76 / 12 -> 776.61768 | N79: =N$65 * N$76 / 12 -> 780.72815 | O79: =O$65 * O$76 / 12 -> 777.79178
A81: Subordinated Note
E84: Subordinated Note balance as of 30/04/2020 | F84: =CaseData!$I$17 -> 500000 | G84: USD
E86: Subordinated Note beginning balance | G86: USD | J86: =IF( J$11 = 1, $F$84, I88) -> 500000 | K86: =IF( K$11 = 1, $F$39, J88) -> 500000 | L86: =IF( L$11 = 1, $F$39, K88) -> 500000 | M86: =IF( M$11 = 1, $F$39, L88) -> 500000 | N86: =IF( N$11 = 1, $F$39, M88) -> 0 | O86: =IF( O$11 = 1, $F$39, N88) -> 0
E87: Subordinated Note issue / (retirement) | G87: USD | J87: =J$97 * - 1 -> 0 | K87: =K$97 * - 1 -> 0 | L87: =L$97 * - 1 -> 0 | M87: =M$97 * - 1 -> -500000 | N87: =N$97 * - 1 -> 0 | O87: =O$97 * - 1 -> 0
E88: Subordinated Note | G88: USD | J88: =SUM(J86:J87) -> 500000 | K88: =SUM(K86:K87) -> 500000 | L88: =SUM(L86:L87) -> 500000 | M88: =SUM(M86:M87) -> 0 | N88: =SUM(N86:N87) -> 0 | O88: =SUM(O86:O87) -> 0
C90: Subordinated Note retirement
E91: Maturity date | F91: 44196
E92: Early retirement date | F92: 44074 | G92: data validation
E94: Early call prices for retirement on or before:
E95: 44043 | F95: =CaseData!I24 -> 1.03 | G95: %
E96: 44135 | F96: =CaseData!I25 -> 1.02 | G96: % | J96: =IF( J$3 = $F$92, _xlfn.XLOOKUP( $F$92, $E$95:$E$96, $F$95:$F$96,,-1 ), 0 ) -> 0 | K96: =IF( K$3 = $F$92, _xlfn.XLOOKUP( $F$92, $E$95:$E$96, $F$95:$F$96,,-1 ), 0 ) -> 0 | L96: =IF( L$3 = $F$92, _xlfn.XLOOKUP( $F$92, $E$95:$E$96, $F$95:$F$96,,-1 ), 0 ) -> 0 | M96: =IF( M$3 = $F$92, _xlfn.XLOOKUP( $F$92, $E$95:$E$96, $F$95:$F$96,,-1 ), 0 ) -> 1.03 | N96: =IF( N$3 = $F$92, _xlfn.XLOOKUP( $F$92, $E$95:$E$96, $F$95:$F$96,,-1 ), 0 ) -> 0 | O96: =IF( O$3 = $F$92, _xlfn.XLOOKUP( $F$92, $E$95:$E$96, $F$95:$F$96,,-1 ), 0 ) -> 0
E97: Face value of subordinated note | G97: USD | J97: =IF( J$3 = $F$92, $F$84, 0 ) -> 0 | K97: =IF( K$3 = $F$92, $F$84, 0 ) -> 0 | L97: =IF( L$3 = $F$92, $F$84, 0 ) -> 0 | M97: =IF( M$3 = $F$92, $F$84, 0 ) -> 500000 | N97: =IF( N$3 = $F$92, $F$84, 0 ) -> 0 | O97: =IF( O$3 = $F$92, $F$84, 0 ) -> 0
E98: Early call premium over the face value | G98: USD | J98: =IF( J$97 > 0, J$97 * J$96 - $F$84, 0 ) -> 0 | K98: =IF( K$97 > 0, K$97 * K$96 - $F$84, 0 ) -> 0 | L98: =IF( L$97 > 0, L$97 * L$96 - $F$84, 0 ) -> 0 | M98: =IF( M$97 > 0, M$97 * M$96 - $F$84, 0 ) -> 15000 | N98: =IF( N$97 > 0, N$97 * N$96 - $F$84, 0 ) -> 0 | O98: =IF( O$97 > 0, O$97 * O$96 - $F$84, 0 ) -> 0
E99: Refinincing costs of existing Subordinated Note | G99: USD | H99: =SUM( J99:O99) -> 515000 | J99: =SUM(J97:J98) -> 0 | K99: =SUM(K97:K98) -> 0 | L99: =SUM(L97:L98) -> 0 | M99: =SUM(M97:M98) -> 515000 | N99: =SUM(N97:N98) -> 0 | O99: =SUM(O97:O98) -> 0
C101: Subordinated Note interest expenses
E102: Effective interest rate on Subordinated Note | F102: =CaseData!$I$19 -> 0.07125 | G102: %
E103: Subordinated Note interest accrued | G103: USD | H103: =SUM(J103:O103) -> 11875 | J103: =J$86 * $F$102 / 12 -> 2968.75 | K103: =K$86 * $F$102 / 12 -> 2968.75 | L103: =L$86 * $F$102 / 12 -> 2968.75 | M103: =M$86 * $F$102 / 12 -> 2968.75 | N103: =N$86 * $F$102 / 12 -> 0 | O103: =O$86 * $F$102 / 12 -> 0
C105: Subordinated Note interest paid
E106: =E$99 -> Refinincing costs of existing Subordinated Note | G106: =G$99 -> USD | J106: =J$99 -> 0 | K106: =K$99 -> 0 | L106: =L$99 -> 0 | M106: =M$99 -> 515000 | N106: =N$99 -> 0 | O106: =O$99 -> 0
E107: Interest payable semi-annually on:
F108: =CaseData!$I$20 -> 43951 | G108: date
F109: =CaseData!$I$21 -> 44135 | G109: date
E110: Subordinated Note interest paid | G110: USD | H110: =SUM(J110:O110) -> 11875 | J110: =IF( J$106 > 0, J$103 * J$10, 0 ) -> 0 | K110: =IF( K$106 > 0, K$103 * K$10, 0 ) -> 0 | L110: =IF( L$106 > 0, L$103 * L$10, 0 ) -> 0 | M110: =IF( M$106 > 0, M$103 * M$10, 0 ) -> 11875 | N110: =IF( N$106 > 0, N$103 * N$10, 0 ) -> 0 | O110: =IF( O$106 > 0, O$103 * O$10, 0 ) -> 0
A112: New Subordinated Note
E114: New Subordinated Note balance as of 30/04/2020 | F114: 0 | G114: USD
E116: New Subordinated Note beginning balance | G116: USD | J116: =IF( J$11 = 1, $F$114, I119) -> 0 | K116: =IF( K$11 = 1, $F$114, J119) -> 0 | L116: =IF( L$11 = 1, $F$114, K119) -> 0 | M116: =IF( M$11 = 1, $F$114, L119) -> 0 | N116: =IF( N$11 = 1, $F$114, M119) -> 515000 | O116: =IF( O$11 = 1, $F$114, N119) -> 515000
E117: New Subordinated Note issue / (retirement) | G117: =G$97 -> USD | J117: =J$97 -> 0 | K117: =K$97 -> 0 | L117: =L$97 -> 0 | M117: =M$97 -> 500000 | N117: =N$97 -> 0 | O117: =O$97 -> 0
E118: =E$98 -> Early call premium over the face value | G118: =G$98 -> USD | J118: =J$98 -> 0 | K118: =K$98 -> 0 | L118: =L$98 -> 0 | M118: =M$98 -> 15000 | N118: =N$98 -> 0 | O118: =O$98 -> 0
E119: New Subordinated Note | G119: USD | J119: =SUM(J116:J118) -> 0 | K119: =SUM(K116:K118) -> 0 | L119: =SUM(L116:L118) -> 0 | M119: =SUM(M116:M118) -> 515000 | N119: =SUM(N116:N118) -> 515000 | O119: =SUM(O116:O118) -> 515000
C122: New Subordinated Note interest expenses
E123: Effective interest rate on New Subordinated Note | G123: % | J123: {=_xlfn.XLOOKUP( $J$3:$O$3, CaseData!$K$17:$K$22, CaseData!$L$17:$L$22 )} -> 0.0505 | K123: 0.0525 | L123: 0.057 | M123: 0.0595 | N123: 0.0615 | O123: 0.064
E124: New Subordinated Note interest accrued | G124: USD | H124: =SUM(J124:O124) -> 7939.5833 | J124: =J$119 * J$123 / 12 -> 0 | K124: =K$119 * K$123 / 12 -> 0 | L124: =L$119 * L$123 / 12 -> 0 | M124: =M$119 * M$123 / 12 -> 2553.5417 | N124: =N$119 * N$123 / 12 -> 2639.375 | O124: =O$119 * O$123 / 12 -> 2746.6667
C126: New Subordinated Note interest paid
E127: =E$99 -> Refinincing costs of existing Subordinated Note | G127: =G$99 -> USD | J127: =J$119 -> 0 | K127: =K$119 -> 0 | L127: =L$119 -> 0 | M127: =M$119 -> 515000 | N127: =N$119 -> 515000 | O127: =O$119 -> 515000
E128: Interest payable semi-annually on:
F129: =CaseData!$I$20 -> 43951 | G129: date
F130: =CaseData!$I$21 -> 44135 | G130: date
E131: Subordinated Note interest paid | G131: USD | H131: =SUM(J131:O131) -> 7939.5833 | J131: =IF( AND( J127 > 0, OR( J$3 = $F$129, J$3 = $F$130 ) ), SUM( $I124:J124 ), 0 ) -> 0 | K131: =IF( AND( K127 > 0, OR( K$3 = $F$129, K$3 = $F$130 ) ), SUM( $I124:K124 ), 0 ) -> 0 | L131: =IF( AND( L127 > 0, OR( L$3 = $F$129, L$3 = $F$130 ) ), SUM( $I124:L124 ), 0 ) -> 0 | M131: =IF( AND( M127 > 0, OR( M$3 = $F$129, M$3 = $F$130 ) ), SUM( $I124:M124 ), 0 ) -> 0 | N131: =IF( AND( N127 > 0, OR( N$3 = $F$129, N$3 = $F$130 ) ), SUM( $I124:N124 ), 0 ) -> 0 | O131: =IF( AND( O127 > 0, OR( O$3 = $F$129, O$3 = $F$130 ) ), SUM( $I124:O124 ), 0 ) -> 7939.5833
A134: Principal addition / (repayment)
E136: Used in the FCF after repayment of debt service and taxes
E138: =E$66 -> Senior Secured Term Loan drawdown / (repayment) | G138: =G$66 -> USD | H138: =SUM(J138:O138) -> -12676.182 | J138: =J$66 -> -2179.6875 | K138: =K$66 -> -2152.4414 | L138: =L$66 -> -2125.5359 | M138: =M$66 -> -2098.9667 | N138: =N$66 -> -2072.7296 | O138: =O$66 -> -2046.8205
E139: =E$87 -> Subordinated Note issue / (retirement) | G139: =G$87 -> USD | H139: =SUM(J139:O139) -> -500000 | J139: =J$87 -> 0 | K139: =K$87 -> 0 | L139: =L$87 -> 0 | M139: =M$87 -> -500000 | N139: =N$87 -> 0 | O139: =O$87 -> 0
E140: =E$117 -> New Subordinated Note issue / (retirement) | G140: =G$117 -> USD | H140: =SUM(J140:O140) -> 500000 | J140: =J$117 -> 0 | K140: =K$117 -> 0 | L140: =L$117 -> 0 | M140: =M$117 -> 500000 | N140: =N$117 -> 0 | O140: =O$117 -> 0
E141: =E$118 -> Early call premium over the face value | G141: =G$118 -> USD | H141: =SUM(J141:O141) -> 15000 | J141: =J$118 -> 0 | K141: =K$118 -> 0 | L141: =L$118 -> 0 | M141: =M$118 -> 15000 | N141: =N$118 -> 0 | O141: =O$118 -> 0
E142: Principal addition / (repayment) | G142: USD | H142: =SUM(J142:O142) -> 2323.8184 | J142: =SUM(J138:J141) -> -2179.6875 | K142: =SUM(K138:K141) -> -2152.4414 | L142: =SUM(L138:L141) -> -2125.5359 | M142: =SUM(M138:M141) -> 12901.033 | N142: =SUM(N138:N141) -> -2072.7296 | O142: =SUM(O138:O141) -> -2046.8205
A145: Interest expenses accrued
E147: Used in the FCF after repayment of debt service and taxes
C149: Interest expenses accrued
...

Sheet CaseData
B1: YHF Ltd.
B2: (in thousands of $)
B4: Existing Debt as at April 30, 2020
B6: Revolving Credit Facility:
B7: Max. Amount | E7: 50000 | G7: Annual Rates on Drawn Funds (Paid Monthly) | K7: Model start | L7: 43952 | M7: date
B8: Balance Outstanding | E8: 12473 | G8: (spread based on previous month's ratio) | K8: Periods | L8: 6 | M8: months
G9: Total Debt / | I9: Spread to | K9: Model end | L9: =EOMONTH( start_date, periods ) -> 44165 | M9: date
B10: Annual Commitment Fee (on Undrawn Portion) | E10: 80 | G10: EBITDA >= | I10: LIBOR | K10: Topic | L10: Debt
B11: (payable monthly) | G11: 0 | I11: 100 | K11: Tax rate | L11: 0.25 | M11: %
G12: 2 | I12: 175
B13: Interest Coverage Ratio | E13: 2.5 | G13: 3 | I13: 225
G14: 3.5 | I14: 300
B16: Senior Secured Term Loan: | G16: Subordinated Notes: | K16: New Subordinated Note
B17: Balance Outstanding | E17: 174375 | G17: Face Amount | I17: 500000 | K17: 43982 | L17: 0.0505
B18: Original Amount | E18: 225000 | G18: Amortization | I18: 0 | K18: 44012 | L18: 0.0525
G19: Annual Coupon | I19: 0.07125 | K19: 44043 | L19: 0.057
B20: Monthy Amortization | E20: 0.0125 | G20: Payable semi-annually on: | I20: 43951 | K20: 44074 | L20: 0.0595
I21: 44135 | K21: 44104 | L21: 0.0615
B22: Annual Interest Rate | E22: Same | G22: Final Maturity | I22: Oct. 31, 2020 | K22: 44135 | L22: 0.064
B23: (payable monthly) | E23: as revolver | G23: Early Call Prices:
G24: Before 7/31/20 | I24: 1.03
B25: Final Maturity | E25: Jun. 30, 2025 | G25: Before 10/31/20 | I25: 1.02
B27: Historical Debt Details
B29: Revolving Credit Facility: | E29: 43524 | F29: 43555 | G29: 43585 | H29: 43616 | I29: 43646 | J29: 43677 | K29: 43708 | L29: 43738 | M29: 43769 | N29: 43799 | O29: 43830 | P29: 43861 | Q29: 43890 | R29: 43921 | S29: 43951
B30: Ending Balance | D30: 10029 | E30: 5395 | F30: 11094 | G30: 12111 | H30: 12263 | I30: 21116 | J30: 26477 | K30: 31004 | L30: 18530 | M30: 8274 | N30: 31247 | O30: 33481 | P30: 15891 | Q30: 36380 | R30: 13877 | S30: 12473
B31: Drawn Interest | E31: 44.337 | F31: 24.929 | G31: 49.137 | H31: 53.884 | I31: 51.709 | J31: 97.239 | K31: 112.814 | L31: 131.534 | M31: 82.721 | N31: 36.771 | O31: 130.274 | P31: 141.792 | Q31: 68.583 | R31: 165.832 | S31: 60.272
B32: Undrawn Interest | E32: 26.647 | F32: 29.737 | G32: 25.937 | H32: 25.259 | I32: 25.158 | J32: 19.256 | K32: 15.682 | L32: 12.664 | M32: 20.98 | N32: 27.817 | O32: 12.502 | P32: 11.013 | Q32: 22.739 | R32: 9.08 | S32: 24.082
B34: Senior Secured Term Loan:
B35: Ending Balance | D35: 216562.5 | E35: 213750 | F35: 210937.5 | G35: 208125 | H35: 205312.5 | I35: 202500 | J35: 199687.5 | K35: 196875 | L35: 194062.5 | M35: 191250 | N35: 188437.5 | O35: 185625 | P35: 182812.5 | Q35: 180000 | R35: 177187.5 | S35: 174375
B36: Interest | E36: 957.387 | F36: 987.703 | G36: 934.277 | H36: 925.983 | I36: 865.734 | J36: 932.513 | K36: 850.835 | L36: 835.242 | M36: 866.327 | N36: 849.947 | O36: 785.627 | P36: 786.122 | Q36: 788.988 | R36: 820.5 | S36: 769.584
B38: Subordinated Notes:
B39: Ending Balance | D39: 500000 | E39: 500000 | F39: 500000 | G39: 500000 | H39: 500000 | I39: 500000 | J39: 500000 | K39: 500000 | L39: 500000 | M39: 500000 | N39: 500000 | O39: 500000 | P39: 500000 | Q39: 500000 | R39: 500000 | S39: 500000
B40: Interest | E40: 2968.75 | F40: 2968.75 | G40: 2968.75 | H40: 2968.75 | I40: 2968.75 | J40: 2968.75 | K40: 2968.75 | L40: 2968.75 | M40: 2968.75 | N40: 2968.75 | O40: 2968.75 | P40: 2968.75 | Q40: 2968.75 | R40: 2968.75 | S40: 2968.75
B43: Total Debt | D43: 726591.5 | E43: 719145 | F43: 722031.5 | G43: 720236 | H43: 717575.5 | I43: 723616 | J43: 726164.5 | K43: 727879 | L43: 712592.5 | M43: 699524 | N43: 719684.5 | O43: 719106 | P43: 698703.5 | Q43: 716380 | R43: 691064.5 | S43: 686848
B44: TTM EBITDA | D44: 183244 | E44: 191930 | F44: 199032 | G44: 175519 | H44: 170868 | I44: 156913 | J44: 179890 | K44: 174023 | L44: 198141 | M44: 191052 | N44: 189901 | O44: 165475 | P44: 198550 | Q44: 187963 | R44: 180401 | S44: 191177
B45: Total Debt / EBITDA | D45: 3.9651585 | E45: 3.7469129 | F45: 3.6277156 | G45: 4.1034646 | H45: 4.1995897 | I45: 4.6115746 | J45: 4.0367141 | K45: 4.1826598 | L45: 3.596391 | M45: 3.6614325 | N45: 3.7897878 | O45: 4.3457078 | P45: 3.5190305 | Q45: 3.811282 | R45: 3.8307132 | S45: 3.5927334
B46: LIBOR | D46: 0.02317 | E46: 0.02305 | F46: 0.02545 | G46: 0.02315 | H46: 0.02339 | I46: 0.0206 | J46: 0.02526 | K46: 0.02113 | L46: 0.02091 | M46: 0.02357 | N46: 0.02333 | O46: 0.02003 | P46: 0.02082 | Q46: 0.02179 | R46: 0.0247 | S46: 0.02212
B47: Spread | E47: 0.03 | F47: 0.03 | G47: 0.03 | H47: 0.03 | I47: 0.03 | J47: 0.03 | K47: 0.03 | L47: 0.03 | M47: 0.03 | N47: 0.03 | O47: 0.03 | P47: 0.03 | Q47: 0.03 | R47: 0.03 | S47: 0.03
B48: Rate | E48: 0.05305 | F48: 0.05545 | G48: 0.05315 | H48: 0.05339 | I48: 0.0506 | J48: 0.05526 | K48: 0.05113 | L48: 0.05091 | M48: 0.05357 | N48: 0.05333 | O48: 0.05003 | P48: 0.05082 | Q48: 0.05179 | R48: 0.0547 | S48: 0.05212
B51: Forecasted Data
E53: 43982 | F53: 44012 | G53: 44043 | H53: 44074 | I53: 44104 | J53: 44135
B54: TTM EBITDA | E54: 193220 | F54: 189600 | G54: 186312 | H54: 185545 | I54: 185313 | J54: 183795
B55: TTM Capex | E55: 81423 | F55: 63499 | G55: 89256 | H55: 86777 | I55: 77656 | J55: 83704
B56: Free Cash Flow Before Debt Service & Taxes | E56: 10393.67 | F56: 8667.573 | G56: 6355.84 | H56: 8884.205 | I56: 11026.2 | J56: 5745.409
B57: LIBOR | E57: 0.0225 | F57: 0.0235 | G57: 0.0245 | H57: 0.0255 | I57: 0.0265 | J57: 0.027

Sheet CaseSolution
B1: YHF Ltd.
B2: (in thousands of $)
B4: =CaseData!$B$4 -> Existing Debt as at April 30, 2020
B6: Revolving Credit Facility:
B7: Max. Amount | D7: =CaseData!E7 -> 50000 | F7: Annual Rates on Drawn Funds (Paid Monthly) | J7: Taxes
B8: Balance Outstanding | D8: =CaseData!E8 -> 12473 | F8: (spread based on previous month's ratio)
F9: Total Debt / | H9: Spread to | J9: Applicable Rate: | L9: 0.25
B10: Annual Commitment Fee (on Undrawn Portion) | D10: =CaseData!E10 -> 80 | F10: EBITDA >= | H10: LIBOR
B11: (payable monthly) | F11: =CaseData!G11 -> 0 | H11: =CaseData!I11 -> 100
F12: =CaseData!G12 -> 2 | H12: =CaseData!I12 -> 175
B13: Interest Coverage Ratio | D13: =CaseData!E13 -> 2.5 | F13: =CaseData!G13 -> 3 | H13: =CaseData!I13 -> 225
F14: =CaseData!G14 -> 3.5 | H14: =CaseData!I14 -> 300
B16: Senior Secured Term Loan: | F16: Subordinated Notes: | J16: New Senior Notes:
B17: Balance Outstanding | D17: =CaseData!E17 -> 174375 | F17: Face Amount | H17: =CaseData!I17 -> 500000 | J17: Date Issued | L17: 44043
B18: Original Amount | D18: =CaseData!E18 -> 225000 | F18: Amortization | H18: =CaseData!I18 -> 0 | J18: Annual Coupons:
F19: Annual Coupon | H19: =CaseData!I19 -> 0.07125 | J19: {=TRANSPOSE(D65:I65)} -> 43982 | L19: 0.0505
B20: Monthy Amortization | D20: =CaseData!E20 -> 0.0125 | F20: Payable semi-annually on: | H20: 43951 | J20: 44012 | L20: 0.0525
H21: 44135 | J21: 44043 | L21: 0.057
B22: Annual Interest Rate | D22: =CaseData!E22 -> Same | F22: Final Maturity | H22: =CaseData!I22 -> Oct. 31, 2020 | J22: 44074 | L22: 0.0595
B23: (payable monthly) | D23: =CaseData!E23 -> as revolver | F23: Call Prices: | J23: 44104 | L23: 0.0615
F24: =R31 -> 43951 | H24: 1.03 | J24: 44135 | L24: 0.064
B25: Final Maturity | D25: =CaseData!E25 -> Jun. 30, 2025 | F25: 44043 | H25: 1.02
J26: Payable semi-annually on: | L26: =EOMONTH(L17,6) -> 44227
L27: =EOMONTH(L26,6) -> 44408
B29: Historical Debt Details
B31: =B6 -> Revolving Credit Facility: | D31: =CaseData!E29 -> 43524 | E31: =CaseData!F29 -> 43555 | F31: =CaseData!G29 -> 43585 | G31: =CaseData!H29 -> 43616 | H31: =CaseData!I29 -> 43646 | I31: =CaseData!J29 -> 43677 | J31: =CaseData!K29 -> 43708 | K31: =CaseData!L29 -> 43738 | ... R31: =CaseData!S29 -> 43951
B32: Ending Balance | C32: =CaseData!D30 -> 10029 | D32: =CaseData!E30 -> 5395 | E32: =CaseData!F30 -> 11094 | F32: =CaseData!G30 -> 12111 | G32: =CaseData!H30 -> 12263 | H32: =CaseData!I30 -> 21116 | I32: =CaseData!J30 -> 26477 | J32: =CaseData!K30 -> 31004 | ... R32: =CaseData!S30 -> 12473
B33: Drawn Interest | D33: =CaseData!E31 -> 44.337 | E33: =CaseData!F31 -> 24.929 | F33: =CaseData!G31 -> 49.137 | G33: =CaseData!H31 -> 53.884 | H33: =CaseData!I31 -> 51.709 | I33: =CaseData!J31 -> 97.239 | J33: =CaseData!K31 -> 112.814 | K33: =CaseData!L31 -> 131.534 | ... R33: =CaseData!S31 -> 60.272
B34: Undrawn Interest | D34: =CaseData!E32 -> 26.647 | E34: =CaseData!F32 -> 29.737 | F34: =CaseData!G32 -> 25.937 | G34: =CaseData!H32 -> 25.259 | H34: =CaseData!I32 -> 25.158 | I34: =CaseData!J32 -> 19.256 | J34: =CaseData!K32 -> 15.682 | K34: =CaseData!L32 -> 12.664 | ... R34: =CaseData!S32 -> 24.082
B35: Total Reveolver Interest | D35: =D33+D34 -> 70.984 | E35: =E33+E34 -> 54.666 | F35: =F33+F34 -> 75.074 | G35: =G33+G34 -> 79.143 | H35: =H33+H34 -> 76.867 | I35: =I33+I34 -> 116.495 | J35: =J33+J34 -> 128.496 | K35: =K33+K34 -> 144.198 | ... R35: =R33+R34 -> 84.354
B37: Senior Secured Term Loan:
B38: Ending Balance | C38: =CaseData!D35 -> 216562.5 | D38: =CaseData!E35 -> 213750 | E38: =CaseData!F35 -> 210937.5 | F38: =CaseData!G35 -> 208125 | G38: =CaseData!H35 -> 205312.5 | H38: =CaseData!I35 -> 202500 | I38: =CaseData!J35 -> 199687.5 | J38: =CaseData!K35 -> 196875 | ... R38: =CaseData!S35 -> 174375
B39: Interest | D39: =CaseData!E36 -> 957.387 | E39: =CaseData!F36 -> 987.703 | F39: =CaseData!G36 -> 934.277 | G39: =CaseData!H36 -> 925.983 | H39: =CaseData!I36 -> 865.734 | I39: =CaseData!J36 -> 932.513 | J39: =CaseData!K36 -> 850.835 | K39: =CaseData!L36 -> 835.242 | ... R39: =CaseData!S36 -> 769.584
B41: =F16 -> Subordinated Notes:
B42: Ending Balance | C42: =CaseData!D39 -> 500000 | D42: =CaseData!E39 -> 500000 | E42: =CaseData!F39 -> 500000 | F42: =CaseData!G39 -> 500000 | G42: =CaseData!H39 -> 500000 | H42: =CaseData!I39 -> 500000 | I42: =CaseData!J39 -> 500000 | J42: =CaseData!K39 -> 500000 | ... R42: =CaseData!S39 -> 500000
B43: Interest | D43: =CaseData!E40 -> 2968.75 | E43: =CaseData!F40 -> 2968.75 | F43: =CaseData!G40 -> 2968.75 | G43: =CaseData!H40 -> 2968.75 | H43: =CaseData!I40 -> 2968.75 | I43: =CaseData!J40 -> 2968.75 | J43: =CaseData!K40 -> 2968.75 | K43: =CaseData!L40 -> 2968.75 | ... R43: =CaseData!S40 -> 2968.75
B46: Total Debt | C46: =C32+C38+C42 -> 726591.5 | D46: =D32+D38+D42 -> 719145 | E46: =E32+E38+E42 -> 722031.5 | F46: =F32+F38+F42 -> 720236 | G46: =G32+G38+G42 -> 717575.5 | H46: =H32+H38+H42 -> 723616 | I46: =I32+I38+I42 -> 726164.5 | J46: =J32+J38+J42 -> 727879 | ... R46: =R32+R38+R42 -> 686848
B47: TTM EBITDA | C47: =CaseData!D44 -> 183244 | D47: =CaseData!E44 -> 191930 | E47: =CaseData!F44 -> 199032 | F47: =CaseData!G44 -> 175519 | G47: =CaseData!H44 -> 170868 | H47: =CaseData!I44 -> 156913 | I47: =CaseData!J44 -> 179890 | J47: =CaseData!K44 -> 174023 | ... R47: =CaseData!S44 -> 191177
B48: Total Debt / EBITDA | C48: =C46/C47 -> 3.9651585 | D48: =D46/D47 -> 3.7469129 | E48: =E46/E47 -> 3.6277156 | F48: =F46/F47 -> 4.1034646 | G48: =G46/G47 -> 4.1995897 | H48: =H46/H47 -> 4.6115746 | I48: =I46/I47 -> 4.0367141 | J48: =J46/J47 -> 4.1826598 | ... R48: =R46/R47 -> 3.5927334
B49: LIBOR | C49: =CaseData!D46 -> 0.02317 | D49: =CaseData!E46 -> 0.02305 | E49: =CaseData!F46 -> 0.02545 | F49: =CaseData!G46 -> 0.02315 | G49: =CaseData!H46 -> 0.02339 | H49: =CaseData!I46 -> 0.0206 | I49: =CaseData!J46 -> 0.02526 | J49: =CaseData!K46 -> 0.02113 | ... R49: =CaseData!S46 -> 0.02212
B50: Spread | D50: =CaseData!E47 -> 0.03 | E50: =CaseData!F47 -> 0.03 | F50: =CaseData!G47 -> 0.03 | G50: =CaseData!H47 -> 0.03 | H50: =CaseData!I47 -> 0.03 | I50: =CaseData!J47 -> 0.03 | J50: =CaseData!K47 -> 0.03 | K50: =CaseData!L47 -> 0.03 | ... R50: =CaseData!S47 -> 0.03
B51: Rate | D51: =D49+D50 -> 0.05305 | E51: =E49+E50 -> 0.05545 | F51: =F49+F50 -> 0.05315 | G51: =G49+G50 -> 0.05339 | H51: =H49+H50 -> 0.0506 | I51: =I49+I50 -> 0.05526 | J51: =J49+J50 -> 0.05113 | K51: =K49+K50 -> 0.05091 | ... R51: =R49+R50 -> 0.05212
B52: Total Interest | D52: =D33+D34+D39+D43 -> 3997.121 | E52: =E33+E34+E39+E43 -> 4011.119 | F52: =F33+F34+F39+F43 -> 3978.101 | G52: =G33+G34+G39+G43 -> 3973.876 | H52: =H33+H34+H39+H43 -> 3911.351 | I52: =I33+I34+I39+I43 -> 4017.758 | J52: =J33+J34+J39+J43 -> 3948.081 | K52: =K33+K34+K39+K43 -> 3948.19 | ... R52: =R33+R34+R39+R43 -> 3822.688
B55: Forecasted Data
C57: =CaseData!$S$29 -> 43951 | D57: =EOMONTH(R31,1) -> 43982 | E57: =EOMONTH(D57,1) -> 44012 | F57: =EOMONTH(E57,1) -> 44043 | G57: =EOMONTH(F57,1) -> 44074 | H57: =EOMONTH(G57,1) -> 44104 | I57: =EOMONTH(H57,1) -> 44135
B58: TTM EBITDA | C58: =CaseData!$S$44 -> 191177 | D58: =CaseData!E54 -> 193220 | E58: =CaseData!F54 -> 189600 | F58: =CaseData!G54 -> 186312 | G58: =CaseData!H54 -> 185545 | H58: =CaseData!I54 -> 185313 | I58: =CaseData!J54 -> 183795
B59: TTM Capex | D59: =CaseData!E55 -> 81423 | E59: =CaseData!F55 -> 63499 | F59: =CaseData!G55 -> 89256 | G59: =CaseData!H55 -> 86777 | H59: =CaseData!I55 -> 77656 | I59: =CaseData!J55 -> 83704
B60: FCF Before Debt Service & Taxes | D60: =CaseData!E56 -> 10393.67 | E60: =CaseData!F56 -> 8667.573 | F60: =CaseData!G56 -> 6355.84 | G60: =CaseData!H56 -> 8884.205 | H60: =CaseData!I56 -> 11026.2 | I60: =CaseData!J56 -> 5745.409
B61: LIBOR | D61: =CaseData!E57 -> 0.0225 | E61: =CaseData!F57 -> 0.0235 | F61: =CaseData!G57 -> 0.0245 | G61: =CaseData!H57 -> 0.0255 | H61: =CaseData!I57 -> 0.0265 | I61: =CaseData!J57 -> 0.027
B63: New Calculations
C65: =CaseData!$S$29 -> 43951 | D65: =D57 -> 43982 | E65: =E57 -> 44012 | F65: =F57 -> 44043 | G65: =G57 -> 44074 | H65: =H57 -> 44104 | I65: =I57 -> 44135
B67: Total Debt / EBITDA | C67: =C138/C58 -> 3.5927334 | D67: =D138/D58 -> 3.513831 | E67: =E138/E58 -> 3.5459873 | F67: =F138/F58 -> 3.6837486 | G67: =G138/G58 -> 3.6632042 | H67: =H138/H58 -> 3.6232476 | I67: =I138/I58 -> 3.6317636
B69: Taxes | C69: =C$65 -> 43951 | D69: =D$65 -> 43982 | E69: =E$65 -> 44012 | F69: =F$65 -> 44043 | G69: =G$65 -> 44074 | H69: =H$65 -> 44104 | I69: =I$65 -> 44135
B70: FCF Before Debt Service & Taxes | D70: =D60 -> 10393.67 | E70: =E60 -> 8667.573 | F70: =F60 -> 6355.84 | G70: =G60 -> 8884.205 | H70: =H60 -> 11026.2 | I70: =I60 -> 5745.409
B71: Less: Interest Expense (Accrued) | D71: =-D152 -> -3811.228 | E71: =-E152 -> -3794.9483 | F71: =-F152 -> -3782.3202 | G71: =-G152 -> -3264.4176 | H71: =-H152 -> -3250.4106 | I71: =-I152 -> -3221.9008
B72: Taxable Income | D72: =SUM(D70:D71) -> 6582.442 | E72: =SUM(E70:E71) -> 4872.6247 | F72: =SUM(F70:F71) -> 2573.5198 | G72: =SUM(G70:G71) -> 5619.7874 | H72: =SUM(H70:H71) -> 7775.7894 | I72: =SUM(I70:I71) -> 2523.5082
B74: Cash Taxes | D74: =D72*$L$9 -> 1645.6105 | E74: =E72*$L$9 -> 1218.1562 | F74: =F72*$L$9 -> 643.37994 | G74: =G72*$L$9 -> 1404.9468 | H74: =H72*$L$9 -> 1943.9474 | I74: =I72*$L$9 -> 630.87706
B76: Revolver | C76: =C$65 -> 43951 | D76: =D$65 -> 43982 | E76: =E$65 -> 44012 | F76: =F$65 -> 44043 | G76: =G$65 -> 44074 | H76: =H$65 -> 44104 | I76: =I$65 -> 44135
B77: Beginning Balance | D77: =C79 -> 12473 | E77: =D79 -> 7379.9185 | F77: =E79 -> 3569.2 | G77: =F79 -> 10389.06 | H77: =G79 -> 6564.2197 | I77: =H79 -> 1122.3776
B78: Additions / Repayments | D78: =-MIN(D77,D94) -> -5093.0815 | E78: =-MIN(E77,E94) -> -3810.7185 | F78: =-MIN(F77,F94) -> 6819.8602 | G78: =-MIN(G77,G94) -> -3824.8405 | H78: =-MIN(H77,H94) -> -5441.8421 | I78: =-MIN(I77,I94) -> -1122.3776
B79: Ending Balance | C79: =R32 -> 12473 | D79: =SUM(D77:D78) -> 7379.9185 | E79: =SUM(E77:E78) -> 3569.2 | F79: =SUM(F77:F78) -> 10389.06 | G79: =SUM(G77:G78) -> 6564.2197 | H79: =SUM(H77:H78) -> 1122.3776 | I79: =SUM(I77:I78) -> 0
B81: LIBOR | D81: =D61 -> 0.0225 | E81: =E61 -> 0.0235 | F81: =F61 -> 0.0245 | G81: =G61 -> 0.0255 | H81: =H61 -> 0.0265 | I81: =I61 -> 0.027
B82: Spread | D82: =VLOOKUP(C67,$F$11:$H$14,COLUMNS($F$11:$H$14),TRUE)/10000 -> 0.03 | E82: =VLOOKUP(D67,$F$11:$H$14,COLUMNS($F$11:$H$14),TRUE)/10000 -> 0.03 | F82: =VLOOKUP(E67,$F$11:$H$14,COLUMNS($F$11:$H$14),TRUE)/10000 -> 0.03 | G82: =VLOOKUP(F67,$F$11:$H$14,COLUMNS($F$11:$H$14),TRUE)/10000 -> 0.03 | H82: =VLOOKUP(G67,$F$11:$H$14,COLUMNS($F$11:$H$14),TRUE)/10000 -> 0.03 | I82: =VLOOKUP(H67,$F$11:$H$14,COLUMNS($F$11:$H$14),TRUE)/10000 -> 0.03
B83: Effective Interest Rate (Annual) | D83: =D81+D82 -> 0.0525 | E83: =E81+E82 -> 0.0535 | F83: =F81+F82 -> 0.0545 | G83: =G81+G82 -> 0.0555 | H83: =H81+H82 -> 0.0565 | I83: =I81+I82 -> 0.057
B85: Drawn Interest Expense | D85: =C79*D83/12 -> 54.569375 | E85: =D79*E83/12 -> 32.902137 | F85: =E79*F83/12 -> 16.210117 | G85: =F79*G83/12 -> 48.049403 | H85: =G79*H83/12 -> 30.906534 | I85: =H79*I83/12 -> 5.3312936
B86: Standby Fee | D86: =($D$7-C79)*$D$10/120000 -> 25.018 | E86: =($D$7-D79)*$D$10/120000 -> 28.413388 | F86: =($D$7-E79)*$D$10/120000 -> 30.953867 | G86: =($D$7-F79)*$D$10/120000 -> 26.407293 | H86: =($D$7-G79)*$D$10/120000 -> 28.957187 | I86: =($D$7-H79)*$D$10/120000 -> 32.585082
B87: Total Revolver Interest | D87: =SUM(D85:D86) -> 79.587375 | E87: =SUM(E85:E86) -> 61.315524 | F87: =SUM(F85:F86) -> 47.163983 | G87: =SUM(G85:G86) -> 74.456697 | H87: =SUM(H85:H86) -> 59.863721 | I87: =SUM(I85:I86) -> 37.916375
B89: FCF Available for (Needed From) Revolver:
B90: FCF Before Debt Service & Taxes | D90: =D70 -> 10393.67 | E90: =E70 -> 8667.573 | F90: =F70 -> 6355.84 | G90: =G70 -> 8884.205 | H90: =H70 -> 11026.2 | I90: =I70 -> 5745.409
B91: Principal Additions / (Repayments) | D91: =D145 -> -2812.5 | E91: =E145 -> -2812.5 | F91: =F145 -> -2812.5 | G91: =G145 -> -2812.5 | H91: =H145 -> -2812.5 | I91: =I145 -> -2812.5
B92: Less: Cash Interest | D92: =-D159 -> -842.478 | E92: =-E159 -> -826.19834 | F92: =-F159 -> -9719.8202 | G92: =-G159 -> -841.91763 | H92: =-H159 -> -827.9106 | I92: =-I159 -> -799.40075
B93: Less: Taxes | D93: =-D74 -> -1645.6105 | E93: =-E74 -> -1218.1562 | F93: =-F74 -> -643.37994 | G93: =-G74 -> -1404.9468 | H93: =-H74 -> -1943.9474 | I93: =-I74 -> -630.87706
B94: FCF Available for (Needed From) Revolver | D94: =SUM(D90:D93) -> 5093.0815 | E94: =SUM(E90:E93) -> 3810.7185 | F94: =SUM(F90:F93) -> -6819.8602 | G94: =SUM(G90:G93) -> 3824.8405 | H94: =SUM(H90:H93) -> 5441.8421 | I94: =SUM(I90:I93) -> 1502.6312
B96: Senior Term Loan | C96: =C$65 -> 43951 | D96: =D$65 -> 43982 | E96: =E$65 -> 44012 | F96: =F$65 -> 44043 | G96: =G$65 -> 44074 | H96: =H$65 -> 44104 | I96: =I$65 -> 44135
B97: Beginning Balance | D97: =C99 -> 174375 | E97: =D99 -> 171562.5 | F97: =E99 -> 168750 | G97: =F99 -> 165937.5 | H97: =G99 -> 163125 | I97: =H99 -> 160312.5
B98: Additions / Repayments | D98: =-$D$18*$D$20 -> -2812.5 | E98: =-$D$18*$D$20 -> -2812.5 | F98: =-$D$18*$D$20 -> -2812.5 | G98: =-$D$18*$D$20 -> -2812.5 | H98: =-$D$18*$D$20 -> -2812.5 | I98: =-$D$18*$D$20 -> -2812.5
B99: Ending Balance | C99: =R38 -> 174375 | D99: =SUM(D97:D98) -> 171562.5 | E99: =SUM(E97:E98) -> 168750 | F99: =SUM(F97:F98) -> 165937.5 | G99: =SUM(G97:G98) -> 163125 | H99: =SUM(H97:H98) -> 160312.5 | I99: =SUM(I97:I98) -> 157500
B101: LIBOR | D101: =D81 -> 0.0225 | E101: =E81 -> 0.0235 | F101: =F81 -> 0.0245 | G101: =G81 -> 0.0255 | H101: =H81 -> 0.0265 | I101: =I81 -> 0.027
B102: Spread | D102: =D82 -> 0.03 | E102: =E82 -> 0.03 | F102: =F82 -> 0.03 | G102: =G82 -> 0.03 | H102: =H82 -> 0.03 | I102: =I82 -> 0.03
B103: Effective Interest Rate (Annual) | D103: =D101+D102 -> 0.0525 | E103: =E101+E102 -> 0.0535 | F103: =F101+F102 -> 0.0545 | G103: =G101+G102 -> 0.0555 | H103: =H101+H102 -> 0.0565 | I103: =I101+I102 -> 0.057
B105: Interest Expense | D105: =C99*D103/12 -> 762.89062 | E105: =D99*E103/12 -> 764.88281 | F105: =E99*F103/12 -> 766.40625 | G105: =F99*G103/12 -> 767.46094 | H105: =G99*H103/12 -> 768.04688 | I105: =H99*I103/12 -> 761.48438
B107: Existing Subordinated Notes | C107: =C$65 -> 43951 | D107: =D$65 -> 43982 | E107: =E$65 -> 44012 | F107: =F$65 -> 44043 | G107: =G$65 -> 44074 | H107: =H$65 -> 44104 | I107: =I$65 -> 44135
B108: Beginning Balance | D108: =C110 -> 500000 | E108: =D110 -> 500000 | F108: =E110 -> 500000 | G108: =F110 -> 0 | H108: =G110 -> 0 | I108: =H110 -> 0
B109: Additions / Repayments | D109: =IF(D107=$L$17,-D108,0) -> 0 | E109: =IF(E107=$L$17,-E108,0) -> 0 | F109: =IF(F107=$L$17,-F108,0) -> -500000 | G109: =IF(G107=$L$17,-G108,0) -> 0 | H109: =IF(H107=$L$17,-H108,0) -> 0 | I109: =IF(I107=$L$17,-I108,0) -> 0
B110: Ending Balance | C110: =R42 -> 500000 | D110: =SUM(D108:D109) -> 500000 | E110: =SUM(E108:E109) -> 500000 | F110: =SUM(F108:F109) -> 0 | G110: =SUM(G108:G109) -> 0 | H110: =SUM(H108:H109) -> 0 | I110: =SUM(I108:I109) -> 0
B112: Call Price | D112: =IF(D107=$L$17,VLOOKUP(D107,$F$24:$H$26,COLUMNS($F$24:$H$26),TRUE),0) -> 0 | E112: =IF(E107=$L$17,VLOOKUP(E107,$F$24:$H$26,COLUMNS($F$24:$H$26),TRUE),0) -> 0 | F112: =IF(F107=$L$17,VLOOKUP(F107,$F$24:$H$26,COLUMNS($F$24:$H$26),TRUE),0) -> 1.02 | G112: =IF(G107=$L$17,VLOOKUP(G107,$F$24:$H$26,COLUMNS($F$24:$H$26),TRUE),0) -> 0 | H112: =IF(H107=$L$17,VLOOKUP(H107,$F$24:$H$26,COLUMNS($F$24:$H$26),TRUE),0) -> 0 | I112: =IF(I107=$L$17,VLOOKUP(I107,$F$24:$H$26,COLUMNS($F$24:$H$26),TRUE),0) -> 0
B113: Cash Needed to Refinance | D113: =-D109*D112 -> 0 | E113: =-E109*E112 -> 0 | F113: =-F109*F112 -> 510000 | G113: =-G109*G112 -> 0 | H113: =-H109*H112 -> 0 | I113: =-I109*I112 -> 0
B115: Effective Interest Rate (Annual) | D115: =$H$19 -> 0.07125 | E115: =$H$19 -> 0.07125 | F115: =$H$19 -> 0.07125 | G115: =$H$19 -> 0.07125 | H115: =$H$19 -> 0.07125 | I115: =$H$19 -> 0.07125
B117: Interest Expense | D117: =C110*D115/12 -> 2968.75 | E117: =D110*E115/12 -> 2968.75 | F117: =E110*F115/12 -> 2968.75 | G117: =F110*G115/12 -> 0 | H117: =G110*H115/12 -> 0 | I117: =H110*I115/12 -> 0
B119: Cash Interest Payment? | D119: =IF(D112>0,1,0) -> 0 | E119: =IF(E112>0,1,0) -> 0 | F119: =IF(F112>0,1,0) -> 1 | G119: =IF(G112>0,1,0) -> 0 | H119: =IF(H112>0,1,0) -> 0 | I119: =IF(I112>0,1,0) -> 0
B120: Cash Interest | D120: =$D$117*COUNT($D$119:D119)*D119 -> 0 | E120: =$D$117*COUNT($D$119:E119)*E119 -> 0 | F120: =$D$117*COUNT($D$119:F119)*F119 -> 8906.25 | G120: =$D$117*COUNT($D$119:G119)*G119 -> 0 | H120: =$D$117*COUNT($D$119:H119)*H119 -> 0 | I120: =$D$117*COUNT($D$119:I119)*I119 -> 0
B122: New Senior Notes | C122: =C$65 -> 43951 | D122: =D$65 -> 43982 | E122: =E$65 -> 44012 | F122: =F$65 -> 44043 | G122: =G$65 -> 44074 | H122: =H$65 -> 44104 | I122: =I$65 -> 44135
B123: Outstanding? | D123: =IF(D127>0,1,0) -> 0 | E123: =IF(E127>0,1,0) -> 0 | F123: =IF(F127>0,1,0) -> 1 | G123: =IF(G127>0,1,0) -> 1 | H123: =IF(H127>0,1,0) -> 1 | I123: =IF(I127>0,1,0) -> 1
B125: Beginning Balance | D125: =C127 -> 0 | E125: =D127 -> 0 | F125: =E127 -> 0 | G125: =F127 -> 510000 | H125: =G127 -> 510000 | I125: =H127 -> 510000
B126: Additions / Repayments | D126: =D113 -> 0 | E126: =E113 -> 0 | F126: =F113 -> 510000 | G126: =G113 -> 0 | H126: =H113 -> 0 | I126: =I113 -> 0
B127: Ending Balance | C127: 0 | D127: =SUM(D125:D126) -> 0 | E127: =SUM(E125:E126) -> 0 | F127: =SUM(F125:F126) -> 510000 | G127: =SUM(G125:G126) -> 510000 | H127: =SUM(H125:H126) -> 510000 | I127: =SUM(I125:I126) -> 510000
B129: Effective Interest Rate (Annual) | D129: =IF(D112=0,C129,VLOOKUP(D65,$J$19:$L$24,COLUMNS($J$19:$L$24),TRUE)) -> 0 | E129: =IF(E112=0,D129,VLOOKUP(E65,$J$19:$L$24,COLUMNS($J$19:$L$24),TRUE)) -> 0 | F129: =IF(F112=0,E129,VLOOKUP(F65,$J$19:$L$24,COLUMNS($J$19:$L$24),TRUE)) -> 0.057 | G129: =IF(G112=0,F129,VLOOKUP(G65,$J$19:$L$24,COLUMNS($J$19:$L$24),TRUE)) -> 0.057 | H129: =IF(H112=0,G129,VLOOKUP(H65,$J$19:$L$24,COLUMNS($J$19:$L$24),TRUE)) -> 0.057 | I129: =IF(I112=0,H129,VLOOKUP(I65,$J$19:$L$24,COLUMNS($J$19:$L$24),TRUE)) -> 0.057
B131: Interest Expense | D131: =C127*D129/12 -> 0 | E131: =D127*E129/12 -> 0 | F131: =E127*F129/12 -> 0 | G131: =F127*G129/12 -> 2422.5 | H131: =G127*H129/12 -> 2422.5 | I131: =H127*I129/12 -> 2422.5
B133: Total Debt - End of Period | C133: =C$65 -> 43951 | D133: =D$65 -> 43982 | E133: =E$65 -> 44012 | F133: =F$65 -> 44043 | G133: =G$65 -> 44074 | H133: =H$65 -> 44104 | I133: =I$65 -> 44135
B134: Revolver | C134: =C79 -> 12473 | D134: =D79 -> 7379.9185 | E134: =E79 -> 3569.2 | F134: =F79 -> 10389.06 | G134: =G79 -> 6564.2197 | H134: =H79 -> 1122.3776 | I134: =I79 -> 0
...
