Workbook
Name company: CaseData!$D$133
Name ebidta_profiles: _xlfn.ANCHORARRAY(CaseData!$D$137)
Name ebidta_selector: Debt!$H$3
Name periods: CaseData!$G$32
Name start_date: CaseData!$G$30
Name topic: "CFM Topic: " & CaseData!$D$134

Sheet Debt
A1: {=company} -> Black Rat SPV 2
A2: {=topic} -> CFM Topic: Debt | H2: EBIDTA Profile | J2: {=_xlfn.ANCHORARRAY($J$137)} -> 43466 | K2: 43556 | L2: 43647 | M2: 43739 | N2: 43831 | O2: 43922 | P2: 44013 | Q2: 44105 | R2: 44197 | S2: 44287 | T2: 44378 | U2: 44470 | V2: 44562 | W2: 44652 | X2: 44743 | Y2: 44835 | Z2: 44927 | AA2: 45017 | AB2: 45108 | AC2: 45200 | AD2: 45292 | AE2: 45383 | AF2: 45474 | AG2: 45566 | AH2: 45658 | AI2: 45748 | AJ2: 45839 | AK2: 45931 | AL2: 46023 | AM2: 46113 | AN2: 46204 | AO2: 46296 | AP2: 46388 | AQ2: 46478 | AR2: 46569 | AS2: 46661 | AT2: 46753 | AU2: 46844 | AV2: 46935 | AW2: 47027
A3: DEBT SCHEDULE | F3: Constant | G3: Unit | H3: 6 | J3: {=_xlfn.ANCHORARRAY( $J$138)} -> 43555 | K3: 43646 | L3: 43738 | M3: 43830 | N3: 43921 | O3: 44012 | P3: 44104 | Q3: 44196 | R3: 44286 | S3: 44377 | T3: 44469 | U3: 44561 | V3: 44651 | W3: 44742 | X3: 44834 | Y3: 44926 | Z3: 45016 | AA3: 45107 | AB3: 45199 | AC3: 45291 | AD3: 45382 | AE3: 45473 | AF3: 45565 | AG3: 45657 | AH3: 45747 | AI3: 45838 | AJ3: 45930 | AK3: 46022 | AL3: 46112 | AM3: 46203 | AN3: 46295 | AO3: 46387 | AP3: 46477 | AQ3: 46568 | AR3: 46660 | AS3: 46752 | AT3: 46843 | AU3: 46934 | AV3: 47026 | AW3: 47118
A5: Cash flow
E8: EBIDTA | G8: USD | J8: {=INDEX( CaseData!$F$89:$K$128, MATCH(_xlfn.ANCHORARRAY( Debt!J3), CaseData!$D$89:$D$128, 0 ), MATCH( ebidta_selector, CaseData!$F$86:$K$86, 0 ) )} -> 602417 | K8: 595476 | L8: 593198 | M8: 606599 | N8: 631767 | O8: 610527 | P8: 585598 | Q8: 637572 | R8: 646990 | S8: 675583 | T8: 584611 | U8: 218154 | V8: 227447 | W8: 265153 | X8: 259078 | Y8: 604305 | Z8: 574768 | AA8: 641271 | AB8: 640757 | AC8: 633725 | AD8: 576167 | AE8: 581131 | AF8: 709982 | AG8: 602019 | AH8: 675479 | AI8: 669801 | AJ8: 709031 | AK8: 693006 | AL8: 717913 | AM8: 628697 | AN8: 657781 | AO8: 700979 | AP8: 638273 | AQ8: 652849 | AR8: 724981 | AS8: 637701 | AT8: 745903 | AU8: 750208 | AV8: 740965 | AW8: 750009
E9: =E$65 -> Debt Service Reserve Account interest income | G9: =G$65 -> USD | I9: =I$65 -> 0 | J9: =J$65 -> 1875 | K9: =K$65 -> 2721.7971 | L9: =L$65 -> 3561.0701 | M9: =M$65 -> 4408.1208 | N9: =N$65 -> 5313.1204 | O9: =O$65 -> 6313.8208 | P9: =P$65 -> 1875 | ... AW9: =AW$65 -> 1875
E10: Funds available for Debt repayment | G10: USD | J10: =SUM(J8:J9) -> 604292 | K10: =SUM(K8:K9) -> 598197.8 | L10: =SUM(L8:L9) -> 596759.07 | M10: =SUM(M8:M9) -> 611007.12 | N10: =SUM(N8:N9) -> 637080.12 | O10: =SUM(O8:O9) -> 616840.82 | P10: =SUM(P8:P9) -> 587473 | Q10: =SUM(Q8:Q9) -> 639447 | ... AW10: =SUM(AW8:AW9) -> 751884
E12: =E$80 -> Senior Debt interest expenses | G12: =G$80 -> USD | I12: =I$80 -> 0 | J12: =J$80 * - 1 -> -125000 | K12: =K$80 * - 1 -> -121831.51 | L12: =L$80 * - 1 -> -118674.5 | M12: =M$80 * - 1 -> -115521.95 | N12: =N$80 * - 1 -> -112345.05 | O12: =O$80 * - 1 -> -109121.53 | P12: =P$80 * - 1 -> -105957.66 | Q12: =Q$80 * - 1 -> -102758.28 | ... AW12: =AW$80 * - 1 -> 0
E13: =E$73 -> Senior Debt principal addition / (repayment) | G13: =G$73 -> USD | I13: =I$73 -> 0 | J13: =J$73 -> -253479.44 | K13: =K$73 -> -252560.16 | L13: =L$73 -> -252204.38 | M13: =M$73 -> -254151.94 | N13: =N$73 -> -257881.62 | O13: =O$73 -> -253109.58 | P13: =P$73 -> -255950.67 | ... AW13: =AW$73 -> 0
E14: Funds available after Senior Debt service | G14: USD | J14: =SUM(J10:J13) -> 225812.56 | K14: =SUM(K10:K13) -> 223806.13 | L14: =SUM(L10:L13) -> 225880.18 | M14: =SUM(M10:M13) -> 241333.23 | N14: =SUM(N10:N13) -> 266853.45 | O14: =SUM(O10:O13) -> 254609.71 | P14: =SUM(P10:P13) -> 225564.67 | Q14: =SUM(Q10:Q13) -> 280039.78 | ... AW14: =SUM(AW10:AW13) -> 751884
E16: Withdrawal from DSRA to cover for Senior Debt repayment shortfall | G16: USD | J16: =- MIN( J14, 0 ) -> 0 | K16: =- MIN( K14, 0 ) -> 0 | L16: =- MIN( L14, 0 ) -> 0 | M16: =- MIN( M14, 0 ) -> 0 | N16: =- MIN( N14, 0 ) -> 0 | O16: =- MIN( O14, 0 ) -> 0 | P16: =- MIN( P14, 0 ) -> 0 | Q16: =- MIN( Q14, 0 ) -> 0 | ... AW16: =- MIN( AW14, 0 ) -> 0
E17: Top Up of DSRA to keep required minimum balance | G17: USD | J17: =- MAX( MIN( J14, $F$51 - SUM( J54:J55 ) ), 0 ) -> 0 | K17: =- MAX( MIN( K14, $F$51 - SUM( K54:K55 ) ), 0 ) -> 0 | L17: =- MAX( MIN( L14, $F$51 - SUM( L54:L55 ) ), 0 ) -> 0 | M17: =- MAX( MIN( M14, $F$51 - SUM( M54:M55 ) ), 0 ) -> 0 | N17: =- MAX( MIN( N14, $F$51 - SUM( N54:N55 ) ), 0 ) -> 0 | O17: =- MAX( MIN( O14, $F$51 - SUM( O54:O55 ) ), 0 ) -> 0 | P17: =- MAX( MIN( P14, $F$51 - SUM( P54:P55 ) ), 0 ) -> 0 | Q17: =- MAX( MIN( Q14, $F$51 - SUM( Q54:Q55 ) ), 0 ) -> 0 | ... AW17: =- MAX( MIN( AW14, $F$51 - SUM( AW54:AW55 ) ), 0 ) -> 0
E18: DSRA Additions in Lockup | G18: USD | J18: =IF( J$45 = 1, -SUM( J14:J17 ), 0 ) -> -225812.56 | K18: =IF( K$45 = 1, -SUM( K14:K17 ), 0 ) -> -223806.13 | L18: =IF( L$45 = 1, -SUM( L14:L17 ), 0 ) -> -225880.18 | M18: =IF( M$45 = 1, -SUM( M14:M17 ), 0 ) -> -241333.23 | N18: =IF( N$45 = 1, -SUM( N14:N17 ), 0 ) -> -266853.45 | O18: =IF( O$45 = 1, -SUM( O14:O17 ), 0 ) -> 0 | P18: =IF( P$45 = 1, -SUM( P14:P17 ), 0 ) -> 0 | Q18: =IF( Q$45 = 1, -SUM( Q14:Q17 ), 0 ) -> 0 | ... AW18: =IF( AW$45 = 1, -SUM( AW14:AW17 ), 0 ) -> 0
E19: =E$58 -> Release from DSRA | G19: =G$58 -> USD | J19: =J$58 * - 1 -> 0 | K19: =K$58 * - 1 -> 0 | L19: =L$58 * - 1 -> 0 | M19: =M$58 * - 1 -> 0 | N19: =N$58 * - 1 -> 0 | O19: =O$58 * - 1 -> 1183685.6 | P19: =P$58 * - 1 -> 0 | Q19: =Q$58 * - 1 -> 0 | ... AW19: =AW$58 * - 1 -> 0
E20: Funds available for Junior Debt service | G20: USD | J20: =SUM(J14:J19) -> 0 | K20: =SUM(K14:K19) -> 0 | L20: =SUM(L14:L19) -> 0 | M20: =SUM(M14:M19) -> 0 | N20: =SUM(N14:N19) -> 0 | O20: =SUM(O14:O19) -> 1438295.3 | P20: =SUM(P14:P19) -> 225564.67 | Q20: =SUM(Q14:Q19) -> 280039.78 | ... AW20: =SUM(AW14:AW19) -> 751884
E22: =E$101 -> Junior Debt interest paid | G22: USD | J22: =J$101 * - 1 -> 0 | K22: =K$101 * - 1 -> 0 | L22: =L$101 * - 1 -> 0 | M22: =M$101 * - 1 -> 0 | N22: =N$101 * - 1 -> 0 | O22: =O$101 * - 1 -> -114514.74 | P22: =P$101 * - 1 -> -91348.58 | Q22: =Q$101 * - 1 -> -88999.799 | ... AW22: =AW$101 * - 1 -> -2625
E23: Funds Available for Junior Debt Scheduled Repayments | G23: USD | J23: =SUM(J20:J22) -> 0 | K23: =SUM(K20:K22) -> 0 | L23: =SUM(L20:L22) -> 0 | M23: =SUM(M20:M22) -> 0 | N23: =SUM(N20:N22) -> 0 | O23: =SUM(O20:O22) -> 1323780.5 | P23: =SUM(P20:P22) -> 134216.09 | Q23: =SUM(Q20:Q22) -> 191039.98 | ... AW23: =SUM(AW20:AW22) -> 749259
E25: =E$106 -> Junior Debt Scheduled Repayment Paid | G25: =G$106 -> USD | I25: =I$106 -> 0 | J25: =J$106 * - 1 -> 0 | K25: =K$106 * - 1 -> 0 | L25: =L$106 * - 1 -> 0 | M25: =M$106 * - 1 -> 0 | N25: =N$106 * - 1 -> 0 | O25: =O$106 * - 1 -> -150000 | P25: =P$106 * - 1 -> -134216.09 | Q25: =Q$106 * - 1 -> -150000 | ... AW25: =AW$106 * - 1 -> -150000
E26: Funds Available for Junior Debt Arrears Amount Owed | G26: =G$106 -> USD | J26: =SUM(J23:J25) -> 0 | K26: =SUM(K23:K25) -> 0 | L26: =SUM(L23:L25) -> 0 | M26: =SUM(M23:M25) -> 0 | N26: =SUM(N23:N25) -> 0 | O26: =SUM(O23:O25) -> 1173780.5 | P26: =SUM(P23:P25) -> 0 | Q26: =SUM(Q23:Q25) -> 41039.979 | ... AW26: =SUM(AW23:AW25) -> 599259
E28: =E$116 -> Repayment of arrears owed | G28: =G$116 -> USD | I28: =I$116 -> 0 | J28: =J$116 -> 0 | K28: =K$116 -> 0 | L28: =L$116 -> 0 | M28: =M$116 -> 0 | N28: =N$116 -> 0 | O28: =O$116 -> -1173780.5 | P28: =P$116 -> 0 | ... AW28: =AW$116 -> 0
E29: Funds distributed to Equity | G29: USD | J29: =SUM(J26:J28) -> 0 | K29: =SUM(K26:K28) -> 0 | L29: =SUM(L26:L28) -> 0 | M29: =SUM(M26:M28) -> 0 | N29: =SUM(N26:N28) -> 0 | O29: =SUM(O26:O28) -> 0 | P29: =SUM(P26:P28) -> 0 | Q29: =SUM(Q26:Q28) -> 0 | ... AW29: =SUM(AW26:AW28) -> 599259
A34: DSCR (Last Twelve Months)
E36: Senior DSCR Lock up trigger | F36: =CaseData!$G$7 -> 1.62 | G36: factor
E38: EBIDTA | G38: USD | J38: =J8 -> 602417 | K38: =SUM(J8:K8) -> 1197893 | L38: =SUM( J8:L8) -> 1791091 | M38: =SUM( J8:M8) -> 2397690 | N38: =SUM( K8:N8) -> 2427040 | O38: =SUM( L8:O8) -> 2442091 | P38: =SUM( M8:P8) -> 2434491 | Q38: =SUM( N8:Q8) -> 2465464 | R38: =SUM( O8:R8) -> 2480687 | S38: =SUM( P8:S8) -> 2545743 | T38: =SUM( Q8:T8) -> 2544756 | ... AW38: =SUM( AT8:AW8) -> 2987085
E39: =E$65 -> Debt Service Reserve Account interest income | G39: =G$65 -> USD | I39: =I$65 -> 0 | J39: =J65 -> 1875 | K39: =SUM( J65:K65) -> 4596.7971 | L39: =SUM( J65:L65) -> 8157.8672 | M39: =SUM( J65:M65) -> 12565.988 | N39: =SUM( K65:N65) -> 16004.108 | O39: =SUM( L65:O65) -> 19596.132 | P39: =SUM( M65:P65) -> 17910.062 | Q39: =SUM( N65:Q65) -> 15376.941 | R39: =SUM( O65:R65) -> 11938.821 | S39: =SUM( P65:S65) -> 7500 | T39: =SUM( Q65:T65) -> 7500 | ... AW39: =SUM( AT65:AW65) -> 7500
E40: =E$80 -> Senior Debt interest expenses | G40: =G$80 -> USD | I40: =I$80 -> 0 | J40: =J80 * - 1 -> -125000 | K40: =SUM( J80:K80 ) * - 1 -> -246831.51 | L40: =SUM( J80:L80 ) * - 1 -> -365506.01 | M40: =SUM( J80:M80 ) * - 1 -> -481027.96 | N40: =SUM( K80:N80 ) * - 1 -> -468373.01 | O40: =SUM( L80:O80 ) * - 1 -> -455663.04 | P40: =SUM( M80:P80 ) * - 1 -> -442946.19 | Q40: =SUM( N80:Q80 ) * - 1 -> -430182.52 | R40: =SUM( O80:R80 ) * - 1 -> -417387.63 | S40: =SUM( P80:S80 ) * - 1 -> -404346.95 | T40: =SUM( Q80:T80 ) * - 1 -> -391197.77 | ... AW40: =SUM( AT80:AW80 ) * - 1 -> 0
E41: =E$73 -> Senior Debt principal addition / (repayment) | G41: =G$73 -> USD | I41: =I$73 -> 0 | J41: =J$73 -> -253479.44 | K41: =SUM( J73:K73) -> -506039.6 | L41: =SUM( J73:L73) -> -758243.99 | M41: =SUM( J73:M73) -> -1012395.9 | N41: =SUM( K73:N73) -> -1016798.1 | O41: =SUM( L73:O73) -> -1017347.5 | P41: =SUM( M73:P73) -> -1021093.8 | Q41: =SUM( N73:Q73) -> -1023590.8 | R41: =SUM( O73:R73) -> -1043255.1 | S41: =SUM( P73:S73) -> -1051934.2 | T41: =SUM( Q73:T73) -> -1066850.6 | ... AW41: =SUM( AT73:AW73) -> 0
E43: DSCR LTM | G43: factor | J43: =IFERROR(SUM(J38,J39)/-SUM(J40,J41),"n/a") -> 1.596631 | K43: =IFERROR(SUM(K38,K39)/-SUM(K40,K41),"n/a") -> 1.5972054 | L43: =IFERROR(SUM(L38,L39)/-SUM(L40,L41),"n/a") -> 1.6011113 | M43: =IFERROR(SUM(M38,M39)/-SUM(M40,M41),"n/a") -> 1.6139128 | N43: =IFERROR(SUM(N38,N39)/-SUM(N40,N41),"n/a") -> 1.644958 | O43: =IFERROR(SUM(O38,O39)/-SUM(O40,O41),"n/a") -> 1.6711945 | P43: =IFERROR(SUM(P38,P39)/-SUM(P40,P41),"n/a") -> 1.6750916 | Q43: =IFERROR(SUM(Q38,Q39)/-SUM(Q40,Q41),"n/a") -> 1.706484 | ... AW43: =IFERROR(SUM(AW38,AW39)/-SUM(AW40,AW41),"n/a") -> n/a
E44: Lock up trigger flag | G44: flag | J44: =IF( J$43 < $F$36, 1, 0 ) -> 1 | K44: =IF( K$43 < $F$36, 1, 0 ) -> 1 | L44: =IF( L$43 < $F$36, 1, 0 ) -> 1 | M44: =IF( M$43 < $F$36, 1, 0 ) -> 1 | N44: =IF( N$43 < $F$36, 1, 0 ) -> 0 | O44: =IF( O$43 < $F$36, 1, 0 ) -> 0 | P44: =IF( P$43 < $F$36, 1, 0 ) -> 0 | Q44: =IF( Q$43 < $F$36, 1, 0 ) -> 0 | ... AW44: =IF( AW$43 < $F$36, 1, 0 ) -> 0
E45: Release trigger | G45: flag | J45: =MAX(I44:J44) -> 1 | K45: =MAX(J44:K44) -> 1 | L45: =MAX(K44:L44) -> 1 | M45: =MAX(L44:M44) -> 1 | N45: =MAX(M44:N44) -> 1 | O45: =MAX(N44:O44) -> 0 | P45: =MAX(O44:P44) -> 0 | Q45: =MAX(P44:Q44) -> 0 | ... AW45: =MAX(AV44:AW44) -> 0
A48: Debt Service Reserve Account
E50: Debt Service Reserve Account Debt balance at model start | F50: =CaseData!G$14 -> 500000 | G50: USD
E51: Required minimum balance during term of Senior Facility | F51: =CaseData!$G$15 -> 500000 | G51: USD
E54: Debt Service Reserve Account Debt opening balance | G54: USD | J54: =I$59 -> 500000 | K54: =J$59 -> 725812.56 | L54: =K$59 -> 949618.69 | M54: =L$59 -> 1175498.9 | N54: =M$59 -> 1416832.1 | O54: =N$59 -> 1683685.6 | P54: =O$59 -> 500000 | Q54: =P$59 -> 500000 | ... AW54: =AV$59 -> 500000
E55: =E$16 -> Withdrawal from DSRA to cover for Senior Debt repayment shortfall | G55: =G$16 -> USD | I55: =I$16 -> 0 | J55: =J$16 * - 1 -> 0 | K55: =K$16 * - 1 -> 0 | L55: =L$16 * - 1 -> 0 | M55: =M$16 * - 1 -> 0 | N55: =N$16 * - 1 -> 0 | O55: =O$16 * - 1 -> 0 | P55: =P$16 * - 1 -> 0 | Q55: =Q$16 * - 1 -> 0 | ... AW55: =AW$16 * - 1 -> 0
E56: Top Up of DSRA to keep required minimum balance | G56: USD | J56: =-J17 -> 0 | K56: =-K17 -> 0 | L56: =-L17 -> 0 | M56: =-M17 -> 0 | N56: =-N17 -> 0 | O56: =-O17 -> 0 | P56: =-P17 -> 0 | Q56: =-Q17 -> 0 | ... AW56: =-AW17 -> 0
E57: =E$18 -> DSRA Additions in Lockup | G57: =G$18 -> USD | I57: =I$18 -> 0 | J57: =J$18 * - 1 -> 225812.56 | K57: =K$18 * - 1 -> 223806.13 | L57: =L$18 * - 1 -> 225880.18 | M57: =M$18 * - 1 -> 241333.23 | N57: =N$18 * - 1 -> 266853.45 | O57: =O$18 * - 1 -> 0 | P57: =P$18 * - 1 -> 0 | Q57: =Q$18 * - 1 -> 0 | ... AW57: =AW$18 * - 1 -> 0
E58: Release from DSRA | G58: USD | J58: =IF( J$45 = 0, $F$51 - SUM( J54:J57 ), 0 ) -> 0 | K58: =IF( K$45 = 0, $F$51 - SUM( K54:K57 ), 0 ) -> 0 | L58: =IF( L$45 = 0, $F$51 - SUM( L54:L57 ), 0 ) -> 0 | M58: =IF( M$45 = 0, $F$51 - SUM( M54:M57 ), 0 ) -> 0 | N58: =IF( N$45 = 0, $F$51 - SUM( N54:N57 ), 0 ) -> 0 | O58: =IF( O$45 = 0, $F$51 - SUM( O54:O57 ), 0 ) -> -1183685.6 | P58: =IF( P$45 = 0, $F$51 - SUM( P54:P57 ), 0 ) -> 0 | Q58: =IF( Q$45 = 0, $F$51 - SUM( Q54:Q57 ), 0 ) -> 0 | ... AW58: =IF( AW$45 = 0, $F$51 - SUM( AW54:AW57 ), 0 ) -> 0
E59: Debt Service Reserve Account Debt | G59: USD | I59: =$F$50 -> 500000 | J59: =SUM(J54:J58) -> 725812.56 | K59: =SUM(K54:K58) -> 949618.69 | L59: =SUM(L54:L58) -> 1175498.9 | M59: =SUM(M54:M58) -> 1416832.1 | N59: =SUM(N54:N58) -> 1683685.6 | O59: =SUM(O54:O58) -> 500000 | P59: =SUM(P54:P58) -> 500000 | Q59: =SUM(Q54:Q58) -> 500000 | ... AW59: =SUM(AW54:AW58) -> 500000
D62: Debt Service Reserve Account interest income
E63: Annual cash interest rate | F63: =CaseData!$G$16 -> 0.015 | G63: %
E64: Quarterly cash interest rate | F64: =$F$63/4 -> 0.00375 | G64: %
E65: Debt Service Reserve Account interest income | G65: USD | H65: =SUM( J65:AW65) -> 96988.418 | J65: =J$54 * $F$64 -> 1875 | K65: =K$54 * $F$64 -> 2721.7971 | L65: =L$54 * $F$64 -> 3561.0701 | M65: =M$54 * $F$64 -> 4408.1208 | N65: =N$54 * $F$64 -> 5313.1204 | O65: =O$54 * $F$64 -> 6313.8208 | P65: =P$54 * $F$64 -> 1875 | Q65: =Q$54 * $F$64 -> 1875 | ... AW65: =AW$54 * $F$64 -> 1875
A68: Senior Debt
E70: Senior Debt balance at model start date | F70: =CaseData!$G$4 -> 10000000 | G70: USD
E72: Senior Debt opening balance | G72: USD | J72: =I$74 -> 10000000 | K72: =J$74 -> 9746520.6 | L72: =K$74 -> 9493960.4 | M72: =L$74 -> 9241756 | N72: =M$74 -> 8987604.1 | O72: =N$74 -> 8729722.5 | P72: =O$74 -> 8476612.9 | Q72: =P$74 -> 8220662.2 | ... AW72: =AV$74 -> 0
E73: Senior Debt principal addition / (repayment) | G73: USD | J73: {=INDEX( CaseData!$G$42:$G$81, MATCH(_xlfn.ANCHORARRAY( $J$3), CaseData!$D$42:$D$81, 0 ) )} -> -253479.44 | K73: -252560.16 | L73: -252204.38 | M73: -254151.94 | N73: -257881.62 | O73: -253109.58 | P73: -255950.67 | Q73: -256648.94 | R73: -277545.95 | S73: -261788.6 | T73: -270867.07 | U73: -269376.8 | V73: -271815.12 | W73: -291592.25 | X73: -296806.05 | Y73: -306446.68 | Z73: -296395.59 | AA73: -309492.76 | AB73: -318980.31 | AC73: -329615.9 | AD73: -344826.09 | AE73: -334741.98 | AF73: -349935.7 | AG73: -346099.89 | AH73: -351035.59 | AI73: -359246.86 | AJ73: -381624.67 | AK73: -368562.76 | AL73: -367781.46 | AM73: -382318.73 | AN73: -409886.6 | AO73: -412061.29 | AP73: -55168.571 | AQ73: 0 | AR73: 0 | AS73: 0 | AT73: 0 | AU73: 0 | AV73: 0 | AW73: 0
E74: Senior Debt | G74: USD | I74: =$F$70 -> 10000000 | J74: =SUM(J72:J73) -> 9746520.6 | K74: =SUM(K72:K73) -> 9493960.4 | L74: =SUM(L72:L73) -> 9241756 | M74: =SUM(M72:M73) -> 8987604.1 | N74: =SUM(N72:N73) -> 8729722.5 | O74: =SUM(O72:O73) -> 8476612.9 | P74: =SUM(P72:P73) -> 8220662.2 | Q74: =SUM(Q72:Q73) -> 7964013.3 | ... AW74: =SUM(AW72:AW73) -> 0
D77: Senior Debt interest expenses
E78: Annual cash interest rate | F78: =CaseData!$G$5 -> 0.05 | G78: %
E79: Quarterly cash interest rate | F79: =$F$78/4 -> 0.0125 | G79: %
E80: Senior Debt interest expenses | G80: USD | H80: =SUM(J80:AW80) -> 2253687.6 | J80: =J$72 * $F$79 -> 125000 | K80: =K$72 * $F$79 -> 121831.51 | L80: =L$72 * $F$79 -> 118674.5 | M80: =M$72 * $F$79 -> 115521.95 | N80: =N$72 * $F$79 -> 112345.05 | O80: =O$72 * $F$79 -> 109121.53 | P80: =P$72 * $F$79 -> 105957.66 | Q80: =Q$72 * $F$79 -> 102758.28 | ... AW80: =AW$72 * $F$79 -> 0
A83: Junior Debt
E85: Junior Debt balance at model start date | F85: =CaseData!$G$19 -> 6000000 | G85: USD
E87: Junior Debt opening balance | G87: USD | J87: =I$91 -> 6000000 | K87: =J$91 -> 6105000 | L87: =K$91 -> 6211837.5 | M87: =L$91 -> 6320544.7 | N87: =M$91 -> 6431154.2 | O87: =N$91 -> 6543699.4 | P87: =O$91 -> 5219918.9 | Q87: =P$91 -> 5085702.8 | ... AW87: =AV$91 -> 150000
E88: =E$102 -> Unmet Junior Debt interest owed | G88: =G$102 -> USD | I88: =I$102 -> 0 | J88: =J$102 -> 105000 | K88: =K$102 -> 106837.5 | L88: =L$102 -> 108707.16 | M88: =M$102 -> 110609.53 | N88: =N$102 -> 112545.2 | O88: =O$102 -> 0 | P88: =P$102 -> 0 | ... AW88: =AW$102 -> 0
E89: =E$106 -> Junior Debt Scheduled Repayment Paid | G89: =G$106 -> USD | I89: =I$106 -> 0 | J89: =J$106 * - 1 -> 0 | K89: =K$106 * - 1 -> 0 | L89: =L$106 * - 1 -> 0 | M89: =M$106 * - 1 -> 0 | N89: =N$106 * - 1 -> 0 | O89: =O$106 * - 1 -> -150000 | P89: =P$106 * - 1 -> -134216.09 | Q89: =Q$106 * - 1 -> -150000 | ... AW89: =AW$106 * - 1 -> -150000
E90: =E$116 -> Repayment of arrears owed | G90: =G$116 -> USD | I90: =I$116 -> 0 | J90: =J$116 -> 0 | K90: =K$116 -> 0 | L90: =L$116 -> 0 | M90: =M$116 -> 0 | N90: =N$116 -> 0 | O90: =O$116 -> -1173780.5 | P90: =P$116 -> 0 | ... AW90: =AW$116 -> 0
E91: Junior Debt | G91: USD | I91: =$F$85 -> 6000000 | J91: =SUM(J87,J88,J89,J90) -> 6105000 | K91: =SUM(K87,K88,K89,K90) -> 6211837.5 | L91: =SUM(L87,L88,L89,L90) -> 6320544.7 | M91: =SUM(M87,M88,M89,M90) -> 6431154.2 | N91: =SUM(N87,N88,N89,N90) -> 6543699.4 | O91: =SUM(O87,O88,O89,O90) -> 5219918.9 | P91: =SUM(P87,P88,P89,P90) -> 5085702.8 | Q91: =SUM(Q87,Q88,Q89,Q90) -> 4894662.8 | ... AW91: =SUM(AW87,AW88,AW89,AW90) -> -8.1490725e-10
D94: Junior Debt interest expenses
E95: Annual cash interest rate | F95: =CaseData!$G$20 -> 0.07 | G95: %
E96: Quarterly cash interest rate | F96: =$F$95/4 -> 0.0175 | G96: %
E97: Junior Debt interest expenses | G97: USD | H97: =SUM(J97:AW97) -> 2708518.4 | J97: =J$87 * $F$96 -> 105000 | K97: =K$87 * $F$96 -> 106837.5 | L97: =L$87 * $F$96 -> 108707.16 | M97: =M$87 * $F$96 -> 110609.53 | N97: =N$87 * $F$96 -> 112545.2 | O97: =O$87 * $F$96 -> 114514.74 | P97: =P$87 * $F$96 -> 91348.58 | Q97: =Q$87 * $F$96 -> 88999.799 | ... AW97: =AW$87 * $F$96 -> 2625
E99: =E$20 -> Funds available for Junior Debt service | G99: =G$20 -> USD | I99: =I$20 -> 0 | J99: =J$20 -> 0 | K99: =K$20 -> 0 | L99: =L$20 -> 0 | M99: =M$20 -> 0 | N99: =N$20 -> 0 | O99: =O$20 -> 1438295.3 | P99: =P$20 -> 225564.67 | ... AW99: =AW$20 -> 751884
E101: Junior Debt interest paid | G101: USD | H101: =SUM(J101:AW101) -> 1119394.1 | J101: =MIN( J$97, J$99 ) -> 0 | K101: =MIN( K$97, K$99 ) -> 0 | L101: =MIN( L$97, L$99 ) -> 0 | M101: =MIN( M$97, M$99 ) -> 0 | N101: =MIN( N$97, N$99 ) -> 0 | O101: =MIN( O$97, O$99 ) -> 114514.74 | P101: =MIN( P$97, P$99 ) -> 91348.58 | Q101: =MIN( Q$97, Q$99 ) -> 88999.799 | ... AW101: =MIN( AW$97, AW$99 ) -> 2625
E102: Unmet Junior Debt interest owed | G102: USD | J102: =J$97 - J$101 -> 105000 | K102: =K$97 - K$101 -> 106837.5 | L102: =L$97 - L$101 -> 108707.16 | M102: =M$97 - M$101 -> 110609.53 | N102: =N$97 - N$101 -> 112545.2 | O102: =O$97 - O$101 -> 0 | P102: =P$97 - P$101 -> 0 | Q102: =Q$97 - Q$101 -> 0 | ... AW102: =AW$97 - AW$101 -> 0
E104: Scheduled Junior Debt repayment | G104: USD | J104: {=INDEX( CaseData!$J$42:$J$81, MATCH(_xlfn.ANCHORARRAY( $J$3), CaseData!$D$42:$D$81, 0 ) ) * - 1} -> 150000 | K104: 150000 | L104: 150000 | M104: 150000 | N104: 150000 | O104: 150000 | P104: 150000 | Q104: 150000 | R104: 150000 | S104: 150000 | T104: 150000 | U104: 150000 | V104: 150000 | W104: 150000 | X104: 150000 | Y104: 150000 | Z104: 150000 | AA104: 150000 | AB104: 150000 | AC104: 150000 | AD104: 150000 | AE104: 150000 | AF104: 150000 | AG104: 150000 | AH104: 150000 | AI104: 150000 | AJ104: 150000 | AK104: 150000 | AL104: 150000 | AM104: 150000 | AN104: 150000 | AO104: 150000 | AP104: 150000 | AQ104: 150000 | AR104: 150000 | AS104: 150000 | AT104: 150000 | AU104: 150000 | AV104: 150000 | AW104: 150000
E105: =E$23 -> Funds Available for Junior Debt Scheduled Repayments | G105: =G$23 -> USD | I105: =I$23 -> 0 | J105: =J$23 -> 0 | K105: =K$23 -> 0 | L105: =L$23 -> 0 | M105: =M$23 -> 0 | N105: =N$23 -> 0 | O105: =O$23 -> 1323780.5 | P105: =P$23 -> 134216.09 | ... AW105: =AW$23 -> 749259
E106: Junior Debt Scheduled Repayment Paid | G106: USD | J106: =MIN( J$104, J$105 ) -> 0 | K106: =MIN( K$104, K$105 ) -> 0 | L106: =MIN( L$104, L$105 ) -> 0 | M106: =MIN( M$104, M$105 ) -> 0 | N106: =MIN( N$104, N$105 ) -> 0 | O106: =MIN( O$104, O$105 ) -> 150000 | P106: =MIN( P$104, P$105 ) -> 134216.09 | Q106: =MIN( Q$104, Q$105 ) -> 150000 | ... AW106: =MIN( AW$104, AW$105 ) -> 150000
E107: Unmet Scheduled Junior Debt repayment | G107: USD | J107: =J$104 - J$106 -> 150000 | K107: =K$104 - K$106 -> 150000 | L107: =L$104 - L$106 -> 150000 | M107: =M$104 - M$106 -> 150000 | N107: =N$104 - N$106 -> 150000 | O107: =O$104 - O$106 -> 0 | P107: =P$104 - P$106 -> 15783.913 | Q107: =Q$104 - Q$106 -> 0 | ... AW107: =AW$104 - AW$106 -> 0
D109: Arrears Amount Owed
E111: =E$26 -> Funds Available for Junior Debt Arrears Amount Owed | G111: =G$26 -> USD | I111: =I$26 -> 0 | J111: =J$26 -> 0 | K111: =K$26 -> 0 | L111: =L$26 -> 0 | M111: =M$26 -> 0 | N111: =N$26 -> 0 | O111: =O$26 -> 1173780.5 | P111: =P$26 -> 0 | ... AW111: =AW$26 -> 599259
E113: Arrears amount owed opening balance | J113: =I117 -> 0 | K113: =J117 -> 255000 | L113: =K117 -> 511837.5 | M113: =L117 -> 770544.66 | N113: =M117 -> 1031154.2 | O113: =N117 -> 1293699.4 | P113: =O117 -> 119918.86 | Q113: =P117 -> 135702.78 | ... AW113: =AV117 -> 0
E114: =E$102 -> Unmet Junior Debt interest owed | G114: =G$102 -> USD | I114: =I$102 -> 0 | J114: =J$102 -> 105000 | K114: =K$102 -> 106837.5 | L114: =L$102 -> 108707.16 | M114: =M$102 -> 110609.53 | N114: =N$102 -> 112545.2 | O114: =O$102 -> 0 | P114: =P$102 -> 0 | ... AW114: =AW$102 -> 0
E115: =E$107 -> Unmet Scheduled Junior Debt repayment | G115: =G$107 -> USD | I115: =I$107 -> 0 | J115: =J$107 -> 150000 | K115: =K$107 -> 150000 | L115: =L$107 -> 150000 | M115: =M$107 -> 150000 | N115: =N$107 -> 150000 | O115: =O$107 -> 0 | P115: =P$107 -> 15783.913 | ... AW115: =AW$107 -> 0
E116: Repayment of arrears owed | G116: USD | J116: =- MIN( J$111, SUM( J113:J115 ) ) -> 0 | K116: =- MIN( K$111, SUM( K113:K115 ) ) -> 0 | L116: =- MIN( L$111, SUM( L113:L115 ) ) -> 0 | M116: =- MIN( M$111, SUM( M113:M115 ) ) -> 0 | N116: =- MIN( N$111, SUM( N113:N115 ) ) -> 0 | O116: =- MIN( O$111, SUM( O113:O115 ) ) -> -1173780.5 | P116: =- MIN( P$111, SUM( P113:P115 ) ) -> 0 | Q116: =- MIN( Q$111, SUM( Q113:Q115 ) ) -> -41039.979 | ... AW116: =- MIN( AW$111, SUM( AW113:AW115 ) ) -> 0
E117: Arrears amount owed closing balance | G117: USD | J117: =SUM(J113:J116) -> 255000 | K117: =SUM(K113:K116) -> 511837.5 | L117: =SUM(L113:L116) -> 770544.66 | M117: =SUM(M113:M116) -> 1031154.2 | N117: =SUM(N113:N116) -> 1293699.4 | O117: =SUM(O113:O116) -> 119918.86 | P117: =SUM(P113:P116) -> 135702.78 | Q117: =SUM(Q113:Q116) -> 94662.797 | ... AW117: =SUM(AW113:AW116) -> 0
A120: Answers
C122: a) | E122: Build schedules for Senior and Junior Debt, DSRA, Equity and Cash flow waterfall | J122: see above
C123: b) | E123: Ensure that the model has flexibility for the user to change EBIDTA scenario | J123: see above
C124: c) | E124: Under EBIDTA scenario 3, what is the closing balance of the Junior Debt on 31/3/2021 | J124: 4713427
C125: e) | E125: Under EBIDTA scenario 2, what is the minimum balance of the DSRA during the period 2019-15 | J125: 500000
C126: f) | E126: Under EBIDTA scenario 6, what is the total cash interest expenses for the Junior Debt | J126: 2708518.4
C127: g) | E127: Under EBIDTA scenario 4, what is the outstanding Junior Debt balance on 31/12/2028 | J127: 0
A133: Model timeline
E135: Model start date | F135: =start_date -> 43465 | G135: date
E136: Number of model periods | F136: =periods -> 40 | G136: quarters
E137: Model period beginning | G137: date | J137: {=EDATE( start_date + 1, _xlfn.SEQUENCE( 1, periods, 0, 3 ) )} -> 43466 | K137: 43556 | L137: 43647 | M137: 43739 | N137: 43831 | O137: 43922 | P137: 44013 | Q137: 44105 | R137: 44197 | S137: 44287 | T137: 44378 | U137: 44470 | V137: 44562 | W137: 44652 | X137: 44743 | Y137: 44835 | Z137: 44927 | AA137: 45017 | AB137: 45108 | AC137: 45200 | AD137: 45292 | AE137: 45383 | AF137: 45474 | AG137: 45566 | AH137: 45658 | AI137: 45748 | AJ137: 45839 | AK137: 45931 | AL137: 46023 | AM137: 46113 | AN137: 46204 | AO137: 46296 | AP137: 46388 | AQ137: 46478 | AR137: 46569 | AS137: 46661 | AT137: 46753 | AU137: 46844 | AV137: 46935 | AW137: 47027
E138: Model period ending | G138: date | J138: {=EOMONTH( start_date, _xlfn.SEQUENCE( 1, periods, 3, 3 ) )} -> 43555 | K138: 43646 | L138: 43738 | M138: 43830 | N138: 43921 | O138: 44012 | P138: 44104 | Q138: 44196 | R138: 44286 | S138: 44377 | T138: 44469 | U138: 44561 | V138: 44651 | W138: 44742 | X138: 44834 | Y138: 44926 | Z138: 45016 | AA138: 45107 | AB138: 45199 | AC138: 45291 | AD138: 45382 | AE138: 45473 | AF138: 45565 | AG138: 45657 | AH138: 45747 | AI138: 45838 | AJ138: 45930 | AK138: 46022 | AL138: 46112 | AM138: 46203 | AN138: 46295 | AO138: 46387 | AP138: 46477 | AQ138: 46568 | AR138: 46660 | AS138: 46752 | AT138: 46843 | AU138: 46934 | AV138: 47026 | AW138: 47118
E139: Quarter | G139: quarter | J139: {=MONTH(_xlfn.ANCHORARRAY( J138) ) / 4} -> 0.75 | K139: 1.5 | L139: 2.25 | M139: 3 | N139: 0.75 | O139: 1.5 | P139: 2.25 | Q139: 3 | R139: 0.75 | S139: 1.5 | T139: 2.25 | U139: 3 | V139: 0.75 | W139: 1.5 | X139: 2.25 | Y139: 3 | Z139: 0.75 | AA139: 1.5 | AB139: 2.25 | AC139: 3 | AD139: 0.75 | AE139: 1.5 | AF139: 2.25 | AG139: 3 | AH139: 0.75 | AI139: 1.5 | AJ139: 2.25 | AK139: 3 | AL139: 0.75 | AM139: 1.5 | AN139: 2.25 | AO139: 3 | AP139: 0.75 | AQ139: 1.5 | AR139: 2.25 | AS139: 3 | AT139: 0.75 | AU139: 1.5 | AV139: 2.25 | AW139: 3
E140: Year | G140: year | J140: {=YEAR(_xlfn.ANCHORARRAY( J138) )} -> 2019 | K140: 2019 | L140: 2019 | M140: 2019 | N140: 2020 | O140: 2020 | P140: 2020 | Q140: 2020 | R140: 2021 | S140: 2021 | T140: 2021 | U140: 2021 | V140: 2022 | W140: 2022 | X140: 2022 | Y140: 2022 | Z140: 2023 | AA140: 2023 | AB140: 2023 | AC140: 2023 | AD140: 2024 | AE140: 2024 | AF140: 2024 | AG140: 2024 | AH140: 2025 | AI140: 2025 | AJ140: 2025 | AK140: 2025 | AL140: 2026 | AM140: 2026 | AN140: 2026 | AO140: 2026 | AP140: 2027 | AQ140: 2027 | AR140: 2027 | AS140: 2027 | AT140: 2028 | AU140: 2028 | AV140: 2028 | AW140: 2028

Sheet CaseData
A1: Assumptions
B3: Senior Facility
C4: Facility Balance at model start date | E4: [$] | G4: 10000000
C5: Annual cash interest rate | E5: [% p.a.] | G5: 0.05 | K5: Scenario
K6: Toggle for EBITDA values
C7: Senior DSCR Lock up trigger | E7: [x] | G7: 1.62
C8: Look-back quarters for DSCR incl. current quarter (Last Twelve Months) | E8: [#] | G8: 4 | H8: Do not change | K8: DSCR
C10: To get out of lock-up: | J10: LTM | K10: EBITDA + Interest Income / Senior Debt Costs
C11: Number of quarters required for Sr DSCR to be greater than lock-up trigger: | E11: [# qtrs] | G11: 2 | H11: Do not change
B13: Debt Service Reserve Account
C14: Initial balance at project start (already funded) | G14: 500000
C15: Required minimum balance during term of Senior Facility | G15: 500000
C16: Cash interest rate earned on account balance | E16: [% p.a.] | G16: 0.015
J17: =PMT((G5/4),33,G4,0,0) -> -371678.65
B18: Junior Facility
C19: Facility Balance at model start date | E19: [$] | G19: 6000000
C20: Annual cash interest rate | E20: [% p.a.] | G20: 0.07 | H20: =G19/G21 -> 150000
C21: Amortisation Quarters | E21: [#] | G21: 40
C22: Scheduled final payment date | E22: [date] | G22: =EOMONTH(G30,3*G21) -> 47118
B24: Equity
C25: Contribution amount at model start date | E25: [$] | G25: 4000000
C26: Discount rate for Net Present Value Calculations | E26: [% p.a.] | G26: 0.095
B29: Other Assumptions
C30: Model start date (Project start date) | E30: [date] | G30: 43465
C31: Initial quarter end date | E31: [date] | G31: =EOMONTH(G30,3) -> 43555
C32: Number of quarters in project | E32: [# qtrs] | G32: 40
C33: Final quarter end date (Project end date) | E33: [date] | G33: =EOMONTH(G30,G32*3) -> 47118
C35: Cash interest rate earned on cash account balance | E35: [% p.a.] | G35: 0.015
B38: Schedule Debt Repayments | G38: Senior Debt | J38: Junior Debt
G39: Scheduled Snr | H39: Scheduled Snr | J39: Scheduled Jnr | K39: Scheduled Jnr
G40: Principal | H40: Closing Balance | J40: Principal | K40: Closing Balance
D41: Quarter Ending | G41: [$] | H41: [$] | J41: [$] | K41: [$]
D42: =$G$31 -> 43555 | G42: -253479.44 | H42: =G4+G42 -> 9746520.6 | J42: -150000 | K42: =G19+J42 -> 5850000
D43: =EOMONTH(D42,3) -> 43646 | G43: -252560.16 | H43: =H42+G43 -> 9493960.4 | J43: -150000 | K43: =K42+J43 -> 5700000
D44: =EOMONTH(D43,3) -> 43738 | G44: -252204.38 | H44: =H43+G44 -> 9241756 | J44: -150000 | K44: =K43+J44 -> 5550000
D45: =EOMONTH(D44,3) -> 43830 | G45: -254151.94 | H45: =H44+G45 -> 8987604.1 | J45: -150000 | K45: =K44+J45 -> 5400000
D46: =EOMONTH(D45,3) -> 43921 | G46: -257881.62 | H46: =H45+G46 -> 8729722.5 | J46: -150000 | K46: =K45+J46 -> 5250000
D47: =EOMONTH(D46,3) -> 44012 | G47: -253109.58 | H47: =H46+G47 -> 8476612.9 | J47: -150000 | K47: =K46+J47 -> 5100000
D48: =EOMONTH(D47,3) -> 44104 | G48: -255950.67 | H48: =H47+G48 -> 8220662.2 | J48: -150000 | K48: =K47+J48 -> 4950000
D49: =EOMONTH(D48,3) -> 44196 | G49: -256648.94 | H49: =H48+G49 -> 7964013.3 | J49: -150000 | K49: =K48+J49 -> 4800000
D50: =EOMONTH(D49,3) -> 44286 | G50: -277545.95 | H50: =H49+G50 -> 7686467.3 | J50: -150000 | K50: =K49+J50 -> 4650000
D51: =EOMONTH(D50,3) -> 44377 | G51: -261788.6 | H51: =H50+G51 -> 7424678.7 | J51: -150000 | K51: =K50+J51 -> 4500000
D52: =EOMONTH(D51,3) -> 44469 | G52: -270867.07 | H52: =H51+G52 -> 7153811.6 | J52: -150000 | K52: =K51+J52 -> 4350000
D53: =EOMONTH(D52,3) -> 44561 | G53: -269376.8 | H53: =H52+G53 -> 6884434.8 | J53: -150000 | K53: =K52+J53 -> 4200000
D54: =EOMONTH(D53,3) -> 44651 | G54: -271815.12 | H54: =H53+G54 -> 6612619.7 | J54: -150000 | K54: =K53+J54 -> 4050000
... D74: =EOMONTH(D73,3) -> 46477 | G74: -55168.571 | H74: =H73+G74 -> 0 | J74: -150000 | K74: =K73+J74 -> 1050000
D75: =EOMONTH(D74,3) -> 46568 | H75: =H74+G75 -> 0 | J75: -150000 | K75: =K74+J75 -> 900000
D76: =EOMONTH(D75,3) -> 46660 | H76: =H75+G76 -> 0 | J76: -150000 | K76: =K75+J76 -> 750000
D77: =EOMONTH(D76,3) -> 46752 | H77: =H76+G77 -> 0 | J77: -150000 | K77: =K76+J77 -> 600000
D78: =EOMONTH(D77,3) -> 46843 | H78: =H77+G78 -> 0 | J78: -150000 | K78: =K77+J78 -> 450000
D79: =EOMONTH(D78,3) -> 46934 | H79: =H78+G79 -> 0 | J79: -150000 | K79: =K78+J79 -> 300000
D80: =EOMONTH(D79,3) -> 47026 | H80: =H79+G80 -> 0 | J80: -150000 | K80: =K79+J80 -> 150000
D81: =EOMONTH(D80,3) -> 47118 | H81: =H80+G81 -> 0 | J81: -150000 | K81: =K80+J81 -> 0
B84: EBITDA Profiles
D86: Profile Number --> | F86: 1 | G86: 2 | H86: 3 | I86: 4 | J86: 5 | K86: 6
D87: Profile Name --> | F87: Base Case | G87: Case 2 | H87: Case 3 | I87: Case 4 | J87: Case 5 | K87: Case 6 | M87: {=TRANSPOSE( $F$87:$K$87 )} -> Base Case
D88: Quarter Ending | F88: [$] | G88: [$] | H88: [$] | I88: [$] | J88: [$] | K88: [$] | M88: Case 2
D89: =$G$31 -> 43555 | F89: 679388 | G89: 736761 | H89: 571081 | I89: 655292 | J89: 679388 | K89: 602417 | M89: Case 3
D90: =EOMONTH(D89,3) -> 43646 | F90: 672030 | G90: 640675 | H90: 638069 | I90: 621828 | J90: 672030 | K90: 595476 | M90: Case 4
D91: =EOMONTH(D90,3) -> 43738 | F91: 665707 | G91: 699072 | H91: 613173 | I91: 648860 | J91: 665707 | K91: 593198 | M91: Case 5
D92: =EOMONTH(D91,3) -> 43830 | F92: 663538 | G92: 716185 | H92: 660141 | I92: 631452 | J92: 663538 | K92: 606599 | M92: Case 6
D93: =EOMONTH(D92,3) -> 43921 | F93: 664533 | G93: 745018 | H93: 660429 | I93: 627040 | J93: 664533 | K93: 631767
D94: =EOMONTH(D93,3) -> 44012 | F94: 650141 | G94: 647540 | H94: 627234 | I94: 642721 | J94: 650141 | K94: 610527
D95: =EOMONTH(D94,3) -> 44104 | F95: 649560 | G95: 610710 | H95: 540570 | I95: 614186 | J95: 649560 | K95: 585598
D96: =EOMONTH(D95,3) -> 44196 | F96: 645058 | G96: 524218 | H96: 559566 | I96: 637301 | J96: 322529 | K96: 637572
D97: =EOMONTH(D96,3) -> 44286 | F97: 676898 | G97: 588415 | H97: 641777 | I97: 614478 | J97: 338449 | K97: 646990
D98: =EOMONTH(D97,3) -> 44377 | F98: 642290 | G98: 734340 | H98: 535813 | I98: 642224 | J98: 321145 | K98: 675583
D99: =EOMONTH(D98,3) -> 44469 | F99: 652741 | G99: 701469 | H99: 602155 | I99: 609670 | J99: 326370.5 | K99: 584611
D100: =EOMONTH(D99,3) -> 44561 | F100: 643964 | G100: 730507 | H100: 658754 | I100: 579572 | J100: 321982 | K100: 218154
D101: =EOMONTH(D100,3) -> 44651 | F101: 642292 | G101: 647014 | H101: 587599 | I101: 630557 | J101: 642292 | K101: 227447
D102: =EOMONTH(D101,3) -> 44742 | F102: 671775 | G102: 669273 | H102: 642603 | I102: 656933 | J102: 671775 | K102: 265153
D103: =EOMONTH(D102,3) -> 44834 | F103: 674599 | G103: 658660 | H103: 593452 | I103: 673605 | J103: 674599 | K103: 259078
D104: =EOMONTH(D103,3) -> 44926 | F104: 685274 | G104: 818256 | H104: 584660 | I104: 395608 | J104: 685274 | K104: 604305
... D128: =EOMONTH(D127,3) -> 47118 | F128: 772307 | G128: 726385 | H128: 641674 | I128: 699850 | J128: 772307 | K128: 750009
C133: Company | D133: Black Rat SPV 2
C134: CFM Topic | D134: Debt
C137: EBIDTA profile labels | D137: {=TRANSPOSE( CaseData!$F$87:$K$87 )} -> Base Case
D138: Case 2
D139: Case 3
D140: Case 4
D141: Case 5
D142: Case 6
A147: End Sheet

Sheet CaseSolution
B2: Period Start | J2: =I3+1 -> 43466 | K2: =J3+1 -> 43556 | L2: =K3+1 -> 43647 | M2: =L3+1 -> 43739 | N2: =M3+1 -> 43831 | O2: =N3+1 -> 43922 | P2: =O3+1 -> 44013 | Q2: =P3+1 -> 44105 | ... AW2: =AV3+1 -> 47027
B3: Period End | I3: =CaseData!G30 -> 43465 | J3: =EOMONTH(I3,3) -> 43555 | K3: =EOMONTH(J3,3) -> 43646 | L3: =EOMONTH(K3,3) -> 43738 | M3: =EOMONTH(L3,3) -> 43830 | N3: =EOMONTH(M3,3) -> 43921 | O3: =EOMONTH(N3,3) -> 44012 | P3: =EOMONTH(O3,3) -> 44104 | Q3: =EOMONTH(P3,3) -> 44196 | ... AW3: =EOMONTH(AV3,3) -> 47118
B4: Model Quarter | I4: 0 | J4: =I4+1 -> 1 | K4: =J4+1 -> 2 | L4: =K4+1 -> 3 | M4: =L4+1 -> 4 | N4: =M4+1 -> 5 | O4: =N4+1 -> 6 | P4: =O4+1 -> 7 | Q4: =P4+1 -> 8 | ... AW4: =AV4+1 -> 40
B7: Cash Flow Waterfall
C9: EBITDA | H9: Case 6 | J9: =INDEX(CaseData!$F$89:$K$128,MATCH(J$3,CaseData!$D$89:$D$128,0),MATCH($H9,CaseData!$F$87:$K$87,0)) -> 602417 | K9: =INDEX(CaseData!$F$89:$K$128,MATCH(K$3,CaseData!$D$89:$D$128,0),MATCH($H9,CaseData!$F$87:$K$87,0)) -> 595476 | L9: =INDEX(CaseData!$F$89:$K$128,MATCH(L$3,CaseData!$D$89:$D$128,0),MATCH($H9,CaseData!$F$87:$K$87,0)) -> 593198 | M9: =INDEX(CaseData!$F$89:$K$128,MATCH(M$3,CaseData!$D$89:$D$128,0),MATCH($H9,CaseData!$F$87:$K$87,0)) -> 606599 | N9: =INDEX(CaseData!$F$89:$K$128,MATCH(N$3,CaseData!$D$89:$D$128,0),MATCH($H9,CaseData!$F$87:$K$87,0)) -> 631767 | O9: =INDEX(CaseData!$F$89:$K$128,MATCH(O$3,CaseData!$D$89:$D$128,0),MATCH($H9,CaseData!$F$87:$K$87,0)) -> 610527 | P9: =INDEX(CaseData!$F$89:$K$128,MATCH(P$3,CaseData!$D$89:$D$128,0),MATCH($H9,CaseData!$F$87:$K$87,0)) -> 585598 | Q9: =INDEX(CaseData!$F$89:$K$128,MATCH(Q$3,CaseData!$D$89:$D$128,0),MATCH($H9,CaseData!$F$87:$K$87,0)) -> 637572 | ... AW9: =INDEX(CaseData!$F$89:$K$128,MATCH(AW$3,CaseData!$D$89:$D$128,0),MATCH($H9,CaseData!$F$87:$K$87,0)) -> 750009
C10: Interest Income | J10: =J66 -> 1875 | K10: =K66 -> 2721.7971 | L10: =L66 -> 3561.0701 | M10: =M66 -> 4408.1208 | N10: =N66 -> 5313.1204 | O10: =O66 -> 6313.8208 | P10: =P66 -> 1875 | Q10: =Q66 -> 1875 | ... AW10: =AW66 -> 0
C11: Funds Available for Debt Service | J11: =SUM(J9:J10) -> 604292 | K11: =SUM(K9:K10) -> 598197.8 | L11: =SUM(L9:L10) -> 596759.07 | M11: =SUM(M9:M10) -> 611007.12 | N11: =SUM(N9:N10) -> 637080.12 | O11: =SUM(O9:O10) -> 616840.82 | P11: =SUM(P9:P10) -> 587473 | Q11: =SUM(Q9:Q10) -> 639447 | ... AW11: =SUM(AW9:AW10) -> 750009
C13: Sr. Debt Repayment | J13: =INDEX(CaseData!$G$42:$G$81,MATCH(J$3,CaseData!$D$42:$D$81,0)) -> -253479.44 | K13: =INDEX(CaseData!$G$42:$G$81,MATCH(K$3,CaseData!$D$42:$D$81,0)) -> -252560.16 | L13: =INDEX(CaseData!$G$42:$G$81,MATCH(L$3,CaseData!$D$42:$D$81,0)) -> -252204.38 | M13: =INDEX(CaseData!$G$42:$G$81,MATCH(M$3,CaseData!$D$42:$D$81,0)) -> -254151.94 | N13: =INDEX(CaseData!$G$42:$G$81,MATCH(N$3,CaseData!$D$42:$D$81,0)) -> -257881.62 | O13: =INDEX(CaseData!$G$42:$G$81,MATCH(O$3,CaseData!$D$42:$D$81,0)) -> -253109.58 | P13: =INDEX(CaseData!$G$42:$G$81,MATCH(P$3,CaseData!$D$42:$D$81,0)) -> -255950.67 | Q13: =INDEX(CaseData!$G$42:$G$81,MATCH(Q$3,CaseData!$D$42:$D$81,0)) -> -256648.94 | ... AW13: =INDEX(CaseData!$G$42:$G$81,MATCH(AW$3,CaseData!$D$42:$D$81,0)) -> 0
C14: Sr. Debt Interest | J14: =-J41 -> -125000 | K14: =-K41 -> -121831.51 | L14: =-L41 -> -118674.5 | M14: =-M41 -> -115521.95 | N14: =-N41 -> -112345.05 | O14: =-O41 -> -109121.53 | P14: =-P41 -> -105957.66 | Q14: =-Q41 -> -102758.28 | ... AW14: =-AW41 -> 0
C15: Sr. Debt Service | J15: =SUM(J13:J14) -> -378479.44 | K15: =SUM(K13:K14) -> -374391.67 | L15: =SUM(L13:L14) -> -370878.89 | M15: =SUM(M13:M14) -> -369673.89 | N15: =SUM(N13:N14) -> -370226.67 | O15: =SUM(O13:O14) -> -362231.11 | P15: =SUM(P13:P14) -> -361908.33 | Q15: =SUM(Q13:Q14) -> -359407.22 | ... AW15: =SUM(AW13:AW14) -> 0
C17: Funds Available / (Required) post Sr. Debt Service | J17: =SUM(J11,J15) -> 225812.56 | K17: =SUM(K11,K15) -> 223806.13 | L17: =SUM(L11,L15) -> 225880.18 | M17: =SUM(M11,M15) -> 241333.23 | N17: =SUM(N11,N15) -> 266853.45 | O17: =SUM(O11,O15) -> 254609.71 | P17: =SUM(P11,P15) -> 225564.67 | Q17: =SUM(Q11,Q15) -> 280039.78 | ... AW17: =SUM(AW11,AW15) -> 750009
C19: Withdrawl from DSRA | J19: =-MIN(J17,0) -> 0 | K19: =-MIN(K17,0) -> 0 | L19: =-MIN(L17,0) -> 0 | M19: =-MIN(M17,0) -> 0 | N19: =-MIN(N17,0) -> 0 | O19: =-MIN(O17,0) -> 0 | P19: =-MIN(P17,0) -> 0 | Q19: =-MIN(Q17,0) -> 0 | ... AW19: =-MIN(AW17,0) -> 0
C20: Top Up of DSRA | J20: =-MAX(MIN(J17,J68-SUM(J58:J59)),0) -> 0 | K20: =-MAX(MIN(K17,K68-SUM(K58:K59)),0) -> 0 | L20: =-MAX(MIN(L17,L68-SUM(L58:L59)),0) -> 0 | M20: =-MAX(MIN(M17,M68-SUM(M58:M59)),0) -> 0 | N20: =-MAX(MIN(N17,N68-SUM(N58:N59)),0) -> 0 | O20: =-MAX(MIN(O17,O68-SUM(O58:O59)),0) -> 0 | P20: =-MAX(MIN(P17,P68-SUM(P58:P59)),0) -> 0 | Q20: =-MAX(MIN(Q17,Q68-SUM(Q58:Q59)),0) -> 0 | ... AW20: =-MAX(MIN(AW17,AW68-SUM(AW58:AW59)),0) -> 0
C21: Sweep while in Lock-up | J21: =IF(J54=1,-SUM(J17:J20),0) -> -225812.56 | K21: =IF(K54=1,-SUM(K17:K20),0) -> -223806.13 | L21: =IF(L54=1,-SUM(L17:L20),0) -> -225880.18 | M21: =IF(M54=1,-SUM(M17:M20),0) -> -241333.23 | N21: =IF(N54=1,-SUM(N17:N20),0) -> -266853.45 | O21: =IF(O54=1,-SUM(O17:O20),0) -> 0 | P21: =IF(P54=1,-SUM(P17:P20),0) -> 0 | Q21: =IF(Q54=1,-SUM(Q17:Q20),0) -> 0 | ... AW21: =IF(AW54=1,-SUM(AW17:AW20),0) -> 0
C22: Release | J22: =-J62 -> 0 | K22: =-K62 -> 0 | L22: =-L62 -> 0 | M22: =-M62 -> 0 | N22: =-N62 -> 0 | O22: =-O62 -> 1183685.6 | P22: =-P62 -> 0 | Q22: =-Q62 -> 0 | ... AW22: =-AW62 -> 0
C23: Funds Available for Jr. Debt Service | J23: =SUM(J17:J22) -> 0 | K23: =SUM(K17:K22) -> 0 | L23: =SUM(L17:L22) -> 0 | M23: =SUM(M17:M22) -> 0 | N23: =SUM(N17:N22) -> 0 | O23: =SUM(O17:O22) -> 1438295.3 | P23: =SUM(P17:P22) -> 225564.67 | Q23: =SUM(Q17:Q22) -> 280039.78 | ... AW23: =SUM(AW17:AW22) -> 750009
C25: Jr. Debt Interest Paid | J25: =-J82 -> 0 | K25: =-K82 -> 0 | L25: =-L82 -> 0 | M25: =-M82 -> 0 | N25: =-N82 -> 0 | O25: =-O82 -> -114514.74 | P25: =-P82 -> -91348.58 | Q25: =-Q82 -> -88999.799 | ... AW25: =-AW82 -> -2625
C26: Funds Available for Jr. Debt - Scheduled Repayments | J26: =J23+J25 -> 0 | K26: =K23+K25 -> 0 | L26: =L23+L25 -> 0 | M26: =M23+M25 -> 0 | N26: =N23+N25 -> 0 | O26: =O23+O25 -> 1323780.5 | P26: =P23+P25 -> 134216.09 | Q26: =Q23+Q25 -> 191039.98 | ... AW26: =AW23+AW25 -> 747384
C28: Jr. Debt Repayment | J28: =-J88 -> 0 | K28: =-K88 -> 0 | L28: =-L88 -> 0 | M28: =-M88 -> 0 | N28: =-N88 -> 0 | O28: =-O88 -> -150000 | P28: =-P88 -> -134216.09 | Q28: =-Q88 -> -150000 | ... AW28: =-AW88 -> -150000
C29: Funds Available for Jr. Debt - Arrears Amount Owed | J29: =J26+J28 -> 0 | K29: =K26+K28 -> 0 | L29: =L26+L28 -> 0 | M29: =M26+M28 -> 0 | N29: =N26+N28 -> 0 | O29: =O26+O28 -> 1173780.5 | P29: =P26+P28 -> 0 | Q29: =Q26+Q28 -> 41039.979 | ... AW29: =AW26+AW28 -> 597384
C31: Arrears Amount Owed Repayment | J31: =J97 -> 0 | K31: =K97 -> 0 | L31: =L97 -> 0 | M31: =M97 -> 0 | N31: =N97 -> 0 | O31: =O97 -> -1173780.5 | P31: =P97 -> 0 | Q31: =Q97 -> -41039.979 | ... AW31: =AW97 -> 0
C32: Funds Distributed to Equity | J32: =SUM(J29,J31) -> 0 | K32: =SUM(K29,K31) -> 0 | L32: =SUM(L29,L31) -> 0 | M32: =SUM(M29,M31) -> 0 | N32: =SUM(N29,N31) -> 0 | O32: =SUM(O29,O31) -> 0 | P32: =SUM(P29,P31) -> 0 | Q32: =SUM(Q29,Q31) -> 0 | ... AW32: =SUM(AW29,AW31) -> 597384
B35: Sr Facility
C36: Opening Balance | J36: =I38 -> 10000000 | K36: =J38 -> 9746520.6 | L36: =K38 -> 9493960.4 | M36: =L38 -> 9241756 | N36: =M38 -> 8987604.1 | O36: =N38 -> 8729722.5 | P36: =O38 -> 8476612.9 | Q36: =P38 -> 8220662.2 | ... AW36: =AV38 -> 0
C37: Repayment | J37: =J13 -> -253479.44 | K37: =K13 -> -252560.16 | L37: =L13 -> -252204.38 | M37: =M13 -> -254151.94 | N37: =N13 -> -257881.62 | O37: =O13 -> -253109.58 | P37: =P13 -> -255950.67 | Q37: =Q13 -> -256648.94 | ... AW37: =AW13 -> 0
C38: Closing Balance | I38: =CaseData!G4 -> 10000000 | J38: =SUM(J36:J37) -> 9746520.6 | K38: =SUM(K36:K37) -> 9493960.4 | L38: =SUM(L36:L37) -> 9241756 | M38: =SUM(M36:M37) -> 8987604.1 | N38: =SUM(N36:N37) -> 8729722.5 | O38: =SUM(O36:O37) -> 8476612.9 | P38: =SUM(P36:P37) -> 8220662.2 | Q38: =SUM(Q36:Q37) -> 7964013.3 | ... AW38: =SUM(AW36:AW37) -> 0
C40: Interest Rate | H40: =CaseData!G5 -> 0.05 | J40: =$H40 -> 0.05 | K40: =$H40 -> 0.05 | L40: =$H40 -> 0.05 | M40: =$H40 -> 0.05 | N40: =$H40 -> 0.05 | O40: =$H40 -> 0.05 | P40: =$H40 -> 0.05 | Q40: =$H40 -> 0.05 | ... AW40: =$H40 -> 0.05
C41: Interest Expense | J41: =J36*J40/4 -> 125000 | K41: =K36*K40/4 -> 121831.51 | L41: =L36*L40/4 -> 118674.5 | M41: =M36*M40/4 -> 115521.95 | N41: =N36*N40/4 -> 112345.05 | O41: =O36*O40/4 -> 109121.53 | P41: =P36*P40/4 -> 105957.66 | Q41: =Q36*Q40/4 -> 102758.28 | ... AW41: =AW36*AW40/4 -> 0
B44: DSCR (LTM) | J44: =J37-J41 -> -378479.44 | K44: =K37-K41 -> -374391.67 | L44: =L37-L41 -> -370878.89 | M44: =M37-M41 -> -369673.89 | N44: =N37-N41 -> -370226.67 | O44: =O37-O41 -> -362231.11 | P44: =P37-P41 -> -361908.33 | Q44: =Q37-Q41 -> -359407.22 | R44: =R37-R41 -> -377096.11
C45: EBITDA | J45: =SUM(J9:J9) -> 602417 | K45: =SUM(J9:K9) -> 1197893 | L45: =SUM(J9:L9) -> 1791091 | M45: =SUM(J9:M9) -> 2397690 | N45: =SUM(K9:N9) -> 2427040 | O45: =SUM(L9:O9) -> 2442091 | P45: =SUM(M9:P9) -> 2434491 | Q45: =SUM(N9:Q9) -> 2465464 | R45: =SUM(O9:R9) -> 2480687 | S45: =SUM(P9:S9) -> 2545743 | T45: =SUM(Q9:T9) -> 2544756 | ... AW45: =SUM(AT9:AW9) -> 2987085
C46: Interest Income | J46: =SUM(J10:J10) -> 1875 | K46: =SUM(J10:K10) -> 4596.7971 | L46: =SUM(J10:L10) -> 8157.8672 | M46: =SUM(J10:M10) -> 12565.988 | N46: =SUM(K10:N10) -> 16004.108 | O46: =SUM(L10:O10) -> 19596.132 | P46: =SUM(M10:P10) -> 17910.062 | Q46: =SUM(N10:Q10) -> 15376.941 | R46: =SUM(O10:R10) -> 11938.821 | S46: =SUM(P10:S10) -> 7500 | T46: =SUM(Q10:T10) -> 7500 | ... AW46: =SUM(AT10:AW10) -> 0
C47: Sr. Interest Expense | J47: =SUM(J41:J41) -> 125000 | K47: =SUM(J41:K41) -> 246831.51 | L47: =SUM(J41:L41) -> 365506.01 | M47: =SUM(J41:M41) -> 481027.96 | N47: =SUM(K41:N41) -> 468373.01 | O47: =SUM(L41:O41) -> 455663.04 | P47: =SUM(M41:P41) -> 442946.19 | Q47: =SUM(N41:Q41) -> 430182.52 | R47: =SUM(O41:R41) -> 417387.63 | S47: =SUM(P41:S41) -> 404346.95 | T47: =SUM(Q41:T41) -> 391197.77 | ... AW47: =SUM(AT41:AW41) -> 0
C48: Sr. Principal Repayments | J48: =-SUM(J37:J37) -> 253479.44 | K48: =-SUM(J37:K37) -> 506039.6 | L48: =-SUM(J37:L37) -> 758243.99 | M48: =-SUM(J37:M37) -> 1012395.9 | N48: =-SUM(K37:N37) -> 1016798.1 | O48: =-SUM(L37:O37) -> 1017347.5 | P48: =-SUM(M37:P37) -> 1021093.8 | Q48: =-SUM(N37:Q37) -> 1023590.8 | R48: =-SUM(O37:R37) -> 1043255.1 | S48: =-SUM(P37:S37) -> 1051934.2 | T48: =-SUM(Q37:T37) -> 1066850.6 | ... AW48: =-SUM(AT37:AW37) -> 0
C50: DSCR | J50: =IFERROR(SUM(J45:J46)/SUM(J47:J48),"n.a.") -> 1.596631 | K50: =IFERROR(SUM(K45:K46)/SUM(K47:K48),"n.a.") -> 1.5972054 | L50: =IFERROR(SUM(L45:L46)/SUM(L47:L48),"n.a.") -> 1.6011113 | M50: =IFERROR(SUM(M45:M46)/SUM(M47:M48),"n.a.") -> 1.6139128 | N50: =IFERROR(SUM(N45:N46)/SUM(N47:N48),"n.a.") -> 1.644958 | O50: =IFERROR(SUM(O45:O46)/SUM(O47:O48),"n.a.") -> 1.6711945 | P50: =IFERROR(SUM(P45:P46)/SUM(P47:P48),"n.a.") -> 1.6750916 | Q50: =IFERROR(SUM(Q45:Q46)/SUM(Q47:Q48),"n.a.") -> 1.706484 | ... AW50: =IFERROR(SUM(AW45:AW46)/SUM(AW47:AW48),"n.a.") -> n.a.
C52: Lock-up Trigger | H52: =CaseData!G7 -> 1.62 | J52: =$H52 -> 1.62 | K52: =$H52 -> 1.62 | L52: =$H52 -> 1.62 | M52: =$H52 -> 1.62 | N52: =$H52 -> 1.62 | O52: =$H52 -> 1.62 | P52: =$H52 -> 1.62 | Q52: =$H52 -> 1.62 | ... AW52: =$H52 -> 1.62
C53: Lock Up Flag | J53: =IF(J50<J52,1,0) -> 1 | K53: =IF(K50<K52,1,0) -> 1 | L53: =IF(L50<L52,1,0) -> 1 | M53: =IF(M50<M52,1,0) -> 1 | N53: =IF(N50<N52,1,0) -> 0 | O53: =IF(O50<O52,1,0) -> 0 | P53: =IF(P50<P52,1,0) -> 0 | Q53: =IF(Q50<Q52,1,0) -> 0 | ... AW53: =IF(AW50<AW52,1,0) -> 0
C54: Release Test | H54: =MAX(J54:AW54) -> 1 | J54: =MAX(I53:J53) -> 1 | K54: =MAX(J53:K53) -> 1 | L54: =MAX(K53:L53) -> 1 | M54: =MAX(L53:M53) -> 1 | N54: =MAX(M53:N53) -> 1 | O54: =MAX(N53:O53) -> 0 | P54: =MAX(O53:P53) -> 0 | Q54: =MAX(P53:Q53) -> 0 | ... AW54: =MAX(AV53:AW53) -> 0
B57: DSRA
C58: Opening Balance | J58: =I63 -> 500000 | K58: =J63 -> 725812.56 | L58: =K63 -> 949618.69 | M58: =L63 -> 1175498.9 | N58: =M63 -> 1416832.1 | O58: =N63 -> 1683685.6 | P58: =O63 -> 500000 | Q58: =P63 -> 500000 | ... AW58: =AV63 -> 0
C59: Fund Sr. Debt Repayment Shortfall | J59: =-J19 -> 0 | K59: =-K19 -> 0 | L59: =-L19 -> 0 | M59: =-M19 -> 0 | N59: =-N19 -> 0 | O59: =-O19 -> 0 | P59: =-P19 -> 0 | Q59: =-Q19 -> 0 | ... AW59: =-AW19 -> 0
C60: Top Up to minimum balance | J60: =-J20 -> 0 | K60: =-K20 -> 0 | L60: =-L20 -> 0 | M60: =-M20 -> 0 | N60: =-N20 -> 0 | O60: =-O20 -> 0 | P60: =-P20 -> 0 | Q60: =-Q20 -> 0 | ... AW60: =-AW20 -> 0
C61: Sweep while in Lock-up | J61: =-J21 -> 225812.56 | K61: =-K21 -> 223806.13 | L61: =-L21 -> 225880.18 | M61: =-M21 -> 241333.23 | N61: =-N21 -> 266853.45 | O61: =-O21 -> 0 | P61: =-P21 -> 0 | Q61: =-Q21 -> 0 | ... AW61: =-AW21 -> 0
C62: Release | J62: =IF(J54=0,J68-SUM(J58:J61),0) -> 0 | K62: =IF(K54=0,K68-SUM(K58:K61),0) -> 0 | L62: =IF(L54=0,L68-SUM(L58:L61),0) -> 0 | M62: =IF(M54=0,M68-SUM(M58:M61),0) -> 0 | N62: =IF(N54=0,N68-SUM(N58:N61),0) -> 0 | O62: =IF(O54=0,O68-SUM(O58:O61),0) -> -1183685.6 | P62: =IF(P54=0,P68-SUM(P58:P61),0) -> 0 | Q62: =IF(Q54=0,Q68-SUM(Q58:Q61),0) -> 0 | ... AW62: =IF(AW54=0,AW68-SUM(AW58:AW61),0) -> 0
C63: Closing Balance | I63: =CaseData!G14 -> 500000 | J63: =SUM(J58:J62) -> 725812.56 | K63: =SUM(K58:K62) -> 949618.69 | L63: =SUM(L58:L62) -> 1175498.9 | M63: =SUM(M58:M62) -> 1416832.1 | N63: =SUM(N58:N62) -> 1683685.6 | O63: =SUM(O58:O62) -> 500000 | P63: =SUM(P58:P62) -> 500000 | Q63: =SUM(Q58:Q62) -> 500000 | ... AW63: =SUM(AW58:AW62) -> 0
C65: Interest Rate | H65: =CaseData!G16 -> 0.015 | J65: =$H65 -> 0.015 | K65: =$H65 -> 0.015 | L65: =$H65 -> 0.015 | M65: =$H65 -> 0.015 | N65: =$H65 -> 0.015 | O65: =$H65 -> 0.015 | P65: =$H65 -> 0.015 | Q65: =$H65 -> 0.015 | ... AW65: =$H65 -> 0.015
C66: Interest Income | J66: =J58*J65/4 -> 1875 | K66: =K58*K65/4 -> 2721.7971 | L66: =L58*L65/4 -> 3561.0701 | M66: =M58*M65/4 -> 4408.1208 | N66: =N58*N65/4 -> 5313.1204 | O66: =O58*O65/4 -> 6313.8208 | P66: =P58*P65/4 -> 1875 | Q66: =Q58*Q65/4 -> 1875 | ... AW66: =AW58*AW65/4 -> 0
C68: Minimum Balance | H68: =CaseData!G15 -> 500000 | J68: =IF(J38>0,$H68,0) -> 500000 | K68: =IF(K38>0,$H68,0) -> 500000 | L68: =IF(L38>0,$H68,0) -> 500000 | M68: =IF(M38>0,$H68,0) -> 500000 | N68: =IF(N38>0,$H68,0) -> 500000 | O68: =IF(O38>0,$H68,0) -> 500000 | P68: =IF(P38>0,$H68,0) -> 500000 | Q68: =IF(Q38>0,$H68,0) -> 500000 | ... AW68: =IF(AW38>0,$H68,0) -> 0
B71: Junior Facility
C72: Opening Balance | J72: =I76 -> 6000000 | K72: =J76 -> 6105000 | L72: =K76 -> 6211837.5 | M72: =L76 -> 6320544.7 | N72: =M76 -> 6431154.2 | O72: =N76 -> 6543699.4 | P72: =O76 -> 5219918.9 | Q72: =P76 -> 5085702.8 | ... AW72: =AV76 -> 150000
C73: Unmet Interest Owed | J73: =J83 -> 105000 | K73: =K83 -> 106837.5 | L73: =L83 -> 108707.16 | M73: =M83 -> 110609.53 | N73: =N83 -> 112545.2 | O73: =O83 -> 0 | P73: =P83 -> 0 | Q73: =Q83 -> 0 | ... AW73: =AW83 -> 0
C74: Scheduled Repayment | J74: =J28 -> 0 | K74: =K28 -> 0 | L74: =L28 -> 0 | M74: =M28 -> 0 | N74: =N28 -> 0 | O74: =O28 -> -150000 | P74: =P28 -> -134216.09 | Q74: =Q28 -> -150000 | ... AW74: =AW28 -> -150000
C75: Arrears Amount Owed Repayment | J75: =J97 -> 0 | K75: =K97 -> 0 | L75: =L97 -> 0 | M75: =M97 -> 0 | N75: =N97 -> 0 | O75: =O97 -> -1173780.5 | P75: =P97 -> 0 | Q75: =Q97 -> -41039.979 | ... AW75: =AW97 -> 0
C76: Closing Balance | I76: =CaseData!G19 -> 6000000 | J76: =SUM(J72:J75) -> 6105000 | K76: =SUM(K72:K75) -> 6211837.5 | L76: =SUM(L72:L75) -> 6320544.7 | M76: =SUM(M72:M75) -> 6431154.2 | N76: =SUM(N72:N75) -> 6543699.4 | O76: =SUM(O72:O75) -> 5219918.9 | P76: =SUM(P72:P75) -> 5085702.8 | Q76: =SUM(Q72:Q75) -> 4894662.8 | ... AW76: =SUM(AW72:AW75) -> 0
C78: Interest Rate | H78: =CaseData!G20 -> 0.07 | J78: =$H78 -> 0.07 | K78: =$H78 -> 0.07 | L78: =$H78 -> 0.07 | M78: =$H78 -> 0.07 | N78: =$H78 -> 0.07 | O78: =$H78 -> 0.07 | P78: =$H78 -> 0.07 | Q78: =$H78 -> 0.07 | ... AW78: =$H78 -> 0.07
C79: Interest Expense | J79: =J72*J78/4 -> 105000 | K79: =K72*K78/4 -> 106837.5 | L79: =L72*L78/4 -> 108707.16 | M79: =M72*M78/4 -> 110609.53 | N79: =N72*N78/4 -> 112545.2 | O79: =O72*O78/4 -> 114514.74 | P79: =P72*P78/4 -> 91348.58 | Q79: =Q72*Q78/4 -> 88999.799 | ... AW79: =AW72*AW78/4 -> 2625
C81: Funds Available for Jr. Debt Service | J81: =J23 -> 0 | K81: =K23 -> 0 | L81: =L23 -> 0 | M81: =M23 -> 0 | N81: =N23 -> 0 | O81: =O23 -> 1438295.3 | P81: =P23 -> 225564.67 | Q81: =Q23 -> 280039.78 | ... AW81: =AW23 -> 750009
C82: Cash Interest Paid | J82: =MIN(J79,J81) -> 0 | K82: =MIN(K79,K81) -> 0 | L82: =MIN(L79,L81) -> 0 | M82: =MIN(M79,M81) -> 0 | N82: =MIN(N79,N81) -> 0 | O82: =MIN(O79,O81) -> 114514.74 | P82: =MIN(P79,P81) -> 91348.58 | Q82: =MIN(Q79,Q81) -> 88999.799 | ... AW82: =MIN(AW79,AW81) -> 2625
C83: Unmet Interest Owed | J83: =J79-J82 -> 105000 | K83: =K79-K82 -> 106837.5 | L83: =L79-L82 -> 108707.16 | M83: =M79-M82 -> 110609.53 | N83: =N79-N82 -> 112545.2 | O83: =O79-O82 -> 0 | P83: =P79-P82 -> 0 | Q83: =Q79-Q82 -> 0 | ... AW83: =AW79-AW82 -> 0
C85: Scheduled Repayment | J85: =-INDEX(CaseData!$J$42:$J$81,MATCH(J$3,CaseData!$D$42:$D$81,0)) -> 150000 | K85: =-INDEX(CaseData!$J$42:$J$81,MATCH(K$3,CaseData!$D$42:$D$81,0)) -> 150000 | L85: =-INDEX(CaseData!$J$42:$J$81,MATCH(L$3,CaseData!$D$42:$D$81,0)) -> 150000 | M85: =-INDEX(CaseData!$J$42:$J$81,MATCH(M$3,CaseData!$D$42:$D$81,0)) -> 150000 | N85: =-INDEX(CaseData!$J$42:$J$81,MATCH(N$3,CaseData!$D$42:$D$81,0)) -> 150000 | O85: =-INDEX(CaseData!$J$42:$J$81,MATCH(O$3,CaseData!$D$42:$D$81,0)) -> 150000 | P85: =-INDEX(CaseData!$J$42:$J$81,MATCH(P$3,CaseData!$D$42:$D$81,0)) -> 150000 | Q85: =-INDEX(CaseData!$J$42:$J$81,MATCH(Q$3,CaseData!$D$42:$D$81,0)) -> 150000 | ... AW85: =-INDEX(CaseData!$J$42:$J$81,MATCH(AW$3,CaseData!$D$42:$D$81,0)) -> 150000
C87: Funds Available for Jr. Debt - Scheduled Repayments | J87: =J26 -> 0 | K87: =K26 -> 0 | L87: =L26 -> 0 | M87: =M26 -> 0 | N87: =N26 -> 0 | O87: =O26 -> 1323780.5 | P87: =P26 -> 134216.09 | Q87: =Q26 -> 191039.98 | ... AW87: =AW26 -> 747384
C88: Scheduled Repayment Paid | J88: =MIN(J85,J87) -> 0 | K88: =MIN(K85,K87) -> 0 | L88: =MIN(L85,L87) -> 0 | M88: =MIN(M85,M87) -> 0 | N88: =MIN(N85,N87) -> 0 | O88: =MIN(O85,O87) -> 150000 | P88: =MIN(P85,P87) -> 134216.09 | Q88: =MIN(Q85,Q87) -> 150000 | ... AW88: =MIN(AW85,AW87) -> 150000
C89: Unmet Scheduled Repayments | J89: =J85-J88 -> 150000 | K89: =K85-K88 -> 150000 | L89: =L85-L88 -> 150000 | M89: =M85-M88 -> 150000 | N89: =N85-N88 -> 150000 | O89: =O85-O88 -> 0 | P89: =P85-P88 -> 15783.913 | Q89: =Q85-Q88 -> 0 | ... AW89: =AW85-AW88 -> 0
C91: Arrears Amount Owed
D92: Funds Available for Jr. Debt - Arrears Amount Owed | J92: =J29 -> 0 | K92: =K29 -> 0 | L92: =L29 -> 0 | M92: =M29 -> 0 | N92: =N29 -> 0 | O92: =O29 -> 1173780.5 | P92: =P29 -> 0 | Q92: =Q29 -> 41039.979 | ... AW92: =AW29 -> 597384
D94: Opening Balance | J94: =I98 -> 0 | K94: =J98 -> 255000 | L94: =K98 -> 511837.5 | M94: =L98 -> 770544.66 | N94: =M98 -> 1031154.2 | O94: =N98 -> 1293699.4 | P94: =O98 -> 119918.86 | Q94: =P98 -> 135702.78 | ... AW94: =AV98 -> 0
D95: Unmet Interest Owed | J95: =J83 -> 105000 | K95: =K83 -> 106837.5 | L95: =L83 -> 108707.16 | M95: =M83 -> 110609.53 | N95: =N83 -> 112545.2 | O95: =O83 -> 0 | P95: =P83 -> 0 | Q95: =Q83 -> 0 | ... AW95: =AW83 -> 0
D96: Unmet Scheduled Repayments | J96: =J89 -> 150000 | K96: =K89 -> 150000 | L96: =L89 -> 150000 | M96: =M89 -> 150000 | N96: =N89 -> 150000 | O96: =O89 -> 0 | P96: =P89 -> 15783.913 | Q96: =Q89 -> 0 | ... AW96: =AW89 -> 0
D97: Repayment | J97: =-MIN(J92,SUM(J94:J96)) -> 0 | K97: =-MIN(K92,SUM(K94:K96)) -> 0 | L97: =-MIN(L92,SUM(L94:L96)) -> 0 | M97: =-MIN(M92,SUM(M94:M96)) -> 0 | N97: =-MIN(N92,SUM(N94:N96)) -> 0 | O97: =-MIN(O92,SUM(O94:O96)) -> -1173780.5 | P97: =-MIN(P92,SUM(P94:P96)) -> 0 | Q97: =-MIN(Q92,SUM(Q94:Q96)) -> -41039.979 | ... AW97: =-MIN(AW92,SUM(AW94:AW96)) -> 0
D98: Closing | I98: 0 | J98: =SUM(J94:J97) -> 255000 | K98: =SUM(K94:K97) -> 511837.5 | L98: =SUM(L94:L97) -> 770544.66 | M98: =SUM(M94:M97) -> 1031154.2 | N98: =SUM(N94:N97) -> 1293699.4 | O98: =SUM(O94:O97) -> 119918.86 | P98: =SUM(P94:P97) -> 135702.78 | Q98: =SUM(Q94:Q97) -> 94662.797 | ... AW98: =SUM(AW94:AW97) -> 0
C101: Answers
C103: C) | F103: Jr Debt | H103: 44286
H104: =INDEX($I$76:$AW$76,MATCH(H103,$I$3:$AW$3,0)) -> 4708550.5
G105: Base Case | H105: 4650000
G106: Case 2 | H106: 4741969.3
G107: Case 3 | H107: 4713427
G108: Case 4 | H108: 4650000
G109: Case 5 | H109: 5124765.9
G110: Case 6 | H110: 4708550.5
C113: D) | F113: First Lockup
H114: =IFERROR(INDEX($J$3:$AW$3,MATCH(1,$J$53:$AW$53,0)),"n.a.") -> 43555
G115: Base Case | H115: n.a.
G116: Case 2 | H116: n.a.
G117: Case 3 | H117: 43555
G118: Case 4 | H118: 44926
G119: Case 5 | H119: 44196
G120: Case 6 | H120: 43555
C122: E) | F122: Min DSRA to 2025
H123: =MIN(J63:AK63) -> 7658.0775
G124: Base Case | H124: 500000
G125: Case 2 | H125: 500000
G126: Case 3 | H126: 500000
G127: Case 4 | H127: 500000
G128: Case 5 | H128: 321664.75
G129: Case 6 | H129: 7658.0775
C131: F) | F131: Total Jr. Debt Int
H132: =SUM(J79:AW79) -> 2701841.3
G133: Base Case | H133: 2152500
G134: Case 2 | H134: 2155333.4
G135: Case 3 | H135: 2302600.7
G136: Case 4 | H136: 2325058.3
...
