Workbook
Name company: CaseData!$H$42
Name end_date: CaseData!$H$38
Name periods: CaseData!$H$37
Name scenarios: CaseData!$E$45:$E$50
Name selector: CaseData!$H$45
Name start_date: CaseData!$H$35
Name topic: "CFM Topic: " & CaseData!$H$43

Sheet Debt
A1: {=company} -> Unicord Construction
A2: {=topic} -> CFM Topic: Debt | J2: {=_xlfn.ANCHORARRAY( J11)} -> 44927 | K2: 45017 | L2: 45108 | M2: 45200 | N2: 45292 | O2: 45383 | P2: 45474 | Q2: 45566 | R2: 45658 | S2: 45748 | T2: 45839 | U2: 45931 | V2: 46023 | W2: 46113 | X2: 46204 | Y2: 46296 | Z2: 46388 | AA2: 46478 | AB2: 46569 | AC2: 46661 | AD2: 46753 | AE2: 46844 | AF2: 46935 | AG2: 47027 | AH2: 47119 | AI2: 47209 | AJ2: 47300 | AK2: 47392 | AL2: 47484 | AM2: 47574 | AN2: 47665 | AO2: 47757 | AP2: 47849 | AQ2: 47939 | AR2: 48030 | AS2: 48122 | AT2: 48214 | AU2: 48305 | AV2: 48396 | AW2: 48488
A3: LIVE SCENARIO | F3: 1 | G3: Unit | H3: Total | J3: {=_xlfn.ANCHORARRAY( J12)} -> 45016 | K3: 45107 | L3: 45199 | M3: 45291 | N3: 45382 | O3: 45473 | P3: 45565 | Q3: 45657 | R3: 45747 | S3: 45838 | T3: 45930 | U3: 46022 | V3: 46112 | W3: 46203 | X3: 46295 | Y3: 46387 | Z3: 46477 | AA3: 46568 | AB3: 46660 | AC3: 46752 | AD3: 46843 | AE3: 46934 | AF3: 47026 | AG3: 47118 | AH3: 47208 | AI3: 47299 | AJ3: 47391 | AK3: 47483 | AL3: 47573 | AM3: 47664 | AN3: 47756 | AO3: 47848 | AP3: 47938 | AQ3: 48029 | AR3: 48121 | AS3: 48213 | AT3: 48304 | AU3: 48395 | AV3: 48487 | AW3: 48579
A5: Model timeline
E7: Model start date | F7: =start_date -> 44926
E8: Model end date | F8: =end_date -> 48579
E9: Number of quarters | F9: =periods -> 40
E11: Model period beginning | G11: date | J11: {=EDATE( start_date + 1, _xlfn.SEQUENCE( 1, periods, 0, 3 ) )} -> 44927 | K11: 45017 | L11: 45108 | M11: 45200 | N11: 45292 | O11: 45383 | P11: 45474 | Q11: 45566 | R11: 45658 | S11: 45748 | T11: 45839 | U11: 45931 | V11: 46023 | W11: 46113 | X11: 46204 | Y11: 46296 | Z11: 46388 | AA11: 46478 | AB11: 46569 | AC11: 46661 | AD11: 46753 | AE11: 46844 | AF11: 46935 | AG11: 47027 | AH11: 47119 | AI11: 47209 | AJ11: 47300 | AK11: 47392 | AL11: 47484 | AM11: 47574 | AN11: 47665 | AO11: 47757 | AP11: 47849 | AQ11: 47939 | AR11: 48030 | AS11: 48122 | AT11: 48214 | AU11: 48305 | AV11: 48396 | AW11: 48488
E12: Model period ending | G12: date | J12: {=EOMONTH( start_date, _xlfn.SEQUENCE( 1, periods, 3, 3 ) )} -> 45016 | K12: 45107 | L12: 45199 | M12: 45291 | N12: 45382 | O12: 45473 | P12: 45565 | Q12: 45657 | R12: 45747 | S12: 45838 | T12: 45930 | U12: 46022 | V12: 46112 | W12: 46203 | X12: 46295 | Y12: 46387 | Z12: 46477 | AA12: 46568 | AB12: 46660 | AC12: 46752 | AD12: 46843 | AE12: 46934 | AF12: 47026 | AG12: 47118 | AH12: 47208 | AI12: 47299 | AJ12: 47391 | AK12: 47483 | AL12: 47573 | AM12: 47664 | AN12: 47756 | AO12: 47848 | AP12: 47938 | AQ12: 48029 | AR12: 48121 | AS12: 48213 | AT12: 48304 | AU12: 48395 | AV12: 48487 | AW12: 48579
E14: Model period counter | G14: counter | H14: {=_xlfn.BYROW(_xlfn.ANCHORARRAY( J14), _xleta.SUM )} -> 40 | J14: {=IF(_xlfn.ANCHORARRAY( J12), I14 + 1, 0 )} -> 1 | K14: 1 | L14: 1 | M14: 1 | N14: 1 | O14: 1 | P14: 1 | Q14: 1 | R14: 1 | S14: 1 | T14: 1 | U14: 1 | V14: 1 | W14: 1 | X14: 1 | Y14: 1 | Z14: 1 | AA14: 1 | AB14: 1 | AC14: 1 | AD14: 1 | AE14: 1 | AF14: 1 | AG14: 1 | AH14: 1 | AI14: 1 | AJ14: 1 | AK14: 1 | AL14: 1 | AM14: 1 | AN14: 1 | AO14: 1 | AP14: 1 | AQ14: 1 | AR14: 1 | AS14: 1 | AT14: 1 | AU14: 1 | AV14: 1 | AW14: 1
E15: Model first period flag | G15: flag | H15: {=_xlfn.BYROW(_xlfn.ANCHORARRAY( J15), _xleta.SUM )} -> 1 | J15: {=IF(_xlfn.ANCHORARRAY( J2) - 1 = start_date, 1, 0 )} -> 1 | K15: 0 | L15: 0 | M15: 0 | N15: 0 | O15: 0 | P15: 0 | Q15: 0 | R15: 0 | S15: 0 | T15: 0 | U15: 0 | V15: 0 | W15: 0 | X15: 0 | Y15: 0 | Z15: 0 | AA15: 0 | AB15: 0 | AC15: 0 | AD15: 0 | AE15: 0 | AF15: 0 | AG15: 0 | AH15: 0 | AI15: 0 | AJ15: 0 | AK15: 0 | AL15: 0 | AM15: 0 | AN15: 0 | AO15: 0 | AP15: 0 | AQ15: 0 | AR15: 0 | AS15: 0 | AT15: 0 | AU15: 0 | AV15: 0 | AW15: 0
E16: Model last period flag | G16: flag | H16: {=_xlfn.BYROW(_xlfn.ANCHORARRAY( J16), _xleta.SUM )} -> 1 | J16: {=IF(_xlfn.ANCHORARRAY( J12) = end_date, 1, 0 )} -> 0 | K16: 0 | L16: 0 | M16: 0 | N16: 0 | O16: 0 | P16: 0 | Q16: 0 | R16: 0 | S16: 0 | T16: 0 | U16: 0 | V16: 0 | W16: 0 | X16: 0 | Y16: 0 | Z16: 0 | AA16: 0 | AB16: 0 | AC16: 0 | AD16: 0 | AE16: 0 | AF16: 0 | AG16: 0 | AH16: 0 | AI16: 0 | AJ16: 0 | AK16: 0 | AL16: 0 | AM16: 0 | AN16: 0 | AO16: 0 | AP16: 0 | AQ16: 0 | AR16: 0 | AS16: 0 | AT16: 0 | AU16: 0 | AV16: 0 | AW16: 1
E18: Mortgage amortization quarters flag | G18: flag | H18: =SUM( J18:AW18) -> 32 | J18: =IF( SUM( $J14:J14 ) <= $F$97, 1, 0 ) -> 1 | K18: =IF( SUM( $J14:K14 ) <= $F$97, 1, 0 ) -> 1 | L18: =IF( SUM( $J14:L14 ) <= $F$97, 1, 0 ) -> 1 | M18: =IF( SUM( $J14:M14 ) <= $F$97, 1, 0 ) -> 1 | N18: =IF( SUM( $J14:N14 ) <= $F$97, 1, 0 ) -> 1 | O18: =IF( SUM( $J14:O14 ) <= $F$97, 1, 0 ) -> 1 | P18: =IF( SUM( $J14:P14 ) <= $F$97, 1, 0 ) -> 1 | Q18: =IF( SUM( $J14:Q14 ) <= $F$97, 1, 0 ) -> 1 | ... AW18: =IF( SUM( $J14:AW14 ) <= $F$97, 1, 0 ) -> 0
E19: Junior Debt amortization quarters flag | G19: flag | H19: =SUM( J19:AW19) -> 40 | J19: =IF( SUM( $J15:J15 ) <= $F$120, 1, 0 ) -> 1 | K19: =IF( SUM( $J15:K15 ) <= $F$120, 1, 0 ) -> 1 | L19: =IF( SUM( $J15:L15 ) <= $F$120, 1, 0 ) -> 1 | M19: =IF( SUM( $J15:M15 ) <= $F$120, 1, 0 ) -> 1 | N19: =IF( SUM( $J15:N15 ) <= $F$120, 1, 0 ) -> 1 | O19: =IF( SUM( $J15:O15 ) <= $F$120, 1, 0 ) -> 1 | P19: =IF( SUM( $J15:P15 ) <= $F$120, 1, 0 ) -> 1 | Q19: =IF( SUM( $J15:Q15 ) <= $F$120, 1, 0 ) -> 1 | ... AW19: =IF( SUM( $J15:AW15 ) <= $F$120, 1, 0 ) -> 1
A21: Cashflow waterfall
E23: EBIDTA | G23: USD | H23: =SUM(_xlfn.ANCHORARRAY( J23)) -> 41939007 | J23: {=INDEX( CaseData!$M$8:$R$47, MATCH(_xlfn.ANCHORARRAY( Debt!J3), CaseData!$K$8:$K$47, 0 ), MATCH( selector, CaseData!$M$5:$R$5, 0 ) )} -> 1019082 | K23: 1008045 | L23: 998560.5 | M23: 995307 | N23: 996799.5 | O23: 975211.5 | P23: 974340 | Q23: 967587 | R23: 1015347 | S23: 963435 | T23: 979111.5 | U23: 965946 | V23: 963438 | W23: 1007662.5 | X23: 1011898.5 | Y23: 1027911 | Z23: 990430.5 | AA23: 1015789.5 | AB23: 1030960.5 | AC23: 1048911 | AD23: 1078854 | AE23: 1039989 | AF23: 1069714.5 | AG23: 1047547.5 | AH23: 1049193 | AI23: 1059516 | AJ23: 1107811.5 | AK23: 1059664.5 | AL23: 1045116 | AM23: 1071954 | AN23: 1133484 | AO23: 1125522 | AP23: 1110844.5 | AQ23: 1096879.5 | AR23: 1133016 | AS23: 1153189.5 | AT23: 1146522 | AU23: 1138092 | AV23: 1157863.5 | AW23: 1158460.5
E24: =E$79 -> Debt Service Reserve Account interest income | G24: =G$79 -> USD | H24: =H$79 -> 60000 | I24: =I$79 -> 0 | J24: =J$79 -> 1875 | K24: =K$79 -> 1875 | L24: =L$79 -> 1875 | M24: =M$79 -> 1875 | N24: =N$79 -> 1875 | ... AW24: =AW$79 -> 0
E25: Funds available for Mortgage repayment | G25: USD | J25: =SUM(J23:J24) -> 1020957 | K25: =SUM(K23:K24) -> 1009920 | L25: =SUM(L23:L24) -> 1000435.5 | M25: =SUM(M23:M24) -> 997182 | N25: =SUM(N23:N24) -> 998674.5 | O25: =SUM(O23:O24) -> 977086.5 | P25: =SUM(P23:P24) -> 976215 | Q25: =SUM(Q23:Q24) -> 969462 | ... AW25: =SUM(AW23:AW24) -> 1158460.5
E27: Mortgage interest expenses | G27: USD | J27: =J$93 * - 1 -> -93750 | K27: =K$93 * - 1 -> -91094.407 | L27: =L$93 * - 1 -> -88422.216 | M27: =M$93 * - 1 -> -85733.324 | N27: =N$93 * - 1 -> -83027.626 | O27: =O$93 * - 1 -> -80305.018 | P27: =P$93 * - 1 -> -77565.394 | Q27: =Q$93 * - 1 -> -74808.647 | ... AW27: =AW$93 * - 1 -> 0
E28: =E$99 -> Mortage principal payment | G28: =G$99 -> USD | I28: =I$99 -> 0 | J28: =J$99 * - 1 -> -424894.93 | K28: =K$99 * - 1 -> -427550.52 | L28: =L$99 * - 1 -> -430222.71 | M28: =M$99 * - 1 -> -432911.61 | N28: =N$99 * - 1 -> -435617.3 | O28: =O$99 * - 1 -> -438339.91 | P28: =P$99 * - 1 -> -441079.54 | Q28: =Q$99 * - 1 -> -443836.28 | ... AW28: =AW$99 * - 1 -> 0
E29: Funds available after Mortgage service | G29: USD | J29: =SUM(J25:J28) -> 502312.07 | K29: =SUM(K25:K28) -> 491275.07 | L29: =SUM(L25:L28) -> 481790.57 | M29: =SUM(M25:M28) -> 478537.07 | N29: =SUM(N25:N28) -> 480029.57 | O29: =SUM(O25:O28) -> 458441.57 | P29: =SUM(P25:P28) -> 457570.07 | Q29: =SUM(Q25:Q28) -> 450817.07 | ... AW29: =SUM(AW25:AW28) -> 1158460.5
E31: Withdrawal from DSRA to cover for Senior Debt repayment shortfall | G31: USD | J31: =J$68 * - 1 -> 0 | K31: =K$68 * - 1 -> 0 | L31: =L$68 * - 1 -> 0 | M31: =M$68 * - 1 -> 0 | N31: =N$68 * - 1 -> 0 | O31: =O$68 * - 1 -> 0 | P31: =P$68 * - 1 -> 0 | Q31: =Q$68 * - 1 -> 0 | ... AW31: =AW$68 * - 1 -> 0
E32: =E$69 -> Top Up of DSRA to keep required minimum balance | G32: =G$69 -> USD | I32: =I$69 -> 0 | J32: =J$69 * - 1 -> 0 | K32: =K$69 * - 1 -> 0 | L32: =L$69 * - 1 -> 0 | M32: =M$69 * - 1 -> 0 | N32: =N$69 * - 1 -> 0 | O32: =O$69 * - 1 -> 0 | P32: =P$69 * - 1 -> 0 | Q32: =Q$69 * - 1 -> 0 | ... AW32: =AW$69 * - 1 -> 0
E33: =E$70 -> DSRA Additions in Lockup | G33: =G$70 -> USD | I33: =I$70 -> 0 | J33: =J$70 * - 1 -> 0 | K33: =K$70 * - 1 -> 0 | L33: =L$70 * - 1 -> 0 | M33: =M$70 * - 1 -> 0 | N33: =N$70 * - 1 -> 0 | O33: =O$70 * - 1 -> 0 | P33: =P$70 * - 1 -> 0 | Q33: =Q$70 * - 1 -> 0 | ... AW33: =AW$70 * - 1 -> 0
E34: Release from DSRA | G34: =G$70 -> USD | J34: =J71 * - 1 -> 0 | K34: =K71 * - 1 -> 0 | L34: =L71 * - 1 -> 0 | M34: =M71 * - 1 -> 0 | N34: =N71 * - 1 -> 0 | O34: =O71 * - 1 -> 0 | P34: =P71 * - 1 -> 0 | Q34: =Q71 * - 1 -> 0 | ... AW34: =AW71 * - 1 -> 0
E35: =E$72 -> Liquidation of DSRA | G35: =G$72 -> USD | I35: =I$72 -> 0 | J35: =J$72 * - 1 -> 0 | K35: =K$72 * - 1 -> 0 | L35: =L$72 * - 1 -> 0 | M35: =M$72 * - 1 -> 0 | N35: =N$72 * - 1 -> 0 | O35: =O$72 * - 1 -> 0 | P35: =P$72 * - 1 -> 0 | Q35: =Q$72 * - 1 -> 0 | ... AW35: =AW$72 * - 1 -> 0
E36: Funds available for Junior Debt service | G36: USD | J36: =SUM( J29:J35) -> 502312.07 | K36: =SUM( K29:K35) -> 491275.07 | L36: =SUM( L29:L35) -> 481790.57 | M36: =SUM( M29:M35) -> 478537.07 | N36: =SUM( N29:N35) -> 480029.57 | O36: =SUM( O29:O35) -> 458441.57 | P36: =SUM( P29:P35) -> 457570.07 | Q36: =SUM( Q29:Q35) -> 450817.07 | ... AW36: =SUM( AW29:AW35) -> 1158460.5
E38: Junior Debt interest paid | G38: USD | J38: =J$116 -> 0 | K38: =K$116 -> 0 | L38: =L$116 -> 0 | M38: =M$116 -> 0 | N38: =N$116 -> 0 | O38: =O$116 -> 0 | P38: =P$116 -> 0 | Q38: =Q$116 -> 0 | ... AW38: =AW$116 -> 0
E39: Funds Available for Junior Debt Scheduled Repayments | G39: USD | J39: =SUM(J36:J38) -> 502312.07 | K39: =SUM(K36:K38) -> 491275.07 | L39: =SUM(L36:L38) -> 481790.57 | M39: =SUM(M36:M38) -> 478537.07 | N39: =SUM(N36:N38) -> 480029.57 | O39: =SUM(O36:O38) -> 458441.57 | P39: =SUM(P36:P38) -> 457570.07 | Q39: =SUM(Q36:Q38) -> 450817.07 | ... AW39: =SUM(AW36:AW38) -> 1158460.5
E41: =E$126 -> Junior Debt amortization paid | G41: =G$126 -> USD | I41: =I$126 -> 0 | J41: =J$126 * - 1 -> -225000 | K41: =K$126 * - 1 -> -225000 | L41: =L$126 * - 1 -> -225000 | M41: =M$126 * - 1 -> -225000 | N41: =N$126 * - 1 -> -225000 | O41: =O$126 * - 1 -> -225000 | P41: =P$126 * - 1 -> -225000 | Q41: =Q$126 * - 1 -> -225000 | ... AW41: =AW$126 * - 1 -> -225000
E42: Funds Available for Junior Debt Arrears Amount Owed | G42: USD | J42: =SUM(J39:J41) -> 277312.07 | K42: =SUM(K39:K41) -> 266275.07 | L42: =SUM(L39:L41) -> 256790.57 | M42: =SUM(M39:M41) -> 253537.07 | N42: =SUM(N39:N41) -> 255029.57 | O42: =SUM(O39:O41) -> 233441.57 | P42: =SUM(P39:P41) -> 232570.07 | Q42: =SUM(Q39:Q41) -> 225817.07 | ... AW42: =SUM(AW39:AW41) -> 933460.5
E44: =E$135 -> Repayment of arrears owed | G44: =G$135 -> USD | I44: =I$135 -> 0 | J44: =J$135 -> 0 | K44: =K$135 -> 0 | L44: =L$135 -> 0 | M44: =M$135 -> 0 | N44: =N$135 -> 0 | O44: =O$135 -> 0 | P44: =P$135 -> 0 | ... AW44: =AW$135 -> 0
E45: Funds distributed to Equity | G45: USD | J45: =SUM(J42:J44) -> 277312.07 | K45: =SUM(K42:K44) -> 266275.07 | L45: =SUM(L42:L44) -> 256790.57 | M45: =SUM(M42:M44) -> 253537.07 | N45: =SUM(N42:N44) -> 255029.57 | O45: =SUM(O42:O44) -> 233441.57 | P45: =SUM(P42:P44) -> 232570.07 | Q45: =SUM(Q42:Q44) -> 225817.07 | ... AW45: =SUM(AW42:AW44) -> 933460.5
A48: DSCR (Last Twelve Months)
E50: =CaseData!C$9 -> Mortgage DSCR Lock up trigger | F50: =CaseData!H$9 -> 1.7 | G50: multiple
E52: EBIDTA | G52: USD | J52: =SUM($J23:J23) -> 1019082 | K52: =SUM($J23:K23) -> 2027127 | L52: =SUM($J23:L23) -> 3025687.5 | M52: =SUM($J23:M23) -> 4020994.5 | N52: =SUM( K23:N23) -> 3998712 | O52: =SUM( L23:O23) -> 3965878.5 | P52: =SUM( M23:P23) -> 3941658 | Q52: =SUM( N23:Q23) -> 3913938 | R52: =SUM( O23:R23) -> 3932485.5 | S52: =SUM( P23:S23) -> 3920709 | T52: =SUM( Q23:T23) -> 3925480.5 | U52: =SUM( R23:U23) -> 3923839.5 | ... AW52: =SUM( AT23:AW23) -> 4600938
E53: =E$79 -> Debt Service Reserve Account interest income | G53: =G$79 -> USD | H53: =H$79 -> 60000 | I53: =I$79 -> 0 | J53: =SUM( $J79:J79 ) -> 1875 | K53: =SUM( $J79:K79 ) -> 3750 | L53: =SUM( $J79:L79 ) -> 5625 | M53: =SUM( $J79:M79 ) -> 7500 | N53: =SUM( K79:N79) -> 7500 | O53: =SUM( L79:O79) -> 7500 | P53: =SUM( M79:P79) -> 7500 | Q53: =SUM( N79:Q79) -> 7500 | R53: =SUM( O79:R79) -> 7500 | S53: =SUM( P79:S79) -> 7500 | T53: =SUM( Q79:T79) -> 7500 | U53: =SUM( R79:U79) -> 7500 | ... AW53: =SUM( AT79:AW79) -> 0
E54: =E$93 -> Mortagage interest expenses | F54: =F$93 -> 0 | G54: =G$93 -> USD | H54: =H$93 -> 1596637.7 | I54: =I$93 -> 0 | J54: =SUM( $J93:J93 ) -> 93750 | K54: =SUM( $J93:K93 ) -> 184844.41 | L54: =SUM( $J93:L93 ) -> 273266.62 | M54: =SUM( $J93:M93 ) -> 358999.95 | N54: =SUM( K93:N93) -> 348277.57 | O54: =SUM( L93:O93) -> 337488.18 | P54: =SUM( M93:P93) -> 326631.36 | Q54: =SUM( N93:Q93) -> 315706.69 | R54: =SUM( O93:R93) -> 304713.73 | S54: =SUM( P93:S93) -> 293652.07 | T54: =SUM( Q93:T93) -> 282521.27 | U54: =SUM( R93:U93) -> 271320.9 | ... AW54: =SUM( AT93:AW93) -> 0
E55: =E$99 -> Mortage principal payment | F55: =F$99 -> 0 | G55: =G$99 -> USD | H55: =H$99 -> 15000000 | I55: =I$99 -> 0 | J55: =SUM( $J99:J99) -> 424894.93 | K55: =SUM( $J99:K99) -> 852445.45 | L55: =SUM( $J99:L99) -> 1282668.2 | M55: =SUM( $J99:M99) -> 1715579.8 | N55: =SUM( K99:N99) -> 1726302.1 | O55: =SUM( L99:O99) -> 1737091.5 | P55: =SUM( M99:P99) -> 1747948.4 | Q55: =SUM( N99:Q99) -> 1758873 | R55: =SUM( O99:R99) -> 1769866 | S55: =SUM( P99:S99) -> 1780927.6 | T55: =SUM( Q99:T99) -> 1792058.4 | U55: =SUM( R99:U99) -> 1803258.8 | ... AW55: =SUM( AT99:AW99) -> 0
E57: DSCR LTM | G57: factor | J57: =IFERROR( SUM( J52, J53 ) / SUM( J54, J55 ), "n/a" ) -> 1.9685086 | K57: =IFERROR( SUM( K52, K53 ) / SUM( K54, K55 ), "n/a" ) -> 1.9578684 | L57: =IFERROR( SUM( L52, L53 ) / SUM( L54, L55 ), "n/a" ) -> 1.9482259 | M57: =IFERROR( SUM( M52, M53 ) / SUM( M54, M55 ), "n/a" ) -> 1.9418364 | N57: =IFERROR( SUM( N52, N53 ) / SUM( N54, N55 ), "n/a" ) -> 1.9310957 | O57: =IFERROR( SUM( O52, O53 ) / SUM( O54, O55 ), "n/a" ) -> 1.9152691 | P57: =IFERROR( SUM( P52, P53 ) / SUM( P54, P55 ), "n/a" ) -> 1.9035942 | Q57: =IFERROR( SUM( Q52, Q53 ) / SUM( Q54, Q55 ), "n/a" ) -> 1.8902325 | ... AW57: =IFERROR( SUM( AW52, AW53 ) / SUM( AW54, AW55 ), "n/a" ) -> n/a
E58: Lock up trigger flag | G58: flag | J58: =IF( ( J$86 > 0 ) * ( $F$50 > J$57 ), 1, 0 ) -> 0 | K58: =IF( ( K$86 > 0 ) * ( $F$50 > K$57 ), 1, 0 ) -> 0 | L58: =IF( ( L$86 > 0 ) * ( $F$50 > L$57 ), 1, 0 ) -> 0 | M58: =IF( ( M$86 > 0 ) * ( $F$50 > M$57 ), 1, 0 ) -> 0 | N58: =IF( ( N$86 > 0 ) * ( $F$50 > N$57 ), 1, 0 ) -> 0 | O58: =IF( ( O$86 > 0 ) * ( $F$50 > O$57 ), 1, 0 ) -> 0 | P58: =IF( ( P$86 > 0 ) * ( $F$50 > P$57 ), 1, 0 ) -> 0 | Q58: =IF( ( Q$86 > 0 ) * ( $F$50 > Q$57 ), 1, 0 ) -> 0 | ... AW58: =IF( ( AW$86 > 0 ) * ( $F$50 > AW$57 ), 1, 0 ) -> 0
E59: Release trigger | G59: flag | J59: =MAX( I58:J58 ) -> 0 | K59: =MAX( J58:K58 ) -> 0 | L59: =MAX( K58:L58 ) -> 0 | M59: =MAX( L58:M58 ) -> 0 | N59: =MAX( M58:N58 ) -> 0 | O59: =MAX( N58:O58 ) -> 0 | P59: =MAX( O58:P58 ) -> 0 | Q59: =MAX( P58:Q58 ) -> 0 | ... AW59: =MAX( AV58:AW58 ) -> 0
A61: Debt Service Reserve Account
E63: =CaseData!C$17 -> Initial balance at project start (already funded) | F63: =CaseData!H$17 -> 750000 | G63: USD
E64: =CaseData!C$18 -> Required minimum balance during term of Mortgage Facility | F64: =CaseData!H$18 -> 750000 | G64: USD
E67: Debt Service Reserve Account Debt opening balance | G67: USD | J67: =I$73 -> 750000 | K67: =J$73 -> 750000 | L67: =K$73 -> 750000 | M67: =L$73 -> 750000 | N67: =M$73 -> 750000 | O67: =N$73 -> 750000 | P67: =O$73 -> 750000 | Q67: =P$73 -> 750000 | ... AW67: =AV$73 -> 0
E68: Withdrawal from DSRA to cover for Mortgage repayment shortfall | G68: USD | J68: =J$18 * MIN( 0, J$29 ) -> 0 | K68: =K$18 * MIN( 0, K$29 ) -> 0 | L68: =L$18 * MIN( 0, L$29 ) -> 0 | M68: =M$18 * MIN( 0, M$29 ) -> 0 | N68: =N$18 * MIN( 0, N$29 ) -> 0 | O68: =O$18 * MIN( 0, O$29 ) -> 0 | P68: =P$18 * MIN( 0, P$29 ) -> 0 | Q68: =Q$18 * MIN( 0, Q$29 ) -> 0 | ... AW68: =AW$18 * MIN( 0, AW$29 ) -> 0
E69: Top Up of DSRA to keep required minimum balance | G69: USD | J69: =J$18 * MAX( MIN( J$29, $F$64 - SUM( J67:J68 ) ), 0 ) -> 0 | K69: =K$18 * MAX( MIN( K$29, $F$64 - SUM( K67:K68 ) ), 0 ) -> 0 | L69: =L$18 * MAX( MIN( L$29, $F$64 - SUM( L67:L68 ) ), 0 ) -> 0 | M69: =M$18 * MAX( MIN( M$29, $F$64 - SUM( M67:M68 ) ), 0 ) -> 0 | N69: =N$18 * MAX( MIN( N$29, $F$64 - SUM( N67:N68 ) ), 0 ) -> 0 | O69: =O$18 * MAX( MIN( O$29, $F$64 - SUM( O67:O68 ) ), 0 ) -> 0 | P69: =P$18 * MAX( MIN( P$29, $F$64 - SUM( P67:P68 ) ), 0 ) -> 0 | Q69: =Q$18 * MAX( MIN( Q$29, $F$64 - SUM( Q67:Q68 ) ), 0 ) -> 0 | ... AW69: =AW$18 * MAX( MIN( AW$29, $F$64 - SUM( AW67:AW68 ) ), 0 ) -> 0
E70: DSRA Additions in Lockup | G70: USD | I70: 0 | J70: =J$18 * IF( J$59 = 1, SUM( J29:J32 ), 0 ) -> 0 | K70: =K$18 * IF( K$59 = 1, SUM( K29:K32 ), 0 ) -> 0 | L70: =L$18 * IF( L$59 = 1, SUM( L29:L32 ), 0 ) -> 0 | M70: =M$18 * IF( M$59 = 1, SUM( M29:M32 ), 0 ) -> 0 | N70: =N$18 * IF( N$59 = 1, SUM( N29:N32 ), 0 ) -> 0 | O70: =O$18 * IF( O$59 = 1, SUM( O29:O32 ), 0 ) -> 0 | P70: =P$18 * IF( P$59 = 1, SUM( P29:P32 ), 0 ) -> 0 | Q70: =Q$18 * IF( Q$59 = 1, SUM( Q29:Q32 ), 0 ) -> 0 | ... AW70: =AW$18 * IF( AW$59 = 1, SUM( AW29:AW32 ), 0 ) -> 0
E71: Release from DSRA | G71: USD | J71: =IF( J$59 = 0, $F$64 - SUM( J67:J70 ), 0 ) -> 0 | K71: =IF( K$59 = 0, $F$64 - SUM( K67:K70 ), 0 ) -> 0 | L71: =IF( L$59 = 0, $F$64 - SUM( L67:L70 ), 0 ) -> 0 | M71: =IF( M$59 = 0, $F$64 - SUM( M67:M70 ), 0 ) -> 0 | N71: =IF( N$59 = 0, $F$64 - SUM( N67:N70 ), 0 ) -> 0 | O71: =IF( O$59 = 0, $F$64 - SUM( O67:O70 ), 0 ) -> 0 | P71: =IF( P$59 = 0, $F$64 - SUM( P67:P70 ), 0 ) -> 0 | Q71: =IF( Q$59 = 0, $F$64 - SUM( Q67:Q70 ), 0 ) -> 0 | ... AD71: =IF( AD$59 = 0, $F$64 - SUM( AD67:AD70 ), 0 ) -> 0
E72: Liquidation of DSRA | G72: USD | J72: =IF( J$88 = 0, - SUM( J67:J69 ), 0 ) -> 0 | K72: =IF( K$88 = 0, - SUM( K67:K69 ), 0 ) -> 0 | L72: =IF( L$88 = 0, - SUM( L67:L69 ), 0 ) -> 0 | M72: =IF( M$88 = 0, - SUM( M67:M69 ), 0 ) -> 0 | N72: =IF( N$88 = 0, - SUM( N67:N69 ), 0 ) -> 0 | O72: =IF( O$88 = 0, - SUM( O67:O69 ), 0 ) -> 0 | P72: =IF( P$88 = 0, - SUM( P67:P69 ), 0 ) -> 0 | Q72: =IF( Q$88 = 0, - SUM( Q67:Q69 ), 0 ) -> 0 | ... AW72: =IF( AW$88 = 0, - SUM( AW67:AW69 ), 0 ) -> 0
E73: Debt Service Reserve Account Debt | G73: USD | I73: =F63 -> 750000 | J73: =SUM(J67:J72 ) -> 750000 | K73: =SUM(K67:K72 ) -> 750000 | L73: =SUM(L67:L72 ) -> 750000 | M73: =SUM(M67:M72 ) -> 750000 | N73: =SUM(N67:N72 ) -> 750000 | O73: =SUM(O67:O72 ) -> 750000 | P73: =SUM(P67:P72 ) -> 750000 | Q73: =SUM(Q67:Q72 ) -> 750000 | ... AW73: =SUM(AW67:AW72 ) -> 0
D76: Debt Service Reserve Account interest income
E77: =CaseData!C$19 -> Cash interest rate earned on account balance | F77: =CaseData!H$19 -> 0.01 | G77: % p.a.
E78: Quarterly cash interest rate | F78: =F77 / 4 -> 0.0025 | G78: %
E79: Debt Service Reserve Account interest income | G79: USD | H79: =SUM( J79:AW79 ) -> 60000 | J79: =$F$78 * J$67 -> 1875 | K79: =$F$78 * K$67 -> 1875 | L79: =$F$78 * L$67 -> 1875 | M79: =$F$78 * M$67 -> 1875 | N79: =$F$78 * N$67 -> 1875 | O79: =$F$78 * O$67 -> 1875 | P79: =$F$78 * P$67 -> 1875 | Q79: =$F$78 * Q$67 -> 1875 | ... AW79: =$F$78 * AW$67 -> 0
A82: Mortgage
E84: Mortgage balance at model start date | F84: =CaseData!$H$4 -> 15000000 | G84: USD
E86: Mortgage opening balance | G86: USD | J86: =I$88 -> 15000000 | K86: =J$88 -> 14575105 | L86: =K$88 -> 14147555 | M86: =L$88 -> 13717332 | N86: =M$88 -> 13284420 | O86: =N$88 -> 12848803 | P86: =O$88 -> 12410463 | Q86: =P$88 -> 11969383 | ... AW86: =AV$88 -> 0
E87: Mortgage amortization | G87: USD | J87: =J$99 * - 1 -> -424894.93 | K87: =K$99 * - 1 -> -427550.52 | L87: =L$99 * - 1 -> -430222.71 | M87: =M$99 * - 1 -> -432911.61 | N87: =N$99 * - 1 -> -435617.3 | O87: =O$99 * - 1 -> -438339.91 | P87: =P$99 * - 1 -> -441079.54 | Q87: =Q$99 * - 1 -> -443836.28 | ... AW87: =AW$99 * - 1 -> 0
E88: Mortgage | G88: USD | I88: =$F$84 -> 15000000 | J88: =SUM(J86:J87) -> 14575105 | K88: =SUM(K86:K87) -> 14147555 | L88: =SUM(L86:L87) -> 13717332 | M88: =SUM(M86:M87) -> 13284420 | N88: =SUM(N86:N87) -> 12848803 | O88: =SUM(O86:O87) -> 12410463 | P88: =SUM(P86:P87) -> 11969383 | Q88: =SUM(Q86:Q87) -> 11525547 | ... AW88: =SUM(AW86:AW87) -> 0
D90: Interest expenses
E91: =CaseData!C$5 -> Annual cash interest rate | F91: =CaseData!H$5 -> 0.025 | G91: % p.a.
E92: Quarterly cash intereest rate | F92: =F91 / 4 -> 0.00625 | G92: %
E93: Mortagage interest expenses | G93: USD | H93: =SUM( J93:AW93) -> 1596637.7 | J93: =$F$92 * J$86 -> 93750 | K93: =$F$92 * K$86 -> 91094.407 | L93: =$F$92 * L$86 -> 88422.216 | M93: =$F$92 * M$86 -> 85733.324 | N93: =$F$92 * N$86 -> 83027.626 | O93: =$F$92 * O$86 -> 80305.018 | P93: =$F$92 * P$86 -> 77565.394 | Q93: =$F$92 * Q$86 -> 74808.647 | ... AW93: =$F$92 * AW$86 -> 0
D95: Amortization
E96: =CaseData!C$6 -> Amortisation Months | F96: =CaseData!H$6 -> 96 | G96: months
E97: Amortisation quarters | F97: =F96 / 3 -> 32 | G97: quarters
E98: Quarterly scheduled payment | F98: =PMT( $F$92, $F$97, $F$84 ) * - 1 -> 518644.93 | G98: USD
E99: Mortage principal payment | G99: USD | H99: =SUM( J99:AW99) -> 15000000 | J99: =MIN( J$86, $F$98 - J$93 ) -> 424894.93 | K99: =MIN( K$86, $F$98 - K$93 ) -> 427550.52 | L99: =MIN( L$86, $F$98 - L$93 ) -> 430222.71 | M99: =MIN( M$86, $F$98 - M$93 ) -> 432911.61 | N99: =MIN( N$86, $F$98 - N$93 ) -> 435617.3 | O99: =MIN( O$86, $F$98 - O$93 ) -> 438339.91 | P99: =MIN( P$86, $F$98 - P$93 ) -> 441079.54 | Q99: =MIN( Q$86, $F$98 - Q$93 ) -> 443836.28 | ... AW99: =MIN( AW$86, $F$98 - AW$93 ) -> 0
A102: Junior Debt
E105: Junior Debt balance at model start date | F105: =CaseData!$H$23 -> 9000000 | G105: USD
E107: Junior Debt opening balance | G107: USD | J107: =I$110 -> 9000000 | K107: =J$110 -> 8775000 | L107: =K$110 -> 8550000 | M107: =L$110 -> 8325000 | N107: =M$110 -> 8100000 | O107: =N$110 -> 7875000 | P107: =O$110 -> 7650000 | Q107: =P$110 -> 7425000 | ... AW107: =AV$110 -> 225000
E108: Junior Debt Scheduled Repayment Paid | G108: USD | I108: 0 | J108: =J$126 * - 1 -> -225000 | K108: =K$126 * - 1 -> -225000 | L108: =L$126 * - 1 -> -225000 | M108: =M$126 * - 1 -> -225000 | N108: =N$126 * - 1 -> -225000 | O108: =O$126 * - 1 -> -225000 | P108: =P$126 * - 1 -> -225000 | Q108: =Q$126 * - 1 -> -225000 | ... AW108: =AW$126 * - 1 -> -225000
E109: Repayment of arrears owed | G109: USD | I109: 0
E110: Junior Debt | G110: USD | I110: =$F$105 -> 9000000 | J110: =SUM(J107:J109) -> 8775000 | K110: =SUM(K107:K109) -> 8550000 | L110: =SUM(L107:L109) -> 8325000 | M110: =SUM(M107:M109) -> 8100000 | N110: =SUM(N107:N109) -> 7875000 | O110: =SUM(O107:O109) -> 7650000 | P110: =SUM(P107:P109) -> 7425000 | Q110: =SUM(Q107:Q109) -> 7200000 | ... AW110: =SUM(AW107:AW109) -> 0
D113: Junior Debt interest expenses
E114: =CaseData!C$5 -> Annual cash interest rate | F114: =CaseData!$H$24 -> 0 | G114: % p.a.
E115: Quarterly cash intereest rate | F115: =F114 / 4 -> 0 | G115: %
E116: Mortagage interest expenses | G116: USD | H116: =SUM( J116:AW116) -> 0 | J116: =J$107 * $F$115 -> 0 | K116: =K$107 * $F$115 -> 0 | L116: =L$107 * $F$115 -> 0 | M116: =M$107 * $F$115 -> 0 | N116: =N$107 * $F$115 -> 0 | O116: =O$107 * $F$115 -> 0 | P116: =P$107 * $F$115 -> 0 | Q116: =Q$107 * $F$115 -> 0 | ... AW116: =AW$107 * $F$115 -> 0
D119: Junior Debt scheduled amortization
E120: =CaseData!C$25 -> Amortisation Quarters | F120: =CaseData!H$25 -> 40 | G120: quarters
E121: Junior Debt scheduled amortization | G121: USD | J121: =J$19 * $F$105 / $F$120 -> 225000 | K121: =K$19 * $F$105 / $F$120 -> 225000 | L121: =L$19 * $F$105 / $F$120 -> 225000 | M121: =M$19 * $F$105 / $F$120 -> 225000 | N121: =N$19 * $F$105 / $F$120 -> 225000 | O121: =O$19 * $F$105 / $F$120 -> 225000 | P121: =P$19 * $F$105 / $F$120 -> 225000 | Q121: =Q$19 * $F$105 / $F$120 -> 225000 | ... AW121: =AW$19 * $F$105 / $F$120 -> 225000
D123: Junior Debt amortization paid
E124: =E$121 -> Junior Debt scheduled amortization | G124: =G$121 -> USD | I124: =I$121 -> 0 | J124: =J$121 -> 225000 | K124: =K$121 -> 225000 | L124: =L$121 -> 225000 | M124: =M$121 -> 225000 | N124: =N$121 -> 225000 | O124: =O$121 -> 225000 | P124: =P$121 -> 225000 | ... AW124: =AW$121 -> 225000
E125: =E$39 -> Funds Available for Junior Debt Scheduled Repayments | G125: =G$39 -> USD | I125: =I$39 -> 0 | J125: =J$39 -> 502312.07 | K125: =K$39 -> 491275.07 | L125: =L$39 -> 481790.57 | M125: =M$39 -> 478537.07 | N125: =N$39 -> 480029.57 | O125: =O$39 -> 458441.57 | P125: =P$39 -> 457570.07 | ... AW125: =AW$39 -> 1158460.5
E126: Junior Debt amortization paid | G126: USD | J126: =MIN( J$125, J$124 ) -> 225000 | K126: =MIN( K$125, K$124 ) -> 225000 | L126: =MIN( L$125, L$124 ) -> 225000 | M126: =MIN( M$125, M$124 ) -> 225000 | N126: =MIN( N$125, N$124 ) -> 225000 | O126: =MIN( O$125, O$124 ) -> 225000 | P126: =MIN( P$125, P$124 ) -> 225000 | Q126: =MIN( Q$125, Q$124 ) -> 225000 | ... AW126: =MIN( AW$125, AW$124 ) -> 225000
E127: Unmet Junior Debt repayment | G127: USD | J127: =J$124 - J126 -> 0 | K127: =K$124 - K126 -> 0 | L127: =L$124 - L126 -> 0 | M127: =M$124 - M126 -> 0 | N127: =N$124 - N126 -> 0 | O127: =O$124 - O126 -> 0 | P127: =P$124 - P126 -> 0 | Q127: =Q$124 - Q126 -> 0 | ... AW127: =AW$124 - AW126 -> 0
D129: Arreas amount owed
E131: =E$42 -> Funds Available for Junior Debt Arrears Amount Owed | G131: =G$42 -> USD | I131: =I$42 -> 0 | J131: =J$42 -> 277312.07 | K131: =K$42 -> 266275.07 | L131: =L$42 -> 256790.57 | M131: =M$42 -> 253537.07 | N131: =N$42 -> 255029.57 | O131: =O$42 -> 233441.57 | P131: =P$42 -> 232570.07 | ... AW131: =AW$42 -> 933460.5
E133: Arrears amount owed opening balance | J133: =I136 -> 0 | K133: =J136 -> 0 | L133: =K136 -> 0 | M133: =L136 -> 0 | N133: =M136 -> 0 | O133: =N136 -> 0 | P133: =O136 -> 0 | Q133: =P136 -> 0 | ... AW133: =AV136 -> 0
E134: =E$127 -> Unmet Junior Debt repayment | G134: =G$127 -> USD | I134: =I$127 -> 0 | J134: =J$127 -> 0 | K134: =K$127 -> 0 | L134: =L$127 -> 0 | M134: =M$127 -> 0 | N134: =N$127 -> 0 | O134: =O$127 -> 0 | P134: =P$127 -> 0 | ... AW134: =AW$127 -> 0
E135: Repayment of arrears owed | G135: USD | J135: =MIN( J131, SUM( J133:J134 ) ) * - 1 -> 0 | K135: =MIN( K131, SUM( K133:K134 ) ) * - 1 -> 0 | L135: =MIN( L131, SUM( L133:L134 ) ) * - 1 -> 0 | M135: =MIN( M131, SUM( M133:M134 ) ) * - 1 -> 0 | N135: =MIN( N131, SUM( N133:N134 ) ) * - 1 -> 0 | O135: =MIN( O131, SUM( O133:O134 ) ) * - 1 -> 0 | P135: =MIN( P131, SUM( P133:P134 ) ) * - 1 -> 0 | Q135: =MIN( Q131, SUM( Q133:Q134 ) ) * - 1 -> 0 | ... AW135: =MIN( AW131, SUM( AW133:AW134 ) ) * - 1 -> 0
E136: Arrears amount owed closing balance | G136: USD | J136: =SUM(J133:J135) -> 0 | K136: =SUM(K133:K135) -> 0 | L136: =SUM(L133:L135) -> 0 | M136: =SUM(M133:M135) -> 0 | N136: =SUM(N133:N135) -> 0 | O136: =SUM(O133:O135) -> 0 | P136: =SUM(P133:P135) -> 0 | Q136: =SUM(Q133:Q135) -> 0 | ... AW136: =SUM(AW133:AW135) -> 0
A139: Equity
E141: =CaseData!C$30 -> Contribution amount at model start date | F141: =CaseData!H$30 * - 1 -> -6000000 | G141: USD
E142: =E$45 -> Funds distributed to Equity | G142: =G$45 -> USD | I142: =I$45 -> 0 | J142: =J$45 -> 277312.07 | K142: =K$45 -> 266275.07 | L142: =L$45 -> 256790.57 | M142: =M$45 -> 253537.07 | N142: =N$45 -> 255029.57 | O142: =O$45 -> 233441.57 | P142: =P$45 -> 232570.07 | ... AW142: =AW$45 -> 933460.5
E144: =CaseData!C$31 -> Discount rate for Net Present Value Calculations | F144: =CaseData!H$31 -> 0.1 | G144: % p.a.
E146: Net Present Value (NPV) | F146: =_xlfn.LET( _xlpm.timeline, _xlfn.HSTACK( start_date,_xlfn.ANCHORARRAY( J3) ), _xlpm.cashflow, _xlfn.HSTACK( $F$141, $J$142:$AW$142 ), _xlpm.rate, $F$144, XNPV( _xlpm.rate, _xlpm.cashflow, _xlpm.timeline ) ) -> 3534408.4 | G146: USD
E147: Internal Rate of Return ( IRR) | F147: =_xlfn.LET( _xlpm.timeline, _xlfn.HSTACK( start_date,_xlfn.ANCHORARRAY( J3) ), _xlpm.cashflow, _xlfn.HSTACK( $F$141, $J$142:$AW$142 ), _xlpm.rate, $F$144, XIRR( _xlpm.cashflow, _xlpm.timeline ) ) -> 0.20079721 | G147: %
...

Sheet CaseData
A1: Assumptions | T1: =MATCH(selector,$M$5:$R$5,0) -> 1
T2: =selector -> 1
B3: Mortgage Facility | T3: =H45 -> 1
C4: Facility Balance at model start date | F4: [$] | H4: 15000000 | J4: EBITDA Profiles
C5: Annual cash interest rate | F5: [% p.a.] | H5: 0.025 | K5: Profile Number --> | M5: 1 | N5: 2 | O5: 3 | P5: 4 | Q5: 5 | R5: 6
C6: Amortisation Months | F6: [#] | H6: 96 | K6: Profile Name --> | M6: Base Case | N6: Case 2 | O6: Case 3 | P6: Case 4 | Q6: Case 5 | R6: Case 6
C7: Scheduled final payment date | F7: [date] | H7: =EOMONTH(H35,H6) -> 47848 | K7: Quarter Ending | M7: [$] | N7: [$] | O7: [$] | P7: [$] | Q7: [$] | R7: [$]
K8: =$H$36 -> 45016 | M8: 1019082 | N8: 1105141.5 | O8: 856621.5 | P8: 982938 | Q8: 1019082 | R8: 903625.5
C9: Mortgage DSCR Lock up trigger | F9: [x] | H9: 1.7 | K9: =EOMONTH(K8,3) -> 45107 | M9: 1008045 | N9: 961012.5 | O9: 957103.5 | P9: 932742 | Q9: 1008045 | R9: 893214
C10: Look-back quarters for DSCR incl. current quarter (Last Twelve Months) | F10: [#] | H10: 4 | I10: Do not change | K10: =EOMONTH(K9,3) -> 45199 | M10: 998560.5 | N10: 1048608 | O10: 919759.5 | P10: 973290 | Q10: 998560.5 | R10: 889797
K11: =EOMONTH(K10,3) -> 45291 | M11: 995307 | N11: 1074277.5 | O11: 990211.5 | P11: 947178 | Q11: 995307 | R11: 909898.5
C12: To get out of lock-up: | K12: =EOMONTH(K11,3) -> 45382 | M12: 996799.5 | N12: 1117527 | O12: 990643.5 | P12: 940560 | Q12: 996799.5 | R12: 947650.5
C13: Number of quarters required for Sr DSCR to be greater than lock-up trigger: | F13: [# qtrs] | H13: 2 | I13: Do not change | K13: =EOMONTH(K12,3) -> 45473 | M13: 975211.5 | N13: 971310 | O13: 940851 | P13: 964081.5 | Q13: 975211.5 | R13: 915790.5
K14: =EOMONTH(K13,3) -> 45565 | M14: 974340 | N14: 916065 | O14: 810855 | P14: 921279 | Q14: 974340 | R14: 878397
K15: =EOMONTH(K14,3) -> 45657 | M15: 967587 | N15: 786327 | O15: 839349 | P15: 955951.5 | Q15: 483793.5 | R15: 956358
B16: Debt Service Reserve Account | K16: =EOMONTH(K15,3) -> 45747 | M16: 1015347 | N16: 882622.5 | O16: 962665.5 | P16: 921717 | Q16: 507673.5 | R16: 970485
C17: Initial balance at project start (already funded) | H17: 750000 | K17: =EOMONTH(K16,3) -> 45838 | M17: 963435 | N17: 1101510 | O17: 803719.5 | P17: 963336 | Q17: 481717.5 | R17: 1013374.5
C18: Required minimum balance during term of Mortgage Facility | H18: 750000 | K18: =EOMONTH(K17,3) -> 45930 | M18: 979111.5 | N18: 1052203.5 | O18: 903232.5 | P18: 914505 | Q18: 489555.75 | R18: 876916.5
C19: Cash interest rate earned on account balance | F19: [% p.a.] | H19: 0.01 | K19: =EOMONTH(K18,3) -> 46022 | M19: 965946 | N19: 1095760.5 | O19: 988131 | P19: 869358 | Q19: 482973 | R19: 327231
K20: =EOMONTH(K19,3) -> 46112 | M20: 963438 | N20: 970521 | O20: 881398.5 | P20: 945835.5 | Q20: 963438 | R20: 341170.5
K21: =EOMONTH(K20,3) -> 46203 | M21: 1007662.5 | N21: 1003909.5 | O21: 963904.5 | P21: 985399.5 | Q21: 1007662.5 | R21: 397729.5
B22: Junior Facility | K22: =EOMONTH(K21,3) -> 46295 | M22: 1011898.5 | N22: 987990 | O22: 890178 | P22: 1010407.5 | Q22: 1011898.5 | R22: 388617
C23: Facility Balance at model start date | F23: [$] | H23: 9000000 | K23: =EOMONTH(K22,3) -> 46387 | M23: 1027911 | N23: 1227384 | O23: 876990 | P23: 593412 | Q23: 1027911 | R23: 906457.5
C24: Annual cash interest rate | F24: [% p.a.] | H24: 0 | K24: =EOMONTH(K23,3) -> 46477 | M24: 990430.5 | N24: 1096188 | O24: 805438.5 | P24: 558492 | Q24: 990430.5 | R24: 862152
C25: Amortisation Quarters | F25: [#] | H25: 40 | K25: =EOMONTH(K24,3) -> 46568 | M25: 1015789.5 | N25: 994783.5 | O25: 928035 | P25: 608830.5 | Q25: 1015789.5 | R25: 961906.5
C26: Scheduled final payment date | F26: [date] | H26: =EOMONTH(H35,3*H25) -> 48579 | K26: =EOMONTH(K25,3) -> 46660 | M26: 1030960.5 | N26: 900456 | O26: 954414 | P26: 607663.5 | Q26: 1030960.5 | R26: 961135.5
K27: =EOMONTH(K26,3) -> 46752 | M27: 1048911 | N27: 941046 | O27: 972483 | P27: 956788.5 | Q27: 1048911 | R27: 950587.5
K28: =EOMONTH(K27,3) -> 46843 | M28: 1078854 | N28: 1093561.5 | O28: 975916.5 | P28: 1020253.5 | Q28: 1078854 | R28: 864250.5
B29: Equity | K29: =EOMONTH(K28,3) -> 46934 | M29: 1039989 | N29: 960078 | O29: 1014169.5 | P29: 1003492.5 | Q29: 1039989 | R29: 871696.5
C30: Contribution amount at model start date | F30: [$] | H30: 6000000 | K30: =EOMONTH(K29,3) -> 47026 | M30: 1069714.5 | N30: 1257165 | O30: 1113783 | P30: 1000381.5 | Q30: 1069714.5 | R30: 1064973
C31: Discount rate for Net Present Value Calculations | F31: [% p.a.] | H31: 0.1 | K31: =EOMONTH(K30,3) -> 47118 | M31: 1047547.5 | N31: 1095327 | O31: 986683.5 | P31: 1030954.5 | Q31: 1047547.5 | R31: 903028.5
K32: =EOMONTH(K31,3) -> 47208 | M32: 1049193 | N32: 885561 | O32: 907974 | P32: 960159 | Q32: 1049193 | R32: 1013218.5
K33: =EOMONTH(K32,3) -> 47299 | M33: 1059516 | N33: 1127121 | O33: 953113.5 | P33: 954321 | Q33: 1059516 | R33: 1004701.5
B34: Other Assumptions | K34: =EOMONTH(K33,3) -> 47391 | M34: 1107811.5 | N34: 992164.5 | O34: 891501 | P34: 1055305.5 | Q34: 1107811.5 | R34: 1063546.5
C35: Model start date (Project start date) | F35: [date] | H35: 44926 | K35: =EOMONTH(K34,3) -> 47483 | M35: 1059664.5 | N35: 1179703.5 | O35: 957454.5 | P35: 1026214.5 | Q35: 1059664.5 | R35: 1039509
C36: Initial quarter end date | F36: [date] | H36: =EOMONTH(H35,3) -> 45016 | K36: =EOMONTH(K35,3) -> 47573 | M36: 1045116 | N36: 976075.5 | O36: 997194 | P36: 1003003.5 | Q36: 1045116 | R36: 1076869.5
C37: Number of quarters in project | F37: [# qtrs] | H37: 40 | K37: =EOMONTH(K36,3) -> 47664 | M37: 1071954 | N37: 958510.5 | O37: 1120617 | P37: 1058319 | Q37: 1071954 | R37: 943045.5
C38: Final quarter end date (Project end date) | F38: [date] | H38: =EOMONTH(H35,H37*3) -> 48579 | K38: =EOMONTH(K37,3) -> 47756 | M38: 1133484 | N38: 1176114 | O38: 1176696 | P38: 1077916.5 | Q38: 1133484 | R38: 986671.5
K39: =EOMONTH(K38,3) -> 47848 | M39: 1125522 | N39: 1138582.5 | O39: 1116520.5 | P39: 1069879.5 | Q39: 1125522 | R39: 1051468.5
C40: Cash interest rate earned on cash account balance | F40: [% p.a.] | H40: 0.01 | K40: =EOMONTH(K39,3) -> 47938 | M40: 1110844.5 | N40: 1221447 | O40: 939954 | P40: 1043466 | Q40: 1110844.5 | R40: 957409.5
K41: =EOMONTH(K40,3) -> 48029 | M41: 1096879.5 | N41: 979699.5 | O41: 1147558.5 | P41: 1025611.5 | Q41: 1096879.5 | R41: 979273.5
C42: Company name | F42: [label] | H42: Unicord Construction | K42: =EOMONTH(K41,3) -> 48121 | M42: 1133016 | N42: 1148931 | O42: 926283 | P42: 1028232 | Q42: 1133016 | R42: 1087471.5
C43: CFM Topic | F43: [label] | H43: Debt | K43: =EOMONTH(K42,3) -> 48213 | M43: 1153189.5 | N43: 1233861 | O43: 947653.5 | P43: 1150174.5 | Q43: 1153189.5 | R43: 956551.5
K44: =EOMONTH(K43,3) -> 48304 | M44: 1146522 | N44: 1187176.5 | O44: 1124563.5 | P44: 1064307 | Q44: 1146522 | R44: 1118854.5
C45: Scenarios | E45: {=TRANSPOSE( $M$6:$R$6)} -> Base Case | F45: scenario selector | H45: =Debt!F3 -> 1 | K45: =EOMONTH(K44,3) -> 48395 | M45: 1138092 | N45: 1164579 | O45: 922500 | P45: 1106622 | Q45: 1138092 | R45: 1125312
E46: Case 2 | K46: =EOMONTH(K45,3) -> 48487 | M46: 1157863.5 | N46: 1370262 | O46: 1095700.5 | P46: 1150093.5 | Q46: 1157863.5 | R46: 1111447.5
E47: Case 3 | K47: =EOMONTH(K46,3) -> 48579 | M47: 1158460.5 | N47: 1089577.5 | O47: 962511 | P47: 1049775 | Q47: 1158460.5 | R47: 1125013.5
E48: Case 4
E49: Case 5
E50: Case 6
A51: End Sheet

Sheet CaseSolution
B2: Unicorn Construction Ltd
B3: Debt Model
H6: Total | J6: =CaseData!H35 -> 44926 | K6: =EOMONTH(J6,3) -> 45016 | L6: =EOMONTH(K6,3) -> 45107 | M6: =EOMONTH(L6,3) -> 45199 | N6: =EOMONTH(M6,3) -> 45291 | O6: =EOMONTH(N6,3) -> 45382 | P6: =EOMONTH(O6,3) -> 45473 | Q6: =EOMONTH(P6,3) -> 45565 | R6: =EOMONTH(Q6,3) -> 45657 | ... AX6: =EOMONTH(AW6,3) -> 48579
B8: Answers
K10: Jr Facility Bal | L10: First Lock up | M10: Max DSRA Bal | N10: Mortgage | O10: Mortgage Bal
C11: a) | E11: See below | K11: 45838 | N11: Total Int | O11: 48579
C12: b) | E12: See below | K12: =INDEX($J$97:$AX$97,MATCH(K11,$J$6:$AX$6,0)) -> 6750000 | L12: =IFERROR(INDEX($K$6:$AX$6,MATCH(1,$K$89:$AX$89,0)),"None") -> None | M12: =MAX(K67:AX67) -> 750000 | N12: =H53 -> 1596637.7 | O12: =INDEX($J$50:$AX$50,MATCH(O11,$J$6:$AX$6,0)) -> 0
C13: c) | E13: =K16 -> 6750000 | J13: Base Case | K13: 6750000 | L13: None | M13: 750000 | N13: 1596637.7 | O13: 0
C14: d) | E14: =L14 -> None | J14: Case 2 | K14: 6750000 | L14: None | M14: 750000 | N14: 1596637.7 | O14: 0
C15: e) | E15: =M15 -> 1897175.9 | J15: Case 3 | K15: 6975000 | L15: 45016 | M15: 1897175.9 | N15: 1596637.7 | O15: 0
C16: f) | E16: =N17 -> 1596637.7 | J16: Case 4 | K16: 6750000 | L16: 46477 | M16: 2410494.1 | N16: 1596637.7 | O16: 0
C17: g) | E17: =$O$18 -> 0 | J17: Case 5 | K17: 7425000 | L17: 45657 | M17: 2560711.7 | N17: 1596637.7 | O17: 0
J18: Case 6 | K18: 6750000 | L18: 46022 | M18: 1759237.7 | N18: 1596637.7 | O18: 0
B21: Cash Flow
C23: EBITDA | G23: Case 2 | H23: =SUM(K23:AX23) -> 42470140 | K23: =INDEX(CaseData!$M$8:$R$47,MATCH(K$6,CaseData!$K$8:$K$47,0),MATCH($G$23,CaseData!$M$6:$R$6,0)) -> 1105141.5 | L23: =INDEX(CaseData!$M$8:$R$47,MATCH(L$6,CaseData!$K$8:$K$47,0),MATCH($G$23,CaseData!$M$6:$R$6,0)) -> 961012.5 | M23: =INDEX(CaseData!$M$8:$R$47,MATCH(M$6,CaseData!$K$8:$K$47,0),MATCH($G$23,CaseData!$M$6:$R$6,0)) -> 1048608 | N23: =INDEX(CaseData!$M$8:$R$47,MATCH(N$6,CaseData!$K$8:$K$47,0),MATCH($G$23,CaseData!$M$6:$R$6,0)) -> 1074277.5 | O23: =INDEX(CaseData!$M$8:$R$47,MATCH(O$6,CaseData!$K$8:$K$47,0),MATCH($G$23,CaseData!$M$6:$R$6,0)) -> 1117527 | P23: =INDEX(CaseData!$M$8:$R$47,MATCH(P$6,CaseData!$K$8:$K$47,0),MATCH($G$23,CaseData!$M$6:$R$6,0)) -> 971310 | Q23: =INDEX(CaseData!$M$8:$R$47,MATCH(Q$6,CaseData!$K$8:$K$47,0),MATCH($G$23,CaseData!$M$6:$R$6,0)) -> 916065 | R23: =INDEX(CaseData!$M$8:$R$47,MATCH(R$6,CaseData!$K$8:$K$47,0),MATCH($G$23,CaseData!$M$6:$R$6,0)) -> 786327 | ... AX23: =INDEX(CaseData!$M$8:$R$47,MATCH(AX$6,CaseData!$K$8:$K$47,0),MATCH($G$23,CaseData!$M$6:$R$6,0)) -> 1089577.5
C24: Interest Income | H24: =SUM(K24:AX24) -> 60000 | K24: =K70 -> 1875 | L24: =L70 -> 1875 | M24: =M70 -> 1875 | N24: =N70 -> 1875 | O24: =O70 -> 1875 | P24: =P70 -> 1875 | Q24: =Q70 -> 1875 | R24: =R70 -> 1875 | ... AX24: =AX70 -> 0
C25: Cash flow | H25: =SUM(K25:AX25) -> 42530140 | K25: =SUM(K23:K24) -> 1107016.5 | L25: =SUM(L23:L24) -> 962887.5 | M25: =SUM(M23:M24) -> 1050483 | N25: =SUM(N23:N24) -> 1076152.5 | O25: =SUM(O23:O24) -> 1119402 | P25: =SUM(P23:P24) -> 973185 | Q25: =SUM(Q23:Q24) -> 917940 | R25: =SUM(R23:R24) -> 788202 | ... AX25: =SUM(AX23:AX24) -> 1089577.5
C27: Mortgage Interest | H27: =SUM(K27:AX27) -> -1596637.7 | K27: =-K53 -> -93750 | L27: =-L53 -> -91094.407 | M27: =-M53 -> -88422.216 | N27: =-N53 -> -85733.324 | O27: =-O53 -> -83027.626 | P27: =-P53 -> -80305.018 | Q27: =-Q53 -> -77565.394 | R27: =-R53 -> -74808.647 | ... AX27: =-AX53 -> 0
C28: Mortgage Principal | H28: =SUM(K28:AX28) -> -15000000 | K28: =K49 -> -424894.93 | L28: =L49 -> -427550.52 | M28: =M49 -> -430222.71 | N28: =N49 -> -432911.61 | O28: =O49 -> -435617.3 | P28: =P49 -> -438339.91 | Q28: =Q49 -> -441079.54 | R28: =R49 -> -443836.28 | ... AX28: =AX49 -> 0
C29: Remaining cash flow | K29: =SUM(K25,K27:K28) -> 588371.57 | L29: =SUM(L25,L27:L28) -> 444242.57 | M29: =SUM(M25,M27:M28) -> 531838.07 | N29: =SUM(N25,N27:N28) -> 557507.57 | O29: =SUM(O25,O27:O28) -> 600757.07 | P29: =SUM(P25,P27:P28) -> 454540.07 | Q29: =SUM(Q25,Q27:Q28) -> 399295.07 | R29: =SUM(R25,R27:R28) -> 269557.07 | ... AX29: =SUM(AX25,AX27:AX28) -> 1089577.5
C31: DSRA Withdrawl | H31: =SUM(K31:AX31) -> 0 | K31: =-MIN(K29,0) -> 0 | L31: =-MIN(L29,0) -> 0 | M31: =-MIN(M29,0) -> 0 | N31: =-MIN(N29,0) -> 0 | O31: =-MIN(O29,0) -> 0 | P31: =-MIN(P29,0) -> 0 | Q31: =-MIN(Q29,0) -> 0 | R31: =-MIN(R29,0) -> 0 | ... AX31: =-MIN(AX29,0) -> 0
C32: DSRA Top Up | H32: =SUM(K32:AX32) -> 0 | K32: =-K63 -> 0 | L32: =-L63 -> 0 | M32: =-M63 -> 0 | N32: =-N63 -> 0 | O32: =-O63 -> 0 | P32: =-P63 -> 0 | Q32: =-Q63 -> 0 | R32: =-R63 -> 0 | ... AX32: =-AX63 -> 0
C33: DSRA Liquidation | H33: =SUM(K33:AX33) -> 750000 | K33: =-K66 -> 0 | L33: =-L66 -> 0 | M33: =-M66 -> 0 | N33: =-N66 -> 0 | O33: =-O66 -> 0 | P33: =-P66 -> 0 | Q33: =-Q66 -> 0 | R33: =-R66 -> 0 | ... AX33: =-AX66 -> 0
C34: Remaining cash flow | K34: =SUM(K29,K31:K33) -> 588371.57 | L34: =SUM(L29,L31:L33) -> 444242.57 | M34: =SUM(M29,M31:M33) -> 531838.07 | N34: =SUM(N29,N31:N33) -> 557507.57 | O34: =SUM(O29,O31:O33) -> 600757.07 | P34: =SUM(P29,P31:P33) -> 454540.07 | Q34: =SUM(Q29,Q31:Q33) -> 399295.07 | R34: =SUM(R29,R31:R33) -> 269557.07 | ... AX34: =SUM(AX29,AX31:AX33) -> 1089577.5
C36: Lock-Up Sweep | H36: =SUM(K36:AX36) -> 0 | K36: =-K64 -> 0 | L36: =-L64 -> 0 | M36: =-M64 -> 0 | N36: =-N64 -> 0 | O36: =-O64 -> 0 | P36: =-P64 -> 0 | Q36: =-Q64 -> 0 | R36: =-R64 -> 0 | ... AX36: =-AX64 -> 0
C37: Lock-up Exit Release | H37: =SUM(K37:AX37) -> 0 | K37: =-K65 -> 0 | L37: =-L65 -> 0 | M37: =-M65 -> 0 | N37: =-N65 -> 0 | O37: =-O65 -> 0 | P37: =-P65 -> 0 | Q37: =-Q65 -> 0 | R37: =-R65 -> 0 | ... AX37: =-AX65 -> 0
C38: Remaining cash flow for Jr. Debt | K38: =SUM(K34,K36:K37) -> 588371.57 | L38: =SUM(L34,L36:L37) -> 444242.57 | M38: =SUM(M34,M36:M37) -> 531838.07 | N38: =SUM(N34,N36:N37) -> 557507.57 | O38: =SUM(O34,O36:O37) -> 600757.07 | P38: =SUM(P34,P36:P37) -> 454540.07 | Q38: =SUM(Q34,Q36:Q37) -> 399295.07 | R38: =SUM(R34,R36:R37) -> 269557.07 | ... AX38: =SUM(AX34,AX36:AX37) -> 1089577.5
C40: Jr. Debt Amortization | H40: =SUM(K40:AX40) -> -9000000 | K40: =K95 -> -225000 | L40: =L95 -> -225000 | M40: =M95 -> -225000 | N40: =N95 -> -225000 | O40: =O95 -> -225000 | P40: =P95 -> -225000 | Q40: =Q95 -> -225000 | R40: =R95 -> -225000 | ... AX40: =AX95 -> -225000
C41: Remaining cash flow for Arrears | K41: =SUM(K38,K40) -> 363371.57 | L41: =SUM(L38,L40) -> 219242.57 | M41: =SUM(M38,M40) -> 306838.07 | N41: =SUM(N38,N40) -> 332507.57 | O41: =SUM(O38,O40) -> 375757.07 | P41: =SUM(P38,P40) -> 229540.07 | Q41: =SUM(Q38,Q40) -> 174295.07 | R41: =SUM(R38,R40) -> 44557.071 | ... AX41: =SUM(AX38,AX40) -> 864577.5
C43: Repayment of Arrears Jr. Debt | H43: =SUM(K43:AX43) -> 0 | K43: =K96 -> 0 | L43: =L96 -> 0 | M43: =M96 -> 0 | N43: =N96 -> 0 | O43: =O96 -> 0 | P43: =P96 -> 0 | Q43: =Q96 -> 0 | R43: =R96 -> 0 | ... AX43: =AX96 -> 0
C44: Cash Flow to Equity | K44: =SUM(K41,K43) -> 363371.57 | L44: =SUM(L41,L43) -> 219242.57 | M44: =SUM(M41,M43) -> 306838.07 | N44: =SUM(N41,N43) -> 332507.57 | O44: =SUM(O41,O43) -> 375757.07 | P44: =SUM(P41,P43) -> 229540.07 | Q44: =SUM(Q41,Q43) -> 174295.07 | R44: =SUM(R41,R43) -> 44557.071 | ... AX44: =SUM(AX41,AX43) -> 864577.5
B46: Mortgage Facility
C48: Opening Balance | K48: =J50 -> 15000000 | L48: =K50 -> 14575105 | M48: =L50 -> 14147555 | N48: =M50 -> 13717332 | O48: =N50 -> 13284420 | P48: =O50 -> 12848803 | Q48: =P50 -> 12410463 | R48: =Q50 -> 11969383 | ... AX48: =AW50 -> 0
C49: Amortization | H49: =SUM(K49:AX49) -> -15000000 | K49: =-K57 -> -424894.93 | L49: =-L57 -> -427550.52 | M49: =-M57 -> -430222.71 | N49: =-N57 -> -432911.61 | O49: =-O57 -> -435617.3 | P49: =-P57 -> -438339.91 | Q49: =-Q57 -> -441079.54 | R49: =-R57 -> -443836.28 | ... AX49: =-AX57 -> 0
C50: Closing Balance | J50: =CaseData!$H$4 -> 15000000 | K50: =SUM(K48:K49) -> 14575105 | L50: =SUM(L48:L49) -> 14147555 | M50: =SUM(M48:M49) -> 13717332 | N50: =SUM(N48:N49) -> 13284420 | O50: =SUM(O48:O49) -> 12848803 | P50: =SUM(P48:P49) -> 12410463 | Q50: =SUM(Q48:Q49) -> 11969383 | R50: =SUM(R48:R49) -> 11525547 | ... AX50: =SUM(AX48:AX49) -> 0
C52: Interest Rate | G52: =CaseData!H5 -> 0.025 | K52: =$G52 -> 0.025 | L52: =$G52 -> 0.025 | M52: =$G52 -> 0.025 | N52: =$G52 -> 0.025 | O52: =$G52 -> 0.025 | P52: =$G52 -> 0.025 | Q52: =$G52 -> 0.025 | R52: =$G52 -> 0.025 | ... AX52: =$G52 -> 0.025
C53: Interest Expense | H53: =SUM(K53:AX53) -> 1596637.7 | K53: =K48*K52/4 -> 93750 | L53: =L48*L52/4 -> 91094.407 | M53: =M48*M52/4 -> 88422.216 | N53: =N48*N52/4 -> 85733.324 | O53: =O48*O52/4 -> 83027.626 | P53: =P48*P52/4 -> 80305.018 | Q53: =Q48*Q52/4 -> 77565.394 | R53: =R48*R52/4 -> 74808.647 | ... AX53: =AX48*AX52/4 -> 0
C55: Term (months) | G55: =CaseData!H6 -> 96
C56: Quarterly Payment | G56: =PMT(G52/4,G55/3,-J50) -> 518644.93 | K56: =IF(K48>0,$G56,0) -> 518644.93 | L56: =IF(L48>0,$G56,0) -> 518644.93 | M56: =IF(M48>0,$G56,0) -> 518644.93 | N56: =IF(N48>0,$G56,0) -> 518644.93 | O56: =IF(O48>0,$G56,0) -> 518644.93 | P56: =IF(P48>0,$G56,0) -> 518644.93 | Q56: =IF(Q48>0,$G56,0) -> 518644.93 | R56: =IF(R48>0,$G56,0) -> 518644.93 | ... AX56: =IF(AX48>0,$G56,0) -> 0
C57: Amortization | K57: =MIN(K56-K53,K48) -> 424894.93 | L57: =MIN(L56-L53,L48) -> 427550.52 | M57: =MIN(M56-M53,M48) -> 430222.71 | N57: =MIN(N56-N53,N48) -> 432911.61 | O57: =MIN(O56-O53,O48) -> 435617.3 | P57: =MIN(P56-P53,P48) -> 438339.91 | Q57: =MIN(Q56-Q53,Q48) -> 441079.54 | R57: =MIN(R56-R53,R48) -> 443836.28 | ... AX57: =MIN(AX56-AX53,AX48) -> 0
B59: Debt Service Reserve Account
C61: Opening Balance | K61: =J67 -> 750000 | L61: =K67 -> 750000 | M61: =L67 -> 750000 | N61: =M67 -> 750000 | O61: =N67 -> 750000 | P61: =O67 -> 750000 | Q61: =P67 -> 750000 | R61: =Q67 -> 750000 | ... AX61: =AW67 -> 0
C62: Withdrawl | H62: =SUM(K62:AX62) -> 0 | K62: =-K31 -> 0 | L62: =-L31 -> 0 | M62: =-M31 -> 0 | N62: =-N31 -> 0 | O62: =-O31 -> 0 | P62: =-P31 -> 0 | Q62: =-Q31 -> 0 | R62: =-R31 -> 0 | ... AX62: =-AX31 -> 0
C63: Top up | H63: =SUM(K63:AX63) -> 0 | K63: =K75 -> 0 | L63: =L75 -> 0 | M63: =M75 -> 0 | N63: =N75 -> 0 | O63: =O75 -> 0 | P63: =P75 -> 0 | Q63: =Q75 -> 0 | R63: =R75 -> 0 | ... AX63: =AX75 -> 0
C64: Lock-Up Sweep | H64: =SUM(K64:AX64) -> 0 | K64: =IF(K90=1,K34,0) -> 0 | L64: =IF(L90=1,L34,0) -> 0 | M64: =IF(M90=1,M34,0) -> 0 | N64: =IF(N90=1,N34,0) -> 0 | O64: =IF(O90=1,O34,0) -> 0 | P64: =IF(P90=1,P34,0) -> 0 | Q64: =IF(Q90=1,Q34,0) -> 0 | R64: =IF(R90=1,R34,0) -> 0 | ... AX64: =IF(AX90=1,AX34,0) -> 0
C65: Lock-Up Exit Release | H65: =SUM(K65:AX65) -> 0 | K65: =IF(K90=0,-K77,0) -> 0 | L65: =IF(L90=0,-L77,0) -> 0 | M65: =IF(M90=0,-M77,0) -> 0 | N65: =IF(N90=0,-N77,0) -> 0 | O65: =IF(O90=0,-O77,0) -> 0 | P65: =IF(P90=0,-P77,0) -> 0 | Q65: =IF(Q90=0,-Q77,0) -> 0 | R65: =IF(R90=0,-R77,0) -> 0 | ... AX65: =IF(AX90=0,-AX77,0) -> 0
C66: Liquidation | H66: =SUM(K66:AX66) -> -750000 | K66: =IF(K$50=0,-SUM(K61:K63),0) -> 0 | L66: =IF(L$50=0,-SUM(L61:L63),0) -> 0 | M66: =IF(M$50=0,-SUM(M61:M63),0) -> 0 | N66: =IF(N$50=0,-SUM(N61:N63),0) -> 0 | O66: =IF(O$50=0,-SUM(O61:O63),0) -> 0 | P66: =IF(P$50=0,-SUM(P61:P63),0) -> 0 | Q66: =IF(Q$50=0,-SUM(Q61:Q63),0) -> 0 | R66: =IF(R$50=0,-SUM(R61:R63),0) -> 0 | ... AX66: =IF(AX$50=0,-SUM(AX61:AX63),0) -> 0
C67: Closing Balance | J67: =CaseData!$H$17 -> 750000 | K67: =SUM(K61:K66) -> 750000 | L67: =SUM(L61:L66) -> 750000 | M67: =SUM(M61:M66) -> 750000 | N67: =SUM(N61:N66) -> 750000 | O67: =SUM(O61:O66) -> 750000 | P67: =SUM(P61:P66) -> 750000 | Q67: =SUM(Q61:Q66) -> 750000 | R67: =SUM(R61:R66) -> 750000 | ... AX67: =SUM(AX61:AX66) -> 0
C69: Interest Rate | G69: =CaseData!H19 -> 0.01 | K69: =$G69 -> 0.01 | L69: =$G69 -> 0.01 | M69: =$G69 -> 0.01 | N69: =$G69 -> 0.01 | O69: =$G69 -> 0.01 | P69: =$G69 -> 0.01 | Q69: =$G69 -> 0.01 | R69: =$G69 -> 0.01 | ... AX69: =$G69 -> 0.01
C70: Interest Expense | H70: =SUM(K70:AX70) -> 60000 | K70: =K61*K69/4 -> 1875 | L70: =L61*L69/4 -> 1875 | M70: =M61*M69/4 -> 1875 | N70: =N61*N69/4 -> 1875 | O70: =O61*O69/4 -> 1875 | P70: =P61*P69/4 -> 1875 | Q70: =Q61*Q69/4 -> 1875 | R70: =R61*R69/4 -> 1875 | ... AX70: =AX61*AX69/4 -> 0
C72: Minimum Balance | G72: =CaseData!H18 -> 750000 | K72: =IF(K$48>0,$G72,0) -> 750000 | L72: =IF(L$48>0,$G72,0) -> 750000 | M72: =IF(M$48>0,$G72,0) -> 750000 | N72: =IF(N$48>0,$G72,0) -> 750000 | O72: =IF(O$48>0,$G72,0) -> 750000 | P72: =IF(P$48>0,$G72,0) -> 750000 | Q72: =IF(Q$48>0,$G72,0) -> 750000 | R72: =IF(R$48>0,$G72,0) -> 750000 | ... AX72: =IF(AX$48>0,$G72,0) -> 0
C73: Top Up Required | K73: =K72-SUM(K61:K62) -> 0 | L73: =L72-SUM(L61:L62) -> 0 | M73: =M72-SUM(M61:M62) -> 0 | N73: =N72-SUM(N61:N62) -> 0 | O73: =O72-SUM(O61:O62) -> 0 | P73: =P72-SUM(P61:P62) -> 0 | Q73: =Q72-SUM(Q61:Q62) -> 0 | R73: =R72-SUM(R61:R62) -> 0 | ... AX73: =AX72-SUM(AX61:AX62) -> 0
C74: Cash flow available | K74: =K29+K31 -> 588371.57 | L74: =L29+L31 -> 444242.57 | M74: =M29+M31 -> 531838.07 | N74: =N29+N31 -> 557507.57 | O74: =O29+O31 -> 600757.07 | P74: =P29+P31 -> 454540.07 | Q74: =Q29+Q31 -> 399295.07 | R74: =R29+R31 -> 269557.07 | ... AX74: =AX29+AX31 -> 1089577.5
C75: Top Up | K75: =MAX(MIN(K73,K74),0) -> 0 | L75: =MAX(MIN(L73,L74),0) -> 0 | M75: =MAX(MIN(M73,M74),0) -> 0 | N75: =MAX(MIN(N73,N74),0) -> 0 | O75: =MAX(MIN(O73,O74),0) -> 0 | P75: =MAX(MIN(P73,P74),0) -> 0 | Q75: =MAX(MIN(Q73,Q74),0) -> 0 | R75: =MAX(MIN(R73,R74),0) -> 0 | ... AX75: =MAX(MIN(AX73,AX74),0) -> 0
C77: Excess Funds to be Released | K77: =MAX(-K73,0) -> 0 | L77: =MAX(-L73,0) -> 0 | M77: =MAX(-M73,0) -> 0 | N77: =MAX(-N73,0) -> 0 | O77: =MAX(-O73,0) -> 0 | P77: =MAX(-P73,0) -> 0 | Q77: =MAX(-Q73,0) -> 0 | R77: =MAX(-R73,0) -> 0 | ... AX77: =MAX(-AX73,0) -> 0
B79: DSCR
C81: EBITDA | K81: =SUM($K23:K23) -> 1105141.5 | L81: =SUM($K23:L23) -> 2066154 | M81: =SUM($K23:M23) -> 3114762 | N81: =SUM(K23:N23) -> 4189039.5 | O81: =SUM(L23:O23) -> 4201425 | P81: =SUM(M23:P23) -> 4211722.5 | Q81: =SUM(N23:Q23) -> 4079179.5 | R81: =SUM(O23:R23) -> 3791229 | S81: =SUM(P23:S23) -> 3556324.5 | T81: =SUM(Q23:T23) -> 3686524.5 | U81: =SUM(R23:U23) -> 3822663 | ... AX81: =SUM(AU23:AX23) -> 4811595
C82: Interest Income | K82: =SUM($K24:K24) -> 1875 | L82: =SUM($K24:L24) -> 3750 | M82: =SUM($K24:M24) -> 5625 | N82: =SUM(K24:N24) -> 7500 | O82: =SUM(L24:O24) -> 7500 | P82: =SUM(M24:P24) -> 7500 | Q82: =SUM(N24:Q24) -> 7500 | R82: =SUM(O24:R24) -> 7500 | S82: =SUM(P24:S24) -> 7500 | T82: =SUM(Q24:T24) -> 7500 | U82: =SUM(R24:U24) -> 7500 | ... AX82: =SUM(AU24:AX24) -> 0
C84: Mortgage Interest | K84: =-SUM($K27:K27) -> 93750 | L84: =-SUM($K27:L27) -> 184844.41 | M84: =-SUM($K27:M27) -> 273266.62 | N84: =-SUM(K27:N27) -> 358999.95 | O84: =-SUM(L27:O27) -> 348277.57 | P84: =-SUM(M27:P27) -> 337488.18 | Q84: =-SUM(N27:Q27) -> 326631.36 | R84: =-SUM(O27:R27) -> 315706.69 | S84: =-SUM(P27:S27) -> 304713.73 | T84: =-SUM(Q27:T27) -> 293652.07 | U84: =-SUM(R27:U27) -> 282521.27 | ... AX84: =-SUM(AU27:AX27) -> 0
C85: Mortgage Principal | K85: =-SUM($K28:K28) -> 424894.93 | L85: =-SUM($K28:L28) -> 852445.45 | M85: =-SUM($K28:M28) -> 1282668.2 | N85: =-SUM(K28:N28) -> 1715579.8 | O85: =-SUM(L28:O28) -> 1726302.1 | P85: =-SUM(M28:P28) -> 1737091.5 | Q85: =-SUM(N28:Q28) -> 1747948.4 | R85: =-SUM(O28:R28) -> 1758873 | S85: =-SUM(P28:S28) -> 1769866 | T85: =-SUM(Q28:T28) -> 1780927.6 | U85: =-SUM(R28:U28) -> 1792058.4 | ... AX85: =-SUM(AU28:AX28) -> 0
C87: DSCR | K87: =IFERROR(SUM(K81:K82)/SUM(K84:K85),0) -> 2.13444 | L87: =IFERROR(SUM(L81:L82)/SUM(L84:L85),0) -> 1.9954924 | M87: =IFERROR(SUM(M81:M82)/SUM(M84:M85),0) -> 2.0054742 | N87: =IFERROR(SUM(N81:N82)/SUM(N84:N85),0) -> 2.0228384 | O87: =IFERROR(SUM(O81:O82)/SUM(O84:O85),0) -> 2.0288085 | P87: =IFERROR(SUM(P81:P82)/SUM(P84:P85),0) -> 2.0337722 | Q87: =IFERROR(SUM(Q81:Q82)/SUM(Q84:Q85),0) -> 1.9698831 | R87: =IFERROR(SUM(R81:R82)/SUM(R84:R85),0) -> 1.8310837 | ... AX87: =IFERROR(SUM(AX81:AX82)/SUM(AX84:AX85),0) -> 0
C88: Lock up Trigger | G88: =CaseData!H9 -> 1.7 | K88: =$G88 -> 1.7 | L88: =$G88 -> 1.7 | M88: =$G88 -> 1.7 | N88: =$G88 -> 1.7 | O88: =$G88 -> 1.7 | P88: =$G88 -> 1.7 | Q88: =$G88 -> 1.7 | R88: =$G88 -> 1.7 | ... AX88: =$G88 -> 1.7
C89: Trigger | K89: =IF(AND(K48>0,K87<K88),1,0) -> 0 | L89: =IF(AND(L48>0,L87<L88),1,0) -> 0 | M89: =IF(AND(M48>0,M87<M88),1,0) -> 0 | N89: =IF(AND(N48>0,N87<N88),1,0) -> 0 | O89: =IF(AND(O48>0,O87<O88),1,0) -> 0 | P89: =IF(AND(P48>0,P87<P88),1,0) -> 0 | Q89: =IF(AND(Q48>0,Q87<Q88),1,0) -> 0 | R89: =IF(AND(R48>0,R87<R88),1,0) -> 0 | ... AX89: =IF(AND(AX48>0,AX87<AX88),1,0) -> 0
C90: Lock up Flag | K90: =IF(SUM(J89:K89)>0,1,0) -> 0 | L90: =IF(SUM(K89:L89)>0,1,0) -> 0 | M90: =IF(SUM(L89:M89)>0,1,0) -> 0 | N90: =IF(SUM(M89:N89)>0,1,0) -> 0 | O90: =IF(SUM(N89:O89)>0,1,0) -> 0 | P90: =IF(SUM(O89:P89)>0,1,0) -> 0 | Q90: =IF(SUM(P89:Q89)>0,1,0) -> 0 | R90: =IF(SUM(Q89:R89)>0,1,0) -> 0 | ... AX90: =IF(SUM(AW89:AX89)>0,1,0) -> 0
B92: Junior Facility
C94: Opening Balance | K94: =J97 -> 9000000 | L94: =K97 -> 8775000 | M94: =L97 -> 8550000 | N94: =M97 -> 8325000 | O94: =N97 -> 8100000 | P94: =O97 -> 7875000 | Q94: =P97 -> 7650000 | R94: =Q97 -> 7425000 | ... AX94: =AW97 -> 225000
C95: Amortization | H95: =SUM(K95:AX95) -> -9000000 | K95: =-K102 -> -225000 | L95: =-L102 -> -225000 | M95: =-M102 -> -225000 | N95: =-N102 -> -225000 | O95: =-O102 -> -225000 | P95: =-P102 -> -225000 | Q95: =-Q102 -> -225000 | R95: =-R102 -> -225000 | ... AX95: =-AX102 -> -225000
C96: Repayment of Arrears | K96: =K109 -> 0 | L96: =L109 -> 0 | M96: =M109 -> 0 | N96: =N109 -> 0 | O96: =O109 -> 0 | P96: =P109 -> 0 | Q96: =Q109 -> 0 | R96: =R109 -> 0 | ... AX96: =AX109 -> 0
C97: Closing Balance | J97: =CaseData!$H$23 -> 9000000 | K97: =SUM(K94:K96) -> 8775000 | L97: =SUM(L94:L96) -> 8550000 | M97: =SUM(M94:M96) -> 8325000 | N97: =SUM(N94:N96) -> 8100000 | O97: =SUM(O94:O96) -> 7875000 | P97: =SUM(P94:P96) -> 7650000 | Q97: =SUM(Q94:Q96) -> 7425000 | R97: =SUM(R94:R96) -> 7200000 | ... AX97: =SUM(AX94:AX96) -> 0
C99: Target Amortization | G99: =CaseData!H25 -> 40 | H99: =SUM(K99:AX99) -> 9000000 | K99: =J97/G99 -> 225000 | L99: =K99 -> 225000 | M99: =L99 -> 225000 | N99: =M99 -> 225000 | O99: =N99 -> 225000 | P99: =O99 -> 225000 | Q99: =P99 -> 225000 | R99: =Q99 -> 225000 | S99: =R99 -> 225000 | ... AX99: =AW99 -> 225000
C100: Cash Flow Available | K100: =K38 -> 588371.57 | L100: =L38 -> 444242.57 | M100: =M38 -> 531838.07 | N100: =N38 -> 557507.57 | O100: =O38 -> 600757.07 | P100: =P38 -> 454540.07 | Q100: =Q38 -> 399295.07 | R100: =R38 -> 269557.07 | ... AX100: =AX38 -> 1089577.5
C102: Amortization | H102: =SUM(K102:AX102) -> 9000000 | K102: =MIN(K99,K100) -> 225000 | L102: =MIN(L99,L100) -> 225000 | M102: =MIN(M99,M100) -> 225000 | N102: =MIN(N99,N100) -> 225000 | O102: =MIN(O99,O100) -> 225000 | P102: =MIN(P99,P100) -> 225000 | Q102: =MIN(Q99,Q100) -> 225000 | R102: =MIN(R99,R100) -> 225000 | ... AX102: =MIN(AX99,AX100) -> 225000
C103: Arrears | H103: =SUM(K103:AX103) -> 0 | K103: =K99-K102 -> 0 | L103: =L99-L102 -> 0 | M103: =M99-M102 -> 0 | N103: =N99-N102 -> 0 | O103: =O99-O102 -> 0 | P103: =P99-P102 -> 0 | Q103: =Q99-Q102 -> 0 | R103: =R99-R102 -> 0 | ... AX103: =AX99-AX102 -> 0
C106: Arrears Amount Owed
D107: Opening Balance | K107: =J110 -> 0 | L107: =K110 -> 0 | M107: =L110 -> 0 | N107: =M110 -> 0 | O107: =N110 -> 0 | P107: =O110 -> 0 | Q107: =P110 -> 0 | R107: =Q110 -> 0 | ... AX107: =AW110 -> 0
D108: Additions | H108: =SUM(K108:AX108) -> 0 | K108: =K103 -> 0 | L108: =L103 -> 0 | M108: =M103 -> 0 | N108: =N103 -> 0 | O108: =O103 -> 0 | P108: =P103 -> 0 | Q108: =Q103 -> 0 | R108: =R103 -> 0 | ... AX108: =AX103 -> 0
D109: Repayment | H109: =SUM(K109:AX109) -> 0 | K109: =-MIN(K112,SUM(K107:K108)) -> 0 | L109: =-MIN(L112,SUM(L107:L108)) -> 0 | M109: =-MIN(M112,SUM(M107:M108)) -> 0 | N109: =-MIN(N112,SUM(N107:N108)) -> 0 | O109: =-MIN(O112,SUM(O107:O108)) -> 0 | P109: =-MIN(P112,SUM(P107:P108)) -> 0 | Q109: =-MIN(Q112,SUM(Q107:Q108)) -> 0 | R109: =-MIN(R112,SUM(R107:R108)) -> 0 | ... AX109: =-MIN(AX112,SUM(AX107:AX108)) -> 0
D110: Closing Balance | J110: 0 | K110: =SUM(K107:K109) -> 0 | L110: =SUM(L107:L109) -> 0 | M110: =SUM(M107:M109) -> 0 | N110: =SUM(N107:N109) -> 0 | O110: =SUM(O107:O109) -> 0 | P110: =SUM(P107:P109) -> 0 | Q110: =SUM(Q107:Q109) -> 0 | R110: =SUM(R107:R109) -> 0 | ... AX110: =SUM(AX107:AX109) -> 0
D112: Remaining cash flow for Arrears | K112: =K41 -> 363371.57 | L112: =L41 -> 219242.57 | M112: =M41 -> 306838.07 | N112: =N41 -> 332507.57 | O112: =O41 -> 375757.07 | P112: =P41 -> 229540.07 | Q112: =Q41 -> 174295.07 | R112: =R41 -> 44557.071 | ... AX112: =AX41 -> 864577.5
B115: Equity
C117: Cash Flow Date | J117: =J6 -> 44926 | K117: =K6 -> 45016 | L117: =L6 -> 45107 | M117: =M6 -> 45199 | N117: =N6 -> 45291 | O117: =O6 -> 45382 | P117: =P6 -> 45473 | Q117: =Q6 -> 45565 | ... AX117: =AX6 -> 48579
C119: Investment | H119: =SUM(K119:AX119) -> 0 | J119: =-CaseData!H30 -> -6000000 | K119: 0 | L119: 0 | M119: 0 | N119: 0 | O119: 0 | P119: 0 | Q119: 0 | R119: 0 | S119: 0 | T119: 0 | U119: 0 | V119: 0 | W119: 0 | X119: 0 | Y119: 0 | Z119: 0 | AA119: 0 | AB119: 0 | AC119: 0 | AD119: 0 | AE119: 0 | AF119: 0 | AG119: 0 | AH119: 0 | AI119: 0 | AJ119: 0 | AK119: 0 | AL119: 0 | AM119: 0 | AN119: 0 | AO119: 0 | AP119: 0 | AQ119: 0 | AR119: 0 | AS119: 0 | AT119: 0 | AU119: 0 | AV119: 0 | AW119: 0 | AX119: 0
C120: Cash flow to Equity | H120: =SUM(K120:AX120) -> 17683503 | J120: 0 | K120: =K44 -> 363371.57 | L120: =L44 -> 219242.57 | M120: =M44 -> 306838.07 | N120: =N44 -> 332507.57 | O120: =O44 -> 375757.07 | P120: =P44 -> 229540.07 | Q120: =Q44 -> 174295.07 | R120: =R44 -> 44557.071 | ... AX120: =AX44 -> 864577.5
C121: Total | H121: =SUM(K121:AX121) -> 17683503 | J121: =SUM(J119:J120) -> -6000000 | K121: =SUM(K119:K120) -> 363371.57 | L121: =SUM(L119:L120) -> 219242.57 | M121: =SUM(M119:M120) -> 306838.07 | N121: =SUM(N119:N120) -> 332507.57 | O121: =SUM(O119:O120) -> 375757.07 | P121: =SUM(P119:P120) -> 229540.07 | Q121: =SUM(Q119:Q120) -> 174295.07 | ... AX121: =SUM(AX119:AX120) -> 864577.5
