Workbook
Name company: LEFT(CaseData!$B$2, 28 )
Name topic: "CFM Topic: " & PROPER( MID(CaseData!$B$2, 32,5) )

Sheet Debt
A1: {=company} -> GRANITE BAY REAL ESTATE INC.
A2: {=topic} -> CFM Topic: Debt
A3: DEBT SCHEDULE | F3: Constant | G3: Unit | H3: Total | J3: =J$259 -> 2024 | K3: =K$259 -> 2025 | L3: =L$259 -> 2026 | M3: =M$259 -> 2027 | N3: =N$259 -> 2028 | O3: =O$259 -> 2029 | P3: =P$259 -> 2030 | Q3: =Q$259 -> 2031 | ... S3: =S$259 -> 2033
A5: Cash Flow Waterfall
C7: Free Cash Flow before Debt Service
E8: =E$110 -> Construction Loan I drawdown | G8: =G$110 -> USD | J8: =J$110 * -1 -> -3500000 | K8: =K$110 * -1 -> 0 | L8: =L$110 * -1 -> 0 | M8: =M$110 * -1 -> 0 | N8: =N$110 * -1 -> 0 | O8: =O$110 * -1 -> 0 | P8: =P$110 * -1 -> 0 | Q8: =Q$110 * -1 -> 0 | ... S8: =S$110 * -1 -> 0
E9: =E$98 -> Free Cash Flow before Debt Service - Property I | G9: =G$98 -> USD | I9: =I$98 -> 0 | J9: =J$98 -> 0 | K9: =K$98 -> 625000 | L9: =L$98 -> 1312500 | M9: =M$98 -> 1378125 | N9: =N$98 -> 1447031.3 | O9: =O$98 -> 1483207 | P9: =P$98 -> 1520287.2 | ... S9: =S$98 -> 1637183
E10: FCF before Debt Service - Property I | G10: USD | J10: =SUM(J8:J9) -> -3500000 | K10: =SUM(K8:K9) -> 625000 | L10: =SUM(L8:L9) -> 1312500 | M10: =SUM(M8:M9) -> 1378125 | N10: =SUM(N8:N9) -> 1447031.3 | O10: =SUM(O8:O9) -> 1483207 | P10: =SUM(P8:P9) -> 1520287.2 | Q10: =SUM(Q8:Q9) -> 1558294.4 | ... S10: =SUM(S8:S9) -> 1637183
E12: =E$153 -> Construction Loan II drawdown | G12: =G$153 -> USD | I12: =I$153 -> 0 | J12: =J$153 * - 1 -> 0 | K12: =K$153 * - 1 -> -4166666.7 | L12: =L$153 * - 1 -> -4166666.7 | M12: =M$153 * - 1 -> -4166666.7 | N12: =N$153 * - 1 -> 0 | O12: =O$153 * - 1 -> 0 | P12: =P$153 * - 1 -> 0 | Q12: =Q$153 * - 1 -> 0 | ... S12: =S$153 * - 1 -> 0
E13: Proceeds from sale of Property II | G13: USD | J13: =IF( J3 = CaseData!$G$36, CaseData!$G$37, 0 ) -> 0 | K13: =IF( K3 = CaseData!$G$36, CaseData!$G$37, 0 ) -> 0 | L13: =IF( L3 = CaseData!$G$36, CaseData!$G$37, 0 ) -> 0 | M13: =IF( M3 = CaseData!$G$36, CaseData!$G$37, 0 ) -> 18750000 | N13: =IF( N3 = CaseData!$G$36, CaseData!$G$37, 0 ) -> 0 | O13: =IF( O3 = CaseData!$G$36, CaseData!$G$37, 0 ) -> 0 | P13: =IF( P3 = CaseData!$G$36, CaseData!$G$37, 0 ) -> 0 | Q13: =IF( Q3 = CaseData!$G$36, CaseData!$G$37, 0 ) -> 0 | ... S13: =IF( S3 = CaseData!$G$36, CaseData!$G$37, 0 ) -> 0
E14: FCF before Debt Service - Property II | G14: USD | J14: =SUM(J12:J13) -> 0 | K14: =SUM(K12:K13) -> -4166666.7 | L14: =SUM(L12:L13) -> -4166666.7 | M14: =SUM(M12:M13) -> 14583333 | N14: =SUM(N12:N13) -> 0 | O14: =SUM(O12:O13) -> 0 | P14: =SUM(P12:P13) -> 0 | Q14: =SUM(Q12:Q13) -> 0 | ... S14: =SUM(S12:S13) -> 0
E16: FCF before Debt Service | G16: USD | J16: =SUM( J10, J14) -> -3500000 | K16: =SUM( K10, K14) -> -3541666.7 | L16: =SUM( L10, L14) -> -2854166.7 | M16: =SUM( M10, M14) -> 15961458 | N16: =SUM( N10, N14) -> 1447031.3 | O16: =SUM( O10, O14) -> 1483207 | P16: =SUM( P10, P14) -> 1520287.2 | Q16: =SUM( Q10, Q14) -> 1558294.4 | ... S16: =SUM( S10, S14) -> 1637183
C18: Free Cash Flow before the Use of Cash and Revolver
E19: =E$16 -> FCF before Debt Service | G19: =G$16 -> USD | I19: =I$16 -> 0 | J19: =J$16 -> -3500000 | K19: =K$16 -> -3541666.7 | L19: =L$16 -> -2854166.7 | M19: =M$16 -> 15961458 | N19: =N$16 -> 1447031.3 | O19: =O$16 -> 1483207 | P19: =P$16 -> 1520287.2 | ... S19: =S$16 -> 1637183
E20: Interest paid | G20: USD | J20: =J$239 * - 1 -> -188873.24 | K20: =K$239 * - 1 -> -378321.39 | L20: =L$239 * - 1 -> -368400.36 | M20: =M$239 * - 1 -> -327594.15 | N20: =N$239 * - 1 -> -252253.51 | O20: =O$239 * - 1 -> -185014.07 | P20: =P$239 * - 1 -> -147362.02 | Q20: =Q$239 * - 1 -> -123893.39 | ... S20: =S$239 * - 1 -> -73933.725
E21: =CaseSolution!C147 -> Construction Debt Issuance (excl . Interest) | G21: USD | J21: =SUM( J$110, J$153 ) -> 3500000 | K21: =SUM( K$110, K$153 ) -> 4166666.7 | L21: =SUM( L$110, L$153 ) -> 4166666.7 | M21: =SUM( M$110, M$153 ) -> 4166666.7 | N21: =SUM( N$110, N$153 ) -> 0 | O21: =SUM( O$110, O$153 ) -> 0 | P21: =SUM( P$110, P$153 ) -> 0 | Q21: =SUM( Q$110, Q$153 ) -> 0 | ... S21: =SUM( S$110, S$153 ) -> 0
E22: =CaseSolution!C148 -> Construction Debt Retirement | G22: USD | J22: =SUM( J$119, J$162 ) -> -7426300 | K22: =SUM( K$119, K$162 ) -> 0 | L22: =SUM( L$119, L$162 ) -> 0 | M22: =SUM( M$119, M$162 ) -> -13563107 | N22: =SUM( N$119, N$162 ) -> 0 | O22: =SUM( O$119, O$162 ) -> 0 | P22: =SUM( P$119, P$162 ) -> 0 | Q22: =SUM( Q$119, Q$162 ) -> 0 | ... S22: =SUM( S$119, S$162 ) -> 0
E23: =CaseSolution!C149 -> Mortgage Issuance | G23: USD | J23: =IF( J3 = $F$124, $F$125, 0 ) -> 7426300 | K23: =IF( K3 = $F$124, $F$125, 0 ) -> 0 | L23: =IF( L3 = $F$124, $F$125, 0 ) -> 0 | M23: =IF( M3 = $F$124, $F$125, 0 ) -> 0 | N23: =IF( N3 = $F$124, $F$125, 0 ) -> 0 | O23: =IF( O3 = $F$124, $F$125, 0 ) -> 0 | P23: =IF( P3 = $F$124, $F$125, 0 ) -> 0 | Q23: =IF( Q3 = $F$124, $F$125, 0 ) -> 0 | ... S23: =IF( S3 = $F$124, $F$125, 0 ) -> 0
E24: =CaseSolution!C150 -> Mortgage Principal Payment | G24: USD | J24: =J$132 * - 1 -> 0 | K24: =K$132 * - 1 -> -217411.77 | L24: =L$132 * - 1 -> -222847.07 | M24: =M$132 * - 1 -> -228418.24 | N24: =N$132 * - 1 -> -234128.7 | O24: =O$132 * - 1 -> -239981.92 | P24: =P$132 * - 1 -> -245981.46 | Q24: =Q$132 * - 1 -> -252131 | ... S24: =S$132 * - 1 -> -264895.13
E26: Free Cash Flow before the Use of Cash and Revolver | G26: USD | J26: =SUM(J19:J24) -> -188873.24 | K26: =SUM(K19:K24) -> 29266.836 | L26: =SUM(L19:L24) -> 721252.58 | M26: =SUM(M19:M24) -> 6009005.6 | N26: =SUM(N19:N24) -> 960649.04 | O26: =SUM(O19:O24) -> 1058211 | P26: =SUM(P19:P24) -> 1126943.7 | Q26: =SUM(Q19:Q24) -> 1182270 | ... S26: =SUM(S19:S24) -> 1298354.2
E28: =E$57 -> Revolver addition / (repayment) | G28: =G$57 -> USD | I28: =I$57 -> 0 | J28: =J$57 -> 188873.24 | K28: =K$57 -> -29266.836 | L28: =L$57 -> -159606.4 | M28: =M$57 -> 0 | N28: =N$57 -> 0 | O28: =O$57 -> 0 | P28: =P$57 -> 0 | ... S28: =S$57 -> 0
C30: Existing Debt Repayment
E32: Cash Available to Pay Existing Debt | G32: =G$57 -> USD | J32: =J26 + J28 -> 0 | K32: =K26 + K28 -> 0 | L32: =L26 + L28 -> 561646.17 | M32: =M26 + M28 -> 6009005.6 | N32: =N26 + N28 -> 960649.04 | O32: =O26 + O28 -> 1058211 | P32: =P26 + P28 -> 1126943.7 | Q32: =Q26 + Q28 -> 1182270 | ... S32: =S26 + S28 -> 1298354.2
E33: =E$248 -> Existing Debt Repayment | F33: =F$248 -> 0 | G33: =G$248 -> USD | H33: =H$248 -> 0 | I33: =I$248 -> 0 | J33: =J$248 -> 0 | K33: =K$248 -> 0 | L33: =L$248 -> -561646.17 | ... S33: =S$248 -> 0
E34: Net change in cash | G34: USD | J34: =SUM(J32:J33) -> 0 | K34: =SUM(K32:K33) -> 0 | L34: =SUM(L32:L33) -> 0 | M34: =SUM(M32:M33) -> 0 | N34: =SUM(N32:N33) -> 0 | O34: =SUM(O32:O33) -> 584913.67 | P34: =SUM(P32:P33) -> 1126943.7 | Q34: =SUM(Q32:Q33) -> 1182270 | ... S34: =SUM(S32:S33) -> 1298354.2
A37: Cash and Revolver
C39: Cash and Cash equivalents
E41: Cash and Cash equivalents initial balance from assumptions | F41: =CaseData!$O$19 -> 0 | G41: USD
E43: Cash and Cash equivalents opening balance | G43: USD | J43: =I45 -> 0 | K43: =J45 -> 0 | L43: =K45 -> 0 | M43: =L45 -> 0 | N43: =M45 -> 0 | O43: =N45 -> 0 | P43: =O45 -> 584913.67 | Q43: =P45 -> 1711857.4 | ... S43: =R45 -> 4133517.2
E44: Net Change in Cash | G44: USD | J44: =J$34 -> 0 | K44: =K$34 -> 0 | L44: =L$34 -> 0 | M44: =M$34 -> 0 | N44: =N$34 -> 0 | O44: =O$34 -> 584913.67 | P44: =P$34 -> 1126943.7 | Q44: =Q$34 -> 1182270 | ... S44: =S$34 -> 1298354.2
E45: Cash and Cash equivalents closing balance | G45: USD | I45: =F41 -> 0 | J45: =SUM(J43:J44) -> 0 | K45: =SUM(K43:K44) -> 0 | L45: =SUM(L43:L44) -> 0 | M45: =SUM(M43:M44) -> 0 | N45: =SUM(N43:N44) -> 0 | O45: =SUM(O43:O44) -> 584913.67 | P45: =SUM(P43:P44) -> 1711857.4 | Q45: =SUM(Q43:Q44) -> 2894127.4 | ... S45: =SUM(S43:S44) -> 5431871.4
D47: Interest earned on cash balance
E48: =CaseData!J$21 -> Interest Rate | F48: =CaseData!O$21 -> 0.015 | G48: %
E49: Interest earned on cash balance | G49: USD | J49: =AVERAGE( J$43, J$45 ) * $F$48 -> 0 | K49: =AVERAGE( K$43, K$45 ) * $F$48 -> 0 | L49: =AVERAGE( L$43, L$45 ) * $F$48 -> 0 | M49: =AVERAGE( M$43, M$45 ) * $F$48 -> 0 | N49: =AVERAGE( N$43, N$45 ) * $F$48 -> 0 | O49: =AVERAGE( O$43, O$45 ) * $F$48 -> 4386.8525 | P49: =AVERAGE( P$43, P$45 ) * $F$48 -> 17225.783 | Q49: =AVERAGE( Q$43, Q$45 ) * $F$48 -> 34544.886 | ... S49: =AVERAGE( S$43, S$45 ) * $F$48 -> 71740.414
C52: Revolver
E54: Revolver initial balance from assumptions | F54: =CaseData!$Q$19 -> 0 | G54: USD
E56: Revolver opening balance | G56: USD | J56: =I$58 -> 0 | K56: =J$58 -> 188873.24 | L56: =K$58 -> 159606.4 | M56: =L$58 -> 0 | N56: =M$58 -> 0 | O56: =N$58 -> 0 | P56: =O$58 -> 0 | Q56: =P$58 -> 0 | ... S56: =R$58 -> 0
E57: Revolver addition / (repayment) | G57: USD | J57: =MAX( - MIN( SUM( J26, J43 ), J56 ), - J$67 ) -> 188873.24 | K57: =MAX( - MIN( SUM( K26, K43 ), K56 ), - K$67 ) -> -29266.836 | L57: =MAX( - MIN( SUM( L26, L43 ), L56 ), - L$67 ) -> -159606.4 | M57: =MAX( - MIN( SUM( M26, M43 ), M56 ), - M$67 ) -> 0 | N57: =MAX( - MIN( SUM( N26, N43 ), N56 ), - N$67 ) -> 0 | O57: =MAX( - MIN( SUM( O26, O43 ), O56 ), - O$67 ) -> 0 | P57: =MAX( - MIN( SUM( P26, P43 ), P56 ), - P$67 ) -> 0 | Q57: =MAX( - MIN( SUM( Q26, Q43 ), Q56 ), - Q$67 ) -> 0 | ... S57: =MAX( - MIN( SUM( S26, S43 ), S56 ), - S$67 ) -> 0
E58: Revolver closing balance | G58: USD | I58: =F54 -> 0 | J58: =SUM(J56:J57) -> 188873.24 | K58: =SUM(K56:K57) -> 159606.4 | L58: =SUM(L56:L57) -> 0 | M58: =SUM(M56:M57) -> 0 | N58: =SUM(N56:N57) -> 0 | O58: =SUM(O56:O57) -> 0 | P58: =SUM(P56:P57) -> 0 | Q58: =SUM(Q56:Q57) -> 0 | ... S58: =SUM(S56:S57) -> 0
D60: Interest expenses on revolver
E61: =CaseData!J$21 -> Interest Rate | F61: =CaseData!$Q$21 -> 0.055 | G61: %
E62: Interest expenses on revolver | G62: USD | J62: =AVERAGE( J56,J58 ) * $F$61 -> 5194.0141 | K62: =AVERAGE( K56,K58 ) * $F$61 -> 9583.1902 | L62: =AVERAGE( L56,L58 ) * $F$61 -> 4389.1761 | M62: =AVERAGE( M56,M58 ) * $F$61 -> 0 | N62: =AVERAGE( N56,N58 ) * $F$61 -> 0 | O62: =AVERAGE( O56,O58 ) * $F$61 -> 0 | P62: =AVERAGE( P56,P58 ) * $F$61 -> 0 | Q62: =AVERAGE( Q56,Q58 ) * $F$61 -> 0 | ... S62: =AVERAGE( S56,S58 ) * $F$61 -> 0
D64: Stand-by fee
E65: Undrawn revolver amount initial balance from assumptions | F65: =CaseData!$Q$20 -> 1000000 | G65: USD
E67: Undrawn revolver amount opening balance | G67: USD | J67: =I$69 -> 1000000 | K67: =J$69 -> 811126.76 | L67: =K$69 -> 840393.6 | M67: =L$69 -> 1000000 | N67: =M$69 -> 1000000 | O67: =N$69 -> 1000000 | P67: =O$69 -> 1000000 | Q67: =P$69 -> 1000000 | ... S67: =R$69 -> 1000000
E68: Drawn amount | G68: USD | J68: =- J57 -> -188873.24 | K68: =- K57 -> 29266.836 | L68: =- L57 -> 159606.4 | M68: =- M57 -> 0 | N68: =- N57 -> 0 | O68: =- O57 -> 0 | P68: =- P57 -> 0 | Q68: =- Q57 -> 0 | ... S68: =- S57 -> 0
E69: Undrawn revolver amount closing balance | G69: USD | I69: =F65 -> 1000000 | J69: =SUM(J67:J68) -> 811126.76 | K69: =SUM(K67:K68) -> 840393.6 | L69: =SUM(L67:L68) -> 1000000 | M69: =SUM(M67:M68) -> 1000000 | N69: =SUM(N67:N68) -> 1000000 | O69: =SUM(O67:O68) -> 1000000 | P69: =SUM(P67:P68) -> 1000000 | Q69: =SUM(Q67:Q68) -> 1000000 | ... S69: =SUM(S67:S68) -> 1000000
E71: Stand-by fee rate | F71: =CaseData!Q$22 -> 0.0075 | G71: %
E72: Stand-by fee on undrawn amount | G72: USD | J72: =AVERAGE( J67, J69 ) * $F$71 -> 6791.7254 | K72: =AVERAGE( K67, K69 ) * $F$71 -> 6193.2013 | L72: =AVERAGE( L67, L69 ) * $F$71 -> 6901.476 | M72: =AVERAGE( M67, M69 ) * $F$71 -> 7500 | N72: =AVERAGE( N67, N69 ) * $F$71 -> 7500 | O72: =AVERAGE( O67, O69 ) * $F$71 -> 7500 | P72: =AVERAGE( P67, P69 ) * $F$71 -> 7500 | Q72: =AVERAGE( Q67, Q69 ) * $F$71 -> 7500 | ... S72: =AVERAGE( S67, S69 ) * $F$71 -> 7500
C75: Interest expenses
E76: =E$49 -> Interest earned on cash balance | F76: =F$49 -> 0 | G76: =G$49 -> USD | H76: =H$49 -> 0 | I76: =I$49 -> 0 | J76: =J$49 * - 1 -> 0 | K76: =K$49 * - 1 -> 0 | L76: =L$49 * - 1 -> 0 | M76: =M$49 * - 1 -> 0 | N76: =N$49 * - 1 -> 0 | O76: =O$49 * - 1 -> -4386.8525 | P76: =P$49 * - 1 -> -17225.783 | Q76: =Q$49 * - 1 -> -34544.886 | ... S76: =S$49 * - 1 -> -71740.414
E77: =E$62 -> Interest expenses on revolver | F77: =F$62 -> 0 | G77: =G$62 -> USD | H77: =H$62 -> 0 | I77: =I$62 -> 0 | J77: =J$62 -> 5194.0141 | K77: =K$62 -> 9583.1902 | L77: =L$62 -> 4389.1761 | ... S77: =S$62 -> 0
E78: =E$72 -> Stand-by fee on undrawn amount | F78: =F$72 -> 0 | G78: =G$72 -> USD | H78: =H$72 -> 0 | I78: =I$72 -> 0 | J78: =J$72 -> 6791.7254 | K78: =K$72 -> 6193.2013 | L78: =L$72 -> 6901.476 | ... S78: =S$72 -> 7500
E79: Net interest expenses on revolver | G79: USD | J79: =SUM(J76:J78) -> 11985.739 | K79: =SUM(K76:K78) -> 15776.392 | L79: =SUM(L76:L78) -> 11290.652 | M79: =SUM(M76:M78) -> 7500 | N79: =SUM(N76:N78) -> 7500 | O79: =SUM(O76:O78) -> 3113.1475 | P79: =SUM(P76:P78) -> -9725.7829 | Q79: =SUM(Q76:Q78) -> -27044.886 | ... S79: =SUM(S76:S78) -> -64240.414
A82: Property I
C85: Free cash flow before Debt Service - Property I
E86: =CaseData!C$19 -> Start Year | F86: =CaseData!$G$19 -> 2025 | G86: year
E87: =CaseData!C$20 -> Free Cash Flow Before Debt Service | F87: =CaseData!G$20 -> 1250000 | G87: USD
E89: =CaseData!C$21 -> Occupancy Rate (2025 - 2025) | F89: =CaseData!$G$21 -> 0.5 | G89: % | I89: 2025
E90: =CaseData!C$22 -> Occupancy Rate in 2026 and Beyond | F90: =CaseData!G$22 -> 1 | G90: % | I90: 2026
E91: Occupancy rate | G91: % | J91: =_xlfn.XLOOKUP( J$3, $I$89:$I$90, $F$89:$F$90, 0, - 1 ) -> 0 | K91: =_xlfn.XLOOKUP( K$3, $I$89:$I$90, $F$89:$F$90, 0, - 1 ) -> 0.5 | L91: =_xlfn.XLOOKUP( L$3, $I$89:$I$90, $F$89:$F$90, 0, - 1 ) -> 1 | M91: =_xlfn.XLOOKUP( M$3, $I$89:$I$90, $F$89:$F$90, 0, - 1 ) -> 1 | N91: =_xlfn.XLOOKUP( N$3, $I$89:$I$90, $F$89:$F$90, 0, - 1 ) -> 1 | O91: =_xlfn.XLOOKUP( O$3, $I$89:$I$90, $F$89:$F$90, 0, - 1 ) -> 1 | P91: =_xlfn.XLOOKUP( P$3, $I$89:$I$90, $F$89:$F$90, 0, - 1 ) -> 1 | Q91: =_xlfn.XLOOKUP( Q$3, $I$89:$I$90, $F$89:$F$90, 0, - 1 ) -> 1 | ... S91: =_xlfn.XLOOKUP( S$3, $I$89:$I$90, $F$89:$F$90, 0, - 1 ) -> 1
E93: =CaseData!C$23 -> Growth Rate (2026 - 2028) | F93: =CaseData!$G$23 -> 0.05 | G93: % | I93: 2026
E94: =CaseData!C$24 -> Growth Rate 2029 and Beyond | F94: =CaseData!$G$24 -> 0.025 | G94: % | I94: 2029
E95: Nominal growth rates | G95: factor | J95: =_xlfn.XLOOKUP( J$3, $I$93:$I$94, $F$93:$F$94, 0, - 1 ) -> 0 | K95: =_xlfn.XLOOKUP( K$3, $I$93:$I$94, $F$93:$F$94, 0, - 1 ) -> 0 | L95: =_xlfn.XLOOKUP( L$3, $I$93:$I$94, $F$93:$F$94, 0, - 1 ) -> 0.05 | M95: =_xlfn.XLOOKUP( M$3, $I$93:$I$94, $F$93:$F$94, 0, - 1 ) -> 0.05 | N95: =_xlfn.XLOOKUP( N$3, $I$93:$I$94, $F$93:$F$94, 0, - 1 ) -> 0.05 | O95: =_xlfn.XLOOKUP( O$3, $I$93:$I$94, $F$93:$F$94, 0, - 1 ) -> 0.025 | P95: =_xlfn.XLOOKUP( P$3, $I$93:$I$94, $F$93:$F$94, 0, - 1 ) -> 0.025 | Q95: =_xlfn.XLOOKUP( Q$3, $I$93:$I$94, $F$93:$F$94, 0, - 1 ) -> 0.025 | ... S95: =_xlfn.XLOOKUP( S$3, $I$93:$I$94, $F$93:$F$94, 0, - 1 ) -> 0.025
E96: Compound growth rates (yoy) | G96: factor | J96: {=_xlfn.LET( _xlpm.rates, $J$95:$S$95, _xlfn.MAKEARRAY( ROWS( 1 ), COLUMNS( _xlpm.rates ), _xlfn.LAMBDA(_xlpm.i,_xlpm.j, INDEX( _xlfn.SCAN( 1, INDEX( _xlpm.rates, _xlpm.i, 0 ), _xlfn.LAMBDA(_xlpm.s,_xlpm.c, _xlpm.s * ( 1 + _xlpm.c ) ) ), _xlpm.j ) ) ) )} -> 1 | K96: 1 | L96: 1.05 | M96: 1.1025 | N96: 1.157625 | O96: 1.1865656 | P96: 1.2162298 | Q96: 1.2466355 | R96: 1.2778014 | S96: 1.3097464
E98: Free Cash Flow before Debt Service - Property I | G98: USD | J98: =IF( J$3 >= $F$86, $F$87 * J$91 * J$96, 0 ) -> 0 | K98: =IF( K$3 >= $F$86, $F$87 * K$91 * K$96, 0 ) -> 625000 | L98: =IF( L$3 >= $F$86, $F$87 * L$91 * L$96, 0 ) -> 1312500 | M98: =IF( M$3 >= $F$86, $F$87 * M$91 * M$96, 0 ) -> 1378125 | N98: =IF( N$3 >= $F$86, $F$87 * N$91 * N$96, 0 ) -> 1447031.3 | O98: =IF( O$3 >= $F$86, $F$87 * O$91 * O$96, 0 ) -> 1483207 | P98: =IF( P$3 >= $F$86, $F$87 * P$91 * P$96, 0 ) -> 1520287.2 | Q98: =IF( Q$3 >= $F$86, $F$87 * Q$91 * Q$96, 0 ) -> 1558294.4 | ... S98: =IF( S$3 >= $F$86, $F$87 * S$91 * S$96, 0 ) -> 1637183
C101: Construction Loan - Property I
E102: Issuance date | F102: =CaseData!$O$31 -> 2023 | G102: date
E103: =CaseData!J$32 -> Payment / Term | F103: =CaseData!O$32 -> 2024 | G103: date
E104: Loan amount | F104: =CaseData!$O$33 -> 7000000 | G104: USD
E106: Amount drawn in 2023 | F106: =CaseData!$O$34 -> 3500000 | G106: USD
E107: Accrued interest in 2023 | F107: =AVERAGE( 0, $F$106 ) * $F$114 -> 105000 | G107: USD
E109: Construction Loan I opening balance | G109: USD | J109: =IF( J3 <= $F$103, I$111, 0 ) -> 3605000 | K109: =IF( K3 <= $F$103, J$111, 0 ) -> 0 | L109: =IF( L3 <= $F$103, K$111, 0 ) -> 0 | M109: =IF( M3 <= $F$103, L$111, 0 ) -> 0 | N109: =IF( N3 <= $F$103, M$111, 0 ) -> 0 | O109: =IF( O3 <= $F$103, N$111, 0 ) -> 0 | P109: =IF( P3 <= $F$103, O$111, 0 ) -> 0 | Q109: =IF( Q3 <= $F$103, P$111, 0 ) -> 0 | ... S109: =IF( S3 <= $F$103, R$111, 0 ) -> 0
E110: Construction Loan I drawdown | G110: USD | J110: =IF( J3 <= $F$103, $F$104 - $F$106, 0 ) -> 3500000 | K110: =IF( K3 <= $F$103, $F$104 - $F$106, 0 ) -> 0 | L110: =IF( L3 <= $F$103, $F$104 - $F$106, 0 ) -> 0 | M110: =IF( M3 <= $F$103, $F$104 - $F$106, 0 ) -> 0 | N110: =IF( N3 <= $F$103, $F$104 - $F$106, 0 ) -> 0 | O110: =IF( O3 <= $F$103, $F$104 - $F$106, 0 ) -> 0 | P110: =IF( P3 <= $F$103, $F$104 - $F$106, 0 ) -> 0 | Q110: =IF( Q3 <= $F$103, $F$104 - $F$106, 0 ) -> 0 | ... S110: =IF( S3 <= $F$103, $F$104 - $F$106, 0 ) -> 0
E111: Construction Loan - Property I amount outstanding before servicing | G111: USD | I111: =SUM( $F$106:$F$107 ) -> 3605000 | J111: =SUM(J109:J110) -> 7105000 | K111: =SUM(K109:K110) -> 0 | L111: =SUM(L109:L110) -> 0 | M111: =SUM(M109:M110) -> 0 | N111: =SUM(N109:N110) -> 0 | O111: =SUM(O109:O110) -> 0 | P111: =SUM(P109:P110) -> 0 | Q111: =SUM(Q109:Q110) -> 0 | ... S111: =SUM(S109:S110) -> 0
D113: Accrued interest expenses
E114: Interest rate | F114: =CaseData!$O$35 -> 0.06 | G114: %
E115: Accrued interest | G115: USD | J115: =IF( J257 = 1, AVERAGE( J109, J111 ) * $F$114, 0 ) -> 321300 | K115: =IF( K257 = 1, AVERAGE( K109, K111 ) * $F$114, 0 ) -> 0 | L115: =IF( L257 = 1, AVERAGE( L109, L111 ) * $F$114, 0 ) -> 0 | M115: =IF( M257 = 1, AVERAGE( M109, M111 ) * $F$114, 0 ) -> 0 | N115: =IF( N257 = 1, AVERAGE( N109, N111 ) * $F$114, 0 ) -> 0 | O115: =IF( O257 = 1, AVERAGE( O109, O111 ) * $F$114, 0 ) -> 0 | P115: =IF( P257 = 1, AVERAGE( P109, P111 ) * $F$114, 0 ) -> 0 | Q115: =IF( Q257 = 1, AVERAGE( Q109, Q111 ) * $F$114, 0 ) -> 0 | ... S115: =IF( S257 = 1, AVERAGE( S109, S111 ) * $F$114, 0 ) -> 0
E116: Construction Loan - Property I amount outstanding before retirement | G116: USD | J116: =J111 + J115 -> 7426300 | K116: =K111 + K115 -> 0 | L116: =L111 + L115 -> 0 | M116: =M111 + M115 -> 0 | N116: =N111 + N115 -> 0 | O116: =O111 + O115 -> 0 | P116: =P111 + P115 -> 0 | Q116: =Q111 + Q115 -> 0 | ... S116: =S111 + S115 -> 0
D118: Retirement
E119: Construction Loan - Property I repayment | G119: USD | J119: =IF( J3 = $F$103, - J$116, 0 ) -> -7426300 | K119: =IF( K3 = $F$103, - K$116, 0 ) -> 0 | L119: =IF( L3 = $F$103, - L$116, 0 ) -> 0 | M119: =IF( M3 = $F$103, - M$116, 0 ) -> 0 | N119: =IF( N3 = $F$103, - N$116, 0 ) -> 0 | O119: =IF( O3 = $F$103, - O$116, 0 ) -> 0 | P119: =IF( P3 = $F$103, - P$116, 0 ) -> 0 | Q119: =IF( Q3 = $F$103, - Q$116, 0 ) -> 0 | ... S119: =IF( S3 = $F$103, - S$116, 0 ) -> 0
E120: Construction Loan - Property I amount outstanding after retirement | J120: =J116 + J119 -> 0 | K120: =K116 + K119 -> 0 | L120: =L116 + L119 -> 0 | M120: =M116 + M119 -> 0 | N120: =N116 + N119 -> 0 | O120: =O116 + O119 -> 0 | P120: =P116 + P119 -> 0 | Q120: =Q116 + Q119 -> 0 | ... S120: =S116 + S119 -> 0
C123: Mortgage Loan - Property I
E124: Issuance date | F124: =CaseData!$S$31 -> 2024 | G124: year
E125: Mortgage loan amount | F125: =- J119 -> 7426300 | G125: USD
E126: Interest rate | F126: =CaseData!$S$35 -> 0.025 | G126: %
E127: Term | F127: =CaseData!$S$32 -> 25 | G127: years
D129: Annual payment
E130: Mortgage Loan annual payment | G130: USD | J130: =IF( J3 >= $F$124 + 1, PMT( $F$126, $F$127, $F$125 ) * - 1, 0 ) -> 0 | K130: =IF( K3 >= $F$124 + 1, PMT( $F$126, $F$127, $F$125 ) * - 1, 0 ) -> 403069.27 | L130: =IF( L3 >= $F$124 + 1, PMT( $F$126, $F$127, $F$125 ) * - 1, 0 ) -> 403069.27 | M130: =IF( M3 >= $F$124 + 1, PMT( $F$126, $F$127, $F$125 ) * - 1, 0 ) -> 403069.27 | N130: =IF( N3 >= $F$124 + 1, PMT( $F$126, $F$127, $F$125 ) * - 1, 0 ) -> 403069.27 | O130: =IF( O3 >= $F$124 + 1, PMT( $F$126, $F$127, $F$125 ) * - 1, 0 ) -> 403069.27 | P130: =IF( P3 >= $F$124 + 1, PMT( $F$126, $F$127, $F$125 ) * - 1, 0 ) -> 403069.27 | Q130: =IF( Q3 >= $F$124 + 1, PMT( $F$126, $F$127, $F$125 ) * - 1, 0 ) -> 403069.27 | ... S130: =IF( S3 >= $F$124 + 1, PMT( $F$126, $F$127, $F$125 ) * - 1, 0 ) -> 403069.27
E131: of which interest paid | G131: USD | J131: =J$137 * $F$126 -> 0 | K131: =K$137 * $F$126 -> 185657.5 | L131: =L$137 * $F$126 -> 180222.21 | M131: =M$137 * $F$126 -> 174651.03 | N131: =N$137 * $F$126 -> 168940.57 | O131: =O$137 * $F$126 -> 163087.36 | P131: =P$137 * $F$126 -> 157087.81 | Q131: =Q$137 * $F$126 -> 150938.27 | ... S131: =S$137 * $F$126 -> 138174.14
E132: of which principal paid | G132: USD | J132: =J130 - J131 -> 0 | K132: =K130 - K131 -> 217411.77 | L132: =L130 - L131 -> 222847.07 | M132: =M130 - M131 -> 228418.24 | N132: =N130 - N131 -> 234128.7 | O132: =O130 - O131 -> 239981.92 | P132: =P130 - P131 -> 245981.46 | Q132: =Q130 - Q131 -> 252131 | ... S132: =S130 - S131 -> 264895.13
E133: Check | G133: USD | J133: =J130-SUM(J131:J132) -> 0 | K133: =K130-SUM(K131:K132) -> 0 | L133: =L130-SUM(L131:L132) -> 0 | M133: =M130-SUM(M131:M132) -> 0 | N133: =N130-SUM(N131:N132) -> 0 | O133: =O130-SUM(O131:O132) -> 0 | P133: =P130-SUM(P131:P132) -> 0 | Q133: =Q130-SUM(Q131:Q132) -> 0 | ... S133: =S130-SUM(S131:S132) -> 0
E135: Mortgage Loan initial balance from assumptions | F135: 0 | G135: USD
E137: Mortgage Loan opening balance | G137: USD | J137: =I$139 -> 0 | K137: =J$139 -> 7426300 | L137: =K$139 -> 7208888.2 | M137: =L$139 -> 6986041.2 | N137: =M$139 -> 6757622.9 | O137: =N$139 -> 6523494.2 | P137: =O$139 -> 6283512.3 | Q137: =P$139 -> 6037530.8 | ... S137: =R$139 -> 5526965.6
E138: Mortgage Loan addition / (repayment) | G138: USD | J138: =IF( J$257 = 1, $F$125, J$132 * - 1 ) -> 7426300 | K138: =IF( K$257 = 1, $F$125, K$132 * - 1 ) -> -217411.77 | L138: =IF( L$257 = 1, $F$125, L$132 * - 1 ) -> -222847.07 | M138: =IF( M$257 = 1, $F$125, M$132 * - 1 ) -> -228418.24 | N138: =IF( N$257 = 1, $F$125, N$132 * - 1 ) -> -234128.7 | O138: =IF( O$257 = 1, $F$125, O$132 * - 1 ) -> -239981.92 | P138: =IF( P$257 = 1, $F$125, P$132 * - 1 ) -> -245981.46 | Q138: =IF( Q$257 = 1, $F$125, Q$132 * - 1 ) -> -252131 | ... S138: =IF( S$257 = 1, $F$125, S$132 * - 1 ) -> -264895.13
E139: Mortgage Loan closing balance | G139: USD | I139: =$F$135 -> 0 | J139: =SUM(J137:J138) -> 7426300 | K139: =SUM(K137:K138) -> 7208888.2 | L139: =SUM(L137:L138) -> 6986041.2 | M139: =SUM(M137:M138) -> 6757622.9 | N139: =SUM(N137:N138) -> 6523494.2 | O139: =SUM(O137:O138) -> 6283512.3 | P139: =SUM(P137:P138) -> 6037530.8 | Q139: =SUM(Q137:Q138) -> 5785399.8 | ... S139: =SUM(S137:S138) -> 5262070.4
A142: Property II
C145: Construction Loan - Property II
E146: =CaseData!J$31 -> Issuance | F146: =CaseData!Q$31 -> 2025 | G146: year
E147: =CaseData!$J$32 -> Payment / Term | F147: =CaseData!$Q$32 -> 2027 | G147: year
...

Sheet CaseData
B2: GRANITE BAY REAL ESTATE INC. - DEBT QUESTION
B3: =MID( B2, 31, 5) -> DEBT
B5: ASSUMPTIONS
B7: TIMING | J7: EXISTING DEBT
G8: Information | O8: Existing Debt I | Q8: Existing Debt II | S8: Existing Debt III
C9: Start Year | G9: 2024 | J9: ="Outstanding Balance as at: "&TEXT((DATE(G9-1,12,31)),"[$-F800]dddd, mmmm dd, yyyy") -> Outstanding Balance as at: December 31, 2023 | O9: 2750000 | Q9: 1500000 | S9: 2225000
C10: Periodicity | G10: Annual | J10: Interest Rate | O10: 0.0925 | Q10: 0.0875 | S10: 0.0795
J11: Annual Payment | O11: Interest Only | Q11: Interest Only | S11: Interest Only
J12: Interest Payment Type | O12: Non-Cash / Accrued | Q12: Non-Cash / Accrued | S12: Cash
J13: Principal Repayment Priority (After Revolver) | O13: Pay Down First | Q13: Pay Down Second | S13: Pay Down Third
B17: FREE CASH FLOW BEFORE DEBT SERVICE | J17: CASH BALANCE AND REVOLVER
G18: Information | O18: Cash Account | Q18: Revolver
C19: Start Year | G19: =O32+1 -> 2025 | J19: ="Outstanding Balance as at: "&TEXT((DATE(G9-1,12,31)),"[$-F800]dddd, mmmm dd, yyyy") -> Outstanding Balance as at: December 31, 2023 | O19: 0 | Q19: 0
C20: Free Cash Flow Before Debt Service | G20: 1250000 | H20: ok | J20: Maximum Amount | O20: N/A | Q20: 1000000
C21: ="Occupancy Rate ("&G19&" - "&G19+F21-1&")" -> Occupancy Rate (2025 - 2025) | F21: 1 | G21: 0.5 | H21: ok | J21: Interest Rate | O21: 0.015 | Q21: 0.055
C22: ="Occupancy Rate in "&G19+F21&" and Beyond" -> Occupancy Rate in 2026 and Beyond | G22: 1 | H22: ok | J22: Standby Fee Rate | O22: N/A | Q22: 0.0075
C23: ="Growth Rate ("&G19+1&" - "&G19+F23&")" -> Growth Rate (2026 - 2028) | F23: 3 | G23: 0.05 | H23: ok | J23: Annual Payment | O23: Interest Only | Q23: Principal + Interest
C24: ="Growth Rate "&G19+F23+1&" and Beyond" -> Growth Rate 2029 and Beyond | G24: 0.025 | H24: ok | J24: Interest Payment Type | O24: Cash | Q24: Cash
J25: Repayment Priority | O25: N/A | Q25: Cash Sweep
B29: PROPERTY DETAILS | J29: NEW DEBT
C30: Property I | G30: Information | O30: Construction Loan I | Q30: Construction Loan II | S30: Mortgage Loan
C31: Start Renting | G31: =G19 -> 2025 | J31: Issuance | O31: 2023 | Q31: 2025 | S31: =O32 -> 2024
C32: Free Cash Flow Before Debt Service Information | G32: See box above | H32: ok | J32: Payment / Term | O32: 2024 | Q32: 2027 | S32: 25
J33: Amount | O33: 7000000 | Q33: 12500000 | S33: End Value of Constr. Loan I
C34: Property II | G34: Information | J34: ="Amount Spent as at: "&TEXT((DATE(G9-1,12,31)),"[$-F800]dddd, mmmm dd, yyyy") -> Amount Spent as at: December 31, 2023 | O34: 3500000 | Q34: N/A | S34: N/A
C35: Construction Start | G35: =Q31 -> 2025 | J35: Interest Rate | O35: 0.06 | Q35: 0.055 | S35: 0.025
C36: Year Sold | G36: =Q32 -> 2027 | J36: Annual Payment | O36: Interest Only | Q36: Interest Only | S36: Principal + Interest
C37: Amount | G37: 18750000 | J37: Interest Payment Type | O37: Non-Cash / Accrued | Q37: Non-Cash / Accrued | S37: Cash
J38: Final Payment | O38: Competion of Construction | Q38: Competion of Construction | S38: N/A (Annual Amortization)

Sheet CaseSolution
B2: GRANITE BAY REAL ESTATE INC. - DEBT ANSWER KEY
B5: (i) BUILD AN ANNUAL MODEL OF THE COMPANY FOR THE TWO PROPERTIES OVER THE NEXT TEN YEARS (I.E., 2024 – 2033).
C6: ="See the Model Build below, beginning in Row "&ROW(A58) -> See the Model Build below, beginning in Row 58
B10: (ii) CREATE A SUMMARY TABLE OUTLINING THE ENDING BALANCE FOR EACH OF THE THREE EXISTING PIECES OF DEBT. WHEN DOES EACH PIECE OF DEBT GET PAID OFF?
C11: =IFERROR(C17&" is Paid off in: "&TEXT(INDEX($I$15:$S$15,MATCH(0,I17:S17,0)),"0;[Red]0")&" (see below for details):",C17&" does NOT get Paid off (see below for details):") -> Existing Debt I is Paid off in: 2027 (see below for details):
C12: =IFERROR(C18&" is Paid off in: "&TEXT(INDEX($I$15:$S$15,MATCH(0,I18:S18,0)),"0;[Red]0")&" (see below for details):",C18&" does NOT get Paid off (see below for details):") -> Existing Debt II is Paid off in: 2027 (see below for details):
C13: =IFERROR(C19&" is Paid off in: "&TEXT(INDEX($I$15:$S$15,MATCH(0,I19:S19,0)),"0;[Red]0")&" (see below for details):",C19&" does NOT get Paid off (see below for details):") -> Existing Debt III is Paid off in: 2029 (see below for details):
C14: =IFERROR("All Existing Debt is Paid off in: "&TEXT(INDEX($I$15:$S$15,MATCH(0,I20:S20,0)),"0;[Red]0")&" (see below for details):","All Existing Debt does not get Paid off (see below for details):") -> All Existing Debt is Paid off in: 2029 (see below for details): | J14: =J$103 -> Forecast
I15: =I$104 -> 2023 | J15: =J$104 -> 2024 | K15: =K$104 -> 2025 | L15: =L$104 -> 2026 | M15: =M$104 -> 2027 | N15: =N$104 -> 2028 | O15: =O$104 -> 2029 | P15: =P$104 -> 2030 | ... S15: =S$104 -> 2033
C16: Existing Debt Summary
C17: =C264 -> Existing Debt I | J17: =J270 -> 3016710.4 | K17: =K270 -> 3309287.8 | L17: =L270 -> 3041359 | M17: =M270 -> 0 | N17: =N270 -> 0 | O17: =O270 -> 0 | P17: =P270 -> 0 | Q17: =Q270 -> 0 | ... S17: =S270 -> 0
C18: =C277 -> Existing Debt II | J18: =J283 -> 1637254.9 | K18: =K283 -> 1787069.1 | L18: =L283 -> 1950591.7 | M18: =M283 -> 0 | N18: =N283 -> 0 | O18: =O283 -> 0 | P18: =P283 -> 0 | Q18: =Q283 -> 0 | ... S18: =S283 -> 0
C19: =C290 -> Existing Debt III | J19: =J296 -> 2225000 | K19: =K296 -> 2225000 | L19: =L296 -> 2225000 | M19: =M296 -> 1433946.4 | N19: =N296 -> 473297.37 | O19: =O296 -> 0 | P19: =P296 -> 0 | Q19: =Q296 -> 0 | ... S19: =S296 -> 0
C20: Total | J20: =SUM(J17:J19) -> 6878965.3 | K20: =SUM(K17:K19) -> 7321356.8 | L20: =SUM(L17:L19) -> 7216950.7 | M20: =SUM(M17:M19) -> 1433946.4 | N20: =SUM(N17:N19) -> 473297.37 | O20: =SUM(O17:O19) -> 0 | P20: =SUM(P17:P19) -> 0 | Q20: =SUM(Q17:Q19) -> 0 | ... S20: =SUM(S17:S19) -> 0
B24: (iii) CREATE A SUMMARY TABLE CONTAINING THE TOTAL AMOUNT OF INTEREST EACH YEAR, BROKEN DOWN INTO CASH INTEREST AND NON-CASH INTEREST.
C25: =C31&" Paid is: "&TEXT(SUM(J31:S31),"$#,##0;[Red]$#,##0") -> Total Interest Paid is: $5059,079
C26: ="This consists of "&C29&" of: "&TEXT(SUM(J29:S29),"$#,##0;[Red]$#,##0")& ", and "&C30&" of: "&TEXT(SUM(J30:S30),"$#,##0;[Red]$#,##0") -> This consists of Non-Cash Interest of: $2914,005, and Cash Interest of: $2145,074 | J26: =J$103 -> Forecast
I27: =I$104 -> 2023 | J27: =J$104 -> 2024 | K27: =K$104 -> 2025 | L27: =L$104 -> 2026 | M27: =M$104 -> 2027 | N27: =N$104 -> 2028 | O27: =O$104 -> 2029 | P27: =P$104 -> 2030 | ... S27: =S$104 -> 2033
C28: Interest Summary
C29: =C317 -> Non-Cash Interest | J29: =J317 -> 725265.26 | K29: =K317 -> 556974.92 | L29: =L317 -> 807292.16 | M29: =M317 -> 824472.86 | N29: =N317 -> 0 | O29: =O317 -> 0 | P29: =P317 -> 0 | Q29: =Q317 -> 0 | ... S29: =S317 -> 0
C30: =C318 -> Cash Interest | J30: =J318 -> 188873.24 | K30: =K318 -> 378321.39 | L30: =L318 -> 368400.36 | M30: =M318 -> 327594.15 | N30: =N318 -> 252253.51 | O30: =O318 -> 185014.07 | P30: =P318 -> 147362.02 | Q30: =Q318 -> 123893.39 | ... S30: =S318 -> 73933.725
C31: =C319 -> Total Interest | J31: =J319 -> 914138.5 | K31: =K319 -> 935296.31 | L31: =L319 -> 1175692.5 | M31: =M319 -> 1152067 | N31: =N319 -> 252253.51 | O31: =O319 -> 185014.07 | P31: =P319 -> 147362.02 | Q31: =Q319 -> 123893.39 | ... S31: =S319 -> 73933.725
B35: (iv) WHAT IS THE AMOUNT OF THE MORTGAGE TAKE-OUT FINANCING FOR PROPERTY I?
C36: ="The Amount of Mortgage Take-Out Financing for Property II is: "&TEXT(-SUM(I184:S184),"$#,##0;[Red]$#,##0") -> The Amount of Mortgage Take-Out Financing for Property II is: $7,426,300
B40: (v) WHAT IS THE PROFIT FROM SELLING PROPERTY II?
C41: ="The Property Sold for: "&TEXT(SUM(J131:S131),"$#,##0;[Red]$#,##0") -> The Property Sold for: $18,750,000
C42: ="Total Loan and Interest Paid was: "&TEXT(SUM(J210:S210),"$#,##0;[Red]$#,##0") -> Total Loan and Interest Paid was: $13,563,107
C43: ="Thus, the Profit from Selling Property II is: "&TEXT(SUM(J131:S131,J210:S210),"$#,##0;[Red]$#,##0") -> Thus, the Profit from Selling Property II is: $5,186,893
B47: (vi) DOES THE REVOLVER EVER GET TRIPPED (I.E., THE BALANCE EXCEEDS THE MAXIMUM AMOUNT)? IF SO, IN WHICH YEAR(S) AND BY HOW MUCH?
C48: ="The Maximum Amount allowed to be Borrowed under the Revolver is: "&TEXT(Q76,"$#,##0;[Red]$#,##0") -> The Maximum Amount allowed to be Borrowed under the Revolver is: $1,000,000
C49: =IF(SUM(J53:S53)<>0,"Yes, the Revolver Trips (see below for details):","No, the Revolver does NOT Trip (see below for details):") -> No, the Revolver does NOT Trip (see below for details): | J49: =J$103 -> Forecast
I50: =I$104 -> 2023 | J50: =J$104 -> 2024 | K50: =K$104 -> 2025 | L50: =L$104 -> 2026 | M50: =M$104 -> 2027 | N50: =N$104 -> 2028 | O50: =O$104 -> 2029 | P50: =P$104 -> 2030 | ... S50: =S$104 -> 2033
C51: Revolver (Drawn Amount)
C52: Amount Outstanding - Ending | J52: =J235 -> 188873.24 | K52: =K235 -> 159606.4 | L52: =L235 -> 0 | M52: =M235 -> 0 | N52: =N235 -> 0 | O52: =O235 -> 0 | P52: =P235 -> 0 | Q52: =Q235 -> 0 | ... S52: =S235 -> 0
C53: Tripped? | J53: =IF(J52>$Q$76,1,0) -> 0 | K53: =IF(K52>$Q$76,1,0) -> 0 | L53: =IF(L52>$Q$76,1,0) -> 0 | M53: =IF(M52>$Q$76,1,0) -> 0 | N53: =IF(N52>$Q$76,1,0) -> 0 | O53: =IF(O52>$Q$76,1,0) -> 0 | P53: =IF(P52>$Q$76,1,0) -> 0 | Q53: =IF(Q52>$Q$76,1,0) -> 0 | ... S53: =IF(S52>$Q$76,1,0) -> 0
C54: Overdrawn by: | J54: =-MIN(J242,J52)*J53 -> 0 | K54: =-MIN(K242,K52)*K53 -> 0 | L54: =-MIN(L242,L52)*L53 -> 0 | M54: =-MIN(M242,M52)*M53 -> 0 | N54: =-MIN(N242,N52)*N53 -> 0 | O54: =-MIN(O242,O52)*O53 -> 0 | P54: =-MIN(P242,P52)*P53 -> 0 | Q54: =-MIN(Q242,Q52)*Q53 -> 0 | ... S54: =-MIN(S242,S52)*S53 -> 0
B58: GRANITE BAY REAL ESTATE INC. - DEBT ANSWER
B61: =CaseData!B5 -> ASSUMPTIONS
B63: =CaseData!B7 -> TIMING | J63: =CaseData!J7 -> EXISTING DEBT
G64: =CaseData!G8 -> Information | O64: =CaseData!O8 -> Existing Debt I | Q64: =CaseData!Q8 -> Existing Debt II | S64: =CaseData!S8 -> Existing Debt III
C65: =CaseData!C9 -> Start Year | G65: =CaseData!G9 -> 2024 | J65: =CaseData!J9 -> Outstanding Balance as at: December 31, 2023 | O65: =CaseData!O9 -> 2750000 | Q65: =CaseData!Q9 -> 1500000 | S65: =CaseData!S9 -> 2225000
C66: =CaseData!C10 -> Periodicity | G66: =CaseData!G10 -> Annual | J66: =CaseData!J10 -> Interest Rate | O66: =CaseData!O10 -> 0.0925 | Q66: =CaseData!Q10 -> 0.0875 | S66: =CaseData!S10 -> 0.0795
J67: =CaseData!J11 -> Annual Payment | O67: =CaseData!O11 -> Interest Only | Q67: =CaseData!Q11 -> Interest Only | S67: =CaseData!S11 -> Interest Only
J68: =CaseData!J12 -> Interest Payment Type | O68: =CaseData!O12 -> Non-Cash / Accrued | Q68: =CaseData!Q12 -> Non-Cash / Accrued | S68: =CaseData!S12 -> Cash
J69: =CaseData!J13 -> Principal Repayment Priority (After Revolver) | O69: =CaseData!O13 -> Pay Down First | Q69: =CaseData!Q13 -> Pay Down Second | S69: =CaseData!S13 -> Pay Down Third
B73: =CaseData!B17 -> FREE CASH FLOW BEFORE DEBT SERVICE | J73: =CaseData!J17 -> CASH BALANCE AND REVOLVER
G74: =CaseData!G18 -> Information | O74: =CaseData!O18 -> Cash Account | Q74: =CaseData!Q18 -> Revolver
C75: =CaseData!C19 -> Start Year | G75: =CaseData!G19 -> 2025 | J75: =CaseData!J19 -> Outstanding Balance as at: December 31, 2023 | O75: =CaseData!O19 -> 0 | Q75: =CaseData!Q19 -> 0
C76: =CaseData!C20 -> Free Cash Flow Before Debt Service | G76: =CaseData!G20 -> 1250000 | J76: =CaseData!J20 -> Maximum Amount | O76: =CaseData!O20 -> N/A | Q76: =CaseData!Q20 -> 1000000
C77: =CaseData!C21 -> Occupancy Rate (2025 - 2025) | F77: =CaseData!F21 -> 1 | G77: =CaseData!G21 -> 0.5 | J77: =CaseData!J21 -> Interest Rate | O77: =CaseData!O21 -> 0.015 | Q77: =CaseData!Q21 -> 0.055
C78: =CaseData!C22 -> Occupancy Rate in 2026 and Beyond | G78: =CaseData!G22 -> 1 | J78: =CaseData!J22 -> Standby Fee Rate | O78: =CaseData!O22 -> N/A | Q78: =CaseData!Q22 -> 0.0075
C79: =CaseData!C23 -> Growth Rate (2026 - 2028) | F79: =CaseData!F23 -> 3 | G79: =CaseData!G23 -> 0.05 | J79: =CaseData!J23 -> Annual Payment | O79: =CaseData!O23 -> Interest Only | Q79: =CaseData!Q23 -> Principal + Interest
C80: =CaseData!C24 -> Growth Rate 2029 and Beyond | G80: =CaseData!G24 -> 0.025 | J80: =CaseData!J24 -> Interest Payment Type | O80: =CaseData!O24 -> Cash | Q80: =CaseData!Q24 -> Cash
J81: =CaseData!J25 -> Repayment Priority | O81: =CaseData!O25 -> N/A | Q81: =CaseData!Q25 -> Cash Sweep
B85: =CaseData!B29 -> PROPERTY DETAILS | J85: =CaseData!J29 -> NEW DEBT
C86: =CaseData!C30 -> Property I | G86: =CaseData!G30 -> Information | O86: =CaseData!O30 -> Construction Loan I | Q86: =CaseData!Q30 -> Construction Loan II | S86: =CaseData!S30 -> Mortgage Loan
C87: =CaseData!C31 -> Start Renting | G87: =CaseData!G31 -> 2025 | J87: =CaseData!J31 -> Issuance | O87: =CaseData!O31 -> 2023 | Q87: =CaseData!Q31 -> 2025 | S87: =CaseData!S31 -> 2024
C88: =CaseData!C32 -> Free Cash Flow Before Debt Service Information | G88: =CaseData!G32 -> See box above | J88: =CaseData!J32 -> Payment / Term | O88: =CaseData!O32 -> 2024 | Q88: =CaseData!Q32 -> 2027 | S88: =CaseData!S32 -> 25
J89: =CaseData!J33 -> Amount | O89: =CaseData!O33 -> 7000000 | Q89: =CaseData!Q33 -> 12500000 | S89: =CaseData!S33 -> End Value of Constr. Loan I
C90: =CaseData!C34 -> Property II | G90: =CaseData!G34 -> Information | J90: =CaseData!J34 -> Amount Spent as at: December 31, 2023 | O90: =CaseData!O34 -> 3500000 | Q90: =CaseData!Q34 -> N/A | S90: =CaseData!S34 -> N/A
C91: =CaseData!C35 -> Construction Start | G91: =CaseData!G35 -> 2025 | J91: =CaseData!J35 -> Interest Rate | O91: =CaseData!O35 -> 0.06 | Q91: =CaseData!Q35 -> 0.055 | S91: =CaseData!S35 -> 0.025
C92: =CaseData!C36 -> Year Sold | G92: =CaseData!G36 -> 2027 | J92: =CaseData!J36 -> Annual Payment | O92: =CaseData!O36 -> Interest Only | Q92: =CaseData!Q36 -> Interest Only | S92: =CaseData!S36 -> Principal + Interest
C93: =CaseData!C37 -> Amount | G93: =CaseData!G37 -> 18750000 | J93: =CaseData!J37 -> Interest Payment Type | O93: =CaseData!O37 -> Non-Cash / Accrued | Q93: =CaseData!Q37 -> Non-Cash / Accrued | S93: =CaseData!S37 -> Cash
J94: =CaseData!J38 -> Final Payment | O94: =CaseData!O38 -> Competion of Construction | Q94: =CaseData!Q38 -> Competion of Construction | S94: =CaseData!S38 -> N/A (Annual Amortization)
B99: MODEL
B101: TIMING AND FREE CASH FLOW BEFORE DEBT SERVICE SCHEDULE
J103: Forecast
I104: =J104-1 -> 2023 | J104: =$G$65 -> 2024 | K104: =J104+1 -> 2025 | L104: =K104+1 -> 2026 | M104: =L104+1 -> 2027 | N104: =M104+1 -> 2028 | O104: =N104+1 -> 2029 | P104: =O104+1 -> 2030 | Q104: =P104+1 -> 2031 | R104: =Q104+1 -> 2032 | S104: =R104+1 -> 2033
C106: Property I Construction Period | G106: =O87&" - "&G111 -> 2023 - 2024 | I106: =IF(AND(I$104>=$O$87,I$104<=$G$111),1,0) -> 1 | J106: =IF(AND(J$104>=$O$87,J$104<=$G$111),1,0) -> 1 | K106: =IF(AND(K$104>=$O$87,K$104<=$G$111),1,0) -> 0 | L106: =IF(AND(L$104>=$O$87,L$104<=$G$111),1,0) -> 0 | M106: =IF(AND(M$104>=$O$87,M$104<=$G$111),1,0) -> 0 | N106: =IF(AND(N$104>=$O$87,N$104<=$G$111),1,0) -> 0 | O106: =IF(AND(O$104>=$O$87,O$104<=$G$111),1,0) -> 0 | P106: =IF(AND(P$104>=$O$87,P$104<=$G$111),1,0) -> 0 | ... S106: =IF(AND(S$104>=$O$87,S$104<=$G$111),1,0) -> 0
C107: Mortgage Payments | G107: =S87+1&" & Onward" -> 2025 & Onward | I107: =IF(I$104>=$S$87+1,1,0) -> 0 | J107: =IF(J$104>=$S$87+1,1,0) -> 0 | K107: =IF(K$104>=$S$87+1,1,0) -> 1 | L107: =IF(L$104>=$S$87+1,1,0) -> 1 | M107: =IF(M$104>=$S$87+1,1,0) -> 1 | N107: =IF(N$104>=$S$87+1,1,0) -> 1 | O107: =IF(O$104>=$S$87+1,1,0) -> 1 | P107: =IF(P$104>=$S$87+1,1,0) -> 1 | ... S107: =IF(S$104>=$S$87+1,1,0) -> 1
C108: Property I Operations Period | G108: =G75&" & Onward" -> 2025 & Onward | I108: =IF(I$104>=$G$113,1,0) -> 0 | J108: =IF(J$104>=$G$113,1,0) -> 0 | K108: =IF(K$104>=$G$113,1,0) -> 1 | L108: =IF(L$104>=$G$113,1,0) -> 1 | M108: =IF(M$104>=$G$113,1,0) -> 1 | N108: =IF(N$104>=$G$113,1,0) -> 1 | O108: =IF(O$104>=$G$113,1,0) -> 1 | P108: =IF(P$104>=$G$113,1,0) -> 1 | ... S108: =IF(S$104>=$G$113,1,0) -> 1
C109: Property II Construction Period | G109: =G114&" - "&G115 -> 2025 - 2027 | I109: =IF(AND(I$104>=$G$114,I$104<=$G$115),1,0) -> 0 | J109: =IF(AND(J$104>=$G$114,J$104<=$G$115),1,0) -> 0 | K109: =IF(AND(K$104>=$G$114,K$104<=$G$115),1,0) -> 1 | L109: =IF(AND(L$104>=$G$114,L$104<=$G$115),1,0) -> 1 | M109: =IF(AND(M$104>=$G$114,M$104<=$G$115),1,0) -> 1 | N109: =IF(AND(N$104>=$G$114,N$104<=$G$115),1,0) -> 0 | O109: =IF(AND(O$104>=$G$114,O$104<=$G$115),1,0) -> 0 | P109: =IF(AND(P$104>=$G$114,P$104<=$G$115),1,0) -> 0 | ... S109: =IF(AND(S$104>=$G$114,S$104<=$G$115),1,0) -> 0
C111: Property I Construction Ends / Payment | G111: =$O$88 -> 2024 | I111: =IF($G111=I$104,1,0) -> 0 | J111: =IF($G111=J$104,1,0) -> 1 | K111: =IF($G111=K$104,1,0) -> 0 | L111: =IF($G111=L$104,1,0) -> 0 | M111: =IF($G111=M$104,1,0) -> 0 | N111: =IF($G111=N$104,1,0) -> 0 | O111: =IF($G111=O$104,1,0) -> 0 | P111: =IF($G111=P$104,1,0) -> 0 | ... S111: =IF($G111=S$104,1,0) -> 0
C112: Mortgage Loan Begins | G112: =$S$87 -> 2024 | I112: =IF($G112=I$104,1,0) -> 0 | J112: =IF($G112=J$104,1,0) -> 1 | K112: =IF($G112=K$104,1,0) -> 0 | L112: =IF($G112=L$104,1,0) -> 0 | M112: =IF($G112=M$104,1,0) -> 0 | N112: =IF($G112=N$104,1,0) -> 0 | O112: =IF($G112=O$104,1,0) -> 0 | P112: =IF($G112=P$104,1,0) -> 0 | ... S112: =IF($G112=S$104,1,0) -> 0
C113: Property I Operations Begins | G113: =$G$87 -> 2025 | I113: =IF($G113=I$104,1,0) -> 0 | J113: =IF($G113=J$104,1,0) -> 0 | K113: =IF($G113=K$104,1,0) -> 1 | L113: =IF($G113=L$104,1,0) -> 0 | M113: =IF($G113=M$104,1,0) -> 0 | N113: =IF($G113=N$104,1,0) -> 0 | O113: =IF($G113=O$104,1,0) -> 0 | P113: =IF($G113=P$104,1,0) -> 0 | ... S113: =IF($G113=S$104,1,0) -> 0
C114: Property II Construction Begins / Issuance | G114: =$Q$87 -> 2025 | I114: =IF($G114=I$104,1,0) -> 0 | J114: =IF($G114=J$104,1,0) -> 0 | K114: =IF($G114=K$104,1,0) -> 1 | L114: =IF($G114=L$104,1,0) -> 0 | M114: =IF($G114=M$104,1,0) -> 0 | N114: =IF($G114=N$104,1,0) -> 0 | O114: =IF($G114=O$104,1,0) -> 0 | P114: =IF($G114=P$104,1,0) -> 0 | ... S114: =IF($G114=S$104,1,0) -> 0
C115: Property II Construction Ends / Payment | G115: =$Q$88 -> 2027 | I115: =IF($G115=I$104,1,0) -> 0 | J115: =IF($G115=J$104,1,0) -> 0 | K115: =IF($G115=K$104,1,0) -> 0 | L115: =IF($G115=L$104,1,0) -> 0 | M115: =IF($G115=M$104,1,0) -> 1 | N115: =IF($G115=N$104,1,0) -> 0 | O115: =IF($G115=O$104,1,0) -> 0 | P115: =IF($G115=P$104,1,0) -> 0 | ... S115: =IF($G115=S$104,1,0) -> 0
C116: Property II Sold In | G116: =$G$92 -> 2027 | I116: =IF($G116=I$104,1,0) -> 0 | J116: =IF($G116=J$104,1,0) -> 0 | K116: =IF($G116=K$104,1,0) -> 0 | L116: =IF($G116=L$104,1,0) -> 0 | M116: =IF($G116=M$104,1,0) -> 1 | N116: =IF($G116=N$104,1,0) -> 0 | O116: =IF($G116=O$104,1,0) -> 0 | P116: =IF($G116=P$104,1,0) -> 0 | ... S116: =IF($G116=S$104,1,0) -> 0
C119: Property I FCF Before Debt Service (before Growth) | G119: =$G$76 -> 1250000 | I119: =$G$119*I108 -> 0 | J119: =$G$119*J108 -> 0 | K119: =$G$119*K108 -> 1250000 | L119: =$G$119*L108 -> 1250000 | M119: =$G$119*M108 -> 1250000 | N119: =$G$119*N108 -> 1250000 | O119: =$G$119*O108 -> 1250000 | P119: =$G$119*P108 -> 1250000 | ... S119: =$G$119*S108 -> 1250000
C120: Property I Occupancy Rate | F120: =$G$77 -> 0.5 | G120: =$G$78 -> 1 | I120: =IF(AND(I$104>=$G$75,I$104<=$G$75+$F$77-1),$F$120,$G$120)*I108 -> 0 | J120: =IF(AND(J$104>=$G$75,J$104<=$G$75+$F$77-1),$F$120,$G$120)*J108 -> 0 | K120: =IF(AND(K$104>=$G$75,K$104<=$G$75+$F$77-1),$F$120,$G$120)*K108 -> 0.5 | L120: =IF(AND(L$104>=$G$75,L$104<=$G$75+$F$77-1),$F$120,$G$120)*L108 -> 1 | M120: =IF(AND(M$104>=$G$75,M$104<=$G$75+$F$77-1),$F$120,$G$120)*M108 -> 1 | N120: =IF(AND(N$104>=$G$75,N$104<=$G$75+$F$77-1),$F$120,$G$120)*N108 -> 1 | O120: =IF(AND(O$104>=$G$75,O$104<=$G$75+$F$77-1),$F$120,$G$120)*O108 -> 1 | P120: =IF(AND(P$104>=$G$75,P$104<=$G$75+$F$77-1),$F$120,$G$120)*P108 -> 1 | ... S120: =IF(AND(S$104>=$G$75,S$104<=$G$75+$F$77-1),$F$120,$G$120)*S108 -> 1
C121: Property I Growth Rate | F121: =$G$79 -> 0.05 | G121: =$G$80 -> 0.025 | I121: =IF(I$104=$G$75,0,IF(AND(I$104>=$G$75+1,I$104<=$G$75+$F$79),$F$121,$G$121)*I108) -> 0 | J121: =IF(J$104=$G$75,0,IF(AND(J$104>=$G$75+1,J$104<=$G$75+$F$79),$F$121,$G$121)*J108) -> 0 | K121: =IF(K$104=$G$75,0,IF(AND(K$104>=$G$75+1,K$104<=$G$75+$F$79),$F$121,$G$121)*K108) -> 0 | L121: =IF(L$104=$G$75,0,IF(AND(L$104>=$G$75+1,L$104<=$G$75+$F$79),$F$121,$G$121)*L108) -> 0.05 | M121: =IF(M$104=$G$75,0,IF(AND(M$104>=$G$75+1,M$104<=$G$75+$F$79),$F$121,$G$121)*M108) -> 0.05 | N121: =IF(N$104=$G$75,0,IF(AND(N$104>=$G$75+1,N$104<=$G$75+$F$79),$F$121,$G$121)*N108) -> 0.05 | O121: =IF(O$104=$G$75,0,IF(AND(O$104>=$G$75+1,O$104<=$G$75+$F$79),$F$121,$G$121)*O108) -> 0.025 | P121: =IF(P$104=$G$75,0,IF(AND(P$104>=$G$75+1,P$104<=$G$75+$F$79),$F$121,$G$121)*P108) -> 0.025 | ... S121: =IF(S$104=$G$75,0,IF(AND(S$104>=$G$75+1,S$104<=$G$75+$F$79),$F$121,$G$121)*S108) -> 0.025
C122: Property I Growth Rate Factor | H122: 1 | I122: =H122*(1+I121) -> 1 | J122: =I122*(1+J121) -> 1 | K122: =J122*(1+K121) -> 1 | L122: =K122*(1+L121) -> 1.05 | M122: =L122*(1+M121) -> 1.1025 | N122: =M122*(1+N121) -> 1.157625 | O122: =N122*(1+O121) -> 1.1865656 | P122: =O122*(1+P121) -> 1.2162298 | ... S122: =R122*(1+S121) -> 1.3097464
C124: Property I - FCF Before Debt Service
C125: Construction Costs | F125: =$O$90 -> 3500000 | G125: =$O$89 -> 7000000 | I125: =IF(I$104=$O$87,-$F$125,-($G$125-$F$125)/(SUM($I$106:$S$106)-1)*I106) -> -3500000 | J125: =IF(J$104=$O$87,-$F$125,-($G$125-$F$125)/(SUM($I$106:$S$106)-1)*J106) -> -3500000 | K125: =IF(K$104=$O$87,-$F$125,-($G$125-$F$125)/(SUM($I$106:$S$106)-1)*K106) -> 0 | L125: =IF(L$104=$O$87,-$F$125,-($G$125-$F$125)/(SUM($I$106:$S$106)-1)*L106) -> 0 | M125: =IF(M$104=$O$87,-$F$125,-($G$125-$F$125)/(SUM($I$106:$S$106)-1)*M106) -> 0 | N125: =IF(N$104=$O$87,-$F$125,-($G$125-$F$125)/(SUM($I$106:$S$106)-1)*N106) -> 0 | O125: =IF(O$104=$O$87,-$F$125,-($G$125-$F$125)/(SUM($I$106:$S$106)-1)*O106) -> 0 | P125: =IF(P$104=$O$87,-$F$125,-($G$125-$F$125)/(SUM($I$106:$S$106)-1)*P106) -> 0 | ... S125: =IF(S$104=$O$87,-$F$125,-($G$125-$F$125)/(SUM($I$106:$S$106)-1)*S106) -> 0
C126: Operations | G126: =G119 -> 1250000 | J126: =J119*J120*J122 -> 0 | K126: =K119*K120*K122 -> 625000 | L126: =L119*L120*L122 -> 1312500 | M126: =M119*M120*M122 -> 1378125 | N126: =N119*N120*N122 -> 1447031.3 | O126: =O119*O120*O122 -> 1483207 | P126: =P119*P120*P122 -> 1520287.2 | Q126: =Q119*Q120*Q122 -> 1558294.4 | ... S126: =S119*S120*S122 -> 1637183
C127: Total FCF Before Debt Service | J127: =SUM(J125:J126) -> -3500000 | K127: =SUM(K125:K126) -> 625000 | L127: =SUM(L125:L126) -> 1312500 | M127: =SUM(M125:M126) -> 1378125 | N127: =SUM(N125:N126) -> 1447031.3 | O127: =SUM(O125:O126) -> 1483207 | P127: =SUM(P125:P126) -> 1520287.2 | Q127: =SUM(Q125:Q126) -> 1558294.4 | ... S127: =SUM(S125:S126) -> 1637183
C129: Property II - FCF Before Debt Service
C130: Construction Costs | G130: =$Q$89 -> 12500000 | J130: =-$G$130/SUM($I$109:$S$109)*J109 -> 0 | K130: =-$G$130/SUM($I$109:$S$109)*K109 -> -4166666.7 | L130: =-$G$130/SUM($I$109:$S$109)*L109 -> -4166666.7 | M130: =-$G$130/SUM($I$109:$S$109)*M109 -> -4166666.7 | N130: =-$G$130/SUM($I$109:$S$109)*N109 -> 0 | O130: =-$G$130/SUM($I$109:$S$109)*O109 -> 0 | P130: =-$G$130/SUM($I$109:$S$109)*P109 -> 0 | Q130: =-$G$130/SUM($I$109:$S$109)*Q109 -> 0 | ... S130: =-$G$130/SUM($I$109:$S$109)*S109 -> 0
C131: Selling Proceeds | G131: =$G$93 -> 18750000 | J131: =J116*$G$131 -> 0 | K131: =K116*$G$131 -> 0 | L131: =L116*$G$131 -> 0 | M131: =M116*$G$131 -> 18750000 | N131: =N116*$G$131 -> 0 | O131: =O116*$G$131 -> 0 | P131: =P116*$G$131 -> 0 | Q131: =Q116*$G$131 -> 0 | ... S131: =S116*$G$131 -> 0
C132: =C127 -> Total FCF Before Debt Service | J132: =SUM(J130:J131) -> 0 | K132: =SUM(K130:K131) -> -4166666.7 | L132: =SUM(L130:L131) -> -4166666.7 | M132: =SUM(M130:M131) -> 14583333 | N132: =SUM(N130:N131) -> 0 | O132: =SUM(O130:O131) -> 0 | P132: =SUM(P130:P131) -> 0 | Q132: =SUM(Q130:Q131) -> 0 | ... S132: =SUM(S130:S131) -> 0
C134: =C124 -> Property I - FCF Before Debt Service | J134: =J127 -> -3500000 | K134: =K127 -> 625000 | L134: =L127 -> 1312500 | M134: =M127 -> 1378125 | N134: =N127 -> 1447031.3 | O134: =O127 -> 1483207 | P134: =P127 -> 1520287.2 | Q134: =Q127 -> 1558294.4 | ... S134: =S127 -> 1637183
C135: =C129 -> Property II - FCF Before Debt Service | J135: =J132 -> 0 | K135: =K132 -> -4166666.7 | L135: =L132 -> -4166666.7 | M135: =M132 -> 14583333 | N135: =N132 -> 0 | O135: =O132 -> 0 | P135: =P132 -> 0 | Q135: =Q132 -> 0 | ... S135: =S132 -> 0
C136: =C132 -> Total FCF Before Debt Service | J136: =SUM(J134:J135) -> -3500000 | K136: =SUM(K134:K135) -> -3541666.7 | L136: =SUM(L134:L135) -> -2854166.7 | M136: =SUM(M134:M135) -> 15961458 | N136: =SUM(N134:N135) -> 1447031.3 | O136: =SUM(O134:O135) -> 1483207 | P136: =SUM(P134:P135) -> 1520287.2 | Q136: =SUM(Q134:Q135) -> 1558294.4 | ... S136: =SUM(S134:S135) -> 1637183
B139: FREE CASH FLOW SCHEDULE
J141: =J$103 -> Forecast
I142: =I$104 -> 2023 | J142: =J$104 -> 2024 | K142: =K$104 -> 2025 | L142: =L$104 -> 2026 | M142: =M$104 -> 2027 | N142: =N$104 -> 2028 | O142: =O$104 -> 2029 | P142: =P$104 -> 2030 | ... S142: =S$104 -> 2033
C144: FCF BEFORE REVOLVER ISSUANCE / (REPAYMENT)
C145: =C136 -> Total FCF Before Debt Service | J145: =J136 -> -3500000 | K145: =K136 -> -3541666.7 | L145: =L136 -> -2854166.7 | M145: =M136 -> 15961458 | N145: =N136 -> 1447031.3 | O145: =O136 -> 1483207 | P145: =P136 -> 1520287.2 | Q145: =Q136 -> 1558294.4 | ... S145: =S136 -> 1637183
C146: Cash Interest Payments | J146: =-J318 -> -188873.24 | K146: =-K318 -> -378321.39 | L146: =-L318 -> -368400.36 | M146: =-M318 -> -327594.15 | N146: =-N318 -> -252253.51 | O146: =-O318 -> -185014.07 | P146: =-P318 -> -147362.02 | Q146: =-Q318 -> -123893.39 | ... S146: =-S318 -> -73933.725
C147: Construction Debt Issuance (excl . Interest) | J147: =SUM(J178,J204) -> 3500000 | K147: =SUM(K178,K204) -> 4166666.7 | L147: =SUM(L178,L204) -> 4166666.7 | M147: =SUM(M178,M204) -> 4166666.7 | N147: =SUM(N178,N204) -> 0 | O147: =SUM(O178,O204) -> 0 | P147: =SUM(P178,P204) -> 0 | Q147: =SUM(Q178,Q204) -> 0 | ... S147: =SUM(S178,S204) -> 0
...
