Workbook
Name company: CaseData!$M$2
Name method_selector: Acquisition!$F$9
Name methods: Acquisition!$S$9:$S$10
Name topic: "CFM Topic: " & CaseData!$M$3

Sheet Acquisition
A1: =company -> Alpha
A2: {=topic} -> CFM Topic: Acquisitions
A3: ACQUISITION SCHEDULE | F3: Constant | G3: Unit | H3: Total | J3: {=_xlfn.SEQUENCE( 1, 5, 2022, 1 )} -> 2022 | K3: 2023 | L3: 2024 | M3: 2025 | N3: 2026
A5: Acquisition assumptions
E7: =CaseData!B$3 -> Value of 100% of Bravo's Equity | F7: =CaseData!E$3 -> 4500 | G7: USD m
E8: =CaseData!B$4 -> Percentage of Bravo's Equity Acquired by Alpha | F8: =CaseData!E$4 -> 1 | G8: =CaseData!D$4 -> %
E9: Consolidation Method | F9: 2 | G9: method selection | S9: Equity
S10: Consolidation
B11: Income Statement
E13: Revenue | J13: {=_xlfn.LET( _xlpm.consolidation_method, $F$9, _xlpm.current_account, $E13, _xlpm.alpha_rows,_xlfn.ANCHORARRAY( $E$95), _xlpm.alpha_data,_xlfn.ANCHORARRAY( $J$95), _xlpm.alpha_account, INDEX( _xlpm.alpha_data, MATCH( _xlpm.current_account, _xlpm.alpha_rows, 0 ), 0 ), _xlpm.beta_rows,_xlfn.ANCHORARRAY( $E$175), _xlpm.beta_data,_xlfn.ANCHORARRAY( $J$175), _xlpm.beta_account, INDEX( _xlpm.beta_data, MATCH( _xlpm.current_account, _xlpm.beta_rows, 0 ), 0 ), IF( _xlpm.consolidation_method = 1, _xlpm.alpha_account, _xlpm.alpha_account + _xlpm.beta_account ) )} -> 5189.2857 | K13: 5463.8929 | L13: 5753.1389 | M13: 6057.8104 | N13: 6378.7363
E14: Less: COGS | J14: {=_xlfn.LET( _xlpm.consolidation_method, $F$9, _xlpm.current_account, $E14, _xlpm.alpha_rows,_xlfn.ANCHORARRAY( $E$95), _xlpm.alpha_data,_xlfn.ANCHORARRAY( $J$95), _xlpm.alpha_account, INDEX( _xlpm.alpha_data, MATCH( _xlpm.current_account, _xlpm.alpha_rows, 0 ), 0 ), _xlpm.beta_rows,_xlfn.ANCHORARRAY( $E$175), _xlpm.beta_data,_xlfn.ANCHORARRAY( $J$175), _xlpm.beta_account, INDEX( _xlpm.beta_data, MATCH( _xlpm.current_account, _xlpm.beta_rows, 0 ), 0 ), IF( _xlpm.consolidation_method = 1, _xlpm.alpha_account, _xlpm.alpha_account + _xlpm.beta_account ) )} -> -3031.3929 | K14: -3136.955 | L14: -3245.2602 | M14: -3356.303 | N14: -3470.0699
E15: Gross Profit | J15: =SUM(J13:J14) -> 2157.8929 | K15: =SUM(K13:K14) -> 2326.9379 | L15: =SUM(L13:L14) -> 2507.8788 | M15: =SUM(M13:M14) -> 2701.5073 | N15: =SUM(N13:N14) -> 2908.6663
E16: Less: SG&A | J16: {=_xlfn.LET( _xlpm.consolidation_method, $F$9, _xlpm.current_account, $E16, _xlpm.alpha_rows,_xlfn.ANCHORARRAY( $E$95), _xlpm.alpha_data,_xlfn.ANCHORARRAY( $J$95), _xlpm.alpha_account, INDEX( _xlpm.alpha_data, MATCH( _xlpm.current_account, _xlpm.alpha_rows, 0 ), 0 ), _xlpm.beta_rows,_xlfn.ANCHORARRAY( $E$175), _xlpm.beta_data,_xlfn.ANCHORARRAY( $J$175), _xlpm.beta_account, INDEX( _xlpm.beta_data, MATCH( _xlpm.current_account, _xlpm.beta_rows, 0 ), 0 ), IF( _xlpm.consolidation_method = 1, _xlpm.alpha_account, _xlpm.alpha_account + _xlpm.beta_account ) )} -> -244.32143 | K16: -257.14321 | L16: -270.64243 | M16: -284.85513 | N16: -299.81931
E17: EBITDA | J17: =SUM(J15:J16) -> 1913.5714 | K17: =SUM(K15:K16) -> 2069.7946 | L17: =SUM(L15:L16) -> 2237.2363 | M17: =SUM(M15:M16) -> 2416.6522 | N17: =SUM(N15:N16) -> 2608.847
E18: Less: Depreciation | J18: {=_xlfn.LET( _xlpm.consolidation_method, $F$9, _xlpm.current_account, $E18, _xlpm.alpha_rows,_xlfn.ANCHORARRAY( $E$95), _xlpm.alpha_data,_xlfn.ANCHORARRAY( $J$95), _xlpm.alpha_account, INDEX( _xlpm.alpha_data, MATCH( _xlpm.current_account, _xlpm.alpha_rows, 0 ), 0 ), _xlpm.beta_rows,_xlfn.ANCHORARRAY( $E$175), _xlpm.beta_data,_xlfn.ANCHORARRAY( $J$175), _xlpm.beta_account, INDEX( _xlpm.beta_data, MATCH( _xlpm.current_account, _xlpm.beta_rows, 0 ), 0 ), IF( _xlpm.consolidation_method = 1, _xlpm.alpha_account, _xlpm.alpha_account + _xlpm.beta_account ) )} -> -770.82143 | K18: -811.55821 | L18: -854.46358 | M18: -899.65387 | N18: -947.25169
E19: EBIT | J19: =SUM(J17:J18) -> 1142.75 | K19: =SUM(K17:K18) -> 1258.2364 | L19: =SUM(L17:L18) -> 1382.7728 | M19: =SUM(M17:M18) -> 1516.9983 | N19: =SUM(N17:N18) -> 1661.5954
E20: Add/(Less): Net Interest Income/(Expense) | J20: {=_xlfn.LET( _xlpm.consolidation_method, $F$9, _xlpm.current_account, $E20, _xlpm.alpha_rows,_xlfn.ANCHORARRAY( $E$95), _xlpm.alpha_data,_xlfn.ANCHORARRAY( $J$95), _xlpm.alpha_account, INDEX( _xlpm.alpha_data, MATCH( _xlpm.current_account, _xlpm.alpha_rows, 0 ), 0 ), _xlpm.beta_rows,_xlfn.ANCHORARRAY( $E$175), _xlpm.beta_data,_xlfn.ANCHORARRAY( $J$175), _xlpm.beta_account, INDEX( _xlpm.beta_data, MATCH( _xlpm.current_account, _xlpm.beta_rows, 0 ), 0 ), IF( _xlpm.consolidation_method = 1, _xlpm.alpha_account, _xlpm.alpha_account + _xlpm.beta_account ) )} -> -328.92383 | K20: -282.89596 | L20: -236.41517 | M20: -189.45455 | N20: -141.98528
E21: Earnings before Share of Earnings from Bravo and Tax | J21: =SUM(J19:J20) -> 813.82617 | K21: =SUM(K19:K20) -> 975.34047 | L21: =SUM(L19:L20) -> 1146.3576 | M21: =SUM(M19:M20) -> 1327.5438 | N21: =SUM(N19:N20) -> 1519.6101
E22: Add: Share of Earnings from Bravo | J22: {=_xlfn.LET( _xlpm.method, $F$9, _xlpm.percent, $F$8, _xlpm.bravo_net_income, INDEX( $J$185:$N$185, 1, 0 ), IF( _xlpm.method = 1, _xlpm.bravo_net_income * _xlpm.percent, 0 ) )} -> 0
E23: EBT | J23: =SUM(J21:J22) -> 813.82617 | K23: =SUM(K21:K22) -> 975.34047 | L23: =SUM(L21:L22) -> 1146.3576 | M23: =SUM(M21:M22) -> 1327.5438 | N23: =SUM(N21:N22) -> 1519.6101
E24: Less: Taxes | J24: {=_xlfn.LET( _xlpm.consolidation_method, $F$9, _xlpm.current_account, $E24, _xlpm.alpha_rows,_xlfn.ANCHORARRAY( $E$95), _xlpm.alpha_data,_xlfn.ANCHORARRAY( $J$95), _xlpm.alpha_account, INDEX( _xlpm.alpha_data, MATCH( _xlpm.current_account, _xlpm.alpha_rows, 0 ), 0 ), _xlpm.beta_rows,_xlfn.ANCHORARRAY( $E$175), _xlpm.beta_data,_xlfn.ANCHORARRAY( $J$175), _xlpm.beta_account, INDEX( _xlpm.beta_data, MATCH( _xlpm.current_account, _xlpm.beta_rows, 0 ), 0 ), IF( _xlpm.consolidation_method = 1, _xlpm.alpha_account, _xlpm.alpha_account + _xlpm.beta_account ) )} -> -198.18253 | K24: -237.50263 | L24: -279.13046 | M24: -323.22734 | N24: -369.96536
E25: Net Earnings before Non controlling Interest | J25: =SUM(J23:J24) -> 615.64364 | K25: =SUM(K23:K24) -> 737.83784 | L25: =SUM(L23:L24) -> 867.22712 | M25: =SUM(M23:M24) -> 1004.3165 | N25: =SUM(N23:N24) -> 1149.6447
E26: Less: Non-Controlling Interest | J26: {=_xlfn.LET( _xlpm.method, $F$9, _xlpm.percent, $F$8, _xlpm.bravo_net_income, INDEX( $J$185:$N$185, 1, 0 ), IF( _xlpm.method = 1, _xlfn.SEQUENCE( 1, 5, 0, 0 ), - _xlpm.bravo_net_income * ( 1 - _xlpm.percent ) ) )} -> 0 | K26: 0 | L26: 0 | M26: 0 | N26: 0
E27: Net Income | J27: =SUM(J25:J26) -> 615.64364 | K27: =SUM(K25:K26) -> 737.83784 | L27: =SUM(L25:L26) -> 867.22712 | M27: =SUM(M25:M26) -> 1004.3165 | N27: =SUM(N25:N26) -> 1149.6447
B29: Cash Flow Statement
D31: Cash Flow from Operations
E32: Net Income | J32: {=J27:N27} -> 615.64364 | K32: 737.83784 | L32: 867.22712 | M32: 1004.3165 | N32: 1149.6447
E33: Add: Depreciation | J33: {=_xlfn.LET( _xlpm.consolidation_method, $F$9, _xlpm.current_account, $E33, _xlpm.alpha_rows,_xlfn.ANCHORARRAY( $E$95), _xlpm.alpha_data,_xlfn.ANCHORARRAY( $J$95), _xlpm.alpha_account, INDEX( _xlpm.alpha_data, MATCH( _xlpm.current_account, _xlpm.alpha_rows, 0 ), 0 ), _xlpm.beta_rows,_xlfn.ANCHORARRAY( $E$175), _xlpm.beta_data,_xlfn.ANCHORARRAY( $J$175), _xlpm.beta_account, INDEX( _xlpm.beta_data, MATCH( _xlpm.current_account, _xlpm.beta_rows, 0 ), 0 ), IF( _xlpm.consolidation_method = 1, _xlpm.alpha_account, _xlpm.alpha_account + _xlpm.beta_account ) )} -> 770.82143 | K33: 811.55821 | L33: 854.46358 | M33: 899.65387 | N33: 947.25169
E34: Add: Non-Controlling Interest | J34: {=_xlfn.LET( _xlpm.method, $F$9, _xlpm.non_controlling_interest, INDEX(_xlfn.ANCHORARRAY( J26), 1, 0 ), IF( _xlpm.method = 1, _xlpm.non_controlling_interest, - _xlpm.non_controlling_interest ) )} -> 0 | K34: 0 | L34: 0 | M34: 0 | N34: 0
E35: Add: Share of Dividends from Bravo | J35: {=_xlfn.LET( _xlpm.method, $F$9, _xlpm.percent, $F$8, _xlpm.bravo_dividends, INDEX( $J$207:$N$207, 1, 0 ), IF( _xlpm.method = 1, - _xlpm.bravo_dividends * _xlpm.percent, _xlfn.SEQUENCE( 1, 5, 0, 0 ) ) )} -> 0 | K35: 0 | L35: 0 | M35: 0 | N35: 0
E36: Add/(Less): Change in W/C | J36: {=_xlfn.LET( _xlpm.consolidation_method, $F$9, _xlpm.current_account, $E36, _xlpm.alpha_rows,_xlfn.ANCHORARRAY( $E$95), _xlpm.alpha_data,_xlfn.ANCHORARRAY( $J$95), _xlpm.alpha_account, INDEX( _xlpm.alpha_data, MATCH( _xlpm.current_account, _xlpm.alpha_rows, 0 ), 0 ), _xlpm.beta_rows,_xlfn.ANCHORARRAY( $E$175), _xlpm.beta_data,_xlfn.ANCHORARRAY( $J$175), _xlpm.beta_account, INDEX( _xlpm.beta_data, MATCH( _xlpm.current_account, _xlpm.beta_rows, 0 ), 0 ), IF( _xlpm.consolidation_method = 1, _xlpm.alpha_account, _xlpm.alpha_account + _xlpm.beta_account ) )} -> -33.544286 | K36: -35.167479 | L36: -36.869147 | M36: -38.653077 | N36: -40.523234
E37: Less: Share of Earnings from Bravo | J37: {=-_xlfn.ANCHORARRAY( J22)} -> 0
E38: Cash Flow from Operations | J38: =SUM(J32:J37) -> 1352.9208 | K38: =SUM(K32:K37) -> 1514.2286 | L38: =SUM(L32:L37) -> 1684.8216 | M38: =SUM(M32:M37) -> 1865.3172 | N38: =SUM(N32:N37) -> 2056.3732
D40: Cash Flow from Investing Activities
E41: Less: Capex | J41: {=_xlfn.LET( _xlpm.consolidation_method, $F$9, _xlpm.current_account, $E41, _xlpm.alpha_rows,_xlfn.ANCHORARRAY( $E$95), _xlpm.alpha_data,_xlfn.ANCHORARRAY( $J$95), _xlpm.alpha_account, INDEX( _xlpm.alpha_data, MATCH( _xlpm.current_account, _xlpm.alpha_rows, 0 ), 0 ), _xlpm.beta_rows,_xlfn.ANCHORARRAY( $E$175), _xlpm.beta_data,_xlfn.ANCHORARRAY( $J$175), _xlpm.beta_account, INDEX( _xlpm.beta_data, MATCH( _xlpm.current_account, _xlpm.beta_rows, 0 ), 0 ), IF( _xlpm.consolidation_method = 1, _xlpm.alpha_account, _xlpm.alpha_account + _xlpm.beta_account ) )} -> -847.90357 | K41: -892.71404 | L41: -939.90994 | M41: -989.61925 | N41: -1041.9769
E42: Cash Flow from Investing Activities | J42: =SUM(J41) -> -847.90357 | K42: =SUM(K41) -> -892.71404 | L42: =SUM(L41) -> -939.90994 | M42: =SUM(M41) -> -989.61925 | N42: =SUM(N41) -> -1041.9769
D44: Cash Flow from Financing Activities
E45: Add/(Less): Issuance/(Repayment) of Debt | J45: {=_xlfn.LET( _xlpm.consolidation_method, $F$9, _xlpm.current_account, $E45, _xlpm.alpha_rows,_xlfn.ANCHORARRAY( $E$95), _xlpm.alpha_data,_xlfn.ANCHORARRAY( $J$95), _xlpm.alpha_account, INDEX( _xlpm.alpha_data, MATCH( _xlpm.current_account, _xlpm.alpha_rows, 0 ), 0 ), _xlpm.beta_rows,_xlfn.ANCHORARRAY( $E$175), _xlpm.beta_data,_xlfn.ANCHORARRAY( $J$175), _xlpm.beta_account, INDEX( _xlpm.beta_data, MATCH( _xlpm.current_account, _xlpm.beta_rows, 0 ), 0 ), IF( _xlpm.consolidation_method = 1, _xlpm.alpha_account, _xlpm.alpha_account + _xlpm.beta_account ) )} -> -700 | K45: -700 | L45: -700 | M45: -700 | N45: -700
E46: Add/(Less): Issuance/(Repayment) of Common Shares | J46: {=_xlfn.LET( _xlpm.consolidation_method, $F$9, _xlpm.current_account, $E46, _xlpm.alpha_rows,_xlfn.ANCHORARRAY( $E$95), _xlpm.alpha_data,_xlfn.ANCHORARRAY( $J$95), _xlpm.alpha_account, INDEX( _xlpm.alpha_data, MATCH( _xlpm.current_account, _xlpm.alpha_rows, 0 ), 0 ), _xlpm.beta_rows,_xlfn.ANCHORARRAY( $E$175), _xlpm.beta_data,_xlfn.ANCHORARRAY( $J$175), _xlpm.beta_account, INDEX( _xlpm.beta_data, MATCH( _xlpm.current_account, _xlpm.beta_rows, 0 ), 0 ), IF( _xlpm.consolidation_method = 1, IF( _xlpm.alpha_account = "", 0, _xlpm.alpha_account ), IFERROR( _xlpm.alpha_account + _xlpm.beta_account, 0 ) ) )} -> 0 | K46: 0 | L46: 0 | M46: 0 | N46: 0
E47: Less: Dividends Paid to Non-Controlling Interests | J47: {=_xlfn.LET( _xlpm.method, $F$9, _xlpm.percent, $F$8, _xlpm.bravo_dividends, INDEX( $J$207:$N$207, 1, 0 ), IF( _xlpm.method = 1, _xlfn.SEQUENCE( 1, 5, 0, 0 ), _xlpm.bravo_dividends * (1 - _xlpm.percent ) ) )} -> 0 | K47: 0 | L47: 0 | M47: 0 | N47: 0
E48: Less: Dividends | J48: {=_xlfn.LET( _xlpm.consolidation_method, $F$9, _xlpm.current_account, $E48, _xlpm.alpha_rows,_xlfn.ANCHORARRAY( $E$95), _xlpm.alpha_data,_xlfn.ANCHORARRAY( $J$95), _xlpm.alpha_account, INDEX( _xlpm.alpha_data, MATCH( _xlpm.current_account, _xlpm.alpha_rows, 0 ), 0 ), _xlpm.beta_rows,_xlfn.ANCHORARRAY( $E$175), _xlpm.beta_data,_xlfn.ANCHORARRAY( $J$175), _xlpm.beta_account, INDEX( _xlpm.beta_data, MATCH( _xlpm.current_account, _xlpm.beta_rows, 0 ), 0 ), IF( _xlpm.consolidation_method = 1, _xlpm.alpha_account, _xlpm.alpha_account ) )} -> -82.518816 | K48: -98.807446 | L48: -116.01164 | M48: -134.19197 | N48: -153.41282
E49: Cash Flow from Financing Activities | J49: =SUM(J45:J48) -> -782.51882 | K49: =SUM(K45:K48) -> -798.80745 | L49: =SUM(L45:L48) -> -816.01164 | M49: =SUM(M45:M48) -> -834.19197 | N49: =SUM(N45:N48) -> -853.41282
E51: Beginning Cash & Equivalents | J51: =H58 -> 1134.4413 | K51: =J53 -> 856.93972 | L51: =K53 -> 679.64681 | M51: =L53 -> 608.54679 | N51: =M53 -> 650.05281
E52: Change in Cash & Equivalents | J52: =SUM( J38,J42,J49) -> -277.50161 | K52: =SUM( K38,K42,K49) -> -177.29291 | L52: =SUM( L38,L42,L49) -> -71.100021 | M52: =SUM( M38,M42,M49) -> 41.506026 | N52: =SUM( N38,N42,N49) -> 160.98349
E53: Ending Cash & Equivalents | J53: =SUM(J51:J52) -> 856.93972 | K53: =SUM(K51:K52) -> 679.64681 | L53: =SUM(L51:L52) -> 608.54679 | M53: =SUM(M51:M52) -> 650.05281 | N53: =SUM(N51:N52) -> 811.03631
B55: Balance sheet | F55: ="Consolidation method: " & IF( F9 = 1, "Equity", "Consolidation" ) -> Consolidation method: Consolidation
F56: Prior to close | G56: Adjustment | H56: 2021
D57: Assets
E58: Cash and Equivalents | F58: =CaseData!C62 -> 4548.8483 | G58: =_xlfn.LET( _xlpm.method, $F$9, _xlpm.value, $F$7, _xlpm.percentage, $F$8, _xlpm.bravo, $F222, IF( _xlpm.method = 1, - _xlpm.value * _xlpm.percentage, ( _xlpm.bravo - ( _xlpm.value * _xlpm.percentage ) ) ) ) -> -3414.4069 | H58: =SUM(F58:G58) -> 1134.4413 | J58: =J53 -> 856.93972 | K58: =K53 -> 679.64681 | L58: =L53 -> 608.54679 | M58: =M53 -> 650.05281 | N58: =N53 -> 811.03631
E59: A/R | F59: =CaseData!C63 -> 280 | G59: =_xlfn.LET( _xlpm.method, $F$9, _xlpm.bravo, $F223, IF( _xlpm.method = 1, 0, _xlpm.bravo ) ) -> 114.28571 | H59: =SUM(F59:G59) -> 394.28571 | J59: {=_xlfn.LET( _xlpm.consolidation_method, $F$9, _xlpm.current_account, $E59, _xlpm.alpha_rows,_xlfn.ANCHORARRAY( $E$95), _xlpm.alpha_data,_xlfn.ANCHORARRAY( $J$95), _xlpm.alpha_account, INDEX( _xlpm.alpha_data, MATCH( _xlpm.current_account, _xlpm.alpha_rows, 0 ), 0 ), _xlpm.beta_rows,_xlfn.ANCHORARRAY( $E$175), _xlpm.beta_data,_xlfn.ANCHORARRAY( $J$175), _xlpm.beta_account, INDEX( _xlpm.beta_data, MATCH( _xlpm.current_account, _xlpm.beta_rows, 0 ), 0 ), IF( _xlpm.consolidation_method = 1, _xlpm.alpha_account, _xlpm.alpha_account + _xlpm.beta_account ) )} -> 415.14286 | K59: 437.11143 | L59: 460.25111 | M59: 484.62483 | N59: 510.2989
E60: Inventories | F60: =CaseData!C64 -> 315 | G60: =_xlfn.LET( _xlpm.method, $F$9, _xlpm.bravo, $F224, IF( _xlpm.method = 1, 0, _xlpm.bravo ) ) -> 124.28571 | H60: =SUM(F60:G60) -> 439.28571 | J60: {=_xlfn.LET( _xlpm.consolidation_method, $F$9, _xlpm.current_account, $E60, _xlpm.alpha_rows,_xlfn.ANCHORARRAY( $E$95), _xlpm.alpha_data,_xlfn.ANCHORARRAY( $J$95), _xlpm.alpha_account, INDEX( _xlpm.alpha_data, MATCH( _xlpm.current_account, _xlpm.alpha_rows, 0 ), 0 ), _xlpm.beta_rows,_xlfn.ANCHORARRAY( $E$175), _xlpm.beta_data,_xlfn.ANCHORARRAY( $J$175), _xlpm.beta_account, INDEX( _xlpm.beta_data, MATCH( _xlpm.current_account, _xlpm.beta_rows, 0 ), 0 ), IF( _xlpm.consolidation_method = 1, _xlpm.alpha_account, _xlpm.alpha_account + _xlpm.beta_account ) )} -> 454.70893 | K60: 470.54325 | L60: 486.78902 | M60: 503.44546 | N60: 520.51049
E61: Other current assets | F61: =CaseData!C65 -> 87.5 | G61: =_xlfn.LET( _xlpm.method, $F$9, _xlpm.bravo, $F225, IF( _xlpm.method = 1, 0, _xlpm.bravo ) ) -> 35.714286 | H61: =SUM(F61:G61) -> 123.21429 | J61: {=_xlfn.LET( _xlpm.consolidation_method, $F$9, _xlpm.current_account, $E61, _xlpm.alpha_rows,_xlfn.ANCHORARRAY( $E$95), _xlpm.alpha_data,_xlfn.ANCHORARRAY( $J$95), _xlpm.alpha_account, INDEX( _xlpm.alpha_data, MATCH( _xlpm.current_account, _xlpm.alpha_rows, 0 ), 0 ), _xlpm.beta_rows,_xlfn.ANCHORARRAY( $E$175), _xlpm.beta_data,_xlfn.ANCHORARRAY( $J$175), _xlpm.beta_account, INDEX( _xlpm.beta_data, MATCH( _xlpm.current_account, _xlpm.beta_rows, 0 ), 0 ), IF( _xlpm.consolidation_method = 1, _xlpm.alpha_account, _xlpm.alpha_account + _xlpm.beta_account ) )} -> 129.73214 | K61: 136.59732 | L61: 143.82847 | M61: 151.44526 | N61: 159.46841
E62: Total current assets | F62: =SUM(F58:F61) -> 5231.3483 | G62: =SUM(G58:G61) -> -3140.1212 | H62: =SUM(H58:H61) -> 2091.227 | J62: =SUM(J58:J61) -> 1856.5236 | K62: =SUM(K58:K61) -> 1723.8988 | L62: =SUM(L58:L61) -> 1699.4154 | M62: =SUM(M58:M61) -> 1789.5684 | N62: =SUM(N58:N61) -> 2001.3141
E64: Investment In Bravo | F64: 0 | G64: =_xlfn.LET( _xlpm.method, $F$9, IF( _xlpm.method = 1, - $G$58, 0 ) ) -> 0 | H64: =SUM(F64:G64) -> 0 | J64: =IF( ( method_selector = 1 ) * ( J$256 = 1 ), $H$64 - J$35 - J$37, IF( ( method_selector = 1 ) * ( J$256 = 0 ), I$64 - J$35 - J$37, IF( ( method_selector = 2 ) * ( J$256 = 1 ), $H$64, I$64 ) ) ) -> 0 | K64: =IF( ( method_selector = 1 ) * ( K$256 = 1 ), $H$64 - K$35 - K$37, IF( ( method_selector = 1 ) * ( K$256 = 0 ), J$64 - K$35 - K$37, IF( ( method_selector = 2 ) * ( K$256 = 1 ), $H$64, J$64 ) ) ) -> 0 | L64: =IF( ( method_selector = 1 ) * ( L$256 = 1 ), $H$64 - L$35 - L$37, IF( ( method_selector = 1 ) * ( L$256 = 0 ), K$64 - L$35 - L$37, IF( ( method_selector = 2 ) * ( L$256 = 1 ), $H$64, K$64 ) ) ) -> 0 | M64: =IF( ( method_selector = 1 ) * ( M$256 = 1 ), $H$64 - M$35 - M$37, IF( ( method_selector = 1 ) * ( M$256 = 0 ), L$64 - M$35 - M$37, IF( ( method_selector = 2 ) * ( M$256 = 1 ), $H$64, L$64 ) ) ) -> 0 | N64: =IF( ( method_selector = 1 ) * ( N$256 = 1 ), $H$64 - N$35 - N$37, IF( ( method_selector = 1 ) * ( N$256 = 0 ), M$64 - N$35 - N$37, IF( ( method_selector = 2 ) * ( N$256 = 1 ), $H$64, M$64 ) ) ) -> 0
E65: Goodwill | F65: 0 | G65: =_xlfn.LET( _xlpm.method, $F$9, _xlpm.value, $F$7, _xlpm.bravo, $F249, IF( _xlpm.method = 1, 0, _xlpm.value - _xlpm.bravo ) ) -> 668.13552 | H65: =SUM(F65:G65) -> 668.13552 | J65: {=_xlfn.LET( _xlpm.method, $F$9, _xlpm.bravo, $H65, IF( _xlpm.method = 1, _xlfn.SEQUENCE( 1, 5, 0, 0 ), _xlfn.SEQUENCE( 1, 5, _xlpm.bravo, 0 ) ) )} -> 668.13552 | K65: 668.13552 | L65: 668.13552 | M65: 668.13552 | N65: 668.13552
E66: Fixed Assets | F66: =CaseData!C68 -> 10500 | G66: =_xlfn.LET( _xlpm.method, $F$9, _xlpm.bravo, $F228, IF( _xlpm.method = 1, 0, _xlpm.bravo ) ) -> 4142.8571 | H66: =SUM(F66:G66) -> 14642.857 | J66: {=_xlfn.LET( _xlpm.consolidation_method, $F$9, _xlpm.current_account, $E66, _xlpm.alpha_rows,_xlfn.ANCHORARRAY( $E$95), _xlpm.alpha_data,_xlfn.ANCHORARRAY( $J$95), _xlpm.alpha_account, INDEX( _xlpm.alpha_data, MATCH( _xlpm.current_account, _xlpm.alpha_rows, 0 ), 0 ), _xlpm.beta_rows,_xlfn.ANCHORARRAY( $E$175), _xlpm.beta_data,_xlfn.ANCHORARRAY( $J$175), _xlpm.beta_account, INDEX( _xlpm.beta_data, MATCH( _xlpm.current_account, _xlpm.beta_rows, 0 ), 0 ), IF( _xlpm.consolidation_method = 1, _xlpm.alpha_account, _xlpm.alpha_account + _xlpm.beta_account ) )} -> 14719.939 | K66: 14801.095 | L66: 14886.541 | M66: 14976.507 | N66: 15071.232
E67: Other LT assets | F67: =CaseData!C69 -> 4 | G67: =_xlfn.LET( _xlpm.method, $F$9, _xlpm.bravo, $F229, IF( _xlpm.method = 1, 0, _xlpm.bravo ) ) -> 12 | H67: =SUM(F67:G67) -> 16 | J67: {=_xlfn.LET( _xlpm.consolidation_method, $F$9, _xlpm.current_account, $E67, _xlpm.alpha_rows,_xlfn.ANCHORARRAY( $E$95), _xlpm.alpha_data,_xlfn.ANCHORARRAY( $J$95), _xlpm.alpha_account, INDEX( _xlpm.alpha_data, MATCH( _xlpm.current_account, _xlpm.alpha_rows, 0 ), 0 ), _xlpm.beta_rows,_xlfn.ANCHORARRAY( $E$175), _xlpm.beta_data,_xlfn.ANCHORARRAY( $J$175), _xlpm.beta_account, INDEX( _xlpm.beta_data, MATCH( _xlpm.current_account, _xlpm.beta_rows, 0 ), 0 ), IF( _xlpm.consolidation_method = 1, _xlpm.alpha_account, _xlpm.alpha_account + _xlpm.beta_account ) )} -> 16 | K67: 16 | L67: 16 | M67: 16 | N67: 16
E68: Total Long-Term Assets | F68: =SUM(F64:F67) -> 10504 | G68: =SUM(G64:G67) -> 4822.9927 | H68: =SUM(H64:H67) -> 15326.993 | J68: =SUM(J64:J67) -> 15404.075 | K68: =SUM(K64:K67) -> 15485.231 | L68: =SUM(L64:L67) -> 15570.677 | M68: =SUM(M64:M67) -> 15660.642 | N68: =SUM(N64:N67) -> 15755.368
E70: Total Assets | F70: =SUM( F62, F68) -> 15735.348 | G70: =SUM( G62, G68) -> 1682.8714 | H70: =SUM( H62, H68) -> 17418.22 | J70: =SUM( J62, J68) -> 17260.598 | K70: =SUM( K62, K68) -> 17209.129 | L70: =SUM( L62, L68) -> 17270.092 | M70: =SUM( M62, M68) -> 17450.211 | N70: =SUM( N62, N68) -> 17756.682
D72: Liabilities
E73: A/P | F73: =CaseData!C75 -> 189 | G73: =_xlfn.LET( _xlpm.method, $F$9, _xlpm.bravo, $F235, IF( _xlpm.method = 1, 0, _xlpm.bravo ) ) -> 74.571429 | H73: =SUM(F73:G73) -> 263.57143 | J73: {=_xlfn.LET( _xlpm.consolidation_method, $F$9, _xlpm.current_account, $E73, _xlpm.alpha_rows,_xlfn.ANCHORARRAY( $E$95), _xlpm.alpha_data,_xlfn.ANCHORARRAY( $J$95), _xlpm.alpha_account, INDEX( _xlpm.alpha_data, MATCH( _xlpm.current_account, _xlpm.alpha_rows, 0 ), 0 ), _xlpm.beta_rows,_xlfn.ANCHORARRAY( $E$175), _xlpm.beta_data,_xlfn.ANCHORARRAY( $J$175), _xlpm.beta_account, INDEX( _xlpm.beta_data, MATCH( _xlpm.current_account, _xlpm.beta_rows, 0 ), 0 ), IF( _xlpm.consolidation_method = 1, _xlpm.alpha_account, _xlpm.alpha_account + _xlpm.beta_account ) )} -> 272.82536 | K73: 282.32595 | L73: 292.07341 | M73: 302.06727 | N73: 312.3063
E74: Long-Term Debt Due within One Year | F74: =CaseData!C76 -> 500 | G74: =_xlfn.LET( _xlpm.method, $F$9, _xlpm.bravo, $F236, IF( _xlpm.method = 1, 0, _xlpm.bravo ) ) -> 200 | H74: =SUM(F74:G74) -> 700 | J74: {=_xlfn.LET( _xlpm.consolidation_method, $F$9, _xlpm.current_account, $E74, _xlpm.alpha_rows,_xlfn.ANCHORARRAY( $E$95), _xlpm.alpha_data,_xlfn.ANCHORARRAY( $J$95), _xlpm.alpha_account, INDEX( _xlpm.alpha_data, MATCH( _xlpm.current_account, _xlpm.alpha_rows, 0 ), 0 ), _xlpm.beta_rows,_xlfn.ANCHORARRAY( $E$175), _xlpm.beta_data,_xlfn.ANCHORARRAY( $J$175), _xlpm.beta_account, INDEX( _xlpm.beta_data, MATCH( _xlpm.current_account, _xlpm.beta_rows, 0 ), 0 ), IF( _xlpm.consolidation_method = 1, _xlpm.alpha_account, _xlpm.alpha_account + _xlpm.beta_account ) )} -> 700 | K74: 700 | L74: 700 | M74: 700 | N74: 700
E75: Other current liabilities | F75: =CaseData!C77 -> 0.3 | G75: =_xlfn.LET( _xlpm.method, $F$9, _xlpm.bravo, $F237, IF( _xlpm.method = 1, 0, _xlpm.bravo ) ) -> 6.3 | H75: =SUM(F75:G75) -> 6.6 | J75: {=_xlfn.LET( _xlpm.consolidation_method, $F$9, _xlpm.current_account, $E75, _xlpm.alpha_rows,_xlfn.ANCHORARRAY( $E$95), _xlpm.alpha_data,_xlfn.ANCHORARRAY( $J$95), _xlpm.alpha_account, INDEX( _xlpm.alpha_data, MATCH( _xlpm.current_account, _xlpm.alpha_rows, 0 ), 0 ), _xlpm.beta_rows,_xlfn.ANCHORARRAY( $E$175), _xlpm.beta_data,_xlfn.ANCHORARRAY( $J$175), _xlpm.beta_account, INDEX( _xlpm.beta_data, MATCH( _xlpm.current_account, _xlpm.beta_rows, 0 ), 0 ), IF( _xlpm.consolidation_method = 1, _xlpm.alpha_account, _xlpm.alpha_account + _xlpm.beta_account ) )} -> 6.6 | K75: 6.6 | L75: 6.6 | M75: 6.6 | N75: 6.6
E76: Total Current Liabilities | F76: =SUM(F73:F75) -> 689.3 | G76: =SUM(G73:G75) -> 280.87143 | H76: =SUM(H73:H75) -> 970.17143 | J76: =SUM(J73:J75) -> 979.42536 | K76: =SUM(K73:K75) -> 988.92595 | L76: =SUM(L73:L75) -> 998.67341 | M76: =SUM(M73:M75) -> 1008.6673 | N76: =SUM(N73:N75) -> 1018.9063
E78: Long-Term Debt | F78: =CaseData!C80 -> 3500 | G78: =_xlfn.LET( _xlpm.method, $F$9, _xlpm.bravo, $F240, IF( _xlpm.method = 1, 0, _xlpm.bravo ) ) -> 1400 | H78: =SUM(F78:G78) -> 4900 | J78: {=_xlfn.LET( _xlpm.consolidation_method, $F$9, _xlpm.current_account, $E78, _xlpm.alpha_rows,_xlfn.ANCHORARRAY( $E$95), _xlpm.alpha_data,_xlfn.ANCHORARRAY( $J$95), _xlpm.alpha_account, INDEX( _xlpm.alpha_data, MATCH( _xlpm.current_account, _xlpm.alpha_rows, 0 ), 0 ), _xlpm.beta_rows,_xlfn.ANCHORARRAY( $E$175), _xlpm.beta_data,_xlfn.ANCHORARRAY( $J$175), _xlpm.beta_account, INDEX( _xlpm.beta_data, MATCH( _xlpm.current_account, _xlpm.beta_rows, 0 ), 0 ), IF( _xlpm.consolidation_method = 1, _xlpm.alpha_account, _xlpm.alpha_account + _xlpm.beta_account ) )} -> 4200 | K78: 3500 | L78: 2800 | M78: 2100 | N78: 1400
E79: Other LT liabilities | F79: =CaseData!C81 -> 1.1 | G79: =_xlfn.LET( _xlpm.method, $F$9, _xlpm.bravo, $F241, IF( _xlpm.method = 1, 0, _xlpm.bravo ) ) -> 2 | H79: =SUM(F79:G79) -> 3.1 | J79: {=_xlfn.LET( _xlpm.consolidation_method, $F$9, _xlpm.current_account, $E79, _xlpm.alpha_rows,_xlfn.ANCHORARRAY( $E$95), _xlpm.alpha_data,_xlfn.ANCHORARRAY( $J$95), _xlpm.alpha_account, INDEX( _xlpm.alpha_data, MATCH( _xlpm.current_account, _xlpm.alpha_rows, 0 ), 0 ), _xlpm.beta_rows,_xlfn.ANCHORARRAY( $E$175), _xlpm.beta_data,_xlfn.ANCHORARRAY( $J$175), _xlpm.beta_account, INDEX( _xlpm.beta_data, MATCH( _xlpm.current_account, _xlpm.beta_rows, 0 ), 0 ), IF( _xlpm.consolidation_method = 1, _xlpm.alpha_account, _xlpm.alpha_account + _xlpm.beta_account ) )} -> 3.1 | K79: 3.1 | L79: 3.1 | M79: 3.1 | N79: 3.1
E80: Total Long-term Liabilities | F80: =SUM(F78:F79) -> 3501.1 | G80: =SUM(G78:G79) -> 1402 | H80: =SUM(H78:H79) -> 4903.1 | J80: =SUM(J78:J79) -> 4203.1 | K80: =SUM(K78:K79) -> 3503.1 | L80: =SUM(L78:L79) -> 2803.1 | M80: =SUM(M78:M79) -> 2103.1 | N80: =SUM(N78:N79) -> 1403.1
E82: Total Liabilities | F82: =SUM( F76, F80 ) -> 4190.4 | G82: =SUM( G76, G80 ) -> 1682.8714 | H82: =SUM( H76, H80 ) -> 5873.2714 | J82: =SUM( J76, J80) -> 5182.5254 | K82: =SUM( K76, K80) -> 4492.026 | L82: =SUM( L76, L80) -> 3801.7734 | M82: =SUM( M76, M80) -> 3111.7673 | N82: =SUM( N76, N80) -> 2422.0063
D84: Shareholders' Equity
E85: Common Shares | F85: =CaseData!C87 -> 3700 | G85: =_xlfn.LET( _xlpm.method, $F$9, _xlpm.bravo, 0, IF( _xlpm.method = 1, 0, _xlpm.bravo ) ) -> 0 | H85: =SUM(F85:G85) -> 3700 | J85: {=_xlfn.LET( _xlpm.consolidation_method, $F$9, _xlpm.current_account, $E85, _xlpm.alpha_rows,_xlfn.ANCHORARRAY( $E$95), _xlpm.alpha_data,_xlfn.ANCHORARRAY( $J$95), _xlpm.alpha_account, INDEX( _xlpm.alpha_data, MATCH( _xlpm.current_account, _xlpm.alpha_rows, 0 ), 0 ), _xlpm.beta_rows,_xlfn.ANCHORARRAY( $E$175), _xlpm.beta_data,_xlfn.ANCHORARRAY( $J$175), _xlpm.beta_account, INDEX( _xlpm.beta_data, MATCH( _xlpm.current_account, _xlpm.beta_rows, 0 ), 0 ), IF( _xlpm.consolidation_method = 1, _xlpm.alpha_account, _xlpm.alpha_account ) )} -> 3700 | K85: 3700 | L85: 3700 | M85: 3700 | N85: 3700
E86: Retained Earnings | F86: =CaseData!C88 -> 7844.9483 | G86: =_xlfn.LET( _xlpm.method, $F$9, _xlpm.bravo, 0, IF( _xlpm.method = 1, 0, _xlpm.bravo ) ) -> 0 | H86: =SUM(F86:G86) -> 7844.9483 | J86: =IF( ( method_selector = 1 ) * ( J$256 = 1 ), $H$86 + J$25 + J$47 + J$48, IF( ( method_selector = 1 ) * ( J$256 = 0 ), I$86 + J$25 + J$47 + J$48, IF( (method_selector = 2 ) * ( J$256 = 1 ), $H$86 + J$27 + J$48, I$86 + J$27 + J$48 ) ) ) -> 8378.0731 | K86: =IF( ( method_selector = 1 ) * ( K$256 = 1 ), $H$86 + K$25 + K$47 + K$48, IF( ( method_selector = 1 ) * ( K$256 = 0 ), J$86 + K$25 + K$47 + K$48, IF( (method_selector = 2 ) * ( K$256 = 1 ), $H$86 + K$27 + K$48, J$86 + K$27 + K$48 ) ) ) -> 9017.1035 | L86: =IF( ( method_selector = 1 ) * ( L$256 = 1 ), $H$86 + L$25 + L$47 + L$48, IF( ( method_selector = 1 ) * ( L$256 = 0 ), K$86 + L$25 + L$47 + L$48, IF( (method_selector = 2 ) * ( L$256 = 1 ), $H$86 + L$27 + L$48, K$86 + L$27 + L$48 ) ) ) -> 9768.319 | M86: =IF( ( method_selector = 1 ) * ( M$256 = 1 ), $H$86 + M$25 + M$47 + M$48, IF( ( method_selector = 1 ) * ( M$256 = 0 ), L$86 + M$25 + M$47 + M$48, IF( (method_selector = 2 ) * ( M$256 = 1 ), $H$86 + M$27 + M$48, L$86 + M$27 + M$48 ) ) ) -> 10638.443 | N86: =IF( ( method_selector = 1 ) * ( N$256 = 1 ), $H$86 + N$25 + N$47 + N$48, IF( ( method_selector = 1 ) * ( N$256 = 0 ), M$86 + N$25 + N$47 + N$48, IF( (method_selector = 2 ) * ( N$256 = 1 ), $H$86 + N$27 + N$48, M$86 + N$27 + N$48 ) ) ) -> 11634.675
E87: Non-Controlling Interest | F87: 0 | G87: =_xlfn.LET( _xlpm.method, $F$9, _xlpm.bravo, 0, IF( _xlpm.method = 1, 0, _xlpm.bravo ) ) -> 0 | H87: =SUM(F87:G87) -> 0 | J87: {=_xlfn.LET( _xlpm.model_operationg_flag,_xlfn.ANCHORARRAY( J257), _xlpm.consolidation_method, $F$9, _xlpm.non_controlling_interest, $H$87, _xlpm.cfo_from_non_controlling,_xlfn.ANCHORARRAY( J34), _xlpm.cff_from_non_controlling,_xlfn.ANCHORARRAY( J47), _xlpm.model_operationg_flag * IF( _xlpm.consolidation_method = 1, _xlpm.non_controlling_interest, _xlpm.non_controlling_interest + _xlpm.cfo_from_non_controlling + _xlpm.cff_from_non_controlling) )} -> 0 | K87: 0 | L87: 0 | M87: 0 | N87: 0
E88: Total Shareholders' Equity | F88: =SUM(F85:F87) -> 11544.948 | G88: =SUM(G85:G87) -> 0 | H88: =SUM(H85:H87) -> 11544.948 | J88: =SUM(J85:J87) -> 12078.073 | K88: =SUM(K85:K87) -> 12717.103 | L88: =SUM(L85:L87) -> 13468.319 | M88: =SUM(M85:M87) -> 14338.443 | N88: =SUM(N85:N87) -> 15334.675
E90: Total Liabilities & Shareholders' Equity | F90: =SUM( F82, F88 ) -> 15735.348 | G90: =SUM( G82, G88 ) -> 1682.8714 | H90: =SUM( H82, H88 ) -> 17418.22 | J90: =SUM( J82, J88) -> 17260.598 | K90: =SUM( K82, K88) -> 17209.129 | L90: =SUM( L82, L88) -> 17270.092 | M90: =SUM( M82, M88) -> 17450.211 | N90: =SUM( N82, N88) -> 17756.682
E91: Check | F91: =F70 - F90 -> 0 | G91: =G70 - G90 -> 0 | H91: =H70 - H90 -> 0 | J91: =J70 - J90 -> 0 | K91: =K70 - K90 -> 0 | L91: =L70 - L90 -> 0 | M91: =M70 - M90 -> 0 | N91: =N70 - N90 -> 0
A93: Alpha financial statement prior to acquisition
E95: {=_xlfn.LET( _xlpm.alpha_data, _xlfn.CHOOSECOLS( CaseData!$B$15:$H$91, {1,3,4,5,6} ), _xlpm.alpha_rows, IF( CaseData!$B$15:$B$91 = 0, "", CaseData!$B$15:$B$91 ), _xlpm.alpha_cols, _xlfn.CHOOSECOLS( CaseData!$C$13:$H$13, {2,3,4,5,6} ), _xlpm.beta_data, _xlfn.CHOOSECOLS( CaseData!$B$104:$H$180, {1,3,4,5,6} ), _xlpm.beta_rows, IF( CaseData!$B$104:$B$180 = 0, "", CaseData!$B$104:$B$180 ), _xlpm.beta_cols, _xlfn.CHOOSECOLS( CaseData!$C$102:$H$102, {2,3,4,5,6} ), _xlpm.alpha_rows )} -> Revenue | J95: {=_xlfn.LET( _xlpm.alpha_data, IF( CaseData!$D$15:$H$91 = 0, "", CaseData!$D$15:$H$91 ), _xlpm.alpha_rows, IF( CaseData!$B$15:$B$91 = 0, "", CaseData!$B$15:$B$91 ), _xlpm.alpha_cols, CaseData!$D$13:$H$13, _xlpm.alpha_before, INDEX( _xlpm.alpha_data, MATCH(_xlfn.ANCHORARRAY( $E$95), _xlpm.alpha_rows, 0 ), MATCH(_xlfn.ANCHORARRAY( $J$3), _xlpm.alpha_cols, 0 ) ), _xlpm.beta_data, IF( CaseData!$D$104:$H$180 = 0, "", CaseData!$D$104:$H$180 ), _xlpm.beta_rows, IF( CaseData!$B$104:$B$180 = 0, "", CaseData!$B$104:$B$180 ), _xlpm.beta_cols, CaseData!$D$102:$H$102, _xlpm.beta_before, INDEX( _xlpm.beta_data, MATCH(_xlfn.ANCHORARRAY( $E$175), _xlpm.beta_rows, 0 ), MATCH(_xlfn.ANCHORARRAY( $J$3), _xlpm.beta_cols, 0 ) ), _xlpm.alpha_before )} -> 3675 | K95: 3858.75 | L95: 4051.6875 | M95: 4254.2719 | N95: 4466.9855
E96: Less: COGS | J96: -2168.25 | K96: -2238.075 | L96: -2309.4619 | M96: -2382.3922 | N96: -2456.842
E97: Gross Profit | J97: 1506.75 | K97: 1620.675 | L97: 1742.2256 | M97: 1871.8796 | N97: 2010.1435
E98: Less: SG&A | J98: -183.75 | K98: -192.9375 | L98: -202.58438 | M98: -212.71359 | N98: -223.34927
E99: EBITDA | J99: 1323 | K99: 1427.7375 | L99: 1539.6413 | M99: 1659.166 | N99: 1786.7942
E100: Less: Depreciation | J100: -551.25 | K100: -578.8125 | L100: -607.75312 | M100: -638.14078 | N100: -670.04782
E101: EBIT | J101: 771.75 | K101: 848.925 | L101: 931.88813 | M101: 1021.0253 | N101: 1116.7464
E102: Add/(Less): Net Interest Income/(Expense) | J102: -221.62456 | K102: -190.20869 | L102: -158.47721 | M102: -126.41212 | N102: -93.994238
E103: EBT | J103: 550.12544 | K103: 658.71631 | L103: 773.41092 | M103: 894.61313 | N103: 1022.7521
E104: Less: Taxes | J104: -137.53136 | K104: -164.67908 | L104: -193.35273 | M104: -223.65328 | N104: -255.68803
E105: Net Income | J105: 412.59408 | K105: 494.03723 | L105: 580.05819 | M105: 670.95985 | N105: 767.0641
E109: Cash Flow Statement
E110: (in USD$ millions, fiscal years ended December 31st)
E114: Cash Flow from Operations
E115: Net Income | J115: 412.59408 | K115: 494.03723 | L115: 580.05819 | M115: 670.95985 | N115: 767.0641
E116: Add: Depreciation | J116: 551.25 | K116: 578.8125 | L116: 607.75312 | M116: 638.14078 | N116: 670.04782
E117: Add/(Less): Change in W/C | J117: -22.47 | K117: -23.48325 | L117: -24.54165 | M117: -25.647182 | N117: -26.801913
E118: Cash Flow from Operations
E120: Cash Flow from Investing Activities
E121: Less: Capex | J121: -606.375 | K121: -636.69375 | L121: -668.52844 | M121: -701.95486 | N121: -737.0526
E122: Cash Flow from Investing Activities
E124: Cash Flow from Financing Activities
E125: Add/(Less): Issuance/(Repayment) of Debt | J125: -500 | K125: -500 | L125: -500 | M125: -500 | N125: -500
E126: Add/(Less): Issuance/(Repayment) of Common Shares
...

Sheet CaseData
A1: Acquisition Assumptions
K2: Company name | M2: Alpha
B3: Value of 100% of Bravo's Equity | D3: USD$ millions | E3: 4500 | K3: Topic | M3: Acquisitions
B4: Percentage of Bravo's Equity Acquired by Alpha | D4: % | E4: 1
A7: Alpha Financial Statements (Prior to the Acquisition)
B10: Income statement
B11: (in USD$ millions, fiscal years ended December 31st)
C13: 2021 | D13: =C13+1 -> 2022 | E13: =D13+1 -> 2023 | F13: =E13+1 -> 2024 | G13: =F13+1 -> 2025 | H13: =G13+1 -> 2026
B15: Revenue | C15: 3500 | D15: 3675 | E15: 3858.75 | F15: 4051.6875 | G15: 4254.2719 | H15: 4466.9855
B16: Less: COGS | C16: -2100 | D16: -2168.25 | E16: -2238.075 | F16: -2309.4619 | G16: -2382.3922 | H16: -2456.842
B17: Gross Profit | C17: =SUM(C15:C16) -> 1400 | D17: =SUM(D15:D16) -> 1506.75 | E17: =SUM(E15:E16) -> 1620.675 | F17: =SUM(F15:F16) -> 1742.2256 | G17: =SUM(G15:G16) -> 1871.8796 | H17: =SUM(H15:H16) -> 2010.1435
B18: Less: SG&A | C18: -175 | D18: -183.75 | E18: -192.9375 | F18: -202.58438 | G18: -212.71359 | H18: -223.34927
B19: EBITDA | C19: =SUM(C17:C18) -> 1225 | D19: =SUM(D17:D18) -> 1323 | E19: =SUM(E17:E18) -> 1427.7375 | F19: =SUM(F17:F18) -> 1539.6413 | G19: =SUM(G17:G18) -> 1659.166 | H19: =SUM(H17:H18) -> 1786.7942
B20: Less: Depreciation | C20: -525 | D20: -551.25 | E20: -578.8125 | F20: -607.75312 | G20: -638.14078 | H20: -670.04782
B21: EBIT | C21: =SUM(C19:C20) -> 700 | D21: =SUM(D19:D20) -> 771.75 | E21: =SUM(E19:E20) -> 848.925 | F21: =SUM(F19:F20) -> 931.88813 | G21: =SUM(G19:G20) -> 1021.0253 | H21: =SUM(H19:H20) -> 1116.7464
B22: Add/(Less): Net Interest Income/(Expense) | C22: -252.75288 | D22: -221.62456 | E22: -190.20869 | F22: -158.47721 | G22: -126.41212 | H22: -93.994238
B23: EBT | C23: =SUM(C21:C22) -> 447.24712 | D23: =SUM(D21:D22) -> 550.12544 | E23: =SUM(E21:E22) -> 658.71631 | F23: =SUM(F21:F22) -> 773.41092 | G23: =SUM(G21:G22) -> 894.61313 | H23: =SUM(H21:H22) -> 1022.7521
B24: Less: Taxes | C24: -111.81178 | D24: -137.53136 | E24: -164.67908 | F24: -193.35273 | G24: -223.65328 | H24: -255.68803
B25: Net Income | C25: =SUM(C23:C24) -> 335.43534 | D25: =SUM(D23:D24) -> 412.59408 | E25: =SUM(E23:E24) -> 494.03723 | F25: =SUM(F23:F24) -> 580.05819 | G25: =SUM(G23:G24) -> 670.95985 | H25: =SUM(H23:H24) -> 767.0641
B29: Cash Flow Statement
B30: (in USD$ millions, fiscal years ended December 31st)
C32: =C13 -> 2021 | D32: =D13 -> 2022 | E32: =E13 -> 2023 | F32: =F13 -> 2024 | G32: =G13 -> 2025 | H32: =H13 -> 2026
B34: Cash Flow from Operations
B35: Net Income | C35: =C25 -> 335.43534 | D35: =D25 -> 412.59408 | E35: =E25 -> 494.03723 | F35: =F25 -> 580.05819 | G35: =G25 -> 670.95985 | H35: =H25 -> 767.0641
B36: Add: Depreciation | C36: =-C20 -> 525 | D36: =-D20 -> 551.25 | E36: =-E20 -> 578.8125 | F36: =-F20 -> 607.75312 | G36: =-G20 -> 638.14078 | H36: =-H20 -> 670.04782
B37: Add/(Less): Change in W/C | C37: -17 | D37: -22.47 | E37: -23.48325 | F37: -24.54165 | G37: -25.647182 | H37: -26.801913
B38: Cash Flow from Operations | C38: =SUM(C35:C37) -> 843.43534 | D38: =SUM(D35:D37) -> 941.37408 | E38: =SUM(E35:E37) -> 1049.3665 | F38: =SUM(F35:F37) -> 1163.2697 | G38: =SUM(G35:G37) -> 1283.4534 | H38: =SUM(H35:H37) -> 1410.31
B40: Cash Flow from Investing Activities
B41: Less: Capex | C41: -577.5 | D41: -606.375 | E41: -636.69375 | F41: -668.52844 | G41: -701.95486 | H41: -737.0526
B42: Cash Flow from Investing Activities | C42: =SUM(C41:C41) -> -577.5 | D42: =SUM(D41:D41) -> -606.375 | E42: =SUM(E41:E41) -> -636.69375 | F42: =SUM(F41:F41) -> -668.52844 | G42: =SUM(G41:G41) -> -701.95486 | H42: =SUM(H41:H41) -> -737.0526
B44: Cash Flow from Financing Activities
B45: Add/(Less): Issuance/(Repayment) of Debt | C45: -500 | D45: -500 | E45: -500 | F45: -500 | G45: -500 | H45: -500
B46: Add/(Less): Issuance/(Repayment) of Common Shares | C46: 0 | D46: 0 | E46: 0 | F46: 0 | G46: 0 | H46: 0
B47: Less: Dividends | C47: -67.087068 | D47: -82.518816 | E47: -98.807446 | F47: -116.01164 | G47: -134.19197 | H47: -153.41282
B48: Cash Flow from Financing Activities | C48: =SUM(C45:C47) -> -567.08707 | D48: =SUM(D45:D47) -> -582.51882 | E48: =SUM(E45:E47) -> -598.80745 | F48: =SUM(F45:F47) -> -616.01164 | G48: =SUM(G45:G47) -> -634.19197 | H48: =SUM(H45:H47) -> -653.41282
B50: Beginning Cash & Equivalents | C50: 4850 | D50: =C52 -> 4548.8483 | E50: =D52 -> 4301.3285 | F50: =E52 -> 4115.1938 | G50: =F52 -> 3993.9234 | H50: =G52 -> 3941.23
B51: Change in Cash & Equivalents | C51: =C38+C42+C48 -> -301.15173 | D51: =D38+D42+D48 -> -247.51973 | E51: =E38+E42+E48 -> -186.13472 | F51: =F38+F42+F48 -> -121.27041 | G51: =G38+G42+G48 -> -52.69338 | H51: =H38+H42+H48 -> 19.844582
B52: Ending Cash & Equivalents | C52: =SUM(C50:C51) -> 4548.8483 | D52: =SUM(D50:D51) -> 4301.3285 | E52: =SUM(E50:E51) -> 4115.1938 | F52: =SUM(F50:F51) -> 3993.9234 | G52: =SUM(G50:G51) -> 3941.23 | H52: =SUM(H50:H51) -> 3961.0746
B56: Balance Sheet
B57: (in USD$ millions, fiscal years ended December 31st)
C59: =C32 -> 2021 | D59: =D32 -> 2022 | E59: =E32 -> 2023 | F59: =F32 -> 2024 | G59: =G32 -> 2025 | H59: =H32 -> 2026
B61: Assets
B62: Cash and Equivalents | C62: =C52 -> 4548.8483 | D62: =D52 -> 4301.3285 | E62: =E52 -> 4115.1938 | F62: =F52 -> 3993.9234 | G62: =G52 -> 3941.23 | H62: =H52 -> 3961.0746
B63: A/R | C63: 280 | D63: 294 | E63: 308.7 | F63: 324.135 | G63: 340.34175 | H63: 357.35884
B64: Inventories | C64: 315 | D64: 325.2375 | E64: 335.71125 | F64: 346.41928 | G64: 357.35884 | H64: 368.5263
B65: Other current assets | C65: 87.5 | D65: 91.875 | E65: 96.46875 | F65: 101.29219 | G65: 106.3568 | H65: 111.67464
B66: Total Current Assets | C66: =SUM(C62:C65) -> 5231.3483 | D66: =SUM(D62:D65) -> 5012.441 | E66: =SUM(E62:E65) -> 4856.0738 | F66: =SUM(F62:F65) -> 4765.7699 | G66: =SUM(G62:G65) -> 4745.2874 | H66: =SUM(H62:H65) -> 4798.6344
B68: Fixed Assets | C68: 10500 | D68: 10555.125 | E68: 10613.006 | F68: 10673.782 | G68: 10737.596 | H68: 10804.6
B69: Other LT assets | C69: 4 | D69: 4 | E69: 4 | F69: 4 | G69: 4 | H69: 4
B70: Total Long-Term Assets | C70: =SUM(C68:C69) -> 10504 | D70: =SUM(D68:D69) -> 10559.125 | E70: =SUM(E68:E69) -> 10617.006 | F70: =SUM(F68:F69) -> 10677.782 | G70: =SUM(G68:G69) -> 10741.596 | H70: =SUM(H68:H69) -> 10808.6
B72: Total Assets | C72: =C66+C70 -> 15735.348 | D72: =D66+D70 -> 15571.566 | E72: =E66+E70 -> 15473.08 | F72: =F66+F70 -> 15443.551 | G72: =G66+G70 -> 15486.883 | H72: =H66+H70 -> 15607.235
B74: Liabilities
B75: A/P | C75: 189 | D75: 195.1425 | E75: 201.42675 | F75: 207.85157 | G75: 214.4153 | H75: 221.11578
B76: Long-Term Debt Due within One Year | C76: 500 | D76: 500 | E76: 500 | F76: 500 | G76: 500 | H76: 500
B77: Other current liabilities | C77: 0.3 | D77: 0.3 | E77: 0.3 | F77: 0.3 | G77: 0.3 | H77: 0.3
B78: Total Current Liabilities | C78: =SUM(C75:C77) -> 689.3 | D78: =SUM(D75:D77) -> 695.4425 | E78: =SUM(E75:E77) -> 701.72675 | F78: =SUM(F75:F77) -> 708.15157 | G78: =SUM(G75:G77) -> 714.7153 | H78: =SUM(H75:H77) -> 721.41578
B80: Long-Term Debt | C80: 3500 | D80: 3000 | E80: 2500 | F80: 2000 | G80: 1500 | H80: 1000
B81: Other LT liabilities | C81: 1.1 | D81: 1.1 | E81: 1.1 | F81: 1.1 | G81: 1.1 | H81: 1.1
B82: Total Long-term Liabilities | C82: =SUM(C80:C81) -> 3501.1 | D82: =SUM(D80:D81) -> 3001.1 | E82: =SUM(E80:E81) -> 2501.1 | F82: =SUM(F80:F81) -> 2001.1 | G82: =SUM(G80:G81) -> 1501.1 | H82: =SUM(H80:H81) -> 1001.1
B84: Total Liabilities | C84: =C78+C82 -> 4190.4 | D84: =D78+D82 -> 3696.5425 | E84: =E78+E82 -> 3202.8267 | F84: =F78+F82 -> 2709.2516 | G84: =G78+G82 -> 2215.8153 | H84: =H78+H82 -> 1722.5158
B86: Shareholders' Equity
B87: Common Shares | C87: 3700 | D87: 3700 | E87: 3700 | F87: 3700 | G87: 3700 | H87: 3700
B88: Retained Earnings | C88: 7844.9483 | D88: 8175.0235 | E88: 8570.2533 | F88: 9034.2999 | G88: 9571.0678 | H88: 10184.719
B89: Total Shareholders' Equity | C89: =SUM(C87:C88) -> 11544.948 | D89: =SUM(D87:D88) -> 11875.024 | E89: =SUM(E87:E88) -> 12270.253 | F89: =SUM(F87:F88) -> 12734.3 | G89: =SUM(G87:G88) -> 13271.068 | H89: =SUM(H87:H88) -> 13884.719
B91: Total Liabilities & Shareholders' Equity | C91: =C84+C89 -> 15735.348 | D91: =D84+D89 -> 15571.566 | E91: =E84+E89 -> 15473.08 | F91: =F84+F89 -> 15443.551 | G91: =G84+G89 -> 15486.883 | H91: =H84+H89 -> 15607.235
B92: Check | C92: =C72-C91 -> 0 | D92: =D72-D91 -> 0 | E92: =E72-E91 -> 0 | F92: =F72-F91 -> 0 | G92: =G72-G91 -> 0 | H92: =H72-H91 -> 0
A96: Bravo Financial Statements (Prior to the Acquisition)
B99: Income statement
B100: (in USD$ millions, fiscal years ended December 31st)
C102: =C59 -> 2021 | D102: =D59 -> 2022 | E102: =E59 -> 2023 | F102: =F59 -> 2024 | G102: =G59 -> 2025 | H102: =H59 -> 2026
B104: Revenue | C104: 1428.5714 | D104: 1514.2857 | E104: 1605.1429 | F104: 1701.4514 | G104: 1803.5385 | H104: 1911.7508
B105: Less: COGS | C105: -828.57143 | D105: -863.14286 | E105: -898.88 | F105: -935.79829 | G105: -973.9108 | H105: -1013.2279
B106: Gross Profit | C106: =SUM(C104:C105) -> 600 | D106: =SUM(D104:D105) -> 651.14286 | E106: =SUM(E104:E105) -> 706.26286 | F106: =SUM(F104:F105) -> 765.65314 | G106: =SUM(G104:G105) -> 829.62772 | H106: =SUM(H104:H105) -> 898.52289
B107: Less: SG&A | C107: -57.142857 | D107: -60.571429 | E107: -64.205714 | F107: -68.058057 | G107: -72.141541 | H107: -76.470033
B108: EBITDA | C108: =SUM(C106:C107) -> 542.85714 | D108: =SUM(D106:D107) -> 590.57143 | E108: =SUM(E106:E107) -> 642.05714 | F108: =SUM(F106:F107) -> 697.59509 | G108: =SUM(G106:G107) -> 757.48618 | H108: =SUM(H106:H107) -> 822.05285
B109: Less: Depreciation | C109: -207.14286 | D109: -219.57143 | E109: -232.74571 | F109: -246.71046 | G109: -261.51308 | H109: -277.20387
B110: EBIT | C110: =SUM(C108:C109) -> 335.71429 | D110: =SUM(D108:D109) -> 371 | E110: =SUM(E108:E109) -> 409.31143 | F110: =SUM(F108:F109) -> 450.88463 | G110: =SUM(G108:G109) -> 495.97309 | H110: =SUM(H108:H109) -> 544.84899
B111: Add/(Less): Net Interest Income/(Expense) | C111: -121.78602 | D111: -107.29928 | E111: -92.687264 | F111: -77.937961 | G111: -63.042431 | H111: -47.991038
B112: EBT | C112: =SUM(C110:C111) -> 213.92827 | D112: =SUM(D110:D111) -> 263.70072 | E112: =SUM(E110:E111) -> 316.62416 | F112: =SUM(F110:F111) -> 372.94667 | G112: =SUM(G110:G111) -> 432.93066 | H112: =SUM(H110:H111) -> 496.85795
B113: Less: Taxes | C113: -49.203502 | D113: -60.651166 | E113: -72.823558 | F113: -85.777734 | G113: -99.574052 | H113: -114.27733
B114: Net Income | C114: =SUM(C112:C113) -> 164.72477 | D114: =SUM(D112:D113) -> 203.04956 | E114: =SUM(E112:E113) -> 243.80061 | F114: =SUM(F112:F113) -> 287.16893 | G114: =SUM(G112:G113) -> 333.35661 | H114: =SUM(H112:H113) -> 382.58062
B118: Cash Flow Statement
B119: (in USD$ millions, fiscal years ended December 31st)
C121: =C102 -> 2021 | D121: =D102 -> 2022 | E121: =E102 -> 2023 | F121: =F102 -> 2024 | G121: =G102 -> 2025 | H121: =H102 -> 2026
B123: Cash Flow from Operations
B124: Net Income | C124: =C114 -> 164.72477 | D124: =D114 -> 203.04956 | E124: =E114 -> 243.80061 | F124: =F114 -> 287.16893 | G124: =G114 -> 333.35661 | H124: =H114 -> 382.58062
B125: Add: Depreciation | C125: =-C109 -> 207.14286 | D125: =-D109 -> 219.57143 | E125: =-E109 -> 232.74571 | F125: =-F109 -> 246.71046 | G125: =-G109 -> 261.51308 | H125: =-H109 -> 277.20387
B126: Add/(Less): Change in W/C | C126: -9 | D126: -11.074286 | E126: -11.684229 | F126: -12.327497 | G126: -13.005895 | H126: -13.721321
B127: Cash Flow from Operations | C127: =SUM(C124:C126) -> 362.86762 | D127: =SUM(D124:D126) -> 411.5467 | E127: =SUM(E124:E126) -> 464.86209 | F127: =SUM(F124:F126) -> 521.55189 | G127: =SUM(G124:G126) -> 581.8638 | H127: =SUM(H124:H126) -> 646.06317
B129: Cash Flow from Investing Activities
B130: Less: Capex | C130: -227.85714 | D130: -241.52857 | E130: -256.02029 | F130: -271.3815 | G130: -287.66439 | H130: -304.92426
B131: Cash Flow from Investing Activities | C131: =SUM(C130:C130) -> -227.85714 | D131: =SUM(D130:D130) -> -241.52857 | E131: =SUM(E130:E130) -> -256.02029 | F131: =SUM(F130:F130) -> -271.3815 | G131: =SUM(G130:G130) -> -287.66439 | H131: =SUM(H130:H130) -> -304.92426
B133: Cash Flow from Financing Activities
B134: Add/(Less): Issuance/(Repayment) of Debt | C134: -200 | D134: -200 | E134: -200 | F134: -200 | G134: -200 | H134: -200
B135: Add/(Less): Issuance/(Repayment) of Common Shares | C135: 0 | D135: 0 | E135: 0 | F135: 0 | G135: 0 | H135: 0
B136: Less: Dividends | C136: -49.41743 | D136: -60.914867 | E136: -73.140182 | F136: -86.15068 | G136: -100.00698 | H136: -114.77419
B137: Cash Flow from Financing Activities | C137: =SUM(C134:C136) -> -249.41743 | D137: =SUM(D134:D136) -> -260.91487 | E137: =SUM(E134:E136) -> -273.14018 | F137: =SUM(F134:F136) -> -286.15068 | G137: =SUM(G134:G136) -> -300.00698 | H137: =SUM(H134:H136) -> -314.77419
B139: Beginning Cash & Equivalents | C139: 1200 | D139: =C141 -> 1085.5931 | E139: =D141 -> 994.69631 | F139: =E141 -> 930.39794 | G139: =F141 -> 894.41765 | H139: =G141 -> 888.61007
B140: Change in Cash & Equivalents | C140: =C127+C131+C137 -> -114.40695 | D140: =D127+D131+D137 -> -90.896739 | E140: =E127+E131+E137 -> -64.298375 | F140: =F127+F131+F137 -> -35.980289 | G140: =G127+G131+G137 -> -5.807577 | H140: =H127+H131+H137 -> 26.364726
B141: Ending Cash & Equivalents | C141: =SUM(C139:C140) -> 1085.5931 | D141: =SUM(D139:D140) -> 994.69631 | E141: =SUM(E139:E140) -> 930.39794 | F141: =SUM(F139:F140) -> 894.41765 | G141: =SUM(G139:G140) -> 888.61007 | H141: =SUM(H139:H140) -> 914.9748
...

Sheet CaseSolution
B2: Pro Forma Financial Statements
C4: Pro Forma Financial Statements | D4: Click Here
B7: Summary Table of Answers
E9: % of Bravo's Equity Acquired by Alpha
E10: 0.25 | F10: 0.75 | G10: 1
C11: 2025 Retained Earnings | D11: =$H$120 -> 10638.443 | E11: 9837.9117 | F11: 10371.6 | G11: 10638.443
C12: 2023 Investment in Bravo | D12: =$F$98 -> 0 | E12: 1203.1988 | F12: 0 | G12: 0
C13: 2024 Non-Controlling Interests | D13: =$G$121 -> 0 | E13: 0 | F13: 1253.4533 | G13: 0
C14: 2026 EBITDA | D14: =$I$41 -> 2608.847 | E14: 1786.7942 | F14: 2608.847 | G14: 2608.847
B18: ="LIVE: CURRENTLY RUNNING: "&UPPER(I27) -> LIVE: CURRENTLY RUNNING: CONSOLIDATION METHOD | K18: EQUITY METHODOLOGY | V18: CONSOLIDATION METHODOLOGY
C20: If Alpha acquires >=20% but <=50% of Bravo's equity, the Equity Method is applied. | F20: 0.2 | G20: 0.5 | H20: Equity Method | L20: =C20 -> If Alpha acquires >=20% but <=50% of Bravo's equity, the Equity Method is applied. | W20: =C21 -> If Alpha acquires >50% of Bravo's equity, the Consolidation Method is applied.
C21: If Alpha acquires >50% of Bravo's equity, the Consolidation Method is applied. | F21: 0.5 | H21: Consolidation Method
B23: Acquisition Assumptions | K23: Acquisition Assumptions | V23: Acquisition Assumptions
C25: Value of 100% of Bravo's Equity | D25: USD$ millions | E25: =CaseData!E3 -> 4500 | G25: BS Check: | I25: =IF(AND(MAX(D125:I125)=0, MIN(D125:I125)=0), "Balanced", "Error") -> Balanced | L25: Value of 100% of Bravo's Equity | M25: USD$ millions | N25: =$E25 -> 4500 | Q25: BS Check: | S25: =IF(AND(MAX(O125:T125)=0, MIN(O125:T125)=0), "Balanced", "Error") -> Balanced | W25: Value of 100% of Bravo's Equity | X25: USD$ millions | Y25: =$E25 -> 4500 | AB25: BS Check: | AD25: =IF(AND(MAX(Z125:AE125)=0, MIN(Z125:AE125)=0), "Balanced", "Error") -> Balanced
C26: Percentage of Bravo's Equity Acquired by Alpha | D26: % | E26: =CaseData!E4 -> 1 | L26: Percentage of Bravo's Equity Acquired by Alpha | M26: % | N26: =$E26 -> 1 | W26: Percentage of Bravo's Equity Acquired by Alpha | X26: % | Y26: =$E26 -> 1
G27: Running: | I27: =VLOOKUP($E$26,$F$20:$H$21,COLUMNS($F$20:$H$20),TRUE) -> Consolidation Method | Q27: Running: | S27: =H20 -> Equity Method | AB27: Running: | AD27: =H21 -> Consolidation Method
B29: ="Alpha Financial Statements (Pro-Forma under "&I27&")" -> Alpha Financial Statements (Pro-Forma under Consolidation Method) | K29: ="Alpha Financial Statements (Pro-Forma under "&S27&")" -> Alpha Financial Statements (Pro-Forma under Equity Method) | V29: ="Alpha Financial Statements (Pro-Forma under "&AD27&")" -> Alpha Financial Statements (Pro-Forma under Consolidation Method)
C32: ="Alpha Income Statement (Pro-Forma under "&I27&")" -> Alpha Income Statement (Pro-Forma under Consolidation Method) | L32: ="Alpha Income Statement (Pro-Forma under "&S27&")" -> Alpha Income Statement (Pro-Forma under Equity Method) | W32: ="Alpha Income Statement (Pro-Forma under "&AD27&")" -> Alpha Income Statement (Pro-Forma under Consolidation Method)
C33: (in USD$ millions, fiscal years ended December 31st) | L33: (in USD$ millions, fiscal years ended December 31st) | W33: (in USD$ millions, fiscal years ended December 31st)
D35: =O35 -> 44561 | E35: =P35 -> 44926 | F35: =Q35 -> 45291 | G35: =R35 -> 45657 | H35: =S35 -> 46022 | I35: =T35 -> 46387 | O35: =O135 -> 44561 | P35: =P135 -> 44926 | Q35: =Q135 -> 45291 | R35: =R135 -> 45657 | S35: =S135 -> 46022 | T35: =T135 -> 46387 | Z35: =Z135 -> 44561 | AA35: =AA135 -> 44926 | AB35: =AB135 -> 45291 | AC35: =AC135 -> 45657 | AD35: =AD135 -> 46022 | AE35: =AE135 -> 46387
C37: Revenue | E37: =IF($I$27=$H$20,P37,AA37) -> 5189.2857 | F37: =IF($I$27=$H$20,Q37,AB37) -> 5463.8929 | G37: =IF($I$27=$H$20,R37,AC37) -> 5753.1389 | H37: =IF($I$27=$H$20,S37,AD37) -> 6057.8104 | I37: =IF($I$27=$H$20,T37,AE37) -> 6378.7363 | L37: Revenue | P37: =P137 -> 3675 | Q37: =Q137 -> 3858.75 | R37: =R137 -> 4051.6875 | S37: =S137 -> 4254.2719 | T37: =T137 -> 4466.9855 | W37: Revenue | AA37: =SUM(AA137,AA226) -> 5189.2857 | AB37: =SUM(AB137,AB226) -> 5463.8929 | AC37: =SUM(AC137,AC226) -> 5753.1389 | AD37: =SUM(AD137,AD226) -> 6057.8104 | AE37: =SUM(AE137,AE226) -> 6378.7363
C38: Less: COGS | E38: =IF($I$27=$H$20,P38,AA38) -> -3031.3929 | F38: =IF($I$27=$H$20,Q38,AB38) -> -3136.955 | G38: =IF($I$27=$H$20,R38,AC38) -> -3245.2602 | H38: =IF($I$27=$H$20,S38,AD38) -> -3356.303 | I38: =IF($I$27=$H$20,T38,AE38) -> -3470.0699 | L38: Less: COGS | P38: =P138 -> -2168.25 | Q38: =Q138 -> -2238.075 | R38: =R138 -> -2309.4619 | S38: =S138 -> -2382.3922 | T38: =T138 -> -2456.842 | W38: Less: COGS | AA38: =SUM(AA138,AA227) -> -3031.3929 | AB38: =SUM(AB138,AB227) -> -3136.955 | AC38: =SUM(AC138,AC227) -> -3245.2602 | AD38: =SUM(AD138,AD227) -> -3356.303 | AE38: =SUM(AE138,AE227) -> -3470.0699
C39: Gross Profit | E39: =SUM(E37:E38) -> 2157.8929 | F39: =SUM(F37:F38) -> 2326.9379 | G39: =SUM(G37:G38) -> 2507.8788 | H39: =SUM(H37:H38) -> 2701.5073 | I39: =SUM(I37:I38) -> 2908.6663 | L39: Gross Profit | P39: =SUM(P37:P38) -> 1506.75 | Q39: =SUM(Q37:Q38) -> 1620.675 | R39: =SUM(R37:R38) -> 1742.2256 | S39: =SUM(S37:S38) -> 1871.8796 | T39: =SUM(T37:T38) -> 2010.1435 | W39: Gross Profit | AA39: =SUM(AA37:AA38) -> 2157.8929 | AB39: =SUM(AB37:AB38) -> 2326.9379 | AC39: =SUM(AC37:AC38) -> 2507.8788 | AD39: =SUM(AD37:AD38) -> 2701.5073 | AE39: =SUM(AE37:AE38) -> 2908.6663
C40: Less: SG&A | E40: =IF($I$27=$H$20,P40,AA40) -> -244.32143 | F40: =IF($I$27=$H$20,Q40,AB40) -> -257.14321 | G40: =IF($I$27=$H$20,R40,AC40) -> -270.64243 | H40: =IF($I$27=$H$20,S40,AD40) -> -284.85513 | I40: =IF($I$27=$H$20,T40,AE40) -> -299.81931 | L40: Less: SG&A | P40: =P140 -> -183.75 | Q40: =Q140 -> -192.9375 | R40: =R140 -> -202.58438 | S40: =S140 -> -212.71359 | T40: =T140 -> -223.34927 | W40: Less: SG&A | AA40: =SUM(AA140,AA229) -> -244.32143 | AB40: =SUM(AB140,AB229) -> -257.14321 | AC40: =SUM(AC140,AC229) -> -270.64243 | AD40: =SUM(AD140,AD229) -> -284.85513 | AE40: =SUM(AE140,AE229) -> -299.81931
C41: EBITDA | E41: =SUM(E39:E40) -> 1913.5714 | F41: =SUM(F39:F40) -> 2069.7946 | G41: =SUM(G39:G40) -> 2237.2363 | H41: =SUM(H39:H40) -> 2416.6522 | I41: =SUM(I39:I40) -> 2608.847 | L41: EBITDA | P41: =SUM(P39:P40) -> 1323 | Q41: =SUM(Q39:Q40) -> 1427.7375 | R41: =SUM(R39:R40) -> 1539.6413 | S41: =SUM(S39:S40) -> 1659.166 | T41: =SUM(T39:T40) -> 1786.7942 | W41: EBITDA | AA41: =SUM(AA39:AA40) -> 1913.5714 | AB41: =SUM(AB39:AB40) -> 2069.7946 | AC41: =SUM(AC39:AC40) -> 2237.2363 | AD41: =SUM(AD39:AD40) -> 2416.6522 | AE41: =SUM(AE39:AE40) -> 2608.847
C42: Less: Depreciation | E42: =IF($I$27=$H$20,P42,AA42) -> -770.82143 | F42: =IF($I$27=$H$20,Q42,AB42) -> -811.55821 | G42: =IF($I$27=$H$20,R42,AC42) -> -854.46358 | H42: =IF($I$27=$H$20,S42,AD42) -> -899.65387 | I42: =IF($I$27=$H$20,T42,AE42) -> -947.25169 | L42: Less: Depreciation | P42: =P142 -> -551.25 | Q42: =Q142 -> -578.8125 | R42: =R142 -> -607.75312 | S42: =S142 -> -638.14078 | T42: =T142 -> -670.04782 | W42: Less: Depreciation | AA42: =SUM(AA142,AA231) -> -770.82143 | AB42: =SUM(AB142,AB231) -> -811.55821 | AC42: =SUM(AC142,AC231) -> -854.46358 | AD42: =SUM(AD142,AD231) -> -899.65387 | AE42: =SUM(AE142,AE231) -> -947.25169
C43: EBIT | E43: =SUM(E41:E42) -> 1142.75 | F43: =SUM(F41:F42) -> 1258.2364 | G43: =SUM(G41:G42) -> 1382.7728 | H43: =SUM(H41:H42) -> 1516.9983 | I43: =SUM(I41:I42) -> 1661.5954 | L43: EBIT | P43: =SUM(P41:P42) -> 771.75 | Q43: =SUM(Q41:Q42) -> 848.925 | R43: =SUM(R41:R42) -> 931.88813 | S43: =SUM(S41:S42) -> 1021.0253 | T43: =SUM(T41:T42) -> 1116.7464 | W43: EBIT | AA43: =SUM(AA41:AA42) -> 1142.75 | AB43: =SUM(AB41:AB42) -> 1258.2364 | AC43: =SUM(AC41:AC42) -> 1382.7728 | AD43: =SUM(AD41:AD42) -> 1516.9983 | AE43: =SUM(AE41:AE42) -> 1661.5954
C44: Add/(Less): Net Interest Income/(Expense) | E44: =IF($I$27=$H$20,P44,AA44) -> -328.92383 | F44: =IF($I$27=$H$20,Q44,AB44) -> -282.89596 | G44: =IF($I$27=$H$20,R44,AC44) -> -236.41517 | H44: =IF($I$27=$H$20,S44,AD44) -> -189.45455 | I44: =IF($I$27=$H$20,T44,AE44) -> -141.98528 | L44: Add/(Less): Net Interest Income/(Expense) | P44: =P144 -> -221.62456 | Q44: =Q144 -> -190.20869 | R44: =R144 -> -158.47721 | S44: =S144 -> -126.41212 | T44: =T144 -> -93.994238 | W44: Add/(Less): Net Interest Income/(Expense) | AA44: =SUM(AA144,AA233) -> -328.92383 | AB44: =SUM(AB144,AB233) -> -282.89596 | AC44: =SUM(AC144,AC233) -> -236.41517 | AD44: =SUM(AD144,AD233) -> -189.45455 | AE44: =SUM(AE144,AE233) -> -141.98528
C45: Earnings before Share of Earnings from Bravo and Tax | E45: =SUM(E43:E44) -> 813.82617 | F45: =SUM(F43:F44) -> 975.34047 | G45: =SUM(G43:G44) -> 1146.3576 | H45: =SUM(H43:H44) -> 1327.5438 | I45: =SUM(I43:I44) -> 1519.6101 | L45: Earnings before Share of Earnings from Bravo and Tax | P45: =SUM(P43:P44) -> 550.12544 | Q45: =SUM(Q43:Q44) -> 658.71631 | R45: =SUM(R43:R44) -> 773.41092 | S45: =SUM(S43:S44) -> 894.61313 | T45: =SUM(T43:T44) -> 1022.7521 | W45: Earnings before Share of Earnings from Bravo and Tax | AA45: =SUM(AA43:AA44) -> 813.82617 | AB45: =SUM(AB43:AB44) -> 975.34047 | AC45: =SUM(AC43:AC44) -> 1146.3576 | AD45: =SUM(AD43:AD44) -> 1327.5438 | AE45: =SUM(AE43:AE44) -> 1519.6101
C46: Add: Share of Earnings from Bravo | E46: =IF($I$27=$H$20,P46,AA46) -> 0 | F46: =IF($I$27=$H$20,Q46,AB46) -> 0 | G46: =IF($I$27=$H$20,R46,AC46) -> 0 | H46: =IF($I$27=$H$20,S46,AD46) -> 0 | I46: =IF($I$27=$H$20,T46,AE46) -> 0 | L46: Add: Share of Earnings from Bravo | P46: =P236*$N$26 -> 203.04956 | Q46: =Q236*$N$26 -> 243.80061 | R46: =R236*$N$26 -> 287.16893 | S46: =S236*$N$26 -> 333.35661 | T46: =T236*$N$26 -> 382.58062 | W46: Add: Share of Earnings from Bravo | AA46: 0 | AB46: 0 | AC46: 0 | AD46: 0 | AE46: 0
C47: EBT | E47: =SUM(E45:E46) -> 813.82617 | F47: =SUM(F45:F46) -> 975.34047 | G47: =SUM(G45:G46) -> 1146.3576 | H47: =SUM(H45:H46) -> 1327.5438 | I47: =SUM(I45:I46) -> 1519.6101 | L47: EBT | P47: =SUM(P45:P46) -> 753.175 | Q47: =SUM(Q45:Q46) -> 902.51691 | R47: =SUM(R45:R46) -> 1060.5799 | S47: =SUM(S45:S46) -> 1227.9697 | T47: =SUM(T45:T46) -> 1405.3327 | W47: EBT | AA47: =SUM(AA45:AA46) -> 813.82617 | AB47: =SUM(AB45:AB46) -> 975.34047 | AC47: =SUM(AC45:AC46) -> 1146.3576 | AD47: =SUM(AD45:AD46) -> 1327.5438 | AE47: =SUM(AE45:AE46) -> 1519.6101
C48: Less: Taxes | E48: =IF($I$27=$H$20,P48,AA48) -> -198.18253 | F48: =IF($I$27=$H$20,Q48,AB48) -> -237.50263 | G48: =IF($I$27=$H$20,R48,AC48) -> -279.13046 | H48: =IF($I$27=$H$20,S48,AD48) -> -323.22734 | I48: =IF($I$27=$H$20,T48,AE48) -> -369.96536 | L48: Less: Taxes | P48: =P146 -> -137.53136 | Q48: =Q146 -> -164.67908 | R48: =R146 -> -193.35273 | S48: =S146 -> -223.65328 | T48: =T146 -> -255.68803 | W48: Less: Taxes | AA48: =SUM(AA146,AA235) -> -198.18253 | AB48: =SUM(AB146,AB235) -> -237.50263 | AC48: =SUM(AC146,AC235) -> -279.13046 | AD48: =SUM(AD146,AD235) -> -323.22734 | AE48: =SUM(AE146,AE235) -> -369.96536
C49: Net Earnings before Noncontrolling Interest | E49: =SUM(E47:E48) -> 615.64364 | F49: =SUM(F47:F48) -> 737.83784 | G49: =SUM(G47:G48) -> 867.22712 | H49: =SUM(H47:H48) -> 1004.3165 | I49: =SUM(I47:I48) -> 1149.6447 | L49: Net Earnings before Noncontrolling Interest | P49: =SUM(P47:P48) -> 615.64364 | Q49: =SUM(Q47:Q48) -> 737.83784 | R49: =SUM(R47:R48) -> 867.22712 | S49: =SUM(S47:S48) -> 1004.3165 | T49: =SUM(T47:T48) -> 1149.6447 | W49: Net Earnings before Noncontrolling Interest | AA49: =SUM(AA47:AA48) -> 615.64364 | AB49: =SUM(AB47:AB48) -> 737.83784 | AC49: =SUM(AC47:AC48) -> 867.22712 | AD49: =SUM(AD47:AD48) -> 1004.3165 | AE49: =SUM(AE47:AE48) -> 1149.6447
C50: Less: Non-Controlling Interest | E50: =IF($I$27=$H$20,P50,AA50) -> 0 | F50: =IF($I$27=$H$20,Q50,AB50) -> 0 | G50: =IF($I$27=$H$20,R50,AC50) -> 0 | H50: =IF($I$27=$H$20,S50,AD50) -> 0 | I50: =IF($I$27=$H$20,T50,AE50) -> 0 | L50: Less: Non-Controlling Interest | P50: 0 | Q50: 0 | R50: 0 | S50: 0 | T50: 0 | W50: Less: Non-Controlling Interest | AA50: =-AA236*(1-$Y$26) -> 0 | AB50: =-AB236*(1-$Y$26) -> 0 | AC50: =-AC236*(1-$Y$26) -> 0 | AD50: =-AD236*(1-$Y$26) -> 0 | AE50: =-AE236*(1-$Y$26) -> 0
C51: Net Income | E51: =SUM(E49:E50) -> 615.64364 | F51: =SUM(F49:F50) -> 737.83784 | G51: =SUM(G49:G50) -> 867.22712 | H51: =SUM(H49:H50) -> 1004.3165 | I51: =SUM(I49:I50) -> 1149.6447 | L51: Net Income | P51: =SUM(P49:P50) -> 615.64364 | Q51: =SUM(Q49:Q50) -> 737.83784 | R51: =SUM(R49:R50) -> 867.22712 | S51: =SUM(S49:S50) -> 1004.3165 | T51: =SUM(T49:T50) -> 1149.6447 | W51: Net Income | AA51: =SUM(AA49:AA50) -> 615.64364 | AB51: =SUM(AB49:AB50) -> 737.83784 | AC51: =SUM(AC49:AC50) -> 867.22712 | AD51: =SUM(AD49:AD50) -> 1004.3165 | AE51: =SUM(AE49:AE50) -> 1149.6447
C55: ="Alpha Cash Flow Statement (Pro-Forma under "&I27&")" -> Alpha Cash Flow Statement (Pro-Forma under Consolidation Method) | L55: ="Alpha Cash Flow Statement (Pro-Forma under "&S27&")" -> Alpha Cash Flow Statement (Pro-Forma under Equity Method) | W55: ="Alpha Cash Flow Statement (Pro-Forma under "&AD27&")" -> Alpha Cash Flow Statement (Pro-Forma under Consolidation Method)
C56: (in USD$ millions, fiscal years ended December 31st) | L56: (in USD$ millions, fiscal years ended December 31st) | W56: (in USD$ millions, fiscal years ended December 31st)
D58: =D35 -> 44561 | E58: =E35 -> 44926 | F58: =F35 -> 45291 | G58: =G35 -> 45657 | H58: =H35 -> 46022 | I58: =I35 -> 46387 | O58: =O35 -> 44561 | P58: =P35 -> 44926 | Q58: =Q35 -> 45291 | R58: =R35 -> 45657 | S58: =S35 -> 46022 | T58: =T35 -> 46387 | Z58: =Z35 -> 44561 | AA58: =AA35 -> 44926 | AB58: =AB35 -> 45291 | AC58: =AC35 -> 45657 | AD58: =AD35 -> 46022 | AE58: =AE35 -> 46387
C60: Cash Flow from Operations | L60: Cash Flow from Operations | W60: Cash Flow from Operations
C61: Net Income | E61: =E51 -> 615.64364 | F61: =F51 -> 737.83784 | G61: =G51 -> 867.22712 | H61: =H51 -> 1004.3165 | I61: =I51 -> 1149.6447 | L61: Net Income | P61: =P51 -> 615.64364 | Q61: =Q51 -> 737.83784 | R61: =R51 -> 867.22712 | S61: =S51 -> 1004.3165 | T61: =T51 -> 1149.6447 | W61: Net Income | AA61: =AA51 -> 615.64364 | AB61: =AB51 -> 737.83784 | AC61: =AC51 -> 867.22712 | AD61: =AD51 -> 1004.3165 | AE61: =AE51 -> 1149.6447
C62: Add: Depreciation | E62: =-E42 -> 770.82143 | F62: =-F42 -> 811.55821 | G62: =-G42 -> 854.46358 | H62: =-H42 -> 899.65387 | I62: =-I42 -> 947.25169 | L62: Add: Depreciation | P62: =-P42 -> 551.25 | Q62: =-Q42 -> 578.8125 | R62: =-R42 -> 607.75312 | S62: =-S42 -> 638.14078 | T62: =-T42 -> 670.04782 | W62: Add: Depreciation | AA62: =-AA42 -> 770.82143 | AB62: =-AB42 -> 811.55821 | AC62: =-AC42 -> 854.46358 | AD62: =-AD42 -> 899.65387 | AE62: =-AE42 -> 947.25169
C63: Add: Non-Controlling Interest | E63: =-E50 -> 0 | F63: =-F50 -> 0 | G63: =-G50 -> 0 | H63: =-H50 -> 0 | I63: =-I50 -> 0 | L63: Add: Non-Controlling Interest | P63: =P50 -> 0 | Q63: =Q50 -> 0 | R63: =R50 -> 0 | S63: =S50 -> 0 | T63: =T50 -> 0 | W63: Add: Non-Controlling Interest | AA63: =-AA50 -> 0 | AB63: =-AB50 -> 0 | AC63: =-AC50 -> 0 | AD63: =-AD50 -> 0 | AE63: =-AE50 -> 0
C64: Add: Share of Dividends from Bravo | E64: =IF($I$27=$H$20,P64,AA64) -> 0 | F64: =IF($I$27=$H$20,Q64,AB64) -> 0 | G64: =IF($I$27=$H$20,R64,AC64) -> 0 | H64: =IF($I$27=$H$20,S64,AD64) -> 0 | I64: =IF($I$27=$H$20,T64,AE64) -> 0 | L64: Add: Share of Dividends from Bravo | P64: =-P258*$N$26 -> 60.914867 | Q64: =-Q258*$N$26 -> 73.140182 | R64: =-R258*$N$26 -> 86.15068 | S64: =-S258*$N$26 -> 100.00698 | T64: =-T258*$N$26 -> 114.77419 | W64: Add: Share of Dividends from Bravo | AA64: 0 | AB64: 0 | AC64: 0 | AD64: 0 | AE64: 0
C65: Add/(Less): Change in W/C | E65: =IF($I$27=$H$20,P65,AA65) -> -33.544286 | F65: =IF($I$27=$H$20,Q65,AB65) -> -35.167479 | G65: =IF($I$27=$H$20,R65,AC65) -> -36.869147 | H65: =IF($I$27=$H$20,S65,AD65) -> -38.653077 | I65: =IF($I$27=$H$20,T65,AE65) -> -40.523234 | L65: Add/(Less): Change in W/C | P65: =P159 -> -22.47 | Q65: =Q159 -> -23.48325 | R65: =R159 -> -24.54165 | S65: =S159 -> -25.647182 | T65: =T159 -> -26.801913 | W65: Add/(Less): Change in W/C | AA65: =SUM(AA159,AA248) -> -33.544286 | AB65: =SUM(AB159,AB248) -> -35.167479 | AC65: =SUM(AC159,AC248) -> -36.869147 | AD65: =SUM(AD159,AD248) -> -38.653077 | AE65: =SUM(AE159,AE248) -> -40.523234
C66: Less: Share of Earnings from Bravo | E66: =-E46 -> 0 | F66: =-F46 -> 0 | G66: =-G46 -> 0 | H66: =-H46 -> 0 | I66: =-I46 -> 0 | L66: Less: Share of Earnings from Bravo | P66: =-P46 -> -203.04956 | Q66: =-Q46 -> -243.80061 | R66: =-R46 -> -287.16893 | S66: =-S46 -> -333.35661 | T66: =-T46 -> -382.58062 | W66: Less: Share of Earnings from Bravo | AA66: =-AA46 -> 0 | AB66: =-AB46 -> 0 | AC66: =-AC46 -> 0 | AD66: =-AD46 -> 0 | AE66: =-AE46 -> 0
C67: Cash Flow from Operations | E67: =SUM(E61:E66) -> 1352.9208 | F67: =SUM(F61:F66) -> 1514.2286 | G67: =SUM(G61:G66) -> 1684.8216 | H67: =SUM(H61:H66) -> 1865.3172 | I67: =SUM(I61:I66) -> 2056.3732 | L67: Cash Flow from Operations | P67: =SUM(P61:P66) -> 1002.2889 | Q67: =SUM(Q61:Q66) -> 1122.5067 | R67: =SUM(R61:R66) -> 1249.4203 | S67: =SUM(S61:S66) -> 1383.4604 | T67: =SUM(T61:T66) -> 1525.0842 | W67: Cash Flow from Operations | AA67: =SUM(AA61:AA66) -> 1352.9208 | AB67: =SUM(AB61:AB66) -> 1514.2286 | AC67: =SUM(AC61:AC66) -> 1684.8216 | AD67: =SUM(AD61:AD66) -> 1865.3172 | AE67: =SUM(AE61:AE66) -> 2056.3732
C69: Cash Flow from Investing Activities | L69: Cash Flow from Investing Activities | W69: Cash Flow from Investing Activities
C70: Less: Capex | E70: =IF($I$27=$H$20,P70,AA70) -> -847.90357 | F70: =IF($I$27=$H$20,Q70,AB70) -> -892.71404 | G70: =IF($I$27=$H$20,R70,AC70) -> -939.90994 | H70: =IF($I$27=$H$20,S70,AD70) -> -989.61925 | I70: =IF($I$27=$H$20,T70,AE70) -> -1041.9769 | L70: Less: Capex | P70: =P163 -> -606.375 | Q70: =Q163 -> -636.69375 | R70: =R163 -> -668.52844 | S70: =S163 -> -701.95486 | T70: =T163 -> -737.0526 | W70: Less: Capex | AA70: =SUM(AA163,AA252) -> -847.90357 | AB70: =SUM(AB163,AB252) -> -892.71404 | AC70: =SUM(AC163,AC252) -> -939.90994 | AD70: =SUM(AD163,AD252) -> -989.61925 | AE70: =SUM(AE163,AE252) -> -1041.9769
C71: Cash Flow from Investing Activities | E71: =SUM(E70:E70) -> -847.90357 | F71: =SUM(F70:F70) -> -892.71404 | G71: =SUM(G70:G70) -> -939.90994 | H71: =SUM(H70:H70) -> -989.61925 | I71: =SUM(I70:I70) -> -1041.9769 | L71: Cash Flow from Investing Activities | P71: =SUM(P70:P70) -> -606.375 | Q71: =SUM(Q70:Q70) -> -636.69375 | R71: =SUM(R70:R70) -> -668.52844 | S71: =SUM(S70:S70) -> -701.95486 | T71: =SUM(T70:T70) -> -737.0526 | W71: Cash Flow from Investing Activities | AA71: =SUM(AA70:AA70) -> -847.90357 | AB71: =SUM(AB70:AB70) -> -892.71404 | AC71: =SUM(AC70:AC70) -> -939.90994 | AD71: =SUM(AD70:AD70) -> -989.61925 | AE71: =SUM(AE70:AE70) -> -1041.9769
C73: Cash Flow from Financing Activities | L73: Cash Flow from Financing Activities | W73: Cash Flow from Financing Activities
C74: Add/(Less): Issuance/(Repayment) of Debt | E74: =IF($I$27=$H$20,P74,AA74) -> -700 | F74: =IF($I$27=$H$20,Q74,AB74) -> -700 | G74: =IF($I$27=$H$20,R74,AC74) -> -700 | H74: =IF($I$27=$H$20,S74,AD74) -> -700 | I74: =IF($I$27=$H$20,T74,AE74) -> -700 | L74: Add/(Less): Issuance/(Repayment) of Debt | P74: =P167 -> -500 | Q74: =Q167 -> -500 | R74: =R167 -> -500 | S74: =S167 -> -500 | T74: =T167 -> -500 | W74: Add/(Less): Issuance/(Repayment) of Debt | AA74: =SUM(AA167,AA256) -> -700 | AB74: =SUM(AB167,AB256) -> -700 | AC74: =SUM(AC167,AC256) -> -700 | AD74: =SUM(AD167,AD256) -> -700 | AE74: =SUM(AE167,AE256) -> -700
C75: Add/(Less): Issuance/(Repayment) of Common Shares | E75: =IF($I$27=$H$20,P75,AA75) -> 0 | F75: =IF($I$27=$H$20,Q75,AB75) -> 0 | G75: =IF($I$27=$H$20,R75,AC75) -> 0 | H75: =IF($I$27=$H$20,S75,AD75) -> 0 | I75: =IF($I$27=$H$20,T75,AE75) -> 0 | L75: Add/(Less): Issuance/(Repayment) of Common Shares | P75: =P168 -> 0 | Q75: =Q168 -> 0 | R75: =R168 -> 0 | S75: =S168 -> 0 | T75: =T168 -> 0 | W75: Add/(Less): Issuance/(Repayment) of Common Shares | AA75: =SUM(AA168,AA257) -> 0 | AB75: =SUM(AB168,AB257) -> 0 | AC75: =SUM(AC168,AC257) -> 0 | AD75: =SUM(AD168,AD257) -> 0 | AE75: =SUM(AE168,AE257) -> 0
C76: Less: Dividends Paid to Non-Controlling Interests | E76: =IF($I$27=$H$20,P76,AA76) -> 0 | F76: =IF($I$27=$H$20,Q76,AB76) -> 0 | G76: =IF($I$27=$H$20,R76,AC76) -> 0 | H76: =IF($I$27=$H$20,S76,AD76) -> 0 | I76: =IF($I$27=$H$20,T76,AE76) -> 0 | L76: Less: Dividends Paid to Non-Controlling Interests | P76: 0 | Q76: 0 | R76: 0 | S76: 0 | T76: 0 | W76: Less: Dividends Paid to Non-Controlling Interests | AA76: =AA258*(1-$Y$26) -> 0 | AB76: =AB258*(1-$Y$26) -> 0 | AC76: =AC258*(1-$Y$26) -> 0 | AD76: =AD258*(1-$Y$26) -> 0 | AE76: =AE258*(1-$Y$26) -> 0
C77: Less: Dividends | E77: =IF($I$27=$H$20,P77,AA77) -> -82.518816 | F77: =IF($I$27=$H$20,Q77,AB77) -> -98.807446 | G77: =IF($I$27=$H$20,R77,AC77) -> -116.01164 | H77: =IF($I$27=$H$20,S77,AD77) -> -134.19197 | I77: =IF($I$27=$H$20,T77,AE77) -> -153.41282 | L77: Less: Dividends | P77: =P169 -> -82.518816 | Q77: =Q169 -> -98.807446 | R77: =R169 -> -116.01164 | S77: =S169 -> -134.19197 | T77: =T169 -> -153.41282 | W77: Less: Dividends | AA77: =SUM(AA169) -> -82.518816 | AB77: =SUM(AB169) -> -98.807446 | AC77: =SUM(AC169) -> -116.01164 | AD77: =SUM(AD169) -> -134.19197 | AE77: =SUM(AE169) -> -153.41282
C78: Cash Flow from Financing Activities | E78: =SUM(E74:E77) -> -782.51882 | F78: =SUM(F74:F77) -> -798.80745 | G78: =SUM(G74:G77) -> -816.01164 | H78: =SUM(H74:H77) -> -834.19197 | I78: =SUM(I74:I77) -> -853.41282 | L78: Cash Flow from Financing Activities | P78: =SUM(P74:P77) -> -582.51882 | Q78: =SUM(Q74:Q77) -> -598.80745 | R78: =SUM(R74:R77) -> -616.01164 | S78: =SUM(S74:S77) -> -634.19197 | T78: =SUM(T74:T77) -> -653.41282 | W78: Cash Flow from Financing Activities | AA78: =SUM(AA74:AA77) -> -782.51882 | AB78: =SUM(AB74:AB77) -> -798.80745 | AC78: =SUM(AC74:AC77) -> -816.01164 | AD78: =SUM(AD74:AD77) -> -834.19197 | AE78: =SUM(AE74:AE77) -> -853.41282
C80: Beginning Cash & Equivalents | E80: =IF($I$27=$H$20,P80,AA80) -> 1134.4413 | F80: =IF($I$27=$H$20,Q80,AB80) -> 856.93972 | G80: =IF($I$27=$H$20,R80,AC80) -> 679.64681 | H80: =IF($I$27=$H$20,S80,AD80) -> 608.54679 | I80: =IF($I$27=$H$20,T80,AE80) -> 650.05281 | L80: Beginning Cash & Equivalents | P80: =O92 -> 48.848272 | Q80: =P82 -> -137.7566 | R80: =Q82 -> -250.75113 | S80: =R82 -> -285.87086 | T80: =S82 -> -238.55726 | W80: Beginning Cash & Equivalents | AA80: =Z92 -> 1134.4413 | AB80: =AA82 -> 856.93972 | AC80: =AB82 -> 679.64681 | AD80: =AC82 -> 608.54679 | AE80: =AD82 -> 650.05281
C81: Change in Cash & Equivalents | E81: =E67+E71+E78 -> -277.50161 | F81: =F67+F71+F78 -> -177.29291 | G81: =G67+G71+G78 -> -71.100021 | H81: =H67+H71+H78 -> 41.506026 | I81: =I67+I71+I78 -> 160.98349 | L81: Change in Cash & Equivalents | P81: =P67+P71+P78 -> -186.60487 | Q81: =Q67+Q71+Q78 -> -112.99453 | R81: =R67+R71+R78 -> -35.119731 | S81: =S67+S71+S78 -> 47.313603 | T81: =T67+T71+T78 -> 134.61877 | W81: Change in Cash & Equivalents | AA81: =AA67+AA71+AA78 -> -277.50161 | AB81: =AB67+AB71+AB78 -> -177.29291 | AC81: =AC67+AC71+AC78 -> -71.100021 | AD81: =AD67+AD71+AD78 -> 41.506026 | AE81: =AE67+AE71+AE78 -> 160.98349
C82: Ending Cash & Equivalents | E82: =SUM(E80:E81) -> 856.93972 | F82: =SUM(F80:F81) -> 679.64681 | G82: =SUM(G80:G81) -> 608.54679 | H82: =SUM(H80:H81) -> 650.05281 | I82: =SUM(I80:I81) -> 811.03631 | L82: Ending Cash & Equivalents | P82: =SUM(P80:P81) -> -137.7566 | Q82: =SUM(Q80:Q81) -> -250.75113 | R82: =SUM(R80:R81) -> -285.87086 | S82: =SUM(S80:S81) -> -238.55726 | T82: =SUM(T80:T81) -> -103.93849 | W82: Ending Cash & Equivalents | AA82: =SUM(AA80:AA81) -> 856.93972 | AB82: =SUM(AB80:AB81) -> 679.64681 | AC82: =SUM(AC80:AC81) -> 608.54679 | AD82: =SUM(AD80:AD81) -> 650.05281 | AE82: =SUM(AE80:AE81) -> 811.03631
C86: ="Alpha Balance Sheet (Pro-Forma under "&I27&")" -> Alpha Balance Sheet (Pro-Forma under Consolidation Method) | L86: ="Alpha Balance Sheet (Pro-Forma under "&S27&")" -> Alpha Balance Sheet (Pro-Forma under Equity Method) | W86: ="Alpha Balance Sheet (Pro-Forma under "&AD27&")" -> Alpha Balance Sheet (Pro-Forma under Consolidation Method)
C87: (in USD$ millions, fiscal years ended December 31st) | L87: (in USD$ millions, fiscal years ended December 31st) | W87: (in USD$ millions, fiscal years ended December 31st)
D89: =D58 -> 44561 | E89: =E58 -> 44926 | F89: =F58 -> 45291 | G89: =G58 -> 45657 | H89: =H58 -> 46022 | I89: =I58 -> 46387 | M89: Prior to Close | N89: Adjustments | O89: =O58 -> 44561 | P89: =P58 -> 44926 | Q89: =Q58 -> 45291 | R89: =R58 -> 45657 | S89: =S58 -> 46022 | T89: =T58 -> 46387 | X89: Prior to Close | Y89: Adjustments | Z89: =Z58 -> 44561 | AA89: =AA58 -> 44926 | AB89: =AB58 -> 45291 | AC89: =AC58 -> 45657 | AD89: =AD58 -> 46022 | AE89: =AE58 -> 46387
C91: Assets | L91: Assets | W91: Assets
C92: Cash and Equivalents | D92: =IF($I$27=$H$20,O92,Z92) -> 1134.4413 | E92: =E82 -> 856.93972 | F92: =F82 -> 679.64681 | G92: =G82 -> 608.54679 | H92: =H82 -> 650.05281 | I92: =I82 -> 811.03631 | L92: Cash and Equivalents | M92: =O184 -> 4548.8483 | N92: =-N26*N25 -> -4500 | O92: =SUM(M92:N92) -> 48.848272 | P92: =P82 -> -137.7566 | Q92: =Q82 -> -250.75113 | R92: =R82 -> -285.87086 | S92: =S82 -> -238.55726 | T92: =T82 -> -103.93849 | W92: Cash and Equivalents | X92: =Z184 -> 4548.8483 | Y92: =Z273-Y25*Y26 -> -3414.4069 | Z92: =SUM(X92:Y92) -> 1134.4413 | AA92: =AA82 -> 856.93972 | AB92: =AB82 -> 679.64681 | AC92: =AC82 -> 608.54679 | AD92: =AD82 -> 650.05281 | AE92: =AE82 -> 811.03631
C93: A/R | D93: =IF($I$27=$H$20,O93,Z93) -> 394.28571 | E93: =IF($I$27=$H$20,P93,AA93) -> 415.14286 | F93: =IF($I$27=$H$20,Q93,AB93) -> 437.11143 | G93: =IF($I$27=$H$20,R93,AC93) -> 460.25111 | H93: =IF($I$27=$H$20,S93,AD93) -> 484.62483 | I93: =IF($I$27=$H$20,T93,AE93) -> 510.2989 | L93: A/R | M93: =O185 -> 280 | N93: 0 | O93: =SUM(M93:N93) -> 280 | P93: =P185 -> 294 | Q93: =Q185 -> 308.7 | R93: =R185 -> 324.135 | S93: =S185 -> 340.34175 | T93: =T185 -> 357.35884 | W93: A/R | X93: =Z185 -> 280 | Y93: =Z274 -> 114.28571 | Z93: =SUM(X93:Y93) -> 394.28571 | AA93: =SUM(AA185,AA274) -> 415.14286 | AB93: =SUM(AB185,AB274) -> 437.11143 | AC93: =SUM(AC185,AC274) -> 460.25111 | AD93: =SUM(AD185,AD274) -> 484.62483 | AE93: =SUM(AE185,AE274) -> 510.2989
C94: Inventories | D94: =IF($I$27=$H$20,O94,Z94) -> 439.28571 | E94: =IF($I$27=$H$20,P94,AA94) -> 454.70893 | F94: =IF($I$27=$H$20,Q94,AB94) -> 470.54325 | G94: =IF($I$27=$H$20,R94,AC94) -> 486.78902 | H94: =IF($I$27=$H$20,S94,AD94) -> 503.44546 | I94: =IF($I$27=$H$20,T94,AE94) -> 520.51049 | L94: Inventories | M94: =O186 -> 315 | N94: 0 | O94: =SUM(M94:N94) -> 315 | P94: =P186 -> 325.2375 | Q94: =Q186 -> 335.71125 | R94: =R186 -> 346.41928 | S94: =S186 -> 357.35884 | T94: =T186 -> 368.5263 | W94: Inventories | X94: =Z186 -> 315 | Y94: =Z275 -> 124.28571 | Z94: =SUM(X94:Y94) -> 439.28571 | AA94: =SUM(AA186,AA275) -> 454.70893 | AB94: =SUM(AB186,AB275) -> 470.54325 | AC94: =SUM(AC186,AC275) -> 486.78902 | AD94: =SUM(AD186,AD275) -> 503.44546 | AE94: =SUM(AE186,AE275) -> 520.51049
C95: Other | D95: =IF($I$27=$H$20,O95,Z95) -> 123.21429 | E95: =IF($I$27=$H$20,P95,AA95) -> 129.73214 | F95: =IF($I$27=$H$20,Q95,AB95) -> 136.59732 | G95: =IF($I$27=$H$20,R95,AC95) -> 143.82847 | H95: =IF($I$27=$H$20,S95,AD95) -> 151.44526 | I95: =IF($I$27=$H$20,T95,AE95) -> 159.46841 | L95: Other | M95: =O187 -> 87.5 | N95: 0 | O95: =SUM(M95:N95) -> 87.5 | P95: =P187 -> 91.875 | Q95: =Q187 -> 96.46875 | R95: =R187 -> 101.29219 | S95: =S187 -> 106.3568 | T95: =T187 -> 111.67464 | W95: Other | X95: =Z187 -> 87.5 | Y95: =Z276 -> 35.714286 | Z95: =SUM(X95:Y95) -> 123.21429 | AA95: =SUM(AA187,AA276) -> 129.73214 | AB95: =SUM(AB187,AB276) -> 136.59732 | AC95: =SUM(AC187,AC276) -> 143.82847 | AD95: =SUM(AD187,AD276) -> 151.44526 | AE95: =SUM(AE187,AE276) -> 159.46841
C96: Total Current Assets | D96: =SUM(D92:D95) -> 2091.227 | E96: =SUM(E92:E95) -> 1856.5236 | F96: =SUM(F92:F95) -> 1723.8988 | G96: =SUM(G92:G95) -> 1699.4154 | H96: =SUM(H92:H95) -> 1789.5684 | I96: =SUM(I92:I95) -> 2001.3141 | L96: Total Current Assets | M96: =SUM(M92:M95) -> 5231.3483 | N96: =SUM(N92:N95) -> -4500 | O96: =SUM(O92:O95) -> 731.34827 | P96: =SUM(P92:P95) -> 573.3559 | Q96: =SUM(Q92:Q95) -> 490.12887 | R96: =SUM(R92:R95) -> 485.97561 | S96: =SUM(S92:S95) -> 565.50013 | T96: =SUM(T92:T95) -> 733.62129 | W96: Total Current Assets | X96: =SUM(X92:X95) -> 5231.3483 | Y96: =SUM(Y92:Y95) -> -3140.1212 | Z96: =SUM(Z92:Z95) -> 2091.227 | AA96: =SUM(AA92:AA95) -> 1856.5236 | AB96: =SUM(AB92:AB95) -> 1723.8988 | AC96: =SUM(AC92:AC95) -> 1699.4154 | AD96: =SUM(AD92:AD95) -> 1789.5684 | AE96: =SUM(AE92:AE95) -> 2001.3141
C98: Investment In Bravo | D98: =IF($I$27=$H$20,O98,Z98) -> 0 | E98: =IF($I$27=$H$20,P98,AA98) -> 0 | F98: =IF($I$27=$H$20,Q98,AB98) -> 0 | G98: =IF($I$27=$H$20,R98,AC98) -> 0 | H98: =IF($I$27=$H$20,S98,AD98) -> 0 | I98: =IF($I$27=$H$20,T98,AE98) -> 0 | L98: Investment In Bravo | M98: 0 | N98: =-N92 -> 4500 | O98: =SUM(M98:N98) -> 4500 | P98: =O98-P66-P64 -> 4642.1347 | Q98: =P98-Q66-Q64 -> 4812.7951 | R98: =Q98-R66-R64 -> 5013.8134 | S98: =R98-S66-S64 -> 5247.163 | T98: =S98-T66-T64 -> 5514.9694 | W98: Investment In Bravo | X98: 0 | Y98: 0 | Z98: =SUM(X98:Y98) -> 0 | AA98: =Z98 -> 0 | AB98: =AA98 -> 0 | AC98: =AB98 -> 0 | AD98: =AC98 -> 0 | AE98: =AD98 -> 0
C99: Goodwill | D99: =IF($I$27=$H$20,O99,Z99) -> 668.13552 | E99: =IF($I$27=$H$20,P99,AA99) -> 668.13552 | F99: =IF($I$27=$H$20,Q99,AB99) -> 668.13552 | G99: =IF($I$27=$H$20,R99,AC99) -> 668.13552 | H99: =IF($I$27=$H$20,S99,AD99) -> 668.13552 | I99: =IF($I$27=$H$20,T99,AE99) -> 668.13552 | L99: Goodwill | M99: 0 | N99: 0 | O99: =SUM(M99:N99) -> 0 | P99: 0 | Q99: 0 | R99: 0 | S99: 0 | T99: 0 | W99: Goodwill | X99: 0 | Y99: =Y25-Z300 -> 668.13552 | Z99: =SUM(X99:Y99) -> 668.13552 | AA99: =Z99 -> 668.13552 | AB99: =AA99 -> 668.13552 | AC99: =AB99 -> 668.13552 | AD99: =AC99 -> 668.13552 | AE99: =AD99 -> 668.13552
C100: Fixed Assets | D100: =IF($I$27=$H$20,O100,Z100) -> 14642.857 | E100: =IF($I$27=$H$20,P100,AA100) -> 14719.939 | F100: =IF($I$27=$H$20,Q100,AB100) -> 14801.095 | G100: =IF($I$27=$H$20,R100,AC100) -> 14886.541 | H100: =IF($I$27=$H$20,S100,AD100) -> 14976.507 | I100: =IF($I$27=$H$20,T100,AE100) -> 15071.232 | L100: Fixed Assets | M100: =O190 -> 10500 | N100: 0 | O100: =SUM(M100:N100) -> 10500 | P100: =P190 -> 10555.125 | Q100: =Q190 -> 10613.006 | R100: =R190 -> 10673.782 | S100: =S190 -> 10737.596 | T100: =T190 -> 10804.6 | W100: Fixed Assets | X100: =Z190 -> 10500 | Y100: =Z279 -> 4142.8571 | Z100: =SUM(X100:Y100) -> 14642.857 | AA100: =SUM(AA190,AA279) -> 14719.939 | AB100: =SUM(AB190,AB279) -> 14801.095 | AC100: =SUM(AC190,AC279) -> 14886.541 | AD100: =SUM(AD190,AD279) -> 14976.507 | AE100: =SUM(AE190,AE279) -> 15071.232
C101: Other | D101: =IF($I$27=$H$20,O101,Z101) -> 16 | E101: =IF($I$27=$H$20,P101,AA101) -> 16 | F101: =IF($I$27=$H$20,Q101,AB101) -> 16 | G101: =IF($I$27=$H$20,R101,AC101) -> 16 | H101: =IF($I$27=$H$20,S101,AD101) -> 16 | I101: =IF($I$27=$H$20,T101,AE101) -> 16 | L101: Other | M101: =O191 -> 4 | N101: 0 | O101: =SUM(M101:N101) -> 4 | P101: =P191 -> 4 | Q101: =Q191 -> 4 | R101: =R191 -> 4 | S101: =S191 -> 4 | T101: =T191 -> 4 | W101: Other | X101: =Z191 -> 4 | Y101: =Z280 -> 12 | Z101: =SUM(X101:Y101) -> 16 | AA101: =SUM(AA191,AA280) -> 16 | AB101: =SUM(AB191,AB280) -> 16 | AC101: =SUM(AC191,AC280) -> 16 | AD101: =SUM(AD191,AD280) -> 16 | AE101: =SUM(AE191,AE280) -> 16
C102: Total Long-Term Assets | D102: =SUM(D98:D101) -> 15326.993 | E102: =SUM(E98:E101) -> 15404.075 | F102: =SUM(F98:F101) -> 15485.231 | G102: =SUM(G98:G101) -> 15570.677 | H102: =SUM(H98:H101) -> 15660.642 | I102: =SUM(I98:I101) -> 15755.368 | L102: Total Long-Term Assets | M102: =SUM(M98:M101) -> 10504 | N102: =SUM(N98:N101) -> 4500 | O102: =SUM(O98:O101) -> 15004 | P102: =SUM(P98:P101) -> 15201.26 | Q102: =SUM(Q98:Q101) -> 15429.801 | R102: =SUM(R98:R101) -> 15691.595 | S102: =SUM(S98:S101) -> 15988.759 | T102: =SUM(T98:T101) -> 16323.57 | W102: Total Long-Term Assets | X102: =SUM(X98:X101) -> 10504 | Y102: =SUM(Y98:Y101) -> 4822.9927 | Z102: =SUM(Z98:Z101) -> 15326.993 | AA102: =SUM(AA98:AA101) -> 15404.075 | AB102: =SUM(AB98:AB101) -> 15485.231 | AC102: =SUM(AC98:AC101) -> 15570.677 | AD102: =SUM(AD98:AD101) -> 15660.642 | AE102: =SUM(AE98:AE101) -> 15755.368
C104: Total Assets | D104: =D96+D102 -> 17418.22 | E104: =E96+E102 -> 17260.598 | F104: =F96+F102 -> 17209.129 | G104: =G96+G102 -> 17270.092 | H104: =H96+H102 -> 17450.211 | I104: =I96+I102 -> 17756.682 | L104: Total Assets | M104: =M96+M102 -> 15735.348 | N104: =N96+N102 -> 0 | O104: =O96+O102 -> 15735.348 | P104: =P96+P102 -> 15774.616 | Q104: =Q96+Q102 -> 15919.93 | R104: =R96+R102 -> 16177.571 | S104: =S96+S102 -> 16554.259 | T104: =T96+T102 -> 17057.191 | W104: Total Assets | X104: =X96+X102 -> 15735.348 | Y104: =Y96+Y102 -> 1682.8714 | Z104: =Z96+Z102 -> 17418.22 | AA104: =AA96+AA102 -> 17260.598 | AB104: =AB96+AB102 -> 17209.129 | AC104: =AC96+AC102 -> 17270.092 | AD104: =AD96+AD102 -> 17450.211 | AE104: =AE96+AE102 -> 17756.682
C106: Liabilities | L106: Liabilities | W106: Liabilities
C107: A/P | D107: =IF($I$27=$H$20,O107,Z107) -> 263.57143 | E107: =IF($I$27=$H$20,P107,AA107) -> 272.82536 | F107: =IF($I$27=$H$20,Q107,AB107) -> 282.32595 | G107: =IF($I$27=$H$20,R107,AC107) -> 292.07341 | H107: =IF($I$27=$H$20,S107,AD107) -> 302.06727 | I107: =IF($I$27=$H$20,T107,AE107) -> 312.3063 | L107: A/P | M107: =O197 -> 189 | N107: 0 | O107: =SUM(M107:N107) -> 189 | P107: =P197 -> 195.1425 | Q107: =Q197 -> 201.42675 | R107: =R197 -> 207.85157 | S107: =S197 -> 214.4153 | T107: =T197 -> 221.11578 | W107: A/P | X107: =Z197 -> 189 | Y107: =Z286 -> 74.571429 | Z107: =SUM(X107:Y107) -> 263.57143 | AA107: =SUM(AA197,AA286) -> 272.82536 | AB107: =SUM(AB197,AB286) -> 282.32595 | AC107: =SUM(AC197,AC286) -> 292.07341 | AD107: =SUM(AD197,AD286) -> 302.06727 | AE107: =SUM(AE197,AE286) -> 312.3063
C108: Long-Term Debt Due within One Year | D108: =IF($I$27=$H$20,O108,Z108) -> 700 | E108: =IF($I$27=$H$20,P108,AA108) -> 700 | F108: =IF($I$27=$H$20,Q108,AB108) -> 700 | G108: =IF($I$27=$H$20,R108,AC108) -> 700 | H108: =IF($I$27=$H$20,S108,AD108) -> 700 | I108: =IF($I$27=$H$20,T108,AE108) -> 700 | L108: Long-Term Debt Due within One Year | M108: =O198 -> 500 | N108: 0 | O108: =SUM(M108:N108) -> 500 | P108: =P198 -> 500 | Q108: =Q198 -> 500 | R108: =R198 -> 500 | S108: =S198 -> 500 | T108: =T198 -> 500 | W108: Long-Term Debt Due within One Year | X108: =Z198 -> 500 | Y108: =Z287 -> 200 | Z108: =SUM(X108:Y108) -> 700 | AA108: =SUM(AA198,AA287) -> 700 | AB108: =SUM(AB198,AB287) -> 700 | AC108: =SUM(AC198,AC287) -> 700 | AD108: =SUM(AD198,AD287) -> 700 | AE108: =SUM(AE198,AE287) -> 700
C109: Other | D109: =IF($I$27=$H$20,O109,Z109) -> 6.6 | E109: =IF($I$27=$H$20,P109,AA109) -> 6.6 | F109: =IF($I$27=$H$20,Q109,AB109) -> 6.6 | G109: =IF($I$27=$H$20,R109,AC109) -> 6.6 | H109: =IF($I$27=$H$20,S109,AD109) -> 6.6 | I109: =IF($I$27=$H$20,T109,AE109) -> 6.6 | L109: Other | M109: =O199 -> 0.3 | N109: 0 | O109: =SUM(M109:N109) -> 0.3 | P109: =P199 -> 0.3 | Q109: =Q199 -> 0.3 | R109: =R199 -> 0.3 | S109: =S199 -> 0.3 | T109: =T199 -> 0.3 | W109: Other | X109: =Z199 -> 0.3 | Y109: =Z288 -> 6.3 | Z109: =SUM(X109:Y109) -> 6.6 | AA109: =SUM(AA199,AA288) -> 6.6 | AB109: =SUM(AB199,AB288) -> 6.6 | AC109: =SUM(AC199,AC288) -> 6.6 | AD109: =SUM(AD199,AD288) -> 6.6 | AE109: =SUM(AE199,AE288) -> 6.6
C110: Total Current Liabilities | D110: =SUM(D107:D109) -> 970.17143 | E110: =SUM(E107:E109) -> 979.42536 | F110: =SUM(F107:F109) -> 988.92595 | G110: =SUM(G107:G109) -> 998.67341 | H110: =SUM(H107:H109) -> 1008.6673 | I110: =SUM(I107:I109) -> 1018.9063 | L110: Total Current Liabilities | M110: =SUM(M107:M109) -> 689.3 | N110: =SUM(N107:N109) -> 0 | O110: =SUM(O107:O109) -> 689.3 | P110: =SUM(P107:P109) -> 695.4425 | Q110: =SUM(Q107:Q109) -> 701.72675 | R110: =SUM(R107:R109) -> 708.15157 | S110: =SUM(S107:S109) -> 714.7153 | T110: =SUM(T107:T109) -> 721.41578 | W110: Total Current Liabilities | X110: =SUM(X107:X109) -> 689.3 | Y110: =SUM(Y107:Y109) -> 280.87143 | Z110: =SUM(Z107:Z109) -> 970.17143 | AA110: =SUM(AA107:AA109) -> 979.42536 | AB110: =SUM(AB107:AB109) -> 988.92595 | AC110: =SUM(AC107:AC109) -> 998.67341 | AD110: =SUM(AD107:AD109) -> 1008.6673 | AE110: =SUM(AE107:AE109) -> 1018.9063
C112: Long-Term Debt | D112: =IF($I$27=$H$20,O112,Z112) -> 4900 | E112: =IF($I$27=$H$20,P112,AA112) -> 4200 | F112: =IF($I$27=$H$20,Q112,AB112) -> 3500 | G112: =IF($I$27=$H$20,R112,AC112) -> 2800 | H112: =IF($I$27=$H$20,S112,AD112) -> 2100 | I112: =IF($I$27=$H$20,T112,AE112) -> 1400 | L112: Long-Term Debt | M112: =O202 -> 3500 | N112: 0 | O112: =SUM(M112:N112) -> 3500 | P112: =P202 -> 3000 | Q112: =Q202 -> 2500 | R112: =R202 -> 2000 | S112: =S202 -> 1500 | T112: =T202 -> 1000 | W112: Long-Term Debt | X112: =Z202 -> 3500 | Y112: =Z291 -> 1400 | Z112: =SUM(X112:Y112) -> 4900 | AA112: =SUM(AA202,AA291) -> 4200 | AB112: =SUM(AB202,AB291) -> 3500 | AC112: =SUM(AC202,AC291) -> 2800 | AD112: =SUM(AD202,AD291) -> 2100 | AE112: =SUM(AE202,AE291) -> 1400
C113: Other | D113: =IF($I$27=$H$20,O113,Z113) -> 3.1 | E113: =IF($I$27=$H$20,P113,AA113) -> 3.1 | F113: =IF($I$27=$H$20,Q113,AB113) -> 3.1 | G113: =IF($I$27=$H$20,R113,AC113) -> 3.1 | H113: =IF($I$27=$H$20,S113,AD113) -> 3.1 | I113: =IF($I$27=$H$20,T113,AE113) -> 3.1 | L113: Other | M113: =O203 -> 1.1 | N113: 0 | O113: =SUM(M113:N113) -> 1.1 | P113: =P203 -> 1.1 | Q113: =Q203 -> 1.1 | R113: =R203 -> 1.1 | S113: =S203 -> 1.1 | T113: =T203 -> 1.1 | W113: Other | X113: =Z203 -> 1.1 | Y113: =Z292 -> 2 | Z113: =SUM(X113:Y113) -> 3.1 | AA113: =SUM(AA203,AA292) -> 3.1 | AB113: =SUM(AB203,AB292) -> 3.1 | AC113: =SUM(AC203,AC292) -> 3.1 | AD113: =SUM(AD203,AD292) -> 3.1 | AE113: =SUM(AE203,AE292) -> 3.1
C114: Total Long-term Liabilities | D114: =SUM(D112:D113) -> 4903.1 | E114: =SUM(E112:E113) -> 4203.1 | F114: =SUM(F112:F113) -> 3503.1 | G114: =SUM(G112:G113) -> 2803.1 | H114: =SUM(H112:H113) -> 2103.1 | I114: =SUM(I112:I113) -> 1403.1 | L114: Total Long-term Liabilities | M114: =SUM(M112:M113) -> 3501.1 | N114: =SUM(N112:N113) -> 0 | O114: =SUM(O112:O113) -> 3501.1 | P114: =SUM(P112:P113) -> 3001.1 | Q114: =SUM(Q112:Q113) -> 2501.1 | R114: =SUM(R112:R113) -> 2001.1 | S114: =SUM(S112:S113) -> 1501.1 | T114: =SUM(T112:T113) -> 1001.1 | W114: Total Long-term Liabilities | X114: =SUM(X112:X113) -> 3501.1 | Y114: =SUM(Y112:Y113) -> 1402 | Z114: =SUM(Z112:Z113) -> 4903.1 | AA114: =SUM(AA112:AA113) -> 4203.1 | AB114: =SUM(AB112:AB113) -> 3503.1 | AC114: =SUM(AC112:AC113) -> 2803.1 | AD114: =SUM(AD112:AD113) -> 2103.1 | AE114: =SUM(AE112:AE113) -> 1403.1
C116: Total Liabilities | D116: =D110+D114 -> 5873.2714 | E116: =E110+E114 -> 5182.5254 | F116: =F110+F114 -> 4492.026 | G116: =G110+G114 -> 3801.7734 | H116: =H110+H114 -> 3111.7673 | I116: =I110+I114 -> 2422.0063 | L116: Total Liabilities | M116: =M110+M114 -> 4190.4 | N116: =N110+N114 -> 0 | O116: =O110+O114 -> 4190.4 | P116: =P110+P114 -> 3696.5425 | Q116: =Q110+Q114 -> 3202.8267 | R116: =R110+R114 -> 2709.2516 | S116: =S110+S114 -> 2215.8153 | T116: =T110+T114 -> 1722.5158 | W116: Total Liabilities | X116: =X110+X114 -> 4190.4 | Y116: =Y110+Y114 -> 1682.8714 | Z116: =Z110+Z114 -> 5873.2714 | AA116: =AA110+AA114 -> 5182.5254 | AB116: =AB110+AB114 -> 4492.026 | AC116: =AC110+AC114 -> 3801.7734 | AD116: =AD110+AD114 -> 3111.7673 | AE116: =AE110+AE114 -> 2422.0063
C118: Shareholders' Equity | L118: Shareholders' Equity | W118: Shareholders' Equity
C119: Common Shares | D119: =IF($I$27=$H$20,O119,Z119) -> 3700 | E119: =IF($I$27=$H$20,P119,AA119) -> 3700 | F119: =IF($I$27=$H$20,Q119,AB119) -> 3700 | G119: =IF($I$27=$H$20,R119,AC119) -> 3700 | H119: =IF($I$27=$H$20,S119,AD119) -> 3700 | I119: =IF($I$27=$H$20,T119,AE119) -> 3700 | L119: Common Shares | M119: =O209 -> 3700 | N119: 0 | O119: =SUM(M119:N119) -> 3700 | P119: =P209 -> 3700 | Q119: =Q209 -> 3700 | R119: =R209 -> 3700 | S119: =S209 -> 3700 | T119: =T209 -> 3700 | W119: Common Shares | X119: =Z209 -> 3700 | Y119: 0 | Z119: =SUM(X119:Y119) -> 3700 | AA119: =AA209 -> 3700 | AB119: =AB209 -> 3700 | AC119: =AC209 -> 3700 | AD119: =AD209 -> 3700 | AE119: =AE209 -> 3700
C120: Retained Earnings | D120: =IF($I$27=$H$20,O120,Z120) -> 7844.9483 | E120: =IF($I$27=$H$20,P120,AA120) -> 8378.0731 | F120: =IF($I$27=$H$20,Q120,AB120) -> 9017.1035 | G120: =IF($I$27=$H$20,R120,AC120) -> 9768.319 | H120: =IF($I$27=$H$20,S120,AD120) -> 10638.443 | I120: =IF($I$27=$H$20,T120,AE120) -> 11634.675 | L120: Retained Earnings | M120: =O210 -> 7844.9483 | N120: 0 | O120: =SUM(M120:N120) -> 7844.9483 | P120: =+O120+P49+P76+P77 -> 8378.0731 | Q120: =+P120+Q49+Q76+Q77 -> 9017.1035 | R120: =+Q120+R49+R76+R77 -> 9768.319 | S120: =+R120+S49+S76+S77 -> 10638.443 | T120: =+S120+T49+T76+T77 -> 11634.675 | W120: Retained Earnings | X120: =Z210 -> 7844.9483 | Y120: 0 | Z120: =SUM(X120:Y120) -> 7844.9483 | AA120: =SUM(Z120,AA51,AA77) -> 8378.0731 | AB120: =SUM(AA120,AB51,AB77) -> 9017.1035 | AC120: =SUM(AB120,AC51,AC77) -> 9768.319 | AD120: =SUM(AC120,AD51,AD77) -> 10638.443 | AE120: =SUM(AD120,AE51,AE77) -> 11634.675
C121: Non-Controlling Interest | D121: =IF($I$27=$H$20,O121,Z121) -> 0 | E121: =IF($I$27=$H$20,P121,AA121) -> 0 | F121: =IF($I$27=$H$20,Q121,AB121) -> 0 | G121: =IF($I$27=$H$20,R121,AC121) -> 0 | H121: =IF($I$27=$H$20,S121,AD121) -> 0 | I121: =IF($I$27=$H$20,T121,AE121) -> 0 | L121: Non-Controlling Interest | M121: 0 | N121: 0 | O121: =SUM(M121:N121) -> 0 | P121: 0 | Q121: 0 | R121: 0 | S121: 0 | T121: 0 | W121: Non-Controlling Interest | X121: 0 | Y121: =(1-Y26)*Y25 -> 0 | Z121: =SUM(X121:Y121) -> 0 | AA121: =Z121+SUM(AA63,AA76) -> 0 | AB121: =AA121+SUM(AB63,AB76) -> 0 | AC121: =AB121+SUM(AC63,AC76) -> 0 | AD121: =AC121+SUM(AD63,AD76) -> 0 | AE121: =AD121+SUM(AE63,AE76) -> 0
C122: Total Shareholders' Equity | D122: =SUM(D119:D121) -> 11544.948 | E122: =SUM(E119:E121) -> 12078.073 | F122: =SUM(F119:F121) -> 12717.103 | G122: =SUM(G119:G121) -> 13468.319 | H122: =SUM(H119:H121) -> 14338.443 | I122: =SUM(I119:I121) -> 15334.675 | L122: Total Shareholders' Equity | M122: =SUM(M119:M121) -> 11544.948 | N122: =SUM(N119:N121) -> 0 | O122: =SUM(O119:O121) -> 11544.948 | P122: =SUM(P119:P121) -> 12078.073 | Q122: =SUM(Q119:Q121) -> 12717.103 | R122: =SUM(R119:R121) -> 13468.319 | S122: =SUM(S119:S121) -> 14338.443 | T122: =SUM(T119:T121) -> 15334.675 | W122: Total Shareholders' Equity | X122: =SUM(X119:X121) -> 11544.948 | Y122: =SUM(Y119:Y121) -> 0 | Z122: =SUM(Z119:Z121) -> 11544.948 | AA122: =SUM(AA119:AA121) -> 12078.073 | AB122: =SUM(AB119:AB121) -> 12717.103 | AC122: =SUM(AC119:AC121) -> 13468.319 | AD122: =SUM(AD119:AD121) -> 14338.443 | AE122: =SUM(AE119:AE121) -> 15334.675
C124: Total Liabilities & Shareholders' Equity | D124: =D116+D122 -> 17418.22 | E124: =E116+E122 -> 17260.598 | F124: =F116+F122 -> 17209.129 | G124: =G116+G122 -> 17270.092 | H124: =H116+H122 -> 17450.211 | I124: =I116+I122 -> 17756.682 | L124: Total Liabilities & Shareholders' Equity | M124: =M116+M122 -> 15735.348 | N124: =N116+N122 -> 0 | O124: =O116+O122 -> 15735.348 | P124: =P116+P122 -> 15774.616 | Q124: =Q116+Q122 -> 15919.93 | R124: =R116+R122 -> 16177.571 | S124: =S116+S122 -> 16554.259 | T124: =T116+T122 -> 17057.191 | W124: Total Liabilities & Shareholders' Equity | X124: =X116+X122 -> 15735.348 | Y124: =Y116+Y122 -> 1682.8714 | Z124: =Z116+Z122 -> 17418.22 | AA124: =AA116+AA122 -> 17260.598 | AB124: =AB116+AB122 -> 17209.129 | AC124: =AC116+AC122 -> 17270.092 | AD124: =AD116+AD122 -> 17450.211 | AE124: =AE116+AE122 -> 17756.682
C125: Check | D125: =D104-D124 -> 0 | E125: =E104-E124 -> 0 | F125: =F104-F124 -> 0 | G125: =G104-G124 -> 0 | H125: =H104-H124 -> 0 | I125: =I104-I124 -> 0 | L125: Check | M125: =M104-M124 -> 0 | N125: =N104-N124 -> 0 | O125: =O104-O124 -> 0 | P125: =P104-P124 -> 0 | Q125: =Q104-Q124 -> 0 | R125: =R104-R124 -> 0 | S125: =S104-S124 -> 0 | T125: =T104-T124 -> 0 | W125: Check | X125: =X104-X124 -> 0 | Y125: =Y104-Y124 -> 0 | Z125: =Z104-Z124 -> 0 | AA125: =AA104-AA124 -> 0 | AB125: =AB104-AB124 -> 0 | AC125: =AC104-AC124 -> 0 | AD125: =AD104-AD124 -> 0 | AE125: =AE104-AE124 -> 0
K129: Alpha Financial Statements (Prior to the Acquisition) | V129: Alpha Financial Statements (Prior to the Acquisition)
L132: Alpha Income Statement (Prior to the Acquisition) | W132: Alpha Income Statement (Prior to the Acquisition)
L133: (in USD$ millions, fiscal years ended December 31st) | W133: (in USD$ millions, fiscal years ended December 31st)
O135: 44561 | P135: =DATE(YEAR(O135)+1,MONTH(O135),DAY(O135)) -> 44926 | Q135: =DATE(YEAR(P135)+1,MONTH(P135),DAY(P135)) -> 45291 | R135: =DATE(YEAR(Q135)+1,MONTH(Q135),DAY(Q135)) -> 45657 | S135: =DATE(YEAR(R135)+1,MONTH(R135),DAY(R135)) -> 46022 | T135: =DATE(YEAR(S135)+1,MONTH(S135),DAY(S135)) -> 46387 | Z135: 44561 | AA135: =DATE(YEAR(Z135)+1,MONTH(Z135),DAY(Z135)) -> 44926 | AB135: =DATE(YEAR(AA135)+1,MONTH(AA135),DAY(AA135)) -> 45291 | AC135: =DATE(YEAR(AB135)+1,MONTH(AB135),DAY(AB135)) -> 45657 | AD135: =DATE(YEAR(AC135)+1,MONTH(AC135),DAY(AC135)) -> 46022 | AE135: =DATE(YEAR(AD135)+1,MONTH(AD135),DAY(AD135)) -> 46387
L137: Revenue | O137: 3500 | P137: 3675 | Q137: 3858.75 | R137: 4051.6875 | S137: 4254.2719 | T137: 4466.9855 | W137: Revenue | Z137: 3500 | AA137: 3675 | AB137: 3858.75 | AC137: 4051.6875 | AD137: 4254.2719 | AE137: 4466.9855
L138: Less: COGS | O138: -2100 | P138: -2168.25 | Q138: -2238.075 | R138: -2309.4619 | S138: -2382.3922 | T138: -2456.842 | W138: Less: COGS | Z138: -2100 | AA138: -2168.25 | AB138: -2238.075 | AC138: -2309.4619 | AD138: -2382.3922 | AE138: -2456.842
L139: Gross Profit | O139: =SUM(O137:O138) -> 1400 | P139: =SUM(P137:P138) -> 1506.75 | Q139: =SUM(Q137:Q138) -> 1620.675 | R139: =SUM(R137:R138) -> 1742.2256 | S139: =SUM(S137:S138) -> 1871.8796 | T139: =SUM(T137:T138) -> 2010.1435 | W139: Gross Profit | Z139: =SUM(Z137:Z138) -> 1400 | AA139: =SUM(AA137:AA138) -> 1506.75 | AB139: =SUM(AB137:AB138) -> 1620.675 | AC139: =SUM(AC137:AC138) -> 1742.2256 | AD139: =SUM(AD137:AD138) -> 1871.8796 | AE139: =SUM(AE137:AE138) -> 2010.1435
L140: Less: SG&A | O140: -175 | P140: -183.75 | Q140: -192.9375 | R140: -202.58438 | S140: -212.71359 | T140: -223.34927 | W140: Less: SG&A | Z140: -175 | AA140: -183.75 | AB140: -192.9375 | AC140: -202.58438 | AD140: -212.71359 | AE140: -223.34927
L141: EBITDA | O141: =SUM(O139:O140) -> 1225 | P141: =SUM(P139:P140) -> 1323 | Q141: =SUM(Q139:Q140) -> 1427.7375 | R141: =SUM(R139:R140) -> 1539.6413 | S141: =SUM(S139:S140) -> 1659.166 | T141: =SUM(T139:T140) -> 1786.7942 | W141: EBITDA | Z141: =SUM(Z139:Z140) -> 1225 | AA141: =SUM(AA139:AA140) -> 1323 | AB141: =SUM(AB139:AB140) -> 1427.7375 | AC141: =SUM(AC139:AC140) -> 1539.6413 | AD141: =SUM(AD139:AD140) -> 1659.166 | AE141: =SUM(AE139:AE140) -> 1786.7942
L142: Less: Depreciation | O142: -525 | P142: -551.25 | Q142: -578.8125 | R142: -607.75312 | S142: -638.14078 | T142: -670.04782 | W142: Less: Depreciation | Z142: -525 | AA142: -551.25 | AB142: -578.8125 | AC142: -607.75312 | AD142: -638.14078 | AE142: -670.04782
L143: EBIT | O143: =SUM(O141:O142) -> 700 | P143: =SUM(P141:P142) -> 771.75 | Q143: =SUM(Q141:Q142) -> 848.925 | R143: =SUM(R141:R142) -> 931.88813 | S143: =SUM(S141:S142) -> 1021.0253 | T143: =SUM(T141:T142) -> 1116.7464 | W143: EBIT | Z143: =SUM(Z141:Z142) -> 700 | AA143: =SUM(AA141:AA142) -> 771.75 | AB143: =SUM(AB141:AB142) -> 848.925 | AC143: =SUM(AC141:AC142) -> 931.88813 | AD143: =SUM(AD141:AD142) -> 1021.0253 | AE143: =SUM(AE141:AE142) -> 1116.7464
...
