Workbook
Name company: Acquisition!$F$270
Name methods: Acquisition!$F$278:$F$279
Name percentage: Acquisition!$F$8
Name Pro_Forma_FS: CaseSolution!$B$29:$I$123
Name selector: Acquisition!$F$9
Name topic: "CFM Topic: " & Acquisition!$F$271
Name value: Acquisition!$F$7

Sheet Acquisition
A1: {=company} -> WV Cars
A2: {=topic} -> CFM Topic: Subsidiaries
A3: ACQUSITION SCHEDULE | J3: =J$277 -> 45291 | K3: =K$277 -> 45657 | L3: =L$277 -> 46022 | M3: =M$277 -> 46387 | N3: =N$277 -> 46752
A5: Acquisition asssumptions
E7: =CaseData!B$3 -> Value of 100% of JP Motors Equity | F7: =CaseData!E$3 -> 6750 | G7: USD m
E8: =CaseData!B$4 -> Percentage of JP Motors' Equity Acquired by WW | F8: =CaseData!E$4 -> 0.6 | G8: =CaseData!D$4 -> %
E9: Method selector | F9: 2 | G9: <= select
A11: Acquisition schedule
B13: Income Statement
E15: Revenue | J15: {=_xlfn.LET( _xlpm.vw_data,_xlfn.ANCHORARRAY( $J$97), _xlpm.vw_rows,_xlfn.ANCHORARRAY( $E$97), _xlpm.vw, INDEX( _xlpm.vw_data, MATCH( $E15, _xlpm.vw_rows, 0 ), 0 ), _xlpm.jp_data,_xlfn.ANCHORARRAY( $J$183), _xlpm.jp_rows,_xlfn.ANCHORARRAY( $E$183), _xlpm.jp, INDEX( _xlpm.jp_data, MATCH( $E15, _xlpm.jp_rows, 0 ), 0 ), IF( selector = 1, _xlpm.vw, _xlpm.vw + _xlpm.jp ) )} -> 7783.9286 | K15: 8195.8393 | L15: 8629.7084 | M15: 9086.7156 | N15: 9568.1044
E16: Less: COGS | J16: {=_xlfn.LET( _xlpm.vw_data,_xlfn.ANCHORARRAY( $J$97), _xlpm.vw_rows,_xlfn.ANCHORARRAY( $E$97), _xlpm.vw, INDEX( _xlpm.vw_data, MATCH( $E16, _xlpm.vw_rows, 0 ), 0 ), _xlpm.jp_data,_xlfn.ANCHORARRAY( $J$183), _xlpm.jp_rows,_xlfn.ANCHORARRAY( $E$183), _xlpm.jp, INDEX( _xlpm.jp_data, MATCH( $E16, _xlpm.jp_rows, 0 ), 0 ), IF( selector = 1, _xlpm.vw, _xlpm.vw + _xlpm.jp ) )} -> -4547.0893 | K16: -4705.4325 | L16: -4867.8902 | M16: -5034.4546 | N16: -5205.1049
E17: Gross Profit | J17: =SUM(J15:J16) -> 3236.8393 | K17: =SUM(K15:K16) -> 3490.4068 | L17: =SUM(L15:L16) -> 3761.8182 | M17: =SUM(M15:M16) -> 4052.261 | N17: =SUM(N15:N16) -> 4362.9995
E18: Less: SG&A | J18: {=_xlfn.LET( _xlpm.vw_data,_xlfn.ANCHORARRAY( $J$97), _xlpm.vw_rows,_xlfn.ANCHORARRAY( $E$97), _xlpm.vw, INDEX( _xlpm.vw_data, MATCH( $E18, _xlpm.vw_rows, 0 ), 0 ), _xlpm.jp_data,_xlfn.ANCHORARRAY( $J$183), _xlpm.jp_rows,_xlfn.ANCHORARRAY( $E$183), _xlpm.jp, INDEX( _xlpm.jp_data, MATCH( $E18, _xlpm.jp_rows, 0 ), 0 ), IF( selector = 1, _xlpm.vw, _xlpm.vw + _xlpm.jp ) )} -> -366.48214 | K18: -385.71482 | L18: -405.96365 | M18: -427.2827 | N18: -449.72896
E19: EBITDA | J19: =SUM(J17:J18) -> 2870.3571 | K19: =SUM(K17:K18) -> 3104.692 | L19: =SUM(L17:L18) -> 3355.8545 | M19: =SUM(M17:M18) -> 3624.9783 | N19: =SUM(N17:N18) -> 3913.2706
E20: Less: Depreciation | J20: {=_xlfn.LET( _xlpm.vw_data,_xlfn.ANCHORARRAY( $J$97), _xlpm.vw_rows,_xlfn.ANCHORARRAY( $E$97), _xlpm.vw, INDEX( _xlpm.vw_data, MATCH( $E20, _xlpm.vw_rows, 0 ), 0 ), _xlpm.jp_data,_xlfn.ANCHORARRAY( $J$183), _xlpm.jp_rows,_xlfn.ANCHORARRAY( $E$183), _xlpm.jp, INDEX( _xlpm.jp_data, MATCH( $E20, _xlpm.jp_rows, 0 ), 0 ), IF( selector = 1, _xlpm.vw, _xlpm.vw + _xlpm.jp ) )} -> -1156.2321 | K20: -1217.3373 | L20: -1281.6954 | M20: -1349.4808 | N20: -1420.8775
E21: EBIT | J21: =SUM(J19:J20) -> 1714.125 | K21: =SUM(K19:K20) -> 1887.3546 | L21: =SUM(L19:L20) -> 2074.1591 | M21: =SUM(M19:M20) -> 2275.4975 | N21: =SUM(N19:N20) -> 2492.393
E22: Add/(Less): Net Interest Income/(Expense) | J22: {=_xlfn.LET( _xlpm.vw_data,_xlfn.ANCHORARRAY( $J$97), _xlpm.vw_rows,_xlfn.ANCHORARRAY( $E$97), _xlpm.vw, INDEX( _xlpm.vw_data, MATCH( $E22, _xlpm.vw_rows, 0 ), 0 ), _xlpm.jp_data,_xlfn.ANCHORARRAY( $J$183), _xlpm.jp_rows,_xlfn.ANCHORARRAY( $E$183), _xlpm.jp, INDEX( _xlpm.jp_data, MATCH( $E22, _xlpm.jp_rows, 0 ), 0 ), IF( selector = 1, _xlpm.vw, _xlpm.vw + _xlpm.jp ) )} -> -493.38575 | K22: -424.34394 | L22: -354.62275 | M22: -284.18182 | N22: -212.97791
E23: EBT | J23: =SUM(J21:J22) -> 1220.7392 | K23: =SUM(K21:K22) -> 1463.0107 | L23: =SUM(L21:L22) -> 1719.5364 | M23: =SUM(M21:M22) -> 1991.3157 | N23: =SUM(N21:N22) -> 2279.4151
E24: Less: Taxes | J24: {=_xlfn.LET( _xlpm.vw_data,_xlfn.ANCHORARRAY( $J$97), _xlpm.vw_rows,_xlfn.ANCHORARRAY( $E$97), _xlpm.vw, INDEX( _xlpm.vw_data, MATCH( $E24, _xlpm.vw_rows, 0 ), 0 ), _xlpm.jp_data,_xlfn.ANCHORARRAY( $J$183), _xlpm.jp_rows,_xlfn.ANCHORARRAY( $E$183), _xlpm.jp, INDEX( _xlpm.jp_data, MATCH( $E24, _xlpm.jp_rows, 0 ), 0 ), IF( selector = 1, _xlpm.vw, _xlpm.vw + _xlpm.jp ) )} -> -297.27379 | K24: -356.25395 | L24: -418.69569 | M24: -484.841 | N24: -554.94804
E25: Net Earnings before Non controlling Interest | J25: =SUM(J23:J24) -> 923.46546 | K25: =SUM(K23:K24) -> 1106.7568 | L25: =SUM(L23:L24) -> 1300.8407 | M25: =SUM(M23:M24) -> 1506.4747 | N25: =SUM(N23:N24) -> 1724.4671
E26: Less: Non-Controlling Interest | J26: {=_xlfn.LET( _xlpm.jp_net_income, INDEX( $J$198:$N$198, 1, 0 ), IF( selector = 1, _xlfn.SEQUENCE( 1, 5, 0, 0 ), - _xlpm.jp_net_income * ( 1 - percentage ) ) )} -> -121.82973 | K26: -146.28036 | L26: -172.30136 | M26: -200.01397 | N26: -229.54837
E27: Add: Investment Income | J27: {=_xlfn.LET( _xlpm.jp_net_income, INDEX( $J$220:$N$220, 1, 0 ), IF( selector = 1, - _xlpm.jp_net_income * percentage, _xlfn.SEQUENCE( 1, 5, 0, 0 ) ) )} -> 0 | K27: 0 | L27: 0 | M27: 0 | N27: 0
E28: Net Income | J28: =SUM(J25:J27) -> 801.63572 | K28: =SUM(K25:K27) -> 960.47639 | L28: =SUM(L25:L27) -> 1128.5393 | M28: =SUM(M25:M27) -> 1306.4607 | N28: =SUM(N25:N27) -> 1494.9187
B31: Cash Flow Statement
D33: Cash Flow from Operations
E34: Net Income | J34: {=INDEX( J28:N28, 1, 0 )} -> 801.63572 | K34: 960.47639 | L34: 1128.5393 | M34: 1306.4607 | N34: 1494.9187
E35: Add: Depreciation | J35: {=_xlfn.LET( _xlpm.vw_data,_xlfn.ANCHORARRAY( $J$97), _xlpm.vw_rows,_xlfn.ANCHORARRAY( $E$97), _xlpm.vw, INDEX( _xlpm.vw_data, MATCH( $E35, _xlpm.vw_rows, 0 ), 0 ), _xlpm.jp_data,_xlfn.ANCHORARRAY( $J$183), _xlpm.jp_rows,_xlfn.ANCHORARRAY( $E$183), _xlpm.jp, INDEX( _xlpm.jp_data, MATCH( $E35, _xlpm.jp_rows, 0 ), 0 ), IF( selector = 1, _xlpm.vw, _xlpm.vw + _xlpm.jp ) )} -> 1156.2321 | K35: 1217.3373 | L35: 1281.6954 | M35: 1349.4808 | N35: 1420.8775
E36: Add: Non-Controlling Interest | J36: {=-_xlfn.ANCHORARRAY( J26)} -> 121.82973 | K36: 146.28036 | L36: 172.30136 | M36: 200.01397 | N36: 229.54837
E37: Add/(Less): Change in W/C | J37: {=_xlfn.LET( _xlpm.vw_data,_xlfn.ANCHORARRAY( $J$97), _xlpm.vw_rows,_xlfn.ANCHORARRAY( $E$97), _xlpm.vw, INDEX( _xlpm.vw_data, MATCH( $E37, _xlpm.vw_rows, 0 ), 0 ), _xlpm.jp_data,_xlfn.ANCHORARRAY( $J$183), _xlpm.jp_rows,_xlfn.ANCHORARRAY( $E$183), _xlpm.jp, INDEX( _xlpm.jp_data, MATCH( $E37, _xlpm.jp_rows, 0 ), 0 ), IF( selector = 1, _xlpm.vw, _xlpm.vw + _xlpm.jp ) )} -> -50.316429 | K37: -52.751218 | L37: -55.303721 | M37: -57.979615 | N37: -60.784851
E38: Cash Flow from Operations | J38: =SUM(J34:J37) -> 2029.3812 | K38: =SUM(K34:K37) -> 2271.3429 | L38: =SUM(L34:L37) -> 2527.2323 | M38: =SUM(M34:M37) -> 2797.9759 | N38: =SUM(N34:N37) -> 3084.5598
D40: Cash Flow from Investing Activities
E41: Less: Capex | J41: {=_xlfn.LET( _xlpm.vw_data,_xlfn.ANCHORARRAY( $J$97), _xlpm.vw_rows,_xlfn.ANCHORARRAY( $E$97), _xlpm.vw, INDEX( _xlpm.vw_data, MATCH( $E41, _xlpm.vw_rows, 0 ), 0 ), _xlpm.jp_data,_xlfn.ANCHORARRAY( $J$183), _xlpm.jp_rows,_xlfn.ANCHORARRAY( $E$183), _xlpm.jp, INDEX( _xlpm.jp_data, MATCH( $E41, _xlpm.jp_rows, 0 ), 0 ), IF( selector = 1, _xlpm.vw, _xlpm.vw + _xlpm.jp ) )} -> -1271.8554 | K41: -1339.0711 | L41: -1409.8649 | M41: -1484.4289 | N41: -1562.9653
E42: Cash Flow from Investing Activities | J42: =SUM( J41) -> -1271.8554 | K42: =SUM( K41) -> -1339.0711 | L42: =SUM( L41) -> -1409.8649 | M42: =SUM( M41) -> -1484.4289 | N42: =SUM( N41) -> -1562.9653
D44: Cash Flow from Financing Activities
E45: Add/(Less): Issuance/(Repayment) of Debt | J45: {=_xlfn.LET( _xlpm.vw_data,_xlfn.ANCHORARRAY( $J$97), _xlpm.vw_rows,_xlfn.ANCHORARRAY( $E$97), _xlpm.vw, INDEX( _xlpm.vw_data, MATCH( $E45, _xlpm.vw_rows, 0 ), 0 ), _xlpm.jp_data,_xlfn.ANCHORARRAY( $J$183), _xlpm.jp_rows,_xlfn.ANCHORARRAY( $E$183), _xlpm.jp, INDEX( _xlpm.jp_data, MATCH( $E45, _xlpm.jp_rows, 0 ), 0 ), IF( selector = 1, _xlpm.vw, _xlpm.vw + _xlpm.jp ) )} -> -1050 | K45: -1050 | L45: -1050 | M45: -1050 | N45: -1050
E46: Add/(Less): Issuance/(Repayment) of Common Shares | J46: {=_xlfn.LET( _xlpm.vw_data,_xlfn.ANCHORARRAY( $J$97), _xlpm.vw_rows,_xlfn.ANCHORARRAY( $E$97), _xlpm.vw, INDEX( _xlpm.vw_data, MATCH( $E46, _xlpm.vw_rows, 0 ), 0 ), _xlpm.jp_data,_xlfn.ANCHORARRAY( $J$183), _xlpm.jp_rows,_xlfn.ANCHORARRAY( $E$183), _xlpm.jp, INDEX( _xlpm.jp_data, MATCH( $E46, _xlpm.jp_rows, 0 ), 0 ), IF( selector = 1, _xlpm.vw, _xlpm.vw + _xlpm.jp ) )} -> 0 | K46: 0 | L46: 0 | M46: 0 | N46: 0
E47: Less: Dividends Paid to Non-Controlling Interests | J47: {=_xlfn.LET( _xlpm.jp_net_income, INDEX( $J$220:$N$220, 1, 0 ), IF( selector = 1, _xlfn.SEQUENCE( 1, 5, 0, 0 ), _xlpm.jp_net_income * (1 - percentage ) ) )} -> -36.54892 | K47: -43.884109 | L47: -51.690408 | M47: -60.00419 | N47: -68.864512
E48: Less: Dividends | J48: {=_xlfn.LET( _xlpm.vw_data,_xlfn.ANCHORARRAY( $J$97), _xlpm.vw_rows,_xlfn.ANCHORARRAY( $E$97), _xlpm.vw, INDEX( _xlpm.vw_data, MATCH( $E48, _xlpm.vw_rows, 0 ), 0 ), _xlpm.jp_data,_xlfn.ANCHORARRAY( $J$183), _xlpm.jp_rows,_xlfn.ANCHORARRAY( $E$183), _xlpm.jp, INDEX( _xlpm.jp_data, MATCH( $E48, _xlpm.jp_rows, 0 ), 0 ), IF( selector = 1, _xlpm.vw, _xlpm.vw ) )} -> -123.77822 | K48: -148.21117 | L48: -174.01746 | M48: -201.28796 | N48: -230.11923
E49: Cash Flow from Financing Activities | J49: =SUM(J45:J48) -> -1210.3271 | K49: =SUM(K45:K48) -> -1242.0953 | L49: =SUM(L45:L48) -> -1275.7079 | M49: =SUM(M45:M48) -> -1311.2921 | N49: =SUM(N45:N48) -> -1348.9837
E51: Beginning Cash & Equivalents | J51: =I$53 -> 4401.662 | K51: =J$53 -> 3948.8607 | L51: =K$53 -> 3639.0372 | M51: =L$53 -> 3480.6967 | N51: =M$53 -> 3482.9516
E52: Change in Cash & Equivalents | J52: =SUM( J38, J42, J49 ) -> -452.80133 | K52: =SUM( K38, K42, K49 ) -> -309.82347 | L52: =SUM( L38, L42, L49 ) -> -158.34044 | M52: =SUM( M38, M42, M49 ) -> 2.254849 | N52: =SUM( N38, N42, N49 ) -> 172.61073
E53: Ending Cash & Equivalents | I53: =$H$59 -> 4401.662 | J53: =SUM(J51:J52) -> 3948.8607 | K53: =SUM(K51:K52) -> 3639.0372 | L53: =SUM(L51:L52) -> 3480.6967 | M53: =SUM(M51:M52) -> 3482.9516 | N53: =SUM(N51:N52) -> 3655.5623
B56: Balance sheet
F57: ="Consolidation method: " & IF( selector = 1, "Cost", "Consolidation" ) -> Consolidation method: Consolidation
D58: Assets | F58: Prior | G58: Adjustment | H58: =$F$276 -> 44926
E59: Cash and Equivalents | F59: {=INDEX( $E$149:$F$153, 0, 2 )} -> 6823.2724 | G59: =_xlfn.LET( _xlpm.jp_cash, $F$235, IF( selector = 1, value * percentage * - 1, _xlpm.jp_cash - ( value * percentage ) ) ) -> -2421.6104 | H59: =SUM(F59:G59) -> 4401.662 | J59: {=INDEX( J53:N53, 1, 0 )} -> 3948.8607 | K59: 3639.0372 | L59: 3480.6967 | M59: 3482.9516 | N59: 3655.5623
E60: A/R | F60: 420 | G60: =_xlfn.LET( _xlpm.jp, $F236, IF( selector = 1, 0, _xlpm.jp ) ) -> 171.42857 | H60: =SUM(F60:G60) -> 591.42857 | J60: {=_xlfn.LET( _xlpm.vw_data,_xlfn.ANCHORARRAY( $J$97), _xlpm.vw_rows,_xlfn.ANCHORARRAY( $E$97), _xlpm.vw, INDEX( _xlpm.vw_data, MATCH( $E60, _xlpm.vw_rows, 0 ), 0 ), _xlpm.jp_data,_xlfn.ANCHORARRAY( $J$183), _xlpm.jp_rows,_xlfn.ANCHORARRAY( $E$183), _xlpm.jp, INDEX( _xlpm.jp_data, MATCH( $E60, _xlpm.jp_rows, 0 ), 0 ), IF( selector = 1, _xlpm.vw, _xlpm.vw + _xlpm.jp ) )} -> 622.71429 | K60: 655.66714 | L60: 690.37667 | M60: 726.93725 | N60: 765.44836
E61: Inventories | F61: 472.5 | G61: =_xlfn.LET( _xlpm.jp, $F237, IF( selector = 1, 0, _xlpm.jp ) ) -> 186.42857 | H61: =SUM(F61:G61) -> 658.92857 | J61: {=_xlfn.LET( _xlpm.vw_data,_xlfn.ANCHORARRAY( $J$97), _xlpm.vw_rows,_xlfn.ANCHORARRAY( $E$97), _xlpm.vw, INDEX( _xlpm.vw_data, MATCH( $E61, _xlpm.vw_rows, 0 ), 0 ), _xlpm.jp_data,_xlfn.ANCHORARRAY( $J$183), _xlpm.jp_rows,_xlfn.ANCHORARRAY( $E$183), _xlpm.jp, INDEX( _xlpm.jp_data, MATCH( $E61, _xlpm.jp_rows, 0 ), 0 ), IF( selector = 1, _xlpm.vw, _xlpm.vw + _xlpm.jp ) )} -> 682.06339 | K61: 705.81488 | L61: 730.18354 | M61: 755.16819 | N61: 780.76574
E62: Other current assets | F62: 131.25 | G62: =_xlfn.LET( _xlpm.jp, $F238, IF( selector = 1, 0, _xlpm.jp ) ) -> 53.571429 | H62: =SUM(F62:G62) -> 184.82143 | J62: {=_xlfn.LET( _xlpm.vw_data,_xlfn.ANCHORARRAY( $J$97), _xlpm.vw_rows,_xlfn.ANCHORARRAY( $E$97), _xlpm.vw, INDEX( _xlpm.vw_data, MATCH( $E62, _xlpm.vw_rows, 0 ), 0 ), _xlpm.jp_data,_xlfn.ANCHORARRAY( $J$183), _xlpm.jp_rows,_xlfn.ANCHORARRAY( $E$183), _xlpm.jp, INDEX( _xlpm.jp_data, MATCH( $E62, _xlpm.jp_rows, 0 ), 0 ), IF( selector = 1, _xlpm.vw, _xlpm.vw + _xlpm.jp ) )} -> 194.59821 | K62: 204.89598 | L62: 215.74271 | M62: 227.16789 | N62: 239.20261
E63: Total Current Assets | F63: 7847.0224 | G63: =SUM(G59:G62) -> -2010.1819 | H63: =SUM(F63:G63) -> 5836.8406 | I63: =H63 -> 5836.8406 | J63: =SUM(J59:J62) -> 5448.2365 | K63: =SUM(K59:K62) -> 5205.4152 | L63: =SUM(L59:L62) -> 5116.9997 | M63: =SUM(M59:M62) -> 5192.2249 | N63: =SUM(N59:N62) -> 5440.979
E65: Investment in JP | F65: 0 | G65: =IF( selector = 1, value * percentage, 0 ) -> 0 | H65: =SUM(F65:G65) -> 0 | I65: =H65 -> 0 | J65: =IF( J$274 = 1, $H65, I65 ) -> 0 | K65: =IF( K$274 = 1, $H$65, J$65 ) -> 0 | L65: =IF( L$274 = 1, $H$65, K$65 ) -> 0 | M65: =IF( M$274 = 1, $H$65, L$65 ) -> 0 | N65: =IF( N$274 = 1, $H$65, M$65 ) -> 0
E66: Goodwill | F66: 0 | G66: =_xlfn.LET( _xlpm.jp, $F$262, IF( selector = 1, 0, value - _xlpm.jp ) ) -> 1002.2033 | H66: =SUM(F66:G66) -> 1002.2033 | I66: =H66 -> 1002.2033 | J66: =IF( J$274 = 1, $H66, I66 ) -> 1002.2033 | K66: =IF( K$274 = 1, $H$66, J$66 ) -> 1002.2033 | L66: =IF( L$274 = 1, $H$66, K$66 ) -> 1002.2033 | M66: =IF( M$274 = 1, $H$66, L$66 ) -> 1002.2033 | N66: =IF( N$274 = 1, $H$66, M$66 ) -> 1002.2033
E67: Fixed Assets | F67: {=INDEX( $E$155:$F$157, 0, 2 )} -> 15750 | G67: =_xlfn.LET( _xlpm.jp, $F241, IF( selector = 1, 0, _xlpm.jp ) ) -> 6214.2857 | H67: =SUM(F67:G67) -> 21964.286 | I67: =H67 -> 21964.286 | J67: {=_xlfn.LET( _xlpm.vw_data,_xlfn.ANCHORARRAY( $J$97), _xlpm.vw_rows,_xlfn.ANCHORARRAY( $E$97), _xlpm.vw, INDEX( _xlpm.vw_data, MATCH( $E67, _xlpm.vw_rows, 0 ), 0 ), _xlpm.jp_data,_xlfn.ANCHORARRAY( $J$183), _xlpm.jp_rows,_xlfn.ANCHORARRAY( $E$183), _xlpm.jp, INDEX( _xlpm.jp_data, MATCH( $E67, _xlpm.jp_rows, 0 ), 0 ), IF( selector = 1, _xlpm.vw, _xlpm.vw + _xlpm.jp ) )} -> 22079.909 | K67: 22201.643 | L67: 22329.812 | M67: 22464.76 | N67: 22606.848
E68: Other LT assets | F68: 6 | G68: =_xlfn.LET( _xlpm.jp, $F242, IF( selector = 1, 0, _xlpm.jp ) ) -> 18 | H68: =SUM(F68:G68) -> 24 | I68: =H68 -> 24 | J68: {=_xlfn.LET( _xlpm.vw_data,_xlfn.ANCHORARRAY( $J$97), _xlpm.vw_rows,_xlfn.ANCHORARRAY( $E$97), _xlpm.vw, INDEX( _xlpm.vw_data, MATCH( $E68, _xlpm.vw_rows, 0 ), 0 ), _xlpm.jp_data,_xlfn.ANCHORARRAY( $J$183), _xlpm.jp_rows,_xlfn.ANCHORARRAY( $E$183), _xlpm.jp, INDEX( _xlpm.jp_data, MATCH( $E68, _xlpm.jp_rows, 0 ), 0 ), IF( selector = 1, _xlpm.vw, _xlpm.vw + _xlpm.jp ) )} -> 24 | K68: 24 | L68: 24 | M68: 24 | N68: 24
E69: Total Long-Term Assets | F69: 15756 | G69: =SUM(G65:G68) -> 7234.489 | H69: =SUM(F69:G69) -> 22990.489 | I69: =H69 -> 22990.489 | J69: =SUM(J65:J68) -> 23106.112 | K69: =SUM(K65:K68) -> 23227.846 | L69: =SUM(L65:L68) -> 23356.015 | M69: =SUM(M65:M68) -> 23490.964 | N69: =SUM(N65:N68) -> 23633.051
E71: Total Assets | F71: =SUM( F63, F69) -> 23603.022 | G71: =SUM( G63, G69) -> 5224.3071 | H71: =SUM(F71:G71) -> 28827.33 | I71: =H71 -> 28827.33 | J71: =SUM( J63, J69) -> 28554.349 | K71: =SUM( K63, K69) -> 28433.261 | L71: =SUM( L63, L69) -> 28473.015 | M71: =SUM( M63, M69) -> 28683.188 | N71: =SUM( N63, N69) -> 29074.03
D73: Liabilities
E74: A/P | F74: {=INDEX( $E$162:$F$165, 0, 2 )} -> 283.5 | G74: =_xlfn.LET( _xlpm.jp, $F248, IF( selector = 1, 0, _xlpm.jp ) ) -> 111.85714 | H74: =SUM(F74:G74) -> 395.35714 | I74: =H74 -> 395.35714 | J74: {=_xlfn.LET( _xlpm.vw_data,_xlfn.ANCHORARRAY( $J$97), _xlpm.vw_rows,_xlfn.ANCHORARRAY( $E$97), _xlpm.vw, INDEX( _xlpm.vw_data, MATCH( $E74, _xlpm.vw_rows, 0 ), 0 ), _xlpm.jp_data,_xlfn.ANCHORARRAY( $J$183), _xlpm.jp_rows,_xlfn.ANCHORARRAY( $E$183), _xlpm.jp, INDEX( _xlpm.jp_data, MATCH( $E74, _xlpm.jp_rows, 0 ), 0 ), IF( selector = 1, _xlpm.vw, _xlpm.vw + _xlpm.jp ) )} -> 409.23804 | K74: 423.48892 | L74: 438.11012 | M74: 453.10091 | N74: 468.45944
E75: Long-Term Debt Due within One Year | F75: 750 | G75: =_xlfn.LET( _xlpm.jp, $F249, IF( selector = 1, 0, _xlpm.jp ) ) -> 300 | H75: =SUM(F75:G75) -> 1050 | I75: =H75 -> 1050 | J75: {=_xlfn.LET( _xlpm.vw_data,_xlfn.ANCHORARRAY( $J$97), _xlpm.vw_rows,_xlfn.ANCHORARRAY( $E$97), _xlpm.vw, INDEX( _xlpm.vw_data, MATCH( $E75, _xlpm.vw_rows, 0 ), 0 ), _xlpm.jp_data,_xlfn.ANCHORARRAY( $J$183), _xlpm.jp_rows,_xlfn.ANCHORARRAY( $E$183), _xlpm.jp, INDEX( _xlpm.jp_data, MATCH( $E75, _xlpm.jp_rows, 0 ), 0 ), IF( selector = 1, _xlpm.vw, _xlpm.vw + _xlpm.jp ) )} -> 1050 | K75: 1050 | L75: 1050 | M75: 1050 | N75: 1050
E76: Other current liabilities | F76: 0.45 | G76: =_xlfn.LET( _xlpm.jp, $F250, IF( selector = 1, 0, _xlpm.jp ) ) -> 9.45 | H76: =SUM(F76:G76) -> 9.9 | I76: =H76 -> 9.9 | J76: {=_xlfn.LET( _xlpm.vw_data,_xlfn.ANCHORARRAY( $J$97), _xlpm.vw_rows,_xlfn.ANCHORARRAY( $E$97), _xlpm.vw, INDEX( _xlpm.vw_data, MATCH( $E76, _xlpm.vw_rows, 0 ), 0 ), _xlpm.jp_data,_xlfn.ANCHORARRAY( $J$183), _xlpm.jp_rows,_xlfn.ANCHORARRAY( $E$183), _xlpm.jp, INDEX( _xlpm.jp_data, MATCH( $E76, _xlpm.jp_rows, 0 ), 0 ), IF( selector = 1, _xlpm.vw, _xlpm.vw + _xlpm.jp ) )} -> 9.9 | K76: 9.9 | L76: 9.9 | M76: 9.9 | N76: 9.9
E77: Total Current Liabilities | F77: 1033.95 | G77: =SUM(G74:G76) -> 421.30714 | H77: =SUM(F77:G77) -> 1455.2571 | I77: =H77 -> 1455.2571 | J77: =SUM(J74:J76) -> 1469.138 | K77: =SUM(K74:K76) -> 1483.3889 | L77: =SUM(L74:L76) -> 1498.0101 | M77: =SUM(M74:M76) -> 1513.0009 | N77: =SUM(N74:N76) -> 1528.3594
E79: Long-Term Debt | F79: {=INDEX( $E$167:$F$169, 0, 2 )} -> 5250 | G79: =_xlfn.LET( _xlpm.jp, $F253, IF( selector = 1, 0, _xlpm.jp ) ) -> 2100 | H79: =SUM(F79:G79) -> 7350 | I79: =H79 -> 7350 | J79: {=_xlfn.LET( _xlpm.vw_data,_xlfn.ANCHORARRAY( $J$97), _xlpm.vw_rows,_xlfn.ANCHORARRAY( $E$97), _xlpm.vw, INDEX( _xlpm.vw_data, MATCH( $E79, _xlpm.vw_rows, 0 ), 0 ), _xlpm.jp_data,_xlfn.ANCHORARRAY( $J$183), _xlpm.jp_rows,_xlfn.ANCHORARRAY( $E$183), _xlpm.jp, INDEX( _xlpm.jp_data, MATCH( $E79, _xlpm.jp_rows, 0 ), 0 ), IF( selector = 1, _xlpm.vw, _xlpm.vw + _xlpm.jp ) )} -> 6300 | K79: 5250 | L79: 4200 | M79: 3150 | N79: 2100
E80: Other LT liabilities | F80: 1.65 | G80: =_xlfn.LET( _xlpm.jp, $F254, IF( selector = 1, 0, _xlpm.jp ) ) -> 3 | H80: =SUM(F80:G80) -> 4.65 | I80: =H80 -> 4.65 | J80: {=_xlfn.LET( _xlpm.vw_data,_xlfn.ANCHORARRAY( $J$97), _xlpm.vw_rows,_xlfn.ANCHORARRAY( $E$97), _xlpm.vw, INDEX( _xlpm.vw_data, MATCH( $E80, _xlpm.vw_rows, 0 ), 0 ), _xlpm.jp_data,_xlfn.ANCHORARRAY( $J$183), _xlpm.jp_rows,_xlfn.ANCHORARRAY( $E$183), _xlpm.jp, INDEX( _xlpm.jp_data, MATCH( $E80, _xlpm.jp_rows, 0 ), 0 ), IF( selector = 1, _xlpm.vw, _xlpm.vw + _xlpm.jp ) )} -> 4.65 | K80: 4.65 | L80: 4.65 | M80: 4.65 | N80: 4.65
E81: Total Long-term Liabilities | F81: 5251.65 | G81: =SUM(G79:G80) -> 2103 | H81: =SUM(F81:G81) -> 7354.65 | I81: =H81 -> 7354.65 | J81: =SUM(J79:J80) -> 6304.65 | K81: =SUM(K79:K80) -> 5254.65 | L81: =SUM(L79:L80) -> 4204.65 | M81: =SUM(M79:M80) -> 3154.65 | N81: =SUM(N79:N80) -> 2104.65
E83: Total Liabilities | F83: =SUM( F77, F81) -> 6285.6 | G83: =SUM( G77, G81) -> 2524.3071 | H83: =SUM(F83:G83) -> 8809.9071 | I83: =H83 -> 8809.9071 | J83: =SUM( J77, J81) -> 7773.788 | K83: =SUM( K77, K81) -> 6738.0389 | L83: =SUM( L77, L81) -> 5702.6601 | M83: =SUM( M77, M81) -> 4667.6509 | N83: =SUM( N77, N81) -> 3633.0094
D85: Shareholders' Equity
E86: Common Shares | F86: {=INDEX( $E$174:$F$175, 0, 2 )} -> 5550 | G86: =IF( selector = 1, 0, 0 ) -> 0 | H86: =SUM(F86:G86) -> 5550 | I86: =H86 -> 5550 | J86: {=_xlfn.LET( _xlpm.vw_data,_xlfn.ANCHORARRAY( $J$97), _xlpm.vw_rows,_xlfn.ANCHORARRAY( $E$97), _xlpm.vw, INDEX( _xlpm.vw_data, MATCH( $E86, _xlpm.vw_rows, 0 ), 0 ), _xlpm.jp_data,_xlfn.ANCHORARRAY( $J$183), _xlpm.jp_rows,_xlfn.ANCHORARRAY( $E$183), _xlpm.jp, INDEX( _xlpm.jp_data, MATCH( $E86, _xlpm.jp_rows, 0 ), 0 ), IF( selector = 1, _xlpm.vw, _xlpm.vw ) )} -> 5550 | K86: 5550 | L86: 5550 | M86: 5550 | N86: 5550
E87: Retained Earnings | F87: 11767.422 | G87: =IF( selector = 1, 0, 0 ) -> 0 | H87: =SUM(F87:G87) -> 11767.422 | I87: =H87 -> 11767.422 | J87: =IF( J$274 = 1, $H87 + J28 + J48, I$87 + J28 + J48 ) -> 12445.28 | K87: =IF( K$274 = 1, $H87 + K28 + K48, J$87 + K28 + K48 ) -> 13257.545 | L87: =IF( L$274 = 1, $H87 + L28 + L48, K$87 + L28 + L48 ) -> 14212.067 | M87: =IF( M$274 = 1, $H87 + M28 + M48, L$87 + M28 + M48 ) -> 15317.24 | N87: =IF( N$274 = 1, $H87 + N28 + N48, M$87 + N28 + N48 ) -> 16582.039
E88: Non-Controlling Interest | F88: 0 | G88: =IF( selector = 1, 0, ( 1 - percentage ) * value) -> 2700 | H88: =SUM(F88:G88) -> 2700 | J88: =IF( J$274 = 1, $H88 + SUM( J$36, J$47 ), I$88 + SUM( J$36, J$47 ) ) -> 2785.2808 | K88: =IF( K$274 = 1, $H88 + SUM( K$36, K$47 ), J$88 + SUM( K$36, K$47 ) ) -> 2887.6771 | L88: =IF( L$274 = 1, $H88 + SUM( L$36, L$47 ), K$88 + SUM( L$36, L$47 ) ) -> 3008.288 | M88: =IF( M$274 = 1, $H88 + SUM( M$36, M$47 ), L$88 + SUM( M$36, M$47 ) ) -> 3148.2978 | N88: =IF( N$274 = 1, $H88 + SUM( N$36, N$47 ), M$88 + SUM( N$36, N$47 ) ) -> 3308.9817
E89: Total Shareholders' Equity | F89: =SUM(F86:F88) -> 17317.422 | G89: =SUM(G86:G88) -> 2700 | H89: =SUM(F89:G89) -> 20017.422 | J89: =SUM(J86:J88) -> 20780.561 | K89: =SUM(K86:K88) -> 21695.222 | L89: =SUM(L86:L88) -> 22770.355 | M89: =SUM(M86:M88) -> 24015.538 | N89: =SUM(N86:N88) -> 25441.021
E91: Total Liabilities & Shareholders' Equity | F91: =SUM( F83, F89) -> 23603.022 | G91: =SUM( G83, G89) -> 5224.3071 | H91: =SUM(F91:G91) -> 28827.33 | I91: =H91 -> 28827.33 | J91: =SUM( J83, J89) -> 28554.349 | K91: =SUM( K83, K89) -> 28433.261 | L91: =SUM( L83, L89) -> 28473.015 | M91: =SUM( M83, M89) -> 28683.188 | N91: =SUM( N83, N89) -> 29074.03
E92: Check | F92: =F71 - F91 -> 0 | G92: =G71 - G91 -> 0 | H92: =H71 - H91 -> 0 | J92: =J71 - J91 -> 0 | K92: =K71 - K91 -> 0 | L92: =L71 - L91 -> 0 | M92: =M71 - M91 -> 0 | N92: =N71 - N91 -> 0
A95: WW Financial Statements (Prior to the Acquisition)
E97: {=IF( INDEX( CaseData!$B$10:$B$92, 0, 1 ) = 0, "", INDEX( CaseData!$B$10:$B$92, 0, 1 ) )} -> Income statement | J97: {=_xlfn.IFNA( INDEX( CaseData!$C$10:$H$92, MATCH(_xlfn.ANCHORARRAY( Acquisition!E97), CaseData!$B$10:$B$92, 0 ), MATCH( Acquisition!$J$277:$N$277, CaseData!$C$13:$H$13, 0 ) ), "" )} -> 0 | K97: 0 | L97: 0 | M97: 0 | N97: 0
E98: (in USD$ millions, fiscal years ended December 31st) | J98: 0 | K98: 0 | L98: 0 | M98: 0 | N98: 0
E102: Revenue | J102: 5512.5 | K102: 5788.125 | L102: 6077.5312 | M102: 6381.4078 | N102: 6700.4782
E103: Less: COGS | J103: -3252.375 | K103: -3357.1125 | L103: -3464.1928 | M103: -3573.5884 | N103: -3685.263
E104: Gross Profit | J104: 2260.125 | K104: 2431.0125 | L104: 2613.3384 | M104: 2807.8194 | N104: 3015.2152
E105: Less: SG&A | J105: -275.625 | K105: -289.40625 | L105: -303.87656 | M105: -319.07039 | N105: -335.02391
E106: EBITDA | J106: 1984.5 | K106: 2141.6063 | L106: 2309.4619 | M106: 2488.749 | N106: 2680.1913
E107: Less: Depreciation | J107: -826.875 | K107: -868.21875 | L107: -911.62969 | M107: -957.21117 | N107: -1005.0717
E108: EBIT | J108: 1157.625 | K108: 1273.3875 | L108: 1397.8322 | M108: 1531.5379 | N108: 1675.1196
E109: Add/(Less): Net Interest Income/(Expense) | J109: -332.43684 | K109: -285.31304 | L109: -237.71581 | M109: -189.61817 | N109: -140.99136
E110: EBT | J110: 825.18816 | K110: 988.07446 | L110: 1160.1164 | M110: 1341.9197 | N110: 1534.1282
E111: Less: Taxes | J111: -206.29704 | K111: -247.01861 | L111: -290.02909 | M111: -335.47993 | N111: -383.53205
E112: Net Income | J112: 618.89112 | K112: 741.05584 | L112: 870.08728 | M112: 1006.4398 | N112: 1150.5961
... E144: (in USD$ millions, fiscal years ended December 31st) | J144: 0 | K144: 0 | L144: 0 | M144: 0 | N144: 0
F147: =$F$276 -> 44926
E148: Assets | F148: {=IF( _xlfn.XLOOKUP( $E$148:$E$179, CaseData!$B$61:$B$92, CaseData!$C$61:$C$92, "", 0 ) = 0, "", _xlfn.XLOOKUP( $E$148:$E$179, CaseData!$B$61:$B$92, CaseData!$C$61:$C$92, "", 0 ) )} | J148: 0 | K148: 0 | L148: 0 | M148: 0 | N148: 0
E149: Cash and Equivalents | F149: 6823.2724 | J149: 6451.9928 | K149: 6172.7907 | L149: 5990.8851 | M149: 5911.845 | N149: 5941.6119
E150: A/R | F150: 420 | J150: 441 | K150: 463.05 | L150: 486.2025 | M150: 510.51263 | N150: 536.03826
E151: Inventories | F151: 472.5 | J151: 487.85625 | K151: 503.56687 | L151: 519.62892 | M151: 536.03826 | N151: 552.78945
E152: Other current assets | F152: 131.25 | J152: 137.8125 | K152: 144.70312 | L152: 151.93828 | M152: 159.5352 | N152: 167.51196
E153: Total Current Assets | F153: 7847.0224 | J153: 7518.6616 | K153: 7284.1107 | L153: 7148.6548 | M153: 7117.9311 | N153: 7197.9516
E155: Fixed Assets | F155: 15750 | J155: 15832.688 | K155: 15919.509 | L155: 16010.672 | M155: 16106.393 | N155: 16206.901
E156: Other LT assets | F156: 6 | J156: 6 | K156: 6 | L156: 6 | M156: 6 | N156: 6
E157: Total Long-Term Assets | F157: 15756 | J157: 15838.688 | K157: 15925.509 | L157: 16016.672 | M157: 16112.393 | N157: 16212.901
E159: Total Assets | F159: 23603.022 | J159: 23357.349 | K159: 23209.62 | L159: 23165.327 | M159: 23230.325 | N159: 23410.852
E161: Liabilities | J161: 0 | K161: 0 | L161: 0 | M161: 0 | N161: 0
E162: A/P | F162: 283.5 | J162: 292.71375 | K162: 302.14012 | L162: 311.77735 | M162: 321.62295 | N162: 331.67367
...

Sheet CaseData
A1: Acquisition Assumptions
B3: Value of 100% of JP Motors Equity | D3: USD$ millions | E3: 6750
B4: Percentage of JP Motors' Equity Acquired by WW | D4: % | E4: 0.6
A7: WW Financial Statements (Prior to the Acquisition)
B10: Income statement
B11: (in USD$ millions, fiscal years ended December 31st)
C13: 44926 | D13: =EOMONTH( C$13, 12 ) -> 45291 | E13: =EOMONTH( D$13, 12 ) -> 45657 | F13: =EOMONTH( E$13, 12 ) -> 46022 | G13: =EOMONTH( F$13, 12 ) -> 46387 | H13: =EOMONTH( G$13, 12 ) -> 46752
B15: Revenue | C15: 5250 | D15: 5512.5 | E15: 5788.125 | F15: 6077.5312 | G15: 6381.4078 | H15: 6700.4782
B16: Less: COGS | C16: -3150 | D16: -3252.375 | E16: -3357.1125 | F16: -3464.1928 | G16: -3573.5884 | H16: -3685.263
B17: Gross Profit | C17: =SUM(C15:C16) -> 2100 | D17: =SUM(D15:D16) -> 2260.125 | E17: =SUM(E15:E16) -> 2431.0125 | F17: =SUM(F15:F16) -> 2613.3384 | G17: =SUM(G15:G16) -> 2807.8194 | H17: =SUM(H15:H16) -> 3015.2152
B18: Less: SG&A | C18: -262.5 | D18: -275.625 | E18: -289.40625 | F18: -303.87656 | G18: -319.07039 | H18: -335.02391
B19: EBITDA | C19: =SUM(C17:C18) -> 1837.5 | D19: =SUM(D17:D18) -> 1984.5 | E19: =SUM(E17:E18) -> 2141.6063 | F19: =SUM(F17:F18) -> 2309.4619 | G19: =SUM(G17:G18) -> 2488.749 | H19: =SUM(H17:H18) -> 2680.1913
B20: Less: Depreciation | C20: -787.5 | D20: -826.875 | E20: -868.21875 | F20: -911.62969 | G20: -957.21117 | H20: -1005.0717
B21: EBIT | C21: =SUM(C19:C20) -> 1050 | D21: =SUM(D19:D20) -> 1157.625 | E21: =SUM(E19:E20) -> 1273.3875 | F21: =SUM(F19:F20) -> 1397.8322 | G21: =SUM(G19:G20) -> 1531.5379 | H21: =SUM(H19:H20) -> 1675.1196
B22: Add/(Less): Net Interest Income/(Expense) | C22: -379.12932 | D22: -332.43684 | E22: -285.31304 | F22: -237.71581 | G22: -189.61817 | H22: -140.99136
B23: EBT | C23: =SUM(C21:C22) -> 670.87068 | D23: =SUM(D21:D22) -> 825.18816 | E23: =SUM(E21:E22) -> 988.07446 | F23: =SUM(F21:F22) -> 1160.1164 | G23: =SUM(G21:G22) -> 1341.9197 | H23: =SUM(H21:H22) -> 1534.1282
B24: Less: Taxes | C24: -167.71767 | D24: -206.29704 | E24: -247.01861 | F24: -290.02909 | G24: -335.47993 | H24: -383.53205
B25: Net Income | C25: =SUM(C23:C24) -> 503.15301 | D25: =SUM(D23:D24) -> 618.89112 | E25: =SUM(E23:E24) -> 741.05584 | F25: =SUM(F23:F24) -> 870.08728 | G25: =SUM(G23:G24) -> 1006.4398 | H25: =SUM(H23:H24) -> 1150.5961
B29: Cash Flow Statement
B30: (in USD$ millions, fiscal years ended December 31st)
C32: =C13 -> 44926 | D32: =D13 -> 45291 | E32: =E13 -> 45657 | F32: =F13 -> 46022 | G32: =G13 -> 46387 | H32: =H13 -> 46752
B34: Cash Flow from Operations
B35: Net Income | C35: =C25 -> 503.15301 | D35: =D25 -> 618.89112 | E35: =E25 -> 741.05584 | F35: =F25 -> 870.08728 | G35: =G25 -> 1006.4398 | H35: =H25 -> 1150.5961
B36: Add: Depreciation | C36: =-C20 -> 787.5 | D36: =-D20 -> 826.875 | E36: =-E20 -> 868.21875 | F36: =-F20 -> 911.62969 | G36: =-G20 -> 957.21117 | H36: =-H20 -> 1005.0717
B37: Add/(Less): Change in W/C | C37: -25.5 | D37: -33.705 | E37: -35.224875 | F37: -36.812475 | G37: -38.470773 | H37: -40.202869
B38: Cash Flow from Operations | C38: =SUM(C35:C37) -> 1265.153 | D38: =SUM(D35:D37) -> 1412.0611 | E38: =SUM(E35:E37) -> 1574.0497 | F38: =SUM(F35:F37) -> 1744.9045 | G38: =SUM(G35:G37) -> 1925.1802 | H38: =SUM(H35:H37) -> 2115.465
B40: Cash Flow from Investing Activities
B41: Less: Capex | C41: -866.25 | D41: -909.5625 | E41: -955.04063 | F41: -1002.7927 | G41: -1052.9323 | H41: -1105.5789
B42: Cash Flow from Investing Activities | C42: =SUM(C41:C41) -> -866.25 | D42: =SUM(D41:D41) -> -909.5625 | E42: =SUM(E41:E41) -> -955.04063 | F42: =SUM(F41:F41) -> -1002.7927 | G42: =SUM(G41:G41) -> -1052.9323 | H42: =SUM(H41:H41) -> -1105.5789
B44: Cash Flow from Financing Activities
B45: Add/(Less): Issuance/(Repayment) of Debt | C45: -750 | D45: -750 | E45: -750 | F45: -750 | G45: -750 | H45: -750
B46: Add/(Less): Issuance/(Repayment) of Common Shares | C46: 0 | D46: 0 | E46: 0 | F46: 0 | G46: 0 | H46: 0
B47: Less: Dividends | C47: -100.6306 | D47: -123.77822 | E47: -148.21117 | F47: -174.01746 | G47: -201.28796 | H47: -230.11923
B48: Cash Flow from Financing Activities | C48: =SUM(C45:C47) -> -850.6306 | D48: =SUM(D45:D47) -> -873.77822 | E48: =SUM(E45:E47) -> -898.21117 | F48: =SUM(F45:F47) -> -924.01746 | G48: =SUM(G45:G47) -> -951.28796 | H48: =SUM(H45:H47) -> -980.11923
B50: Beginning Cash & Equivalents | C50: 7275 | D50: =C52 -> 6823.2724 | E50: =D52 -> 6451.9928 | F50: =E52 -> 6172.7907 | G50: =F52 -> 5990.8851 | H50: =G52 -> 5911.845
B51: Change in Cash & Equivalents | C51: =C38+C42+C48 -> -451.72759 | D51: =D38+D42+D48 -> -371.2796 | E51: =E38+E42+E48 -> -279.20207 | F51: =F38+F42+F48 -> -181.90562 | G51: =G38+G42+G48 -> -79.04007 | H51: =H38+H42+H48 -> 29.766874
B52: Ending Cash & Equivalents | C52: =SUM(C50:C51) -> 6823.2724 | D52: =SUM(D50:D51) -> 6451.9928 | E52: =SUM(E50:E51) -> 6172.7907 | F52: =SUM(F50:F51) -> 5990.8851 | G52: =SUM(G50:G51) -> 5911.845 | H52: =SUM(H50:H51) -> 5941.6119
B56: Balance Sheet
B57: (in USD$ millions, fiscal years ended December 31st)
C59: =C32 -> 44926 | D59: =D32 -> 45291 | E59: =E32 -> 45657 | F59: =F32 -> 46022 | G59: =G32 -> 46387 | H59: =H32 -> 46752
B61: Assets
B62: Cash and Equivalents | C62: =C52 -> 6823.2724 | D62: =D52 -> 6451.9928 | E62: =E52 -> 6172.7907 | F62: =F52 -> 5990.8851 | G62: =G52 -> 5911.845 | H62: =H52 -> 5941.6119
B63: A/R | C63: 420 | D63: 441 | E63: 463.05 | F63: 486.2025 | G63: 510.51263 | H63: 536.03826
B64: Inventories | C64: 472.5 | D64: 487.85625 | E64: 503.56687 | F64: 519.62892 | G64: 536.03826 | H64: 552.78945
B65: Other current assets | C65: 131.25 | D65: 137.8125 | E65: 144.70312 | F65: 151.93828 | G65: 159.5352 | H65: 167.51196
B66: Total Current Assets | C66: =SUM(C62:C65) -> 7847.0224 | D66: =SUM(D62:D65) -> 7518.6616 | E66: =SUM(E62:E65) -> 7284.1107 | F66: =SUM(F62:F65) -> 7148.6548 | G66: =SUM(G62:G65) -> 7117.9311 | H66: =SUM(H62:H65) -> 7197.9516
B68: Fixed Assets | C68: 15750 | D68: 15832.688 | E68: 15919.509 | F68: 16010.672 | G68: 16106.393 | H68: 16206.901
B69: Other LT assets | C69: 6 | D69: 6 | E69: 6 | F69: 6 | G69: 6 | H69: 6
B70: Total Long-Term Assets | C70: =SUM(C68:C69) -> 15756 | D70: =SUM(D68:D69) -> 15838.688 | E70: =SUM(E68:E69) -> 15925.509 | F70: =SUM(F68:F69) -> 16016.672 | G70: =SUM(G68:G69) -> 16112.393 | H70: =SUM(H68:H69) -> 16212.901
B72: Total Assets | C72: =C66+C70 -> 23603.022 | D72: =D66+D70 -> 23357.349 | E72: =E66+E70 -> 23209.62 | F72: =F66+F70 -> 23165.327 | G72: =G66+G70 -> 23230.325 | H72: =H66+H70 -> 23410.852
B74: Liabilities
B75: A/P | C75: 283.5 | D75: 292.71375 | E75: 302.14012 | F75: 311.77735 | G75: 321.62295 | H75: 331.67367
B76: Long-Term Debt Due within One Year | C76: 750 | D76: 750 | E76: 750 | F76: 750 | G76: 750 | H76: 750
B77: Other current liabilities | C77: 0.45 | D77: 0.45 | E77: 0.45 | F77: 0.45 | G77: 0.45 | H77: 0.45
B78: Total Current Liabilities | C78: =SUM(C75:C77) -> 1033.95 | D78: =SUM(D75:D77) -> 1043.1637 | E78: =SUM(E75:E77) -> 1052.5901 | F78: =SUM(F75:F77) -> 1062.2274 | G78: =SUM(G75:G77) -> 1072.073 | H78: =SUM(H75:H77) -> 1082.1237
B80: Long-Term Debt | C80: 5250 | D80: 4500 | E80: 3750 | F80: 3000 | G80: 2250 | H80: 1500
B81: Other LT liabilities | C81: 1.65 | D81: 1.65 | E81: 1.65 | F81: 1.65 | G81: 1.65 | H81: 1.65
B82: Total Long-term Liabilities | C82: =SUM(C80:C81) -> 5251.65 | D82: =SUM(D80:D81) -> 4501.65 | E82: =SUM(E80:E81) -> 3751.65 | F82: =SUM(F80:F81) -> 3001.65 | G82: =SUM(G80:G81) -> 2251.65 | H82: =SUM(H80:H81) -> 1501.65
B84: Total Liabilities | C84: =C78+C82 -> 6285.6 | D84: =D78+D82 -> 5544.8137 | E84: =E78+E82 -> 4804.2401 | F84: =F78+F82 -> 4063.8774 | G84: =G78+G82 -> 3323.723 | H84: =H78+H82 -> 2583.7737
B86: Shareholders' Equity
B87: Common Shares | C87: 5550 | D87: 5550 | E87: 5550 | F87: 5550 | G87: 5550 | H87: 5550
B88: Retained Earnings | C88: 11767.422 | D88: 12262.535 | E88: 12855.38 | F88: 13551.45 | G88: 14356.602 | H88: 15277.079
B89: Total Shareholders' Equity | C89: =SUM(C87:C88) -> 17317.422 | D89: =SUM(D87:D88) -> 17812.535 | E89: =SUM(E87:E88) -> 18405.38 | F89: =SUM(F87:F88) -> 19101.45 | G89: =SUM(G87:G88) -> 19906.602 | H89: =SUM(H87:H88) -> 20827.079
B91: Total Liabilities & Shareholders' Equity | C91: =C84+C89 -> 23603.022 | D91: =D84+D89 -> 23357.349 | E91: =E84+E89 -> 23209.62 | F91: =F84+F89 -> 23165.327 | G91: =G84+G89 -> 23230.325 | H91: =H84+H89 -> 23410.852
B92: Check | C92: =C72-C91 -> 0 | D92: =D72-D91 -> 0 | E92: =E72-E91 -> 0 | F92: =F72-F91 -> 0 | G92: =G72-G91 -> 0 | H92: =H72-H91 -> 0
A96: JP Motors Financial Statements (Prior to the Acquisition)
B99: Income statement
B100: (in USD$ millions, fiscal years ended December 31st)
C102: =C59 -> 44926 | D102: =D59 -> 45291 | E102: =E59 -> 45657 | F102: =F59 -> 46022 | G102: =G59 -> 46387 | H102: =H59 -> 46752
B104: Revenue | C104: 2142.8571 | D104: 2271.4286 | E104: 2407.7143 | F104: 2552.1771 | G104: 2705.3078 | H104: 2867.6262
B105: Less: COGS | C105: -1242.8571 | D105: -1294.7143 | E105: -1348.32 | F105: -1403.6974 | G105: -1460.8662 | H105: -1519.8419
B106: Gross Profit | C106: =SUM(C104:C105) -> 900 | D106: =SUM(D104:D105) -> 976.71429 | E106: =SUM(E104:E105) -> 1059.3943 | F106: =SUM(F104:F105) -> 1148.4797 | G106: =SUM(G104:G105) -> 1244.4416 | H106: =SUM(H104:H105) -> 1347.7843
B107: Less: SG&A | C107: -85.714286 | D107: -90.857143 | E107: -96.308571 | F107: -102.08709 | G107: -108.21231 | H107: -114.70505
B108: EBITDA | C108: =SUM(C106:C107) -> 814.28571 | D108: =SUM(D106:D107) -> 885.85714 | E108: =SUM(E106:E107) -> 963.08571 | F108: =SUM(F106:F107) -> 1046.3926 | G108: =SUM(G106:G107) -> 1136.2293 | H108: =SUM(H106:H107) -> 1233.0793
B109: Less: Depreciation | C109: -310.71429 | D109: -329.35714 | E109: -349.11857 | F109: -370.06569 | G109: -392.26963 | H109: -415.8058
B110: EBIT | C110: =SUM(C108:C109) -> 503.57143 | D110: =SUM(D108:D109) -> 556.5 | E110: =SUM(E108:E109) -> 613.96714 | F110: =SUM(F108:F109) -> 676.32694 | G110: =SUM(G108:G109) -> 743.95964 | H110: =SUM(H108:H109) -> 817.27348
B111: Add/(Less): Net Interest Income/(Expense) | C111: -182.67903 | D111: -160.94891 | E111: -139.0309 | F111: -116.90694 | G111: -94.563646 | H111: -71.986557
B112: EBT | C112: =SUM(C110:C111) -> 320.8924 | D112: =SUM(D110:D111) -> 395.55109 | E112: =SUM(E110:E111) -> 474.93625 | F112: =SUM(F110:F111) -> 559.42 | G112: =SUM(G110:G111) -> 649.39599 | H112: =SUM(H110:H111) -> 745.28692
B113: Less: Taxes | C113: -73.805253 | D113: -90.97675 | E113: -109.23534 | F113: -128.6666 | G113: -149.36108 | H113: -171.41599
B114: Net Income | C114: =SUM(C112:C113) -> 247.08715 | D114: =SUM(D112:D113) -> 304.57434 | E114: =SUM(E112:E113) -> 365.70091 | F114: =SUM(F112:F113) -> 430.7534 | G114: =SUM(G112:G113) -> 500.03491 | H114: =SUM(H112:H113) -> 573.87093
B118: Cash Flow Statement
B119: (in USD$ millions, fiscal years ended December 31st)
C121: =C102 -> 44926 | D121: =D102 -> 45291 | E121: =E102 -> 45657 | F121: =F102 -> 46022 | G121: =G102 -> 46387 | H121: =H102 -> 46752
B123: Cash Flow from Operations
B124: Net Income | C124: =C114 -> 247.08715 | D124: =D114 -> 304.57434 | E124: =E114 -> 365.70091 | F124: =F114 -> 430.7534 | G124: =G114 -> 500.03491 | H124: =H114 -> 573.87093
B125: Add: Depreciation | C125: =-C109 -> 310.71429 | D125: =-D109 -> 329.35714 | E125: =-E109 -> 349.11857 | F125: =-F109 -> 370.06569 | G125: =-G109 -> 392.26963 | H125: =-H109 -> 415.8058
B126: Add/(Less): Change in W/C | C126: -13.5 | D126: -16.611429 | E126: -17.526343 | F126: -18.491246 | G126: -19.508842 | H126: -20.581982
B127: Cash Flow from Operations | C127: =SUM(C124:C126) -> 544.30144 | D127: =SUM(D124:D126) -> 617.32005 | E127: =SUM(E124:E126) -> 697.29314 | F127: =SUM(F124:F126) -> 782.32784 | G127: =SUM(G124:G126) -> 872.7957 | H127: =SUM(H124:H126) -> 969.09475
B129: Cash Flow from Investing Activities
B130: Less: Capex | C130: -341.78571 | D130: -362.29286 | E130: -384.03043 | F130: -407.07225 | G130: -431.49659 | H130: -457.38638
B131: Cash Flow from Investing Activities | C131: =SUM(C130:C130) -> -341.78571 | D131: =SUM(D130:D130) -> -362.29286 | E131: =SUM(E130:E130) -> -384.03043 | F131: =SUM(F130:F130) -> -407.07225 | G131: =SUM(G130:G130) -> -431.49659 | H131: =SUM(H130:H130) -> -457.38638
B133: Cash Flow from Financing Activities
B134: Add/(Less): Issuance/(Repayment) of Debt | C134: -300 | D134: -300 | E134: -300 | F134: -300 | G134: -300 | H134: -300
B135: Add/(Less): Issuance/(Repayment) of Common Shares | C135: 0 | D135: 0 | E135: 0 | F135: 0 | G135: 0 | H135: 0
B136: Less: Dividends | C136: -74.126145 | D136: -91.372301 | E136: -109.71027 | F136: -129.22602 | G136: -150.01047 | H136: -172.16128
B137: Cash Flow from Financing Activities | C137: =SUM(C134:C136) -> -374.12614 | D137: =SUM(D134:D136) -> -391.3723 | E137: =SUM(E134:E136) -> -409.71027 | F137: =SUM(F134:F136) -> -429.22602 | G137: =SUM(G134:G136) -> -450.01047 | H137: =SUM(H134:H136) -> -472.16128
B139: Beginning Cash & Equivalents | C139: 1800 | D139: =C141 -> 1628.3896 | E139: =D141 -> 1492.0445 | F139: =E141 -> 1395.5969 | G139: =F141 -> 1341.6265 | H139: =G141 -> 1332.9151
B140: Change in Cash & Equivalents | C140: =C127+C131+C137 -> -171.61042 | D140: =D127+D131+D137 -> -136.34511 | E140: =E127+E131+E137 -> -96.447563 | F140: =F127+F131+F137 -> -53.970434 | G140: =G127+G131+G137 -> -8.7113656 | H140: =H127+H131+H137 -> 39.547088
B141: Ending Cash & Equivalents | C141: =SUM(C139:C140) -> 1628.3896 | D141: =SUM(D139:D140) -> 1492.0445 | E141: =SUM(E139:E140) -> 1395.5969 | F141: =SUM(F139:F140) -> 1341.6265 | G141: =SUM(G139:G140) -> 1332.9151 | H141: =SUM(H139:H140) -> 1372.4622
B145: Balance Sheet
...

Sheet CaseSolution
B2: Pro Forma Financial Statements
C4: Pro Forma Financial Statements | D4: Click Here
B7: Summary Table of Answers
E9: % of JP Motors' Equity Acquired by WW
E10: 0.15 | F10: 0.6 | G10: 1
C11: 2026 Retained Earnings | D11: =$H$117 -> 15317.24 | E11: 14428.649 | F11: 15317.24 | G11: 15957.665
C12: 2024 Investment in JP Motors | D12: =$F$95 -> 0 | E12: 1012.5 | F12: 0 | G12: 0
C13: 2025 Non-Controlling Interests | D13: =$G$118 -> 3008.288 | E13: 0 | F13: 3008.288 | G13: 0
C14: 2027 EBITDA | D14: =$I$41 -> 3913.2706 | E14: 2680.1913 | F14: 3913.2706 | G14: 3913.2706
B18: ="LIVE: CURRENTLY RUNNING: "&UPPER(I27) -> LIVE: CURRENTLY RUNNING: CONSOLIDATION METHOD | K18: COST METHODOLOGY | V18: CONSOLIDATION METHODOLOGY
C20: If WW acquires <20% JP Motors' equity, the Cost Method is applied. | F20: 0.2 | H20: Cost Method | L20: =C20 -> If WW acquires <20% JP Motors' equity, the Cost Method is applied. | W20: =C21 -> If WW acquires >50% of JP Motors' equity, the Consolidation Method is applied.
C21: If WW acquires >50% of JP Motors' equity, the Consolidation Method is applied. | F21: 0.5 | H21: Consolidation Method
B23: Acquisition Assumptions | K23: Acquisition Assumptions | V23: Acquisition Assumptions
C25: Value of 100% of JP Motors' Equity | D25: USD$ millions | E25: =CaseData!E3 -> 6750 | G25: BS Check: | I25: =IF(AND(MAX(D122:I122)=0, MIN(D122:I122)=0), "Balanced", "Error") -> Balanced | L25: =$C$25 -> Value of 100% of JP Motors' Equity | M25: =$D$25 -> USD$ millions | N25: =$E25 -> 6750 | Q25: BS Check: | S25: =IF(AND(MAX(O122:T122)=0, MIN(O122:T122)=0), "Balanced", "Error") -> Balanced | W25: =$C$25 -> Value of 100% of JP Motors' Equity | X25: =$D$25 -> USD$ millions | Y25: =$E25 -> 6750 | AB25: BS Check: | AD25: =IF(AND(MAX(Z122:AE122)=0, MIN(Z122:AE122)=0), "Balanced", "Error") -> Balanced
C26: Percentage of JP Motors' Equity Acquired by WW | D26: % | E26: =CaseData!E4 -> 0.6 | L26: =$C$26 -> Percentage of JP Motors' Equity Acquired by WW | M26: =$D$26 -> % | N26: =$E26 -> 0.6 | W26: =$C$26 -> Percentage of JP Motors' Equity Acquired by WW | X26: =$D$26 -> % | Y26: =$E26 -> 0.6
G27: Running: | I27: =IF(E26<F20,H20,H21) -> Consolidation Method | Q27: Running: | S27: =H20 -> Cost Method | AB27: Running: | AD27: =H21 -> Consolidation Method
B29: ="WW Financial Statements (Pro-Forma under "&I27&")" -> WW Financial Statements (Pro-Forma under Consolidation Method) | K29: ="WW Financial Statements (Pro-Forma under "&S27&")" -> WW Financial Statements (Pro-Forma under Cost Method) | V29: ="WW Financial Statements (Pro-Forma under "&AD27&")" -> WW Financial Statements (Pro-Forma under Consolidation Method)
C32: ="WW Income Statement (Pro-Forma under "&I27&")" -> WW Income Statement (Pro-Forma under Consolidation Method) | L32: ="WW Income Statement (Pro-Forma under "&S27&")" -> WW Income Statement (Pro-Forma under Cost Method) | W32: ="WW Income Statement (Pro-Forma under "&AD27&")" -> WW Income Statement (Pro-Forma under Consolidation Method)
C33: (in USD$ millions, fiscal years ended December 31st) | L33: (in USD$ millions, fiscal years ended December 31st) | W33: (in USD$ millions, fiscal years ended December 31st)
D35: =O35 -> 44926 | E35: =P35 -> 45291 | F35: =Q35 -> 45657 | G35: =R35 -> 46022 | H35: =S35 -> 46387 | I35: =T35 -> 46752 | O35: =O132 -> 44926 | P35: =P132 -> 45291 | Q35: =Q132 -> 45657 | R35: =R132 -> 46022 | S35: =S132 -> 46387 | T35: =T132 -> 46752 | Z35: =Z132 -> 44926 | AA35: =AA132 -> 45291 | AB35: =AB132 -> 45657 | AC35: =AC132 -> 46022 | AD35: =AD132 -> 46387 | AE35: =AE132 -> 46752
C37: Revenue | E37: =IF($I$27=$H$20,P37,AA37) -> 7783.9286 | F37: =IF($I$27=$H$20,Q37,AB37) -> 8195.8393 | G37: =IF($I$27=$H$20,R37,AC37) -> 8629.7084 | H37: =IF($I$27=$H$20,S37,AD37) -> 9086.7156 | I37: =IF($I$27=$H$20,T37,AE37) -> 9568.1044 | L37: Revenue | P37: =P134 -> 5512.5 | Q37: =Q134 -> 5788.125 | R37: =R134 -> 6077.5312 | S37: =S134 -> 6381.4078 | T37: =T134 -> 6700.4782 | W37: Revenue | AA37: =SUM(AA134,AA223) -> 7783.9286 | AB37: =SUM(AB134,AB223) -> 8195.8393 | AC37: =SUM(AC134,AC223) -> 8629.7084 | AD37: =SUM(AD134,AD223) -> 9086.7156 | AE37: =SUM(AE134,AE223) -> 9568.1044
C38: Less: COGS | E38: =IF($I$27=$H$20,P38,AA38) -> -4547.0893 | F38: =IF($I$27=$H$20,Q38,AB38) -> -4705.4325 | G38: =IF($I$27=$H$20,R38,AC38) -> -4867.8902 | H38: =IF($I$27=$H$20,S38,AD38) -> -5034.4546 | I38: =IF($I$27=$H$20,T38,AE38) -> -5205.1049 | L38: Less: COGS | P38: =P135 -> -3252.375 | Q38: =Q135 -> -3357.1125 | R38: =R135 -> -3464.1928 | S38: =S135 -> -3573.5884 | T38: =T135 -> -3685.263 | W38: Less: COGS | AA38: =SUM(AA135,AA224) -> -4547.0893 | AB38: =SUM(AB135,AB224) -> -4705.4325 | AC38: =SUM(AC135,AC224) -> -4867.8902 | AD38: =SUM(AD135,AD224) -> -5034.4546 | AE38: =SUM(AE135,AE224) -> -5205.1049
C39: Gross Profit | E39: =SUM(E37:E38) -> 3236.8393 | F39: =SUM(F37:F38) -> 3490.4068 | G39: =SUM(G37:G38) -> 3761.8182 | H39: =SUM(H37:H38) -> 4052.261 | I39: =SUM(I37:I38) -> 4362.9995 | L39: Gross Profit | P39: =SUM(P37:P38) -> 2260.125 | Q39: =SUM(Q37:Q38) -> 2431.0125 | R39: =SUM(R37:R38) -> 2613.3384 | S39: =SUM(S37:S38) -> 2807.8194 | T39: =SUM(T37:T38) -> 3015.2152 | W39: Gross Profit | AA39: =SUM(AA37:AA38) -> 3236.8393 | AB39: =SUM(AB37:AB38) -> 3490.4068 | AC39: =SUM(AC37:AC38) -> 3761.8182 | AD39: =SUM(AD37:AD38) -> 4052.261 | AE39: =SUM(AE37:AE38) -> 4362.9995
C40: Less: SG&A | E40: =IF($I$27=$H$20,P40,AA40) -> -366.48214 | F40: =IF($I$27=$H$20,Q40,AB40) -> -385.71482 | G40: =IF($I$27=$H$20,R40,AC40) -> -405.96365 | H40: =IF($I$27=$H$20,S40,AD40) -> -427.2827 | I40: =IF($I$27=$H$20,T40,AE40) -> -449.72896 | L40: Less: SG&A | P40: =P137 -> -275.625 | Q40: =Q137 -> -289.40625 | R40: =R137 -> -303.87656 | S40: =S137 -> -319.07039 | T40: =T137 -> -335.02391 | W40: Less: SG&A | AA40: =SUM(AA137,AA226) -> -366.48214 | AB40: =SUM(AB137,AB226) -> -385.71482 | AC40: =SUM(AC137,AC226) -> -405.96365 | AD40: =SUM(AD137,AD226) -> -427.2827 | AE40: =SUM(AE137,AE226) -> -449.72896
C41: EBITDA | E41: =SUM(E39:E40) -> 2870.3571 | F41: =SUM(F39:F40) -> 3104.692 | G41: =SUM(G39:G40) -> 3355.8545 | H41: =SUM(H39:H40) -> 3624.9783 | I41: =SUM(I39:I40) -> 3913.2706 | L41: EBITDA | P41: =SUM(P39:P40) -> 1984.5 | Q41: =SUM(Q39:Q40) -> 2141.6063 | R41: =SUM(R39:R40) -> 2309.4619 | S41: =SUM(S39:S40) -> 2488.749 | T41: =SUM(T39:T40) -> 2680.1913 | W41: EBITDA | AA41: =SUM(AA39:AA40) -> 2870.3571 | AB41: =SUM(AB39:AB40) -> 3104.692 | AC41: =SUM(AC39:AC40) -> 3355.8545 | AD41: =SUM(AD39:AD40) -> 3624.9783 | AE41: =SUM(AE39:AE40) -> 3913.2706
C42: Less: Depreciation | E42: =IF($I$27=$H$20,P42,AA42) -> -1156.2321 | F42: =IF($I$27=$H$20,Q42,AB42) -> -1217.3373 | G42: =IF($I$27=$H$20,R42,AC42) -> -1281.6954 | H42: =IF($I$27=$H$20,S42,AD42) -> -1349.4808 | I42: =IF($I$27=$H$20,T42,AE42) -> -1420.8775 | L42: Less: Depreciation | P42: =P139 -> -826.875 | Q42: =Q139 -> -868.21875 | R42: =R139 -> -911.62969 | S42: =S139 -> -957.21117 | T42: =T139 -> -1005.0717 | W42: Less: Depreciation | AA42: =SUM(AA139,AA228) -> -1156.2321 | AB42: =SUM(AB139,AB228) -> -1217.3373 | AC42: =SUM(AC139,AC228) -> -1281.6954 | AD42: =SUM(AD139,AD228) -> -1349.4808 | AE42: =SUM(AE139,AE228) -> -1420.8775
C43: EBIT | E43: =SUM(E41:E42) -> 1714.125 | F43: =SUM(F41:F42) -> 1887.3546 | G43: =SUM(G41:G42) -> 2074.1591 | H43: =SUM(H41:H42) -> 2275.4975 | I43: =SUM(I41:I42) -> 2492.393 | L43: EBIT | P43: =SUM(P41:P42) -> 1157.625 | Q43: =SUM(Q41:Q42) -> 1273.3875 | R43: =SUM(R41:R42) -> 1397.8322 | S43: =SUM(S41:S42) -> 1531.5379 | T43: =SUM(T41:T42) -> 1675.1196 | W43: EBIT | AA43: =SUM(AA41:AA42) -> 1714.125 | AB43: =SUM(AB41:AB42) -> 1887.3546 | AC43: =SUM(AC41:AC42) -> 2074.1591 | AD43: =SUM(AD41:AD42) -> 2275.4975 | AE43: =SUM(AE41:AE42) -> 2492.393
C44: Add/(Less): Net Interest Income/(Expense) | E44: =IF($I$27=$H$20,P44,AA44) -> -493.38575 | F44: =IF($I$27=$H$20,Q44,AB44) -> -424.34394 | G44: =IF($I$27=$H$20,R44,AC44) -> -354.62275 | H44: =IF($I$27=$H$20,S44,AD44) -> -284.18182 | I44: =IF($I$27=$H$20,T44,AE44) -> -212.97791 | L44: Add/(Less): Net Interest Income/(Expense) | P44: =P141 -> -332.43684 | Q44: =Q141 -> -285.31304 | R44: =R141 -> -237.71581 | S44: =S141 -> -189.61817 | T44: =T141 -> -140.99136 | W44: Add/(Less): Net Interest Income/(Expense) | AA44: =SUM(AA141,AA230) -> -493.38575 | AB44: =SUM(AB141,AB230) -> -424.34394 | AC44: =SUM(AC141,AC230) -> -354.62275 | AD44: =SUM(AD141,AD230) -> -284.18182 | AE44: =SUM(AE141,AE230) -> -212.97791
C45: EBT | E45: =SUM(E43:E44) -> 1220.7392 | F45: =SUM(F43:F44) -> 1463.0107 | G45: =SUM(G43:G44) -> 1719.5364 | H45: =SUM(H43:H44) -> 1991.3157 | I45: =SUM(I43:I44) -> 2279.4151 | L45: EBT | P45: =SUM(P43:P44) -> 825.18816 | Q45: =SUM(Q43:Q44) -> 988.07446 | R45: =SUM(R43:R44) -> 1160.1164 | S45: =SUM(S43:S44) -> 1341.9197 | T45: =SUM(T43:T44) -> 1534.1282 | W45: EBT | AA45: =SUM(AA43:AA44) -> 1220.7392 | AB45: =SUM(AB43:AB44) -> 1463.0107 | AC45: =SUM(AC43:AC44) -> 1719.5364 | AD45: =SUM(AD43:AD44) -> 1991.3157 | AE45: =SUM(AE43:AE44) -> 2279.4151
C46: Less: Taxes | E46: =IF($I$27=$H$20,P46,AA46) -> -297.27379 | F46: =IF($I$27=$H$20,Q46,AB46) -> -356.25395 | G46: =IF($I$27=$H$20,R46,AC46) -> -418.69569 | H46: =IF($I$27=$H$20,S46,AD46) -> -484.841 | I46: =IF($I$27=$H$20,T46,AE46) -> -554.94804 | L46: Less: Taxes | P46: =P143 -> -206.29704 | Q46: =Q143 -> -247.01861 | R46: =R143 -> -290.02909 | S46: =S143 -> -335.47993 | T46: =T143 -> -383.53205 | W46: Less: Taxes | AA46: =SUM(AA143,AA232) -> -297.27379 | AB46: =SUM(AB143,AB232) -> -356.25395 | AC46: =SUM(AC143,AC232) -> -418.69569 | AD46: =SUM(AD143,AD232) -> -484.841 | AE46: =SUM(AE143,AE232) -> -554.94804
C47: Net Earnings before Noncontrolling Interest | E47: =SUM(E45:E46) -> 923.46546 | F47: =SUM(F45:F46) -> 1106.7568 | G47: =SUM(G45:G46) -> 1300.8407 | H47: =SUM(H45:H46) -> 1506.4747 | I47: =SUM(I45:I46) -> 1724.4671 | L47: Net Earnings before Noncontrolling Interest | P47: =SUM(P45:P46) -> 618.89112 | Q47: =SUM(Q45:Q46) -> 741.05584 | R47: =SUM(R45:R46) -> 870.08728 | S47: =SUM(S45:S46) -> 1006.4398 | T47: =SUM(T45:T46) -> 1150.5961 | W47: Net Earnings before Noncontrolling Interest | AA47: =SUM(AA45:AA46) -> 923.46546 | AB47: =SUM(AB45:AB46) -> 1106.7568 | AC47: =SUM(AC45:AC46) -> 1300.8407 | AD47: =SUM(AD45:AD46) -> 1506.4747 | AE47: =SUM(AE45:AE46) -> 1724.4671
C48: Less: Non-Controlling Interest | E48: =IF($I$27=$H$20,P48,AA48) -> -121.82973 | F48: =IF($I$27=$H$20,Q48,AB48) -> -146.28036 | G48: =IF($I$27=$H$20,R48,AC48) -> -172.30136 | H48: =IF($I$27=$H$20,S48,AD48) -> -200.01397 | I48: =IF($I$27=$H$20,T48,AE48) -> -229.54837 | L48: Less: Non-Controlling Interest | P48: 0 | Q48: 0 | R48: 0 | S48: 0 | T48: 0 | W48: Less: Non-Controlling Interest | AA48: =-AA233*(1-$Y$26) -> -121.82973 | AB48: =-AB233*(1-$Y$26) -> -146.28036 | AC48: =-AC233*(1-$Y$26) -> -172.30136 | AD48: =-AD233*(1-$Y$26) -> -200.01397 | AE48: =-AE233*(1-$Y$26) -> -229.54837
C49: Add: Investment Income | E49: =IF($I$27=$H$20,P49,AA49) -> 0 | F49: =IF($I$27=$H$20,Q49,AB49) -> 0 | G49: =IF($I$27=$H$20,R49,AC49) -> 0 | H49: =IF($I$27=$H$20,S49,AD49) -> 0 | I49: =IF($I$27=$H$20,T49,AE49) -> 0 | L49: Add: Investment Income | P49: =-P255*$N$26 -> 54.82338 | Q49: =-Q255*$N$26 -> 65.826164 | R49: =-R255*$N$26 -> 77.535612 | S49: =-S255*$N$26 -> 90.006284 | T49: =-T255*$N$26 -> 103.29677 | W49: Add: Investment Income | AA49: 0 | AB49: 0 | AC49: 0 | AD49: 0 | AE49: 0
C50: Net Income | E50: =SUM(E47:E49) -> 801.63572 | F50: =SUM(F47:F49) -> 960.47639 | G50: =SUM(G47:G49) -> 1128.5393 | H50: =SUM(H47:H49) -> 1306.4607 | I50: =SUM(I47:I49) -> 1494.9187 | L50: Net Income | P50: =SUM(P47:P49) -> 673.7145 | Q50: =SUM(Q47:Q49) -> 806.88201 | R50: =SUM(R47:R49) -> 947.6229 | S50: =SUM(S47:S49) -> 1096.4461 | T50: =SUM(T47:T49) -> 1253.8929 | W50: Net Income | AA50: =SUM(AA47:AA49) -> 801.63572 | AB50: =SUM(AB47:AB49) -> 960.47639 | AC50: =SUM(AC47:AC49) -> 1128.5393 | AD50: =SUM(AD47:AD49) -> 1306.4607 | AE50: =SUM(AE47:AE49) -> 1494.9187
C54: ="WW Cash Flow Statement (Pro-Forma under "&I27&")" -> WW Cash Flow Statement (Pro-Forma under Consolidation Method) | L54: ="WW Cash Flow Statement (Pro-Forma under "&S27&")" -> WW Cash Flow Statement (Pro-Forma under Cost Method) | W54: ="WW Cash Flow Statement (Pro-Forma under "&AD27&")" -> WW Cash Flow Statement (Pro-Forma under Consolidation Method)
C55: (in USD$ millions, fiscal years ended December 31st) | L55: (in USD$ millions, fiscal years ended December 31st) | W55: (in USD$ millions, fiscal years ended December 31st)
D57: =D35 -> 44926 | E57: =E35 -> 45291 | F57: =F35 -> 45657 | G57: =G35 -> 46022 | H57: =H35 -> 46387 | I57: =I35 -> 46752 | O57: =O35 -> 44926 | P57: =P35 -> 45291 | Q57: =Q35 -> 45657 | R57: =R35 -> 46022 | S57: =S35 -> 46387 | T57: =T35 -> 46752 | Z57: =Z35 -> 44926 | AA57: =AA35 -> 45291 | AB57: =AB35 -> 45657 | AC57: =AC35 -> 46022 | AD57: =AD35 -> 46387 | AE57: =AE35 -> 46752
C59: Cash Flow from Operations | L59: Cash Flow from Operations | W59: Cash Flow from Operations
C60: Net Income | E60: =IF($I$27=$H$20,P60,AA60) -> 801.63572 | F60: =IF($I$27=$H$20,Q60,AB60) -> 960.47639 | G60: =IF($I$27=$H$20,R60,AC60) -> 1128.5393 | H60: =IF($I$27=$H$20,S60,AD60) -> 1306.4607 | I60: =IF($I$27=$H$20,T60,AE60) -> 1494.9187 | L60: Net Income | P60: =P50 -> 673.7145 | Q60: =Q50 -> 806.88201 | R60: =R50 -> 947.6229 | S60: =S50 -> 1096.4461 | T60: =T50 -> 1253.8929 | W60: Net Income | AA60: =AA50 -> 801.63572 | AB60: =AB50 -> 960.47639 | AC60: =AC50 -> 1128.5393 | AD60: =AD50 -> 1306.4607 | AE60: =AE50 -> 1494.9187
C61: Add: Depreciation | E61: =IF($I$27=$H$20,P61,AA61) -> 1156.2321 | F61: =IF($I$27=$H$20,Q61,AB61) -> 1217.3373 | G61: =IF($I$27=$H$20,R61,AC61) -> 1281.6954 | H61: =IF($I$27=$H$20,S61,AD61) -> 1349.4808 | I61: =IF($I$27=$H$20,T61,AE61) -> 1420.8775 | L61: Add: Depreciation | P61: =-P42 -> 826.875 | Q61: =-Q42 -> 868.21875 | R61: =-R42 -> 911.62969 | S61: =-S42 -> 957.21117 | T61: =-T42 -> 1005.0717 | W61: Add: Depreciation | AA61: =-AA42 -> 1156.2321 | AB61: =-AB42 -> 1217.3373 | AC61: =-AC42 -> 1281.6954 | AD61: =-AD42 -> 1349.4808 | AE61: =-AE42 -> 1420.8775
C62: Add: Non-Controlling Interest | E62: =IF($I$27=$H$20,P62,AA62) -> 121.82973 | F62: =IF($I$27=$H$20,Q62,AB62) -> 146.28036 | G62: =IF($I$27=$H$20,R62,AC62) -> 172.30136 | H62: =IF($I$27=$H$20,S62,AD62) -> 200.01397 | I62: =IF($I$27=$H$20,T62,AE62) -> 229.54837 | L62: Add: Non-Controlling Interest | P62: =P48 -> 0 | Q62: =Q48 -> 0 | R62: =R48 -> 0 | S62: =S48 -> 0 | T62: =T48 -> 0 | W62: Add: Non-Controlling Interest | AA62: =-AA48 -> 121.82973 | AB62: =-AB48 -> 146.28036 | AC62: =-AC48 -> 172.30136 | AD62: =-AD48 -> 200.01397 | AE62: =-AE48 -> 229.54837
C63: Add/(Less): Change in W/C | E63: =IF($I$27=$H$20,P63,AA63) -> -50.316429 | F63: =IF($I$27=$H$20,Q63,AB63) -> -52.751218 | G63: =IF($I$27=$H$20,R63,AC63) -> -55.303721 | H63: =IF($I$27=$H$20,S63,AD63) -> -57.979615 | I63: =IF($I$27=$H$20,T63,AE63) -> -60.784851 | L63: Add/(Less): Change in W/C | P63: =P156 -> -33.705 | Q63: =Q156 -> -35.224875 | R63: =R156 -> -36.812475 | S63: =S156 -> -38.470773 | T63: =T156 -> -40.202869 | W63: Add/(Less): Change in W/C | AA63: =SUM(AA156,AA245) -> -50.316429 | AB63: =SUM(AB156,AB245) -> -52.751218 | AC63: =SUM(AC156,AC245) -> -55.303721 | AD63: =SUM(AD156,AD245) -> -57.979615 | AE63: =SUM(AE156,AE245) -> -60.784851
C64: Cash Flow from Operations | E64: =SUM(E60:E63) -> 2029.3812 | F64: =SUM(F60:F63) -> 2271.3429 | G64: =SUM(G60:G63) -> 2527.2323 | H64: =SUM(H60:H63) -> 2797.9759 | I64: =SUM(I60:I63) -> 3084.5598 | L64: Cash Flow from Operations | P64: =SUM(P60:P63) -> 1466.8845 | Q64: =SUM(Q60:Q63) -> 1639.8759 | R64: =SUM(R60:R63) -> 1822.4401 | S64: =SUM(S60:S63) -> 2015.1865 | T64: =SUM(T60:T63) -> 2218.7618 | W64: Cash Flow from Operations | AA64: =SUM(AA60:AA63) -> 2029.3812 | AB64: =SUM(AB60:AB63) -> 2271.3429 | AC64: =SUM(AC60:AC63) -> 2527.2323 | AD64: =SUM(AD60:AD63) -> 2797.9759 | AE64: =SUM(AE60:AE63) -> 3084.5598
C66: Cash Flow from Investing Activities | L66: Cash Flow from Investing Activities | W66: Cash Flow from Investing Activities
C67: Less: Capex | E67: =IF($I$27=$H$20,P67,AA67) -> -1271.8554 | F67: =IF($I$27=$H$20,Q67,AB67) -> -1339.0711 | G67: =IF($I$27=$H$20,R67,AC67) -> -1409.8649 | H67: =IF($I$27=$H$20,S67,AD67) -> -1484.4289 | I67: =IF($I$27=$H$20,T67,AE67) -> -1562.9653 | L67: Less: Capex | P67: =P160 -> -909.5625 | Q67: =Q160 -> -955.04063 | R67: =R160 -> -1002.7927 | S67: =S160 -> -1052.9323 | T67: =T160 -> -1105.5789 | W67: Less: Capex | AA67: =SUM(AA160,AA249) -> -1271.8554 | AB67: =SUM(AB160,AB249) -> -1339.0711 | AC67: =SUM(AC160,AC249) -> -1409.8649 | AD67: =SUM(AD160,AD249) -> -1484.4289 | AE67: =SUM(AE160,AE249) -> -1562.9653
C68: Cash Flow from Investing Activities | E68: =SUM(E67:E67) -> -1271.8554 | F68: =SUM(F67:F67) -> -1339.0711 | G68: =SUM(G67:G67) -> -1409.8649 | H68: =SUM(H67:H67) -> -1484.4289 | I68: =SUM(I67:I67) -> -1562.9653 | L68: Cash Flow from Investing Activities | P68: =SUM(P67:P67) -> -909.5625 | Q68: =SUM(Q67:Q67) -> -955.04063 | R68: =SUM(R67:R67) -> -1002.7927 | S68: =SUM(S67:S67) -> -1052.9323 | T68: =SUM(T67:T67) -> -1105.5789 | W68: Cash Flow from Investing Activities | AA68: =SUM(AA67:AA67) -> -1271.8554 | AB68: =SUM(AB67:AB67) -> -1339.0711 | AC68: =SUM(AC67:AC67) -> -1409.8649 | AD68: =SUM(AD67:AD67) -> -1484.4289 | AE68: =SUM(AE67:AE67) -> -1562.9653
C70: Cash Flow from Financing Activities | L70: Cash Flow from Financing Activities | W70: Cash Flow from Financing Activities
C71: Add/(Less): Issuance/(Repayment) of Debt | E71: =IF($I$27=$H$20,P71,AA71) -> -1050 | F71: =IF($I$27=$H$20,Q71,AB71) -> -1050 | G71: =IF($I$27=$H$20,R71,AC71) -> -1050 | H71: =IF($I$27=$H$20,S71,AD71) -> -1050 | I71: =IF($I$27=$H$20,T71,AE71) -> -1050 | L71: Add/(Less): Issuance/(Repayment) of Debt | P71: =P164 -> -750 | Q71: =Q164 -> -750 | R71: =R164 -> -750 | S71: =S164 -> -750 | T71: =T164 -> -750 | W71: Add/(Less): Issuance/(Repayment) of Debt | AA71: =SUM(AA164,AA253) -> -1050 | AB71: =SUM(AB164,AB253) -> -1050 | AC71: =SUM(AC164,AC253) -> -1050 | AD71: =SUM(AD164,AD253) -> -1050 | AE71: =SUM(AE164,AE253) -> -1050
C72: Add/(Less): Issuance/(Repayment) of Common Shares | E72: =IF($I$27=$H$20,P72,AA72) -> 0 | F72: =IF($I$27=$H$20,Q72,AB72) -> 0 | G72: =IF($I$27=$H$20,R72,AC72) -> 0 | H72: =IF($I$27=$H$20,S72,AD72) -> 0 | I72: =IF($I$27=$H$20,T72,AE72) -> 0 | L72: Add/(Less): Issuance/(Repayment) of Common Shares | P72: =P165 -> 0 | Q72: =Q165 -> 0 | R72: =R165 -> 0 | S72: =S165 -> 0 | T72: =T165 -> 0 | W72: Add/(Less): Issuance/(Repayment) of Common Shares | AA72: =SUM(AA165,AA254) -> 0 | AB72: =SUM(AB165,AB254) -> 0 | AC72: =SUM(AC165,AC254) -> 0 | AD72: =SUM(AD165,AD254) -> 0 | AE72: =SUM(AE165,AE254) -> 0
C73: Less: Dividends Paid to Non-Controlling Interests | E73: =IF($I$27=$H$20,P73,AA73) -> -36.54892 | F73: =IF($I$27=$H$20,Q73,AB73) -> -43.884109 | G73: =IF($I$27=$H$20,R73,AC73) -> -51.690408 | H73: =IF($I$27=$H$20,S73,AD73) -> -60.00419 | I73: =IF($I$27=$H$20,T73,AE73) -> -68.864512 | L73: Less: Dividends Paid to Non-Controlling Interests | P73: 0 | Q73: 0 | R73: 0 | S73: 0 | T73: 0 | W73: Less: Dividends Paid to Non-Controlling Interests | AA73: =AA255*(1-$Y$26) -> -36.54892 | AB73: =AB255*(1-$Y$26) -> -43.884109 | AC73: =AC255*(1-$Y$26) -> -51.690408 | AD73: =AD255*(1-$Y$26) -> -60.00419 | AE73: =AE255*(1-$Y$26) -> -68.864512
C74: Less: Dividends | E74: =IF($I$27=$H$20,P74,AA74) -> -123.77822 | F74: =IF($I$27=$H$20,Q74,AB74) -> -148.21117 | G74: =IF($I$27=$H$20,R74,AC74) -> -174.01746 | H74: =IF($I$27=$H$20,S74,AD74) -> -201.28796 | I74: =IF($I$27=$H$20,T74,AE74) -> -230.11923 | L74: Less: Dividends | P74: =P166 -> -123.77822 | Q74: =Q166 -> -148.21117 | R74: =R166 -> -174.01746 | S74: =S166 -> -201.28796 | T74: =T166 -> -230.11923 | W74: Less: Dividends | AA74: =SUM(AA166) -> -123.77822 | AB74: =SUM(AB166) -> -148.21117 | AC74: =SUM(AC166) -> -174.01746 | AD74: =SUM(AD166) -> -201.28796 | AE74: =SUM(AE166) -> -230.11923
C75: Cash Flow from Financing Activities | E75: =SUM(E71:E74) -> -1210.3271 | F75: =SUM(F71:F74) -> -1242.0953 | G75: =SUM(G71:G74) -> -1275.7079 | H75: =SUM(H71:H74) -> -1311.2921 | I75: =SUM(I71:I74) -> -1348.9837 | L75: Cash Flow from Financing Activities | P75: =SUM(P71:P74) -> -873.77822 | Q75: =SUM(Q71:Q74) -> -898.21117 | R75: =SUM(R71:R74) -> -924.01746 | S75: =SUM(S71:S74) -> -951.28796 | T75: =SUM(T71:T74) -> -980.11923 | W75: Cash Flow from Financing Activities | AA75: =SUM(AA71:AA74) -> -1210.3271 | AB75: =SUM(AB71:AB74) -> -1242.0953 | AC75: =SUM(AC71:AC74) -> -1275.7079 | AD75: =SUM(AD71:AD74) -> -1311.2921 | AE75: =SUM(AE71:AE74) -> -1348.9837
C77: Beginning Cash & Equivalents | E77: =IF($I$27=$H$20,P77,AA77) -> 4401.662 | F77: =IF($I$27=$H$20,Q77,AB77) -> 3948.8607 | G77: =IF($I$27=$H$20,R77,AC77) -> 3639.0372 | H77: =IF($I$27=$H$20,S77,AD77) -> 3480.6967 | I77: =IF($I$27=$H$20,T77,AE77) -> 3482.9516 | L77: Beginning Cash & Equivalents | P77: =O89 -> 2773.2724 | Q77: =P79 -> 2456.8162 | R77: =Q79 -> 2243.4403 | S77: =R79 -> 2139.0703 | T77: =S79 -> 2150.0365 | W77: Beginning Cash & Equivalents | AA77: =Z89 -> 4401.662 | AB77: =AA79 -> 3948.8607 | AC77: =AB79 -> 3639.0372 | AD77: =AC79 -> 3480.6967 | AE77: =AD79 -> 3482.9516
C78: Change in Cash & Equivalents | E78: =IF($I$27=$H$20,P78,AA78) -> -452.80133 | F78: =IF($I$27=$H$20,Q78,AB78) -> -309.82347 | G78: =IF($I$27=$H$20,R78,AC78) -> -158.34044 | H78: =IF($I$27=$H$20,S78,AD78) -> 2.254849 | I78: =IF($I$27=$H$20,T78,AE78) -> 172.61073 | L78: Change in Cash & Equivalents | P78: =P64+P68+P75 -> -316.45622 | Q78: =Q64+Q68+Q75 -> -213.37591 | R78: =R64+R68+R75 -> -104.37001 | S78: =S64+S68+S75 -> 10.966215 | T78: =T64+T68+T75 -> 133.06364 | W78: Change in Cash & Equivalents | AA78: =AA64+AA68+AA75 -> -452.80133 | AB78: =AB64+AB68+AB75 -> -309.82347 | AC78: =AC64+AC68+AC75 -> -158.34044 | AD78: =AD64+AD68+AD75 -> 2.254849 | AE78: =AE64+AE68+AE75 -> 172.61073
C79: Ending Cash & Equivalents | E79: =SUM(E77:E78) -> 3948.8607 | F79: =SUM(F77:F78) -> 3639.0372 | G79: =SUM(G77:G78) -> 3480.6967 | H79: =SUM(H77:H78) -> 3482.9516 | I79: =SUM(I77:I78) -> 3655.5623 | L79: Ending Cash & Equivalents | P79: =SUM(P77:P78) -> 2456.8162 | Q79: =SUM(Q77:Q78) -> 2243.4403 | R79: =SUM(R77:R78) -> 2139.0703 | S79: =SUM(S77:S78) -> 2150.0365 | T79: =SUM(T77:T78) -> 2283.1001 | W79: Ending Cash & Equivalents | AA79: =SUM(AA77:AA78) -> 3948.8607 | AB79: =SUM(AB77:AB78) -> 3639.0372 | AC79: =SUM(AC77:AC78) -> 3480.6967 | AD79: =SUM(AD77:AD78) -> 3482.9516 | AE79: =SUM(AE77:AE78) -> 3655.5623
C83: ="WW Balance Sheet (Pro-Forma under "&I27&")" -> WW Balance Sheet (Pro-Forma under Consolidation Method) | L83: ="WW Balance Sheet (Pro-Forma under "&S27&")" -> WW Balance Sheet (Pro-Forma under Cost Method) | W83: ="WW Balance Sheet (Pro-Forma under "&AD27&")" -> WW Balance Sheet (Pro-Forma under Consolidation Method)
C84: (in USD$ millions, fiscal years ended December 31st) | L84: (in USD$ millions, fiscal years ended December 31st) | W84: (in USD$ millions, fiscal years ended December 31st)
D86: =D57 -> 44926 | E86: =E57 -> 45291 | F86: =F57 -> 45657 | G86: =G57 -> 46022 | H86: =H57 -> 46387 | I86: =I57 -> 46752 | M86: Prior to Close | N86: Adjustments | O86: =O57 -> 44926 | P86: =P57 -> 45291 | Q86: =Q57 -> 45657 | R86: =R57 -> 46022 | S86: =S57 -> 46387 | T86: =T57 -> 46752 | X86: Prior to Close | Y86: Adjustments | Z86: =Z57 -> 44926 | AA86: =AA57 -> 45291 | AB86: =AB57 -> 45657 | AC86: =AC57 -> 46022 | AD86: =AD57 -> 46387 | AE86: =AE57 -> 46752
C88: Assets | L88: Assets | W88: Assets
C89: Cash and Equivalents | D89: =IF($I$27=$H$20,O89,Z89) -> 4401.662 | E89: =IF($I$27=$H$20,P89,AA89) -> 3948.8607 | F89: =IF($I$27=$H$20,Q89,AB89) -> 3639.0372 | G89: =IF($I$27=$H$20,R89,AC89) -> 3480.6967 | H89: =IF($I$27=$H$20,S89,AD89) -> 3482.9516 | I89: =IF($I$27=$H$20,T89,AE89) -> 3655.5623 | L89: Cash and Equivalents | M89: =O181 -> 6823.2724 | N89: =-N26*N25 -> -4050 | O89: =SUM(M89:N89) -> 2773.2724 | P89: =P79 -> 2456.8162 | Q89: =Q79 -> 2243.4403 | R89: =R79 -> 2139.0703 | S89: =S79 -> 2150.0365 | T89: =T79 -> 2283.1001 | W89: Cash and Equivalents | X89: =Z181 -> 6823.2724 | Y89: =Z270-Y25*Y26 -> -2421.6104 | Z89: =SUM(X89:Y89) -> 4401.662 | AA89: =AA79 -> 3948.8607 | AB89: =AB79 -> 3639.0372 | AC89: =AC79 -> 3480.6967 | AD89: =AD79 -> 3482.9516 | AE89: =AE79 -> 3655.5623
C90: A/R | D90: =IF($I$27=$H$20,O90,Z90) -> 591.42857 | E90: =IF($I$27=$H$20,P90,AA90) -> 622.71429 | F90: =IF($I$27=$H$20,Q90,AB90) -> 655.66714 | G90: =IF($I$27=$H$20,R90,AC90) -> 690.37667 | H90: =IF($I$27=$H$20,S90,AD90) -> 726.93725 | I90: =IF($I$27=$H$20,T90,AE90) -> 765.44836 | L90: A/R | M90: =O182 -> 420 | N90: 0 | O90: =SUM(M90:N90) -> 420 | P90: =P182 -> 441 | Q90: =Q182 -> 463.05 | R90: =R182 -> 486.2025 | S90: =S182 -> 510.51263 | T90: =T182 -> 536.03826 | W90: A/R | X90: =Z182 -> 420 | Y90: =Z271 -> 171.42857 | Z90: =SUM(X90:Y90) -> 591.42857 | AA90: =SUM(AA182,AA271) -> 622.71429 | AB90: =SUM(AB182,AB271) -> 655.66714 | AC90: =SUM(AC182,AC271) -> 690.37667 | AD90: =SUM(AD182,AD271) -> 726.93725 | AE90: =SUM(AE182,AE271) -> 765.44836
C91: Inventories | D91: =IF($I$27=$H$20,O91,Z91) -> 658.92857 | E91: =IF($I$27=$H$20,P91,AA91) -> 682.06339 | F91: =IF($I$27=$H$20,Q91,AB91) -> 705.81488 | G91: =IF($I$27=$H$20,R91,AC91) -> 730.18354 | H91: =IF($I$27=$H$20,S91,AD91) -> 755.16819 | I91: =IF($I$27=$H$20,T91,AE91) -> 780.76574 | L91: Inventories | M91: =O183 -> 472.5 | N91: 0 | O91: =SUM(M91:N91) -> 472.5 | P91: =P183 -> 487.85625 | Q91: =Q183 -> 503.56687 | R91: =R183 -> 519.62892 | S91: =S183 -> 536.03826 | T91: =T183 -> 552.78945 | W91: Inventories | X91: =Z183 -> 472.5 | Y91: =Z272 -> 186.42857 | Z91: =SUM(X91:Y91) -> 658.92857 | AA91: =SUM(AA183,AA272) -> 682.06339 | AB91: =SUM(AB183,AB272) -> 705.81488 | AC91: =SUM(AC183,AC272) -> 730.18354 | AD91: =SUM(AD183,AD272) -> 755.16819 | AE91: =SUM(AE183,AE272) -> 780.76574
C92: Other | D92: =IF($I$27=$H$20,O92,Z92) -> 184.82143 | E92: =IF($I$27=$H$20,P92,AA92) -> 194.59821 | F92: =IF($I$27=$H$20,Q92,AB92) -> 204.89598 | G92: =IF($I$27=$H$20,R92,AC92) -> 215.74271 | H92: =IF($I$27=$H$20,S92,AD92) -> 227.16789 | I92: =IF($I$27=$H$20,T92,AE92) -> 239.20261 | L92: Other | M92: =O184 -> 131.25 | N92: 0 | O92: =SUM(M92:N92) -> 131.25 | P92: =P184 -> 137.8125 | Q92: =Q184 -> 144.70312 | R92: =R184 -> 151.93828 | S92: =S184 -> 159.5352 | T92: =T184 -> 167.51196 | W92: Other | X92: =Z184 -> 131.25 | Y92: =Z273 -> 53.571429 | Z92: =SUM(X92:Y92) -> 184.82143 | AA92: =SUM(AA184,AA273) -> 194.59821 | AB92: =SUM(AB184,AB273) -> 204.89598 | AC92: =SUM(AC184,AC273) -> 215.74271 | AD92: =SUM(AD184,AD273) -> 227.16789 | AE92: =SUM(AE184,AE273) -> 239.20261
C93: Total Current Assets | D93: =SUM(D89:D92) -> 5836.8406 | E93: =SUM(E89:E92) -> 5448.2365 | F93: =SUM(F89:F92) -> 5205.4152 | G93: =SUM(G89:G92) -> 5116.9997 | H93: =SUM(H89:H92) -> 5192.2249 | I93: =SUM(I89:I92) -> 5440.979 | L93: Total Current Assets | M93: =SUM(M89:M92) -> 7847.0224 | N93: =SUM(N89:N92) -> -4050 | O93: =SUM(O89:O92) -> 3797.0224 | P93: =SUM(P89:P92) -> 3523.4849 | Q93: =SUM(Q89:Q92) -> 3354.7603 | R93: =SUM(R89:R92) -> 3296.84 | S93: =SUM(S89:S92) -> 3356.1226 | T93: =SUM(T89:T92) -> 3539.4398 | W93: Total Current Assets | X93: =SUM(X89:X92) -> 7847.0224 | Y93: =SUM(Y89:Y92) -> -2010.1819 | Z93: =SUM(Z89:Z92) -> 5836.8406 | AA93: =SUM(AA89:AA92) -> 5448.2365 | AB93: =SUM(AB89:AB92) -> 5205.4152 | AC93: =SUM(AC89:AC92) -> 5116.9997 | AD93: =SUM(AD89:AD92) -> 5192.2249 | AE93: =SUM(AE89:AE92) -> 5440.979
C95: Investment In JP Motors | D95: =IF($I$27=$H$20,O95,Z95) -> 0 | E95: =IF($I$27=$H$20,P95,AA95) -> 0 | F95: =IF($I$27=$H$20,Q95,AB95) -> 0 | G95: =IF($I$27=$H$20,R95,AC95) -> 0 | H95: =IF($I$27=$H$20,S95,AD95) -> 0 | I95: =IF($I$27=$H$20,T95,AE95) -> 0 | L95: Investment In JP Motors | M95: 0 | N95: =-N89 -> 4050 | O95: =SUM(M95:N95) -> 4050 | P95: =O95 -> 4050 | Q95: =P95 -> 4050 | R95: =Q95 -> 4050 | S95: =R95 -> 4050 | T95: =S95 -> 4050 | W95: Investment In JP Motors | X95: 0 | Y95: 0 | Z95: =SUM(X95:Y95) -> 0 | AA95: =Z95 -> 0 | AB95: =AA95 -> 0 | AC95: =AB95 -> 0 | AD95: =AC95 -> 0 | AE95: =AD95 -> 0
C96: Goodwill | D96: =IF($I$27=$H$20,O96,Z96) -> 1002.2033 | E96: =IF($I$27=$H$20,P96,AA96) -> 1002.2033 | F96: =IF($I$27=$H$20,Q96,AB96) -> 1002.2033 | G96: =IF($I$27=$H$20,R96,AC96) -> 1002.2033 | H96: =IF($I$27=$H$20,S96,AD96) -> 1002.2033 | I96: =IF($I$27=$H$20,T96,AE96) -> 1002.2033 | L96: Goodwill | M96: 0 | N96: 0 | O96: =SUM(M96:N96) -> 0 | P96: 0 | Q96: 0 | R96: 0 | S96: 0 | T96: 0 | W96: Goodwill | X96: 0 | Y96: =Y25-Z297 -> 1002.2033 | Z96: =SUM(X96:Y96) -> 1002.2033 | AA96: =Z96 -> 1002.2033 | AB96: =AA96 -> 1002.2033 | AC96: =AB96 -> 1002.2033 | AD96: =AC96 -> 1002.2033 | AE96: =AD96 -> 1002.2033
C97: Fixed Assets | D97: =IF($I$27=$H$20,O97,Z97) -> 21964.286 | E97: =IF($I$27=$H$20,P97,AA97) -> 22079.909 | F97: =IF($I$27=$H$20,Q97,AB97) -> 22201.643 | G97: =IF($I$27=$H$20,R97,AC97) -> 22329.812 | H97: =IF($I$27=$H$20,S97,AD97) -> 22464.76 | I97: =IF($I$27=$H$20,T97,AE97) -> 22606.848 | L97: Fixed Assets | M97: =O187 -> 15750 | N97: 0 | O97: =SUM(M97:N97) -> 15750 | P97: =P187 -> 15832.688 | Q97: =Q187 -> 15919.509 | R97: =R187 -> 16010.672 | S97: =S187 -> 16106.393 | T97: =T187 -> 16206.901 | W97: Fixed Assets | X97: =Z187 -> 15750 | Y97: =Z276 -> 6214.2857 | Z97: =SUM(X97:Y97) -> 21964.286 | AA97: =SUM(AA187,AA276) -> 22079.909 | AB97: =SUM(AB187,AB276) -> 22201.643 | AC97: =SUM(AC187,AC276) -> 22329.812 | AD97: =SUM(AD187,AD276) -> 22464.76 | AE97: =SUM(AE187,AE276) -> 22606.848
C98: Other | D98: =IF($I$27=$H$20,O98,Z98) -> 24 | E98: =IF($I$27=$H$20,P98,AA98) -> 24 | F98: =IF($I$27=$H$20,Q98,AB98) -> 24 | G98: =IF($I$27=$H$20,R98,AC98) -> 24 | H98: =IF($I$27=$H$20,S98,AD98) -> 24 | I98: =IF($I$27=$H$20,T98,AE98) -> 24 | L98: Other | M98: =O188 -> 6 | N98: 0 | O98: =SUM(M98:N98) -> 6 | P98: =P188 -> 6 | Q98: =Q188 -> 6 | R98: =R188 -> 6 | S98: =S188 -> 6 | T98: =T188 -> 6 | W98: Other | X98: =Z188 -> 6 | Y98: =Z277 -> 18 | Z98: =SUM(X98:Y98) -> 24 | AA98: =SUM(AA188,AA277) -> 24 | AB98: =SUM(AB188,AB277) -> 24 | AC98: =SUM(AC188,AC277) -> 24 | AD98: =SUM(AD188,AD277) -> 24 | AE98: =SUM(AE188,AE277) -> 24
C99: Total Long-Term Assets | D99: =SUM(D95:D98) -> 22990.489 | E99: =SUM(E95:E98) -> 23106.112 | F99: =SUM(F95:F98) -> 23227.846 | G99: =SUM(G95:G98) -> 23356.015 | H99: =SUM(H95:H98) -> 23490.964 | I99: =SUM(I95:I98) -> 23633.051 | L99: Total Long-Term Assets | M99: =SUM(M95:M98) -> 15756 | N99: =SUM(N95:N98) -> 4050 | O99: =SUM(O95:O98) -> 19806 | P99: =SUM(P95:P98) -> 19888.688 | Q99: =SUM(Q95:Q98) -> 19975.509 | R99: =SUM(R95:R98) -> 20066.672 | S99: =SUM(S95:S98) -> 20162.393 | T99: =SUM(T95:T98) -> 20262.901 | W99: Total Long-Term Assets | X99: =SUM(X95:X98) -> 15756 | Y99: =SUM(Y95:Y98) -> 7234.489 | Z99: =SUM(Z95:Z98) -> 22990.489 | AA99: =SUM(AA95:AA98) -> 23106.112 | AB99: =SUM(AB95:AB98) -> 23227.846 | AC99: =SUM(AC95:AC98) -> 23356.015 | AD99: =SUM(AD95:AD98) -> 23490.964 | AE99: =SUM(AE95:AE98) -> 23633.051
C101: Total Assets | D101: =D93+D99 -> 28827.33 | E101: =E93+E99 -> 28554.349 | F101: =F93+F99 -> 28433.261 | G101: =G93+G99 -> 28473.015 | H101: =H93+H99 -> 28683.188 | I101: =I93+I99 -> 29074.03 | L101: Total Assets | M101: =M93+M99 -> 23603.022 | N101: =N93+N99 -> 0 | O101: =O93+O99 -> 23603.022 | P101: =P93+P99 -> 23412.172 | Q101: =Q93+Q99 -> 23330.27 | R101: =R93+R99 -> 23363.512 | S101: =S93+S99 -> 23518.516 | T101: =T93+T99 -> 23802.34 | W101: Total Assets | X101: =X93+X99 -> 23603.022 | Y101: =Y93+Y99 -> 5224.3071 | Z101: =Z93+Z99 -> 28827.33 | AA101: =AA93+AA99 -> 28554.349 | AB101: =AB93+AB99 -> 28433.261 | AC101: =AC93+AC99 -> 28473.015 | AD101: =AD93+AD99 -> 28683.188 | AE101: =AE93+AE99 -> 29074.03
C103: Liabilities | L103: Liabilities | W103: Liabilities
C104: A/P | D104: =IF($I$27=$H$20,O104,Z104) -> 395.35714 | E104: =IF($I$27=$H$20,P104,AA104) -> 409.23804 | F104: =IF($I$27=$H$20,Q104,AB104) -> 423.48892 | G104: =IF($I$27=$H$20,R104,AC104) -> 438.11012 | H104: =IF($I$27=$H$20,S104,AD104) -> 453.10091 | I104: =IF($I$27=$H$20,T104,AE104) -> 468.45944 | L104: A/P | M104: =O194 -> 283.5 | N104: 0 | O104: =SUM(M104:N104) -> 283.5 | P104: =P194 -> 292.71375 | Q104: =Q194 -> 302.14012 | R104: =R194 -> 311.77735 | S104: =S194 -> 321.62295 | T104: =T194 -> 331.67367 | W104: A/P | X104: =Z194 -> 283.5 | Y104: =Z283 -> 111.85714 | Z104: =SUM(X104:Y104) -> 395.35714 | AA104: =SUM(AA194,AA283) -> 409.23804 | AB104: =SUM(AB194,AB283) -> 423.48892 | AC104: =SUM(AC194,AC283) -> 438.11012 | AD104: =SUM(AD194,AD283) -> 453.10091 | AE104: =SUM(AE194,AE283) -> 468.45944
C105: Long-Term Debt Due within One Year | D105: =IF($I$27=$H$20,O105,Z105) -> 1050 | E105: =IF($I$27=$H$20,P105,AA105) -> 1050 | F105: =IF($I$27=$H$20,Q105,AB105) -> 1050 | G105: =IF($I$27=$H$20,R105,AC105) -> 1050 | H105: =IF($I$27=$H$20,S105,AD105) -> 1050 | I105: =IF($I$27=$H$20,T105,AE105) -> 1050 | L105: Long-Term Debt Due within One Year | M105: =O195 -> 750 | N105: 0 | O105: =SUM(M105:N105) -> 750 | P105: =P195 -> 750 | Q105: =Q195 -> 750 | R105: =R195 -> 750 | S105: =S195 -> 750 | T105: =T195 -> 750 | W105: Long-Term Debt Due within One Year | X105: =Z195 -> 750 | Y105: =Z284 -> 300 | Z105: =SUM(X105:Y105) -> 1050 | AA105: =SUM(AA195,AA284) -> 1050 | AB105: =SUM(AB195,AB284) -> 1050 | AC105: =SUM(AC195,AC284) -> 1050 | AD105: =SUM(AD195,AD284) -> 1050 | AE105: =SUM(AE195,AE284) -> 1050
C106: Other | D106: =IF($I$27=$H$20,O106,Z106) -> 9.9 | E106: =IF($I$27=$H$20,P106,AA106) -> 9.9 | F106: =IF($I$27=$H$20,Q106,AB106) -> 9.9 | G106: =IF($I$27=$H$20,R106,AC106) -> 9.9 | H106: =IF($I$27=$H$20,S106,AD106) -> 9.9 | I106: =IF($I$27=$H$20,T106,AE106) -> 9.9 | L106: Other | M106: =O196 -> 0.45 | N106: 0 | O106: =SUM(M106:N106) -> 0.45 | P106: =P196 -> 0.45 | Q106: =Q196 -> 0.45 | R106: =R196 -> 0.45 | S106: =S196 -> 0.45 | T106: =T196 -> 0.45 | W106: Other | X106: =Z196 -> 0.45 | Y106: =Z285 -> 9.45 | Z106: =SUM(X106:Y106) -> 9.9 | AA106: =SUM(AA196,AA285) -> 9.9 | AB106: =SUM(AB196,AB285) -> 9.9 | AC106: =SUM(AC196,AC285) -> 9.9 | AD106: =SUM(AD196,AD285) -> 9.9 | AE106: =SUM(AE196,AE285) -> 9.9
C107: Total Current Liabilities | D107: =SUM(D104:D106) -> 1455.2571 | E107: =SUM(E104:E106) -> 1469.138 | F107: =SUM(F104:F106) -> 1483.3889 | G107: =SUM(G104:G106) -> 1498.0101 | H107: =SUM(H104:H106) -> 1513.0009 | I107: =SUM(I104:I106) -> 1528.3594 | L107: Total Current Liabilities | M107: =SUM(M104:M106) -> 1033.95 | N107: =SUM(N104:N106) -> 0 | O107: =SUM(O104:O106) -> 1033.95 | P107: =SUM(P104:P106) -> 1043.1637 | Q107: =SUM(Q104:Q106) -> 1052.5901 | R107: =SUM(R104:R106) -> 1062.2274 | S107: =SUM(S104:S106) -> 1072.073 | T107: =SUM(T104:T106) -> 1082.1237 | W107: Total Current Liabilities | X107: =SUM(X104:X106) -> 1033.95 | Y107: =SUM(Y104:Y106) -> 421.30714 | Z107: =SUM(Z104:Z106) -> 1455.2571 | AA107: =SUM(AA104:AA106) -> 1469.138 | AB107: =SUM(AB104:AB106) -> 1483.3889 | AC107: =SUM(AC104:AC106) -> 1498.0101 | AD107: =SUM(AD104:AD106) -> 1513.0009 | AE107: =SUM(AE104:AE106) -> 1528.3594
C109: Long-Term Debt | D109: =IF($I$27=$H$20,O109,Z109) -> 7350 | E109: =IF($I$27=$H$20,P109,AA109) -> 6300 | F109: =IF($I$27=$H$20,Q109,AB109) -> 5250 | G109: =IF($I$27=$H$20,R109,AC109) -> 4200 | H109: =IF($I$27=$H$20,S109,AD109) -> 3150 | I109: =IF($I$27=$H$20,T109,AE109) -> 2100 | L109: Long-Term Debt | M109: =O199 -> 5250 | N109: 0 | O109: =SUM(M109:N109) -> 5250 | P109: =P199 -> 4500 | Q109: =Q199 -> 3750 | R109: =R199 -> 3000 | S109: =S199 -> 2250 | T109: =T199 -> 1500 | W109: Long-Term Debt | X109: =Z199 -> 5250 | Y109: =Z288 -> 2100 | Z109: =SUM(X109:Y109) -> 7350 | AA109: =SUM(AA199,AA288) -> 6300 | AB109: =SUM(AB199,AB288) -> 5250 | AC109: =SUM(AC199,AC288) -> 4200 | AD109: =SUM(AD199,AD288) -> 3150 | AE109: =SUM(AE199,AE288) -> 2100
C110: Other | D110: =IF($I$27=$H$20,O110,Z110) -> 4.65 | E110: =IF($I$27=$H$20,P110,AA110) -> 4.65 | F110: =IF($I$27=$H$20,Q110,AB110) -> 4.65 | G110: =IF($I$27=$H$20,R110,AC110) -> 4.65 | H110: =IF($I$27=$H$20,S110,AD110) -> 4.65 | I110: =IF($I$27=$H$20,T110,AE110) -> 4.65 | L110: Other | M110: =O200 -> 1.65 | N110: 0 | O110: =SUM(M110:N110) -> 1.65 | P110: =P200 -> 1.65 | Q110: =Q200 -> 1.65 | R110: =R200 -> 1.65 | S110: =S200 -> 1.65 | T110: =T200 -> 1.65 | W110: Other | X110: =Z200 -> 1.65 | Y110: =Z289 -> 3 | Z110: =SUM(X110:Y110) -> 4.65 | AA110: =SUM(AA200,AA289) -> 4.65 | AB110: =SUM(AB200,AB289) -> 4.65 | AC110: =SUM(AC200,AC289) -> 4.65 | AD110: =SUM(AD200,AD289) -> 4.65 | AE110: =SUM(AE200,AE289) -> 4.65
C111: Total Long-term Liabilities | D111: =SUM(D109:D110) -> 7354.65 | E111: =SUM(E109:E110) -> 6304.65 | F111: =SUM(F109:F110) -> 5254.65 | G111: =SUM(G109:G110) -> 4204.65 | H111: =SUM(H109:H110) -> 3154.65 | I111: =SUM(I109:I110) -> 2104.65 | L111: Total Long-term Liabilities | M111: =SUM(M109:M110) -> 5251.65 | N111: =SUM(N109:N110) -> 0 | O111: =SUM(O109:O110) -> 5251.65 | P111: =SUM(P109:P110) -> 4501.65 | Q111: =SUM(Q109:Q110) -> 3751.65 | R111: =SUM(R109:R110) -> 3001.65 | S111: =SUM(S109:S110) -> 2251.65 | T111: =SUM(T109:T110) -> 1501.65 | W111: Total Long-term Liabilities | X111: =SUM(X109:X110) -> 5251.65 | Y111: =SUM(Y109:Y110) -> 2103 | Z111: =SUM(Z109:Z110) -> 7354.65 | AA111: =SUM(AA109:AA110) -> 6304.65 | AB111: =SUM(AB109:AB110) -> 5254.65 | AC111: =SUM(AC109:AC110) -> 4204.65 | AD111: =SUM(AD109:AD110) -> 3154.65 | AE111: =SUM(AE109:AE110) -> 2104.65
C113: Total Liabilities | D113: =D107+D111 -> 8809.9071 | E113: =E107+E111 -> 7773.788 | F113: =F107+F111 -> 6738.0389 | G113: =G107+G111 -> 5702.6601 | H113: =H107+H111 -> 4667.6509 | I113: =I107+I111 -> 3633.0094 | L113: Total Liabilities | M113: =M107+M111 -> 6285.6 | N113: =N107+N111 -> 0 | O113: =O107+O111 -> 6285.6 | P113: =P107+P111 -> 5544.8137 | Q113: =Q107+Q111 -> 4804.2401 | R113: =R107+R111 -> 4063.8774 | S113: =S107+S111 -> 3323.723 | T113: =T107+T111 -> 2583.7737 | W113: Total Liabilities | X113: =X107+X111 -> 6285.6 | Y113: =Y107+Y111 -> 2524.3071 | Z113: =Z107+Z111 -> 8809.9071 | AA113: =AA107+AA111 -> 7773.788 | AB113: =AB107+AB111 -> 6738.0389 | AC113: =AC107+AC111 -> 5702.6601 | AD113: =AD107+AD111 -> 4667.6509 | AE113: =AE107+AE111 -> 3633.0094
C115: Shareholders' Equity | L115: Shareholders' Equity | W115: Shareholders' Equity
C116: Common Shares | D116: =IF($I$27=$H$20,O116,Z116) -> 5550 | E116: =IF($I$27=$H$20,P116,AA116) -> 5550 | F116: =IF($I$27=$H$20,Q116,AB116) -> 5550 | G116: =IF($I$27=$H$20,R116,AC116) -> 5550 | H116: =IF($I$27=$H$20,S116,AD116) -> 5550 | I116: =IF($I$27=$H$20,T116,AE116) -> 5550 | L116: Common Shares | M116: =O206 -> 5550 | N116: 0 | O116: =SUM(M116:N116) -> 5550 | P116: =P206 -> 5550 | Q116: =Q206 -> 5550 | R116: =R206 -> 5550 | S116: =S206 -> 5550 | T116: =T206 -> 5550 | W116: Common Shares | X116: =Z206 -> 5550 | Y116: 0 | Z116: =SUM(X116:Y116) -> 5550 | AA116: =AA206 -> 5550 | AB116: =AB206 -> 5550 | AC116: =AC206 -> 5550 | AD116: =AD206 -> 5550 | AE116: =AE206 -> 5550
C117: Retained Earnings | D117: =IF($I$27=$H$20,O117,Z117) -> 11767.422 | E117: =IF($I$27=$H$20,P117,AA117) -> 12445.28 | F117: =IF($I$27=$H$20,Q117,AB117) -> 13257.545 | G117: =IF($I$27=$H$20,R117,AC117) -> 14212.067 | H117: =IF($I$27=$H$20,S117,AD117) -> 15317.24 | I117: =IF($I$27=$H$20,T117,AE117) -> 16582.039 | L117: Retained Earnings | M117: =O207 -> 11767.422 | N117: 0 | O117: =SUM(M117:N117) -> 11767.422 | P117: =SUM(O117,P50,P74) -> 12317.359 | Q117: =SUM(P117,Q50,Q74) -> 12976.03 | R117: =SUM(Q117,R50,R74) -> 13749.635 | S117: =SUM(R117,S50,S74) -> 14644.793 | T117: =SUM(S117,T50,T74) -> 15668.567 | W117: Retained Earnings | X117: =Z207 -> 11767.422 | Y117: 0 | Z117: =SUM(X117:Y117) -> 11767.422 | AA117: =SUM(Z117,AA50,AA74) -> 12445.28 | AB117: =SUM(AA117,AB50,AB74) -> 13257.545 | AC117: =SUM(AB117,AC50,AC74) -> 14212.067 | AD117: =SUM(AC117,AD50,AD74) -> 15317.24 | AE117: =SUM(AD117,AE50,AE74) -> 16582.039
C118: Non-Controlling Interest | D118: =IF($I$27=$H$20,O118,Z118) -> 2700 | E118: =IF($I$27=$H$20,P118,AA118) -> 2785.2808 | F118: =IF($I$27=$H$20,Q118,AB118) -> 2887.6771 | G118: =IF($I$27=$H$20,R118,AC118) -> 3008.288 | H118: =IF($I$27=$H$20,S118,AD118) -> 3148.2978 | I118: =IF($I$27=$H$20,T118,AE118) -> 3308.9817 | L118: Non-Controlling Interest | M118: 0 | N118: 0 | O118: =SUM(M118:N118) -> 0 | P118: 0 | Q118: 0 | R118: 0 | S118: 0 | T118: 0 | W118: Non-Controlling Interest | X118: 0 | Y118: =(1-Y26)*Y25 -> 2700 | Z118: =SUM(X118:Y118) -> 2700 | AA118: =Z118+SUM(AA62,AA73) -> 2785.2808 | AB118: =AA118+SUM(AB62,AB73) -> 2887.6771 | AC118: =AB118+SUM(AC62,AC73) -> 3008.288 | AD118: =AC118+SUM(AD62,AD73) -> 3148.2978 | AE118: =AD118+SUM(AE62,AE73) -> 3308.9817
C119: Total Shareholders' Equity | D119: =SUM(D116:D118) -> 20017.422 | E119: =SUM(E116:E118) -> 20780.561 | F119: =SUM(F116:F118) -> 21695.222 | G119: =SUM(G116:G118) -> 22770.355 | H119: =SUM(H116:H118) -> 24015.538 | I119: =SUM(I116:I118) -> 25441.021 | L119: Total Shareholders' Equity | M119: =SUM(M116:M118) -> 17317.422 | N119: =SUM(N116:N118) -> 0 | O119: =SUM(O116:O118) -> 17317.422 | P119: =SUM(P116:P118) -> 17867.359 | Q119: =SUM(Q116:Q118) -> 18526.03 | R119: =SUM(R116:R118) -> 19299.635 | S119: =SUM(S116:S118) -> 20194.793 | T119: =SUM(T116:T118) -> 21218.567 | W119: Total Shareholders' Equity | X119: =SUM(X116:X118) -> 17317.422 | Y119: =SUM(Y116:Y118) -> 2700 | Z119: =SUM(Z116:Z118) -> 20017.422 | AA119: =SUM(AA116:AA118) -> 20780.561 | AB119: =SUM(AB116:AB118) -> 21695.222 | AC119: =SUM(AC116:AC118) -> 22770.355 | AD119: =SUM(AD116:AD118) -> 24015.538 | AE119: =SUM(AE116:AE118) -> 25441.021
C121: Total Liabilities & Shareholders' Equity | D121: =D113+D119 -> 28827.33 | E121: =E113+E119 -> 28554.349 | F121: =F113+F119 -> 28433.261 | G121: =G113+G119 -> 28473.015 | H121: =H113+H119 -> 28683.188 | I121: =I113+I119 -> 29074.03 | L121: Total Liabilities & Shareholders' Equity | M121: =M113+M119 -> 23603.022 | N121: =N113+N119 -> 0 | O121: =O113+O119 -> 23603.022 | P121: =P113+P119 -> 23412.172 | Q121: =Q113+Q119 -> 23330.27 | R121: =R113+R119 -> 23363.512 | S121: =S113+S119 -> 23518.516 | T121: =T113+T119 -> 23802.34 | W121: Total Liabilities & Shareholders' Equity | X121: =X113+X119 -> 23603.022 | Y121: =Y113+Y119 -> 5224.3071 | Z121: =Z113+Z119 -> 28827.33 | AA121: =AA113+AA119 -> 28554.349 | AB121: =AB113+AB119 -> 28433.261 | AC121: =AC113+AC119 -> 28473.015 | AD121: =AD113+AD119 -> 28683.188 | AE121: =AE113+AE119 -> 29074.03
C122: Check | D122: =D101-D121 -> 0 | E122: =E101-E121 -> 0 | F122: =F101-F121 -> 0 | G122: =G101-G121 -> 0 | H122: =H101-H121 -> 0 | I122: =I101-I121 -> 0 | L122: Check | M122: =M101-M121 -> 0 | N122: =N101-N121 -> 0 | O122: =O101-O121 -> 0 | P122: =P101-P121 -> 0 | Q122: =Q101-Q121 -> 0 | R122: =R101-R121 -> 0 | S122: =S101-S121 -> 0 | T122: =T101-T121 -> 0 | W122: Check | X122: =X101-X121 -> 0 | Y122: =Y101-Y121 -> 0 | Z122: =Z101-Z121 -> 0 | AA122: =AA101-AA121 -> 0 | AB122: =AB101-AB121 -> 0 | AC122: =AC101-AC121 -> 0 | AD122: =AD101-AD121 -> 0 | AE122: =AE101-AE121 -> 0
K126: WW Financial Statements (Prior to the Acquisition) | V126: WW Financial Statements (Prior to the Acquisition)
L129: WW Income Statement (Prior to the Acquisition) | W129: WW Income Statement (Prior to the Acquisition)
L130: (in USD$ millions, fiscal years ended December 31st) | W130: (in USD$ millions, fiscal years ended December 31st)
O132: =CaseData!$C$13 -> 44926 | P132: =DATE(YEAR(O132)+1,MONTH(O132),DAY(O132)) -> 45291 | Q132: =DATE(YEAR(P132)+1,MONTH(P132),DAY(P132)) -> 45657 | R132: =DATE(YEAR(Q132)+1,MONTH(Q132),DAY(Q132)) -> 46022 | S132: =DATE(YEAR(R132)+1,MONTH(R132),DAY(R132)) -> 46387 | T132: =DATE(YEAR(S132)+1,MONTH(S132),DAY(S132)) -> 46752 | Z132: =CaseData!$C$13 -> 44926 | AA132: =DATE(YEAR(Z132)+1,MONTH(Z132),DAY(Z132)) -> 45291 | AB132: =DATE(YEAR(AA132)+1,MONTH(AA132),DAY(AA132)) -> 45657 | AC132: =DATE(YEAR(AB132)+1,MONTH(AB132),DAY(AB132)) -> 46022 | AD132: =DATE(YEAR(AC132)+1,MONTH(AC132),DAY(AC132)) -> 46387 | AE132: =DATE(YEAR(AD132)+1,MONTH(AD132),DAY(AD132)) -> 46752
L134: Revenue | O134: =CaseData!C15 -> 5250 | P134: =CaseData!D15 -> 5512.5 | Q134: =CaseData!E15 -> 5788.125 | R134: =CaseData!F15 -> 6077.5312 | S134: =CaseData!G15 -> 6381.4078 | T134: =CaseData!H15 -> 6700.4782 | W134: Revenue | Z134: =CaseData!C15 -> 5250 | AA134: =CaseData!D15 -> 5512.5 | AB134: =CaseData!E15 -> 5788.125 | AC134: =CaseData!F15 -> 6077.5312 | AD134: =CaseData!G15 -> 6381.4078 | AE134: =CaseData!H15 -> 6700.4782
L135: Less: COGS | O135: =CaseData!C16 -> -3150 | P135: =CaseData!D16 -> -3252.375 | Q135: =CaseData!E16 -> -3357.1125 | R135: =CaseData!F16 -> -3464.1928 | S135: =CaseData!G16 -> -3573.5884 | T135: =CaseData!H16 -> -3685.263 | W135: Less: COGS | Z135: =CaseData!C16 -> -3150 | AA135: =CaseData!D16 -> -3252.375 | AB135: =CaseData!E16 -> -3357.1125 | AC135: =CaseData!F16 -> -3464.1928 | AD135: =CaseData!G16 -> -3573.5884 | AE135: =CaseData!H16 -> -3685.263
L136: Gross Profit | O136: =SUM(O134:O135) -> 2100 | P136: =SUM(P134:P135) -> 2260.125 | Q136: =SUM(Q134:Q135) -> 2431.0125 | R136: =SUM(R134:R135) -> 2613.3384 | S136: =SUM(S134:S135) -> 2807.8194 | T136: =SUM(T134:T135) -> 3015.2152 | W136: Gross Profit | Z136: =SUM(Z134:Z135) -> 2100 | AA136: =SUM(AA134:AA135) -> 2260.125 | AB136: =SUM(AB134:AB135) -> 2431.0125 | AC136: =SUM(AC134:AC135) -> 2613.3384 | AD136: =SUM(AD134:AD135) -> 2807.8194 | AE136: =SUM(AE134:AE135) -> 3015.2152
L137: Less: SG&A | O137: =CaseData!C18 -> -262.5 | P137: =CaseData!D18 -> -275.625 | Q137: =CaseData!E18 -> -289.40625 | R137: =CaseData!F18 -> -303.87656 | S137: =CaseData!G18 -> -319.07039 | T137: =CaseData!H18 -> -335.02391 | W137: Less: SG&A | Z137: =CaseData!C18 -> -262.5 | AA137: =CaseData!D18 -> -275.625 | AB137: =CaseData!E18 -> -289.40625 | AC137: =CaseData!F18 -> -303.87656 | AD137: =CaseData!G18 -> -319.07039 | AE137: =CaseData!H18 -> -335.02391
L138: EBITDA | O138: =SUM(O136:O137) -> 1837.5 | P138: =SUM(P136:P137) -> 1984.5 | Q138: =SUM(Q136:Q137) -> 2141.6063 | R138: =SUM(R136:R137) -> 2309.4619 | S138: =SUM(S136:S137) -> 2488.749 | T138: =SUM(T136:T137) -> 2680.1913 | W138: EBITDA | Z138: =SUM(Z136:Z137) -> 1837.5 | AA138: =SUM(AA136:AA137) -> 1984.5 | AB138: =SUM(AB136:AB137) -> 2141.6063 | AC138: =SUM(AC136:AC137) -> 2309.4619 | AD138: =SUM(AD136:AD137) -> 2488.749 | AE138: =SUM(AE136:AE137) -> 2680.1913
L139: Less: Depreciation | O139: =CaseData!C20 -> -787.5 | P139: =CaseData!D20 -> -826.875 | Q139: =CaseData!E20 -> -868.21875 | R139: =CaseData!F20 -> -911.62969 | S139: =CaseData!G20 -> -957.21117 | T139: =CaseData!H20 -> -1005.0717 | W139: Less: Depreciation | Z139: =CaseData!C20 -> -787.5 | AA139: =CaseData!D20 -> -826.875 | AB139: =CaseData!E20 -> -868.21875 | AC139: =CaseData!F20 -> -911.62969 | AD139: =CaseData!G20 -> -957.21117 | AE139: =CaseData!H20 -> -1005.0717
L140: EBIT | O140: =SUM(O138:O139) -> 1050 | P140: =SUM(P138:P139) -> 1157.625 | Q140: =SUM(Q138:Q139) -> 1273.3875 | R140: =SUM(R138:R139) -> 1397.8322 | S140: =SUM(S138:S139) -> 1531.5379 | T140: =SUM(T138:T139) -> 1675.1196 | W140: EBIT | Z140: =SUM(Z138:Z139) -> 1050 | AA140: =SUM(AA138:AA139) -> 1157.625 | AB140: =SUM(AB138:AB139) -> 1273.3875 | AC140: =SUM(AC138:AC139) -> 1397.8322 | AD140: =SUM(AD138:AD139) -> 1531.5379 | AE140: =SUM(AE138:AE139) -> 1675.1196
L141: Add/(Less): Net Interest Income/(Expense) | O141: =CaseData!C22 -> -379.12932 | P141: =CaseData!D22 -> -332.43684 | Q141: =CaseData!E22 -> -285.31304 | R141: =CaseData!F22 -> -237.71581 | S141: =CaseData!G22 -> -189.61817 | T141: =CaseData!H22 -> -140.99136 | W141: Add/(Less): Net Interest Income/(Expense) | Z141: =CaseData!C22 -> -379.12932 | AA141: =CaseData!D22 -> -332.43684 | AB141: =CaseData!E22 -> -285.31304 | AC141: =CaseData!F22 -> -237.71581 | AD141: =CaseData!G22 -> -189.61817 | AE141: =CaseData!H22 -> -140.99136
L142: EBT | O142: =SUM(O140:O141) -> 670.87068 | P142: =SUM(P140:P141) -> 825.18816 | Q142: =SUM(Q140:Q141) -> 988.07446 | R142: =SUM(R140:R141) -> 1160.1164 | S142: =SUM(S140:S141) -> 1341.9197 | T142: =SUM(T140:T141) -> 1534.1282 | W142: EBT | Z142: =SUM(Z140:Z141) -> 670.87068 | AA142: =SUM(AA140:AA141) -> 825.18816 | AB142: =SUM(AB140:AB141) -> 988.07446 | AC142: =SUM(AC140:AC141) -> 1160.1164 | AD142: =SUM(AD140:AD141) -> 1341.9197 | AE142: =SUM(AE140:AE141) -> 1534.1282
L143: Less: Taxes | O143: =CaseData!C24 -> -167.71767 | P143: =CaseData!D24 -> -206.29704 | Q143: =CaseData!E24 -> -247.01861 | R143: =CaseData!F24 -> -290.02909 | S143: =CaseData!G24 -> -335.47993 | T143: =CaseData!H24 -> -383.53205 | W143: Less: Taxes | Z143: =CaseData!C24 -> -167.71767 | AA143: =CaseData!D24 -> -206.29704 | AB143: =CaseData!E24 -> -247.01861 | AC143: =CaseData!F24 -> -290.02909 | AD143: =CaseData!G24 -> -335.47993 | AE143: =CaseData!H24 -> -383.53205
...
