Workbook
Name Acquirer: CaseData!$E$8
Name debt: Merger!$F$11
Name premium: Merger!$F$14
Name Target: Merger!$F$17
Name topic: "CFM Topic: " & CaseData!$B$34

Sheet Cover
B3: CFM LEARNING MATERIALS
B8: FINANCIAL MODELING INSTITUTE
B9: LEVEL 2: CHARTERED FINANCIAL MODELER (CFM)
B13: Case Name: | C13: BoTrainers
B14: Topic 8: | C14: M&A and Subsidiaries

Sheet CaseData
B2: Sample CFM M&A Question
A3: x | B3: Case Data
B4: (in US$ millions, except per share amounts)
A6: x | B6: ACQUIRER
B8: Company Name: | E8: BoTrainers
B9: Current Share Price: | E9: 55.4
B10: Fully Diluted Shares Outstanding (mm): | E10: 119.4
B12: Deal Assumptions | G12: Income Statement | M12: Balance Sheet
I13: Last Fiscal | J13: Forecast | O13: =$I$13 -> Last Fiscal
B14: Purchase Price: | I14: Year | J14: 1 | K14: =J14+1 -> 2 | O14: =$I$14 -> Year
B15: Equity Premium | E15: 0.3 | G15: Revenues | I15: 3451.8 | J15: 3586.4 | K15: 3708.3 | M15: Cash & Equivalents | O15: 265.9
B16: % of Gross Assets Written Up | E16: 0.75 | G16: Cost of Goods Sold (ex. D&A) | I16: 1933 | J16: 2001.2 | K16: 2047 | M16: Accounts Receivable | O16: 302.6
B17: Life of Written Up Assets | E17: 12 | G17: Gross Profit | I17: =I15-I16 -> 1518.8 | J17: =J15-J16 -> 1585.2 | K17: =K15-K16 -> 1661.3 | M17: Inventories | O17: 688.5
M18: Other Current Assets | O18: 86.3
B19: Financing: | G19: SG&A Expenses (ex. D&A) | I19: 414.2 | J19: 408.8 | K19: 463.5 | M19: Total Current Assets | O19: =SUM(O15:O18) -> 1343.3
B20: % of Required Funding with New Debt | E20: 0.4 | G20: Other Expenses | I20: 172.6 | J20: 168.6 | K20: 181.7
B21: Cost of New Debt | E21: 0.06 | G21: EBITDA | I21: =I17-SUM(I19:I20) -> 932 | J21: =J17-SUM(J19:J20) -> 1007.8 | K21: =K17-SUM(K19:K20) -> 1016.1 | M21: Fixed Assets (Net) | O21: 1003.8
B22: Interest Income on Cash | E22: 0.01 | M22: Goodwill | O22: 134.5
B23: Minimum Cash on Hand at Closing | E23: 70 | G23: Depreciation & Amortization | I23: 65.2 | J23: 71.7 | K23: 77.9 | M23: Other Long-term Assets | O23: 121.7
G24: Operating Income | I24: =I21-I23 -> 866.8 | J24: =J21-J23 -> 936.1 | K24: =K21-K23 -> 938.2 | M24: Total Assets | O24: =SUM(O19:O23) -> 2603.3
B25: Fees:
B26: Debt Financing Fees (% of Amount Issued) | E26: 0.025 | G26: Interest Expense (Net) | I26: 41.9 | J26: 23.9 | K26: 11.2 | M26: Short-term Debt | O26: 55.3
B27: Other Fees (% of Target Enterprise Value) | E27: 0.005 | G27: Earnings Before Tax | I27: =I24-I26 -> 824.9 | J27: =J24-J26 -> 912.2 | K27: =K24-K26 -> 927 | M27: Accounts Payable | O27: 323
M28: Other Current Liabilities | O28: 538
B29: Other: | G29: Income Tax Expense | I29: 226.8 | J29: 232.6 | K29: 231.8 | M29: Total Current Liabilities | O29: =SUM(O26:O28) -> 916.3
B30: Combined Effective Tax Rate | E30: 0.275 | G30: Net Earnings | I30: =I27-I29 -> 598.1 | J30: =J27-J29 -> 679.6 | K30: =K27-K29 -> 695.2
M31: Long-term Debt | O31: 698.3
G32: Weighted Avg Shares OS | I32: 120.3 | J32: 119.6 | K32: 119.4 | M32: Other Liabilities | O32: 331.8
M33: Total Liabilities | O33: =SUM(O29:O32) -> 1946.4
B34: M&A | G34: Earnings Per Share | I34: =I30/I32 -> 4.9717373 | J34: =J30/J32 -> 5.6822742 | K34: =K30/K32 -> 5.8224456
M35: Shareholders' Equity | O35: 656.9
G36: Revenue Growth | I36: N/A | J36: =J15/I15-1 -> 0.038994148 | K36: =K15/J15-1 -> 0.033989516 | M36: Total Liabilities and Equity | O36: =O33+O35 -> 2603.3
G37: Gross Margin | I37: =I17/I15 -> 0.44000232 | J37: =J17/J15 -> 0.44200312 | K37: =K17/K15 -> 0.44799504
G38: SG&A % of Revenues | I38: =I19/I15 -> 0.11999536 | J38: =J19/J15 -> 0.11398617 | K38: =K19/K15 -> 0.12498989 | M38: CHECK | O38: =ROUND(O24-O36,2) -> 0
G39: Other Expenses % of Revenues | I39: =I20/I15 -> 0.050002897 | J39: =J20/J15 -> 0.04701093 | K39: =K20/K15 -> 0.048998193
G40: EBITDA Margin | I40: =I21/I15 -> 0.27000406 | J40: =J21/J15 -> 0.28100602 | K40: =K21/K15 -> 0.27400696
G41: D&A % of Revenues | I41: =I23/I15 -> 0.018888696 | J41: =J23/J15 -> 0.019992193 | K41: =K23/K15 -> 0.02100693
G42: Operating Income Margin | I42: =I24/I15 -> 0.25111536 | J42: =J24/J15 -> 0.26101383 | K42: =K24/K15 -> 0.25300003
G43: Tax Rate | I43: =I29/I27 -> 0.27494242 | J43: =J29/J27 -> 0.25498794 | K43: =K29/K27 -> 0.25005394
G44: Net Margin | I44: =I30/I15 -> 0.17327192 | J44: =J30/J15 -> 0.18949364 | K44: =K30/K15 -> 0.18747135
G46: Net Debt / EBITDA | I46: =(O26+O31-O15)/I21 -> 0.52328326 | J46: NA | K46: NA
G47: EBITDA / Net Interest Expense | I47: =I21/I26 -> 22.243437 | J47: NA | K47: NA
A51: x | B51: TARGET 1
B53: Company Name: | E53: Highpeak
B54: Current Share Price: | E54: 59.12
B55: Fully Diluted Shares Outstanding (mm): | E55: 41.2
B57: Synergy Assumptions | G57: Income Statement | M57: Balance Sheet
D58: Forecast | I58: =$I$13 -> Last Fiscal | J58: Forecast | O58: =$I$13 -> Last Fiscal
D59: =J59 -> 1 | E59: =K59 -> 2 | I59: =$I$14 -> Year | J59: 1 | K59: =J59+1 -> 2 | O59: =$I$14 -> Year
B60: Revenue Synergies | D60: 105 | E60: 125 | G60: Revenues | I60: 1691.5 | J60: 1796.4 | K60: 1877.2 | M60: Cash & Equivalents | O60: 55.2
B61: Cost of Goods Sold Synergies | D61: 30 | E61: 40 | G61: Cost of Goods Sold (ex. D&A) | I61: 1053.8 | J61: 1131.7 | K61: 1147 | M61: Accounts Receivable | O61: 213.2
B62: SG&A Synergies | D62: 60 | E62: 70 | G62: Gross Profit | I62: =I60-I61 -> 637.7 | J62: =J60-J61 -> 664.7 | K62: =K60-K61 -> 730.2 | M62: Inventories | O62: 360.8
M63: Other Current Assets | O63: 21.7
G64: SG&A Expenses (ex. D&A) | I64: 223.3 | J64: 273.1 | K64: 275.9 | M64: Total Current Assets | O64: =SUM(O60:O63) -> 650.9
G65: Other Expenses | I65: 76.8 | J65: 71.9 | K65: 71.3
G66: EBITDA | I66: =I62-SUM(I64:I65) -> 337.6 | J66: =J62-SUM(J64:J65) -> 319.7 | K66: =K62-SUM(K64:K65) -> 383 | M66: Fixed Assets (Net) | O66: 625.2
M67: Goodwill | O67: 21.4
G68: Depreciation & Amortization | I68: 43 | J68: 52.1 | K68: 52.6 | M68: Other Long-term Assets | O68: 90.5
G69: Operating Income | I69: =I66-I68 -> 294.6 | J69: =J66-J68 -> 267.6 | K69: =K66-K68 -> 330.4 | M69: Total Assets | O69: =SUM(O64:O68) -> 1388
G71: Interest Expense (Net) | I71: 27.3 | J71: 25.2 | K71: 20.1 | M71: Short-term Debt | O71: 0
G72: Earnings Before Tax | I72: =I69-I71 -> 267.3 | J72: =J69-J71 -> 242.4 | K72: =K69-K71 -> 310.3 | M72: Accounts Payable | O72: 158.7
M73: Other Current Liabilities | O73: 111.6
G74: Income Tax Expense | I74: 82.6 | J74: 73.1 | K74: 91 | M74: Total Current Liabilities | O74: =SUM(O71:O73) -> 270.3
G75: Net Earnings | I75: =I72-I74 -> 184.7 | J75: =J72-J74 -> 169.3 | K75: =K72-K74 -> 219.3
M76: Long-term Debt | O76: 546
G77: Weighted Avg Shares OS | I77: 41 | J77: 40.5 | K77: 40.4 | M77: Other Liabilities | O77: 121.3
M78: Total Liabilities | O78: =SUM(O74:O77) -> 937.6
G79: Earnings Per Share | I79: =I75/I77 -> 4.504878 | J79: =J75/J77 -> 4.1802469 | K79: =K75/K77 -> 5.4282178
M80: Shareholders' Equity | O80: 450.4
G81: Revenue Growth | I81: N/A | J81: =J60/I60-1 -> 0.062015962 | K81: =K60/J60-1 -> 0.044978847 | M81: Total Liabilities & Equity | O81: =O78+O80 -> 1388
G82: Gross Margin | I82: =I62/I60 -> 0.37700266 | J82: =J62/J60 -> 0.37001781 | K82: =K62/K60 -> 0.38898359
G83: SG&A % of Revenues | I83: =I64/I60 -> 0.13201301 | J83: =J64/J60 -> 0.15202627 | K83: =K64/K60 -> 0.14697422 | M83: CHECK | O83: =ROUND(O69-O81,2) -> 0
G84: Other Expenses % of Revenues | I84: =I65/I60 -> 0.045403488 | J84: =J65/J60 -> 0.040024493 | K84: =K65/K60 -> 0.037982101
G85: EBITDA Margin | I85: =I66/I60 -> 0.19958617 | J85: =J66/J60 -> 0.17796705 | K85: =K66/K60 -> 0.20402727
G86: D&A % of Revenues | I86: =I68/I60 -> 0.025421224 | J86: =J68/J60 -> 0.029002449 | K86: =K68/K60 -> 0.028020456
G87: Operating Income Margin | I87: =I69/I60 -> 0.17416494 | J87: =J69/J60 -> 0.1489646 | K87: =K69/K60 -> 0.17600682
G88: Tax Rate | I88: =I74/I72 -> 0.30901609 | J88: =J74/J72 -> 0.30156766 | K88: =K74/K72 -> 0.29326458
G89: Net Margin | I89: =I75/I60 -> 0.10919302 | J89: =J75/J60 -> 0.094244044 | K89: =K75/K60 -> 0.11682293
G91: Net Debt / EBITDA | I91: =(O71+O76-O60)/I66 -> 1.4537915 | J91: NA | K91: NA
G92: EBITDA / Net Interest Expense | I92: =I66/I71 -> 12.3663 | J92: NA | K92: NA
A96: x | B96: TARGET 2
B98: Company Name: | E98: NoLace
B99: Equity Value: | E99: 2900
B101: Synergy Assumptions | G101: Income Statement | M101: Balance Sheet
D102: Forecast | I102: =$I$13 -> Last Fiscal | J102: Forecast | O102: =$I$13 -> Last Fiscal
D103: =J103 -> 1 | E103: =K103 -> 2 | I103: =$I$14 -> Year | J103: 1 | K103: =J103+1 -> 2 | O103: =$I$14 -> Year
B104: Revenue Synergies | D104: 20 | E104: 25 | G104: Revenues | I104: 2144.2 | J104: 2320 | K104: 2440.6 | M104: Cash & Equivalents | O104: 334.2
B105: Cost of Goods Sold Synergies | D105: 40 | E105: 55 | G105: Cost of Goods Sold (ex. D&A) | I105: 879.1 | J105: 967.4 | K105: 1000.6 | M105: Accounts Receivable | O105: 317.2
B106: SG&A Synergies | D106: 15 | E106: 25 | G106: Gross Profit | I106: =I104-I105 -> 1265.1 | J106: =J104-J105 -> 1352.6 | K106: =K104-K105 -> 1440 | M106: Inventories | O106: 206.9
M107: Other Current Assets | O107: 44.4
G108: SG&A Expenses (ex. D&A) | I108: 243.1 | J108: 241.3 | K108: 248.9 | M108: Total Current Assets | O108: =SUM(O104:O107) -> 902.7
G109: Other Expenses | I109: 12.1 | J109: 23.2 | K109: 24.4
G110: EBITDA | I110: =I106-SUM(I108:I109) -> 1009.9 | J110: =J106-SUM(J108:J109) -> 1088.1 | K110: =K106-SUM(K108:K109) -> 1166.7 | M110: Fixed Assets (Net) | O110: 1196.8
M111: Goodwill | O111: 100.3
G112: Depreciation & Amortization | I112: 74.8 | J112: 88.2 | K112: 97.6 | M112: Other Long-term Assets | O112: 452.1
G113: Operating Income | I113: =I110-I112 -> 935.1 | J113: =J110-J112 -> 999.9 | K113: =K110-K112 -> 1069.1 | M113: Total Assets | O113: =SUM(O108:O112) -> 2651.9
G115: Interest Expense (Net) | I115: 143.7 | J115: 144.1 | K115: 124.8 | M115: Short-term Debt | O115: 55.9
G116: Earnings Before Tax | I116: =I113-I115 -> 791.4 | J116: =J113-J115 -> 855.8 | K116: =K113-K115 -> 944.3 | M116: Accounts Payable | O116: 168.6
M117: Other Current Liabilities | O117: 200.1
G118: Income Tax Expense | I118: 216.4 | J118: 231.9 | K118: 255.9 | M118: Total Current Liabilities | O118: =SUM(O114:O117) -> 424.6
...

Sheet Merger
A1: =Acquirer -> BoTrainers
A2: {=topic} -> CFM Topic: M&A
A3: MERGER MODEL | F3: Constant | G3: Unit
A5: Assumptions
C7: Acquirer
E8: Acquirer | F8: =Acquirer -> BoTrainers | G8: label
E9: =CaseData!B$9 -> Current Share Price: | F9: =CaseData!E$9 -> 55.4 | G9: USD
E10: =CaseData!B$16 -> % of Gross Assets Written Up | F10: =CaseData!E$16 -> 0.75 | G10: %
E11: =CaseData!B$20 -> % of Required Funding with New Debt | F11: =CaseData!E$20 -> 0.4 | G11: %
E12: =CaseData!B$23 -> Minimum Cash on Hand at Closing | F12: =CaseData!E$23 -> 70 | G12: USD m
E13: =CaseData!B$17 -> Life of Written Up Assets | F13: =CaseData!E$17 -> 12 | G13: years
E14: =CaseData!B$15 -> Equity Premium | F14: =CaseData!E$15 -> 0.3 | G14: %
C16: Target
E17: Target | F17: Highpeak | G17: label
E18: =CaseData!B$21 -> Cost of New Debt | F18: =CaseData!E$21 -> 0.06 | G18: %
E19: =CaseData!B$22 -> Interest Income on Cash | F19: =CaseData!E$22 -> 0.01 | G19: %
E20: =CaseData!B$26 -> Debt Financing Fees (% of Amount Issued) | F20: =CaseData!E$26 -> 0.025 | G20: %
E21: =CaseData!B$27 -> Other Fees (% of Target Enterprise Value) | F21: =CaseData!E$27 -> 0.005 | G21: %
E22: =CaseData!B$30 -> Combined Effective Tax Rate | F22: =CaseData!E$30 -> 0.275 | G22: %
A25: Purchase Price Allocation
C27: Goodwill
D29: Purchase price of Equity
E30: Pre-acquisition Equity Value | F30: =INDEX( TargetData!$E$9:$E$55, MATCH( RIGHT( Merger!$E30, 12 ), TargetData!$B$9:$B$55, 0 ), 1 ) -> 2435.744 | G30: USD m
E31: =E$14 -> Equity Premium | F31: =F$14 -> 0.3 | G31: %
E32: Purchase Price of Equity | F32: =F30 * ( 1 + F31 ) -> 3166.4672 | G32: USD m
D34: Enterprise Value
D35: plus | E35: Short-term Debt | F35: =IF( INDEX( TargetData!$E$9:$E$55, MATCH( $E35, TargetData!$B$9:$B$55, 0 ), 1 ) = "", 0, INDEX( TargetData!$E$9:$E$55, MATCH( $E35, TargetData!$B$9:$B$55, 0 ), 1 ) ) -> 0 | G35: USD m
D36: plus | E36: Long-term Debt | F36: =IF( INDEX( TargetData!$E$9:$E$55, MATCH( $E36, TargetData!$B$9:$B$55, 0 ), 1 ) = "", 0, INDEX( TargetData!$E$9:$E$55, MATCH( $E36, TargetData!$B$9:$B$55, 0 ), 1 ) ) -> 546 | G36: USD m
D37: less | E37: Cash & Equivalents | F37: =IF( INDEX( TargetData!$E$9:$E$55, MATCH( $E37, TargetData!$B$9:$B$55, 0 ), 1 ) = "", 0, - INDEX( TargetData!$E$9:$E$55, MATCH( $E37, TargetData!$B$9:$B$55, 0 ), 1 ) ) -> -55.2 | G37: USD m
E38: Enterprise Value | F38: =SUM(F32:F37) -> 3657.2672 | G38: USD m
D40: Fair Market Value of Net Assets
E41: Total assets | F41: =IF( INDEX( TargetData!$E$9:$E$55, MATCH( $E41, TargetData!$B$9:$B$55, 0 ), 1 ) = "", 0, INDEX( TargetData!$E$9:$E$55, MATCH( $E41, TargetData!$B$9:$B$55, 0 ), 1 ) ) -> 1388 | G41: USD m
D42: plus | E42: Assets Write-Ups | F42: =F41 * F10 -> 1041 | G42: USD m
D43: less | E43: Goodwill | F43: =IF( INDEX( TargetData!$E$9:$E$55, MATCH( $E43, TargetData!$B$9:$B$55, 0 ), 1 ) = "", 0, - INDEX( TargetData!$E$9:$E$55, MATCH( $E43, TargetData!$B$9:$B$55, 0 ), 1 ) ) -> -21.4 | G43: USD m
D44: less | E44: Total liabilities | F44: =IF( INDEX( TargetData!$E$9:$E$55, MATCH( $E44, TargetData!$B$9:$B$55, 0 ), 1 ) = "", 0, - INDEX( TargetData!$E$9:$E$55, MATCH( $E44, TargetData!$B$9:$B$55, 0 ), 1 ) ) -> -937.6 | G44: USD m
D45: less | E45: Deferred tax liabilities | F45: =- $F$42 * $F$22 -> -286.275 | G45: USD m
E46: Fair Market Value of Net Assets | F46: =SUM(F41:F45) -> 1183.725 | G46: USD m
D48: Goodwill
E49: =E$32 -> Purchase Price of Equity | F49: =F$32 -> 3166.4672 | G49: =G$32 -> USD m
D50: less | E50: =E$46 -> Fair Market Value of Net Assets | F50: =F$46 -> 1183.725 | G50: =G$46 -> USD m
E51: Goodwill | F51: =F49 - F50 -> 1982.7422 | G51: =G$46 -> USD m
A54: Sources and Uses of Funds
D56: Sources of Funds
E57: Cash & Equivalents | F57: =_xlfn.LET( _xlpm.acquirer_cash, CaseData!$O$15, _xlpm.target_cash, TargetData!$E$37, _xlpm.min_balance, Merger!$F$12, _xlpm.acquirer_cash + _xlpm.target_cash - _xlpm.min_balance ) -> 251.1 | G57: USD m
E58: Debt | F58: =_xlfn.LET( _xlpm.source_of_funds, $F$60, _xlpm.cash, $F$57, _xlpm.debt_percentage, $F$11, ( _xlpm.source_of_funds - _xlpm.cash ) * _xlpm.debt_percentage ) -> 1405.7069 | G58: USD m
E59: Equity | F59: =_xlfn.LET( _xlpm.sources, $F$60, _xlpm.cash, $F$57, _xlpm.debt, $F$58, _xlpm.sources - ( _xlpm.cash + _xlpm.debt ) ) -> 2108.5603 | G59: USD m
E60: Sources of Funds | F60: =$F$68 -> 3765.3672 | G60: USD m
D62: Uses of Funds
E63: Purchase of Target Equity | F63: =$F32 -> 3166.4672 | G63: USD m
E64: Refinincing of Target Short-term Debt | F64: =F35 -> 0 | G64: USD m
E65: Refinincing of Target Long-term Debt | F65: =F36 -> 546 | G65: USD m
E66: Debt Financing Fees | F66: =_xlfn.LET( _xlpm.purchase_cost, $F$63, _xlpm.ST_debt, $F$64, _xlpm.LT_debt, $F$65, _xlpm.cash, $F$57, _xlpm.debt_percentage, $F$11, _xlpm.debt_fees, $F$20, ( _xlpm.purchase_cost + _xlpm.ST_debt + _xlpm.LT_debt - _xlpm.cash ) * _xlpm.debt_percentage * _xlpm.debt_fees ) -> 34.613672 | G66: USD m
E67: Other Fees | F67: =$F$38 * $F$21 -> 18.286336 | G67: USD m
E68: Uses of Funds | F68: =SUM(F63:F67) -> 3765.3672 | G68: USD m
E71: Shares issued | F71: =_xlfn.LET( _xlpm.equity, $F$59, _xlpm.acquirer_share_price, $F$9, _xlpm.equity / _xlpm.acquirer_share_price ) -> 38.060656 | G71: shares m
A74: Pro Forma Financial Statements
C76: Income Statement
F78: Forecast Year 1 | K78: Forecast Year 2
F79: =Acquirer -> BoTrainers | G79: =Target -> Highpeak | H79: Adjustment | I79: =Acquirer & " Pro Forma" -> BoTrainers Pro Forma | K79: =Acquirer -> BoTrainers | L79: =Target -> Highpeak | M79: Adjustment | N79: =Acquirer & " Pro Forma" -> BoTrainers Pro Forma
E81: Revenues | F81: =_xlfn.XLOOKUP( $E81, CaseData!$G$15:$G$30, CaseData!$J$15:$J$30,,0 ) -> 3586.4 | G81: =_xlfn.XLOOKUP( $E81, TargetData!$B$16:$B$23, TargetData!$E$16:$E$23,, 0 ) -> 1796.4 | H81: =TargetData!$E21 -> 105 | I81: =SUM(F81:H81) -> 5487.8 | K81: =_xlfn.XLOOKUP( $E81, CaseData!$G$15:$G$30, CaseData!$K$15:$K$30,,0 ) -> 3708.3 | L81: =_xlfn.XLOOKUP( $E81, TargetData!$B$26:$B$33, TargetData!$E$26:$E$33,, 0 ) -> 1877.2 | M81: =TargetData!$E$31 -> 125 | N81: =SUM(K81:M81) -> 5710.5
E82: Cost of Goods Sold (ex. D&A) | F82: =_xlfn.XLOOKUP( $E82, CaseData!$G$15:$G$30, CaseData!$J$15:$J$30,,0 ) * -1 -> -2001.2 | G82: =_xlfn.XLOOKUP( $E82, TargetData!$B$16:$B$23, TargetData!$E$16:$E$23,, 0 ) * -1 -> -1131.7 | H82: =TargetData!$E22 * - 1 -> -30 | I82: =SUM( F82:G82 ) - H82 -> -3102.9 | K82: =_xlfn.XLOOKUP( $E82, CaseData!$G$15:$G$30, CaseData!$K$15:$K$30,,0 ) * - 1 -> -2047 | L82: =_xlfn.XLOOKUP( $E82, TargetData!$B$26:$B$33, TargetData!$E$26:$E$33,, 0 ) * - 1 -> -1147 | M82: =TargetData!$E$32 * - 1 -> -40 | N82: =SUM( K82:L82 ) - M82 -> -3154
E83: Gross Profit | F83: =SUM(F81:F82) -> 1585.2 | G83: =SUM(G81:G82) -> 664.7 | H83: =H81 - H82 -> 135 | I83: =SUM(I81:I82) -> 2384.9 | K83: =SUM(K81:K82) -> 1661.3 | L83: =SUM(L81:L82) -> 730.2 | M83: =M81 - M82 -> 165 | N83: =SUM(N81:N82) -> 2556.5
E85: SG&A Expenses (ex. D&A) | F85: =_xlfn.XLOOKUP( $E85, CaseData!$G$15:$G$30, CaseData!$J$15:$J$30,,0 ) * -1 -> -408.8 | G85: =_xlfn.XLOOKUP( $E85, TargetData!$B$16:$B$23, TargetData!$E$16:$E$23,, 0 ) * -1 -> -273.1 | H85: =TargetData!$E23 * - 1 -> -60 | I85: =SUM( F85:G85 ) - H85 -> -621.9 | K85: =_xlfn.XLOOKUP( $E85, CaseData!$G$15:$G$30, CaseData!$K$15:$K$30,,0 ) * - 1 -> -463.5 | L85: =_xlfn.XLOOKUP( $E85, TargetData!$B$26:$B$33, TargetData!$E$26:$E$33,, 0 ) * - 1 -> -275.9 | M85: =TargetData!$E$33 * - 1 -> -70 | N85: =SUM( K85:L85 ) - M85 -> -669.4
E86: Other Expenses | F86: =_xlfn.XLOOKUP( $E86, CaseData!$G$15:$G$30, CaseData!$J$15:$J$30,,0 ) * -1 -> -168.6 | G86: =_xlfn.XLOOKUP( $E86, TargetData!$B$16:$B$23, TargetData!$E$16:$E$23,, 0 ) * -1 -> -71.9 | I86: =SUM(F86:H86) -> -240.5 | K86: =_xlfn.XLOOKUP( $E86, CaseData!$G$15:$G$30, CaseData!$K$15:$K$30,,0 ) * - 1 -> -181.7 | L86: =_xlfn.XLOOKUP( $E86, TargetData!$B$26:$B$33, TargetData!$E$26:$E$33,, 0 ) * - 1 -> -71.3 | N86: =SUM(K86:M86) -> -253
E87: EBITDA | F87: =SUM(F83:F86) -> 1007.8 | G87: =SUM(G83:G86) -> 319.7 | H87: =H83 - H85 -> 195 | I87: =SUM(I83:I86) -> 1522.5 | K87: =SUM(K83:K86) -> 1016.1 | L87: =SUM(L83:L86) -> 383 | M87: =M83 - M85 -> 235 | N87: =SUM(N83:N86) -> 1634.1
E89: Depreciation & Amortization | F89: =_xlfn.XLOOKUP( $E89, CaseData!$G$15:$G$30, CaseData!$J$15:$J$30,,0 ) * -1 -> -71.7 | G89: =_xlfn.XLOOKUP( $E89, TargetData!$B$16:$B$23, TargetData!$E$16:$E$23,, 0 ) * -1 -> -52.1 | H89: =_xlfn.LET( _xlpm.assets_write_ups, $F$42, _xlpm.life_of_assets, $F$13, _xlpm.assets_write_ups / _xlpm.life_of_assets * - 1 ) -> -86.75 | I89: =SUM(F89:H89) -> -210.55 | K89: =_xlfn.XLOOKUP( $E89, CaseData!$G$15:$G$30, CaseData!$K$15:$K$30,,0 ) * - 1 -> -77.9 | L89: =_xlfn.XLOOKUP( $E89, TargetData!$B$26:$B$33, TargetData!$E$26:$E$33,, 0 ) * - 1 -> -52.6 | M89: =_xlfn.LET( _xlpm.assets_write_ups, $F$42, _xlpm.life_of_assets, $F$13, _xlpm.assets_write_ups / _xlpm.life_of_assets * - 1 ) -> -86.75 | N89: =SUM(K89:M89) -> -217.25
E90: Operating Income | F90: =SUM(F87:F89) -> 936.1 | G90: =SUM(G87:G89) -> 267.6 | H90: =SUM(H87:H89) -> 108.25 | I90: =SUM(I87:I89) -> 1311.95 | K90: =SUM(K87:K89) -> 938.2 | L90: =SUM(L87:L89) -> 330.4 | M90: =SUM(M87:M89) -> 148.25 | N90: =SUM(N87:N89) -> 1416.85
E92: Interest Expense (Net) | F92: =_xlfn.XLOOKUP( $E92, CaseData!$G$15:$G$30, CaseData!$J$15:$J$30,,0 ) * -1 -> -23.9 | G92: =NA() -> #N/A | H92: =_xlfn.LET( _xlpm.acquirer_new_debt, $F$58, _xlpm.interest_rate, $F$18, _xlpm.cash_balance, $F$110 - $I$110, _xlpm.interest_earned, $F$19, ( _xlpm.acquirer_new_debt * _xlpm.interest_rate * - 1 ) + ( _xlpm.cash_balance * _xlpm.interest_earned ) ) -> -82.383413 | I92: =SUM( F92, H92) -> -106.28341 | K92: =_xlfn.XLOOKUP( $E92, CaseData!$G$15:$G$30, CaseData!$K$15:$K$30,,0 ) * - 1 -> -11.2 | L92: =NA() -> #N/A | M92: =H92 -> -82.383413 | N92: =SUM( K92, M92) -> -93.583413
E93: Earnings Before Tax | F93: =SUM(F90:F92) -> 912.2 | G93: =NA() -> #N/A | H93: =SUM(H90:H92) -> 25.866587 | I93: =SUM(I90:I92) -> 1205.6666 | K93: =SUM(K90:K92) -> 927 | L93: =NA() -> #N/A | M93: =SUM(M90:M92) -> 65.866587 | N93: =SUM(N90:N92) -> 1323.2666
E95: Income Tax Expense | F95: =_xlfn.XLOOKUP( $E95, CaseData!$G$15:$G$30, CaseData!$J$15:$J$30,,0 ) * -1 -> -232.6 | G95: =NA() -> #N/A | H95: =( F95 + I93 * $F$22 ) * - 1 -> -98.958311 | I95: =SUM( F95, H95 ) -> -331.55831 | K95: =_xlfn.XLOOKUP( $E95, CaseData!$G$15:$G$30, CaseData!$K$15:$K$30,,0 ) * - 1 -> -231.8 | L95: =NA() -> #N/A | M95: =( K95 + N93 * $F$22 ) * - 1 -> -132.09831 | N95: =SUM( K95, M95 ) -> -363.89831
E96: Net Earnings | F96: =SUM(F93:F95) -> 679.6 | G96: =NA() -> #N/A | H96: =H93 - H95 -> 124.8249 | I96: =SUM(I93:I95) -> 874.10828 | K96: =SUM(K93:K95) -> 695.2 | L96: =NA() -> #N/A | M96: =SUM(M93:M95) -> -66.231724 | N96: =SUM(N93:N95) -> 959.36828
E99: Weighted average shares outstanding | F99: =CaseData!$E$10 -> 119.4 | G99: =NA() -> #N/A | H99: =$F$71 -> 38.060656 | I99: =SUM( F99, H99) -> 157.46066
E100: Earnings per share | F100: =F96 / F99 -> 5.6917923 | I100: =I96 / I99 -> 5.5512806 | K100: =K96 / F99 -> 5.8224456 | N100: =N96 / I99 -> 6.0927491
E101: Accredtion / dilution (USD) | I101: =I100 - F100 -> -0.14051174 | N101: =N100 - K100 -> 0.27030359
E102: Accredtion / dilution (%) | I102: =I101 / F100 -> -0.024686731 | N102: =N101 / K100 -> 0.046424408
C105: Closing Balance Sheet
F108: =Acquirer -> BoTrainers | G108: =Target -> Highpeak | H108: Adjustment | I108: =Acquirer & " Pro Forma" -> BoTrainers Pro Forma
E110: Cash & Equivalents | F110: =_xlfn.XLOOKUP( $E110, CaseData!$M$15:$M$36, CaseData!$O$15:$O$36,,0 ) -> 265.9 | G110: =_xlfn.XLOOKUP( $E110, TargetData!$B$9:$B$55, TargetData!$E$9:$E$55,,0 ) -> 55.2 | H110: =_xlfn.LET( _xlpm.acquirer_cash, $F$110, _xlpm.target_cash, $G$110, _xlpm.minimum_balance, $F$12, ( _xlpm.acquirer_cash + _xlpm.target_cash - _xlpm.minimum_balance ) * - 1 ) -> -251.1 | I110: =SUM(F110:H110) -> 70
E111: Accounts Receivable | F111: =_xlfn.XLOOKUP( $E111, CaseData!$M$15:$M$36, CaseData!$O$15:$O$36,,0 ) -> 302.6 | G111: =_xlfn.XLOOKUP( $E111, TargetData!$B$9:$B$55, TargetData!$E$9:$E$55,,0 ) -> 213.2 | I111: =SUM(F111:H111) -> 515.8
E112: Inventories | F112: =_xlfn.XLOOKUP( $E112, CaseData!$M$15:$M$36, CaseData!$O$15:$O$36,,0 ) -> 688.5 | G112: =_xlfn.XLOOKUP( $E112, TargetData!$B$9:$B$55, TargetData!$E$9:$E$55,,0 ) -> 360.8 | I112: =SUM(F112:H112) -> 1049.3
E113: Other Current Assets | F113: =_xlfn.XLOOKUP( $E113, CaseData!$M$15:$M$36, CaseData!$O$15:$O$36,,0 ) -> 86.3 | G113: =_xlfn.XLOOKUP( $E113, TargetData!$B$9:$B$55, TargetData!$E$9:$E$55,,0 ) -> 21.7 | I113: =SUM(F113:H113) -> 108
E114: Total Current Assets | F114: =_xlfn.XLOOKUP( $E114, CaseData!$M$15:$M$36, CaseData!$O$15:$O$36,,0 ) -> 1343.3 | G114: =SUM(G110:G113) -> 650.9 | H114: =SUM(H110:H113) -> -251.1 | I114: =SUM(I110:I113) -> 1743.1
E116: Fixed Assets (Net) | F116: =_xlfn.XLOOKUP( $E116, CaseData!$M$15:$M$36, CaseData!$O$15:$O$36,,0 ) -> 1003.8 | G116: =_xlfn.XLOOKUP( $E116, TargetData!$B$9:$B$55, TargetData!$E$9:$E$55,,0 ) -> 625.2 | H116: 0 | I116: =SUM(F116:H116) -> 1629
E117: Goodwill | F117: =_xlfn.XLOOKUP( $E117, CaseData!$M$15:$M$36, CaseData!$O$15:$O$36,,0 ) -> 134.5 | G117: =_xlfn.XLOOKUP( $E117, TargetData!$B$9:$B$55, TargetData!$E$9:$E$55,,0 ) -> 21.4 | H117: =_xlfn.LET( _xlpm.new_goodwill, $F$51, _xlpm.target_goodwill, $G$117, _xlpm.new_goodwill - _xlpm.target_goodwill ) -> 1961.3422 | I117: =SUM(F117:H117) -> 2117.2422
E118: Other Long-term Assets | F118: =_xlfn.XLOOKUP( $E118, CaseData!$M$15:$M$36, CaseData!$O$15:$O$36,,0 ) -> 121.7 | G118: =_xlfn.XLOOKUP( $E118, TargetData!$B$9:$B$55, TargetData!$E$9:$E$55,,0 ) -> 90.5 | H118: =_xlfn.LET( _xlpm.assets_write_ups, $F$42, _xlpm.assets_write_ups ) -> 1041 | I118: =SUM(F118:H118) -> 1253.2
E119: Total Assets | F119: =_xlfn.XLOOKUP( $E119, CaseData!$M$15:$M$36, CaseData!$O$15:$O$36,,0 ) -> 2603.3 | G119: =SUM(G114:G118) -> 1388 | H119: =SUM(H114:H118) -> 2751.2422 | I119: =SUM(I114:I118) -> 6742.5422
E121: Short-term Debt | F121: =_xlfn.XLOOKUP( $E121, CaseData!$M$15:$M$36, CaseData!$O$15:$O$36,,0 ) -> 55.3 | G121: =IF( _xlfn.XLOOKUP( $E121, TargetData!$B$9:$B$55, TargetData!$E$9:$E$55,,0 ) <> "", _xlfn.XLOOKUP( $E121, TargetData!$B$9:$B$55, TargetData!$E$9:$E$55,,0 ), 0 ) -> 0 | H121: =_xlfn.LET( _xlpm.ST_debt, $F$64, -_xlpm.ST_debt ) -> 0 | I121: =SUM(F121:H121) -> 55.3
E122: Accounts Payable | F122: =_xlfn.XLOOKUP( $E122, CaseData!$M$15:$M$36, CaseData!$O$15:$O$36,,0 ) -> 323 | G122: =_xlfn.XLOOKUP( $E122, TargetData!$B$9:$B$55, TargetData!$E$9:$E$55,,0 ) -> 158.7 | H122: 0 | I122: =SUM(F122:H122) -> 481.7
E123: Other Current Liabilities | F123: =_xlfn.XLOOKUP( $E123, CaseData!$M$15:$M$36, CaseData!$O$15:$O$36,,0 ) -> 538 | G123: =_xlfn.XLOOKUP( $E123, TargetData!$B$9:$B$55, TargetData!$E$9:$E$55,,0 ) -> 111.6 | H123: 0 | I123: =SUM(F123:H123) -> 649.6
E124: Total Current Liabilities | F124: =_xlfn.XLOOKUP( $E124, CaseData!$M$15:$M$36, CaseData!$O$15:$O$36,,0 ) -> 916.3 | G124: =SUM(G121:G123) -> 270.3 | H124: =SUM(H121:H123) -> 0 | I124: =SUM(I121:I123) -> 1186.6
E126: Long-term Debt | F126: =_xlfn.XLOOKUP( $E126, CaseData!$M$15:$M$36, CaseData!$O$15:$O$36,,0 ) -> 698.3 | G126: =_xlfn.XLOOKUP( $E126, TargetData!$B$9:$B$55, TargetData!$E$9:$E$55,,0 ) -> 546 | H126: =_xlfn.LET( _xlpm.new_LT_debt, $F$58, _xlpm.target_LT_debt, $G$126, _xlpm.new_LT_debt - _xlpm.target_LT_debt ) -> 859.70688 | I126: =SUM(F126:H126) -> 2104.0069
E127: Other Liabilities | F127: =_xlfn.XLOOKUP( $E127, CaseData!$M$15:$M$36, CaseData!$O$15:$O$36,,0 ) -> 331.8 | G127: =_xlfn.XLOOKUP( $E127, TargetData!$B$9:$B$55, TargetData!$E$9:$E$55,,0 ) -> 121.3 | H127: =_xlfn.LET( _xlpm.deferred_tax_liabilities, $F$45, _xlpm.deferred_tax_liabilities * - 1 ) -> 286.275 | I127: =SUM(F127:H127) -> 739.375
E128: Total Liabilities | F128: =_xlfn.XLOOKUP( $E128, CaseData!$M$15:$M$36, CaseData!$O$15:$O$36,,0 ) -> 1946.4 | G128: =SUM(G126:G127) -> 667.3 | H128: =SUM(H124:H127) -> 1145.9819 | I128: =SUM(I124:I127) -> 4029.9819
E130: Shareholders' Equity | F130: =_xlfn.XLOOKUP( $E130, CaseData!$M$15:$M$36, CaseData!$O$15:$O$36,,0 ) -> 656.9 | G130: =_xlfn.XLOOKUP( $E130, TargetData!$B$9:$B$55, TargetData!$E$9:$E$55,,0 ) -> 450.4 | H130: =_xlfn.LET( _xlpm.acquirer_equity, $F$59, _xlpm.target_equity, $G$130, _xlpm.debt_fees, $F$66, _xlpm.other_fees, $F$67, _xlpm.acquirer_equity - _xlpm.target_equity - _xlpm.debt_fees - _xlpm.other_fees ) -> 1605.2603 | I130: =SUM(F130:H130) -> 2712.5603
E131: Total Liabilities and Equity | F131: =_xlfn.XLOOKUP( $E131, CaseData!$M$15:$M$36, CaseData!$O$15:$O$36,,0 ) -> 2603.3 | G131: =_xlfn.XLOOKUP( $E131, TargetData!$B$9:$B$55, TargetData!$E$9:$E$55,,0 ) -> 1388 | H131: =SUM(H128:H130) -> 2751.2422 | I131: =SUM(I128:I130) -> 6742.5422
E134: Net Debt / Year 1 EBIDTA | F134: =( F121 + F126 - F110 ) / F87 -> 0.48392538 | I134: =( I121 + I126 - I110 ) / I87 -> 1.372287
E135: Year 1 EBIDTA / Net Interest Expenses | F135: =F87 / - F92 -> 42.167364 | I135: =I87 / - I92 -> 14.324907
A138: Sensitivity Analysis
D140: Equity premium
F141: Forecast Year 1 | K141: Forecast Year 2
...

Sheet TargetData
B2: Sample CFM M&A Question
B3: Target Data Selector
B4: (in US$ millions, except per share amounts)
E6: LIVE TARGET | G6: =CaseData!B51 -> TARGET 1 | H6: =CaseData!B96 -> TARGET 2
B7: COMPANY NAME | E7: =Target -> Highpeak | G7: =CaseData!E$53 -> Highpeak | H7: =CaseData!$E$98 -> NoLace
B9: SHARE CAPITAL
B10: Current Share Price | E10: {=IF( _xlfn.XLOOKUP( $E$7, $G$7:$H$7,G10:H55) > 0, _xlfn.XLOOKUP( $E$7, $G$7:$H$7,G10:H55), "" )} -> 59.12 | G10: =CaseData!E$54 -> 59.12 | H10: NA
B11: Fully Diluted Shares Outstanding (mm) | E11: 41.2 | G11: =CaseData!E$55 -> 41.2 | H11: NA
B12: Equity Value | E12: 2435.744 | G12: =G10 * G11 -> 2435.744 | H12: =CaseData!$E$99 -> 2900
B14: INCOME STATEMENT
B15: ="Forecast Year "&CaseData!J14 -> Forecast Year 1
B16: Revenues | E16: 1796.4 | G16: =CaseData!J60 -> 1796.4 | H16: =CaseData!J104 -> 2320
B17: Cost of Goods Sold (ex. D&A) | E17: 1131.7 | G17: =CaseData!J61 -> 1131.7 | H17: =CaseData!J105 -> 967.4
B18: SG&A Expenses (ex. D&A) | E18: 273.1 | G18: =CaseData!J64 -> 273.1 | H18: =CaseData!J108 -> 241.3
B19: Other Expenses | E19: 71.9 | G19: =CaseData!J65 -> 71.9 | H19: =CaseData!J109 -> 23.2
B20: Depreciation & Amortization | E20: 52.1 | G20: =CaseData!$J$68 -> 52.1 | H20: =CaseData!$J$112 -> 88.2
B21: Revenue Synergies | E21: 105 | G21: =CaseData!$D$60 -> 105 | H21: =CaseData!D104 -> 20
B22: Cost of Goods Sold Synergies | E22: 30 | G22: =CaseData!$D$61 -> 30 | H22: =CaseData!D105 -> 40
B23: SG&A Synergies | E23: 60 | G23: =CaseData!$D$62 -> 60 | H23: =CaseData!D106 -> 15
B25: ="Forecast Year "&CaseData!K14 -> Forecast Year 2
B26: Revenues | E26: 1877.2 | G26: =CaseData!K60 -> 1877.2 | H26: =CaseData!K104 -> 2440.6
B27: Cost of Goods Sold (ex. D&A) | E27: 1147 | G27: =CaseData!K61 -> 1147 | H27: =CaseData!K105 -> 1000.6
B28: SG&A Expenses (ex. D&A) | E28: 275.9 | G28: =CaseData!K64 -> 275.9 | H28: =CaseData!K108 -> 248.9
B29: Other Expenses | E29: 71.3 | G29: =CaseData!K65 -> 71.3 | H29: =CaseData!K109 -> 24.4
B30: Depreciation & Amortization | E30: 52.6 | G30: =CaseData!$K$68 -> 52.6 | H30: =CaseData!$K$112 -> 97.6
B31: Revenue Synergies | E31: 125 | G31: =CaseData!E60 -> 125 | H31: =CaseData!E104 -> 25
B32: Cost of Goods Sold Synergies | E32: 40 | G32: =CaseData!E61 -> 40 | H32: =CaseData!E105 -> 55
B33: SG&A Synergies | E33: 70 | G33: =CaseData!E62 -> 70 | H33: =CaseData!E106 -> 25
B35: HISTORICAL BALANCE SHEET
B36: Assets
B37: Cash & Equivalents | E37: 55.2 | G37: =CaseData!O60 -> 55.2 | H37: =CaseData!O104 -> 334.2
B38: Accounts Receivable | E38: 213.2 | G38: =CaseData!O61 -> 213.2 | H38: =CaseData!O105 -> 317.2
B39: Inventories | E39: 360.8 | G39: =CaseData!O62 -> 360.8 | H39: =CaseData!O106 -> 206.9
B40: Other Current Assets | E40: 21.7 | G40: =CaseData!O63 -> 21.7 | H40: =CaseData!O107 -> 44.4
B41: Fixed Assets (Net) | E41: 625.2 | G41: =CaseData!O66 -> 625.2 | H41: =CaseData!O110 -> 1196.8
B42: Goodwill | E42: 21.4 | G42: =CaseData!O67 -> 21.4 | H42: =CaseData!O111 -> 100.3
B43: Other Long-term Assets | E43: 90.5 | G43: =CaseData!O68 -> 90.5 | H43: =CaseData!O112 -> 452.1
B44: Total Assets | E44: 1388 | G44: =SUM(G37:G43) -> 1388 | H44: =SUM(H37:H43) -> 2651.9
B46: Liabilities and Equity
B47: Short-term Debt | G47: =CaseData!O71 -> 0 | H47: =CaseData!O115 -> 55.9
B48: Accounts Payable | E48: 158.7 | G48: =CaseData!O72 -> 158.7 | H48: =CaseData!O116 -> 168.6
B49: Other Current Liabilities | E49: 111.6 | G49: =CaseData!O73 -> 111.6 | H49: =CaseData!O117 -> 200.1
B50: Long-term Debt | E50: 546 | G50: =CaseData!O76 -> 546 | H50: =CaseData!O120 -> 1796.2
B51: Other Liabilities | E51: 121.3 | G51: =CaseData!O77 -> 121.3 | H51: =CaseData!O121 -> 176.6
B52: Total Liabilities | E52: 937.6 | G52: =SUM(G47:G51) -> 937.6 | H52: =SUM(H47:H51) -> 2397.4
B54: Shareholders' Equity | E54: 450.4 | G54: =CaseData!$O$80 -> 450.4 | H54: =CaseData!$O$124 -> 254.5
B55: Total Liabilities and Equity | E55: 1388 | G55: =SUM(G52:G54) -> 1388 | H55: =SUM(H52:H54) -> 2651.9
