Workbook
Name company: Input!$F$151
Name scenarios: Input!$F$154:$F$183
Name selector: Output!$I$6
Name topic: "CFM Topic: " &Input!$F$152

Sheet Output
A1: =company -> Rock Climbing Inc
A2: {=topic} -> CFM Topic: Sensitivity Analysis
A3: OUTPUT SCHEDULE
F6: Selector | I6: 18
F7: =Input!E$8 -> Comparison scenario | I7: =Input!F$8 -> Base
A10: Key Outputs
G12: Key Outputs per scenario and sensitivity | L12: In comparison to Base Case | Q12: IRR accretion scenarios or sensitivity | V12: IRR decrease scenarios or sensitivity
G13: IRR | H13: Net Sales Proceeds | I13: EBIDTA | J13: Revenue | L13: IRR | M13: Net Sales Proceeds | N13: EBIDTA | O13: Revenue | Q13: Top 5 | R13: Scenario or Sensitivity | S13: Delta to base | T13: IRR | V13: Bottom 5 | W13: Scenario or Sensitivity | X13: Delta to base | Y13: IRR
G14: =CaseCalcs!$E$119 -> 0.27882521 | H14: =CaseCalcs!$E$102 -> 5467208.7 | I14: =CaseCalcs!$E$52 -> 3612751.3 | J14: =CaseCalcs!$E$40 -> 12801811
E15: {=scenarios} -> Base | F15: {=_xlfn.SEQUENCE( ROWS( scenarios ) )} -> 1 | G15: 0.27663035 | H15: 5399940.8 | I15: 3585322.2 | J15: 12761011
E16: Scenario 1 | F16: 2 | G16: 0.26156512 | H16: 4916167.5 | I16: 3421517.7 | J16: 12717534 | L16: =( G16 - $G$15 ) / $G$15 -> -0.054459784 | M16: =( H16 - $H$15 ) / $H$15 -> -0.08958862 | N16: =( I16 - $I$15 ) / $I$15 -> -0.045687543 | O16: =( J16 - $J$15 ) / $J$15 -> -0.0034070888 | Q16: 1 | R16: {=_xlfn.XLOOKUP($S16,$L$15:$L$44,_xlfn.ANCHORARRAY($E$15))} -> Sensitivity 24 | S16: =LARGE($L$15:$L$44, $Q16 ) -> 0.28567803 | T16: =_xlfn.XLOOKUP($S16,$L$15:$L$44,$G$15:$G$44) -> 0.35565756 | V16: 5 | W16: {=_xlfn.XLOOKUP($X16,$L$15:$L$44,_xlfn.ANCHORARRAY($E$15))} -> Scenario 4 | X16: =SMALL( $L$15:$L$44, $V16 ) -> -0.067147242 | Y16: =_xlfn.XLOOKUP($X16,$L$15:$L$44,$G$15:$G$44) -> 0.25805538
E17: Scenario 2 | F17: 3 | G17: 0.27630394 | H17: 5390160.8 | I17: 3581202.1 | J17: 12695911 | L17: =( G17 - $G$15 ) / $G$15 -> -0.0011799391 | M17: =( H17 - $H$15 ) / $H$15 -> -0.0018111224 | N17: =( I17 - $I$15 ) / $I$15 -> -0.0011491738 | O17: =( J17 - $J$15 ) / $J$15 -> -0.0051015302 | Q17: 2 | R17: {=_xlfn.XLOOKUP($S17,$L$15:$L$44,_xlfn.ANCHORARRAY($E$15))} -> Sensitivity 19 | S17: =LARGE($L$15:$L$44, $Q17 ) -> 0.2540419 | T17: =_xlfn.XLOOKUP($S17,$L$15:$L$44,$G$15:$G$44) -> 0.34690605 | V17: 4 | W17: {=_xlfn.XLOOKUP($X17,$L$15:$L$44,_xlfn.ANCHORARRAY($E$15))} -> Sensitivity 1 | X17: =SMALL( $L$15:$L$44, $V17 ) -> -0.080924747 | Y17: =_xlfn.XLOOKUP($X17,$L$15:$L$44,$G$15:$G$44) -> 0.25424411
E18: Scenario 3 | F18: 4 | G18: 0.27319233 | H18: 5428419.8 | I18: 3529612.3 | J18: 13316613 | L18: =( G18 - $G$15 ) / $G$15 -> -0.012428209 | M18: =( H18 - $H$15 ) / $H$15 -> 0.0052739528 | N18: =( I18 - $I$15 ) / $I$15 -> -0.015538318 | O18: =( J18 - $J$15 ) / $J$15 -> 0.043538993 | Q18: 3 | R18: {=_xlfn.XLOOKUP($S18,$L$15:$L$44,_xlfn.ANCHORARRAY($E$15))} -> Sensitivity 3 | S18: =LARGE($L$15:$L$44, $Q18 ) -> 0.19106541 | T18: =_xlfn.XLOOKUP($S18,$L$15:$L$44,$G$15:$G$44) -> 0.32948484 | V18: 3 | W18: {=_xlfn.XLOOKUP($X18,$L$15:$L$44,_xlfn.ANCHORARRAY($E$15))} -> Sensitivity 20 | X18: =SMALL( $L$15:$L$44, $V18 ) -> -0.14546053 | Y18: =_xlfn.XLOOKUP($X18,$L$15:$L$44,$G$15:$G$44) -> 0.23639155
E19: Scenario 4 | F19: 5 | G19: 0.25805538 | H19: 5431155.7 | I19: 3597586 | J19: 12779176 | L19: =( G19 - $G$15 ) / $G$15 -> -0.067147242 | M19: =( H19 - $H$15 ) / $H$15 -> 0.0057806063 | N19: =( I19 - $I$15 ) / $I$15 -> 0.0034205569 | O19: =( J19 - $J$15 ) / $J$15 -> 0.0014234194 | Q19: 4 | R19: {=_xlfn.XLOOKUP($S19,$L$15:$L$44,_xlfn.ANCHORARRAY($E$15))} -> Sensitivity 7 | S19: =LARGE($L$15:$L$44, $Q19 ) -> 0.14397411 | T19: =_xlfn.XLOOKUP($S19,$L$15:$L$44,$G$15:$G$44) -> 0.31645796 | V19: 2 | W19: {=_xlfn.XLOOKUP($X19,$L$15:$L$44,_xlfn.ANCHORARRAY($E$15))} -> Sensitivity 8 | X19: =SMALL( $L$15:$L$44, $V19 ) -> -0.1558596 | Y19: =_xlfn.XLOOKUP($X19,$L$15:$L$44,$G$15:$G$44) -> 0.23351485
E20: Scenario 5 | F20: 6 | G20: 0.3102164 | H20: 6342386.9 | I20: 4082520.8 | J20: 13276683 | L20: =( G20 - $G$15 ) / $G$15 -> 0.1214113 | M20: =( H20 - $H$15 ) / $H$15 -> 0.17452896 | N20: =( I20 - $I$15 ) / $I$15 -> 0.13867613 | O20: =( J20 - $J$15 ) / $J$15 -> 0.04040992 | Q20: 5 | R20: {=_xlfn.XLOOKUP($S20,$L$15:$L$44,_xlfn.ANCHORARRAY($E$15))} -> Scenario 5 | S20: =LARGE($L$15:$L$44, $Q20 ) -> 0.1214113 | T20: =_xlfn.XLOOKUP($S20,$L$15:$L$44,$G$15:$G$44) -> 0.3102164 | V20: 1 | W20: {=_xlfn.XLOOKUP($X20,$L$15:$L$44,_xlfn.ANCHORARRAY($E$15))} -> Sensitivity 4 | X20: =SMALL( $L$15:$L$44, $V20 ) -> -0.21144654 | Y20: =_xlfn.XLOOKUP($X20,$L$15:$L$44,$G$15:$G$44) -> 0.21813782
E21: Sensitivity 1 | F21: 7 | G21: 0.25424411 | H21: 5399940.8 | I21: 3585322.2 | J21: 12761011 | L21: =( G21 - $G$15 ) / $G$15 -> -0.080924747 | M21: =( H21 - $H$15 ) / $H$15 -> 0 | N21: =( I21 - $I$15 ) / $I$15 -> 0 | O21: =( J21 - $J$15 ) / $J$15 -> 0
E22: Sensitivity 2 | F22: 8 | G22: 0.30231774 | H22: 5399940.8 | I22: 3585322.2 | J22: 12761011 | L22: =( G22 - $G$15 ) / $G$15 -> 0.092858201 | M22: =( H22 - $H$15 ) / $H$15 -> 0 | N22: =( I22 - $I$15 ) / $I$15 -> 0 | O22: =( J22 - $J$15 ) / $J$15 -> 0
E23: Sensitivity 3 | F23: 9 | G23: 0.32948484 | H23: 6421703.4 | I23: 4360119.9 | J23: 13535809 | L23: =( G23 - $G$15 ) / $G$15 -> 0.19106541 | M23: =( H23 - $H$15 ) / $H$15 -> 0.18921737 | N23: =( I23 - $I$15 ) / $I$15 -> 0.21610267 | O23: =( J23 - $J$15 ) / $J$15 -> 0.060716012
E24: Sensitivity 4 | F24: 10 | G24: 0.21813782 | H24: 4378178.2 | I24: 2810524.5 | J24: 11986214 | L24: =( G24 - $G$15 ) / $G$15 -> -0.21144654 | M24: =( H24 - $H$15 ) / $H$15 -> -0.18921737 | N24: =( I24 - $I$15 ) / $I$15 -> -0.21610267 | O24: =( J24 - $J$15 ) / $J$15 -> -0.060716012
E25: Sensitivity 5 | F25: 11 | G25: 0.29081978 | H25: 5833265.5 | I25: 3774280.9 | J25: 12949970 | L25: =( G25 - $G$15 ) / $G$15 -> 0.051293844 | M25: =( H25 - $H$15 ) / $H$15 -> 0.08024619 | N25: =( I25 - $I$15 ) / $I$15 -> 0.052703394 | O25: =( J25 - $J$15 ) / $J$15 -> 0.014807498
E26: Sensitivity 6 | F26: 12 | G26: 0.26316245 | H26: 5013504.7 | I26: 3417955.3 | J26: 12593644 | L26: =( G26 - $G$15 ) / $G$15 -> -0.048685533 | M26: =( H26 - $H$15 ) / $H$15 -> -0.071563022 | N26: =( I26 - $I$15 ) / $I$15 -> -0.04668115 | O26: =( J26 - $J$15 ) / $J$15 -> -0.013115494
E27: Sensitivity 7 | F27: 13 | G27: 0.31645796 | H27: 6178492.1 | I27: 4162733.2 | J27: 13730087 | L27: =( G27 - $G$15 ) / $G$15 -> 0.14397411 | M27: =( H27 - $H$15 ) / $H$15 -> 0.14417775 | N27: =( I27 - $I$15 ) / $I$15 -> 0.16104857 | O27: =( J27 - $J$15 ) / $J$15 -> 0.075940366
E28: Sensitivity 8 | F28: 14 | G28: 0.23351485 | H28: 4621389.5 | I28: 3007911.2 | J28: 11791936 | L28: =( G28 - $G$15 ) / $G$15 -> -0.1558596 | M28: =( H28 - $H$15 ) / $H$15 -> -0.14417775 | N28: =( I28 - $I$15 ) / $I$15 -> -0.16104857 | O28: =( J28 - $J$15 ) / $J$15 -> -0.075940366
E29: Sensitivity 9 | F29: 15 | G29: 0.283671 | H29: 5615189.5 | I29: 3675846.8 | J29: 12851536 | L29: =( G29 - $G$15 ) / $G$15 -> 0.025451494 | M29: =( H29 - $H$15 ) / $H$15 -> 0.039861318 | N29: =( I29 - $I$15 ) / $I$15 -> 0.025248651 | O29: =( J29 - $J$15 ) / $J$15 -> 0.0070938383
E30: Sensitivity 10 | F30: 16 | G30: 0.2695457 | H30: 5191748.7 | I30: 3496918.8 | J30: 12672608 | L30: =( G30 - $G$15 ) / $G$15 -> -0.025610508 | M30: =( H30 - $H$15 ) / $H$15 -> -0.038554521 | N30: =( I30 - $I$15 ) / $I$15 -> -0.024657038 | O30: =( J30 - $J$15 ) / $J$15 -> -0.0069276192
E31: Sensitivity 11 | F31: 17 | G31: 0.28886271 | H31: 5783915.3 | I31: 3743955 | J31: 13025464 | L31: =( G31 - $G$15 ) / $G$15 -> 0.044219166 | M31: =( H31 - $H$15 ) / $H$15 -> 0.071107175 | N31: =( I31 - $I$15 ) / $I$15 -> 0.044245063 | O31: =( J31 - $J$15 ) / $J$15 -> 0.020723479
E32: Sensitivity 12 | F32: 18 | G32: 0.27882521 | H32: 5467208.7 | I32: 3612751.3 | J32: 12801811 | L32: =( G32 - $G$15 ) / $G$15 -> 0.0079342618 | M32: =( H32 - $H$15 ) / $H$15 -> 0.012457152 | N32: =( I32 - $I$15 ) / $I$15 -> 0.0076503824 | O32: =( J32 - $J$15 ) / $J$15 -> 0.003197195
... E44: Sensitivity 24 | F44: 30 | G44: 0.35565756 | H44: 1841827.1 | I44: 752497.61 | J44: 3335581.4 | L44: =( G44 - $G$15 ) / $G$15 -> 0.28567803 | M44: =( H44 - $H$15 ) / $H$15 -> -0.65891717 | N44: =( I44 - $I$15 ) / $I$15 -> -0.79011716 | O44: =( J44 - $J$15 ) / $J$15 -> -0.73861152

Sheet Input
A1: {=company} -> Rock Climbing Inc
A2: {=topic} -> CFM Topic: Sensitivity Analysis
A3: ASSUMPTIONS SCHEDULE
K5: =IF( K$6 = $F$186, "q","" ) | L5: =IF( L$6 = $F$186, "q","" ) | M5: =IF( M$6 = $F$186, "q","" ) | N5: =IF( N$6 = $F$186, "q","" ) | O5: =IF( O$6 = $F$186, "q","" ) | P5: =IF( P$6 = $F$186, "q","" ) | Q5: =IF( Q$6 = $F$186, "q","" ) | R5: =IF( R$6 = $F$186, "q","" ) | ... AN5: =IF( AN$6 = $F$186, "q","" )
E6: Live Case | K6: {=TRANSPOSE( scenarios )} -> Base | L6: Scenario 1 | M6: Scenario 2 | N6: Scenario 3 | O6: Scenario 4 | P6: Scenario 5 | Q6: Sensitivity 1 | R6: Sensitivity 2 | S6: Sensitivity 3 | T6: Sensitivity 4 | U6: Sensitivity 5 | V6: Sensitivity 6 | W6: Sensitivity 7 | X6: Sensitivity 8 | Y6: Sensitivity 9 | Z6: Sensitivity 10 | AA6: Sensitivity 11 | AB6: Sensitivity 12 | AC6: Sensitivity 13 | AD6: Sensitivity 14 | AE6: Sensitivity 15 | AF6: Sensitivity 16 | AG6: Sensitivity 17 | AH6: Sensitivity 18 | AI6: Sensitivity 19 | AJ6: Sensitivity 20 | AK6: Sensitivity 21 | AL6: Sensitivity 22 | AM6: Sensitivity 23 | AN6: Sensitivity 24
E7: {=REPT( CHAR( 10 ), 2 ) & "Case description" & REPT( CHAR( 10 ), 2 ) & INDEX( $K$7:$AN$7, selector )} -> Case description Input: Year on Year change to Ordinary Casual Visits Requested change: plus 50 basis points to all years (excluding 2022) | K7: Base case scenario | L7: =CaseAnalysis!$B35 -> Change the escalation rate of regular membership fees from 4.00% to 3.00%, and add 1.00% to the Regular members YoY growth for each of 2023, 2024, 2025 and 2026. | M7: =CaseAnalysis!$B36 -> Increase the Casual Visit Ordinary 2022 price to $30.00, and decrease the number of 2022 Ordinary Casual visits from 5,000 to 4,500. | N7: =CaseAnalysis!$B37 -> Increase Fixed Expenses in 2022 to $420,000, and increase the number of 2022 Ordinary Casual visits from 5,000 to 6,000. Increase the # of Friends of Members Casuals visits to 13 per member per year. | O7: =CaseAnalysis!$B38 -> Perform a larger refurbishment that costs 800,000, still with 400,000 debt funded and the remainder equity funded. Change the 2027 YoY regular member growth to 22%, and the 2027 YoY Casual Visit growth to 12%. | P7: =CaseAnalysis!$B39 -> At the start of 2023, convert all Foundation Members to Regular Members. Assume that 20% will quit the gym in protest, and 80% will convert. (This may require some logic changes to the model.) | Q7: {=TRANSPOSE( CaseAnalysis!$E$4:$E$27 )} -> Input: Initial Purchase Cost Requested change: plus 10% of base value | R7: Input: Initial Purchase Cost Requested change: minus 10% of base value | S7: Input: 2022 Membership fee (Regular member) Requested change: plus 10% of base value | T7: Input: 2022 Membership fee (Regular member) Requested change: minus 10% of base value | U7: Input: Escalation rate of membership fees Requested change: plus 50 basis points (e.g. from 4.00% up to 4.50%) | V7: Input: Escalation rate of membership fees Requested change: minus 50 basis points | W7: Input: Number of Regular members at start of 2022 Requested change: plus 50 people from base value | X7: Input: Number of Regular members at start of 2022 Requested change: minus 50 people from base value | Y7: Input: Increase in Casual Visit Prices each year Requested change: plus 50 basis points | Z7: Input: Increase in Casual Visit Prices each year Requested change: minus 50 basis points | AA7: Input: Year on Year change to Regular Members Requested change: plus 50 basis points to all years (excluding 2022) | AB7: Input: Year on Year change to Ordinary Casual Visits Requested change: plus 50 basis points to all years (excluding 2022) | AC7: Input: Escalation rate of fixed expenses Requested change: plus 50 basis points | AD7: Input: Escalation rate of fixed expenses Requested change: minus 50 basis points | AE7: Input: Escalation rate of variable expenses Requested change: plus 50 basis points | AF7: Input: Escalation rate of variable expenses Requested change: minus 50 basis points | AG7: Input: Initial Purchase Debt Facility Interest Rate Requested change: plus 50 basis points | AH7: Input: Refurbishment Debt Facility Interest Rate Requested change: plus 50 basis points | AI7: Input: Initial Purchase % funded by Debt Requested change: change % funded to 80% | AJ7: Input: Initial Purchase % funded by Debt Requested change: change % funded to 40% | AK7: Input: Refurbishment % funded by Debt Requested change: change % funded to 90% | AL7: Input: Refurbishment % funded by Debt Requested change: change % funded to 70% | AM7: Input: Time of Sale of Business Requested change: bring forward to end of 2028 | AN7: Input: Time of Sale of Business Requested change: bring forward to end of 2024
E8: Comparison scenario | F8: =INDEX( scenarios, 1, 1 ) -> Base
E9: Input differences | F9: =COUNTIF( $I$12:$I$144, "tu" ) -> 9
F11: Constant | G11: Unit
B13: Initial Purchase
E15: Initial Purchase Date (Day 0) - DO NOT CHANGE | F15: 44561 | G15: [date]
E16: Initial Purchase Costs on day 0 | F16: {=IF( INDEX( $K16:$AN16, selector ) = "", INDEX( $K16:$AN16, , 1 ), INDEX( $K16:$AN16, 1, selector ))} -> 2000000 | G16: [$] | I16: =IF( $F16 = $K16, "vw", "tu" ) -> vw | K16: 2000000 | Q16: 2200000 | R16: 1800000
B18: Revenues
D20: Membership Fees
E21: Membership fees per Foundation member in 2022 | F21: {=IF( INDEX( $K21:$AN21, selector ) = "", INDEX( $K21:$AN21, , 1 ), INDEX( $K21:$AN21, 1, selector ))} -> 900 | G21: [$ / member] | I21: =IF( $F21 = $K21, "vw", "tu" ) -> vw | K21: 900
E22: Membership fees per Regular member in 2022 | F22: {=IF( INDEX( $K22:$AN22, selector ) = "", INDEX( $K22:$AN22, , 1 ), INDEX( $K22:$AN22, 1, selector ))} -> 1200 | G22: [$ / member] | I22: =IF( $F22 = $K22, "vw", "tu" ) -> vw | K22: 1200 | S22: 1320 | T22: 1080
E23: Escalation rate of Foundation membership fees | F23: {=IF( INDEX( $K23:$AN23, selector ) = "", INDEX( $K23:$AN23, , 1 ), INDEX( $K23:$AN23, 1, selector ))} -> 0 | G23: [%] | I23: =IF( $F23 = $K23, "vw", "tu" ) -> vw | K23: 0 | U23: 0.005 | V23: 0
E24: Escalation rate of Regular membership fees | F24: {=IF( INDEX( $K24:$AN24, selector ) = "", INDEX( $K24:$AN24, , 1 ), INDEX( $K24:$AN24, 1, selector ))} -> 0.04 | G24: [%] | I24: =IF( $F24 = $K24, "vw", "tu" ) -> vw | K24: 0.04 | L24: 0.03 | U24: 0.045 | V24: 0.035
D26: Initial Membership Numbers | P26: changed in the model
E27: Number of Foundation members at start of 2022 | F27: {=IF( INDEX( $K27:$AN27, selector ) = "", INDEX( $K27:$AN27, , 1 ), INDEX( $K27:$AN27, 1, selector ))} -> 120 | G27: [#] | I27: =IF( $F27 = $K27, "vw", "tu" ) -> vw | K27: 120
E28: Number of Regular members at start of 2022 | F28: {=IF( INDEX( $K28:$AN28, selector ) = "", INDEX( $K28:$AN28, , 1 ), INDEX( $K28:$AN28, 1, selector ))} -> 500 | G28: [#] | I28: =IF( $F28 = $K28, "vw", "tu" ) -> vw | K28: 500 | W28: 550 | X28: 450
D30: Year on Year (YoY %) change in membership numbers
E31: Assume the change happens on Day 1 of each year
F32: Foundation Members
E33: Calendar Year | F33: Change
E34: =YEAR($F$15)+1 -> 2022 | F34: {=IF( INDEX( $K34:$AN34, selector ) = "", INDEX( $K34:$AN34, , 1 ), INDEX( $K34:$AN34, 1, selector ))} -> 0 | G34: [%] | I34: =IF( $F34 = $K34, "vw", "tu" ) -> vw | K34: 0
E35: =E34+1 -> 2023 | F35: {=IF( INDEX( $K35:$AN35, selector ) = "", INDEX( $K35:$AN35, , 1 ), INDEX( $K35:$AN35, 1, selector ))} -> -0.02 | G35: [%] | I35: =IF( $F35 = $K35, "vw", "tu" ) -> vw | K35: -0.02
E36: =E35+1 -> 2024 | F36: {=IF( INDEX( $K36:$AN36, selector ) = "", INDEX( $K36:$AN36, , 1 ), INDEX( $K36:$AN36, 1, selector ))} -> -0.02 | G36: [%] | I36: =IF( $F36 = $K36, "vw", "tu" ) -> vw | K36: -0.02
E37: =E36+1 -> 2025 | F37: {=IF( INDEX( $K37:$AN37, selector ) = "", INDEX( $K37:$AN37, , 1 ), INDEX( $K37:$AN37, 1, selector ))} -> -0.02 | G37: [%] | I37: =IF( $F37 = $K37, "vw", "tu" ) -> vw | K37: -0.02
E38: =E37+1 -> 2026 | F38: {=IF( INDEX( $K38:$AN38, selector ) = "", INDEX( $K38:$AN38, , 1 ), INDEX( $K38:$AN38, 1, selector ))} -> -0.02 | G38: [%] | I38: =IF( $F38 = $K38, "vw", "tu" ) -> vw | K38: -0.02
E39: =E38+1 -> 2027 | F39: {=IF( INDEX( $K39:$AN39, selector ) = "", INDEX( $K39:$AN39, , 1 ), INDEX( $K39:$AN39, 1, selector ))} -> -0.02 | G39: [%] | I39: =IF( $F39 = $K39, "vw", "tu" ) -> vw | K39: -0.02
E40: =E39+1 -> 2028 | F40: {=IF( INDEX( $K40:$AN40, selector ) = "", INDEX( $K40:$AN40, , 1 ), INDEX( $K40:$AN40, 1, selector ))} -> -0.02 | G40: [%] | I40: =IF( $F40 = $K40, "vw", "tu" ) -> vw | K40: -0.02
E41: =E40+1 -> 2029 | F41: {=IF( INDEX( $K41:$AN41, selector ) = "", INDEX( $K41:$AN41, , 1 ), INDEX( $K41:$AN41, 1, selector ))} -> -0.02 | G41: [%] | I41: =IF( $F41 = $K41, "vw", "tu" ) -> vw | K41: -0.02
E42: =E41+1 -> 2030 | F42: {=IF( INDEX( $K42:$AN42, selector ) = "", INDEX( $K42:$AN42, , 1 ), INDEX( $K42:$AN42, 1, selector ))} -> -0.02 | G42: [%] | I42: =IF( $F42 = $K42, "vw", "tu" ) -> vw | K42: -0.02
E43: =E42+1 -> 2031 | F43: {=IF( INDEX( $K43:$AN43, selector ) = "", INDEX( $K43:$AN43, , 1 ), INDEX( $K43:$AN43, 1, selector ))} -> -0.02 | G43: [%] | I43: =IF( $F43 = $K43, "vw", "tu" ) -> vw | K43: -0.02
F45: Regular Members
E46: Calendar Year | F46: Change
E47: =YEAR($F$15)+1 -> 2022 | F47: {=IF( INDEX( $K47:$AN47, selector ) = "", INDEX( $K47:$AN47, , 1 ), INDEX( $K47:$AN47, 1, selector ))} -> 0 | G47: [%] | I47: =IF( $F47 = $K47, "vw", "tu" ) -> vw | K47: 0 | AA47: 0.005
E48: =E47+1 -> 2023 | F48: {=IF( INDEX( $K48:$AN48, selector ) = "", INDEX( $K48:$AN48, , 1 ), INDEX( $K48:$AN48, 1, selector ))} -> 0.06 | G48: [%] | I48: =IF( $F48 = $K48, "vw", "tu" ) -> vw | K48: 0.06 | L48: 0.07 | AA48: 0.065
E49: =E48+1 -> 2024 | F49: {=IF( INDEX( $K49:$AN49, selector ) = "", INDEX( $K49:$AN49, , 1 ), INDEX( $K49:$AN49, 1, selector ))} -> 0.04 | G49: [%] | I49: =IF( $F49 = $K49, "vw", "tu" ) -> vw | K49: 0.04 | L49: 0.05 | AA49: 0.045
E50: =E49+1 -> 2025 | F50: {=IF( INDEX( $K50:$AN50, selector ) = "", INDEX( $K50:$AN50, , 1 ), INDEX( $K50:$AN50, 1, selector ))} -> 0.02 | G50: [%] | I50: =IF( $F50 = $K50, "vw", "tu" ) -> vw | K50: 0.02 | L50: 0.03 | AA50: 0.03
E51: =E50+1 -> 2026 | F51: {=IF( INDEX( $K51:$AN51, selector ) = "", INDEX( $K51:$AN51, , 1 ), INDEX( $K51:$AN51, 1, selector ))} -> 0.01 | G51: [%] | I51: =IF( $F51 = $K51, "vw", "tu" ) -> vw | K51: 0.01 | L51: 0.02 | AA51: 0.015
E52: =E51+1 -> 2027 | F52: {=IF( INDEX( $K52:$AN52, selector ) = "", INDEX( $K52:$AN52, , 1 ), INDEX( $K52:$AN52, 1, selector ))} -> 0.17 | G52: [%] | I52: =IF( $F52 = $K52, "vw", "tu" ) -> vw | K52: 0.17 | AA52: 0.175
E53: =E52+1 -> 2028 | F53: {=IF( INDEX( $K53:$AN53, selector ) = "", INDEX( $K53:$AN53, , 1 ), INDEX( $K53:$AN53, 1, selector ))} -> 0.02 | G53: [%] | I53: =IF( $F53 = $K53, "vw", "tu" ) -> vw | K53: 0.02 | AA53: 0.025
E54: =E53+1 -> 2029 | F54: {=IF( INDEX( $K54:$AN54, selector ) = "", INDEX( $K54:$AN54, , 1 ), INDEX( $K54:$AN54, 1, selector ))} -> 0.01 | G54: [%] | I54: =IF( $F54 = $K54, "vw", "tu" ) -> vw | K54: 0.01 | AA54: 0.02
E55: =E54+1 -> 2030 | F55: {=IF( INDEX( $K55:$AN55, selector ) = "", INDEX( $K55:$AN55, , 1 ), INDEX( $K55:$AN55, 1, selector ))} -> 0.01 | G55: [%] | I55: =IF( $F55 = $K55, "vw", "tu" ) -> vw | K55: 0.01 | AA55: 0.015
E56: =E55+1 -> 2031 | F56: {=IF( INDEX( $K56:$AN56, selector ) = "", INDEX( $K56:$AN56, , 1 ), INDEX( $K56:$AN56, 1, selector ))} -> 0.01 | G56: [%] | I56: =IF( $F56 = $K56, "vw", "tu" ) -> vw | K56: 0.01 | AA56: 0.01
D59: Casual Visit Fees
E60: Price per visit in 2022 - Ordinary Casual | F60: {=IF( INDEX( $K60:$AN60, selector ) = "", INDEX( $K60:$AN60, , 1 ), INDEX( $K60:$AN60, 1, selector ))} -> 28 | G60: [$ / visit] | I60: =IF( $F60 = $K60, "vw", "tu" ) -> vw | K60: 28 | M60: 30
E61: Price per visit in 2022 - Friends of Members | F61: {=IF( INDEX( $K61:$AN61, selector ) = "", INDEX( $K61:$AN61, , 1 ), INDEX( $K61:$AN61, 1, selector ))} -> 24 | G61: [$ / visit] | I61: =IF( $F61 = $K61, "vw", "tu" ) -> vw | K61: 24
E62: Increase in price each year | F62: {=IF( INDEX( $K62:$AN62, selector ) = "", INDEX( $K62:$AN62, , 1 ), INDEX( $K62:$AN62, 1, selector ))} -> 0.05 | G62: [%] | I62: =IF( $F62 = $K62, "vw", "tu" ) -> vw | K62: 0.05 | Y62: 0.055 | Z62: 0.045
D64: Number of Casual visits per year
E65: Ordinary Casual visits in 2022 | F65: {=IF( INDEX( $K65:$AN65, selector ) = "", INDEX( $K65:$AN65, , 1 ), INDEX( $K65:$AN65, 1, selector ))} -> 5000 | G65: [#] | I65: =IF( $F65 = $K65, "vw", "tu" ) -> vw | K65: 5000 | M65: 4500 | N65: 6000
E67: Year on Year (YoY %) change in Ordinary Casual visits each year
F69: Ordinary Casual Visits
E70: Calendar Year | F70: Change
E71: =YEAR($F$15)+1 -> 2022 | F71: {=IF( INDEX( $K71:$AN71, selector ) = "", INDEX( $K71:$AN71, , 1 ), INDEX( $K71:$AN71, 1, selector ))} -> 0 | I71: =IF( $F71 = $K71, "vw", "tu" ) -> vw | K71: 0 | AB71: 0
E72: =E71+1 -> 2023 | F72: {=IF( INDEX( $K72:$AN72, selector ) = "", INDEX( $K72:$AN72, , 1 ), INDEX( $K72:$AN72, 1, selector ))} -> 0.035 | G72: [%] | I72: =IF( $F72 = $K72, "vw", "tu" ) -> tu | K72: 0.03 | AB72: 0.035
E73: =E72+1 -> 2024 | F73: {=IF( INDEX( $K73:$AN73, selector ) = "", INDEX( $K73:$AN73, , 1 ), INDEX( $K73:$AN73, 1, selector ))} -> 0.035 | G73: [%] | I73: =IF( $F73 = $K73, "vw", "tu" ) -> tu | K73: 0.03 | AB73: 0.035
E74: =E73+1 -> 2025 | F74: {=IF( INDEX( $K74:$AN74, selector ) = "", INDEX( $K74:$AN74, , 1 ), INDEX( $K74:$AN74, 1, selector ))} -> 0.035 | G74: [%] | I74: =IF( $F74 = $K74, "vw", "tu" ) -> tu | K74: 0.03 | AB74: 0.035
E75: =E74+1 -> 2026 | F75: {=IF( INDEX( $K75:$AN75, selector ) = "", INDEX( $K75:$AN75, , 1 ), INDEX( $K75:$AN75, 1, selector ))} -> 0.035 | G75: [%] | I75: =IF( $F75 = $K75, "vw", "tu" ) -> tu | K75: 0.03 | AB75: 0.035
E76: =E75+1 -> 2027 | F76: {=IF( INDEX( $K76:$AN76, selector ) = "", INDEX( $K76:$AN76, , 1 ), INDEX( $K76:$AN76, 1, selector ))} -> 0.105 | G76: [%] | I76: =IF( $F76 = $K76, "vw", "tu" ) -> tu | K76: 0.1 | O76: 0.12 | AB76: 0.105
E77: =E76+1 -> 2028 | F77: {=IF( INDEX( $K77:$AN77, selector ) = "", INDEX( $K77:$AN77, , 1 ), INDEX( $K77:$AN77, 1, selector ))} -> 0.035 | G77: [%] | I77: =IF( $F77 = $K77, "vw", "tu" ) -> tu | K77: 0.03 | AB77: 0.035
E78: =E77+1 -> 2029 | F78: {=IF( INDEX( $K78:$AN78, selector ) = "", INDEX( $K78:$AN78, , 1 ), INDEX( $K78:$AN78, 1, selector ))} -> 0.035 | G78: [%] | I78: =IF( $F78 = $K78, "vw", "tu" ) -> tu | K78: 0.03 | AB78: 0.035
E79: =E78+1 -> 2030 | F79: {=IF( INDEX( $K79:$AN79, selector ) = "", INDEX( $K79:$AN79, , 1 ), INDEX( $K79:$AN79, 1, selector ))} -> 0.035 | G79: [%] | I79: =IF( $F79 = $K79, "vw", "tu" ) -> tu | K79: 0.03 | AB79: 0.035
E80: =E79+1 -> 2031 | F80: {=IF( INDEX( $K80:$AN80, selector ) = "", INDEX( $K80:$AN80, , 1 ), INDEX( $K80:$AN80, 1, selector ))} -> 0.035 | G80: [%] | I80: =IF( $F80 = $K80, "vw", "tu" ) -> tu | K80: 0.03 | AB80: 0.035
E82: # of Casual Visits - Friends of Members | F82: {=IF( INDEX( $K82:$AN82, selector ) = "", INDEX( $K82:$AN82, , 1 ), INDEX( $K82:$AN82, 1, selector ))} -> 12 | G82: [# per year per member] | I82: =IF( $F82 = $K82, "vw", "tu" ) -> vw | K82: 12 | N82: 13
B85: Expenses
D87: Fixed Expenses
E88: Fixed Expenses in 2022 | F88: {=IF( INDEX( $K88:$AN88, selector ) = "", INDEX( $K88:$AN88, , 1 ), INDEX( $K88:$AN88, 1, selector ))} -> 380000 | G88: [$] | I88: =IF( $F88 = $K88, "vw", "tu" ) -> vw | K88: 380000 | N88: 420000
E89: Escalation rate of Fixed Expenses | F89: {=IF( INDEX( $K89:$AN89, selector ) = "", INDEX( $K89:$AN89, , 1 ), INDEX( $K89:$AN89, 1, selector ))} -> 0.035 | G89: [%] | I89: =IF( $F89 = $K89, "vw", "tu" ) -> vw | K89: 0.035 | AC89: 0.04 | AD89: 0.03
D91: Variable Expenses
E92: Expenses per member per year in 2022 | F92: {=IF( INDEX( $K92:$AN92, selector ) = "", INDEX( $K92:$AN92, , 1 ), INDEX( $K92:$AN92, 1, selector ))} -> 500 | G92: [$] | I92: =IF( $F92 = $K92, "vw", "tu" ) -> vw | K92: 500
E93: Expenses per casual visit in 2022 | F93: {=IF( INDEX( $K93:$AN93, selector ) = "", INDEX( $K93:$AN93, , 1 ), INDEX( $K93:$AN93, 1, selector ))} -> 10 | G93: [$] | I93: =IF( $F93 = $K93, "vw", "tu" ) -> vw | K93: 10
E94: Escalation rate of Variable Expenses | F94: {=IF( INDEX( $K94:$AN94, selector ) = "", INDEX( $K94:$AN94, , 1 ), INDEX( $K94:$AN94, 1, selector ))} -> 0.035 | G94: [%] | I94: =IF( $F94 = $K94, "vw", "tu" ) -> vw | K94: 0.035 | AE94: 0.04 | AF94: 0.03
B97: CAPEX and Depreciation
E99: Refurbishment Costs | F99: {=IF( INDEX( $K99:$AN99, selector ) = "", INDEX( $K99:$AN99, , 1 ), INDEX( $K99:$AN99, 1, selector ))} -> 500000 | G99: [$] | I99: =IF( $F99 = $K99, "vw", "tu" ) -> vw | K99: 500000 | O99: 800000
E100: Time of Refurbishment Costs (end of calendar year #) | F100: {=IF( INDEX( $K100:$AN100, selector ) = "", INDEX( $K100:$AN100, , 1 ), INDEX( $K100:$AN100, 1, selector ))} -> 2025 | G100: [year #] | I100: =IF( $F100 = $K100, "vw", "tu" ) -> vw | K100: 2025
E101: Years to depreciate Refurb. Costs over (Straight Line) | F101: {=IF( INDEX( $K101:$AN101, selector ) = "", INDEX( $K101:$AN101, , 1 ), INDEX( $K101:$AN101, 1, selector ))} -> 8 | G101: [years] | I101: =IF( $F101 = $K101, "vw", "tu" ) -> vw | K101: 8
E102: Depreciation per year | F102: =F99/F101 -> 62500 | G102: [$]
B105: Debt Financing
D107: Initial Purchase
E108: % of Initial Purchase Cost funded by Debt | F108: {=IF( INDEX( $K108:$AN108, selector ) = "", INDEX( $K108:$AN108, , 1 ), INDEX( $K108:$AN108, 1, selector ))} -> 0.6 | G108: [%] | I108: =IF( $F108 = $K108, "vw", "tu" ) -> vw | K108: 0.6 | AI108: 0.8 | AJ108: 0.4
E109: Amount of Initial Purchase Cost funded by Debt | F109: =F108*F16 -> 1200000 | G109: [$]
E110: Length of Loan | F110: {=IF( INDEX( $K110:$AN110, selector ) = "", INDEX( $K110:$AN110, , 1 ), INDEX( $K110:$AN110, 1, selector ))} -> 8 | G110: [years] | I110: =IF( $F110 = $K110, "vw", "tu" ) -> vw | K110: 8
E111: Principal Repayment each year end | F111: =F109/F110 -> 150000 | G111: [$]
E112: Interest Rate per annum (paid each year end) | F112: {=IF( INDEX( $K112:$AN112, selector ) = "", INDEX( $K112:$AN112, , 1 ), INDEX( $K112:$AN112, 1, selector ))} -> 0.05 | G112: [%] | I112: =IF( $F112 = $K112, "vw", "tu" ) -> vw | K112: 0.05 | AG112: 0.055
D114: Refurbishment
E115: % of Refurbishment Cost funded by Debt | F115: {=IF( INDEX( $K115:$AN115, selector ) = "", INDEX( $K115:$AN115, , 1 ), INDEX( $K115:$AN115, 1, selector ))} -> 0.8 | G115: [%] | I115: =IF( $F115 = $K115, "vw", "tu" ) -> vw | K115: 0.8 | O115: 0.5 | AK115: 0.9 | AL115: 0.7
E116: Amount of Refurbishment Cost funded by Debt | F116: =F99*F115 -> 400000 | G116: [$]
E117: Length of Loan | F117: {=IF( INDEX( $K117:$AN117, selector ) = "", INDEX( $K117:$AN117, , 1 ), INDEX( $K117:$AN117, 1, selector ))} -> 6 | G117: [years] | I117: =IF( $F117 = $K117, "vw", "tu" ) -> vw | K117: 6
E118: Principal Repayment each year end | F118: =F116/F117 -> 66666.667 | G118: [$]
E119: Interest Rate per annum (paid each year end) | F119: {=IF( INDEX( $K119:$AN119, selector ) = "", INDEX( $K119:$AN119, , 1 ), INDEX( $K119:$AN119, 1, selector ))} -> 0.06 | G119: [%] | I119: =IF( $F119 = $K119, "vw", "tu" ) -> vw | K119: 0.06 | AH119: 0.065
B122: Equity Financing
E124: Initial Purchase Equity Contribution | F124: =F16-F109 -> 800000 | G124: [$]
E125: Refurbishment Equity Contribution | F125: =F99-F116 -> 100000 | G125: [$]
B128: Cash
D130: Notes about Cash
E131: There are no working capital considerations, and no timing delays for any cash flows.
E132: All remaining cash (after tax) is distributed to Equity at the end of each year
...

Sheet CaseCalcs
A1: CALCULATION SCHEDULE
A3: 2 | C3: Calculations
D5: Period Start | E5: Select Live Case | K5: =J6+1 -> 44562 | L5: =K6+1 -> 44927 | M5: =L6+1 -> 45292 | N5: =M6+1 -> 45658 | O5: =N6+1 -> 46023 | P5: =O6+1 -> 46388 | Q5: =P6+1 -> 46753 | R5: =Q6+1 -> 47119 | ... T5: =S6+1 -> 47849
D6: Period End | J6: =Input!$F$15 -> 44561 | K6: =EOMONTH(J6,12) -> 44926 | L6: =EOMONTH(K6,12) -> 45291 | M6: =EOMONTH(L6,12) -> 45657 | N6: =EOMONTH(M6,12) -> 46022 | O6: =EOMONTH(N6,12) -> 46387 | P6: =EOMONTH(O6,12) -> 46752 | Q6: =EOMONTH(P6,12) -> 47118 | R6: =EOMONTH(Q6,12) -> 47483 | ... T6: =EOMONTH(S6,12) -> 48213
D7: Calendar Year | J7: =YEAR(J6) -> 2021 | K7: =YEAR(K6) -> 2022 | L7: =YEAR(L6) -> 2023 | M7: =YEAR(M6) -> 2024 | N7: =YEAR(N6) -> 2025 | O7: =YEAR(O6) -> 2026 | P7: =YEAR(P6) -> 2027 | Q7: =YEAR(Q6) -> 2028 | ... T7: =YEAR(T6) -> 2031
A10: =MAX(A$3:A9)+0.01 -> 2.01 | C10: Operations
D12: Operating Period Number | F12: [#] | J12: 0 | K12: =J12+1 -> 1 | L12: =K12+1 -> 2 | M12: =L12+1 -> 3 | N12: =M12+1 -> 4 | O12: =N12+1 -> 5 | P12: =O12+1 -> 6 | Q12: =P12+1 -> 7 | R12: =Q12+1 -> 8 | ... T12: =S12+1 -> 10
D13: Operating Period? (i.e. before Sale of Business) | F13: [flag] | G13: =Input!$F$144 -> 2030 | J13: =1*(J$7<=$G13) -> 1 | K13: =1*(K$7<=$G13) -> 1 | L13: =1*(L$7<=$G13) -> 1 | M13: =1*(M$7<=$G13) -> 1 | N13: =1*(N$7<=$G13) -> 1 | O13: =1*(O$7<=$G13) -> 1 | P13: =1*(P$7<=$G13) -> 1 | Q13: =1*(Q$7<=$G13) -> 1 | ... T13: =1*(T$7<=$G13) -> 0
B15: Operations
D16: Membership Prices
D17: Price per Foundation membership | F17: [$] | G17: =Input!F21 -> 900 | H17: =Input!F23 -> 0 | K17: =$G17 -> 900 | L17: =K17*(1+$H17) -> 900 | M17: =L17*(1+$H17) -> 900 | N17: =M17*(1+$H17) -> 900 | O17: =N17*(1+$H17) -> 900 | P17: =O17*(1+$H17) -> 900 | Q17: =P17*(1+$H17) -> 900 | R17: =Q17*(1+$H17) -> 900 | S17: =R17*(1+$H17) -> 900 | T17: =S17*(1+$H17) -> 900
D18: Price per Regular membership | G18: =Input!F22 -> 1200 | H18: =Input!F24 -> 0.04 | K18: =$G18 -> 1200 | L18: =K18*(1+$H18) -> 1248 | M18: =L18*(1+$H18) -> 1297.92 | N18: =M18*(1+$H18) -> 1349.8368 | O18: =N18*(1+$H18) -> 1403.8303 | P18: =O18*(1+$H18) -> 1459.9835 | Q18: =P18*(1+$H18) -> 1518.3828 | R18: =Q18*(1+$H18) -> 1579.1181 | S18: =R18*(1+$H18) -> 1642.2829 | T18: =S18*(1+$H18) -> 1707.9742
D20: Membership Numbers
D21: Foundation Members - Year of Year Growth | F21: [%] | K21: =INDEX(Input!$F$34:$F$43,MATCH(K$7,Input!$E$34:$E$43,0)) -> 0 | L21: =INDEX(Input!$F$34:$F$43,MATCH(L$7,Input!$E$34:$E$43,0)) -> -0.02 | M21: =INDEX(Input!$F$34:$F$43,MATCH(M$7,Input!$E$34:$E$43,0)) -> -0.02 | N21: =INDEX(Input!$F$34:$F$43,MATCH(N$7,Input!$E$34:$E$43,0)) -> -0.02 | O21: =INDEX(Input!$F$34:$F$43,MATCH(O$7,Input!$E$34:$E$43,0)) -> -0.02 | P21: =INDEX(Input!$F$34:$F$43,MATCH(P$7,Input!$E$34:$E$43,0)) -> -0.02 | Q21: =INDEX(Input!$F$34:$F$43,MATCH(Q$7,Input!$E$34:$E$43,0)) -> -0.02 | R21: =INDEX(Input!$F$34:$F$43,MATCH(R$7,Input!$E$34:$E$43,0)) -> -0.02 | ... T21: =INDEX(Input!$F$34:$F$43,MATCH(T$7,Input!$E$34:$E$43,0)) -> -0.02
D22: Regular Members - Year on Year Growth | F22: [%] | K22: =INDEX(Input!$F$47:$F$56,MATCH(K$7,Input!$E$47:$E$56,0)) -> 0 | L22: =INDEX(Input!$F$47:$F$56,MATCH(L$7,Input!$E$47:$E$56,0)) -> 0.06 | M22: =INDEX(Input!$F$47:$F$56,MATCH(M$7,Input!$E$47:$E$56,0)) -> 0.04 | N22: =INDEX(Input!$F$47:$F$56,MATCH(N$7,Input!$E$47:$E$56,0)) -> 0.02 | O22: =INDEX(Input!$F$47:$F$56,MATCH(O$7,Input!$E$47:$E$56,0)) -> 0.01 | P22: =INDEX(Input!$F$47:$F$56,MATCH(P$7,Input!$E$47:$E$56,0)) -> 0.17 | Q22: =INDEX(Input!$F$47:$F$56,MATCH(Q$7,Input!$E$47:$E$56,0)) -> 0.02 | R22: =INDEX(Input!$F$47:$F$56,MATCH(R$7,Input!$E$47:$E$56,0)) -> 0.01 | ... T22: =INDEX(Input!$F$47:$F$56,MATCH(T$7,Input!$E$47:$E$56,0)) -> 0.01
D23: Foundation Members during year | E23: =SUM(J23:T23) -> 1097.5632 | F23: [#] | G23: =Input!F27 -> 120 | K23: =G23 -> 120 | L23: =IF( selector = 6, 0, K23*(1+L21) ) -> 117.6 | M23: =IF( selector = 6, 0, L23*(1+M21) ) -> 115.248 | N23: =IF( selector = 6, 0, M23*(1+N21) ) -> 112.94304 | O23: =IF( selector = 6, 0, N23*(1+O21) ) -> 110.68418 | P23: =IF( selector = 6, 0, O23*(1+P21) ) -> 108.4705 | Q23: =IF( selector = 6, 0, P23*(1+Q21) ) -> 106.30109 | R23: =IF( selector = 6, 0, Q23*(1+R21) ) -> 104.17506 | S23: =IF( selector = 6, 0, R23*(1+S21) ) -> 102.09156 | T23: =IF( selector = 6, 0, S23*(1+T21) ) -> 100.04973
D24: Regular Members during year | E24: =SUM(J24:T24) -> 6127.253 | F24: [#] | G24: =Input!F28 -> 500 | K24: =G24 -> 500 | L24: =IF( selector = 6, ( K23 * 0.8 ) + K24*(1+L22), K24*(1+L22) ) -> 530 | M24: =L24*(1+M22) -> 551.2 | N24: =M24*(1+N22) -> 562.224 | O24: =N24*(1+O22) -> 567.84624 | P24: =O24*(1+P22) -> 664.3801 | Q24: =P24*(1+Q22) -> 677.6677 | R24: =Q24*(1+R22) -> 684.44438 | S24: =R24*(1+S22) -> 691.28882 | T24: =S24*(1+T22) -> 698.20171
D26: Casual Prices
D27: Price per casual visit - Ordinary | F27: [$] | G27: =Input!F60 -> 28 | H27: =Input!$F$62 -> 0.05 | K27: =G27 -> 28 | L27: =K27*(1+$H27) -> 29.4 | M27: =L27*(1+$H27) -> 30.87 | N27: =M27*(1+$H27) -> 32.4135 | O27: =N27*(1+$H27) -> 34.034175 | P27: =O27*(1+$H27) -> 35.735884 | Q27: =P27*(1+$H27) -> 37.522678 | R27: =Q27*(1+$H27) -> 39.398812 | S27: =R27*(1+$H27) -> 41.368752 | T27: =S27*(1+$H27) -> 43.43719
D28: Price per casual visit - Friends of Members | F28: [$] | G28: =Input!F61 -> 24 | H28: =Input!$F$62 -> 0.05 | K28: =G28 -> 24 | L28: =K28*(1+$H28) -> 25.2 | M28: =L28*(1+$H28) -> 26.46 | N28: =M28*(1+$H28) -> 27.783 | O28: =N28*(1+$H28) -> 29.17215 | P28: =O28*(1+$H28) -> 30.630758 | Q28: =P28*(1+$H28) -> 32.162295 | R28: =Q28*(1+$H28) -> 33.77041 | S28: =R28*(1+$H28) -> 35.458931 | T28: =S28*(1+$H28) -> 37.231877
D30: Casual Visit Numbers
D31: Casual visits - Year on Year Growth | F31: [%] | K31: =INDEX(Input!$F$71:$F$80,MATCH(K$7,Input!$E$71:$E$80,0)) -> 0 | L31: =INDEX(Input!$F$71:$F$80,MATCH(L$7,Input!$E$71:$E$80,0)) -> 0.035 | M31: =INDEX(Input!$F$71:$F$80,MATCH(M$7,Input!$E$71:$E$80,0)) -> 0.035 | N31: =INDEX(Input!$F$71:$F$80,MATCH(N$7,Input!$E$71:$E$80,0)) -> 0.035 | O31: =INDEX(Input!$F$71:$F$80,MATCH(O$7,Input!$E$71:$E$80,0)) -> 0.035 | P31: =INDEX(Input!$F$71:$F$80,MATCH(P$7,Input!$E$71:$E$80,0)) -> 0.105 | Q31: =INDEX(Input!$F$71:$F$80,MATCH(Q$7,Input!$E$71:$E$80,0)) -> 0.035 | R31: =INDEX(Input!$F$71:$F$80,MATCH(R$7,Input!$E$71:$E$80,0)) -> 0.035 | ... T31: =INDEX(Input!$F$71:$F$80,MATCH(T$7,Input!$E$71:$E$80,0)) -> 0.035
D32: Casual visits - Ordinary | E32: =SUM(J32:T32) -> 60810.709 | F32: [#] | G32: =Input!F65 -> 5000 | K32: =G32 -> 5000 | L32: =K32*(1+L31) -> 5175 | M32: =L32*(1+M31) -> 5356.125 | N32: =M32*(1+N31) -> 5543.5894 | O32: =N32*(1+O31) -> 5737.615 | P32: =O32*(1+P31) -> 6340.0646 | Q32: =P32*(1+Q31) -> 6561.9668 | R32: =Q32*(1+R31) -> 6791.6357 | S32: =R32*(1+S31) -> 7029.3429 | T32: =S32*(1+T31) -> 7275.3699
D33: Casual visits - Friends of Members | E33: =SUM(J33:T33) -> 86697.793 | F33: [#] | G33: =Input!F82 -> 12 | K33: =$G33*SUM(K23:K24) -> 7440 | L33: =$G33*SUM(L23:L24) -> 7771.2 | M33: =$G33*SUM(M23:M24) -> 7997.376 | N33: =$G33*SUM(N23:N24) -> 8102.0045 | O33: =$G33*SUM(O23:O24) -> 8142.365 | P33: =$G33*SUM(P23:P24) -> 9274.2072 | Q33: =$G33*SUM(Q23:Q24) -> 9407.6255 | R33: =$G33*SUM(R23:R24) -> 9463.4333 | ... T33: =$G33*SUM(T23:T24) -> 9579.0173
C35: Revenues
D36: Membership Fees - Foundation | E36: =SUM(J36:T36) -> 897762.08 | F36: [$] | J36: 0 | K36: =K17*K23*K$13 -> 108000 | L36: =L17*L23*L$13 -> 105840 | M36: =M17*M23*M$13 -> 103723.2 | N36: =N17*N23*N$13 -> 101648.74 | O36: =O17*O23*O$13 -> 99615.761 | P36: =P17*P23*P$13 -> 97623.446 | Q36: =Q17*Q23*Q$13 -> 95670.977 | R36: =R17*R23*R$13 -> 93757.558 | ... T36: =T17*T23*T$13 -> 0
D37: Membership Fees - Regular | E37: =SUM(J37:T37) -> 7747977.2 | F37: [$] | J37: 0 | K37: =K18*K24*K$13 -> 600000 | L37: =L18*L24*L$13 -> 661440 | M37: =M18*M24*M$13 -> 715413.5 | N37: =N18*N24*N$13 -> 758910.65 | O37: =O18*O24*O$13 -> 797159.74 | P37: =P18*P24*P$13 -> 969983.97 | Q37: =Q18*Q24*Q$13 -> 1028959 | R37: =R18*R24*R$13 -> 1080818.5 | ... T37: =T18*T24*T$13 -> 0
D38: Casual Visit Fees - Ordinary | E38: =SUM(J38:T38) -> 1863618.6 | F38: [$] | J38: 0 | K38: =K27*K32*K$13 -> 140000 | L38: =L27*L32*L$13 -> 152145 | M38: =M27*M32*M$13 -> 165343.58 | N38: =N27*N32*N$13 -> 179687.13 | O38: =O27*O32*O$13 -> 195274.99 | P38: =P27*P32*P$13 -> 226567.81 | Q38: =Q27*Q32*Q$13 -> 246222.57 | R38: =R27*R32*R$13 -> 267582.38 | ... T38: =T27*T32*T$13 -> 0
D39: Casual Visit Fees - Friends of Members | E39: =SUM(J39:T39) -> 2292453 | J39: 0 | K39: =K28*K33*K$13 -> 178560 | L39: =L28*L33*L$13 -> 195834.24 | M39: =M28*M33*M$13 -> 211610.57 | N39: =N28*N33*N$13 -> 225097.99 | O39: =O28*O33*O$13 -> 237530.29 | P39: =P28*P33*P$13 -> 284075.99 | Q39: =Q28*Q33*Q$13 -> 302570.83 | R39: =R28*R33*R$13 -> 319584.02 | ... T39: =T28*T33*T$13 -> 0
D40: Total Revenues | E40: =SUM(J40:T40) -> 12801811 | F40: [$] | J40: =SUM(J36:J39) -> 0 | K40: =SUM(K36:K39) -> 1026560 | L40: =SUM(L36:L39) -> 1115259.2 | M40: =SUM(M36:M39) -> 1196090.9 | N40: =SUM(N36:N39) -> 1265344.5 | O40: =SUM(O36:O39) -> 1329580.8 | P40: =SUM(P36:P39) -> 1578251.2 | Q40: =SUM(Q36:Q39) -> 1673423.4 | ... T40: =SUM(T36:T39) -> 0
C42: Expenses
D43: Variable Expenses per member per year | F43: [$] | G43: =Input!F92 -> 500 | H43: =Input!$F$94 -> 0.035 | K43: =G43 -> 500 | L43: =K43*(1+$H43) -> 517.5 | M43: =L43*(1+$H43) -> 535.6125 | N43: =M43*(1+$H43) -> 554.35894 | O43: =N43*(1+$H43) -> 573.7615 | P43: =O43*(1+$H43) -> 593.84315 | Q43: =P43*(1+$H43) -> 614.62766 | R43: =Q43*(1+$H43) -> 636.13963 | S43: =R43*(1+$H43) -> 658.40452 | T43: =S43*(1+$H43) -> 681.44868
D44: Variable Expenses per casual visit | F44: [$] | G44: =Input!F93 -> 10 | H44: =Input!$F$94 -> 0.035 | K44: =G44 -> 10 | L44: =K44*(1+$H44) -> 10.35 | M44: =L44*(1+$H44) -> 10.71225 | N44: =M44*(1+$H44) -> 11.087179 | O44: =N44*(1+$H44) -> 11.47523 | P44: =O44*(1+$H44) -> 11.876863 | Q44: =P44*(1+$H44) -> 12.292553 | R44: =Q44*(1+$H44) -> 12.722793 | S44: =R44*(1+$H44) -> 13.16809 | T44: =S44*(1+$H44) -> 13.628974
D47: Fixed Expenses | E47: =SUM(J47:T47) -> 3940028.4 | F47: [$] | G47: =Input!F88 -> 380000 | H47: =Input!F89 -> 0.035 | J47: 0 | K47: =$G47*K$13 -> 380000 | L47: =K47*(1+$H47)*L$13 -> 393300 | M47: =L47*(1+$H47)*M$13 -> 407065.5 | N47: =M47*(1+$H47)*N$13 -> 421312.79 | O47: =N47*(1+$H47)*O$13 -> 436058.74 | P47: =O47*(1+$H47)*P$13 -> 451320.8 | Q47: =P47*(1+$H47)*Q$13 -> 467117.02 | R47: =Q47*(1+$H47)*R$13 -> 483466.12 | S47: =R47*(1+$H47)*S$13 -> 500387.43 | T47: =S47*(1+$H47)*T$13 -> 0
D48: Variable Expenses - Member visits | E48: =SUM(J48:T48) -> 3730528.6 | F48: [$] | J48: 0 | K48: =K43*SUM(K23:K24)*K$13 -> 310000 | L48: =L43*SUM(L23:L24)*L$13 -> 335133 | M48: =M43*SUM(M23:M24)*M$13 -> 356957.88 | N48: =N43*SUM(N23:N24)*N$13 -> 374284.88 | O48: =O43*SUM(O23:O24)*O$13 -> 389314.63 | P48: =P43*SUM(P23:P24)*P$13 -> 458952.03 | Q48: =Q43*SUM(Q23:Q24)*Q$13 -> 481848.9 | R48: =R43*SUM(R23:R24)*R$13 -> 501672.08 | ... T48: =T43*SUM(T23:T24)*T$13 -> 0
D49: Variable Expenses - Casual visits | E49: =SUM(J49:T49) -> 1518502.5 | F49: [$] | J49: 0 | K49: =K44*SUM(K32:K33)*K$13 -> 124400 | L49: =L44*SUM(L32:L33)*L$13 -> 133993.17 | M49: =M44*SUM(M32:M33)*M$13 -> 143046.04 | N49: =N44*SUM(N32:N33)*N$13 -> 151291.14 | O49: =O44*SUM(O32:O33)*O$13 -> 159275.96 | P49: =P44*SUM(P32:P33)*P$13 -> 185448.57 | Q49: =Q44*SUM(Q32:Q33)*Q$13 -> 196307.06 | R49: =R44*SUM(R32:R33)*R$13 -> 206809.87 | ... T49: =T44*SUM(T32:T33)*T$13 -> 0
D50: Total Expenses | E50: =SUM(J50:T50) -> 9189059.5 | F50: [$] | J50: =SUM(J47:J49) -> 0 | K50: =SUM(K47:K49) -> 814400 | L50: =SUM(L47:L49) -> 862426.17 | M50: =SUM(M47:M49) -> 907069.42 | N50: =SUM(N47:N49) -> 946888.81 | O50: =SUM(O47:O49) -> 984649.33 | P50: =SUM(P47:P49) -> 1095721.4 | Q50: =SUM(Q47:Q49) -> 1145273 | ... T50: =SUM(T47:T49) -> 0
D52: EBITDA | E52: =SUM(J52:T52) -> 3612751.3 | F52: [$] | J52: =J40-J50 -> 0 | K52: =K40-K50 -> 212160 | L52: =L40-L50 -> 252833.07 | M52: =M40-M50 -> 289021.43 | N52: =N40-N50 -> 318455.69 | O52: =O40-O50 -> 344931.46 | P52: =P40-P50 -> 482529.82 | Q52: =Q40-Q50 -> 528150.38 | ... T52: =T40-T50 -> 0
A55: =MAX(A$3:A54)+0.01 -> 2.02 | C55: Debt
B57: Debt
C58: Initial Purchase Facility
D59: Opening Balance | F59: [$] | J59: =I62*J$13 -> 0 | K59: =J62*K$13 -> 1200000 | L59: =K62*L$13 -> 1050000 | M59: =L62*M$13 -> 900000 | N59: =M62*N$13 -> 750000 | O59: =N62*O$13 -> 600000 | P59: =O62*P$13 -> 450000 | Q59: =P62*Q$13 -> 300000 | ... T59: =S62*T$13 -> 0
D60: Drawdown | E60: =SUM(J60:T60) -> 1200000 | F60: [$] | G60: =Input!F109 -> 1200000 | H60: =YEAR(Input!F15) -> 2021 | J60: =$G60*($H60=J$7)*J$13 -> 1200000 | K60: =$G60*($H60=K$7)*K$13 -> 0 | L60: =$G60*($H60=L$7)*L$13 -> 0 | M60: =$G60*($H60=M$7)*M$13 -> 0 | N60: =$G60*($H60=N$7)*N$13 -> 0 | O60: =$G60*($H60=O$7)*O$13 -> 0 | P60: =$G60*($H60=P$7)*P$13 -> 0 | Q60: =$G60*($H60=Q$7)*Q$13 -> 0 | ... T60: =$G60*($H60=T$7)*T$13 -> 0
D61: Repayment | E61: =SUM(J61:T61) -> -1200000 | F61: [$] | G61: =Input!F111 -> 150000 | J61: =-MIN(J59,$G61)*J$13 -> 0 | K61: =-MIN(K59,$G61)*K$13 -> -150000 | L61: =-MIN(L59,$G61)*L$13 -> -150000 | M61: =-MIN(M59,$G61)*M$13 -> -150000 | N61: =-MIN(N59,$G61)*N$13 -> -150000 | O61: =-MIN(O59,$G61)*O$13 -> -150000 | P61: =-MIN(P59,$G61)*P$13 -> -150000 | Q61: =-MIN(Q59,$G61)*Q$13 -> -150000 | ... T61: =-MIN(T59,$G61)*T$13 -> 0
D62: Closing Balance | F62: [$] | J62: =SUM(J59:J61) -> 1200000 | K62: =SUM(K59:K61) -> 1050000 | L62: =SUM(L59:L61) -> 900000 | M62: =SUM(M59:M61) -> 750000 | N62: =SUM(N59:N61) -> 600000 | O62: =SUM(O59:O61) -> 450000 | P62: =SUM(P59:P61) -> 300000 | Q62: =SUM(Q59:Q61) -> 150000 | ... T62: =SUM(T59:T61) -> 0
D64: Interest Expense | E64: =SUM(J64:T64) -> 270000 | F64: [$] | G64: =Input!$F$112 -> 0.05 | J64: =$G64*J59*J$13 -> 0 | K64: =$G64*K59*K$13 -> 60000 | L64: =$G64*L59*L$13 -> 52500 | M64: =$G64*M59*M$13 -> 45000 | N64: =$G64*N59*N$13 -> 37500 | O64: =$G64*O59*O$13 -> 30000 | P64: =$G64*P59*P$13 -> 22500 | Q64: =$G64*Q59*Q$13 -> 15000 | ... T64: =$G64*T59*T$13 -> 0
C66: Refurbishment Facility
D67: Opening Balance | F67: [$] | J67: =I70*J$13 -> 0 | K67: =J70*K$13 -> 0 | L67: =K70*L$13 -> 0 | M67: =L70*M$13 -> 0 | N67: =M70*N$13 -> 0 | O67: =N70*O$13 -> 400000 | P67: =O70*P$13 -> 333333.33 | Q67: =P70*Q$13 -> 266666.67 | ... T67: =S70*T$13 -> 0
D68: Drawdown | E68: =SUM(J68:T68) -> 400000 | F68: [$] | G68: =Input!F116 -> 400000 | H68: =Input!F100 -> 2025 | J68: =$G68*($H68=J$7)*J$13 -> 0 | K68: =$G68*($H68=K$7)*K$13 -> 0 | L68: =$G68*($H68=L$7)*L$13 -> 0 | M68: =$G68*($H68=M$7)*M$13 -> 0 | N68: =$G68*($H68=N$7)*N$13 -> 400000 | O68: =$G68*($H68=O$7)*O$13 -> 0 | P68: =$G68*($H68=P$7)*P$13 -> 0 | Q68: =$G68*($H68=Q$7)*Q$13 -> 0 | ... T68: =$G68*($H68=T$7)*T$13 -> 0
D69: Repayment | E69: =SUM(J69:T69) -> -333333.33 | F69: [$] | G69: =Input!F118 -> 66666.667 | J69: =-MIN(J67,$G69)*J$13 -> 0 | K69: =-MIN(K67,$G69)*K$13 -> 0 | L69: =-MIN(L67,$G69)*L$13 -> 0 | M69: =-MIN(M67,$G69)*M$13 -> 0 | N69: =-MIN(N67,$G69)*N$13 -> 0 | O69: =-MIN(O67,$G69)*O$13 -> -66666.667 | P69: =-MIN(P67,$G69)*P$13 -> -66666.667 | Q69: =-MIN(Q67,$G69)*Q$13 -> -66666.667 | ... T69: =-MIN(T67,$G69)*T$13 -> 0
D70: Closing Balance | F70: [$] | J70: =SUM(J67:J69) -> 0 | K70: =SUM(K67:K69) -> 0 | L70: =SUM(L67:L69) -> 0 | M70: =SUM(M67:M69) -> 0 | N70: =SUM(N67:N69) -> 400000 | O70: =SUM(O67:O69) -> 333333.33 | P70: =SUM(P67:P69) -> 266666.67 | Q70: =SUM(Q67:Q69) -> 200000 | ... T70: =SUM(T67:T69) -> 0
D72: Interest Expense | E72: =SUM(J72:T72) -> 80000 | F72: [$] | G72: =Input!$F$119 -> 0.06 | J72: =$G72*J67*J$13 -> 0 | K72: =$G72*K67*K$13 -> 0 | L72: =$G72*L67*L$13 -> 0 | M72: =$G72*M67*M$13 -> 0 | N72: =$G72*N67*N$13 -> 0 | O72: =$G72*O67*O$13 -> 24000 | P72: =$G72*P67*P$13 -> 20000 | Q72: =$G72*Q67*Q$13 -> 16000 | ... T72: =$G72*T67*T$13 -> 0
A74: =MAX(A$3:A73)+0.01 -> 2.03 | C74: Depreciation, Tax and Cash Result
B76: Depreciation
D77: Opening Balance | F77: [$] | J77: =I80*J$13 -> 0 | K77: =J80*K$13 -> 0 | L77: =K80*L$13 -> 0 | M77: =L80*M$13 -> 0 | N77: =M80*N$13 -> 0 | O77: =N80*O$13 -> 500000 | P77: =O80*P$13 -> 437500 | Q77: =P80*Q$13 -> 375000 | ... T77: =S80*T$13 -> 0
D78: Add: Capex | E78: =SUM(J78:T78) -> 500000 | F78: [$] | G78: =Input!F99 -> 500000 | H78: =Input!F100 -> 2025 | J78: =$G78*($H78=J$7)*J$13 -> 0 | K78: =$G78*($H78=K$7)*K$13 -> 0 | L78: =$G78*($H78=L$7)*L$13 -> 0 | M78: =$G78*($H78=M$7)*M$13 -> 0 | N78: =$G78*($H78=N$7)*N$13 -> 500000 | O78: =$G78*($H78=O$7)*O$13 -> 0 | P78: =$G78*($H78=P$7)*P$13 -> 0 | Q78: =$G78*($H78=Q$7)*Q$13 -> 0 | ... T78: =$G78*($H78=T$7)*T$13 -> 0
D79: Less: Depreciation | E79: =SUM(J79:T79) -> -312500 | F79: [$] | G79: =Input!F102 -> 62500 | J79: =-MIN(J77,$G79)*J$13 -> 0 | K79: =-MIN(K77,$G79)*K$13 -> 0 | L79: =-MIN(L77,$G79)*L$13 -> 0 | M79: =-MIN(M77,$G79)*M$13 -> 0 | N79: =-MIN(N77,$G79)*N$13 -> 0 | O79: =-MIN(O77,$G79)*O$13 -> -62500 | P79: =-MIN(P77,$G79)*P$13 -> -62500 | Q79: =-MIN(Q77,$G79)*Q$13 -> -62500 | ... T79: =-MIN(T77,$G79)*T$13 -> 0
D80: Closing Balance | F80: [$] | J80: =SUM(J77:J79) -> 0 | K80: =SUM(K77:K79) -> 0 | L80: =SUM(L77:L79) -> 0 | M80: =SUM(M77:M79) -> 0 | N80: =SUM(N77:N79) -> 500000 | O80: =SUM(O77:O79) -> 437500 | P80: =SUM(P77:P79) -> 375000 | Q80: =SUM(Q77:Q79) -> 312500 | ... T80: =SUM(T77:T79) -> 0
B82: Tax
D83: EBITDA | E83: =SUM(J83:T83) -> 3612751.3 | F83: [$] | J83: =J52 -> 0 | K83: =K52 -> 212160 | L83: =L52 -> 252833.07 | M83: =M52 -> 289021.43 | N83: =N52 -> 318455.69 | O83: =O52 -> 344931.46 | P83: =P52 -> 482529.82 | Q83: =Q52 -> 528150.38 | ... T83: =T52 -> 0
D84: Less: Interest on Debt | E84: =SUM(J84:T84) -> -350000 | F84: [$] | J84: =-SUM(J64,J72) -> 0 | K84: =-SUM(K64,K72) -> -60000 | L84: =-SUM(L64,L72) -> -52500 | M84: =-SUM(M64,M72) -> -45000 | N84: =-SUM(N64,N72) -> -37500 | O84: =-SUM(O64,O72) -> -54000 | P84: =-SUM(P64,P72) -> -42500 | Q84: =-SUM(Q64,Q72) -> -31000 | ... T84: =-SUM(T64,T72) -> 0
D85: Less: Depreciation | E85: =SUM(J85:T85) -> -312500 | F85: [$] | J85: =J79 -> 0 | K85: =K79 -> 0 | L85: =L79 -> 0 | M85: =M79 -> 0 | N85: =N79 -> 0 | O85: =O79 -> -62500 | P85: =P79 -> -62500 | Q85: =Q79 -> -62500 | ... T85: =T79 -> 0
D86: Taxable Income | E86: =SUM(J86:T86) -> 2950251.3 | F86: [$] | J86: =SUM(J83:J85) -> 0 | K86: =SUM(K83:K85) -> 152160 | L86: =SUM(L83:L85) -> 200333.07 | M86: =SUM(M83:M85) -> 244021.43 | N86: =SUM(N83:N85) -> 280955.69 | O86: =SUM(O83:O85) -> 228431.46 | P86: =SUM(P83:P85) -> 377529.82 | Q86: =SUM(Q83:Q85) -> 434650.38 | ... T86: =SUM(T83:T85) -> 0
D87: Tax paid / (refunded) | E87: =SUM(J87:T87) -> 885075.39 | F87: [$] | G87: =Input!F138 -> 0.3 | J87: =$G87*J86 -> 0 | K87: =$G87*K86 -> 45648 | L87: =$G87*L86 -> 60099.921 | M87: =$G87*M86 -> 73206.429 | N87: =$G87*N86 -> 84286.708 | O87: =$G87*O86 -> 68529.437 | P87: =$G87*P86 -> 113258.95 | Q87: =$G87*Q86 -> 130395.11 | ... T87: =$G87*T86 -> 0
B89: Cash Result
D90: EBITDA | E90: =SUM(J90:T90) -> 3612751.3 | J90: =J52 -> 0 | K90: =K52 -> 212160 | L90: =L52 -> 252833.07 | M90: =M52 -> 289021.43 | N90: =N52 -> 318455.69 | O90: =O52 -> 344931.46 | P90: =P52 -> 482529.82 | Q90: =Q52 -> 528150.38 | ... T90: =T52 -> 0
D91: Less: Interest on Debt | E91: =SUM(J91:T91) -> -80000 | J91: =-SUM(J63,J72) -> 0 | K91: =-SUM(K63,K72) -> 0 | L91: =-SUM(L63,L72) -> 0 | M91: =-SUM(M63,M72) -> 0 | N91: =-SUM(N63,N72) -> 0 | O91: =-SUM(O63,O72) -> -24000 | P91: =-SUM(P63,P72) -> -20000 | Q91: =-SUM(Q63,Q72) -> -16000 | ... T91: =-SUM(T63,T72) -> 0
D92: Less: Principal on Debt | E92: =SUM(J92:T92) -> -1533333.3 | J92: =SUM(J61,J69) -> 0 | K92: =SUM(K61,K69) -> -150000 | L92: =SUM(L61,L69) -> -150000 | M92: =SUM(M61,M69) -> -150000 | N92: =SUM(N61,N69) -> -150000 | O92: =SUM(O61,O69) -> -216666.67 | P92: =SUM(P61,P69) -> -216666.67 | Q92: =SUM(Q61,Q69) -> -216666.67 | ... T92: =SUM(T61,T69) -> 0
D93: Tax (paid) / refunded | E93: =SUM(J93:T93) -> -885075.39 | J93: =0-J87 -> 0 | K93: =0-K87 -> -45648 | L93: =0-L87 -> -60099.921 | M93: =0-M87 -> -73206.429 | N93: =0-N87 -> -84286.708 | O93: =0-O87 -> -68529.437 | P93: =0-P87 -> -113258.95 | Q93: =0-Q87 -> -130395.11 | ... T93: =0-T87 -> 0
D94: Net cash result for period | E94: =SUM(J94:T94) -> 1114342.6 | J94: =SUM(J90:J93) -> 0 | K94: =SUM(K90:K93) -> 16512 | L94: =SUM(L90:L93) -> 42733.149 | M94: =SUM(M90:M93) -> 65815.002 | N94: =SUM(N90:N93) -> 84168.984 | O94: =SUM(O90:O93) -> 35735.352 | P94: =SUM(P90:P93) -> 132604.21 | Q94: =SUM(Q90:Q93) -> 165088.6 | ... T94: =SUM(T90:T93) -> 0
A96: =MAX(A$3:A95)+0.01 -> 2.04 | C96: Sale Proceeds
B98: Sale Proceeds
D99: Sale Period | F99: [flag] | G99: =Input!F144 -> 2030 | J99: =1*($G99=J$7) -> 0 | K99: =1*($G99=K$7) -> 0 | L99: =1*($G99=L$7) -> 0 | M99: =1*($G99=M$7) -> 0 | N99: =1*($G99=N$7) -> 0 | O99: =1*($G99=O$7) -> 0 | P99: =1*($G99=P$7) -> 0 | Q99: =1*($G99=Q$7) -> 0 | ... T99: =1*($G99=T$7) -> 0
D100: Initial Sale Proceeds | E100: =SUM(J100:T100) -> 5533875.3 | F100: [$] | G100: =Input!F143 -> 9 | J100: =J99*$G100*J52 -> 0 | K100: =K99*$G100*K52 -> 0 | L100: =L99*$G100*L52 -> 0 | M100: =M99*$G100*M52 -> 0 | N100: =N99*$G100*N52 -> 0 | O100: =O99*$G100*O52 -> 0 | P100: =P99*$G100*P52 -> 0 | Q100: =Q99*$G100*Q52 -> 0 | ... T100: =T99*$G100*T52 -> 0
D101: Less: pay off remaining debt | E101: =SUM(J101:T101) -> -66666.667 | F101: [$] | J101: =-SUM(J62,J70)*J99 -> 0 | K101: =-SUM(K62,K70)*K99 -> 0 | L101: =-SUM(L62,L70)*L99 -> 0 | M101: =-SUM(M62,M70)*M99 -> 0 | N101: =-SUM(N62,N70)*N99 -> 0 | O101: =-SUM(O62,O70)*O99 -> 0 | P101: =-SUM(P62,P70)*P99 -> 0 | Q101: =-SUM(Q62,Q70)*Q99 -> 0 | ... T101: =-SUM(T62,T70)*T99 -> 0
D102: Net Sale Proceeds to Equity | E102: =SUM(J102:T102) -> 5467208.7 | F102: [$] | J102: =SUM(J100:J101) -> 0 | K102: =SUM(K100:K101) -> 0 | L102: =SUM(L100:L101) -> 0 | M102: =SUM(M100:M101) -> 0 | N102: =SUM(N100:N101) -> 0 | O102: =SUM(O100:O101) -> 0 | P102: =SUM(P100:P101) -> 0 | Q102: =SUM(Q100:Q101) -> 0 | ... T102: =SUM(T100:T101) -> 0
A104: =MAX(A$3:A103)+0.01 -> 2.05 | C104: Equity
B106: Equity
C107: Planned Investment Activities
D108: Equity Contribution for Initial Purchase | E108: =SUM(J108:T108) -> 800000 | F108: [$] | G108: =Input!F124 -> 800000 | H108: =YEAR(Input!F15) -> 2021 | J108: =$G108*(J$7=$H108)*J$13 -> 800000 | K108: =$G108*(K$7=$H108)*K$13 -> 0 | L108: =$G108*(L$7=$H108)*L$13 -> 0 | M108: =$G108*(M$7=$H108)*M$13 -> 0 | N108: =$G108*(N$7=$H108)*N$13 -> 0 | O108: =$G108*(O$7=$H108)*O$13 -> 0 | P108: =$G108*(P$7=$H108)*P$13 -> 0 | Q108: =$G108*(Q$7=$H108)*Q$13 -> 0 | ... T108: =$G108*(T$7=$H108)*T$13 -> 0
D109: Equity Contribution for Refurbishment | E109: =SUM(J109:T109) -> 100000 | F109: [$] | G109: =Input!F125 -> 100000 | H109: =Input!F100 -> 2025 | J109: =$G109*(J$7=$H109)*J$13 -> 0 | K109: =$G109*(K$7=$H109)*K$13 -> 0 | L109: =$G109*(L$7=$H109)*L$13 -> 0 | M109: =$G109*(M$7=$H109)*M$13 -> 0 | N109: =$G109*(N$7=$H109)*N$13 -> 100000 | O109: =$G109*(O$7=$H109)*O$13 -> 0 | P109: =$G109*(P$7=$H109)*P$13 -> 0 | Q109: =$G109*(Q$7=$H109)*Q$13 -> 0 | ... T109: =$G109*(T$7=$H109)*T$13 -> 0
C111: Cash flows to / (from) Equity
D112: Equity Contribution for Initial Purchase | E112: =SUM(J112:T112) -> -800000 | F112: [$] | J112: =-J108 -> -800000 | K112: =-K108 -> 0 | L112: =-L108 -> 0 | M112: =-M108 -> 0 | N112: =-N108 -> 0 | O112: =-O108 -> 0 | P112: =-P108 -> 0 | Q112: =-Q108 -> 0 | ... T112: =-T108 -> 0
D113: Equity Contribution for Refurbishment | E113: =SUM(J113:T113) -> -100000 | F113: [$] | J113: =-J109 -> 0 | K113: =-K109 -> 0 | L113: =-L109 -> 0 | M113: =-M109 -> 0 | N113: =-N109 -> -100000 | O113: =-O109 -> 0 | P113: =-P109 -> 0 | Q113: =-Q109 -> 0 | ... T113: =-T109 -> 0
D114: Equity Contribution for cash shortfall | E114: =SUM(J114:T114) -> 0 | F114: [$] | J114: =MIN(0,J94) -> 0 | K114: =MIN(0,K94) -> 0 | L114: =MIN(0,L94) -> 0 | M114: =MIN(0,M94) -> 0 | N114: =MIN(0,N94) -> 0 | O114: =MIN(0,O94) -> 0 | P114: =MIN(0,P94) -> 0 | Q114: =MIN(0,Q94) -> 0 | ... T114: =MIN(0,T94) -> 0
D115: Distribution of Cash | E115: =SUM(J115:T115) -> 1114342.6 | F115: [$] | J115: =MAX(0,J94) -> 0 | K115: =MAX(0,K94) -> 16512 | L115: =MAX(0,L94) -> 42733.149 | M115: =MAX(0,M94) -> 65815.002 | N115: =MAX(0,N94) -> 84168.984 | O115: =MAX(0,O94) -> 35735.352 | P115: =MAX(0,P94) -> 132604.21 | Q115: =MAX(0,Q94) -> 165088.6 | ... T115: =MAX(0,T94) -> 0
D116: Distribution of Net Sale Proceeds | E116: =SUM(J116:T116) -> 5467208.7 | F116: [$] | J116: =J102 -> 0 | K116: =K102 -> 0 | L116: =L102 -> 0 | M116: =M102 -> 0 | N116: =N102 -> 0 | O116: =O102 -> 0 | P116: =P102 -> 0 | Q116: =Q102 -> 0 | ... T116: =T102 -> 0
D117: Total Cashflow to Equity | E117: =SUM(J117:T117) -> 5681551.3 | F117: [$] | J117: =SUM(J112:J116) -> -800000 | K117: =SUM(K112:K116) -> 16512 | L117: =SUM(L112:L116) -> 42733.149 | M117: =SUM(M112:M116) -> 65815.002 | N117: =SUM(N112:N116) -> -15831.016 | O117: =SUM(O112:O116) -> 35735.352 | P117: =SUM(P112:P116) -> 132604.21 | Q117: =SUM(Q112:Q116) -> 165088.6 | ... T117: =SUM(T112:T116) -> 0
D119: Rate of Return to Equity (XIRR) | E119: =XIRR(J117:T117,J6:T6) -> 0.27882521 | F119: [%]
C123: End Sheet

Sheet CaseAnalysis
A2: Sensitivity Analysis
B3: Input | C3: Requested change
A4: 1 | B4: Initial Purchase Cost | C4: plus 10% of base value | E4: ="Input: " & CHAR(10) & $B4 & REPT(CHAR(10), 2 ) & "Requested change: " & CHAR(10) & $C4 -> Input: Initial Purchase Cost Requested change: plus 10% of base value
A5: 2 | B5: Initial Purchase Cost | C5: minus 10% of base value | E5: ="Input: " & CHAR(10) & $B5 & REPT(CHAR(10), 2 ) & "Requested change: " & CHAR(10) & $C5 -> Input: Initial Purchase Cost Requested change: minus 10% of base value
A6: 3 | B6: 2022 Membership fee (Regular member) | C6: plus 10% of base value | E6: ="Input: " & CHAR(10) & $B6 & REPT(CHAR(10), 2 ) & "Requested change: " & CHAR(10) & $C6 -> Input: 2022 Membership fee (Regular member) Requested change: plus 10% of base value
A7: 4 | B7: 2022 Membership fee (Regular member) | C7: minus 10% of base value | E7: ="Input: " & CHAR(10) & $B7 & REPT(CHAR(10), 2 ) & "Requested change: " & CHAR(10) & $C7 -> Input: 2022 Membership fee (Regular member) Requested change: minus 10% of base value
A8: 5 | B8: Escalation rate of membership fees | C8: plus 50 basis points (e.g. from 4.00% up to 4.50%) | E8: ="Input: " & CHAR(10) & $B8 & REPT(CHAR(10), 2 ) & "Requested change: " & CHAR(10) & $C8 -> Input: Escalation rate of membership fees Requested change: plus 50 basis points (e.g. from 4.00% up to 4.50%)
A9: 6 | B9: Escalation rate of membership fees | C9: minus 50 basis points | E9: ="Input: " & CHAR(10) & $B9 & REPT(CHAR(10), 2 ) & "Requested change: " & CHAR(10) & $C9 -> Input: Escalation rate of membership fees Requested change: minus 50 basis points
A10: 7 | B10: Number of Regular members at start of 2022 | C10: plus 50 people from base value | E10: ="Input: " & CHAR(10) & $B10 & REPT(CHAR(10), 2 ) & "Requested change: " & CHAR(10) & $C10 -> Input: Number of Regular members at start of 2022 Requested change: plus 50 people from base value
A11: 8 | B11: Number of Regular members at start of 2022 | C11: minus 50 people from base value | E11: ="Input: " & CHAR(10) & $B11 & REPT(CHAR(10), 2 ) & "Requested change: " & CHAR(10) & $C11 -> Input: Number of Regular members at start of 2022 Requested change: minus 50 people from base value
A12: 9 | B12: Increase in Casual Visit Prices each year | C12: plus 50 basis points | E12: ="Input: " & CHAR(10) & $B12 & REPT(CHAR(10), 2 ) & "Requested change: " & CHAR(10) & $C12 -> Input: Increase in Casual Visit Prices each year Requested change: plus 50 basis points
A13: 10 | B13: Increase in Casual Visit Prices each year | C13: minus 50 basis points | E13: ="Input: " & CHAR(10) & $B13 & REPT(CHAR(10), 2 ) & "Requested change: " & CHAR(10) & $C13 -> Input: Increase in Casual Visit Prices each year Requested change: minus 50 basis points
A14: 11 | B14: Year on Year change to Regular Members | C14: plus 50 basis points to all years (excluding 2022) | E14: ="Input: " & CHAR(10) & $B14 & REPT(CHAR(10), 2 ) & "Requested change: " & CHAR(10) & $C14 -> Input: Year on Year change to Regular Members Requested change: plus 50 basis points to all years (excluding 2022)
A15: 12 | B15: Year on Year change to Ordinary Casual Visits | C15: plus 50 basis points to all years (excluding 2022) | E15: ="Input: " & CHAR(10) & $B15 & REPT(CHAR(10), 2 ) & "Requested change: " & CHAR(10) & $C15 -> Input: Year on Year change to Ordinary Casual Visits Requested change: plus 50 basis points to all years (excluding 2022)
... A27: 24 | B27: Time of Sale of Business | C27: bring forward to end of 2024 | E27: ="Input: " & CHAR(10) & $B27 & REPT(CHAR(10), 2 ) & "Requested change: " & CHAR(10) & $C27 -> Input: Time of Sale of Business Requested change: bring forward to end of 2024
B29: Output to examine for each sensitivity
A30: 1 | B30: Equity IRR
A33: Scenarios
B34: Description
A35: 1 | B35: Change the escalation rate of regular membership fees from 4.00% to 3.00%, and add 1.00% to the Regular members YoY growth for each of 2023, 2024, 2025 and 2026.
A36: 2 | B36: Increase the Casual Visit Ordinary 2022 price to $30.00, and decrease the number of 2022 Ordinary Casual visits from 5,000 to 4,500.
A37: 3 | B37: Increase Fixed Expenses in 2022 to $420,000, and increase the number of 2022 Ordinary Casual visits from 5,000 to 6,000. Increase the # of Friends of Members Casuals visits to 13 per member per year.
A38: 4 | B38: Perform a larger refurbishment that costs 800,000, still with 400,000 debt funded and the remainder equity funded. Change the 2027 YoY regular member growth to 22%, and the 2027 YoY Casual Visit growth to 12%.
A39: 5 | B39: At the start of 2023, convert all Foundation Members to Regular Members. Assume that 20% will quit the gym in protest, and 80% will convert. (This may require some logic changes to the model.)
B41: Key Outputs to examine for each scenario
A42: 1 | B42: Equity IRR
A43: 2 | B43: Net Sale Proceeds
A44: 3 | B44: Total EBITDA (sum over all years)
A45: 4 | B45: Total Revenues
