Workbook
Name company: CaseData!$L$9
Name end_date: CaseData!$N$7
Name months: Calculations!$F$10
Name start_date: CaseData!$L$6
Name topic: "CFM Topic: " & CaseData!$L$10

Sheet Calculations
A1: {=company} -> United Landlords Ltd
A2: {=topic} -> CFM Topic: Timing flexibility
A3: CALCULATIONS SCHEDULE | F3: Constant | G3: Unit | H3: Total | J3: {=_xlfn.ANCHORARRAY( J11)} -> 44592 | K3: 44620 | L3: 44651 | M3: 44681 | N3: 44712 | O3: 44742 | P3: 44773 | Q3: 44804 | R3: 44834 | S3: 44865 | T3: 44895 | U3: 44926 | V3: 44957 | W3: 44985 | X3: 45016 | Y3: 45046 | Z3: 45077 | AA3: 45107 | AB3: 45138 | AC3: 45169 | AD3: 45199 | AE3: 45230 | AF3: 45260 | AG3: 45291 | AH3: 45322 | AI3: 45351 | AJ3: 45382 | AK3: 45412 | AL3: 45443 | AM3: 45473 | AN3: 45504 | AO3: 45535 | AP3: 45565 | AQ3: 45596 | AR3: 45626 | AS3: 45657 | AT3: 45688 | AU3: 45716 | AV3: 45747 | AW3: 45777 | AX3: 45808 | AY3: 45838 | AZ3: 45869 | BA3: 45900 | BB3: 45930 | BC3: 45961 | BD3: 45991 | BE3: 46022 | BF3: 46053 | BG3: 46081 | BH3: 46112 | BI3: 46142 | BJ3: 46173 | BK3: 46203 | BL3: 46234 | BM3: 46265 | BN3: 46295 | BO3: 46326 | BP3: 46356 | BQ3: 46387 | BR3: 46418 | BS3: 46446 | BT3: 46477 | BU3: 46507 | BV3: 46538 | BW3: 46568 | BX3: 46599 | BY3: 46630 | BZ3: 46660 | CA3: 46691 | CB3: 46721 | CC3: 46752 | CD3: 46783 | CE3: 46812 | CF3: 46843 | CG3: 46873 | CH3: 46904 | CI3: 46934 | CJ3: 46965 | CK3: 46996 | CL3: 47026 | CM3: 47057 | CN3: 47087 | CO3: 47118 | CP3: 47149 | CQ3: 47177 | CR3: 47208 | CS3: 47238 | CT3: 47269 | CU3: 47299 | CV3: 47330 | CW3: 47361 | CX3: 47391 | CY3: 47422 | CZ3: 47452 | DA3: 47483 | DB3: 47514 | DC3: 47542 | DD3: 47573 | DE3: 47603 | DF3: 47634 | DG3: 47664 | DH3: 47695 | DI3: 47726 | DJ3: 47756 | DK3: 47787 | DL3: 47817 | DM3: 47848 | DN3: 47879 | DO3: 47907 | DP3: 47938 | DQ3: 47968 | DR3: 47999 | DS3: 48029 | DT3: 48060 | DU3: 48091 | DV3: 48121 | DW3: 48152 | DX3: 48182 | DY3: 48213
A5: Model technical inputs
E7: Model start date | F7: =start_date -> 44562 | G7: date
E8: Model end date | F8: =end_date -> 48213 | G8: date
E9: Delay in project start | F9: 0 | G9: years
E10: Periods | F10: =( VALUE(F8)-VALUE(F7) ) / 365 * 12 -> 120.03288 | G10: months
E11: Model timeline | G11: date | J11: {=EOMONTH( start_date, _xlfn.SEQUENCE( 1, months, 0, 1 ) )} -> 44592 | K11: 44620 | L11: 44651 | M11: 44681 | N11: 44712 | O11: 44742 | P11: 44773 | Q11: 44804 | R11: 44834 | S11: 44865 | T11: 44895 | U11: 44926 | V11: 44957 | W11: 44985 | X11: 45016 | Y11: 45046 | Z11: 45077 | AA11: 45107 | AB11: 45138 | AC11: 45169 | AD11: 45199 | AE11: 45230 | AF11: 45260 | AG11: 45291 | AH11: 45322 | AI11: 45351 | AJ11: 45382 | AK11: 45412 | AL11: 45443 | AM11: 45473 | AN11: 45504 | AO11: 45535 | AP11: 45565 | AQ11: 45596 | AR11: 45626 | AS11: 45657 | AT11: 45688 | AU11: 45716 | AV11: 45747 | AW11: 45777 | AX11: 45808 | AY11: 45838 | AZ11: 45869 | BA11: 45900 | BB11: 45930 | BC11: 45961 | BD11: 45991 | BE11: 46022 | BF11: 46053 | BG11: 46081 | BH11: 46112 | BI11: 46142 | BJ11: 46173 | BK11: 46203 | BL11: 46234 | BM11: 46265 | BN11: 46295 | BO11: 46326 | BP11: 46356 | BQ11: 46387 | BR11: 46418 | BS11: 46446 | BT11: 46477 | BU11: 46507 | BV11: 46538 | BW11: 46568 | BX11: 46599 | BY11: 46630 | BZ11: 46660 | CA11: 46691 | CB11: 46721 | CC11: 46752 | CD11: 46783 | CE11: 46812 | CF11: 46843 | CG11: 46873 | CH11: 46904 | CI11: 46934 | CJ11: 46965 | CK11: 46996 | CL11: 47026 | CM11: 47057 | CN11: 47087 | CO11: 47118 | CP11: 47149 | CQ11: 47177 | CR11: 47208 | CS11: 47238 | CT11: 47269 | CU11: 47299 | CV11: 47330 | CW11: 47361 | CX11: 47391 | CY11: 47422 | CZ11: 47452 | DA11: 47483 | DB11: 47514 | DC11: 47542 | DD11: 47573 | DE11: 47603 | DF11: 47634 | DG11: 47664 | DH11: 47695 | DI11: 47726 | DJ11: 47756 | DK11: 47787 | DL11: 47817 | DM11: 47848 | DN11: 47879 | DO11: 47907 | DP11: 47938 | DQ11: 47968 | DR11: 47999 | DS11: 48029 | DT11: 48060 | DU11: 48091 | DV11: 48121 | DW11: 48152 | DX11: 48182 | DY11: 48213
A13: Existing properties
C15: Rent revenues
C16: (adjusted for inflation and vacancy)
E17: {=INDEX( CaseData!$A$6:$B$10,, 1 )} -> Property A | G17: USD | H17: {=_xlfn.BYROW(_xlfn.ANCHORARRAY( J17), _xleta.SUM )} -> 1.1037505e+08 | J17: {=_xlfn.LET( _xlpm.timeline,_xlfn.ANCHORARRAY( $J$3), _xlpm.inflation_flag, IF( MONTH( _xlpm.timeline ) = 1, 1, 0 ), _xlpm.inflation_data, CaseData!$J$15:$M$24, _xlpm.annual_rate, _xlfn.XLOOKUP( YEAR( _xlpm.timeline ), INDEX( _xlpm.inflation_data,, 1 ), INDEX( _xlpm.inflation_data,, 2 ) ), _xlpm.effective_step, _xlpm.inflation_flag * _xlpm.annual_rate, _xlpm.inflation_factor, _xlfn.SCAN( 1, _xlpm.effective_step, _xlfn.LAMBDA(_xlpm.prev,_xlpm.step, IF( _xlpm.step = 0, _xlpm.prev, _xlpm.prev * ( 1 + _xlpm.step ) ) ) ), _xlpm.property_data, CaseData!$A$6:$D$10, _xlpm.property_rows, INDEX( _xlpm.property_data, 0, 1 ), _xlpm.current_property, INDEX(_xlfn.ANCHORARRAY( E17),, 1 ), _xlpm.vacancy_factor, 1 - INDEX( _xlpm.property_data, MATCH( _xlpm.current_property, _xlpm.property_rows, 0 ), 3 ), _xlpm.rent, INDEX( _xlpm.property_data,, 2 ), _xlpm.rent * _xlpm.inflation_factor * _xlpm.vacancy_factor )} -> 789022.5 | K17: 789022.5 | L17: 789022.5 | M17: 789022.5 | N17: 789022.5 | O17: 789022.5 | P17: 789022.5 | Q17: 789022.5 | R17: 789022.5 | S17: 789022.5 | T17: 789022.5 | U17: 789022.5 | V17: 824528.51 | W17: 824528.51 | X17: 824528.51 | Y17: 824528.51 | Z17: 824528.51 | AA17: 824528.51 | AB17: 824528.51 | AC17: 824528.51 | AD17: 824528.51 | AE17: 824528.51 | AF17: 824528.51 | AG17: 824528.51 | AH17: 857509.65 | AI17: 857509.65 | AJ17: 857509.65 | AK17: 857509.65 | AL17: 857509.65 | AM17: 857509.65 | AN17: 857509.65 | AO17: 857509.65 | AP17: 857509.65 | AQ17: 857509.65 | AR17: 857509.65 | AS17: 857509.65 | AT17: 887522.49 | AU17: 887522.49 | AV17: 887522.49 | AW17: 887522.49 | AX17: 887522.49 | AY17: 887522.49 | AZ17: 887522.49 | BA17: 887522.49 | BB17: 887522.49 | BC17: 887522.49 | BD17: 887522.49 | BE17: 887522.49 | BF17: 914148.17 | BG17: 914148.17 | BH17: 914148.17 | BI17: 914148.17 | BJ17: 914148.17 | BK17: 914148.17 | BL17: 914148.17 | BM17: 914148.17 | BN17: 914148.17 | BO17: 914148.17 | BP17: 914148.17 | BQ17: 914148.17 | BR17: 937001.87 | BS17: 937001.87 | BT17: 937001.87 | BU17: 937001.87 | BV17: 937001.87 | BW17: 937001.87 | BX17: 937001.87 | BY17: 937001.87 | BZ17: 937001.87 | CA17: 937001.87 | CB17: 937001.87 | CC17: 937001.87 | CD17: 960426.92 | CE17: 960426.92 | CF17: 960426.92 | CG17: 960426.92 | CH17: 960426.92 | CI17: 960426.92 | CJ17: 960426.92 | CK17: 960426.92 | CL17: 960426.92 | CM17: 960426.92 | CN17: 960426.92 | CO17: 960426.92 | CP17: 984437.59 | CQ17: 984437.59 | CR17: 984437.59 | CS17: 984437.59 | CT17: 984437.59 | CU17: 984437.59 | CV17: 984437.59 | CW17: 984437.59 | CX17: 984437.59 | CY17: 984437.59 | CZ17: 984437.59 | DA17: 984437.59 | DB17: 1009048.5 | DC17: 1009048.5 | DD17: 1009048.5 | DE17: 1009048.5 | DF17: 1009048.5 | DG17: 1009048.5 | DH17: 1009048.5 | DI17: 1009048.5 | DJ17: 1009048.5 | DK17: 1009048.5 | DL17: 1009048.5 | DM17: 1009048.5 | DN17: 1034274.7 | DO17: 1034274.7 | DP17: 1034274.7 | DQ17: 1034274.7 | DR17: 1034274.7 | DS17: 1034274.7 | DT17: 1034274.7 | DU17: 1034274.7 | DV17: 1034274.7 | DW17: 1034274.7 | DX17: 1034274.7 | DY17: 1034274.7
E18: Property B | G18: USD | H18: 61197234 | J18: 437472 | K18: 437472 | L18: 437472 | M18: 437472 | N18: 437472 | O18: 437472 | P18: 437472 | Q18: 437472 | R18: 437472 | S18: 437472 | T18: 437472 | U18: 437472 | V18: 457158.24 | W18: 457158.24 | X18: 457158.24 | Y18: 457158.24 | Z18: 457158.24 | AA18: 457158.24 | AB18: 457158.24 | AC18: 457158.24 | AD18: 457158.24 | AE18: 457158.24 | AF18: 457158.24 | AG18: 457158.24 | AH18: 475444.57 | AI18: 475444.57 | AJ18: 475444.57 | AK18: 475444.57 | AL18: 475444.57 | AM18: 475444.57 | AN18: 475444.57 | AO18: 475444.57 | AP18: 475444.57 | AQ18: 475444.57 | AR18: 475444.57 | AS18: 475444.57 | AT18: 492085.13 | AU18: 492085.13 | AV18: 492085.13 | AW18: 492085.13 | AX18: 492085.13 | AY18: 492085.13 | AZ18: 492085.13 | BA18: 492085.13 | BB18: 492085.13 | BC18: 492085.13 | BD18: 492085.13 | BE18: 492085.13 | BF18: 506847.68 | BG18: 506847.68 | BH18: 506847.68 | BI18: 506847.68 | BJ18: 506847.68 | BK18: 506847.68 | BL18: 506847.68 | BM18: 506847.68 | BN18: 506847.68 | BO18: 506847.68 | BP18: 506847.68 | BQ18: 506847.68 | BR18: 519518.88 | BS18: 519518.88 | BT18: 519518.88 | BU18: 519518.88 | BV18: 519518.88 | BW18: 519518.88 | BX18: 519518.88 | BY18: 519518.88 | BZ18: 519518.88 | CA18: 519518.88 | CB18: 519518.88 | CC18: 519518.88 | CD18: 532506.85 | CE18: 532506.85 | CF18: 532506.85 | CG18: 532506.85 | CH18: 532506.85 | CI18: 532506.85 | CJ18: 532506.85 | CK18: 532506.85 | CL18: 532506.85 | CM18: 532506.85 | CN18: 532506.85 | CO18: 532506.85 | CP18: 545819.52 | CQ18: 545819.52 | CR18: 545819.52 | CS18: 545819.52 | CT18: 545819.52 | CU18: 545819.52 | CV18: 545819.52 | CW18: 545819.52 | CX18: 545819.52 | CY18: 545819.52 | CZ18: 545819.52 | DA18: 545819.52 | DB18: 559465.01 | DC18: 559465.01 | DD18: 559465.01 | DE18: 559465.01 | DF18: 559465.01 | DG18: 559465.01 | DH18: 559465.01 | DI18: 559465.01 | DJ18: 559465.01 | DK18: 559465.01 | DL18: 559465.01 | DM18: 559465.01 | DN18: 573451.63 | DO18: 573451.63 | DP18: 573451.63 | DQ18: 573451.63 | DR18: 573451.63 | DS18: 573451.63 | DT18: 573451.63 | DU18: 573451.63 | DV18: 573451.63 | DW18: 573451.63 | DX18: 573451.63 | DY18: 573451.63
E19: Property C | G19: USD | H19: 94715880 | J19: 677082 | K19: 677082 | L19: 677082 | M19: 677082 | N19: 677082 | O19: 677082 | P19: 677082 | Q19: 677082 | R19: 677082 | S19: 677082 | T19: 677082 | U19: 677082 | V19: 707550.69 | W19: 707550.69 | X19: 707550.69 | Y19: 707550.69 | Z19: 707550.69 | AA19: 707550.69 | AB19: 707550.69 | AC19: 707550.69 | AD19: 707550.69 | AE19: 707550.69 | AF19: 707550.69 | AG19: 707550.69 | AH19: 735852.72 | AI19: 735852.72 | AJ19: 735852.72 | AK19: 735852.72 | AL19: 735852.72 | AM19: 735852.72 | AN19: 735852.72 | AO19: 735852.72 | AP19: 735852.72 | AQ19: 735852.72 | AR19: 735852.72 | AS19: 735852.72 | AT19: 761607.56 | AU19: 761607.56 | AV19: 761607.56 | AW19: 761607.56 | AX19: 761607.56 | AY19: 761607.56 | AZ19: 761607.56 | BA19: 761607.56 | BB19: 761607.56 | BC19: 761607.56 | BD19: 761607.56 | BE19: 761607.56 | BF19: 784455.79 | BG19: 784455.79 | BH19: 784455.79 | BI19: 784455.79 | BJ19: 784455.79 | BK19: 784455.79 | BL19: 784455.79 | BM19: 784455.79 | BN19: 784455.79 | BO19: 784455.79 | BP19: 784455.79 | BQ19: 784455.79 | BR19: 804067.18 | BS19: 804067.18 | BT19: 804067.18 | BU19: 804067.18 | BV19: 804067.18 | BW19: 804067.18 | BX19: 804067.18 | BY19: 804067.18 | BZ19: 804067.18 | CA19: 804067.18 | CB19: 804067.18 | CC19: 804067.18 | CD19: 824168.86 | CE19: 824168.86 | CF19: 824168.86 | CG19: 824168.86 | CH19: 824168.86 | CI19: 824168.86 | CJ19: 824168.86 | CK19: 824168.86 | CL19: 824168.86 | CM19: 824168.86 | CN19: 824168.86 | CO19: 824168.86 | CP19: 844773.09 | CQ19: 844773.09 | CR19: 844773.09 | CS19: 844773.09 | CT19: 844773.09 | CU19: 844773.09 | CV19: 844773.09 | CW19: 844773.09 | CX19: 844773.09 | CY19: 844773.09 | CZ19: 844773.09 | DA19: 844773.09 | DB19: 865892.41 | DC19: 865892.41 | DD19: 865892.41 | DE19: 865892.41 | DF19: 865892.41 | DG19: 865892.41 | DH19: 865892.41 | DI19: 865892.41 | DJ19: 865892.41 | DK19: 865892.41 | DL19: 865892.41 | DM19: 865892.41 | DN19: 887539.72 | DO19: 887539.72 | DP19: 887539.72 | DQ19: 887539.72 | DR19: 887539.72 | DS19: 887539.72 | DT19: 887539.72 | DU19: 887539.72 | DV19: 887539.72 | DW19: 887539.72 | DX19: 887539.72 | DY19: 887539.72
E20: Property D | G20: USD | H20: 1.040635e+08 | J20: 743904 | K20: 743904 | L20: 743904 | M20: 743904 | N20: 743904 | O20: 743904 | P20: 743904 | Q20: 743904 | R20: 743904 | S20: 743904 | T20: 743904 | U20: 743904 | V20: 777379.68 | W20: 777379.68 | X20: 777379.68 | Y20: 777379.68 | Z20: 777379.68 | AA20: 777379.68 | AB20: 777379.68 | AC20: 777379.68 | AD20: 777379.68 | AE20: 777379.68 | AF20: 777379.68 | AG20: 777379.68 | AH20: 808474.87 | AI20: 808474.87 | AJ20: 808474.87 | AK20: 808474.87 | AL20: 808474.87 | AM20: 808474.87 | AN20: 808474.87 | AO20: 808474.87 | AP20: 808474.87 | AQ20: 808474.87 | AR20: 808474.87 | AS20: 808474.87 | AT20: 836771.49 | AU20: 836771.49 | AV20: 836771.49 | AW20: 836771.49 | AX20: 836771.49 | AY20: 836771.49 | AZ20: 836771.49 | BA20: 836771.49 | BB20: 836771.49 | BC20: 836771.49 | BD20: 836771.49 | BE20: 836771.49 | BF20: 861874.63 | BG20: 861874.63 | BH20: 861874.63 | BI20: 861874.63 | BJ20: 861874.63 | BK20: 861874.63 | BL20: 861874.63 | BM20: 861874.63 | BN20: 861874.63 | BO20: 861874.63 | BP20: 861874.63 | BQ20: 861874.63 | BR20: 883421.5 | BS20: 883421.5 | BT20: 883421.5 | BU20: 883421.5 | BV20: 883421.5 | BW20: 883421.5 | BX20: 883421.5 | BY20: 883421.5 | BZ20: 883421.5 | CA20: 883421.5 | CB20: 883421.5 | CC20: 883421.5 | CD20: 905507.04 | CE20: 905507.04 | CF20: 905507.04 | CG20: 905507.04 | CH20: 905507.04 | CI20: 905507.04 | CJ20: 905507.04 | CK20: 905507.04 | CL20: 905507.04 | CM20: 905507.04 | CN20: 905507.04 | CO20: 905507.04 | CP20: 928144.71 | CQ20: 928144.71 | CR20: 928144.71 | CS20: 928144.71 | CT20: 928144.71 | CU20: 928144.71 | CV20: 928144.71 | CW20: 928144.71 | CX20: 928144.71 | CY20: 928144.71 | CZ20: 928144.71 | DA20: 928144.71 | DB20: 951348.33 | DC20: 951348.33 | DD20: 951348.33 | DE20: 951348.33 | DF20: 951348.33 | DG20: 951348.33 | DH20: 951348.33 | DI20: 951348.33 | DJ20: 951348.33 | DK20: 951348.33 | DL20: 951348.33 | DM20: 951348.33 | DN20: 975132.04 | DO20: 975132.04 | DP20: 975132.04 | DQ20: 975132.04 | DR20: 975132.04 | DS20: 975132.04 | DT20: 975132.04 | DU20: 975132.04 | DV20: 975132.04 | DW20: 975132.04 | DX20: 975132.04 | DY20: 975132.04
E21: Property E | G21: USD | H21: 78789382 | J21: 563230.5 | K21: 563230.5 | L21: 563230.5 | M21: 563230.5 | N21: 563230.5 | O21: 563230.5 | P21: 563230.5 | Q21: 563230.5 | R21: 563230.5 | S21: 563230.5 | T21: 563230.5 | U21: 563230.5 | V21: 588575.87 | W21: 588575.87 | X21: 588575.87 | Y21: 588575.87 | Z21: 588575.87 | AA21: 588575.87 | AB21: 588575.87 | AC21: 588575.87 | AD21: 588575.87 | AE21: 588575.87 | AF21: 588575.87 | AG21: 588575.87 | AH21: 612118.91 | AI21: 612118.91 | AJ21: 612118.91 | AK21: 612118.91 | AL21: 612118.91 | AM21: 612118.91 | AN21: 612118.91 | AO21: 612118.91 | AP21: 612118.91 | AQ21: 612118.91 | AR21: 612118.91 | AS21: 612118.91 | AT21: 633543.07 | AU21: 633543.07 | AV21: 633543.07 | AW21: 633543.07 | AX21: 633543.07 | AY21: 633543.07 | AZ21: 633543.07 | BA21: 633543.07 | BB21: 633543.07 | BC21: 633543.07 | BD21: 633543.07 | BE21: 633543.07 | BF21: 652549.36 | BG21: 652549.36 | BH21: 652549.36 | BI21: 652549.36 | BJ21: 652549.36 | BK21: 652549.36 | BL21: 652549.36 | BM21: 652549.36 | BN21: 652549.36 | BO21: 652549.36 | BP21: 652549.36 | BQ21: 652549.36 | BR21: 668863.1 | BS21: 668863.1 | BT21: 668863.1 | BU21: 668863.1 | BV21: 668863.1 | BW21: 668863.1 | BX21: 668863.1 | BY21: 668863.1 | BZ21: 668863.1 | CA21: 668863.1 | CB21: 668863.1 | CC21: 668863.1 | CD21: 685584.67 | CE21: 685584.67 | CF21: 685584.67 | CG21: 685584.67 | CH21: 685584.67 | CI21: 685584.67 | CJ21: 685584.67 | CK21: 685584.67 | CL21: 685584.67 | CM21: 685584.67 | CN21: 685584.67 | CO21: 685584.67 | CP21: 702724.29 | CQ21: 702724.29 | CR21: 702724.29 | CS21: 702724.29 | CT21: 702724.29 | CU21: 702724.29 | CV21: 702724.29 | CW21: 702724.29 | CX21: 702724.29 | CY21: 702724.29 | CZ21: 702724.29 | DA21: 702724.29 | DB21: 720292.4 | DC21: 720292.4 | DD21: 720292.4 | DE21: 720292.4 | DF21: 720292.4 | DG21: 720292.4 | DH21: 720292.4 | DI21: 720292.4 | DJ21: 720292.4 | DK21: 720292.4 | DL21: 720292.4 | DM21: 720292.4 | DN21: 738299.71 | DO21: 738299.71 | DP21: 738299.71 | DQ21: 738299.71 | DR21: 738299.71 | DS21: 738299.71 | DT21: 738299.71 | DU21: 738299.71 | DV21: 738299.71 | DW21: 738299.71 | DX21: 738299.71 | DY21: 738299.71
E22: Rent revenue from existing properties | G22: USD | H22: {=_xlfn.BYROW(_xlfn.ANCHORARRAY( J22), _xleta.SUM )} -> 4.4914105e+08 | J22: {=_xlfn.BYCOL(_xlfn.ANCHORARRAY( J17), _xleta.SUM )} -> 3210711 | K22: 3210711 | L22: 3210711 | M22: 3210711 | N22: 3210711 | O22: 3210711 | P22: 3210711 | Q22: 3210711 | R22: 3210711 | S22: 3210711 | T22: 3210711 | U22: 3210711 | V22: 3355193 | W22: 3355193 | X22: 3355193 | Y22: 3355193 | Z22: 3355193 | AA22: 3355193 | AB22: 3355193 | AC22: 3355193 | AD22: 3355193 | AE22: 3355193 | AF22: 3355193 | AG22: 3355193 | AH22: 3489400.7 | AI22: 3489400.7 | AJ22: 3489400.7 | AK22: 3489400.7 | AL22: 3489400.7 | AM22: 3489400.7 | AN22: 3489400.7 | AO22: 3489400.7 | AP22: 3489400.7 | AQ22: 3489400.7 | AR22: 3489400.7 | AS22: 3489400.7 | AT22: 3611529.7 | AU22: 3611529.7 | AV22: 3611529.7 | AW22: 3611529.7 | AX22: 3611529.7 | AY22: 3611529.7 | AZ22: 3611529.7 | BA22: 3611529.7 | BB22: 3611529.7 | BC22: 3611529.7 | BD22: 3611529.7 | BE22: 3611529.7 | BF22: 3719875.6 | BG22: 3719875.6 | BH22: 3719875.6 | BI22: 3719875.6 | BJ22: 3719875.6 | BK22: 3719875.6 | BL22: 3719875.6 | BM22: 3719875.6 | BN22: 3719875.6 | BO22: 3719875.6 | BP22: 3719875.6 | BQ22: 3719875.6 | BR22: 3812872.5 | BS22: 3812872.5 | BT22: 3812872.5 | BU22: 3812872.5 | BV22: 3812872.5 | BW22: 3812872.5 | BX22: 3812872.5 | BY22: 3812872.5 | BZ22: 3812872.5 | CA22: 3812872.5 | CB22: 3812872.5 | CC22: 3812872.5 | CD22: 3908194.3 | CE22: 3908194.3 | CF22: 3908194.3 | CG22: 3908194.3 | CH22: 3908194.3 | CI22: 3908194.3 | CJ22: 3908194.3 | CK22: 3908194.3 | CL22: 3908194.3 | CM22: 3908194.3 | CN22: 3908194.3 | CO22: 3908194.3 | CP22: 4005899.2 | CQ22: 4005899.2 | CR22: 4005899.2 | CS22: 4005899.2 | CT22: 4005899.2 | CU22: 4005899.2 | CV22: 4005899.2 | CW22: 4005899.2 | CX22: 4005899.2 | CY22: 4005899.2 | CZ22: 4005899.2 | DA22: 4005899.2 | DB22: 4106046.7 | DC22: 4106046.7 | DD22: 4106046.7 | DE22: 4106046.7 | DF22: 4106046.7 | DG22: 4106046.7 | DH22: 4106046.7 | DI22: 4106046.7 | DJ22: 4106046.7 | DK22: 4106046.7 | DL22: 4106046.7 | DM22: 4106046.7 | DN22: 4208697.8 | DO22: 4208697.8 | DP22: 4208697.8 | DQ22: 4208697.8 | DR22: 4208697.8 | DS22: 4208697.8 | DT22: 4208697.8 | DU22: 4208697.8 | DV22: 4208697.8 | DW22: 4208697.8 | DX22: 4208697.8 | DY22: 4208697.8
C25: OPEX
C26: (adjusted for inflation)
E27: {=INDEX( CaseData!$A$6:$D$10,, 1 )} -> Property A | G27: USD | H27: {=_xlfn.BYROW(_xlfn.ANCHORARRAY( J27), _xleta.SUM )} -> 27250266 | J27: {=_xlfn.LET( _xlpm.timeline,_xlfn.ANCHORARRAY( $J$3), _xlpm.inflation_flag, IF( MONTH( _xlpm.timeline ) = 1, 1, 0 ), _xlpm.inflation_data, CaseData!$J$15:$M$24, _xlpm.annual_rate, _xlfn.XLOOKUP( YEAR( _xlpm.timeline ), INDEX( _xlpm.inflation_data,, 1 ), INDEX( _xlpm.inflation_data,, 3 ) ), _xlpm.effective_step, _xlpm.inflation_flag * _xlpm.annual_rate, _xlpm.inflation_factor, _xlfn.SCAN( 1, _xlpm.effective_step, _xlfn.LAMBDA(_xlpm.prev,_xlpm.step, IF( _xlpm.step = 0, _xlpm.prev, _xlpm.prev * ( 1 + _xlpm.step ) ) ) ), _xlpm.property_data, CaseData!$A$6:$D$10, _xlpm.opex, INDEX( _xlpm.property_data,, 4 ), _xlpm.opex * _xlpm.inflation_factor )} -> 202693.75 | K27: 202693.75 | L27: 202693.75 | M27: 202693.75 | N27: 202693.75 | O27: 202693.75 | P27: 202693.75 | Q27: 202693.75 | R27: 202693.75 | S27: 202693.75 | T27: 202693.75 | U27: 202693.75 | V27: 207761.09 | W27: 207761.09 | X27: 207761.09 | Y27: 207761.09 | Z27: 207761.09 | AA27: 207761.09 | AB27: 207761.09 | AC27: 207761.09 | AD27: 207761.09 | AE27: 207761.09 | AF27: 207761.09 | AG27: 207761.09 | AH27: 212955.12 | AI27: 212955.12 | AJ27: 212955.12 | AK27: 212955.12 | AL27: 212955.12 | AM27: 212955.12 | AN27: 212955.12 | AO27: 212955.12 | AP27: 212955.12 | AQ27: 212955.12 | AR27: 212955.12 | AS27: 212955.12 | AT27: 218279 | AU27: 218279 | AV27: 218279 | AW27: 218279 | AX27: 218279 | AY27: 218279 | AZ27: 218279 | BA27: 218279 | BB27: 218279 | BC27: 218279 | BD27: 218279 | BE27: 218279 | BF27: 223735.97 | BG27: 223735.97 | BH27: 223735.97 | BI27: 223735.97 | BJ27: 223735.97 | BK27: 223735.97 | BL27: 223735.97 | BM27: 223735.97 | BN27: 223735.97 | BO27: 223735.97 | BP27: 223735.97 | BQ27: 223735.97 | BR27: 229329.37 | BS27: 229329.37 | BT27: 229329.37 | BU27: 229329.37 | BV27: 229329.37 | BW27: 229329.37 | BX27: 229329.37 | BY27: 229329.37 | BZ27: 229329.37 | CA27: 229329.37 | CB27: 229329.37 | CC27: 229329.37 | CD27: 235062.61 | CE27: 235062.61 | CF27: 235062.61 | CG27: 235062.61 | CH27: 235062.61 | CI27: 235062.61 | CJ27: 235062.61 | CK27: 235062.61 | CL27: 235062.61 | CM27: 235062.61 | CN27: 235062.61 | CO27: 235062.61 | CP27: 240939.17 | CQ27: 240939.17 | CR27: 240939.17 | CS27: 240939.17 | CT27: 240939.17 | CU27: 240939.17 | CV27: 240939.17 | CW27: 240939.17 | CX27: 240939.17 | CY27: 240939.17 | CZ27: 240939.17 | DA27: 240939.17 | DB27: 246962.65 | DC27: 246962.65 | DD27: 246962.65 | DE27: 246962.65 | DF27: 246962.65 | DG27: 246962.65 | DH27: 246962.65 | DI27: 246962.65 | DJ27: 246962.65 | DK27: 246962.65 | DL27: 246962.65 | DM27: 246962.65 | DN27: 253136.72 | DO27: 253136.72 | DP27: 253136.72 | DQ27: 253136.72 | DR27: 253136.72 | DS27: 253136.72 | DT27: 253136.72 | DU27: 253136.72 | DV27: 253136.72 | DW27: 253136.72 | DX27: 253136.72 | DY27: 253136.72
E28: Property B | G28: USD | H28: 21607290 | J28: 160720 | K28: 160720 | L28: 160720 | M28: 160720 | N28: 160720 | O28: 160720 | P28: 160720 | Q28: 160720 | R28: 160720 | S28: 160720 | T28: 160720 | U28: 160720 | V28: 164738 | W28: 164738 | X28: 164738 | Y28: 164738 | Z28: 164738 | AA28: 164738 | AB28: 164738 | AC28: 164738 | AD28: 164738 | AE28: 164738 | AF28: 164738 | AG28: 164738 | AH28: 168856.45 | AI28: 168856.45 | AJ28: 168856.45 | AK28: 168856.45 | AL28: 168856.45 | AM28: 168856.45 | AN28: 168856.45 | AO28: 168856.45 | AP28: 168856.45 | AQ28: 168856.45 | AR28: 168856.45 | AS28: 168856.45 | AT28: 173077.86 | AU28: 173077.86 | AV28: 173077.86 | AW28: 173077.86 | AX28: 173077.86 | AY28: 173077.86 | AZ28: 173077.86 | BA28: 173077.86 | BB28: 173077.86 | BC28: 173077.86 | BD28: 173077.86 | BE28: 173077.86 | BF28: 177404.81 | BG28: 177404.81 | BH28: 177404.81 | BI28: 177404.81 | BJ28: 177404.81 | BK28: 177404.81 | BL28: 177404.81 | BM28: 177404.81 | BN28: 177404.81 | BO28: 177404.81 | BP28: 177404.81 | BQ28: 177404.81 | BR28: 181839.93 | BS28: 181839.93 | BT28: 181839.93 | BU28: 181839.93 | BV28: 181839.93 | BW28: 181839.93 | BX28: 181839.93 | BY28: 181839.93 | BZ28: 181839.93 | CA28: 181839.93 | CB28: 181839.93 | CC28: 181839.93 | CD28: 186385.93 | CE28: 186385.93 | CF28: 186385.93 | CG28: 186385.93 | CH28: 186385.93 | CI28: 186385.93 | CJ28: 186385.93 | CK28: 186385.93 | CL28: 186385.93 | CM28: 186385.93 | CN28: 186385.93 | CO28: 186385.93 | CP28: 191045.57 | CQ28: 191045.57 | CR28: 191045.57 | CS28: 191045.57 | CT28: 191045.57 | CU28: 191045.57 | CV28: 191045.57 | CW28: 191045.57 | CX28: 191045.57 | CY28: 191045.57 | CZ28: 191045.57 | DA28: 191045.57 | DB28: 195821.71 | DC28: 195821.71 | DD28: 195821.71 | DE28: 195821.71 | DF28: 195821.71 | DG28: 195821.71 | DH28: 195821.71 | DI28: 195821.71 | DJ28: 195821.71 | DK28: 195821.71 | DL28: 195821.71 | DM28: 195821.71 | DN28: 200717.26 | DO28: 200717.26 | DP28: 200717.26 | DQ28: 200717.26 | DR28: 200717.26 | DS28: 200717.26 | DT28: 200717.26 | DU28: 200717.26 | DV28: 200717.26 | DW28: 200717.26 | DX28: 200717.26 | DY28: 200717.26
E29: Property C | G29: USD | H29: 23632974 | J29: 175787.5 | K29: 175787.5 | L29: 175787.5 | M29: 175787.5 | N29: 175787.5 | O29: 175787.5 | P29: 175787.5 | Q29: 175787.5 | R29: 175787.5 | S29: 175787.5 | T29: 175787.5 | U29: 175787.5 | V29: 180182.19 | W29: 180182.19 | X29: 180182.19 | Y29: 180182.19 | Z29: 180182.19 | AA29: 180182.19 | AB29: 180182.19 | AC29: 180182.19 | AD29: 180182.19 | AE29: 180182.19 | AF29: 180182.19 | AG29: 180182.19 | AH29: 184686.74 | AI29: 184686.74 | AJ29: 184686.74 | AK29: 184686.74 | AL29: 184686.74 | AM29: 184686.74 | AN29: 184686.74 | AO29: 184686.74 | AP29: 184686.74 | AQ29: 184686.74 | AR29: 184686.74 | AS29: 184686.74 | AT29: 189303.91 | AU29: 189303.91 | AV29: 189303.91 | AW29: 189303.91 | AX29: 189303.91 | AY29: 189303.91 | AZ29: 189303.91 | BA29: 189303.91 | BB29: 189303.91 | BC29: 189303.91 | BD29: 189303.91 | BE29: 189303.91 | BF29: 194036.51 | BG29: 194036.51 | BH29: 194036.51 | BI29: 194036.51 | BJ29: 194036.51 | BK29: 194036.51 | BL29: 194036.51 | BM29: 194036.51 | BN29: 194036.51 | BO29: 194036.51 | BP29: 194036.51 | BQ29: 194036.51 | BR29: 198887.42 | BS29: 198887.42 | BT29: 198887.42 | BU29: 198887.42 | BV29: 198887.42 | BW29: 198887.42 | BX29: 198887.42 | BY29: 198887.42 | BZ29: 198887.42 | CA29: 198887.42 | CB29: 198887.42 | CC29: 198887.42 | CD29: 203859.61 | CE29: 203859.61 | CF29: 203859.61 | CG29: 203859.61 | CH29: 203859.61 | CI29: 203859.61 | CJ29: 203859.61 | CK29: 203859.61 | CL29: 203859.61 | CM29: 203859.61 | CN29: 203859.61 | CO29: 203859.61 | CP29: 208956.1 | CQ29: 208956.1 | CR29: 208956.1 | CS29: 208956.1 | CT29: 208956.1 | CU29: 208956.1 | CV29: 208956.1 | CW29: 208956.1 | CX29: 208956.1 | CY29: 208956.1 | CZ29: 208956.1 | DA29: 208956.1 | DB29: 214180 | DC29: 214180 | DD29: 214180 | DE29: 214180 | DF29: 214180 | DG29: 214180 | DH29: 214180 | DI29: 214180 | DJ29: 214180 | DK29: 214180 | DL29: 214180 | DM29: 214180 | DN29: 219534.5 | DO29: 219534.5 | DP29: 219534.5 | DQ29: 219534.5 | DR29: 219534.5 | DS29: 219534.5 | DT29: 219534.5 | DU29: 219534.5 | DV29: 219534.5 | DW29: 219534.5 | DX29: 219534.5 | DY29: 219534.5
E30: Property D | G30: USD | H30: 28475322 | J30: 211806 | K30: 211806 | L30: 211806 | M30: 211806 | N30: 211806 | O30: 211806 | P30: 211806 | Q30: 211806 | R30: 211806 | S30: 211806 | T30: 211806 | U30: 211806 | V30: 217101.15 | W30: 217101.15 | X30: 217101.15 | Y30: 217101.15 | Z30: 217101.15 | AA30: 217101.15 | AB30: 217101.15 | AC30: 217101.15 | AD30: 217101.15 | AE30: 217101.15 | AF30: 217101.15 | AG30: 217101.15 | AH30: 222528.68 | AI30: 222528.68 | AJ30: 222528.68 | AK30: 222528.68 | AL30: 222528.68 | AM30: 222528.68 | AN30: 222528.68 | AO30: 222528.68 | AP30: 222528.68 | AQ30: 222528.68 | AR30: 222528.68 | AS30: 222528.68 | AT30: 228091.9 | AU30: 228091.9 | AV30: 228091.9 | AW30: 228091.9 | AX30: 228091.9 | AY30: 228091.9 | AZ30: 228091.9 | BA30: 228091.9 | BB30: 228091.9 | BC30: 228091.9 | BD30: 228091.9 | BE30: 228091.9 | BF30: 233794.19 | BG30: 233794.19 | BH30: 233794.19 | BI30: 233794.19 | BJ30: 233794.19 | BK30: 233794.19 | BL30: 233794.19 | BM30: 233794.19 | BN30: 233794.19 | BO30: 233794.19 | BP30: 233794.19 | BQ30: 233794.19 | BR30: 239639.05 | BS30: 239639.05 | BT30: 239639.05 | BU30: 239639.05 | BV30: 239639.05 | BW30: 239639.05 | BX30: 239639.05 | BY30: 239639.05 | BZ30: 239639.05 | CA30: 239639.05 | CB30: 239639.05 | CC30: 239639.05 | CD30: 245630.02 | CE30: 245630.02 | CF30: 245630.02 | CG30: 245630.02 | CH30: 245630.02 | CI30: 245630.02 | CJ30: 245630.02 | CK30: 245630.02 | CL30: 245630.02 | CM30: 245630.02 | CN30: 245630.02 | CO30: 245630.02 | CP30: 251770.77 | CQ30: 251770.77 | CR30: 251770.77 | CS30: 251770.77 | CT30: 251770.77 | CU30: 251770.77 | CV30: 251770.77 | CW30: 251770.77 | CX30: 251770.77 | CY30: 251770.77 | CZ30: 251770.77 | DA30: 251770.77 | DB30: 258065.04 | DC30: 258065.04 | DD30: 258065.04 | DE30: 258065.04 | DF30: 258065.04 | DG30: 258065.04 | DH30: 258065.04 | DI30: 258065.04 | DJ30: 258065.04 | DK30: 258065.04 | DL30: 258065.04 | DM30: 258065.04 | DN30: 264516.67 | DO30: 264516.67 | DP30: 264516.67 | DQ30: 264516.67 | DR30: 264516.67 | DS30: 264516.67 | DT30: 264516.67 | DU30: 264516.67 | DV30: 264516.67 | DW30: 264516.67 | DX30: 264516.67 | DY30: 264516.67
E31: Property E | G31: USD | H31: 24385370 | J31: 181384 | K31: 181384 | L31: 181384 | M31: 181384 | N31: 181384 | O31: 181384 | P31: 181384 | Q31: 181384 | R31: 181384 | S31: 181384 | T31: 181384 | U31: 181384 | V31: 185918.6 | W31: 185918.6 | X31: 185918.6 | Y31: 185918.6 | Z31: 185918.6 | AA31: 185918.6 | AB31: 185918.6 | AC31: 185918.6 | AD31: 185918.6 | AE31: 185918.6 | AF31: 185918.6 | AG31: 185918.6 | AH31: 190566.56 | AI31: 190566.56 | AJ31: 190566.56 | AK31: 190566.56 | AL31: 190566.56 | AM31: 190566.56 | AN31: 190566.56 | AO31: 190566.56 | AP31: 190566.56 | AQ31: 190566.56 | AR31: 190566.56 | AS31: 190566.56 | AT31: 195330.73 | AU31: 195330.73 | AV31: 195330.73 | AW31: 195330.73 | AX31: 195330.73 | AY31: 195330.73 | AZ31: 195330.73 | BA31: 195330.73 | BB31: 195330.73 | BC31: 195330.73 | BD31: 195330.73 | BE31: 195330.73 | BF31: 200214 | BG31: 200214 | BH31: 200214 | BI31: 200214 | BJ31: 200214 | BK31: 200214 | BL31: 200214 | BM31: 200214 | BN31: 200214 | BO31: 200214 | BP31: 200214 | BQ31: 200214 | BR31: 205219.35 | BS31: 205219.35 | BT31: 205219.35 | BU31: 205219.35 | BV31: 205219.35 | BW31: 205219.35 | BX31: 205219.35 | BY31: 205219.35 | BZ31: 205219.35 | CA31: 205219.35 | CB31: 205219.35 | CC31: 205219.35 | CD31: 210349.83 | CE31: 210349.83 | CF31: 210349.83 | CG31: 210349.83 | CH31: 210349.83 | CI31: 210349.83 | CJ31: 210349.83 | CK31: 210349.83 | CL31: 210349.83 | CM31: 210349.83 | CN31: 210349.83 | CO31: 210349.83 | CP31: 215608.58 | CQ31: 215608.58 | CR31: 215608.58 | CS31: 215608.58 | CT31: 215608.58 | CU31: 215608.58 | CV31: 215608.58 | CW31: 215608.58 | CX31: 215608.58 | CY31: 215608.58 | CZ31: 215608.58 | DA31: 215608.58 | DB31: 220998.79 | DC31: 220998.79 | DD31: 220998.79 | DE31: 220998.79 | DF31: 220998.79 | DG31: 220998.79 | DH31: 220998.79 | DI31: 220998.79 | DJ31: 220998.79 | DK31: 220998.79 | DL31: 220998.79 | DM31: 220998.79 | DN31: 226523.76 | DO31: 226523.76 | DP31: 226523.76 | DQ31: 226523.76 | DR31: 226523.76 | DS31: 226523.76 | DT31: 226523.76 | DU31: 226523.76 | DV31: 226523.76 | DW31: 226523.76 | DX31: 226523.76 | DY31: 226523.76
E32: Opex from existing properties | G32: USD | H32: {=_xlfn.BYROW(_xlfn.ANCHORARRAY( J32), _xleta.SUM )} -> 1.2535122e+08 | J32: {=_xlfn.BYCOL(_xlfn.ANCHORARRAY( J27), _xleta.SUM )} -> 932391.25 | K32: 932391.25 | L32: 932391.25 | M32: 932391.25 | N32: 932391.25 | O32: 932391.25 | P32: 932391.25 | Q32: 932391.25 | R32: 932391.25 | S32: 932391.25 | T32: 932391.25 | U32: 932391.25 | V32: 955701.03 | W32: 955701.03 | X32: 955701.03 | Y32: 955701.03 | Z32: 955701.03 | AA32: 955701.03 | AB32: 955701.03 | AC32: 955701.03 | AD32: 955701.03 | AE32: 955701.03 | AF32: 955701.03 | AG32: 955701.03 | AH32: 979593.56 | AI32: 979593.56 | AJ32: 979593.56 | AK32: 979593.56 | AL32: 979593.56 | AM32: 979593.56 | AN32: 979593.56 | AO32: 979593.56 | AP32: 979593.56 | AQ32: 979593.56 | AR32: 979593.56 | AS32: 979593.56 | AT32: 1004083.4 | AU32: 1004083.4 | AV32: 1004083.4 | AW32: 1004083.4 | AX32: 1004083.4 | AY32: 1004083.4 | AZ32: 1004083.4 | BA32: 1004083.4 | BB32: 1004083.4 | BC32: 1004083.4 | BD32: 1004083.4 | BE32: 1004083.4 | BF32: 1029185.5 | BG32: 1029185.5 | BH32: 1029185.5 | BI32: 1029185.5 | BJ32: 1029185.5 | BK32: 1029185.5 | BL32: 1029185.5 | BM32: 1029185.5 | BN32: 1029185.5 | BO32: 1029185.5 | BP32: 1029185.5 | BQ32: 1029185.5 | BR32: 1054915.1 | BS32: 1054915.1 | BT32: 1054915.1 | BU32: 1054915.1 | BV32: 1054915.1 | BW32: 1054915.1 | BX32: 1054915.1 | BY32: 1054915.1 | BZ32: 1054915.1 | CA32: 1054915.1 | CB32: 1054915.1 | CC32: 1054915.1 | CD32: 1081288 | CE32: 1081288 | CF32: 1081288 | CG32: 1081288 | CH32: 1081288 | CI32: 1081288 | CJ32: 1081288 | CK32: 1081288 | CL32: 1081288 | CM32: 1081288 | CN32: 1081288 | CO32: 1081288 | CP32: 1108320.2 | CQ32: 1108320.2 | CR32: 1108320.2 | CS32: 1108320.2 | CT32: 1108320.2 | CU32: 1108320.2 | CV32: 1108320.2 | CW32: 1108320.2 | CX32: 1108320.2 | CY32: 1108320.2 | CZ32: 1108320.2 | DA32: 1108320.2 | DB32: 1136028.2 | DC32: 1136028.2 | DD32: 1136028.2 | DE32: 1136028.2 | DF32: 1136028.2 | DG32: 1136028.2 | DH32: 1136028.2 | DI32: 1136028.2 | DJ32: 1136028.2 | DK32: 1136028.2 | DL32: 1136028.2 | DM32: 1136028.2 | DN32: 1164428.9 | DO32: 1164428.9 | DP32: 1164428.9 | DQ32: 1164428.9 | DR32: 1164428.9 | DS32: 1164428.9 | DT32: 1164428.9 | DU32: 1164428.9 | DV32: 1164428.9 | DW32: 1164428.9 | DX32: 1164428.9 | DY32: 1164428.9
A34: New properties
C37: Land acquisition
C38: (adjusted for inflation)
E39: {=_xlfn.LET( _xlpm.property_data, CaseData!$A$15:$H$24, _xlfn.CHOOSECOLS( _xlpm.property_data, 1 ) )} -> Property F | G39: USD | J39: {=_xlfn.LET( _xlpm.timeline,_xlfn.ANCHORARRAY( $J$3), _xlpm.properties_data, CaseData!$A$15:$H$24, _xlpm.project_start, IF( $F$9 = 0, 0, 12 ), _xlpm.land_acquisition, _xlfn.MAKEARRAY( ROWS( _xlpm.properties_data ), COLUMNS( _xlpm.timeline ), _xlfn.LAMBDA(_xlpm.r,_xlpm.c, IF( INDEX( _xlpm.timeline, _xlpm.c ) = EOMONTH( INDEX( _xlpm.properties_data, _xlpm.r, 6), _xlpm.project_start), INDEX( _xlpm.properties_data, _xlpm.r, 4), 0 ) ) ), _xlpm.inflation_flag, IF( MONTH( _xlpm.timeline ) = 1, 1, 0 ), _xlpm.inflation_data, CaseData!$J$15:$M$24, _xlpm.annual_rate, _xlfn.XLOOKUP( YEAR( _xlpm.timeline ), INDEX( _xlpm.inflation_data,, 1 ), INDEX( _xlpm.inflation_data,, 4 ) ), _xlpm.effective_step, _xlpm.inflation_flag * _xlpm.annual_rate, _xlpm.inflation_factor, _xlfn.SCAN( 1, _xlpm.effective_step, _xlfn.LAMBDA(_xlpm.prev,_xlpm.step, IF( _xlpm.step = 0, _xlpm.prev, _xlpm.prev * ( 1 + _xlpm.step ) ) ) ), _xlpm.land_acquisition * _xlpm.inflation_factor )} -> 4316130 | K39: 0 | L39: 0 | M39: 0 | N39: 0 | O39: 0 | P39: 0 | Q39: 0 | R39: 0 | S39: 0 | T39: 0 | U39: 0 | V39: 0 | W39: 0 | X39: 0 | Y39: 0 | Z39: 0 | AA39: 0 | AB39: 0 | AC39: 0 | AD39: 0 | AE39: 0 | AF39: 0 | AG39: 0 | AH39: 0 | AI39: 0 | AJ39: 0 | AK39: 0 | AL39: 0 | AM39: 0 | AN39: 0 | AO39: 0 | AP39: 0 | AQ39: 0 | AR39: 0 | AS39: 0 | AT39: 0 | AU39: 0 | AV39: 0 | AW39: 0 | AX39: 0 | AY39: 0 | AZ39: 0 | BA39: 0 | BB39: 0 | BC39: 0 | BD39: 0 | BE39: 0 | BF39: 0 | BG39: 0 | BH39: 0 | BI39: 0 | BJ39: 0 | BK39: 0 | BL39: 0 | BM39: 0 | BN39: 0 | BO39: 0 | BP39: 0 | BQ39: 0 | BR39: 0 | BS39: 0 | BT39: 0 | BU39: 0 | BV39: 0 | BW39: 0 | BX39: 0 | BY39: 0 | BZ39: 0 | CA39: 0 | CB39: 0 | CC39: 0 | CD39: 0 | CE39: 0 | CF39: 0 | CG39: 0 | CH39: 0 | CI39: 0 | CJ39: 0 | CK39: 0 | CL39: 0 | CM39: 0 | CN39: 0 | CO39: 0 | CP39: 0 | CQ39: 0 | CR39: 0 | CS39: 0 | CT39: 0 | CU39: 0 | CV39: 0 | CW39: 0 | CX39: 0 | CY39: 0 | CZ39: 0 | DA39: 0 | DB39: 0 | DC39: 0 | DD39: 0 | DE39: 0 | DF39: 0 | DG39: 0 | DH39: 0 | DI39: 0 | DJ39: 0 | DK39: 0 | DL39: 0 | DM39: 0 | DN39: 0 | DO39: 0 | DP39: 0 | DQ39: 0 | DR39: 0 | DS39: 0 | DT39: 0 | DU39: 0 | DV39: 0 | DW39: 0 | DX39: 0 | DY39: 0
E40: Property G | G40: USD | J40: 0 | K40: 0 | L40: 0 | M40: 3908898 | N40: 0 | O40: 0 | P40: 0 | Q40: 0 | R40: 0 | S40: 0 | T40: 0 | U40: 0 | V40: 0 | W40: 0 | X40: 0 | Y40: 0 | Z40: 0 | AA40: 0 | AB40: 0 | AC40: 0 | AD40: 0 | AE40: 0 | AF40: 0 | AG40: 0 | AH40: 0 | AI40: 0 | AJ40: 0 | AK40: 0 | AL40: 0 | AM40: 0 | AN40: 0 | AO40: 0 | AP40: 0 | AQ40: 0 | AR40: 0 | AS40: 0 | AT40: 0 | AU40: 0 | AV40: 0 | AW40: 0 | AX40: 0 | AY40: 0 | AZ40: 0 | BA40: 0 | BB40: 0 | BC40: 0 | BD40: 0 | BE40: 0 | BF40: 0 | BG40: 0 | BH40: 0 | BI40: 0 | BJ40: 0 | BK40: 0 | BL40: 0 | BM40: 0 | BN40: 0 | BO40: 0 | BP40: 0 | BQ40: 0 | BR40: 0 | BS40: 0 | BT40: 0 | BU40: 0 | BV40: 0 | BW40: 0 | BX40: 0 | BY40: 0 | BZ40: 0 | CA40: 0 | CB40: 0 | CC40: 0 | CD40: 0 | CE40: 0 | CF40: 0 | CG40: 0 | CH40: 0 | CI40: 0 | CJ40: 0 | CK40: 0 | CL40: 0 | CM40: 0 | CN40: 0 | CO40: 0 | CP40: 0 | CQ40: 0 | CR40: 0 | CS40: 0 | CT40: 0 | CU40: 0 | CV40: 0 | CW40: 0 | CX40: 0 | CY40: 0 | CZ40: 0 | DA40: 0 | DB40: 0 | DC40: 0 | DD40: 0 | DE40: 0 | DF40: 0 | DG40: 0 | DH40: 0 | DI40: 0 | DJ40: 0 | DK40: 0 | DL40: 0 | DM40: 0 | DN40: 0 | DO40: 0 | DP40: 0 | DQ40: 0 | DR40: 0 | DS40: 0 | DT40: 0 | DU40: 0 | DV40: 0 | DW40: 0 | DX40: 0 | DY40: 0
E41: Property H | G41: USD | J41: 0 | K41: 0 | L41: 0 | M41: 0 | N41: 0 | O41: 0 | P41: 4936701 | Q41: 0 | R41: 0 | S41: 0 | T41: 0 | U41: 0 | V41: 0 | W41: 0 | X41: 0 | Y41: 0 | Z41: 0 | AA41: 0 | AB41: 0 | AC41: 0 | AD41: 0 | AE41: 0 | AF41: 0 | AG41: 0 | AH41: 0 | AI41: 0 | AJ41: 0 | AK41: 0 | AL41: 0 | AM41: 0 | AN41: 0 | AO41: 0 | AP41: 0 | AQ41: 0 | AR41: 0 | AS41: 0 | AT41: 0 | AU41: 0 | AV41: 0 | AW41: 0 | AX41: 0 | AY41: 0 | AZ41: 0 | BA41: 0 | BB41: 0 | BC41: 0 | BD41: 0 | BE41: 0 | BF41: 0 | BG41: 0 | BH41: 0 | BI41: 0 | BJ41: 0 | BK41: 0 | BL41: 0 | BM41: 0 | BN41: 0 | BO41: 0 | BP41: 0 | BQ41: 0 | BR41: 0 | BS41: 0 | BT41: 0 | BU41: 0 | BV41: 0 | BW41: 0 | BX41: 0 | BY41: 0 | BZ41: 0 | CA41: 0 | CB41: 0 | CC41: 0 | CD41: 0 | CE41: 0 | CF41: 0 | CG41: 0 | CH41: 0 | CI41: 0 | CJ41: 0 | CK41: 0 | CL41: 0 | CM41: 0 | CN41: 0 | CO41: 0 | CP41: 0 | CQ41: 0 | CR41: 0 | CS41: 0 | CT41: 0 | CU41: 0 | CV41: 0 | CW41: 0 | CX41: 0 | CY41: 0 | CZ41: 0 | DA41: 0 | DB41: 0 | DC41: 0 | DD41: 0 | DE41: 0 | DF41: 0 | DG41: 0 | DH41: 0 | DI41: 0 | DJ41: 0 | DK41: 0 | DL41: 0 | DM41: 0 | DN41: 0 | DO41: 0 | DP41: 0 | DQ41: 0 | DR41: 0 | DS41: 0 | DT41: 0 | DU41: 0 | DV41: 0 | DW41: 0 | DX41: 0 | DY41: 0
E42: Property I | G42: USD | J42: 0 | K42: 0 | L42: 0 | M42: 0 | N42: 0 | O42: 0 | P42: 0 | Q42: 0 | R42: 0 | S42: 6597360 | T42: 0 | U42: 0 | V42: 0 | W42: 0 | X42: 0 | Y42: 0 | Z42: 0 | AA42: 0 | AB42: 0 | AC42: 0 | AD42: 0 | AE42: 0 | AF42: 0 | AG42: 0 | AH42: 0 | AI42: 0 | AJ42: 0 | AK42: 0 | AL42: 0 | AM42: 0 | AN42: 0 | AO42: 0 | AP42: 0 | AQ42: 0 | AR42: 0 | AS42: 0 | AT42: 0 | AU42: 0 | AV42: 0 | AW42: 0 | AX42: 0 | AY42: 0 | AZ42: 0 | BA42: 0 | BB42: 0 | BC42: 0 | BD42: 0 | BE42: 0 | BF42: 0 | BG42: 0 | BH42: 0 | BI42: 0 | BJ42: 0 | BK42: 0 | BL42: 0 | BM42: 0 | BN42: 0 | BO42: 0 | BP42: 0 | BQ42: 0 | BR42: 0 | BS42: 0 | BT42: 0 | BU42: 0 | BV42: 0 | BW42: 0 | BX42: 0 | BY42: 0 | BZ42: 0 | CA42: 0 | CB42: 0 | CC42: 0 | CD42: 0 | CE42: 0 | CF42: 0 | CG42: 0 | CH42: 0 | CI42: 0 | CJ42: 0 | CK42: 0 | CL42: 0 | CM42: 0 | CN42: 0 | CO42: 0 | CP42: 0 | CQ42: 0 | CR42: 0 | CS42: 0 | CT42: 0 | CU42: 0 | CV42: 0 | CW42: 0 | CX42: 0 | CY42: 0 | CZ42: 0 | DA42: 0 | DB42: 0 | DC42: 0 | DD42: 0 | DE42: 0 | DF42: 0 | DG42: 0 | DH42: 0 | DI42: 0 | DJ42: 0 | DK42: 0 | DL42: 0 | DM42: 0 | DN42: 0 | DO42: 0 | DP42: 0 | DQ42: 0 | DR42: 0 | DS42: 0 | DT42: 0 | DU42: 0 | DV42: 0 | DW42: 0 | DX42: 0 | DY42: 0
E43: Property J | G43: USD | J43: 0 | K43: 0 | L43: 0 | M43: 0 | N43: 0 | O43: 0 | P43: 0 | Q43: 0 | R43: 0 | S43: 0 | T43: 0 | U43: 0 | V43: 4793841.4 | W43: 0 | X43: 0 | Y43: 0 | Z43: 0 | AA43: 0 | AB43: 0 | AC43: 0 | AD43: 0 | AE43: 0 | AF43: 0 | AG43: 0 | AH43: 0 | AI43: 0 | AJ43: 0 | AK43: 0 | AL43: 0 | AM43: 0 | AN43: 0 | AO43: 0 | AP43: 0 | AQ43: 0 | AR43: 0 | AS43: 0 | AT43: 0 | AU43: 0 | AV43: 0 | AW43: 0 | AX43: 0 | AY43: 0 | AZ43: 0 | BA43: 0 | BB43: 0 | BC43: 0 | BD43: 0 | BE43: 0 | BF43: 0 | BG43: 0 | BH43: 0 | BI43: 0 | BJ43: 0 | BK43: 0 | BL43: 0 | BM43: 0 | BN43: 0 | BO43: 0 | BP43: 0 | BQ43: 0 | BR43: 0 | BS43: 0 | BT43: 0 | BU43: 0 | BV43: 0 | BW43: 0 | BX43: 0 | BY43: 0 | BZ43: 0 | CA43: 0 | CB43: 0 | CC43: 0 | CD43: 0 | CE43: 0 | CF43: 0 | CG43: 0 | CH43: 0 | CI43: 0 | CJ43: 0 | CK43: 0 | CL43: 0 | CM43: 0 | CN43: 0 | CO43: 0 | CP43: 0 | CQ43: 0 | CR43: 0 | CS43: 0 | CT43: 0 | CU43: 0 | CV43: 0 | CW43: 0 | CX43: 0 | CY43: 0 | CZ43: 0 | DA43: 0 | DB43: 0 | DC43: 0 | DD43: 0 | DE43: 0 | DF43: 0 | DG43: 0 | DH43: 0 | DI43: 0 | DJ43: 0 | DK43: 0 | DL43: 0 | DM43: 0 | DN43: 0 | DO43: 0 | DP43: 0 | DQ43: 0 | DR43: 0 | DS43: 0 | DT43: 0 | DU43: 0 | DV43: 0 | DW43: 0 | DX43: 0 | DY43: 0
E44: Property K | G44: USD | J44: 0 | K44: 0 | L44: 0 | M44: 0 | N44: 0 | O44: 0 | P44: 0 | Q44: 0 | R44: 0 | S44: 0 | T44: 0 | U44: 0 | V44: 0 | W44: 0 | X44: 0 | Y44: 3262091.3 | Z44: 0 | AA44: 0 | AB44: 0 | AC44: 0 | AD44: 0 | AE44: 0 | AF44: 0 | AG44: 0 | AH44: 0 | AI44: 0 | AJ44: 0 | AK44: 0 | AL44: 0 | AM44: 0 | AN44: 0 | AO44: 0 | AP44: 0 | AQ44: 0 | AR44: 0 | AS44: 0 | AT44: 0 | AU44: 0 | AV44: 0 | AW44: 0 | AX44: 0 | AY44: 0 | AZ44: 0 | BA44: 0 | BB44: 0 | BC44: 0 | BD44: 0 | BE44: 0 | BF44: 0 | BG44: 0 | BH44: 0 | BI44: 0 | BJ44: 0 | BK44: 0 | BL44: 0 | BM44: 0 | BN44: 0 | BO44: 0 | BP44: 0 | BQ44: 0 | BR44: 0 | BS44: 0 | BT44: 0 | BU44: 0 | BV44: 0 | BW44: 0 | BX44: 0 | BY44: 0 | BZ44: 0 | CA44: 0 | CB44: 0 | CC44: 0 | CD44: 0 | CE44: 0 | CF44: 0 | CG44: 0 | CH44: 0 | CI44: 0 | CJ44: 0 | CK44: 0 | CL44: 0 | CM44: 0 | CN44: 0 | CO44: 0 | CP44: 0 | CQ44: 0 | CR44: 0 | CS44: 0 | CT44: 0 | CU44: 0 | CV44: 0 | CW44: 0 | CX44: 0 | CY44: 0 | CZ44: 0 | DA44: 0 | DB44: 0 | DC44: 0 | DD44: 0 | DE44: 0 | DF44: 0 | DG44: 0 | DH44: 0 | DI44: 0 | DJ44: 0 | DK44: 0 | DL44: 0 | DM44: 0 | DN44: 0 | DO44: 0 | DP44: 0 | DQ44: 0 | DR44: 0 | DS44: 0 | DT44: 0 | DU44: 0 | DV44: 0 | DW44: 0 | DX44: 0 | DY44: 0
E45: Property L | G45: USD | J45: 0 | K45: 0 | L45: 0 | M45: 0 | N45: 0 | O45: 0 | P45: 0 | Q45: 0 | R45: 0 | S45: 0 | T45: 0 | U45: 0 | V45: 0 | W45: 0 | X45: 0 | Y45: 0 | Z45: 0 | AA45: 0 | AB45: 0 | AC45: 0 | AD45: 0 | AE45: 0 | AF45: 0 | AG45: 0 | AH45: 7810190.4 | AI45: 0 | AJ45: 0 | AK45: 0 | AL45: 0 | AM45: 0 | AN45: 0 | AO45: 0 | AP45: 0 | AQ45: 0 | AR45: 0 | AS45: 0 | AT45: 0 | AU45: 0 | AV45: 0 | AW45: 0 | AX45: 0 | AY45: 0 | AZ45: 0 | BA45: 0 | BB45: 0 | BC45: 0 | BD45: 0 | BE45: 0 | BF45: 0 | BG45: 0 | BH45: 0 | BI45: 0 | BJ45: 0 | BK45: 0 | BL45: 0 | BM45: 0 | BN45: 0 | BO45: 0 | BP45: 0 | BQ45: 0 | BR45: 0 | BS45: 0 | BT45: 0 | BU45: 0 | BV45: 0 | BW45: 0 | BX45: 0 | BY45: 0 | BZ45: 0 | CA45: 0 | CB45: 0 | CC45: 0 | CD45: 0 | CE45: 0 | CF45: 0 | CG45: 0 | CH45: 0 | CI45: 0 | CJ45: 0 | CK45: 0 | CL45: 0 | CM45: 0 | CN45: 0 | CO45: 0 | CP45: 0 | CQ45: 0 | CR45: 0 | CS45: 0 | CT45: 0 | CU45: 0 | CV45: 0 | CW45: 0 | CX45: 0 | CY45: 0 | CZ45: 0 | DA45: 0 | DB45: 0 | DC45: 0 | DD45: 0 | DE45: 0 | DF45: 0 | DG45: 0 | DH45: 0 | DI45: 0 | DJ45: 0 | DK45: 0 | DL45: 0 | DM45: 0 | DN45: 0 | DO45: 0 | DP45: 0 | DQ45: 0 | DR45: 0 | DS45: 0 | DT45: 0 | DU45: 0 | DV45: 0 | DW45: 0 | DX45: 0 | DY45: 0
E46: Property M | G46: USD | J46: 0 | K46: 0 | L46: 0 | M46: 0 | N46: 0 | O46: 0 | P46: 0 | Q46: 0 | R46: 0 | S46: 0 | T46: 0 | U46: 0 | V46: 0 | W46: 0 | X46: 0 | Y46: 0 | Z46: 0 | AA46: 0 | AB46: 0 | AC46: 0 | AD46: 0 | AE46: 0 | AF46: 0 | AG46: 0 | AH46: 0 | AI46: 0 | AJ46: 0 | AK46: 4223861.2 | AL46: 0 | AM46: 0 | AN46: 0 | AO46: 0 | AP46: 0 | AQ46: 0 | AR46: 0 | AS46: 0 | AT46: 0 | AU46: 0 | AV46: 0 | AW46: 0 | AX46: 0 | AY46: 0 | AZ46: 0 | BA46: 0 | BB46: 0 | BC46: 0 | BD46: 0 | BE46: 0 | BF46: 0 | BG46: 0 | BH46: 0 | BI46: 0 | BJ46: 0 | BK46: 0 | BL46: 0 | BM46: 0 | BN46: 0 | BO46: 0 | BP46: 0 | BQ46: 0 | BR46: 0 | BS46: 0 | BT46: 0 | BU46: 0 | BV46: 0 | BW46: 0 | BX46: 0 | BY46: 0 | BZ46: 0 | CA46: 0 | CB46: 0 | CC46: 0 | CD46: 0 | CE46: 0 | CF46: 0 | CG46: 0 | CH46: 0 | CI46: 0 | CJ46: 0 | CK46: 0 | CL46: 0 | CM46: 0 | CN46: 0 | CO46: 0 | CP46: 0 | CQ46: 0 | CR46: 0 | CS46: 0 | CT46: 0 | CU46: 0 | CV46: 0 | CW46: 0 | CX46: 0 | CY46: 0 | CZ46: 0 | DA46: 0 | DB46: 0 | DC46: 0 | DD46: 0 | DE46: 0 | DF46: 0 | DG46: 0 | DH46: 0 | DI46: 0 | DJ46: 0 | DK46: 0 | DL46: 0 | DM46: 0 | DN46: 0 | DO46: 0 | DP46: 0 | DQ46: 0 | DR46: 0 | DS46: 0 | DT46: 0 | DU46: 0 | DV46: 0 | DW46: 0 | DX46: 0 | DY46: 0
E47: Property N | G47: USD | J47: 0 | K47: 0 | L47: 0 | M47: 0 | N47: 0 | O47: 0 | P47: 0 | Q47: 0 | R47: 0 | S47: 0 | T47: 0 | U47: 0 | V47: 0 | W47: 0 | X47: 0 | Y47: 0 | Z47: 0 | AA47: 0 | AB47: 0 | AC47: 0 | AD47: 0 | AE47: 0 | AF47: 0 | AG47: 0 | AH47: 0 | AI47: 0 | AJ47: 0 | AK47: 0 | AL47: 0 | AM47: 0 | AN47: 0 | AO47: 0 | AP47: 0 | AQ47: 0 | AR47: 0 | AS47: 0 | AT47: 6440334.2 | AU47: 0 | AV47: 0 | AW47: 0 | AX47: 0 | AY47: 0 | AZ47: 0 | BA47: 0 | BB47: 0 | BC47: 0 | BD47: 0 | BE47: 0 | BF47: 0 | BG47: 0 | BH47: 0 | BI47: 0 | BJ47: 0 | BK47: 0 | BL47: 0 | BM47: 0 | BN47: 0 | BO47: 0 | BP47: 0 | BQ47: 0 | BR47: 0 | BS47: 0 | BT47: 0 | BU47: 0 | BV47: 0 | BW47: 0 | BX47: 0 | BY47: 0 | BZ47: 0 | CA47: 0 | CB47: 0 | CC47: 0 | CD47: 0 | CE47: 0 | CF47: 0 | CG47: 0 | CH47: 0 | CI47: 0 | CJ47: 0 | CK47: 0 | CL47: 0 | CM47: 0 | CN47: 0 | CO47: 0 | CP47: 0 | CQ47: 0 | CR47: 0 | CS47: 0 | CT47: 0 | CU47: 0 | CV47: 0 | CW47: 0 | CX47: 0 | CY47: 0 | CZ47: 0 | DA47: 0 | DB47: 0 | DC47: 0 | DD47: 0 | DE47: 0 | DF47: 0 | DG47: 0 | DH47: 0 | DI47: 0 | DJ47: 0 | DK47: 0 | DL47: 0 | DM47: 0 | DN47: 0 | DO47: 0 | DP47: 0 | DQ47: 0 | DR47: 0 | DS47: 0 | DT47: 0 | DU47: 0 | DV47: 0 | DW47: 0 | DX47: 0 | DY47: 0
E48: Property O | G48: USD | J48: 0 | K48: 0 | L48: 0 | M48: 0 | N48: 0 | O48: 0 | P48: 0 | Q48: 0 | R48: 0 | S48: 0 | T48: 0 | U48: 0 | V48: 0 | W48: 0 | X48: 0 | Y48: 0 | Z48: 0 | AA48: 0 | AB48: 0 | AC48: 0 | AD48: 0 | AE48: 0 | AF48: 0 | AG48: 0 | AH48: 0 | AI48: 0 | AJ48: 0 | AK48: 0 | AL48: 0 | AM48: 0 | AN48: 0 | AO48: 0 | AP48: 0 | AQ48: 0 | AR48: 0 | AS48: 0 | AT48: 0 | AU48: 0 | AV48: 0 | AW48: 0 | AX48: 0 | AY48: 0 | AZ48: 6385768.3 | BA48: 0 | BB48: 0 | BC48: 0 | BD48: 0 | BE48: 0 | BF48: 0 | BG48: 0 | BH48: 0 | BI48: 0 | BJ48: 0 | BK48: 0 | BL48: 0 | BM48: 0 | BN48: 0 | BO48: 0 | BP48: 0 | BQ48: 0 | BR48: 0 | BS48: 0 | BT48: 0 | BU48: 0 | BV48: 0 | BW48: 0 | BX48: 0 | BY48: 0 | BZ48: 0 | CA48: 0 | CB48: 0 | CC48: 0 | CD48: 0 | CE48: 0 | CF48: 0 | CG48: 0 | CH48: 0 | CI48: 0 | CJ48: 0 | CK48: 0 | CL48: 0 | CM48: 0 | CN48: 0 | CO48: 0 | CP48: 0 | CQ48: 0 | CR48: 0 | CS48: 0 | CT48: 0 | CU48: 0 | CV48: 0 | CW48: 0 | CX48: 0 | CY48: 0 | CZ48: 0 | DA48: 0 | DB48: 0 | DC48: 0 | DD48: 0 | DE48: 0 | DF48: 0 | DG48: 0 | DH48: 0 | DI48: 0 | DJ48: 0 | DK48: 0 | DL48: 0 | DM48: 0 | DN48: 0 | DO48: 0 | DP48: 0 | DQ48: 0 | DR48: 0 | DS48: 0 | DT48: 0 | DU48: 0 | DV48: 0 | DW48: 0 | DX48: 0 | DY48: 0
E49: Land acquisition | G49: USD | J49: {=_xlfn.BYCOL(_xlfn.ANCHORARRAY( J39), _xleta.SUM )} -> 4316130 | K49: 0 | L49: 0 | M49: 3908898 | N49: 0 | O49: 0 | P49: 4936701 | Q49: 0 | R49: 0 | S49: 6597360 | T49: 0 | U49: 0 | V49: 4793841.4 | W49: 0 | X49: 0 | Y49: 3262091.3 | Z49: 0 | AA49: 0 | AB49: 0 | AC49: 0 | AD49: 0 | AE49: 0 | AF49: 0 | AG49: 0 | AH49: 7810190.4 | AI49: 0 | AJ49: 0 | AK49: 4223861.2 | AL49: 0 | AM49: 0 | AN49: 0 | AO49: 0 | AP49: 0 | AQ49: 0 | AR49: 0 | AS49: 0 | AT49: 6440334.2 | AU49: 0 | AV49: 0 | AW49: 0 | AX49: 0 | AY49: 0 | AZ49: 6385768.3 | BA49: 0 | BB49: 0 | BC49: 0 | BD49: 0 | BE49: 0 | BF49: 0 | BG49: 0 | BH49: 0 | BI49: 0 | BJ49: 0 | BK49: 0 | BL49: 0 | BM49: 0 | BN49: 0 | BO49: 0 | BP49: 0 | BQ49: 0 | BR49: 0 | BS49: 0 | BT49: 0 | BU49: 0 | BV49: 0 | BW49: 0 | BX49: 0 | BY49: 0 | BZ49: 0 | CA49: 0 | CB49: 0 | CC49: 0 | CD49: 0 | CE49: 0 | CF49: 0 | CG49: 0 | CH49: 0 | CI49: 0 | CJ49: 0 | CK49: 0 | CL49: 0 | CM49: 0 | CN49: 0 | CO49: 0 | CP49: 0 | CQ49: 0 | CR49: 0 | CS49: 0 | CT49: 0 | CU49: 0 | CV49: 0 | CW49: 0 | CX49: 0 | CY49: 0 | CZ49: 0 | DA49: 0 | DB49: 0 | DC49: 0 | DD49: 0 | DE49: 0 | DF49: 0 | DG49: 0 | DH49: 0 | DI49: 0 | DJ49: 0 | DK49: 0 | DL49: 0 | DM49: 0 | DN49: 0 | DO49: 0 | DP49: 0 | DQ49: 0 | DR49: 0 | DS49: 0 | DT49: 0 | DU49: 0 | DV49: 0 | DW49: 0 | DX49: 0 | DY49: 0
C52: Construction costs
C53: (adjusted for inflation)
E54: {=_xlfn.LET( _xlpm.property_data, CaseData!$A$15:$H$24, _xlfn.CHOOSECOLS( _xlpm.property_data, 1 ) )} -> Property F | G54: USD | J54: {=_xlfn.LET( _xlpm.timeline,_xlfn.ANCHORARRAY( $J$3), _xlpm.property_data, CaseData!$A$15:$H$24, _xlpm.construction_costs, INDEX( _xlpm.property_data,, 5 ), _xlpm.purchase_date, INDEX( _xlpm.property_data,, 6 ), _xlpm.preparation_months, INDEX( _xlpm.property_data,, 7 ), _xlpm.months_of_construction,INDEX( _xlpm.property_data,, 8 ), _xlpm.delay, IF( $F$9 = 0, 0, 12 ), _xlpm.construction_start, _xlfn.MAKEARRAY( ROWS( _xlpm.property_data ), 1, _xlfn.LAMBDA(_xlpm.r,_xlpm.c, EOMONTH( INDEX( _xlpm.purchase_date, _xlpm.r ), INDEX( _xlpm.preparation_months, _xlpm.r ) + _xlpm.delay ) ) ), _xlpm.construction_duration, _xlfn.MAKEARRAY( ROWS( _xlpm.property_data ), COLUMNS( _xlpm.timeline ), _xlfn.LAMBDA(_xlpm.r,_xlpm.c, IF( ( INDEX( _xlpm.timeline,, _xlpm.c ) >= INDEX( _xlpm.construction_start, _xlpm.r, 1 ) ) * ( INDEX( _xlpm.timeline,, _xlpm.c ) < EOMONTH( INDEX( _xlpm.construction_start, _xlpm.r, 1 ), INDEX( _xlpm.months_of_construction, _xlpm.r ) ) ), 1, 0 ) ) ), _xlpm.construction_bell, CaseData!$B$30:$N$53, _xlpm.construction_length, CaseData!$B$29:$N$29, _xlpm.construction_month, CaseData!$A$30:$A$53, _xlpm.elapsed_month, _xlfn.MAKEARRAY( ROWS( _xlpm.property_data ), COLUMNS( _xlpm.timeline ), _xlfn.LAMBDA(_xlpm.r,_xlpm.c, SUM( INDEX( _xlpm.construction_duration, _xlpm.r, _xlfn.SEQUENCE( 1, _xlpm.c ) ) ) ) ), _xlpm.POC, _xlfn.IFNA( INDEX( _xlpm.construction_bell, MATCH( _xlpm.elapsed_month, _xlpm.construction_month, 0 ), MATCH( _xlpm.months_of_construction, _xlpm.construction_length, 0 ) ), 0 ) * _xlpm.construction_duration, _xlpm.inflation_flag, IF( MONTH( _xlpm.timeline ) = 1, 1, 0 ), _xlpm.inflation_data, CaseData!$J$15:$M$24, _xlpm.annual_rate, _xlfn.XLOOKUP( YEAR( _xlpm.timeline ), INDEX( _xlpm.inflation_data,, 1 ), INDEX( _xlpm.inflation_data,, 3 ) ), _xlpm.effective_step, _xlpm.inflation_flag * _xlpm.annual_rate, _xlpm.inflation_factor, _xlfn.SCAN( 1, _xlpm.effective_step, _xlfn.LAMBDA(_xlpm.prev,_xlpm.step, _xlpm.prev * ( 1 + _xlpm.step ) ) ), _xlpm.locked_factor, _xlfn.XLOOKUP( _xlpm.construction_start, _xlpm.timeline, _xlpm.inflation_factor ), ( _xlpm.construction_costs * _xlpm.locked_factor ) * _xlpm.POC )} -> 0 | K54: 0 | L54: 0 | M54: 0 | N54: 948007.12 | O54: 1053341.2 | P54: 1264009.5 | Q54: 1474677.8 | R54: 1685346 | S54: 2106682.5 | T54: 2949355.5 | U54: 4213365 | V54: 4634701.5 | W54: 4634701.5 | X54: 4634701.5 | Y54: 3792028.5 | Z54: 3370692 | AA54: 2949355.5 | AB54: 2422684.9 | AC54: 0 | AD54: 0 | AE54: 0 | AF54: 0 | AG54: 0 | AH54: 0 | AI54: 0 | AJ54: 0 | AK54: 0 | AL54: 0 | AM54: 0 | AN54: 0 | AO54: 0 | AP54: 0 | AQ54: 0 | AR54: 0 | AS54: 0 | AT54: 0 | AU54: 0 | AV54: 0 | AW54: 0 | AX54: 0 | AY54: 0 | AZ54: 0 | BA54: 0 | BB54: 0 | BC54: 0 | BD54: 0 | BE54: 0 | BF54: 0 | BG54: 0 | BH54: 0 | BI54: 0 | BJ54: 0 | BK54: 0 | BL54: 0 | BM54: 0 | BN54: 0 | BO54: 0 | BP54: 0 | BQ54: 0 | BR54: 0 | BS54: 0 | BT54: 0 | BU54: 0 | BV54: 0 | BW54: 0 | BX54: 0 | BY54: 0 | BZ54: 0 | CA54: 0 | CB54: 0 | CC54: 0 | CD54: 0 | CE54: 0 | CF54: 0 | CG54: 0 | CH54: 0 | CI54: 0 | CJ54: 0 | CK54: 0 | CL54: 0 | CM54: 0 | CN54: 0 | CO54: 0 | CP54: 0 | CQ54: 0 | CR54: 0 | CS54: 0 | CT54: 0 | CU54: 0 | CV54: 0 | CW54: 0 | CX54: 0 | CY54: 0 | CZ54: 0 | DA54: 0 | DB54: 0 | DC54: 0 | DD54: 0 | DE54: 0 | DF54: 0 | DG54: 0 | DH54: 0 | DI54: 0 | DJ54: 0 | DK54: 0 | DL54: 0 | DM54: 0 | DN54: 0 | DO54: 0 | DP54: 0 | DQ54: 0 | DR54: 0 | DS54: 0 | DT54: 0 | DU54: 0 | DV54: 0 | DW54: 0 | DX54: 0 | DY54: 0
E55: Property G | G55: USD | J55: 0 | K55: 0 | L55: 0 | M55: 0 | N55: 0 | O55: 0 | P55: 0 | Q55: 0 | R55: 635971.5 | S55: 953957.25 | T55: 1271943 | U55: 1589928.8 | V55: 1907914.5 | W55: 2543886 | X55: 3179857.5 | Y55: 3815829 | Z55: 4451800.5 | AA55: 5087772 | AB55: 4451800.5 | AC55: 1907914.5 | AD55: 0 | AE55: 0 | AF55: 0 | AG55: 0 | AH55: 0 | AI55: 0 | AJ55: 0 | AK55: 0 | AL55: 0 | AM55: 0 | AN55: 0 | AO55: 0 | AP55: 0 | AQ55: 0 | AR55: 0 | AS55: 0 | AT55: 0 | AU55: 0 | AV55: 0 | AW55: 0 | AX55: 0 | AY55: 0 | AZ55: 0 | BA55: 0 | BB55: 0 | BC55: 0 | BD55: 0 | BE55: 0 | BF55: 0 | BG55: 0 | BH55: 0 | BI55: 0 | BJ55: 0 | BK55: 0 | BL55: 0 | BM55: 0 | BN55: 0 | BO55: 0 | BP55: 0 | BQ55: 0 | BR55: 0 | BS55: 0 | BT55: 0 | BU55: 0 | BV55: 0 | BW55: 0 | BX55: 0 | BY55: 0 | BZ55: 0 | CA55: 0 | CB55: 0 | CC55: 0 | CD55: 0 | CE55: 0 | CF55: 0 | CG55: 0 | CH55: 0 | CI55: 0 | CJ55: 0 | CK55: 0 | CL55: 0 | CM55: 0 | CN55: 0 | CO55: 0 | CP55: 0 | CQ55: 0 | CR55: 0 | CS55: 0 | CT55: 0 | CU55: 0 | CV55: 0 | CW55: 0 | CX55: 0 | CY55: 0 | CZ55: 0 | DA55: 0 | DB55: 0 | DC55: 0 | DD55: 0 | DE55: 0 | DF55: 0 | DG55: 0 | DH55: 0 | DI55: 0 | DJ55: 0 | DK55: 0 | DL55: 0 | DM55: 0 | DN55: 0 | DO55: 0 | DP55: 0 | DQ55: 0 | DR55: 0 | DS55: 0 | DT55: 0 | DU55: 0 | DV55: 0 | DW55: 0 | DX55: 0 | DY55: 0
E56: Property H | G56: USD | J56: 0 | K56: 0 | L56: 0 | M56: 0 | N56: 0 | O56: 0 | P56: 0 | Q56: 0 | R56: 0 | S56: 876211 | T56: 876211 | U56: 1314316.5 | V56: 1314316.5 | W56: 1533369.2 | X56: 1752422 | Y56: 2190527.5 | Z56: 3066738.5 | AA56: 3942949.5 | AB56: 4381055 | AC56: 4381055 | AD56: 4381055 | AE56: 4381055 | AF56: 3942949.5 | AG56: 3066738.5 | AH56: 2409580.2 | AI56: 0 | AJ56: 0 | AK56: 0 | AL56: 0 | AM56: 0 | AN56: 0 | AO56: 0 | AP56: 0 | AQ56: 0 | AR56: 0 | AS56: 0 | AT56: 0 | AU56: 0 | AV56: 0 | AW56: 0 | AX56: 0 | AY56: 0 | AZ56: 0 | BA56: 0 | BB56: 0 | BC56: 0 | BD56: 0 | BE56: 0 | BF56: 0 | BG56: 0 | BH56: 0 | BI56: 0 | BJ56: 0 | BK56: 0 | BL56: 0 | BM56: 0 | BN56: 0 | BO56: 0 | BP56: 0 | BQ56: 0 | BR56: 0 | BS56: 0 | BT56: 0 | BU56: 0 | BV56: 0 | BW56: 0 | BX56: 0 | BY56: 0 | BZ56: 0 | CA56: 0 | CB56: 0 | CC56: 0 | CD56: 0 | CE56: 0 | CF56: 0 | CG56: 0 | CH56: 0 | CI56: 0 | CJ56: 0 | CK56: 0 | CL56: 0 | CM56: 0 | CN56: 0 | CO56: 0 | CP56: 0 | CQ56: 0 | CR56: 0 | CS56: 0 | CT56: 0 | CU56: 0 | CV56: 0 | CW56: 0 | CX56: 0 | CY56: 0 | CZ56: 0 | DA56: 0 | DB56: 0 | DC56: 0 | DD56: 0 | DE56: 0 | DF56: 0 | DG56: 0 | DH56: 0 | DI56: 0 | DJ56: 0 | DK56: 0 | DL56: 0 | DM56: 0 | DN56: 0 | DO56: 0 | DP56: 0 | DQ56: 0 | DR56: 0 | DS56: 0 | DT56: 0 | DU56: 0 | DV56: 0 | DW56: 0 | DX56: 0 | DY56: 0
E57: Property I | G57: USD | J57: 0 | K57: 0 | L57: 0 | M57: 0 | N57: 0 | O57: 0 | P57: 0 | Q57: 0 | R57: 0 | S57: 0 | T57: 0 | U57: 0 | V57: 0 | W57: 0 | X57: 825160.87 | Y57: 825160.87 | Z57: 1100214.5 | AA57: 1375268.1 | AB57: 1375268.1 | AC57: 1650321.7 | AD57: 1925375.4 | AE57: 2200429 | AF57: 3300643.5 | AG57: 3575697.1 | AH57: 4125804.4 | AI57: 4950965.2 | AJ57: 4950965.2 | AK57: 4950965.2 | AL57: 4950965.2 | AM57: 4950965.2 | AN57: 3850750.8 | AO57: 2750536.2 | AP57: 1375268.1 | AQ57: 0 | AR57: 0 | AS57: 0 | AT57: 0 | AU57: 0 | AV57: 0 | AW57: 0 | AX57: 0 | AY57: 0 | AZ57: 0 | BA57: 0 | BB57: 0 | BC57: 0 | BD57: 0 | BE57: 0 | BF57: 0 | BG57: 0 | BH57: 0 | BI57: 0 | BJ57: 0 | BK57: 0 | BL57: 0 | BM57: 0 | BN57: 0 | BO57: 0 | BP57: 0 | BQ57: 0 | BR57: 0 | BS57: 0 | BT57: 0 | BU57: 0 | BV57: 0 | BW57: 0 | BX57: 0 | BY57: 0 | BZ57: 0 | CA57: 0 | CB57: 0 | CC57: 0 | CD57: 0 | CE57: 0 | CF57: 0 | CG57: 0 | CH57: 0 | CI57: 0 | CJ57: 0 | CK57: 0 | CL57: 0 | CM57: 0 | CN57: 0 | CO57: 0 | CP57: 0 | CQ57: 0 | CR57: 0 | CS57: 0 | CT57: 0 | CU57: 0 | CV57: 0 | CW57: 0 | CX57: 0 | CY57: 0 | CZ57: 0 | DA57: 0 | DB57: 0 | DC57: 0 | DD57: 0 | DE57: 0 | DF57: 0 | DG57: 0 | DH57: 0 | DI57: 0 | DJ57: 0 | DK57: 0 | DL57: 0 | DM57: 0 | DN57: 0 | DO57: 0 | DP57: 0 | DQ57: 0 | DR57: 0 | DS57: 0 | DT57: 0 | DU57: 0 | DV57: 0 | DW57: 0 | DX57: 0 | DY57: 0
E58: Property J | G58: USD | J58: 0 | K58: 0 | L58: 0 | M58: 0 | N58: 0 | O58: 0 | P58: 0 | Q58: 0 | R58: 0 | S58: 0 | T58: 0 | U58: 0 | V58: 0 | W58: 0 | X58: 0 | Y58: 0 | Z58: 0 | AA58: 765023.1 | AB58: 765023.1 | AC58: 1530046.2 | AD58: 1530046.2 | AE58: 1530046.2 | AF58: 1530046.2 | AG58: 2040061.6 | AH58: 2550077 | AI58: 3060092.4 | AJ58: 3570107.8 | AK58: 4080123.2 | AL58: 4590138.6 | AM58: 5100154 | AN58: 5100154 | AO58: 5100154 | AP58: 4080123.2 | AQ58: 2550077 | AR58: 1530046.2 | AS58: 0 | AT58: 0 | AU58: 0 | AV58: 0 | AW58: 0 | AX58: 0 | AY58: 0 | AZ58: 0 | BA58: 0 | BB58: 0 | BC58: 0 | BD58: 0 | BE58: 0 | BF58: 0 | BG58: 0 | BH58: 0 | BI58: 0 | BJ58: 0 | BK58: 0 | BL58: 0 | BM58: 0 | BN58: 0 | BO58: 0 | BP58: 0 | BQ58: 0 | BR58: 0 | BS58: 0 | BT58: 0 | BU58: 0 | BV58: 0 | BW58: 0 | BX58: 0 | BY58: 0 | BZ58: 0 | CA58: 0 | CB58: 0 | CC58: 0 | CD58: 0 | CE58: 0 | CF58: 0 | CG58: 0 | CH58: 0 | CI58: 0 | CJ58: 0 | CK58: 0 | CL58: 0 | CM58: 0 | CN58: 0 | CO58: 0 | CP58: 0 | CQ58: 0 | CR58: 0 | CS58: 0 | CT58: 0 | CU58: 0 | CV58: 0 | CW58: 0 | CX58: 0 | CY58: 0 | CZ58: 0 | DA58: 0 | DB58: 0 | DC58: 0 | DD58: 0 | DE58: 0 | DF58: 0 | DG58: 0 | DH58: 0 | DI58: 0 | DJ58: 0 | DK58: 0 | DL58: 0 | DM58: 0 | DN58: 0 | DO58: 0 | DP58: 0 | DQ58: 0 | DR58: 0 | DS58: 0 | DT58: 0 | DU58: 0 | DV58: 0 | DW58: 0 | DX58: 0 | DY58: 0
E59: Property K | G59: USD | J59: 0 | K59: 0 | L59: 0 | M59: 0 | N59: 0 | O59: 0 | P59: 0 | Q59: 0 | R59: 0 | S59: 0 | T59: 0 | U59: 0 | V59: 0 | W59: 0 | X59: 0 | Y59: 0 | Z59: 0 | AA59: 0 | AB59: 0 | AC59: 0 | AD59: 0 | AE59: 694105.91 | AF59: 1041158.9 | AG59: 1388211.8 | AH59: 1735264.8 | AI59: 2082317.7 | AJ59: 2776423.6 | AK59: 3470529.6 | AL59: 4164635.5 | AM59: 4858741.4 | AN59: 5552847.3 | AO59: 4858741.4 | AP59: 2082317.7 | AQ59: 0 | AR59: 0 | AS59: 0 | AT59: 0 | AU59: 0 | AV59: 0 | AW59: 0 | AX59: 0 | AY59: 0 | AZ59: 0 | BA59: 0 | BB59: 0 | BC59: 0 | BD59: 0 | BE59: 0 | BF59: 0 | BG59: 0 | BH59: 0 | BI59: 0 | BJ59: 0 | BK59: 0 | BL59: 0 | BM59: 0 | BN59: 0 | BO59: 0 | BP59: 0 | BQ59: 0 | BR59: 0 | BS59: 0 | BT59: 0 | BU59: 0 | BV59: 0 | BW59: 0 | BX59: 0 | BY59: 0 | BZ59: 0 | CA59: 0 | CB59: 0 | CC59: 0 | CD59: 0 | CE59: 0 | CF59: 0 | CG59: 0 | CH59: 0 | CI59: 0 | CJ59: 0 | CK59: 0 | CL59: 0 | CM59: 0 | CN59: 0 | CO59: 0 | CP59: 0 | CQ59: 0 | CR59: 0 | CS59: 0 | CT59: 0 | CU59: 0 | CV59: 0 | CW59: 0 | CX59: 0 | CY59: 0 | CZ59: 0 | DA59: 0 | DB59: 0 | DC59: 0 | DD59: 0 | DE59: 0 | DF59: 0 | DG59: 0 | DH59: 0 | DI59: 0 | DJ59: 0 | DK59: 0 | DL59: 0 | DM59: 0 | DN59: 0 | DO59: 0 | DP59: 0 | DQ59: 0 | DR59: 0 | DS59: 0 | DT59: 0 | DU59: 0 | DV59: 0 | DW59: 0 | DX59: 0 | DY59: 0
E60: Property L | G60: USD | J60: 0 | K60: 0 | L60: 0 | M60: 0 | N60: 0 | O60: 0 | P60: 0 | Q60: 0 | R60: 0 | S60: 0 | T60: 0 | U60: 0 | V60: 0 | W60: 0 | X60: 0 | Y60: 0 | Z60: 0 | AA60: 0 | AB60: 0 | AC60: 0 | AD60: 0 | AE60: 0 | AF60: 0 | AG60: 0 | AH60: 0 | AI60: 0 | AJ60: 0 | AK60: 670041.35 | AL60: 670041.35 | AM60: 1005062 | AN60: 1340082.7 | AO60: 1340082.7 | AP60: 1675103.4 | AQ60: 1675103.4 | AR60: 2010124 | AS60: 2010124 | AT60: 2345144.7 | AU60: 2680165.4 | AV60: 3015186.1 | AW60: 3350206.7 | AX60: 3685227.4 | AY60: 4020248.1 | AZ60: 4690289.4 | BA60: 5360330.8 | BB60: 5360330.8 | BC60: 5360330.8 | BD60: 5360330.8 | BE60: 4020248.1 | BF60: 3350206.7 | BG60: 2010124 | BH60: 0 | BI60: 0 | BJ60: 0 | BK60: 0 | BL60: 0 | BM60: 0 | BN60: 0 | BO60: 0 | BP60: 0 | BQ60: 0 | BR60: 0 | BS60: 0 | BT60: 0 | BU60: 0 | BV60: 0 | BW60: 0 | BX60: 0 | BY60: 0 | BZ60: 0 | CA60: 0 | CB60: 0 | CC60: 0 | CD60: 0 | CE60: 0 | CF60: 0 | CG60: 0 | CH60: 0 | CI60: 0 | CJ60: 0 | CK60: 0 | CL60: 0 | CM60: 0 | CN60: 0 | CO60: 0 | CP60: 0 | CQ60: 0 | CR60: 0 | CS60: 0 | CT60: 0 | CU60: 0 | CV60: 0 | CW60: 0 | CX60: 0 | CY60: 0 | CZ60: 0 | DA60: 0 | DB60: 0 | DC60: 0 | DD60: 0 | DE60: 0 | DF60: 0 | DG60: 0 | DH60: 0 | DI60: 0 | DJ60: 0 | DK60: 0 | DL60: 0 | DM60: 0 | DN60: 0 | DO60: 0 | DP60: 0 | DQ60: 0 | DR60: 0 | DS60: 0 | DT60: 0 | DU60: 0 | DV60: 0 | DW60: 0 | DX60: 0 | DY60: 0
E61: Property M | G61: USD | J61: 0 | K61: 0 | L61: 0 | M61: 0 | N61: 0 | O61: 0 | P61: 0 | Q61: 0 | R61: 0 | S61: 0 | T61: 0 | U61: 0 | V61: 0 | W61: 0 | X61: 0 | Y61: 0 | Z61: 0 | AA61: 0 | AB61: 0 | AC61: 0 | AD61: 0 | AE61: 0 | AF61: 0 | AG61: 0 | AH61: 0 | AI61: 0 | AJ61: 0 | AK61: 0 | AL61: 0 | AM61: 0 | AN61: 0 | AO61: 0 | AP61: 0 | AQ61: 747383.63 | AR61: 871947.57 | AS61: 1245639.4 | AT61: 1370203.3 | AU61: 1743895.1 | AV61: 1993023 | AW61: 2491278.8 | AX61: 2989534.5 | AY61: 3487790.3 | AZ61: 3986046 | BA61: 4484301.8 | BB61: 4484301.8 | BC61: 4484301.8 | BD61: 4484301.8 | BE61: 4484301.8 | BF61: 3986046 | BG61: 2491278.8 | BH61: 0 | BI61: 0 | BJ61: 0 | BK61: 0 | BL61: 0 | BM61: 0 | BN61: 0 | BO61: 0 | BP61: 0 | BQ61: 0 | BR61: 0 | BS61: 0 | BT61: 0 | BU61: 0 | BV61: 0 | BW61: 0 | BX61: 0 | BY61: 0 | BZ61: 0 | CA61: 0 | CB61: 0 | CC61: 0 | CD61: 0 | CE61: 0 | CF61: 0 | CG61: 0 | CH61: 0 | CI61: 0 | CJ61: 0 | CK61: 0 | CL61: 0 | CM61: 0 | CN61: 0 | CO61: 0 | CP61: 0 | CQ61: 0 | CR61: 0 | CS61: 0 | CT61: 0 | CU61: 0 | CV61: 0 | CW61: 0 | CX61: 0 | CY61: 0 | CZ61: 0 | DA61: 0 | DB61: 0 | DC61: 0 | DD61: 0 | DE61: 0 | DF61: 0 | DG61: 0 | DH61: 0 | DI61: 0 | DJ61: 0 | DK61: 0 | DL61: 0 | DM61: 0 | DN61: 0 | DO61: 0 | DP61: 0 | DQ61: 0 | DR61: 0 | DS61: 0 | DT61: 0 | DU61: 0 | DV61: 0 | DW61: 0 | DX61: 0 | DY61: 0
E62: Property N | G62: USD | J62: 0 | K62: 0 | L62: 0 | M62: 0 | N62: 0 | O62: 0 | P62: 0 | Q62: 0 | R62: 0 | S62: 0 | T62: 0 | U62: 0 | V62: 0 | W62: 0 | X62: 0 | Y62: 0 | Z62: 0 | AA62: 0 | AB62: 0 | AC62: 0 | AD62: 0 | AE62: 0 | AF62: 0 | AG62: 0 | AH62: 0 | AI62: 0 | AJ62: 0 | AK62: 0 | AL62: 0 | AM62: 0 | AN62: 0 | AO62: 0 | AP62: 0 | AQ62: 0 | AR62: 0 | AS62: 0 | AT62: 0 | AU62: 0 | AV62: 0 | AW62: 0 | AX62: 0 | AY62: 668778.15 | AZ62: 668778.15 | BA62: 1003167.2 | BB62: 1337556.3 | BC62: 1337556.3 | BD62: 1671945.4 | BE62: 2006334.5 | BF62: 2006334.5 | BG62: 2006334.5 | BH62: 2675112.6 | BI62: 3009501.7 | BJ62: 3343890.8 | BK62: 3678279.8 | BL62: 4012668.9 | BM62: 4681447.1 | BN62: 5350225.2 | BO62: 5350225.2 | BP62: 5350225.2 | BQ62: 5350225.2 | BR62: 4681447.1 | BS62: 4012668.9 | BT62: 2675112.6 | BU62: 0 | BV62: 0 | BW62: 0 | BX62: 0 | BY62: 0 | BZ62: 0 | CA62: 0 | CB62: 0 | CC62: 0 | CD62: 0 | CE62: 0 | CF62: 0 | CG62: 0 | CH62: 0 | CI62: 0 | CJ62: 0 | CK62: 0 | CL62: 0 | CM62: 0 | CN62: 0 | CO62: 0 | CP62: 0 | CQ62: 0 | CR62: 0 | CS62: 0 | CT62: 0 | CU62: 0 | CV62: 0 | CW62: 0 | CX62: 0 | CY62: 0 | CZ62: 0 | DA62: 0 | DB62: 0 | DC62: 0 | DD62: 0 | DE62: 0 | DF62: 0 | DG62: 0 | DH62: 0 | DI62: 0 | DJ62: 0 | DK62: 0 | DL62: 0 | DM62: 0 | DN62: 0 | DO62: 0 | DP62: 0 | DQ62: 0 | DR62: 0 | DS62: 0 | DT62: 0 | DU62: 0 | DV62: 0 | DW62: 0 | DX62: 0 | DY62: 0
E63: Property O | G63: USD | J63: 0 | K63: 0 | L63: 0 | M63: 0 | N63: 0 | O63: 0 | P63: 0 | Q63: 0 | R63: 0 | S63: 0 | T63: 0 | U63: 0 | V63: 0 | W63: 0 | X63: 0 | Y63: 0 | Z63: 0 | AA63: 0 | AB63: 0 | AC63: 0 | AD63: 0 | AE63: 0 | AF63: 0 | AG63: 0 | AH63: 0 | AI63: 0 | AJ63: 0 | AK63: 0 | AL63: 0 | AM63: 0 | AN63: 0 | AO63: 0 | AP63: 0 | AQ63: 0 | AR63: 0 | AS63: 0 | AT63: 0 | AU63: 0 | AV63: 0 | AW63: 0 | AX63: 0 | AY63: 0 | AZ63: 0 | BA63: 0 | BB63: 0 | BC63: 0 | BD63: 0 | BE63: 746000.9 | BF63: 746000.9 | BG63: 746000.9 | BH63: 1492001.8 | BI63: 1492001.8 | BJ63: 1492001.8 | BK63: 1492001.8 | BL63: 2238002.7 | BM63: 2238002.7 | BN63: 2238002.7 | BO63: 2984003.6 | BP63: 2984003.6 | BQ63: 3730004.5 | BR63: 3730004.5 | BS63: 4476005.4 | BT63: 4476005.4 | BU63: 5222006.3 | BV63: 5222006.3 | BW63: 5968007.2 | BX63: 5968007.2 | BY63: 5968007.2 | BZ63: 4476005.4 | CA63: 2984003.6 | CB63: 1492001.8 | CC63: 0 | CD63: 0 | CE63: 0 | CF63: 0 | CG63: 0 | CH63: 0 | CI63: 0 | CJ63: 0 | CK63: 0 | CL63: 0 | CM63: 0 | CN63: 0 | CO63: 0 | CP63: 0 | CQ63: 0 | CR63: 0 | CS63: 0 | CT63: 0 | CU63: 0 | CV63: 0 | CW63: 0 | CX63: 0 | CY63: 0 | CZ63: 0 | DA63: 0 | DB63: 0 | DC63: 0 | DD63: 0 | DE63: 0 | DF63: 0 | DG63: 0 | DH63: 0 | DI63: 0 | DJ63: 0 | DK63: 0 | DL63: 0 | DM63: 0 | DN63: 0 | DO63: 0 | DP63: 0 | DQ63: 0 | DR63: 0 | DS63: 0 | DT63: 0 | DU63: 0 | DV63: 0 | DW63: 0 | DX63: 0 | DY63: 0
E64: Construction costs | G64: USD | J64: {=_xlfn.BYCOL(_xlfn.ANCHORARRAY( $J$54), _xleta.SUM )} -> 0 | K64: 0 | L64: 0 | M64: 0 | N64: 948007.12 | O64: 1053341.2 | P64: 1264009.5 | Q64: 1474677.8 | R64: 2321317.5 | S64: 3936850.8 | T64: 5097509.5 | U64: 7117610.2 | V64: 7856932.5 | W64: 8711956.8 | X64: 10392142 | Y64: 10623546 | Z64: 11989446 | AA64: 14120368 | AB64: 13395832 | AC64: 9469337.4 | AD64: 7836476.6 | AE64: 8805636.1 | AF64: 9814798.1 | AG64: 10070709 | AH64: 10820726 | AI64: 10093375 | AJ64: 11297497 | AK64: 13171659 | AL64: 14375781 | AM64: 15914923 | AN64: 15843835 | AO64: 14049514 | AP64: 9212812.4 | AQ64: 4972564 | AR64: 4412117.8 | AS64: 3255763.4 | AT64: 3715348 | AU64: 4424060.5 | AV64: 5008209.1 | AW64: 5841485.5 | AX64: 6674761.9 | AY64: 8176816.5 | AZ64: 9345113.6 | BA64: 10847800 | BB64: 11182189 | BC64: 11182189 | BD64: 11516578 | BE64: 11256885 | BF64: 10088588 | BG64: 7253738.2 | BH64: 4167114.4 | BI64: 4501503.5 | BJ64: 4835892.6 | BK64: 5170281.7 | BL64: 6250671.6 | BM64: 6919449.8 | BN64: 7588227.9 | BO64: 8334228.8 | BP64: 8334228.8 | BQ64: 9080229.8 | BR64: 8411451.6 | BS64: 8488674.3 | BT64: 7151118 | BU64: 5222006.3 | BV64: 5222006.3 | BW64: 5968007.2 | BX64: 5968007.2 | BY64: 5968007.2 | BZ64: 4476005.4 | CA64: 2984003.6 | CB64: 1492001.8 | CC64: 0 | CD64: 0 | CE64: 0 | CF64: 0 | CG64: 0 | CH64: 0 | CI64: 0 | CJ64: 0 | CK64: 0 | CL64: 0 | CM64: 0 | CN64: 0 | CO64: 0 | CP64: 0 | CQ64: 0 | CR64: 0 | CS64: 0 | CT64: 0 | CU64: 0 | CV64: 0 | CW64: 0 | CX64: 0 | CY64: 0 | CZ64: 0 | DA64: 0 | DB64: 0 | DC64: 0 | DD64: 0 | DE64: 0 | DF64: 0 | DG64: 0 | DH64: 0 | DI64: 0 | DJ64: 0 | DK64: 0 | DL64: 0 | DM64: 0 | DN64: 0 | DO64: 0 | DP64: 0 | DQ64: 0 | DR64: 0 | DS64: 0 | DT64: 0 | DU64: 0 | DV64: 0 | DW64: 0 | DX64: 0 | DY64: 0
C67: Rent revenues
C68: (adjusted for inflation and vacancy)
E69: {=_xlfn.LET( _xlpm.property_data, CaseData!$A$15:$H$24, _xlfn.CHOOSECOLS( _xlpm.property_data, {1} ) )} -> Property F | G69: USD | J69: {=_xlfn.LET( _xlpm.timeline,_xlfn.ANCHORARRAY( $J$3), _xlpm.property_data, CaseData!$A$15:$H$24, _xlpm.property_rows, INDEX( _xlpm.property_data, 0, 1 ), _xlpm.purchase_date, INDEX( _xlpm.property_data,, 6 ), _xlpm.prep_months, INDEX( _xlpm.property_data,, 7 ), _xlpm.const_months, INDEX( _xlpm.property_data,, 8 ), _xlpm.delay, IF( $F$9 = 0, 0, 12 ), _xlpm.moo_bp, CaseData!$F$6:$F$9, _xlpm.vac_bp, CaseData!$H$6:$H$9, _xlpm.operation_start, _xlfn.MAKEARRAY( ROWS( _xlpm.property_data ), 1, _xlfn.LAMBDA(_xlpm.r,_xlpm.c, EOMONTH( INDEX( _xlpm.purchase_date, _xlpm.r ), INDEX( _xlpm.prep_months, _xlpm.r ) + INDEX( _xlpm.const_months, _xlpm.r ) + _xlpm.delay ) ) ), _xlpm.operation_flag, _xlfn.MAKEARRAY( ROWS( _xlpm.property_data ), COLUMNS( _xlpm.timeline ), _xlfn.LAMBDA(_xlpm.r,_xlpm.c, IF( INDEX( _xlpm.timeline,, _xlpm.c ) >= INDEX( _xlpm.operation_start, _xlpm.r, 1 ), 1, 0 ) ) ), _xlpm.elapsed_month, _xlfn.MAKEARRAY( ROWS( _xlpm.property_data ), COLUMNS( _xlpm.timeline ), _xlfn.LAMBDA(_xlpm.r,_xlpm.c, SUM( INDEX(_xlpm.operation_flag, _xlpm.r, _xlfn.SEQUENCE( 1, _xlpm.c ) ) ) ) ), _xlpm.vacancy_rate, _xlfn.MAKEARRAY( ROWS( _xlpm.property_data ), COLUMNS( _xlpm.timeline ), _xlfn.LAMBDA(_xlpm.r,_xlpm.c, _xlfn.LET( _xlpm.moo, MEDIAN( 1, INDEX( _xlpm.elapsed_month, _xlpm.r, _xlpm.c ), 24 ), _xlpm.seg, MIN( MATCH( _xlpm.moo, _xlpm.moo_bp, 1 ), 3 ), _xlpm.lower_moo, INDEX( _xlpm.moo_bp, _xlpm.seg ), _xlpm.upper_moo, INDEX( _xlpm.moo_bp, _xlpm.seg + 1 ), _xlpm.lower_vac, INDEX( _xlpm.vac_bp, _xlpm.seg ), _xlpm.upper_vac, INDEX( _xlpm.vac_bp, _xlpm.seg + 1 ), IF( INDEX( _xlpm.operation_flag, _xlpm.r, _xlpm.c ) = 0, 0, _xlpm.lower_vac + ( _xlpm.upper_vac - _xlpm.lower_vac ) * ( _xlpm.moo - _xlpm.lower_moo ) / ( _xlpm.upper_moo - _xlpm.lower_moo ) ) ) ) ), _xlpm.vacancy_factor, 1 - _xlpm.vacancy_rate, _xlpm.inflation_flag, IF( MONTH( _xlpm.timeline ) = 1, 1, 0 ), _xlpm.inflation_data, CaseData!$J$15:$M$24, _xlpm.annual_rate, _xlfn.XLOOKUP( YEAR( _xlpm.timeline ), INDEX( _xlpm.inflation_data,, 1 ), INDEX( _xlpm.inflation_data,, 2 ) ), _xlpm.effective_step, _xlpm.inflation_flag * _xlpm.annual_rate, _xlpm.inflation_factor, _xlfn.SCAN( 1, _xlpm.effective_step, _xlfn.LAMBDA(_xlpm.prev,_xlpm.step, IF( _xlpm.step = 0, _xlpm.prev, _xlpm.prev * ( 1 + _xlpm.step ) ) ) ), _xlpm.rent, INDEX( _xlpm.property_data,, 2 ), _xlpm.operation_flag * _xlpm.rent * _xlpm.inflation_factor * _xlpm.vacancy_factor )} -> 0 | K69: 0 | L69: 0 | M69: 0 | N69: 0 | O69: 0 | P69: 0 | Q69: 0 | R69: 0 | S69: 0 | T69: 0 | U69: 0 | V69: 0 | W69: 0 | X69: 0 | Y69: 0 | Z69: 0 | AA69: 0 | AB69: 0 | AC69: 121246.12 | AD69: 169744.57 | AE69: 218243.02 | AF69: 266741.48 | AG69: 315239.92 | AH69: 378287.91 | AI69: 390897.51 | AJ69: 403507.1 | AK69: 416116.7 | AL69: 428726.3 | AM69: 441335.9 | AN69: 453945.49 | AO69: 456047.09 | AP69: 458148.69 | AQ69: 460250.29 | AR69: 462351.89 | AS69: 464453.49 | AT69: 482884.52 | AU69: 485059.67 | AV69: 487234.83 | AW69: 489409.98 | AX69: 491585.14 | AY69: 493760.29 | AZ69: 495935.45 | BA69: 495935.45 | BB69: 495935.45 | BC69: 495935.45 | BD69: 495935.45 | BE69: 495935.45 | BF69: 510813.51 | BG69: 510813.51 | BH69: 510813.51 | BI69: 510813.51 | BJ69: 510813.51 | BK69: 510813.51 | BL69: 510813.51 | BM69: 510813.51 | BN69: 510813.51 | BO69: 510813.51 | BP69: 510813.51 | BQ69: 510813.51 | BR69: 523583.85 | BS69: 523583.85 | BT69: 523583.85 | BU69: 523583.85 | BV69: 523583.85 | BW69: 523583.85 | BX69: 523583.85 | BY69: 523583.85 | BZ69: 523583.85 | CA69: 523583.85 | CB69: 523583.85 | CC69: 523583.85 | CD69: 536673.45 | CE69: 536673.45 | CF69: 536673.45 | CG69: 536673.45 | CH69: 536673.45 | CI69: 536673.45 | CJ69: 536673.45 | CK69: 536673.45 | CL69: 536673.45 | CM69: 536673.45 | CN69: 536673.45 | CO69: 536673.45 | CP69: 550090.28 | CQ69: 550090.28 | CR69: 550090.28 | CS69: 550090.28 | CT69: 550090.28 | CU69: 550090.28 | CV69: 550090.28 | CW69: 550090.28 | CX69: 550090.28 | CY69: 550090.28 | CZ69: 550090.28 | DA69: 550090.28 | DB69: 563842.54 | DC69: 563842.54 | DD69: 563842.54 | DE69: 563842.54 | DF69: 563842.54 | DG69: 563842.54 | DH69: 563842.54 | DI69: 563842.54 | DJ69: 563842.54 | DK69: 563842.54 | DL69: 563842.54 | DM69: 563842.54 | DN69: 577938.6 | DO69: 577938.6 | DP69: 577938.6 | DQ69: 577938.6 | DR69: 577938.6 | DS69: 577938.6 | DT69: 577938.6 | DU69: 577938.6 | DV69: 577938.6 | DW69: 577938.6 | DX69: 577938.6 | DY69: 577938.6
E70: Property G | G70: USD | J70: 0 | K70: 0 | L70: 0 | M70: 0 | N70: 0 | O70: 0 | P70: 0 | Q70: 0 | R70: 0 | S70: 0 | T70: 0 | U70: 0 | V70: 0 | W70: 0 | X70: 0 | Y70: 0 | Z70: 0 | AA70: 0 | AB70: 0 | AC70: 0 | AD70: 105061.69 | AE70: 147086.36 | AF70: 189111.04 | AG70: 231135.71 | AH70: 284086.8 | AI70: 327792.46 | AJ70: 338718.88 | AK70: 349645.3 | AL70: 360571.71 | AM70: 371498.13 | AN70: 382424.54 | AO70: 393350.96 | AP70: 395172.03 | AQ70: 396993.1 | AR70: 398814.17 | AS70: 400635.23 | AT70: 416542.27 | AU70: 418427.08 | AV70: 420311.89 | AW70: 422196.69 | AX70: 424081.5 | AY70: 425966.31 | AZ70: 427851.11 | BA70: 429735.92 | BB70: 429735.92 | BC70: 429735.92 | BD70: 429735.92 | BE70: 429735.92 | BF70: 442628 | BG70: 442628 | BH70: 442628 | BI70: 442628 | BJ70: 442628 | BK70: 442628 | BL70: 442628 | BM70: 442628 | BN70: 442628 | BO70: 442628 | BP70: 442628 | BQ70: 442628 | BR70: 453693.7 | BS70: 453693.7 | BT70: 453693.7 | BU70: 453693.7 | BV70: 453693.7 | BW70: 453693.7 | BX70: 453693.7 | BY70: 453693.7 | BZ70: 453693.7 | CA70: 453693.7 | CB70: 453693.7 | CC70: 453693.7 | CD70: 465036.04 | CE70: 465036.04 | CF70: 465036.04 | CG70: 465036.04 | CH70: 465036.04 | CI70: 465036.04 | CJ70: 465036.04 | CK70: 465036.04 | CL70: 465036.04 | CM70: 465036.04 | CN70: 465036.04 | CO70: 465036.04 | CP70: 476661.94 | CQ70: 476661.94 | CR70: 476661.94 | CS70: 476661.94 | CT70: 476661.94 | CU70: 476661.94 | CV70: 476661.94 | CW70: 476661.94 | CX70: 476661.94 | CY70: 476661.94 | CZ70: 476661.94 | DA70: 476661.94 | DB70: 488578.49 | DC70: 488578.49 | DD70: 488578.49 | DE70: 488578.49 | DF70: 488578.49 | DG70: 488578.49 | DH70: 488578.49 | DI70: 488578.49 | DJ70: 488578.49 | DK70: 488578.49 | DL70: 488578.49 | DM70: 488578.49 | DN70: 500792.95 | DO70: 500792.95 | DP70: 500792.95 | DQ70: 500792.95 | DR70: 500792.95 | DS70: 500792.95 | DT70: 500792.95 | DU70: 500792.95 | DV70: 500792.95 | DW70: 500792.95 | DX70: 500792.95 | DY70: 500792.95
E71: Property H | G71: USD | J71: 0 | K71: 0 | L71: 0 | M71: 0 | N71: 0 | O71: 0 | P71: 0 | Q71: 0 | R71: 0 | S71: 0 | T71: 0 | U71: 0 | V71: 0 | W71: 0 | X71: 0 | Y71: 0 | Z71: 0 | AA71: 0 | AB71: 0 | AC71: 0 | AD71: 0 | AE71: 0 | AF71: 0 | AG71: 0 | AH71: 0 | AI71: 141786.65 | AJ71: 198501.3 | AK71: 255215.96 | AL71: 311930.62 | AM71: 368645.28 | AN71: 425359.94 | AO71: 439538.6 | AP71: 453717.26 | AQ71: 467895.93 | AR71: 482074.59 | AS71: 496253.26 | AT71: 528297.04 | AU71: 530742.86 | AV71: 533188.68 | AW71: 535634.5 | AX71: 538080.32 | AY71: 540526.14 | AZ71: 542971.96 | BA71: 545417.78 | BB71: 547863.6 | BC71: 550309.42 | BD71: 552755.24 | BE71: 555201.06 | BF71: 574376.28 | BG71: 574376.28 | BH71: 574376.28 | BI71: 574376.28 | BJ71: 574376.28 | BK71: 574376.28 | BL71: 574376.28 | BM71: 574376.28 | BN71: 574376.28 | BO71: 574376.28 | BP71: 574376.28 | BQ71: 574376.28 | BR71: 588735.69 | BS71: 588735.69 | BT71: 588735.69 | BU71: 588735.69 | BV71: 588735.69 | BW71: 588735.69 | BX71: 588735.69 | BY71: 588735.69 | BZ71: 588735.69 | CA71: 588735.69 | CB71: 588735.69 | CC71: 588735.69 | CD71: 603454.08 | CE71: 603454.08 | CF71: 603454.08 | CG71: 603454.08 | CH71: 603454.08 | CI71: 603454.08 | CJ71: 603454.08 | CK71: 603454.08 | CL71: 603454.08 | CM71: 603454.08 | CN71: 603454.08 | CO71: 603454.08 | CP71: 618540.43 | CQ71: 618540.43 | CR71: 618540.43 | CS71: 618540.43 | CT71: 618540.43 | CU71: 618540.43 | CV71: 618540.43 | CW71: 618540.43 | CX71: 618540.43 | CY71: 618540.43 | CZ71: 618540.43 | DA71: 618540.43 | DB71: 634003.94 | DC71: 634003.94 | DD71: 634003.94 | DE71: 634003.94 | DF71: 634003.94 | DG71: 634003.94 | DH71: 634003.94 | DI71: 634003.94 | DJ71: 634003.94 | DK71: 634003.94 | DL71: 634003.94 | DM71: 634003.94 | DN71: 649854.04 | DO71: 649854.04 | DP71: 649854.04 | DQ71: 649854.04 | DR71: 649854.04 | DS71: 649854.04 | DT71: 649854.04 | DU71: 649854.04 | DV71: 649854.04 | DW71: 649854.04 | DX71: 649854.04 | DY71: 649854.04
E72: Property I | G72: USD | J72: 0 | K72: 0 | L72: 0 | M72: 0 | N72: 0 | O72: 0 | P72: 0 | Q72: 0 | R72: 0 | S72: 0 | T72: 0 | U72: 0 | V72: 0 | W72: 0 | X72: 0 | Y72: 0 | Z72: 0 | AA72: 0 | AB72: 0 | AC72: 0 | AD72: 0 | AE72: 0 | AF72: 0 | AG72: 0 | AH72: 0 | AI72: 0 | AJ72: 0 | AK72: 0 | AL72: 0 | AM72: 0 | AN72: 0 | AO72: 0 | AP72: 0 | AQ72: 169744.58 | AR72: 237642.4 | AS72: 305540.23 | AT72: 386508.4 | AU72: 456782.65 | AV72: 527056.91 | AW72: 544625.47 | AX72: 562194.03 | AY72: 579762.6 | AZ72: 597331.16 | BA72: 614899.72 | BB72: 632468.29 | BC72: 635396.38 | BD72: 638324.47 | BE72: 641252.57 | BF72: 663506.08 | BG72: 666522.02 | BH72: 669537.96 | BI72: 672553.89 | BJ72: 675569.83 | BK72: 678585.77 | BL72: 681601.7 | BM72: 684617.64 | BN72: 687633.58 | BO72: 687633.58 | BP72: 687633.58 | BQ72: 687633.58 | BR72: 704824.42 | BS72: 704824.42 | BT72: 704824.42 | BU72: 704824.42 | BV72: 704824.42 | BW72: 704824.42 | BX72: 704824.42 | BY72: 704824.42 | BZ72: 704824.42 | CA72: 704824.42 | CB72: 704824.42 | CC72: 704824.42 | CD72: 722445.03 | CE72: 722445.03 | CF72: 722445.03 | CG72: 722445.03 | CH72: 722445.03 | CI72: 722445.03 | CJ72: 722445.03 | CK72: 722445.03 | CL72: 722445.03 | CM72: 722445.03 | CN72: 722445.03 | CO72: 722445.03 | CP72: 740506.15 | CQ72: 740506.15 | CR72: 740506.15 | CS72: 740506.15 | CT72: 740506.15 | CU72: 740506.15 | CV72: 740506.15 | CW72: 740506.15 | CX72: 740506.15 | CY72: 740506.15 | CZ72: 740506.15 | DA72: 740506.15 | DB72: 759018.81 | DC72: 759018.81 | DD72: 759018.81 | DE72: 759018.81 | DF72: 759018.81 | DG72: 759018.81 | DH72: 759018.81 | DI72: 759018.81 | DJ72: 759018.81 | DK72: 759018.81 | DL72: 759018.81 | DM72: 759018.81 | DN72: 777994.28 | DO72: 777994.28 | DP72: 777994.28 | DQ72: 777994.28 | DR72: 777994.28 | DS72: 777994.28 | DT72: 777994.28 | DU72: 777994.28 | DV72: 777994.28 | DW72: 777994.28 | DX72: 777994.28 | DY72: 777994.28
E73: Property J | G73: USD | J73: 0 | K73: 0 | L73: 0 | M73: 0 | N73: 0 | O73: 0 | P73: 0 | Q73: 0 | R73: 0 | S73: 0 | T73: 0 | U73: 0 | V73: 0 | W73: 0 | X73: 0 | Y73: 0 | Z73: 0 | AA73: 0 | AB73: 0 | AC73: 0 | AD73: 0 | AE73: 0 | AF73: 0 | AG73: 0 | AH73: 0 | AI73: 0 | AJ73: 0 | AK73: 0 | AL73: 0 | AM73: 0 | AN73: 0 | AO73: 0 | AP73: 0 | AQ73: 0 | AR73: 0 | AS73: 168888.72 | AT73: 244719.76 | AU73: 314639.69 | AV73: 384559.62 | AW73: 454479.55 | AX73: 524399.48 | AY73: 541879.46 | AZ73: 559359.44 | BA73: 576839.42 | BB73: 594319.41 | BC73: 611799.39 | BD73: 629279.37 | BE73: 632192.7 | BF73: 654159.21 | BG73: 657159.94 | BH73: 660160.67 | BI73: 663161.4 | BJ73: 666162.13 | BK73: 669162.86 | BL73: 672163.59 | BM73: 675164.32 | BN73: 678165.06 | BO73: 681165.79 | BP73: 684166.52 | BQ73: 684166.52 | BR73: 701270.68 | BS73: 701270.68 | BT73: 701270.68 | BU73: 701270.68 | BV73: 701270.68 | BW73: 701270.68 | BX73: 701270.68 | BY73: 701270.68 | BZ73: 701270.68 | CA73: 701270.68 | CB73: 701270.68 | CC73: 701270.68 | CD73: 718802.45 | CE73: 718802.45 | CF73: 718802.45 | CG73: 718802.45 | CH73: 718802.45 | CI73: 718802.45 | CJ73: 718802.45 | CK73: 718802.45 | CL73: 718802.45 | CM73: 718802.45 | CN73: 718802.45 | CO73: 718802.45 | CP73: 736772.51 | CQ73: 736772.51 | CR73: 736772.51 | CS73: 736772.51 | CT73: 736772.51 | CU73: 736772.51 | CV73: 736772.51 | CW73: 736772.51 | CX73: 736772.51 | CY73: 736772.51 | CZ73: 736772.51 | DA73: 736772.51 | DB73: 755191.82 | DC73: 755191.82 | DD73: 755191.82 | DE73: 755191.82 | DF73: 755191.82 | DG73: 755191.82 | DH73: 755191.82 | DI73: 755191.82 | DJ73: 755191.82 | DK73: 755191.82 | DL73: 755191.82 | DM73: 755191.82 | DN73: 774071.61 | DO73: 774071.61 | DP73: 774071.61 | DQ73: 774071.61 | DR73: 774071.61 | DS73: 774071.61 | DT73: 774071.61 | DU73: 774071.61 | DV73: 774071.61 | DW73: 774071.61 | DX73: 774071.61 | DY73: 774071.61
E74: Property K | G74: USD | J74: 0 | K74: 0 | L74: 0 | M74: 0 | N74: 0 | O74: 0 | P74: 0 | Q74: 0 | R74: 0 | S74: 0 | T74: 0 | U74: 0 | V74: 0 | W74: 0 | X74: 0 | Y74: 0 | Z74: 0 | AA74: 0 | AB74: 0 | AC74: 0 | AD74: 0 | AE74: 0 | AF74: 0 | AG74: 0 | AH74: 0 | AI74: 0 | AJ74: 0 | AK74: 0 | AL74: 0 | AM74: 0 | AN74: 0 | AO74: 0 | AP74: 0 | AQ74: 103558.46 | AR74: 144981.84 | AS74: 186405.22 | AT74: 235802.6 | AU74: 278675.8 | AV74: 321549 | AW74: 332267.3 | AX74: 342985.6 | AY74: 353703.9 | AZ74: 364422.2 | BA74: 375140.5 | BB74: 385858.8 | BC74: 387645.19 | BD74: 389431.57 | BE74: 391217.95 | BF74: 404794.47 | BG74: 406634.44 | BH74: 408474.42 | BI74: 410314.39 | BJ74: 412154.37 | BK74: 413994.34 | BL74: 415834.32 | BM74: 417674.29 | BN74: 419514.27 | BO74: 419514.27 | BP74: 419514.27 | BQ74: 419514.27 | BR74: 430002.12 | BS74: 430002.12 | BT74: 430002.12 | BU74: 430002.12 | BV74: 430002.12 | BW74: 430002.12 | BX74: 430002.12 | BY74: 430002.12 | BZ74: 430002.12 | CA74: 430002.12 | CB74: 430002.12 | CC74: 430002.12 | CD74: 440752.18 | CE74: 440752.18 | CF74: 440752.18 | CG74: 440752.18 | CH74: 440752.18 | CI74: 440752.18 | CJ74: 440752.18 | CK74: 440752.18 | CL74: 440752.18 | CM74: 440752.18 | CN74: 440752.18 | CO74: 440752.18 | CP74: 451770.98 | CQ74: 451770.98 | CR74: 451770.98 | CS74: 451770.98 | CT74: 451770.98 | CU74: 451770.98 | CV74: 451770.98 | CW74: 451770.98 | CX74: 451770.98 | CY74: 451770.98 | CZ74: 451770.98 | DA74: 451770.98 | DB74: 463065.25 | DC74: 463065.25 | DD74: 463065.25 | DE74: 463065.25 | DF74: 463065.25 | DG74: 463065.25 | DH74: 463065.25 | DI74: 463065.25 | DJ74: 463065.25 | DK74: 463065.25 | DL74: 463065.25 | DM74: 463065.25 | DN74: 474641.89 | DO74: 474641.89 | DP74: 474641.89 | DQ74: 474641.89 | DR74: 474641.89 | DS74: 474641.89 | DT74: 474641.89 | DU74: 474641.89 | DV74: 474641.89 | DW74: 474641.89 | DX74: 474641.89 | DY74: 474641.89
E75: Property L | G75: USD | J75: 0 | K75: 0 | L75: 0 | M75: 0 | N75: 0 | O75: 0 | P75: 0 | Q75: 0 | R75: 0 | S75: 0 | T75: 0 | U75: 0 | V75: 0 | W75: 0 | X75: 0 | Y75: 0 | Z75: 0 | AA75: 0 | AB75: 0 | AC75: 0 | AD75: 0 | AE75: 0 | AF75: 0 | AG75: 0 | AH75: 0 | AI75: 0 | AJ75: 0 | AK75: 0 | AL75: 0 | AM75: 0 | AN75: 0 | AO75: 0 | AP75: 0 | AQ75: 0 | AR75: 0 | AS75: 0 | AT75: 0 | AU75: 0 | AV75: 0 | AW75: 0 | AX75: 0 | AY75: 0 | AZ75: 0 | BA75: 0 | BB75: 0 | BC75: 0 | BD75: 0 | BE75: 0 | BF75: 0 | BG75: 0 | BH75: 222621.75 | BI75: 311670.45 | BJ75: 400719.15 | BK75: 489767.85 | BL75: 578816.55 | BM75: 667865.25 | BN75: 690127.43 | BO75: 712389.6 | BP75: 734651.78 | BQ75: 756913.95 | BR75: 798655.53 | BS75: 821474.26 | BT75: 825277.38 | BU75: 829080.5 | BV75: 832883.62 | BW75: 836686.75 | BX75: 840489.87 | BY75: 844292.99 | BZ75: 848096.11 | CA75: 851899.23 | CB75: 855702.35 | CC75: 859505.47 | CD75: 884891.31 | CE75: 888789.51 | CF75: 888789.51 | CG75: 888789.51 | CH75: 888789.51 | CI75: 888789.51 | CJ75: 888789.51 | CK75: 888789.51 | CL75: 888789.51 | CM75: 888789.51 | CN75: 888789.51 | CO75: 888789.51 | CP75: 911009.25 | CQ75: 911009.25 | CR75: 911009.25 | CS75: 911009.25 | CT75: 911009.25 | CU75: 911009.25 | CV75: 911009.25 | CW75: 911009.25 | CX75: 911009.25 | CY75: 911009.25 | CZ75: 911009.25 | DA75: 911009.25 | DB75: 933784.48 | DC75: 933784.48 | DD75: 933784.48 | DE75: 933784.48 | DF75: 933784.48 | DG75: 933784.48 | DH75: 933784.48 | DI75: 933784.48 | DJ75: 933784.48 | DK75: 933784.48 | DL75: 933784.48 | DM75: 933784.48 | DN75: 957129.09 | DO75: 957129.09 | DP75: 957129.09 | DQ75: 957129.09 | DR75: 957129.09 | DS75: 957129.09 | DT75: 957129.09 | DU75: 957129.09 | DV75: 957129.09 | DW75: 957129.09 | DX75: 957129.09 | DY75: 957129.09
E76: Property M | G76: USD | J76: 0 | K76: 0 | L76: 0 | M76: 0 | N76: 0 | O76: 0 | P76: 0 | Q76: 0 | R76: 0 | S76: 0 | T76: 0 | U76: 0 | V76: 0 | W76: 0 | X76: 0 | Y76: 0 | Z76: 0 | AA76: 0 | AB76: 0 | AC76: 0 | AD76: 0 | AE76: 0 | AF76: 0 | AG76: 0 | AH76: 0 | AI76: 0 | AJ76: 0 | AK76: 0 | AL76: 0 | AM76: 0 | AN76: 0 | AO76: 0 | AP76: 0 | AQ76: 0 | AR76: 0 | AS76: 0 | AT76: 0 | AU76: 0 | AV76: 0 | AW76: 0 | AX76: 0 | AY76: 0 | AZ76: 0 | BA76: 0 | BB76: 0 | BC76: 0 | BD76: 0 | BE76: 0 | BF76: 0 | BG76: 0 | BH76: 163620.9 | BI76: 229069.27 | BJ76: 294517.63 | BK76: 359965.99 | BL76: 425414.35 | BM76: 490862.71 | BN76: 507224.8 | BO76: 523586.89 | BP76: 539948.98 | BQ76: 556311.07 | BR76: 586989.99 | BS76: 603761.14 | BT76: 606556.33 | BU76: 609351.52 | BV76: 612146.71 | BW76: 614941.9 | BX76: 617737.09 | BY76: 620532.28 | BZ76: 623327.47 | CA76: 626122.66 | CB76: 628917.85 | CC76: 631713.04 | CD76: 650370.94 | CE76: 653236.01 | CF76: 653236.01 | CG76: 653236.01 | CH76: 653236.01 | CI76: 653236.01 | CJ76: 653236.01 | CK76: 653236.01 | CL76: 653236.01 | CM76: 653236.01 | CN76: 653236.01 | CO76: 653236.01 | CP76: 669566.91 | CQ76: 669566.91 | CR76: 669566.91 | CS76: 669566.91 | CT76: 669566.91 | CU76: 669566.91 | CV76: 669566.91 | CW76: 669566.91 | CX76: 669566.91 | CY76: 669566.91 | CZ76: 669566.91 | DA76: 669566.91 | DB76: 686306.08 | DC76: 686306.08 | DD76: 686306.08 | DE76: 686306.08 | DF76: 686306.08 | DG76: 686306.08 | DH76: 686306.08 | DI76: 686306.08 | DJ76: 686306.08 | DK76: 686306.08 | DL76: 686306.08 | DM76: 686306.08 | DN76: 703463.73 | DO76: 703463.73 | DP76: 703463.73 | DQ76: 703463.73 | DR76: 703463.73 | DS76: 703463.73 | DT76: 703463.73 | DU76: 703463.73 | DV76: 703463.73 | DW76: 703463.73 | DX76: 703463.73 | DY76: 703463.73
E77: Property N | G77: USD | J77: 0 | K77: 0 | L77: 0 | M77: 0 | N77: 0 | O77: 0 | P77: 0 | Q77: 0 | R77: 0 | S77: 0 | T77: 0 | U77: 0 | V77: 0 | W77: 0 | X77: 0 | Y77: 0 | Z77: 0 | AA77: 0 | AB77: 0 | AC77: 0 | AD77: 0 | AE77: 0 | AF77: 0 | AG77: 0 | AH77: 0 | AI77: 0 | AJ77: 0 | AK77: 0 | AL77: 0 | AM77: 0 | AN77: 0 | AO77: 0 | AP77: 0 | AQ77: 0 | AR77: 0 | AS77: 0 | AT77: 0 | AU77: 0 | AV77: 0 | AW77: 0 | AX77: 0 | AY77: 0 | AZ77: 0 | BA77: 0 | BB77: 0 | BC77: 0 | BD77: 0 | BE77: 0 | BF77: 0 | BG77: 0 | BH77: 0 | BI77: 0 | BJ77: 0 | BK77: 0 | BL77: 0 | BM77: 0 | BN77: 0 | BO77: 0 | BP77: 0 | BQ77: 0 | BR77: 0 | BS77: 0 | BT77: 0 | BU77: 233174.99 | BV77: 326444.99 | BW77: 419714.99 | BX77: 512984.99 | BY77: 606254.99 | BZ77: 699524.98 | CA77: 722842.48 | CB77: 746159.98 | CC77: 769477.48 | CD77: 812614.86 | CE77: 836515.29 | CF77: 860415.73 | CG77: 864399.14 | CH77: 868382.54 | CI77: 872365.95 | CJ77: 876349.35 | CK77: 880332.76 | CL77: 884316.17 | CM77: 888299.57 | CN77: 892282.98 | CO77: 896266.39 | CP77: 922756.04 | CQ77: 926839.03 | CR77: 930922.02 | CS77: 930922.02 | CT77: 930922.02 | CU77: 930922.02 | CV77: 930922.02 | CW77: 930922.02 | CX77: 930922.02 | CY77: 930922.02 | CZ77: 930922.02 | DA77: 930922.02 | DB77: 954195.07 | DC77: 954195.07 | DD77: 954195.07 | DE77: 954195.07 | DF77: 954195.07 | DG77: 954195.07 | DH77: 954195.07 | DI77: 954195.07 | DJ77: 954195.07 | DK77: 954195.07 | DL77: 954195.07 | DM77: 954195.07 | DN77: 978049.95 | DO77: 978049.95 | DP77: 978049.95 | DQ77: 978049.95 | DR77: 978049.95 | DS77: 978049.95 | DT77: 978049.95 | DU77: 978049.95 | DV77: 978049.95 | DW77: 978049.95 | DX77: 978049.95 | DY77: 978049.95
E78: Property O | G78: USD | J78: 0 | K78: 0 | L78: 0 | M78: 0 | N78: 0 | O78: 0 | P78: 0 | Q78: 0 | R78: 0 | S78: 0 | T78: 0 | U78: 0 | V78: 0 | W78: 0 | X78: 0 | Y78: 0 | Z78: 0 | AA78: 0 | AB78: 0 | AC78: 0 | AD78: 0 | AE78: 0 | AF78: 0 | AG78: 0 | AH78: 0 | AI78: 0 | AJ78: 0 | AK78: 0 | AL78: 0 | AM78: 0 | AN78: 0 | AO78: 0 | AP78: 0 | AQ78: 0 | AR78: 0 | AS78: 0 | AT78: 0 | AU78: 0 | AV78: 0 | AW78: 0 | AX78: 0 | AY78: 0 | AZ78: 0 | BA78: 0 | BB78: 0 | BC78: 0 | BD78: 0 | BE78: 0 | BF78: 0 | BG78: 0 | BH78: 0 | BI78: 0 | BJ78: 0 | BK78: 0 | BL78: 0 | BM78: 0 | BN78: 0 | BO78: 0 | BP78: 0 | BQ78: 0 | BR78: 0 | BS78: 0 | BT78: 0 | BU78: 0 | BV78: 0 | BW78: 0 | BX78: 0 | BY78: 0 | BZ78: 0 | CA78: 0 | CB78: 0 | CC78: 239409.62 | CD78: 343552.8 | CE78: 441710.75 | CF78: 539868.69 | CG78: 638026.64 | CH78: 736184.58 | CI78: 760724.07 | CJ78: 785263.55 | CK78: 809803.04 | CL78: 834342.53 | CM78: 858882.01 | CN78: 883421.5 | CO78: 887511.41 | CP78: 913891.36 | CQ78: 918083.52 | CR78: 922275.68 | CS78: 926467.85 | CT78: 930660.01 | CU78: 934852.17 | CV78: 939044.33 | CW78: 943236.5 | CX78: 947428.66 | CY78: 951620.82 | CZ78: 955812.98 | DA78: 955812.98 | DB78: 979708.31 | DC78: 979708.31 | DD78: 979708.31 | DE78: 979708.31 | DF78: 979708.31 | DG78: 979708.31 | DH78: 979708.31 | DI78: 979708.31 | DJ78: 979708.31 | DK78: 979708.31 | DL78: 979708.31 | DM78: 979708.31 | DN78: 1004201 | DO78: 1004201 | DP78: 1004201 | DQ78: 1004201 | DR78: 1004201 | DS78: 1004201 | DT78: 1004201 | DU78: 1004201 | DV78: 1004201 | DW78: 1004201 | DX78: 1004201 | DY78: 1004201
E79: Rent revenue from new properties | G79: USD | J79: {=_xlfn.BYCOL(_xlfn.ANCHORARRAY( $J$69), _xleta.SUM )} -> 0 | K79: 0 | L79: 0 | M79: 0 | N79: 0 | O79: 0 | P79: 0 | Q79: 0 | R79: 0 | S79: 0 | T79: 0 | U79: 0 | V79: 0 | W79: 0 | X79: 0 | Y79: 0 | Z79: 0 | AA79: 0 | AB79: 0 | AC79: 121246.12 | AD79: 274806.26 | AE79: 365329.39 | AF79: 455852.51 | AG79: 546375.64 | AH79: 662374.71 | AI79: 860476.62 | AJ79: 940727.29 | AK79: 1020978 | AL79: 1101228.6 | AM79: 1181479.3 | AN79: 1261730 | AO79: 1288936.6 | AP79: 1307038 | AQ79: 1598442.3 | AR79: 1725864.9 | AS79: 2022176.2 | AT79: 2294754.6 | AU79: 2484327.8 | AV79: 2673900.9 | AW79: 2778613.5 | AX79: 2883326.1 | AY79: 2935598.7 | AZ79: 2987871.3 | BA79: 3037968.8 | BB79: 3086181.5 | BC79: 3110821.7 | BD79: 3135462 | BE79: 3145535.6 | BF79: 3250277.6 | BG79: 3258134.2 | BH79: 3652233.5 | BI79: 3814587.2 | BJ79: 3976940.9 | BK79: 4139294.6 | BL79: 4301648.3 | BM79: 4464002 | BN79: 4510482.9 | BO79: 4552107.9 | BP79: 4593732.9 | BQ79: 4632357.2 | BR79: 4787756 | BS79: 4827345.8 | BT79: 4833944.2 | BU79: 5073717.5 | BV79: 5173585.8 | BW79: 5273454.1 | BX79: 5373322.4 | BY79: 5473190.7 | BZ79: 5573059 | CA79: 5602974.8 | CB79: 5632890.6 | CC79: 5902216.1 | CD79: 6178593.1 | CE79: 6307414.8 | CF79: 6429473.2 | CG79: 6531614.5 | CH79: 6633755.9 | CI79: 6662278.7 | CJ79: 6690801.6 | CK79: 6719324.5 | CL79: 6747847.4 | CM79: 6776370.3 | CN79: 6804893.2 | CO79: 6812966.5 | CP79: 6991565.8 | CQ79: 6999841 | CR79: 7008116.2 | CS79: 7012308.3 | CT79: 7016500.5 | CU79: 7020692.6 | CV79: 7024884.8 | CW79: 7029077 | CX79: 7033269.1 | CY79: 7037461.3 | CZ79: 7041653.5 | DA79: 7041653.5 | DB79: 7217694.8 | DC79: 7217694.8 | DD79: 7217694.8 | DE79: 7217694.8 | DF79: 7217694.8 | DG79: 7217694.8 | DH79: 7217694.8 | DI79: 7217694.8 | DJ79: 7217694.8 | DK79: 7217694.8 | DL79: 7217694.8 | DM79: 7217694.8 | DN79: 7398137.2 | DO79: 7398137.2 | DP79: 7398137.2 | DQ79: 7398137.2 | DR79: 7398137.2 | DS79: 7398137.2 | DT79: 7398137.2 | DU79: 7398137.2 | DV79: 7398137.2 | DW79: 7398137.2 | DX79: 7398137.2 | DY79: 7398137.2
C82: OPEX
C83: (adjusted for inflation)
E84: {=_xlfn.LET( _xlpm.property_data, CaseData!$A$15:$H$24, _xlfn.CHOOSECOLS( _xlpm.property_data, {1} ) )} -> Property F | G84: USD | J84: {=_xlfn.LET( _xlpm.timeline,_xlfn.ANCHORARRAY( $J$3), _xlpm.property_data, CaseData!$A$15:$H$24, _xlpm.property_rows, INDEX( _xlpm.property_data, 0, 1 ), _xlpm.purchase_date, INDEX( _xlpm.property_data,, 6 ), _xlpm.prep_months, INDEX( _xlpm.property_data,, 7 ), _xlpm.const_months, INDEX( _xlpm.property_data,, 8 ), _xlpm.delay, IF( $F$9 = 0, 0, 12 ), _xlpm.operation_start, _xlfn.MAKEARRAY( ROWS( _xlpm.property_data ), 1, _xlfn.LAMBDA(_xlpm.r,_xlpm.c, EOMONTH( INDEX( _xlpm.purchase_date, _xlpm.r ), INDEX( _xlpm.prep_months, _xlpm.r ) + INDEX( _xlpm.const_months, _xlpm.r ) + _xlpm.delay ) ) ), _xlpm.operation_flag, _xlfn.MAKEARRAY( ROWS( _xlpm.property_data ), COLUMNS( _xlpm.timeline ), _xlfn.LAMBDA(_xlpm.r,_xlpm.c, IF( INDEX( _xlpm.timeline,, _xlpm.c ) >= INDEX( _xlpm.operation_start, _xlpm.r, 1 ), 1, 0 ) ) ), _xlpm.elapsed_month, _xlfn.MAKEARRAY( ROWS( _xlpm.property_data ), COLUMNS( _xlpm.timeline ), _xlfn.LAMBDA(_xlpm.r,_xlpm.c, SUM( INDEX(_xlpm.operation_flag, _xlpm.r, _xlfn.SEQUENCE( 1, _xlpm.c ) ) ) ) ), _xlpm.inflation_flag, IF( MONTH( _xlpm.timeline ) = 1, 1, 0 ), _xlpm.inflation_data, CaseData!$J$15:$M$24, _xlpm.annual_rate, _xlfn.XLOOKUP( YEAR( _xlpm.timeline ), INDEX( _xlpm.inflation_data,, 1 ), INDEX( _xlpm.inflation_data,, 3 ) ), _xlpm.effective_step, _xlpm.inflation_flag * _xlpm.annual_rate, _xlpm.inflation_factor, _xlfn.SCAN( 1, _xlpm.effective_step, _xlfn.LAMBDA(_xlpm.prev,_xlpm.step, IF( _xlpm.step = 0, _xlpm.prev, _xlpm.prev * ( 1 + _xlpm.step ) ) ) ), _xlpm.opex, INDEX( _xlpm.property_data,, 3 ), _xlpm.operation_flag * _xlpm.opex * _xlpm.inflation_factor )} -> 0 | K84: 0 | L84: 0 | M84: 0 | N84: 0 | O84: 0 | P84: 0 | Q84: 0 | R84: 0 | S84: 0 | T84: 0 | U84: 0 | V84: 0 | W84: 0 | X84: 0 | Y84: 0 | Z84: 0 | AA84: 0 | AB84: 0 | AC84: 143956.64 | AD84: 143956.64 | AE84: 143956.64 | AF84: 143956.64 | AG84: 143956.64 | AH84: 147555.55 | AI84: 147555.55 | AJ84: 147555.55 | AK84: 147555.55 | AL84: 147555.55 | AM84: 147555.55 | AN84: 147555.55 | AO84: 147555.55 | AP84: 147555.55 | AQ84: 147555.55 | AR84: 147555.55 | AS84: 147555.55 | AT84: 151244.44 | AU84: 151244.44 | AV84: 151244.44 | AW84: 151244.44 | AX84: 151244.44 | AY84: 151244.44 | AZ84: 151244.44 | BA84: 151244.44 | BB84: 151244.44 | BC84: 151244.44 | BD84: 151244.44 | BE84: 151244.44 | BF84: 155025.55 | BG84: 155025.55 | BH84: 155025.55 | BI84: 155025.55 | BJ84: 155025.55 | BK84: 155025.55 | BL84: 155025.55 | BM84: 155025.55 | BN84: 155025.55 | BO84: 155025.55 | BP84: 155025.55 | BQ84: 155025.55 | BR84: 158901.19 | BS84: 158901.19 | BT84: 158901.19 | BU84: 158901.19 | BV84: 158901.19 | BW84: 158901.19 | BX84: 158901.19 | BY84: 158901.19 | BZ84: 158901.19 | CA84: 158901.19 | CB84: 158901.19 | CC84: 158901.19 | CD84: 162873.72 | CE84: 162873.72 | CF84: 162873.72 | CG84: 162873.72 | CH84: 162873.72 | CI84: 162873.72 | CJ84: 162873.72 | CK84: 162873.72 | CL84: 162873.72 | CM84: 162873.72 | CN84: 162873.72 | CO84: 162873.72 | CP84: 166945.57 | CQ84: 166945.57 | CR84: 166945.57 | CS84: 166945.57 | CT84: 166945.57 | CU84: 166945.57 | CV84: 166945.57 | CW84: 166945.57 | CX84: 166945.57 | CY84: 166945.57 | CZ84: 166945.57 | DA84: 166945.57 | DB84: 171119.2 | DC84: 171119.2 | DD84: 171119.2 | DE84: 171119.2 | DF84: 171119.2 | DG84: 171119.2 | DH84: 171119.2 | DI84: 171119.2 | DJ84: 171119.2 | DK84: 171119.2 | DL84: 171119.2 | DM84: 171119.2 | DN84: 175397.18 | DO84: 175397.18 | DP84: 175397.18 | DQ84: 175397.18 | DR84: 175397.18 | DS84: 175397.18 | DT84: 175397.18 | DU84: 175397.18 | DV84: 175397.18 | DW84: 175397.18 | DX84: 175397.18 | DY84: 175397.18
E85: Property G | G85: USD | J85: 0 | K85: 0 | L85: 0 | M85: 0 | N85: 0 | O85: 0 | P85: 0 | Q85: 0 | R85: 0 | S85: 0 | T85: 0 | U85: 0 | V85: 0 | W85: 0 | X85: 0 | Y85: 0 | Z85: 0 | AA85: 0 | AB85: 0 | AC85: 0 | AD85: 120716.81 | AE85: 120716.81 | AF85: 120716.81 | AG85: 120716.81 | AH85: 123734.73 | AI85: 123734.73 | AJ85: 123734.73 | AK85: 123734.73 | AL85: 123734.73 | AM85: 123734.73 | AN85: 123734.73 | AO85: 123734.73 | AP85: 123734.73 | AQ85: 123734.73 | AR85: 123734.73 | AS85: 123734.73 | AT85: 126828.1 | AU85: 126828.1 | AV85: 126828.1 | AW85: 126828.1 | AX85: 126828.1 | AY85: 126828.1 | AZ85: 126828.1 | BA85: 126828.1 | BB85: 126828.1 | BC85: 126828.1 | BD85: 126828.1 | BE85: 126828.1 | BF85: 129998.8 | BG85: 129998.8 | BH85: 129998.8 | BI85: 129998.8 | BJ85: 129998.8 | BK85: 129998.8 | BL85: 129998.8 | BM85: 129998.8 | BN85: 129998.8 | BO85: 129998.8 | BP85: 129998.8 | BQ85: 129998.8 | BR85: 133248.77 | BS85: 133248.77 | BT85: 133248.77 | BU85: 133248.77 | BV85: 133248.77 | BW85: 133248.77 | BX85: 133248.77 | BY85: 133248.77 | BZ85: 133248.77 | CA85: 133248.77 | CB85: 133248.77 | CC85: 133248.77 | CD85: 136579.99 | CE85: 136579.99 | CF85: 136579.99 | CG85: 136579.99 | CH85: 136579.99 | CI85: 136579.99 | CJ85: 136579.99 | CK85: 136579.99 | CL85: 136579.99 | CM85: 136579.99 | CN85: 136579.99 | CO85: 136579.99 | CP85: 139994.49 | CQ85: 139994.49 | CR85: 139994.49 | CS85: 139994.49 | CT85: 139994.49 | CU85: 139994.49 | CV85: 139994.49 | CW85: 139994.49 | CX85: 139994.49 | CY85: 139994.49 | CZ85: 139994.49 | DA85: 139994.49 | DB85: 143494.36 | DC85: 143494.36 | DD85: 143494.36 | DE85: 143494.36 | DF85: 143494.36 | DG85: 143494.36 | DH85: 143494.36 | DI85: 143494.36 | DJ85: 143494.36 | DK85: 143494.36 | DL85: 143494.36 | DM85: 143494.36 | DN85: 147081.71 | DO85: 147081.71 | DP85: 147081.71 | DQ85: 147081.71 | DR85: 147081.71 | DS85: 147081.71 | DT85: 147081.71 | DU85: 147081.71 | DV85: 147081.71 | DW85: 147081.71 | DX85: 147081.71 | DY85: 147081.71
E86: Property H | G86: USD | J86: 0 | K86: 0 | L86: 0 | M86: 0 | N86: 0 | O86: 0 | P86: 0 | Q86: 0 | R86: 0 | S86: 0 | T86: 0 | U86: 0 | V86: 0 | W86: 0 | X86: 0 | Y86: 0 | Z86: 0 | AA86: 0 | AB86: 0 | AC86: 0 | AD86: 0 | AE86: 0 | AF86: 0 | AG86: 0 | AH86: 0 | AI86: 144507.95 | AJ86: 144507.95 | AK86: 144507.95 | AL86: 144507.95 | AM86: 144507.95 | AN86: 144507.95 | AO86: 144507.95 | AP86: 144507.95 | AQ86: 144507.95 | AR86: 144507.95 | AS86: 144507.95 | AT86: 148120.65 | AU86: 148120.65 | AV86: 148120.65 | AW86: 148120.65 | AX86: 148120.65 | AY86: 148120.65 | AZ86: 148120.65 | BA86: 148120.65 | BB86: 148120.65 | BC86: 148120.65 | BD86: 148120.65 | BE86: 148120.65 | BF86: 151823.67 | BG86: 151823.67 | BH86: 151823.67 | BI86: 151823.67 | BJ86: 151823.67 | BK86: 151823.67 | BL86: 151823.67 | BM86: 151823.67 | BN86: 151823.67 | BO86: 151823.67 | BP86: 151823.67 | BQ86: 151823.67 | BR86: 155619.26 | BS86: 155619.26 | BT86: 155619.26 | BU86: 155619.26 | BV86: 155619.26 | BW86: 155619.26 | BX86: 155619.26 | BY86: 155619.26 | BZ86: 155619.26 | CA86: 155619.26 | CB86: 155619.26 | CC86: 155619.26 | CD86: 159509.74 | CE86: 159509.74 | CF86: 159509.74 | CG86: 159509.74 | CH86: 159509.74 | CI86: 159509.74 | CJ86: 159509.74 | CK86: 159509.74 | CL86: 159509.74 | CM86: 159509.74 | CN86: 159509.74 | CO86: 159509.74 | CP86: 163497.48 | CQ86: 163497.48 | CR86: 163497.48 | CS86: 163497.48 | CT86: 163497.48 | CU86: 163497.48 | CV86: 163497.48 | CW86: 163497.48 | CX86: 163497.48 | CY86: 163497.48 | CZ86: 163497.48 | DA86: 163497.48 | DB86: 167584.92 | DC86: 167584.92 | DD86: 167584.92 | DE86: 167584.92 | DF86: 167584.92 | DG86: 167584.92 | DH86: 167584.92 | DI86: 167584.92 | DJ86: 167584.92 | DK86: 167584.92 | DL86: 167584.92 | DM86: 167584.92 | DN86: 171774.54 | DO86: 171774.54 | DP86: 171774.54 | DQ86: 171774.54 | DR86: 171774.54 | DS86: 171774.54 | DT86: 171774.54 | DU86: 171774.54 | DV86: 171774.54 | DW86: 171774.54 | DX86: 171774.54 | DY86: 171774.54
E87: Property I | G87: USD | J87: 0 | K87: 0 | L87: 0 | M87: 0 | N87: 0 | O87: 0 | P87: 0 | Q87: 0 | R87: 0 | S87: 0 | T87: 0 | U87: 0 | V87: 0 | W87: 0 | X87: 0 | Y87: 0 | Z87: 0 | AA87: 0 | AB87: 0 | AC87: 0 | AD87: 0 | AE87: 0 | AF87: 0 | AG87: 0 | AH87: 0 | AI87: 0 | AJ87: 0 | AK87: 0 | AL87: 0 | AM87: 0 | AN87: 0 | AO87: 0 | AP87: 0 | AQ87: 179409.98 | AR87: 179409.98 | AS87: 179409.98 | AT87: 183895.23 | AU87: 183895.23 | AV87: 183895.23 | AW87: 183895.23 | AX87: 183895.23 | AY87: 183895.23 | AZ87: 183895.23 | BA87: 183895.23 | BB87: 183895.23 | BC87: 183895.23 | BD87: 183895.23 | BE87: 183895.23 | BF87: 188492.61 | BG87: 188492.61 | BH87: 188492.61 | BI87: 188492.61 | BJ87: 188492.61 | BK87: 188492.61 | BL87: 188492.61 | BM87: 188492.61 | BN87: 188492.61 | BO87: 188492.61 | BP87: 188492.61 | BQ87: 188492.61 | BR87: 193204.92 | BS87: 193204.92 | BT87: 193204.92 | BU87: 193204.92 | BV87: 193204.92 | BW87: 193204.92 | BX87: 193204.92 | BY87: 193204.92 | BZ87: 193204.92 | CA87: 193204.92 | CB87: 193204.92 | CC87: 193204.92 | CD87: 198035.05 | CE87: 198035.05 | CF87: 198035.05 | CG87: 198035.05 | CH87: 198035.05 | CI87: 198035.05 | CJ87: 198035.05 | CK87: 198035.05 | CL87: 198035.05 | CM87: 198035.05 | CN87: 198035.05 | CO87: 198035.05 | CP87: 202985.92 | CQ87: 202985.92 | CR87: 202985.92 | CS87: 202985.92 | CT87: 202985.92 | CU87: 202985.92 | CV87: 202985.92 | CW87: 202985.92 | CX87: 202985.92 | CY87: 202985.92 | CZ87: 202985.92 | DA87: 202985.92 | DB87: 208060.57 | DC87: 208060.57 | DD87: 208060.57 | DE87: 208060.57 | DF87: 208060.57 | DG87: 208060.57 | DH87: 208060.57 | DI87: 208060.57 | DJ87: 208060.57 | DK87: 208060.57 | DL87: 208060.57 | DM87: 208060.57 | DN87: 213262.09 | DO87: 213262.09 | DP87: 213262.09 | DQ87: 213262.09 | DR87: 213262.09 | DS87: 213262.09 | DT87: 213262.09 | DU87: 213262.09 | DV87: 213262.09 | DW87: 213262.09 | DX87: 213262.09 | DY87: 213262.09
E88: Property J | G88: USD | J88: 0 | K88: 0 | L88: 0 | M88: 0 | N88: 0 | O88: 0 | P88: 0 | Q88: 0 | R88: 0 | S88: 0 | T88: 0 | U88: 0 | V88: 0 | W88: 0 | X88: 0 | Y88: 0 | Z88: 0 | AA88: 0 | AB88: 0 | AC88: 0 | AD88: 0 | AE88: 0 | AF88: 0 | AG88: 0 | AH88: 0 | AI88: 0 | AJ88: 0 | AK88: 0 | AL88: 0 | AM88: 0 | AN88: 0 | AO88: 0 | AP88: 0 | AQ88: 0 | AR88: 0 | AS88: 178505.39 | AT88: 182968.02 | AU88: 182968.02 | AV88: 182968.02 | AW88: 182968.02 | AX88: 182968.02 | AY88: 182968.02 | AZ88: 182968.02 | BA88: 182968.02 | BB88: 182968.02 | BC88: 182968.02 | BD88: 182968.02 | BE88: 182968.02 | BF88: 187542.23 | BG88: 187542.23 | BH88: 187542.23 | BI88: 187542.23 | BJ88: 187542.23 | BK88: 187542.23 | BL88: 187542.23 | BM88: 187542.23 | BN88: 187542.23 | BO88: 187542.23 | BP88: 187542.23 | BQ88: 187542.23 | BR88: 192230.78 | BS88: 192230.78 | BT88: 192230.78 | BU88: 192230.78 | BV88: 192230.78 | BW88: 192230.78 | BX88: 192230.78 | BY88: 192230.78 | BZ88: 192230.78 | CA88: 192230.78 | CB88: 192230.78 | CC88: 192230.78 | CD88: 197036.55 | CE88: 197036.55 | CF88: 197036.55 | CG88: 197036.55 | CH88: 197036.55 | CI88: 197036.55 | CJ88: 197036.55 | CK88: 197036.55 | CL88: 197036.55 | CM88: 197036.55 | CN88: 197036.55 | CO88: 197036.55 | CP88: 201962.46 | CQ88: 201962.46 | CR88: 201962.46 | CS88: 201962.46 | CT88: 201962.46 | CU88: 201962.46 | CV88: 201962.46 | CW88: 201962.46 | CX88: 201962.46 | CY88: 201962.46 | CZ88: 201962.46 | DA88: 201962.46 | DB88: 207011.53 | DC88: 207011.53 | DD88: 207011.53 | DE88: 207011.53 | DF88: 207011.53 | DG88: 207011.53 | DH88: 207011.53 | DI88: 207011.53 | DJ88: 207011.53 | DK88: 207011.53 | DL88: 207011.53 | DM88: 207011.53 | DN88: 212186.81 | DO88: 212186.81 | DP88: 212186.81 | DQ88: 212186.81 | DR88: 212186.81 | DS88: 212186.81 | DT88: 212186.81 | DU88: 212186.81 | DV88: 212186.81 | DW88: 212186.81 | DX88: 212186.81 | DY88: 212186.81
E89: Property K | G89: USD | J89: 0 | K89: 0 | L89: 0 | M89: 0 | N89: 0 | O89: 0 | P89: 0 | Q89: 0 | R89: 0 | S89: 0 | T89: 0 | U89: 0 | V89: 0 | W89: 0 | X89: 0 | Y89: 0 | Z89: 0 | AA89: 0 | AB89: 0 | AC89: 0 | AD89: 0 | AE89: 0 | AF89: 0 | AG89: 0 | AH89: 0 | AI89: 0 | AJ89: 0 | AK89: 0 | AL89: 0 | AM89: 0 | AN89: 0 | AO89: 0 | AP89: 0 | AQ89: 113364.28 | AR89: 113364.28 | AS89: 113364.28 | AT89: 116198.38 | AU89: 116198.38 | AV89: 116198.38 | AW89: 116198.38 | AX89: 116198.38 | AY89: 116198.38 | AZ89: 116198.38 | BA89: 116198.38 | BB89: 116198.38 | BC89: 116198.38 | BD89: 116198.38 | BE89: 116198.38 | BF89: 119103.34 | BG89: 119103.34 | BH89: 119103.34 | BI89: 119103.34 | BJ89: 119103.34 | BK89: 119103.34 | BL89: 119103.34 | BM89: 119103.34 | BN89: 119103.34 | BO89: 119103.34 | BP89: 119103.34 | BQ89: 119103.34 | BR89: 122080.93 | BS89: 122080.93 | BT89: 122080.93 | BU89: 122080.93 | BV89: 122080.93 | BW89: 122080.93 | BX89: 122080.93 | BY89: 122080.93 | BZ89: 122080.93 | CA89: 122080.93 | CB89: 122080.93 | CC89: 122080.93 | CD89: 125132.95 | CE89: 125132.95 | CF89: 125132.95 | CG89: 125132.95 | CH89: 125132.95 | CI89: 125132.95 | CJ89: 125132.95 | CK89: 125132.95 | CL89: 125132.95 | CM89: 125132.95 | CN89: 125132.95 | CO89: 125132.95 | CP89: 128261.27 | CQ89: 128261.27 | CR89: 128261.27 | CS89: 128261.27 | CT89: 128261.27 | CU89: 128261.27 | CV89: 128261.27 | CW89: 128261.27 | CX89: 128261.27 | CY89: 128261.27 | CZ89: 128261.27 | DA89: 128261.27 | DB89: 131467.8 | DC89: 131467.8 | DD89: 131467.8 | DE89: 131467.8 | DF89: 131467.8 | DG89: 131467.8 | DH89: 131467.8 | DI89: 131467.8 | DJ89: 131467.8 | DK89: 131467.8 | DL89: 131467.8 | DM89: 131467.8 | DN89: 134754.5 | DO89: 134754.5 | DP89: 134754.5 | DQ89: 134754.5 | DR89: 134754.5 | DS89: 134754.5 | DT89: 134754.5 | DU89: 134754.5 | DV89: 134754.5 | DW89: 134754.5 | DX89: 134754.5 | DY89: 134754.5
E90: Property L | G90: USD | J90: 0 | K90: 0 | L90: 0 | M90: 0 | N90: 0 | O90: 0 | P90: 0 | Q90: 0 | R90: 0 | S90: 0 | T90: 0 | U90: 0 | V90: 0 | W90: 0 | X90: 0 | Y90: 0 | Z90: 0 | AA90: 0 | AB90: 0 | AC90: 0 | AD90: 0 | AE90: 0 | AF90: 0 | AG90: 0 | AH90: 0 | AI90: 0 | AJ90: 0 | AK90: 0 | AL90: 0 | AM90: 0 | AN90: 0 | AO90: 0 | AP90: 0 | AQ90: 0 | AR90: 0 | AS90: 0 | AT90: 0 | AU90: 0 | AV90: 0 | AW90: 0 | AX90: 0 | AY90: 0 | AZ90: 0 | BA90: 0 | BB90: 0 | BC90: 0 | BD90: 0 | BE90: 0 | BF90: 0 | BG90: 0 | BH90: 281584.88 | BI90: 281584.88 | BJ90: 281584.88 | BK90: 281584.88 | BL90: 281584.88 | BM90: 281584.88 | BN90: 281584.88 | BO90: 281584.88 | BP90: 281584.88 | BQ90: 281584.88 | BR90: 288624.5 | BS90: 288624.5 | BT90: 288624.5 | BU90: 288624.5 | BV90: 288624.5 | BW90: 288624.5 | BX90: 288624.5 | BY90: 288624.5 | BZ90: 288624.5 | CA90: 288624.5 | CB90: 288624.5 | CC90: 288624.5 | CD90: 295840.11 | CE90: 295840.11 | CF90: 295840.11 | CG90: 295840.11 | CH90: 295840.11 | CI90: 295840.11 | CJ90: 295840.11 | CK90: 295840.11 | CL90: 295840.11 | CM90: 295840.11 | CN90: 295840.11 | CO90: 295840.11 | CP90: 303236.11 | CQ90: 303236.11 | CR90: 303236.11 | CS90: 303236.11 | CT90: 303236.11 | CU90: 303236.11 | CV90: 303236.11 | CW90: 303236.11 | CX90: 303236.11 | CY90: 303236.11 | CZ90: 303236.11 | DA90: 303236.11 | DB90: 310817.02 | DC90: 310817.02 | DD90: 310817.02 | DE90: 310817.02 | DF90: 310817.02 | DG90: 310817.02 | DH90: 310817.02 | DI90: 310817.02 | DJ90: 310817.02 | DK90: 310817.02 | DL90: 310817.02 | DM90: 310817.02 | DN90: 318587.44 | DO90: 318587.44 | DP90: 318587.44 | DQ90: 318587.44 | DR90: 318587.44 | DS90: 318587.44 | DT90: 318587.44 | DU90: 318587.44 | DV90: 318587.44 | DW90: 318587.44 | DX90: 318587.44 | DY90: 318587.44
E91: Property M | G91: USD | J91: 0 | K91: 0 | L91: 0 | M91: 0 | N91: 0 | O91: 0 | P91: 0 | Q91: 0 | R91: 0 | S91: 0 | T91: 0 | U91: 0 | V91: 0 | W91: 0 | X91: 0 | Y91: 0 | Z91: 0 | AA91: 0 | AB91: 0 | AC91: 0 | AD91: 0 | AE91: 0 | AF91: 0 | AG91: 0 | AH91: 0 | AI91: 0 | AJ91: 0 | AK91: 0 | AL91: 0 | AM91: 0 | AN91: 0 | AO91: 0 | AP91: 0 | AQ91: 0 | AR91: 0 | AS91: 0 | AT91: 0 | AU91: 0 | AV91: 0 | AW91: 0 | AX91: 0 | AY91: 0 | AZ91: 0 | BA91: 0 | BB91: 0 | BC91: 0 | BD91: 0 | BE91: 0 | BF91: 0 | BG91: 0 | BH91: 206957.19 | BI91: 206957.19 | BJ91: 206957.19 | BK91: 206957.19 | BL91: 206957.19 | BM91: 206957.19 | BN91: 206957.19 | BO91: 206957.19 | BP91: 206957.19 | BQ91: 206957.19 | BR91: 212131.12 | BS91: 212131.12 | BT91: 212131.12 | BU91: 212131.12 | BV91: 212131.12 | BW91: 212131.12 | BX91: 212131.12 | BY91: 212131.12 | BZ91: 212131.12 | CA91: 212131.12 | CB91: 212131.12 | CC91: 212131.12 | CD91: 217434.4 | CE91: 217434.4 | CF91: 217434.4 | CG91: 217434.4 | CH91: 217434.4 | CI91: 217434.4 | CJ91: 217434.4 | CK91: 217434.4 | CL91: 217434.4 | CM91: 217434.4 | CN91: 217434.4 | CO91: 217434.4 | CP91: 222870.26 | CQ91: 222870.26 | CR91: 222870.26 | CS91: 222870.26 | CT91: 222870.26 | CU91: 222870.26 | CV91: 222870.26 | CW91: 222870.26 | CX91: 222870.26 | CY91: 222870.26 | CZ91: 222870.26 | DA91: 222870.26 | DB91: 228442.01 | DC91: 228442.01 | DD91: 228442.01 | DE91: 228442.01 | DF91: 228442.01 | DG91: 228442.01 | DH91: 228442.01 | DI91: 228442.01 | DJ91: 228442.01 | DK91: 228442.01 | DL91: 228442.01 | DM91: 228442.01 | DN91: 234153.06 | DO91: 234153.06 | DP91: 234153.06 | DQ91: 234153.06 | DR91: 234153.06 | DS91: 234153.06 | DT91: 234153.06 | DU91: 234153.06 | DV91: 234153.06 | DW91: 234153.06 | DX91: 234153.06 | DY91: 234153.06
E92: Property N | G92: USD | J92: 0 | K92: 0 | L92: 0 | M92: 0 | N92: 0 | O92: 0 | P92: 0 | Q92: 0 | R92: 0 | S92: 0 | T92: 0 | U92: 0 | V92: 0 | W92: 0 | X92: 0 | Y92: 0 | Z92: 0 | AA92: 0 | AB92: 0 | AC92: 0 | AD92: 0 | AE92: 0 | AF92: 0 | AG92: 0 | AH92: 0 | AI92: 0 | AJ92: 0 | AK92: 0 | AL92: 0 | AM92: 0 | AN92: 0 | AO92: 0 | AP92: 0 | AQ92: 0 | AR92: 0 | AS92: 0 | AT92: 0 | AU92: 0 | AV92: 0 | AW92: 0 | AX92: 0 | AY92: 0 | AZ92: 0 | BA92: 0 | BB92: 0 | BC92: 0 | BD92: 0 | BE92: 0 | BF92: 0 | BG92: 0 | BH92: 0 | BI92: 0 | BJ92: 0 | BK92: 0 | BL92: 0 | BM92: 0 | BN92: 0 | BO92: 0 | BP92: 0 | BQ92: 0 | BR92: 0 | BS92: 0 | BT92: 0 | BU92: 225537.18 | BV92: 225537.18 | BW92: 225537.18 | BX92: 225537.18 | BY92: 225537.18 | BZ92: 225537.18 | CA92: 225537.18 | CB92: 225537.18 | CC92: 225537.18 | CD92: 231175.61 | CE92: 231175.61 | CF92: 231175.61 | CG92: 231175.61 | CH92: 231175.61 | CI92: 231175.61 | CJ92: 231175.61 | CK92: 231175.61 | CL92: 231175.61 | CM92: 231175.61 | CN92: 231175.61 | CO92: 231175.61 | CP92: 236955 | CQ92: 236955 | CR92: 236955 | CS92: 236955 | CT92: 236955 | CU92: 236955 | CV92: 236955 | CW92: 236955 | CX92: 236955 | CY92: 236955 | CZ92: 236955 | DA92: 236955 | DB92: 242878.87 | DC92: 242878.87 | DD92: 242878.87 | DE92: 242878.87 | DF92: 242878.87 | DG92: 242878.87 | DH92: 242878.87 | DI92: 242878.87 | DJ92: 242878.87 | DK92: 242878.87 | DL92: 242878.87 | DM92: 242878.87 | DN92: 248950.84 | DO92: 248950.84 | DP92: 248950.84 | DQ92: 248950.84 | DR92: 248950.84 | DS92: 248950.84 | DT92: 248950.84 | DU92: 248950.84 | DV92: 248950.84 | DW92: 248950.84 | DX92: 248950.84 | DY92: 248950.84
E93: Property O | G93: USD | J93: 0 | K93: 0 | L93: 0 | M93: 0 | N93: 0 | O93: 0 | P93: 0 | Q93: 0 | R93: 0 | S93: 0 | T93: 0 | U93: 0 | V93: 0 | W93: 0 | X93: 0 | Y93: 0 | Z93: 0 | AA93: 0 | AB93: 0 | AC93: 0 | AD93: 0 | AE93: 0 | AF93: 0 | AG93: 0 | AH93: 0 | AI93: 0 | AJ93: 0 | AK93: 0 | AL93: 0 | AM93: 0 | AN93: 0 | AO93: 0 | AP93: 0 | AQ93: 0 | AR93: 0 | AS93: 0 | AT93: 0 | AU93: 0 | AV93: 0 | AW93: 0 | AX93: 0 | AY93: 0 | AZ93: 0 | BA93: 0 | BB93: 0 | BC93: 0 | BD93: 0 | BE93: 0 | BF93: 0 | BG93: 0 | BH93: 0 | BI93: 0 | BJ93: 0 | BK93: 0 | BL93: 0 | BM93: 0 | BN93: 0 | BO93: 0 | BP93: 0 | BQ93: 0 | BR93: 0 | BS93: 0 | BT93: 0 | BU93: 0 | BV93: 0 | BW93: 0 | BX93: 0 | BY93: 0 | BZ93: 0 | CA93: 0 | CB93: 0 | CC93: 276099.81 | CD93: 283002.3 | CE93: 283002.3 | CF93: 283002.3 | CG93: 283002.3 | CH93: 283002.3 | CI93: 283002.3 | CJ93: 283002.3 | CK93: 283002.3 | CL93: 283002.3 | CM93: 283002.3 | CN93: 283002.3 | CO93: 283002.3 | CP93: 290077.36 | CQ93: 290077.36 | CR93: 290077.36 | CS93: 290077.36 | CT93: 290077.36 | CU93: 290077.36 | CV93: 290077.36 | CW93: 290077.36 | CX93: 290077.36 | CY93: 290077.36 | CZ93: 290077.36 | DA93: 290077.36 | DB93: 297329.3 | DC93: 297329.3 | DD93: 297329.3 | DE93: 297329.3 | DF93: 297329.3 | DG93: 297329.3 | DH93: 297329.3 | DI93: 297329.3 | DJ93: 297329.3 | DK93: 297329.3 | DL93: 297329.3 | DM93: 297329.3 | DN93: 304762.53 | DO93: 304762.53 | DP93: 304762.53 | DQ93: 304762.53 | DR93: 304762.53 | DS93: 304762.53 | DT93: 304762.53 | DU93: 304762.53 | DV93: 304762.53 | DW93: 304762.53 | DX93: 304762.53 | DY93: 304762.53
E94: Opex from new properties | G94: USD | J94: {=_xlfn.BYCOL(_xlfn.ANCHORARRAY( J84), _xleta.SUM )} -> 0 | K94: 0 | L94: 0 | M94: 0 | N94: 0 | O94: 0 | P94: 0 | Q94: 0 | R94: 0 | S94: 0 | T94: 0 | U94: 0 | V94: 0 | W94: 0 | X94: 0 | Y94: 0 | Z94: 0 | AA94: 0 | AB94: 0 | AC94: 143956.64 | AD94: 264673.45 | AE94: 264673.45 | AF94: 264673.45 | AG94: 264673.45 | AH94: 271290.29 | AI94: 415798.24 | AJ94: 415798.24 | AK94: 415798.24 | AL94: 415798.24 | AM94: 415798.24 | AN94: 415798.24 | AO94: 415798.24 | AP94: 415798.24 | AQ94: 708572.49 | AR94: 708572.49 | AS94: 887077.88 | AT94: 909254.83 | AU94: 909254.83 | AV94: 909254.83 | AW94: 909254.83 | AX94: 909254.83 | AY94: 909254.83 | AZ94: 909254.83 | BA94: 909254.83 | BB94: 909254.83 | BC94: 909254.83 | BD94: 909254.83 | BE94: 909254.83 | BF94: 931986.2 | BG94: 931986.2 | BH94: 1420528.3 | BI94: 1420528.3 | BJ94: 1420528.3 | BK94: 1420528.3 | BL94: 1420528.3 | BM94: 1420528.3 | BN94: 1420528.3 | BO94: 1420528.3 | BP94: 1420528.3 | BQ94: 1420528.3 | BR94: 1456041.5 | BS94: 1456041.5 | BT94: 1456041.5 | BU94: 1681578.7 | BV94: 1681578.7 | BW94: 1681578.7 | BX94: 1681578.7 | BY94: 1681578.7 | BZ94: 1681578.7 | CA94: 1681578.7 | CB94: 1681578.7 | CC94: 1957678.5 | CD94: 2006620.4 | CE94: 2006620.4 | CF94: 2006620.4 | CG94: 2006620.4 | CH94: 2006620.4 | CI94: 2006620.4 | CJ94: 2006620.4 | CK94: 2006620.4 | CL94: 2006620.4 | CM94: 2006620.4 | CN94: 2006620.4 | CO94: 2006620.4 | CP94: 2056785.9 | CQ94: 2056785.9 | CR94: 2056785.9 | CS94: 2056785.9 | CT94: 2056785.9 | CU94: 2056785.9 | CV94: 2056785.9 | CW94: 2056785.9 | CX94: 2056785.9 | CY94: 2056785.9 | CZ94: 2056785.9 | DA94: 2056785.9 | DB94: 2108205.6 | DC94: 2108205.6 | DD94: 2108205.6 | DE94: 2108205.6 | DF94: 2108205.6 | DG94: 2108205.6 | DH94: 2108205.6 | DI94: 2108205.6 | DJ94: 2108205.6 | DK94: 2108205.6 | DL94: 2108205.6 | DM94: 2108205.6 | DN94: 2160910.7 | DO94: 2160910.7 | DP94: 2160910.7 | DQ94: 2160910.7 | DR94: 2160910.7 | DS94: 2160910.7 | DT94: 2160910.7 | DU94: 2160910.7 | DV94: 2160910.7 | DW94: 2160910.7 | DX94: 2160910.7 | DY94: 2160910.7
A97: Management Fee
E99: Gross Rent Revenue on Existing Properties | G99: USD | J99: {=_xlfn.LET( _xlpm.timeline,_xlfn.ANCHORARRAY( $J$3), _xlpm.inflation_flag, IF( MONTH( _xlpm.timeline ) = 1, 1, 0 ), _xlpm.inflation_data, CaseData!$J$15:$M$24, _xlpm.annual_rate, _xlfn.XLOOKUP( YEAR( _xlpm.timeline ), INDEX( _xlpm.inflation_data,, 1 ), INDEX( _xlpm.inflation_data,, 2 ) ), _xlpm.effective_step, _xlpm.inflation_flag * _xlpm.annual_rate, _xlpm.inflation_factor, _xlfn.SCAN( 1, _xlpm.effective_step, _xlfn.LAMBDA(_xlpm.prev,_xlpm.step, IF( _xlpm.step = 0, _xlpm.prev, _xlpm.prev * ( 1 + _xlpm.step ) ) ) ), _xlpm.property_data, CaseData!$A$6:$D$10, _xlpm.total_rent, SUM( INDEX( _xlpm.property_data,, 2 ) ), _xlpm.total_rent * _xlpm.inflation_factor )} -> 3376800 | K99: 3376800 | L99: 3376800 | M99: 3376800 | N99: 3376800 | O99: 3376800 | P99: 3376800 | Q99: 3376800 | R99: 3376800 | S99: 3376800 | T99: 3376800 | U99: 3376800 | V99: 3528756 | W99: 3528756 | X99: 3528756 | Y99: 3528756 | Z99: 3528756 | AA99: 3528756 | AB99: 3528756 | AC99: 3528756 | AD99: 3528756 | AE99: 3528756 | AF99: 3528756 | AG99: 3528756 | AH99: 3669906.2 | AI99: 3669906.2 | AJ99: 3669906.2 | AK99: 3669906.2 | AL99: 3669906.2 | AM99: 3669906.2 | AN99: 3669906.2 | AO99: 3669906.2 | AP99: 3669906.2 | AQ99: 3669906.2 | AR99: 3669906.2 | AS99: 3669906.2 | AT99: 3798353 | AU99: 3798353 | AV99: 3798353 | AW99: 3798353 | AX99: 3798353 | AY99: 3798353 | AZ99: 3798353 | BA99: 3798353 | BB99: 3798353 | BC99: 3798353 | BD99: 3798353 | BE99: 3798353 | BF99: 3912303.5 | BG99: 3912303.5 | BH99: 3912303.5 | BI99: 3912303.5 | BJ99: 3912303.5 | BK99: 3912303.5 | BL99: 3912303.5 | BM99: 3912303.5 | BN99: 3912303.5 | BO99: 3912303.5 | BP99: 3912303.5 | BQ99: 3912303.5 | BR99: 4010111.1 | BS99: 4010111.1 | BT99: 4010111.1 | BU99: 4010111.1 | BV99: 4010111.1 | BW99: 4010111.1 | BX99: 4010111.1 | BY99: 4010111.1 | BZ99: 4010111.1 | CA99: 4010111.1 | CB99: 4010111.1 | CC99: 4010111.1 | CD99: 4110363.9 | CE99: 4110363.9 | CF99: 4110363.9 | CG99: 4110363.9 | CH99: 4110363.9 | CI99: 4110363.9 | CJ99: 4110363.9 | CK99: 4110363.9 | CL99: 4110363.9 | CM99: 4110363.9 | CN99: 4110363.9 | CO99: 4110363.9 | CP99: 4213123 | CQ99: 4213123 | CR99: 4213123 | CS99: 4213123 | CT99: 4213123 | CU99: 4213123 | CV99: 4213123 | CW99: 4213123 | CX99: 4213123 | CY99: 4213123 | CZ99: 4213123 | DA99: 4213123 | DB99: 4318451.1 | DC99: 4318451.1 | DD99: 4318451.1 | DE99: 4318451.1 | DF99: 4318451.1 | DG99: 4318451.1 | DH99: 4318451.1 | DI99: 4318451.1 | DJ99: 4318451.1 | DK99: 4318451.1 | DL99: 4318451.1 | DM99: 4318451.1 | DN99: 4426412.4 | DO99: 4426412.4 | DP99: 4426412.4 | DQ99: 4426412.4 | DR99: 4426412.4 | DS99: 4426412.4 | DT99: 4426412.4 | DU99: 4426412.4 | DV99: 4426412.4 | DW99: 4426412.4 | DX99: 4426412.4 | DY99: 4426412.4
E100: Gross Rent Revenue on New Properties | G100: USD | J100: {=_xlfn.LET( _xlpm.timeline,_xlfn.ANCHORARRAY( $J$3), _xlpm.property_data, CaseData!$A$15:$H$24, _xlpm.property_rows, INDEX( _xlpm.property_data, 0, 1 ), _xlpm.purchase_date, INDEX( _xlpm.property_data,, 6 ), _xlpm.prep_months, INDEX( _xlpm.property_data,, 7 ), _xlpm.const_months, INDEX( _xlpm.property_data,, 8 ), _xlpm.delay, IF( $F$9 = 0, 0, 12 ), _xlpm.operation_start, _xlfn.MAKEARRAY( ROWS( _xlpm.property_data ), 1, _xlfn.LAMBDA(_xlpm.r,_xlpm.c, EOMONTH( INDEX( _xlpm.purchase_date, _xlpm.r ), INDEX( _xlpm.prep_months, _xlpm.r ) + INDEX( _xlpm.const_months, _xlpm.r ) + _xlpm.delay ) ) ), _xlpm.operation_flag, _xlfn.MAKEARRAY( ROWS( _xlpm.property_data ), COLUMNS( _xlpm.timeline ), _xlfn.LAMBDA(_xlpm.r,_xlpm.c, IF( INDEX( _xlpm.timeline,, _xlpm.c ) >= INDEX( _xlpm.operation_start, _xlpm.r, 1 ), 1, 0 ) ) ), _xlpm.inflation_flag, IF( MONTH( _xlpm.timeline ) = 1, 1, 0 ), _xlpm.inflation_data, CaseData!$J$15:$M$24, _xlpm.annual_rate, _xlfn.XLOOKUP( YEAR( _xlpm.timeline ), INDEX( _xlpm.inflation_data,, 1 ), INDEX( _xlpm.inflation_data,, 2 ) ), _xlpm.effective_step, _xlpm.inflation_flag * _xlpm.annual_rate, _xlpm.inflation_factor, _xlfn.SCAN( 1, _xlpm.effective_step, _xlfn.LAMBDA(_xlpm.prev,_xlpm.step, IF( _xlpm.step = 0, _xlpm.prev, _xlpm.prev * ( 1 + _xlpm.step ) ) ) ), _xlpm.rent, INDEX( _xlpm.property_data,, 2 ), _xlpm.total_rent, _xlfn.BYCOL( _xlpm.operation_flag * _xlpm.rent, _xleta.SUM ), _xlpm.total_rent * _xlpm.inflation_factor )} -> 0 | K100: 0 | L100: 0 | M100: 0 | N100: 0 | O100: 0 | P100: 0 | Q100: 0 | R100: 0 | S100: 0 | T100: 0 | U100: 0 | V100: 0 | W100: 0 | X100: 0 | Y100: 0 | Z100: 0 | AA100: 0 | AB100: 0 | AC100: 484984.5 | AD100: 905231.25 | AE100: 905231.25 | AF100: 905231.25 | AG100: 905231.25 | AH100: 941440.5 | AI100: 1508587.1 | AJ100: 1508587.1 | AK100: 1508587.1 | AL100: 1508587.1 | AM100: 1508587.1 | AN100: 1508587.1 | AO100: 1508587.1 | AP100: 1508587.1 | AQ100: 2601799.2 | AR100: 2601799.2 | AS100: 3277354.1 | AT100: 3392061.5 | AU100: 3392061.5 | AV100: 3392061.5 | AW100: 3392061.5 | AX100: 3392061.5 | AY100: 3392061.5 | AZ100: 3392061.5 | BA100: 3392061.5 | BB100: 3392061.5 | BC100: 3392061.5 | BD100: 3392061.5 | BE100: 3392061.5 | BF100: 3493823.3 | BG100: 3493823.3 | BH100: 5038793.9 | BI100: 5038793.9 | BJ100: 5038793.9 | BK100: 5038793.9 | BL100: 5038793.9 | BM100: 5038793.9 | BN100: 5038793.9 | BO100: 5038793.9 | BP100: 5038793.9 | BQ100: 5038793.9 | BR100: 5164763.8 | BS100: 5164763.8 | BT100: 5164763.8 | BU100: 6097463.8 | BV100: 6097463.8 | BW100: 6097463.8 | BX100: 6097463.8 | BY100: 6097463.8 | BZ100: 6097463.8 | CA100: 6097463.8 | CB100: 6097463.8 | CC100: 7055102.2 | CD100: 7231479.8 | CE100: 7231479.8 | CF100: 7231479.8 | CG100: 7231479.8 | CH100: 7231479.8 | CI100: 7231479.8 | CJ100: 7231479.8 | CK100: 7231479.8 | CL100: 7231479.8 | CM100: 7231479.8 | CN100: 7231479.8 | CO100: 7231479.8 | CP100: 7412266.8 | CQ100: 7412266.8 | CR100: 7412266.8 | CS100: 7412266.8 | CT100: 7412266.8 | CU100: 7412266.8 | CV100: 7412266.8 | CW100: 7412266.8 | CX100: 7412266.8 | CY100: 7412266.8 | CZ100: 7412266.8 | DA100: 7412266.8 | DB100: 7597573.5 | DC100: 7597573.5 | DD100: 7597573.5 | DE100: 7597573.5 | DF100: 7597573.5 | DG100: 7597573.5 | DH100: 7597573.5 | DI100: 7597573.5 | DJ100: 7597573.5 | DK100: 7597573.5 | DL100: 7597573.5 | DM100: 7597573.5 | DN100: 7787512.8 | DO100: 7787512.8 | DP100: 7787512.8 | DQ100: 7787512.8 | DR100: 7787512.8 | DS100: 7787512.8 | DT100: 7787512.8 | DU100: 7787512.8 | DV100: 7787512.8 | DW100: 7787512.8 | DX100: 7787512.8 | DY100: 7787512.8
E101: Total Gross Rent Revenue | G101: USD | J101: {=_xlfn.BYCOL( $J$99:$DY$100, _xleta.SUM )} -> 3376800 | K101: 3376800 | L101: 3376800 | M101: 3376800 | N101: 3376800 | O101: 3376800 | P101: 3376800 | Q101: 3376800 | R101: 3376800 | S101: 3376800 | T101: 3376800 | U101: 3376800 | V101: 3528756 | W101: 3528756 | X101: 3528756 | Y101: 3528756 | Z101: 3528756 | AA101: 3528756 | AB101: 3528756 | AC101: 4013740.5 | AD101: 4433987.2 | AE101: 4433987.2 | AF101: 4433987.2 | AG101: 4433987.2 | AH101: 4611346.7 | AI101: 5178493.3 | AJ101: 5178493.3 | AK101: 5178493.3 | AL101: 5178493.3 | AM101: 5178493.3 | AN101: 5178493.3 | AO101: 5178493.3 | AP101: 5178493.3 | AQ101: 6271705.4 | AR101: 6271705.4 | AS101: 6947260.3 | AT101: 7190414.4 | AU101: 7190414.4 | AV101: 7190414.4 | AW101: 7190414.4 | AX101: 7190414.4 | AY101: 7190414.4 | AZ101: 7190414.4 | BA101: 7190414.4 | BB101: 7190414.4 | BC101: 7190414.4 | BD101: 7190414.4 | BE101: 7190414.4 | BF101: 7406126.9 | BG101: 7406126.9 | BH101: 8951097.5 | BI101: 8951097.5 | BJ101: 8951097.5 | BK101: 8951097.5 | BL101: 8951097.5 | BM101: 8951097.5 | BN101: 8951097.5 | BO101: 8951097.5 | BP101: 8951097.5 | BQ101: 8951097.5 | BR101: 9174874.9 | BS101: 9174874.9 | BT101: 9174874.9 | BU101: 10107575 | BV101: 10107575 | BW101: 10107575 | BX101: 10107575 | BY101: 10107575 | BZ101: 10107575 | CA101: 10107575 | CB101: 10107575 | CC101: 11065213 | CD101: 11341844 | CE101: 11341844 | CF101: 11341844 | CG101: 11341844 | CH101: 11341844 | CI101: 11341844 | CJ101: 11341844 | CK101: 11341844 | CL101: 11341844 | CM101: 11341844 | CN101: 11341844 | CO101: 11341844 | CP101: 11625390 | CQ101: 11625390 | CR101: 11625390 | CS101: 11625390 | CT101: 11625390 | CU101: 11625390 | CV101: 11625390 | CW101: 11625390 | CX101: 11625390 | CY101: 11625390 | CZ101: 11625390 | DA101: 11625390 | DB101: 11916025 | DC101: 11916025 | DD101: 11916025 | DE101: 11916025 | DF101: 11916025 | DG101: 11916025 | DH101: 11916025 | DI101: 11916025 | DJ101: 11916025 | DK101: 11916025 | DL101: 11916025 | DM101: 11916025 | DN101: 12213925 | DO101: 12213925 | DP101: 12213925 | DQ101: 12213925 | DR101: 12213925 | DS101: 12213925 | DT101: 12213925 | DU101: 12213925 | DV101: 12213925 | DW101: 12213925 | DX101: 12213925 | DY101: 12213925
E103: Management Fee | G103: USD | J103: {=_xlfn.LET( _xlpm.management_fee, CaseData!$L$7, _xlpm.gross_rent_revenue,_xlfn.ANCHORARRAY( Calculations!J101), _xlpm.management_fee * _xlpm.gross_rent_revenue )} -> 67536 | K103: 67536 | L103: 67536 | M103: 67536 | N103: 67536 | O103: 67536 | P103: 67536 | Q103: 67536 | R103: 67536 | S103: 67536 | T103: 67536 | U103: 67536 | V103: 70575.12 | W103: 70575.12 | X103: 70575.12 | Y103: 70575.12 | Z103: 70575.12 | AA103: 70575.12 | AB103: 70575.12 | AC103: 80274.81 | AD103: 88679.745 | AE103: 88679.745 | AF103: 88679.745 | AG103: 88679.745 | AH103: 92226.935 | AI103: 103569.87 | AJ103: 103569.87 | AK103: 103569.87 | AL103: 103569.87 | AM103: 103569.87 | AN103: 103569.87 | AO103: 103569.87 | AP103: 103569.87 | AQ103: 125434.11 | AR103: 125434.11 | AS103: 138945.21 | AT103: 143808.29 | AU103: 143808.29 | AV103: 143808.29 | AW103: 143808.29 | AX103: 143808.29 | AY103: 143808.29 | AZ103: 143808.29 | BA103: 143808.29 | BB103: 143808.29 | BC103: 143808.29 | BD103: 143808.29 | BE103: 143808.29 | BF103: 148122.54 | BG103: 148122.54 | BH103: 179021.95 | BI103: 179021.95 | BJ103: 179021.95 | BK103: 179021.95 | BL103: 179021.95 | BM103: 179021.95 | BN103: 179021.95 | BO103: 179021.95 | BP103: 179021.95 | BQ103: 179021.95 | BR103: 183497.5 | BS103: 183497.5 | BT103: 183497.5 | BU103: 202151.5 | BV103: 202151.5 | BW103: 202151.5 | BX103: 202151.5 | BY103: 202151.5 | BZ103: 202151.5 | CA103: 202151.5 | CB103: 202151.5 | CC103: 221304.27 | CD103: 226836.87 | CE103: 226836.87 | CF103: 226836.87 | CG103: 226836.87 | CH103: 226836.87 | CI103: 226836.87 | CJ103: 226836.87 | CK103: 226836.87 | CL103: 226836.87 | CM103: 226836.87 | CN103: 226836.87 | CO103: 226836.87 | CP103: 232507.8 | CQ103: 232507.8 | CR103: 232507.8 | CS103: 232507.8 | CT103: 232507.8 | CU103: 232507.8 | CV103: 232507.8 | CW103: 232507.8 | CX103: 232507.8 | CY103: 232507.8 | CZ103: 232507.8 | DA103: 232507.8 | DB103: 238320.49 | DC103: 238320.49 | DD103: 238320.49 | DE103: 238320.49 | DF103: 238320.49 | DG103: 238320.49 | DH103: 238320.49 | DI103: 238320.49 | DJ103: 238320.49 | DK103: 238320.49 | DL103: 238320.49 | DM103: 238320.49 | DN103: 244278.5 | DO103: 244278.5 | DP103: 244278.5 | DQ103: 244278.5 | DR103: 244278.5 | DS103: 244278.5 | DT103: 244278.5 | DU103: 244278.5 | DV103: 244278.5 | DW103: 244278.5 | DX103: 244278.5 | DY103: 244278.5
A106: Project Cashflow Summary
C109: Revenues
C110: (adjusted for inflation and vacancy)
E111: =E$22 -> Rent revenue from existing properties | G111: USD | J111: {=_xlfn.ANCHORARRAY( J22)} -> 3210711 | K111: 3210711 | L111: 3210711 | M111: 3210711 | N111: 3210711 | O111: 3210711 | P111: 3210711 | Q111: 3210711 | R111: 3210711 | S111: 3210711 | T111: 3210711 | U111: 3210711 | V111: 3355193 | W111: 3355193 | X111: 3355193 | Y111: 3355193 | Z111: 3355193 | AA111: 3355193 | AB111: 3355193 | AC111: 3355193 | AD111: 3355193 | AE111: 3355193 | AF111: 3355193 | AG111: 3355193 | AH111: 3489400.7 | AI111: 3489400.7 | AJ111: 3489400.7 | AK111: 3489400.7 | AL111: 3489400.7 | AM111: 3489400.7 | AN111: 3489400.7 | AO111: 3489400.7 | AP111: 3489400.7 | AQ111: 3489400.7 | AR111: 3489400.7 | AS111: 3489400.7 | AT111: 3611529.7 | AU111: 3611529.7 | AV111: 3611529.7 | AW111: 3611529.7 | AX111: 3611529.7 | AY111: 3611529.7 | AZ111: 3611529.7 | BA111: 3611529.7 | BB111: 3611529.7 | BC111: 3611529.7 | BD111: 3611529.7 | BE111: 3611529.7 | BF111: 3719875.6 | BG111: 3719875.6 | BH111: 3719875.6 | BI111: 3719875.6 | BJ111: 3719875.6 | BK111: 3719875.6 | BL111: 3719875.6 | BM111: 3719875.6 | BN111: 3719875.6 | BO111: 3719875.6 | BP111: 3719875.6 | BQ111: 3719875.6 | BR111: 3812872.5 | BS111: 3812872.5 | BT111: 3812872.5 | BU111: 3812872.5 | BV111: 3812872.5 | BW111: 3812872.5 | BX111: 3812872.5 | BY111: 3812872.5 | BZ111: 3812872.5 | CA111: 3812872.5 | CB111: 3812872.5 | CC111: 3812872.5 | CD111: 3908194.3 | CE111: 3908194.3 | CF111: 3908194.3 | CG111: 3908194.3 | CH111: 3908194.3 | CI111: 3908194.3 | CJ111: 3908194.3 | CK111: 3908194.3 | CL111: 3908194.3 | CM111: 3908194.3 | CN111: 3908194.3 | CO111: 3908194.3 | CP111: 4005899.2 | CQ111: 4005899.2 | CR111: 4005899.2 | CS111: 4005899.2 | CT111: 4005899.2 | CU111: 4005899.2 | CV111: 4005899.2 | CW111: 4005899.2 | CX111: 4005899.2 | CY111: 4005899.2 | CZ111: 4005899.2 | DA111: 4005899.2 | DB111: 4106046.7 | DC111: 4106046.7 | DD111: 4106046.7 | DE111: 4106046.7 | DF111: 4106046.7 | DG111: 4106046.7 | DH111: 4106046.7 | DI111: 4106046.7 | DJ111: 4106046.7 | DK111: 4106046.7 | DL111: 4106046.7 | DM111: 4106046.7 | DN111: 4208697.8 | DO111: 4208697.8 | DP111: 4208697.8 | DQ111: 4208697.8 | DR111: 4208697.8 | DS111: 4208697.8 | DT111: 4208697.8 | DU111: 4208697.8 | DV111: 4208697.8 | DW111: 4208697.8 | DX111: 4208697.8 | DY111: 4208697.8
E112: =E$79 -> Rent revenue from new properties | G112: =G$79 -> USD | J112: {=_xlfn.ANCHORARRAY( J79)} -> 0 | K112: 0 | L112: 0 | M112: 0 | N112: 0 | O112: 0 | P112: 0 | Q112: 0 | R112: 0 | S112: 0 | T112: 0 | U112: 0 | V112: 0 | W112: 0 | X112: 0 | Y112: 0 | Z112: 0 | AA112: 0 | AB112: 0 | AC112: 121246.12 | AD112: 274806.26 | AE112: 365329.39 | AF112: 455852.51 | AG112: 546375.64 | AH112: 662374.71 | AI112: 860476.62 | AJ112: 940727.29 | AK112: 1020978 | AL112: 1101228.6 | AM112: 1181479.3 | AN112: 1261730 | AO112: 1288936.6 | AP112: 1307038 | AQ112: 1598442.3 | AR112: 1725864.9 | AS112: 2022176.2 | AT112: 2294754.6 | AU112: 2484327.8 | AV112: 2673900.9 | AW112: 2778613.5 | AX112: 2883326.1 | AY112: 2935598.7 | AZ112: 2987871.3 | BA112: 3037968.8 | BB112: 3086181.5 | BC112: 3110821.7 | BD112: 3135462 | BE112: 3145535.6 | BF112: 3250277.6 | BG112: 3258134.2 | BH112: 3652233.5 | BI112: 3814587.2 | BJ112: 3976940.9 | BK112: 4139294.6 | BL112: 4301648.3 | BM112: 4464002 | BN112: 4510482.9 | BO112: 4552107.9 | BP112: 4593732.9 | BQ112: 4632357.2 | BR112: 4787756 | BS112: 4827345.8 | BT112: 4833944.2 | BU112: 5073717.5 | BV112: 5173585.8 | BW112: 5273454.1 | BX112: 5373322.4 | BY112: 5473190.7 | BZ112: 5573059 | CA112: 5602974.8 | CB112: 5632890.6 | CC112: 5902216.1 | CD112: 6178593.1 | CE112: 6307414.8 | CF112: 6429473.2 | CG112: 6531614.5 | CH112: 6633755.9 | CI112: 6662278.7 | CJ112: 6690801.6 | CK112: 6719324.5 | CL112: 6747847.4 | CM112: 6776370.3 | CN112: 6804893.2 | CO112: 6812966.5 | CP112: 6991565.8 | CQ112: 6999841 | CR112: 7008116.2 | CS112: 7012308.3 | CT112: 7016500.5 | CU112: 7020692.6 | CV112: 7024884.8 | CW112: 7029077 | CX112: 7033269.1 | CY112: 7037461.3 | CZ112: 7041653.5 | DA112: 7041653.5 | DB112: 7217694.8 | DC112: 7217694.8 | DD112: 7217694.8 | DE112: 7217694.8 | DF112: 7217694.8 | DG112: 7217694.8 | DH112: 7217694.8 | DI112: 7217694.8 | DJ112: 7217694.8 | DK112: 7217694.8 | DL112: 7217694.8 | DM112: 7217694.8 | DN112: 7398137.2 | DO112: 7398137.2 | DP112: 7398137.2 | DQ112: 7398137.2 | DR112: 7398137.2 | DS112: 7398137.2 | DT112: 7398137.2 | DU112: 7398137.2 | DV112: 7398137.2 | DW112: 7398137.2 | DX112: 7398137.2 | DY112: 7398137.2
C114: Costs
C115: (adjusted for inflation)
E116: =E$32 -> Opex from existing properties | G116: =G$32 -> USD | J116: {=_xlfn.ANCHORARRAY( J32) * - 1} -> -932391.25 | K116: -932391.25 | L116: -932391.25 | M116: -932391.25 | N116: -932391.25 | O116: -932391.25 | P116: -932391.25 | Q116: -932391.25 | R116: -932391.25 | S116: -932391.25 | T116: -932391.25 | U116: -932391.25 | V116: -955701.03 | W116: -955701.03 | X116: -955701.03 | Y116: -955701.03 | Z116: -955701.03 | AA116: -955701.03 | AB116: -955701.03 | AC116: -955701.03 | AD116: -955701.03 | AE116: -955701.03 | AF116: -955701.03 | AG116: -955701.03 | AH116: -979593.56 | AI116: -979593.56 | AJ116: -979593.56 | AK116: -979593.56 | AL116: -979593.56 | AM116: -979593.56 | AN116: -979593.56 | AO116: -979593.56 | AP116: -979593.56 | AQ116: -979593.56 | AR116: -979593.56 | AS116: -979593.56 | AT116: -1004083.4 | AU116: -1004083.4 | AV116: -1004083.4 | AW116: -1004083.4 | AX116: -1004083.4 | AY116: -1004083.4 | AZ116: -1004083.4 | BA116: -1004083.4 | BB116: -1004083.4 | BC116: -1004083.4 | BD116: -1004083.4 | BE116: -1004083.4 | BF116: -1029185.5 | BG116: -1029185.5 | BH116: -1029185.5 | BI116: -1029185.5 | BJ116: -1029185.5 | BK116: -1029185.5 | BL116: -1029185.5 | BM116: -1029185.5 | BN116: -1029185.5 | BO116: -1029185.5 | BP116: -1029185.5 | BQ116: -1029185.5 | BR116: -1054915.1 | BS116: -1054915.1 | BT116: -1054915.1 | BU116: -1054915.1 | BV116: -1054915.1 | BW116: -1054915.1 | BX116: -1054915.1 | BY116: -1054915.1 | BZ116: -1054915.1 | CA116: -1054915.1 | CB116: -1054915.1 | CC116: -1054915.1 | CD116: -1081288 | CE116: -1081288 | CF116: -1081288 | CG116: -1081288 | CH116: -1081288 | CI116: -1081288 | CJ116: -1081288 | CK116: -1081288 | CL116: -1081288 | CM116: -1081288 | CN116: -1081288 | CO116: -1081288 | CP116: -1108320.2 | CQ116: -1108320.2 | CR116: -1108320.2 | CS116: -1108320.2 | CT116: -1108320.2 | CU116: -1108320.2 | CV116: -1108320.2 | CW116: -1108320.2 | CX116: -1108320.2 | CY116: -1108320.2 | CZ116: -1108320.2 | DA116: -1108320.2 | DB116: -1136028.2 | DC116: -1136028.2 | DD116: -1136028.2 | DE116: -1136028.2 | DF116: -1136028.2 | DG116: -1136028.2 | DH116: -1136028.2 | DI116: -1136028.2 | DJ116: -1136028.2 | DK116: -1136028.2 | DL116: -1136028.2 | DM116: -1136028.2 | DN116: -1164428.9 | DO116: -1164428.9 | DP116: -1164428.9 | DQ116: -1164428.9 | DR116: -1164428.9 | DS116: -1164428.9 | DT116: -1164428.9 | DU116: -1164428.9 | DV116: -1164428.9 | DW116: -1164428.9 | DX116: -1164428.9 | DY116: -1164428.9
E117: =E$49 -> Land acquisition | G117: =G$49 -> USD | J117: {=_xlfn.ANCHORARRAY( J49) * - 1} -> -4316130 | K117: 0 | L117: 0 | M117: -3908898 | N117: 0 | O117: 0 | P117: -4936701 | Q117: 0 | R117: 0 | S117: -6597360 | T117: 0 | U117: 0 | V117: -4793841.4 | W117: 0 | X117: 0 | Y117: -3262091.3 | Z117: 0 | AA117: 0 | AB117: 0 | AC117: 0 | AD117: 0 | AE117: 0 | AF117: 0 | AG117: 0 | AH117: -7810190.4 | AI117: 0 | AJ117: 0 | AK117: -4223861.2 | AL117: 0 | AM117: 0 | AN117: 0 | AO117: 0 | AP117: 0 | AQ117: 0 | AR117: 0 | AS117: 0 | AT117: -6440334.2 | AU117: 0 | AV117: 0 | AW117: 0 | AX117: 0 | AY117: 0 | AZ117: -6385768.3 | BA117: 0 | BB117: 0 | BC117: 0 | BD117: 0 | BE117: 0 | BF117: 0 | BG117: 0 | BH117: 0 | BI117: 0 | BJ117: 0 | BK117: 0 | BL117: 0 | BM117: 0 | BN117: 0 | BO117: 0 | BP117: 0 | BQ117: 0 | BR117: 0 | BS117: 0 | BT117: 0 | BU117: 0 | BV117: 0 | BW117: 0 | BX117: 0 | BY117: 0 | BZ117: 0 | CA117: 0 | CB117: 0 | CC117: 0 | CD117: 0 | CE117: 0 | CF117: 0 | CG117: 0 | CH117: 0 | CI117: 0 | CJ117: 0 | CK117: 0 | CL117: 0 | CM117: 0 | CN117: 0 | CO117: 0 | CP117: 0 | CQ117: 0 | CR117: 0 | CS117: 0 | CT117: 0 | CU117: 0 | CV117: 0 | CW117: 0 | CX117: 0 | CY117: 0 | CZ117: 0 | DA117: 0 | DB117: 0 | DC117: 0 | DD117: 0 | DE117: 0 | DF117: 0 | DG117: 0 | DH117: 0 | DI117: 0 | DJ117: 0 | DK117: 0 | DL117: 0 | DM117: 0 | DN117: 0 | DO117: 0 | DP117: 0 | DQ117: 0 | DR117: 0 | DS117: 0 | DT117: 0 | DU117: 0 | DV117: 0 | DW117: 0 | DX117: 0 | DY117: 0
E118: =E$64 -> Construction costs | G118: =G$64 -> USD | J118: {=_xlfn.ANCHORARRAY( J64) * - 1} -> 0 | K118: 0 | L118: 0 | M118: 0 | N118: -948007.12 | O118: -1053341.2 | P118: -1264009.5 | Q118: -1474677.8 | R118: -2321317.5 | S118: -3936850.8 | T118: -5097509.5 | U118: -7117610.2 | V118: -7856932.5 | W118: -8711956.8 | X118: -10392142 | Y118: -10623546 | Z118: -11989446 | AA118: -14120368 | AB118: -13395832 | AC118: -9469337.4 | AD118: -7836476.6 | AE118: -8805636.1 | AF118: -9814798.1 | AG118: -10070709 | AH118: -10820726 | AI118: -10093375 | AJ118: -11297497 | AK118: -13171659 | AL118: -14375781 | AM118: -15914923 | AN118: -15843835 | AO118: -14049514 | AP118: -9212812.4 | AQ118: -4972564 | AR118: -4412117.8 | AS118: -3255763.4 | AT118: -3715348 | AU118: -4424060.5 | AV118: -5008209.1 | AW118: -5841485.5 | AX118: -6674761.9 | AY118: -8176816.5 | AZ118: -9345113.6 | BA118: -10847800 | BB118: -11182189 | BC118: -11182189 | BD118: -11516578 | BE118: -11256885 | BF118: -10088588 | BG118: -7253738.2 | BH118: -4167114.4 | BI118: -4501503.5 | BJ118: -4835892.6 | BK118: -5170281.7 | BL118: -6250671.6 | BM118: -6919449.8 | BN118: -7588227.9 | BO118: -8334228.8 | BP118: -8334228.8 | BQ118: -9080229.8 | BR118: -8411451.6 | BS118: -8488674.3 | BT118: -7151118 | BU118: -5222006.3 | BV118: -5222006.3 | BW118: -5968007.2 | BX118: -5968007.2 | BY118: -5968007.2 | BZ118: -4476005.4 | CA118: -2984003.6 | CB118: -1492001.8 | CC118: 0 | CD118: 0 | CE118: 0 | CF118: 0 | CG118: 0 | CH118: 0 | CI118: 0 | CJ118: 0 | CK118: 0 | CL118: 0 | CM118: 0 | CN118: 0 | CO118: 0 | CP118: 0 | CQ118: 0 | CR118: 0 | CS118: 0 | CT118: 0 | CU118: 0 | CV118: 0 | CW118: 0 | CX118: 0 | CY118: 0 | CZ118: 0 | DA118: 0 | DB118: 0 | DC118: 0 | DD118: 0 | DE118: 0 | DF118: 0 | DG118: 0 | DH118: 0 | DI118: 0 | DJ118: 0 | DK118: 0 | DL118: 0 | DM118: 0 | DN118: 0 | DO118: 0 | DP118: 0 | DQ118: 0 | DR118: 0 | DS118: 0 | DT118: 0 | DU118: 0 | DV118: 0 | DW118: 0 | DX118: 0 | DY118: 0
E119: =E$94 -> Opex from new properties | G119: =G$94 -> USD | J119: {=_xlfn.ANCHORARRAY( J94) * - 1} -> 0 | K119: 0 | L119: 0 | M119: 0 | N119: 0 | O119: 0 | P119: 0 | Q119: 0 | R119: 0 | S119: 0 | T119: 0 | U119: 0 | V119: 0 | W119: 0 | X119: 0 | Y119: 0 | Z119: 0 | AA119: 0 | AB119: 0 | AC119: -143956.64 | AD119: -264673.45 | AE119: -264673.45 | AF119: -264673.45 | AG119: -264673.45 | AH119: -271290.29 | AI119: -415798.24 | AJ119: -415798.24 | AK119: -415798.24 | AL119: -415798.24 | AM119: -415798.24 | AN119: -415798.24 | AO119: -415798.24 | AP119: -415798.24 | AQ119: -708572.49 | AR119: -708572.49 | AS119: -887077.88 | AT119: -909254.83 | AU119: -909254.83 | AV119: -909254.83 | AW119: -909254.83 | AX119: -909254.83 | AY119: -909254.83 | AZ119: -909254.83 | BA119: -909254.83 | BB119: -909254.83 | BC119: -909254.83 | BD119: -909254.83 | BE119: -909254.83 | BF119: -931986.2 | BG119: -931986.2 | BH119: -1420528.3 | BI119: -1420528.3 | BJ119: -1420528.3 | BK119: -1420528.3 | BL119: -1420528.3 | BM119: -1420528.3 | BN119: -1420528.3 | BO119: -1420528.3 | BP119: -1420528.3 | BQ119: -1420528.3 | BR119: -1456041.5 | BS119: -1456041.5 | BT119: -1456041.5 | BU119: -1681578.7 | BV119: -1681578.7 | BW119: -1681578.7 | BX119: -1681578.7 | BY119: -1681578.7 | BZ119: -1681578.7 | CA119: -1681578.7 | CB119: -1681578.7 | CC119: -1957678.5 | CD119: -2006620.4 | CE119: -2006620.4 | CF119: -2006620.4 | CG119: -2006620.4 | CH119: -2006620.4 | CI119: -2006620.4 | CJ119: -2006620.4 | CK119: -2006620.4 | CL119: -2006620.4 | CM119: -2006620.4 | CN119: -2006620.4 | CO119: -2006620.4 | CP119: -2056785.9 | CQ119: -2056785.9 | CR119: -2056785.9 | CS119: -2056785.9 | CT119: -2056785.9 | CU119: -2056785.9 | CV119: -2056785.9 | CW119: -2056785.9 | CX119: -2056785.9 | CY119: -2056785.9 | CZ119: -2056785.9 | DA119: -2056785.9 | DB119: -2108205.6 | DC119: -2108205.6 | DD119: -2108205.6 | DE119: -2108205.6 | DF119: -2108205.6 | DG119: -2108205.6 | DH119: -2108205.6 | DI119: -2108205.6 | DJ119: -2108205.6 | DK119: -2108205.6 | DL119: -2108205.6 | DM119: -2108205.6 | DN119: -2160910.7 | DO119: -2160910.7 | DP119: -2160910.7 | DQ119: -2160910.7 | DR119: -2160910.7 | DS119: -2160910.7 | DT119: -2160910.7 | DU119: -2160910.7 | DV119: -2160910.7 | DW119: -2160910.7 | DX119: -2160910.7 | DY119: -2160910.7
E120: =E$103 -> Management Fee | G120: =G$103 -> USD | J120: {=_xlfn.ANCHORARRAY( J103) * - 1} -> -67536 | K120: -67536 | L120: -67536 | M120: -67536 | N120: -67536 | O120: -67536 | P120: -67536 | Q120: -67536 | R120: -67536 | S120: -67536 | T120: -67536 | U120: -67536 | V120: -70575.12 | W120: -70575.12 | X120: -70575.12 | Y120: -70575.12 | Z120: -70575.12 | AA120: -70575.12 | AB120: -70575.12 | AC120: -80274.81 | AD120: -88679.745 | AE120: -88679.745 | AF120: -88679.745 | AG120: -88679.745 | AH120: -92226.935 | AI120: -103569.87 | AJ120: -103569.87 | AK120: -103569.87 | AL120: -103569.87 | AM120: -103569.87 | AN120: -103569.87 | AO120: -103569.87 | AP120: -103569.87 | AQ120: -125434.11 | AR120: -125434.11 | AS120: -138945.21 | AT120: -143808.29 | AU120: -143808.29 | AV120: -143808.29 | AW120: -143808.29 | AX120: -143808.29 | AY120: -143808.29 | AZ120: -143808.29 | BA120: -143808.29 | BB120: -143808.29 | BC120: -143808.29 | BD120: -143808.29 | BE120: -143808.29 | BF120: -148122.54 | BG120: -148122.54 | BH120: -179021.95 | BI120: -179021.95 | BJ120: -179021.95 | BK120: -179021.95 | BL120: -179021.95 | BM120: -179021.95 | BN120: -179021.95 | BO120: -179021.95 | BP120: -179021.95 | BQ120: -179021.95 | BR120: -183497.5 | BS120: -183497.5 | BT120: -183497.5 | BU120: -202151.5 | BV120: -202151.5 | BW120: -202151.5 | BX120: -202151.5 | BY120: -202151.5 | BZ120: -202151.5 | CA120: -202151.5 | CB120: -202151.5 | CC120: -221304.27 | CD120: -226836.87 | CE120: -226836.87 | CF120: -226836.87 | CG120: -226836.87 | CH120: -226836.87 | CI120: -226836.87 | CJ120: -226836.87 | CK120: -226836.87 | CL120: -226836.87 | CM120: -226836.87 | CN120: -226836.87 | CO120: -226836.87 | CP120: -232507.8 | CQ120: -232507.8 | CR120: -232507.8 | CS120: -232507.8 | CT120: -232507.8 | CU120: -232507.8 | CV120: -232507.8 | CW120: -232507.8 | CX120: -232507.8 | CY120: -232507.8 | CZ120: -232507.8 | DA120: -232507.8 | DB120: -238320.49 | DC120: -238320.49 | DD120: -238320.49 | DE120: -238320.49 | DF120: -238320.49 | DG120: -238320.49 | DH120: -238320.49 | DI120: -238320.49 | DJ120: -238320.49 | DK120: -238320.49 | DL120: -238320.49 | DM120: -238320.49 | DN120: -244278.5 | DO120: -244278.5 | DP120: -244278.5 | DQ120: -244278.5 | DR120: -244278.5 | DS120: -244278.5 | DT120: -244278.5 | DU120: -244278.5 | DV120: -244278.5 | DW120: -244278.5 | DX120: -244278.5 | DY120: -244278.5
C122: Net Change in Cash | G122: USD | J122: {=_xlfn.BYCOL($J$111:$DY$120, _xleta.SUM )} -> -2105346.2 | K122: 2210783.8 | L122: 2210783.8 | M122: -1698114.2 | N122: 1262776.6 | O122: 1157442.5 | P122: -3989926.8 | Q122: 736106 | R122: -110533.75 | S122: -8323427 | T122: -2886725.8 | U122: -4906826.5 | V122: -10321857 | W122: -6383039.9 | X122: -8063225 | Y122: -11556720 | Z122: -9660528.7 | AA122: -11791451 | AB122: -11066915 | AC122: -7172830.8 | AD122: -5515531.5 | AE122: -6394168 | AF122: -7312806.8 | AG122: -7478194.6 | AH122: -15822252 | AI122: -7242459.7 | AJ122: -8366330.4 | AK122: -14384104 | AL122: -11284113 | AM122: -12743004 | AN122: -12591666 | AO122: -10770139 | AP122: -5915335.4 | AQ122: -1698321.1 | AR122: -1010452.4 | AS122: 250196.8 | AT122: -6306544.4 | AU122: -385349.55 | AV122: -779924.94 | AW122: -1508488.8 | AX122: -2237052.6 | AY122: -3686834.6 | AZ122: -11188627 | BA122: -6255447.8 | BB122: -6541624.2 | BC122: -6516983.9 | BD122: -6826732.7 | BE122: -6556966.4 | BF122: -5227729.2 | BG122: -2385022.6 | BH122: 576259 | BI122: 404223.63 | BJ122: 232188.26 | BK122: 60152.882 | BL122: -857883.4 | BM122: -1364307.8 | BN122: -1986605.1 | BO122: -2690981 | BP122: -2649356 | BQ122: -3356732.6 | BR122: -2505277.2 | BS122: -2542910.1 | BT122: -1198755.4 | BU122: 725938.4 | BV122: 825806.71 | BW122: 179674.11 | BX122: 279542.42 | BY122: 379410.73 | BZ122: 1971280.8 | CA122: 3493198.5 | CB122: 5015116.1 | CC122: 6481190.7 | CD122: 6772042.2 | CE122: 6900863.8 | CF122: 7022922.2 | CG122: 7125063.6 | CH122: 7227204.9 | CI122: 7255727.8 | CJ122: 7284250.7 | CK122: 7312773.6 | CL122: 7341296.5 | CM122: 7369819.4 | CN122: 7398342.3 | CO122: 7406415.6 | CP122: 7599851.1 | CQ122: 7608126.3 | CR122: 7616401.4 | CS122: 7620593.6 | CT122: 7624785.8 | CU122: 7628977.9 | CV122: 7633170.1 | CW122: 7637362.2 | CX122: 7641554.4 | CY122: 7645746.6 | CZ122: 7649938.7 | DA122: 7649938.7 | DB122: 7841187.2 | DC122: 7841187.2 | DD122: 7841187.2 | DE122: 7841187.2 | DF122: 7841187.2 | DG122: 7841187.2 | DH122: 7841187.2 | DI122: 7841187.2 | DJ122: 7841187.2 | DK122: 7841187.2 | DL122: 7841187.2 | DM122: 7841187.2 | DN122: 8037216.9 | DO122: 8037216.9 | DP122: 8037216.9 | DQ122: 8037216.9 | DR122: 8037216.9 | DS122: 8037216.9 | DT122: 8037216.9 | DU122: 8037216.9 | DV122: 8037216.9 | DW122: 8037216.9 | DX122: 8037216.9 | DY122: 8037216.9
E124: Cash initial balance | G124: USD | J124: {=_xlfn.DROP( _xlfn.HSTACK( 0,_xlfn.ANCHORARRAY( J126) ),, -1 )} -> 0 | K124: -2105346.2 | L124: 105437.5 | M124: 2316221.2 | N124: 618107 | O124: 1880883.6 | P124: 3038326.1 | Q124: -951600.62 | R124: -215494.63 | S124: -326028.38 | T124: -8649455.4 | U124: -11536181 | V124: -16443008 | W124: -26764865 | X124: -33147905 | Y124: -41211130 | Z124: -52767850 | AA124: -62428379 | AB124: -74219830 | AC124: -85286745 | AD124: -92459576 | AE124: -97975107 | AF124: -1.0436928e+08 | AG124: -1.1168208e+08 | AH124: -1.1916028e+08 | AI124: -1.3498253e+08 | AJ124: -1.4222499e+08 | AK124: -1.5059132e+08 | AL124: -1.6497542e+08 | AM124: -1.7625954e+08 | AN124: -1.8900254e+08 | AO124: -2.0159421e+08 | AP124: -2.1236434e+08 | AQ124: -2.1827968e+08 | AR124: -2.19978e+08 | AS124: -2.2098845e+08 | AT124: -2.2073826e+08 | AU124: -2.270448e+08 | AV124: -2.2743015e+08 | AW124: -2.2821007e+08 | AX124: -2.2971856e+08 | AY124: -2.3195562e+08 | AZ124: -2.3564245e+08 | BA124: -2.4683108e+08 | BB124: -2.5308653e+08 | BC124: -2.5962815e+08 | BD124: -2.6614513e+08 | BE124: -2.7297187e+08 | BF124: -2.7952883e+08 | BG124: -2.8475656e+08 | BH124: -2.8714158e+08 | BI124: -2.8656533e+08 | BJ124: -2.861611e+08 | BK124: -2.8592891e+08 | BL124: -2.8586876e+08 | BM124: -2.8672664e+08 | BN124: -2.8809095e+08 | BO124: -2.9007756e+08 | BP124: -2.9276854e+08 | BQ124: -2.9541789e+08 | BR124: -2.9877463e+08 | BS124: -3.012799e+08 | BT124: -3.0382281e+08 | BU124: -3.0502157e+08 | BV124: -3.0429563e+08 | BW124: -3.0346982e+08 | BX124: -3.0329015e+08 | BY124: -3.0301061e+08 | BZ124: -3.026312e+08 | CA124: -3.0065992e+08 | CB124: -2.9716672e+08 | CC124: -2.921516e+08 | CD124: -2.8567041e+08 | CE124: -2.7889837e+08 | CF124: -2.7199751e+08 | CG124: -2.6497458e+08 | CH124: -2.5784952e+08 | CI124: -2.5062231e+08 | CJ124: -2.4336659e+08 | CK124: -2.3608234e+08 | CL124: -2.2876956e+08 | CM124: -2.2142827e+08 | CN124: -2.1405845e+08 | CO124: -2.066601e+08 | CP124: -1.9925369e+08 | CQ124: -1.9165384e+08 | CR124: -1.8404571e+08 | CS124: -1.7642931e+08 | CT124: -1.6880872e+08 | CU124: -1.6118393e+08 | CV124: -1.5355495e+08 | CW124: -1.4592178e+08 | CX124: -1.3828442e+08 | CY124: -1.3064287e+08 | CZ124: -1.2299712e+08 | DA124: -1.1534718e+08 | DB124: -1.0769724e+08 | DC124: -99856055 | DD124: -92014868 | DE124: -84173681 | DF124: -76332493 | DG124: -68491306 | DH124: -60650119 | DI124: -52808932 | DJ124: -44967745 | DK124: -37126558 | DL124: -29285370 | DM124: -21444183 | DN124: -13602996 | DO124: -5565779.1 | DP124: 2471437.8 | DQ124: 10508655 | DR124: 18545872 | DS124: 26583088 | DT124: 34620305 | DU124: 42657522 | DV124: 50694739 | DW124: 58731956 | DX124: 66769173 | DY124: 74806390
E125: Net Change in Cash | G125: USD | J125: {=_xlfn.ANCHORARRAY( J122)} -> -2105346.2 | K125: 2210783.8 | L125: 2210783.8 | M125: -1698114.2 | N125: 1262776.6 | O125: 1157442.5 | P125: -3989926.8 | Q125: 736106 | R125: -110533.75 | S125: -8323427 | T125: -2886725.8 | U125: -4906826.5 | V125: -10321857 | W125: -6383039.9 | X125: -8063225 | Y125: -11556720 | Z125: -9660528.7 | AA125: -11791451 | AB125: -11066915 | AC125: -7172830.8 | AD125: -5515531.5 | AE125: -6394168 | AF125: -7312806.8 | AG125: -7478194.6 | AH125: -15822252 | AI125: -7242459.7 | AJ125: -8366330.4 | AK125: -14384104 | AL125: -11284113 | AM125: -12743004 | AN125: -12591666 | AO125: -10770139 | AP125: -5915335.4 | AQ125: -1698321.1 | AR125: -1010452.4 | AS125: 250196.8 | AT125: -6306544.4 | AU125: -385349.55 | AV125: -779924.94 | AW125: -1508488.8 | AX125: -2237052.6 | AY125: -3686834.6 | AZ125: -11188627 | BA125: -6255447.8 | BB125: -6541624.2 | BC125: -6516983.9 | BD125: -6826732.7 | BE125: -6556966.4 | BF125: -5227729.2 | BG125: -2385022.6 | BH125: 576259 | BI125: 404223.63 | BJ125: 232188.26 | BK125: 60152.882 | BL125: -857883.4 | BM125: -1364307.8 | BN125: -1986605.1 | BO125: -2690981 | BP125: -2649356 | BQ125: -3356732.6 | BR125: -2505277.2 | BS125: -2542910.1 | BT125: -1198755.4 | BU125: 725938.4 | BV125: 825806.71 | BW125: 179674.11 | BX125: 279542.42 | BY125: 379410.73 | BZ125: 1971280.8 | CA125: 3493198.5 | CB125: 5015116.1 | CC125: 6481190.7 | CD125: 6772042.2 | CE125: 6900863.8 | CF125: 7022922.2 | CG125: 7125063.6 | CH125: 7227204.9 | CI125: 7255727.8 | CJ125: 7284250.7 | CK125: 7312773.6 | CL125: 7341296.5 | CM125: 7369819.4 | CN125: 7398342.3 | CO125: 7406415.6 | CP125: 7599851.1 | CQ125: 7608126.3 | CR125: 7616401.4 | CS125: 7620593.6 | CT125: 7624785.8 | CU125: 7628977.9 | CV125: 7633170.1 | CW125: 7637362.2 | CX125: 7641554.4 | CY125: 7645746.6 | CZ125: 7649938.7 | DA125: 7649938.7 | DB125: 7841187.2 | DC125: 7841187.2 | DD125: 7841187.2 | DE125: 7841187.2 | DF125: 7841187.2 | DG125: 7841187.2 | DH125: 7841187.2 | DI125: 7841187.2 | DJ125: 7841187.2 | DK125: 7841187.2 | DL125: 7841187.2 | DM125: 7841187.2 | DN125: 8037216.9 | DO125: 8037216.9 | DP125: 8037216.9 | DQ125: 8037216.9 | DR125: 8037216.9 | DS125: 8037216.9 | DT125: 8037216.9 | DU125: 8037216.9 | DV125: 8037216.9 | DW125: 8037216.9 | DX125: 8037216.9 | DY125: 8037216.9
E126: Cash closing balance | G126: USD | J126: {=_xlfn.SCAN( 0,_xlfn.ANCHORARRAY( J125), _xleta.SUM )} -> -2105346.2 | K126: 105437.5 | L126: 2316221.2 | M126: 618107 | N126: 1880883.6 | O126: 3038326.1 | P126: -951600.62 | Q126: -215494.63 | R126: -326028.38 | S126: -8649455.4 | T126: -11536181 | U126: -16443008 | V126: -26764865 | W126: -33147905 | X126: -41211130 | Y126: -52767850 | Z126: -62428379 | AA126: -74219830 | AB126: -85286745 | AC126: -92459576 | AD126: -97975107 | AE126: -1.0436928e+08 | AF126: -1.1168208e+08 | AG126: -1.1916028e+08 | AH126: -1.3498253e+08 | AI126: -1.4222499e+08 | AJ126: -1.5059132e+08 | AK126: -1.6497542e+08 | AL126: -1.7625954e+08 | AM126: -1.8900254e+08 | AN126: -2.0159421e+08 | AO126: -2.1236434e+08 | AP126: -2.1827968e+08 | AQ126: -2.19978e+08 | AR126: -2.2098845e+08 | AS126: -2.2073826e+08 | AT126: -2.270448e+08 | AU126: -2.2743015e+08 | AV126: -2.2821007e+08 | AW126: -2.2971856e+08 | AX126: -2.3195562e+08 | AY126: -2.3564245e+08 | AZ126: -2.4683108e+08 | BA126: -2.5308653e+08 | BB126: -2.5962815e+08 | BC126: -2.6614513e+08 | BD126: -2.7297187e+08 | BE126: -2.7952883e+08 | BF126: -2.8475656e+08 | BG126: -2.8714158e+08 | BH126: -2.8656533e+08 | BI126: -2.861611e+08 | BJ126: -2.8592891e+08 | BK126: -2.8586876e+08 | BL126: -2.8672664e+08 | BM126: -2.8809095e+08 | BN126: -2.9007756e+08 | BO126: -2.9276854e+08 | BP126: -2.9541789e+08 | BQ126: -2.9877463e+08 | BR126: -3.012799e+08 | BS126: -3.0382281e+08 | BT126: -3.0502157e+08 | BU126: -3.0429563e+08 | BV126: -3.0346982e+08 | BW126: -3.0329015e+08 | BX126: -3.0301061e+08 | BY126: -3.026312e+08 | BZ126: -3.0065992e+08 | CA126: -2.9716672e+08 | CB126: -2.921516e+08 | CC126: -2.8567041e+08 | CD126: -2.7889837e+08 | CE126: -2.7199751e+08 | CF126: -2.6497458e+08 | CG126: -2.5784952e+08 | CH126: -2.5062231e+08 | CI126: -2.4336659e+08 | CJ126: -2.3608234e+08 | CK126: -2.2876956e+08 | CL126: -2.2142827e+08 | CM126: -2.1405845e+08 | CN126: -2.066601e+08 | CO126: -1.9925369e+08 | CP126: -1.9165384e+08 | CQ126: -1.8404571e+08 | CR126: -1.7642931e+08 | CS126: -1.6880872e+08 | CT126: -1.6118393e+08 | CU126: -1.5355495e+08 | CV126: -1.4592178e+08 | CW126: -1.3828442e+08 | CX126: -1.3064287e+08 | CY126: -1.2299712e+08 | CZ126: -1.1534718e+08 | DA126: -1.0769724e+08 | DB126: -99856055 | DC126: -92014868 | DD126: -84173681 | DE126: -76332493 | DF126: -68491306 | DG126: -60650119 | DH126: -52808932 | DI126: -44967745 | DJ126: -37126558 | DK126: -29285370 | DL126: -21444183 | DM126: -13602996 | DN126: -5565779.1 | DO126: 2471437.8 | DP126: 10508655 | DQ126: 18545872 | DR126: 26583088 | DS126: 34620305 | DT126: 42657522 | DU126: 50694739 | DV126: 58731956 | DW126: 66769173 | DX126: 74806390 | DY126: 82843607

Sheet CaseData
A1: Key Model Assumptions
A3: Existing Property Assumptions | F3: New Property Vacancy Rates | J3: Other Assumptions
A5: Existing Properties | B5: Gross Rent (Monthly) | C5: Vacancy Rate | D5: OPEX (Monthly) | F5: Month of Operations | H5: Vacancy Rate | J5: Other Assumptions
A6: Property A | B6: 791000 | C6: 0.05 | D6: 197750 | F6: 1 | H6: 0.75 | J6: Model Start Date | L6: 44562 | M6: Valuation | N6: 20
A7: Property B | B7: 448000 | C7: 0.07 | D7: 156800 | F7: 6 | H7: 0.25 | J7: Property Mgmt Fee | L7: 0.02 | M7: Sale Date | N7: 48213
A8: Property C | B8: 686000 | C8: 0.06 | D8: 171500 | F8: 12 | H8: 0.1
A9: Property D | B9: 738000 | C9: 0.04 | D9: 206640 | F9: 24 | H9: 0.05 | J9: Company name | L9: United Landlords Ltd | M9: label
A10: Property E | B10: 553000 | C10: 0.03 | D10: 176960 | J10: CFM Topic | L10: Timing flexibility
A12: New Property Assumptions | J12: Inflation Assumptions
A14: New Properties | B14: Gross Rent (Monthly) | C14: OPEX (Monthly) | D14: Land Cost | E14: Construction Costs | F14: Land Acquisition | G14: Prep Work Length | H14: Construction Length | J14: Calendar Year | K14: Rent Increase | L14: Cost Increase | M14: Land Appreciation
A15: Property F | B15: 442000 | C15: 137020 | D15: 4110600 | E15: 41106000 | F15: 44562 | G15: 4 | H15: 15 | J15: =YEAR(L6) -> 2022 | K15: 0.05 | L15: 0.025 | M15: 0.05
A16: Property G | B16: 383000 | C16: 114900 | D16: 3722760 | E16: 31023000 | F16: 44652 | G16: 5 | H16: 12 | J16: =J15+1 -> 2023 | K16: 0.045 | L16: 0.025 | M16: 0.045
A17: Property H | B17: 497000 | C17: 134190 | D17: 4701620 | E17: 42742000 | F17: 44743 | G17: 3 | H17: 16 | J17: =J16+1 -> 2024 | K17: 0.04 | L17: 0.025 | M17: 0.04
A18: Property I | B18: 595000 | C18: 166600 | D18: 6283200 | E18: 52360000 | F18: 44835 | G18: 5 | H18: 19 | J18: =J17+1 -> 2025 | K18: 0.035 | L18: 0.025 | M18: 0.035
A19: Property J | B19: 592000 | C19: 165760 | D19: 4368960 | E19: 48544000 | F19: 44927 | G19: 5 | H19: 18 | J19: =J18+1 -> 2026 | K19: 0.03 | L19: 0.025 | M19: 0.03
A20: Property K | B20: 363000 | C20: 105270 | D20: 2972970 | E20: 33033000 | F20: 45017 | G20: 6 | H20: 12 | J20: =J19+1 -> 2027 | K20: 0.025 | L20: 0.025 | M20: 0.025
A21: Property L | B21: 732000 | C21: 248880 | D21: 6844200 | E21: 62220000 | F21: 45292 | G21: 3 | H21: 23 | J21: =J20+1 -> 2028 | K21: 0.025 | L21: 0.025 | M21: 0.025
A22: Property M | B22: 538000 | C22: 182920 | D22: 3701440 | E22: 46268000 | F22: 45383 | G22: 6 | H22: 17 | J22: =J21+1 -> 2029 | K22: 0.025 | L22: 0.025 | M22: 0.025
A23: Property N | B23: 748000 | C23: 194480 | D23: 5452920 | E23: 60588000 | F23: 45658 | G23: 5 | H23: 22 | J23: =J22+1 -> 2030 | K23: 0.025 | L23: 0.025 | M23: 0.025
A24: Property O | B24: 768000 | C24: 238080 | D24: 5406720 | E24: 67584000 | F24: 45839 | G24: 5 | H24: 24 | J24: =J23+1 -> 2031 | K24: 0.025 | L24: 0.025 | M24: 0.025
A26: Construction Bell Assumptions
A28: Construction Bell | B28: % Completed Each Month for Different Construction Lengths
A29: Month of Construction | B29: 24 | C29: =B29-1 -> 23 | D29: =C29-1 -> 22 | E29: =D29-1 -> 21 | F29: =E29-1 -> 20 | G29: =F29-1 -> 19 | H29: =G29-1 -> 18 | I29: =H29-1 -> 17 | J29: =I29-1 -> 16 | ... N29: =M29-1 -> 12
A30: 1 | B30: 0.01 | C30: 0.01 | D30: 0.01 | E30: 0.0125 | F30: 0.015 | G30: 0.015 | H30: 0.015 | I30: 0.015 | J30: 0.02 | K30: 0.0225 | L30: 0.02 | M30: 0.02 | N30: 0.02
A31: =A30+1 -> 2 | B31: 0.01 | C31: 0.01 | D31: 0.01 | E31: 0.0125 | F31: 0.015 | G31: 0.015 | H31: 0.015 | I31: 0.0175 | J31: 0.02 | K31: 0.025 | L31: 0.03 | M31: 0.03 | N31: 0.03
A32: =A31+1 -> 3 | B32: 0.01 | C32: 0.015 | D32: 0.015 | E32: 0.015 | F32: 0.015 | G32: 0.02 | H32: 0.03 | I32: 0.025 | J32: 0.03 | K32: 0.03 | L32: 0.035 | M32: 0.035 | N32: 0.04
A33: =A32+1 -> 4 | B33: 0.02 | C33: 0.02 | D33: 0.02 | E33: 0.0175 | F33: 0.02 | G33: 0.025 | H33: 0.03 | I33: 0.0275 | J33: 0.03 | K33: 0.035 | L33: 0.04 | M33: 0.045 | N33: 0.05
A34: =A33+1 -> 5 | B34: 0.02 | C34: 0.02 | D34: 0.02 | E34: 0.02 | F34: 0.025 | G34: 0.025 | H34: 0.03 | I34: 0.035 | J34: 0.035 | K34: 0.04 | L34: 0.045 | M34: 0.05 | N34: 0.06
A35: =A34+1 -> 6 | B35: 0.02 | C35: 0.025 | D35: 0.025 | E35: 0.025 | F35: 0.0275 | G35: 0.03 | H35: 0.03 | I35: 0.04 | J35: 0.04 | K35: 0.05 | L35: 0.06 | M35: 0.07 | N35: 0.08
A36: =A35+1 -> 7 | B36: 0.02 | C36: 0.025 | D36: 0.03 | E36: 0.03 | F36: 0.035 | G36: 0.035 | H36: 0.04 | I36: 0.05 | J36: 0.05 | K36: 0.07 | L36: 0.08 | M36: 0.08 | N36: 0.1
A37: =A36+1 -> 8 | B37: 0.03 | C37: 0.03 | D37: 0.03 | E37: 0.03 | F37: 0.035 | G37: 0.04 | H37: 0.05 | I37: 0.06 | J37: 0.07 | K37: 0.1 | L37: 0.1 | M37: 0.1 | N37: 0.12
A38: =A37+1 -> 9 | B38: 0.03 | C38: 0.03 | D38: 0.03 | E38: 0.035 | F38: 0.04 | G38: 0.06 | H38: 0.06 | I38: 0.07 | J38: 0.09 | K38: 0.11 | L38: 0.12 | M38: 0.14 | N38: 0.14
A39: =A38+1 -> 10 | B39: 0.03 | C39: 0.035 | D39: 0.04 | E39: 0.05 | F39: 0.05 | G39: 0.065 | H39: 0.07 | I39: 0.08 | J39: 0.1 | K39: 0.11 | L39: 0.12 | M39: 0.14 | N39: 0.16
A40: =A39+1 -> 11 | B40: 0.04 | C40: 0.04 | D40: 0.045 | E40: 0.06 | F40: 0.06 | G40: 0.075 | H40: 0.08 | I40: 0.09 | J40: 0.1 | K40: 0.11 | L40: 0.12 | M40: 0.14 | N40: 0.14
A41: =A40+1 -> 12 | B41: 0.04 | C41: 0.045 | D41: 0.05 | E41: 0.07 | F41: 0.07 | G41: 0.09 | H41: 0.09 | I41: 0.09 | J41: 0.1 | K41: 0.09 | L41: 0.1 | M41: 0.1 | N41: 0.06
A42: =A41+1 -> 13 | B42: 0.05 | C42: 0.05 | D42: 0.055 | E42: 0.08 | F42: 0.09 | G42: 0.09 | H42: 0.1 | I42: 0.09 | J42: 0.1 | K42: 0.08 | L42: 0.08 | M42: 0.05
A43: =A42+1 -> 14 | B43: 0.05 | C43: 0.055 | D43: 0.06 | E43: 0.09 | F43: 0.09 | G43: 0.09 | H43: 0.1 | I43: 0.09 | J43: 0.09 | K43: 0.07 | L43: 0.05
A44: =A43+1 -> 15 | B44: 0.06 | C44: 0.06 | D44: 0.07 | E44: 0.09 | F44: 0.09 | G44: 0.09 | H44: 0.1 | I44: 0.09 | J44: 0.07 | K44: 0.0575
A45: =A44+1 -> 16 | B45: 0.06 | C45: 0.07 | D45: 0.08 | E45: 0.09 | F45: 0.09 | G45: 0.09 | H45: 0.08 | I45: 0.08 | J45: 0.055
A46: =A45+1 -> 17 | B46: 0.07 | C46: 0.08 | D46: 0.08 | E46: 0.09 | F46: 0.09 | G46: 0.07 | H46: 0.05 | I46: 0.05
A47: =A46+1 -> 18 | B47: 0.07 | C47: 0.08 | D47: 0.08 | E47: 0.0725 | F47: 0.07 | G47: 0.05 | H47: 0.03
A48: =A47+1 -> 19 | B48: 0.08 | C48: 0.08 | D48: 0.08 | E48: 0.05 | F48: 0.05 | G48: 0.025
A49: =A48+1 -> 20 | B49: 0.08 | C49: 0.08 | D49: 0.07 | E49: 0.035 | F49: 0.0225
A50: =A49+1 -> 21 | B50: 0.08 | C50: 0.06 | D50: 0.06 | E50: 0.025
A51: =A50+1 -> 22 | B51: 0.06 | C51: 0.05 | D51: 0.04
A52: =A51+1 -> 23 | B52: 0.04 | C52: 0.03
A53: =A52+1 -> 24 | B53: 0.02
A54: Total | B54: =SUM(B30:B53) -> 1 | C54: =SUM(C30:C53) -> 1 | D54: =SUM(D30:D53) -> 1 | E54: =SUM(E30:E53) -> 1 | F54: =SUM(F30:F53) -> 1 | G54: =SUM(G30:G53) -> 1 | H54: =SUM(H30:H53) -> 1 | I54: =SUM(I30:I53) -> 1 | ... N54: =SUM(N30:N53) -> 1

Sheet CaseSolution
B2: Period Start | G2: =CaseData!$L$6 -> 44562 | H2: =G3+1 -> 44593 | I2: =H3+1 -> 44621 | J2: =I3+1 -> 44652 | K2: =J3+1 -> 44682 | L2: =K3+1 -> 44713 | M2: =L3+1 -> 44743 | N2: =M3+1 -> 44774 | O2: =N3+1 -> 44805 | ... DV2: =DU3+1 -> 48183
B3: Period End | F3: =G2-1 -> 44561 | G3: =EOMONTH(G2,0) -> 44592 | H3: =EOMONTH(H2,0) -> 44620 | I3: =EOMONTH(I2,0) -> 44651 | J3: =EOMONTH(J2,0) -> 44681 | K3: =EOMONTH(K2,0) -> 44712 | L3: =EOMONTH(L2,0) -> 44742 | M3: =EOMONTH(M2,0) -> 44773 | N3: =EOMONTH(N2,0) -> 44804 | ... DV3: =EOMONTH(DV2,0) -> 48213
B4: Period # | F4: 0 | G4: =F4+1 -> 1 | H4: =G4+1 -> 2 | I4: =H4+1 -> 3 | J4: =I4+1 -> 4 | K4: =J4+1 -> 5 | L4: =K4+1 -> 6 | M4: =L4+1 -> 7 | N4: =M4+1 -> 8 | ... DV4: =DU4+1 -> 120
B6: 1. Cashflow Summary
B8: Total Project Cashflow for the Month | E8: [$] | G8: =SUM(G9:G13) -> -2105346.2 | H8: =SUM(H9:H13) -> 2210783.8 | I8: =SUM(I9:I13) -> 2210783.8 | J8: =SUM(J9:J13) -> -1698114.2 | K8: =SUM(K9:K13) -> 1262776.6 | L8: =SUM(L9:L13) -> 1157442.5 | M8: =SUM(M9:M13) -> -3989926.8 | N8: =SUM(N9:N13) -> 736106 | ... DV8: =SUM(DV9:DV13) -> 8037216.9
B9: Net Rent Revenue | E9: [$] | G9: =G22 -> 3210711 | H9: =H22 -> 3210711 | I9: =I22 -> 3210711 | J9: =J22 -> 3210711 | K9: =K22 -> 3210711 | L9: =L22 -> 3210711 | M9: =M22 -> 3210711 | N9: =N22 -> 3210711 | ... DV9: =DV22 -> 11606835
B10: Operating Expenses | E10: [$] | G10: =-G46 -> -932391.25 | H10: =-H46 -> -932391.25 | I10: =-I46 -> -932391.25 | J10: =-J46 -> -932391.25 | K10: =-K46 -> -932391.25 | L10: =-L46 -> -932391.25 | M10: =-M46 -> -932391.25 | N10: =-N46 -> -932391.25 | ... DV10: =-DV46 -> -3325339.6
B11: Property Management Fee | E11: [$] | G11: =-G70 -> -67536 | H11: =-H70 -> -67536 | I11: =-I70 -> -67536 | J11: =-J70 -> -67536 | K11: =-K70 -> -67536 | L11: =-L70 -> -67536 | M11: =-M70 -> -67536 | N11: =-N70 -> -67536 | ... DV11: =-DV70 -> -244278.5
B12: Land Acquisition Cost | E12: [$] | G12: =-G95 -> -4316130 | H12: =-H95 -> 0 | I12: =-I95 -> 0 | J12: =-J95 -> -3908898 | K12: =-K95 -> 0 | L12: =-L95 -> 0 | M12: =-M95 -> -4936701 | N12: =-N95 -> 0 | ... DV12: =-DV95 -> 0
B13: Construction Cost | E13: [$] | G13: =-G110 -> 0 | H13: =-H110 -> 0 | I13: =-I110 -> 0 | J13: =-J110 -> 0 | K13: =-K110 -> -948007.12 | L13: =-L110 -> -1053341.2 | M13: =-M110 -> -1264009.5 | N13: =-N110 -> -1474677.8 | ... DV13: =-DV110 -> 0
B15: Opening Cash | E15: [$] | G15: 0 | H15: =G16 -> -2105346.2 | I15: =H16 -> 105437.5 | J15: =I16 -> 2316221.2 | K15: =J16 -> 618107 | L15: =K16 -> 1880883.6 | M15: =L16 -> 3038326.1 | N15: =M16 -> -951600.62 | O15: =N16 -> -215494.63 | ... DV15: =DU16 -> 74806390
B16: Closing Cash | E16: [$] | G16: =G8+G15 -> -2105346.2 | H16: =H8+H15 -> 105437.5 | I16: =I8+I15 -> 2316221.2 | J16: =J8+J15 -> 618107 | K16: =K8+K15 -> 1880883.6 | L16: =L8+L15 -> 3038326.1 | M16: =M8+M15 -> -951600.62 | N16: =N8+N15 -> -215494.63 | ... DV16: =DV8+DV15 -> 82843607
B17: NOI | E17: [$] | G17: =SUM(G9:G11) -> 2210783.8 | H17: =SUM(H9:H11) -> 2210783.8 | I17: =SUM(I9:I11) -> 2210783.8 | J17: =SUM(J9:J11) -> 2210783.8 | K17: =SUM(K9:K11) -> 2210783.8 | L17: =SUM(L9:L11) -> 2210783.8 | M17: =SUM(M9:M11) -> 2210783.8 | N17: =SUM(N9:N11) -> 2210783.8 | ... DV17: =SUM(DV9:DV11) -> 8037216.9
B19: 2. Rent Revenue Forecast
B22: Rent Revenue, Net | E22: [$] | G22: =SUBTOTAL(9,G24:G41) -> 3210711 | H22: =SUBTOTAL(9,H24:H41) -> 3210711 | I22: =SUBTOTAL(9,I24:I41) -> 3210711 | J22: =SUBTOTAL(9,J24:J41) -> 3210711 | K22: =SUBTOTAL(9,K24:K41) -> 3210711 | L22: =SUBTOTAL(9,L24:L41) -> 3210711 | M22: =SUBTOTAL(9,M24:M41) -> 3210711 | N22: =SUBTOTAL(9,N24:N41) -> 3210711 | ... DV22: =SUBTOTAL(9,DV24:DV41) -> 11606835
B24: Existing Properties | C24: Gross Revenue | D24: Vacancy Rate | E24: [$] | G24: =SUBTOTAL(9,G25:G29) -> 3210711 | H24: =SUBTOTAL(9,H25:H29) -> 3210711 | I24: =SUBTOTAL(9,I25:I29) -> 3210711 | J24: =SUBTOTAL(9,J25:J29) -> 3210711 | K24: =SUBTOTAL(9,K25:K29) -> 3210711 | L24: =SUBTOTAL(9,L25:L29) -> 3210711 | M24: =SUBTOTAL(9,M25:M29) -> 3210711 | N24: =SUBTOTAL(9,N25:N29) -> 3210711 | ... DV24: =SUBTOTAL(9,DV25:DV29) -> 4208697.8
B25: =CaseData!A6 -> Property A | C25: =CaseData!B6 -> 791000 | D25: =CaseData!C6 -> 0.05 | E25: [$] | G25: =$C25*(1-$D25)*G$210 -> 789022.5 | H25: =$C25*(1-$D25)*H$210 -> 789022.5 | I25: =$C25*(1-$D25)*I$210 -> 789022.5 | J25: =$C25*(1-$D25)*J$210 -> 789022.5 | K25: =$C25*(1-$D25)*K$210 -> 789022.5 | L25: =$C25*(1-$D25)*L$210 -> 789022.5 | M25: =$C25*(1-$D25)*M$210 -> 789022.5 | N25: =$C25*(1-$D25)*N$210 -> 789022.5 | ... DV25: =$C25*(1-$D25)*DV$210 -> 1034274.7
B26: =CaseData!A7 -> Property B | C26: =CaseData!B7 -> 448000 | D26: =CaseData!C7 -> 0.07 | E26: [$] | G26: =$C26*(1-$D26)*G$210 -> 437472 | H26: =$C26*(1-$D26)*H$210 -> 437472 | I26: =$C26*(1-$D26)*I$210 -> 437472 | J26: =$C26*(1-$D26)*J$210 -> 437472 | K26: =$C26*(1-$D26)*K$210 -> 437472 | L26: =$C26*(1-$D26)*L$210 -> 437472 | M26: =$C26*(1-$D26)*M$210 -> 437472 | N26: =$C26*(1-$D26)*N$210 -> 437472 | ... DV26: =$C26*(1-$D26)*DV$210 -> 573451.63
B27: =CaseData!A8 -> Property C | C27: =CaseData!B8 -> 686000 | D27: =CaseData!C8 -> 0.06 | E27: [$] | G27: =$C27*(1-$D27)*G$210 -> 677082 | H27: =$C27*(1-$D27)*H$210 -> 677082 | I27: =$C27*(1-$D27)*I$210 -> 677082 | J27: =$C27*(1-$D27)*J$210 -> 677082 | K27: =$C27*(1-$D27)*K$210 -> 677082 | L27: =$C27*(1-$D27)*L$210 -> 677082 | M27: =$C27*(1-$D27)*M$210 -> 677082 | N27: =$C27*(1-$D27)*N$210 -> 677082 | ... DV27: =$C27*(1-$D27)*DV$210 -> 887539.72
B28: =CaseData!A9 -> Property D | C28: =CaseData!B9 -> 738000 | D28: =CaseData!C9 -> 0.04 | E28: [$] | G28: =$C28*(1-$D28)*G$210 -> 743904 | H28: =$C28*(1-$D28)*H$210 -> 743904 | I28: =$C28*(1-$D28)*I$210 -> 743904 | J28: =$C28*(1-$D28)*J$210 -> 743904 | K28: =$C28*(1-$D28)*K$210 -> 743904 | L28: =$C28*(1-$D28)*L$210 -> 743904 | M28: =$C28*(1-$D28)*M$210 -> 743904 | N28: =$C28*(1-$D28)*N$210 -> 743904 | ... DV28: =$C28*(1-$D28)*DV$210 -> 975132.04
B29: =CaseData!A10 -> Property E | C29: =CaseData!B10 -> 553000 | D29: =CaseData!C10 -> 0.03 | E29: [$] | G29: =$C29*(1-$D29)*G$210 -> 563230.5 | H29: =$C29*(1-$D29)*H$210 -> 563230.5 | I29: =$C29*(1-$D29)*I$210 -> 563230.5 | J29: =$C29*(1-$D29)*J$210 -> 563230.5 | K29: =$C29*(1-$D29)*K$210 -> 563230.5 | L29: =$C29*(1-$D29)*L$210 -> 563230.5 | M29: =$C29*(1-$D29)*M$210 -> 563230.5 | N29: =$C29*(1-$D29)*N$210 -> 563230.5 | ... DV29: =$C29*(1-$D29)*DV$210 -> 738299.71
B31: New Properties | C31: Gross Revenue | E31: [$] | G31: =SUBTOTAL(9,G32:G41) -> 0 | H31: =SUBTOTAL(9,H32:H41) -> 0 | I31: =SUBTOTAL(9,I32:I41) -> 0 | J31: =SUBTOTAL(9,J32:J41) -> 0 | K31: =SUBTOTAL(9,K32:K41) -> 0 | L31: =SUBTOTAL(9,L32:L41) -> 0 | M31: =SUBTOTAL(9,M32:M41) -> 0 | N31: =SUBTOTAL(9,N32:N41) -> 0 | ... DV31: =SUBTOTAL(9,DV32:DV41) -> 7398137.2
B32: =CaseData!A15 -> Property F | C32: =CaseData!B15 -> 442000 | E32: [$] | G32: =IF(G179=0,0,$C32*(1-G192)*G$210) -> 0 | H32: =IF(H179=0,0,$C32*(1-H192)*H$210) -> 0 | I32: =IF(I179=0,0,$C32*(1-I192)*I$210) -> 0 | J32: =IF(J179=0,0,$C32*(1-J192)*J$210) -> 0 | K32: =IF(K179=0,0,$C32*(1-K192)*K$210) -> 0 | L32: =IF(L179=0,0,$C32*(1-L192)*L$210) -> 0 | M32: =IF(M179=0,0,$C32*(1-M192)*M$210) -> 0 | N32: =IF(N179=0,0,$C32*(1-N192)*N$210) -> 0 | ... DV32: =IF(DV179=0,0,$C32*(1-DV192)*DV$210) -> 577938.6
B33: =CaseData!A16 -> Property G | C33: =CaseData!B16 -> 383000 | E33: [$] | G33: =IF(G180=0,0,$C33*(1-G193)*G$210) -> 0 | H33: =IF(H180=0,0,$C33*(1-H193)*H$210) -> 0 | I33: =IF(I180=0,0,$C33*(1-I193)*I$210) -> 0 | J33: =IF(J180=0,0,$C33*(1-J193)*J$210) -> 0 | K33: =IF(K180=0,0,$C33*(1-K193)*K$210) -> 0 | L33: =IF(L180=0,0,$C33*(1-L193)*L$210) -> 0 | M33: =IF(M180=0,0,$C33*(1-M193)*M$210) -> 0 | N33: =IF(N180=0,0,$C33*(1-N193)*N$210) -> 0 | ... DV33: =IF(DV180=0,0,$C33*(1-DV193)*DV$210) -> 500792.95
B34: =CaseData!A17 -> Property H | C34: =CaseData!B17 -> 497000 | E34: [$] | G34: =IF(G181=0,0,$C34*(1-G194)*G$210) -> 0 | H34: =IF(H181=0,0,$C34*(1-H194)*H$210) -> 0 | I34: =IF(I181=0,0,$C34*(1-I194)*I$210) -> 0 | J34: =IF(J181=0,0,$C34*(1-J194)*J$210) -> 0 | K34: =IF(K181=0,0,$C34*(1-K194)*K$210) -> 0 | L34: =IF(L181=0,0,$C34*(1-L194)*L$210) -> 0 | M34: =IF(M181=0,0,$C34*(1-M194)*M$210) -> 0 | N34: =IF(N181=0,0,$C34*(1-N194)*N$210) -> 0 | ... DV34: =IF(DV181=0,0,$C34*(1-DV194)*DV$210) -> 649854.04
B35: =CaseData!A18 -> Property I | C35: =CaseData!B18 -> 595000 | E35: [$] | G35: =IF(G182=0,0,$C35*(1-G195)*G$210) -> 0 | H35: =IF(H182=0,0,$C35*(1-H195)*H$210) -> 0 | I35: =IF(I182=0,0,$C35*(1-I195)*I$210) -> 0 | J35: =IF(J182=0,0,$C35*(1-J195)*J$210) -> 0 | K35: =IF(K182=0,0,$C35*(1-K195)*K$210) -> 0 | L35: =IF(L182=0,0,$C35*(1-L195)*L$210) -> 0 | M35: =IF(M182=0,0,$C35*(1-M195)*M$210) -> 0 | N35: =IF(N182=0,0,$C35*(1-N195)*N$210) -> 0 | ... DV35: =IF(DV182=0,0,$C35*(1-DV195)*DV$210) -> 777994.28
B36: =CaseData!A19 -> Property J | C36: =CaseData!B19 -> 592000 | E36: [$] | G36: =IF(G183=0,0,$C36*(1-G196)*G$210) -> 0 | H36: =IF(H183=0,0,$C36*(1-H196)*H$210) -> 0 | I36: =IF(I183=0,0,$C36*(1-I196)*I$210) -> 0 | J36: =IF(J183=0,0,$C36*(1-J196)*J$210) -> 0 | K36: =IF(K183=0,0,$C36*(1-K196)*K$210) -> 0 | L36: =IF(L183=0,0,$C36*(1-L196)*L$210) -> 0 | M36: =IF(M183=0,0,$C36*(1-M196)*M$210) -> 0 | N36: =IF(N183=0,0,$C36*(1-N196)*N$210) -> 0 | ... DV36: =IF(DV183=0,0,$C36*(1-DV196)*DV$210) -> 774071.61
B37: =CaseData!A20 -> Property K | C37: =CaseData!B20 -> 363000 | E37: [$] | G37: =IF(G184=0,0,$C37*(1-G197)*G$210) -> 0 | H37: =IF(H184=0,0,$C37*(1-H197)*H$210) -> 0 | I37: =IF(I184=0,0,$C37*(1-I197)*I$210) -> 0 | J37: =IF(J184=0,0,$C37*(1-J197)*J$210) -> 0 | K37: =IF(K184=0,0,$C37*(1-K197)*K$210) -> 0 | L37: =IF(L184=0,0,$C37*(1-L197)*L$210) -> 0 | M37: =IF(M184=0,0,$C37*(1-M197)*M$210) -> 0 | N37: =IF(N184=0,0,$C37*(1-N197)*N$210) -> 0 | ... DV37: =IF(DV184=0,0,$C37*(1-DV197)*DV$210) -> 474641.89
B38: =CaseData!A21 -> Property L | C38: =CaseData!B21 -> 732000 | E38: [$] | G38: =IF(G185=0,0,$C38*(1-G198)*G$210) -> 0 | H38: =IF(H185=0,0,$C38*(1-H198)*H$210) -> 0 | I38: =IF(I185=0,0,$C38*(1-I198)*I$210) -> 0 | J38: =IF(J185=0,0,$C38*(1-J198)*J$210) -> 0 | K38: =IF(K185=0,0,$C38*(1-K198)*K$210) -> 0 | L38: =IF(L185=0,0,$C38*(1-L198)*L$210) -> 0 | M38: =IF(M185=0,0,$C38*(1-M198)*M$210) -> 0 | N38: =IF(N185=0,0,$C38*(1-N198)*N$210) -> 0 | ... DV38: =IF(DV185=0,0,$C38*(1-DV198)*DV$210) -> 957129.09
B39: =CaseData!A22 -> Property M | C39: =CaseData!B22 -> 538000 | E39: [$] | G39: =IF(G186=0,0,$C39*(1-G199)*G$210) -> 0 | H39: =IF(H186=0,0,$C39*(1-H199)*H$210) -> 0 | I39: =IF(I186=0,0,$C39*(1-I199)*I$210) -> 0 | J39: =IF(J186=0,0,$C39*(1-J199)*J$210) -> 0 | K39: =IF(K186=0,0,$C39*(1-K199)*K$210) -> 0 | L39: =IF(L186=0,0,$C39*(1-L199)*L$210) -> 0 | M39: =IF(M186=0,0,$C39*(1-M199)*M$210) -> 0 | N39: =IF(N186=0,0,$C39*(1-N199)*N$210) -> 0 | ... DV39: =IF(DV186=0,0,$C39*(1-DV199)*DV$210) -> 703463.73
B40: =CaseData!A23 -> Property N | C40: =CaseData!B23 -> 748000 | E40: [$] | G40: =IF(G187=0,0,$C40*(1-G200)*G$210) -> 0 | H40: =IF(H187=0,0,$C40*(1-H200)*H$210) -> 0 | I40: =IF(I187=0,0,$C40*(1-I200)*I$210) -> 0 | J40: =IF(J187=0,0,$C40*(1-J200)*J$210) -> 0 | K40: =IF(K187=0,0,$C40*(1-K200)*K$210) -> 0 | L40: =IF(L187=0,0,$C40*(1-L200)*L$210) -> 0 | M40: =IF(M187=0,0,$C40*(1-M200)*M$210) -> 0 | N40: =IF(N187=0,0,$C40*(1-N200)*N$210) -> 0 | ... DV40: =IF(DV187=0,0,$C40*(1-DV200)*DV$210) -> 978049.95
B41: =CaseData!A24 -> Property O | C41: =CaseData!B24 -> 768000 | E41: [$] | G41: =IF(G188=0,0,$C41*(1-G201)*G$210) -> 0 | H41: =IF(H188=0,0,$C41*(1-H201)*H$210) -> 0 | I41: =IF(I188=0,0,$C41*(1-I201)*I$210) -> 0 | J41: =IF(J188=0,0,$C41*(1-J201)*J$210) -> 0 | K41: =IF(K188=0,0,$C41*(1-K201)*K$210) -> 0 | L41: =IF(L188=0,0,$C41*(1-L201)*L$210) -> 0 | M41: =IF(M188=0,0,$C41*(1-M201)*M$210) -> 0 | N41: =IF(N188=0,0,$C41*(1-N201)*N$210) -> 0 | ... DV41: =IF(DV188=0,0,$C41*(1-DV201)*DV$210) -> 1004201
B44: 3. OPEX Forecast
B46: Total OPEX | E46: [$] | G46: =SUBTOTAL(9,G48:G65) -> 932391.25 | H46: =SUBTOTAL(9,H48:H65) -> 932391.25 | I46: =SUBTOTAL(9,I48:I65) -> 932391.25 | J46: =SUBTOTAL(9,J48:J65) -> 932391.25 | K46: =SUBTOTAL(9,K48:K65) -> 932391.25 | L46: =SUBTOTAL(9,L48:L65) -> 932391.25 | M46: =SUBTOTAL(9,M48:M65) -> 932391.25 | N46: =SUBTOTAL(9,N48:N65) -> 932391.25 | ... DV46: =SUBTOTAL(9,DV48:DV65) -> 3325339.6
B48: Existing Properties | C48: OPEX | E48: [$] | G48: =SUBTOTAL(9,G49:G53) -> 932391.25 | H48: =SUBTOTAL(9,H49:H53) -> 932391.25 | I48: =SUBTOTAL(9,I49:I53) -> 932391.25 | J48: =SUBTOTAL(9,J49:J53) -> 932391.25 | K48: =SUBTOTAL(9,K49:K53) -> 932391.25 | L48: =SUBTOTAL(9,L49:L53) -> 932391.25 | M48: =SUBTOTAL(9,M49:M53) -> 932391.25 | N48: =SUBTOTAL(9,N49:N53) -> 932391.25 | ... DV48: =SUBTOTAL(9,DV49:DV53) -> 1164428.9
B49: =B25 -> Property A | C49: =CaseData!D6 -> 197750 | E49: [$] | G49: =$C49*G$211 -> 202693.75 | H49: =$C49*H$211 -> 202693.75 | I49: =$C49*I$211 -> 202693.75 | J49: =$C49*J$211 -> 202693.75 | K49: =$C49*K$211 -> 202693.75 | L49: =$C49*L$211 -> 202693.75 | M49: =$C49*M$211 -> 202693.75 | N49: =$C49*N$211 -> 202693.75 | ... DV49: =$C49*DV$211 -> 253136.72
B50: =B26 -> Property B | C50: =CaseData!D7 -> 156800 | E50: [$] | G50: =$C50*G$211 -> 160720 | H50: =$C50*H$211 -> 160720 | I50: =$C50*I$211 -> 160720 | J50: =$C50*J$211 -> 160720 | K50: =$C50*K$211 -> 160720 | L50: =$C50*L$211 -> 160720 | M50: =$C50*M$211 -> 160720 | N50: =$C50*N$211 -> 160720 | ... DV50: =$C50*DV$211 -> 200717.26
B51: =B27 -> Property C | C51: =CaseData!D8 -> 171500 | E51: [$] | G51: =$C51*G$211 -> 175787.5 | H51: =$C51*H$211 -> 175787.5 | I51: =$C51*I$211 -> 175787.5 | J51: =$C51*J$211 -> 175787.5 | K51: =$C51*K$211 -> 175787.5 | L51: =$C51*L$211 -> 175787.5 | M51: =$C51*M$211 -> 175787.5 | N51: =$C51*N$211 -> 175787.5 | ... DV51: =$C51*DV$211 -> 219534.5
B52: =B28 -> Property D | C52: =CaseData!D9 -> 206640 | E52: [$] | G52: =$C52*G$211 -> 211806 | H52: =$C52*H$211 -> 211806 | I52: =$C52*I$211 -> 211806 | J52: =$C52*J$211 -> 211806 | K52: =$C52*K$211 -> 211806 | L52: =$C52*L$211 -> 211806 | M52: =$C52*M$211 -> 211806 | N52: =$C52*N$211 -> 211806 | ... DV52: =$C52*DV$211 -> 264516.67
B53: =B29 -> Property E | C53: =CaseData!D10 -> 176960 | E53: [$] | G53: =$C53*G$211 -> 181384 | H53: =$C53*H$211 -> 181384 | I53: =$C53*I$211 -> 181384 | J53: =$C53*J$211 -> 181384 | K53: =$C53*K$211 -> 181384 | L53: =$C53*L$211 -> 181384 | M53: =$C53*M$211 -> 181384 | N53: =$C53*N$211 -> 181384 | ... DV53: =$C53*DV$211 -> 226523.76
B55: New Properties | C55: OPEX | E55: [$] | G55: =SUBTOTAL(9,G56:G65) -> 0 | H55: =SUBTOTAL(9,H56:H65) -> 0 | I55: =SUBTOTAL(9,I56:I65) -> 0 | J55: =SUBTOTAL(9,J56:J65) -> 0 | K55: =SUBTOTAL(9,K56:K65) -> 0 | L55: =SUBTOTAL(9,L56:L65) -> 0 | M55: =SUBTOTAL(9,M56:M65) -> 0 | N55: =SUBTOTAL(9,N56:N65) -> 0 | ... DV55: =SUBTOTAL(9,DV56:DV65) -> 2160910.7
B56: =B32 -> Property F | C56: =CaseData!C15 -> 137020 | E56: [$] | G56: =$C56*G$211*IF(G179=0,0,1) -> 0 | H56: =$C56*H$211*IF(H179=0,0,1) -> 0 | I56: =$C56*I$211*IF(I179=0,0,1) -> 0 | J56: =$C56*J$211*IF(J179=0,0,1) -> 0 | K56: =$C56*K$211*IF(K179=0,0,1) -> 0 | L56: =$C56*L$211*IF(L179=0,0,1) -> 0 | M56: =$C56*M$211*IF(M179=0,0,1) -> 0 | N56: =$C56*N$211*IF(N179=0,0,1) -> 0 | ... DV56: =$C56*DV$211*IF(DV179=0,0,1) -> 175397.18
B57: =B33 -> Property G | C57: =CaseData!C16 -> 114900 | E57: [$] | G57: =$C57*G$211*IF(G180=0,0,1) -> 0 | H57: =$C57*H$211*IF(H180=0,0,1) -> 0 | I57: =$C57*I$211*IF(I180=0,0,1) -> 0 | J57: =$C57*J$211*IF(J180=0,0,1) -> 0 | K57: =$C57*K$211*IF(K180=0,0,1) -> 0 | L57: =$C57*L$211*IF(L180=0,0,1) -> 0 | M57: =$C57*M$211*IF(M180=0,0,1) -> 0 | N57: =$C57*N$211*IF(N180=0,0,1) -> 0 | ... DV57: =$C57*DV$211*IF(DV180=0,0,1) -> 147081.71
B58: =B34 -> Property H | C58: =CaseData!C17 -> 134190 | E58: [$] | G58: =$C58*G$211*IF(G181=0,0,1) -> 0 | H58: =$C58*H$211*IF(H181=0,0,1) -> 0 | I58: =$C58*I$211*IF(I181=0,0,1) -> 0 | J58: =$C58*J$211*IF(J181=0,0,1) -> 0 | K58: =$C58*K$211*IF(K181=0,0,1) -> 0 | L58: =$C58*L$211*IF(L181=0,0,1) -> 0 | M58: =$C58*M$211*IF(M181=0,0,1) -> 0 | N58: =$C58*N$211*IF(N181=0,0,1) -> 0 | ... DV58: =$C58*DV$211*IF(DV181=0,0,1) -> 171774.54
B59: =B35 -> Property I | C59: =CaseData!C18 -> 166600 | E59: [$] | G59: =$C59*G$211*IF(G182=0,0,1) -> 0 | H59: =$C59*H$211*IF(H182=0,0,1) -> 0 | I59: =$C59*I$211*IF(I182=0,0,1) -> 0 | J59: =$C59*J$211*IF(J182=0,0,1) -> 0 | K59: =$C59*K$211*IF(K182=0,0,1) -> 0 | L59: =$C59*L$211*IF(L182=0,0,1) -> 0 | M59: =$C59*M$211*IF(M182=0,0,1) -> 0 | N59: =$C59*N$211*IF(N182=0,0,1) -> 0 | ... DV59: =$C59*DV$211*IF(DV182=0,0,1) -> 213262.09
B60: =B36 -> Property J | C60: =CaseData!C19 -> 165760 | E60: [$] | G60: =$C60*G$211*IF(G183=0,0,1) -> 0 | H60: =$C60*H$211*IF(H183=0,0,1) -> 0 | I60: =$C60*I$211*IF(I183=0,0,1) -> 0 | J60: =$C60*J$211*IF(J183=0,0,1) -> 0 | K60: =$C60*K$211*IF(K183=0,0,1) -> 0 | L60: =$C60*L$211*IF(L183=0,0,1) -> 0 | M60: =$C60*M$211*IF(M183=0,0,1) -> 0 | N60: =$C60*N$211*IF(N183=0,0,1) -> 0 | ... DV60: =$C60*DV$211*IF(DV183=0,0,1) -> 212186.81
B61: =B37 -> Property K | C61: =CaseData!C20 -> 105270 | E61: [$] | G61: =$C61*G$211*IF(G184=0,0,1) -> 0 | H61: =$C61*H$211*IF(H184=0,0,1) -> 0 | I61: =$C61*I$211*IF(I184=0,0,1) -> 0 | J61: =$C61*J$211*IF(J184=0,0,1) -> 0 | K61: =$C61*K$211*IF(K184=0,0,1) -> 0 | L61: =$C61*L$211*IF(L184=0,0,1) -> 0 | M61: =$C61*M$211*IF(M184=0,0,1) -> 0 | N61: =$C61*N$211*IF(N184=0,0,1) -> 0 | ... DV61: =$C61*DV$211*IF(DV184=0,0,1) -> 134754.5
B62: =B38 -> Property L | C62: =CaseData!C21 -> 248880 | E62: [$] | G62: =$C62*G$211*IF(G185=0,0,1) -> 0 | H62: =$C62*H$211*IF(H185=0,0,1) -> 0 | I62: =$C62*I$211*IF(I185=0,0,1) -> 0 | J62: =$C62*J$211*IF(J185=0,0,1) -> 0 | K62: =$C62*K$211*IF(K185=0,0,1) -> 0 | L62: =$C62*L$211*IF(L185=0,0,1) -> 0 | M62: =$C62*M$211*IF(M185=0,0,1) -> 0 | N62: =$C62*N$211*IF(N185=0,0,1) -> 0 | ... DV62: =$C62*DV$211*IF(DV185=0,0,1) -> 318587.44
B63: =B39 -> Property M | C63: =CaseData!C22 -> 182920 | E63: [$] | G63: =$C63*G$211*IF(G186=0,0,1) -> 0 | H63: =$C63*H$211*IF(H186=0,0,1) -> 0 | I63: =$C63*I$211*IF(I186=0,0,1) -> 0 | J63: =$C63*J$211*IF(J186=0,0,1) -> 0 | K63: =$C63*K$211*IF(K186=0,0,1) -> 0 | L63: =$C63*L$211*IF(L186=0,0,1) -> 0 | M63: =$C63*M$211*IF(M186=0,0,1) -> 0 | N63: =$C63*N$211*IF(N186=0,0,1) -> 0 | ... DV63: =$C63*DV$211*IF(DV186=0,0,1) -> 234153.06
B64: =B40 -> Property N | C64: =CaseData!C23 -> 194480 | E64: [$] | G64: =$C64*G$211*IF(G187=0,0,1) -> 0 | H64: =$C64*H$211*IF(H187=0,0,1) -> 0 | I64: =$C64*I$211*IF(I187=0,0,1) -> 0 | J64: =$C64*J$211*IF(J187=0,0,1) -> 0 | K64: =$C64*K$211*IF(K187=0,0,1) -> 0 | L64: =$C64*L$211*IF(L187=0,0,1) -> 0 | M64: =$C64*M$211*IF(M187=0,0,1) -> 0 | N64: =$C64*N$211*IF(N187=0,0,1) -> 0 | ... DV64: =$C64*DV$211*IF(DV187=0,0,1) -> 248950.84
B65: =B41 -> Property O | C65: =CaseData!C24 -> 238080 | E65: [$] | G65: =$C65*G$211*IF(G188=0,0,1) -> 0 | H65: =$C65*H$211*IF(H188=0,0,1) -> 0 | I65: =$C65*I$211*IF(I188=0,0,1) -> 0 | J65: =$C65*J$211*IF(J188=0,0,1) -> 0 | K65: =$C65*K$211*IF(K188=0,0,1) -> 0 | L65: =$C65*L$211*IF(L188=0,0,1) -> 0 | M65: =$C65*M$211*IF(M188=0,0,1) -> 0 | N65: =$C65*N$211*IF(N188=0,0,1) -> 0 | ... DV65: =$C65*DV$211*IF(DV188=0,0,1) -> 304762.53
B68: 4. Property Management Fee Forecast
B70: Property Management Fee | C70: =CaseData!L7 -> 0.02 | E70: [$] | G70: =$C70*G72 -> 67536 | H70: =$C70*H72 -> 67536 | I70: =$C70*I72 -> 67536 | J70: =$C70*J72 -> 67536 | K70: =$C70*K72 -> 67536 | L70: =$C70*L72 -> 67536 | M70: =$C70*M72 -> 67536 | N70: =$C70*N72 -> 67536 | ... DV70: =$C70*DV72 -> 244278.5
B72: Applicable Gross Rent Revenue | E72: [$] | G72: =SUBTOTAL(9,G74:G91) -> 3376800 | H72: =SUBTOTAL(9,H74:H91) -> 3376800 | I72: =SUBTOTAL(9,I74:I91) -> 3376800 | J72: =SUBTOTAL(9,J74:J91) -> 3376800 | K72: =SUBTOTAL(9,K74:K91) -> 3376800 | L72: =SUBTOTAL(9,L74:L91) -> 3376800 | M72: =SUBTOTAL(9,M74:M91) -> 3376800 | N72: =SUBTOTAL(9,N74:N91) -> 3376800 | ... DV72: =SUBTOTAL(9,DV74:DV91) -> 12213925
B74: Existing Properties - Gross Rent | E74: [$] | G74: =SUBTOTAL(9,G75:G79) -> 3376800 | H74: =SUBTOTAL(9,H75:H79) -> 3376800 | I74: =SUBTOTAL(9,I75:I79) -> 3376800 | J74: =SUBTOTAL(9,J75:J79) -> 3376800 | K74: =SUBTOTAL(9,K75:K79) -> 3376800 | L74: =SUBTOTAL(9,L75:L79) -> 3376800 | M74: =SUBTOTAL(9,M75:M79) -> 3376800 | N74: =SUBTOTAL(9,N75:N79) -> 3376800 | ... DV74: =SUBTOTAL(9,DV75:DV79) -> 4426412.4
B75: =B49 -> Property A | E75: [$] | G75: =$C25*G$210 -> 830550 | H75: =$C25*H$210 -> 830550 | I75: =$C25*I$210 -> 830550 | J75: =$C25*J$210 -> 830550 | K75: =$C25*K$210 -> 830550 | L75: =$C25*L$210 -> 830550 | M75: =$C25*M$210 -> 830550 | N75: =$C25*N$210 -> 830550 | ... DV75: =$C25*DV$210 -> 1088710.3
B76: =B50 -> Property B | E76: [$] | G76: =$C26*G$210 -> 470400 | H76: =$C26*H$210 -> 470400 | I76: =$C26*I$210 -> 470400 | J76: =$C26*J$210 -> 470400 | K76: =$C26*K$210 -> 470400 | L76: =$C26*L$210 -> 470400 | M76: =$C26*M$210 -> 470400 | N76: =$C26*N$210 -> 470400 | ... DV76: =$C26*DV$210 -> 616614.66
B77: =B51 -> Property C | E77: [$] | G77: =$C27*G$210 -> 720300 | H77: =$C27*H$210 -> 720300 | I77: =$C27*I$210 -> 720300 | J77: =$C27*J$210 -> 720300 | K77: =$C27*K$210 -> 720300 | L77: =$C27*L$210 -> 720300 | M77: =$C27*M$210 -> 720300 | N77: =$C27*N$210 -> 720300 | ... DV77: =$C27*DV$210 -> 944191.19
B78: =B52 -> Property D | E78: [$] | G78: =$C28*G$210 -> 774900 | H78: =$C28*H$210 -> 774900 | I78: =$C28*I$210 -> 774900 | J78: =$C28*J$210 -> 774900 | K78: =$C28*K$210 -> 774900 | L78: =$C28*L$210 -> 774900 | M78: =$C28*M$210 -> 774900 | N78: =$C28*N$210 -> 774900 | ... DV78: =$C28*DV$210 -> 1015762.5
B79: =B53 -> Property E | E79: [$] | G79: =$C29*G$210 -> 580650 | H79: =$C29*H$210 -> 580650 | I79: =$C29*I$210 -> 580650 | J79: =$C29*J$210 -> 580650 | K79: =$C29*K$210 -> 580650 | L79: =$C29*L$210 -> 580650 | M79: =$C29*M$210 -> 580650 | N79: =$C29*N$210 -> 580650 | ... DV79: =$C29*DV$210 -> 761133.72
B81: New Properties - Gross Rent | E81: [$] | G81: =SUBTOTAL(9,G82:G91) -> 0 | H81: =SUBTOTAL(9,H82:H91) -> 0 | I81: =SUBTOTAL(9,I82:I91) -> 0 | J81: =SUBTOTAL(9,J82:J91) -> 0 | K81: =SUBTOTAL(9,K82:K91) -> 0 | L81: =SUBTOTAL(9,L82:L91) -> 0 | M81: =SUBTOTAL(9,M82:M91) -> 0 | N81: =SUBTOTAL(9,N82:N91) -> 0 | ... DV81: =SUBTOTAL(9,DV82:DV91) -> 7787512.8
B82: =B56 -> Property F | E82: [$] | G82: =$C32*G$210*MIN(G179,1) -> 0 | H82: =$C32*H$210*MIN(H179,1) -> 0 | I82: =$C32*I$210*MIN(I179,1) -> 0 | J82: =$C32*J$210*MIN(J179,1) -> 0 | K82: =$C32*K$210*MIN(K179,1) -> 0 | L82: =$C32*L$210*MIN(L179,1) -> 0 | M82: =$C32*M$210*MIN(M179,1) -> 0 | N82: =$C32*N$210*MIN(N179,1) -> 0 | ... DV82: =$C32*DV$210*MIN(DV179,1) -> 608356.43
B83: =B57 -> Property G | E83: [$] | G83: =$C33*G$210*MIN(G180,1) -> 0 | H83: =$C33*H$210*MIN(H180,1) -> 0 | I83: =$C33*I$210*MIN(I180,1) -> 0 | J83: =$C33*J$210*MIN(J180,1) -> 0 | K83: =$C33*K$210*MIN(K180,1) -> 0 | L83: =$C33*L$210*MIN(L180,1) -> 0 | M83: =$C33*M$210*MIN(M180,1) -> 0 | N83: =$C33*N$210*MIN(N180,1) -> 0 | ... DV83: =$C33*DV$210*MIN(DV180,1) -> 527150.48
B84: =B58 -> Property H | E84: [$] | G84: =$C34*G$210*MIN(G181,1) -> 0 | H84: =$C34*H$210*MIN(H181,1) -> 0 | I84: =$C34*I$210*MIN(I181,1) -> 0 | J84: =$C34*J$210*MIN(J181,1) -> 0 | K84: =$C34*K$210*MIN(K181,1) -> 0 | L84: =$C34*L$210*MIN(L181,1) -> 0 | M84: =$C34*M$210*MIN(M181,1) -> 0 | N84: =$C34*N$210*MIN(N181,1) -> 0 | ... DV84: =$C34*DV$210*MIN(DV181,1) -> 684056.89
B85: =B59 -> Property I | E85: [$] | G85: =$C35*G$210*MIN(G182,1) -> 0 | H85: =$C35*H$210*MIN(H182,1) -> 0 | I85: =$C35*I$210*MIN(I182,1) -> 0 | J85: =$C35*J$210*MIN(J182,1) -> 0 | K85: =$C35*K$210*MIN(K182,1) -> 0 | L85: =$C35*L$210*MIN(L182,1) -> 0 | M85: =$C35*M$210*MIN(M182,1) -> 0 | N85: =$C35*N$210*MIN(N182,1) -> 0 | ... DV85: =$C35*DV$210*MIN(DV182,1) -> 818941.34
B86: =B60 -> Property J | E86: [$] | G86: =$C36*G$210*MIN(G183,1) -> 0 | H86: =$C36*H$210*MIN(H183,1) -> 0 | I86: =$C36*I$210*MIN(I183,1) -> 0 | J86: =$C36*J$210*MIN(J183,1) -> 0 | K86: =$C36*K$210*MIN(K183,1) -> 0 | L86: =$C36*L$210*MIN(L183,1) -> 0 | M86: =$C36*M$210*MIN(M183,1) -> 0 | N86: =$C36*N$210*MIN(N183,1) -> 0 | ... DV86: =$C36*DV$210*MIN(DV183,1) -> 814812.23
B87: =B61 -> Property K | E87: [$] | G87: =$C37*G$210*MIN(G184,1) -> 0 | H87: =$C37*H$210*MIN(H184,1) -> 0 | I87: =$C37*I$210*MIN(I184,1) -> 0 | J87: =$C37*J$210*MIN(J184,1) -> 0 | K87: =$C37*K$210*MIN(K184,1) -> 0 | L87: =$C37*L$210*MIN(L184,1) -> 0 | M87: =$C37*M$210*MIN(M184,1) -> 0 | N87: =$C37*N$210*MIN(N184,1) -> 0 | ... DV87: =$C37*DV$210*MIN(DV184,1) -> 499623.04
B88: =B62 -> Property L | E88: [$] | G88: =$C38*G$210*MIN(G185,1) -> 0 | H88: =$C38*H$210*MIN(H185,1) -> 0 | I88: =$C38*I$210*MIN(I185,1) -> 0 | J88: =$C38*J$210*MIN(J185,1) -> 0 | K88: =$C38*K$210*MIN(K185,1) -> 0 | L88: =$C38*L$210*MIN(L185,1) -> 0 | M88: =$C38*M$210*MIN(M185,1) -> 0 | N88: =$C38*N$210*MIN(N185,1) -> 0 | ... DV88: =$C38*DV$210*MIN(DV185,1) -> 1007504.3
B89: =B63 -> Property M | E89: [$] | G89: =$C39*G$210*MIN(G186,1) -> 0 | H89: =$C39*H$210*MIN(H186,1) -> 0 | I89: =$C39*I$210*MIN(I186,1) -> 0 | J89: =$C39*J$210*MIN(J186,1) -> 0 | K89: =$C39*K$210*MIN(K186,1) -> 0 | L89: =$C39*L$210*MIN(L186,1) -> 0 | M89: =$C39*M$210*MIN(M186,1) -> 0 | N89: =$C39*N$210*MIN(N186,1) -> 0 | ... DV89: =$C39*DV$210*MIN(DV186,1) -> 740488.14
B90: =B64 -> Property N | E90: [$] | G90: =$C40*G$210*MIN(G187,1) -> 0 | H90: =$C40*H$210*MIN(H187,1) -> 0 | I90: =$C40*I$210*MIN(I187,1) -> 0 | J90: =$C40*J$210*MIN(J187,1) -> 0 | K90: =$C40*K$210*MIN(K187,1) -> 0 | L90: =$C40*L$210*MIN(L187,1) -> 0 | M90: =$C40*M$210*MIN(M187,1) -> 0 | N90: =$C40*N$210*MIN(N187,1) -> 0 | ... DV90: =$C40*DV$210*MIN(DV187,1) -> 1029526.3
B91: =B65 -> Property O | E91: [$] | G91: =$C41*G$210*MIN(G188,1) -> 0 | H91: =$C41*H$210*MIN(H188,1) -> 0 | I91: =$C41*I$210*MIN(I188,1) -> 0 | J91: =$C41*J$210*MIN(J188,1) -> 0 | K91: =$C41*K$210*MIN(K188,1) -> 0 | L91: =$C41*L$210*MIN(L188,1) -> 0 | M91: =$C41*M$210*MIN(M188,1) -> 0 | N91: =$C41*N$210*MIN(N188,1) -> 0 | ... DV91: =$C41*DV$210*MIN(DV188,1) -> 1057053.7
B93: 5. Land Acquisition Cost Forecast
B95: New Properties - Land Acquisition | C95: Land Cost Real | D95: Acquisition Month | E95: [$] | G95: =SUBTOTAL(9,G96:G105) -> 4316130 | H95: =SUBTOTAL(9,H96:H105) -> 0 | I95: =SUBTOTAL(9,I96:I105) -> 0 | J95: =SUBTOTAL(9,J96:J105) -> 3908898 | K95: =SUBTOTAL(9,K96:K105) -> 0 | L95: =SUBTOTAL(9,L96:L105) -> 0 | M95: =SUBTOTAL(9,M96:M105) -> 4936701 | N95: =SUBTOTAL(9,N96:N105) -> 0 | ... DV95: =SUBTOTAL(9,DV96:DV105) -> 0
B96: =B82 -> Property F | C96: =CaseData!D15 -> 4110600 | D96: =D127 -> 1 | E96: [$] | G96: =IF($D96=G$4,1,0)*$C96*G$212 -> 4316130 | H96: =IF($D96=H$4,1,0)*$C96*H$212 -> 0 | I96: =IF($D96=I$4,1,0)*$C96*I$212 -> 0 | J96: =IF($D96=J$4,1,0)*$C96*J$212 -> 0 | K96: =IF($D96=K$4,1,0)*$C96*K$212 -> 0 | L96: =IF($D96=L$4,1,0)*$C96*L$212 -> 0 | M96: =IF($D96=M$4,1,0)*$C96*M$212 -> 0 | N96: =IF($D96=N$4,1,0)*$C96*N$212 -> 0 | ... DV96: =IF($D96=DV$4,1,0)*$C96*DV$212 -> 0
B97: =B83 -> Property G | C97: =CaseData!D16 -> 3722760 | D97: =D128 -> 4 | E97: [$] | G97: =IF($D97=G$4,1,0)*$C97*G$212 -> 0 | H97: =IF($D97=H$4,1,0)*$C97*H$212 -> 0 | I97: =IF($D97=I$4,1,0)*$C97*I$212 -> 0 | J97: =IF($D97=J$4,1,0)*$C97*J$212 -> 3908898 | K97: =IF($D97=K$4,1,0)*$C97*K$212 -> 0 | L97: =IF($D97=L$4,1,0)*$C97*L$212 -> 0 | M97: =IF($D97=M$4,1,0)*$C97*M$212 -> 0 | N97: =IF($D97=N$4,1,0)*$C97*N$212 -> 0 | ... DV97: =IF($D97=DV$4,1,0)*$C97*DV$212 -> 0
B98: =B84 -> Property H | C98: =CaseData!D17 -> 4701620 | D98: =D129 -> 7 | E98: [$] | G98: =IF($D98=G$4,1,0)*$C98*G$212 -> 0 | H98: =IF($D98=H$4,1,0)*$C98*H$212 -> 0 | I98: =IF($D98=I$4,1,0)*$C98*I$212 -> 0 | J98: =IF($D98=J$4,1,0)*$C98*J$212 -> 0 | K98: =IF($D98=K$4,1,0)*$C98*K$212 -> 0 | L98: =IF($D98=L$4,1,0)*$C98*L$212 -> 0 | M98: =IF($D98=M$4,1,0)*$C98*M$212 -> 4936701 | N98: =IF($D98=N$4,1,0)*$C98*N$212 -> 0 | ... DV98: =IF($D98=DV$4,1,0)*$C98*DV$212 -> 0
B99: =B85 -> Property I | C99: =CaseData!D18 -> 6283200 | D99: =D130 -> 10 | E99: [$] | G99: =IF($D99=G$4,1,0)*$C99*G$212 -> 0 | H99: =IF($D99=H$4,1,0)*$C99*H$212 -> 0 | I99: =IF($D99=I$4,1,0)*$C99*I$212 -> 0 | J99: =IF($D99=J$4,1,0)*$C99*J$212 -> 0 | K99: =IF($D99=K$4,1,0)*$C99*K$212 -> 0 | L99: =IF($D99=L$4,1,0)*$C99*L$212 -> 0 | M99: =IF($D99=M$4,1,0)*$C99*M$212 -> 0 | N99: =IF($D99=N$4,1,0)*$C99*N$212 -> 0 | ... DV99: =IF($D99=DV$4,1,0)*$C99*DV$212 -> 0
B100: =B86 -> Property J | C100: =CaseData!D19 -> 4368960 | D100: =D131 -> 13 | E100: [$] | G100: =IF($D100=G$4,1,0)*$C100*G$212 -> 0 | H100: =IF($D100=H$4,1,0)*$C100*H$212 -> 0 | I100: =IF($D100=I$4,1,0)*$C100*I$212 -> 0 | J100: =IF($D100=J$4,1,0)*$C100*J$212 -> 0 | K100: =IF($D100=K$4,1,0)*$C100*K$212 -> 0 | L100: =IF($D100=L$4,1,0)*$C100*L$212 -> 0 | M100: =IF($D100=M$4,1,0)*$C100*M$212 -> 0 | N100: =IF($D100=N$4,1,0)*$C100*N$212 -> 0 | ... DV100: =IF($D100=DV$4,1,0)*$C100*DV$212 -> 0
B101: =B87 -> Property K | C101: =CaseData!D20 -> 2972970 | D101: =D132 -> 16 | E101: [$] | G101: =IF($D101=G$4,1,0)*$C101*G$212 -> 0 | H101: =IF($D101=H$4,1,0)*$C101*H$212 -> 0 | I101: =IF($D101=I$4,1,0)*$C101*I$212 -> 0 | J101: =IF($D101=J$4,1,0)*$C101*J$212 -> 0 | K101: =IF($D101=K$4,1,0)*$C101*K$212 -> 0 | L101: =IF($D101=L$4,1,0)*$C101*L$212 -> 0 | M101: =IF($D101=M$4,1,0)*$C101*M$212 -> 0 | N101: =IF($D101=N$4,1,0)*$C101*N$212 -> 0 | ... DV101: =IF($D101=DV$4,1,0)*$C101*DV$212 -> 0
B102: =B88 -> Property L | C102: =CaseData!D21 -> 6844200 | D102: =D133 -> 25 | E102: [$] | G102: =IF($D102=G$4,1,0)*$C102*G$212 -> 0 | H102: =IF($D102=H$4,1,0)*$C102*H$212 -> 0 | I102: =IF($D102=I$4,1,0)*$C102*I$212 -> 0 | J102: =IF($D102=J$4,1,0)*$C102*J$212 -> 0 | K102: =IF($D102=K$4,1,0)*$C102*K$212 -> 0 | L102: =IF($D102=L$4,1,0)*$C102*L$212 -> 0 | M102: =IF($D102=M$4,1,0)*$C102*M$212 -> 0 | N102: =IF($D102=N$4,1,0)*$C102*N$212 -> 0 | ... DV102: =IF($D102=DV$4,1,0)*$C102*DV$212 -> 0
B103: =B89 -> Property M | C103: =CaseData!D22 -> 3701440 | D103: =D134 -> 28 | E103: [$] | G103: =IF($D103=G$4,1,0)*$C103*G$212 -> 0 | H103: =IF($D103=H$4,1,0)*$C103*H$212 -> 0 | I103: =IF($D103=I$4,1,0)*$C103*I$212 -> 0 | J103: =IF($D103=J$4,1,0)*$C103*J$212 -> 0 | K103: =IF($D103=K$4,1,0)*$C103*K$212 -> 0 | L103: =IF($D103=L$4,1,0)*$C103*L$212 -> 0 | M103: =IF($D103=M$4,1,0)*$C103*M$212 -> 0 | N103: =IF($D103=N$4,1,0)*$C103*N$212 -> 0 | ... DV103: =IF($D103=DV$4,1,0)*$C103*DV$212 -> 0
B104: =B90 -> Property N | C104: =CaseData!D23 -> 5452920 | D104: =D135 -> 37 | E104: [$] | G104: =IF($D104=G$4,1,0)*$C104*G$212 -> 0 | H104: =IF($D104=H$4,1,0)*$C104*H$212 -> 0 | I104: =IF($D104=I$4,1,0)*$C104*I$212 -> 0 | J104: =IF($D104=J$4,1,0)*$C104*J$212 -> 0 | K104: =IF($D104=K$4,1,0)*$C104*K$212 -> 0 | L104: =IF($D104=L$4,1,0)*$C104*L$212 -> 0 | M104: =IF($D104=M$4,1,0)*$C104*M$212 -> 0 | N104: =IF($D104=N$4,1,0)*$C104*N$212 -> 0 | ... DV104: =IF($D104=DV$4,1,0)*$C104*DV$212 -> 0
B105: =B91 -> Property O | C105: =CaseData!D24 -> 5406720 | D105: =D136 -> 43 | E105: [$] | G105: =IF($D105=G$4,1,0)*$C105*G$212 -> 0 | H105: =IF($D105=H$4,1,0)*$C105*H$212 -> 0 | I105: =IF($D105=I$4,1,0)*$C105*I$212 -> 0 | J105: =IF($D105=J$4,1,0)*$C105*J$212 -> 0 | K105: =IF($D105=K$4,1,0)*$C105*K$212 -> 0 | L105: =IF($D105=L$4,1,0)*$C105*L$212 -> 0 | M105: =IF($D105=M$4,1,0)*$C105*M$212 -> 0 | N105: =IF($D105=N$4,1,0)*$C105*N$212 -> 0 | ... DV105: =IF($D105=DV$4,1,0)*$C105*DV$212 -> 0
B108: 6. Construction Cost Forecast
B110: New Properties - Construction Costs | C110: CC Nominal | E110: [$] | G110: =SUBTOTAL(9,G111:G120) -> 0 | H110: =SUBTOTAL(9,H111:H120) -> 0 | I110: =SUBTOTAL(9,I111:I120) -> 0 | J110: =SUBTOTAL(9,J111:J120) -> 0 | K110: =SUBTOTAL(9,K111:K120) -> 948007.12 | L110: =SUBTOTAL(9,L111:L120) -> 1053341.2 | M110: =SUBTOTAL(9,M111:M120) -> 1264009.5 | N110: =SUBTOTAL(9,N111:N120) -> 1474677.8 | ... DV110: =SUBTOTAL(9,DV111:DV120) -> 0
B111: =B96 -> Property F | C111: =M127 -> 42133650 | E111: [$] | G111: =$C111*G166 -> 0 | H111: =$C111*H166 -> 0 | I111: =$C111*I166 -> 0 | J111: =$C111*J166 -> 0 | K111: =$C111*K166 -> 948007.12 | L111: =$C111*L166 -> 1053341.2 | M111: =$C111*M166 -> 1264009.5 | N111: =$C111*N166 -> 1474677.8 | ... DV111: =$C111*DV166 -> 0
B112: =B97 -> Property G | C112: =M128 -> 31798575 | E112: [$] | G112: =$C112*G167 -> 0 | H112: =$C112*H167 -> 0 | I112: =$C112*I167 -> 0 | J112: =$C112*J167 -> 0 | K112: =$C112*K167 -> 0 | L112: =$C112*L167 -> 0 | M112: =$C112*M167 -> 0 | N112: =$C112*N167 -> 0 | ... DV112: =$C112*DV167 -> 0
B113: =B98 -> Property H | C113: =M129 -> 43810550 | E113: [$] | G113: =$C113*G168 -> 0 | H113: =$C113*H168 -> 0 | I113: =$C113*I168 -> 0 | J113: =$C113*J168 -> 0 | K113: =$C113*K168 -> 0 | L113: =$C113*L168 -> 0 | M113: =$C113*M168 -> 0 | N113: =$C113*N168 -> 0 | ... DV113: =$C113*DV168 -> 0
B114: =B99 -> Property I | C114: =M130 -> 55010725 | E114: [$] | G114: =$C114*G169 -> 0 | H114: =$C114*H169 -> 0 | I114: =$C114*I169 -> 0 | J114: =$C114*J169 -> 0 | K114: =$C114*K169 -> 0 | L114: =$C114*L169 -> 0 | M114: =$C114*M169 -> 0 | N114: =$C114*N169 -> 0 | ... DV114: =$C114*DV169 -> 0
B115: =B100 -> Property J | C115: =M131 -> 51001540 | E115: [$] | G115: =$C115*G170 -> 0 | H115: =$C115*H170 -> 0 | I115: =$C115*I170 -> 0 | J115: =$C115*J170 -> 0 | K115: =$C115*K170 -> 0 | L115: =$C115*L170 -> 0 | M115: =$C115*M170 -> 0 | N115: =$C115*N170 -> 0 | ... DV115: =$C115*DV170 -> 0
B116: =B101 -> Property K | C116: =M132 -> 34705296 | E116: [$] | G116: =$C116*G171 -> 0 | H116: =$C116*H171 -> 0 | I116: =$C116*I171 -> 0 | J116: =$C116*J171 -> 0 | K116: =$C116*K171 -> 0 | L116: =$C116*L171 -> 0 | M116: =$C116*M171 -> 0 | N116: =$C116*N171 -> 0 | ... DV116: =$C116*DV171 -> 0
B117: =B102 -> Property L | C117: =M133 -> 67004135 | E117: [$] | G117: =$C117*G172 -> 0 | H117: =$C117*H172 -> 0 | I117: =$C117*I172 -> 0 | J117: =$C117*J172 -> 0 | K117: =$C117*K172 -> 0 | L117: =$C117*L172 -> 0 | M117: =$C117*M172 -> 0 | N117: =$C117*N172 -> 0 | ... DV117: =$C117*DV172 -> 0
B118: =B103 -> Property M | C118: =M134 -> 49825575 | E118: [$] | G118: =$C118*G173 -> 0 | H118: =$C118*H173 -> 0 | I118: =$C118*I173 -> 0 | J118: =$C118*J173 -> 0 | K118: =$C118*K173 -> 0 | L118: =$C118*L173 -> 0 | M118: =$C118*M173 -> 0 | N118: =$C118*N173 -> 0 | ... DV118: =$C118*DV173 -> 0
B119: =B104 -> Property N | C119: =M135 -> 66877815 | E119: [$] | G119: =$C119*G174 -> 0 | H119: =$C119*H174 -> 0 | I119: =$C119*I174 -> 0 | J119: =$C119*J174 -> 0 | K119: =$C119*K174 -> 0 | L119: =$C119*L174 -> 0 | M119: =$C119*M174 -> 0 | N119: =$C119*N174 -> 0 | ... DV119: =$C119*DV174 -> 0
B120: =B105 -> Property O | C120: =M136 -> 74600090 | E120: [$] | G120: =$C120*G175 -> 0 | H120: =$C120*H175 -> 0 | I120: =$C120*I175 -> 0 | J120: =$C120*J175 -> 0 | K120: =$C120*K175 -> 0 | L120: =$C120*L175 -> 0 | M120: =$C120*M175 -> 0 | N120: =$C120*N175 -> 0 | ... DV120: =$C120*DV175 -> 0
B123: 7. Timeline Calculations
B125: New Properties - Timeline
B126: Property | C126: Land Acquisition Date | D126: Land Acquisition Month | F126: Site Cost - Real | G126: Site Appreciation | H126: Site Cost - Nominal | I126: Prep Work Length | J126: Construction Start Month | K126: Construction Cost - Real | L126: Cost Inflation | M126: Construction Cost - Nominal | N126: Construction Length | O126: Operations Start Month
B127: =B32 -> Property F | C127: =CaseData!F15 -> 44562 | D127: =INDEX($G$4:$DV$4,MATCH($C127,$G$2:$DV$2,1)) -> 1 | F127: =CaseData!D15 -> 4110600 | G127: {=INDEX($G$212:$DV$212,1, D127)} -> 1.05 | H127: =F127*G127 -> 4316130 | I127: =CaseData!G15 -> 4 | J127: =D127+I127 -> 5 | K127: =CaseData!E15 -> 41106000 | L127: {=INDEX($G$211:$DV$211,1, J127)} -> 1.025 | M127: =K127*L127 -> 42133650 | N127: =CaseData!H15 -> 15 | O127: =J127+N127 -> 20
B128: =B33 -> Property G | C128: =CaseData!F16 -> 44652 | D128: =INDEX($G$4:$DV$4,MATCH($C128,$G$2:$DV$2,1)) -> 4 | F128: =CaseData!D16 -> 3722760 | G128: {=INDEX($G$212:$DV$212,1, D128)} -> 1.05 | H128: =F128*G128 -> 3908898 | I128: =CaseData!G16 -> 5 | J128: =D128+I128 -> 9 | K128: =CaseData!E16 -> 31023000 | L128: {=INDEX($G$211:$DV$211,1, J128)} -> 1.025 | M128: =K128*L128 -> 31798575 | N128: =CaseData!H16 -> 12 | O128: =J128+N128 -> 21
...
